{
  "type": "Feature",
  "properties": {
    "name:eng_x_preferred":[
        "Maybury"
    ],
    "name:eus_x_preferred":[
        "Maybury"
    ],
    "wd:wordcount":161,
    "wof:name":"Maybury",
    "wof:placetype":"neighbourhood"
},
  "geometry": {"coordinates":[-3.3124978661972,55.94420125397455],"type":"Point"}
}