{
  "type": "Feature",
  "properties": {
    "gn:gn_country":"GB",
    "gn:gn_fcode":"PPL",
    "gn:gn_pop":0,
    "iso:country":"GB",
    "name:cat_x_preferred":[
        "Strathdon"
    ],
    "name:chi_x_preferred":[
        "\u65af\u7279\u62c9\u65af\u767b"
    ],
    "name:dut_x_preferred":[
        "Strathdon"
    ],
    "name:eng_x_preferred":[
        "Strathdon"
    ],
    "name:fre_x_preferred":[
        "Strathdon"
    ],
    "name:ger_x_preferred":[
        "Strathdon"
    ],
    "name:gle_x_preferred":[
        "Srath Dheathain"
    ],
    "name:ita_x_preferred":[
        "Strathdon"
    ],
    "name:oci_x_preferred":[
        "Strathdon"
    ],
    "name:sco_x_preferred":[
        "Strathdon"
    ],
    "name:spa_x_preferred":[
        "Strathdon"
    ],
    "qs_pg:aaroncc":"GB",
    "qs_pg:gn_country":"GB",
    "qs_pg:gn_fcode":"PPL",
    "qs_pg:gn_pop":0,
    "qs_pg:name":"Strathdon",
    "qs_pg:name_adm0":"United Kingdom",
    "qs_pg:name_adm1":"Scotland",
    "qs_pg:photos":382,
    "qs_pg:photos_1k":77,
    "qs_pg:photos_9k":2,
    "qs_pg:photos_9r":5,
    "qs_pg:photos_all":382,
    "qs_pg:photos_sr":6,
    "qs_pg:pop_sr":0,
    "qs_pg:qs_pg_placetype":"locality",
    "qs_pg:qs_pg_placetype_gp":"Town",
    "qs_pg:woe_adm0":23424975,
    "woe:adm0_id":23424975,
    "woe:name_adm0":"United Kingdom",
    "woe:name_adm1":"Scotland",
    "woe:placetype":"Town",
    "wof:name":"Strathdon",
    "wof:placetype":"locality"
},
  "geometry": {"coordinates":[-3.07102,57.1999],"type":"Point"}
}