{
  "type": "Feature",
  "properties": {
    "iso:country":"GB",
    "name:ceb_x_preferred":[
        "Lakeland"
    ],
    "name:deu_x_preferred":[
        "Lakeland"
    ],
    "name:fra_x_preferred":[
        "Lakeland"
    ],
    "name:ita_x_preferred":[
        "Lakeland"
    ],
    "name:kor_x_preferred":[
        "\ub808\uc774\ud074\ub79c\ub4dc"
    ],
    "name:nld_x_preferred":[
        "Lakeland"
    ],
    "name:pol_x_preferred":[
        "Lakeland"
    ],
    "name:por_x_preferred":[
        "Lakeland"
    ],
    "name:rus_x_preferred":[
        "\u041b\u0435\u0439\u043a\u043b\u0435\u043d\u0434"
    ],
    "name:spa_x_preferred":[
        "Lakeland"
    ],
    "name:srp_x_preferred":[
        "\u041b\u0435\u0458\u043a\u043b\u0430\u043d\u0434"
    ],
    "name:ukr_x_preferred":[
        "\u041b\u0435\u0439\u043a\u043b\u0435\u043d\u0434"
    ],
    "name:urd_x_preferred":[
        "\u0644\u06cc\u06a9\u0644\u06cc\u0646\u0688"
    ],
    "name:vol_x_preferred":[
        "Lakeland"
    ],
    "qs_pg:aaroncc":"GB",
    "qs_pg:name":"Lakeland",
    "qs_pg:name_adm0":"United Kingdom",
    "qs_pg:name_adm1":"England",
    "qs_pg:photos":132,
    "qs_pg:photos_1k":27,
    "qs_pg:photos_9k":1,
    "qs_pg:photos_9r":3,
    "qs_pg:photos_all":132,
    "qs_pg:photos_sr":3,
    "qs_pg:pop_sr":0,
    "qs_pg:qs_pg_placetype":"locality",
    "qs_pg:qs_pg_placetype_gp":"Town",
    "qs_pg:woe_adm0":23424975,
    "woe:adm0_id":23424975,
    "woe:name_adm0":"United Kingdom",
    "woe:name_adm1":"England",
    "woe:placetype":"Town",
    "wof:name":"Lakeland",
    "wof:placetype":"neighbourhood"
},
  "geometry": {"coordinates":[-3.8194975,50.627305],"type":"Point"}
}