{
  "type": "Feature",
  "properties": {
    "gn:gn_country":"GB",
    "gn:gn_fcode":"PPL",
    "gn:gn_pop":0,
    "iso:country":"GB",
    "name:cym_x_preferred":[
        "Apsley"
    ],
    "name:eng_x_preferred":[
        "Apsley"
    ],
    "name:fra_x_preferred":[
        "Apsley"
    ],
    "name:ita_x_preferred":[
        "Apsley"
    ],
    "name:nld_x_preferred":[
        "Apsley"
    ],
    "name:pol_x_preferred":[
        "Apsley"
    ],
    "qs_pg:aaroncc":"GB",
    "qs_pg:gn_country":"GB",
    "qs_pg:gn_fcode":"PPL",
    "qs_pg:gn_pop":0,
    "qs_pg:name":"Apsley",
    "qs_pg:name_adm0":"United Kingdom",
    "qs_pg:name_adm1":"England",
    "qs_pg:photos":545,
    "qs_pg:photos_1k":110,
    "qs_pg:photos_9k":2,
    "qs_pg:photos_9r":5,
    "qs_pg:photos_all":545,
    "qs_pg:photos_sr":7,
    "qs_pg:pop_sr":0,
    "qs_pg:qs_pg_placetype":"locality",
    "qs_pg:qs_pg_placetype_gp":"Town",
    "qs_pg:woe_adm0":23424975,
    "woe:adm0_id":23424975,
    "woe:name_adm0":"United Kingdom",
    "woe:name_adm1":"England",
    "woe:placetype":"Town",
    "wof:name":"Apsley",
    "wof:placetype":"neighbourhood"
},
  "geometry": {"coordinates":[-0.4678,51.73641],"type":"Point"}
}