{
  "type": "Feature",
  "properties": {
    "iso:country":"GB",
    "name:cym_x_preferred":[
        "Jackfield"
    ],
    "name:eng_x_preferred":[
        "Jackfield"
    ],
    "name:fra_x_preferred":[
        "Jackfield"
    ],
    "name:heb_x_preferred":[
        "\u05d2'\u05e7\u05e4\u05d9\u05dc\u05d3"
    ],
    "name:nld_x_preferred":[
        "Jackfield"
    ],
    "name:pol_x_preferred":[
        "Jackfield"
    ],
    "name:zho_x_preferred":[
        "\u5091\u514b\u83f2\u723e"
    ],
    "qs_pg:aaroncc":"GB",
    "qs_pg:name":"Jackfield",
    "qs_pg:name_adm0":"United Kingdom",
    "qs_pg:name_adm1":"England",
    "qs_pg:photos":303,
    "qs_pg:photos_1k":61,
    "qs_pg:photos_9k":1,
    "qs_pg:photos_9r":5,
    "qs_pg:photos_all":303,
    "qs_pg:photos_sr":5,
    "qs_pg:pop_sr":0,
    "qs_pg:qs_pg_placetype":"locality",
    "qs_pg:qs_pg_placetype_gp":"Town",
    "qs_pg:woe_adm0":23424975,
    "woe:adm0_id":23424975,
    "woe:name_adm0":"United Kingdom",
    "woe:name_adm1":"England",
    "woe:placetype":"Town",
    "wof:name":"Jackfield",
    "wof:placetype":"neighbourhood"
},
  "geometry": {"coordinates":[-2.457032,52.62108],"type":"Point"}
}