{
  "type": "Feature",
  "properties": {
    "gn:country":"GB",
    "gn:fcode":"PPL",
    "gn:population":0,
    "iso:country":"GB",
    "name:swe_x_preferred":[
        "Blackmore End"
    ],
    "qs_pg:aaroncc":"GB",
    "qs_pg:gn_country":"GB",
    "qs_pg:gn_fcode":"PPL",
    "qs_pg:gn_pop":0,
    "qs_pg:name":"Blackmore End",
    "qs_pg:name_adm0":"United Kingdom",
    "qs_pg:name_adm1":"England",
    "qs_pg:photos":27,
    "qs_pg:photos_1k":5,
    "qs_pg:photos_9k":1,
    "qs_pg:photos_9r":2,
    "qs_pg:photos_all":27,
    "qs_pg:photos_sr":2,
    "qs_pg:pop_sr":0,
    "qs_pg:qs_pg_placetype":"locality",
    "qs_pg:qs_pg_placetype_gp":"Town",
    "qs_pg:woe_adm0":23424975,
    "woe:adm0_id":23424975,
    "woe:name_adm0":"United Kingdom",
    "woe:name_adm1":"England",
    "woe:placetype":"Town",
    "wof:name":"Blackmore End",
    "wof:placetype":"neighbourhood",
    "wof:population":829
},
  "geometry": {"coordinates":[0.31865,51.69256],"type":"Point"}
}