{
  "type": "Feature",
  "properties": {
    "iso:country":"GB",
    "name:ara_x_preferred":[
        "\u0622\u0628\u0628\u0631 \u0643\u0648\u0644\u0647\u0645"
    ],
    "name:arz_x_preferred":[
        "\u0622\u0628\u0628\u0631 \u0643\u0648\u0644\u0647\u0645"
    ],
    "name:cym_x_preferred":[
        "Upper Culham"
    ],
    "name:deu_x_preferred":[
        "Upper Culham"
    ],
    "name:eng_x_preferred":[
        "Upper Culham"
    ],
    "name:fra_x_preferred":[
        "Upper Culham"
    ],
    "name:gle_x_preferred":[
        "Upper Culham"
    ],
    "name:nld_x_preferred":[
        "Upper Culham"
    ],
    "name:pol_x_preferred":[
        "Upper Culham"
    ],
    "qs_pg:aaroncc":"GB",
    "qs_pg:name":"Upper Culham",
    "qs_pg:name_adm0":"United Kingdom",
    "qs_pg:name_adm1":"England",
    "qs_pg:photos":35,
    "qs_pg:photos_1k":7,
    "qs_pg:photos_9k":1,
    "qs_pg:photos_9r":2,
    "qs_pg:photos_all":35,
    "qs_pg:photos_sr":2,
    "qs_pg:pop_sr":0,
    "qs_pg:qs_pg_placetype":"locality",
    "qs_pg:qs_pg_placetype_gp":"Town",
    "qs_pg:woe_adm0":23424975,
    "woe:adm0_id":23424975,
    "woe:name_adm0":"United Kingdom",
    "woe:name_adm1":"England",
    "woe:placetype":"Town",
    "wof:name":"Upper Culham",
    "wof:placetype":"neighbourhood"
},
  "geometry": {"coordinates":[-0.862941,51.531106],"type":"Point"}
}