{
  "type": "Feature",
  "properties": {
    "iso:country":"GB",
    "name:ceb_x_preferred":[
        "Keresley"
    ],
    "name:eng_x_preferred":[
        "Keresley"
    ],
    "name:gle_x_preferred":[
        "Keresley"
    ],
    "name:pol_x_preferred":[
        "Keresley"
    ],
    "name:swe_x_preferred":[
        "Keresley"
    ],
    "name:unk_x_variant":[
        "Keresley"
    ],
    "qs:gn_adm0_cc":"GB",
    "qs:gn_local":2652221,
    "qs:local_max":5581,
    "qs:local_sum":33638,
    "qs:localhoods":22,
    "qs:name":"Keresley",
    "qs:name_adm0":"United Kingdom",
    "qs:name_adm1":"England",
    "qs:name_adm2":"West Midlands",
    "qs:name_lau":"Coventry City",
    "qs:name_local":"Coventry",
    "qs:photo_max":59,
    "qs:photo_sum":642,
    "qs:placetype":"Suburb",
    "qs:quad_count":66,
    "qs:woe_adm0":23424975,
    "qs:woe_adm1":24554868,
    "qs:woe_adm2":12602191,
    "qs:woe_lau":12695864,
    "qs:woe_local":17044,
    "qs:woe_ver":"7.10.0",
    "wd:wordcount":911,
    "wof:lang":[
        "eng"
    ],
    "wof:name":"Keresley",
    "wof:placetype":"neighbourhood"
},
  "geometry": {"coordinates":[-1.532685,52.441051],"type":"Point"}
}