{
  "type": "Feature",
  "properties": {
    "iso:country": "GB",
    "wof:name": "Mytholmes",
    "wof:placetype": "neighbourhood"
  },
  "geometry": {"coordinates":[-1.9521974925388,53.8348588905739],"type":"Point"}
}
