{
  "type": "Feature",
  "properties": {
    "iso:country":"GB",
    "name:ast_x_preferred":[
        "Thornhill"
    ],
    "name:ceb_x_preferred":[
        "Thornhill"
    ],
    "name:cym_x_preferred":[
        "Thornhill"
    ],
    "name:deu_x_preferred":[
        "Thornhill"
    ],
    "name:eng_x_preferred":[
        "Thornhill"
    ],
    "name:eus_x_preferred":[
        "Thornhill"
    ],
    "name:fas_x_preferred":[
        "\u062a\u0648\u0631\u0646\u0647\u06cc\u0644"
    ],
    "name:gla_x_preferred":[
        "B\u00e0rr na Dris"
    ],
    "name:gle_x_preferred":[
        "B\u00e1rr na Driseig"
    ],
    "name:ita_x_preferred":[
        "Thornhill"
    ],
    "name:nld_x_preferred":[
        "Thornhill"
    ],
    "name:por_x_preferred":[
        "Thornhill"
    ],
    "name:sco_x_preferred":[
        "Thornhill"
    ],
    "name:slv_x_preferred":[
        "Thornhill"
    ],
    "name:spa_x_preferred":[
        "Thornhill"
    ],
    "name:swe_x_preferred":[
        "Thornhill"
    ],
    "qs:a0":"United Kingdom",
    "qs:a1":"*Dumfries and Galloway",
    "qs:a1_lc":"GB11QH0000",
    "qs:a1r":"0Scotland",
    "qs:a1r_lc":"GB11000000",
    "qs:adm0":"United Kingdom",
    "qs:la_lc":"*",
    "qs:level":"locality",
    "qs:loc":"Thornhill",
    "qs:loc_alt":"Thornhill",
    "qs:pop":0,
    "qs:type":"buffered point",
    "wd:wordcount":719,
    "wof:lang":[
        "eng"
    ],
    "wof:name":"Thornhill",
    "wof:placetype":"locality"
},
  "geometry": {"coordinates":[-3.766227,55.240726],"type":"Point"}
}