{
  "type": "Feature",
  "properties": {
    "iso:country":"GB",
    "name:ceb_x_preferred":[
        "Whiston"
    ],
    "name:dan_x_preferred":[
        "Whiston"
    ],
    "name:deu_x_preferred":[
        "Whiston"
    ],
    "name:fra_x_preferred":[
        "Whiston"
    ],
    "name:ita_x_preferred":[
        "Whiston"
    ],
    "name:nld_x_preferred":[
        "Whiston"
    ],
    "name:pol_x_preferred":[
        "Whiston"
    ],
    "name:rus_x_preferred":[
        "\u0423\u0438\u0441\u0442\u043e\u043d"
    ],
    "name:swe_x_preferred":[
        "Whiston"
    ],
    "wof:name":"Whiston",
    "wof:placetype":"neighbourhood"
},
  "geometry": {"coordinates":[-1.32670505163743,53.40612387815469],"type":"Point"}
}