{
  "type": "Feature",
  "properties": {
    "gn:admin1_code":"SCT",
    "gn:admin2_code":"W3",
    "gn:asciiname":"Easter Quarff",
    "gn:country_code":"GB",
    "gn:dem":31,
    "gn:feature_class":"P",
    "gn:feature_code":"PPL",
    "gn:name":"Easter Quarff",
    "gn:population":0,
    "gn:timezone":"Europe/London",
    "iso:country":"GB",
    "wof:name":"Easter Quarff",
    "wof:placetype":"locality"
},
  "geometry": {"coordinates":[-1.23507,60.10171],"type":"Point"}
}