{
  "type": "Feature",
  "properties": {
    "gn:admin1_code":"NIR",
    "gn:admin2_code":"N09000006",
    "gn:asciiname":"Stralongford",
    "gn:country_code":"GB",
    "gn:dem":95,
    "gn:feature_class":"P",
    "gn:feature_code":"PPL",
    "gn:name":"Stralongford",
    "gn:population":0,
    "gn:timezone":"Europe/London",
    "iso:country":"GB",
    "wof:name":"Stralongford",
    "wof:placetype":"locality"
},
  "geometry": {"coordinates":[-7.56667,54.48333],"type":"Point"}
}