{
  "type": "Feature",
  "properties": {
    "gn:country":"GB",
    "iso:country":"GB",
    "name:bre_x_preferred":[
        "Eirisgeigh"
    ],
    "name:ceb_x_preferred":[
        "Eriskay"
    ],
    "name:ces_x_preferred":[
        "Eriskay"
    ],
    "name:cym_x_preferred":[
        "Eirisgeidh"
    ],
    "name:deu_x_preferred":[
        "Eriskay"
    ],
    "name:ell_x_preferred":[
        "\u0388\u03c1\u03b9\u03c3\u03ba\u03b9"
    ],
    "name:eus_x_preferred":[
        "Eriskay"
    ],
    "name:fra_x_preferred":[
        "Eriskay"
    ],
    "name:gla_x_preferred":[
        "\u00c8irisgeigh"
    ],
    "name:gle_x_preferred":[
        "\u00c8irisgeigh"
    ],
    "name:hun_x_preferred":[
        "Eriskay"
    ],
    "name:ita_x_preferred":[
        "Eriskay"
    ],
    "name:nld_x_preferred":[
        "Eriskay"
    ],
    "name:nno_x_preferred":[
        "Eriskay"
    ],
    "name:nor_x_preferred":[
        "Eriskay"
    ],
    "name:por_x_preferred":[
        "Eriskay"
    ],
    "name:rus_x_preferred":[
        "\u042d\u0440\u0438\u0441\u043a\u0435\u0439"
    ],
    "name:sco_x_preferred":[
        "Eriskay"
    ],
    "name:swe_x_preferred":[
        "Eriskay"
    ],
    "name:zho_x_preferred":[
        "\u57c3\u91cc\u65af\u51f1\u5cf6"
    ],
    "qs_pg:aaroncc":"GB",
    "qs_pg:gn_country":"GB",
    "qs_pg:name":"Eriskay",
    "qs_pg:name_adm0":"United Kingdom",
    "qs_pg:name_adm1":"Scotland",
    "qs_pg:photos":181,
    "qs_pg:photos_1k":37,
    "qs_pg:photos_9k":1,
    "qs_pg:photos_9r":4,
    "qs_pg:photos_all":181,
    "qs_pg:photos_sr":4,
    "qs_pg:pop_sr":0,
    "qs_pg:qs_pg_placetype":"locality",
    "qs_pg:qs_pg_placetype_gp":"Town",
    "qs_pg:woe_adm0":23424975,
    "woe:adm0_id":23424975,
    "woe:name_adm0":"United Kingdom",
    "woe:name_adm1":"Scotland",
    "woe:placetype":"Town",
    "wof:name":"Eriskay",
    "wof:placetype":"locality"
},
  "geometry": {"coordinates":[-7.307667,57.080761],"type":"Point"}
}