{
  "type": "Feature",
  "properties": {
    "gn:country":"GB",
    "gn:fcode":"PPL",
    "gn:population":0,
    "iso:country":"GB",
    "name:eng_x_preferred":[
        "Flockton"
    ],
    "name:fra_x_preferred":[
        "Flockton"
    ],
    "name:nld_x_preferred":[
        "Flockton"
    ],
    "name:pol_x_preferred":[
        "Flockton"
    ],
    "name:spa_x_preferred":[
        "Flockton"
    ],
    "name:swe_x_preferred":[
        "Flockton"
    ],
    "qs_pg:aaroncc":"GB",
    "qs_pg:gn_country":"GB",
    "qs_pg:gn_fcode":"PPL",
    "qs_pg:gn_pop":0,
    "qs_pg:name":"Flockton",
    "qs_pg:name_adm0":"United Kingdom",
    "qs_pg:name_adm1":"England",
    "qs_pg:photos":107,
    "qs_pg:photos_1k":22,
    "qs_pg:photos_9k":1,
    "qs_pg:photos_9r":3,
    "qs_pg:photos_all":107,
    "qs_pg:photos_sr":3,
    "qs_pg:pop_sr":0,
    "qs_pg:qs_pg_placetype":"locality",
    "qs_pg:qs_pg_placetype_gp":"Town",
    "qs_pg:woe_adm0":23424975,
    "woe:adm0_id":23424975,
    "woe:name_adm0":"United Kingdom",
    "woe:name_adm1":"England",
    "woe:placetype":"Town",
    "wof:name":"Flockton",
    "wof:placetype":"neighbourhood",
    "wof:population":1368
},
  "geometry": {"coordinates":[-1.63945,53.63034],"type":"Point"}
}