{
  "type": "Feature",
  "properties": {
    "gn:country":"GB",
    "gn:fcode":"PPL",
    "gn:population":0,
    "iso:country":"GB",
    "name:azb_x_preferred":[
        "\u067e\u0648\u0631\u062a\u0686\u0633\u062a\u0631"
    ],
    "name:deu_x_preferred":[
        "Portchester"
    ],
    "name:eng_x_preferred":[
        "Portchester"
    ],
    "name:fas_x_preferred":[
        "\u067e\u0648\u0631\u062a\u0686\u0633\u062a\u0631"
    ],
    "name:fra_x_preferred":[
        "Portchester"
    ],
    "name:gle_x_preferred":[
        "Portchester"
    ],
    "name:heb_x_preferred":[
        "\u05e4\u05d5\u05e8\u05d8\u05e6'\u05e1\u05d8\u05e8"
    ],
    "name:lat_x_preferred":[
        "Portchester"
    ],
    "name:nld_x_preferred":[
        "Portchester"
    ],
    "name:pol_x_preferred":[
        "Portchester"
    ],
    "name:sco_x_preferred":[
        "Portchester"
    ],
    "name:swe_x_preferred":[
        "Portchester"
    ],
    "name:und_x_variant":[
        "Porchester"
    ],
    "name:zho_x_preferred":[
        "\u6ce2\u7279\u5207\u65af\u7279"
    ],
    "qs_pg:aaroncc":"GB",
    "qs_pg:gn_country":"GB",
    "qs_pg:gn_fcode":"PPL",
    "qs_pg:gn_pop":0,
    "qs_pg:name":"Portchester",
    "qs_pg:name_adm0":"United Kingdom",
    "qs_pg:name_adm1":"England",
    "qs_pg:photos":1075,
    "qs_pg:photos_1k":218,
    "qs_pg:photos_9k":5,
    "qs_pg:photos_9r":7,
    "qs_pg:photos_all":1075,
    "qs_pg:photos_sr":11,
    "qs_pg:pop_sr":0,
    "qs_pg:qs_pg_placetype":"locality",
    "qs_pg:qs_pg_placetype_gp":"Town",
    "qs_pg:woe_adm0":23424975,
    "woe:adm0_id":23424975,
    "woe:name_adm0":"United Kingdom",
    "woe:name_adm1":"England",
    "woe:placetype":"Town",
    "wof:name":"Portchester",
    "wof:placetype":"neighbourhood"
},
  "geometry": {"coordinates":[-1.12043,50.84172],"type":"Point"}
}