{
  "type": "Feature",
  "properties": {
    "gn:country":"GB",
    "gn:fcode":"PPL",
    "gn:population":0,
    "iso:country":"GB",
    "name:ast_x_preferred":[
        "Portchester"
    ],
    "name:azb_x_preferred":[
        "\u067e\u0648\u0631\u062a\u0686\u0633\u062a\u0631"
    ],
    "name:cat_x_preferred":[
        "Portchester"
    ],
    "name:deu_x_preferred":[
        "Portchester"
    ],
    "name:ell_x_preferred":[
        "\u03a0\u03cc\u03c1\u03c4\u03c3\u03b5\u03c3\u03c4\u03b5\u03c1"
    ],
    "name:eng_x_preferred":[
        "Portchester"
    ],
    "name:fas_x_preferred":[
        "\u067e\u0648\u0631\u062a\u0686\u0633\u062a\u0631"
    ],
    "name:fra_x_preferred":[
        "Portchester"
    ],
    "name:gle_x_preferred":[
        "Portchester"
    ],
    "name:heb_x_preferred":[
        "\u05e4\u05d5\u05e8\u05d8\u05e6'\u05e1\u05d8\u05e8"
    ],
    "name:hye_x_preferred":[
        "\u0553\u0578\u0580\u0569\u0579\u0565\u057d\u057f\u0565\u0580"
    ],
    "name:ita_x_preferred":[
        "Portchester"
    ],
    "name:jpn_x_preferred":[
        "\u30dd\u30fc\u30c8\u30c1\u30a7\u30b9\u30bf\u30fc"
    ],
    "name:lat_x_preferred":[
        "Portchester"
    ],
    "name:nld_x_preferred":[
        "Portchester"
    ],
    "name:nrm_x_preferred":[
        "Portch\u00eatre"
    ],
    "name:pol_x_preferred":[
        "Portchester"
    ],
    "name:rus_x_preferred":[
        "\u041f\u043e\u0440\u0442\u0447\u0435\u0441\u0442\u0435\u0440"
    ],
    "name:sco_x_preferred":[
        "Portchester"
    ],
    "name:swe_x_preferred":[
        "Portchester"
    ],
    "name:und_x_variant":[
        "Porchester"
    ],
    "name:zho_x_preferred":[
        "\u6ce2\u7279\u5207\u65af\u7279"
    ],
    "qs_pg:aaroncc":"GB",
    "qs_pg:gn_country":"GB",
    "qs_pg:gn_fcode":"PPL",
    "qs_pg:gn_pop":0,
    "qs_pg:name":"Portchester",
    "qs_pg:name_adm0":"United Kingdom",
    "qs_pg:name_adm1":"England",
    "qs_pg:photos":1075,
    "qs_pg:photos_1k":218,
    "qs_pg:photos_9k":5,
    "qs_pg:photos_9r":7,
    "qs_pg:photos_all":1075,
    "qs_pg:photos_sr":11,
    "qs_pg:pop_sr":0,
    "qs_pg:qs_pg_placetype":"locality",
    "qs_pg:qs_pg_placetype_gp":"Town",
    "qs_pg:woe_adm0":23424975,
    "woe:adm0_id":23424975,
    "woe:name_adm0":"United Kingdom",
    "woe:name_adm1":"England",
    "woe:placetype":"Town",
    "wof:name":"Portchester",
    "wof:placetype":"neighbourhood"
},
  "geometry": {"coordinates":[-1.12043,50.84172],"type":"Point"}
}