{
  "type": "Feature",
  "properties": {
    "iso:country":"GB",
    "name:ceb_x_preferred":[
        "Badgers Mount"
    ],
    "name:cym_x_preferred":[
        "Badgers Mount"
    ],
    "name:eng_x_preferred":[
        "Badgers Mount"
    ],
    "name:fra_x_preferred":[
        "Badgers Mount"
    ],
    "name:nld_x_preferred":[
        "Badgers Mount"
    ],
    "name:pol_x_preferred":[
        "Badgers Mount"
    ],
    "name:spa_x_preferred":[
        "Badgers Mount"
    ],
    "name:swe_x_preferred":[
        "Badgers Mount"
    ],
    "qs_pg:aaroncc":"GB",
    "qs_pg:name":"Badgers Mount",
    "qs_pg:name_adm0":"United Kingdom",
    "qs_pg:name_adm1":"England",
    "qs_pg:photos":25,
    "qs_pg:photos_1k":5,
    "qs_pg:photos_9k":1,
    "qs_pg:photos_9r":1,
    "qs_pg:photos_all":25,
    "qs_pg:photos_sr":1,
    "qs_pg:pop_sr":0,
    "qs_pg:qs_pg_placetype":"locality",
    "qs_pg:qs_pg_placetype_gp":"Town",
    "qs_pg:woe_adm0":23424975,
    "woe:adm0_id":23424975,
    "woe:name_adm0":"United Kingdom",
    "woe:name_adm1":"England",
    "woe:placetype":"Town",
    "wof:name":"Badgers Mount",
    "wof:placetype":"neighbourhood"
},
  "geometry": {"coordinates":[0.149323,51.340907],"type":"Point"}
}