{
  "type": "Feature",
  "properties": {
    "gn:country": "GB",
    "gn:fcode": "PPL",
    "gn:population": 568,
    "iso:country": "GB",
    "name:bre_x_preferred": [
      "Inbhir Aora"
    ],
    "name:bul_x_preferred": [
      "Инверарай"
    ],
    "name:cat_x_preferred": [
      "Inveraray"
    ],
    "name:ceb_x_preferred": [
      "Inveraray"
    ],
    "name:cym_x_preferred": [
      "Inveraray"
    ],
    "name:deu_x_preferred": [
      "Inveraray"
    ],
    "name:eng_x_preferred": [
      "Inveraray"
    ],
    "name:eus_x_preferred": [
      "Inveraray"
    ],
    "name:fas_x_preferred": [
      "اینوراری"
    ],
    "name:fra_x_preferred": [
      "Inveraray"
    ],
    "name:gla_x_preferred": [
      "Inbhir Aora"
    ],
    "name:gle_x_preferred": [
      "Inbhir Aora"
    ],
    "name:glg_x_preferred": [
      "Inveraray"
    ],
    "name:heb_x_preferred": [
      "אינוורארי"
    ],
    "name:ita_x_preferred": [
      "Inveraray"
    ],
    "name:jpn_x_preferred": [
      "インバレライ"
    ],
    "name:nld_x_preferred": [
      "Inveraray"
    ],
    "name:nno_x_preferred": [
      "Inveraray"
    ],
    "name:nob_x_preferred": [
      "Inveraray"
    ],
    "name:pol_x_preferred": [
      "Inveraray"
    ],
    "name:sco_x_preferred": [
      "Inverara"
    ],
    "name:spa_x_preferred": [
      "Inveraray"
    ],
    "name:swe_x_preferred": [
      "Inveraray"
    ],
    "name:zho_x_preferred": [
      "因弗拉裡"
    ],
    "qs_pg:aaroncc": "GB",
    "qs_pg:gn_country": "GB",
    "qs_pg:gn_fcode": "PPL",
    "qs_pg:gn_pop": 568,
    "qs_pg:name": "Inveraray",
    "qs_pg:name_adm0": "United Kingdom",
    "qs_pg:name_adm1": "Scotland",
    "qs_pg:photos": 4996,
    "qs_pg:photos_1k": 1000,
    "qs_pg:photos_9k": 22,
    "qs_pg:photos_9r": 14,
    "qs_pg:photos_all": 4996,
    "qs_pg:photos_sr": 24,
    "qs_pg:pop_sr": 2,
    "qs_pg:qs_pg_placetype": "locality",
    "qs_pg:qs_pg_placetype_gp": "Town",
    "qs_pg:woe_adm0": 23424975,
    "woe:adm0_id": 23424975,
    "woe:name_adm0": "United Kingdom",
    "woe:name_adm1": "Scotland",
    "woe:placetype": "Town",
    "wof:name": "Inveraray",
    "wof:placetype": "locality",
    "wof:population": 570
  },
  "geometry": {"coordinates":[-5.07474,56.23052],"type":"Point"}
}
