{
  "type": "Feature",
  "properties": {
    "gn:country":"GB",
    "gn:fcode":"PPL",
    "gn:population":568,
    "iso:country":"GB",
    "name:ast_x_preferred":[
        "Inveraray"
    ],
    "name:bre_x_preferred":[
        "Inbhir Aora"
    ],
    "name:bul_x_preferred":[
        "\u0418\u043d\u0432\u0435\u0440\u0430\u0440\u0430\u0439"
    ],
    "name:cat_x_preferred":[
        "Inveraray"
    ],
    "name:ceb_x_preferred":[
        "Inveraray"
    ],
    "name:ces_x_preferred":[
        "Inveraray"
    ],
    "name:cym_x_preferred":[
        "Inveraray"
    ],
    "name:deu_x_preferred":[
        "Inveraray"
    ],
    "name:eng_x_preferred":[
        "Inveraray"
    ],
    "name:eus_x_preferred":[
        "Inveraray"
    ],
    "name:fas_x_preferred":[
        "\u0627\u06cc\u0646\u0648\u0631\u0627\u0631\u06cc"
    ],
    "name:fra_x_preferred":[
        "Inveraray"
    ],
    "name:gla_x_preferred":[
        "Inbhir Aora"
    ],
    "name:gle_x_preferred":[
        "Inbhir Aora"
    ],
    "name:glg_x_preferred":[
        "Inveraray"
    ],
    "name:heb_x_preferred":[
        "\u05d0\u05d9\u05e0\u05d5\u05d5\u05e8\u05d0\u05e8\u05d9"
    ],
    "name:ita_x_preferred":[
        "Inveraray"
    ],
    "name:jpn_x_preferred":[
        "\u30a4\u30f3\u30d0\u30ec\u30e9\u30a4"
    ],
    "name:nld_x_preferred":[
        "Inveraray"
    ],
    "name:nno_x_preferred":[
        "Inveraray"
    ],
    "name:nob_x_preferred":[
        "Inveraray"
    ],
    "name:pol_x_preferred":[
        "Inveraray"
    ],
    "name:rus_x_preferred":[
        "\u0418\u043d\u0432\u0435\u0440\u0435\u0440\u0435\u0439"
    ],
    "name:sco_x_preferred":[
        "Inverara"
    ],
    "name:sco_x_variant":[
        "Inverera"
    ],
    "name:spa_x_preferred":[
        "Inveraray"
    ],
    "name:swe_x_preferred":[
        "Inveraray"
    ],
    "name:zho_x_preferred":[
        "\u56e0\u5f17\u62c9\u88e1"
    ],
    "qs_pg:aaroncc":"GB",
    "qs_pg:gn_country":"GB",
    "qs_pg:gn_fcode":"PPL",
    "qs_pg:gn_pop":568,
    "qs_pg:name":"Inveraray",
    "qs_pg:name_adm0":"United Kingdom",
    "qs_pg:name_adm1":"Scotland",
    "qs_pg:photos":4996,
    "qs_pg:photos_1k":1000,
    "qs_pg:photos_9k":22,
    "qs_pg:photos_9r":14,
    "qs_pg:photos_all":4996,
    "qs_pg:photos_sr":24,
    "qs_pg:pop_sr":2,
    "qs_pg:qs_pg_placetype":"locality",
    "qs_pg:qs_pg_placetype_gp":"Town",
    "qs_pg:woe_adm0":23424975,
    "woe:adm0_id":23424975,
    "woe:name_adm0":"United Kingdom",
    "woe:name_adm1":"Scotland",
    "woe:placetype":"Town",
    "wof:name":"Inveraray",
    "wof:placetype":"locality",
    "wof:population":570
},
  "geometry": {"coordinates":[-5.07474,56.23052],"type":"Point"}
}