{
  "type": "Feature",
  "properties": {
    "iso:country":"GB",
    "name:ara_x_preferred":[
        "\u0646\u0633\u062a\u0644\u0646"
    ],
    "name:arz_x_preferred":[
        "\u0646\u0633\u062a\u0644\u0646"
    ],
    "name:cor_x_preferred":[
        "Nansalen"
    ],
    "name:cym_x_preferred":[
        "Nanstallon"
    ],
    "name:cym_x_variant":[
        "Nansalen"
    ],
    "name:eng_x_preferred":[
        "Nanstallon"
    ],
    "name:eus_x_preferred":[
        "Nanstallon"
    ],
    "name:fra_x_preferred":[
        "Nanstallon"
    ],
    "name:gle_x_preferred":[
        "Nanstallon"
    ],
    "name:jpn_x_preferred":[
        "\u30ca\u30f3\u30b9\u30bf\u30ed\u30f3"
    ],
    "name:nld_x_preferred":[
        "Nanstallon"
    ],
    "name:pol_x_preferred":[
        "Nanstallon"
    ],
    "name:spa_x_preferred":[
        "Nanstallon"
    ],
    "name:swe_x_preferred":[
        "Nanstallon"
    ],
    "qs_pg:aaroncc":"GB",
    "qs_pg:name":"Nanstallon",
    "qs_pg:name_adm0":"United Kingdom",
    "qs_pg:name_adm1":"England",
    "qs_pg:photos":85,
    "qs_pg:photos_1k":17,
    "qs_pg:photos_9k":1,
    "qs_pg:photos_9r":3,
    "qs_pg:photos_all":85,
    "qs_pg:photos_sr":3,
    "qs_pg:pop_sr":0,
    "qs_pg:qs_pg_placetype":"locality",
    "qs_pg:qs_pg_placetype_gp":"Town",
    "qs_pg:woe_adm0":23424975,
    "woe:adm0_id":23424975,
    "woe:name_adm0":"United Kingdom",
    "woe:name_adm1":"England",
    "woe:placetype":"Town",
    "wof:name":"Nanstallon",
    "wof:placetype":"neighbourhood"
},
  "geometry": {"coordinates":[-4.762551,50.473621],"type":"Point"}
}