{
  "type": "Feature",
  "properties": {
    "gn:admin1_code":"SCT",
    "gn:admin2_code":"V8",
    "gn:asciiname":"Salsburgh",
    "gn:country_code":"GB",
    "gn:dem":240,
    "gn:feature_class":"P",
    "gn:feature_code":"PPL",
    "gn:name":"Salsburgh",
    "gn:population":1540,
    "gn:timezone":"Europe/London",
    "iso:country":"GB",
    "name:cym_x_preferred":[
        "Salsburgh"
    ],
    "name:eus_x_preferred":[
        "Salsburgh"
    ],
    "name:spa_x_preferred":[
        "Salsburgh"
    ],
    "name:swe_x_preferred":[
        "Salsburgh"
    ],
    "wof:name":"Salsburgh",
    "wof:placetype":"locality",
    "wof:population":1540
},
  "geometry": {"coordinates":[-3.87264,55.84277],"type":"Point"}
}