{
  "type": "Feature",
  "properties": {
    "iso:country":"GB",
    "name:bre_x_preferred":[
        "Cefneithin"
    ],
    "name:cym_x_preferred":[
        "Cefneithin"
    ],
    "name:eng_x_preferred":[
        "Cefneithin"
    ],
    "name:fra_x_preferred":[
        "Cefneithin"
    ],
    "name:gla_x_preferred":[
        "Cefneithin"
    ],
    "name:gle_x_preferred":[
        "Cefneithin"
    ],
    "name:nld_x_preferred":[
        "Cefneithin"
    ],
    "name:sco_x_preferred":[
        "Cefneithin"
    ],
    "qs:a0":"United Kingdom",
    "qs:a1":"*Sir Gaerfyrddin#Carmarthenshire",
    "qs:a1_lc":"GB13NU0000",
    "qs:a1r":"0Wales",
    "qs:a1r_lc":"GB13000000",
    "qs:adm0":"United Kingdom",
    "qs:la_lc":"*",
    "qs:level":"locality",
    "qs:loc":"Cefneithin",
    "qs:loc_alt":"Cefneithin",
    "qs:pop":0,
    "qs:type":"buffered point",
    "wd:wordcount":124,
    "wof:lang":[
        "eng"
    ],
    "wof:name":"Cefneithin",
    "wof:placetype":"neighbourhood"
},
  "geometry": {"coordinates":[-4.082394,51.796782],"type":"Point"}
}