{
  "type": "Feature",
  "properties": {
    "gn:admin1_code":"SCT",
    "gn:admin2_code":"V6",
    "gn:asciiname":"Knock",
    "gn:country_code":"GB",
    "gn:dem":140,
    "gn:feature_class":"P",
    "gn:feature_code":"PPL",
    "gn:name":"Knock",
    "gn:population":0,
    "gn:timezone":"Europe/London",
    "iso:country":"GB",
    "wof:name":"Knock",
    "wof:placetype":"locality"
},
  "geometry": {"coordinates":[-2.75,57.55],"type":"Point"}
}