{
  "type": "Feature",
  "properties": {
    "gn:admin1_code":"SCT",
    "gn:admin2_code":"V6",
    "gn:asciiname":"Knock",
    "gn:country_code":"GB",
    "gn:dem":140,
    "gn:feature_class":"P",
    "gn:feature_code":"PPL",
    "gn:name":"Knock",
    "gn:population":0,
    "gn:timezone":"Europe/London",
    "iso:country":"GB",
    "name:ceb_x_preferred":[
        "Knock"
    ],
    "name:deu_x_preferred":[
        "Knock"
    ],
    "name:fra_x_preferred":[
        "Knock"
    ],
    "name:ido_x_preferred":[
        "Knock"
    ],
    "name:ita_x_preferred":[
        "Knock"
    ],
    "name:jpn_x_preferred":[
        "\u30ce\u30c3\u30af"
    ],
    "name:nld_x_preferred":[
        "Knock"
    ],
    "name:pol_x_preferred":[
        "Knock"
    ],
    "name:swe_x_preferred":[
        "Knock"
    ],
    "wof:name":"Knock",
    "wof:placetype":"locality"
},
  "geometry": {"coordinates":[-2.75,57.55],"type":"Point"}
}