{
  "type": "Feature",
  "properties": {
    "gn:admin1_code":"SCT",
    "gn:admin2_code":"T8",
    "gn:asciiname":"Drumore",
    "gn:country_code":"GB",
    "gn:dem":26,
    "gn:feature_class":"P",
    "gn:feature_code":"PPL",
    "gn:name":"Drumore",
    "gn:population":0,
    "gn:timezone":"Europe/London",
    "iso:country":"GB",
    "wof:name":"Drumore",
    "wof:placetype":"locality"
},
  "geometry": {"coordinates":[-5.62749,55.43904],"type":"Point"}
}