{
  "type": "Feature",
  "properties": {
    "iso:country":"GB",
    "name:deu_x_preferred":[
        "Scholes"
    ],
    "name:fra_x_preferred":[
        "Scholes"
    ],
    "name:ita_x_preferred":[
        "Scholes"
    ],
    "name:nds_x_preferred":[
        "Scholes"
    ],
    "name:nld_x_preferred":[
        "Scholes"
    ],
    "name:pol_x_preferred":[
        "Scholes"
    ],
    "name:por_x_preferred":[
        "Scholes"
    ],
    "name:rus_x_preferred":[
        "\u0421\u043a\u043e\u0443\u043b\u0437"
    ],
    "name:spa_x_preferred":[
        "Scholes"
    ],
    "name:swe_x_preferred":[
        "Scholes"
    ],
    "name:ukr_x_preferred":[
        "\u0421\u043a\u043e\u0443\u043b\u0437"
    ],
    "wof:name":"Scholes",
    "wof:placetype":"neighbourhood"
},
  "geometry": {"coordinates":[-1.97278256301585,53.84192396510671],"type":"Point"}
}