{
  "type": "Feature",
  "properties": {
    "gn:admin1_code":"WLS",
    "gn:admin2_code":"X6",
    "gn:admin3_code":"00NQ023",
    "gn:asciiname":"Dihewid",
    "gn:cc2":"GB",
    "gn:country_code":"GB",
    "gn:dem":226,
    "gn:feature_class":"P",
    "gn:feature_code":"PPL",
    "gn:name":"Dihewid",
    "gn:population":0,
    "gn:timezone":"Europe/London",
    "iso:country":"GB",
    "name:bre_x_preferred":[
        "Dihewyd"
    ],
    "name:cym_x_preferred":[
        "Dihewyd"
    ],
    "name:eus_x_preferred":[
        "Dihewyd"
    ],
    "name:und_x_variant":[
        "Dihewid"
    ],
    "wof:name":"Dihewid",
    "wof:placetype":"neighbourhood"
},
  "geometry": {"coordinates":[-4.21667,52.18333],"type":"Point"}
}