{
  "type": "Feature",
  "properties": {
    "gn:gn_country":"GB",
    "gn:gn_fcode":"PPL",
    "gn:gn_pop":1,
    "gn:population":1540,
    "iso:country":"GB",
    "name:dut_x_preferred":[
        "Rosewell"
    ],
    "name:eng_x_preferred":[
        "Rosewell"
    ],
    "name:fre_x_preferred":[
        "Rosewell"
    ],
    "name:ger_x_preferred":[
        "Rosewell"
    ],
    "name:jpn_x_preferred":[
        "\u30ed\u30ba\u30a6\u30a7\u30eb"
    ],
    "name:swe_x_preferred":[
        "Rosewell"
    ],
    "qs_pg:aaroncc":"GB",
    "qs_pg:gn_country":"GB",
    "qs_pg:gn_fcode":"PPL",
    "qs_pg:gn_pop":1,
    "qs_pg:name":"Rosewell",
    "qs_pg:name_adm0":"United Kingdom",
    "qs_pg:name_adm1":"Scotland",
    "qs_pg:photos":202,
    "qs_pg:photos_1k":41,
    "qs_pg:photos_9k":1,
    "qs_pg:photos_9r":4,
    "qs_pg:photos_all":202,
    "qs_pg:photos_sr":4,
    "qs_pg:pop_sr":1,
    "qs_pg:qs_pg_placetype":"locality",
    "qs_pg:qs_pg_placetype_gp":"Town",
    "qs_pg:woe_adm0":23424975,
    "woe:adm0_id":23424975,
    "woe:name_adm0":"United Kingdom",
    "woe:name_adm1":"Scotland",
    "woe:placetype":"Town",
    "wof:name":"Rosewell",
    "wof:placetype":"locality",
    "wof:population":1540
},
  "geometry": {"coordinates":[-3.13625,55.85075],"type":"Point"}
}