{
  "type": "Feature",
  "properties": {
    "gn:admin1_code":"SCT",
    "gn:admin2_code":"V6",
    "gn:asciiname":"Kirktown of Mortlach",
    "gn:cc2":"GB",
    "gn:country_code":"GB",
    "gn:dem":212,
    "gn:feature_class":"P",
    "gn:feature_code":"PPL",
    "gn:name":"Kirktown of Mortlach",
    "gn:population":0,
    "gn:timezone":"Europe/London",
    "iso:country":"GB",
    "name:und_x_variant":[
        "Mortlach",
        "Kirktown of Mortlach"
    ],
    "wof:name":"Kirktown of Mortlach",
    "wof:placetype":"locality"
},
  "geometry": {"coordinates":[-3.13333,57.43333000000001],"type":"Point"}
}