{
  "type": "Feature",
  "properties": {
    "gn:admin1_code": "ENG",
    "gn:admin2_code": "O2",
    "gn:admin3_code": "00GF024",
    "gn:asciiname": "Cherrington",
    "gn:country_code": "GB",
    "gn:dem": 65,
    "gn:feature_class": "P",
    "gn:feature_code": "PPL",
    "gn:name": "Cherrington",
    "gn:population": 0,
    "gn:timezone": "Europe/London",
    "iso:country": "GB",
    "name:cym_x_preferred": [
      "Cherrington"
    ],
    "name:pol_x_preferred": [
      "Cherrington"
    ],
    "wof:name": "Cherrington",
    "wof:placetype": "neighbourhood"
  },
  "geometry": {"coordinates":[-2.49644,52.77634000000001],"type":"Point"}
}
