{
  "type": "Feature",
  "properties": {
    "gn:admin1_code":"ENG",
    "gn:admin2_code":"J7",
    "gn:admin3_code":"36UF",
    "gn:admin4_code":"36UF051",
    "gn:asciiname":"West Heslerton",
    "gn:country_code":"GB",
    "gn:dem":45,
    "gn:feature_class":"P",
    "gn:feature_code":"PPL",
    "gn:name":"West Heslerton",
    "gn:population":0,
    "gn:timezone":"Europe/London",
    "iso:country":"GB",
    "name:pol_x_preferred":[
        "West Heslerton"
    ],
    "name:und_x_variant":[
        "Heslerton"
    ],
    "wof:name":"West Heslerton",
    "wof:placetype":"neighbourhood"
},
  "geometry": {"coordinates":[-0.60755,54.17222],"type":"Point"}
}