{
  "type": "Feature",
  "properties": {
    "gn:admin1_code": "SCT",
    "gn:admin2_code": "T6",
    "gn:asciiname": "Tillinamolt",
    "gn:country_code": "GB",
    "gn:dem": 99,
    "gn:feature_class": "P",
    "gn:feature_code": "PPL",
    "gn:name": "Tillinamolt",
    "gn:population": 0,
    "gn:timezone": "Europe/London",
    "iso:country": "GB",
    "wof:name": "Tillinamolt",
    "wof:placetype": "locality"
  },
  "geometry": {"coordinates":[-2.18333,57.61666999999999],"type":"Point"}
}
