{
  "type": "Feature",
  "properties": {
    "iso:country":"GB",
    "name:eng_x_preferred":[
        "Knockentiber"
    ],
    "name:eus_x_preferred":[
        "Knockentiber"
    ],
    "name:fra_x_preferred":[
        "Knockentiber"
    ],
    "name:gla_x_preferred":[
        "Cnoc an Tiobair"
    ],
    "name:gle_x_preferred":[
        "Cnoc an Tobair"
    ],
    "name:nld_x_preferred":[
        "Knockentiber"
    ],
    "qs_pg:aaroncc":"GB",
    "qs_pg:name":"Knockentiber",
    "qs_pg:name_adm0":"United Kingdom",
    "qs_pg:name_adm1":"Scotland",
    "qs_pg:photos":14,
    "qs_pg:photos_1k":3,
    "qs_pg:photos_9k":1,
    "qs_pg:photos_9r":1,
    "qs_pg:photos_all":14,
    "qs_pg:photos_sr":1,
    "qs_pg:pop_sr":0,
    "qs_pg:qs_pg_placetype":"locality",
    "qs_pg:qs_pg_placetype_gp":"Town",
    "qs_pg:woe_adm0":23424975,
    "woe:adm0_id":23424975,
    "woe:name_adm0":"United Kingdom",
    "woe:name_adm1":"Scotland",
    "woe:placetype":"Town",
    "wof:name":"Knockentiber",
    "wof:placetype":"locality"
},
  "geometry": {"coordinates":[-4.54425,55.620725],"type":"Point"}
}