{
  "type": "Feature",
  "properties": {
    "iso:country":"GB",
    "name:cym_x_preferred":[
        "Borras"
    ],
    "name:eng_x_preferred":[
        "Borras"
    ],
    "name:eus_x_preferred":[
        "Borras"
    ],
    "name:fra_x_preferred":[
        "Borras"
    ],
    "name:gle_x_preferred":[
        "Borras"
    ],
    "name:nld_x_preferred":[
        "Borras"
    ],
    "qs_pg:aaroncc":"GB",
    "qs_pg:name":"Borras",
    "qs_pg:name_adm0":"United Kingdom",
    "qs_pg:name_adm1":"Wales",
    "qs_pg:photos":182,
    "qs_pg:photos_1k":37,
    "qs_pg:photos_9k":1,
    "qs_pg:photos_9r":4,
    "qs_pg:photos_all":182,
    "qs_pg:photos_sr":4,
    "qs_pg:pop_sr":0,
    "qs_pg:qs_pg_placetype":"locality",
    "qs_pg:qs_pg_placetype_gp":"Town",
    "qs_pg:woe_adm0":23424975,
    "woe:adm0_id":23424975,
    "woe:name_adm0":"United Kingdom",
    "woe:name_adm1":"Wales",
    "woe:placetype":"Town",
    "wof:name":"Borras",
    "wof:placetype":"neighbourhood"
},
  "geometry": {"coordinates":[-2.965944,53.058395],"type":"Point"}
}