{
  "type": "Feature",
  "properties": {
    "gn:admin1_code":"ENG",
    "gn:admin2_code":"P6",
    "gn:admin3_code":"45UD",
    "gn:admin4_code":"45UD008",
    "gn:asciiname":"Bury Common",
    "gn:country_code":"GB",
    "gn:dem":10,
    "gn:feature_class":"P",
    "gn:feature_code":"PPL",
    "gn:name":"Bury Common",
    "gn:population":0,
    "gn:timezone":"Europe/London",
    "iso:country":"GB",
    "wof:name":"Bury Common",
    "wof:placetype":"neighbourhood"
},
  "geometry": {"coordinates":[-0.56545,50.91783],"type":"Point"}
}