{
  "type": "Feature",
  "properties": {
    "iso:country":"GB",
    "wof:name":"St George's",
    "wof:placetype":"neighbourhood"
},
  "geometry": {"coordinates":[-1.47700621691535,53.38188499392873],"type":"Point"}
}