{
  "type": "Feature",
  "properties": {
    "iso:country":"GB",
    "name:eng_x_preferred":[
        "Westgate"
    ],
    "name:unk_x_variant":[
        "Westgate"
    ],
    "qs:gn_adm0_cc":"GB",
    "qs:gn_local":2652890,
    "qs:gn_nam_loc":"cleckheaton",
    "qs:gn_namadm1":"ENG",
    "qs:local_max":550,
    "qs:local_sum":990,
    "qs:localhoods":4,
    "qs:name":"Westgate",
    "qs:name_adm0":"United Kingdom",
    "qs:name_adm1":"England",
    "qs:name_adm2":"West Yorkshire",
    "qs:name_lau":"Kirklees Metropolitan Borough",
    "qs:name_local":"Cleckheaton",
    "qs:photo_max":5,
    "qs:photo_sum":11,
    "qs:placetype":"Suburb",
    "qs:quad_count":6,
    "qs:woe_adm0":23424975,
    "qs:woe_adm1":24554868,
    "qs:woe_adm2":12602197,
    "qs:woe_lau":12695872,
    "qs:woe_local":16253,
    "qs:woe_ver":"7.10.0",
    "wof:lang":[
        "eng"
    ],
    "wof:name":"Westgate",
    "wof:placetype":"neighbourhood"
},
  "geometry": {"coordinates":[-1.733093,53.725503],"type":"Point"}
}