{
  "type": "Feature",
  "properties": {
    "gn:gn_country":"GB",
    "gn:gn_fcode":"PPL",
    "gn:gn_pop":0,
    "iso:country":"GB",
    "name:ara_x_preferred":[
        "\u0628\u0644\u062f\u0644\u0648"
    ],
    "name:dut_x_preferred":[
        "Bledlow"
    ],
    "name:eng_x_preferred":[
        "Bledlow"
    ],
    "name:fre_x_preferred":[
        "Bledlow"
    ],
    "name:pol_x_preferred":[
        "Bledlow"
    ],
    "name:wel_x_preferred":[
        "Bledlow"
    ],
    "qs_pg:aaroncc":"GB",
    "qs_pg:gn_country":"GB",
    "qs_pg:gn_fcode":"PPL",
    "qs_pg:gn_pop":0,
    "qs_pg:name":"Bledlow",
    "qs_pg:name_adm0":"United Kingdom",
    "qs_pg:name_adm1":"England",
    "qs_pg:photos":95,
    "qs_pg:photos_1k":19,
    "qs_pg:photos_9k":1,
    "qs_pg:photos_9r":3,
    "qs_pg:photos_all":95,
    "qs_pg:photos_sr":3,
    "qs_pg:pop_sr":0,
    "qs_pg:qs_pg_placetype":"locality",
    "qs_pg:qs_pg_placetype_gp":"Town",
    "qs_pg:woe_adm0":23424975,
    "woe:adm0_id":23424975,
    "woe:name_adm0":"United Kingdom",
    "woe:name_adm1":"England",
    "woe:placetype":"Town",
    "wof:name":"Bledlow",
    "wof:placetype":"neighbourhood"
},
  "geometry": {"coordinates":[-0.87719,51.71222],"type":"Point"}
}