{
  "type": "Feature",
  "properties": {
    "gn:admin1_code":"ENG",
    "gn:admin2_code":"O7",
    "gn:asciiname":"Carleton",
    "gn:country_code":"GB",
    "gn:dem":45,
    "gn:feature_class":"P",
    "gn:feature_code":"PPL",
    "gn:name":"Carleton",
    "gn:population":0,
    "gn:timezone":"Europe/London",
    "iso:country":"GB",
    "wof:name":"Carleton",
    "wof:placetype":"neighbourhood"
},
  "geometry": {"coordinates":[-1.29244,53.67551],"type":"Point"}
}