{
  "type": "Feature",
  "properties": {
    "iso:country":"GB",
    "name:afr_x_preferred":[
        "Southchurch"
    ],
    "name:ceb_x_preferred":[
        "Southchurch Village"
    ],
    "name:eng_x_preferred":[
        "Southchurch"
    ],
    "name:gle_x_preferred":[
        "Southchurch"
    ],
    "name:nld_x_preferred":[
        "Southchurch"
    ],
    "name:pol_x_preferred":[
        "Southchurch"
    ],
    "name:swe_x_preferred":[
        "Southchurch Village"
    ],
    "name:unk_x_variant":[
        "Southchurch"
    ],
    "qs:gn_adm0_cc":"GB",
    "qs:gn_local":2637433,
    "qs:local_max":5221,
    "qs:local_sum":7624,
    "qs:localhoods":2,
    "qs:name":"Southchurch",
    "qs:name_adm0":"United Kingdom",
    "qs:name_adm1":"England",
    "qs:name_adm2":"Essex",
    "qs:name_lau":"Southend-on-Sea Borough",
    "qs:name_local":"Southend-on-Sea",
    "qs:photo_max":577,
    "qs:photo_sum":5221,
    "qs:placetype":"Suburb",
    "qs:quad_count":145,
    "qs:woe_adm0":23424975,
    "qs:woe_adm1":24554868,
    "qs:woe_adm2":12602168,
    "qs:woe_lau":12696175,
    "qs:woe_local":35375,
    "qs:woe_ver":"7.10.0",
    "wd:wordcount":918,
    "wof:lang":[
        "eng"
    ],
    "wof:name":"Southchurch",
    "wof:placetype":"neighbourhood"
},
  "geometry": {"coordinates":[0.719235,51.535935],"type":"Point"}
}