{
  "type": "Feature",
  "properties": {
    "gn:admin1_code":"WLS",
    "gn:admin2_code":"Y7",
    "gn:admin3_code":"00NS036",
    "gn:asciiname":"Waterston",
    "gn:country_code":"GB",
    "gn:dem":60,
    "gn:feature_class":"P",
    "gn:feature_code":"PPL",
    "gn:name":"Waterston",
    "gn:population":335,
    "gn:timezone":"Europe/London",
    "iso:country":"GB",
    "name:cym_x_preferred":[
        "Waterston"
    ],
    "wof:name":"Waterston",
    "wof:placetype":"neighbourhood",
    "wof:population":335
},
  "geometry": {"coordinates":[-4.98775,51.71264],"type":"Point"}
}