{
  "type": "Feature",
  "properties": {
    "gn:gn_country":"GB",
    "gn:gn_fcode":"PPLX",
    "gn:gn_pop":5300,
    "gn:population":5300,
    "iso:country":"GB",
    "qs_pg:aaroncc":"GB",
    "qs_pg:gn_country":"GB",
    "qs_pg:gn_fcode":"PPLX",
    "qs_pg:gn_pop":5300,
    "qs_pg:name":"New Ferry",
    "qs_pg:photos_9r":0,
    "qs_pg:photos_sr":0,
    "qs_pg:pop_sr":5,
    "qs_pg:qs_pg_placetype":"neighbourhood",
    "wof:name":"New Ferry",
    "wof:placetype":"neighbourhood",
    "wof:population":5300
},
  "geometry": {"coordinates":[-2.99377,53.36046],"type":"Point"}
}