{
  "type": "Feature",
  "properties": {
    "iso:country":"GB",
    "name:eng_x_preferred":[
        "Holywell"
    ],
    "wof:name":"Holywell",
    "wof:placetype":"neighbourhood"
},
  "geometry": {"coordinates":[-1.2451016668028,51.75728917260699],"type":"Point"}
}