{
  "type": "Feature",
  "properties": {
    "gn:admin1_code": "ENG",
    "gn:admin2_code": "P6",
    "gn:admin3_code": "45UF",
    "gn:admin4_code": "45UF021",
    "gn:asciiname": "Clemsfold",
    "gn:country_code": "GB",
    "gn:dem": 52,
    "gn:feature_class": "P",
    "gn:feature_code": "PPL",
    "gn:name": "Clemsfold",
    "gn:population": 0,
    "gn:timezone": "Europe/London",
    "iso:country": "GB",
    "wof:name": "Clemsfold",
    "wof:placetype": "neighbourhood"
  },
  "geometry": {"coordinates":[-0.39512,51.08953],"type":"Point"}
}
