{
  "type": "Feature",
  "properties": {
    "gn:country":"GB",
    "gn:fcode":"PPL",
    "gn:population":0,
    "iso:country":"GB",
    "name:eng_x_preferred":[
        "Elsecar"
    ],
    "name:fra_x_preferred":[
        "Elsecar"
    ],
    "name:nld_x_preferred":[
        "Elsecar"
    ],
    "name:pol_x_preferred":[
        "Elsecar"
    ],
    "qs_pg:aaroncc":"GB",
    "qs_pg:gn_country":"GB",
    "qs_pg:gn_fcode":"PPL",
    "qs_pg:gn_pop":0,
    "qs_pg:name":"Elsecar",
    "qs_pg:name_adm0":"United Kingdom",
    "qs_pg:name_adm1":"England",
    "qs_pg:photos":2013,
    "qs_pg:photos_1k":408,
    "qs_pg:photos_9k":9,
    "qs_pg:photos_9r":9,
    "qs_pg:photos_all":2013,
    "qs_pg:photos_sr":15,
    "qs_pg:pop_sr":0,
    "qs_pg:qs_pg_placetype":"locality",
    "qs_pg:qs_pg_placetype_gp":"Town",
    "qs_pg:woe_adm0":23424975,
    "woe:adm0_id":23424975,
    "woe:name_adm0":"United Kingdom",
    "woe:name_adm1":"England",
    "woe:placetype":"Town",
    "wof:name":"Elsecar",
    "wof:placetype":"neighbourhood"
},
  "geometry": {"coordinates":[-1.42591,53.49892],"type":"Point"}
}