{
  "type": "Feature",
  "properties": {
    "iso:country":"GB",
    "name:eng_x_preferred":[
        "The Waterways"
    ],
    "name:eng_x_variant":[
        "Waterways"
    ],
    "wof:name":"The Waterways",
    "wof:placetype":"neighbourhood"
},
  "geometry": {"coordinates":[-1.27329706215394,51.77270272220495],"type":"Point"}
}