{
  "type": "Feature",
  "properties": {
    "gn:country":"GB",
    "gn:fcode":"PPL",
    "gn:population":0,
    "iso:country":"GB",
    "name:ceb_x_preferred":[
        "Flecknoe"
    ],
    "name:eng_x_preferred":[
        "Flecknoe"
    ],
    "name:fra_x_preferred":[
        "Flecknoe"
    ],
    "name:gle_x_preferred":[
        "Flecknoe"
    ],
    "name:nld_x_preferred":[
        "Flecknoe"
    ],
    "name:pol_x_preferred":[
        "Flecknoe"
    ],
    "name:swe_x_preferred":[
        "Flecknoe"
    ],
    "qs_pg:aaroncc":"GB",
    "qs_pg:gn_country":"GB",
    "qs_pg:gn_fcode":"PPL",
    "qs_pg:gn_pop":0,
    "qs_pg:name":"Flecknoe",
    "qs_pg:name_adm0":"United Kingdom",
    "qs_pg:name_adm1":"England",
    "qs_pg:photos":110,
    "qs_pg:photos_1k":22,
    "qs_pg:photos_9k":1,
    "qs_pg:photos_9r":3,
    "qs_pg:photos_all":110,
    "qs_pg:photos_sr":3,
    "qs_pg:pop_sr":0,
    "qs_pg:qs_pg_placetype":"locality",
    "qs_pg:qs_pg_placetype_gp":"Town",
    "qs_pg:woe_adm0":23424975,
    "woe:adm0_id":23424975,
    "woe:name_adm0":"United Kingdom",
    "woe:name_adm1":"England",
    "woe:placetype":"Town",
    "wof:name":"Flecknoe",
    "wof:placetype":"neighbourhood",
    "wof:population":284
},
  "geometry": {"coordinates":[-1.24618,52.26669],"type":"Point"}
}