{
  "type": "Feature",
  "properties": {
    "iso:country":"GB",
    "name:cym_x_preferred":[
        "Winchburgh"
    ],
    "name:deu_x_preferred":[
        "Winchburgh"
    ],
    "name:eus_x_preferred":[
        "Winchburgh"
    ],
    "name:spa_x_preferred":[
        "Winchburgh"
    ],
    "name:swe_x_preferred":[
        "Winchburgh"
    ],
    "qs_pg:aaroncc":"GB",
    "qs_pg:name":"Winchburgh",
    "qs_pg:name_adm0":"United Kingdom",
    "qs_pg:name_adm1":"Scotland",
    "qs_pg:photos":40,
    "qs_pg:photos_1k":8,
    "qs_pg:photos_9k":1,
    "qs_pg:photos_9r":2,
    "qs_pg:photos_all":40,
    "qs_pg:photos_sr":2,
    "qs_pg:pop_sr":0,
    "qs_pg:qs_pg_placetype":"locality",
    "qs_pg:qs_pg_placetype_gp":"Town",
    "qs_pg:woe_adm0":23424975,
    "woe:adm0_id":23424975,
    "woe:name_adm0":"United Kingdom",
    "woe:name_adm1":"Scotland",
    "woe:placetype":"Town",
    "wof:name":"Winchburgh",
    "wof:placetype":"locality"
},
  "geometry": {"coordinates":[-3.458933,55.9575755],"type":"Point"}
}