{
  "type": "Feature",
  "properties": {
    "gn:admin1_code":"WLS",
    "gn:admin2_code":"Y8",
    "gn:admin3_code":"00NN031",
    "gn:asciiname":"Cregrina",
    "gn:country_code":"GB",
    "gn:dem":190,
    "gn:feature_class":"P",
    "gn:feature_code":"PPL",
    "gn:name":"Cregrina",
    "gn:population":0,
    "gn:timezone":"Europe/London",
    "iso:country":"GB",
    "name:und_x_variant":[
        "Cregina",
        "Cregrina"
    ],
    "wof:name":"Cregrina",
    "wof:placetype":"neighbourhood"
},
  "geometry": {"coordinates":[-3.28202,52.16047],"type":"Point"}
}