{
  "type": "Feature",
  "properties": {
    "gn:admin1_code":"SCT",
    "gn:admin2_code":"V3",
    "gn:asciiname":"Muir of Ord",
    "gn:country_code":"GB",
    "gn:dem":35,
    "gn:feature_class":"P",
    "gn:feature_code":"PPL",
    "gn:name":"Muir of Ord",
    "gn:population":2620,
    "gn:timezone":"Europe/London",
    "iso:country":"GB",
    "name:ceb_x_preferred":[
        "Muir of Ord"
    ],
    "name:cym_x_preferred":[
        "Muir of Ord"
    ],
    "name:deu_x_preferred":[
        "Muir of Ord"
    ],
    "name:eus_x_preferred":[
        "Muir of Ord"
    ],
    "name:fry_x_preferred":[
        "Muir of Ord"
    ],
    "name:gla_x_preferred":[
        "Am Bl\u00e0r Dubh"
    ],
    "name:gle_x_preferred":[
        "Am Bl\u00e1r Dubh"
    ],
    "name:ita_x_preferred":[
        "Muir of Ord"
    ],
    "name:nld_x_preferred":[
        "Muir of Ord"
    ],
    "name:nno_x_preferred":[
        "Muir of Ord"
    ],
    "name:nor_x_preferred":[
        "Muir of Ord"
    ],
    "name:sco_x_preferred":[
        "Muir o Ord"
    ],
    "name:spa_x_preferred":[
        "Muir of Ord"
    ],
    "name:swe_x_preferred":[
        "Muir of Ord"
    ],
    "wof:name":"Muir of Ord",
    "wof:placetype":"locality",
    "wof:population":2620
},
  "geometry": {"coordinates":[-4.45939,57.51976],"type":"Point"}
}