{
  "type": "Feature",
  "properties": {
    "gn:admin1_code":"NIR",
    "gn:admin2_code":"N09000007",
    "gn:asciiname":"Ravernet",
    "gn:cc2":"GB",
    "gn:country_code":"GB",
    "gn:dem":97,
    "gn:feature_class":"P",
    "gn:feature_code":"PPL",
    "gn:name":"Ravernet",
    "gn:population":0,
    "gn:timezone":"Europe/London",
    "iso:country":"GB",
    "name:eus_x_preferred":[
        "Ravernet"
    ],
    "name:gle_x_preferred":[
        "R\u00e1th Bhearnait"
    ],
    "name:msa_x_preferred":[
        "Ravernet"
    ],
    "name:pli_x_preferred":[
        "\u0930\u0935\u0947\u0930\u094d\u0928\u0947\u091f"
    ],
    "name:spa_x_preferred":[
        "Ravernet"
    ],
    "name:und_x_variant":[
        "Ravennet"
    ],
    "wof:name":"Ravernet",
    "wof:placetype":"locality"
},
  "geometry": {"coordinates":[-6.05,54.46666999999999],"type":"Point"}
}