{
  "type": "Feature",
  "properties": {
    "iso:country": "GB",
    "name:ben_x_preferred": [
      "রাস্ট্রিক"
    ],
    "name:deu_x_preferred": [
      "Rastrick"
    ],
    "name:eng_x_preferred": [
      "Rastrick"
    ],
    "name:fra_x_preferred": [
      "Rastrick"
    ],
    "name:guj_x_preferred": [
      "રૅસ્ટ્રિક"
    ],
    "name:jpn_x_preferred": [
      "ラストリック"
    ],
    "name:kan_x_preferred": [
      "ರಾಸ್ಟ್ರಿಕ್"
    ],
    "name:kor_x_preferred": [
      "래스트릭"
    ],
    "name:lit_x_preferred": [
      "Rastrikas"
    ],
    "name:nld_x_preferred": [
      "Rastrick"
    ],
    "name:pol_x_preferred": [
      "Rastrick"
    ],
    "name:por_x_preferred": [
      "Rastrick"
    ],
    "name:rus_x_preferred": [
      "Растрик"
    ],
    "name:spa_x_preferred": [
      "Rastrick"
    ],
    "name:tam_x_preferred": [
      "ராஸ்ட்ரிக்"
    ],
    "name:tel_x_preferred": [
      "రాస్త్రిక్ట్"
    ],
    "name:urd_x_preferred": [
      "راستریک"
    ],
    "qs_pg:aaroncc": "GB",
    "qs_pg:name": "Rastrick",
    "qs_pg:name_adm0": "United Kingdom",
    "qs_pg:name_adm1": "England",
    "qs_pg:photos": 145,
    "qs_pg:photos_1k": 29,
    "qs_pg:photos_9k": 1,
    "qs_pg:photos_9r": 3,
    "qs_pg:photos_all": 145,
    "qs_pg:photos_sr": 3,
    "qs_pg:pop_sr": 0,
    "qs_pg:qs_pg_placetype": "locality",
    "qs_pg:qs_pg_placetype_gp": "Town",
    "qs_pg:woe_adm0": 23424975,
    "woe:adm0_id": 23424975,
    "woe:name_adm0": "United Kingdom",
    "woe:name_adm1": "England",
    "woe:placetype": "Town",
    "wof:name": "Rastrick",
    "wof:placetype": "neighbourhood"
  },
  "geometry": {"coordinates":[-1.79856,53.693911],"type":"Point"}
}
