{
  "type": "Feature",
  "properties": {
    "iso:country":"GB",
    "name:ang_x_preferred":[
        "R\u00e6stw\u012b\u010b"
    ],
    "name:ben_x_preferred":[
        "\u09b0\u09be\u09b8\u09cd\u099f\u09cd\u09b0\u09bf\u0995"
    ],
    "name:deu_x_preferred":[
        "Rastrick"
    ],
    "name:eng_x_preferred":[
        "Rastrick"
    ],
    "name:fra_x_preferred":[
        "Rastrick"
    ],
    "name:gle_x_preferred":[
        "Rastrick"
    ],
    "name:guj_x_preferred":[
        "\u0ab0\u0ac5\u0ab8\u0acd\u0a9f\u0acd\u0ab0\u0abf\u0a95"
    ],
    "name:jpn_x_preferred":[
        "\u30e9\u30b9\u30c8\u30ea\u30c3\u30af"
    ],
    "name:kan_x_preferred":[
        "\u0cb0\u0cbe\u0cb8\u0ccd\u0c9f\u0ccd\u0cb0\u0cbf\u0c95\u0ccd"
    ],
    "name:kor_x_preferred":[
        "\ub798\uc2a4\ud2b8\ub9ad"
    ],
    "name:lit_x_preferred":[
        "Rastrikas"
    ],
    "name:nld_x_preferred":[
        "Rastrick"
    ],
    "name:pol_x_preferred":[
        "Rastrick"
    ],
    "name:por_x_preferred":[
        "Rastrick"
    ],
    "name:rus_x_preferred":[
        "\u0420\u0430\u0441\u0442\u0440\u0438\u043a"
    ],
    "name:spa_x_preferred":[
        "Rastrick"
    ],
    "name:tam_x_preferred":[
        "\u0bb0\u0bbe\u0bb8\u0bcd\u0b9f\u0bcd\u0bb0\u0bbf\u0b95\u0bcd"
    ],
    "name:tel_x_preferred":[
        "\u0c30\u0c3e\u0c38\u0c4d\u0c24\u0c4d\u0c30\u0c3f\u0c15\u0c4d\u0c1f\u0c4d"
    ],
    "name:urd_x_preferred":[
        "\u0631\u0627\u0633\u062a\u0631\u06cc\u06a9"
    ],
    "qs_pg:aaroncc":"GB",
    "qs_pg:name":"Rastrick",
    "qs_pg:name_adm0":"United Kingdom",
    "qs_pg:name_adm1":"England",
    "qs_pg:photos":145,
    "qs_pg:photos_1k":29,
    "qs_pg:photos_9k":1,
    "qs_pg:photos_9r":3,
    "qs_pg:photos_all":145,
    "qs_pg:photos_sr":3,
    "qs_pg:pop_sr":0,
    "qs_pg:qs_pg_placetype":"locality",
    "qs_pg:qs_pg_placetype_gp":"Town",
    "qs_pg:woe_adm0":23424975,
    "woe:adm0_id":23424975,
    "woe:name_adm0":"United Kingdom",
    "woe:name_adm1":"England",
    "woe:placetype":"Town",
    "wof:name":"Rastrick",
    "wof:placetype":"neighbourhood"
},
  "geometry": {"coordinates":[-1.79856,53.693911],"type":"Point"}
}