{
  "type": "Feature",
  "properties": {
    "iso:country": "GB",
    "wof:name": "Wolverhampton City Centre",
    "wof:placetype": "neighbourhood"
  },
  "geometry": {"coordinates":[-2.12946018001667,52.58740087950371],"type":"Point"}
}
