{
  "type": "Feature",
  "properties": {
    "gn:admin1_code": "ENG",
    "gn:admin2_code": "D4",
    "gn:admin3_code": "18UG",
    "gn:admin4_code": "18UG048",
    "gn:asciiname": "Smithaleigh",
    "gn:country_code": "GB",
    "gn:dem": 63,
    "gn:feature_class": "P",
    "gn:feature_code": "PPL",
    "gn:name": "Smithaleigh",
    "gn:population": 0,
    "gn:timezone": "Europe/London",
    "iso:country": "GB",
    "wof:name": "Smithaleigh",
    "wof:placetype": "neighbourhood"
  },
  "geometry": {"coordinates":[-3.98662,50.38108],"type":"Point"}
}
