{
  "type": "Feature",
  "properties": {
    "gn:country":"GB",
    "gn:fcode":"PPL",
    "gn:population":1989,
    "iso:country":"GB",
    "name:ceb_x_preferred":[
        "Cliffe"
    ],
    "name:cym_x_preferred":[
        "Cliffe"
    ],
    "name:eng_x_preferred":[
        "Cliffe"
    ],
    "name:fra_x_preferred":[
        "Cliffe"
    ],
    "name:nld_x_preferred":[
        "Cliffe"
    ],
    "name:pol_x_preferred":[
        "Cliffe"
    ],
    "name:pol_x_variant":[
        "Cliffe"
    ],
    "name:spa_x_preferred":[
        "Cliffe"
    ],
    "name:swe_x_preferred":[
        "Cliffe"
    ],
    "name:swe_x_variant":[
        "Cliffe"
    ],
    "name:und_x_variant":[
        "Cliffe-at-Hoo"
    ],
    "qs_pg:aaroncc":"GB",
    "qs_pg:gn_country":"GB",
    "qs_pg:gn_fcode":"PPL",
    "qs_pg:gn_pop":1989,
    "qs_pg:name":"Cliffe",
    "qs_pg:name_adm0":"United Kingdom",
    "qs_pg:name_adm1":"England",
    "qs_pg:photos":1230,
    "qs_pg:photos_1k":249,
    "qs_pg:photos_9k":5,
    "qs_pg:photos_9r":7,
    "qs_pg:photos_all":1230,
    "qs_pg:photos_sr":11,
    "qs_pg:pop_sr":3,
    "qs_pg:qs_pg_placetype":"locality",
    "qs_pg:qs_pg_placetype_gp":"Town",
    "qs_pg:woe_adm0":23424975,
    "woe:adm0_id":23424975,
    "woe:name_adm0":"United Kingdom",
    "woe:name_adm1":"England",
    "woe:placetype":"Town",
    "wof:name":"Cliffe",
    "wof:placetype":"neighbourhood",
    "wof:population":2403
},
  "geometry": {"coordinates":[0.49833,51.46224],"type":"Point"}
}