{
  "type": "Feature",
  "properties": {
    "gn:admin1_code":"SCT",
    "gn:admin2_code":"T7",
    "gn:asciiname":"Duntrune",
    "gn:country_code":"GB",
    "gn:dem":123,
    "gn:feature_class":"P",
    "gn:feature_code":"PPL",
    "gn:name":"Duntrune",
    "gn:population":0,
    "gn:timezone":"Europe/London",
    "iso:country":"GB",
    "wof:name":"Duntrune",
    "wof:placetype":"locality"
},
  "geometry": {"coordinates":[-2.9073,56.5203],"type":"Point"}
}