{
  "type": "Feature",
  "properties": {
    "gn:country": "GB",
    "gn:fcode": "PPL",
    "gn:population": 0,
    "iso:country": "GB",
    "name:ben_x_preferred": [
      "টুইড্ডেল"
    ],
    "name:deu_x_preferred": [
      "Tweedsmuir"
    ],
    "name:eng_x_preferred": [
      "Tweedsmuir"
    ],
    "name:eus_x_preferred": [
      "Tweedsmuir"
    ],
    "name:fra_x_preferred": [
      "Tweedsmuir"
    ],
    "name:gle_x_preferred": [
      "Sliabh Thuaidh"
    ],
    "name:guj_x_preferred": [
      "ટ્વિડ્સમ્યુઈર"
    ],
    "name:jpn_x_preferred": [
      "ツイーズミュア"
    ],
    "name:kan_x_preferred": [
      "ಟ್ವೀಡ್ಸ್ಮುಯಿರ್"
    ],
    "name:kor_x_preferred": [
      "트위드데일"
    ],
    "name:lit_x_preferred": [
      "Tvedeilas"
    ],
    "name:nld_x_preferred": [
      "Tweedsmuir"
    ],
    "name:por_x_preferred": [
      "Tweedsmuir"
    ],
    "name:rus_x_preferred": [
      "Твидсмур"
    ],
    "name:spa_x_preferred": [
      "Tweedsmuir"
    ],
    "name:tam_x_preferred": [
      "டீவீடிஸ்முயிற்"
    ],
    "name:tel_x_preferred": [
      "ట్వీడ్స్మియుర్"
    ],
    "name:urd_x_preferred": [
      "توییدسمویر"
    ],
    "qs_pg:aaroncc": "GB",
    "qs_pg:gn_country": "GB",
    "qs_pg:gn_fcode": "PPL",
    "qs_pg:gn_pop": 0,
    "qs_pg:name": "Tweedsmuir",
    "qs_pg:name_adm0": "United Kingdom",
    "qs_pg:name_adm1": "Scotland",
    "qs_pg:photos": 112,
    "qs_pg:photos_1k": 23,
    "qs_pg:photos_9k": 1,
    "qs_pg:photos_9r": 3,
    "qs_pg:photos_all": 112,
    "qs_pg:photos_sr": 3,
    "qs_pg:pop_sr": 0,
    "qs_pg:qs_pg_placetype": "locality",
    "qs_pg:qs_pg_placetype_gp": "Town",
    "qs_pg:woe_adm0": 23424975,
    "woe:adm0_id": 23424975,
    "woe:name_adm0": "United Kingdom",
    "woe:name_adm1": "Scotland",
    "woe:placetype": "Town",
    "wof:name": "Tweedsmuir",
    "wof:placetype": "locality"
  },
  "geometry": {"coordinates":[-3.43296,55.50534],"type":"Point"}
}
