{
  "type": "Feature",
  "properties": {
    "gn:country":"GB",
    "gn:fcode":"PPL",
    "gn:population":0,
    "iso:country":"GB",
    "name:ben_x_preferred":[
        "\u099f\u09c1\u0987\u09a1\u09cd\u09a1\u09c7\u09b2"
    ],
    "name:deu_x_preferred":[
        "Tweedsmuir"
    ],
    "name:eng_x_preferred":[
        "Tweedsmuir"
    ],
    "name:eus_x_preferred":[
        "Tweedsmuir"
    ],
    "name:fra_x_preferred":[
        "Tweedsmuir"
    ],
    "name:gle_x_preferred":[
        "Sliabh Thuaidh"
    ],
    "name:guj_x_preferred":[
        "\u0a9f\u0acd\u0ab5\u0abf\u0aa1\u0acd\u0ab8\u0aae\u0acd\u0aaf\u0ac1\u0a88\u0ab0"
    ],
    "name:jpn_x_preferred":[
        "\u30c4\u30a4\u30fc\u30ba\u30df\u30e5\u30a2"
    ],
    "name:kan_x_preferred":[
        "\u0c9f\u0ccd\u0cb5\u0cc0\u0ca1\u0ccd\u0cb8\u0ccd\u0cae\u0cc1\u0caf\u0cbf\u0cb0\u0ccd"
    ],
    "name:kor_x_preferred":[
        "\ud2b8\uc704\ub4dc\ub370\uc77c"
    ],
    "name:lit_x_preferred":[
        "Tvedeilas"
    ],
    "name:nld_x_preferred":[
        "Tweedsmuir"
    ],
    "name:por_x_preferred":[
        "Tweedsmuir"
    ],
    "name:rus_x_preferred":[
        "\u0422\u0432\u0438\u0434\u0441\u043c\u0443\u0440"
    ],
    "name:spa_x_preferred":[
        "Tweedsmuir"
    ],
    "name:tam_x_preferred":[
        "\u0b9f\u0bc0\u0bb5\u0bc0\u0b9f\u0bbf\u0bb8\u0bcd\u0bae\u0bc1\u0baf\u0bbf\u0bb1\u0bcd"
    ],
    "name:tel_x_preferred":[
        "\u0c1f\u0c4d\u0c35\u0c40\u0c21\u0c4d\u0c38\u0c4d\u0c2e\u0c3f\u0c2f\u0c41\u0c30\u0c4d"
    ],
    "name:urd_x_preferred":[
        "\u062a\u0648\u06cc\u06cc\u062f\u0633\u0645\u0648\u06cc\u0631"
    ],
    "qs_pg:aaroncc":"GB",
    "qs_pg:gn_country":"GB",
    "qs_pg:gn_fcode":"PPL",
    "qs_pg:gn_pop":0,
    "qs_pg:name":"Tweedsmuir",
    "qs_pg:name_adm0":"United Kingdom",
    "qs_pg:name_adm1":"Scotland",
    "qs_pg:photos":112,
    "qs_pg:photos_1k":23,
    "qs_pg:photos_9k":1,
    "qs_pg:photos_9r":3,
    "qs_pg:photos_all":112,
    "qs_pg:photos_sr":3,
    "qs_pg:pop_sr":0,
    "qs_pg:qs_pg_placetype":"locality",
    "qs_pg:qs_pg_placetype_gp":"Town",
    "qs_pg:woe_adm0":23424975,
    "woe:adm0_id":23424975,
    "woe:name_adm0":"United Kingdom",
    "woe:name_adm1":"Scotland",
    "woe:placetype":"Town",
    "wof:name":"Tweedsmuir",
    "wof:placetype":"locality"
},
  "geometry": {"coordinates":[-3.43296,55.50534],"type":"Point"}
}