{
  "type": "Feature",
  "properties": {
    "iso:country": "GB",
    "wof:name": "Parson Cross",
    "wof:placetype": "neighbourhood"
  },
  "geometry": {"coordinates":[-1.4816370249745,53.4274535793263],"type":"Point"}
}
