{
  "type": "Feature",
  "properties": {
    "gn:population": 1365,
    "iso:country": "GB",
    "name:bul_x_preferred": [
      "Балинамалард"
    ],
    "name:ceb_x_preferred": [
      "Ballinamallard"
    ],
    "name:ell_x_preferred": [
      "Μπεϊλινάμαλαρντ"
    ],
    "name:eng_x_preferred": [
      "Ballinamallard"
    ],
    "name:eus_x_preferred": [
      "Ballinamallard"
    ],
    "name:fas_x_preferred": [
      "بالینامالارد"
    ],
    "name:fra_x_preferred": [
      "Ballinamallard"
    ],
    "name:gle_x_preferred": [
      "Béal Átha na Mallacht"
    ],
    "name:ita_x_preferred": [
      "Ballinamallard"
    ],
    "name:jpn_x_preferred": [
      "バリナマラード"
    ],
    "name:lit_x_preferred": [
      "Balinamalardas"
    ],
    "name:msa_x_preferred": [
      "Ballinamallard"
    ],
    "name:nld_x_preferred": [
      "Ballinamallard"
    ],
    "name:pli_x_preferred": [
      "बल्लिनामाल्लार्ड"
    ],
    "name:spa_x_preferred": [
      "Ballinamallard"
    ],
    "name:swe_x_preferred": [
      "Ballinamallard"
    ],
    "name:und_x_variant": [
      "Ballanamallard"
    ],
    "qs:a0": "United Kingdom",
    "qs:a1": "*Fermanagh",
    "qs:a1_lc": "N_A",
    "qs:a1r": "0Northern Ireland",
    "qs:a1r_lc": "N_A",
    "qs:adm0": "United Kingdom",
    "qs:la_lc": "*",
    "qs:level": "locality",
    "qs:loc": "Ballinamallard",
    "qs:loc_alt": "Ballinamallard",
    "qs:pop": 0,
    "qs:type": "buffered point",
    "wd:wordcount": 1225,
    "wof:name": "Ballinamallard",
    "wof:placetype": "locality",
    "wof:population": 1365
  },
  "geometry": {"coordinates":[-7.592059,54.421753],"type":"Point"}
}
