{
  "type": "Feature",
  "properties": {
    "gn:admin1_code":"SCT",
    "gn:admin2_code":"V3",
    "gn:asciiname":"Auchness",
    "gn:cc2":"GB",
    "gn:country_code":"GB",
    "gn:dem":28,
    "gn:feature_class":"P",
    "gn:feature_code":"PPL",
    "gn:name":"Auchness",
    "gn:population":0,
    "gn:timezone":"Europe/London",
    "iso:country":"GB",
    "name:und_x_variant":[
        "Achness",
        "Auchness"
    ],
    "wof:name":"Auchness",
    "wof:placetype":"locality"
},
  "geometry": {"coordinates":[-4.58333,57.98333],"type":"Point"}
}