{
  "type": "Feature",
  "properties": {
    "gn:country":"GB",
    "gn:fcode":"PPL",
    "gn:population":0,
    "iso:country":"GB",
    "name:cat_x_preferred":[
        "Alvie"
    ],
    "name:eng_x_preferred":[
        "Alvie"
    ],
    "name:eus_x_preferred":[
        "Alvie"
    ],
    "name:gle_x_preferred":[
        "Albhaidh"
    ],
    "name:nld_x_preferred":[
        "Alvie"
    ],
    "qs_pg:aaroncc":"GB",
    "qs_pg:gn_country":"GB",
    "qs_pg:gn_fcode":"PPL",
    "qs_pg:gn_pop":0,
    "qs_pg:name":"Alvie",
    "qs_pg:name_adm0":"United Kingdom",
    "qs_pg:name_adm1":"Scotland",
    "qs_pg:photos":827,
    "qs_pg:photos_1k":168,
    "qs_pg:photos_9k":4,
    "qs_pg:photos_9r":6,
    "qs_pg:photos_all":827,
    "qs_pg:photos_sr":9,
    "qs_pg:pop_sr":0,
    "qs_pg:qs_pg_placetype":"locality",
    "qs_pg:qs_pg_placetype_gp":"Town",
    "qs_pg:woe_adm0":23424975,
    "woe:adm0_id":23424975,
    "woe:name_adm0":"United Kingdom",
    "woe:name_adm1":"Scotland",
    "woe:placetype":"Town",
    "wof:name":"Alvie",
    "wof:placetype":"locality"
},
  "geometry": {"coordinates":[-3.91608,57.13879],"type":"Point"}
}