{
  "type": "Feature",
  "properties": {
    "iso:country":"GB",
    "name:ara_x_preferred":[
        "\u0636\u0641\u0629"
    ],
    "name:arg_x_preferred":[
        "Ribera"
    ],
    "name:aym_x_preferred":[
        "Qawaya"
    ],
    "name:aze_x_preferred":[
        "Sahil"
    ],
    "name:ben_x_preferred":[
        "\u09a4\u09c0\u09b0"
    ],
    "name:cat_x_preferred":[
        "Ribera"
    ],
    "name:deu_x_preferred":[
        "Ufer"
    ],
    "name:epo_x_preferred":[
        "Bordo"
    ],
    "name:est_x_preferred":[
        "Rand"
    ],
    "name:fas_x_preferred":[
        "\u06a9\u0631\u0627\u0646\u0647"
    ],
    "name:fra_x_preferred":[
        "Rivage"
    ],
    "name:gle_x_preferred":[
        "Cladach"
    ],
    "name:heb_x_preferred":[
        "\u05e7\u05d5 \u05d7\u05d5\u05e3"
    ],
    "name:ido_x_preferred":[
        "Rivo"
    ],
    "name:ind_x_preferred":[
        "Bibir pantai"
    ],
    "name:kaz_x_preferred":[
        "\u0422\u0435\u04a3\u0456\u0437 \u0436\u0430\u0493\u0430\u043b\u0430\u0443\u044b"
    ],
    "name:lav_x_preferred":[
        "Krasts"
    ],
    "name:lit_x_preferred":[
        "Krantas"
    ],
    "name:nld_x_preferred":[
        "Kustlijn"
    ],
    "name:nno_x_preferred":[
        "Strandlinje"
    ],
    "name:nor_x_preferred":[
        "Strandlinje"
    ],
    "name:pol_x_preferred":[
        "Linia brzegowa"
    ],
    "name:ron_x_preferred":[
        "Mal"
    ],
    "name:spa_x_preferred":[
        "Ribera"
    ],
    "name:ukr_x_preferred":[
        "\u0411\u0435\u0440\u0435\u0433"
    ],
    "qs_pg:aaroncc":"GB",
    "qs_pg:name":"Shore",
    "qs_pg:name_adm0":"United Kingdom",
    "qs_pg:name_adm1":"England",
    "qs_pg:photos":156,
    "qs_pg:photos_1k":32,
    "qs_pg:photos_9k":1,
    "qs_pg:photos_9r":4,
    "qs_pg:photos_all":156,
    "qs_pg:photos_sr":4,
    "qs_pg:pop_sr":0,
    "qs_pg:qs_pg_placetype":"locality",
    "qs_pg:qs_pg_placetype_gp":"Town",
    "qs_pg:woe_adm0":23424975,
    "woe:adm0_id":23424975,
    "woe:name_adm0":"United Kingdom",
    "woe:name_adm1":"England",
    "woe:placetype":"Town",
    "wof:name":"Shore",
    "wof:placetype":"neighbourhood"
},
  "geometry": {"coordinates":[-2.0999245,53.641305],"type":"Point"}
}