{
  "type": "Feature",
  "properties": {
    "gn:gn_country":"GB",
    "gn:gn_fcode":"PPL",
    "gn:gn_pop":0,
    "iso:country":"GB",
    "name:cym_x_preferred":[
        "Exbury"
    ],
    "name:eng_x_preferred":[
        "Exbury"
    ],
    "name:fra_x_preferred":[
        "Exbury"
    ],
    "name:nld_x_preferred":[
        "Exbury"
    ],
    "name:pol_x_preferred":[
        "Exbury"
    ],
    "name:rus_x_preferred":[
        "\u042d\u043a\u0441\u0431\u0435\u0440\u0438"
    ],
    "qs_pg:aaroncc":"GB",
    "qs_pg:gn_country":"GB",
    "qs_pg:gn_fcode":"PPL",
    "qs_pg:gn_pop":0,
    "qs_pg:name":"Exbury",
    "qs_pg:name_adm0":"United Kingdom",
    "qs_pg:name_adm1":"England",
    "qs_pg:photos":2809,
    "qs_pg:photos_1k":569,
    "qs_pg:photos_9k":12,
    "qs_pg:photos_9r":11,
    "qs_pg:photos_all":2809,
    "qs_pg:photos_sr":19,
    "qs_pg:pop_sr":0,
    "qs_pg:qs_pg_placetype":"locality",
    "qs_pg:qs_pg_placetype_gp":"Town",
    "qs_pg:woe_adm0":23424975,
    "woe:adm0_id":23424975,
    "woe:name_adm0":"United Kingdom",
    "woe:name_adm1":"England",
    "woe:placetype":"Town",
    "wof:name":"Exbury",
    "wof:placetype":"neighbourhood"
},
  "geometry": {"coordinates":[-1.39668,50.80097],"type":"Point"}
}