{
  "type": "Feature",
  "properties": {
    "gn:gn_country":"GB",
    "gn:gn_fcode":"PPL",
    "gn:gn_pop":0,
    "gn:population":836,
    "iso:country":"GB",
    "name:cze_x_preferred":[
        "Waltham on the Wolds"
    ],
    "name:dut_x_preferred":[
        "Waltham on the Wolds"
    ],
    "name:eng_x_preferred":[
        "Waltham on the Wolds"
    ],
    "name:fre_x_preferred":[
        "Waltham on the Wolds"
    ],
    "name:ita_x_preferred":[
        "Waltham on the Wolds"
    ],
    "name:pol_x_preferred":[
        "Waltham on the Wolds"
    ],
    "name:swe_x_preferred":[
        "Waltham on the Wolds"
    ],
    "name:unk_x_variant":[
        "Waltham"
    ],
    "name:wel_x_preferred":[
        "Waltham on the Wolds"
    ],
    "qs_pg:aaroncc":"GB",
    "qs_pg:gn_country":"GB",
    "qs_pg:gn_fcode":"PPL",
    "qs_pg:gn_pop":0,
    "qs_pg:name":"Waltham on the Wolds",
    "qs_pg:name_adm0":"United Kingdom",
    "qs_pg:name_adm1":"England",
    "qs_pg:photos":29,
    "qs_pg:photos_1k":6,
    "qs_pg:photos_9k":1,
    "qs_pg:photos_9r":2,
    "qs_pg:photos_all":29,
    "qs_pg:photos_sr":2,
    "qs_pg:pop_sr":0,
    "qs_pg:qs_pg_placetype":"locality",
    "qs_pg:qs_pg_placetype_gp":"Town",
    "qs_pg:woe_adm0":23424975,
    "woe:adm0_id":23424975,
    "woe:name_adm0":"United Kingdom",
    "woe:name_adm1":"England",
    "woe:placetype":"Town",
    "wof:name":"Waltham on the Wolds",
    "wof:placetype":"neighbourhood",
    "wof:population":836
},
  "geometry": {"coordinates":[-0.80835,52.81698],"type":"Point"}
}