{
  "type": "Feature",
  "properties": {
    "gn:country": "GB",
    "gn:fcode": "PPL",
    "gn:population": 0,
    "iso:country": "GB",
    "name:bul_x_preferred": [
      "Нюбридж"
    ],
    "name:ceb_x_preferred": [
      "Newbridge"
    ],
    "name:ces_x_preferred": [
      "Newbridge"
    ],
    "name:cym_x_preferred": [
      "Newbridge"
    ],
    "name:deu_x_preferred": [
      "Newbridge"
    ],
    "name:fra_x_preferred": [
      "Newbridge"
    ],
    "name:kor_x_preferred": [
      "뉴브리지"
    ],
    "name:nld_x_preferred": [
      "Newbridge"
    ],
    "name:pol_x_preferred": [
      "Newbridge"
    ],
    "name:slk_x_preferred": [
      "Newbridge"
    ],
    "name:swe_x_preferred": [
      "Newbridge"
    ],
    "qs_pg:aaroncc": "GB",
    "qs_pg:gn_country": "GB",
    "qs_pg:gn_fcode": "PPL",
    "qs_pg:gn_pop": 0,
    "qs_pg:name": "Newbridge",
    "qs_pg:name_adm0": "United Kingdom",
    "qs_pg:name_adm1": "Wales",
    "qs_pg:photos": 208,
    "qs_pg:photos_1k": 42,
    "qs_pg:photos_9k": 1,
    "qs_pg:photos_9r": 4,
    "qs_pg:photos_all": 208,
    "qs_pg:photos_sr": 4,
    "qs_pg:pop_sr": 0,
    "qs_pg:qs_pg_placetype": "locality",
    "qs_pg:qs_pg_placetype_gp": "Town",
    "qs_pg:woe_adm0": 23424975,
    "woe:adm0_id": 23424975,
    "woe:name_adm0": "United Kingdom",
    "woe:name_adm1": "Wales",
    "woe:placetype": "Town",
    "wof:name": "Newbridge",
    "wof:placetype": "neighbourhood"
  },
  "geometry": {"coordinates":[-3.26667,52.68333],"type":"Point"}
}
