{
  "type": "Feature",
  "properties": {
    "gn:country": "GB",
    "gn:fcode": "PPL",
    "gn:population": 0,
    "iso:country": "GB",
    "name:aze_x_preferred": [
      "Qlendeyl"
    ],
    "name:bar_x_preferred": [
      "Glendale"
    ],
    "name:bel_x_preferred": [
      "Глендэйл"
    ],
    "name:bul_x_preferred": [
      "Глендейл"
    ],
    "name:cat_x_preferred": [
      "Glendale"
    ],
    "name:ceb_x_preferred": [
      "Glendale"
    ],
    "name:ces_x_preferred": [
      "Glendale"
    ],
    "name:dan_x_preferred": [
      "Glendale"
    ],
    "name:deu_x_preferred": [
      "Glendale"
    ],
    "name:est_x_preferred": [
      "Glendale"
    ],
    "name:fas_x_preferred": [
      "گلندیل"
    ],
    "name:fin_x_preferred": [
      "Glendale"
    ],
    "name:fra_x_preferred": [
      "Glendale"
    ],
    "name:glg_x_preferred": [
      "Glendale"
    ],
    "name:heb_x_preferred": [
      "גלנדייל"
    ],
    "name:hrv_x_preferred": [
      "Glendale"
    ],
    "name:hun_x_preferred": [
      "Glendale"
    ],
    "name:ido_x_preferred": [
      "Glendale"
    ],
    "name:ita_x_preferred": [
      "Glendale"
    ],
    "name:jpn_x_preferred": [
      "グレンデール"
    ],
    "name:kor_x_preferred": [
      "글렌데일"
    ],
    "name:mlg_x_preferred": [
      "Glendale"
    ],
    "name:nld_x_preferred": [
      "Glendale"
    ],
    "name:nor_x_preferred": [
      "Glendale"
    ],
    "name:pol_x_preferred": [
      "Glendale"
    ],
    "name:por_x_preferred": [
      "Glendale"
    ],
    "name:rus_x_preferred": [
      "Глендейл"
    ],
    "name:slk_x_preferred": [
      "Glendale"
    ],
    "name:spa_x_preferred": [
      "Glendale"
    ],
    "name:srp_x_preferred": [
      "Глендејл"
    ],
    "name:swa_x_preferred": [
      "Glendale"
    ],
    "name:swe_x_preferred": [
      "Glendale"
    ],
    "name:szl_x_preferred": [
      "Glendale"
    ],
    "name:tha_x_preferred": [
      "เกล็นเดล"
    ],
    "name:tur_x_preferred": [
      "Glendale"
    ],
    "name:ukr_x_preferred": [
      "Глендейл"
    ],
    "name:urd_x_preferred": [
      "گلینڈیل"
    ],
    "name:vol_x_preferred": [
      "Glendale"
    ],
    "qs_pg:aaroncc": "GB",
    "qs_pg:gn_country": "GB",
    "qs_pg:gn_fcode": "PPL",
    "qs_pg:gn_pop": 0,
    "qs_pg:name": "Glendale",
    "qs_pg:name_adm0": "United Kingdom",
    "qs_pg:name_adm1": "Scotland",
    "qs_pg:photos": 655,
    "qs_pg:photos_1k": 133,
    "qs_pg:photos_9k": 3,
    "qs_pg:photos_9r": 5,
    "qs_pg:photos_all": 655,
    "qs_pg:photos_sr": 8,
    "qs_pg:pop_sr": 0,
    "qs_pg:qs_pg_placetype": "locality",
    "qs_pg:qs_pg_placetype_gp": "Town",
    "qs_pg:woe_adm0": 23424975,
    "woe:adm0_id": 23424975,
    "woe:name_adm0": "United Kingdom",
    "woe:name_adm1": "Scotland",
    "woe:placetype": "Town",
    "wof:name": "Glendale",
    "wof:placetype": "locality"
  },
  "geometry": {"coordinates":[-7.03743,57.77998],"type":"Point"}
}
