{
  "type": "Feature",
  "properties": {
    "gn:country":"GB",
    "gn:fcode":"PPL",
    "gn:population":0,
    "iso:country":"GB",
    "name:eng_x_preferred":[
        "Balchladich"
    ],
    "name:eus_x_preferred":[
        "Balchladich"
    ],
    "name:gla_x_preferred":[
        "Baile a' Chladaich"
    ],
    "name:gle_x_preferred":[
        "Baile a' Chladaich"
    ],
    "name:nld_x_preferred":[
        "Balchladich"
    ],
    "name:und_x_variant":[
        "Ballcladdich"
    ],
    "qs_pg:aaroncc":"GB",
    "qs_pg:gn_country":"GB",
    "qs_pg:gn_fcode":"PPL",
    "qs_pg:gn_pop":0,
    "qs_pg:name":"Balchladich",
    "qs_pg:name_adm0":"United Kingdom",
    "qs_pg:name_adm1":"Scotland",
    "qs_pg:photos":48,
    "qs_pg:photos_1k":10,
    "qs_pg:photos_9k":1,
    "qs_pg:photos_9r":2,
    "qs_pg:photos_all":48,
    "qs_pg:photos_sr":2,
    "qs_pg:pop_sr":0,
    "qs_pg:qs_pg_placetype":"locality",
    "qs_pg:qs_pg_placetype_gp":"Town",
    "qs_pg:woe_adm0":23424975,
    "woe:adm0_id":23424975,
    "woe:name_adm0":"United Kingdom",
    "woe:name_adm1":"Scotland",
    "woe:placetype":"Town",
    "wof:name":"Balchladich",
    "wof:placetype":"locality"
},
  "geometry": {"coordinates":[-5.35,58.21667],"type":"Point"}
}