{
  "type": "Feature",
  "properties": {
    "iso:country":"GB",
    "name:nld_x_preferred":[
        "Campbell Park"
    ],
    "name:nor_x_preferred":[
        "Campbell Park"
    ],
    "name:pol_x_preferred":[
        "Campbell Park"
    ],
    "wof:name":"Campbell Park",
    "wof:placetype":"neighbourhood"
},
  "geometry": {"coordinates":[-1.5074652333848,54.97101577915058],"type":"Point"}
}