{
  "type": "Feature",
  "properties": {
    "iso:country":"GB",
    "name:cym_x_preferred":[
        "South Wigston"
    ],
    "name:eng_x_preferred":[
        "South Wigston"
    ],
    "name:eng_x_variant":[
        "S Wigston"
    ],
    "name:fra_x_preferred":[
        "South Wigston"
    ],
    "name:nld_x_preferred":[
        "South Wigston"
    ],
    "name:pol_x_preferred":[
        "South Wigston"
    ],
    "name:unk_x_variant":[
        "South Wigston"
    ],
    "name:zho_x_preferred":[
        "\u5a01\u502b\u5e0c\u723e"
    ],
    "qs:gn_fcode":"PPL",
    "qs:gn_local":0,
    "qs:gn_namadm1":"ENG",
    "qs:gn_name":"South Wigston",
    "qs:local_max":715,
    "qs:local_sum":715,
    "qs:localhoods":1,
    "qs:name":"South Wigston",
    "qs:name_adm0":"United Kingdom",
    "qs:name_adm1":"England",
    "qs:name_adm2":"Leicestershire",
    "qs:name_lau":"Oadby and Wigston Borough",
    "qs:name_local":"Oadby and Wigston Borough",
    "qs:photo_max":149,
    "qs:photo_sum":715,
    "qs:placetype":"Suburb",
    "qs:quad_count":74,
    "qs:woe_adm0":23424975,
    "qs:woe_adm1":24554868,
    "qs:woe_adm2":12602144,
    "qs:woe_lau":12696015,
    "qs:woe_local":12696015,
    "qs:woe_ver":"7.10.0",
    "wd:wordcount":1774,
    "wof:lang":[
        "eng"
    ],
    "wof:name":"South Wigston",
    "wof:placetype":"neighbourhood"
},
  "geometry": {"coordinates":[-1.133321,52.577825],"type":"Point"}
}