{
  "type": "Feature",
  "properties": {
    "iso:country":"GB",
    "name:eng_x_preferred":[
        "Knowle Park"
    ],
    "wof:name":"Knowle Park",
    "wof:placetype":"neighbourhood"
},
  "geometry": {"coordinates":[-2.57057840094181,51.43019254863213],"type":"Point"}
}