{
  "type": "Feature",
  "properties": {
    "iso:country": "GB",
    "name:eus_x_preferred": [
      "Clachan"
    ],
    "name:gle_x_preferred": [
      "Clachan"
    ],
    "name:glg_x_preferred": [
      "Clachan"
    ],
    "name:pol_x_preferred": [
      "Clachan"
    ],
    "name:sco_x_preferred": [
      "Clachan"
    ],
    "qs_pg:aaroncc": "GB",
    "qs_pg:name": "Clachan",
    "qs_pg:name_adm0": "United Kingdom",
    "qs_pg:name_adm1": "Scotland",
    "qs_pg:photos": 128,
    "qs_pg:photos_1k": 26,
    "qs_pg:photos_9k": 1,
    "qs_pg:photos_9r": 3,
    "qs_pg:photos_all": 128,
    "qs_pg:photos_sr": 3,
    "qs_pg:pop_sr": 0,
    "qs_pg:qs_pg_placetype": "locality",
    "qs_pg:qs_pg_placetype_gp": "Town",
    "qs_pg:woe_adm0": 23424975,
    "woe:adm0_id": 23424975,
    "woe:name_adm0": "United Kingdom",
    "woe:name_adm1": "Scotland",
    "woe:placetype": "Town",
    "wof:name": "Clachan",
    "wof:placetype": "locality"
  },
  "geometry": {"coordinates":[-6.177495,57.613417],"type":"Point"}
}
