{
  "type": "Feature",
  "properties": {
    "iso:country":"GB",
    "name:cym_x_preferred":[
        "Wrightington Bar"
    ],
    "name:eng_x_preferred":[
        "Wrightington Bar"
    ],
    "name:fra_x_preferred":[
        "Wrightington Bar"
    ],
    "name:nld_x_preferred":[
        "Wrightington Bar"
    ],
    "name:pol_x_preferred":[
        "Wrightington Bar"
    ],
    "qs_pg:aaroncc":"GB",
    "qs_pg:name":"Wrightington Bar",
    "qs_pg:name_adm0":"United Kingdom",
    "qs_pg:name_adm1":"England",
    "qs_pg:photos":460,
    "qs_pg:photos_1k":93,
    "qs_pg:photos_9k":2,
    "qs_pg:photos_9r":5,
    "qs_pg:photos_all":460,
    "qs_pg:photos_sr":7,
    "qs_pg:pop_sr":0,
    "qs_pg:qs_pg_placetype":"locality",
    "qs_pg:qs_pg_placetype_gp":"Town",
    "qs_pg:woe_adm0":23424975,
    "woe:adm0_id":23424975,
    "woe:name_adm0":"United Kingdom",
    "woe:name_adm1":"England",
    "woe:placetype":"Town",
    "wof:name":"Wrightington Bar",
    "wof:placetype":"neighbourhood"
},
  "geometry": {"coordinates":[-2.698527,53.633105],"type":"Point"}
}