{
  "type": "Feature",
  "properties": {
    "gn:admin1_code": "SCT",
    "gn:admin2_code": "V1",
    "gn:asciiname": "Cameron",
    "gn:country_code": "GB",
    "gn:dem": 162,
    "gn:feature_class": "P",
    "gn:feature_code": "PPL",
    "gn:name": "Cameron",
    "gn:population": 0,
    "gn:timezone": "Europe/London",
    "iso:country": "GB",
    "name:ara_x_preferred": [
      "كاميرون"
    ],
    "name:bel_x_preferred": [
      "Кэмеран"
    ],
    "name:cat_x_preferred": [
      "Cameron"
    ],
    "name:ceb_x_preferred": [
      "Cameron"
    ],
    "name:ces_x_preferred": [
      "Cameron"
    ],
    "name:dan_x_preferred": [
      "Cameron"
    ],
    "name:deu_x_preferred": [
      "Cameron"
    ],
    "name:ell_x_preferred": [
      "Κάμερον"
    ],
    "name:fra_x_preferred": [
      "Cameron"
    ],
    "name:heb_x_preferred": [
      "קמרון"
    ],
    "name:hun_x_preferred": [
      "Cameron"
    ],
    "name:ita_x_preferred": [
      "Cameron"
    ],
    "name:jpn_x_preferred": [
      "キャメロン"
    ],
    "name:kor_x_preferred": [
      "캐머런"
    ],
    "name:lav_x_preferred": [
      "Kemerons"
    ],
    "name:nld_x_preferred": [
      "Cameron"
    ],
    "name:pol_x_preferred": [
      "Cameron"
    ],
    "name:por_x_preferred": [
      "Cameron"
    ],
    "name:ron_x_preferred": [
      "Cameron"
    ],
    "name:rus_x_preferred": [
      "Камерон"
    ],
    "name:spa_x_preferred": [
      "Cameron"
    ],
    "name:srp_x_preferred": [
      "Камерон"
    ],
    "name:swe_x_preferred": [
      "Cameron"
    ],
    "name:tha_x_preferred": [
      "คาเมรอน"
    ],
    "name:ukr_x_preferred": [
      "Камерон"
    ],
    "name:urd_x_preferred": [
      "کیمرون"
    ],
    "name:vol_x_preferred": [
      "Cameron"
    ],
    "wof:name": "Cameron",
    "wof:placetype": "locality"
  },
  "geometry": {"coordinates":[-2.85176,56.29445],"type":"Point"}
}
