{
  "type": "Feature",
  "properties": {
    "gn:admin1_code":"SCT",
    "gn:admin2_code":"V1",
    "gn:asciiname":"Cameron",
    "gn:country_code":"GB",
    "gn:dem":162,
    "gn:feature_class":"P",
    "gn:feature_code":"PPL",
    "gn:name":"Cameron",
    "gn:population":0,
    "gn:timezone":"Europe/London",
    "iso:country":"GB",
    "wof:name":"Cameron",
    "wof:placetype":"locality"
},
  "geometry": {"coordinates":[-2.85176,56.29445],"type":"Point"}
}