{
  "type": "Feature",
  "properties": {
    "gn:admin1_code": "ENG",
    "gn:admin2_code": "C7",
    "gn:asciiname": "Whitley",
    "gn:country_code": "GB",
    "gn:dem": 73,
    "gn:feature_class": "P",
    "gn:feature_code": "PPL",
    "gn:name": "Whitley",
    "gn:population": 0,
    "gn:timezone": "Europe/London",
    "iso:country": "GB",
    "name:ceb_x_preferred": [
      "Whitley"
    ],
    "name:deu_x_preferred": [
      "Whitley"
    ],
    "name:fin_x_preferred": [
      "Whitley"
    ],
    "name:fra_x_preferred": [
      "Whitley"
    ],
    "name:ita_x_preferred": [
      "Whitley"
    ],
    "name:jpn_x_preferred": [
      "ホイットレー"
    ],
    "name:nld_x_preferred": [
      "Whitley"
    ],
    "name:pol_x_preferred": [
      "Whitley"
    ],
    "name:por_x_preferred": [
      "Whitley"
    ],
    "name:srp_x_preferred": [
      "Витли"
    ],
    "name:swe_x_preferred": [
      "Whitley"
    ],
    "wof:name": "Whitley",
    "wof:placetype": "neighbourhood"
  },
  "geometry": {"coordinates":[-1.49345,52.39509],"type":"Point"}
}
