{
  "type": "Feature",
  "properties": {
    "gn:admin1_code":"ENG",
    "gn:admin2_code":"H7",
    "gn:admin3_code":"32UB",
    "gn:admin4_code":"32UB007",
    "gn:asciiname":"Humby",
    "gn:country_code":"GB",
    "gn:dem":4,
    "gn:feature_class":"P",
    "gn:feature_code":"PPL",
    "gn:name":"Humby",
    "gn:population":0,
    "gn:timezone":"Europe/London",
    "iso:country":"GB",
    "name:deu_x_preferred":[
        "Humby"
    ],
    "wof:name":"Humby",
    "wof:placetype":"neighbourhood"
},
  "geometry": {"coordinates":[-0.05,52.86666999999999],"type":"Point"}
}