{
  "type": "Feature",
  "properties": {
    "iso:country":"GB",
    "name:deu_x_preferred":[
        "Buckland Abbey"
    ],
    "name:gle_x_preferred":[
        "Buckland Abbey"
    ],
    "name:rus_x_preferred":[
        "\u0411\u0430\u043a\u043b\u044d\u043d\u0434-\u042d\u0431\u0431\u0438"
    ],
    "qs_pg:aaroncc":"GB",
    "qs_pg:name":"Buckland Abbey",
    "qs_pg:name_adm0":"United Kingdom",
    "qs_pg:name_adm1":"England",
    "qs_pg:photos":293,
    "qs_pg:photos_1k":59,
    "qs_pg:photos_9k":1,
    "qs_pg:photos_9r":4,
    "qs_pg:photos_all":293,
    "qs_pg:photos_sr":5,
    "qs_pg:pop_sr":0,
    "qs_pg:qs_pg_placetype":"locality",
    "qs_pg:qs_pg_placetype_gp":"Town",
    "qs_pg:woe_adm0":23424975,
    "woe:adm0_id":23424975,
    "woe:name_adm0":"United Kingdom",
    "woe:name_adm1":"England",
    "woe:placetype":"Town",
    "wof:name":"Buckland Abbey",
    "wof:placetype":"neighbourhood"
},
  "geometry": {"coordinates":[-4.130945,50.481186],"type":"Point"}
}