{
  "type": "Feature",
  "properties": {
    "iso:country":"GB",
    "name:eng_x_preferred":[
        "Nomansland"
    ],
    "name:nld_x_preferred":[
        "Nomansland"
    ],
    "name:pol_x_preferred":[
        "Nomansland"
    ],
    "name:pol_x_variant":[
        "Nomansland"
    ],
    "name:spa_x_preferred":[
        "Nomansland"
    ],
    "qs_pg:aaroncc":"GB",
    "qs_pg:name":"Nomansland",
    "qs_pg:name_adm0":"United Kingdom",
    "qs_pg:name_adm1":"England",
    "qs_pg:photos":2546,
    "qs_pg:photos_1k":516,
    "qs_pg:photos_9k":11,
    "qs_pg:photos_9r":10,
    "qs_pg:photos_all":2546,
    "qs_pg:photos_sr":18,
    "qs_pg:pop_sr":0,
    "qs_pg:qs_pg_placetype":"locality",
    "qs_pg:qs_pg_placetype_gp":"Town",
    "qs_pg:woe_adm0":23424975,
    "woe:adm0_id":23424975,
    "woe:name_adm0":"United Kingdom",
    "woe:name_adm1":"England",
    "woe:placetype":"Town",
    "wof:name":"Nomansland",
    "wof:placetype":"neighbourhood"
},
  "geometry": {"coordinates":[-1.645288,50.924354],"type":"Point"}
}