{
  "type": "Feature",
  "properties": {
    "iso:country":"GB",
    "name:deu_x_preferred":[
        "Furzton"
    ],
    "name:eng_x_preferred":[
        "Furzton"
    ],
    "qs_pg:aaroncc":"GB",
    "qs_pg:name":"Furzton",
    "qs_pg:name_adm0":"United Kingdom",
    "qs_pg:name_adm1":"England",
    "qs_pg:photos":600,
    "qs_pg:photos_1k":122,
    "qs_pg:photos_9k":3,
    "qs_pg:photos_9r":5,
    "qs_pg:photos_all":600,
    "qs_pg:photos_sr":8,
    "qs_pg:pop_sr":0,
    "qs_pg:qs_pg_placetype":"locality",
    "qs_pg:qs_pg_placetype_gp":"Town",
    "qs_pg:woe_adm0":23424975,
    "woe:adm0_id":23424975,
    "woe:name_adm0":"United Kingdom",
    "woe:name_adm1":"England",
    "woe:placetype":"Town",
    "wof:name":"Furzton",
    "wof:placetype":"neighbourhood"
},
  "geometry": {"coordinates":[-0.762519,52.017773],"type":"Point"}
}