{
  "type": "Feature",
  "properties": {
    "iso:country":"GB",
    "name:eus_x_preferred":[
        "Muirshearlich"
    ],
    "name:gle_x_preferred":[
        "Muir S\u00edorlaich"
    ],
    "name:nld_x_preferred":[
        "Muirshearlich"
    ],
    "qs_pg:aaroncc":"GB",
    "qs_pg:name":"Muirshearlich",
    "qs_pg:name_adm0":"United Kingdom",
    "qs_pg:name_adm1":"Scotland",
    "qs_pg:photos":19,
    "qs_pg:photos_1k":4,
    "qs_pg:photos_9k":1,
    "qs_pg:photos_9r":1,
    "qs_pg:photos_all":19,
    "qs_pg:photos_sr":1,
    "qs_pg:pop_sr":0,
    "qs_pg:qs_pg_placetype":"locality",
    "qs_pg:qs_pg_placetype_gp":"Town",
    "qs_pg:woe_adm0":23424975,
    "woe:adm0_id":23424975,
    "woe:name_adm0":"United Kingdom",
    "woe:name_adm1":"Scotland",
    "woe:placetype":"Town",
    "wof:name":"Muirshearlich",
    "wof:placetype":"locality"
},
  "geometry": {"coordinates":[-5.053367,56.879092],"type":"Point"}
}