{
  "type": "Feature",
  "properties": {
    "gn:admin1_code":"ENG",
    "gn:admin2_code":"H7",
    "gn:admin3_code":"32UC",
    "gn:admin4_code":"32UC188",
    "gn:asciiname":"Kirkstead",
    "gn:country_code":"GB",
    "gn:dem":9,
    "gn:feature_class":"P",
    "gn:feature_code":"PPL",
    "gn:name":"Kirkstead",
    "gn:population":0,
    "gn:timezone":"Europe/London",
    "iso:country":"GB",
    "name:cym_x_preferred":[
        "Kirkstead"
    ],
    "name:pol_x_preferred":[
        "Kirkstead"
    ],
    "wof:name":"Kirkstead",
    "wof:placetype":"neighbourhood"
},
  "geometry": {"coordinates":[-0.21531,53.14124],"type":"Point"}
}