{
  "type": "Feature",
  "properties": {
    "gn:population":10914,
    "iso:country":"GB",
    "name:ceb_x_preferred":[
        "Beighton"
    ],
    "name:eng_x_preferred":[
        "Deighton"
    ],
    "name:eng_x_variant":[
        "Beighton Ward"
    ],
    "name:ita_x_preferred":[
        "Beighton"
    ],
    "name:pol_x_preferred":[
        "Beighton"
    ],
    "name:por_x_preferred":[
        "Beighton"
    ],
    "name:swe_x_preferred":[
        "Beighton"
    ],
    "qs:gn_fcode":"PPL",
    "qs:gn_local":0,
    "qs:gn_namadm1":"ENG",
    "qs:gn_name":"Beighton",
    "qs:local_max":5224,
    "qs:local_sum":14356,
    "qs:localhoods":28,
    "qs:name":"Deighton",
    "qs:name_adm0":"United Kingdom",
    "qs:name_adm1":"England",
    "qs:name_adm2":"West Yorkshire",
    "qs:name_lau":"Kirklees Metropolitan Borough",
    "qs:name_local":"Huddersfield",
    "qs:photo_max":18,
    "qs:photo_sum":58,
    "qs:placetype":"Suburb",
    "qs:quad_count":8,
    "qs:woe_adm0":23424975,
    "qs:woe_adm1":24554868,
    "qs:woe_adm2":12602197,
    "qs:woe_lau":12695872,
    "qs:woe_local":24083,
    "qs:woe_ver":"7.10.0",
    "wof:lang":[
        "eng"
    ],
    "wof:name":"Deighton",
    "wof:placetype":"neighbourhood",
    "wof:population":10914
},
  "geometry": {"coordinates":[-1.74534,53.671505],"type":"Point"}
}