{
  "type": "Feature",
  "properties": {
    "gn:admin1_code":"WLS",
    "gn:admin2_code":"Y7",
    "gn:admin3_code":"00NS040",
    "gn:asciiname":"Newchapel",
    "gn:country_code":"GB",
    "gn:dem":120,
    "gn:feature_class":"P",
    "gn:feature_code":"PPL",
    "gn:name":"Newchapel",
    "gn:population":0,
    "gn:timezone":"Europe/London",
    "iso:country":"GB",
    "name:pol_x_preferred":[
        "Newchapel"
    ],
    "wof:name":"Newchapel",
    "wof:placetype":"neighbourhood"
},
  "geometry": {"coordinates":[-4.58333,52.03333],"type":"Point"}
}