{
  "type": "Feature",
  "properties": {
    "iso:country":"GB",
    "name:bre_x_preferred":[
        "Blaengarw"
    ],
    "name:cym_x_preferred":[
        "Blaengarw"
    ],
    "name:deu_x_preferred":[
        "Blaengarw"
    ],
    "name:eng_x_preferred":[
        "Blaengarw"
    ],
    "name:eus_x_preferred":[
        "Blaengarw"
    ],
    "name:fra_x_preferred":[
        "Blaengarw"
    ],
    "name:glg_x_preferred":[
        "Blaengarw"
    ],
    "name:nld_x_preferred":[
        "Blaengarw"
    ],
    "name:nob_x_preferred":[
        "Blaengarw"
    ],
    "name:nor_x_preferred":[
        "Blaengarw"
    ],
    "name:sco_x_preferred":[
        "Blaengarw"
    ],
    "qs:a0":"United Kingdom",
    "qs:a1":"*Pen-y-bont ar Ogwr#Bridgend",
    "qs:a1_lc":"GB13PB0000",
    "qs:a1r":"0Wales",
    "qs:a1r_lc":"GB13000000",
    "qs:adm0":"United Kingdom",
    "qs:la_lc":"*",
    "qs:level":"locality",
    "qs:loc":"Blaengarw",
    "qs:loc_alt":"Blaengarw",
    "qs:pop":0,
    "qs:type":"buffered point",
    "wd:wordcount":396,
    "wof:name":"Blaengarw",
    "wof:placetype":"neighbourhood"
},
  "geometry": {"coordinates":[-3.583202,51.611962],"type":"Point"}
}