{
  "type": "Feature",
  "properties": {
    "gn:admin1_code":"SCT",
    "gn:admin2_code":"T6",
    "gn:asciiname":"Blairs",
    "gn:country_code":"GB",
    "gn:dem":110,
    "gn:feature_class":"P",
    "gn:feature_code":"PPL",
    "gn:name":"Blairs",
    "gn:population":0,
    "gn:timezone":"Europe/London",
    "iso:country":"GB",
    "wof:name":"Blairs",
    "wof:placetype":"locality"
},
  "geometry": {"coordinates":[-2.39347,57.2342],"type":"Point"}
}