{
  "type": "Feature",
  "properties": {
    "gn:admin1_code": "ENG",
    "gn:admin2_code": "G5",
    "gn:admin3_code": "29UE",
    "gn:asciiname": "Beltinge",
    "gn:country_code": "GB",
    "gn:dem": 34,
    "gn:feature_class": "P",
    "gn:feature_code": "PPL",
    "gn:name": "Beltinge",
    "gn:population": 0,
    "gn:timezone": "Europe/London",
    "iso:country": "GB",
    "name:fra_x_preferred": [
      "Beltinge"
    ],
    "name:pol_x_preferred": [
      "Beltinge"
    ],
    "wof:name": "Beltinge",
    "wof:placetype": "neighbourhood"
  },
  "geometry": {"coordinates":[1.1568,51.37074000000001],"type":"Point"}
}
