{
  "type": "Feature",
  "properties": {
    "iso:country":"GB",
    "name:cor_x_preferred":[
        "Boselwydh"
    ],
    "name:cym_x_preferred":[
        "Bodelva"
    ],
    "name:cym_x_variant":[
        "Boselwydh"
    ],
    "name:eng_x_preferred":[
        "Bodelva"
    ],
    "name:eus_x_preferred":[
        "Bodelva"
    ],
    "name:fra_x_preferred":[
        "Bodelva"
    ],
    "name:jpn_x_preferred":[
        "\u30dc\u30c7\u30eb\u30d0"
    ],
    "name:pol_x_preferred":[
        "Bodelva"
    ],
    "qs_pg:aaroncc":"GB",
    "qs_pg:name":"Bodelva",
    "qs_pg:name_adm0":"United Kingdom",
    "qs_pg:name_adm1":"England",
    "qs_pg:photos":4994,
    "qs_pg:photos_1k":1000,
    "qs_pg:photos_9k":22,
    "qs_pg:photos_9r":14,
    "qs_pg:photos_all":4994,
    "qs_pg:photos_sr":24,
    "qs_pg:pop_sr":0,
    "qs_pg:qs_pg_placetype":"locality",
    "qs_pg:qs_pg_placetype_gp":"Town",
    "qs_pg:woe_adm0":23424975,
    "woe:adm0_id":23424975,
    "woe:name_adm0":"United Kingdom",
    "woe:name_adm1":"England",
    "woe:placetype":"Town",
    "wof:name":"Bodelva",
    "wof:placetype":"neighbourhood"
},
  "geometry": {"coordinates":[-4.741802,50.360654],"type":"Point"}
}