{
  "type": "Feature",
  "properties": {
    "iso:country":"GB",
    "wof:name":"Little Sheffield",
    "wof:placetype":"neighbourhood"
},
  "geometry": {"coordinates":[-1.47686329074068,53.37061313310966],"type":"Point"}
}