{
  "type": "Feature",
  "properties": {
    "iso:country":"GB",
    "name:ceb_x_preferred":[
        "Marton"
    ],
    "name:che_x_preferred":[
        "\u041c\u0430\u0440\u0442\u043e\u043d"
    ],
    "name:deu_x_preferred":[
        "Marton"
    ],
    "name:eng_x_preferred":[
        "Marton"
    ],
    "name:eng_x_variant":[
        "Marton in Cleveland",
        "Marton-in-Cleveland"
    ],
    "name:fas_x_preferred":[
        "\u0645\u0627\u0631\u062a\u0648\u0646"
    ],
    "name:fra_x_preferred":[
        "Marton"
    ],
    "name:hun_x_preferred":[
        "M\u00e1rton"
    ],
    "name:ita_x_preferred":[
        "Marton"
    ],
    "name:nld_x_preferred":[
        "Marton"
    ],
    "name:pol_x_preferred":[
        "Marton"
    ],
    "name:rus_x_preferred":[
        "\u041c\u0430\u0440\u0442\u043e\u043d"
    ],
    "name:slk_x_preferred":[
        "Marton"
    ],
    "name:swe_x_preferred":[
        "Marton"
    ],
    "name:ukr_x_preferred":[
        "\u041c\u0430\u0440\u0442\u043e\u043d"
    ],
    "qs:gn_adm0_cc":"GB",
    "qs:gn_fcode":"PPL",
    "qs:gn_local":0,
    "qs:gn_namadm1":"ENG",
    "qs:gn_name":"Marton",
    "qs:local_max":4739,
    "qs:local_sum":15614,
    "qs:localhoods":9,
    "qs:name":"Marton",
    "qs:name_adm0":"United Kingdom",
    "qs:name_adm1":"England",
    "qs:name_adm2":"North Yorkshire",
    "qs:name_lau":"Middlesbrough",
    "qs:name_local":"Middlesbrough",
    "qs:photo_max":424,
    "qs:photo_sum":1868,
    "qs:placetype":"Suburb",
    "qs:quad_count":64,
    "qs:woe_adm0":23424975,
    "qs:woe_adm1":24554868,
    "qs:woe_adm2":12602195,
    "qs:woe_lau":12696141,
    "qs:woe_local":28869,
    "qs:woe_ver":"7.10.0",
    "wd:wordcount":252,
    "wof:lang":[
        "eng"
    ],
    "wof:name":"Marton",
    "wof:placetype":"neighbourhood"
},
  "geometry": {"coordinates":[-1.209646,54.534364],"type":"Point"}
}