{
  "type": "Feature",
  "properties": {
    "gn:country":"GB",
    "gn:fcode":"PPL",
    "gn:population":0,
    "iso:country":"GB",
    "name:eng_x_preferred":[
        "Struy"
    ],
    "name:eus_x_preferred":[
        "Struy"
    ],
    "name:gla_x_preferred":[
        "An t-Sr\u00f9igh"
    ],
    "name:gle_x_preferred":[
        "An t-Sr\u00faigh"
    ],
    "name:gle_x_variant":[
        "An t-Sr\u00f9igh"
    ],
    "name:nld_x_preferred":[
        "Struy"
    ],
    "name:swe_x_preferred":[
        "Struy"
    ],
    "qs_pg:aaroncc":"GB",
    "qs_pg:gn_country":"GB",
    "qs_pg:gn_fcode":"PPL",
    "qs_pg:gn_pop":0,
    "qs_pg:name":"Struy",
    "qs_pg:name_adm0":"United Kingdom",
    "qs_pg:name_adm1":"Scotland",
    "qs_pg:photos":424,
    "qs_pg:photos_1k":86,
    "qs_pg:photos_9k":2,
    "qs_pg:photos_9r":5,
    "qs_pg:photos_all":424,
    "qs_pg:photos_sr":6,
    "qs_pg:pop_sr":0,
    "qs_pg:qs_pg_placetype":"locality",
    "qs_pg:qs_pg_placetype_gp":"Town",
    "qs_pg:woe_adm0":23424975,
    "woe:adm0_id":23424975,
    "woe:name_adm0":"United Kingdom",
    "woe:name_adm1":"Scotland",
    "woe:placetype":"Town",
    "wof:name":"Struy",
    "wof:placetype":"locality"
},
  "geometry": {"coordinates":[-4.66576,57.4224],"type":"Point"}
}