{
  "type": "Feature",
  "properties": {
    "gn:admin1_code":"SCT",
    "gn:admin2_code":"W1",
    "gn:asciiname":"Lair",
    "gn:country_code":"GB",
    "gn:dem":335,
    "gn:feature_class":"P",
    "gn:feature_code":"PPL",
    "gn:name":"Lair",
    "gn:population":0,
    "gn:timezone":"Europe/London",
    "iso:country":"GB",
    "name:ceb_x_preferred":[
        "Lair"
    ],
    "name:deu_x_preferred":[
        "Lair"
    ],
    "name:fin_x_preferred":[
        "Lair"
    ],
    "name:fra_x_preferred":[
        "Lair"
    ],
    "name:swe_x_preferred":[
        "Lair"
    ],
    "wof:name":"Lair",
    "wof:placetype":"locality"
},
  "geometry": {"coordinates":[-3.40585,56.75381],"type":"Point"}
}