{
  "type": "Feature",
  "properties": {
    "gn:admin1_code":"SCT",
    "gn:admin2_code":"T9",
    "gn:asciiname":"Wedderlie",
    "gn:country_code":"GB",
    "gn:dem":225,
    "gn:feature_class":"P",
    "gn:feature_code":"PPL",
    "gn:name":"Wedderlie",
    "gn:population":0,
    "gn:timezone":"Europe/London",
    "iso:country":"GB",
    "wof:name":"Wedderlie",
    "wof:placetype":"locality"
},
  "geometry": {"coordinates":[-2.56667,55.75],"type":"Point"}
}