{
  "type": "Feature",
  "properties": {
    "iso:country":"GB",
    "name:ceb_x_preferred":[
        "Goring-by-Sea"
    ],
    "name:eng_x_colloquial":[
        "Goring"
    ],
    "name:eng_x_preferred":[
        "Goring by Sea"
    ],
    "name:eng_x_variant":[
        "Goring",
        "Goring-by-Sea"
    ],
    "name:fra_x_preferred":[
        "Goring-by-Sea"
    ],
    "name:nld_x_preferred":[
        "Goring-by-Sea"
    ],
    "name:pol_x_preferred":[
        "Goring-by-Sea"
    ],
    "name:swe_x_preferred":[
        "Goring-by-Sea"
    ],
    "qs:gn_adm0_cc":"GB",
    "qs:gn_fcode":"PPL",
    "qs:gn_local":2633521,
    "qs:gn_nam_loc":"worthing",
    "qs:gn_namadm1":"ENG",
    "qs:gn_name":"Goring-by-Sea",
    "qs:local_max":4979,
    "qs:local_sum":8456,
    "qs:localhoods":7,
    "qs:name":"Goring by Sea",
    "qs:name_adm0":"United Kingdom",
    "qs:name_adm1":"England",
    "qs:name_adm2":"West Sussex",
    "qs:name_lau":"Worthing Borough",
    "qs:name_local":"Worthing",
    "qs:photo_max":128,
    "qs:photo_sum":1137,
    "qs:placetype":"Suburb",
    "qs:quad_count":81,
    "qs:woe_adm0":23424975,
    "qs:woe_adm1":24554868,
    "qs:woe_adm2":12602177,
    "qs:woe_lau":12696109,
    "qs:woe_local":41169,
    "qs:woe_ver":"7.10.0",
    "wd:wordcount":266,
    "wof:lang":[
        "eng"
    ],
    "wof:name":"Goring by Sea",
    "wof:placetype":"neighbourhood"
},
  "geometry": {"coordinates":[-0.42977,50.814006],"type":"Point"}
}