{
  "type": "Feature",
  "properties": {
    "iso:country": "GB",
    "name:eng_x_preferred": [
      "Meathop"
    ],
    "name:pol_x_preferred": [
      "Meathop"
    ],
    "qs_pg:aaroncc": "GB",
    "qs_pg:name": "Meathop",
    "qs_pg:name_adm0": "United Kingdom",
    "qs_pg:name_adm1": "England",
    "qs_pg:photos": 50,
    "qs_pg:photos_1k": 10,
    "qs_pg:photos_9k": 1,
    "qs_pg:photos_9r": 2,
    "qs_pg:photos_all": 50,
    "qs_pg:photos_sr": 2,
    "qs_pg:pop_sr": 0,
    "qs_pg:qs_pg_placetype": "locality",
    "qs_pg:qs_pg_placetype_gp": "Town",
    "qs_pg:woe_adm0": 23424975,
    "woe:adm0_id": 23424975,
    "woe:name_adm0": "United Kingdom",
    "woe:name_adm1": "England",
    "woe:placetype": "Town",
    "wof:name": "Meathop",
    "wof:placetype": "neighbourhood"
  },
  "geometry": {"coordinates":[-2.866792,54.215685],"type":"Point"}
}
