{
  "type": "Feature",
  "properties": {
    "gn:admin1_code":"SCT",
    "gn:admin2_code":"V3",
    "gn:asciiname":"Glenmore",
    "gn:country_code":"GB",
    "gn:dem":327,
    "gn:feature_class":"P",
    "gn:feature_code":"PPL",
    "gn:name":"Glenmore",
    "gn:population":0,
    "gn:timezone":"Europe/London",
    "iso:country":"GB",
    "name:ceb_x_preferred":[
        "Glenmore"
    ],
    "name:deu_x_preferred":[
        "Glenmore"
    ],
    "name:fra_x_preferred":[
        "Glenmore"
    ],
    "name:ind_x_preferred":[
        "Glenmore"
    ],
    "name:pol_x_preferred":[
        "Glenmore"
    ],
    "name:swe_x_preferred":[
        "Glenmore"
    ],
    "wof:name":"Glenmore",
    "wof:placetype":"locality"
},
  "geometry": {"coordinates":[-3.6957,57.16608000000001],"type":"Point"}
}