{
  "type": "Feature",
  "properties": {
    "iso:country":"GB",
    "name:eng_x_preferred":[
        "Chapel-le-Dale"
    ],
    "name:fra_x_preferred":[
        "Chapel-le-Dale"
    ],
    "name:nld_x_preferred":[
        "Chapel-le-Dale"
    ],
    "name:pnb_x_preferred":[
        "\u0686\u06cc\u067e\u0644-\u0644\u06cc-\u0688\u06cc\u0644"
    ],
    "name:pol_x_preferred":[
        "Chapel-le-Dale"
    ],
    "qs_pg:aaroncc":"GB",
    "qs_pg:name":"Chapel le Dale",
    "qs_pg:name_adm0":"United Kingdom",
    "qs_pg:name_adm1":"England",
    "qs_pg:photos":3627,
    "qs_pg:photos_1k":735,
    "qs_pg:photos_9k":16,
    "qs_pg:photos_9r":12,
    "qs_pg:photos_all":3627,
    "qs_pg:photos_sr":21,
    "qs_pg:pop_sr":0,
    "qs_pg:qs_pg_placetype":"locality",
    "qs_pg:qs_pg_placetype_gp":"Town",
    "qs_pg:woe_adm0":23424975,
    "woe:adm0_id":23424975,
    "woe:name_adm0":"United Kingdom",
    "woe:name_adm1":"England",
    "woe:placetype":"Town",
    "wof:name":"Chapel le Dale",
    "wof:placetype":"neighbourhood"
},
  "geometry": {"coordinates":[-2.365064,54.209845],"type":"Point"}
}