{
  "type": "Feature",
  "properties": {
    "gn:admin1_code":"ENG",
    "gn:admin2_code":"G5",
    "gn:admin3_code":"6945807",
    "gn:admin4_code":"29UC023",
    "gn:asciiname":"Hersden",
    "gn:country_code":"GB",
    "gn:dem":31,
    "gn:feature_class":"P",
    "gn:feature_code":"PPL",
    "gn:name":"Hersden",
    "gn:population":0,
    "gn:timezone":"Europe/London",
    "iso:country":"GB",
    "name:ceb_x_preferred":[
        "Hersden"
    ],
    "name:cym_x_preferred":[
        "Hersden"
    ],
    "name:fra_x_preferred":[
        "Hersden"
    ],
    "name:pol_x_preferred":[
        "Hersden"
    ],
    "name:spa_x_preferred":[
        "Hersden"
    ],
    "name:swe_x_preferred":[
        "Hersden"
    ],
    "wof:name":"Hersden",
    "wof:placetype":"neighbourhood"
},
  "geometry": {"coordinates":[1.16541,51.31495],"type":"Point"}
}