{
  "type": "Feature",
  "properties": {
    "gn:country": "GB",
    "gn:fcode": "PPL",
    "gn:population": 0,
    "iso:country": "GB",
    "name:ceb_x_preferred": [
      "Fettercairn"
    ],
    "name:deu_x_preferred": [
      "Fettercairn"
    ],
    "name:eng_x_preferred": [
      "Fettercairn"
    ],
    "name:eus_x_preferred": [
      "Fettercairn"
    ],
    "name:fra_x_preferred": [
      "Fettercairn"
    ],
    "name:gle_x_preferred": [
      "Fothair Chárdain"
    ],
    "name:glg_x_preferred": [
      "Fettercairn"
    ],
    "name:heb_x_preferred": [
      "פטרקיירן"
    ],
    "name:nld_x_preferred": [
      "Fettercairn"
    ],
    "name:rus_x_preferred": [
      "Феттеркэрн"
    ],
    "name:sco_x_preferred": [
      "Fettercairn"
    ],
    "name:swe_x_preferred": [
      "Fettercairn"
    ],
    "qs_pg:aaroncc": "GB",
    "qs_pg:gn_country": "GB",
    "qs_pg:gn_fcode": "PPL",
    "qs_pg:gn_pop": 0,
    "qs_pg:name": "Fettercairn",
    "qs_pg:name_adm0": "United Kingdom",
    "qs_pg:name_adm1": "Scotland",
    "qs_pg:photos": 183,
    "qs_pg:photos_1k": 37,
    "qs_pg:photos_9k": 1,
    "qs_pg:photos_9r": 4,
    "qs_pg:photos_all": 183,
    "qs_pg:photos_sr": 4,
    "qs_pg:pop_sr": 0,
    "qs_pg:qs_pg_placetype": "locality",
    "qs_pg:qs_pg_placetype_gp": "Town",
    "qs_pg:woe_adm0": 23424975,
    "woe:adm0_id": 23424975,
    "woe:name_adm0": "United Kingdom",
    "woe:name_adm1": "Scotland",
    "woe:placetype": "Town",
    "wof:name": "Fettercairn",
    "wof:placetype": "locality"
  },
  "geometry": {"coordinates":[-2.57482,56.85125],"type":"Point"}
}
