{
  "type": "Feature",
  "properties": {
    "iso:country": "GB",
    "name:ceb_x_preferred": [
      "Warton Airport"
    ],
    "name:eng_x_preferred": [
      "Warton Aerodrome"
    ],
    "name:eng_x_variant": [
      "WRT",
      "EGNO"
    ],
    "name:fas_x_preferred": [
      "فرودگاه وارتون"
    ],
    "name:heb_x_preferred": [
      "וורטון"
    ],
    "name:jpn_x_preferred": [
      "ウォートン空港"
    ],
    "name:msa_x_preferred": [
      "Lapangan Terbang Warton"
    ],
    "name:pms_x_preferred": [
      "Warton Aerodrome"
    ],
    "name:swe_x_preferred": [
      "Warton Airport"
    ],
    "name:tgk_x_preferred": [
      "Фурудгоҳи вортун"
    ],
    "oa:elevation_ft": "55",
    "oa:type": "medium_airport",
    "woe:hierarchy": {
      "country_id": 23424975,
      "county_id": 12602160,
      "localadmin_id": 12695999,
      "planet_id": 1,
      "state_id": 24554868
    },
    "wof:name": "Warton Airport",
    "wof:placetype": "campus"
  },
  "geometry": {"coordinates":[-2.883889,53.745],"type":"Point"}
}
