{
  "type": "Feature",
  "properties": {
    "iso:country":"GB",
    "oa:elevation_ft":"55",
    "oa:type":"medium_airport",
    "woe:hierarchy":{
        "country_id":23424975,
        "county_id":12602160,
        "localadmin_id":12695999,
        "planet_id":1,
        "state_id":24554868
    },
    "wof:name":"Warton Airport",
    "wof:placetype":"campus"
},
  "geometry": {"coordinates":[-2.8838888888889,53.745],"type":"Point"}
}