{
  "type": "Feature",
  "properties": {
    "iso:country":"GB",
    "name:ceb_x_preferred":[
        "Warton Airport"
    ],
    "name:eng_x_preferred":[
        "Warton Aerodrome"
    ],
    "name:eng_x_variant":[
        "WRT",
        "EGNO"
    ],
    "name:fas_x_preferred":[
        "\u0641\u0631\u0648\u062f\u06af\u0627\u0647 \u0648\u0627\u0631\u062a\u0648\u0646"
    ],
    "name:fra_x_preferred":[
        "RAF Warton"
    ],
    "name:heb_x_preferred":[
        "\u05d5\u05d5\u05e8\u05d8\u05d5\u05df"
    ],
    "name:jpn_x_preferred":[
        "\u30a6\u30a9\u30fc\u30c8\u30f3\u7a7a\u6e2f"
    ],
    "name:msa_x_preferred":[
        "Lapangan Terbang Warton"
    ],
    "name:pms_x_preferred":[
        "Warton Aerodrome"
    ],
    "name:swe_x_preferred":[
        "Warton Airport"
    ],
    "name:tgk_x_preferred":[
        "\u0424\u0443\u0440\u0443\u0434\u0433\u043e\u04b3\u0438 \u0432\u043e\u0440\u0442\u0443\u043d"
    ],
    "oa:elevation_ft":"55",
    "oa:type":"medium_airport",
    "woe:hierarchy":{
        "country_id":23424975,
        "county_id":12602160,
        "localadmin_id":12695999,
        "planet_id":1,
        "state_id":24554868
    },
    "wof:name":"Warton Airport",
    "wof:placetype":"campus"
},
  "geometry": {"coordinates":[-2.883889,53.745],"type":"Point"}
}