{
  "type": "Feature",
  "properties": {
    "iso:country":"GB",
    "name:cym_x_preferred":[
        "Walmer Bridge"
    ],
    "name:eng_x_preferred":[
        "Walmer Bridge"
    ],
    "name:fra_x_preferred":[
        "Walmer Bridge"
    ],
    "name:gle_x_preferred":[
        "Walmer Bridge"
    ],
    "name:nld_x_preferred":[
        "Walmer Bridge"
    ],
    "name:pol_x_preferred":[
        "Walmer Bridge"
    ],
    "qs_pg:aaroncc":"GB",
    "qs_pg:name":"Walmer Bridge",
    "qs_pg:name_adm0":"United Kingdom",
    "qs_pg:name_adm1":"England",
    "qs_pg:photos":20,
    "qs_pg:photos_1k":4,
    "qs_pg:photos_9k":1,
    "qs_pg:photos_9r":1,
    "qs_pg:photos_all":20,
    "qs_pg:photos_sr":1,
    "qs_pg:pop_sr":0,
    "qs_pg:qs_pg_placetype":"locality",
    "qs_pg:qs_pg_placetype_gp":"Town",
    "qs_pg:woe_adm0":23424975,
    "woe:adm0_id":23424975,
    "woe:name_adm0":"United Kingdom",
    "woe:name_adm1":"England",
    "woe:placetype":"Town",
    "wof:name":"Walmer Bridge",
    "wof:placetype":"neighbourhood"
},
  "geometry": {"coordinates":[-2.789239,53.718044],"type":"Point"}
}