{
  "type": "Feature",
  "properties": {
    "iso:country":"GB",
    "name:ceb_x_preferred":[
        "Harthill"
    ],
    "name:cym_x_preferred":[
        "Harthill"
    ],
    "name:eng_x_preferred":[
        "Harthill"
    ],
    "name:eus_x_preferred":[
        "Harthill"
    ],
    "name:fra_x_preferred":[
        "Harthill"
    ],
    "name:nld_x_preferred":[
        "Harthill"
    ],
    "name:nob_x_preferred":[
        "Harthill"
    ],
    "name:spa_x_preferred":[
        "Harthill"
    ],
    "name:swe_x_preferred":[
        "Harthill"
    ],
    "name:zho_x_preferred":[
        "\u54c8\u7279\u5e0c\u5c14"
    ],
    "qs:a0":"United Kingdom",
    "qs:a1":"*North Lanarkshire",
    "qs:a1_lc":"GB11QZ0000",
    "qs:a1r":"0Scotland",
    "qs:a1r_lc":"GB11000000",
    "qs:adm0":"United Kingdom",
    "qs:la_lc":"*",
    "qs:level":"locality",
    "qs:loc":"Harthill",
    "qs:loc_alt":"Harthill",
    "qs:pop":0,
    "qs:type":"buffered point",
    "wof:name":"Harthill",
    "wof:placetype":"locality"
},
  "geometry": {"coordinates":[-3.747851,55.86021],"type":"Point"}
}