{
  "type": "Feature",
  "properties": {
    "iso:country":"GB",
    "name:eng_x_preferred":[
        "Harthill"
    ],
    "name:nld_x_preferred":[
        "Harthill"
    ],
    "name:nob_x_preferred":[
        "Harthill"
    ],
    "name:swe_x_preferred":[
        "Harthill"
    ],
    "qs:a0":"United Kingdom",
    "qs:a1":"*North Lanarkshire",
    "qs:a1_lc":"GB11QZ0000",
    "qs:a1r":"0Scotland",
    "qs:a1r_lc":"GB11000000",
    "qs:adm0":"United Kingdom",
    "qs:la_lc":"*",
    "qs:level":"locality",
    "qs:loc":"Harthill",
    "qs:loc_alt":"Harthill",
    "qs:pop":0,
    "qs:type":"buffered point",
    "wof:name":"Harthill",
    "wof:placetype":"locality"
},
  "geometry": {"coordinates":[-3.747851,55.86021],"type":"Point"}
}