{
  "type": "Feature",
  "properties": {
    "gn:gn_country":"GB",
    "gn:gn_fcode":"PPL",
    "gn:gn_pop":5377,
    "gn:population":5377,
    "iso:country":"GB",
    "name:ceb_x_preferred":[
        "Hoo"
    ],
    "name:deu_x_preferred":[
        "Hoo"
    ],
    "name:pol_x_preferred":[
        "Hoo"
    ],
    "name:swe_x_preferred":[
        "Hoo"
    ],
    "qs_pg:aaroncc":"GB",
    "qs_pg:gn_country":"GB",
    "qs_pg:gn_fcode":"PPL",
    "qs_pg:gn_pop":5377,
    "qs_pg:name":"Hoo",
    "qs_pg:name_adm0":"United Kingdom",
    "qs_pg:name_adm1":"England",
    "qs_pg:photos":132,
    "qs_pg:photos_1k":27,
    "qs_pg:photos_9k":1,
    "qs_pg:photos_9r":3,
    "qs_pg:photos_all":132,
    "qs_pg:photos_sr":3,
    "qs_pg:pop_sr":5,
    "qs_pg:qs_pg_placetype":"locality",
    "qs_pg:qs_pg_placetype_gp":"Town",
    "qs_pg:woe_adm0":23424975,
    "woe:adm0_id":23424975,
    "woe:name_adm0":"United Kingdom",
    "woe:name_adm1":"England",
    "woe:placetype":"Town",
    "wof:name":"Hoo",
    "wof:placetype":"neighbourhood",
    "wof:population":5377
},
  "geometry": {"coordinates":[0.5652,51.41752],"type":"Point"}
}