{
  "type": "Feature",
  "properties": {
    "gn:admin1_code":"ENG",
    "gn:admin2_code":"P8",
    "gn:admin3_code":"00HY007",
    "gn:asciiname":"Ratfyn",
    "gn:country_code":"GB",
    "gn:dem":81,
    "gn:feature_class":"P",
    "gn:feature_code":"PPL",
    "gn:name":"Ratfyn",
    "gn:population":0,
    "gn:timezone":"Europe/London",
    "iso:country":"GB",
    "wof:name":"Ratfyn",
    "wof:placetype":"neighbourhood"
},
  "geometry": {"coordinates":[-1.77129,51.1819],"type":"Point"}
}