{
  "type": "Feature",
  "properties": {
    "iso:country": "GB",
    "name:ben_x_preferred": [
      "হর্বুরি"
    ],
    "name:bul_x_preferred": [
      "Хорбурй"
    ],
    "name:ceb_x_preferred": [
      "Horbury"
    ],
    "name:deu_x_preferred": [
      "Horbury"
    ],
    "name:eng_x_preferred": [
      "Horbury"
    ],
    "name:fra_x_preferred": [
      "Horbury"
    ],
    "name:guj_x_preferred": [
      "હોરબરી"
    ],
    "name:ita_x_preferred": [
      "Horbury"
    ],
    "name:jpn_x_preferred": [
      "ホーベリー"
    ],
    "name:kan_x_preferred": [
      "ಹೊರ್ಬರಿ"
    ],
    "name:kor_x_preferred": [
      "호버리"
    ],
    "name:lit_x_preferred": [
      "Horberis"
    ],
    "name:nld_x_preferred": [
      "Horbury"
    ],
    "name:pol_x_preferred": [
      "Horbury"
    ],
    "name:por_x_preferred": [
      "Horbury"
    ],
    "name:rus_x_preferred": [
      "Хорбёри"
    ],
    "name:spa_x_preferred": [
      "Horbury"
    ],
    "name:swe_x_preferred": [
      "Horbury"
    ],
    "name:tam_x_preferred": [
      "ஹொர்புரி"
    ],
    "name:tel_x_preferred": [
      "హర్బురి"
    ],
    "name:urd_x_preferred": [
      "ہوربوری"
    ],
    "name:zho_x_preferred": [
      "霍布里"
    ],
    "qs_pg:aaroncc": "GB",
    "qs_pg:name": "Horbury",
    "qs_pg:name_adm0": "United Kingdom",
    "qs_pg:name_adm1": "England",
    "qs_pg:photos": 545,
    "qs_pg:photos_1k": 110,
    "qs_pg:photos_9k": 2,
    "qs_pg:photos_9r": 5,
    "qs_pg:photos_all": 545,
    "qs_pg:photos_sr": 7,
    "qs_pg:pop_sr": 0,
    "qs_pg:qs_pg_placetype": "locality",
    "qs_pg:qs_pg_placetype_gp": "Town",
    "qs_pg:woe_adm0": 23424975,
    "woe:adm0_id": 23424975,
    "woe:name_adm0": "United Kingdom",
    "woe:name_adm1": "England",
    "woe:placetype": "Town",
    "wof:name": "Horbury",
    "wof:placetype": "neighbourhood"
  },
  "geometry": {"coordinates":[-1.560401,53.660611],"type":"Point"}
}
