{
  "type": "Feature",
  "properties": {
    "iso:country":"GB",
    "name:ben_x_preferred":[
        "\u09b9\u09b0\u09cd\u09ac\u09c1\u09b0\u09bf"
    ],
    "name:bul_x_preferred":[
        "\u0425\u043e\u0440\u0431\u0443\u0440\u0439"
    ],
    "name:ceb_x_preferred":[
        "Horbury"
    ],
    "name:deu_x_preferred":[
        "Horbury"
    ],
    "name:eng_x_preferred":[
        "Horbury"
    ],
    "name:fas_x_preferred":[
        "\u0647\u0648\u0631\u0628\u0631\u06cc"
    ],
    "name:fra_x_preferred":[
        "Horbury"
    ],
    "name:gle_x_preferred":[
        "Horbury"
    ],
    "name:guj_x_preferred":[
        "\u0ab9\u0acb\u0ab0\u0aac\u0ab0\u0ac0"
    ],
    "name:ita_x_preferred":[
        "Horbury"
    ],
    "name:jpn_x_preferred":[
        "\u30db\u30fc\u30d9\u30ea\u30fc"
    ],
    "name:kan_x_preferred":[
        "\u0cb9\u0cca\u0cb0\u0ccd\u0cac\u0cb0\u0cbf"
    ],
    "name:kor_x_preferred":[
        "\ud638\ubc84\ub9ac"
    ],
    "name:lit_x_preferred":[
        "Horberis"
    ],
    "name:nld_x_preferred":[
        "Horbury"
    ],
    "name:pol_x_preferred":[
        "Horbury"
    ],
    "name:por_x_preferred":[
        "Horbury"
    ],
    "name:rus_x_preferred":[
        "\u0425\u043e\u0440\u0431\u0451\u0440\u0438"
    ],
    "name:spa_x_preferred":[
        "Horbury"
    ],
    "name:swe_x_preferred":[
        "Horbury"
    ],
    "name:tam_x_preferred":[
        "\u0bb9\u0bca\u0bb0\u0bcd\u0baa\u0bc1\u0bb0\u0bbf"
    ],
    "name:tel_x_preferred":[
        "\u0c39\u0c30\u0c4d\u0c2c\u0c41\u0c30\u0c3f"
    ],
    "name:urd_x_preferred":[
        "\u06c1\u0648\u0631\u0628\u0648\u0631\u06cc"
    ],
    "name:zho_x_preferred":[
        "\u970d\u5e03\u91cc"
    ],
    "qs_pg:aaroncc":"GB",
    "qs_pg:name":"Horbury",
    "qs_pg:name_adm0":"United Kingdom",
    "qs_pg:name_adm1":"England",
    "qs_pg:photos":545,
    "qs_pg:photos_1k":110,
    "qs_pg:photos_9k":2,
    "qs_pg:photos_9r":5,
    "qs_pg:photos_all":545,
    "qs_pg:photos_sr":7,
    "qs_pg:pop_sr":0,
    "qs_pg:qs_pg_placetype":"locality",
    "qs_pg:qs_pg_placetype_gp":"Town",
    "qs_pg:woe_adm0":23424975,
    "woe:adm0_id":23424975,
    "woe:name_adm0":"United Kingdom",
    "woe:name_adm1":"England",
    "woe:placetype":"Town",
    "wof:name":"Horbury",
    "wof:placetype":"neighbourhood"
},
  "geometry": {"coordinates":[-1.560401,53.660611],"type":"Point"}
}