{
  "type": "Feature",
  "properties": {
    "gn:admin1_code":"SCT",
    "gn:admin2_code":"T9",
    "gn:asciiname":"Polwarth",
    "gn:country_code":"GB",
    "gn:dem":173,
    "gn:feature_class":"P",
    "gn:feature_code":"PPL",
    "gn:name":"Polwarth",
    "gn:population":0,
    "gn:timezone":"Europe/London",
    "iso:country":"GB",
    "name:eus_x_preferred":[
        "Polwarth"
    ],
    "name:sco_x_preferred":[
        "Polart"
    ],
    "wof:name":"Polwarth",
    "wof:placetype":"locality"
},
  "geometry": {"coordinates":[-2.40777,55.74545],"type":"Point"}
}