{
  "type": "Feature",
  "properties": {
    "iso:country": "GB",
    "name:ceb_x_preferred": [
      "Thirlmere"
    ],
    "name:deu_x_preferred": [
      "Thirlmere"
    ],
    "name:fra_x_preferred": [
      "Thirlmere"
    ],
    "name:nno_x_preferred": [
      "Thirlmere"
    ],
    "name:pnb_x_preferred": [
      "تھرلمیئر"
    ],
    "name:swe_x_preferred": [
      "Thirlmere"
    ],
    "name:zho_x_preferred": [
      "瑟爾米爾"
    ],
    "qs_pg:aaroncc": "GB",
    "qs_pg:name": "Thirlmere",
    "qs_pg:name_adm0": "United Kingdom",
    "qs_pg:name_adm1": "England",
    "qs_pg:photos": 926,
    "qs_pg:photos_1k": 188,
    "qs_pg:photos_9k": 4,
    "qs_pg:photos_9r": 6,
    "qs_pg:photos_all": 926,
    "qs_pg:photos_sr": 10,
    "qs_pg:pop_sr": 0,
    "qs_pg:qs_pg_placetype": "locality",
    "qs_pg:qs_pg_placetype_gp": "Town",
    "qs_pg:woe_adm0": 23424975,
    "woe:adm0_id": 23424975,
    "woe:name_adm0": "United Kingdom",
    "woe:name_adm1": "England",
    "woe:placetype": "Town",
    "wof:name": "Thirlmere",
    "wof:placetype": "neighbourhood"
  },
  "geometry": {"coordinates":[-3.062712,54.560815],"type":"Point"}
}
