{
  "type": "Feature",
  "properties": {
    "gn:admin1_code":"ENG",
    "gn:admin2_code":"F2",
    "gn:admin3_code":"24UN",
    "gn:admin4_code":"24UN026",
    "gn:asciiname":"Upper Somborne",
    "gn:country_code":"GB",
    "gn:dem":63,
    "gn:feature_class":"P",
    "gn:feature_code":"PPL",
    "gn:name":"Upper Somborne",
    "gn:population":0,
    "gn:timezone":"Europe/London",
    "iso:country":"GB",
    "wof:name":"Upper Somborne",
    "wof:placetype":"neighbourhood"
},
  "geometry": {"coordinates":[-1.4338,51.08936],"type":"Point"}
}