{
  "type": "Feature",
  "properties": {
    "gn:admin1_code": "WLS",
    "gn:admin2_code": "X7",
    "gn:admin3_code": "00NU028",
    "gn:asciiname": "Capel Hendre",
    "gn:cc2": "GB",
    "gn:country_code": "GB",
    "gn:dem": 119,
    "gn:feature_class": "P",
    "gn:feature_code": "PPL",
    "gn:name": "Capel Hendre",
    "gn:population": 0,
    "gn:timezone": "Europe/London",
    "iso:country": "GB",
    "name:und_x_variant": [
      "Hendre",
      "Capel Hendre"
    ],
    "wof:name": "Capel Hendre",
    "wof:placetype": "neighbourhood"
  },
  "geometry": {"coordinates":[-4.04194,51.78278],"type":"Point"}
}
