{
  "type": "Feature",
  "properties": {
    "gn:population": 10000,
    "iso:country": "GB",
    "name:bel_x_preferred": [
      "Горад Ардросан"
    ],
    "name:bel_x_variant": [
      "Ардрасан",
      "Горад Ардрасан"
    ],
    "name:ben_x_preferred": [
      "আড্রোস্যান"
    ],
    "name:cat_x_preferred": [
      "Ardrossan"
    ],
    "name:ceb_x_preferred": [
      "Ardrossan"
    ],
    "name:cym_x_preferred": [
      "Ardrossan"
    ],
    "name:deu_x_preferred": [
      "Ardrossan"
    ],
    "name:eng_x_preferred": [
      "Ardrossan"
    ],
    "name:eus_x_preferred": [
      "Ardrossan"
    ],
    "name:fas_x_preferred": [
      "آردروسان"
    ],
    "name:fra_x_preferred": [
      "Ardrossan"
    ],
    "name:gla_x_preferred": [
      "Àird Rosain"
    ],
    "name:gle_x_preferred": [
      "Áird Rosain"
    ],
    "name:glv_x_preferred": [
      "Ard Rushen"
    ],
    "name:guj_x_preferred": [
      "અર્ડ્રોસન"
    ],
    "name:hbs_x_preferred": [
      "Ardrossan"
    ],
    "name:heb_x_preferred": [
      "ארדרסון"
    ],
    "name:ita_x_preferred": [
      "Ardrossan"
    ],
    "name:jpn_x_preferred": [
      "アードロッサン"
    ],
    "name:kan_x_preferred": [
      "ಅರ್ಡ್ರಾಸನ್"
    ],
    "name:kor_x_preferred": [
      "아드로산"
    ],
    "name:lit_x_preferred": [
      "Ardrosanas"
    ],
    "name:nld_x_preferred": [
      "Ardrossan"
    ],
    "name:nno_x_preferred": [
      "Ardrossan"
    ],
    "name:nob_x_preferred": [
      "Ardrossan"
    ],
    "name:nor_x_preferred": [
      "Ardrossan"
    ],
    "name:pol_x_preferred": [
      "Ardrossan"
    ],
    "name:por_x_preferred": [
      "Ardrossan"
    ],
    "name:rus_x_preferred": [
      "Ардроссан"
    ],
    "name:sco_x_preferred": [
      "Ardrussan"
    ],
    "name:spa_x_preferred": [
      "Ardrossan"
    ],
    "name:swe_x_preferred": [
      "Ardrossan"
    ],
    "name:tam_x_preferred": [
      "ஆர்டரோசன்"
    ],
    "name:tel_x_preferred": [
      "అడ్రాసన్"
    ],
    "name:ukr_x_preferred": [
      "Ардроссан"
    ],
    "name:urd_x_preferred": [
      "اردروسان"
    ],
    "qs:a0": "United Kingdom",
    "qs:a1": "*North Ayrshire",
    "qs:a1_lc": "GB11QY0000",
    "qs:a1r": "0Scotland",
    "qs:a1r_lc": "GB11000000",
    "qs:adm0": "United Kingdom",
    "qs:la_lc": "*",
    "qs:level": "locality",
    "qs:loc": "Ardrossan",
    "qs:loc_alt": "Ardrossan",
    "qs:pop": 0,
    "qs:type": "buffered point",
    "wd:wordcount": 2817,
    "wof:name": "Ardrossan",
    "wof:placetype": "locality",
    "wof:population": 10000
  },
  "geometry": {"coordinates":[-4.796742,55.646868],"type":"Point"}
}
