{
  "type": "Feature",
  "properties": {
    "gn:admin1_code":"ENG",
    "gn:admin2_code":"L6",
    "gn:admin3_code":"00GG045",
    "gn:asciiname":"Marton",
    "gn:country_code":"GB",
    "gn:dem":108,
    "gn:feature_class":"P",
    "gn:feature_code":"PPL",
    "gn:name":"Marton",
    "gn:population":0,
    "gn:timezone":"Europe/London",
    "iso:country":"GB",
    "name:ceb_x_preferred":[
        "Marton"
    ],
    "name:che_x_preferred":[
        "\u041c\u0430\u0440\u0442\u043e\u043d"
    ],
    "name:deu_x_preferred":[
        "Marton"
    ],
    "name:fas_x_preferred":[
        "\u0645\u0627\u0631\u062a\u0648\u0646"
    ],
    "name:fra_x_preferred":[
        "Marton"
    ],
    "name:hun_x_preferred":[
        "M\u00e1rton"
    ],
    "name:ita_x_preferred":[
        "Marton"
    ],
    "name:nld_x_preferred":[
        "Marton"
    ],
    "name:pol_x_preferred":[
        "Marton"
    ],
    "name:rus_x_preferred":[
        "\u041c\u0430\u0440\u0442\u043e\u043d"
    ],
    "name:slk_x_preferred":[
        "Marton"
    ],
    "name:swe_x_preferred":[
        "Marton"
    ],
    "name:ukr_x_preferred":[
        "\u041c\u0430\u0440\u0442\u043e\u043d"
    ],
    "wof:name":"Marton",
    "wof:placetype":"neighbourhood"
},
  "geometry": {"coordinates":[-3.05,52.61666999999999],"type":"Point"}
}