{
  "type": "Feature",
  "properties": {
    "iso:country": "GB",
    "name:eng_x_preferred": [
      "Church Coppenhall"
    ],
    "qs:gn_adm0_cc": "GB",
    "qs:gn_fcode": "PPL",
    "qs:gn_local": 2652002,
    "qs:gn_nam_loc": "crewe",
    "qs:gn_namadm1": "ENG",
    "qs:gn_name": "Church Coppenhall",
    "qs:local_max": 2415,
    "qs:local_sum": 2415,
    "qs:localhoods": 1,
    "qs:name": "Church Coppenhall",
    "qs:name_adm0": "United Kingdom",
    "qs:name_adm1": "England",
    "qs:name_adm2": "Cheshire",
    "qs:name_lau": "Crewe and Nantwich Borough",
    "qs:name_local": "Crewe",
    "qs:photo_max": 320,
    "qs:photo_sum": 2415,
    "qs:placetype": "Suburb",
    "qs:quad_count": 113,
    "qs:woe_adm0": 23424975,
    "qs:woe_adm1": 24554868,
    "qs:woe_adm2": 12602157,
    "qs:woe_lau": 12695889,
    "qs:woe_local": 17293,
    "qs:woe_ver": "7.10.0",
    "wof:lang": [
      "eng"
    ],
    "wof:name": "Church Coppenhall",
    "wof:placetype": "neighbourhood"
  },
  "geometry": {"coordinates":[-2.453912,53.102494],"type":"Point"}
}
