{
  "type": "Feature",
  "properties": {
    "gn:admin1_code":"SCT",
    "gn:admin2_code":"W3",
    "gn:asciiname":"Burravoe",
    "gn:country":"GB",
    "gn:country_code":"GB",
    "gn:dem":-9999,
    "gn:fcode":"PPL",
    "gn:feature_class":"P",
    "gn:feature_code":"PPL",
    "gn:name":"Burravoe",
    "gn:population":0,
    "gn:timezone":"Europe/London",
    "iso:country":"GB",
    "name:eng_x_preferred":[
        "Burravoe"
    ],
    "name:eus_x_preferred":[
        "Burravoe"
    ],
    "name:fao_x_preferred":[
        "Burravoe"
    ],
    "name:fra_x_preferred":[
        "Burravoe"
    ],
    "name:hun_x_preferred":[
        "Burravoe"
    ],
    "name:nld_x_preferred":[
        "Burravoe"
    ],
    "name:rus_x_preferred":[
        "\u0411\u0430\u0440\u0440\u0430\u0432\u043e"
    ],
    "name:sco_x_preferred":[
        "Burravoe"
    ],
    "qs_pg:aaroncc":"GB",
    "qs_pg:gn_country":"GB",
    "qs_pg:gn_fcode":"PPL",
    "qs_pg:gn_pop":0,
    "qs_pg:name":"Burravoe",
    "qs_pg:name_adm0":"United Kingdom",
    "qs_pg:name_adm1":"Scotland",
    "qs_pg:photos":37,
    "qs_pg:photos_1k":7,
    "qs_pg:photos_9k":1,
    "qs_pg:photos_9r":2,
    "qs_pg:photos_all":37,
    "qs_pg:photos_sr":2,
    "qs_pg:pop_sr":0,
    "qs_pg:qs_pg_placetype":"locality",
    "qs_pg:qs_pg_placetype_gp":"Town",
    "qs_pg:woe_adm0":23424975,
    "woe:adm0_id":23424975,
    "woe:name_adm0":"United Kingdom",
    "woe:name_adm1":"Scotland",
    "woe:placetype":"Town",
    "wof:name":"Burravoe",
    "wof:placetype":"locality"
},
  "geometry": {"coordinates":[-1.05,60.5],"type":"Point"}
}