{
  "type": "Feature",
  "properties": {
    "gn:country":"GB",
    "gn:fcode":"PPL",
    "gn:population":32176,
    "iso:country":"GB",
    "name:cat_x_preferred":[
        "Borehamwood"
    ],
    "name:ceb_x_preferred":[
        "Borehamwood"
    ],
    "name:cym_x_preferred":[
        "Borehamwood"
    ],
    "name:deu_x_preferred":[
        "Borehamwood"
    ],
    "name:eng_x_preferred":[
        "Borehamwood"
    ],
    "name:fas_x_preferred":[
        "\u0628\u0648\u0631\u0647\u0627\u0645\u200c\u0648\u0648\u062f"
    ],
    "name:fra_x_preferred":[
        "Borehamwood"
    ],
    "name:gle_x_preferred":[
        "Borehamwood"
    ],
    "name:ita_x_preferred":[
        "Borehamwood"
    ],
    "name:jpn_x_preferred":[
        "\u30dc\u30a2\u30cf\u30e0\u30a6\u30c3\u30c9"
    ],
    "name:nld_x_preferred":[
        "Borehamwood"
    ],
    "name:nno_x_preferred":[
        "Borehamwood"
    ],
    "name:oci_x_preferred":[
        "Borehamwood"
    ],
    "name:pol_x_preferred":[
        "Borehamwood"
    ],
    "name:por_x_preferred":[
        "Borehamwood"
    ],
    "name:ron_x_preferred":[
        "Borehamwood"
    ],
    "name:spa_x_preferred":[
        "Borehamwood"
    ],
    "name:swe_x_preferred":[
        "Borehamwood"
    ],
    "name:vol_x_preferred":[
        "Borehamwood"
    ],
    "name:zho_x_preferred":[
        "\u535a\u52d2\u59c6\u4f0d\u5fb7"
    ],
    "qs_pg:aaroncc":"GB",
    "qs_pg:gn_country":"GB",
    "qs_pg:gn_fcode":"PPL",
    "qs_pg:gn_pop":32176,
    "qs_pg:name":"Borehamwood",
    "qs_pg:name_adm0":"United Kingdom",
    "qs_pg:name_adm1":"England",
    "qs_pg:photos":1757,
    "qs_pg:photos_1k":356,
    "qs_pg:photos_9k":8,
    "qs_pg:photos_9r":8,
    "qs_pg:photos_all":1757,
    "qs_pg:photos_sr":14,
    "qs_pg:pop_sr":7,
    "qs_pg:qs_pg_placetype":"locality",
    "qs_pg:qs_pg_placetype_gp":"Town",
    "qs_pg:woe_adm0":23424975,
    "woe:adm0_id":23424975,
    "woe:name_adm0":"United Kingdom",
    "woe:name_adm1":"England",
    "woe:placetype":"Town",
    "wof:name":"Borehamwood",
    "wof:placetype":"neighbourhood",
    "wof:population":32176
},
  "geometry": {"coordinates":[-0.27762,51.65468],"type":"Point"}
}