{
  "type": "Feature",
  "properties": {
    "gn:population":3024,
    "iso:country":"GB",
    "name:eng_x_preferred":[
        "Ditton Hill"
    ],
    "qs:gn_fcode":"PPLX",
    "qs:gn_local":0,
    "qs:gn_namadm1":"ENG",
    "qs:gn_name":"Ditton Hill",
    "qs:local_max":888,
    "qs:local_sum":1035,
    "qs:localhoods":2,
    "qs:name":"Ditton Hill",
    "qs:name_adm0":"United Kingdom",
    "qs:name_adm1":"England",
    "qs:name_adm2":"Surrey",
    "qs:name_lau":"Elmbridge Borough",
    "qs:name_local":"Elmbridge Borough",
    "qs:photo_max":77,
    "qs:photo_sum":147,
    "qs:placetype":"Suburb",
    "qs:quad_count":6,
    "qs:woe_adm0":23424975,
    "qs:woe_adm1":24554868,
    "qs:woe_adm2":12602176,
    "qs:woe_lau":12696087,
    "qs:woe_local":12696087,
    "qs:woe_ver":"7.10.0",
    "wof:lang":[
        "eng"
    ],
    "wof:name":"Ditton Hill",
    "wof:placetype":"neighbourhood",
    "wof:population":3024
},
  "geometry": {"coordinates":[-0.316763,51.380078],"type":"Point"}
}