{
  "type": "Feature",
  "properties": {
    "gn:gn_country":"GB",
    "gn:gn_fcode":"PPL",
    "gn:gn_pop":13572,
    "gn:population":13572,
    "iso:country":"GB",
    "name:eng_x_preferred":[
        "Kirk Sandall"
    ],
    "name:nld_x_preferred":[
        "Kirk Sandall"
    ],
    "name:pol_x_preferred":[
        "Kirk Sandall"
    ],
    "name:swe_x_preferred":[
        "Kirk Sandall"
    ],
    "qs_pg:aaroncc":"GB",
    "qs_pg:gn_country":"GB",
    "qs_pg:gn_fcode":"PPL",
    "qs_pg:gn_pop":13572,
    "qs_pg:name":"Old Kirk Sandall",
    "qs_pg:name_adm0":"United Kingdom",
    "qs_pg:name_adm1":"England",
    "qs_pg:photos_9k":1,
    "qs_pg:photos_9r":1,
    "qs_pg:photos_all":1,
    "qs_pg:photos_sr":0,
    "qs_pg:pop_sr":6,
    "qs_pg:qs_pg_placetype":"locality",
    "qs_pg:qs_pg_placetype_gp":"Town",
    "qs_pg:woe_adm0":23424975,
    "woe:adm0_id":23424975,
    "woe:name_adm0":"United Kingdom",
    "woe:name_adm1":"England",
    "woe:placetype":"Town",
    "wof:name":"Old Kirk Sandall",
    "wof:placetype":"neighbourhood",
    "wof:population":13572
},
  "geometry": {"coordinates":[-1.06876,53.56211],"type":"Point"}
}