{
  "type": "Feature",
  "properties": {
    "gn:population": 4939,
    "iso:country": "GB",
    "name:bar_x_preferred": [
      "Campbeltown"
    ],
    "name:bre_x_preferred": [
      "Ceann Loch Chille Chiarain"
    ],
    "name:cat_x_preferred": [
      "Campbeltown"
    ],
    "name:ceb_x_preferred": [
      "Campbeltown"
    ],
    "name:cym_x_preferred": [
      "Campbeltown"
    ],
    "name:dan_x_preferred": [
      "Campbeltown"
    ],
    "name:deu_x_preferred": [
      "Campbeltown"
    ],
    "name:eng_x_preferred": [
      "Campbeltown"
    ],
    "name:eus_x_preferred": [
      "Campbeltown"
    ],
    "name:fas_x_preferred": [
      "کمپبل‌تاون"
    ],
    "name:fra_x_preferred": [
      "Campbeltown"
    ],
    "name:gla_x_preferred": [
      "Ceann Loch Chille Chiarain"
    ],
    "name:gle_x_preferred": [
      "Ceann Loch Chille Chiaráin"
    ],
    "name:glv_x_preferred": [
      "Balley Keeill Charane"
    ],
    "name:hbs_x_preferred": [
      "Campbeltown"
    ],
    "name:hye_x_preferred": [
      "Քեմբելթաուն"
    ],
    "name:ita_x_preferred": [
      "Campbeltown"
    ],
    "name:jpn_x_preferred": [
      "キャンベルタウン"
    ],
    "name:kor_x_preferred": [
      "캠벨타운"
    ],
    "name:nld_x_preferred": [
      "Campbeltown"
    ],
    "name:nno_x_preferred": [
      "Campbeltown"
    ],
    "name:nob_x_preferred": [
      "Campbeltown"
    ],
    "name:nor_x_preferred": [
      "Campbeltown"
    ],
    "name:pol_x_preferred": [
      "Campbeltown"
    ],
    "name:por_x_preferred": [
      "Campbeltown"
    ],
    "name:rus_x_preferred": [
      "Кэмпбелтаун"
    ],
    "name:sco_x_preferred": [
      "Cammeltoun"
    ],
    "name:spa_x_preferred": [
      "Campbeltown"
    ],
    "name:swe_x_preferred": [
      "Campbeltown"
    ],
    "name:ukr_x_preferred": [
      "Кемпбелтаун"
    ],
    "name:urd_x_preferred": [
      "کیمبلٹن"
    ],
    "name:zho_x_preferred": [
      "坎貝爾城"
    ],
    "qs:a0": "United Kingdom",
    "qs:a1": "*Argyll and Bute",
    "qs:a1_lc": "GB11QD0000",
    "qs:a1r": "0Scotland",
    "qs:a1r_lc": "GB11000000",
    "qs:adm0": "United Kingdom",
    "qs:la_lc": "*",
    "qs:level": "locality",
    "qs:loc": "Campbeltown",
    "qs:loc_alt": "Campbeltown",
    "qs:pop": 0,
    "qs:type": "buffered point",
    "wd:wordcount": 1830,
    "wof:name": "Campbeltown",
    "wof:placetype": "locality",
    "wof:population": 4939
  },
  "geometry": {"coordinates":[-5.60668,55.424258],"type":"Point"}
}
