{
  "type": "Feature",
  "properties": {
    "gn:population": 4418,
    "iso:country": "GB",
    "name:ceb_x_preferred": [
      "Bridge of Weir"
    ],
    "name:ces_x_preferred": [
      "Bridge of Weir"
    ],
    "name:cym_x_preferred": [
      "Bridge of Weir"
    ],
    "name:eng_x_preferred": [
      "Bridge of Weir"
    ],
    "name:eus_x_preferred": [
      "Bridge of Weir"
    ],
    "name:fas_x_preferred": [
      "بریج آو ویر"
    ],
    "name:fra_x_preferred": [
      "Bridge of Weir"
    ],
    "name:gla_x_preferred": [
      "Bridge of Weir"
    ],
    "name:ita_x_preferred": [
      "Bridge of Weir"
    ],
    "name:nld_x_preferred": [
      "Bridge of Weir"
    ],
    "name:nno_x_preferred": [
      "Bridge of Weir"
    ],
    "name:nob_x_preferred": [
      "Bridge of Weir"
    ],
    "name:nor_x_preferred": [
      "Bridge of Weir"
    ],
    "name:rus_x_preferred": [
      "Бридж-оф-Вейр"
    ],
    "name:spa_x_preferred": [
      "Bridge of Weir"
    ],
    "name:swe_x_preferred": [
      "Bridge of Weir"
    ],
    "qs:a0": "United Kingdom",
    "qs:a1": "*Renfrewshire",
    "qs:a1_lc": "GB11RC0000",
    "qs:a1r": "0Scotland",
    "qs:a1r_lc": "GB11000000",
    "qs:adm0": "United Kingdom",
    "qs:la_lc": "*",
    "qs:level": "locality",
    "qs:loc": "Bridge of Weir",
    "qs:loc_alt": "Bridge of Weir",
    "qs:pop": 0,
    "qs:type": "buffered point",
    "wd:wordcount": 944,
    "wof:name": "Bridge of Weir",
    "wof:placetype": "locality",
    "wof:population": 4418
  },
  "geometry": {"coordinates":[-4.57354,55.856311],"type":"Point"}
}
