{
  "type": "Feature",
  "properties": {
    "gn:country":"GB",
    "gn:fcode":"PPL",
    "gn:population":0,
    "iso:country":"GB",
    "name:deu_x_preferred":[
        "Achiltibuie"
    ],
    "name:eng_x_preferred":[
        "Achiltibuie"
    ],
    "name:eus_x_preferred":[
        "Achiltibuie"
    ],
    "name:fra_x_preferred":[
        "Achiltibuie"
    ],
    "name:gla_x_preferred":[
        "Aichillidh Bhuidhe"
    ],
    "name:gle_x_preferred":[
        "Achd Ille Bhuidhe"
    ],
    "name:nld_x_preferred":[
        "Achiltibuie"
    ],
    "name:swe_x_preferred":[
        "Achiltibuie"
    ],
    "qs_pg:aaroncc":"GB",
    "qs_pg:gn_country":"GB",
    "qs_pg:gn_fcode":"PPL",
    "qs_pg:gn_pop":0,
    "qs_pg:name":"Achiltibuie",
    "qs_pg:name_adm0":"United Kingdom",
    "qs_pg:name_adm1":"Scotland",
    "qs_pg:photos":849,
    "qs_pg:photos_1k":172,
    "qs_pg:photos_9k":4,
    "qs_pg:photos_9r":6,
    "qs_pg:photos_all":849,
    "qs_pg:photos_sr":9,
    "qs_pg:pop_sr":0,
    "qs_pg:qs_pg_placetype":"locality",
    "qs_pg:qs_pg_placetype_gp":"Town",
    "qs_pg:woe_adm0":23424975,
    "woe:adm0_id":23424975,
    "woe:name_adm0":"United Kingdom",
    "woe:name_adm1":"Scotland",
    "woe:placetype":"Town",
    "wof:name":"Achiltibuie",
    "wof:placetype":"locality"
},
  "geometry": {"coordinates":[-5.3457,58.0216],"type":"Point"}
}