{
  "type": "Feature",
  "properties": {
    "iso:country": "GB",
    "name:azb_x_preferred": [
      "میلتون"
    ],
    "name:cat_x_preferred": [
      "Milton"
    ],
    "name:ceb_x_preferred": [
      "Milton"
    ],
    "name:deu_x_preferred": [
      "Milton"
    ],
    "name:est_x_preferred": [
      "Milton"
    ],
    "name:fas_x_preferred": [
      "میلتون"
    ],
    "name:fin_x_preferred": [
      "Milton"
    ],
    "name:fra_x_preferred": [
      "Milton"
    ],
    "name:heb_x_preferred": [
      "מילטון"
    ],
    "name:hun_x_preferred": [
      "Milton"
    ],
    "name:ita_x_preferred": [
      "Milton"
    ],
    "name:jpn_x_preferred": [
      "ミルトン"
    ],
    "name:nld_x_preferred": [
      "Milton"
    ],
    "name:pol_x_preferred": [
      "Milton"
    ],
    "name:por_x_preferred": [
      "Milton"
    ],
    "name:rus_x_preferred": [
      "Мильтон"
    ],
    "name:slk_x_preferred": [
      "Milton"
    ],
    "name:spa_x_preferred": [
      "Milton"
    ],
    "name:swe_x_preferred": [
      "Milton"
    ],
    "name:ukr_x_preferred": [
      "Мілтон"
    ],
    "name:urd_x_preferred": [
      "ملٹن"
    ],
    "name:vol_x_preferred": [
      "Milton"
    ],
    "name:zho_x_preferred": [
      "米尔顿"
    ],
    "qs_pg:aaroncc": "GB",
    "qs_pg:name": "Milton",
    "qs_pg:name_adm0": "United Kingdom",
    "qs_pg:name_adm1": "Wales",
    "qs_pg:photos": 26,
    "qs_pg:photos_1k": 5,
    "qs_pg:photos_9k": 1,
    "qs_pg:photos_9r": 2,
    "qs_pg:photos_all": 26,
    "qs_pg:photos_sr": 2,
    "qs_pg:pop_sr": 0,
    "qs_pg:qs_pg_placetype": "locality",
    "qs_pg:qs_pg_placetype_gp": "Town",
    "qs_pg:woe_adm0": 23424975,
    "woe:adm0_id": 23424975,
    "woe:name_adm0": "United Kingdom",
    "woe:name_adm1": "Wales",
    "woe:placetype": "Town",
    "wof:name": "Milton",
    "wof:placetype": "neighbourhood"
  },
  "geometry": {"coordinates":[-4.8577795,51.7029355],"type":"Point"}
}
