{
  "type": "Feature",
  "properties": {
    "iso:country":"GB",
    "name:azb_x_preferred":[
        "\u0645\u06cc\u0644\u062a\u0648\u0646"
    ],
    "name:cat_x_preferred":[
        "Milton"
    ],
    "name:ceb_x_preferred":[
        "Milton"
    ],
    "name:deu_x_preferred":[
        "Milton"
    ],
    "name:est_x_preferred":[
        "Milton"
    ],
    "name:fas_x_preferred":[
        "\u0645\u06cc\u0644\u062a\u0648\u0646"
    ],
    "name:fin_x_preferred":[
        "Milton"
    ],
    "name:fra_x_preferred":[
        "Milton"
    ],
    "name:heb_x_preferred":[
        "\u05de\u05d9\u05dc\u05d8\u05d5\u05df"
    ],
    "name:hun_x_preferred":[
        "Milton"
    ],
    "name:ita_x_preferred":[
        "Milton"
    ],
    "name:jpn_x_preferred":[
        "\u30df\u30eb\u30c8\u30f3"
    ],
    "name:nld_x_preferred":[
        "Milton"
    ],
    "name:pol_x_preferred":[
        "Milton"
    ],
    "name:por_x_preferred":[
        "Milton"
    ],
    "name:rus_x_preferred":[
        "\u041c\u0438\u043b\u044c\u0442\u043e\u043d"
    ],
    "name:slk_x_preferred":[
        "Milton"
    ],
    "name:spa_x_preferred":[
        "Milton"
    ],
    "name:swe_x_preferred":[
        "Milton"
    ],
    "name:ukr_x_preferred":[
        "\u041c\u0456\u043b\u0442\u043e\u043d"
    ],
    "name:urd_x_preferred":[
        "\u0645\u0644\u0679\u0646"
    ],
    "name:vol_x_preferred":[
        "Milton"
    ],
    "name:zho_x_preferred":[
        "\u7c73\u5c14\u987f"
    ],
    "qs_pg:aaroncc":"GB",
    "qs_pg:name":"Milton",
    "qs_pg:name_adm0":"United Kingdom",
    "qs_pg:name_adm1":"Wales",
    "qs_pg:photos":26,
    "qs_pg:photos_1k":5,
    "qs_pg:photos_9k":1,
    "qs_pg:photos_9r":2,
    "qs_pg:photos_all":26,
    "qs_pg:photos_sr":2,
    "qs_pg:pop_sr":0,
    "qs_pg:qs_pg_placetype":"locality",
    "qs_pg:qs_pg_placetype_gp":"Town",
    "qs_pg:woe_adm0":23424975,
    "woe:adm0_id":23424975,
    "woe:name_adm0":"United Kingdom",
    "woe:name_adm1":"Wales",
    "woe:placetype":"Town",
    "wof:name":"Milton",
    "wof:placetype":"neighbourhood"
},
  "geometry": {"coordinates":[-4.8577795,51.7029355],"type":"Point"}
}