{
  "type": "Feature",
  "properties": {
    "gn:admin1_code":"SCT",
    "gn:admin2_code":"V3",
    "gn:asciiname":"Achentoul",
    "gn:cc2":"GB",
    "gn:country_code":"GB",
    "gn:dem":159,
    "gn:feature_class":"P",
    "gn:feature_code":"PPL",
    "gn:name":"Achentoul",
    "gn:population":0,
    "gn:timezone":"Europe/London",
    "iso:country":"GB",
    "name:eus_x_preferred":[
        "Achentoul"
    ],
    "name:nld_x_preferred":[
        "Achentoul"
    ],
    "name:und_x_variant":[
        "Achintoul",
        "Auchintoul"
    ],
    "wof:name":"Achentoul",
    "wof:placetype":"locality"
},
  "geometry": {"coordinates":[-3.91667,58.26667],"type":"Point"}
}