{
  "type": "Feature",
  "properties": {
    "iso:country":"GB",
    "name:ceb_x_preferred":[
        "Victoria Park"
    ],
    "name:deu_x_preferred":[
        "Victoria Park"
    ],
    "name:fra_x_preferred":[
        "Parc Victoria"
    ],
    "name:ita_x_preferred":[
        "Victoria Park"
    ],
    "name:jpn_x_preferred":[
        "\u30f4\u30a3\u30af\u30c8\u30ea\u30a2\u30fb\u30d1\u30fc\u30af"
    ],
    "name:mlg_x_preferred":[
        "Victoria Park"
    ],
    "name:nld_x_preferred":[
        "Victoria Park"
    ],
    "name:nor_x_preferred":[
        "Victoria Park"
    ],
    "name:pol_x_preferred":[
        "Victoria Park"
    ],
    "name:swe_x_preferred":[
        "Victoria Park"
    ],
    "name:ukr_x_preferred":[
        "\u0412\u0456\u043a\u0442\u043e\u0440\u0456\u044f \u041f\u0430\u0440\u043a"
    ],
    "name:zho_x_preferred":[
        "\u7dad\u591a\u5229\u4e9e\u516c\u5712"
    ],
    "wd:wordcount":558,
    "wof:name":"Victoria Park",
    "wof:placetype":"neighbourhood"
},
  "geometry": {"coordinates":[-2.21744752292178,53.45737964624402],"type":"Point"}
}