{
  "type": "Feature",
  "properties": {
    "gn:country":"GB",
    "gn:fcode":"PPL",
    "gn:population":0,
    "iso:country":"GB",
    "name:eng_x_preferred":[
        "Craignure"
    ],
    "name:eus_x_preferred":[
        "Craignure"
    ],
    "name:fra_x_preferred":[
        "Craignure"
    ],
    "name:gla_x_preferred":[
        "Creag an Iubhar"
    ],
    "name:gle_x_preferred":[
        "Creag an Iubhair"
    ],
    "name:heb_x_preferred":[
        "\u05e7\u05e8\u05d9\u05d9\u05d2\u05e0\u05d5\u05e8"
    ],
    "name:ita_x_preferred":[
        "Craignure"
    ],
    "name:nld_x_preferred":[
        "Craignure"
    ],
    "name:swe_x_preferred":[
        "Craignure"
    ],
    "name:zho_x_preferred":[
        "\u514b\u96f7\u683c\u7ebd\u5c14"
    ],
    "qs_pg:aaroncc":"GB",
    "qs_pg:gn_country":"GB",
    "qs_pg:gn_fcode":"PPL",
    "qs_pg:gn_pop":0,
    "qs_pg:name":"Craignure",
    "qs_pg:name_adm0":"United Kingdom",
    "qs_pg:name_adm1":"Scotland",
    "qs_pg:photos":1298,
    "qs_pg:photos_1k":263,
    "qs_pg:photos_9k":6,
    "qs_pg:photos_9r":7,
    "qs_pg:photos_all":1298,
    "qs_pg:photos_sr":12,
    "qs_pg:pop_sr":0,
    "qs_pg:qs_pg_placetype":"locality",
    "qs_pg:qs_pg_placetype_gp":"Town",
    "qs_pg:woe_adm0":23424975,
    "woe:adm0_id":23424975,
    "woe:name_adm0":"United Kingdom",
    "woe:name_adm1":"Scotland",
    "woe:placetype":"Town",
    "wof:name":"Craignure",
    "wof:placetype":"locality"
},
  "geometry": {"coordinates":[-5.69924,56.46775],"type":"Point"}
}