{
  "type": "Feature",
  "properties": {
    "iso:country":"GB",
    "name:ces_x_preferred":[
        "Trigon"
    ],
    "name:dan_x_preferred":[
        "Trigon"
    ],
    "name:deu_x_preferred":[
        "Trigon"
    ],
    "name:fra_x_preferred":[
        "Trigon"
    ],
    "name:jpn_x_preferred":[
        "\u30c8\u30e9\u30a4\u30f3"
    ],
    "name:rus_x_preferred":[
        "\u0422\u0440\u0438\u0433\u043e\u043d"
    ],
    "qs_pg:aaroncc":"GB",
    "qs_pg:name":"Trigon",
    "qs_pg:name_adm0":"United Kingdom",
    "qs_pg:name_adm1":"England",
    "qs_pg:photos":98,
    "qs_pg:photos_1k":20,
    "qs_pg:photos_9k":1,
    "qs_pg:photos_9r":3,
    "qs_pg:photos_all":98,
    "qs_pg:photos_sr":3,
    "qs_pg:pop_sr":0,
    "qs_pg:qs_pg_placetype":"locality",
    "qs_pg:qs_pg_placetype_gp":"Town",
    "qs_pg:woe_adm0":23424975,
    "woe:adm0_id":23424975,
    "woe:name_adm0":"United Kingdom",
    "woe:name_adm1":"England",
    "woe:placetype":"Town",
    "wof:name":"Trigon",
    "wof:placetype":"neighbourhood"
},
  "geometry": {"coordinates":[-2.14405,50.720536],"type":"Point"}
}