{
  "type": "Feature",
  "properties": {
    "gn:country":"GB",
    "gn:fcode":"PPLA3",
    "gn:population":5074,
    "iso:country":"GB",
    "name:ast_x_preferred":[
        "Woburn Sands"
    ],
    "name:azb_x_preferred":[
        "\u0648\u0648\u0628\u0648\u0631\u0646 \u0633\u0646\u062f\u0632"
    ],
    "name:ceb_x_preferred":[
        "Woburn Sands"
    ],
    "name:cym_x_preferred":[
        "Woburn Sands"
    ],
    "name:eng_x_preferred":[
        "Woburn Sands"
    ],
    "name:fas_x_preferred":[
        "\u0648\u0648\u0628\u0648\u0631\u0646 \u0633\u0646\u062f\u0632"
    ],
    "name:fra_x_preferred":[
        "Woburn Sands"
    ],
    "name:gle_x_preferred":[
        "Woburn Sands"
    ],
    "name:ita_x_preferred":[
        "Woburn Sands"
    ],
    "name:lld_x_preferred":[
        "Woburn Sands"
    ],
    "name:nan_x_preferred":[
        "Woburn Sands"
    ],
    "name:nld_x_preferred":[
        "Woburn Sands"
    ],
    "name:nob_x_preferred":[
        "Woburn Sands"
    ],
    "name:pol_x_preferred":[
        "Woburn Sands"
    ],
    "name:spa_x_preferred":[
        "Woburn Sands"
    ],
    "name:swe_x_preferred":[
        "Woburn Sands"
    ],
    "qs_pg:aaroncc":"GB",
    "qs_pg:gn_country":"GB",
    "qs_pg:gn_fcode":"PPLA3",
    "qs_pg:gn_pop":5074,
    "qs_pg:name":"Woburn Sands",
    "qs_pg:photos_9r":0,
    "qs_pg:photos_sr":0,
    "qs_pg:pop_sr":5,
    "qs_pg:qs_pg_placetype":"locality",
    "wof:name":"Woburn Sands",
    "wof:placetype":"neighbourhood",
    "wof:population":5074
},
  "geometry": {"coordinates":[-0.64982,52.01579],"type":"Point"}
}