{
  "type": "Feature",
  "properties": {
    "gn:country": "GB",
    "gn:fcode": "PPL",
    "gn:population": 0,
    "iso:country": "GB",
    "name:bul_x_preferred": [
      "Батхфорд"
    ],
    "name:ceb_x_preferred": [
      "Bathford"
    ],
    "name:deu_x_preferred": [
      "Bathford"
    ],
    "name:eng_x_preferred": [
      "Bathford"
    ],
    "name:fas_x_preferred": [
      "بتفور"
    ],
    "name:fra_x_preferred": [
      "Bathford"
    ],
    "name:ita_x_preferred": [
      "Bathford"
    ],
    "name:nld_x_preferred": [
      "Bathford"
    ],
    "name:pol_x_preferred": [
      "Bathford"
    ],
    "name:swe_x_preferred": [
      "Bathford"
    ],
    "qs_pg:aaroncc": "GB",
    "qs_pg:gn_country": "GB",
    "qs_pg:gn_fcode": "PPL",
    "qs_pg:gn_pop": 0,
    "qs_pg:name": "Batsford",
    "qs_pg:name_adm0": "United Kingdom",
    "qs_pg:name_adm1": "England",
    "qs_pg:photos": 506,
    "qs_pg:photos_1k": 103,
    "qs_pg:photos_9k": 2,
    "qs_pg:photos_9r": 5,
    "qs_pg:photos_all": 506,
    "qs_pg:photos_sr": 7,
    "qs_pg:pop_sr": 0,
    "qs_pg:qs_pg_placetype": "locality",
    "qs_pg:qs_pg_placetype_gp": "Town",
    "qs_pg:woe_adm0": 23424975,
    "woe:adm0_id": 23424975,
    "woe:name_adm0": "United Kingdom",
    "woe:name_adm1": "England",
    "woe:placetype": "Town",
    "wof:name": "Batsford",
    "wof:placetype": "neighbourhood"
  },
  "geometry": {"coordinates":[-2.30161,51.4002],"type":"Point"}
}
