{
  "type": "Feature",
  "properties": {
    "gn:gn_country":"GB",
    "gn:gn_fcode":"PPL",
    "gn:gn_pop":2132,
    "gn:population":2094,
    "iso:country":"GB",
    "name:ara_x_preferred":[
        "\u0643\u064a\u0646\u062a\u0628\u0648\u0631\u064a"
    ],
    "name:azb_x_preferred":[
        "\u06a9\u06cc\u0646\u062a\u200c\u0628\u0648\u0631\u06cc"
    ],
    "name:ceb_x_preferred":[
        "Kintbury"
    ],
    "name:cym_x_preferred":[
        "Kintbury"
    ],
    "name:eng_x_preferred":[
        "Kintbury"
    ],
    "name:fas_x_preferred":[
        "\u06a9\u06cc\u0646\u062a\u200c\u0628\u0648\u0631\u06cc"
    ],
    "name:fra_x_preferred":[
        "Kintbury"
    ],
    "name:ita_x_preferred":[
        "Kintbury"
    ],
    "name:lat_x_preferred":[
        "Kintbury"
    ],
    "name:nld_x_preferred":[
        "Kintbury"
    ],
    "name:pol_x_preferred":[
        "Kintbury"
    ],
    "name:spa_x_preferred":[
        "Kintbury"
    ],
    "name:swe_x_preferred":[
        "Kintbury "
    ],
    "name:swe_x_variant":[
        "Kintbury"
    ],
    "qs_pg:aaroncc":"GB",
    "qs_pg:gn_country":"GB",
    "qs_pg:gn_fcode":"PPL",
    "qs_pg:gn_pop":2132,
    "qs_pg:name":"Saintbury",
    "qs_pg:name_adm0":"United Kingdom",
    "qs_pg:name_adm1":"England",
    "qs_pg:photos":19,
    "qs_pg:photos_1k":4,
    "qs_pg:photos_9k":1,
    "qs_pg:photos_9r":1,
    "qs_pg:photos_all":19,
    "qs_pg:photos_sr":1,
    "qs_pg:pop_sr":4,
    "qs_pg:qs_pg_placetype":"locality",
    "qs_pg:qs_pg_placetype_gp":"Town",
    "qs_pg:woe_adm0":23424975,
    "woe:adm0_id":23424975,
    "woe:name_adm0":"United Kingdom",
    "woe:name_adm1":"England",
    "woe:placetype":"Town",
    "wof:name":"Saintbury",
    "wof:placetype":"neighbourhood",
    "wof:population":2094
},
  "geometry": {"coordinates":[-1.44865,51.39958],"type":"Point"}
}