{
  "type": "Feature",
  "properties": {
    "gn:gn_country":"GB",
    "gn:gn_fcode":"PPL",
    "gn:gn_pop":202,
    "gn:population":202,
    "iso:country":"GB",
    "name:bul_x_preferred":[
        "\u0427\u0440\u0438\u0441\u0442\u043e\u043d"
    ],
    "name:eng_x_preferred":[
        "Christon"
    ],
    "name:pol_x_preferred":[
        "Christon"
    ],
    "name:swe_x_preferred":[
        "Christon"
    ],
    "qs_pg:aaroncc":"GB",
    "qs_pg:gn_country":"GB",
    "qs_pg:gn_fcode":"PPL",
    "qs_pg:gn_pop":202,
    "qs_pg:name":"Christon",
    "qs_pg:name_adm0":"United Kingdom",
    "qs_pg:name_adm1":"England",
    "qs_pg:photos":44,
    "qs_pg:photos_1k":9,
    "qs_pg:photos_9k":1,
    "qs_pg:photos_9r":2,
    "qs_pg:photos_all":44,
    "qs_pg:photos_sr":2,
    "qs_pg:pop_sr":2,
    "qs_pg:qs_pg_placetype":"locality",
    "qs_pg:qs_pg_placetype_gp":"Town",
    "qs_pg:woe_adm0":23424975,
    "woe:adm0_id":23424975,
    "woe:name_adm0":"United Kingdom",
    "woe:name_adm1":"England",
    "woe:placetype":"Town",
    "wof:name":"Christon",
    "wof:placetype":"neighbourhood",
    "wof:population":202
},
  "geometry": {"coordinates":[-2.894,51.31088],"type":"Point"}
}