{
  "type": "Feature",
  "properties": {
    "gn:admin1_code":"ENG",
    "gn:admin2_code":"M5",
    "gn:admin3_code":"22UL",
    "gn:asciiname":"Prittlewell",
    "gn:country_code":"GB",
    "gn:dem":19,
    "gn:feature_class":"P",
    "gn:feature_code":"PPL",
    "gn:name":"Prittlewell",
    "gn:population":0,
    "gn:timezone":"Europe/London",
    "iso:country":"GB",
    "wof:name":"Prittlewell",
    "wof:placetype":"neighbourhood"
},
  "geometry": {"coordinates":[0.70299,51.55073],"type":"Point"}
}