{
  "type": "Feature",
  "properties": {
    "gn:admin1_code":"ENG",
    "gn:admin2_code":"M5",
    "gn:admin3_code":"22UL",
    "gn:asciiname":"Prittlewell",
    "gn:country_code":"GB",
    "gn:dem":19,
    "gn:feature_class":"P",
    "gn:feature_code":"PPL",
    "gn:name":"Prittlewell",
    "gn:population":0,
    "gn:timezone":"Europe/London",
    "iso:country":"GB",
    "name:fas_x_preferred":[
        "\u067e\u0631\u06cc\u062a\u0644\u0648\u0644"
    ],
    "name:fra_x_preferred":[
        "Prittlewell"
    ],
    "name:gle_x_preferred":[
        "Prittlewell"
    ],
    "name:ita_x_preferred":[
        "Prittlewell"
    ],
    "name:nld_x_preferred":[
        "Prittlewell"
    ],
    "name:pol_x_preferred":[
        "Prittlewell"
    ],
    "name:por_x_preferred":[
        "Prittlewell"
    ],
    "wof:name":"Prittlewell",
    "wof:placetype":"neighbourhood"
},
  "geometry": {"coordinates":[0.70299,51.55073],"type":"Point"}
}