{
  "type": "Feature",
  "properties": {
    "iso:country": "GB",
    "name:azb_x_preferred": [
      "تورنتن"
    ],
    "name:bel_x_preferred": [
      "Торнтан"
    ],
    "name:cat_x_preferred": [
      "Thornton"
    ],
    "name:ceb_x_preferred": [
      "Thornton"
    ],
    "name:ces_x_preferred": [
      "Thornton"
    ],
    "name:deu_x_preferred": [
      "Thornton"
    ],
    "name:eng_x_preferred": [
      "Thornton"
    ],
    "name:fas_x_preferred": [
      "تورنتن"
    ],
    "name:fin_x_preferred": [
      "Thornton"
    ],
    "name:fra_x_preferred": [
      "Thornton"
    ],
    "name:fry_x_preferred": [
      "Thornton"
    ],
    "name:heb_x_preferred": [
      "תורנתון"
    ],
    "name:hye_x_preferred": [
      "Տորնտոն"
    ],
    "name:ita_x_preferred": [
      "Thornton"
    ],
    "name:jpn_x_preferred": [
      "ソーントン"
    ],
    "name:kat_x_preferred": [
      "თორნტონი"
    ],
    "name:lim_x_preferred": [
      "Thornton"
    ],
    "name:nld_x_preferred": [
      "Thornton"
    ],
    "name:pol_x_preferred": [
      "Thornton"
    ],
    "name:por_x_preferred": [
      "Thornton"
    ],
    "name:rus_x_preferred": [
      "Торнтон"
    ],
    "name:slv_x_preferred": [
      "Thornton"
    ],
    "name:spa_x_preferred": [
      "Thornton"
    ],
    "name:swe_x_preferred": [
      "Thornton"
    ],
    "qs:gn_adm0_cc": "GB",
    "qs:gn_fcode": "PPL",
    "qs:gn_local": 2654993,
    "qs:gn_nam_loc": "Bradford",
    "qs:gn_namadm1": "ENG",
    "qs:gn_name": "Thornton",
    "qs:local_max": 4399,
    "qs:local_sum": 22210,
    "qs:localhoods": 31,
    "qs:name": "Thornton",
    "qs:name_adm0": "United Kingdom",
    "qs:name_adm1": "England",
    "qs:name_adm2": "West Yorkshire",
    "qs:name_lau": "Bradford City of",
    "qs:name_local": "Bradford",
    "qs:photo_max": 56,
    "qs:photo_sum": 510,
    "qs:placetype": "Suburb",
    "qs:quad_count": 71,
    "qs:woe_adm0": 23424975,
    "qs:woe_adm1": 24554868,
    "qs:woe_adm2": 12602197,
    "qs:woe_lau": 12695870,
    "qs:woe_local": 13527,
    "qs:woe_ver": "7.10.0",
    "wof:lang": [
      "eng"
    ],
    "wof:name": "Thornton",
    "wof:placetype": "neighbourhood"
  },
  "geometry": {"coordinates":[-1.849602,53.791393],"type":"Point"}
}
