{
  "type": "Feature",
  "properties": {
    "iso:country":"GB",
    "name:azb_x_preferred":[
        "\u062a\u0648\u0631\u0646\u062a\u0646"
    ],
    "name:bel_x_preferred":[
        "\u0422\u043e\u0440\u043d\u0442\u0430\u043d"
    ],
    "name:cat_x_preferred":[
        "Thornton"
    ],
    "name:ceb_x_preferred":[
        "Thornton"
    ],
    "name:ces_x_preferred":[
        "Thornton"
    ],
    "name:deu_x_preferred":[
        "Thornton"
    ],
    "name:eng_x_preferred":[
        "Thornton"
    ],
    "name:fas_x_preferred":[
        "\u062a\u0648\u0631\u0646\u062a\u0646"
    ],
    "name:fin_x_preferred":[
        "Thornton"
    ],
    "name:fra_x_preferred":[
        "Thornton"
    ],
    "name:fry_x_preferred":[
        "Thornton"
    ],
    "name:heb_x_preferred":[
        "\u05ea\u05d5\u05e8\u05e0\u05ea\u05d5\u05df"
    ],
    "name:hye_x_preferred":[
        "\u054f\u0578\u0580\u0576\u057f\u0578\u0576"
    ],
    "name:ita_x_preferred":[
        "Thornton"
    ],
    "name:jpn_x_preferred":[
        "\u30bd\u30fc\u30f3\u30c8\u30f3"
    ],
    "name:kat_x_preferred":[
        "\u10d7\u10dd\u10e0\u10dc\u10e2\u10dd\u10dc\u10d8"
    ],
    "name:lim_x_preferred":[
        "Thornton"
    ],
    "name:nld_x_preferred":[
        "Thornton"
    ],
    "name:pol_x_preferred":[
        "Thornton"
    ],
    "name:por_x_preferred":[
        "Thornton"
    ],
    "name:rus_x_preferred":[
        "\u0422\u043e\u0440\u043d\u0442\u043e\u043d"
    ],
    "name:slv_x_preferred":[
        "Thornton"
    ],
    "name:spa_x_preferred":[
        "Thornton"
    ],
    "name:swe_x_preferred":[
        "Thornton"
    ],
    "name:unk_x_variant":[
        "Thornton"
    ],
    "qs:gn_adm0_cc":"GB",
    "qs:gn_fcode":"PPL",
    "qs:gn_local":2654993,
    "qs:gn_nam_loc":"Bradford",
    "qs:gn_namadm1":"ENG",
    "qs:gn_name":"Thornton",
    "qs:local_max":4399,
    "qs:local_sum":22210,
    "qs:localhoods":31,
    "qs:name":"Thornton",
    "qs:name_adm0":"United Kingdom",
    "qs:name_adm1":"England",
    "qs:name_adm2":"West Yorkshire",
    "qs:name_lau":"Bradford City of",
    "qs:name_local":"Bradford",
    "qs:photo_max":56,
    "qs:photo_sum":510,
    "qs:placetype":"Suburb",
    "qs:quad_count":71,
    "qs:woe_adm0":23424975,
    "qs:woe_adm1":24554868,
    "qs:woe_adm2":12602197,
    "qs:woe_lau":12695870,
    "qs:woe_local":13527,
    "qs:woe_ver":"7.10.0",
    "wof:lang":[
        "eng"
    ],
    "wof:name":"Thornton",
    "wof:placetype":"neighbourhood"
},
  "geometry": {"coordinates":[-1.849602,53.791393],"type":"Point"}
}