{
  "type": "Feature",
  "properties": {
    "gn:country":"GB",
    "gn:fcode":"PPL",
    "gn:population":0,
    "iso:country":"GB",
    "name:azb_x_preferred":[
        "\u0628\u0627\u06cc\u0641\u0644\u06cc\u062a"
    ],
    "name:cat_x_preferred":[
        "Byfleet"
    ],
    "name:ceb_x_preferred":[
        "Byfleet"
    ],
    "name:cym_x_preferred":[
        "Byfleet"
    ],
    "name:deu_x_preferred":[
        "Byfleet"
    ],
    "name:eng_x_preferred":[
        "Byfleet"
    ],
    "name:fas_x_preferred":[
        "\u0628\u0627\u06cc\u0641\u0644\u06cc\u062a"
    ],
    "name:fra_x_preferred":[
        "Byfleet"
    ],
    "name:gle_x_preferred":[
        "Byfleet"
    ],
    "name:ita_x_preferred":[
        "Byfleet"
    ],
    "name:jpn_x_preferred":[
        "\u30d0\u30a4\u30d5\u30ea\u30fc\u30c8"
    ],
    "name:lld_x_preferred":[
        "Byfleet"
    ],
    "name:nan_x_preferred":[
        "Byfleet"
    ],
    "name:nld_x_preferred":[
        "Byfleet"
    ],
    "name:pol_x_preferred":[
        "Byfleet"
    ],
    "name:pol_x_variant":[
        "Elterwater"
    ],
    "name:ron_x_preferred":[
        "Byfleet"
    ],
    "name:spa_x_preferred":[
        "Byfleet"
    ],
    "name:swe_x_preferred":[
        "Byfleet"
    ],
    "name:szl_x_preferred":[
        "Byfleet"
    ],
    "name:urd_x_preferred":[
        "\u0628\u0627\u0626\u06cc\u0641\u0644\u06cc\u0679"
    ],
    "name:zho_x_preferred":[
        "\u62dc\u592b\u5229\u7279"
    ],
    "qs_pg:aaroncc":"GB",
    "qs_pg:gn_country":"GB",
    "qs_pg:gn_fcode":"PPL",
    "qs_pg:gn_pop":0,
    "qs_pg:name":"Byfleet",
    "qs_pg:name_adm0":"United Kingdom",
    "qs_pg:name_adm1":"England",
    "qs_pg:photos":1616,
    "qs_pg:photos_1k":327,
    "qs_pg:photos_9k":7,
    "qs_pg:photos_9r":8,
    "qs_pg:photos_all":1616,
    "qs_pg:photos_sr":13,
    "qs_pg:pop_sr":0,
    "qs_pg:qs_pg_placetype":"locality",
    "qs_pg:qs_pg_placetype_gp":"Town",
    "qs_pg:woe_adm0":23424975,
    "woe:adm0_id":23424975,
    "woe:name_adm0":"United Kingdom",
    "woe:name_adm1":"England",
    "woe:placetype":"Town",
    "wof:name":"Byfleet",
    "wof:placetype":"neighbourhood"
},
  "geometry": {"coordinates":[-0.47396,51.33884],"type":"Point"}
}