{
  "type": "Feature",
  "properties": {
    "gn:admin1_code": "ENG",
    "gn:admin2_code": "O7",
    "gn:admin3_code": "00DB020",
    "gn:asciiname": "Moorthorpe",
    "gn:country_code": "GB",
    "gn:dem": 43,
    "gn:feature_class": "P",
    "gn:feature_code": "PPL",
    "gn:name": "Moorthorpe",
    "gn:population": 0,
    "gn:timezone": "Europe/London",
    "iso:country": "GB",
    "name:pol_x_preferred": [
      "Moorthorpe"
    ],
    "wof:name": "Moorthorpe",
    "wof:placetype": "neighbourhood"
  },
  "geometry": {"coordinates":[-1.29948,53.58761],"type":"Point"}
}
