{
  "type": "Feature",
  "properties": {
    "gn:admin1_code": "SCT",
    "gn:admin2_code": "W3",
    "gn:asciiname": "Ham",
    "gn:country_code": "GB",
    "gn:dem": 77,
    "gn:feature_class": "P",
    "gn:feature_code": "PPLL",
    "gn:name": "Ham",
    "gn:population": 0,
    "gn:timezone": "Europe/London",
    "iso:country": "GB",
    "name:ara_x_preferred": [
      "هام"
    ],
    "name:arg_x_preferred": [
      "Pernil"
    ],
    "name:ast_x_preferred": [
      "Xamón"
    ],
    "name:aze_x_preferred": [
      "Vetçina"
    ],
    "name:bel_x_preferred": [
      "Вяндліна"
    ],
    "name:bos_x_preferred": [
      "Šunka"
    ],
    "name:bul_x_preferred": [
      "Шунка"
    ],
    "name:cat_x_preferred": [
      "Pernil"
    ],
    "name:ces_x_preferred": [
      "Šunka"
    ],
    "name:dan_x_preferred": [
      "Skinke"
    ],
    "name:deu_x_preferred": [
      "Schinken"
    ],
    "name:eml_x_preferred": [
      "Parsótt"
    ],
    "name:epo_x_preferred": [
      "Ŝinko"
    ],
    "name:eus_x_preferred": [
      "Urdaiazpiko"
    ],
    "name:fas_x_preferred": [
      "ژامبون"
    ],
    "name:fin_x_preferred": [
      "Kinkku"
    ],
    "name:fra_x_preferred": [
      "Jambon"
    ],
    "name:gle_x_preferred": [
      "Liamhás"
    ],
    "name:glg_x_preferred": [
      "Xamón"
    ],
    "name:grn_x_preferred": [
      "Kuvãju"
    ],
    "name:hak_x_preferred": [
      "Hâ-mu"
    ],
    "name:heb_x_preferred": [
      "שינקן"
    ],
    "name:hrv_x_preferred": [
      "Šunka"
    ],
    "name:hun_x_preferred": [
      "Sonka"
    ],
    "name:hye_x_preferred": [
      "Ազդրապուխտ"
    ],
    "name:ido_x_preferred": [
      "Shinko"
    ],
    "name:ind_x_preferred": [
      "Ham"
    ],
    "name:isl_x_preferred": [
      "Skinka"
    ],
    "name:ita_x_preferred": [
      "Prosciutto"
    ],
    "name:jav_x_preferred": [
      "Ham"
    ],
    "name:kan_x_preferred": [
      "ಹ್ಯಾಮ್"
    ],
    "name:kur_x_preferred": [
      "Jambon"
    ],
    "name:lav_x_preferred": [
      "Šķiņķis"
    ],
    "name:lim_x_preferred": [
      "Sjink"
    ],
    "name:lmo_x_preferred": [
      "Giambon"
    ],
    "name:ltz_x_preferred": [
      "Ham"
    ],
    "name:mkd_x_preferred": [
      "Шунка"
    ],
    "name:msa_x_preferred": [
      "Ham"
    ],
    "name:nap_x_preferred": [
      "Presutto"
    ],
    "name:nld_x_preferred": [
      "Ham"
    ],
    "name:nno_x_preferred": [
      "Skinke"
    ],
    "name:nor_x_preferred": [
      "Skinke"
    ],
    "name:oci_x_preferred": [
      "Cambajon"
    ],
    "name:pol_x_preferred": [
      "Szynka"
    ],
    "name:por_x_preferred": [
      "Presunto"
    ],
    "name:ron_x_preferred": [
      "Jambon"
    ],
    "name:rus_x_preferred": [
      "Ветчина"
    ],
    "name:sco_x_preferred": [
      "Ham"
    ],
    "name:slk_x_preferred": [
      "Šunka"
    ],
    "name:slv_x_preferred": [
      "Šunka"
    ],
    "name:spa_x_preferred": [
      "Jamón"
    ],
    "name:srp_x_preferred": [
      "Шунка"
    ],
    "name:swe_x_preferred": [
      "Skinka"
    ],
    "name:tgl_x_preferred": [
      "Hamon"
    ],
    "name:tha_x_preferred": [
      "แฮม"
    ],
    "name:tur_x_preferred": [
      "Jambon"
    ],
    "name:ukr_x_preferred": [
      "Шинка"
    ],
    "name:vie_x_preferred": [
      "Giăm bông"
    ],
    "name:yid_x_preferred": [
      "שינקען"
    ],
    "wof:name": "Ham",
    "wof:placetype": "locality"
  },
  "geometry": {"coordinates":[-1.114,60.13792],"type":"Point"}
}
