{
  "type": "Feature",
  "properties": {
    "gn:country":"GB",
    "gn:fcode":"PPL",
    "gn:population":0,
    "iso:country":"GB",
    "name:ara_x_preferred":[
        "\u0628\u0648\u0631\u063a"
    ],
    "name:deu_x_preferred":[
        "Borgue"
    ],
    "name:eng_x_preferred":[
        "Borgue"
    ],
    "name:eus_x_preferred":[
        "Borgue"
    ],
    "name:fra_x_preferred":[
        "Borgue"
    ],
    "name:gla_x_preferred":[
        "Borgh"
    ],
    "name:nld_x_preferred":[
        "Borgue"
    ],
    "qs_pg:aaroncc":"GB",
    "qs_pg:gn_country":"GB",
    "qs_pg:gn_fcode":"PPL",
    "qs_pg:gn_pop":0,
    "qs_pg:name":"Borgue",
    "qs_pg:name_adm0":"United Kingdom",
    "qs_pg:name_adm1":"Scotland",
    "qs_pg:photos":133,
    "qs_pg:photos_1k":27,
    "qs_pg:photos_9k":1,
    "qs_pg:photos_9r":3,
    "qs_pg:photos_all":133,
    "qs_pg:photos_sr":3,
    "qs_pg:pop_sr":0,
    "qs_pg:qs_pg_placetype":"locality",
    "qs_pg:qs_pg_placetype_gp":"Town",
    "qs_pg:woe_adm0":23424975,
    "woe:adm0_id":23424975,
    "woe:name_adm0":"United Kingdom",
    "woe:name_adm1":"Scotland",
    "woe:placetype":"Town",
    "wof:name":"Borgue",
    "wof:placetype":"locality"
},
  "geometry": {"coordinates":[-4.13414,54.8122],"type":"Point"}
}