{
  "type": "Feature",
  "properties": {
    "iso:country":"GB",
    "name:eng_x_preferred":[
        "Rushey Mead"
    ],
    "wof:name":"Rushey Mead",
    "wof:placetype":"neighbourhood"
},
  "geometry": {"coordinates":[-1.10560422961834,52.66465039830648],"type":"Point"}
}