{
  "type": "Feature",
  "properties": {
    "gn:admin1_code":"ENG",
    "gn:admin2_code":"D4",
    "gn:admin3_code":"18UE",
    "gn:admin4_code":"18UE011",
    "gn:asciiname":"Charles",
    "gn:country_code":"GB",
    "gn:dem":230,
    "gn:feature_class":"P",
    "gn:feature_code":"PPL",
    "gn:name":"Charles",
    "gn:population":0,
    "gn:timezone":"Europe/London",
    "iso:country":"GB",
    "name:pol_x_preferred":[
        "Charles"
    ],
    "wof:name":"Charles",
    "wof:placetype":"neighbourhood"
},
  "geometry": {"coordinates":[-3.8798,51.07907],"type":"Point"}
}