{
  "type": "Feature",
  "properties": {
    "iso:country":"GB",
    "name:eng_x_preferred":[
        "Woodhey"
    ],
    "name:unk_x_variant":[
        "Woodley",
        "Woodhey"
    ],
    "qs:gn_fcode":"PPL",
    "qs:gn_local":0,
    "qs:gn_namadm1":"ENG",
    "qs:gn_name":"Woodley",
    "qs:local_max":2891,
    "qs:local_sum":6453,
    "qs:localhoods":5,
    "qs:name":"Woodhey",
    "qs:name_adm0":"United Kingdom",
    "qs:name_adm1":"England",
    "qs:name_adm2":"Merseyside",
    "qs:name_lau":"Wirral Metropolitan Borough",
    "qs:name_local":"Wirral Metropolitan Borough",
    "qs:photo_max":52,
    "qs:photo_sum":286,
    "qs:placetype":"Suburb",
    "qs:quad_count":29,
    "qs:woe_adm0":23424975,
    "qs:woe_adm1":24554868,
    "qs:woe_adm2":12602161,
    "qs:woe_lau":12695853,
    "qs:woe_local":12695853,
    "qs:woe_ver":"7.10.0",
    "wof:lang":[
        "eng"
    ],
    "wof:name":"Woodhey",
    "wof:placetype":"neighbourhood"
},
  "geometry": {"coordinates":[-3.004034,53.368607],"type":"Point"}
}