{
  "type": "Feature",
  "properties": {
    "iso:country":"GB",
    "name:dan_x_preferred":[
        "Westend"
    ],
    "name:deu_x_preferred":[
        "Westend"
    ],
    "name:fin_x_preferred":[
        "Westend"
    ],
    "name:fra_x_preferred":[
        "Westend"
    ],
    "name:ita_x_preferred":[
        "Westend"
    ],
    "name:nld_x_preferred":[
        "Westend"
    ],
    "name:pol_x_preferred":[
        "Westend"
    ],
    "name:swe_x_preferred":[
        "Westend"
    ],
    "name:tur_x_preferred":[
        "Westend"
    ],
    "qs_pg:aaroncc":"GB",
    "qs_pg:name":"Westend",
    "qs_pg:name_adm0":"United Kingdom",
    "qs_pg:name_adm1":"England",
    "qs_pg:photos":82,
    "qs_pg:photos_1k":17,
    "qs_pg:photos_9k":1,
    "qs_pg:photos_9r":3,
    "qs_pg:photos_all":82,
    "qs_pg:photos_sr":3,
    "qs_pg:pop_sr":0,
    "qs_pg:qs_pg_placetype":"locality",
    "qs_pg:qs_pg_placetype_gp":"Town",
    "qs_pg:woe_adm0":23424975,
    "woe:adm0_id":23424975,
    "woe:name_adm0":"United Kingdom",
    "woe:name_adm1":"England",
    "woe:placetype":"Town",
    "wof:name":"Westend",
    "wof:placetype":"neighbourhood"
},
  "geometry": {"coordinates":[-2.331333,51.775063],"type":"Point"}
}