{
  "type": "Feature",
  "properties": {
    "gn:admin1_code":"ENG",
    "gn:admin2_code":"C9",
    "gn:admin3_code":"16UG",
    "gn:admin4_code":"16UG024",
    "gn:asciiname":"Kents Bank",
    "gn:country_code":"GB",
    "gn:dem":20,
    "gn:feature_class":"P",
    "gn:feature_code":"PPL",
    "gn:name":"Kents Bank",
    "gn:population":0,
    "gn:timezone":"Europe/London",
    "iso:country":"GB",
    "name:cym_x_preferred":[
        "Kents Bank"
    ],
    "name:pol_x_preferred":[
        "Kents Bank"
    ],
    "wof:name":"Kents Bank",
    "wof:placetype":"neighbourhood"
},
  "geometry": {"coordinates":[-2.92631,54.17343],"type":"Point"}
}