{
  "type": "Feature",
  "properties": {
    "iso:country":"GB",
    "name:eng_x_preferred":[
        "Withiel Florey"
    ],
    "name:pol_x_preferred":[
        "Withiel Florey"
    ],
    "qs_pg:aaroncc":"GB",
    "qs_pg:name":"Withiel Florey",
    "qs_pg:name_adm0":"United Kingdom",
    "qs_pg:name_adm1":"England",
    "qs_pg:photos":394,
    "qs_pg:photos_1k":80,
    "qs_pg:photos_9k":2,
    "qs_pg:photos_9r":5,
    "qs_pg:photos_all":394,
    "qs_pg:photos_sr":6,
    "qs_pg:pop_sr":0,
    "qs_pg:qs_pg_placetype":"locality",
    "qs_pg:qs_pg_placetype_gp":"Town",
    "qs_pg:woe_adm0":23424975,
    "woe:adm0_id":23424975,
    "woe:name_adm0":"United Kingdom",
    "woe:name_adm1":"England",
    "woe:placetype":"Town",
    "wof:name":"Withiel Florey",
    "wof:placetype":"neighbourhood"
},
  "geometry": {"coordinates":[-3.469448,51.067302],"type":"Point"}
}