{
  "type": "Feature",
  "properties": {
    "gn:country":"GB",
    "gn:fcode":"PPL",
    "gn:population":0,
    "iso:country":"GB",
    "name:eng_x_preferred":[
        "Brome"
    ],
    "name:fra_x_preferred":[
        "Brome"
    ],
    "name:ita_x_preferred":[
        "Brome"
    ],
    "name:nld_x_preferred":[
        "Brome"
    ],
    "name:pol_x_preferred":[
        "Brome"
    ],
    "name:pol_x_variant":[
        "Brome"
    ],
    "name:swe_x_preferred":[
        "Brome"
    ],
    "qs_pg:aaroncc":"GB",
    "qs_pg:gn_country":"GB",
    "qs_pg:gn_fcode":"PPL",
    "qs_pg:gn_pop":0,
    "qs_pg:name":"Brome",
    "qs_pg:name_adm0":"United Kingdom",
    "qs_pg:name_adm1":"England",
    "qs_pg:photos":165,
    "qs_pg:photos_1k":33,
    "qs_pg:photos_9k":1,
    "qs_pg:photos_9r":4,
    "qs_pg:photos_all":165,
    "qs_pg:photos_sr":4,
    "qs_pg:pop_sr":0,
    "qs_pg:qs_pg_placetype":"locality",
    "qs_pg:qs_pg_placetype_gp":"Town",
    "qs_pg:woe_adm0":23424975,
    "woe:adm0_id":23424975,
    "woe:name_adm0":"United Kingdom",
    "woe:name_adm1":"England",
    "woe:placetype":"Town",
    "wof:name":"Brome",
    "wof:placetype":"neighbourhood"
},
  "geometry": {"coordinates":[1.1338,52.34408],"type":"Point"}
}