{
  "type": "Feature",
  "properties": {
    "gn:country":"GB",
    "gn:fcode":"PPL",
    "gn:population":0,
    "iso:country":"GB",
    "name:ben_x_preferred":[
        "\u09b2\u09c0\u0995 \u0989\u099f\u09cd\u099f\u09a8"
    ],
    "name:deu_x_preferred":[
        "Leek Wootton"
    ],
    "name:eng_x_preferred":[
        "Leek Wootton"
    ],
    "name:fra_x_preferred":[
        "Leek Wootton"
    ],
    "name:gle_x_preferred":[
        "Leek Wootton"
    ],
    "name:guj_x_preferred":[
        "\u0ab2\u0abf\u0a95 \u0ab5\u0ac2\u0a9f\u0aa8"
    ],
    "name:jpn_x_preferred":[
        "\u30ea\u30fc\u30af\u30fb\u30a6\u30fc\u30c3\u30c8\u30f3"
    ],
    "name:kan_x_preferred":[
        "\u0cb2\u0cc0\u0c95\u0ccd \u0cb5\u0cc2\u0c9f\u0ca8\u0ccd"
    ],
    "name:kor_x_preferred":[
        "\ub9ac\ud06c \uc6b0\ud2bc"
    ],
    "name:lit_x_preferred":[
        "Lik Vutonas"
    ],
    "name:lld_x_preferred":[
        "Leek Wootton"
    ],
    "name:nld_x_preferred":[
        "Leek Wootton"
    ],
    "name:pol_x_preferred":[
        "Leek Wootton"
    ],
    "name:por_x_preferred":[
        "Leek Wootton"
    ],
    "name:rus_x_preferred":[
        "\u041b\u0438\u043a-\u0412\u0443\u0442\u0442\u043e\u043d"
    ],
    "name:spa_x_preferred":[
        "Leek Wootton"
    ],
    "name:swe_x_preferred":[
        "Leek Wootton"
    ],
    "name:tam_x_preferred":[
        "\u0bb2\u0bc0\u0b95\u0bcd\u0bb5\u0bc2\u0b9f\u0bcd\u0b9f\u0ba9\u0bcd"
    ],
    "name:tel_x_preferred":[
        "\u0c32\u0c40\u0c15\u0c4d \u0c0a\u0c1f\u0c28\u0c4d"
    ],
    "name:urd_x_preferred":[
        "\u0644\u06cc\u06a9\u00a0\u0648\u0648\u062a\u0679\u0646"
    ],
    "qs_pg:aaroncc":"GB",
    "qs_pg:gn_country":"GB",
    "qs_pg:gn_fcode":"PPL",
    "qs_pg:gn_pop":0,
    "qs_pg:name":"Leek Wootton",
    "qs_pg:name_adm0":"United Kingdom",
    "qs_pg:name_adm1":"England",
    "qs_pg:photos":72,
    "qs_pg:photos_1k":15,
    "qs_pg:photos_9k":1,
    "qs_pg:photos_9r":2,
    "qs_pg:photos_all":72,
    "qs_pg:photos_sr":2,
    "qs_pg:pop_sr":0,
    "qs_pg:qs_pg_placetype":"locality",
    "qs_pg:qs_pg_placetype_gp":"Town",
    "qs_pg:woe_adm0":23424975,
    "woe:adm0_id":23424975,
    "woe:name_adm0":"United Kingdom",
    "woe:name_adm1":"England",
    "woe:placetype":"Town",
    "wof:name":"Leek Wootton",
    "wof:placetype":"neighbourhood",
    "wof:population":1017
},
  "geometry": {"coordinates":[-1.5769,52.31845],"type":"Point"}
}