{
  "type": "Feature",
  "properties": {
    "gn:country": "GB",
    "gn:fcode": "PPL",
    "gn:population": 0,
    "iso:country": "GB",
    "name:ben_x_preferred": [
      "লীক উট্টন"
    ],
    "name:deu_x_preferred": [
      "Leek Wootton"
    ],
    "name:eng_x_preferred": [
      "Leek Wootton"
    ],
    "name:fra_x_preferred": [
      "Leek Wootton"
    ],
    "name:guj_x_preferred": [
      "લિક વૂટન"
    ],
    "name:jpn_x_preferred": [
      "リーク・ウーットン"
    ],
    "name:kan_x_preferred": [
      "ಲೀಕ್ ವೂಟನ್"
    ],
    "name:kor_x_preferred": [
      "리크 우튼"
    ],
    "name:lit_x_preferred": [
      "Lik Vutonas"
    ],
    "name:nld_x_preferred": [
      "Leek Wootton"
    ],
    "name:pol_x_preferred": [
      "Leek Wootton"
    ],
    "name:por_x_preferred": [
      "Leek Wootton"
    ],
    "name:rus_x_preferred": [
      "Лик-Вуттон"
    ],
    "name:spa_x_preferred": [
      "Leek Wootton"
    ],
    "name:tam_x_preferred": [
      "லீக்வூட்டன்"
    ],
    "name:tel_x_preferred": [
      "లీక్ ఊటన్"
    ],
    "name:urd_x_preferred": [
      "لیک ووتٹن"
    ],
    "qs_pg:aaroncc": "GB",
    "qs_pg:gn_country": "GB",
    "qs_pg:gn_fcode": "PPL",
    "qs_pg:gn_pop": 0,
    "qs_pg:name": "Leek Wootton",
    "qs_pg:name_adm0": "United Kingdom",
    "qs_pg:name_adm1": "England",
    "qs_pg:photos": 72,
    "qs_pg:photos_1k": 15,
    "qs_pg:photos_9k": 1,
    "qs_pg:photos_9r": 2,
    "qs_pg:photos_all": 72,
    "qs_pg:photos_sr": 2,
    "qs_pg:pop_sr": 0,
    "qs_pg:qs_pg_placetype": "locality",
    "qs_pg:qs_pg_placetype_gp": "Town",
    "qs_pg:woe_adm0": 23424975,
    "woe:adm0_id": 23424975,
    "woe:name_adm0": "United Kingdom",
    "woe:name_adm1": "England",
    "woe:placetype": "Town",
    "wof:name": "Leek Wootton",
    "wof:placetype": "neighbourhood",
    "wof:population": 1017
  },
  "geometry": {"coordinates":[-1.5769,52.31845],"type":"Point"}
}
