{
  "type": "Feature",
  "properties": {
    "gn:country":"GB",
    "gn:fcode":"PPL",
    "gn:population":0,
    "iso:country":"GB",
    "name:ara_x_preferred":[
        "\u0623\u0644\u0641\u0631\u0633\u062a\u0648\u0643"
    ],
    "name:arz_x_preferred":[
        "\u0627\u0644\u0641\u0631\u0633\u062a\u0648\u0643"
    ],
    "name:cat_x_preferred":[
        "Alverstoke"
    ],
    "name:cym_x_preferred":[
        "Alverstoke"
    ],
    "name:deu_x_preferred":[
        "Alverstoke"
    ],
    "name:eng_x_preferred":[
        "Alverstoke"
    ],
    "name:fra_x_preferred":[
        "Alverstoke"
    ],
    "name:gle_x_preferred":[
        "Alverstoke"
    ],
    "name:heb_x_preferred":[
        "\u05d0\u05dc\u05d1\u05e8\u05e1\u05d8\u05d5\u05e7"
    ],
    "name:nld_x_preferred":[
        "Alverstoke"
    ],
    "name:pol_x_preferred":[
        "Alverstoke"
    ],
    "name:por_x_preferred":[
        "Alverstoke"
    ],
    "qs_pg:aaroncc":"GB",
    "qs_pg:gn_country":"GB",
    "qs_pg:gn_fcode":"PPL",
    "qs_pg:gn_pop":0,
    "qs_pg:name":"Alverstoke",
    "qs_pg:name_adm0":"United Kingdom",
    "qs_pg:name_adm1":"England",
    "qs_pg:photos":492,
    "qs_pg:photos_1k":100,
    "qs_pg:photos_9k":2,
    "qs_pg:photos_9r":5,
    "qs_pg:photos_all":492,
    "qs_pg:photos_sr":7,
    "qs_pg:pop_sr":0,
    "qs_pg:qs_pg_placetype":"locality",
    "qs_pg:qs_pg_placetype_gp":"Town",
    "qs_pg:woe_adm0":23424975,
    "woe:adm0_id":23424975,
    "woe:name_adm0":"United Kingdom",
    "woe:name_adm1":"England",
    "woe:placetype":"Town",
    "wof:name":"Alverstoke",
    "wof:placetype":"neighbourhood"
},
  "geometry": {"coordinates":[-1.14971,50.78842],"type":"Point"}
}