{
  "type": "Feature",
  "properties": {
    "gn:admin1_code":"SCT",
    "gn:admin2_code":"T6",
    "gn:asciiname":"Nether Kinmundy",
    "gn:country_code":"GB",
    "gn:dem":77,
    "gn:feature_class":"P",
    "gn:feature_code":"PPL",
    "gn:name":"Nether Kinmundy",
    "gn:population":0,
    "gn:timezone":"Europe/London",
    "iso:country":"GB",
    "name:und_x_variant":[
        "Nether Kilmundy",
        "Nether Kinmundy"
    ],
    "wof:name":"Nether Kinmundy",
    "wof:placetype":"locality"
},
  "geometry": {"coordinates":[-1.91659,57.48576],"type":"Point"}
}