{
  "type": "Feature",
  "properties": {
    "gn:country":"GB",
    "gn:fcode":"PPL",
    "gn:population":0,
    "iso:country":"GB",
    "name:cym_x_preferred":[
        "Barling"
    ],
    "name:eng_x_preferred":[
        "Barling"
    ],
    "name:fra_x_preferred":[
        "Barling"
    ],
    "name:gle_x_preferred":[
        "Barling"
    ],
    "name:nld_x_preferred":[
        "Barling Magna"
    ],
    "name:nld_x_variant":[
        "Barling"
    ],
    "name:pol_x_preferred":[
        "Barling"
    ],
    "name:swe_x_preferred":[
        "Barling"
    ],
    "qs_pg:aaroncc":"GB",
    "qs_pg:gn_country":"GB",
    "qs_pg:gn_fcode":"PPL",
    "qs_pg:gn_pop":0,
    "qs_pg:name":"Barling",
    "qs_pg:name_adm0":"United Kingdom",
    "qs_pg:name_adm1":"England",
    "qs_pg:photos":111,
    "qs_pg:photos_1k":22,
    "qs_pg:photos_9k":1,
    "qs_pg:photos_9r":3,
    "qs_pg:photos_all":111,
    "qs_pg:photos_sr":3,
    "qs_pg:pop_sr":0,
    "qs_pg:qs_pg_placetype":"locality",
    "qs_pg:qs_pg_placetype_gp":"Town",
    "qs_pg:woe_adm0":23424975,
    "woe:adm0_id":23424975,
    "woe:name_adm0":"United Kingdom",
    "woe:name_adm1":"England",
    "woe:placetype":"Town",
    "wof:name":"Barling",
    "wof:placetype":"neighbourhood"
},
  "geometry": {"coordinates":[0.78321,51.57104],"type":"Point"}
}