{
  "type": "Feature",
  "properties": {
    "iso:country":"GB",
    "name:jpn_x_preferred":[
        "\u30b9\u30c6\u30f3\u30ab\u30e9\u30fc\u30b3\u30fc\u30c8"
    ],
    "qs_pg:aaroncc":"GB",
    "qs_pg:name":"Balmacaan",
    "qs_pg:name_adm0":"United Kingdom",
    "qs_pg:name_adm1":"Scotland",
    "qs_pg:photos":10,
    "qs_pg:photos_1k":2,
    "qs_pg:photos_9k":1,
    "qs_pg:photos_9r":1,
    "qs_pg:photos_all":10,
    "qs_pg:photos_sr":1,
    "qs_pg:pop_sr":0,
    "qs_pg:qs_pg_placetype":"locality",
    "qs_pg:qs_pg_placetype_gp":"Town",
    "qs_pg:woe_adm0":23424975,
    "woe:adm0_id":23424975,
    "woe:name_adm0":"United Kingdom",
    "woe:name_adm1":"Scotland",
    "woe:placetype":"Town",
    "wof:name":"Balmacaan",
    "wof:placetype":"locality"
},
  "geometry": {"coordinates":[-4.505424,57.3160185],"type":"Point"}
}