{
  "type": "Feature",
  "properties": {
    "gn:admin1_code":"SCT",
    "gn:admin2_code":"V3",
    "gn:asciiname":"Occumster",
    "gn:country_code":"GB",
    "gn:dem":75,
    "gn:feature_class":"P",
    "gn:feature_code":"PPL",
    "gn:name":"Occumster",
    "gn:population":0,
    "gn:timezone":"Europe/London",
    "iso:country":"GB",
    "wof:name":"Occumster",
    "wof:placetype":"locality"
},
  "geometry": {"coordinates":[-3.25734,58.30753000000001],"type":"Point"}
}