{
  "type": "Feature",
  "properties": {
    "gn:admin1_code":"WLS",
    "gn:admin2_code":"Y7",
    "gn:admin3_code":"00NS042",
    "gn:asciiname":"New Park",
    "gn:country_code":"GB",
    "gn:dem":34,
    "gn:feature_class":"P",
    "gn:feature_code":"PPL",
    "gn:name":"New Park",
    "gn:population":0,
    "gn:timezone":"Europe/London",
    "iso:country":"GB",
    "wof:name":"New Park",
    "wof:placetype":"neighbourhood"
},
  "geometry": {"coordinates":[-4.87194,51.76389],"type":"Point"}
}