{
  "type": "Feature",
  "properties": {
    "gn:country":"GB",
    "gn:fcode":"PPL",
    "gn:population":0,
    "iso:country":"GB",
    "name:bre_x_preferred":[
        "Aberogwr"
    ],
    "name:cym_x_preferred":[
        "Aberogwr"
    ],
    "name:eng_x_preferred":[
        "Ogmore-by-Sea"
    ],
    "name:eus_x_preferred":[
        "Ogmore-by-Sea"
    ],
    "name:fra_x_preferred":[
        "Ogmore-by-Sea"
    ],
    "name:nld_x_preferred":[
        "Ogmore-by-Sea"
    ],
    "name:spa_x_preferred":[
        "Ogmore-by-Sea"
    ],
    "name:swe_x_preferred":[
        "Ogmore-by-sea"
    ],
    "qs_pg:aaroncc":"GB",
    "qs_pg:gn_country":"GB",
    "qs_pg:gn_fcode":"PPL",
    "qs_pg:gn_pop":0,
    "qs_pg:name":"Ogmore-by-Sea",
    "qs_pg:name_adm0":"United Kingdom",
    "qs_pg:name_adm1":"Wales",
    "qs_pg:photos":737,
    "qs_pg:photos_1k":149,
    "qs_pg:photos_9k":3,
    "qs_pg:photos_9r":5,
    "qs_pg:photos_all":737,
    "qs_pg:photos_sr":8,
    "qs_pg:pop_sr":0,
    "qs_pg:qs_pg_placetype":"locality",
    "qs_pg:qs_pg_placetype_gp":"Town",
    "qs_pg:woe_adm0":23424975,
    "woe:adm0_id":23424975,
    "woe:name_adm0":"United Kingdom",
    "woe:name_adm1":"Wales",
    "woe:placetype":"Town",
    "wof:name":"Ogmore-by-Sea",
    "wof:placetype":"neighbourhood",
    "wof:population":878
},
  "geometry": {"coordinates":[-3.63028,51.46056],"type":"Point"}
}