{
  "type": "Feature",
  "properties": {
    "gn:admin1_code":"ENG",
    "gn:admin2_code":"E6",
    "gn:admin3_code":"23UC",
    "gn:admin4_code":"23UC034",
    "gn:asciiname":"Coln Saint Denis",
    "gn:country_code":"GB",
    "gn:dem":146,
    "gn:feature_class":"P",
    "gn:feature_code":"PPL",
    "gn:name":"Coln Saint Denis",
    "gn:population":0,
    "gn:timezone":"Europe/London",
    "iso:country":"GB",
    "wof:name":"Coln Saint Denis",
    "wof:placetype":"neighbourhood"
},
  "geometry": {"coordinates":[-1.86667,51.78333],"type":"Point"}
}