{
  "type": "Feature",
  "properties": {
    "gn:population": 2545,
    "iso:country": "GB",
    "name:bul_x_preferred": [
      "Авиеморе"
    ],
    "name:ceb_x_preferred": [
      "Aviemore"
    ],
    "name:cym_x_preferred": [
      "Aviemore"
    ],
    "name:deu_x_preferred": [
      "Aviemore"
    ],
    "name:eng_x_preferred": [
      "Aviemore"
    ],
    "name:eus_x_preferred": [
      "Aviemore"
    ],
    "name:fas_x_preferred": [
      "اویمور"
    ],
    "name:fra_x_preferred": [
      "Aviemore"
    ],
    "name:gla_x_preferred": [
      "An Aghaidh Mhòr"
    ],
    "name:gle_x_preferred": [
      "An Aghaidh Mhór"
    ],
    "name:heb_x_preferred": [
      "אבימור"
    ],
    "name:ita_x_preferred": [
      "Aviemore"
    ],
    "name:jpn_x_preferred": [
      "アビモア"
    ],
    "name:mri_x_preferred": [
      "Aviemore"
    ],
    "name:nld_x_preferred": [
      "Aviemore"
    ],
    "name:nno_x_preferred": [
      "Aviemore"
    ],
    "name:nob_x_preferred": [
      "Aviemore"
    ],
    "name:nor_x_preferred": [
      "Aviemore"
    ],
    "name:pol_x_preferred": [
      "Aviemore"
    ],
    "name:spa_x_preferred": [
      "Aviemore"
    ],
    "name:swe_x_preferred": [
      "Aviemore"
    ],
    "name:zho_x_preferred": [
      "阿维莫尔"
    ],
    "qs:a0": "United Kingdom",
    "qs:a1": "*Highland",
    "qs:a1_lc": "GB11QT0000",
    "qs:a1r": "0Scotland",
    "qs:a1r_lc": "GB11000000",
    "qs:adm0": "United Kingdom",
    "qs:la_lc": "*",
    "qs:level": "locality",
    "qs:loc": "Aviemore",
    "qs:loc_alt": "Aviemore",
    "qs:pop": 0,
    "qs:type": "buffered point",
    "wd:wordcount": 670,
    "wof:lang": [
      "eng"
    ],
    "wof:name": "Aviemore",
    "wof:placetype": "locality",
    "wof:population": 2545
  },
  "geometry": {"coordinates":[-3.833483,57.19149],"type":"Point"}
}
