{
  "type": "Feature",
  "properties": {
    "iso:country": "GB",
    "name:afr_x_preferred": [
      "Lughawe Londen-Southend"
    ],
    "name:ceb_x_preferred": [
      "London Southend Airport"
    ],
    "name:ces_x_preferred": [
      "Letiště London Southend"
    ],
    "name:deu_x_preferred": [
      "London Southend Airport"
    ],
    "name:eng_x_preferred": [
      "London Southend Airport"
    ],
    "name:eng_x_variant": [
      "SEN",
      "EGMC"
    ],
    "name:epo_x_preferred": [
      "Londona Sudfina Flughaveno"
    ],
    "name:est_x_preferred": [
      "Londoni Southendi lennujaam"
    ],
    "name:fas_x_preferred": [
      "فرودگاه جنوبی لندن"
    ],
    "name:fra_x_preferred": [
      "Aéroport de Londres-Southend"
    ],
    "name:glg_x_preferred": [
      "Aeroporto de Londres-Southend"
    ],
    "name:ita_x_preferred": [
      "Aeroporto di Southend"
    ],
    "name:jpn_x_preferred": [
      "ロンドン・サウスエンド空港"
    ],
    "name:kor_x_preferred": [
      "런던 사우스엔드 공항"
    ],
    "name:msa_x_preferred": [
      "Lapangan Terbang Southend"
    ],
    "name:nld_x_preferred": [
      "London Southend Airport"
    ],
    "name:nld_x_variant": [
      "Luchthaven London Southend"
    ],
    "name:pms_x_preferred": [
      "London Southend Airport"
    ],
    "name:pol_x_preferred": [
      "Port lotniczy Londyn-Southend"
    ],
    "name:ron_x_preferred": [
      "Aeroportul Londra Southend"
    ],
    "name:rus_x_preferred": [
      "Саутенд"
    ],
    "name:rus_x_variant": [
      "Саусенд"
    ],
    "name:slk_x_preferred": [
      "Letisko Londýn-Southend"
    ],
    "name:spa_x_preferred": [
      "Aeropuerto de Londres-Southend"
    ],
    "name:swe_x_preferred": [
      "London Southend Airport"
    ],
    "name:tgk_x_preferred": [
      "Фурудгоҳи ҷанубе лондан"
    ],
    "name:tur_x_preferred": [
      "Londra Southend Havalimanı"
    ],
    "name:ukr_x_preferred": [
      "Лондон-Саутенд"
    ],
    "name:vie_x_preferred": [
      "Sân bay London Southend"
    ],
    "name:zho_x_preferred": [
      "伦敦绍森德机场"
    ],
    "oa:elevation_ft": "49",
    "oa:type": "medium_airport",
    "wd:wordcount": 4600,
    "woe:hierarchy": {
      "country_id": 23424975,
      "county_id": 12602168,
      "localadmin_id": 12695949,
      "planet_id": 1,
      "state_id": 24554868
    },
    "wof:name": "Southend Airport",
    "wof:placetype": "campus"
  },
  "geometry": {"coordinates":[0.693333,51.570278],"type":"Point"}
}
