{
  "type": "Feature",
  "properties": {
    "iso:country":"GB",
    "name:afr_x_preferred":[
        "Lughawe Londen-Southend"
    ],
    "name:ceb_x_preferred":[
        "London Southend Airport"
    ],
    "name:ces_x_preferred":[
        "Leti\u0161t\u011b London Southend"
    ],
    "name:deu_x_preferred":[
        "London Southend Airport"
    ],
    "name:eng_x_preferred":[
        "London Southend Airport"
    ],
    "name:epo_x_preferred":[
        "Londona Sudfina Flughaveno"
    ],
    "name:est_x_preferred":[
        "Londoni Southendi lennujaam"
    ],
    "name:fas_x_preferred":[
        "\u0641\u0631\u0648\u062f\u06af\u0627\u0647 \u062c\u0646\u0648\u0628\u06cc \u0644\u0646\u062f\u0646"
    ],
    "name:fra_x_preferred":[
        "A\u00e9roport de Londres-Southend"
    ],
    "name:glg_x_preferred":[
        "Aeroporto de Londres-Southend"
    ],
    "name:ita_x_preferred":[
        "Aeroporto di Southend"
    ],
    "name:jpn_x_preferred":[
        "\u30ed\u30f3\u30c9\u30f3\u30fb\u30b5\u30a6\u30b9\u30a8\u30f3\u30c9\u7a7a\u6e2f"
    ],
    "name:kor_x_preferred":[
        "\ub7f0\ub358 \uc0ac\uc6b0\uc2a4\uc5d4\ub4dc \uacf5\ud56d"
    ],
    "name:msa_x_preferred":[
        "Lapangan Terbang Southend"
    ],
    "name:nld_x_preferred":[
        "London Southend Airport"
    ],
    "name:nld_x_variant":[
        "Luchthaven London Southend"
    ],
    "name:pms_x_preferred":[
        "London Southend Airport"
    ],
    "name:pol_x_preferred":[
        "Port lotniczy Londyn-Southend"
    ],
    "name:ron_x_preferred":[
        "Aeroportul Londra Southend"
    ],
    "name:rus_x_preferred":[
        "\u0421\u0430\u0443\u0442\u0435\u043d\u0434"
    ],
    "name:rus_x_variant":[
        "\u0421\u0430\u0443\u0441\u0435\u043d\u0434"
    ],
    "name:slk_x_preferred":[
        "Letisko Lond\u00fdn-Southend"
    ],
    "name:spa_x_preferred":[
        "Aeropuerto de Londres-Southend"
    ],
    "name:swe_x_preferred":[
        "London Southend Airport"
    ],
    "name:tgk_x_preferred":[
        "\u0424\u0443\u0440\u0443\u0434\u0433\u043e\u04b3\u0438 \u04b7\u0430\u043d\u0443\u0431\u0435 \u043b\u043e\u043d\u0434\u0430\u043d"
    ],
    "name:tur_x_preferred":[
        "Londra Southend Havaliman\u0131"
    ],
    "name:ukr_x_preferred":[
        "\u041b\u043e\u043d\u0434\u043e\u043d-\u0421\u0430\u0443\u0442\u0435\u043d\u0434"
    ],
    "name:vie_x_preferred":[
        "S\u00e2n bay London Southend"
    ],
    "name:zho_x_preferred":[
        "\u4f26\u6566\u7ecd\u68ee\u5fb7\u673a\u573a"
    ],
    "oa:elevation_ft":"49",
    "oa:type":"medium_airport",
    "wd:wordcount":4600,
    "woe:hierarchy":{
        "country_id":23424975,
        "county_id":12602168,
        "localadmin_id":12695949,
        "planet_id":1,
        "state_id":24554868
    },
    "wof:name":"Southend Airport",
    "wof:placetype":"campus"
},
  "geometry": {"coordinates":[0.69333333333333,51.570277777778],"type":"Point"}
}