{
  "type": "Feature",
  "properties": {
    "iso:country":"GB",
    "name:eng_x_preferred":[
        "Northern Moor"
    ],
    "name:gle_x_preferred":[
        "Northern Moor"
    ],
    "name:zho_x_preferred":[
        "\u5317\u6469\u723e"
    ],
    "wd:wordcount":162,
    "wof:name":"Northern Moor",
    "wof:placetype":"neighbourhood"
},
  "geometry": {"coordinates":[-2.286398,53.411002],"type":"Point"}
}