{
  "type": "Feature",
  "properties": {
    "name:eng_x_preferred":[
        "Northern Moor"
    ],
    "name:gle_x_preferred":[
        "Northern Moor"
    ],
    "wd:wordcount":162,
    "wof:name":"Northern Moor",
    "wof:placetype":"neighbourhood"
},
  "geometry": {"coordinates":[-2.28639821069064,53.41100175857913],"type":"Point"}
}