{
  "type": "Feature",
  "properties": {
    "iso:country":"GB",
    "name:eng_x_preferred":[
        "Efford"
    ],
    "name:gle_x_preferred":[
        "Efford"
    ],
    "name:pol_x_preferred":[
        "Efford"
    ],
    "qs:gn_adm0_cc":"GB",
    "qs:gn_fcode":"PPL",
    "qs:gn_local":2640194,
    "qs:gn_nam_loc":"Plymouth",
    "qs:gn_namadm1":"ENG",
    "qs:gn_name":"Exford",
    "qs:local_max":8196,
    "qs:local_sum":38773,
    "qs:localhoods":38,
    "qs:name":"Efford",
    "qs:name_adm0":"United Kingdom",
    "qs:name_adm1":"England",
    "qs:name_adm2":"Devon",
    "qs:name_lau":"Plymouth City",
    "qs:name_local":"Plymouth",
    "qs:photo_max":45,
    "qs:photo_sum":264,
    "qs:placetype":"Suburb",
    "qs:quad_count":23,
    "qs:woe_adm0":23424975,
    "qs:woe_adm1":24554868,
    "qs:woe_adm2":12602182,
    "qs:woe_lau":12696173,
    "qs:woe_local":32185,
    "qs:woe_ver":"7.10.0",
    "wd:wordcount":683,
    "wof:lang":[
        "eng"
    ],
    "wof:name":"Efford",
    "wof:placetype":"neighbourhood"
},
  "geometry": {"coordinates":[-4.106008,50.384735],"type":"Point"}
}