{
  "type": "Feature",
  "properties": {
    "iso:country":"GB",
    "name:cym_x_preferred":[
        "Martinscroft"
    ],
    "name:eng_x_preferred":[
        "Martinscroft"
    ],
    "name:fra_x_preferred":[
        "Martinscroft"
    ],
    "name:nld_x_preferred":[
        "Martinscroft"
    ],
    "name:pol_x_preferred":[
        "Martinscroft"
    ],
    "qs_pg:aaroncc":"GB",
    "qs_pg:name":"Martinscroft",
    "qs_pg:name_adm0":"United Kingdom",
    "qs_pg:name_adm1":"England",
    "qs_pg:photos":7,
    "qs_pg:photos_1k":1,
    "qs_pg:photos_9k":1,
    "qs_pg:photos_9r":1,
    "qs_pg:photos_all":7,
    "qs_pg:photos_sr":1,
    "qs_pg:pop_sr":0,
    "qs_pg:qs_pg_placetype":"locality",
    "qs_pg:qs_pg_placetype_gp":"Town",
    "qs_pg:woe_adm0":23424975,
    "woe:adm0_id":23424975,
    "woe:name_adm0":"United Kingdom",
    "woe:name_adm1":"England",
    "woe:placetype":"Town",
    "wof:name":"Martinscroft",
    "wof:placetype":"neighbourhood"
},
  "geometry": {"coordinates":[-2.522263,53.398875],"type":"Point"}
}