{
  "type": "Feature",
  "properties": {
    "gn:country":"GB",
    "gn:fcode":"PPL",
    "gn:population":0,
    "iso:country":"GB",
    "name:deu_x_preferred":[
        "Grandtully"
    ],
    "name:eng_x_preferred":[
        "Grandtully"
    ],
    "name:eus_x_preferred":[
        "Grandtully"
    ],
    "name:fra_x_preferred":[
        "Grandtully"
    ],
    "name:gle_x_preferred":[
        "Gar an Tulaich"
    ],
    "name:nld_x_preferred":[
        "Grandtully"
    ],
    "name:sco_x_preferred":[
        "Grantellie"
    ],
    "qs_pg:aaroncc":"GB",
    "qs_pg:gn_country":"GB",
    "qs_pg:gn_fcode":"PPL",
    "qs_pg:gn_pop":0,
    "qs_pg:name":"Grandtully",
    "qs_pg:name_adm0":"United Kingdom",
    "qs_pg:name_adm1":"Scotland",
    "qs_pg:photos":331,
    "qs_pg:photos_1k":67,
    "qs_pg:photos_9k":1,
    "qs_pg:photos_9r":5,
    "qs_pg:photos_all":331,
    "qs_pg:photos_sr":5,
    "qs_pg:pop_sr":0,
    "qs_pg:qs_pg_placetype":"locality",
    "qs_pg:qs_pg_placetype_gp":"Town",
    "qs_pg:woe_adm0":23424975,
    "woe:adm0_id":23424975,
    "woe:name_adm0":"United Kingdom",
    "woe:name_adm1":"Scotland",
    "woe:placetype":"Town",
    "wof:name":"Grandtully",
    "wof:placetype":"locality"
},
  "geometry": {"coordinates":[-3.77455,56.65612],"type":"Point"}
}