{
  "type": "Feature",
  "properties": {
    "iso:country":"GB",
    "name:azb_x_preferred":[
        "\u0622\u0644\u062a\u0646\u0632"
    ],
    "name:eus_x_preferred":[
        "Altens"
    ],
    "name:fas_x_preferred":[
        "\u0622\u0644\u062a\u0646\u0632"
    ],
    "qs_pg:aaroncc":"GB",
    "qs_pg:name":"Altens",
    "qs_pg:name_adm0":"United Kingdom",
    "qs_pg:name_adm1":"Scotland",
    "qs_pg:photos":279,
    "qs_pg:photos_1k":57,
    "qs_pg:photos_9k":1,
    "qs_pg:photos_9r":4,
    "qs_pg:photos_all":279,
    "qs_pg:photos_sr":5,
    "qs_pg:pop_sr":0,
    "qs_pg:qs_pg_placetype":"locality",
    "qs_pg:qs_pg_placetype_gp":"Town",
    "qs_pg:woe_adm0":23424975,
    "woe:adm0_id":23424975,
    "woe:name_adm0":"United Kingdom",
    "woe:name_adm1":"Scotland",
    "woe:placetype":"Town",
    "wof:name":"Altens",
    "wof:placetype":"locality"
},
  "geometry": {"coordinates":[-2.080342,57.115181],"type":"Point"}
}