{
  "type": "Feature",
  "properties": {
    "gn:admin1_code": "ENG",
    "gn:admin2_code": "K2",
    "gn:admin3_code": "38UF",
    "gn:admin4_code": "38UF064",
    "gn:asciiname": "Ledwell",
    "gn:country_code": "GB",
    "gn:dem": 170,
    "gn:feature_class": "P",
    "gn:feature_code": "PPL",
    "gn:name": "Ledwell",
    "gn:population": 0,
    "gn:timezone": "Europe/London",
    "iso:country": "GB",
    "wof:name": "Ledwell",
    "wof:placetype": "neighbourhood"
  },
  "geometry": {"coordinates":[-1.39046,51.95014000000001],"type":"Point"}
}
