{
  "type": "Feature",
  "properties": {
    "iso:country":"GB",
    "name:eng_x_preferred":[
        "Bridgeyate"
    ],
    "name:fra_x_preferred":[
        "Bridgeyate"
    ],
    "name:nld_x_preferred":[
        "Bridgeyate"
    ],
    "name:pol_x_preferred":[
        "Bridgeyate"
    ],
    "qs:gn_fcode":"PPL",
    "qs:gn_local":0,
    "qs:gn_namadm1":"ENG",
    "qs:gn_name":"Bridgwater",
    "qs:local_max":169,
    "qs:local_sum":169,
    "qs:localhoods":1,
    "qs:name":"Bridgeyate",
    "qs:name_adm0":"United Kingdom",
    "qs:name_adm1":"England",
    "qs:name_adm2":"Gloucestershire",
    "qs:name_lau":"South Gloucestershire",
    "qs:name_local":"South Gloucestershire",
    "qs:photo_max":30,
    "qs:photo_sum":169,
    "qs:placetype":"Suburb",
    "qs:quad_count":39,
    "qs:woe_adm0":23424975,
    "qs:woe_adm1":24554868,
    "qs:woe_adm2":12602184,
    "qs:woe_lau":12696146,
    "qs:woe_local":12696146,
    "qs:woe_ver":"7.10.0",
    "wd:wordcount":244,
    "wof:lang":[
        "eng"
    ],
    "wof:name":"Bridgeyate",
    "wof:placetype":"neighbourhood"
},
  "geometry": {"coordinates":[-2.441874,51.456181],"type":"Point"}
}