{
  "type": "Feature",
  "properties": {
    "iso:country":"GB",
    "name:deu_x_preferred":[
        "Knowle"
    ],
    "name:nld_x_preferred":[
        "Knowle"
    ],
    "name:pol_x_preferred":[
        "Knowle"
    ],
    "name:swe_x_preferred":[
        "Knowle"
    ],
    "qs_pg:aaroncc":"GB",
    "qs_pg:name":"Knowle",
    "qs_pg:name_adm0":"United Kingdom",
    "qs_pg:name_adm1":"England",
    "qs_pg:photos":133,
    "qs_pg:photos_1k":27,
    "qs_pg:photos_9k":1,
    "qs_pg:photos_9r":3,
    "qs_pg:photos_all":133,
    "qs_pg:photos_sr":3,
    "qs_pg:pop_sr":0,
    "qs_pg:qs_pg_placetype":"locality",
    "qs_pg:qs_pg_placetype_gp":"Town",
    "qs_pg:woe_adm0":23424975,
    "woe:adm0_id":23424975,
    "woe:name_adm0":"United Kingdom",
    "woe:name_adm1":"England",
    "woe:placetype":"Town",
    "wof:name":"Knowle",
    "wof:placetype":"neighbourhood"
},
  "geometry": {"coordinates":[-3.341817,50.636179],"type":"Point"}
}