{
  "type": "Feature",
  "properties": {
    "gn:country":"GB",
    "gn:fcode":"PPL",
    "gn:population":0,
    "iso:country":"GB",
    "name:ceb_x_preferred":[
        "Saint Fergus"
    ],
    "name:deu_x_preferred":[
        "St Fergus"
    ],
    "name:eng_x_preferred":[
        "St Fergus"
    ],
    "name:eus_x_preferred":[
        "St Fergus"
    ],
    "name:fra_x_preferred":[
        "St Fergus"
    ],
    "name:gle_x_preferred":[
        "Peit Fhearghais"
    ],
    "name:nld_x_preferred":[
        "St Fergus"
    ],
    "name:sco_x_preferred":[
        "St Fergus"
    ],
    "name:spa_x_preferred":[
        "St Fergus"
    ],
    "name:swe_x_preferred":[
        "Saint Fergus"
    ],
    "name:swe_x_variant":[
        "St Fergus"
    ],
    "qs_pg:aaroncc":"GB",
    "qs_pg:gn_country":"GB",
    "qs_pg:gn_fcode":"PPL",
    "qs_pg:gn_pop":0,
    "qs_pg:name":"St. Fergus",
    "qs_pg:name_adm0":"United Kingdom",
    "qs_pg:name_adm1":"Scotland",
    "qs_pg:photos":79,
    "qs_pg:photos_1k":16,
    "qs_pg:photos_9k":1,
    "qs_pg:photos_9r":3,
    "qs_pg:photos_all":79,
    "qs_pg:photos_sr":3,
    "qs_pg:pop_sr":0,
    "qs_pg:qs_pg_placetype":"locality",
    "qs_pg:qs_pg_placetype_gp":"Town",
    "qs_pg:woe_adm0":23424975,
    "woe:adm0_id":23424975,
    "woe:name_adm0":"United Kingdom",
    "woe:name_adm1":"Scotland",
    "woe:placetype":"Town",
    "wof:name":"St. Fergus",
    "wof:placetype":"locality",
    "wof:population":750
},
  "geometry": {"coordinates":[-1.83333,57.55],"type":"Point"}
}