{
  "type": "Feature",
  "properties": {
    "gn:country":"GB",
    "gn:fcode":"PPL",
    "gn:population":1266,
    "iso:country":"GB",
    "name:bul_x_preferred":[
        "\u0410\u043b\u0430\u043d\u0442\u043e\u043d"
    ],
    "name:ceb_x_preferred":[
        "Allanton"
    ],
    "name:eng_x_preferred":[
        "Allanton"
    ],
    "name:eus_x_preferred":[
        "Allanton"
    ],
    "name:gla_x_preferred":[
        "Baile Alain"
    ],
    "name:gle_x_preferred":[
        "Baile Alain"
    ],
    "name:nld_x_preferred":[
        "Allanton"
    ],
    "name:swe_x_preferred":[
        "Allanton"
    ],
    "qs_pg:aaroncc":"GB",
    "qs_pg:gn_country":"GB",
    "qs_pg:gn_fcode":"PPL",
    "qs_pg:gn_pop":1266,
    "qs_pg:name":"Allanton",
    "qs_pg:name_adm0":"United Kingdom",
    "qs_pg:name_adm1":"Scotland",
    "qs_pg:photos":39,
    "qs_pg:photos_1k":8,
    "qs_pg:photos_9k":1,
    "qs_pg:photos_9r":2,
    "qs_pg:photos_all":39,
    "qs_pg:photos_sr":2,
    "qs_pg:pop_sr":3,
    "qs_pg:qs_pg_placetype":"locality",
    "qs_pg:qs_pg_placetype_gp":"Town",
    "qs_pg:woe_adm0":23424975,
    "woe:adm0_id":23424975,
    "woe:name_adm0":"United Kingdom",
    "woe:name_adm1":"Scotland",
    "woe:placetype":"Town",
    "wof:name":"Allanton",
    "wof:placetype":"locality",
    "wof:population":1266
},
  "geometry": {"coordinates":[-2.21667,55.78333],"type":"Point"}
}