{
  "type": "Feature",
  "properties": {
    "iso:country":"GB",
    "name:eng_x_preferred":[
        "Woods End"
    ],
    "qs:gn_adm0_cc":"GB",
    "qs:gn_local":2635062,
    "qs:gn_nam_loc":"urmston",
    "qs:gn_namadm1":"ENG",
    "qs:local_max":2536,
    "qs:local_sum":3892,
    "qs:localhoods":2,
    "qs:name":"Woods End",
    "qs:name_adm0":"United Kingdom",
    "qs:name_adm1":"England",
    "qs:name_adm2":"Greater Manchester",
    "qs:name_lau":"Trafford Metropolitan Borough",
    "qs:name_local":"Urmston",
    "qs:photo_max":296,
    "qs:photo_sum":1356,
    "qs:placetype":"Suburb",
    "qs:quad_count":85,
    "qs:woe_adm0":23424975,
    "qs:woe_adm1":24554868,
    "qs:woe_adm2":12602158,
    "qs:woe_lau":12695847,
    "qs:woe_local":38822,
    "qs:woe_ver":"7.10.0",
    "wof:lang":[
        "eng"
    ],
    "wof:name":"Woods End",
    "wof:placetype":"neighbourhood"
},
  "geometry": {"coordinates":[-2.393887,53.450402],"type":"Point"}
}