{
  "type": "Feature",
  "properties": {
    "iso:country": "GB",
    "name:bre_x_preferred": [
      "Libanus"
    ],
    "name:cym_x_preferred": [
      "Libanus"
    ],
    "name:eng_x_preferred": [
      "Libanus"
    ],
    "name:eus_x_preferred": [
      "Libanus"
    ],
    "name:fra_x_preferred": [
      "Libanus"
    ],
    "name:nld_x_preferred": [
      "Libanus"
    ],
    "qs_pg:aaroncc": "GB",
    "qs_pg:name": "Libanus",
    "qs_pg:name_adm0": "United Kingdom",
    "qs_pg:name_adm1": "Wales",
    "qs_pg:photos": 321,
    "qs_pg:photos_1k": 65,
    "qs_pg:photos_9k": 1,
    "qs_pg:photos_9r": 5,
    "qs_pg:photos_all": 321,
    "qs_pg:photos_sr": 5,
    "qs_pg:pop_sr": 0,
    "qs_pg:qs_pg_placetype": "locality",
    "qs_pg:qs_pg_placetype_gp": "Town",
    "qs_pg:woe_adm0": 23424975,
    "woe:adm0_id": 23424975,
    "woe:name_adm0": "United Kingdom",
    "woe:name_adm1": "Wales",
    "woe:placetype": "Town",
    "wof:name": "Libanus",
    "wof:placetype": "neighbourhood"
  },
  "geometry": {"coordinates":[-3.487815,51.922888],"type":"Point"}
}
