{
  "type": "Feature",
  "properties": {
    "gn:admin1_code": "ENG",
    "gn:admin2_code": "N5",
    "gn:admin3_code": "42UH",
    "gn:admin4_code": "42UH051",
    "gn:asciiname": "Henham",
    "gn:country_code": "GB",
    "gn:dem": 20,
    "gn:feature_class": "P",
    "gn:feature_code": "PPL",
    "gn:name": "Henham",
    "gn:population": 0,
    "gn:timezone": "Europe/London",
    "iso:country": "GB",
    "name:ceb_x_preferred": [
      "Henham"
    ],
    "name:cym_x_preferred": [
      "Henham"
    ],
    "name:deu_x_preferred": [
      "Henham"
    ],
    "name:fas_x_preferred": [
      "هنام"
    ],
    "name:ita_x_preferred": [
      "Henham"
    ],
    "name:nld_x_preferred": [
      "Henham"
    ],
    "name:pol_x_preferred": [
      "Henham"
    ],
    "name:spa_x_preferred": [
      "Henham"
    ],
    "name:swe_x_preferred": [
      "Henham"
    ],
    "wof:name": "Henham",
    "wof:placetype": "neighbourhood"
  },
  "geometry": {"coordinates":[1.59787,52.34847],"type":"Point"}
}
