{
  "type": "Feature",
  "properties": {
    "gn:country":"GB",
    "gn:fcode":"PPL",
    "gn:population":0,
    "iso:country":"GB",
    "name:cym_x_preferred":[
        "Cark"
    ],
    "name:deu_x_preferred":[
        "Cark-in-Cartmel"
    ],
    "name:eng_x_preferred":[
        "Cark"
    ],
    "name:fra_x_preferred":[
        "Cark"
    ],
    "name:gle_x_preferred":[
        "Cark"
    ],
    "name:nld_x_preferred":[
        "Cark"
    ],
    "name:pol_x_preferred":[
        "Cark"
    ],
    "qs_pg:aaroncc":"GB",
    "qs_pg:gn_country":"GB",
    "qs_pg:gn_fcode":"PPL",
    "qs_pg:gn_pop":0,
    "qs_pg:name":"Cark",
    "qs_pg:name_adm0":"United Kingdom",
    "qs_pg:name_adm1":"England",
    "qs_pg:photos":187,
    "qs_pg:photos_1k":38,
    "qs_pg:photos_9k":1,
    "qs_pg:photos_9r":4,
    "qs_pg:photos_all":187,
    "qs_pg:photos_sr":4,
    "qs_pg:pop_sr":0,
    "qs_pg:qs_pg_placetype":"locality",
    "qs_pg:qs_pg_placetype_gp":"Town",
    "qs_pg:woe_adm0":23424975,
    "woe:adm0_id":23424975,
    "woe:name_adm0":"United Kingdom",
    "woe:name_adm1":"England",
    "woe:placetype":"Town",
    "wof:name":"Cark",
    "wof:placetype":"neighbourhood"
},
  "geometry": {"coordinates":[-2.97591,54.17938],"type":"Point"}
}