{
  "type": "Feature",
  "properties": {
    "iso:country":"GB",
    "wof:name":"Lower Shenkill",
    "wof:placetype":"neighbourhood"
},
  "geometry": {"coordinates":[-5.94197799189397,54.60361136035916],"type":"Point"}
}