{
  "type": "Feature",
  "properties": {
    "iso:country":"GB",
    "name:eng_x_preferred":[
        "Holbeach St Matthew"
    ],
    "name:eng_x_variant":[
        "Holbeach Saint Matthew"
    ],
    "name:gle_x_preferred":[
        "Holbeach St Matthew"
    ],
    "name:nld_x_preferred":[
        "Holbeach St Matthew"
    ],
    "qs_pg:aaroncc":"GB",
    "qs_pg:name":"Holbeach St. Matthew",
    "qs_pg:name_adm0":"United Kingdom",
    "qs_pg:name_adm1":"England",
    "qs_pg:photos":24,
    "qs_pg:photos_1k":5,
    "qs_pg:photos_9k":1,
    "qs_pg:photos_9r":1,
    "qs_pg:photos_all":24,
    "qs_pg:photos_sr":1,
    "qs_pg:pop_sr":0,
    "qs_pg:qs_pg_placetype":"locality",
    "qs_pg:qs_pg_placetype_gp":"Town",
    "qs_pg:woe_adm0":23424975,
    "woe:adm0_id":23424975,
    "woe:name_adm0":"United Kingdom",
    "woe:name_adm1":"England",
    "woe:placetype":"Town",
    "wof:name":"Holbeach St. Matthew",
    "wof:placetype":"neighbourhood"
},
  "geometry": {"coordinates":[0.091724,52.889642],"type":"Point"}
}