{
  "type": "Feature",
  "properties": {
    "iso:country":"GB",
    "name:ara_x_preferred":[
        "\u0647\u0645\u0633\u0648\u0648\u0631\u062b"
    ],
    "name:arz_x_preferred":[
        "\u0647\u0645\u0633\u0648\u0648\u0631\u062b"
    ],
    "name:ast_x_preferred":[
        "Hemsworth"
    ],
    "name:azb_x_preferred":[
        "\u0647\u0645\u0633\u0648\u0648\u0631\u062b"
    ],
    "name:ben_x_preferred":[
        "\u09b9\u09c7\u09ae\u09b8\u0993\u09b0\u09cd\u09a5"
    ],
    "name:ceb_x_preferred":[
        "Hemsworth"
    ],
    "name:cym_x_preferred":[
        "Hemsworth"
    ],
    "name:deu_x_preferred":[
        "Hemsworth"
    ],
    "name:eng_x_preferred":[
        "Hemsworth"
    ],
    "name:fas_x_preferred":[
        "\u0647\u0645\u0633\u0648\u0648\u0631\u062b"
    ],
    "name:fra_x_preferred":[
        "Hemsworth"
    ],
    "name:gle_x_preferred":[
        "Hemsworth"
    ],
    "name:guj_x_preferred":[
        "\u0ab9\u0ac7\u0aae\u0acd\u0ab8\u0ab5\u0ab0\u0acd\u0aa5"
    ],
    "name:heb_x_preferred":[
        "\u05d4\u05de\u05e1\u05d5\u05d5\u05e8\u05ea'"
    ],
    "name:ita_x_preferred":[
        "Hemsworth"
    ],
    "name:jpn_x_preferred":[
        "\u30d8\u30e0\u30ba\u30ef\u30fc\u30b9"
    ],
    "name:kan_x_preferred":[
        "\u0cb9\u0cc6\u0cae\u0ccd\u0cb8\u0ccd\u0cb5\u0cb0\u0ccd\u0ca4\u0ccd"
    ],
    "name:kor_x_preferred":[
        "\ud584\uc2a4\uc6cc\uc2a4"
    ],
    "name:lit_x_preferred":[
        "Hemsvortas"
    ],
    "name:nan_x_preferred":[
        "Hemsworth"
    ],
    "name:nld_x_preferred":[
        "Hemsworth"
    ],
    "name:nno_x_preferred":[
        "Hemsworth"
    ],
    "name:pol_x_preferred":[
        "Hemsworth"
    ],
    "name:por_x_preferred":[
        "Hemsworth"
    ],
    "name:ron_x_preferred":[
        "Hemsworth"
    ],
    "name:rus_x_preferred":[
        "\u0425\u0435\u043c\u0441\u0432\u043e\u0440\u0444"
    ],
    "name:spa_x_preferred":[
        "Hemsworth"
    ],
    "name:swe_x_preferred":[
        "Hemsworth"
    ],
    "name:tel_x_preferred":[
        "\u0c39\u0c46\u0c2e\u0c4d\u0c38\u0c4d\u0c35\u0c30\u0c4d\u0c24\u0c4d"
    ],
    "name:tur_x_preferred":[
        "Hemsworth"
    ],
    "name:ukr_x_preferred":[
        "\u0413\u0435\u043c\u0441\u0432\u043e\u0440\u0442"
    ],
    "name:urd_x_preferred":[
        "\u06c1\u06cc\u0645\u0633\u0648\u0648\u0631\u062a\u06be"
    ],
    "qs:a0":"United Kingdom",
    "qs:a1":"*Wakefield",
    "qs:a1_lc":"GB12DB0000",
    "qs:a1r":"0England",
    "qs:a1r_lc":"GB12000000",
    "qs:adm0":"United Kingdom",
    "qs:la_lc":"*",
    "qs:level":"locality",
    "qs:loc":"Hemsworth",
    "qs:loc_alt":"Hemsworth",
    "qs:pop":0,
    "qs:type":"buffered point",
    "wd:wordcount":653,
    "wof:name":"Hemsworth",
    "wof:placetype":"neighbourhood"
},
  "geometry": {"coordinates":[-1.34989,53.609344],"type":"Point"}
}