{
  "type": "Feature",
  "properties": {
    "iso:country": "GB",
    "name:azb_x_preferred": [
      "همسوورث"
    ],
    "name:ben_x_preferred": [
      "হেমসওর্থ"
    ],
    "name:ceb_x_preferred": [
      "Hemsworth"
    ],
    "name:cym_x_preferred": [
      "Hemsworth"
    ],
    "name:deu_x_preferred": [
      "Hemsworth"
    ],
    "name:eng_x_preferred": [
      "Hemsworth"
    ],
    "name:fas_x_preferred": [
      "همسوورث"
    ],
    "name:fra_x_preferred": [
      "Hemsworth"
    ],
    "name:gle_x_preferred": [
      "Hemsworth"
    ],
    "name:guj_x_preferred": [
      "હેમ્સવર્થ"
    ],
    "name:heb_x_preferred": [
      "המסוורת'"
    ],
    "name:ita_x_preferred": [
      "Hemsworth"
    ],
    "name:jpn_x_preferred": [
      "ヘムズワース"
    ],
    "name:kan_x_preferred": [
      "ಹೆಮ್ಸ್ವರ್ತ್"
    ],
    "name:kor_x_preferred": [
      "햄스워스"
    ],
    "name:lit_x_preferred": [
      "Hemsvortas"
    ],
    "name:nld_x_preferred": [
      "Hemsworth"
    ],
    "name:nno_x_preferred": [
      "Hemsworth"
    ],
    "name:pol_x_preferred": [
      "Hemsworth"
    ],
    "name:por_x_preferred": [
      "Hemsworth"
    ],
    "name:ron_x_preferred": [
      "Hemsworth"
    ],
    "name:rus_x_preferred": [
      "Хемсворф"
    ],
    "name:spa_x_preferred": [
      "Hemsworth"
    ],
    "name:swe_x_preferred": [
      "Hemsworth"
    ],
    "name:tel_x_preferred": [
      "హెమ్స్వర్త్"
    ],
    "name:urd_x_preferred": [
      "ہیمسوورتھ"
    ],
    "qs:a0": "United Kingdom",
    "qs:a1": "*Wakefield",
    "qs:a1_lc": "GB12DB0000",
    "qs:a1r": "0England",
    "qs:a1r_lc": "GB12000000",
    "qs:adm0": "United Kingdom",
    "qs:la_lc": "*",
    "qs:level": "locality",
    "qs:loc": "Hemsworth",
    "qs:loc_alt": "Hemsworth",
    "qs:pop": 0,
    "qs:type": "buffered point",
    "wd:wordcount": 653,
    "wof:name": "Hemsworth",
    "wof:placetype": "neighbourhood"
  },
  "geometry": {"coordinates":[-1.34989,53.609344],"type":"Point"}
}
