{
  "type": "Feature",
  "properties": {
    "gn:country":"GB",
    "gn:fcode":"PPL",
    "gn:population":0,
    "iso:country":"GB",
    "name:ceb_x_preferred":[
        "West Row"
    ],
    "name:eng_x_preferred":[
        "West Row"
    ],
    "name:fra_x_preferred":[
        "West Row"
    ],
    "name:gle_x_preferred":[
        "West Row"
    ],
    "name:lld_x_preferred":[
        "West Row"
    ],
    "name:nld_x_preferred":[
        "West Row"
    ],
    "name:pol_x_preferred":[
        "West Row"
    ],
    "name:swe_x_preferred":[
        "West Row"
    ],
    "name:tur_x_preferred":[
        "West Row"
    ],
    "qs_pg:aaroncc":"GB",
    "qs_pg:gn_country":"GB",
    "qs_pg:gn_fcode":"PPL",
    "qs_pg:gn_pop":0,
    "qs_pg:name":"West Row",
    "qs_pg:name_adm0":"United Kingdom",
    "qs_pg:name_adm1":"England",
    "qs_pg:photos":356,
    "qs_pg:photos_1k":72,
    "qs_pg:photos_9k":2,
    "qs_pg:photos_9r":5,
    "qs_pg:photos_all":356,
    "qs_pg:photos_sr":6,
    "qs_pg:pop_sr":0,
    "qs_pg:qs_pg_placetype":"locality",
    "qs_pg:qs_pg_placetype_gp":"Town",
    "qs_pg:woe_adm0":23424975,
    "woe:adm0_id":23424975,
    "woe:name_adm0":"United Kingdom",
    "woe:name_adm1":"England",
    "woe:placetype":"Town",
    "wof:name":"West Row",
    "wof:placetype":"neighbourhood"
},
  "geometry": {"coordinates":[0.46121,52.35117],"type":"Point"}
}