{
  "type": "Feature",
  "properties": {
    "gn:admin1_code":"NIR",
    "gn:admin2_code":"N09000010",
    "gn:asciiname":"Ballyculter",
    "gn:country_code":"GB",
    "gn:dem":25,
    "gn:feature_class":"P",
    "gn:feature_code":"PPL",
    "gn:name":"Ballyculter",
    "gn:population":0,
    "gn:timezone":"Europe/London",
    "iso:country":"GB",
    "wof:name":"Ballyculter",
    "wof:placetype":"locality"
},
  "geometry": {"coordinates":[-5.58333,54.33333],"type":"Point"}
}