{
  "type": "Feature",
  "properties": {
    "iso:country":"GB",
    "name:eng_x_preferred":[
        "Eashing"
    ],
    "qs:a0":"United Kingdom",
    "qs:a1":"*Surrey",
    "qs:a1_lc":"GB12430000",
    "qs:a1r":"0England",
    "qs:a1r_lc":"GB12000000",
    "qs:adm0":"United Kingdom",
    "qs:la_lc":"*",
    "qs:level":"locality",
    "qs:loc":"Eashing",
    "qs:loc_alt":"Eashing",
    "qs:pop":0,
    "qs:type":"buffered point",
    "wof:name":"Eashing",
    "wof:placetype":"neighbourhood"
},
  "geometry": {"coordinates":[-0.651994,51.187821],"type":"Point"}
}