{
  "type": "Feature",
  "properties": {
    "iso:country":"GB",
    "name:ceb_x_preferred":[
        "Grove"
    ],
    "name:dan_x_preferred":[
        "Grove"
    ],
    "name:deu_x_preferred":[
        "Grove"
    ],
    "name:epo_x_preferred":[
        "Grove"
    ],
    "name:eus_x_preferred":[
        "Grove"
    ],
    "name:fin_x_preferred":[
        "Grove"
    ],
    "name:fra_x_preferred":[
        "Grove"
    ],
    "name:heb_x_preferred":[
        "\u05d2\u05e8\u05d5\u05d1"
    ],
    "name:ita_x_preferred":[
        "Grove"
    ],
    "name:nld_x_preferred":[
        "Grove"
    ],
    "name:pol_x_preferred":[
        "Grove"
    ],
    "name:por_x_preferred":[
        "Grove"
    ],
    "name:rus_x_preferred":[
        "\u0413\u0440\u043e\u0443\u0432"
    ],
    "name:spa_x_preferred":[
        "Grove"
    ],
    "name:swe_x_preferred":[
        "Grove"
    ],
    "name:ukr_x_preferred":[
        "\u0413\u0440\u043e\u0432"
    ],
    "name:vol_x_preferred":[
        "Grove"
    ],
    "qs_pg:aaroncc":"GB",
    "qs_pg:name":"Grove",
    "qs_pg:name_adm0":"United Kingdom",
    "qs_pg:name_adm1":"England",
    "qs_pg:photos":79,
    "qs_pg:photos_1k":16,
    "qs_pg:photos_9k":1,
    "qs_pg:photos_9r":3,
    "qs_pg:photos_all":79,
    "qs_pg:photos_sr":3,
    "qs_pg:pop_sr":0,
    "qs_pg:qs_pg_placetype":"locality",
    "qs_pg:qs_pg_placetype_gp":"Town",
    "qs_pg:woe_adm0":23424975,
    "woe:adm0_id":23424975,
    "woe:name_adm0":"United Kingdom",
    "woe:name_adm1":"England",
    "woe:placetype":"Town",
    "wof:name":"Grove",
    "wof:placetype":"neighbourhood"
},
  "geometry": {"coordinates":[1.211929,51.316022],"type":"Point"}
}