{
  "type": "Feature",
  "properties": {
    "gn:admin1_code": "ENG",
    "gn:admin2_code": "N3",
    "gn:admin3_code": "00EF019",
    "gn:asciiname": "Norton",
    "gn:cc2": "GB",
    "gn:country_code": "GB",
    "gn:dem": 86,
    "gn:feature_class": "P",
    "gn:feature_code": "PPL",
    "gn:name": "Norton",
    "gn:population": 0,
    "gn:timezone": "Europe/London",
    "iso:country": "GB",
    "name:ara_x_preferred": [
      "نورتون"
    ],
    "name:bar_x_preferred": [
      "Norton"
    ],
    "name:cat_x_preferred": [
      "Norton"
    ],
    "name:ceb_x_preferred": [
      "Norton"
    ],
    "name:ces_x_preferred": [
      "Norton"
    ],
    "name:cym_x_preferred": [
      "Norton"
    ],
    "name:dan_x_preferred": [
      "Norton"
    ],
    "name:deu_x_preferred": [
      "Norton"
    ],
    "name:fas_x_preferred": [
      "نورتون"
    ],
    "name:fin_x_preferred": [
      "Norton"
    ],
    "name:fra_x_preferred": [
      "Norton"
    ],
    "name:heb_x_preferred": [
      "נורטון"
    ],
    "name:hun_x_preferred": [
      "Norton"
    ],
    "name:ita_x_preferred": [
      "Norton"
    ],
    "name:jpn_x_preferred": [
      "ノートン"
    ],
    "name:nld_x_preferred": [
      "Norton"
    ],
    "name:pol_x_preferred": [
      "Norton"
    ],
    "name:por_x_preferred": [
      "Norton"
    ],
    "name:rus_x_preferred": [
      "Нортон"
    ],
    "name:spa_x_preferred": [
      "Norton"
    ],
    "name:srp_x_preferred": [
      "Нортон"
    ],
    "name:swa_x_preferred": [
      "Norton"
    ],
    "name:swe_x_preferred": [
      "Norton"
    ],
    "name:ukr_x_preferred": [
      "Нортон"
    ],
    "name:und_x_variant": [
      "Tees Norton",
      "Norton-on-Tees"
    ],
    "name:vol_x_preferred": [
      "Norton"
    ],
    "wof:name": "Norton",
    "wof:placetype": "neighbourhood"
  },
  "geometry": {"coordinates":[-1.47938,54.65854],"type":"Point"}
}
