{
  "type": "Feature",
  "properties": {
    "gn:admin1_code":"ENG",
    "gn:admin2_code":"N3",
    "gn:admin3_code":"00EF019",
    "gn:asciiname":"Norton",
    "gn:cc2":"GB",
    "gn:country_code":"GB",
    "gn:dem":86,
    "gn:feature_class":"P",
    "gn:feature_code":"PPL",
    "gn:name":"Norton",
    "gn:population":0,
    "gn:timezone":"Europe/London",
    "iso:country":"GB",
    "name:und_x_variant":[
        "Tees Norton",
        "Norton-on-Tees",
        "Norton"
    ],
    "wof:name":"Norton",
    "wof:placetype":"neighbourhood"
},
  "geometry": {"coordinates":[-1.47938,54.65854],"type":"Point"}
}