{
  "type": "Feature",
  "properties": {
    "gn:admin1_code":"ENG",
    "gn:admin2_code":"N3",
    "gn:admin3_code":"00EF019",
    "gn:asciiname":"Norton",
    "gn:cc2":"GB",
    "gn:country_code":"GB",
    "gn:dem":86,
    "gn:feature_class":"P",
    "gn:feature_code":"PPL",
    "gn:name":"Norton",
    "gn:population":0,
    "gn:timezone":"Europe/London",
    "iso:country":"GB",
    "name:ara_x_preferred":[
        "\u0646\u0648\u0631\u062a\u0648\u0646"
    ],
    "name:bar_x_preferred":[
        "Norton"
    ],
    "name:cat_x_preferred":[
        "Norton"
    ],
    "name:ceb_x_preferred":[
        "Norton"
    ],
    "name:ces_x_preferred":[
        "Norton"
    ],
    "name:cym_x_preferred":[
        "Norton"
    ],
    "name:dan_x_preferred":[
        "Norton"
    ],
    "name:deu_x_preferred":[
        "Norton"
    ],
    "name:fas_x_preferred":[
        "\u0646\u0648\u0631\u062a\u0648\u0646"
    ],
    "name:fin_x_preferred":[
        "Norton"
    ],
    "name:fra_x_preferred":[
        "Norton"
    ],
    "name:heb_x_preferred":[
        "\u05e0\u05d5\u05e8\u05d8\u05d5\u05df"
    ],
    "name:hun_x_preferred":[
        "Norton"
    ],
    "name:ita_x_preferred":[
        "Norton"
    ],
    "name:jpn_x_preferred":[
        "\u30ce\u30fc\u30c8\u30f3"
    ],
    "name:nld_x_preferred":[
        "Norton"
    ],
    "name:pol_x_preferred":[
        "Norton"
    ],
    "name:por_x_preferred":[
        "Norton"
    ],
    "name:rus_x_preferred":[
        "\u041d\u043e\u0440\u0442\u043e\u043d"
    ],
    "name:spa_x_preferred":[
        "Norton"
    ],
    "name:srp_x_preferred":[
        "\u041d\u043e\u0440\u0442\u043e\u043d"
    ],
    "name:swa_x_preferred":[
        "Norton"
    ],
    "name:swe_x_preferred":[
        "Norton"
    ],
    "name:ukr_x_preferred":[
        "\u041d\u043e\u0440\u0442\u043e\u043d"
    ],
    "name:und_x_variant":[
        "Tees Norton",
        "Norton-on-Tees"
    ],
    "name:vol_x_preferred":[
        "Norton"
    ],
    "wof:name":"Norton",
    "wof:placetype":"neighbourhood"
},
  "geometry": {"coordinates":[-1.47938,54.65854],"type":"Point"}
}