{
  "type": "Feature",
  "properties": {
    "iso:country":"GB",
    "name:eng_x_preferred":[
        "Bill Quay"
    ],
    "name:unk_x_variant":[
        "Bill Quay"
    ],
    "qs:gn_local":0,
    "qs:local_max":6046,
    "qs:local_sum":22603,
    "qs:localhoods":17,
    "qs:name":"Bill Quay",
    "qs:name_adm0":"United Kingdom",
    "qs:name_adm1":"England",
    "qs:name_adm2":"Tyne and Wear",
    "qs:name_lau":"Gateshead Metropolitan Borough",
    "qs:name_local":"Gateshead",
    "qs:photo_max":173,
    "qs:photo_sum":803,
    "qs:placetype":"Suburb",
    "qs:quad_count":47,
    "qs:woe_adm0":23424975,
    "qs:woe_adm1":24554868,
    "qs:woe_adm2":12602156,
    "qs:woe_lau":12695858,
    "qs:woe_local":20928,
    "qs:woe_ver":"7.10.0",
    "wd:wordcount":386,
    "wof:lang":[
        "eng"
    ],
    "wof:name":"Bill Quay",
    "wof:placetype":"neighbourhood"
},
  "geometry": {"coordinates":[-1.538257,54.95752],"type":"Point"}
}