{
  "type": "Feature",
  "properties": {
    "iso:country": "GB",
    "name:eng_x_preferred": [
      "Brockhurst"
    ],
    "name:fra_x_preferred": [
      "Brockhurst"
    ],
    "qs:gn_adm0_cc": "GB",
    "qs:gn_fcode": "PPL",
    "qs:gn_local": 2648272,
    "qs:gn_nam_loc": "gosport",
    "qs:gn_namadm1": "ENG",
    "qs:gn_name": "Brockhurst",
    "qs:local_max": 4206,
    "qs:local_sum": 8405,
    "qs:localhoods": 4,
    "qs:name": "Brockhurst",
    "qs:name_adm0": "United Kingdom",
    "qs:name_adm1": "England",
    "qs:name_adm2": "Hampshire",
    "qs:name_lau": "Gosport Borough",
    "qs:name_local": "Gosport",
    "qs:photo_max": 3378,
    "qs:photo_sum": 4206,
    "qs:placetype": "Suburb",
    "qs:quad_count": 65,
    "qs:woe_adm0": 23424975,
    "qs:woe_adm1": 24554868,
    "qs:woe_adm2": 12602169,
    "qs:woe_lau": 12695962,
    "qs:woe_local": 21418,
    "qs:woe_ver": "7.10.0",
    "wd:wordcount": 187,
    "wof:lang": [
      "eng"
    ],
    "wof:name": "Brockhurst",
    "wof:placetype": "neighbourhood"
  },
  "geometry": {"coordinates":[-1.156913,50.794206],"type":"Point"}
}
