{
  "type": "Feature",
  "properties": {
    "gn:country": "GB",
    "gn:fcode": "PPL",
    "gn:population": 0,
    "iso:country": "GB",
    "name:bul_x_preferred": [
      "Дурнес"
    ],
    "name:cat_x_preferred": [
      "Durness"
    ],
    "name:ceb_x_preferred": [
      "Durness"
    ],
    "name:deu_x_preferred": [
      "Durness"
    ],
    "name:eng_x_preferred": [
      "Durness"
    ],
    "name:eus_x_preferred": [
      "Durness"
    ],
    "name:fra_x_preferred": [
      "Durness"
    ],
    "name:gla_x_preferred": [
      "Diùranais"
    ],
    "name:gle_x_preferred": [
      "Diúranais"
    ],
    "name:heb_x_preferred": [
      "ריספונד"
    ],
    "name:ita_x_preferred": [
      "Durness"
    ],
    "name:jpn_x_preferred": [
      "ダーネス"
    ],
    "name:lit_x_preferred": [
      "Dernesas"
    ],
    "name:nld_x_preferred": [
      "Durness"
    ],
    "name:spa_x_preferred": [
      "Durness"
    ],
    "name:swe_x_preferred": [
      "Durness"
    ],
    "qs_pg:aaroncc": "GB",
    "qs_pg:gn_country": "GB",
    "qs_pg:gn_fcode": "PPL",
    "qs_pg:gn_pop": 0,
    "qs_pg:name": "Durness",
    "qs_pg:name_adm0": "United Kingdom",
    "qs_pg:name_adm1": "Scotland",
    "qs_pg:photos": 471,
    "qs_pg:photos_1k": 95,
    "qs_pg:photos_9k": 2,
    "qs_pg:photos_9r": 5,
    "qs_pg:photos_all": 471,
    "qs_pg:photos_sr": 7,
    "qs_pg:pop_sr": 0,
    "qs_pg:qs_pg_placetype": "locality",
    "qs_pg:qs_pg_placetype_gp": "Town",
    "qs_pg:woe_adm0": 23424975,
    "woe:adm0_id": 23424975,
    "woe:name_adm0": "United Kingdom",
    "woe:name_adm1": "Scotland",
    "woe:placetype": "Town",
    "wof:name": "Durness",
    "wof:placetype": "locality"
  },
  "geometry": {"coordinates":[-4.74632,58.56829],"type":"Point"}
}
