{
  "type": "Feature",
  "properties": {
    "iso:country":"GB",
    "name:ben_x_preferred":[
        "\u09a1\u09cd\u09b0\u09bf\u0982\u09b9\u09be\u0989\u09b8"
    ],
    "name:deu_x_preferred":[
        "Dringhouses"
    ],
    "name:eng_x_preferred":[
        "Dringhouses"
    ],
    "name:fra_x_preferred":[
        "Dringhouses"
    ],
    "name:gle_x_preferred":[
        "Dringhouses"
    ],
    "name:guj_x_preferred":[
        "\u0aa1\u0acd\u0ab0\u0abf\u0a82\u0a97\u0ab9\u0abe\u0a89\u0ab8\u0ac0\u0ab8"
    ],
    "name:jpn_x_preferred":[
        "\u30c9\u30ea\u30f3\u30b0\u30cf\u30a6\u30b8\u30ba"
    ],
    "name:kan_x_preferred":[
        "\u0ca1\u0ccd\u0cb0\u0cbf\u0c82\u0c97\u0ccd\u0cb9\u0ccc\u0cb8\u0cc6\u0cb8\u0ccd"
    ],
    "name:kor_x_preferred":[
        "\ub4dc\ub9c1\ud06c\ud558\uc6b0\uc2a4"
    ],
    "name:lit_x_preferred":[
        "Dringhausesas"
    ],
    "name:por_x_preferred":[
        "Dringhouses"
    ],
    "name:rus_x_preferred":[
        "\u0414\u0440\u0438\u043d\u0433\u0445\u0430\u0443\u0441\u0435\u0441"
    ],
    "name:spa_x_preferred":[
        "Dringhouses"
    ],
    "name:tam_x_preferred":[
        "\u0b9f\u0bcd\u0bb0\u0bbf\u0b99\u0bcd\u0bb9\u0bcc\u0bb8\u0bbf\u0bb8\u0bcd"
    ],
    "name:tel_x_preferred":[
        "\u0c21\u0c4d\u0c30\u0c3f\u0c02\u0c17\u0c4d\u0c39\u0c4c\u0c38\u0c46\u0c38\u0c4d"
    ],
    "name:urd_x_preferred":[
        "\u062f\u0631\u06cc\u0646\u06af\u06be\u0648\u0648\u0633\u06cc\u0633"
    ],
    "qs:gn_fcode":"PPL",
    "qs:gn_local":0,
    "qs:gn_namadm1":"ENG",
    "qs:gn_name":"Brighouse",
    "qs:local_max":6977,
    "qs:local_sum":18915,
    "qs:localhoods":4,
    "qs:name":"Dringhouses",
    "qs:name_adm0":"United Kingdom",
    "qs:name_adm1":"England",
    "qs:name_adm2":"North Yorkshire",
    "qs:name_lau":"York City",
    "qs:name_local":"York",
    "qs:photo_max":311,
    "qs:photo_sum":2327,
    "qs:placetype":"Suburb",
    "qs:quad_count":95,
    "qs:woe_adm0":23424975,
    "qs:woe_adm1":24554868,
    "qs:woe_adm2":12602195,
    "qs:woe_lau":12696148,
    "qs:woe_local":41415,
    "qs:woe_ver":"7.10.0",
    "wd:wordcount":2097,
    "wof:lang":[
        "eng"
    ],
    "wof:name":"Dringhouses",
    "wof:placetype":"neighbourhood"
},
  "geometry": {"coordinates":[-1.096997,53.946889],"type":"Point"}
}