{
  "type": "Feature",
  "properties": {
    "iso:country": "GB",
    "name:ben_x_preferred": [
      "ড্রিংহাউস"
    ],
    "name:deu_x_preferred": [
      "Dringhouses"
    ],
    "name:eng_x_preferred": [
      "Dringhouses"
    ],
    "name:fra_x_preferred": [
      "Dringhouses"
    ],
    "name:gle_x_preferred": [
      "Dringhouses"
    ],
    "name:guj_x_preferred": [
      "ડ્રિંગહાઉસીસ"
    ],
    "name:jpn_x_preferred": [
      "ドリングハウジズ"
    ],
    "name:kan_x_preferred": [
      "ಡ್ರಿಂಗ್ಹೌಸೆಸ್"
    ],
    "name:kor_x_preferred": [
      "드링크하우스"
    ],
    "name:lit_x_preferred": [
      "Dringhausesas"
    ],
    "name:por_x_preferred": [
      "Dringhouses"
    ],
    "name:rus_x_preferred": [
      "Дрингхаусес"
    ],
    "name:spa_x_preferred": [
      "Dringhouses"
    ],
    "name:tam_x_preferred": [
      "ட்ரிங்ஹௌஸிஸ்"
    ],
    "name:tel_x_preferred": [
      "డ్రింగ్హౌసెస్"
    ],
    "name:urd_x_preferred": [
      "درینگھووسیس"
    ],
    "qs:gn_fcode": "PPL",
    "qs:gn_local": 0,
    "qs:gn_namadm1": "ENG",
    "qs:gn_name": "Brighouse",
    "qs:local_max": 6977,
    "qs:local_sum": 18915,
    "qs:localhoods": 4,
    "qs:name": "Dringhouses",
    "qs:name_adm0": "United Kingdom",
    "qs:name_adm1": "England",
    "qs:name_adm2": "North Yorkshire",
    "qs:name_lau": "York City",
    "qs:name_local": "York",
    "qs:photo_max": 311,
    "qs:photo_sum": 2327,
    "qs:placetype": "Suburb",
    "qs:quad_count": 95,
    "qs:woe_adm0": 23424975,
    "qs:woe_adm1": 24554868,
    "qs:woe_adm2": 12602195,
    "qs:woe_lau": 12696148,
    "qs:woe_local": 41415,
    "qs:woe_ver": "7.10.0",
    "wd:wordcount": 2097,
    "wof:lang": [
      "eng"
    ],
    "wof:name": "Dringhouses",
    "wof:placetype": "neighbourhood"
  },
  "geometry": {"coordinates":[-1.096997,53.946889],"type":"Point"}
}
