{
  "type": "Feature",
  "properties": {
    "iso:country":"GB",
    "name:eng_x_preferred":[
        "Trumpington"
    ],
    "name:nld_x_preferred":[
        "Trumpington"
    ],
    "name:pol_x_preferred":[
        "Trumpington"
    ],
    "name:swe_x_preferred":[
        "Trumpington"
    ],
    "name:unk_x_variant":[
        "Trumpington"
    ],
    "name:zho_x_preferred":[
        "\u7279\u862d\u5e73\u9813"
    ],
    "qs:gn_adm0_cc":"GB",
    "qs:gn_fcode":"PPL",
    "qs:gn_local":2653941,
    "qs:gn_nam_loc":"Cambridge, Cambridgeshire, Cambridge, England, GB",
    "qs:gn_namadm1":"ENG",
    "qs:gn_name":"Trumpington",
    "qs:local_max":12386,
    "qs:local_sum":48350,
    "qs:localhoods":5,
    "qs:name":"Trumpington",
    "qs:name_adm0":"United Kingdom",
    "qs:name_adm1":"England",
    "qs:name_adm2":"Cambridgeshire",
    "qs:name_lau":"Cambridge City",
    "qs:name_local":"Cambridge",
    "qs:photo_max":617,
    "qs:photo_sum":10130,
    "qs:placetype":"Suburb",
    "qs:quad_count":402,
    "qs:woe_adm0":23424975,
    "qs:woe_adm1":24554868,
    "qs:woe_adm2":12602140,
    "qs:woe_lau":12695882,
    "qs:woe_local":14979,
    "qs:woe_ver":"7.10.0",
    "wd:wordcount":993,
    "wof:lang":[
        "eng"
    ],
    "wof:name":"Trumpington",
    "wof:placetype":"neighbourhood"
},
  "geometry": {"coordinates":[0.128009,52.180497],"type":"Point"}
}