{
  "type": "Feature",
  "properties": {
    "iso:country":"GB",
    "name:eng_x_preferred":[
        "Airntully"
    ],
    "name:eus_x_preferred":[
        "Airntully"
    ],
    "name:fra_x_preferred":[
        "Airntully"
    ],
    "name:nld_x_preferred":[
        "Airntully"
    ],
    "name:sco_x_preferred":[
        "Airntully"
    ],
    "qs_pg:aaroncc":"GB",
    "qs_pg:name":"Airntully",
    "qs_pg:name_adm0":"United Kingdom",
    "qs_pg:name_adm1":"Scotland",
    "qs_pg:photos":26,
    "qs_pg:photos_1k":5,
    "qs_pg:photos_9k":1,
    "qs_pg:photos_9r":2,
    "qs_pg:photos_all":26,
    "qs_pg:photos_sr":2,
    "qs_pg:pop_sr":0,
    "qs_pg:qs_pg_placetype":"locality",
    "qs_pg:qs_pg_placetype_gp":"Town",
    "qs_pg:woe_adm0":23424975,
    "woe:adm0_id":23424975,
    "woe:name_adm0":"United Kingdom",
    "woe:name_adm1":"Scotland",
    "woe:placetype":"Town",
    "wof:name":"Airntully",
    "wof:placetype":"locality"
},
  "geometry": {"coordinates":[-3.474512,56.504671],"type":"Point"}
}