{
  "type": "Feature",
  "properties": {
    "gn:country":"GB",
    "gn:fcode":"PPL",
    "gn:population":0,
    "iso:country":"GB",
    "name:azb_x_preferred":[
        "\u067e\u0648\u0644\u0627"
    ],
    "name:cat_x_preferred":[
        "Polla"
    ],
    "name:ceb_x_preferred":[
        "Polla"
    ],
    "name:ita_x_preferred":[
        "Polla"
    ],
    "name:rus_x_preferred":[
        "\u041f\u043e\u043b\u043b\u0430"
    ],
    "name:spa_x_preferred":[
        "Polla"
    ],
    "name:swe_x_preferred":[
        "Polla"
    ],
    "qs_pg:aaroncc":"GB",
    "qs_pg:gn_country":"GB",
    "qs_pg:gn_fcode":"PPL",
    "qs_pg:gn_pop":0,
    "qs_pg:name":"Polla",
    "qs_pg:name_adm0":"United Kingdom",
    "qs_pg:name_adm1":"Scotland",
    "qs_pg:photos":127,
    "qs_pg:photos_1k":26,
    "qs_pg:photos_9k":1,
    "qs_pg:photos_9r":3,
    "qs_pg:photos_all":127,
    "qs_pg:photos_sr":3,
    "qs_pg:pop_sr":0,
    "qs_pg:qs_pg_placetype":"locality",
    "qs_pg:qs_pg_placetype_gp":"Town",
    "qs_pg:woe_adm0":23424975,
    "woe:adm0_id":23424975,
    "woe:name_adm0":"United Kingdom",
    "woe:name_adm1":"Scotland",
    "woe:placetype":"Town",
    "wof:name":"Polla",
    "wof:placetype":"locality"
},
  "geometry": {"coordinates":[-4.76669,58.44935],"type":"Point"}
}