{
  "type": "Feature",
  "properties": {
    "gn:gn_country":"GB",
    "gn:gn_fcode":"PPL",
    "gn:gn_pop":440,
    "gn:population":440,
    "iso:country":"GB",
    "name:ceb_x_preferred":[
        "West Dereham"
    ],
    "name:cym_x_preferred":[
        "West Dereham"
    ],
    "name:eng_x_preferred":[
        "West Dereham"
    ],
    "name:fas_x_preferred":[
        "\u0648\u0633\u062a \u062f\u0631\u0647\u0627\u0645"
    ],
    "name:fra_x_preferred":[
        "West Dereham"
    ],
    "name:ita_x_preferred":[
        "West Dereham"
    ],
    "name:nld_x_preferred":[
        "West Dereham"
    ],
    "name:pol_x_preferred":[
        "West Dereham"
    ],
    "name:swe_x_preferred":[
        "West Dereham "
    ],
    "name:swe_x_variant":[
        "West Dereham"
    ],
    "qs_pg:aaroncc":"GB",
    "qs_pg:gn_country":"GB",
    "qs_pg:gn_fcode":"PPL",
    "qs_pg:gn_pop":440,
    "qs_pg:name":"West Earlham",
    "qs_pg:name_adm0":"United Kingdom",
    "qs_pg:name_adm1":"England",
    "qs_pg:photos_9r":0,
    "qs_pg:photos_sr":0,
    "qs_pg:pop_sr":2,
    "qs_pg:qs_pg_placetype":"locality",
    "qs_pg:qs_pg_placetype_gp":"Town",
    "qs_pg:woe_adm0":23424975,
    "woe:adm0_id":23424975,
    "woe:name_adm0":"United Kingdom",
    "woe:name_adm1":"England",
    "woe:placetype":"Town",
    "wof:name":"West Earlham",
    "wof:placetype":"neighbourhood",
    "wof:population":440
},
  "geometry": {"coordinates":[0.44801,52.58148],"type":"Point"}
}