{
  "type": "Feature",
  "properties": {
    "gn:country": "GB",
    "gn:fcode": "PPL",
    "gn:population": 0,
    "iso:country": "GB",
    "name:ceb_x_preferred": [
      "Gresham"
    ],
    "name:deu_x_preferred": [
      "Gresham"
    ],
    "name:fra_x_preferred": [
      "Gresham"
    ],
    "name:heb_x_preferred": [
      "גרשם"
    ],
    "name:hun_x_preferred": [
      "Gresham"
    ],
    "name:ita_x_preferred": [
      "Gresham"
    ],
    "name:nds_x_preferred": [
      "Gresham"
    ],
    "name:nld_x_preferred": [
      "Gresham"
    ],
    "name:pol_x_preferred": [
      "Gresham"
    ],
    "name:por_x_preferred": [
      "Gresham"
    ],
    "name:spa_x_preferred": [
      "Gresham"
    ],
    "name:srp_x_preferred": [
      "Грешам"
    ],
    "name:swe_x_preferred": [
      "Gresham"
    ],
    "name:ukr_x_preferred": [
      "Грешем"
    ],
    "name:vol_x_preferred": [
      "Gresham"
    ],
    "qs_pg:aaroncc": "GB",
    "qs_pg:gn_country": "GB",
    "qs_pg:gn_fcode": "PPL",
    "qs_pg:gn_pop": 0,
    "qs_pg:name": "Gresham",
    "qs_pg:name_adm0": "United Kingdom",
    "qs_pg:name_adm1": "England",
    "qs_pg:photos": 9,
    "qs_pg:photos_1k": 2,
    "qs_pg:photos_9k": 1,
    "qs_pg:photos_9r": 1,
    "qs_pg:photos_all": 9,
    "qs_pg:photos_sr": 1,
    "qs_pg:pop_sr": 0,
    "qs_pg:qs_pg_placetype": "locality",
    "qs_pg:qs_pg_placetype_gp": "Town",
    "qs_pg:woe_adm0": 23424975,
    "woe:adm0_id": 23424975,
    "woe:name_adm0": "United Kingdom",
    "woe:name_adm1": "England",
    "woe:placetype": "Town",
    "wof:name": "Gresham",
    "wof:placetype": "neighbourhood"
  },
  "geometry": {"coordinates":[1.54108,52.4046],"type":"Point"}
}
