{
  "type": "Feature",
  "properties": {
    "gn:admin1_code":"SCT",
    "gn:admin2_code":"T6",
    "gn:asciiname":"Woodend",
    "gn:country_code":"GB",
    "gn:dem":106,
    "gn:feature_class":"P",
    "gn:feature_code":"PPLL",
    "gn:name":"Woodend",
    "gn:population":0,
    "gn:timezone":"Europe/London",
    "iso:country":"GB",
    "name:ceb_x_preferred":[
        "Woodend"
    ],
    "name:deu_x_preferred":[
        "Woodend"
    ],
    "name:fra_x_preferred":[
        "Woodend"
    ],
    "name:pol_x_preferred":[
        "Woodend"
    ],
    "name:swe_x_preferred":[
        "Woodend"
    ],
    "wof:name":"Woodend",
    "wof:placetype":"locality"
},
  "geometry": {"coordinates":[-2.21306,57.27709],"type":"Point"}
}