{
  "type": "Feature",
  "properties": {
    "iso:country": "GB",
    "name:eng_x_preferred": [
      "Anston"
    ],
    "name:eng_x_variant": [
      "Aston"
    ],
    "name:nld_x_preferred": [
      "Aston"
    ],
    "name:pol_x_preferred": [
      "Aston"
    ],
    "name:swe_x_preferred": [
      "Aston"
    ],
    "qs:a0": "United Kingdom",
    "qs:a1": "*Rotherham",
    "qs:a1_lc": "GB12CF0000",
    "qs:a1r": "0England",
    "qs:a1r_lc": "GB12000000",
    "qs:adm0": "United Kingdom",
    "qs:la_lc": "*",
    "qs:level": "locality",
    "qs:loc": "Anston",
    "qs:loc_alt": "Anston",
    "qs:pop": 0,
    "qs:type": "buffered point",
    "wof:name": "Anston",
    "wof:placetype": "neighbourhood"
  },
  "geometry": {"coordinates":[-1.212156,53.362226],"type":"Point"}
}
