{
  "type": "Feature",
  "properties": {
    "iso:country":"GB",
    "name:eng_x_preferred":[
        "Clephanton"
    ],
    "name:eus_x_preferred":[
        "Clephanton"
    ],
    "name:nld_x_preferred":[
        "Clephanton"
    ],
    "qs_pg:aaroncc":"GB",
    "qs_pg:name":"Clephanton",
    "qs_pg:name_adm0":"United Kingdom",
    "qs_pg:name_adm1":"Scotland",
    "qs_pg:photos":146,
    "qs_pg:photos_1k":30,
    "qs_pg:photos_9k":1,
    "qs_pg:photos_9r":3,
    "qs_pg:photos_all":146,
    "qs_pg:photos_sr":3,
    "qs_pg:pop_sr":0,
    "qs_pg:qs_pg_placetype":"locality",
    "qs_pg:qs_pg_placetype_gp":"Town",
    "qs_pg:woe_adm0":23424975,
    "woe:adm0_id":23424975,
    "woe:name_adm0":"United Kingdom",
    "woe:name_adm1":"Scotland",
    "woe:placetype":"Town",
    "wof:name":"Clephanton",
    "wof:placetype":"locality"
},
  "geometry": {"coordinates":[-3.93568,57.524303],"type":"Point"}
}