{
  "type": "Feature",
  "properties": {
    "iso:country":"GB",
    "name:eng_x_preferred":[
        "Balnafoich"
    ],
    "name:eus_x_preferred":[
        "Balnafoich"
    ],
    "name:gle_x_preferred":[
        "Baile Na Faich"
    ],
    "name:nld_x_preferred":[
        "Balnafoich"
    ],
    "qs_pg:aaroncc":"GB",
    "qs_pg:name":"Balnafoich",
    "qs_pg:name_adm0":"United Kingdom",
    "qs_pg:name_adm1":"Scotland",
    "qs_pg:photos":103,
    "qs_pg:photos_1k":21,
    "qs_pg:photos_9k":1,
    "qs_pg:photos_9r":3,
    "qs_pg:photos_all":103,
    "qs_pg:photos_sr":3,
    "qs_pg:pop_sr":0,
    "qs_pg:qs_pg_placetype":"locality",
    "qs_pg:qs_pg_placetype_gp":"Town",
    "qs_pg:woe_adm0":23424975,
    "woe:adm0_id":23424975,
    "woe:name_adm0":"United Kingdom",
    "woe:name_adm1":"Scotland",
    "woe:placetype":"Town",
    "wof:name":"Balnafoich",
    "wof:placetype":"locality"
},
  "geometry": {"coordinates":[-4.1918,57.393369],"type":"Point"}
}