{
  "type": "Feature",
  "properties": {
    "iso:country": "GB",
    "name:ces_x_preferred": [
      "Pier Head"
    ],
    "name:deu_x_preferred": [
      "Pier Head"
    ],
    "name:eng_x_preferred": [
      "Pier Head"
    ],
    "name:fas_x_preferred": [
      "پیر هد"
    ],
    "name:fra_x_preferred": [
      "Pier Head"
    ],
    "name:jpn_x_preferred": [
      "ピア・ヘッド"
    ],
    "name:nld_x_preferred": [
      "Pier Head"
    ],
    "name:pol_x_preferred": [
      "Pier Head"
    ],
    "name:pol_x_variant": [
      "Union Kloof"
    ],
    "name:slk_x_preferred": [
      "Pier Head"
    ],
    "name:spa_x_preferred": [
      "Pier Head"
    ],
    "name:zho_x_preferred": [
      "皮爾希德"
    ],
    "wd:wordcount": 1680,
    "wof:name": "Pier Head",
    "wof:placetype": "neighbourhood"
  },
  "geometry": {"coordinates":[-2.99665507880057,53.40504489571063],"type":"Point"}
}
