{
  "type": "Feature",
  "properties": {
    "name:ces_x_preferred":[
        "Pier Head"
    ],
    "name:deu_x_preferred":[
        "Pier Head"
    ],
    "name:eng_x_preferred":[
        "Pier Head"
    ],
    "name:fas_x_preferred":[
        "\u067e\u06cc\u0631 \u0647\u062f"
    ],
    "name:fra_x_preferred":[
        "Pier Head"
    ],
    "name:jpn_x_preferred":[
        "\u30d4\u30a2\u30fb\u30d8\u30c3\u30c9"
    ],
    "name:nld_x_preferred":[
        "Pier Head"
    ],
    "name:pol_x_preferred":[
        "Pier Head"
    ],
    "name:pol_x_variant":[
        "Union Kloof"
    ],
    "name:slk_x_preferred":[
        "Pier Head"
    ],
    "name:spa_x_preferred":[
        "Pier Head"
    ],
    "name:zho_x_preferred":[
        "\u76ae\u723e\u5e0c\u5fb7"
    ],
    "wd:wordcount":1680,
    "wof:name":"Pier Head",
    "wof:placetype":"neighbourhood"
},
  "geometry": {"coordinates":[-2.99665507880057,53.40504489571063],"type":"Point"}
}