{
  "type": "Feature",
  "properties": {
    "iso:country":"GB",
    "name:ceb_x_preferred":[
        "Dufftown"
    ],
    "name:ces_x_preferred":[
        "Dufftown"
    ],
    "name:cym_x_preferred":[
        "Dufftown"
    ],
    "name:deu_x_preferred":[
        "Dufftown"
    ],
    "name:eng_x_preferred":[
        "Dufftown"
    ],
    "name:eus_x_preferred":[
        "Dufftown"
    ],
    "name:fas_x_preferred":[
        "\u062f\u0627\u0641\u062a\u0627\u0648\u0646"
    ],
    "name:fra_x_preferred":[
        "Dufftown"
    ],
    "name:gla_x_preferred":[
        "Baile Bhainidh"
    ],
    "name:gle_x_preferred":[
        "Baile Bh\u00e1inidh"
    ],
    "name:hin_x_preferred":[
        "\u0921\u092b\u091f\u093e\u0909\u0928"
    ],
    "name:ita_x_preferred":[
        "Dufftown"
    ],
    "name:jpn_x_preferred":[
        "\u30c0\u30d5\u30bf\u30a6\u30f3"
    ],
    "name:nld_x_preferred":[
        "Dufftown"
    ],
    "name:nno_x_preferred":[
        "Dufftown"
    ],
    "name:nob_x_preferred":[
        "Dufftown"
    ],
    "name:nor_x_preferred":[
        "Dufftown"
    ],
    "name:pol_x_preferred":[
        "Dufftown"
    ],
    "name:rus_x_preferred":[
        "\u0414\u0430\u0444\u0442\u0430\u0443\u043d"
    ],
    "name:sco_x_preferred":[
        "Dufftoun"
    ],
    "name:spa_x_preferred":[
        "Dufftown"
    ],
    "name:swe_x_preferred":[
        "Dufftown"
    ],
    "name:zho_x_preferred":[
        "\u675c\u592b\u6566"
    ],
    "qs:a0":"United Kingdom",
    "qs:a1":"*Moray",
    "qs:a1_lc":"GB11QX0000",
    "qs:a1r":"0Scotland",
    "qs:a1r_lc":"GB11000000",
    "qs:adm0":"United Kingdom",
    "qs:la_lc":"*",
    "qs:level":"locality",
    "qs:loc":"Dufftown",
    "qs:loc_alt":"Dufftown",
    "qs:pop":0,
    "qs:type":"buffered point",
    "wd:wordcount":664,
    "wof:name":"Dufftown",
    "wof:placetype":"locality"
},
  "geometry": {"coordinates":[-3.129403,57.444506],"type":"Point"}
}