{
  "type": "Feature",
  "properties": {
    "iso:country": "GB",
    "name:ceb_x_preferred": [
      "Dufftown"
    ],
    "name:ces_x_preferred": [
      "Dufftown"
    ],
    "name:cym_x_preferred": [
      "Dufftown"
    ],
    "name:deu_x_preferred": [
      "Dufftown"
    ],
    "name:eng_x_preferred": [
      "Dufftown"
    ],
    "name:eus_x_preferred": [
      "Dufftown"
    ],
    "name:fas_x_preferred": [
      "دافتاون"
    ],
    "name:fra_x_preferred": [
      "Dufftown"
    ],
    "name:gla_x_preferred": [
      "Baile Bhainidh"
    ],
    "name:gle_x_preferred": [
      "Baile Bháinidh"
    ],
    "name:hin_x_preferred": [
      "डफटाउन"
    ],
    "name:ita_x_preferred": [
      "Dufftown"
    ],
    "name:jpn_x_preferred": [
      "ダフタウン"
    ],
    "name:nld_x_preferred": [
      "Dufftown"
    ],
    "name:nno_x_preferred": [
      "Dufftown"
    ],
    "name:nob_x_preferred": [
      "Dufftown"
    ],
    "name:nor_x_preferred": [
      "Dufftown"
    ],
    "name:pol_x_preferred": [
      "Dufftown"
    ],
    "name:rus_x_preferred": [
      "Дафтаун"
    ],
    "name:sco_x_preferred": [
      "Dufftoun"
    ],
    "name:spa_x_preferred": [
      "Dufftown"
    ],
    "name:swe_x_preferred": [
      "Dufftown"
    ],
    "name:zho_x_preferred": [
      "杜夫敦"
    ],
    "qs:a0": "United Kingdom",
    "qs:a1": "*Moray",
    "qs:a1_lc": "GB11QX0000",
    "qs:a1r": "0Scotland",
    "qs:a1r_lc": "GB11000000",
    "qs:adm0": "United Kingdom",
    "qs:la_lc": "*",
    "qs:level": "locality",
    "qs:loc": "Dufftown",
    "qs:loc_alt": "Dufftown",
    "qs:pop": 0,
    "qs:type": "buffered point",
    "wd:wordcount": 664,
    "wof:name": "Dufftown",
    "wof:placetype": "locality"
  },
  "geometry": {"coordinates":[-3.129403,57.444506],"type":"Point"}
}
