{
  "type": "Feature",
  "properties": {
    "gn:country": "GB",
    "gn:fcode": "PPL",
    "gn:population": 1286,
    "iso:country": "GB",
    "name:bul_x_preferred": [
      "Гленариф"
    ],
    "name:ceb_x_preferred": [
      "Glenariff"
    ],
    "name:eng_x_preferred": [
      "Glenariff"
    ],
    "name:gle_x_preferred": [
      "Gleann Aireamh"
    ],
    "name:lit_x_preferred": [
      "Glenarifas"
    ],
    "name:nld_x_preferred": [
      "Glenariff"
    ],
    "name:swe_x_preferred": [
      "Glenariff"
    ],
    "name:und_x_variant": [
      "Warren"
    ],
    "qs_pg:aaroncc": "GB",
    "qs_pg:gn_country": "GB",
    "qs_pg:gn_fcode": "PPL",
    "qs_pg:gn_pop": 1286,
    "qs_pg:name": "Glenariff",
    "qs_pg:name_adm0": "United Kingdom",
    "qs_pg:name_adm1": "Northern Ireland",
    "qs_pg:photos": 444,
    "qs_pg:photos_1k": 90,
    "qs_pg:photos_9k": 2,
    "qs_pg:photos_9r": 5,
    "qs_pg:photos_all": 444,
    "qs_pg:photos_sr": 6,
    "qs_pg:pop_sr": 3,
    "qs_pg:qs_pg_placetype": "locality",
    "qs_pg:qs_pg_placetype_gp": "Town",
    "qs_pg:woe_adm0": 23424975,
    "woe:adm0_id": 23424975,
    "woe:name_adm0": "United Kingdom",
    "woe:name_adm1": "Northern Ireland",
    "woe:placetype": "Town",
    "wof:name": "Glenariff",
    "wof:placetype": "locality",
    "wof:population": 1286
  },
  "geometry": {"coordinates":[-6.06667,55.05],"type":"Point"}
}
