{
  "type": "Feature",
  "properties": {
    "gn:country":"GB",
    "gn:fcode":"PPL",
    "gn:population":0,
    "iso:country":"GB",
    "name:deu_x_preferred":[
        "Esholt"
    ],
    "name:eng_x_preferred":[
        "Esholt"
    ],
    "name:fin_x_preferred":[
        "Esholt"
    ],
    "name:fra_x_preferred":[
        "Esholt"
    ],
    "name:gle_x_preferred":[
        "Esholt"
    ],
    "name:nld_x_preferred":[
        "Esholt"
    ],
    "name:pol_x_preferred":[
        "Esholt"
    ],
    "name:swe_x_preferred":[
        "Esholt"
    ],
    "name:zho_x_preferred":[
        "\u57c3\u8212\u723e\u7279"
    ],
    "qs_pg:aaroncc":"GB",
    "qs_pg:gn_country":"GB",
    "qs_pg:gn_fcode":"PPL",
    "qs_pg:gn_pop":0,
    "qs_pg:name":"Esholt",
    "qs_pg:name_adm0":"United Kingdom",
    "qs_pg:name_adm1":"England",
    "qs_pg:photos":952,
    "qs_pg:photos_1k":193,
    "qs_pg:photos_9k":4,
    "qs_pg:photos_9r":6,
    "qs_pg:photos_all":952,
    "qs_pg:photos_sr":10,
    "qs_pg:pop_sr":0,
    "qs_pg:qs_pg_placetype":"locality",
    "qs_pg:qs_pg_placetype_gp":"Town",
    "qs_pg:woe_adm0":23424975,
    "woe:adm0_id":23424975,
    "woe:name_adm0":"United Kingdom",
    "woe:name_adm1":"England",
    "woe:placetype":"Town",
    "wof:name":"Esholt",
    "wof:placetype":"neighbourhood"
},
  "geometry": {"coordinates":[-1.724474,53.857611],"type":"Point"}
}