{
  "type": "Feature",
  "properties": {
    "iso:country":"GB",
    "name:pol_x_preferred":[
        "Esholt"
    ],
    "wof:name":"Esholt",
    "wof:placetype":"neighbourhood"
},
  "geometry": {"coordinates":[-1.72447425631638,53.85761142631275],"type":"Point"}
}