{
  "type": "Feature",
  "properties": {
    "gn:gn_country":"GB",
    "gn:gn_fcode":"PPL",
    "gn:gn_pop":0,
    "iso:country":"GB",
    "name:ang_x_preferred":[
        "Walhshalh \u01f7eald"
    ],
    "name:chi_x_preferred":[
        "\u534e\u6377\u4f0d\u5fb7"
    ],
    "name:dut_x_preferred":[
        "Walsall Wood"
    ],
    "name:eng_x_preferred":[
        "Walsall Wood"
    ],
    "name:fre_x_preferred":[
        "Walsall Wood"
    ],
    "name:ger_x_preferred":[
        "Walsall Wood"
    ],
    "name:lat_x_preferred":[
        "Walsall Wood"
    ],
    "name:pol_x_preferred":[
        "Walsall Wood"
    ],
    "name:rus_x_preferred":[
        "\u0423\u043e\u043b\u0441\u043e\u043b\u043b \u0412\u0443\u0434"
    ],
    "name:sco_x_preferred":[
        "Walsall Wood"
    ],
    "name:spa_x_preferred":[
        "Walsall Wood"
    ],
    "name:swe_x_preferred":[
        "Walsall Wood"
    ],
    "name:vol_x_preferred":[
        "Walsall Wood"
    ],
    "name:wel_x_preferred":[
        "Walsall Wood"
    ],
    "qs_pg:aaroncc":"GB",
    "qs_pg:gn_country":"GB",
    "qs_pg:gn_fcode":"PPL",
    "qs_pg:gn_pop":0,
    "qs_pg:name":"Walsall Wood",
    "qs_pg:name_adm0":"United Kingdom",
    "qs_pg:name_adm1":"England",
    "qs_pg:photos_9r":0,
    "qs_pg:photos_sr":0,
    "qs_pg:pop_sr":0,
    "qs_pg:qs_pg_placetype":"locality",
    "qs_pg:qs_pg_placetype_gp":"Town",
    "qs_pg:woe_adm0":23424975,
    "woe:adm0_id":23424975,
    "woe:name_adm0":"United Kingdom",
    "woe:name_adm1":"England",
    "woe:placetype":"Town",
    "wof:name":"Walsall Wood",
    "wof:placetype":"neighbourhood"
},
  "geometry": {"coordinates":[-1.93165,52.62676],"type":"Point"}
}