{
  "type": "Feature",
  "properties": {
    "gn:country": "GB",
    "gn:fcode": "PPL",
    "gn:population": 0,
    "iso:country": "GB",
    "name:ang_x_preferred": [
      "Walhshalh Ƿeald"
    ],
    "name:ceb_x_preferred": [
      "Walsall Wood"
    ],
    "name:cym_x_preferred": [
      "Walsall Wood"
    ],
    "name:deu_x_preferred": [
      "Walsall Wood"
    ],
    "name:eng_x_preferred": [
      "Walsall Wood"
    ],
    "name:fas_x_preferred": [
      "والسال وود"
    ],
    "name:fra_x_preferred": [
      "Walsall Wood"
    ],
    "name:lat_x_preferred": [
      "Walsall Wood"
    ],
    "name:nld_x_preferred": [
      "Walsall Wood"
    ],
    "name:pol_x_preferred": [
      "Walsall Wood"
    ],
    "name:rus_x_preferred": [
      "Уолсолл Вуд"
    ],
    "name:sco_x_preferred": [
      "Walsall Wood"
    ],
    "name:spa_x_preferred": [
      "Walsall Wood"
    ],
    "name:swe_x_preferred": [
      "Walsall Wood"
    ],
    "name:vol_x_preferred": [
      "Walsall Wood"
    ],
    "name:zho_x_preferred": [
      "华捷伍德"
    ],
    "qs_pg:aaroncc": "GB",
    "qs_pg:gn_country": "GB",
    "qs_pg:gn_fcode": "PPL",
    "qs_pg:gn_pop": 0,
    "qs_pg:name": "Walsall Wood",
    "qs_pg:name_adm0": "United Kingdom",
    "qs_pg:name_adm1": "England",
    "qs_pg:photos_9r": 0,
    "qs_pg:photos_sr": 0,
    "qs_pg:pop_sr": 0,
    "qs_pg:qs_pg_placetype": "locality",
    "qs_pg:qs_pg_placetype_gp": "Town",
    "qs_pg:woe_adm0": 23424975,
    "woe:adm0_id": 23424975,
    "woe:name_adm0": "United Kingdom",
    "woe:name_adm1": "England",
    "woe:placetype": "Town",
    "wof:name": "Walsall Wood",
    "wof:placetype": "neighbourhood"
  },
  "geometry": {"coordinates":[-1.93165,52.62676],"type":"Point"}
}
