{
  "type": "Feature",
  "properties": {
    "gn:population": 40000,
    "iso:country": "GB",
    "name:ceb_x_preferred": [
      "Bloxwich"
    ],
    "name:eng_x_preferred": [
      "Bloxwich"
    ],
    "name:fas_x_preferred": [
      "بلاکسویچ"
    ],
    "name:fra_x_preferred": [
      "Bloxwich"
    ],
    "name:gle_x_preferred": [
      "Bloxwich"
    ],
    "name:ita_x_preferred": [
      "Bloxwich"
    ],
    "name:jpn_x_preferred": [
      "ブロックスウィッチ"
    ],
    "name:nld_x_preferred": [
      "Bloxwich"
    ],
    "name:nno_x_preferred": [
      "Bloxwich"
    ],
    "name:pol_x_preferred": [
      "Bloxwich"
    ],
    "name:ron_x_preferred": [
      "Bloxwich"
    ],
    "name:spa_x_preferred": [
      "Bloxwich"
    ],
    "name:swe_x_preferred": [
      "Bloxwich"
    ],
    "name:zho_x_preferred": [
      "植物学湾"
    ],
    "name:zho_x_variant": [
      "布洛克斯威奇"
    ],
    "qs:gn_fcode": "PPL",
    "qs:gn_local": 0,
    "qs:gn_namadm1": "ENG",
    "qs:gn_name": "Bloxwich",
    "qs:local_max": 2515,
    "qs:local_sum": 9671,
    "qs:localhoods": 12,
    "qs:name": "Bloxwich",
    "qs:name_adm0": "United Kingdom",
    "qs:name_adm1": "England",
    "qs:name_adm2": "West Midlands",
    "qs:name_lau": "Walsall Metropolitan Borough",
    "qs:name_local": "Walsall",
    "qs:photo_max": 92,
    "qs:photo_sum": 363,
    "qs:placetype": "Suburb",
    "qs:quad_count": 35,
    "qs:woe_adm0": 23424975,
    "qs:woe_adm1": 24554868,
    "qs:woe_adm2": 12602191,
    "qs:woe_lau": 12695868,
    "qs:woe_local": 39052,
    "qs:woe_ver": "7.10.0",
    "wd:wordcount": 1166,
    "wof:lang": [
      "eng"
    ],
    "wof:name": "Bloxwich",
    "wof:placetype": "neighbourhood",
    "wof:population": 40000
  },
  "geometry": {"coordinates":[-2.00213,52.616287],"type":"Point"}
}
