{
  "type": "Feature",
  "properties": {
    "iso:country":"GB",
    "name:cat_x_preferred":[
        "Ardmore"
    ],
    "name:ceb_x_preferred":[
        "Ardmore"
    ],
    "name:ces_x_preferred":[
        "Ardmore"
    ],
    "name:deu_x_preferred":[
        "Ardmore"
    ],
    "name:eus_x_preferred":[
        "Ardmore"
    ],
    "name:fra_x_preferred":[
        "Ardmore"
    ],
    "name:ido_x_preferred":[
        "Ardmore"
    ],
    "name:ita_x_preferred":[
        "Ardmore"
    ],
    "name:nld_x_preferred":[
        "Ardmore"
    ],
    "name:pol_x_preferred":[
        "Ardmore"
    ],
    "name:por_x_preferred":[
        "Ardmore"
    ],
    "name:rus_x_preferred":[
        "\u0410\u0440\u0434\u043c\u043e\u0440"
    ],
    "name:spa_x_preferred":[
        "Ardmore"
    ],
    "name:srp_x_preferred":[
        "\u0410\u0440\u0434\u043c\u043e\u0440"
    ],
    "name:swe_x_preferred":[
        "Ardmore"
    ],
    "name:ukr_x_preferred":[
        "\u0410\u0440\u0434\u043c\u043e\u0440"
    ],
    "name:vol_x_preferred":[
        "Ardmore"
    ],
    "qs_pg:aaroncc":"GB",
    "qs_pg:name":"Ardmore",
    "qs_pg:name_adm0":"United Kingdom",
    "qs_pg:name_adm1":"Scotland",
    "qs_pg:photos":38,
    "qs_pg:photos_1k":8,
    "qs_pg:photos_9k":1,
    "qs_pg:photos_9r":2,
    "qs_pg:photos_all":38,
    "qs_pg:photos_sr":2,
    "qs_pg:pop_sr":0,
    "qs_pg:qs_pg_placetype":"locality",
    "qs_pg:qs_pg_placetype_gp":"Town",
    "qs_pg:woe_adm0":23424975,
    "woe:adm0_id":23424975,
    "woe:name_adm0":"United Kingdom",
    "woe:name_adm1":"Scotland",
    "woe:placetype":"Town",
    "wof:name":"Ardmore",
    "wof:placetype":"locality"
},
  "geometry": {"coordinates":[-7.329458,57.39515],"type":"Point"}
}