{
  "type": "Feature",
  "properties": {
    "iso:country":"GB",
    "name:cym_x_preferred":[
        "Ring's End"
    ],
    "name:eng_x_preferred":[
        "Ring's End"
    ],
    "name:fra_x_preferred":[
        "Ring's End"
    ],
    "name:gle_x_preferred":[
        "Ring's End"
    ],
    "name:nld_x_preferred":[
        "Ring's End"
    ],
    "qs_pg:aaroncc":"GB",
    "qs_pg:name":"Rings End",
    "qs_pg:name_adm0":"United Kingdom",
    "qs_pg:name_adm1":"England",
    "qs_pg:photos":339,
    "qs_pg:photos_1k":69,
    "qs_pg:photos_9k":2,
    "qs_pg:photos_9r":5,
    "qs_pg:photos_all":339,
    "qs_pg:photos_sr":5,
    "qs_pg:pop_sr":0,
    "qs_pg:qs_pg_placetype":"locality",
    "qs_pg:qs_pg_placetype_gp":"Town",
    "qs_pg:woe_adm0":23424975,
    "woe:adm0_id":23424975,
    "woe:name_adm0":"United Kingdom",
    "woe:name_adm1":"England",
    "woe:placetype":"Town",
    "wof:name":"Rings End",
    "wof:placetype":"neighbourhood"
},
  "geometry": {"coordinates":[0.080337,52.583169],"type":"Point"}
}