{
  "type": "Feature",
  "properties": {
    "iso:country":"GB",
    "name:cym_x_preferred":[
        "Furzebrook"
    ],
    "name:deu_x_preferred":[
        "Furzebrook"
    ],
    "name:eng_x_preferred":[
        "Freshbrook"
    ],
    "name:eng_x_variant":[
        "Furzebrook"
    ],
    "name:fra_x_preferred":[
        "Furzebrook"
    ],
    "name:gle_x_preferred":[
        "Furzebrook"
    ],
    "name:nld_x_preferred":[
        "Furzebrook"
    ],
    "name:pol_x_preferred":[
        "Furzebrook"
    ],
    "qs:gn_fcode":"PPL",
    "qs:gn_local":0,
    "qs:gn_namadm1":"ENG",
    "qs:gn_name":"Furzebrook",
    "qs:local_max":4986,
    "qs:local_sum":18288,
    "qs:localhoods":17,
    "qs:name":"Freshbrook",
    "qs:name_adm0":"United Kingdom",
    "qs:name_adm1":"England",
    "qs:name_adm2":"Wiltshire",
    "qs:name_lau":"Swindon Borough",
    "qs:name_local":"Swindon",
    "qs:photo_max":158,
    "qs:photo_sum":523,
    "qs:placetype":"Suburb",
    "qs:quad_count":23,
    "qs:woe_adm0":23424975,
    "qs:woe_adm1":24554868,
    "qs:woe_adm2":12602186,
    "qs:woe_lau":12696162,
    "qs:woe_local":36796,
    "qs:woe_ver":"7.10.0",
    "wof:lang":[
        "eng"
    ],
    "wof:name":"Freshbrook",
    "wof:placetype":"neighbourhood"
},
  "geometry": {"coordinates":[-1.850819,51.557552],"type":"Point"}
}