{
  "type": "Feature",
  "properties": {
    "iso:country":"GB",
    "name:eng_x_preferred":[
        "High Shields"
    ],
    "qs:gn_adm0_cc":"GB",
    "qs:gn_local":2637329,
    "qs:gn_nam_loc":"South Shields, England, GB",
    "qs:gn_namadm1":"ENG",
    "qs:local_max":5256,
    "qs:local_sum":13333,
    "qs:localhoods":7,
    "qs:name":"High Shields",
    "qs:name_adm0":"United Kingdom",
    "qs:name_adm1":"England",
    "qs:name_adm2":"Tyne and Wear",
    "qs:name_lau":"South Tyneside Metropolitan Borough",
    "qs:name_local":"South Shields",
    "qs:photo_max":202,
    "qs:photo_sum":1580,
    "qs:placetype":"Suburb",
    "qs:quad_count":63,
    "qs:woe_adm0":23424975,
    "qs:woe_adm1":24554868,
    "qs:woe_adm2":12602156,
    "qs:woe_lau":12695861,
    "qs:woe_local":35318,
    "qs:woe_ver":"7.10.0",
    "wof:lang":[
        "eng"
    ],
    "wof:name":"High Shields",
    "wof:placetype":"neighbourhood"
},
  "geometry": {"coordinates":[-1.438228,54.9893],"type":"Point"}
}