{
  "type": "Feature",
  "properties": {
    "gn:population":33467,
    "iso:country":"GB",
    "name:ceb_x_preferred":[
        "Leighton Buzzard"
    ],
    "name:dut_x_preferred":[
        "Leighton Buzzard"
    ],
    "name:eng_x_preferred":[
        "Leighton Buzzard"
    ],
    "name:fra_x_preferred":[
        "Leighton Buzzard"
    ],
    "name:fre_x_preferred":[
        "Leighton Buzzard"
    ],
    "name:ger_x_preferred":[
        "Leighton Buzzard"
    ],
    "name:gle_x_preferred":[
        "Leighton Buzzard"
    ],
    "name:ita_x_preferred":[
        "Leighton Buzzard"
    ],
    "name:jpn_x_preferred":[
        "\u30ec\u30a4\u30c8\u30f3\u30fb\u30d0\u30b6\u30fc\u30c9"
    ],
    "name:nld_x_preferred":[
        "Leighton Buzzard"
    ],
    "name:nno_x_preferred":[
        "Leighton Buzzard"
    ],
    "name:nob_x_preferred":[
        "Leighton Buzzard"
    ],
    "name:nor_x_preferred":[
        "Leighton Buzzard"
    ],
    "name:pol_x_preferred":[
        "Leighton Buzzard"
    ],
    "name:ron_x_preferred":[
        "Leighton Buzzard"
    ],
    "name:rum_x_preferred":[
        "Leighton Buzzard"
    ],
    "name:rus_x_preferred":[
        "\u041b\u0435\u0439\u00ad\u0442\u043e\u043d-\u0411\u0430\u0437\u00ad\u0437\u0430\u0440\u00ad\u0434"
    ],
    "name:spa_x_preferred":[
        "Leighton Buzzard"
    ],
    "name:swe_x_preferred":[
        "Leighton Buzzard"
    ],
    "name:vol_x_preferred":[
        "Leighton Buzzard"
    ],
    "qs:a0":"United Kingdom",
    "qs:a1":"*Central Bedfordshire",
    "qs:a1_lc":"GB12KC0000",
    "qs:a1r":"0England",
    "qs:a1r_lc":"GB12000000",
    "qs:adm0":"United Kingdom",
    "qs:la_lc":"*",
    "qs:level":"locality",
    "qs:loc":"Leighton Buzzard",
    "qs:loc_alt":"Leighton Buzzard",
    "qs:pop":0,
    "qs:type":"buffered point",
    "wd:wordcount":1828,
    "wof:name":"Leighton Buzzard",
    "wof:placetype":"neighbourhood",
    "wof:population":33467
},
  "geometry": {"coordinates":[-0.671603,51.917055],"type":"Point"}
}