{
  "type": "Feature",
  "properties": {
    "gn:population":33467,
    "iso:country":"GB",
    "name:ast_x_preferred":[
        "Leighton Buzzard"
    ],
    "name:ceb_x_preferred":[
        "Leighton Buzzard"
    ],
    "name:cym_x_preferred":[
        "Leighton Buzzard"
    ],
    "name:deu_x_preferred":[
        "Leighton Buzzard"
    ],
    "name:eng_x_preferred":[
        "Leighton Buzzard"
    ],
    "name:epo_x_preferred":[
        "Leighton Buzzard"
    ],
    "name:fas_x_preferred":[
        "\u0644\u06cc\u062a\u0648\u0646 \u0628\u0648\u0632\u0627\u0631\u062f"
    ],
    "name:fra_x_preferred":[
        "Leighton Buzzard"
    ],
    "name:gle_x_preferred":[
        "Leighton Buzzard"
    ],
    "name:heb_x_preferred":[
        "\u05dc\u05d9\u05d9\u05d8\u05d5\u05df \u05d1\u05d0\u05d6\u05e8\u05d3"
    ],
    "name:ita_x_preferred":[
        "Leighton Buzzard"
    ],
    "name:jpn_x_preferred":[
        "\u30ec\u30a4\u30c8\u30f3\u30fb\u30d0\u30b6\u30fc\u30c9"
    ],
    "name:kor_x_preferred":[
        "\ub808\uc774\ud134 \ubc84\uc800\ub4dc"
    ],
    "name:lld_x_preferred":[
        "Leighton Buzzard"
    ],
    "name:nld_x_preferred":[
        "Leighton Buzzard"
    ],
    "name:nno_x_preferred":[
        "Leighton Buzzard"
    ],
    "name:nob_x_preferred":[
        "Leighton Buzzard"
    ],
    "name:nor_x_preferred":[
        "Leighton Buzzard"
    ],
    "name:pol_x_preferred":[
        "Leighton Buzzard"
    ],
    "name:ron_x_preferred":[
        "Leighton Buzzard"
    ],
    "name:rus_x_preferred":[
        "\u041b\u0435\u0439\u00ad\u0442\u043e\u043d-\u0411\u0430\u0437\u00ad\u0437\u0430\u0440\u00ad\u0434"
    ],
    "name:spa_x_preferred":[
        "Leighton Buzzard"
    ],
    "name:swe_x_preferred":[
        "Leighton Buzzard"
    ],
    "name:vol_x_preferred":[
        "Leighton Buzzard"
    ],
    "name:zho_x_preferred":[
        "\u83b1\u987f\u5df4\u624e\u5fb7"
    ],
    "qs:a0":"United Kingdom",
    "qs:a1":"*Central Bedfordshire",
    "qs:a1_lc":"GB12KC0000",
    "qs:a1r":"0England",
    "qs:a1r_lc":"GB12000000",
    "qs:adm0":"United Kingdom",
    "qs:la_lc":"*",
    "qs:level":"locality",
    "qs:loc":"Leighton Buzzard",
    "qs:loc_alt":"Leighton Buzzard",
    "qs:pop":0,
    "qs:type":"buffered point",
    "wd:wordcount":1828,
    "wof:name":"Leighton Buzzard",
    "wof:placetype":"neighbourhood",
    "wof:population":33467
},
  "geometry": {"coordinates":[-0.671603,51.917055],"type":"Point"}
}