{
  "type": "Feature",
  "properties": {
    "gn:country":"GB",
    "gn:fcode":"PPL",
    "gn:population":27539,
    "iso:country":"GB",
    "name:azb_x_preferred":[
        "\u06a9\u06cc\u0631\u0628\u06cc-\u0627\u06cc\u0646-\u0627\u0634\u0641\u06cc\u0644\u062f"
    ],
    "name:bul_x_preferred":[
        "\u041a\u044a\u0440\u043a\u0431\u0438 \u0438\u043d \u0410\u0448\u0444\u0438\u0439\u043b\u0434"
    ],
    "name:ceb_x_preferred":[
        "Kirkby in Ashfield"
    ],
    "name:cym_x_preferred":[
        "Kirkby-in-Ashfield"
    ],
    "name:deu_x_preferred":[
        "Kirkby-in-Ashfield"
    ],
    "name:eng_x_preferred":[
        "Kirkby-in-Ashfield"
    ],
    "name:fas_x_preferred":[
        "\u06a9\u06cc\u0631\u0628\u06cc-\u0627\u06cc\u0646-\u0627\u0634\u0641\u06cc\u0644\u062f"
    ],
    "name:fra_x_preferred":[
        "Kirkby-in-Ashfield"
    ],
    "name:gle_x_preferred":[
        "Kirkby-in-Ashfield"
    ],
    "name:ita_x_preferred":[
        "Kirkby-in-Ashfield"
    ],
    "name:jpn_x_preferred":[
        "\u30ab\u30fc\u30af\u30d3\u30fc\u30fb\u30a4\u30f3\u30fb\u30a2\u30c3\u30b7\u30e5\u30d5\u30a3\u30fc\u30eb\u30c9"
    ],
    "name:nld_x_preferred":[
        "Kirkby-in-Ashfield"
    ],
    "name:nno_x_preferred":[
        "Kirkby-in-Ashfield"
    ],
    "name:nob_x_preferred":[
        "Kirkby-in-Ashfield"
    ],
    "name:pol_x_preferred":[
        "Kirkby-in-Ashfield"
    ],
    "name:ron_x_preferred":[
        "Kirkby-in-Ashfield"
    ],
    "name:swe_x_preferred":[
        "Kirkby in Ashfield"
    ],
    "name:und_x_variant":[
        "Kirkby"
    ],
    "name:vol_x_preferred":[
        "Kirby-in-Ashfield"
    ],
    "qs_pg:aaroncc":"GB",
    "qs_pg:gn_country":"GB",
    "qs_pg:gn_fcode":"PPL",
    "qs_pg:gn_pop":27539,
    "qs_pg:name":"Kirkby in Ashfield",
    "qs_pg:name_adm0":"United Kingdom",
    "qs_pg:name_adm1":"England",
    "qs_pg:photos":283,
    "qs_pg:photos_1k":57,
    "qs_pg:photos_9k":1,
    "qs_pg:photos_9r":4,
    "qs_pg:photos_all":283,
    "qs_pg:photos_sr":5,
    "qs_pg:pop_sr":7,
    "qs_pg:qs_pg_placetype":"locality",
    "qs_pg:qs_pg_placetype_gp":"Town",
    "qs_pg:woe_adm0":23424975,
    "woe:adm0_id":23424975,
    "woe:name_adm0":"United Kingdom",
    "woe:name_adm1":"England",
    "woe:placetype":"Town",
    "wof:name":"Kirkby in Ashfield",
    "wof:placetype":"neighbourhood",
    "wof:population":27539
},
  "geometry": {"coordinates":[-1.24379,53.09982],"type":"Point"}
}