{
  "type": "Feature",
  "properties": {
    "iso:country":"GB",
    "name:eng_x_preferred":[
        "Westcotes"
    ],
    "name:eng_x_variant":[
        "West End"
    ],
    "wof:name":"Westcotes",
    "wof:placetype":"neighbourhood"
},
  "geometry": {"coordinates":[-1.15259655520354,52.62947340804695],"type":"Point"}
}