{
  "type": "Feature",
  "properties": {
    "iso:country":"GB",
    "name:ceb_x_preferred":[
        "Brightwell"
    ],
    "name:eng_x_preferred":[
        "Brightwell"
    ],
    "name:fra_x_preferred":[
        "Brightwell"
    ],
    "name:gle_x_preferred":[
        "Brightwell"
    ],
    "name:lld_x_preferred":[
        "Brightwell"
    ],
    "name:nan_x_preferred":[
        "Brightwell"
    ],
    "name:nld_x_preferred":[
        "Brightwell"
    ],
    "name:pol_x_preferred":[
        "Brightwell"
    ],
    "name:swe_x_preferred":[
        "Brightwell"
    ],
    "name:tur_x_preferred":[
        "Brightwell"
    ],
    "qs_pg:aaroncc":"GB",
    "qs_pg:name":"Brightwell",
    "qs_pg:name_adm0":"United Kingdom",
    "qs_pg:name_adm1":"England",
    "qs_pg:photos":243,
    "qs_pg:photos_1k":49,
    "qs_pg:photos_9k":1,
    "qs_pg:photos_9r":4,
    "qs_pg:photos_all":243,
    "qs_pg:photos_sr":4,
    "qs_pg:pop_sr":0,
    "qs_pg:qs_pg_placetype":"locality",
    "qs_pg:qs_pg_placetype_gp":"Town",
    "qs_pg:woe_adm0":23424975,
    "woe:adm0_id":23424975,
    "woe:name_adm0":"United Kingdom",
    "woe:name_adm1":"England",
    "woe:placetype":"Town",
    "wof:name":"Brightwell",
    "wof:placetype":"neighbourhood"
},
  "geometry": {"coordinates":[1.331148,52.050497],"type":"Point"}
}