{
  "type": "Feature",
  "properties": {
    "iso:country": "GB",
    "name:ceb_x_preferred": [
      "Bayfield"
    ],
    "name:deu_x_preferred": [
      "Bayfield"
    ],
    "name:fra_x_preferred": [
      "Bayfield"
    ],
    "name:ita_x_preferred": [
      "Bayfield"
    ],
    "name:nld_x_preferred": [
      "Bayfield"
    ],
    "name:pol_x_preferred": [
      "Bayfield"
    ],
    "name:por_x_preferred": [
      "Bayfield"
    ],
    "name:srp_x_preferred": [
      "Бајфилд"
    ],
    "name:ukr_x_preferred": [
      "Бейфілд"
    ],
    "name:vol_x_preferred": [
      "Bayfield"
    ],
    "qs_pg:aaroncc": "GB",
    "qs_pg:name": "Bayfield",
    "qs_pg:name_adm0": "United Kingdom",
    "qs_pg:name_adm1": "Wales",
    "qs_pg:photos": 9,
    "qs_pg:photos_1k": 2,
    "qs_pg:photos_9k": 1,
    "qs_pg:photos_9r": 1,
    "qs_pg:photos_all": 9,
    "qs_pg:photos_sr": 1,
    "qs_pg:pop_sr": 0,
    "qs_pg:qs_pg_placetype": "locality",
    "qs_pg:qs_pg_placetype_gp": "Town",
    "qs_pg:woe_adm0": 23424975,
    "woe:adm0_id": 23424975,
    "woe:name_adm0": "United Kingdom",
    "woe:name_adm1": "Wales",
    "woe:placetype": "Town",
    "wof:name": "Bayfield",
    "wof:placetype": "neighbourhood"
  },
  "geometry": {"coordinates":[-2.694053,51.641352],"type":"Point"}
}
