{
  "type": "Feature",
  "properties": {
    "iso:country":"GB",
    "name:eng_x_preferred":[
        "Tuffley"
    ],
    "name:pol_x_preferred":[
        "Tuffley"
    ],
    "name:swe_x_preferred":[
        "Tuffley"
    ],
    "qs:gn_adm0_cc":"GB",
    "qs:gn_local":2648404,
    "qs:gn_nam_loc":"Gloucester, Gloucester, Gloucestershire, England, GB",
    "qs:gn_namadm1":"ENG",
    "qs:local_max":4990,
    "qs:local_sum":10986,
    "qs:localhoods":13,
    "qs:name":"Tuffley",
    "qs:name_adm0":"United Kingdom",
    "qs:name_adm1":"England",
    "qs:name_adm2":"Gloucestershire",
    "qs:name_lau":"Gloucester City",
    "qs:name_local":"Gloucester",
    "qs:photo_max":69,
    "qs:photo_sum":362,
    "qs:placetype":"Suburb",
    "qs:quad_count":44,
    "qs:woe_adm0":23424975,
    "qs:woe_adm1":24554868,
    "qs:woe_adm2":12602184,
    "qs:woe_lau":12695955,
    "qs:woe_local":21248,
    "qs:woe_ver":"7.10.0",
    "wd:wordcount":485,
    "wof:lang":[
        "eng"
    ],
    "wof:name":"Tuffley",
    "wof:placetype":"neighbourhood"
},
  "geometry": {"coordinates":[-2.234892,51.823769],"type":"Point"}
}