{
  "type": "Feature",
  "properties": {
    "iso:country":"GB",
    "wof:name":"Percy Main",
    "wof:placetype":"neighbourhood"
},
  "geometry": {"coordinates":[-1.47413377360835,54.99819235622834],"type":"Point"}
}