{
  "type": "Feature",
  "properties": {
    "iso:country":"GB",
    "name:eng_x_preferred":[
        "Baddeley Green"
    ],
    "name:fra_x_preferred":[
        "Baddeley Green"
    ],
    "name:nld_x_preferred":[
        "Baddeley Green"
    ],
    "name:pol_x_preferred":[
        "Baddeley Green"
    ],
    "qs:gn_adm0_cc":"GB",
    "qs:gn_fcode":"PPL",
    "qs:gn_local":2636841,
    "qs:gn_namadm1":"ENG",
    "qs:gn_name":"Bartley Green",
    "qs:local_max":5204,
    "qs:local_sum":30618,
    "qs:localhoods":23,
    "qs:name":"Baddeley Green",
    "qs:name_adm0":"United Kingdom",
    "qs:name_adm1":"England",
    "qs:name_adm2":"Staffordshire",
    "qs:name_lau":"Stoke-on-Trent City",
    "qs:name_local":"Stoke-on-Trent",
    "qs:photo_max":141,
    "qs:photo_sum":173,
    "qs:placetype":"Suburb",
    "qs:quad_count":8,
    "qs:woe_adm0":23424975,
    "qs:woe_adm1":24554868,
    "qs:woe_adm2":12602189,
    "qs:woe_lau":12696161,
    "qs:woe_local":36240,
    "qs:woe_ver":"7.10.0",
    "wd:wordcount":91,
    "wof:lang":[
        "eng"
    ],
    "wof:name":"Baddeley Green",
    "wof:placetype":"neighbourhood"
},
  "geometry": {"coordinates":[-2.139627,53.063578],"type":"Point"}
}