{
  "type": "Feature",
  "properties": {
    "iso:country":"GB",
    "name:eng_x_preferred":[
        "Rose Green"
    ],
    "wof:name":"Rose Green",
    "wof:placetype":"neighbourhood"
},
  "geometry": {"coordinates":[-2.54840366270203,51.46662352431814],"type":"Point"}
}