{
  "type": "Feature",
  "properties": {
    "gn:admin1_code":"SCT",
    "gn:admin2_code":"W5",
    "gn:asciiname":"Elsrickle",
    "gn:country_code":"GB",
    "gn:dem":268,
    "gn:feature_class":"P",
    "gn:feature_code":"PPL",
    "gn:name":"Elsrickle",
    "gn:population":0,
    "gn:timezone":"Europe/London",
    "iso:country":"GB",
    "name:deu_x_preferred":[
        "Elsrickle"
    ],
    "name:eus_x_preferred":[
        "Elsrickle"
    ],
    "wof:name":"Elsrickle",
    "wof:placetype":"locality"
},
  "geometry": {"coordinates":[-3.49546,55.67506],"type":"Point"}
}