{
  "type": "Feature",
  "properties": {
    "iso:country": "GB",
    "name:eng_x_preferred": [
      "North Oxford"
    ],
    "wof:name": "North Oxford",
    "wof:placetype": "neighbourhood"
  },
  "geometry": {"coordinates":[-1.26362679971997,51.76997629703955],"type":"Point"}
}
