{
  "type": "Feature",
  "properties": {
    "iso:country":"GB",
    "name:cym_x_preferred":[
        "Little Leighs"
    ],
    "name:eng_x_preferred":[
        "Little Leighs"
    ],
    "name:fra_x_preferred":[
        "Little Leighs"
    ],
    "name:gle_x_preferred":[
        "Little Leighs"
    ],
    "name:lat_x_preferred":[
        "Lega Parva"
    ],
    "name:nld_x_preferred":[
        "Little Leighs"
    ],
    "name:pol_x_preferred":[
        "Little Leighs"
    ],
    "name:swe_x_preferred":[
        "Little Leighs"
    ],
    "qs_pg:aaroncc":"GB",
    "qs_pg:name":"Little Leighs",
    "qs_pg:name_adm0":"United Kingdom",
    "qs_pg:name_adm1":"England",
    "qs_pg:photos":73,
    "qs_pg:photos_1k":15,
    "qs_pg:photos_9k":1,
    "qs_pg:photos_9r":2,
    "qs_pg:photos_all":73,
    "qs_pg:photos_sr":2,
    "qs_pg:pop_sr":0,
    "qs_pg:qs_pg_placetype":"locality",
    "qs_pg:qs_pg_placetype_gp":"Town",
    "qs_pg:woe_adm0":23424975,
    "woe:adm0_id":23424975,
    "woe:name_adm0":"United Kingdom",
    "woe:name_adm1":"England",
    "woe:placetype":"Town",
    "wof:name":"Little Leighs",
    "wof:placetype":"neighbourhood"
},
  "geometry": {"coordinates":[0.492708,51.823113],"type":"Point"}
}