{
  "type": "Feature",
  "properties": {
    "iso:country":"GB",
    "name:cym_x_preferred":[
        "Harman's Cross"
    ],
    "name:deu_x_preferred":[
        "Harman\u2019s Cross"
    ],
    "name:eng_x_preferred":[
        "Harman's Cross"
    ],
    "name:fra_x_preferred":[
        "Harman's Cross"
    ],
    "name:nld_x_preferred":[
        "Harman's Cross"
    ],
    "name:pol_x_preferred":[
        "Harman's Cross"
    ],
    "qs_pg:aaroncc":"GB",
    "qs_pg:name":"Harman's Cross",
    "qs_pg:name_adm0":"United Kingdom",
    "qs_pg:name_adm1":"England",
    "qs_pg:photos":779,
    "qs_pg:photos_1k":158,
    "qs_pg:photos_9k":3,
    "qs_pg:photos_9r":6,
    "qs_pg:photos_all":779,
    "qs_pg:photos_sr":9,
    "qs_pg:pop_sr":0,
    "qs_pg:qs_pg_placetype":"locality",
    "qs_pg:qs_pg_placetype_gp":"Town",
    "qs_pg:woe_adm0":23424975,
    "woe:adm0_id":23424975,
    "woe:name_adm0":"United Kingdom",
    "woe:name_adm1":"England",
    "woe:placetype":"Town",
    "wof:name":"Harman's Cross",
    "wof:placetype":"neighbourhood"
},
  "geometry": {"coordinates":[-2.024442,50.620281],"type":"Point"}
}