{
  "type": "Feature",
  "properties": {
    "gn:admin1_code": "ENG",
    "gn:admin2_code": "J6",
    "gn:admin3_code": "00EM141",
    "gn:asciiname": "Ouston",
    "gn:country_code": "GB",
    "gn:dem": 137,
    "gn:feature_class": "P",
    "gn:feature_code": "PPL",
    "gn:name": "Ouston",
    "gn:population": 0,
    "gn:timezone": "Europe/London",
    "iso:country": "GB",
    "name:pol_x_preferred": [
      "Ouston"
    ],
    "name:srp_x_preferred": [
      "Оустон"
    ],
    "wof:name": "Ouston",
    "wof:placetype": "neighbourhood"
  },
  "geometry": {"coordinates":[-1.87386,55.01963000000001],"type":"Point"}
}
