{
  "type": "Feature",
  "properties": {
    "iso:country":"GB",
    "name:eng_x_preferred":[
        "Highburton"
    ],
    "name:fra_x_preferred":[
        "Highburton"
    ],
    "name:nld_x_preferred":[
        "Highburton"
    ],
    "name:pol_x_preferred":[
        "Highburton"
    ],
    "qs_pg:aaroncc":"GB",
    "qs_pg:name":"Highburton",
    "qs_pg:name_adm0":"United Kingdom",
    "qs_pg:name_adm1":"England",
    "qs_pg:photos":78,
    "qs_pg:photos_1k":16,
    "qs_pg:photos_9k":1,
    "qs_pg:photos_9r":3,
    "qs_pg:photos_all":78,
    "qs_pg:photos_sr":3,
    "qs_pg:pop_sr":0,
    "qs_pg:qs_pg_placetype":"locality",
    "qs_pg:qs_pg_placetype_gp":"Town",
    "qs_pg:woe_adm0":23424975,
    "woe:adm0_id":23424975,
    "woe:name_adm0":"United Kingdom",
    "woe:name_adm1":"England",
    "woe:placetype":"Town",
    "wof:name":"Highburton",
    "wof:placetype":"neighbourhood"
},
  "geometry": {"coordinates":[-1.712386,53.61721],"type":"Point"}
}