{
  "type": "Feature",
  "properties": {
    "iso:country":"GB",
    "name:cym_x_preferred":[
        "Dovenby"
    ],
    "name:eng_x_preferred":[
        "Dovenby"
    ],
    "name:fra_x_preferred":[
        "Dovenby"
    ],
    "name:gle_x_preferred":[
        "Dovenby"
    ],
    "name:lld_x_preferred":[
        "Dovenby"
    ],
    "name:nld_x_preferred":[
        "Dovenby"
    ],
    "name:pol_x_preferred":[
        "Dovenby"
    ],
    "name:swe_x_preferred":[
        "Dovenby"
    ],
    "qs_pg:aaroncc":"GB",
    "qs_pg:name":"Dovenby",
    "qs_pg:name_adm0":"United Kingdom",
    "qs_pg:name_adm1":"England",
    "qs_pg:photos":61,
    "qs_pg:photos_1k":12,
    "qs_pg:photos_9k":1,
    "qs_pg:photos_9r":2,
    "qs_pg:photos_all":61,
    "qs_pg:photos_sr":2,
    "qs_pg:pop_sr":0,
    "qs_pg:qs_pg_placetype":"locality",
    "qs_pg:qs_pg_placetype_gp":"Town",
    "qs_pg:woe_adm0":23424975,
    "woe:adm0_id":23424975,
    "woe:name_adm0":"United Kingdom",
    "woe:name_adm1":"England",
    "woe:placetype":"Town",
    "wof:name":"Dovenby",
    "wof:placetype":"neighbourhood"
},
  "geometry": {"coordinates":[-3.405654,54.68672],"type":"Point"}
}