{
  "type": "Feature",
  "properties": {
    "iso:country":"GB",
    "name:eng_x_preferred":[
        "Shut End"
    ],
    "qs:gn_adm0_cc":"GB",
    "qs:gn_local":2654724,
    "qs:gn_nam_loc":"brierley hill",
    "qs:gn_namadm1":"ENG",
    "qs:local_max":859,
    "qs:local_sum":2246,
    "qs:localhoods":5,
    "qs:name":"Shut End",
    "qs:name_adm0":"United Kingdom",
    "qs:name_adm1":"England",
    "qs:name_adm2":"West Midlands",
    "qs:name_lau":"Dudley Metropolitan Borough",
    "qs:name_local":"Brierley Hill",
    "qs:photo_max":73,
    "qs:photo_sum":492,
    "qs:placetype":"Suburb",
    "qs:quad_count":46,
    "qs:woe_adm0":23424975,
    "qs:woe_adm1":24554868,
    "qs:woe_adm2":12602191,
    "qs:woe_lau":12695865,
    "qs:woe_local":13893,
    "qs:woe_ver":"7.10.0",
    "wof:lang":[
        "eng"
    ],
    "wof:name":"Shut End",
    "wof:placetype":"neighbourhood"
},
  "geometry": {"coordinates":[-2.1686,52.503754],"type":"Point"}
}