{
  "type": "Feature",
  "properties": {
    "iso:country":"GB",
    "name:ara_x_preferred":[
        "\u0642\u0644\u0639\u0629 \u0645\u0644\u062c\u0631\u064a\u0641"
    ],
    "name:deu_x_preferred":[
        "Mulgrave Castle"
    ],
    "qs_pg:aaroncc":"GB",
    "qs_pg:name":"Mulgrave Castle",
    "qs_pg:name_adm0":"United Kingdom",
    "qs_pg:name_adm1":"England",
    "qs_pg:photos":17,
    "qs_pg:photos_1k":3,
    "qs_pg:photos_9k":1,
    "qs_pg:photos_9r":1,
    "qs_pg:photos_all":17,
    "qs_pg:photos_sr":1,
    "qs_pg:pop_sr":0,
    "qs_pg:qs_pg_placetype":"locality",
    "qs_pg:qs_pg_placetype_gp":"Town",
    "qs_pg:woe_adm0":23424975,
    "woe:adm0_id":23424975,
    "woe:name_adm0":"United Kingdom",
    "woe:name_adm1":"England",
    "woe:placetype":"Town",
    "wof:name":"Mulgrave Castle",
    "wof:placetype":"neighbourhood"
},
  "geometry": {"coordinates":[-0.692009,54.50115],"type":"Point"}
}