{
  "type": "Feature",
  "properties": {
    "gn:country":"GB",
    "gn:fcode":"PPL",
    "gn:population":0,
    "iso:country":"GB",
    "name:bre_x_preferred":[
        "Pencader"
    ],
    "name:ceb_x_preferred":[
        "Pencader"
    ],
    "name:cym_x_preferred":[
        "Pencader"
    ],
    "name:deu_x_preferred":[
        "Pencader"
    ],
    "name:eng_x_preferred":[
        "Pencader"
    ],
    "name:eus_x_preferred":[
        "Pencader"
    ],
    "name:fas_x_preferred":[
        "\u067e\u0646\u06a9\u0627\u062f\u0631"
    ],
    "name:fra_x_preferred":[
        "Pencader"
    ],
    "name:glg_x_preferred":[
        "Pencader"
    ],
    "name:nld_x_preferred":[
        "Pencader"
    ],
    "name:sco_x_preferred":[
        "Pencader"
    ],
    "name:spa_x_preferred":[
        "Pencader"
    ],
    "name:swe_x_preferred":[
        "Pencader"
    ],
    "qs_pg:aaroncc":"GB",
    "qs_pg:gn_country":"GB",
    "qs_pg:gn_fcode":"PPL",
    "qs_pg:gn_pop":0,
    "qs_pg:name":"Pencader",
    "qs_pg:name_adm0":"United Kingdom",
    "qs_pg:name_adm1":"Wales",
    "qs_pg:photos":540,
    "qs_pg:photos_1k":109,
    "qs_pg:photos_9k":2,
    "qs_pg:photos_9r":5,
    "qs_pg:photos_all":540,
    "qs_pg:photos_sr":7,
    "qs_pg:pop_sr":0,
    "qs_pg:qs_pg_placetype":"locality",
    "qs_pg:qs_pg_placetype_gp":"Town",
    "qs_pg:woe_adm0":23424975,
    "woe:adm0_id":23424975,
    "woe:name_adm0":"United Kingdom",
    "woe:name_adm1":"Wales",
    "woe:placetype":"Town",
    "wof:name":"Pencader",
    "wof:placetype":"neighbourhood",
    "wof:population":1107
},
  "geometry": {"coordinates":[-4.26575,52.0008],"type":"Point"}
}