{
  "type": "Feature",
  "properties": {
    "iso:country":"GB",
    "name:eng_x_preferred":[
        "Charleston"
    ],
    "name:unk_x_variant":[
        "Charleston"
    ],
    "qs:gn_fcode":"PPL",
    "qs:gn_local":0,
    "qs:gn_namadm1":"SCT",
    "qs:gn_name":"Charlestown",
    "qs:local_max":4949,
    "qs:local_sum":11872,
    "qs:localhoods":6,
    "qs:name":"Charleston",
    "qs:name_adm0":"United Kingdom",
    "qs:name_adm1":"Scotland",
    "qs:name_adm2":"Strathclyde",
    "qs:name_lau":"Renfrewshire",
    "qs:name_local":"Paisley",
    "qs:photo_max":93,
    "qs:photo_sum":500,
    "qs:placetype":"Suburb",
    "qs:quad_count":33,
    "qs:woe_adm0":23424975,
    "qs:woe_adm1":12578048,
    "qs:woe_adm2":12602207,
    "qs:woe_lau":12696207,
    "qs:woe_local":31342,
    "qs:woe_ver":"7.10.0",
    "wof:lang":[
        "eng"
    ],
    "wof:name":"Charleston",
    "wof:placetype":"neighbourhood"
},
  "geometry": {"coordinates":[-4.421716,55.83047],"type":"Point"}
}