{
  "type": "Feature",
  "properties": {
    "iso:country":"GB",
    "name:ben_x_preferred":[
        "\u0985\u09cd\u09af\u09be\u09a1\u0989\u0987\u0995 \u09b2\u09be \u09b8\u09cd\u099f\u09cd\u09b0\u09bf\u099f"
    ],
    "name:dut_x_preferred":[
        "Adwick le Street"
    ],
    "name:eng_x_preferred":[
        "Adwick le Street"
    ],
    "name:fre_x_preferred":[
        "Adwick le Street"
    ],
    "name:ger_x_preferred":[
        "Adwick le Street"
    ],
    "name:guj_x_preferred":[
        "\u0a8f\u0aa1\u0ab5\u0abf\u0a95 \u0ab2\u0ac7 \u0ab8\u0acd\u0a9f\u0acd\u0ab0\u0ac0\u0a9f"
    ],
    "name:ita_x_preferred":[
        "Adwick le Street"
    ],
    "name:jpn_x_preferred":[
        "\u30a2\u30c9\u30a6\u30a3\u30c3\u30af\u30fb\u30ec\u30fb\u30b9\u30c8\u30ea\u30fc\u30c8"
    ],
    "name:kan_x_preferred":[
        "\u0c85\u0ca1\u0ccd\u0cb5\u0cbf\u0c95\u0ccd \u0cb2\u0cc6 \u0cb8\u0ccd\u0c9f\u0ccd\u0cb0\u0cc0\u0c9f\u0ccd"
    ],
    "name:kor_x_preferred":[
        "\uc560\ub4dc\uc705 \ub808 \uc2a4\ud2b8\ub9ac\ud2b8"
    ],
    "name:lit_x_preferred":[
        "Advik le stritas"
    ],
    "name:pol_x_preferred":[
        "Adwick le Street"
    ],
    "name:por_x_preferred":[
        "Adwick le Street"
    ],
    "name:rus_x_preferred":[
        "\u042d\u0434\u0432\u0438\u043a-\u043b\u0435-\u0421\u0442\u0440\u0438\u0442"
    ],
    "name:spa_x_preferred":[
        "Adwick le Street"
    ],
    "name:tam_x_preferred":[
        "\u0b85\u0b9f\u0bb5\u0bbf\u0b95\u0bcd  \u0bb2\u0bc0  \u0bb8\u0bcd\u0b9f\u0bcd\u0bb0\u0bc0\u0b9f\u0bcd"
    ],
    "name:tel_x_preferred":[
        "\u0c05\u0c21\u0c4d\u0c35\u0c3f\u0c15\u0c4d \u0c32\u0c47 \u0c38\u0c4d\u0c1f\u0c4d\u0c30\u0c40\u0c1f\u0c4d"
    ],
    "name:urd_x_preferred":[
        "\u0627\u062f\u0648\u06cc\u06a9\u00a0\u0644\u06d2 \u0627\u0633\u0679\u0631\u06cc\u0679"
    ],
    "qs:a0":"United Kingdom",
    "qs:a1":"*Doncaster",
    "qs:a1_lc":"GB12CE0000",
    "qs:a1r":"0England",
    "qs:a1r_lc":"GB12000000",
    "qs:adm0":"United Kingdom",
    "qs:la_lc":"*",
    "qs:level":"locality",
    "qs:loc":"Adwick le Street",
    "qs:loc_alt":"Adwick le Street",
    "qs:pop":0,
    "qs:type":"buffered point",
    "wd:wordcount":1085,
    "wof:name":"Adwick le Street",
    "wof:placetype":"neighbourhood"
},
  "geometry": {"coordinates":[-1.192249,53.561553],"type":"Point"}
}