{
  "type": "Feature",
  "properties": {
    "iso:country": "GB",
    "name:ben_x_preferred": [
      "অ্যাডউইক লা স্ট্রিট"
    ],
    "name:deu_x_preferred": [
      "Adwick le Street"
    ],
    "name:eng_x_preferred": [
      "Adwick le Street"
    ],
    "name:fra_x_preferred": [
      "Adwick le Street"
    ],
    "name:guj_x_preferred": [
      "એડવિક લે સ્ટ્રીટ"
    ],
    "name:ita_x_preferred": [
      "Adwick le Street"
    ],
    "name:jpn_x_preferred": [
      "アドウィック・レ・ストリート"
    ],
    "name:kan_x_preferred": [
      "ಅಡ್ವಿಕ್ ಲೆ ಸ್ಟ್ರೀಟ್"
    ],
    "name:kor_x_preferred": [
      "애드윅 레 스트리트"
    ],
    "name:lit_x_preferred": [
      "Advik le stritas"
    ],
    "name:nld_x_preferred": [
      "Adwick le Street"
    ],
    "name:pol_x_preferred": [
      "Adwick le Street"
    ],
    "name:por_x_preferred": [
      "Adwick le Street"
    ],
    "name:rus_x_preferred": [
      "Эдвик-ле-Стрит"
    ],
    "name:spa_x_preferred": [
      "Adwick le Street"
    ],
    "name:swe_x_preferred": [
      "Adwick le Street"
    ],
    "name:tam_x_preferred": [
      "அடவிக் லீ ஸ்ட்ரீட்"
    ],
    "name:tel_x_preferred": [
      "అడ్విక్ లే స్ట్రీట్"
    ],
    "name:urd_x_preferred": [
      "ادویک لے اسٹریٹ"
    ],
    "qs:a0": "United Kingdom",
    "qs:a1": "*Doncaster",
    "qs:a1_lc": "GB12CE0000",
    "qs:a1r": "0England",
    "qs:a1r_lc": "GB12000000",
    "qs:adm0": "United Kingdom",
    "qs:la_lc": "*",
    "qs:level": "locality",
    "qs:loc": "Adwick le Street",
    "qs:loc_alt": "Adwick le Street",
    "qs:pop": 0,
    "qs:type": "buffered point",
    "wd:wordcount": 1085,
    "wof:name": "Adwick le Street",
    "wof:placetype": "neighbourhood"
  },
  "geometry": {"coordinates":[-1.192249,53.561553],"type":"Point"}
}
