{
  "type": "Feature",
  "properties": {
    "iso:country":"GB",
    "name:ces_x_preferred":[
        "Longbridge"
    ],
    "name:ell_x_preferred":[
        "\u039b\u03cc\u03bd\u03b3\u03ba\u03bc\u03c0\u03c1\u03b9\u03c4\u03b6"
    ],
    "name:fra_x_preferred":[
        "Longbridge"
    ],
    "name:gle_x_preferred":[
        "Longbridge"
    ],
    "name:nld_x_preferred":[
        "Longbridge"
    ],
    "name:pol_x_preferred":[
        "Longbridge"
    ],
    "name:rus_x_preferred":[
        "\u041b\u043e\u043d\u0433\u0431\u0440\u0438\u0434\u0436"
    ],
    "name:swe_x_preferred":[
        "Longbridge"
    ],
    "qs_pg:aaroncc":"GB",
    "qs_pg:name":"Longbridge",
    "qs_pg:name_adm0":"United Kingdom",
    "qs_pg:name_adm1":"England",
    "qs_pg:photos":34,
    "qs_pg:photos_1k":7,
    "qs_pg:photos_9k":1,
    "qs_pg:photos_9r":2,
    "qs_pg:photos_all":34,
    "qs_pg:photos_sr":2,
    "qs_pg:pop_sr":0,
    "qs_pg:qs_pg_placetype":"locality",
    "qs_pg:qs_pg_placetype_gp":"Town",
    "qs_pg:woe_adm0":23424975,
    "woe:adm0_id":23424975,
    "woe:name_adm0":"United Kingdom",
    "woe:name_adm1":"England",
    "woe:placetype":"Town",
    "wof:name":"Longbridge",
    "wof:placetype":"neighbourhood"
},
  "geometry": {"coordinates":[-1.605892,52.261118],"type":"Point"}
}