{
  "type": "Feature",
  "properties": {
    "iso:country": "GB",
    "name:ceb_x_preferred": [
      "Linton"
    ],
    "name:deu_x_preferred": [
      "Linton"
    ],
    "name:fra_x_preferred": [
      "Linton"
    ],
    "name:ita_x_preferred": [
      "Linton"
    ],
    "name:jpn_x_preferred": [
      "リントン"
    ],
    "name:nld_x_preferred": [
      "Linton"
    ],
    "name:pol_x_preferred": [
      "Linton"
    ],
    "name:por_x_preferred": [
      "Linton"
    ],
    "name:spa_x_preferred": [
      "Linton"
    ],
    "name:srp_x_preferred": [
      "Листон"
    ],
    "name:swe_x_preferred": [
      "Linton"
    ],
    "name:ukr_x_preferred": [
      "Лінтон"
    ],
    "wof:name": "Linton",
    "wof:placetype": "neighbourhood"
  },
  "geometry": {"coordinates":[-1.40897479184716,53.91583730669592],"type":"Point"}
}
