{
  "type": "Feature",
  "properties": {
    "gn:country":"GB",
    "gn:fcode":"PPL",
    "gn:population":0,
    "iso:country":"GB",
    "name:bre_x_preferred":[
        "Pontrhydfendigaid"
    ],
    "name:cat_x_preferred":[
        "Pontrhydfendigaid"
    ],
    "name:ces_x_preferred":[
        "Pontrhydfendigaid"
    ],
    "name:cym_x_preferred":[
        "Pontrhydfendigaid"
    ],
    "name:deu_x_preferred":[
        "Pontrhydfendigaid"
    ],
    "name:eng_x_preferred":[
        "Pontrhydfendigaid"
    ],
    "name:eus_x_preferred":[
        "Pontrhydfendigaid"
    ],
    "name:fra_x_preferred":[
        "Pontrhydfendigaid"
    ],
    "name:gle_x_preferred":[
        "Pontrhydfendigaid"
    ],
    "name:glg_x_preferred":[
        "Pontrhydfendigaid"
    ],
    "name:nld_x_preferred":[
        "Pontrhydfendigaid"
    ],
    "name:pol_x_preferred":[
        "Pontrhydfendigaid"
    ],
    "name:sco_x_preferred":[
        "Pontrhydfendigaid"
    ],
    "name:spa_x_preferred":[
        "Pontrhydfendigaid"
    ],
    "name:swe_x_preferred":[
        "Pontrhydfendigaid"
    ],
    "name:und_x_variant":[
        "Pontrhyfendigaid"
    ],
    "qs_pg:aaroncc":"GB",
    "qs_pg:gn_country":"GB",
    "qs_pg:gn_fcode":"PPL",
    "qs_pg:gn_pop":0,
    "qs_pg:name":"Pontrhydfendigaid",
    "qs_pg:name_adm0":"United Kingdom",
    "qs_pg:name_adm1":"Wales",
    "qs_pg:photos":749,
    "qs_pg:photos_1k":152,
    "qs_pg:photos_9k":3,
    "qs_pg:photos_9r":5,
    "qs_pg:photos_all":749,
    "qs_pg:photos_sr":8,
    "qs_pg:pop_sr":0,
    "qs_pg:qs_pg_placetype":"locality",
    "qs_pg:qs_pg_placetype_gp":"Town",
    "qs_pg:woe_adm0":23424975,
    "woe:adm0_id":23424975,
    "woe:name_adm0":"United Kingdom",
    "woe:name_adm1":"Wales",
    "woe:placetype":"Town",
    "wof:name":"Pontrhydfendigaid",
    "wof:placetype":"neighbourhood",
    "wof:population":712
},
  "geometry": {"coordinates":[-3.863,52.28258],"type":"Point"}
}