{
  "type": "Feature",
  "properties": {
    "gn:admin1_code":"ENG",
    "gn:admin2_code":"G5",
    "gn:admin3_code":"29UM",
    "gn:admin4_code":"29UM004",
    "gn:asciiname":"Key Street",
    "gn:country_code":"GB",
    "gn:dem":30,
    "gn:feature_class":"P",
    "gn:feature_code":"PPL",
    "gn:name":"Key Street",
    "gn:population":0,
    "gn:timezone":"Europe/London",
    "iso:country":"GB",
    "wof:name":"Key Street",
    "wof:placetype":"neighbourhood"
},
  "geometry": {"coordinates":[0.69893,51.3454],"type":"Point"}
}