{
  "type": "Feature",
  "properties": {
    "gn:admin1_code":"ENG",
    "gn:admin2_code":"I9",
    "gn:admin3_code":"33UB",
    "gn:admin4_code":"33UB077",
    "gn:asciiname":"Eccles",
    "gn:country_code":"GB",
    "gn:dem":38,
    "gn:feature_class":"P",
    "gn:feature_code":"PPL",
    "gn:name":"Eccles",
    "gn:population":0,
    "gn:timezone":"Europe/London",
    "iso:country":"GB",
    "name:bre_x_preferred":[
        "Eccles"
    ],
    "name:ceb_x_preferred":[
        "Eccles"
    ],
    "name:deu_x_preferred":[
        "Eccles"
    ],
    "name:epo_x_preferred":[
        "Eccles"
    ],
    "name:fra_x_preferred":[
        "Eccles"
    ],
    "name:ita_x_preferred":[
        "Eccles"
    ],
    "name:jpn_x_preferred":[
        "\u30a8\u30af\u30eb\u30ba"
    ],
    "name:nld_x_preferred":[
        "Eccles"
    ],
    "name:pol_x_preferred":[
        "Eccles"
    ],
    "name:rus_x_preferred":[
        "\u042d\u043a\u043a\u043b\u0437"
    ],
    "name:spa_x_preferred":[
        "Eccles"
    ],
    "name:swe_x_preferred":[
        "Eccles"
    ],
    "name:vol_x_preferred":[
        "Eccles"
    ],
    "wof:name":"Eccles",
    "wof:placetype":"neighbourhood"
},
  "geometry": {"coordinates":[0.96834,52.47238],"type":"Point"}
}