{
  "type": "Feature",
  "properties": {
    "gn:country": "GB",
    "gn:fcode": "PPL",
    "gn:population": 0,
    "iso:country": "GB",
    "name:ceb_x_preferred": [
      "Scampton"
    ],
    "name:cym_x_preferred": [
      "Scampton"
    ],
    "name:eng_x_preferred": [
      "Scampton"
    ],
    "name:fra_x_preferred": [
      "Scampton"
    ],
    "name:jpn_x_preferred": [
      "スキャプトン"
    ],
    "name:nld_x_preferred": [
      "Scampton"
    ],
    "name:pol_x_preferred": [
      "Scampton"
    ],
    "name:swe_x_preferred": [
      "Scampton"
    ],
    "name:swe_x_variant": [
      "Scampton"
    ],
    "name:und_x_variant": [
      "Scrampton"
    ],
    "name:vol_x_preferred": [
      "Shelton"
    ],
    "name:zho_x_preferred": [
      "斯坎普頓"
    ],
    "qs_pg:aaroncc": "GB",
    "qs_pg:gn_country": "GB",
    "qs_pg:gn_fcode": "PPL",
    "qs_pg:gn_pop": 0,
    "qs_pg:name": "Scampston",
    "qs_pg:name_adm0": "United Kingdom",
    "qs_pg:name_adm1": "England",
    "qs_pg:photos": 148,
    "qs_pg:photos_1k": 30,
    "qs_pg:photos_9k": 1,
    "qs_pg:photos_9r": 3,
    "qs_pg:photos_all": 148,
    "qs_pg:photos_sr": 3,
    "qs_pg:pop_sr": 0,
    "qs_pg:qs_pg_placetype": "locality",
    "qs_pg:qs_pg_placetype_gp": "Town",
    "qs_pg:woe_adm0": 23424975,
    "woe:adm0_id": 23424975,
    "woe:name_adm0": "United Kingdom",
    "woe:name_adm1": "England",
    "woe:placetype": "Town",
    "wof:name": "Scampston",
    "wof:placetype": "neighbourhood"
  },
  "geometry": {"coordinates":[-0.57478,53.30181],"type":"Point"}
}
