{
  "type": "Feature",
  "properties": {
    "iso:country":"GB",
    "name:eng_x_preferred":[
        "Gendros"
    ],
    "qs:gn_adm0_cc":"GB",
    "qs:gn_local":2636432,
    "qs:gn_nam_loc":"Swansea, Wales, GB",
    "qs:gn_namadm1":"WLS",
    "qs:local_max":5058,
    "qs:local_sum":16167,
    "qs:localhoods":17,
    "qs:name":"Gendros",
    "qs:name_adm0":"United Kingdom",
    "qs:name_adm1":"Wales",
    "qs:name_adm2":"Swansea City and County",
    "qs:name_lau":"Swansea City and County",
    "qs:name_local":"Swansea",
    "qs:photo_max":8,
    "qs:photo_sum":18,
    "qs:placetype":"Suburb",
    "qs:quad_count":4,
    "qs:woe_adm0":23424975,
    "qs:woe_adm1":12578049,
    "qs:woe_adm2":12602229,
    "qs:woe_lau":12696131,
    "qs:woe_local":36758,
    "qs:woe_ver":"7.10.0",
    "wd:wordcount":116,
    "wof:lang":[
        "eng"
    ],
    "wof:name":"Gendros",
    "wof:placetype":"neighbourhood"
},
  "geometry": {"coordinates":[-3.987488,51.629951],"type":"Point"}
}