{
  "type": "Feature",
  "properties": {
    "gn:gn_country":"GB",
    "gn:gn_fcode":"PPL",
    "gn:gn_pop":0,
    "iso:country":"GB",
    "name:eng_x_preferred":[
        "Bettisfield"
    ],
    "name:eus_x_preferred":[
        "Bettisfield"
    ],
    "name:heb_x_preferred":[
        "\u05d1\u05d8\u05d9\u05e1\u05e4\u05d9\u05dc\u05d3"
    ],
    "name:jpn_x_preferred":[
        "\u30d9\u30c6\u30a3\u30b9\u30d5\u30a3\u30fc\u30eb\u30c9"
    ],
    "name:nld_x_preferred":[
        "Bettisfield"
    ],
    "qs_pg:aaroncc":"GB",
    "qs_pg:gn_country":"GB",
    "qs_pg:gn_fcode":"PPL",
    "qs_pg:gn_pop":0,
    "qs_pg:name":"Bettisfield",
    "qs_pg:name_adm0":"United Kingdom",
    "qs_pg:name_adm1":"Wales",
    "qs_pg:photos":41,
    "qs_pg:photos_1k":8,
    "qs_pg:photos_9k":1,
    "qs_pg:photos_9r":2,
    "qs_pg:photos_all":41,
    "qs_pg:photos_sr":2,
    "qs_pg:pop_sr":0,
    "qs_pg:qs_pg_placetype":"locality",
    "qs_pg:qs_pg_placetype_gp":"Town",
    "qs_pg:woe_adm0":23424975,
    "woe:adm0_id":23424975,
    "woe:name_adm0":"United Kingdom",
    "woe:name_adm1":"Wales",
    "woe:placetype":"Town",
    "wof:name":"Bettisfield",
    "wof:placetype":"neighbourhood"
},
  "geometry": {"coordinates":[-2.80548,52.91415],"type":"Point"}
}