{
  "type": "Feature",
  "properties": {
    "iso:country":"GB",
    "name:eng_x_preferred":[
        "Sharoe Green"
    ],
    "name:pol_x_preferred":[
        "Sharoe Green"
    ],
    "name:unk_x_variant":[
        "Sharoe Green"
    ],
    "qs:gn_adm0_cc":"GB",
    "qs:gn_local":2639912,
    "qs:gn_nam_loc":"Preston, Lancashire, England, GB",
    "qs:gn_namadm1":"ENG",
    "qs:local_max":4953,
    "qs:local_sum":17452,
    "qs:localhoods":9,
    "qs:name":"Sharoe Green",
    "qs:name_adm0":"United Kingdom",
    "qs:name_adm1":"England",
    "qs:name_adm2":"Lancashire",
    "qs:name_lau":"Preston Borough",
    "qs:name_local":"Preston",
    "qs:photo_max":289,
    "qs:photo_sum":1177,
    "qs:placetype":"Suburb",
    "qs:quad_count":71,
    "qs:woe_adm0":23424975,
    "qs:woe_adm1":24554868,
    "qs:woe_adm2":12602160,
    "qs:woe_lau":12696003,
    "qs:woe_local":32566,
    "qs:woe_ver":"7.10.0",
    "wd:wordcount":219,
    "wof:lang":[
        "eng"
    ],
    "wof:name":"Sharoe Green",
    "wof:placetype":"neighbourhood"
},
  "geometry": {"coordinates":[-2.707239,53.786352],"type":"Point"}
}