{
  "type": "Feature",
  "properties": {
    "iso:country": "GB",
    "name:eng_x_preferred": [
      "Waterfoot"
    ],
    "name:eus_x_preferred": [
      "Waterfoot"
    ],
    "name:msa_x_preferred": [
      "Waterfoot"
    ],
    "name:nld_x_preferred": [
      "Waterfoot"
    ],
    "name:pli_x_preferred": [
      "वातेर्फूत"
    ],
    "name:sco_x_preferred": [
      "Watterfit"
    ],
    "name:spa_x_preferred": [
      "Waterfoot"
    ],
    "qs_pg:aaroncc": "GB",
    "qs_pg:name": "Waterfoot",
    "qs_pg:name_adm0": "United Kingdom",
    "qs_pg:name_adm1": "Northern Ireland",
    "qs_pg:photos": 312,
    "qs_pg:photos_1k": 63,
    "qs_pg:photos_9k": 1,
    "qs_pg:photos_9r": 5,
    "qs_pg:photos_all": 312,
    "qs_pg:photos_sr": 5,
    "qs_pg:pop_sr": 0,
    "qs_pg:qs_pg_placetype": "locality",
    "qs_pg:qs_pg_placetype_gp": "Town",
    "qs_pg:woe_adm0": 23424975,
    "woe:adm0_id": 23424975,
    "woe:name_adm0": "United Kingdom",
    "woe:name_adm1": "Northern Ireland",
    "woe:placetype": "Town",
    "wof:name": "Waterfoot",
    "wof:placetype": "locality"
  },
  "geometry": {"coordinates":[-6.058565,55.062837],"type":"Point"}
}
