{
  "type": "Feature",
  "properties": {
    "gn:admin1_code":"ENG",
    "gn:admin2_code":"C9",
    "gn:admin3_code":"16UB",
    "gn:admin4_code":"16UB008",
    "gn:asciiname":"Torpenhow",
    "gn:country_code":"GB",
    "gn:dem":135,
    "gn:feature_class":"P",
    "gn:feature_code":"PPL",
    "gn:name":"Torpenhow",
    "gn:population":0,
    "gn:timezone":"Europe/London",
    "iso:country":"GB",
    "wof:name":"Torpenhow",
    "wof:placetype":"neighbourhood"
},
  "geometry": {"coordinates":[-3.24069,54.74605],"type":"Point"}
}