{
  "type": "Feature",
  "properties": {
    "gn:admin1_code": "WLS",
    "gn:admin2_code": "Y7",
    "gn:admin3_code": "00NS035",
    "gn:asciiname": "Llanhowell",
    "gn:cc2": "GB",
    "gn:country_code": "GB",
    "gn:dem": 64,
    "gn:feature_class": "P",
    "gn:feature_code": "PPL",
    "gn:name": "Llanhowell",
    "gn:population": 0,
    "gn:timezone": "Europe/London",
    "iso:country": "GB",
    "name:und_x_variant": [
      "Llanhowel",
      "Llanhowell"
    ],
    "wof:name": "Llanhowell",
    "wof:placetype": "neighbourhood"
  },
  "geometry": {"coordinates":[-5.16861,51.90222],"type":"Point"}
}
