{
  "type": "Feature",
  "properties": {
    "iso:country": "GB",
    "name:azb_x_preferred": [
      "بلانتایر"
    ],
    "name:bel_x_preferred": [
      "Блантайр"
    ],
    "name:ben_x_preferred": [
      "ব্লানটিরে"
    ],
    "name:ceb_x_preferred": [
      "High Blantyre"
    ],
    "name:cym_x_preferred": [
      "Blantyre"
    ],
    "name:deu_x_preferred": [
      "Blantyre"
    ],
    "name:ell_x_preferred": [
      "Μπλαντάιρ"
    ],
    "name:eng_x_preferred": [
      "Blantyre"
    ],
    "name:eus_x_preferred": [
      "Blantyre"
    ],
    "name:fas_x_preferred": [
      "بلانتایر"
    ],
    "name:fra_x_preferred": [
      "Blantyre"
    ],
    "name:gla_x_preferred": [
      "Baile an t-Saoir"
    ],
    "name:gle_x_preferred": [
      "Baile an t-Saoir"
    ],
    "name:guj_x_preferred": [
      "બ્લેનટાયર"
    ],
    "name:heb_x_preferred": [
      "בלנטייר"
    ],
    "name:hye_x_preferred": [
      "Բլենտայր"
    ],
    "name:ita_x_preferred": [
      "Blantyre"
    ],
    "name:jpn_x_preferred": [
      "ブランタイヤ―"
    ],
    "name:kan_x_preferred": [
      "ಬ್ಲಾಂಟೈರ್"
    ],
    "name:kat_x_preferred": [
      "ბლანტაირი"
    ],
    "name:kor_x_preferred": [
      "블랜타이어"
    ],
    "name:lit_x_preferred": [
      "Blantiras"
    ],
    "name:nld_x_preferred": [
      "Blantyre"
    ],
    "name:nno_x_preferred": [
      "Blantyre i South Lanarkshire"
    ],
    "name:nob_x_preferred": [
      "Blantyre"
    ],
    "name:pol_x_preferred": [
      "Blantyre"
    ],
    "name:por_x_preferred": [
      "Blantyre"
    ],
    "name:rus_x_preferred": [
      "Блантир"
    ],
    "name:slv_x_preferred": [
      "Blantyre"
    ],
    "name:spa_x_preferred": [
      "Blantyre"
    ],
    "name:swe_x_preferred": [
      "Blantyre"
    ],
    "name:tam_x_preferred": [
      "ப்ளாண்ட்யர்"
    ],
    "name:tel_x_preferred": [
      ""
    ],
    "name:ukr_x_preferred": [
      "Блантайр"
    ],
    "name:urd_x_preferred": [
      "بلانتیری"
    ],
    "name:zho_x_preferred": [
      "布兰太尔"
    ],
    "qs_pg:aaroncc": "GB",
    "qs_pg:name": "Blantyre",
    "qs_pg:name_adm0": "United Kingdom",
    "qs_pg:name_adm1": "Scotland",
    "qs_pg:photos": 1004,
    "qs_pg:photos_1k": 203,
    "qs_pg:photos_9k": 4,
    "qs_pg:photos_9r": 7,
    "qs_pg:photos_all": 1004,
    "qs_pg:photos_sr": 11,
    "qs_pg:pop_sr": 0,
    "qs_pg:qs_pg_placetype": "locality",
    "qs_pg:qs_pg_placetype_gp": "Town",
    "qs_pg:woe_adm0": 23424975,
    "woe:adm0_id": 23424975,
    "woe:name_adm0": "United Kingdom",
    "woe:name_adm1": "Scotland",
    "woe:placetype": "Town",
    "wof:name": "Blantyre",
    "wof:placetype": "locality"
  },
  "geometry": {"coordinates":[-4.087982,55.79186],"type":"Point"}
}
