{
  "type": "Feature",
  "properties": {
    "iso:country":"GB",
    "name:eng_x_preferred":[
        "Clachnaharry"
    ],
    "name:eus_x_preferred":[
        "Clachnaharry"
    ],
    "name:fra_x_preferred":[
        "Clachnaharry"
    ],
    "name:gle_x_preferred":[
        "Clach na h-Aithrigh"
    ],
    "qs_pg:aaroncc":"GB",
    "qs_pg:name":"Clachnaharry",
    "qs_pg:name_adm0":"United Kingdom",
    "qs_pg:name_adm1":"Scotland",
    "qs_pg:photos":131,
    "qs_pg:photos_1k":27,
    "qs_pg:photos_9k":1,
    "qs_pg:photos_9r":3,
    "qs_pg:photos_all":131,
    "qs_pg:photos_sr":3,
    "qs_pg:pop_sr":0,
    "qs_pg:qs_pg_placetype":"locality",
    "qs_pg:qs_pg_placetype_gp":"Town",
    "qs_pg:woe_adm0":23424975,
    "woe:adm0_id":23424975,
    "woe:name_adm0":"United Kingdom",
    "woe:name_adm1":"Scotland",
    "woe:placetype":"Town",
    "wof:name":"Clachnaharry",
    "wof:placetype":"locality"
},
  "geometry": {"coordinates":[-4.256172,57.489146],"type":"Point"}
}