{
  "type": "Feature",
  "properties": {
    "gn:admin1_code":"ENG",
    "gn:admin2_code":"J7",
    "gn:admin3_code":"36UD",
    "gn:admin4_code":"36UD082",
    "gn:asciiname":"Markington",
    "gn:country_code":"GB",
    "gn:dem":92,
    "gn:feature_class":"P",
    "gn:feature_code":"PPL",
    "gn:name":"Markington",
    "gn:population":0,
    "gn:timezone":"Europe/London",
    "iso:country":"GB",
    "name:pol_x_preferred":[
        "Markington"
    ],
    "wof:name":"Markington",
    "wof:placetype":"neighbourhood"
},
  "geometry": {"coordinates":[-1.56341,54.0787],"type":"Point"}
}