{
  "type": "Feature",
  "properties": {
    "iso:country":"GB",
    "name:eng_x_preferred":[
        "Winsdon Hill"
    ],
    "name:unk_x_variant":[
        "Winsdon Hill"
    ],
    "qs:gn_adm0_cc":"GB",
    "qs:gn_fcode":"PPLX",
    "qs:gn_local":2643336,
    "qs:gn_nam_loc":"new bilton",
    "qs:gn_namadm1":"ENG",
    "qs:gn_name":"Quaindon Hill",
    "qs:local_max":2611,
    "qs:local_sum":6612,
    "qs:localhoods":6,
    "qs:name":"Winsdon Hill",
    "qs:name_adm0":"United Kingdom",
    "qs:name_adm1":"England",
    "qs:name_adm2":"Bedfordshire",
    "qs:name_lau":"Luton Borough",
    "qs:name_local":"Luton",
    "qs:photo_max":447,
    "qs:photo_sum":2611,
    "qs:placetype":"Suburb",
    "qs:quad_count":96,
    "qs:woe_adm0":23424975,
    "qs:woe_adm1":24554868,
    "qs:woe_adm2":12602163,
    "qs:woe_lau":12696155,
    "qs:woe_local":27997,
    "qs:woe_ver":"7.10.0",
    "wof:lang":[
        "eng"
    ],
    "wof:name":"Winsdon Hill",
    "wof:placetype":"neighbourhood"
},
  "geometry": {"coordinates":[-0.424508,51.874516],"type":"Point"}
}