{
  "type": "Feature",
  "properties": {
    "gn:admin1_code":"ENG",
    "gn:admin2_code":"F2",
    "gn:admin3_code":"24UP",
    "gn:admin4_code":"24UP041",
    "gn:asciiname":"Twyford",
    "gn:country_code":"GB",
    "gn:dem":37,
    "gn:feature_class":"P",
    "gn:feature_code":"PPL",
    "gn:name":"Twyford",
    "gn:population":0,
    "gn:timezone":"Europe/London",
    "iso:country":"GB",
    "name:ceb_x_preferred":[
        "Twyford"
    ],
    "name:cym_x_preferred":[
        "Twyford"
    ],
    "name:fas_x_preferred":[
        "\u062a\u0648\u06cc\u0641\u0648\u0631\u062f"
    ],
    "name:ita_x_preferred":[
        "Twyford"
    ],
    "name:nld_x_preferred":[
        "Twyford"
    ],
    "name:pol_x_preferred":[
        "Twyford"
    ],
    "name:spa_x_preferred":[
        "Twyford"
    ],
    "name:swe_x_preferred":[
        "Twyford"
    ],
    "wof:name":"Twyford",
    "wof:placetype":"neighbourhood"
},
  "geometry": {"coordinates":[-1.3151,51.02218],"type":"Point"}
}