{
  "type": "Feature",
  "properties": {
    "iso:country": "GB",
    "name:cym_x_preferred": [
      "Rhydlafar"
    ],
    "name:eng_x_preferred": [
      "Rhydlafar"
    ],
    "wof:name": "Rhydlafar",
    "wof:placetype": "neighbourhood"
  },
  "geometry": {"coordinates":[-3.28065321208394,51.51180385934752],"type":"Point"}
}
