{
  "type": "Feature",
  "properties": {
    "iso:country":"GB",
    "name:eng_x_preferred":[
        "Slaithwaite"
    ],
    "name:fas_x_preferred":[
        "\u0627\u0633\u0644\u06cc\u062a\u0648\u06cc\u062a"
    ],
    "name:fra_x_preferred":[
        "Slaithwaite"
    ],
    "name:gle_x_preferred":[
        "Slaithwaite"
    ],
    "name:ita_x_preferred":[
        "Slaithwaite"
    ],
    "name:jpn_x_preferred":[
        "\u30b9\u30e9\u30b9\u30a6\u30a7\u30a4\u30c8"
    ],
    "name:nld_x_preferred":[
        "Slaithwaite"
    ],
    "name:pol_x_preferred":[
        "Slaithwaite"
    ],
    "name:swe_x_preferred":[
        "Slaithwaite"
    ],
    "name:zho_x_preferred":[
        "\u65af\u83b1\u65af\u97e6\u7279"
    ],
    "qs_pg:aaroncc":"GB",
    "qs_pg:name":"Slaithwaite",
    "qs_pg:name_adm0":"United Kingdom",
    "qs_pg:name_adm1":"England",
    "qs_pg:photos":859,
    "qs_pg:photos_1k":174,
    "qs_pg:photos_9k":4,
    "qs_pg:photos_9r":6,
    "qs_pg:photos_all":859,
    "qs_pg:photos_sr":10,
    "qs_pg:pop_sr":0,
    "qs_pg:qs_pg_placetype":"locality",
    "qs_pg:qs_pg_placetype_gp":"Town",
    "qs_pg:woe_adm0":23424975,
    "woe:adm0_id":23424975,
    "woe:name_adm0":"United Kingdom",
    "woe:name_adm1":"England",
    "woe:placetype":"Town",
    "wof:name":"Slaithwaite",
    "wof:placetype":"neighbourhood"
},
  "geometry": {"coordinates":[-1.861839,53.625299],"type":"Point"}
}