{
  "type": "Feature",
  "properties": {
    "iso:country": "GB",
    "name:eng_x_preferred": [
      "Slaithwaite"
    ],
    "name:fas_x_preferred": [
      "اسلیتویت"
    ],
    "name:fra_x_preferred": [
      "Slaithwaite"
    ],
    "name:ita_x_preferred": [
      "Slaithwaite"
    ],
    "name:jpn_x_preferred": [
      "スラスウェイト"
    ],
    "name:nld_x_preferred": [
      "Slaithwaite"
    ],
    "name:pol_x_preferred": [
      "Slaithwaite"
    ],
    "qs_pg:aaroncc": "GB",
    "qs_pg:name": "Slaithwaite",
    "qs_pg:name_adm0": "United Kingdom",
    "qs_pg:name_adm1": "England",
    "qs_pg:photos": 859,
    "qs_pg:photos_1k": 174,
    "qs_pg:photos_9k": 4,
    "qs_pg:photos_9r": 6,
    "qs_pg:photos_all": 859,
    "qs_pg:photos_sr": 10,
    "qs_pg:pop_sr": 0,
    "qs_pg:qs_pg_placetype": "locality",
    "qs_pg:qs_pg_placetype_gp": "Town",
    "qs_pg:woe_adm0": 23424975,
    "woe:adm0_id": 23424975,
    "woe:name_adm0": "United Kingdom",
    "woe:name_adm1": "England",
    "woe:placetype": "Town",
    "wof:name": "Slaithwaite",
    "wof:placetype": "neighbourhood"
  },
  "geometry": {"coordinates":[-1.861839,53.625299],"type":"Point"}
}
