{
  "type": "Feature",
  "properties": {
    "gn:country": "GB",
    "iso:country": "GB",
    "qs_pg:aaroncc": "GB",
    "qs_pg:gn_country": "GB",
    "qs_pg:name": "Seal Sands",
    "qs_pg:name_adm0": "United Kingdom",
    "qs_pg:name_adm1": "England",
    "qs_pg:photos": 2853,
    "qs_pg:photos_1k": 578,
    "qs_pg:photos_9k": 13,
    "qs_pg:photos_9r": 11,
    "qs_pg:photos_all": 2853,
    "qs_pg:photos_sr": 19,
    "qs_pg:pop_sr": 0,
    "qs_pg:qs_pg_placetype": "locality",
    "qs_pg:qs_pg_placetype_gp": "Town",
    "qs_pg:woe_adm0": 23424975,
    "woe:adm0_id": 23424975,
    "woe:name_adm0": "United Kingdom",
    "woe:name_adm1": "England",
    "woe:placetype": "Town",
    "wof:name": "Seal Sands",
    "wof:placetype": "neighbourhood"
  },
  "geometry": {"coordinates":[-1.14129,54.637982],"type":"Point"}
}
