{
  "type": "Feature",
  "properties": {
    "gn:country":"GB",
    "gn:fcode":"PPL",
    "gn:population":0,
    "iso:country":"GB",
    "name:cym_x_preferred":[
        "Lusby"
    ],
    "name:cym_x_variant":[
        "Lusb"
    ],
    "name:eng_x_preferred":[
        "Lusby"
    ],
    "name:fra_x_preferred":[
        "Lusby"
    ],
    "name:gle_x_preferred":[
        "Lusby"
    ],
    "name:nld_x_preferred":[
        "Lusby"
    ],
    "name:pol_x_preferred":[
        "Lusby"
    ],
    "qs_pg:aaroncc":"GB",
    "qs_pg:gn_country":"GB",
    "qs_pg:gn_fcode":"PPL",
    "qs_pg:gn_pop":0,
    "qs_pg:name":"Lusby",
    "qs_pg:name_adm0":"United Kingdom",
    "qs_pg:name_adm1":"England",
    "qs_pg:photos":39,
    "qs_pg:photos_1k":8,
    "qs_pg:photos_9k":1,
    "qs_pg:photos_9r":2,
    "qs_pg:photos_all":39,
    "qs_pg:photos_sr":2,
    "qs_pg:pop_sr":0,
    "qs_pg:qs_pg_placetype":"locality",
    "qs_pg:qs_pg_placetype_gp":"Town",
    "qs_pg:woe_adm0":23424975,
    "woe:adm0_id":23424975,
    "woe:name_adm0":"United Kingdom",
    "woe:name_adm1":"England",
    "woe:placetype":"Town",
    "wof:name":"Lusby",
    "wof:placetype":"neighbourhood"
},
  "geometry": {"coordinates":[0.00289,53.19041],"type":"Point"}
}