{
  "type": "Feature",
  "properties": {
    "gn:admin1_code":"ENG",
    "gn:admin2_code":"E4",
    "gn:admin3_code":"22UH",
    "gn:admin4_code":"22UH005",
    "gn:asciiname":"Clatterford End",
    "gn:country_code":"GB",
    "gn:dem":66,
    "gn:feature_class":"P",
    "gn:feature_code":"PPL",
    "gn:name":"Clatterford End",
    "gn:population":0,
    "gn:timezone":"Europe/London",
    "iso:country":"GB",
    "wof:name":"Clatterford End",
    "wof:placetype":"neighbourhood"
},
  "geometry": {"coordinates":[0.26264,51.7367],"type":"Point"}
}