{
  "type": "Feature",
  "properties": {
    "gn:admin1_code":"NIR",
    "gn:admin2_code":"N09000005",
    "gn:asciiname":"Ballyetragh",
    "gn:country_code":"GB",
    "gn:dem":170,
    "gn:feature_class":"P",
    "gn:feature_code":"PPL",
    "gn:name":"Ballyetragh",
    "gn:population":0,
    "gn:timezone":"Europe/London",
    "iso:country":"GB",
    "wof:name":"Ballyetragh",
    "wof:placetype":"locality"
},
  "geometry": {"coordinates":[-7.75,54.65],"type":"Point"}
}