{
  "type": "Feature",
  "properties": {
    "gn:country":"GB",
    "iso:country":"GB",
    "name:deu_x_preferred":[
        "Raffin"
    ],
    "name:fra_x_preferred":[
        "Raffin"
    ],
    "qs_pg:aaroncc":"GB",
    "qs_pg:gn_country":"GB",
    "qs_pg:name":"Raffin",
    "qs_pg:name_adm0":"United Kingdom",
    "qs_pg:name_adm1":"Scotland",
    "qs_pg:photos":547,
    "qs_pg:photos_1k":111,
    "qs_pg:photos_9k":2,
    "qs_pg:photos_9r":5,
    "qs_pg:photos_all":547,
    "qs_pg:photos_sr":7,
    "qs_pg:pop_sr":0,
    "qs_pg:qs_pg_placetype":"locality",
    "qs_pg:qs_pg_placetype_gp":"Town",
    "qs_pg:woe_adm0":23424975,
    "woe:adm0_id":23424975,
    "woe:name_adm0":"United Kingdom",
    "woe:name_adm1":"Scotland",
    "woe:placetype":"Town",
    "wof:name":"Raffin",
    "wof:placetype":"locality"
},
  "geometry": {"coordinates":[-5.399608,58.240434],"type":"Point"}
}