{
  "type": "Feature",
  "properties": {
    "iso:country":"GB",
    "name:eng_x_preferred":[
        "Charlestown"
    ],
    "name:eus_x_preferred":[
        "Charlestown"
    ],
    "name:fas_x_preferred":[
        "\u0686\u0627\u0631\u0644\u0632\u062a\u0627\u0648\u0646"
    ],
    "name:fra_x_preferred":[
        "Charlestown "
    ],
    "name:fra_x_variant":[
        "Charlestown"
    ],
    "name:gle_x_preferred":[
        "Charlestown"
    ],
    "name:heb_x_preferred":[
        "\u05e6'\u05d0\u05e8\u05dc\u05e1\u05d8\u05d0\u05d5\u05df"
    ],
    "name:ita_x_preferred":[
        "Charlestown"
    ],
    "name:nld_x_preferred":[
        "Charlestown"
    ],
    "name:nob_x_preferred":[
        "Charlestown"
    ],
    "name:pol_x_preferred":[
        "Charlestown"
    ],
    "name:unk_x_variant":[
        "Earlestown"
    ],
    "name:urd_x_preferred":[
        "\u0686\u0627\u0631\u0644\u0633 \u0679\u0627\u0624\u0646\u060c \u06a9\u0648\u0631\u0646\u0648\u0627\u0644"
    ],
    "name:urd_x_variant":[
        "\u0686\u0627\u0631\u0644\u0633 \u0679\u0627\u0624\u0646"
    ],
    "qs:a0":"United Kingdom",
    "qs:a1":"*Cornwall",
    "qs:a1_lc":"GB12HE0000",
    "qs:a1r":"0England",
    "qs:a1r_lc":"GB12000000",
    "qs:adm0":"United Kingdom",
    "qs:la_lc":"*",
    "qs:level":"locality",
    "qs:loc":"Charlestown",
    "qs:loc_alt":"Charlestown",
    "qs:pop":0,
    "qs:type":"buffered point",
    "wd:wordcount":1774,
    "wof:name":"Charlestown",
    "wof:placetype":"neighbourhood"
},
  "geometry": {"coordinates":[-4.758635,50.333055],"type":"Point"}
}