{
  "type": "Feature",
  "properties": {
    "iso:country": "GB",
    "name:eng_x_preferred": [
      "Charlestown"
    ],
    "name:eus_x_preferred": [
      "Charlestown"
    ],
    "name:fas_x_preferred": [
      "چارلزتاون"
    ],
    "name:fra_x_preferred": [
      "Charlestown"
    ],
    "name:fra_x_variant": [
      "Charlestown"
    ],
    "name:gle_x_preferred": [
      "Charlestown"
    ],
    "name:heb_x_preferred": [
      "צ'ארלסטאון"
    ],
    "name:ita_x_preferred": [
      "Charlestown"
    ],
    "name:nld_x_preferred": [
      "Charlestown"
    ],
    "name:nob_x_preferred": [
      "Charlestown"
    ],
    "name:pol_x_preferred": [
      "Charlestown"
    ],
    "name:und_x_variant": [
      "Earlestown"
    ],
    "name:urd_x_preferred": [
      "چارلس ٹاؤن، کورنوال"
    ],
    "name:urd_x_variant": [
      "چارلس ٹاؤن"
    ],
    "qs:a0": "United Kingdom",
    "qs:a1": "*Cornwall",
    "qs:a1_lc": "GB12HE0000",
    "qs:a1r": "0England",
    "qs:a1r_lc": "GB12000000",
    "qs:adm0": "United Kingdom",
    "qs:la_lc": "*",
    "qs:level": "locality",
    "qs:loc": "Charlestown",
    "qs:loc_alt": "Charlestown",
    "qs:pop": 0,
    "qs:type": "buffered point",
    "wd:wordcount": 1774,
    "wof:name": "Charlestown",
    "wof:placetype": "neighbourhood"
  },
  "geometry": {"coordinates":[-4.758635,50.333055],"type":"Point"}
}
