{
  "type": "Feature",
  "properties": {
    "iso:country": "GB",
    "name:afr_x_preferred": [
      "Ekster"
    ],
    "name:ara_x_preferred": [
      "عقعق"
    ],
    "name:epo_x_preferred": [
      "Pigoj"
    ],
    "name:fas_x_preferred": [
      "زاغی"
    ],
    "name:fin_x_preferred": [
      "Harakkalinnut"
    ],
    "name:fra_x_preferred": [
      "Pie"
    ],
    "name:gle_x_preferred": [
      "Snag breac"
    ],
    "name:heb_x_preferred": [
      "עקעקים"
    ],
    "name:hye_x_preferred": [
      "Կաչաղակներ"
    ],
    "name:lav_x_preferred": [
      "Žagatas"
    ],
    "name:mal_x_preferred": [
      "മാഗ്പീ"
    ],
    "name:pcd_x_preferred": [
      "Agache"
    ],
    "name:pnb_x_preferred": [
      "سیانا کاں"
    ],
    "name:por_x_preferred": [
      "Pega"
    ],
    "name:swa_x_preferred": [
      "Kinubi"
    ],
    "name:tam_x_preferred": [
      "மேக்பை"
    ],
    "name:tel_x_preferred": [
      "కొండకాటి పిట్ట"
    ],
    "name:tgl_x_preferred": [
      "Dominiko"
    ],
    "name:tha_x_preferred": [
      "นกสาลิกา"
    ],
    "qs_pg:aaroncc": "GB",
    "qs_pg:name": "Magpie",
    "qs_pg:name_adm0": "United Kingdom",
    "qs_pg:name_adm1": "England",
    "qs_pg:photos": 32,
    "qs_pg:photos_1k": 6,
    "qs_pg:photos_9k": 1,
    "qs_pg:photos_9r": 2,
    "qs_pg:photos_all": 32,
    "qs_pg:photos_sr": 2,
    "qs_pg:pop_sr": 0,
    "qs_pg:qs_pg_placetype": "locality",
    "qs_pg:qs_pg_placetype_gp": "Town",
    "qs_pg:woe_adm0": 23424975,
    "woe:adm0_id": 23424975,
    "woe:name_adm0": "United Kingdom",
    "woe:name_adm1": "England",
    "woe:placetype": "Town",
    "wof:name": "Magpie",
    "wof:placetype": "neighbourhood"
  },
  "geometry": {"coordinates":[-4.111395,50.512826],"type":"Point"}
}
