{
  "type": "Feature",
  "properties": {
    "iso:country":"GB",
    "name:afr_x_preferred":[
        "Ekster"
    ],
    "name:ara_x_preferred":[
        "\u0639\u0642\u0639\u0642"
    ],
    "name:epo_x_preferred":[
        "Pigoj"
    ],
    "name:fas_x_preferred":[
        "\u0632\u0627\u063a\u06cc"
    ],
    "name:fin_x_preferred":[
        "Harakkalinnut"
    ],
    "name:fra_x_preferred":[
        "Pie"
    ],
    "name:gle_x_preferred":[
        "Snag breac"
    ],
    "name:heb_x_preferred":[
        "\u05e2\u05e7\u05e2\u05e7\u05d9\u05dd"
    ],
    "name:hye_x_preferred":[
        "\u053f\u0561\u0579\u0561\u0572\u0561\u056f\u0576\u0565\u0580"
    ],
    "name:lav_x_preferred":[
        "\u017dagatas"
    ],
    "name:mal_x_preferred":[
        "\u0d2e\u0d3e\u0d17\u0d4d\u0d2a\u0d40"
    ],
    "name:pcd_x_preferred":[
        "Agache"
    ],
    "name:pnb_x_preferred":[
        "\u0633\u06cc\u0627\u0646\u0627 \u06a9\u0627\u06ba"
    ],
    "name:por_x_preferred":[
        "Pega"
    ],
    "name:swa_x_preferred":[
        "Kinubi"
    ],
    "name:tam_x_preferred":[
        "\u0bae\u0bc7\u0b95\u0bcd\u0baa\u0bc8"
    ],
    "name:tel_x_preferred":[
        "\u0c15\u0c4a\u0c02\u0c21\u0c15\u0c3e\u0c1f\u0c3f \u0c2a\u0c3f\u0c1f\u0c4d\u0c1f"
    ],
    "name:tgl_x_preferred":[
        "Dominiko"
    ],
    "name:tha_x_preferred":[
        "\u0e19\u0e01\u0e2a\u0e32\u0e25\u0e34\u0e01\u0e32"
    ],
    "qs_pg:aaroncc":"GB",
    "qs_pg:name":"Magpie",
    "qs_pg:name_adm0":"United Kingdom",
    "qs_pg:name_adm1":"England",
    "qs_pg:photos":32,
    "qs_pg:photos_1k":6,
    "qs_pg:photos_9k":1,
    "qs_pg:photos_9r":2,
    "qs_pg:photos_all":32,
    "qs_pg:photos_sr":2,
    "qs_pg:pop_sr":0,
    "qs_pg:qs_pg_placetype":"locality",
    "qs_pg:qs_pg_placetype_gp":"Town",
    "qs_pg:woe_adm0":23424975,
    "woe:adm0_id":23424975,
    "woe:name_adm0":"United Kingdom",
    "woe:name_adm1":"England",
    "woe:placetype":"Town",
    "wof:name":"Magpie",
    "wof:placetype":"neighbourhood"
},
  "geometry": {"coordinates":[-4.111395,50.512826],"type":"Point"}
}