{
  "type": "Feature",
  "properties": {
    "gn:gn_country":"GB",
    "gn:gn_fcode":"PPL",
    "gn:gn_pop":651,
    "gn:population":950,
    "iso:country":"GB",
    "name:bul_x_preferred":[
        "\u0411\u043b\u0430\u0438\u0440\u0445\u0430\u043b"
    ],
    "name:ceb_x_preferred":[
        "Blairhall"
    ],
    "name:cym_x_preferred":[
        "Blairhall"
    ],
    "name:eng_x_preferred":[
        "Blairhall"
    ],
    "name:eus_x_preferred":[
        "Blairhall"
    ],
    "name:fra_x_preferred":[
        "Blairhall"
    ],
    "name:nld_x_preferred":[
        "Blairhall"
    ],
    "name:spa_x_preferred":[
        "Blairhall"
    ],
    "name:swe_x_preferred":[
        "Blairhall"
    ],
    "qs_pg:aaroncc":"GB",
    "qs_pg:gn_country":"GB",
    "qs_pg:gn_fcode":"PPL",
    "qs_pg:gn_pop":651,
    "qs_pg:name":"Blairhall",
    "qs_pg:name_adm0":"United Kingdom",
    "qs_pg:name_adm1":"Scotland",
    "qs_pg:photos":52,
    "qs_pg:photos_1k":11,
    "qs_pg:photos_9k":1,
    "qs_pg:photos_9r":2,
    "qs_pg:photos_all":52,
    "qs_pg:photos_sr":2,
    "qs_pg:pop_sr":2,
    "qs_pg:qs_pg_placetype":"locality",
    "qs_pg:qs_pg_placetype_gp":"Town",
    "qs_pg:woe_adm0":23424975,
    "woe:adm0_id":23424975,
    "woe:name_adm0":"United Kingdom",
    "woe:name_adm1":"Scotland",
    "woe:placetype":"Town",
    "wof:name":"Blairhall",
    "wof:placetype":"locality",
    "wof:population":950
},
  "geometry": {"coordinates":[-3.60223,56.08788],"type":"Point"}
}