{
  "type": "Feature",
  "properties": {
    "gn:admin1_code": "ENG",
    "gn:admin2_code": "J4",
    "gn:admin3_code": "00HC003",
    "gn:asciiname": "Banwell Castle",
    "gn:country_code": "GB",
    "gn:dem": 63,
    "gn:feature_class": "P",
    "gn:feature_code": "PPL",
    "gn:name": "Banwell Castle",
    "gn:population": 0,
    "gn:timezone": "Europe/London",
    "iso:country": "GB",
    "wof:name": "Banwell Castle",
    "wof:placetype": "neighbourhood"
  },
  "geometry": {"coordinates":[-2.86053,51.32407],"type":"Point"}
}
