{
  "type": "Feature",
  "properties": {
    "iso:country":"GB",
    "name:ceb_x_preferred":[
        "Cape Cornwall"
    ],
    "name:deu_x_preferred":[
        "Cape Cornwall"
    ],
    "name:eus_x_preferred":[
        "Kornualles lurmuturra"
    ],
    "name:fas_x_preferred":[
        "\u062f\u0645\u0627\u063a\u0647 \u06a9\u0648\u0631\u0646\u0648\u0627\u0644"
    ],
    "name:fra_x_preferred":[
        "Cap Cornwall"
    ],
    "name:ita_x_preferred":[
        "Capo Cornwall"
    ],
    "name:nld_x_preferred":[
        "Cape Cornwall"
    ],
    "name:nno_x_preferred":[
        "Cape Cornwall"
    ],
    "name:pol_x_preferred":[
        "Cape Cornwall"
    ],
    "name:spa_x_preferred":[
        "Cabo Cornualles"
    ],
    "name:swe_x_preferred":[
        "Cape Cornwall"
    ],
    "qs_pg:aaroncc":"GB",
    "qs_pg:name":"Cape Cornwall",
    "qs_pg:name_adm0":"United Kingdom",
    "qs_pg:name_adm1":"England",
    "qs_pg:photos":1924,
    "qs_pg:photos_1k":390,
    "qs_pg:photos_9k":9,
    "qs_pg:photos_9r":9,
    "qs_pg:photos_all":1924,
    "qs_pg:photos_sr":15,
    "qs_pg:pop_sr":0,
    "qs_pg:qs_pg_placetype":"locality",
    "qs_pg:qs_pg_placetype_gp":"Town",
    "qs_pg:woe_adm0":23424975,
    "woe:adm0_id":23424975,
    "woe:name_adm0":"United Kingdom",
    "woe:name_adm1":"England",
    "woe:placetype":"Town",
    "wof:name":"Cape Cornwall",
    "wof:placetype":"neighbourhood"
},
  "geometry": {"coordinates":[-5.706,50.126369],"type":"Point"}
}