{
  "type": "Feature",
  "properties": {
    "iso:country":"GB",
    "name:cym_x_preferred":[
        "Blackmoor Gate"
    ],
    "name:eng_x_preferred":[
        "Blackmoor Gate"
    ],
    "name:fra_x_preferred":[
        "Blackmoor Gate"
    ],
    "name:nld_x_preferred":[
        "Blackmoor Gate"
    ],
    "qs_pg:aaroncc":"GB",
    "qs_pg:name":"Blackmoor Gate",
    "qs_pg:name_adm0":"United Kingdom",
    "qs_pg:name_adm1":"England",
    "qs_pg:photos":457,
    "qs_pg:photos_1k":93,
    "qs_pg:photos_9k":2,
    "qs_pg:photos_9r":5,
    "qs_pg:photos_all":457,
    "qs_pg:photos_sr":7,
    "qs_pg:pop_sr":0,
    "qs_pg:qs_pg_placetype":"locality",
    "qs_pg:qs_pg_placetype_gp":"Town",
    "qs_pg:woe_adm0":23424975,
    "woe:adm0_id":23424975,
    "woe:name_adm0":"United Kingdom",
    "woe:name_adm1":"England",
    "woe:placetype":"Town",
    "wof:name":"Blackmoor Gate",
    "wof:placetype":"neighbourhood"
},
  "geometry": {"coordinates":[-3.925123,51.149847],"type":"Point"}
}