{
  "type": "Feature",
  "properties": {
    "iso:country": "GB",
    "name:arg_x_preferred": [
      "Garòs"
    ],
    "name:cat_x_preferred": [
      "Garòs"
    ],
    "name:ceb_x_preferred": [
      "Garos"
    ],
    "name:deu_x_preferred": [
      "Garos"
    ],
    "name:eus_x_preferred": [
      "Garos"
    ],
    "name:fra_x_preferred": [
      "Garos"
    ],
    "name:hun_x_preferred": [
      "Garos"
    ],
    "name:ita_x_preferred": [
      "Garos"
    ],
    "name:kaz_x_preferred": [
      "Гарос"
    ],
    "name:lat_x_preferred": [
      "Garos"
    ],
    "name:mlg_x_preferred": [
      "Garos"
    ],
    "name:msa_x_preferred": [
      "Garos"
    ],
    "name:nld_x_preferred": [
      "Garos"
    ],
    "name:oci_x_preferred": [
      "Garòs"
    ],
    "name:pms_x_preferred": [
      "Garos"
    ],
    "name:pol_x_preferred": [
      "Garos"
    ],
    "name:por_x_preferred": [
      "Garos"
    ],
    "name:ron_x_preferred": [
      "Garos"
    ],
    "name:rus_x_preferred": [
      "Гарос"
    ],
    "name:slk_x_preferred": [
      "Garos"
    ],
    "name:spa_x_preferred": [
      "Garos"
    ],
    "name:swe_x_preferred": [
      "Garos"
    ],
    "name:ukr_x_preferred": [
      "Гарос"
    ],
    "name:uzb_x_preferred": [
      "Garos"
    ],
    "name:vie_x_preferred": [
      "Garos"
    ],
    "name:vol_x_preferred": [
      "Garos"
    ],
    "name:war_x_preferred": [
      "Garos"
    ],
    "qs_pg:aaroncc": "GB",
    "qs_pg:name": "Garos",
    "qs_pg:name_adm0": "United Kingdom",
    "qs_pg:name_adm1": "Scotland",
    "qs_pg:photos": 174,
    "qs_pg:photos_1k": 35,
    "qs_pg:photos_9k": 1,
    "qs_pg:photos_9r": 4,
    "qs_pg:photos_all": 174,
    "qs_pg:photos_sr": 4,
    "qs_pg:pop_sr": 0,
    "qs_pg:qs_pg_placetype": "locality",
    "qs_pg:qs_pg_placetype_gp": "Town",
    "qs_pg:woe_adm0": 23424975,
    "woe:adm0_id": 23424975,
    "woe:name_adm0": "United Kingdom",
    "woe:name_adm1": "Scotland",
    "woe:placetype": "Town",
    "wof:name": "Garos",
    "wof:placetype": "locality"
  },
  "geometry": {"coordinates":[-6.1867615,57.521538],"type":"Point"}
}
