{
  "type": "Feature",
  "properties": {
    "iso:country":"GB",
    "name:eng_x_preferred":[
        "South Stoneham"
    ],
    "name:eng_x_variant":[
        "S Stoneham"
    ],
    "name:unk_x_variant":[
        "South Stoneham"
    ],
    "qs:gn_fcode":"PPLX",
    "qs:gn_local":0,
    "qs:gn_nam_loc":"princes risborough",
    "qs:gn_namadm1":"ENG",
    "qs:gn_name":"South Stoneham",
    "qs:local_max":4987,
    "qs:local_sum":37365,
    "qs:localhoods":16,
    "qs:name":"South Stoneham",
    "qs:name_adm0":"United Kingdom",
    "qs:name_adm1":"England",
    "qs:name_adm2":"Hampshire",
    "qs:name_lau":"Southampton City",
    "qs:name_local":"Southampton",
    "qs:photo_max":2266,
    "qs:photo_sum":4987,
    "qs:placetype":"Suburb",
    "qs:quad_count":67,
    "qs:woe_adm0":23424975,
    "qs:woe_adm1":24554868,
    "qs:woe_adm2":12602169,
    "qs:woe_lau":12696160,
    "qs:woe_local":35356,
    "qs:woe_ver":"7.10.0",
    "wd:wordcount":1785,
    "wof:lang":[
        "eng"
    ],
    "wof:name":"South Stoneham",
    "wof:placetype":"neighbourhood"
},
  "geometry": {"coordinates":[-1.364243,50.950175],"type":"Point"}
}