{
  "type": "Feature",
  "properties": {
    "gn:admin1_code":"ENG",
    "gn:admin2_code":"G2",
    "gn:admin3_code":"00MW019",
    "gn:asciiname":"Hamstead",
    "gn:country_code":"GB",
    "gn:dem":49,
    "gn:feature_class":"P",
    "gn:feature_code":"PPL",
    "gn:name":"Hamstead",
    "gn:population":0,
    "gn:timezone":"Europe/London",
    "iso:country":"GB",
    "name:pol_x_preferred":[
        "Hamstead"
    ],
    "wof:name":"Hamstead",
    "wof:placetype":"neighbourhood"
},
  "geometry": {"coordinates":[-1.43809,50.72032],"type":"Point"}
}