{
  "type": "Feature",
  "properties": {
    "iso:country":"GB",
    "name:ara_x_preferred":[
        "\u062c\u0645\u0628"
    ],
    "name:arz_x_preferred":[
        "\u062c\u0645\u0628"
    ],
    "name:eng_x_preferred":[
        "Jump"
    ],
    "name:fra_x_preferred":[
        "Jump"
    ],
    "name:gle_x_preferred":[
        "Jump"
    ],
    "name:nld_x_preferred":[
        "Jump"
    ],
    "name:nob_x_preferred":[
        "Jump"
    ],
    "name:pol_x_preferred":[
        "Jump"
    ],
    "qs_pg:aaroncc":"GB",
    "qs_pg:name":"Jump",
    "qs_pg:name_adm0":"United Kingdom",
    "qs_pg:name_adm1":"England",
    "qs_pg:photos":50,
    "qs_pg:photos_1k":10,
    "qs_pg:photos_9k":1,
    "qs_pg:photos_9r":2,
    "qs_pg:photos_all":50,
    "qs_pg:photos_sr":2,
    "qs_pg:pop_sr":0,
    "qs_pg:qs_pg_placetype":"locality",
    "qs_pg:qs_pg_placetype_gp":"Town",
    "qs_pg:woe_adm0":23424975,
    "woe:adm0_id":23424975,
    "woe:name_adm0":"United Kingdom",
    "woe:name_adm1":"England",
    "woe:placetype":"Town",
    "wof:name":"Jump",
    "wof:placetype":"neighbourhood"
},
  "geometry": {"coordinates":[-1.42951,53.506821],"type":"Point"}
}