{
  "type": "Feature",
  "properties": {
    "gn:population":2212,
    "iso:country":"GB",
    "name:ceb_x_preferred":[
        "Sion Mills"
    ],
    "name:eng_x_preferred":[
        "Sion Mills"
    ],
    "name:eus_x_preferred":[
        "Sion Mills"
    ],
    "name:fas_x_preferred":[
        "\u0633\u06cc\u0648\u0646 \u0645\u06cc\u0644\u0632"
    ],
    "name:fra_x_preferred":[
        "Sion Mills"
    ],
    "name:gle_x_preferred":[
        "Muileann an tSi\u00e1in"
    ],
    "name:ita_x_preferred":[
        "Sion Mills"
    ],
    "name:msa_x_preferred":[
        "Sion Mills"
    ],
    "name:nld_x_preferred":[
        "Sion Mills"
    ],
    "name:pli_x_preferred":[
        "\u0938\u093e\u092f\u0928 \u092e\u093f\u0932\u094d\u0938"
    ],
    "name:spa_x_preferred":[
        "Sion Mills"
    ],
    "name:swe_x_preferred":[
        "Sion Mills"
    ],
    "name:und_x_variant":[
        "Sion Mill"
    ],
    "qs:a0":"United Kingdom",
    "qs:a1":"*Strabane",
    "qs:a1_lc":"N_A",
    "qs:a1r":"0Northern Ireland",
    "qs:a1r_lc":"N_A",
    "qs:adm0":"United Kingdom",
    "qs:la_lc":"*",
    "qs:level":"locality",
    "qs:loc":"Sion Mills",
    "qs:loc_alt":"Sion Mills",
    "qs:pop":0,
    "qs:type":"buffered point",
    "wd:wordcount":1027,
    "wof:name":"Sion Mills",
    "wof:placetype":"locality",
    "wof:population":2212
},
  "geometry": {"coordinates":[-7.473219,54.783832],"type":"Point"}
}