{
  "type": "Feature",
  "properties": {
    "gn:country":"GB",
    "gn:fcode":"PPL",
    "gn:population":0,
    "iso:country":"GB",
    "name:ceb_x_preferred":[
        "Whitton"
    ],
    "name:deu_x_preferred":[
        "Whitton"
    ],
    "name:fra_x_preferred":[
        "Whitton"
    ],
    "name:hin_x_preferred":[
        "\u0939\u094d\u0935\u093f\u091f\u0928"
    ],
    "name:ita_x_preferred":[
        "Whitton"
    ],
    "name:nld_x_preferred":[
        "Whitton"
    ],
    "name:pol_x_preferred":[
        "Whitton"
    ],
    "name:rus_x_preferred":[
        "\u0423\u0438\u0442\u0442\u043e\u043d"
    ],
    "name:sco_x_preferred":[
        "Whitton"
    ],
    "name:swe_x_preferred":[
        "Whitton"
    ],
    "qs_pg:aaroncc":"GB",
    "qs_pg:gn_country":"GB",
    "qs_pg:gn_fcode":"PPL",
    "qs_pg:gn_pop":0,
    "qs_pg:name":"Whitton",
    "qs_pg:name_adm0":"United Kingdom",
    "qs_pg:name_adm1":"England",
    "qs_pg:photos":95,
    "qs_pg:photos_1k":19,
    "qs_pg:photos_9k":1,
    "qs_pg:photos_9r":3,
    "qs_pg:photos_all":95,
    "qs_pg:photos_sr":3,
    "qs_pg:pop_sr":0,
    "qs_pg:qs_pg_placetype":"locality",
    "qs_pg:qs_pg_placetype_gp":"Town",
    "qs_pg:woe_adm0":23424975,
    "woe:adm0_id":23424975,
    "woe:name_adm0":"United Kingdom",
    "woe:name_adm1":"England",
    "woe:placetype":"Town",
    "wof:name":"Whitton",
    "wof:placetype":"locality"
},
  "geometry": {"coordinates":[-2.38333,55.48333],"type":"Point"}
}