{
  "type": "Feature",
  "properties": {
    "iso:country":"GB",
    "name:bre_x_preferred":[
        "Pwll"
    ],
    "name:cym_x_preferred":[
        "Pwll"
    ],
    "name:eng_x_preferred":[
        "Pwll"
    ],
    "name:eus_x_preferred":[
        "Pwll"
    ],
    "name:fra_x_preferred":[
        "Pwll"
    ],
    "name:nld_x_preferred":[
        "Pwll"
    ],
    "name:spa_x_preferred":[
        "Pwll"
    ],
    "name:swe_x_preferred":[
        "Pwll"
    ],
    "qs_pg:aaroncc":"GB",
    "qs_pg:name":"Pwll",
    "qs_pg:name_adm0":"United Kingdom",
    "qs_pg:name_adm1":"Wales",
    "qs_pg:photos":92,
    "qs_pg:photos_1k":19,
    "qs_pg:photos_9k":1,
    "qs_pg:photos_9r":3,
    "qs_pg:photos_all":92,
    "qs_pg:photos_sr":3,
    "qs_pg:pop_sr":0,
    "qs_pg:qs_pg_placetype":"locality",
    "qs_pg:qs_pg_placetype_gp":"Town",
    "qs_pg:woe_adm0":23424975,
    "woe:adm0_id":23424975,
    "woe:name_adm0":"United Kingdom",
    "woe:name_adm1":"Wales",
    "woe:placetype":"Town",
    "wof:name":"Pwll",
    "wof:placetype":"neighbourhood"
},
  "geometry": {"coordinates":[-4.256429,51.680432],"type":"Point"}
}