{
  "type": "Feature",
  "properties": {
    "gn:gn_country":"GB",
    "gn:gn_fcode":"PPL",
    "gn:gn_pop":0,
    "iso:country":"GB",
    "name:eng_x_preferred":[
        "Ballycassidy"
    ],
    "name:fra_x_preferred":[
        "Ballycassidy"
    ],
    "name:gle_x_preferred":[
        "Baile U\u00ed Chaiside"
    ],
    "name:msa_x_preferred":[
        "Ballycassidy"
    ],
    "name:nld_x_preferred":[
        "Ballycassidy"
    ],
    "name:pli_x_preferred":[
        "\u092c\u0932\u094d\u0932\u094d\u092f\u094d\u0915\u093e\u0938\u094d\u0938\u093f\u0926\u094d\u092f"
    ],
    "qs_pg:aaroncc":"GB",
    "qs_pg:gn_country":"GB",
    "qs_pg:gn_fcode":"PPL",
    "qs_pg:gn_pop":0,
    "qs_pg:name":"Ballycassidy",
    "qs_pg:name_adm0":"United Kingdom",
    "qs_pg:name_adm1":"Northern Ireland",
    "qs_pg:photos":135,
    "qs_pg:photos_1k":27,
    "qs_pg:photos_9k":1,
    "qs_pg:photos_9r":3,
    "qs_pg:photos_all":135,
    "qs_pg:photos_sr":3,
    "qs_pg:pop_sr":0,
    "qs_pg:qs_pg_placetype":"locality",
    "qs_pg:qs_pg_placetype_gp":"Town",
    "qs_pg:woe_adm0":23424975,
    "woe:adm0_id":23424975,
    "woe:name_adm0":"United Kingdom",
    "woe:name_adm1":"Northern Ireland",
    "woe:placetype":"Town",
    "wof:name":"Ballycassidy",
    "wof:placetype":"locality"
},
  "geometry": {"coordinates":[-7.64756,54.40352],"type":"Point"}
}