{
  "type": "Feature",
  "properties": {
    "gn:country": "GB",
    "gn:fcode": "PPL",
    "gn:population": 12739,
    "iso:country": "GB",
    "name:bul_x_preferred": [
      "Фримлей"
    ],
    "name:ceb_x_preferred": [
      "Frimley"
    ],
    "name:eng_x_preferred": [
      "Frimley"
    ],
    "name:fas_x_preferred": [
      "فریملی"
    ],
    "name:fra_x_preferred": [
      "Frimley"
    ],
    "name:heb_x_preferred": [
      "פרימלי"
    ],
    "name:ita_x_preferred": [
      "Frimley"
    ],
    "name:jpn_x_preferred": [
      "フリムリー"
    ],
    "name:kat_x_preferred": [
      "ფრიმლი"
    ],
    "name:nld_x_preferred": [
      "Frimley"
    ],
    "name:nno_x_preferred": [
      "Frimley"
    ],
    "name:nob_x_preferred": [
      "Frimley"
    ],
    "name:pol_x_preferred": [
      "Frimley"
    ],
    "name:por_x_preferred": [
      "Frimley"
    ],
    "name:rus_x_preferred": [
      "Фримли"
    ],
    "name:spa_x_preferred": [
      "Frimley"
    ],
    "name:swe_x_preferred": [
      "Frimley"
    ],
    "qs_pg:aaroncc": "GB",
    "qs_pg:gn_country": "GB",
    "qs_pg:gn_fcode": "PPL",
    "qs_pg:gn_pop": 12739,
    "qs_pg:name": "Frimley",
    "qs_pg:name_adm0": "United Kingdom",
    "qs_pg:name_adm1": "England",
    "qs_pg:photos": 691,
    "qs_pg:photos_1k": 140,
    "qs_pg:photos_9k": 3,
    "qs_pg:photos_9r": 5,
    "qs_pg:photos_all": 691,
    "qs_pg:photos_sr": 8,
    "qs_pg:pop_sr": 6,
    "qs_pg:qs_pg_placetype": "locality",
    "qs_pg:qs_pg_placetype_gp": "Town",
    "qs_pg:woe_adm0": 23424975,
    "woe:adm0_id": 23424975,
    "woe:name_adm0": "United Kingdom",
    "woe:name_adm1": "England",
    "woe:placetype": "Town",
    "wof:name": "Frimley",
    "wof:placetype": "neighbourhood",
    "wof:population": 12739
  },
  "geometry": {"coordinates":[-0.72527,51.30288],"type":"Point"}
}
