{
  "type": "Feature",
  "properties": {
    "iso:country":"GB",
    "name:eng_x_preferred":[
        "Aldrington"
    ],
    "name:nld_x_preferred":[
        "Aldrington"
    ],
    "name:unk_x_variant":[
        "Aldrington"
    ],
    "qs:gn_fcode":"PPL",
    "qs:gn_local":0,
    "qs:gn_namadm1":"ENG",
    "qs:gn_name":"Allington",
    "qs:local_max":4760,
    "qs:local_sum":7557,
    "qs:localhoods":3,
    "qs:name":"Aldrington",
    "qs:name_adm0":"United Kingdom",
    "qs:name_adm1":"England",
    "qs:name_adm2":"East Sussex",
    "qs:name_lau":"Brighton and Hove City",
    "qs:name_local":"Hove",
    "qs:photo_max":398,
    "qs:photo_sum":4760,
    "qs:placetype":"Suburb",
    "qs:quad_count":136,
    "qs:woe_adm0":23424975,
    "qs:woe_adm1":24554868,
    "qs:woe_adm2":12602167,
    "qs:woe_lau":12696151,
    "qs:woe_local":24024,
    "qs:woe_ver":"7.10.0",
    "wd:wordcount":434,
    "wof:lang":[
        "eng"
    ],
    "wof:name":"Aldrington",
    "wof:placetype":"neighbourhood"
},
  "geometry": {"coordinates":[-0.188474,50.828467],"type":"Point"}
}