{
  "type": "Feature",
  "properties": {
    "gn:admin1_code":"ENG",
    "gn:admin2_code":"J7",
    "gn:admin3_code":"36UD",
    "gn:admin4_code":"36UD048",
    "gn:asciiname":"Walshford",
    "gn:country_code":"GB",
    "gn:dem":25,
    "gn:feature_class":"P",
    "gn:feature_code":"PPLL",
    "gn:name":"Walshford",
    "gn:population":0,
    "gn:timezone":"Europe/London",
    "iso:country":"GB",
    "name:pol_x_preferred":[
        "Walshford"
    ],
    "wof:name":"Walshford",
    "wof:placetype":"neighbourhood"
},
  "geometry": {"coordinates":[-1.37243,53.97356],"type":"Point"}
}