{
  "type": "Feature",
  "properties": {
    "gn:admin1_code":"ENG",
    "gn:admin2_code":"I9",
    "gn:admin3_code":"33UH",
    "gn:admin4_code":"33UH099",
    "gn:asciiname":"Hapton",
    "gn:country_code":"GB",
    "gn:dem":24,
    "gn:feature_class":"P",
    "gn:feature_code":"PPL",
    "gn:name":"Hapton",
    "gn:population":0,
    "gn:timezone":"Europe/London",
    "iso:country":"GB",
    "name:nld_x_preferred":[
        "Hapton"
    ],
    "name:pol_x_preferred":[
        "Hapton"
    ],
    "wof:name":"Hapton",
    "wof:placetype":"neighbourhood"
},
  "geometry": {"coordinates":[1.20652,52.52202],"type":"Point"}
}