{
  "type": "Feature",
  "properties": {
    "gn:admin1_code":"ENG",
    "gn:admin2_code":"G5",
    "gn:admin3_code":"29UG",
    "gn:admin4_code":"29UG001",
    "gn:asciiname":"Gold Street",
    "gn:country_code":"GB",
    "gn:dem":99,
    "gn:feature_class":"P",
    "gn:feature_code":"PPL",
    "gn:name":"Gold Street",
    "gn:population":0,
    "gn:timezone":"Europe/London",
    "iso:country":"GB",
    "wof:name":"Gold Street",
    "wof:placetype":"neighbourhood"
},
  "geometry": {"coordinates":[0.38733,51.38431],"type":"Point"}
}