{
  "type": "Feature",
  "properties": {
    "gn:admin1_code":"ENG",
    "gn:admin2_code":"F2",
    "gn:admin3_code":"24UC",
    "gn:admin4_code":"24UC035",
    "gn:asciiname":"Hollywater",
    "gn:country_code":"GB",
    "gn:dem":77,
    "gn:feature_class":"P",
    "gn:feature_code":"PPL",
    "gn:name":"Hollywater",
    "gn:population":0,
    "gn:timezone":"Europe/London",
    "iso:country":"GB",
    "name:cym_x_preferred":[
        "Hollywater"
    ],
    "name:pol_x_preferred":[
        "Hollywater"
    ],
    "wof:name":"Hollywater",
    "wof:placetype":"neighbourhood"
},
  "geometry": {"coordinates":[-0.85243,51.10223],"type":"Point"}
}