{
  "type": "Feature",
  "properties": {
    "iso:country": "GB",
    "name:ben_x_preferred": [
      "হলিওয়েল"
    ],
    "name:bre_x_preferred": [
      "Treffynnon"
    ],
    "name:bul_x_preferred": [
      "Хоулиуел"
    ],
    "name:cat_x_preferred": [
      "Treffynnon"
    ],
    "name:ceb_x_preferred": [
      "Holywell"
    ],
    "name:cor_x_preferred": [
      "Treffynnon"
    ],
    "name:cym_x_preferred": [
      "Treffynnon"
    ],
    "name:deu_x_preferred": [
      "Holywell"
    ],
    "name:eng_x_preferred": [
      "Holywell"
    ],
    "name:eng_x_variant": [
      "Treffynnon"
    ],
    "name:eus_x_preferred": [
      "Treffynnon"
    ],
    "name:fas_x_preferred": [
      "هولیول"
    ],
    "name:fra_x_preferred": [
      "Holywell"
    ],
    "name:gla_x_preferred": [
      "Treffynnon"
    ],
    "name:gle_x_preferred": [
      "Treffynnon"
    ],
    "name:glg_x_preferred": [
      "Treffynnon"
    ],
    "name:guj_x_preferred": [
      "હોલીવેલ"
    ],
    "name:heb_x_preferred": [
      "הוליוול"
    ],
    "name:hye_x_preferred": [
      "Հոլիպւել"
    ],
    "name:ita_x_preferred": [
      "Holywell"
    ],
    "name:jpn_x_preferred": [
      "ホリーウェル"
    ],
    "name:kan_x_preferred": [
      "ಹೋಲಿ ವೆಲ್"
    ],
    "name:kor_x_preferred": [
      "홀리웰"
    ],
    "name:lit_x_preferred": [
      "Holivelis"
    ],
    "name:nld_x_preferred": [
      "Holywell"
    ],
    "name:nob_x_preferred": [
      "Holywell"
    ],
    "name:pol_x_preferred": [
      "Holywell"
    ],
    "name:por_x_preferred": [
      "Holywell"
    ],
    "name:rus_x_preferred": [
      "Холивел"
    ],
    "name:sco_x_preferred": [
      "Treffynnon"
    ],
    "name:spa_x_preferred": [
      "Holywell"
    ],
    "name:swe_x_preferred": [
      "Holywell"
    ],
    "name:swe_x_variant": [
      "Holywell"
    ],
    "name:tam_x_preferred": [
      "லீக்"
    ],
    "name:tel_x_preferred": [
      "హోలీ వెల్"
    ],
    "name:urd_x_preferred": [
      "ہولیویل"
    ],
    "name:zho_x_preferred": [
      "霍利韋爾"
    ],
    "qs:a0": "United Kingdom",
    "qs:a1": "*Sir y Fflint#Flintshire",
    "qs:a1_lc": "GB13NJ0000",
    "qs:a1r": "0Wales",
    "qs:a1r_lc": "GB13000000",
    "qs:adm0": "United Kingdom",
    "qs:la_lc": "*",
    "qs:level": "locality",
    "qs:loc": "Holywell",
    "qs:loc_alt": "Holywell",
    "qs:pop": 0,
    "qs:type": "buffered point",
    "wd:wordcount": 1124,
    "wof:lang": [
      "eng"
    ],
    "wof:name": "Holywell",
    "wof:placetype": "neighbourhood"
  },
  "geometry": {"coordinates":[-3.21513,53.269821],"type":"Point"}
}
