{
  "type": "Feature",
  "properties": {
    "gn:country":"GB",
    "gn:fcode":"PPL",
    "gn:population":2418,
    "iso:country":"GB",
    "name:ceb_x_preferred":[
        "Crosshouse"
    ],
    "name:cym_x_preferred":[
        "Crosshouse"
    ],
    "name:deu_x_preferred":[
        "Crosshouse"
    ],
    "name:eng_x_preferred":[
        "Crosshouse"
    ],
    "name:eus_x_preferred":[
        "Crosshouse"
    ],
    "name:fra_x_preferred":[
        "Crosshouse"
    ],
    "name:gla_x_preferred":[
        "Crosshouse"
    ],
    "name:gle_x_preferred":[
        "Crosshouse"
    ],
    "name:heb_x_preferred":[
        "\u05e7\u05e8\u05d5\u05e1\u05d4\u05d0\u05d5\u05e1"
    ],
    "name:nld_x_preferred":[
        "Crosshouse"
    ],
    "name:nno_x_preferred":[
        "Crosshouse"
    ],
    "name:nob_x_preferred":[
        "Crosshouse"
    ],
    "name:spa_x_preferred":[
        "Crosshouse"
    ],
    "name:swe_x_preferred":[
        "Crosshouse"
    ],
    "name:zho_x_preferred":[
        "\u514b\u7f57\u65af\u8c6a\u65af"
    ],
    "qs_pg:aaroncc":"GB",
    "qs_pg:gn_country":"GB",
    "qs_pg:gn_fcode":"PPL",
    "qs_pg:gn_pop":2418,
    "qs_pg:name":"Crosshouse",
    "qs_pg:name_adm0":"United Kingdom",
    "qs_pg:name_adm1":"Scotland",
    "qs_pg:photos":41,
    "qs_pg:photos_1k":8,
    "qs_pg:photos_9k":1,
    "qs_pg:photos_9r":2,
    "qs_pg:photos_all":41,
    "qs_pg:photos_sr":2,
    "qs_pg:pop_sr":4,
    "qs_pg:qs_pg_placetype":"locality",
    "qs_pg:qs_pg_placetype_gp":"Town",
    "qs_pg:woe_adm0":23424975,
    "woe:adm0_id":23424975,
    "woe:name_adm0":"United Kingdom",
    "woe:name_adm1":"Scotland",
    "woe:placetype":"Town",
    "wof:name":"Crosshouse",
    "wof:placetype":"locality",
    "wof:population":2850
},
  "geometry": {"coordinates":[-4.55091,55.61258],"type":"Point"}
}