{
  "type": "Feature",
  "properties": {
    "gn:admin1_code":"ENG",
    "gn:admin2_code":"I9",
    "gn:admin3_code":"33UE",
    "gn:admin4_code":"33UE062",
    "gn:asciiname":"Bexwell",
    "gn:country_code":"GB",
    "gn:dem":34,
    "gn:feature_class":"P",
    "gn:feature_code":"PPL",
    "gn:name":"Bexwell",
    "gn:population":0,
    "gn:timezone":"Europe/London",
    "iso:country":"GB",
    "name:cym_x_preferred":[
        "Bexwell"
    ],
    "name:pol_x_preferred":[
        "Bexwell"
    ],
    "wof:name":"Bexwell",
    "wof:placetype":"neighbourhood"
},
  "geometry": {"coordinates":[0.41323,52.60399],"type":"Point"}
}