{
  "type": "Feature",
  "properties": {
    "gn:admin1_code":"ENG",
    "gn:admin2_code":"E6",
    "gn:admin3_code":"23UG",
    "gn:admin4_code":"23UG004",
    "gn:asciiname":"Little Witcombe",
    "gn:country_code":"GB",
    "gn:dem":87,
    "gn:feature_class":"P",
    "gn:feature_code":"PPL",
    "gn:name":"Little Witcombe",
    "gn:population":0,
    "gn:timezone":"Europe/London",
    "iso:country":"GB",
    "wof:name":"Little Witcombe",
    "wof:placetype":"neighbourhood"
},
  "geometry": {"coordinates":[-2.13029,51.84064],"type":"Point"}
}