{
  "type": "Feature",
  "properties": {
    "gn:admin1_code":"ENG",
    "gn:admin2_code":"C6",
    "gn:admin3_code":"00HE144",
    "gn:asciiname":"Port Gaverne",
    "gn:country_code":"GB",
    "gn:dem":30,
    "gn:feature_class":"P",
    "gn:feature_code":"PPL",
    "gn:name":"Port Gaverne",
    "gn:population":0,
    "gn:timezone":"Europe/London",
    "iso:country":"GB",
    "name:eus_x_preferred":[
        "Port Gaverne"
    ],
    "name:spa_x_preferred":[
        "Port Gaverne"
    ],
    "wof:name":"Port Gaverne",
    "wof:placetype":"neighbourhood"
},
  "geometry": {"coordinates":[-4.82227,50.59198],"type":"Point"}
}