{
  "type": "Feature",
  "properties": {
    "gn:admin1_code":"ENG",
    "gn:admin2_code":"A3",
    "gn:asciiname":"Cundy Cross",
    "gn:country_code":"GB",
    "gn:dem":40,
    "gn:feature_class":"P",
    "gn:feature_code":"PPL",
    "gn:name":"Cundy Cross",
    "gn:population":0,
    "gn:timezone":"Europe/London",
    "iso:country":"GB",
    "wof:name":"Cundy Cross",
    "wof:placetype":"neighbourhood"
},
  "geometry": {"coordinates":[-1.43545,53.5538],"type":"Point"}
}