{
  "type": "Feature",
  "properties": {
    "gn:population":1880,
    "iso:country":"GB",
    "name:ben_x_preferred":[
        "\u0985\u0995\u09b2\u09c7"
    ],
    "name:ceb_x_preferred":[
        "Auckley"
    ],
    "name:deu_x_preferred":[
        "Auckley"
    ],
    "name:eng_x_preferred":[
        "Thackley"
    ],
    "name:eng_x_variant":[
        "Auckley"
    ],
    "name:fra_x_preferred":[
        "Auckley"
    ],
    "name:guj_x_preferred":[
        "\u0a93\u0a95\u0ab2\u0ac0"
    ],
    "name:jpn_x_preferred":[
        "\u30aa\u30a6\u30af\u30ea\u30fc"
    ],
    "name:kan_x_preferred":[
        "\u0c86\u0c95\u0ccd\u0cb2\u0cc6"
    ],
    "name:kor_x_preferred":[
        "\uc624\ud074\ub9ac"
    ],
    "name:lit_x_preferred":[
        "Oklis"
    ],
    "name:nld_x_preferred":[
        "Auckley"
    ],
    "name:pol_x_preferred":[
        "Auckley"
    ],
    "name:por_x_preferred":[
        "Auckley"
    ],
    "name:rus_x_preferred":[
        "\u041e\u043a\u043b\u0438"
    ],
    "name:spa_x_preferred":[
        "Auckley"
    ],
    "name:swe_x_preferred":[
        "Auckley"
    ],
    "name:tam_x_preferred":[
        "\u0b86\u0b95\u0bcd\u0b95\u0bb3\u0bc7"
    ],
    "name:tel_x_preferred":[
        "\u0c05\u0c15\u0c4d\u0c32\u0c3f"
    ],
    "name:urd_x_preferred":[
        "\u0627\u0648\u06a9\u0644\u06d2"
    ],
    "qs:gn_adm0_cc":"GB",
    "qs:gn_fcode":"PPL",
    "qs:gn_local":2654993,
    "qs:gn_nam_loc":"Bradford",
    "qs:gn_namadm1":"ENG",
    "qs:gn_name":"Auckley",
    "qs:local_max":4399,
    "qs:local_sum":22210,
    "qs:localhoods":31,
    "qs:name":"Thackley",
    "qs:name_adm0":"United Kingdom",
    "qs:name_adm1":"England",
    "qs:name_adm2":"West Yorkshire",
    "qs:name_lau":"Bradford City of",
    "qs:name_local":"Bradford",
    "qs:photo_max":93,
    "qs:photo_sum":764,
    "qs:placetype":"Suburb",
    "qs:quad_count":85,
    "qs:woe_adm0":23424975,
    "qs:woe_adm1":24554868,
    "qs:woe_adm2":12602197,
    "qs:woe_lau":12695870,
    "qs:woe_local":13527,
    "qs:woe_ver":"7.10.0",
    "wd:wordcount":598,
    "wof:lang":[
        "eng"
    ],
    "wof:name":"Thackley",
    "wof:placetype":"neighbourhood",
    "wof:population":1880
},
  "geometry": {"coordinates":[-1.73461,53.84389],"type":"Point"}
}