{
  "type": "Feature",
  "properties": {
    "gn:population":1880,
    "iso:country":"GB",
    "name:ceb_x_preferred":[
        "Auckley"
    ],
    "name:eng_x_preferred":[
        "Thackley"
    ],
    "name:nld_x_preferred":[
        "Auckley"
    ],
    "name:pol_x_preferred":[
        "Auckley"
    ],
    "name:swe_x_preferred":[
        "Auckley"
    ],
    "name:unk_x_variant":[
        "Thackley"
    ],
    "qs:gn_adm0_cc":"GB",
    "qs:gn_fcode":"PPL",
    "qs:gn_local":2654993,
    "qs:gn_nam_loc":"Bradford",
    "qs:gn_namadm1":"ENG",
    "qs:gn_name":"Auckley",
    "qs:local_max":4399,
    "qs:local_sum":22210,
    "qs:localhoods":31,
    "qs:name":"Thackley",
    "qs:name_adm0":"United Kingdom",
    "qs:name_adm1":"England",
    "qs:name_adm2":"West Yorkshire",
    "qs:name_lau":"Bradford City of",
    "qs:name_local":"Bradford",
    "qs:photo_max":93,
    "qs:photo_sum":764,
    "qs:placetype":"Suburb",
    "qs:quad_count":85,
    "qs:woe_adm0":23424975,
    "qs:woe_adm1":24554868,
    "qs:woe_adm2":12602197,
    "qs:woe_lau":12695870,
    "qs:woe_local":13527,
    "qs:woe_ver":"7.10.0",
    "wd:wordcount":598,
    "wof:lang":[
        "eng"
    ],
    "wof:name":"Thackley",
    "wof:placetype":"neighbourhood",
    "wof:population":1880
},
  "geometry": {"coordinates":[-1.73461,53.84389],"type":"Point"}
}