{
  "type": "Feature",
  "properties": {
    "gn:country":"GB",
    "gn:fcode":"PPL",
    "gn:population":0,
    "iso:country":"GB",
    "name:ben_x_preferred":[
        "\u0995\u09cd\u09af\u09be\u09b8\u09b2\u099f\u09a8"
    ],
    "name:deu_x_preferred":[
        "Castleton"
    ],
    "name:eng_x_preferred":[
        "Castleton"
    ],
    "name:fra_x_preferred":[
        "Castleton"
    ],
    "name:guj_x_preferred":[
        "\u0a95\u0ac7\u0ab8\u0ab2\u0a9f\u0aa8"
    ],
    "name:jpn_x_preferred":[
        "\u30ad\u30e3\u30c3\u30b9\u30eb\u30c8\u30f3"
    ],
    "name:kan_x_preferred":[
        "\u0c95\u0ccd\u0caf\u0cbe\u0cb8\u0ccd\u0c9f\u0ca8\u0ccd\u0c9f\u0ca8\u0ccd"
    ],
    "name:kor_x_preferred":[
        "\uce90\uc2ac\ud134"
    ],
    "name:lit_x_preferred":[
        "Kasltonas"
    ],
    "name:nld_x_preferred":[
        "Castleton"
    ],
    "name:pol_x_preferred":[
        "Castleton"
    ],
    "name:por_x_preferred":[
        "Castleton"
    ],
    "name:rus_x_preferred":[
        "\u041a\u0430\u0441\u0442\u043b\u0442\u043e\u043d"
    ],
    "name:spa_x_preferred":[
        "Castleton"
    ],
    "name:tam_x_preferred":[
        "\u0b95\u0bc7\u0bb8\u0bcd\u0bb2\u0bc7\u0b9f\u0bcd\u0b9f\u0bbe\u0ba9\u0bcd"
    ],
    "name:tel_x_preferred":[
        "\u0c15\u0c4d\u0c2f\u0c3e\u0c38\u0c4d\u0c1f\u0c32\u0c4d \u0c1f\u0c28\u0c4d"
    ],
    "name:urd_x_preferred":[
        "\u06a9\u0627\u0633\u062a\u0644\u06cc\u0679\u0646"
    ],
    "qs_pg:aaroncc":"GB",
    "qs_pg:gn_country":"GB",
    "qs_pg:gn_fcode":"PPL",
    "qs_pg:gn_pop":0,
    "qs_pg:name":"Castle Bolton",
    "qs_pg:name_adm0":"United Kingdom",
    "qs_pg:name_adm1":"England",
    "qs_pg:photos":790,
    "qs_pg:photos_1k":160,
    "qs_pg:photos_9k":4,
    "qs_pg:photos_9r":6,
    "qs_pg:photos_all":790,
    "qs_pg:photos_sr":9,
    "qs_pg:pop_sr":0,
    "qs_pg:qs_pg_placetype":"locality",
    "qs_pg:qs_pg_placetype_gp":"Town",
    "qs_pg:woe_adm0":23424975,
    "woe:adm0_id":23424975,
    "woe:name_adm0":"United Kingdom",
    "woe:name_adm1":"England",
    "woe:placetype":"Town",
    "wof:name":"Castle Bolton",
    "wof:placetype":"neighbourhood"
},
  "geometry": {"coordinates":[-2.18333,53.58333],"type":"Point"}
}