{
  "type": "Feature",
  "properties": {
    "iso:country":"GB",
    "name:eng_x_preferred":[
        "Grandpont"
    ],
    "wof:name":"Grandpont",
    "wof:placetype":"neighbourhood"
},
  "geometry": {"coordinates":[-1.25893471972241,51.7445807680632],"type":"Point"}
}