{
  "type": "Feature",
  "properties": {
    "iso:country": "GB",
    "name:eng_x_preferred": [
      "Maw Green"
    ],
    "qs:gn_local": 0,
    "qs:local_max": 2515,
    "qs:local_sum": 9671,
    "qs:localhoods": 12,
    "qs:name": "Maw Green",
    "qs:name_adm0": "United Kingdom",
    "qs:name_adm1": "England",
    "qs:name_adm2": "West Midlands",
    "qs:name_lau": "Walsall Metropolitan Borough",
    "qs:name_local": "Walsall",
    "qs:photo_max": 69,
    "qs:photo_sum": 336,
    "qs:placetype": "Suburb",
    "qs:quad_count": 28,
    "qs:woe_adm0": 23424975,
    "qs:woe_adm1": 24554868,
    "qs:woe_adm2": 12602191,
    "qs:woe_lau": 12695868,
    "qs:woe_local": 39052,
    "qs:woe_ver": "7.10.0",
    "wof:lang": [
      "eng"
    ],
    "wof:name": "Maw Green",
    "wof:placetype": "neighbourhood"
  },
  "geometry": {"coordinates":[-1.979436,52.56956],"type":"Point"}
}
