{
  "type": "Feature",
  "properties": {
    "iso:country":"GB",
    "wof:name":"Brook Hill",
    "wof:placetype":"neighbourhood"
},
  "geometry": {"coordinates":[-1.76072343532182,53.84786547048629],"type":"Point"}
}