{
  "type": "Feature",
  "properties": {
    "gn:admin1_code":"ENG",
    "gn:admin2_code":"J3",
    "gn:admin3_code":"00FD023",
    "gn:asciiname":"Garthorpe",
    "gn:country_code":"GB",
    "gn:dem":6,
    "gn:feature_class":"P",
    "gn:feature_code":"PPL",
    "gn:name":"Garthorpe",
    "gn:population":0,
    "gn:timezone":"Europe/London",
    "iso:country":"GB",
    "wof:name":"Garthorpe",
    "wof:placetype":"neighbourhood"
},
  "geometry": {"coordinates":[-0.71716,53.66231],"type":"Point"}
}