{
  "type": "Feature",
  "properties": {
    "iso:country":"GB",
    "name:eng_x_preferred":[
        "Sterte"
    ],
    "name:nld_x_preferred":[
        "Sterte"
    ],
    "qs:gn_local":0,
    "qs:local_max":5072,
    "qs:local_sum":20849,
    "qs:localhoods":9,
    "qs:name":"Sterte",
    "qs:name_adm0":"United Kingdom",
    "qs:name_adm1":"England",
    "qs:name_adm2":"Dorset",
    "qs:name_lau":"Poole Borough",
    "qs:name_local":"Poole",
    "qs:photo_max":873,
    "qs:photo_sum":5072,
    "qs:placetype":"Suburb",
    "qs:quad_count":91,
    "qs:woe_adm0":23424975,
    "qs:woe_adm1":24554868,
    "qs:woe_adm2":12602183,
    "qs:woe_lau":12696157,
    "qs:woe_local":32326,
    "qs:woe_ver":"7.10.0",
    "wd:wordcount":49,
    "wof:lang":[
        "eng"
    ],
    "wof:name":"Sterte",
    "wof:placetype":"neighbourhood"
},
  "geometry": {"coordinates":[-1.987727,50.717319],"type":"Point"}
}