{
  "type": "Feature",
  "properties": {
    "iso:country":"GB",
    "name:ceb_x_preferred":[
        "Tarbert"
    ],
    "name:cym_x_preferred":[
        "Tarbert"
    ],
    "name:deu_x_preferred":[
        "Tarbert"
    ],
    "name:eng_x_preferred":[
        "Tarbert"
    ],
    "name:eus_x_preferred":[
        "Tarbert"
    ],
    "name:fas_x_preferred":[
        "\u062a\u0627\u0631\u0628\u0631\u062a"
    ],
    "name:fra_x_preferred":[
        "Tarbert"
    ],
    "name:gla_x_preferred":[
        "Tairbeart Loch F\u00ecne"
    ],
    "name:gle_x_preferred":[
        "An Tairbeart"
    ],
    "name:glg_x_preferred":[
        "Tarbert"
    ],
    "name:jpn_x_preferred":[
        "\u30bf\u30fc\u30d0\u30fc\u30c8"
    ],
    "name:nld_x_preferred":[
        "Tarbert"
    ],
    "name:nno_x_preferred":[
        "Tarbert"
    ],
    "name:nob_x_preferred":[
        "Tarbert"
    ],
    "name:nor_x_preferred":[
        "Tarbert"
    ],
    "name:pol_x_preferred":[
        "Tarbert"
    ],
    "name:spa_x_preferred":[
        "Tarbert"
    ],
    "name:swe_x_preferred":[
        "Tarbert"
    ],
    "name:zho_x_preferred":[
        "\u5854\u4f2f\u7279"
    ],
    "qs:a0":"United Kingdom",
    "qs:a1":"*Argyll and Bute",
    "qs:a1_lc":"GB11QD0000",
    "qs:a1r":"0Scotland",
    "qs:a1r_lc":"GB11000000",
    "qs:adm0":"United Kingdom",
    "qs:la_lc":"*",
    "qs:level":"locality",
    "qs:loc":"Tarbert",
    "qs:loc_alt":"Tarbert",
    "qs:pop":0,
    "qs:type":"buffered point",
    "wd:wordcount":1237,
    "wof:name":"Tarbert",
    "wof:placetype":"locality"
},
  "geometry": {"coordinates":[-5.416034,55.863214],"type":"Point"}
}