{
  "type": "Feature",
  "properties": {
    "gn:admin1_code":"ENG",
    "gn:admin2_code":"A9",
    "gn:asciiname":"Squires Gate",
    "gn:country_code":"GB",
    "gn:dem":11,
    "gn:feature_class":"P",
    "gn:feature_code":"PPL",
    "gn:name":"Squires Gate",
    "gn:population":0,
    "gn:timezone":"Europe/London",
    "iso:country":"GB",
    "name:pol_x_preferred":[
        "Squires Gate"
    ],
    "wof:name":"Squires Gate",
    "wof:placetype":"neighbourhood"
},
  "geometry": {"coordinates":[-3.0439,53.78181],"type":"Point"}
}