{
  "type": "Feature",
  "properties": {
    "iso:country":"GB",
    "name:cat_x_preferred":[
        "Middletown"
    ],
    "name:ceb_x_preferred":[
        "Middletown"
    ],
    "name:deu_x_preferred":[
        "Middletown"
    ],
    "name:epo_x_preferred":[
        "Middletown"
    ],
    "name:fin_x_preferred":[
        "Middletown"
    ],
    "name:fra_x_preferred":[
        "Middletown"
    ],
    "name:ita_x_preferred":[
        "Middletown"
    ],
    "name:jpn_x_preferred":[
        "\u30df\u30c9\u30eb\u30bf\u30a6\u30f3"
    ],
    "name:kor_x_preferred":[
        "\ubbf8\ub4e4\ud0c0\uc6b4"
    ],
    "name:nld_x_preferred":[
        "Middletown"
    ],
    "name:nor_x_preferred":[
        "Middletown"
    ],
    "name:pol_x_preferred":[
        "Middletown"
    ],
    "name:por_x_preferred":[
        "Middletown"
    ],
    "name:rus_x_preferred":[
        "\u041c\u0438\u0434\u043b\u0442\u0430\u0443\u043d"
    ],
    "name:slk_x_preferred":[
        "Middletown"
    ],
    "name:spa_x_preferred":[
        "Middletown"
    ],
    "name:srp_x_preferred":[
        "\u041c\u0438\u0434\u043b\u0442\u0430\u0443\u043d"
    ],
    "name:swa_x_preferred":[
        "Middletown"
    ],
    "name:swe_x_preferred":[
        "Middletown"
    ],
    "name:ukr_x_preferred":[
        "\u041c\u0456\u0434\u0434\u043b\u0442\u0430\u0443\u043d"
    ],
    "name:urd_x_preferred":[
        "\u0645\u0688\u0644 \u0679\u0627\u0624\u0646"
    ],
    "name:vol_x_preferred":[
        "Middletown"
    ],
    "name:zho_x_preferred":[
        "\u7c73\u5fb7\u5c14\u6566"
    ],
    "qs_pg:aaroncc":"GB",
    "qs_pg:name":"Middletown",
    "qs_pg:name_adm0":"United Kingdom",
    "qs_pg:name_adm1":"Wales",
    "qs_pg:photos":41,
    "qs_pg:photos_1k":8,
    "qs_pg:photos_9k":1,
    "qs_pg:photos_9r":2,
    "qs_pg:photos_all":41,
    "qs_pg:photos_sr":2,
    "qs_pg:pop_sr":0,
    "qs_pg:qs_pg_placetype":"locality",
    "qs_pg:qs_pg_placetype_gp":"Town",
    "qs_pg:woe_adm0":23424975,
    "woe:adm0_id":23424975,
    "woe:name_adm0":"United Kingdom",
    "woe:name_adm1":"Wales",
    "woe:placetype":"Town",
    "wof:name":"Middletown",
    "wof:placetype":"neighbourhood"
},
  "geometry": {"coordinates":[-3.035058,52.706867],"type":"Point"}
}