{
  "type": "Feature",
  "properties": {
    "iso:country":"GB",
    "name:eng_x_preferred":[
        "Annat"
    ],
    "name:gle_x_preferred":[
        "An Annaid"
    ],
    "name:nld_x_preferred":[
        "Annat"
    ],
    "qs_pg:aaroncc":"GB",
    "qs_pg:name":"Annat",
    "qs_pg:name_adm0":"United Kingdom",
    "qs_pg:name_adm1":"Scotland",
    "qs_pg:photos":937,
    "qs_pg:photos_1k":190,
    "qs_pg:photos_9k":4,
    "qs_pg:photos_9r":6,
    "qs_pg:photos_all":937,
    "qs_pg:photos_sr":10,
    "qs_pg:pop_sr":0,
    "qs_pg:qs_pg_placetype":"locality",
    "qs_pg:qs_pg_placetype_gp":"Town",
    "qs_pg:woe_adm0":23424975,
    "woe:adm0_id":23424975,
    "woe:name_adm0":"United Kingdom",
    "woe:name_adm1":"Scotland",
    "woe:placetype":"Town",
    "wof:name":"Annat",
    "wof:placetype":"locality"
},
  "geometry": {"coordinates":[-5.523118,57.529188],"type":"Point"}
}