{
  "type": "Feature",
  "properties": {
    "gn:population":740,
    "iso:country":"GB",
    "name:bul_x_preferred":[
        "\u0414\u0435\u043d\u0441\u043e\u043b\u0435"
    ],
    "name:ceb_x_preferred":[
        "Densole"
    ],
    "name:cym_x_preferred":[
        "Densole"
    ],
    "name:eng_x_preferred":[
        "Densole"
    ],
    "name:fra_x_preferred":[
        "Densole"
    ],
    "name:nld_x_preferred":[
        "Densole"
    ],
    "name:pol_x_preferred":[
        "Densole"
    ],
    "name:spa_x_preferred":[
        "Densole"
    ],
    "name:swe_x_preferred":[
        "Densole"
    ],
    "qs:a0":"United Kingdom",
    "qs:a1":"*Kent",
    "qs:a1_lc":"GB12290000",
    "qs:a1r":"0England",
    "qs:a1r_lc":"GB12000000",
    "qs:adm0":"United Kingdom",
    "qs:la_lc":"*",
    "qs:level":"locality",
    "qs:loc":"Densole",
    "qs:loc_alt":"Densole",
    "qs:pop":0,
    "qs:type":"buffered point",
    "wd:wordcount":237,
    "wof:name":"Densole",
    "wof:placetype":"neighbourhood",
    "wof:population":740
},
  "geometry": {"coordinates":[1.157076,51.130291],"type":"Point"}
}