{
  "type": "Feature",
  "properties": {
    "gn:gn_fcode":"PPL",
    "gn:gn_pop":0,
    "iso:country":"GB",
    "name:eng_x_preferred":[
        "Littleton"
    ],
    "qs_pg:aaroncc":"GB",
    "qs_pg:gn_fcode":"PPL",
    "qs_pg:gn_pop":0,
    "qs_pg:name":"Littleton",
    "qs_pg:name_adm0":"United Kingdom",
    "qs_pg:name_adm1":"England",
    "qs_pg:photos":35,
    "qs_pg:photos_1k":7,
    "qs_pg:photos_9k":1,
    "qs_pg:photos_9r":2,
    "qs_pg:photos_all":35,
    "qs_pg:photos_sr":2,
    "qs_pg:pop_sr":0,
    "qs_pg:qs_pg_placetype":"locality",
    "qs_pg:qs_pg_placetype_gp":"Town",
    "qs_pg:woe_adm0":23424975,
    "woe:adm0_id":23424975,
    "woe:name_adm0":"United Kingdom",
    "woe:name_adm1":"England",
    "woe:placetype":"Town",
    "wof:name":"Littleton",
    "wof:placetype":"neighbourhood"
},
  "geometry": {"coordinates":[-1.351318,51.084547],"type":"Point"}
}