{
  "type": "Feature",
  "properties": {
    "iso:country": "GB",
    "qs_pg:aaroncc": "GB",
    "qs_pg:name": "Fairy Cross",
    "qs_pg:name_adm0": "United Kingdom",
    "qs_pg:name_adm1": "England",
    "qs_pg:photos": 13,
    "qs_pg:photos_1k": 3,
    "qs_pg:photos_9k": 1,
    "qs_pg:photos_9r": 1,
    "qs_pg:photos_all": 13,
    "qs_pg:photos_sr": 1,
    "qs_pg:pop_sr": 0,
    "qs_pg:qs_pg_placetype": "locality",
    "qs_pg:qs_pg_placetype_gp": "Town",
    "qs_pg:woe_adm0": 23424975,
    "woe:adm0_id": 23424975,
    "woe:name_adm0": "United Kingdom",
    "woe:name_adm1": "England",
    "woe:placetype": "Town",
    "wof:name": "Fairy Cross",
    "wof:placetype": "neighbourhood"
  },
  "geometry": {"coordinates":[-4.276084,50.9982],"type":"Point"}
}
