{
  "type": "Feature",
  "properties": {
    "iso:country":"GB",
    "name:eus_x_preferred":[
        "Braehead"
    ],
    "qs_pg:aaroncc":"GB",
    "qs_pg:name":"Braehead",
    "qs_pg:name_adm0":"United Kingdom",
    "qs_pg:name_adm1":"Scotland",
    "qs_pg:photos":80,
    "qs_pg:photos_1k":16,
    "qs_pg:photos_9k":1,
    "qs_pg:photos_9r":3,
    "qs_pg:photos_all":80,
    "qs_pg:photos_sr":3,
    "qs_pg:pop_sr":0,
    "qs_pg:qs_pg_placetype":"locality",
    "qs_pg:qs_pg_placetype_gp":"Town",
    "qs_pg:woe_adm0":23424975,
    "woe:adm0_id":23424975,
    "woe:name_adm0":"United Kingdom",
    "woe:name_adm1":"Scotland",
    "woe:placetype":"Town",
    "wof:name":"Braehead",
    "wof:placetype":"locality"
},
  "geometry": {"coordinates":[-2.987976,59.296115],"type":"Point"}
}