{
  "type": "Feature",
  "properties": {
    "iso:country":"GB",
    "name:eng_x_preferred":[
        "Bradley"
    ],
    "name:unk_x_variant":[
        "Bradley"
    ],
    "qs:gn_fcode":"PPL",
    "qs:gn_local":0,
    "qs:gn_namadm1":"ENG",
    "qs:gn_name":"Bradley",
    "qs:local_max":5224,
    "qs:local_sum":14356,
    "qs:localhoods":28,
    "qs:name":"Bradley",
    "qs:name_adm0":"United Kingdom",
    "qs:name_adm1":"England",
    "qs:name_adm2":"West Yorkshire",
    "qs:name_lau":"Kirklees Metropolitan Borough",
    "qs:name_local":"Huddersfield",
    "qs:photo_max":97,
    "qs:photo_sum":649,
    "qs:placetype":"Suburb",
    "qs:quad_count":69,
    "qs:woe_adm0":23424975,
    "qs:woe_adm1":24554868,
    "qs:woe_adm2":12602197,
    "qs:woe_lau":12695872,
    "qs:woe_local":24083,
    "qs:woe_ver":"7.10.0",
    "wof:lang":[
        "eng"
    ],
    "wof:name":"Bradley",
    "wof:placetype":"neighbourhood"
},
  "geometry": {"coordinates":[-1.74148,53.686846],"type":"Point"}
}