{
  "type": "Feature",
  "properties": {
    "gn:gn_country":"GB",
    "gn:gn_fcode":"PPL",
    "gn:gn_pop":0,
    "iso:country":"GB",
    "name:bre_x_preferred":[
        "Gairloch"
    ],
    "name:cat_x_preferred":[
        "Gairloch"
    ],
    "name:ceb_x_preferred":[
        "Gairloch"
    ],
    "name:cym_x_preferred":[
        "Gairloch"
    ],
    "name:deu_x_preferred":[
        "Gairloch"
    ],
    "name:eng_x_preferred":[
        "Gairloch"
    ],
    "name:eus_x_preferred":[
        "Gairloch"
    ],
    "name:fra_x_preferred":[
        "Gairloch"
    ],
    "name:gla_x_preferred":[
        "Ge\u00e0rrloch"
    ],
    "name:gle_x_preferred":[
        "Ge\u00e1rrloch"
    ],
    "name:ita_x_preferred":[
        "Gairloch"
    ],
    "name:jpn_x_preferred":[
        "\u30b2\u30a4\u30ed\u30c3\u30db"
    ],
    "name:nld_x_preferred":[
        "Gairloch"
    ],
    "name:sco_x_preferred":[
        "Gairloch"
    ],
    "name:spa_x_preferred":[
        "Gairloch"
    ],
    "name:swe_x_preferred":[
        "Gairloch"
    ],
    "qs_pg:aaroncc":"GB",
    "qs_pg:gn_country":"GB",
    "qs_pg:gn_fcode":"PPL",
    "qs_pg:gn_pop":0,
    "qs_pg:name":"Gairloch",
    "qs_pg:name_adm0":"United Kingdom",
    "qs_pg:name_adm1":"Scotland",
    "qs_pg:photos":3371,
    "qs_pg:photos_1k":683,
    "qs_pg:photos_9k":15,
    "qs_pg:photos_9r":11,
    "qs_pg:photos_all":3371,
    "qs_pg:photos_sr":20,
    "qs_pg:pop_sr":0,
    "qs_pg:qs_pg_placetype":"locality",
    "qs_pg:qs_pg_placetype_gp":"Town",
    "qs_pg:woe_adm0":23424975,
    "woe:adm0_id":23424975,
    "woe:name_adm0":"United Kingdom",
    "woe:name_adm1":"Scotland",
    "woe:placetype":"Town",
    "wof:name":"Gairloch",
    "wof:placetype":"locality"
},
  "geometry": {"coordinates":[-5.67924,57.72029],"type":"Point"}
}