{
  "type": "Feature",
  "properties": {
    "gn:admin1_code": "WLS",
    "gn:admin2_code": "Y8",
    "gn:admin3_code": "00NN029",
    "gn:asciiname": "Cemmaes",
    "gn:country_code": "GB",
    "gn:dem": 41,
    "gn:feature_class": "P",
    "gn:feature_code": "PPL",
    "gn:name": "Cemmaes",
    "gn:population": 0,
    "gn:timezone": "Europe/London",
    "iso:country": "GB",
    "name:bre_x_preferred": [
      "Cemais"
    ],
    "name:cym_x_preferred": [
      "Cemais"
    ],
    "name:eus_x_preferred": [
      "Cemmaes"
    ],
    "wof:name": "Cemmaes",
    "wof:placetype": "neighbourhood"
  },
  "geometry": {"coordinates":[-3.71708,52.64063],"type":"Point"}
}
