{
  "type": "Feature",
  "properties": {
    "iso:country":"GB",
    "name:ceb_x_preferred":[
        "Hempstead"
    ],
    "name:deu_x_preferred":[
        "Hempstead"
    ],
    "name:eng_x_preferred":[
        "Hempstead"
    ],
    "name:fra_x_preferred":[
        "Hempstead"
    ],
    "name:ita_x_preferred":[
        "Hempstead"
    ],
    "name:kor_x_preferred":[
        "\ud5f4\ud504\uc2a4\ud14c\ub4dc"
    ],
    "name:nld_x_preferred":[
        "Hempstead"
    ],
    "name:nor_x_preferred":[
        "Hempstead"
    ],
    "name:pol_x_preferred":[
        "Hempstead"
    ],
    "name:rus_x_preferred":[
        "\u0425\u0435\u043c\u043f\u0441\u0442\u0435\u0434"
    ],
    "name:spa_x_preferred":[
        "Hempstead"
    ],
    "name:srp_x_preferred":[
        "\u0425\u0435\u043c\u043f\u0441\u0442\u0435\u0434"
    ],
    "name:swe_x_preferred":[
        "Hempstead"
    ],
    "name:ukr_x_preferred":[
        "\u0413\u0435\u043c\u043f\u0441\u0442\u0435\u0434"
    ],
    "name:vol_x_preferred":[
        "Hempstead"
    ],
    "qs:gn_adm0_cc":"GB",
    "qs:gn_fcode":"PPL",
    "qs:gn_local":2648657,
    "qs:gn_nam_loc":"gillingham",
    "qs:gn_namadm1":"ENG",
    "qs:gn_name":"Hempstead",
    "qs:local_max":5047,
    "qs:local_sum":7988,
    "qs:localhoods":4,
    "qs:name":"Hempstead",
    "qs:name_adm0":"United Kingdom",
    "qs:name_adm1":"England",
    "qs:name_adm2":"Kent",
    "qs:name_lau":"Medway",
    "qs:name_local":"Gillingham",
    "qs:photo_max":111,
    "qs:photo_sum":1167,
    "qs:placetype":"Suburb",
    "qs:quad_count":89,
    "qs:woe_adm0":23424975,
    "qs:woe_adm1":24554868,
    "qs:woe_adm2":12602173,
    "qs:woe_lau":12696177,
    "qs:woe_local":21048,
    "qs:woe_ver":"7.10.0",
    "wof:lang":[
        "eng"
    ],
    "wof:name":"Hempstead",
    "wof:placetype":"neighbourhood"
},
  "geometry": {"coordinates":[0.570976,51.350852],"type":"Point"}
}