{
  "type": "Feature",
  "properties": {
    "gn:population":1671,
    "iso:country":"GB",
    "name:ceb_x_preferred":[
        "Pencaitland"
    ],
    "name:cym_x_preferred":[
        "Pencaitland"
    ],
    "name:deu_x_preferred":[
        "Pencaitland"
    ],
    "name:eng_x_preferred":[
        "Pencaitland"
    ],
    "name:eus_x_preferred":[
        "Pencaitland"
    ],
    "name:fas_x_preferred":[
        "\u067e\u0646\u06a9\u06cc\u062a\u0644\u0646\u062f"
    ],
    "name:fra_x_preferred":[
        "Pencaitland"
    ],
    "name:gla_x_preferred":[
        "Pencaitland"
    ],
    "name:ita_x_preferred":[
        "Pencaitland"
    ],
    "name:nld_x_preferred":[
        "Pencaitland"
    ],
    "name:spa_x_preferred":[
        "Pencaitland"
    ],
    "name:swe_x_preferred":[
        "Pencaitland"
    ],
    "qs:a0":"United Kingdom",
    "qs:a1":"*East Lothian",
    "qs:a1_lc":"GB11QM0000",
    "qs:a1r":"0Scotland",
    "qs:a1r_lc":"GB11000000",
    "qs:adm0":"United Kingdom",
    "qs:la_lc":"*",
    "qs:level":"locality",
    "qs:loc":"Pencaitland",
    "qs:loc_alt":"Pencaitland",
    "qs:pop":0,
    "qs:type":"buffered point",
    "wd:wordcount":1847,
    "wof:name":"Pencaitland",
    "wof:placetype":"locality",
    "wof:population":1671
},
  "geometry": {"coordinates":[-2.898773,55.911019],"type":"Point"}
}