{
  "type": "Feature",
  "properties": {
    "iso:country":"GB",
    "name:cym_x_preferred":[
        "Boultham"
    ],
    "name:eng_x_preferred":[
        "New Boultham"
    ],
    "name:eng_x_variant":[
        "Boultham"
    ],
    "name:fra_x_preferred":[
        "Boultham"
    ],
    "name:gle_x_preferred":[
        "Boultham"
    ],
    "name:lld_x_preferred":[
        "Boultham"
    ],
    "name:nld_x_preferred":[
        "Boultham"
    ],
    "name:pol_x_preferred":[
        "Boultham"
    ],
    "qs:gn_adm0_cc":"GB",
    "qs:gn_fcode":"PPL",
    "qs:gn_local":2644487,
    "qs:gn_nam_loc":"Lincoln, Lincoln, Lincolnshire, England, GB",
    "qs:gn_namadm1":"ENG",
    "qs:gn_name":"Boultham",
    "qs:local_max":5138,
    "qs:local_sum":8466,
    "qs:localhoods":5,
    "qs:name":"New Boultham",
    "qs:name_adm0":"United Kingdom",
    "qs:name_adm1":"England",
    "qs:name_adm2":"Lincolnshire",
    "qs:name_lau":"Lincoln City",
    "qs:name_local":"Lincoln",
    "qs:photo_max":1045,
    "qs:photo_sum":5138,
    "qs:placetype":"Suburb",
    "qs:quad_count":127,
    "qs:woe_adm0":23424975,
    "qs:woe_adm1":24554868,
    "qs:woe_adm2":12602145,
    "qs:woe_lau":12696018,
    "qs:woe_local":26279,
    "qs:woe_ver":"7.10.0",
    "wd:wordcount":225,
    "wof:lang":[
        "eng"
    ],
    "wof:name":"New Boultham",
    "wof:placetype":"neighbourhood"
},
  "geometry": {"coordinates":[-0.540873,53.232244],"type":"Point"}
}