{
  "type": "Feature",
  "properties": {
    "gn:admin1_code":"ENG",
    "gn:admin2_code":"F7",
    "gn:admin3_code":"00GA142",
    "gn:asciiname":"Shenmore",
    "gn:country_code":"GB",
    "gn:dem":95,
    "gn:feature_class":"P",
    "gn:feature_code":"PPL",
    "gn:name":"Shenmore",
    "gn:population":0,
    "gn:timezone":"Europe/London",
    "iso:country":"GB",
    "wof:name":"Shenmore",
    "wof:placetype":"neighbourhood"
},
  "geometry": {"coordinates":[-2.88284,52.04051],"type":"Point"}
}