{
  "type": "Feature",
  "properties": {
    "gn:admin1_code":"SCT",
    "gn:admin2_code":"W1",
    "gn:asciiname":"Dall",
    "gn:country_code":"GB",
    "gn:dem":217,
    "gn:feature_class":"P",
    "gn:feature_code":"PPL",
    "gn:name":"Dall",
    "gn:population":0,
    "gn:timezone":"Europe/London",
    "iso:country":"GB",
    "name:cat_x_preferred":[
        "Dall"
    ],
    "name:deu_x_preferred":[
        "Dall"
    ],
    "name:ita_x_preferred":[
        "Dall"
    ],
    "name:nds_x_preferred":[
        "Dall"
    ],
    "name:nld_x_preferred":[
        "Dall"
    ],
    "name:swe_x_preferred":[
        "Dall"
    ],
    "wof:name":"Dall",
    "wof:placetype":"locality"
},
  "geometry": {"coordinates":[-4.29702,56.67971],"type":"Point"}
}