{
  "type": "Feature",
  "properties": {
    "gn:admin1_code":"SCT",
    "gn:admin2_code":"V3",
    "gn:asciiname":"Bowermadden",
    "gn:country_code":"GB",
    "gn:dem":52,
    "gn:feature_class":"P",
    "gn:feature_code":"PPL",
    "gn:name":"Bowermadden",
    "gn:population":0,
    "gn:timezone":"Europe/London",
    "iso:country":"GB",
    "wof:name":"Bowermadden",
    "wof:placetype":"locality"
},
  "geometry": {"coordinates":[-3.30265,58.55654000000001],"type":"Point"}
}