{
  "type": "Feature",
  "properties": {
    "gn:country":"GB",
    "gn:fcode":"PPL",
    "gn:population":665,
    "iso:country":"GB",
    "name:bar_x_preferred":[
        "Ochiltree"
    ],
    "name:bul_x_preferred":[
        "\u041e\u0447\u0438\u043b\u0442\u0440\u0435"
    ],
    "name:ceb_x_preferred":[
        "Ochiltree"
    ],
    "name:cym_x_preferred":[
        "Ochiltree"
    ],
    "name:deu_x_preferred":[
        "Ochiltree"
    ],
    "name:eng_x_preferred":[
        "Ochiltree"
    ],
    "name:eus_x_preferred":[
        "Ochiltree"
    ],
    "name:fra_x_preferred":[
        "Ochiltree"
    ],
    "name:gla_x_preferred":[
        "Ochiltree"
    ],
    "name:gle_x_preferred":[
        "Ochail-Treabh"
    ],
    "name:gle_x_variant":[
        "Ochiltree"
    ],
    "name:ita_x_preferred":[
        "Ochiltree"
    ],
    "name:nld_x_preferred":[
        "Ochiltree"
    ],
    "name:sco_x_preferred":[
        "Ochiltree"
    ],
    "name:spa_x_preferred":[
        "Ochiltree"
    ],
    "name:swe_x_preferred":[
        "Ochiltree"
    ],
    "qs_pg:aaroncc":"GB",
    "qs_pg:gn_country":"GB",
    "qs_pg:gn_fcode":"PPL",
    "qs_pg:gn_pop":665,
    "qs_pg:name":"Ochiltree",
    "qs_pg:name_adm0":"United Kingdom",
    "qs_pg:name_adm1":"Scotland",
    "qs_pg:photos":134,
    "qs_pg:photos_1k":27,
    "qs_pg:photos_9k":1,
    "qs_pg:photos_9r":3,
    "qs_pg:photos_all":134,
    "qs_pg:photos_sr":3,
    "qs_pg:pop_sr":2,
    "qs_pg:qs_pg_placetype":"locality",
    "qs_pg:qs_pg_placetype_gp":"Town",
    "qs_pg:woe_adm0":23424975,
    "woe:adm0_id":23424975,
    "woe:name_adm0":"United Kingdom",
    "woe:name_adm1":"Scotland",
    "woe:placetype":"Town",
    "wof:name":"Ochiltree",
    "wof:placetype":"locality",
    "wof:population":1080
},
  "geometry": {"coordinates":[-4.36782,55.45981],"type":"Point"}
}