{
  "type": "Feature",
  "properties": {
    "gn:admin1_code":"ENG",
    "gn:admin2_code":"C6",
    "gn:admin3_code":"00HE026",
    "gn:asciiname":"Carines",
    "gn:country_code":"GB",
    "gn:dem":39,
    "gn:feature_class":"P",
    "gn:feature_code":"PPL",
    "gn:name":"Carines",
    "gn:population":0,
    "gn:timezone":"Europe/London",
    "iso:country":"GB",
    "wof:name":"Carines",
    "wof:placetype":"neighbourhood"
},
  "geometry": {"coordinates":[-5.11105,50.38975],"type":"Point"}
}