{
  "type": "Feature",
  "properties": {
    "gn:country":"GB",
    "gn:fcode":"PPL",
    "gn:population":0,
    "iso:country":"GB",
    "name:eng_x_preferred":[
        "Great Kimble"
    ],
    "name:gle_x_preferred":[
        "Great Kimble"
    ],
    "name:pol_x_preferred":[
        "Great Kimble"
    ],
    "name:spa_x_preferred":[
        "Great Kimble"
    ],
    "name:swe_x_preferred":[
        "Great Kimble"
    ],
    "name:und_x_variant":[
        "Kimble"
    ],
    "qs_pg:aaroncc":"GB",
    "qs_pg:gn_country":"GB",
    "qs_pg:gn_fcode":"PPL",
    "qs_pg:gn_pop":0,
    "qs_pg:name":"Great Kimble",
    "qs_pg:name_adm0":"United Kingdom",
    "qs_pg:name_adm1":"England",
    "qs_pg:photos":255,
    "qs_pg:photos_1k":52,
    "qs_pg:photos_9k":1,
    "qs_pg:photos_9r":4,
    "qs_pg:photos_all":255,
    "qs_pg:photos_sr":5,
    "qs_pg:pop_sr":0,
    "qs_pg:qs_pg_placetype":"locality",
    "qs_pg:qs_pg_placetype_gp":"Town",
    "qs_pg:woe_adm0":23424975,
    "woe:adm0_id":23424975,
    "woe:name_adm0":"United Kingdom",
    "woe:name_adm1":"England",
    "woe:placetype":"Town",
    "wof:name":"Great Kimble",
    "wof:placetype":"neighbourhood",
    "wof:population":698
},
  "geometry": {"coordinates":[-0.82209,51.75966],"type":"Point"}
}