{
  "type": "Feature",
  "properties": {
    "gn:gn_country":"GB",
    "iso:country":"GB",
    "name:bre_x_preferred":[
        "Tre-saith"
    ],
    "name:cym_x_preferred":[
        "Tre-saith"
    ],
    "name:eng_x_preferred":[
        "Tresaith"
    ],
    "name:fra_x_preferred":[
        "Tresaith"
    ],
    "name:nld_x_preferred":[
        "Tresaith"
    ],
    "qs_pg:aaroncc":"GB",
    "qs_pg:gn_country":"GB",
    "qs_pg:name":"Tresaith",
    "qs_pg:name_adm0":"United Kingdom",
    "qs_pg:name_adm1":"Wales",
    "qs_pg:photos":699,
    "qs_pg:photos_1k":142,
    "qs_pg:photos_9k":3,
    "qs_pg:photos_9r":5,
    "qs_pg:photos_all":699,
    "qs_pg:photos_sr":8,
    "qs_pg:pop_sr":0,
    "qs_pg:qs_pg_placetype":"locality",
    "qs_pg:qs_pg_placetype_gp":"Town",
    "qs_pg:woe_adm0":23424975,
    "woe:adm0_id":23424975,
    "woe:name_adm0":"United Kingdom",
    "woe:name_adm1":"Wales",
    "woe:placetype":"Town",
    "wof:name":"Tresaith",
    "wof:placetype":"neighbourhood"
},
  "geometry": {"coordinates":[-4.473667,52.160434],"type":"Point"}
}