{
  "type": "Feature",
  "properties": {
    "iso:country":"GB",
    "name:bre_x_preferred":[
        "Srath Nabhair"
    ],
    "name:eus_x_preferred":[
        "Strathnaver"
    ],
    "name:gla_x_preferred":[
        "Srath Nabhair"
    ],
    "name:gle_x_preferred":[
        "Srath Nabhair"
    ],
    "name:nld_x_preferred":[
        "Strathnaver"
    ],
    "name:srp_x_preferred":[
        "\u041d\u0435\u0458\u0432\u0435\u0440"
    ],
    "qs_pg:aaroncc":"GB",
    "qs_pg:name":"Strathnaver",
    "qs_pg:name_adm0":"United Kingdom",
    "qs_pg:name_adm1":"Scotland",
    "qs_pg:photos":6,
    "qs_pg:photos_1k":1,
    "qs_pg:photos_9k":1,
    "qs_pg:photos_9r":1,
    "qs_pg:photos_all":6,
    "qs_pg:photos_sr":1,
    "qs_pg:pop_sr":0,
    "qs_pg:qs_pg_placetype":"locality",
    "qs_pg:qs_pg_placetype_gp":"Town",
    "qs_pg:woe_adm0":23424975,
    "woe:adm0_id":23424975,
    "woe:name_adm0":"United Kingdom",
    "woe:name_adm1":"Scotland",
    "woe:placetype":"Town",
    "wof:name":"Strathnaver",
    "wof:placetype":"locality"
},
  "geometry": {"coordinates":[-4.234508,58.366008],"type":"Point"}
}