{
  "type": "Feature",
  "properties": {
    "gn:admin1_code":"NIR",
    "gn:admin2_code":"N09000001",
    "gn:asciiname":"Carnmoney",
    "gn:cc2":"GB",
    "gn:country_code":"GB",
    "gn:dem":152,
    "gn:feature_class":"P",
    "gn:feature_code":"PPL",
    "gn:name":"Carnmoney",
    "gn:population":2775,
    "gn:timezone":"Europe/London",
    "iso:country":"GB",
    "name:ceb_x_preferred":[
        "Carnmoney"
    ],
    "name:swe_x_preferred":[
        "Carnmoney"
    ],
    "name:und_x_variant":[
        "Carmoney"
    ],
    "wof:name":"Carnmoney",
    "wof:placetype":"locality",
    "wof:population":2775
},
  "geometry": {"coordinates":[-5.95,54.68333000000001],"type":"Point"}
}