{
  "type": "Feature",
  "properties": {
    "iso:country":"GB",
    "wof:name":"Graveleythorpe",
    "wof:placetype":"neighbourhood"
},
  "geometry": {"coordinates":[-1.4616748610879,53.80106173196397],"type":"Point"}
}