{
  "type": "Feature",
  "properties": {
    "iso:country":"GB",
    "name:deu_x_preferred":[
        "M\u00fchle von Shawbost"
    ],
    "name:eng_x_preferred":[
        "Shawbost"
    ],
    "name:fra_x_preferred":[
        "Shawbost"
    ],
    "name:gla_x_preferred":[
        "Siabost"
    ],
    "name:gle_x_preferred":[
        "Siabost"
    ],
    "name:nld_x_preferred":[
        "Shawbost"
    ],
    "name:swe_x_preferred":[
        "Loch Shawbost"
    ],
    "qs_pg:aaroncc":"GB",
    "qs_pg:name":"Shawbost",
    "qs_pg:name_adm0":"United Kingdom",
    "qs_pg:name_adm1":"Scotland",
    "qs_pg:photos":35,
    "qs_pg:photos_1k":7,
    "qs_pg:photos_9k":1,
    "qs_pg:photos_9r":2,
    "qs_pg:photos_all":35,
    "qs_pg:photos_sr":2,
    "qs_pg:pop_sr":0,
    "qs_pg:qs_pg_placetype":"locality",
    "qs_pg:qs_pg_placetype_gp":"Town",
    "qs_pg:woe_adm0":23424975,
    "woe:adm0_id":23424975,
    "woe:name_adm0":"United Kingdom",
    "woe:name_adm1":"Scotland",
    "woe:placetype":"Town",
    "wof:name":"Shawbost",
    "wof:placetype":"locality"
},
  "geometry": {"coordinates":[-6.671447,58.329333],"type":"Point"}
}