{
  "type": "Feature",
  "properties": {
    "iso:country":"GB",
    "name:eng_x_preferred":[
        "Hare Croft"
    ],
    "name:eng_x_variant":[
        "Harecroft"
    ],
    "wof:name":"Hare Croft",
    "wof:placetype":"neighbourhood"
},
  "geometry": {"coordinates":[-1.87599410794449,53.81763436065157],"type":"Point"}
}