{
  "type": "Feature",
  "properties": {
    "gn:population":1735,
    "iso:country":"GB",
    "name:bul_x_preferred":[
        "\u0411\u0430\u043b\u0439\u043a\u0435\u043b\u0439"
    ],
    "name:ceb_x_preferred":[
        "Ballykelly"
    ],
    "name:eng_x_preferred":[
        "Ballykelly"
    ],
    "name:eus_x_preferred":[
        "Ballykelly"
    ],
    "name:fas_x_preferred":[
        "\u0628\u0627\u0644\u06cc\u200c\u06a9\u0644\u06cc"
    ],
    "name:fra_x_preferred":[
        "Ballykelly"
    ],
    "name:gla_x_preferred":[
        "Baile U\u00ed Cheallaigh"
    ],
    "name:gle_x_preferred":[
        "Baile U\u00ed Cheallaigh"
    ],
    "name:ita_x_preferred":[
        "Ballykelly"
    ],
    "name:msa_x_preferred":[
        "Ballykelly"
    ],
    "name:nld_x_preferred":[
        "Ballykelly"
    ],
    "name:nob_x_preferred":[
        "Ballykelly"
    ],
    "name:pli_x_preferred":[
        "\u092c\u0932\u094d\u0932\u094d\u092f\u094d\u0915\u0947\u0932\u094d\u0932\u0940"
    ],
    "name:spa_x_preferred":[
        "Ballykelly"
    ],
    "name:swe_x_preferred":[
        "Ballykelly"
    ],
    "qs:a0":"United Kingdom",
    "qs:a1":"*Limavady",
    "qs:a1_lc":"N_A",
    "qs:a1r":"0Northern Ireland",
    "qs:a1r_lc":"N_A",
    "qs:adm0":"United Kingdom",
    "qs:la_lc":"*",
    "qs:level":"locality",
    "qs:loc":"Ballykelly",
    "qs:loc_alt":"Ballykelly",
    "qs:pop":0,
    "qs:type":"buffered point",
    "wof:name":"Ballykelly",
    "wof:placetype":"locality",
    "wof:population":1735
},
  "geometry": {"coordinates":[-7.021512,55.043537],"type":"Point"}
}