{
  "type": "Feature",
  "properties": {
    "gn:admin1_code": "WLS",
    "gn:admin2_code": "Y4",
    "gn:admin3_code": "00PP014",
    "gn:asciiname": "Saint Maughans",
    "gn:cc2": "GB",
    "gn:country_code": "GB",
    "gn:dem": 94,
    "gn:feature_class": "P",
    "gn:feature_code": "PPL",
    "gn:name": "Saint Maughans",
    "gn:population": 0,
    "gn:timezone": "Europe/London",
    "iso:country": "GB",
    "name:und_x_variant": [
      "Saint Maughan",
      "Saint Maughans"
    ],
    "wof:name": "Saint Maughans",
    "wof:placetype": "neighbourhood"
  },
  "geometry": {"coordinates":[-2.78333,51.85],"type":"Point"}
}
