{
  "type": "Feature",
  "properties": {
    "gn:admin1_code":"ENG",
    "gn:admin2_code":"B2",
    "gn:asciiname":"Wick",
    "gn:country_code":"GB",
    "gn:dem":2,
    "gn:feature_class":"P",
    "gn:feature_code":"PPL",
    "gn:name":"Wick",
    "gn:population":0,
    "gn:timezone":"Europe/London",
    "iso:country":"GB",
    "name:cym_x_preferred":[
        "Wick"
    ],
    "name:pol_x_preferred":[
        "Wick"
    ],
    "wof:name":"Wick",
    "wof:placetype":"neighbourhood"
},
  "geometry": {"coordinates":[-1.78,50.72757],"type":"Point"}
}