{
  "type": "Feature",
  "properties": {
    "gn:admin1_code":"ENG",
    "gn:admin2_code":"E1",
    "gn:admin3_code":"00FB031",
    "gn:asciiname":"Low Catton",
    "gn:country_code":"GB",
    "gn:dem":16,
    "gn:feature_class":"P",
    "gn:feature_code":"PPL",
    "gn:name":"Low Catton",
    "gn:population":0,
    "gn:timezone":"Europe/London",
    "iso:country":"GB",
    "name:pol_x_preferred":[
        "Low Catton"
    ],
    "name:und_x_variant":[
        "Catton"
    ],
    "wof:name":"Low Catton",
    "wof:placetype":"neighbourhood"
},
  "geometry": {"coordinates":[-0.92627,53.97439],"type":"Point"}
}