{
  "type": "Feature",
  "properties": {
    "iso:country":"GB",
    "name:eng_x_preferred":[
        "Walnut Tree"
    ],
    "name:nld_x_preferred":[
        "Walnut Tree"
    ],
    "name:pol_x_preferred":[
        "Walnut Tree"
    ],
    "qs_pg:aaroncc":"GB",
    "qs_pg:name":"Walnut Tree",
    "qs_pg:name_adm0":"United Kingdom",
    "qs_pg:name_adm1":"England",
    "qs_pg:photos":10,
    "qs_pg:photos_1k":2,
    "qs_pg:photos_9k":1,
    "qs_pg:photos_9r":1,
    "qs_pg:photos_all":10,
    "qs_pg:photos_sr":1,
    "qs_pg:pop_sr":0,
    "qs_pg:qs_pg_placetype":"locality",
    "qs_pg:qs_pg_placetype_gp":"Town",
    "qs_pg:woe_adm0":23424975,
    "woe:adm0_id":23424975,
    "woe:name_adm0":"United Kingdom",
    "woe:name_adm1":"England",
    "woe:placetype":"Town",
    "wof:name":"Walnut Tree",
    "wof:placetype":"neighbourhood"
},
  "geometry": {"coordinates":[-0.6946485,52.0180505],"type":"Point"}
}