{
  "type": "Feature",
  "properties": {
    "iso:country":"GB",
    "name:eng_x_preferred":[
        "Charlton-All-Saints"
    ],
    "name:fra_x_preferred":[
        "Charlton-All-Saints"
    ],
    "name:gle_x_preferred":[
        "Charlton-All-Saints"
    ],
    "name:nld_x_preferred":[
        "Charlton-All-Saints"
    ],
    "name:pol_x_preferred":[
        "Charlton-All-Saints"
    ],
    "qs_pg:aaroncc":"GB",
    "qs_pg:name":"Charlton-All-Saints",
    "qs_pg:name_adm0":"United Kingdom",
    "qs_pg:name_adm1":"England",
    "qs_pg:photos":96,
    "qs_pg:photos_1k":19,
    "qs_pg:photos_9k":1,
    "qs_pg:photos_9r":3,
    "qs_pg:photos_all":96,
    "qs_pg:photos_sr":3,
    "qs_pg:pop_sr":0,
    "qs_pg:qs_pg_placetype":"locality",
    "qs_pg:qs_pg_placetype_gp":"Town",
    "qs_pg:woe_adm0":23424975,
    "woe:adm0_id":23424975,
    "woe:name_adm0":"United Kingdom",
    "woe:name_adm1":"England",
    "woe:placetype":"Town",
    "wof:name":"Charlton-All-Saints",
    "wof:placetype":"neighbourhood"
},
  "geometry": {"coordinates":[-1.744388,51.012675],"type":"Point"}
}