{
  "type": "Feature",
  "properties": {
    "iso:country":"GB",
    "name:bre_x_preferred":[
        "New Town"
    ],
    "name:ceb_x_preferred":[
        "New Town"
    ],
    "name:dan_x_preferred":[
        "New Town"
    ],
    "name:deu_x_preferred":[
        "New Town"
    ],
    "name:fin_x_preferred":[
        "New Town"
    ],
    "name:mlg_x_preferred":[
        "New Town"
    ],
    "name:nld_x_preferred":[
        "New Town"
    ],
    "name:sco_x_preferred":[
        "New Town"
    ],
    "name:swe_x_preferred":[
        "New Town"
    ],
    "qs_pg:aaroncc":"GB",
    "qs_pg:name":"New Town",
    "qs_pg:name_adm0":"United Kingdom",
    "qs_pg:name_adm1":"England",
    "qs_pg:photos":136,
    "qs_pg:photos_1k":28,
    "qs_pg:photos_9k":1,
    "qs_pg:photos_9r":3,
    "qs_pg:photos_all":136,
    "qs_pg:photos_sr":3,
    "qs_pg:pop_sr":0,
    "qs_pg:qs_pg_placetype":"locality",
    "qs_pg:qs_pg_placetype_gp":"Town",
    "qs_pg:woe_adm0":23424975,
    "woe:adm0_id":23424975,
    "woe:name_adm0":"United Kingdom",
    "woe:name_adm1":"England",
    "woe:placetype":"Town",
    "wof:name":"New Town",
    "wof:placetype":"neighbourhood"
},
  "geometry": {"coordinates":[0.094048,50.9714],"type":"Point"}
}