{
  "type": "Feature",
  "properties": {
    "gn:gn_country":"GB",
    "gn:gn_fcode":"PPL",
    "gn:gn_pop":0,
    "iso:country":"GB",
    "name:ara_x_preferred":[
        "\u0644\u0646\u0631\u064a\u062b"
    ],
    "name:bul_x_preferred":[
        "\u041b\u0430\u043d\u0440\u0435\u0430\u0442\u0445"
    ],
    "name:cor_x_preferred":[
        "Lannreydhow"
    ],
    "name:dut_x_preferred":[
        "Lanreath"
    ],
    "name:eng_x_preferred":[
        "Lanreath"
    ],
    "name:fre_x_preferred":[
        "Lanreath"
    ],
    "name:ger_x_preferred":[
        "Lanreath"
    ],
    "name:lat_x_preferred":[
        "Lanreath"
    ],
    "name:pol_x_preferred":[
        "Lanreath"
    ],
    "name:rus_x_preferred":[
        "\u041b\u0430\u043d\u0440\u0438\u0442"
    ],
    "name:swe_x_preferred":[
        "Lanreath"
    ],
    "name:unk_x_variant":[
        "Lanreath"
    ],
    "name:wel_x_preferred":[
        "Lanreath"
    ],
    "qs_pg:aaroncc":"GB",
    "qs_pg:gn_country":"GB",
    "qs_pg:gn_fcode":"PPL",
    "qs_pg:gn_pop":0,
    "qs_pg:name":"Millandreath",
    "qs_pg:name_adm0":"United Kingdom",
    "qs_pg:name_adm1":"England",
    "qs_pg:photos":49,
    "qs_pg:photos_1k":10,
    "qs_pg:photos_9k":1,
    "qs_pg:photos_9r":2,
    "qs_pg:photos_all":49,
    "qs_pg:photos_sr":2,
    "qs_pg:pop_sr":0,
    "qs_pg:qs_pg_placetype":"locality",
    "qs_pg:qs_pg_placetype_gp":"Town",
    "qs_pg:woe_adm0":23424975,
    "woe:adm0_id":23424975,
    "woe:name_adm0":"United Kingdom",
    "woe:name_adm1":"England",
    "woe:placetype":"Town",
    "wof:name":"Millandreath",
    "wof:placetype":"neighbourhood"
},
  "geometry": {"coordinates":[-4.56037,50.38414],"type":"Point"}
}