{
  "type": "Feature",
  "properties": {
    "gn:country":"GB",
    "gn:fcode":"PPL",
    "gn:population":0,
    "iso:country":"GB",
    "name:cym_x_preferred":[
        "Buckenham"
    ],
    "name:eng_x_preferred":[
        "Buckenham"
    ],
    "name:fra_x_preferred":[
        "Buckenham"
    ],
    "name:gle_x_preferred":[
        "Buckenham"
    ],
    "name:jpn_x_preferred":[
        "\u30d0\u30c3\u30b1\u30ca\u30e0"
    ],
    "name:lld_x_preferred":[
        "Buckenham"
    ],
    "name:nld_x_preferred":[
        "Buckenham"
    ],
    "name:pol_x_preferred":[
        "Buckenham"
    ],
    "qs_pg:aaroncc":"GB",
    "qs_pg:gn_country":"GB",
    "qs_pg:gn_fcode":"PPL",
    "qs_pg:gn_pop":0,
    "qs_pg:name":"Buckenham",
    "qs_pg:name_adm0":"United Kingdom",
    "qs_pg:name_adm1":"England",
    "qs_pg:photos":403,
    "qs_pg:photos_1k":82,
    "qs_pg:photos_9k":2,
    "qs_pg:photos_9r":5,
    "qs_pg:photos_all":403,
    "qs_pg:photos_sr":6,
    "qs_pg:pop_sr":0,
    "qs_pg:qs_pg_placetype":"locality",
    "qs_pg:qs_pg_placetype_gp":"Town",
    "qs_pg:woe_adm0":23424975,
    "woe:adm0_id":23424975,
    "woe:name_adm0":"United Kingdom",
    "woe:name_adm1":"England",
    "woe:placetype":"Town",
    "wof:name":"Buckenham",
    "wof:placetype":"neighbourhood"
},
  "geometry": {"coordinates":[1.47861,52.60114],"type":"Point"}
}