{
  "type": "Feature",
  "properties": {
    "iso:country":"GB",
    "name:eng_x_preferred":[
        "Washpool"
    ],
    "qs:gn_local":0,
    "qs:local_max":4986,
    "qs:local_sum":18288,
    "qs:localhoods":17,
    "qs:name":"Washpool",
    "qs:name_adm0":"United Kingdom",
    "qs:name_adm1":"England",
    "qs:name_adm2":"Wiltshire",
    "qs:name_lau":"Swindon Borough",
    "qs:name_local":"Swindon",
    "qs:photo_max":12,
    "qs:photo_sum":24,
    "qs:placetype":"Suburb",
    "qs:quad_count":5,
    "qs:woe_adm0":23424975,
    "qs:woe_adm1":24554868,
    "qs:woe_adm2":12602186,
    "qs:woe_lau":12696162,
    "qs:woe_local":36796,
    "qs:woe_ver":"7.10.0",
    "wof:lang":[
        "eng"
    ],
    "wof:name":"Washpool",
    "wof:placetype":"neighbourhood"
},
  "geometry": {"coordinates":[-1.87706,51.577494],"type":"Point"}
}