{
  "type": "Feature",
  "properties": {
    "gn:admin1_code": "05",
    "gn:asciiname": "Katalymata ton Plakoton",
    "gn:country_code": "GB",
    "gn:dem": 21,
    "gn:feature_class": "P",
    "gn:feature_code": "PPL",
    "gn:name": "Katalymata ton Plakoton",
    "gn:population": 0,
    "gn:timezone": "Asia/Nicosia",
    "iso:country": "GB",
    "name:ell_x_preferred": [
      "Katalýmata ton Plakotón"
    ],
    "name:ell_x_variant": [
      "Καταλύματα των Πλακωτών"
    ],
    "wof:name": "Katalymata ton Plakoton",
    "wof:placetype": "locality"
  },
  "geometry": {"coordinates":[32.94583,34.58333],"type":"Point"}
}
