{
  "type": "Feature",
  "properties": {
    "gn:admin1_code": "ENG",
    "gn:admin2_code": "H5",
    "gn:admin3_code": "31UD",
    "gn:admin4_code": "31UD019",
    "gn:asciiname": "Gloostone",
    "gn:country_code": "GB",
    "gn:dem": 111,
    "gn:feature_class": "P",
    "gn:feature_code": "PPL",
    "gn:name": "Gloostone",
    "gn:population": 0,
    "gn:timezone": "Europe/London",
    "iso:country": "GB",
    "wof:name": "Gloostone",
    "wof:placetype": "neighbourhood"
  },
  "geometry": {"coordinates":[-0.88333,52.55],"type":"Point"}
}
