{
  "type": "Feature",
  "properties": {
    "iso:country":"GB",
    "name:deu_x_preferred":[
        "Allasdale"
    ],
    "name:eng_x_preferred":[
        "Allasdale"
    ],
    "name:eus_x_preferred":[
        "Allasdale"
    ],
    "name:fra_x_preferred":[
        "Allasdale"
    ],
    "name:gle_x_preferred":[
        "Allathasdal"
    ],
    "name:nld_x_preferred":[
        "Allasdale"
    ],
    "qs_pg:aaroncc":"GB",
    "qs_pg:name":"Allasdale",
    "qs_pg:name_adm0":"United Kingdom",
    "qs_pg:name_adm1":"Scotland",
    "qs_pg:photos":122,
    "qs_pg:photos_1k":25,
    "qs_pg:photos_9k":1,
    "qs_pg:photos_9r":3,
    "qs_pg:photos_all":122,
    "qs_pg:photos_sr":3,
    "qs_pg:pop_sr":0,
    "qs_pg:qs_pg_placetype":"locality",
    "qs_pg:qs_pg_placetype_gp":"Town",
    "qs_pg:woe_adm0":23424975,
    "woe:adm0_id":23424975,
    "woe:name_adm0":"United Kingdom",
    "woe:name_adm1":"Scotland",
    "woe:placetype":"Town",
    "wof:name":"Allasdale",
    "wof:placetype":"locality"
},
  "geometry": {"coordinates":[-7.506923,57.004569],"type":"Point"}
}