{
  "type": "Feature",
  "properties": {
    "gn:admin1_code": "ENG",
    "gn:admin2_code": "J7",
    "gn:admin3_code": "36UF",
    "gn:admin4_code": "36UF043",
    "gn:asciiname": "Great Habton",
    "gn:country_code": "GB",
    "gn:dem": 25,
    "gn:feature_class": "P",
    "gn:feature_code": "PPLA4",
    "gn:name": "Great Habton",
    "gn:population": 0,
    "gn:timezone": "Europe/London",
    "iso:country": "GB",
    "name:und_x_variant": [
      "Habton",
      "Great Habton"
    ],
    "wof:name": "Great Habton",
    "wof:placetype": "neighbourhood"
  },
  "geometry": {"coordinates":[-0.84166,54.17841],"type":"Point"}
}
