{
  "type": "Feature",
  "properties": {
    "gn:admin1_code":"SCT",
    "gn:admin2_code":"T8",
    "gn:asciiname":"Portachoillan",
    "gn:country_code":"GB",
    "gn:dem":4,
    "gn:feature_class":"P",
    "gn:feature_code":"PPL",
    "gn:name":"Portachoillan",
    "gn:population":0,
    "gn:timezone":"Europe/London",
    "iso:country":"GB",
    "wof:name":"Portachoillan",
    "wof:placetype":"locality"
},
  "geometry": {"coordinates":[-5.57402,55.76247],"type":"Point"}
}