{
  "type": "Feature",
  "properties": {
    "gn:admin1_code":"ENG",
    "gn:admin2_code":"J1",
    "gn:admin3_code":"34UG",
    "gn:admin4_code":"34UG024",
    "gn:asciiname":"Showsley",
    "gn:country_code":"GB",
    "gn:dem":121,
    "gn:feature_class":"P",
    "gn:feature_code":"PPL",
    "gn:name":"Showsley",
    "gn:population":0,
    "gn:timezone":"Europe/London",
    "iso:country":"GB",
    "wof:name":"Showsley",
    "wof:placetype":"neighbourhood"
},
  "geometry": {"coordinates":[-0.96671,52.15171],"type":"Point"}
}