{
  "type": "Feature",
  "properties": {
    "iso:country":"GB",
    "name:eng_x_preferred":[
        "Derrycrin"
    ],
    "name:eus_x_preferred":[
        "Derrycrin"
    ],
    "name:fra_x_preferred":[
        "Derrycrin"
    ],
    "name:gle_x_preferred":[
        "Doire Cr\u00edon"
    ],
    "name:msa_x_preferred":[
        "Derrychrin"
    ],
    "name:nld_x_preferred":[
        "Derrycrin"
    ],
    "name:pli_x_preferred":[
        "\u0926\u0947\u0930\u094d\u0930\u094d\u092f\u094d\u091a\u0930\u093f\u0928"
    ],
    "qs_pg:aaroncc":"GB",
    "qs_pg:name":"Derrychrin",
    "qs_pg:name_adm0":"United Kingdom",
    "qs_pg:name_adm1":"Northern Ireland",
    "qs_pg:photos":10,
    "qs_pg:photos_1k":2,
    "qs_pg:photos_9k":1,
    "qs_pg:photos_9r":1,
    "qs_pg:photos_all":10,
    "qs_pg:photos_sr":1,
    "qs_pg:pop_sr":0,
    "qs_pg:qs_pg_placetype":"locality",
    "qs_pg:qs_pg_placetype_gp":"Town",
    "qs_pg:woe_adm0":23424975,
    "woe:adm0_id":23424975,
    "woe:name_adm0":"United Kingdom",
    "woe:name_adm1":"Northern Ireland",
    "woe:placetype":"Town",
    "wof:name":"Derrychrin",
    "wof:placetype":"locality"
},
  "geometry": {"coordinates":[-6.539749,54.681395],"type":"Point"}
}