{
  "type": "Feature",
  "properties": {
    "gn:country":"GB",
    "gn:fcode":"PPL",
    "gn:population":0,
    "iso:country":"GB",
    "name:ceb_x_preferred":[
        "Godshill"
    ],
    "name:cym_x_preferred":[
        "Godshill"
    ],
    "name:fas_x_preferred":[
        "\u06af\u0627\u062f\u0632\u0647\u06cc\u0644"
    ],
    "name:ita_x_preferred":[
        "Godshill"
    ],
    "name:nld_x_preferred":[
        "Godshill"
    ],
    "name:pol_x_preferred":[
        "Godshill"
    ],
    "name:spa_x_preferred":[
        "Godshill"
    ],
    "name:swe_x_preferred":[
        "Godshill"
    ],
    "qs_pg:aaroncc":"GB",
    "qs_pg:gn_country":"GB",
    "qs_pg:gn_fcode":"PPL",
    "qs_pg:gn_pop":0,
    "qs_pg:name":"Godshill",
    "qs_pg:name_adm0":"United Kingdom",
    "qs_pg:name_adm1":"England",
    "qs_pg:photos":100,
    "qs_pg:photos_1k":20,
    "qs_pg:photos_9k":1,
    "qs_pg:photos_9r":3,
    "qs_pg:photos_all":100,
    "qs_pg:photos_sr":3,
    "qs_pg:pop_sr":0,
    "qs_pg:qs_pg_placetype":"locality",
    "qs_pg:qs_pg_placetype_gp":"Town",
    "qs_pg:woe_adm0":23424975,
    "woe:adm0_id":23424975,
    "woe:name_adm0":"United Kingdom",
    "woe:name_adm1":"England",
    "woe:placetype":"Town",
    "wof:name":"Godshill",
    "wof:placetype":"neighbourhood",
    "wof:population":436
},
  "geometry": {"coordinates":[-1.75,50.91667],"type":"Point"}
}