{
  "type": "Feature",
  "properties": {
    "gn:admin1_code":"SCT",
    "gn:admin2_code":"U2",
    "gn:admin3_code":"16UB",
    "gn:asciiname":"Mouswald",
    "gn:country_code":"GB",
    "gn:dem":51,
    "gn:feature_class":"P",
    "gn:feature_code":"PPL",
    "gn:name":"Mouswald",
    "gn:population":0,
    "gn:timezone":"Europe/London",
    "iso:country":"GB",
    "name:deu_x_preferred":[
        "Mouswald"
    ],
    "name:eus_x_preferred":[
        "Mouswald"
    ],
    "name:gla_x_preferred":[
        "Mouswald"
    ],
    "name:gle_x_preferred":[
        "Mouswald"
    ],
    "name:sco_x_preferred":[
        "Moosal"
    ],
    "wof:name":"Mouswald",
    "wof:placetype":"locality"
},
  "geometry": {"coordinates":[-3.46466,55.03998000000001],"type":"Point"}
}