{
  "type": "Feature",
  "properties": {
    "iso:country":"GB",
    "wof:name":"Tong Street",
    "wof:placetype":"neighbourhood"
},
  "geometry": {"coordinates":[-1.70437555998542,53.76630722411411],"type":"Point"}
}