{
  "type": "Feature",
  "properties": {
    "gn:country": "GB",
    "gn:fcode": "PPL",
    "gn:population": 0,
    "iso:country": "GB",
    "name:ben_x_preferred": [
      "অকওর্থ"
    ],
    "name:cat_x_preferred": [
      "Ackworth"
    ],
    "name:ceb_x_preferred": [
      "Ackworth"
    ],
    "name:deu_x_preferred": [
      "Ackworth"
    ],
    "name:eng_x_preferred": [
      "Ackworth"
    ],
    "name:epo_x_preferred": [
      "Ackworth"
    ],
    "name:fas_x_preferred": [
      "اکورث"
    ],
    "name:fra_x_preferred": [
      "Ackworth"
    ],
    "name:guj_x_preferred": [
      "એકવર્થ"
    ],
    "name:ido_x_preferred": [
      "Ackworth"
    ],
    "name:jpn_x_preferred": [
      "アクワース"
    ],
    "name:jpn_x_variant": [
      "アクワース"
    ],
    "name:kan_x_preferred": [
      "ಆಕ್ವರ್ತ್"
    ],
    "name:kor_x_preferred": [
      "애크웜"
    ],
    "name:lit_x_preferred": [
      "Akvortas"
    ],
    "name:nld_x_preferred": [
      "Ackworth"
    ],
    "name:pol_x_preferred": [
      "Ackworth"
    ],
    "name:por_x_preferred": [
      "Ackworth"
    ],
    "name:rus_x_preferred": [
      "Экворф"
    ],
    "name:spa_x_preferred": [
      "Ackworth"
    ],
    "name:swe_x_preferred": [
      "Ackworth"
    ],
    "name:tam_x_preferred": [
      "ஆக்ஒர்த்"
    ],
    "name:tel_x_preferred": [
      "అక్వర్త్"
    ],
    "name:urd_x_preferred": [
      "اکوورتھ"
    ],
    "qs_pg:aaroncc": "GB",
    "qs_pg:gn_country": "GB",
    "qs_pg:gn_fcode": "PPL",
    "qs_pg:gn_pop": 0,
    "qs_pg:name": "High Ackworth",
    "qs_pg:name_adm0": "United Kingdom",
    "qs_pg:name_adm1": "England",
    "qs_pg:photos": 193,
    "qs_pg:photos_1k": 39,
    "qs_pg:photos_9k": 1,
    "qs_pg:photos_9r": 4,
    "qs_pg:photos_all": 193,
    "qs_pg:photos_sr": 4,
    "qs_pg:pop_sr": 0,
    "qs_pg:qs_pg_placetype": "locality",
    "qs_pg:qs_pg_placetype_gp": "Town",
    "qs_pg:woe_adm0": 23424975,
    "woe:adm0_id": 23424975,
    "woe:name_adm0": "United Kingdom",
    "woe:name_adm1": "England",
    "woe:placetype": "Town",
    "wof:name": "High Ackworth",
    "wof:placetype": "neighbourhood"
  },
  "geometry": {"coordinates":[-1.33372,53.65603],"type":"Point"}
}
