{
  "type": "Feature",
  "properties": {
    "gn:country":"GB",
    "gn:fcode":"PPL",
    "gn:population":0,
    "iso:country":"GB",
    "name:ben_x_preferred":[
        "\u0985\u0995\u0993\u09b0\u09cd\u09a5"
    ],
    "name:cat_x_preferred":[
        "Ackworth"
    ],
    "name:ceb_x_preferred":[
        "Ackworth"
    ],
    "name:deu_x_preferred":[
        "Ackworth"
    ],
    "name:eng_x_preferred":[
        "Ackworth"
    ],
    "name:epo_x_preferred":[
        "Ackworth"
    ],
    "name:fas_x_preferred":[
        "\u0627\u06a9\u0648\u0631\u062b"
    ],
    "name:fra_x_preferred":[
        "Ackworth"
    ],
    "name:guj_x_preferred":[
        "\u0a8f\u0a95\u0ab5\u0ab0\u0acd\u0aa5"
    ],
    "name:ido_x_preferred":[
        "Ackworth"
    ],
    "name:jpn_x_preferred":[
        "\u30a2\u30af\u30ef\u30fc\u30b9"
    ],
    "name:jpn_x_variant":[
        "\u30a2\u30af\u30ef\u30fc\u30b9"
    ],
    "name:kan_x_preferred":[
        "\u0c86\u0c95\u0ccd\u0cb5\u0cb0\u0ccd\u0ca4\u0ccd"
    ],
    "name:kor_x_preferred":[
        "\uc560\ud06c\uc6dc"
    ],
    "name:lit_x_preferred":[
        "Akvortas"
    ],
    "name:nld_x_preferred":[
        "Ackworth"
    ],
    "name:pol_x_preferred":[
        "Ackworth"
    ],
    "name:por_x_preferred":[
        "Ackworth"
    ],
    "name:rus_x_preferred":[
        "\u042d\u043a\u0432\u043e\u0440\u0444"
    ],
    "name:spa_x_preferred":[
        "Ackworth"
    ],
    "name:swe_x_preferred":[
        "Ackworth"
    ],
    "name:tam_x_preferred":[
        "\u0b86\u0b95\u0bcd\u0b92\u0bb0\u0bcd\u0ba4\u0bcd"
    ],
    "name:tel_x_preferred":[
        "\u0c05\u0c15\u0c4d\u0c35\u0c30\u0c4d\u0c24\u0c4d"
    ],
    "name:urd_x_preferred":[
        "\u0627\u06a9\u0648\u0648\u0631\u062a\u06be"
    ],
    "qs_pg:aaroncc":"GB",
    "qs_pg:gn_country":"GB",
    "qs_pg:gn_fcode":"PPL",
    "qs_pg:gn_pop":0,
    "qs_pg:name":"High Ackworth",
    "qs_pg:name_adm0":"United Kingdom",
    "qs_pg:name_adm1":"England",
    "qs_pg:photos":193,
    "qs_pg:photos_1k":39,
    "qs_pg:photos_9k":1,
    "qs_pg:photos_9r":4,
    "qs_pg:photos_all":193,
    "qs_pg:photos_sr":4,
    "qs_pg:pop_sr":0,
    "qs_pg:qs_pg_placetype":"locality",
    "qs_pg:qs_pg_placetype_gp":"Town",
    "qs_pg:woe_adm0":23424975,
    "woe:adm0_id":23424975,
    "woe:name_adm0":"United Kingdom",
    "woe:name_adm1":"England",
    "woe:placetype":"Town",
    "wof:name":"High Ackworth",
    "wof:placetype":"neighbourhood"
},
  "geometry": {"coordinates":[-1.33372,53.65603],"type":"Point"}
}