{
  "type": "Feature",
  "properties": {
    "iso:country": "GB",
    "name:ceb_x_preferred": [
      "Worston"
    ],
    "name:cym_x_preferred": [
      "Worston"
    ],
    "name:fas_x_preferred": [
      "ورستون"
    ],
    "name:ita_x_preferred": [
      "Worston"
    ],
    "name:nld_x_preferred": [
      "Worston"
    ],
    "name:pol_x_preferred": [
      "Worston"
    ],
    "name:swe_x_preferred": [
      "Worston"
    ],
    "qs_pg:aaroncc": "GB",
    "qs_pg:name": "Worston",
    "qs_pg:name_adm0": "United Kingdom",
    "qs_pg:name_adm1": "England",
    "qs_pg:photos": 14,
    "qs_pg:photos_1k": 3,
    "qs_pg:photos_9k": 1,
    "qs_pg:photos_9r": 1,
    "qs_pg:photos_all": 14,
    "qs_pg:photos_sr": 1,
    "qs_pg:pop_sr": 0,
    "qs_pg:qs_pg_placetype": "locality",
    "qs_pg:qs_pg_placetype_gp": "Town",
    "qs_pg:woe_adm0": 23424975,
    "woe:adm0_id": 23424975,
    "woe:name_adm0": "United Kingdom",
    "woe:name_adm1": "England",
    "woe:placetype": "Town",
    "wof:name": "Worston",
    "wof:placetype": "neighbourhood"
  },
  "geometry": {"coordinates":[-3.9624225,50.3661495],"type":"Point"}
}
