{
  "type": "Feature",
  "properties": {
    "gn:admin1_code":"NIR",
    "gn:admin2_code":"N09000008",
    "gn:asciiname":"Clogh",
    "gn:cc2":"GB",
    "gn:country_code":"GB",
    "gn:dem":157,
    "gn:feature_class":"P",
    "gn:feature_code":"PPL",
    "gn:name":"Clogh",
    "gn:population":0,
    "gn:timezone":"Europe/London",
    "iso:country":"GB",
    "name:und_x_variant":[
        "Clough",
        "Clogh"
    ],
    "wof:name":"Clogh",
    "wof:placetype":"locality"
},
  "geometry": {"coordinates":[-6.28333,54.96666999999999],"type":"Point"}
}