{
  "type": "Feature",
  "properties": {
    "gn:admin1_code": "SCT",
    "gn:admin2_code": "V1",
    "gn:asciiname": "Fordell",
    "gn:country_code": "GB",
    "gn:dem": 125,
    "gn:feature_class": "P",
    "gn:feature_code": "PPL",
    "gn:name": "Fordell",
    "gn:population": 0,
    "gn:timezone": "Europe/London",
    "iso:country": "GB",
    "name:und_x_variant": [
      "Fordel",
      "Fordell"
    ],
    "wof:name": "Fordell",
    "wof:placetype": "locality"
  },
  "geometry": {"coordinates":[-3.35888,56.08143000000001],"type":"Point"}
}
