{
  "type": "Feature",
  "properties": {
    "gn:admin1_code":"ENG",
    "gn:admin2_code":"G5",
    "gn:admin3_code":"29UG",
    "gn:admin4_code":"29UG006",
    "gn:asciiname":"Vigo Village",
    "gn:country_code":"GB",
    "gn:dem":194,
    "gn:feature_class":"P",
    "gn:feature_code":"PPL",
    "gn:name":"Vigo Village",
    "gn:population":0,
    "gn:timezone":"Europe/London",
    "iso:country":"GB",
    "wof:name":"Vigo Village",
    "wof:placetype":"neighbourhood"
},
  "geometry": {"coordinates":[0.35139,51.33053],"type":"Point"}
}