{
  "type": "Feature",
  "properties": {
    "gn:country": "GB",
    "gn:fcode": "PPL",
    "gn:population": 0,
    "iso:country": "GB",
    "name:ben_x_preferred": [
      "ইস্ট টিলবুরি"
    ],
    "name:cym_x_preferred": [
      "East Tilbury"
    ],
    "name:deu_x_preferred": [
      "East Tilbury"
    ],
    "name:eng_x_preferred": [
      "East Tilbury"
    ],
    "name:fas_x_preferred": [
      "تیلبری شرقی"
    ],
    "name:fra_x_preferred": [
      "East Tilbury"
    ],
    "name:guj_x_preferred": [
      "પૂર્વ તિલબરી"
    ],
    "name:jpn_x_preferred": [
      "東ティルベリー"
    ],
    "name:kan_x_preferred": [
      "ಈಸ್ಟ್ ಟಿಲ್ಬರಿ"
    ],
    "name:kor_x_preferred": [
      "이스트 티벌리"
    ],
    "name:lit_x_preferred": [
      "Ist Tilburis"
    ],
    "name:nld_x_preferred": [
      "East Tilbury"
    ],
    "name:pol_x_preferred": [
      "East Tilbury"
    ],
    "name:por_x_preferred": [
      "East Tilbury"
    ],
    "name:rus_x_preferred": [
      "Ист-Тилбери"
    ],
    "name:spa_x_preferred": [
      "East Tilbury"
    ],
    "name:swe_x_preferred": [
      "East Tilbury"
    ],
    "name:tam_x_preferred": [
      "கிழக்கு தில்புரி"
    ],
    "name:tel_x_preferred": [
      "తూర్పు తిల్బరి"
    ],
    "name:urd_x_preferred": [
      "ایسٹ تلبوری"
    ],
    "name:zho_x_preferred": [
      "東提爾布利"
    ],
    "qs_pg:aaroncc": "GB",
    "qs_pg:gn_country": "GB",
    "qs_pg:gn_fcode": "PPL",
    "qs_pg:gn_pop": 0,
    "qs_pg:name": "East Tilbury",
    "qs_pg:name_adm0": "United Kingdom",
    "qs_pg:name_adm1": "England",
    "qs_pg:photos": 588,
    "qs_pg:photos_1k": 119,
    "qs_pg:photos_9k": 3,
    "qs_pg:photos_9r": 5,
    "qs_pg:photos_all": 588,
    "qs_pg:photos_sr": 8,
    "qs_pg:pop_sr": 0,
    "qs_pg:qs_pg_placetype": "locality",
    "qs_pg:qs_pg_placetype_gp": "Town",
    "qs_pg:woe_adm0": 23424975,
    "woe:adm0_id": 23424975,
    "woe:name_adm0": "United Kingdom",
    "woe:name_adm1": "England",
    "woe:placetype": "Town",
    "wof:name": "East Tilbury",
    "wof:placetype": "neighbourhood",
    "wof:population": 5471
  },
  "geometry": {"coordinates":[0.41714,51.48053],"type":"Point"}
}
