{
  "type": "Feature",
  "properties": {
    "gn:country":"GB",
    "gn:fcode":"PPL",
    "gn:population":0,
    "iso:country":"GB",
    "name:ben_x_preferred":[
        "\u0987\u09b8\u09cd\u099f \u099f\u09bf\u09b2\u09ac\u09c1\u09b0\u09bf"
    ],
    "name:ceb_x_preferred":[
        "East Tilbury"
    ],
    "name:cym_x_preferred":[
        "East Tilbury"
    ],
    "name:deu_x_preferred":[
        "East Tilbury"
    ],
    "name:eng_x_preferred":[
        "East Tilbury"
    ],
    "name:fas_x_preferred":[
        "\u062a\u06cc\u0644\u0628\u0631\u06cc \u0634\u0631\u0642\u06cc"
    ],
    "name:fra_x_preferred":[
        "East Tilbury"
    ],
    "name:gle_x_preferred":[
        "East Tilbury"
    ],
    "name:guj_x_preferred":[
        "\u0aaa\u0ac2\u0ab0\u0acd\u0ab5 \u0aa4\u0abf\u0ab2\u0aac\u0ab0\u0ac0"
    ],
    "name:heb_x_preferred":[
        "\u05de\u05d6\u05e8\u05d7 \u05d8\u05d9\u05dc\u05d1\u05e8\u05d9"
    ],
    "name:jpn_x_preferred":[
        "\u6771\u30c6\u30a3\u30eb\u30d9\u30ea\u30fc"
    ],
    "name:kan_x_preferred":[
        "\u0c88\u0cb8\u0ccd\u0c9f\u0ccd \u0c9f\u0cbf\u0cb2\u0ccd\u0cac\u0cb0\u0cbf"
    ],
    "name:kor_x_preferred":[
        "\uc774\uc2a4\ud2b8 \ud2f0\ubc8c\ub9ac"
    ],
    "name:lat_x_preferred":[
        "Tiliberia Magna"
    ],
    "name:lit_x_preferred":[
        "Ist Tilburis"
    ],
    "name:nld_x_preferred":[
        "East Tilbury"
    ],
    "name:pol_x_preferred":[
        "East Tilbury"
    ],
    "name:por_x_preferred":[
        "East Tilbury"
    ],
    "name:rus_x_preferred":[
        "\u0418\u0441\u0442-\u0422\u0438\u043b\u0431\u0435\u0440\u0438"
    ],
    "name:spa_x_preferred":[
        "East Tilbury"
    ],
    "name:swe_x_preferred":[
        "East Tilbury"
    ],
    "name:tam_x_preferred":[
        "\u0b95\u0bbf\u0bb4\u0b95\u0bcd\u0b95\u0bc1 \u0ba4\u0bbf\u0bb2\u0bcd\u0baa\u0bc1\u0bb0\u0bbf"
    ],
    "name:tel_x_preferred":[
        "\u0c24\u0c42\u0c30\u0c4d\u0c2a\u0c41 \u0c24\u0c3f\u0c32\u0c4d\u0c2c\u0c30\u0c3f"
    ],
    "name:ukr_x_preferred":[
        "\u0406\u0441\u0442-\u0422\u0456\u043b\u0431\u0435\u0440\u0456"
    ],
    "name:urd_x_preferred":[
        "\u0627\u06cc\u0633\u0679 \u062a\u0644\u0628\u0648\u0631\u06cc"
    ],
    "name:zho_x_preferred":[
        "\u6771\u63d0\u723e\u5e03\u5229"
    ],
    "qs_pg:aaroncc":"GB",
    "qs_pg:gn_country":"GB",
    "qs_pg:gn_fcode":"PPL",
    "qs_pg:gn_pop":0,
    "qs_pg:name":"East Tilbury",
    "qs_pg:name_adm0":"United Kingdom",
    "qs_pg:name_adm1":"England",
    "qs_pg:photos":588,
    "qs_pg:photos_1k":119,
    "qs_pg:photos_9k":3,
    "qs_pg:photos_9r":5,
    "qs_pg:photos_all":588,
    "qs_pg:photos_sr":8,
    "qs_pg:pop_sr":0,
    "qs_pg:qs_pg_placetype":"locality",
    "qs_pg:qs_pg_placetype_gp":"Town",
    "qs_pg:woe_adm0":23424975,
    "woe:adm0_id":23424975,
    "woe:name_adm0":"United Kingdom",
    "woe:name_adm1":"England",
    "woe:placetype":"Town",
    "wof:name":"East Tilbury",
    "wof:placetype":"neighbourhood",
    "wof:population":5471
},
  "geometry": {"coordinates":[0.41714,51.48053],"type":"Point"}
}