{
  "type": "Feature",
  "properties": {
    "gn:admin1_code": "ENG",
    "gn:admin2_code": "O7",
    "gn:admin3_code": "00DB027",
    "gn:asciiname": "Bretton Country Park",
    "gn:country_code": "GB",
    "gn:dem": 119,
    "gn:feature_class": "P",
    "gn:feature_code": "PPL",
    "gn:name": "Bretton Country Park",
    "gn:population": 0,
    "gn:timezone": "Europe/London",
    "iso:country": "GB",
    "wof:name": "Bretton Country Park",
    "wof:placetype": "neighbourhood"
  },
  "geometry": {"coordinates":[-1.57079,53.61288],"type":"Point"}
}
