{
  "type": "Feature",
  "properties": {
    "gn:admin1_code":"ENG",
    "gn:admin2_code":"E6",
    "gn:admin3_code":"23UD",
    "gn:admin4_code":"23UD015",
    "gn:asciiname":"Solomon Tump",
    "gn:country_code":"GB",
    "gn:dem":43,
    "gn:feature_class":"P",
    "gn:feature_code":"PPL",
    "gn:name":"Solomon Tump",
    "gn:population":0,
    "gn:timezone":"Europe/London",
    "iso:country":"GB",
    "wof:name":"Solomon Tump",
    "wof:placetype":"neighbourhood"
},
  "geometry": {"coordinates":[-2.39403,51.87596],"type":"Point"}
}