{
  "type": "Feature",
  "properties": {
    "iso:country": "GB",
    "name:cat_x_preferred": [
      "Woodside"
    ],
    "name:ceb_x_preferred": [
      "Woodside"
    ],
    "name:deu_x_preferred": [
      "Woodside"
    ],
    "name:fin_x_preferred": [
      "Woodside"
    ],
    "name:fra_x_preferred": [
      "Woodside"
    ],
    "name:fry_x_preferred": [
      "Woodside"
    ],
    "name:hin_x_preferred": [
      "वुडसाइड पार्क"
    ],
    "name:ita_x_preferred": [
      "Woodside"
    ],
    "name:kor_x_preferred": [
      "우드사이드"
    ],
    "name:nld_x_preferred": [
      "Woodside"
    ],
    "name:pol_x_preferred": [
      "Woodside"
    ],
    "name:por_x_preferred": [
      "Woodside"
    ],
    "name:rus_x_preferred": [
      "Вудсайд"
    ],
    "name:srp_x_preferred": [
      "Вудсајд"
    ],
    "name:swe_x_preferred": [
      "Woodside"
    ],
    "name:vol_x_preferred": [
      "Woodside"
    ],
    "wof:name": "Woodside",
    "wof:placetype": "neighbourhood"
  },
  "geometry": {"coordinates":[-1.79012046091621,53.75680219689379],"type":"Point"}
}
