{
  "type": "Feature",
  "properties": {
    "gn:gn_country":"GB",
    "gn:gn_fcode":"PPL",
    "gn:gn_pop":4388,
    "gn:population":4388,
    "iso:country":"GB",
    "name:ceb_x_preferred":[
        "Coningsby"
    ],
    "name:cym_x_preferred":[
        "Coningsby"
    ],
    "name:eng_x_preferred":[
        "Coningsby"
    ],
    "name:epo_x_preferred":[
        "Coningsby"
    ],
    "name:gle_x_preferred":[
        "Coningsby"
    ],
    "name:ita_x_preferred":[
        "Coningsby"
    ],
    "name:jpn_x_preferred":[
        "\u30b3\u30cb\u30f3\u30b0\u30b9\u30d3\u30fc"
    ],
    "name:nld_x_preferred":[
        "Coningsby"
    ],
    "name:pol_x_preferred":[
        "Coningsby"
    ],
    "name:swe_x_preferred":[
        "Coningsby"
    ],
    "qs_pg:aaroncc":"GB",
    "qs_pg:gn_country":"GB",
    "qs_pg:gn_fcode":"PPL",
    "qs_pg:gn_pop":4388,
    "qs_pg:name":"RAF Coningsby",
    "qs_pg:name_adm0":"United Kingdom",
    "qs_pg:name_adm1":"England",
    "qs_pg:photos":2753,
    "qs_pg:photos_1k":558,
    "qs_pg:photos_9k":12,
    "qs_pg:photos_9r":10,
    "qs_pg:photos_all":2753,
    "qs_pg:photos_sr":19,
    "qs_pg:pop_sr":4,
    "qs_pg:qs_pg_placetype":"locality",
    "qs_pg:qs_pg_placetype_gp":"Town",
    "qs_pg:woe_adm0":23424975,
    "woe:adm0_id":23424975,
    "woe:name_adm0":"United Kingdom",
    "woe:name_adm1":"England",
    "woe:placetype":"Town",
    "wof:name":"RAF Coningsby",
    "wof:placetype":"neighbourhood",
    "wof:population":4388
},
  "geometry": {"coordinates":[-0.17595,53.10598],"type":"Point"}
}