{
  "type": "Feature",
  "properties": {
    "gn:gn_country":"GB",
    "gn:gn_fcode":"PPL",
    "gn:gn_pop":0,
    "iso:country":"GB",
    "name:dut_x_preferred":[
        "Cross In Hand"
    ],
    "name:eng_x_preferred":[
        "Cross In Hand"
    ],
    "name:fre_x_preferred":[
        "Cross In Hand"
    ],
    "name:pol_x_preferred":[
        "Cross In Hand"
    ],
    "name:wel_x_preferred":[
        "Cross In Hand"
    ],
    "qs_pg:aaroncc":"GB",
    "qs_pg:gn_country":"GB",
    "qs_pg:gn_fcode":"PPL",
    "qs_pg:gn_pop":0,
    "qs_pg:name":"Cross in Hand",
    "qs_pg:name_adm0":"United Kingdom",
    "qs_pg:name_adm1":"England",
    "qs_pg:photos_9r":0,
    "qs_pg:photos_sr":0,
    "qs_pg:pop_sr":0,
    "qs_pg:qs_pg_placetype":"locality",
    "qs_pg:qs_pg_placetype_gp":"Town",
    "qs_pg:woe_adm0":23424975,
    "woe:adm0_id":23424975,
    "woe:name_adm0":"United Kingdom",
    "woe:name_adm1":"England",
    "woe:placetype":"Town",
    "wof:name":"Cross in Hand",
    "wof:placetype":"neighbourhood"
},
  "geometry": {"coordinates":[0.2238,50.97359],"type":"Point"}
}