{
  "type": "Feature",
  "properties": {
    "gn:country":"GB",
    "gn:fcode":"PPL",
    "gn:population":0,
    "iso:country":"GB",
    "name:bre_x_preferred":[
        "T\u0177-croes"
    ],
    "name:ceb_x_preferred":[
        "Tycroes"
    ],
    "name:cym_x_preferred":[
        "T\u0177-croes"
    ],
    "name:eng_x_preferred":[
        "Tycroes"
    ],
    "name:eus_x_preferred":[
        "Tycroes"
    ],
    "name:fra_x_preferred":[
        "Tycroes"
    ],
    "name:gle_x_preferred":[
        "T\u0177-croes"
    ],
    "name:nld_x_preferred":[
        "Tycroes"
    ],
    "name:spa_x_preferred":[
        "Tycroes"
    ],
    "name:swe_x_preferred":[
        "Tycroes"
    ],
    "qs_pg:aaroncc":"GB",
    "qs_pg:gn_country":"GB",
    "qs_pg:gn_fcode":"PPL",
    "qs_pg:gn_pop":0,
    "qs_pg:name":"Tycroes",
    "qs_pg:name_adm0":"United Kingdom",
    "qs_pg:name_adm1":"Wales",
    "qs_pg:photos_9k":1,
    "qs_pg:photos_9r":1,
    "qs_pg:photos_all":5,
    "qs_pg:photos_sr":0,
    "qs_pg:pop_sr":0,
    "qs_pg:qs_pg_placetype":"locality",
    "qs_pg:qs_pg_placetype_gp":"Town",
    "qs_pg:woe_adm0":23424975,
    "woe:adm0_id":23424975,
    "woe:name_adm0":"United Kingdom",
    "woe:name_adm1":"Wales",
    "woe:placetype":"Town",
    "wof:name":"Tycroes",
    "wof:placetype":"neighbourhood",
    "wof:population":2156
},
  "geometry": {"coordinates":[-4.02,51.77806],"type":"Point"}
}