{
  "type": "Feature",
  "properties": {
    "iso:country":"GB",
    "name:cym_x_preferred":[
        "West Bay"
    ],
    "name:deu_x_preferred":[
        "West Bay"
    ],
    "name:eng_x_preferred":[
        "West Bay"
    ],
    "name:fas_x_preferred":[
        "\u0648\u0633\u062a \u0628\u06cc"
    ],
    "name:fra_x_preferred":[
        "West Bay"
    ],
    "name:ita_x_preferred":[
        "West Bay"
    ],
    "name:jpn_x_preferred":[
        "\u30a6\u30a7\u30b9\u30c8\u30d9\u30a4"
    ],
    "name:nld_x_preferred":[
        "West Bay"
    ],
    "name:rus_x_preferred":[
        "\u0412\u0435\u0441\u0442-\u0411\u044d\u0439"
    ],
    "name:spa_x_preferred":[
        "West Bay"
    ],
    "qs_pg:aaroncc":"GB",
    "qs_pg:name":"West Bay",
    "qs_pg:name_adm0":"United Kingdom",
    "qs_pg:name_adm1":"England",
    "qs_pg:photos":3309,
    "qs_pg:photos_1k":671,
    "qs_pg:photos_9k":15,
    "qs_pg:photos_9r":11,
    "qs_pg:photos_all":3309,
    "qs_pg:photos_sr":20,
    "qs_pg:pop_sr":0,
    "qs_pg:qs_pg_placetype":"locality",
    "qs_pg:qs_pg_placetype_gp":"Town",
    "qs_pg:woe_adm0":23424975,
    "woe:adm0_id":23424975,
    "woe:name_adm0":"United Kingdom",
    "woe:name_adm1":"England",
    "woe:placetype":"Town",
    "wof:name":"West Bay",
    "wof:placetype":"neighbourhood"
},
  "geometry": {"coordinates":[-2.762374,50.710591],"type":"Point"}
}