{
  "type": "Feature",
  "properties": {
    "iso:country":"GB",
    "wof:name":"Wellington Hill",
    "wof:placetype":"neighbourhood"
},
  "geometry": {"coordinates":[-1.46974294986417,53.83804971699996],"type":"Point"}
}