{
  "type": "Feature",
  "properties": {
    "iso:country":"GB",
    "name:eng_x_preferred":[
        "Jersey Marine"
    ],
    "name:fra_x_preferred":[
        "Jersey Marine"
    ],
    "name:nld_x_preferred":[
        "Jersey Marine"
    ],
    "qs_pg:aaroncc":"GB",
    "qs_pg:name":"Jersey Marine",
    "qs_pg:name_adm0":"United Kingdom",
    "qs_pg:name_adm1":"Wales",
    "qs_pg:photos":98,
    "qs_pg:photos_1k":20,
    "qs_pg:photos_9k":1,
    "qs_pg:photos_9r":3,
    "qs_pg:photos_all":98,
    "qs_pg:photos_sr":3,
    "qs_pg:pop_sr":0,
    "qs_pg:qs_pg_placetype":"locality",
    "qs_pg:qs_pg_placetype_gp":"Town",
    "qs_pg:woe_adm0":23424975,
    "woe:adm0_id":23424975,
    "woe:name_adm0":"United Kingdom",
    "woe:name_adm1":"Wales",
    "woe:placetype":"Town",
    "wof:name":"Jersey Marine",
    "wof:placetype":"neighbourhood"
},
  "geometry": {"coordinates":[-3.861222,51.632962],"type":"Point"}
}