{
  "type": "Feature",
  "properties": {
    "gn:admin1_code":"ENG",
    "gn:admin2_code":"N7",
    "gn:admin3_code":"43UL",
    "gn:admin4_code":"43UL011",
    "gn:asciiname":"Spreakley",
    "gn:country_code":"GB",
    "gn:dem":63,
    "gn:feature_class":"P",
    "gn:feature_code":"PPL",
    "gn:name":"Spreakley",
    "gn:population":0,
    "gn:timezone":"Europe/London",
    "iso:country":"GB",
    "wof:name":"Spreakley",
    "wof:placetype":"neighbourhood"
},
  "geometry": {"coordinates":[-0.80187,51.17192],"type":"Point"}
}