{
  "type": "Feature",
  "properties": {
    "iso:country":"GB",
    "name:azb_x_preferred":[
        "\u0627\u0644\u062f\u062a\u0631\u0627\u0641\u0648\u0631\u062f"
    ],
    "name:deu_x_preferred":[
        "Old Trafford"
    ],
    "name:eng_x_preferred":[
        "Old Trafford"
    ],
    "name:fas_x_preferred":[
        "\u0627\u0644\u062f\u062a\u0631\u0627\u0641\u0648\u0631\u062f"
    ],
    "name:jpn_x_preferred":[
        "\u30aa\u30fc\u30eb\u30c9\u30fb\u30c8\u30e9\u30d5\u30a9\u30fc\u30c9"
    ],
    "name:nld_x_preferred":[
        "Old Trafford"
    ],
    "name:urd_x_preferred":[
        "\u0627\u0648\u0644\u0688 \u0679\u0631\u06cc\u0641\u0631\u0688"
    ],
    "qs:gn_fcode":"PPLX",
    "qs:gn_local":0,
    "qs:gn_namadm1":"ENG",
    "qs:gn_name":"Old Trafford",
    "qs:local_max":2766,
    "qs:local_sum":4268,
    "qs:localhoods":3,
    "qs:name":"Old Trafford",
    "qs:name_adm0":"United Kingdom",
    "qs:name_adm1":"England",
    "qs:name_adm2":"Greater Manchester",
    "qs:name_lau":"Manchester City",
    "qs:name_local":"Stretford",
    "qs:photo_max":568,
    "qs:photo_sum":1423,
    "qs:placetype":"Suburb",
    "qs:quad_count":40,
    "qs:woe_adm0":23424975,
    "qs:woe_adm1":24554868,
    "qs:woe_adm2":12602158,
    "qs:woe_lau":12695841,
    "qs:woe_local":36479,
    "qs:woe_ver":"7.10.0",
    "wof:lang":[
        "eng"
    ],
    "wof:name":"Old Trafford",
    "wof:placetype":"neighbourhood"
},
  "geometry": {"coordinates":[-2.285719,53.459961],"type":"Point"}
}