{
  "type": "Feature",
  "properties": {
    "iso:country":"GB",
    "name:eng_x_preferred":[
        "Old Trafford"
    ],
    "name:unk_x_variant":[
        "Old Trafford"
    ],
    "qs:gn_fcode":"PPLX",
    "qs:gn_local":0,
    "qs:gn_namadm1":"ENG",
    "qs:gn_name":"Old Trafford",
    "qs:local_max":2766,
    "qs:local_sum":4268,
    "qs:localhoods":3,
    "qs:name":"Old Trafford",
    "qs:name_adm0":"United Kingdom",
    "qs:name_adm1":"England",
    "qs:name_adm2":"Greater Manchester",
    "qs:name_lau":"Manchester City",
    "qs:name_local":"Stretford",
    "qs:photo_max":568,
    "qs:photo_sum":1423,
    "qs:placetype":"Suburb",
    "qs:quad_count":40,
    "qs:woe_adm0":23424975,
    "qs:woe_adm1":24554868,
    "qs:woe_adm2":12602158,
    "qs:woe_lau":12695841,
    "qs:woe_local":36479,
    "qs:woe_ver":"7.10.0",
    "wof:lang":[
        "eng"
    ],
    "wof:name":"Old Trafford",
    "wof:placetype":"neighbourhood"
},
  "geometry": {"coordinates":[-2.285719,53.459961],"type":"Point"}
}