{
  "type": "Feature",
  "properties": {
    "gn:admin1_code":"ENG",
    "gn:admin2_code":"I9",
    "gn:admin3_code":"33UC",
    "gn:admin4_code":"33UC026",
    "gn:asciiname":"Witchingham",
    "gn:country_code":"GB",
    "gn:dem":41,
    "gn:feature_class":"P",
    "gn:feature_code":"PPL",
    "gn:name":"Witchingham",
    "gn:population":0,
    "gn:timezone":"Europe/London",
    "iso:country":"GB",
    "wof:name":"Witchingham",
    "wof:placetype":"neighbourhood"
},
  "geometry": {"coordinates":[1.11667,52.73333],"type":"Point"}
}