{
  "type": "Feature",
  "properties": {
    "gn:admin1_code": "ENG",
    "gn:admin2_code": "H7",
    "gn:admin3_code": "32UH",
    "gn:admin4_code": "32UH113",
    "gn:asciiname": "Toft next Newton",
    "gn:country_code": "GB",
    "gn:dem": 17,
    "gn:feature_class": "P",
    "gn:feature_code": "PPL",
    "gn:name": "Toft next Newton",
    "gn:population": 0,
    "gn:timezone": "Europe/London",
    "iso:country": "GB",
    "name:und_x_variant": [
      "Toft",
      "Toft next Newton"
    ],
    "wof:name": "Toft next Newton",
    "wof:placetype": "neighbourhood"
  },
  "geometry": {"coordinates":[-0.43325,53.3809],"type":"Point"}
}
