{
  "type": "Feature",
  "properties": {
    "gn:country": "GB",
    "gn:fcode": "PPL",
    "gn:population": 0,
    "iso:country": "GB",
    "name:ceb_x_preferred": [
      "Bellanaleck"
    ],
    "name:eng_x_preferred": [
      "Bellanaleck"
    ],
    "name:eus_x_preferred": [
      "Bellanaleck"
    ],
    "name:fra_x_preferred": [
      "Bellanaleck"
    ],
    "name:gle_x_preferred": [
      "Bealach na Leice"
    ],
    "name:ita_x_preferred": [
      "Bellanaleck"
    ],
    "name:msa_x_preferred": [
      "Bellanaleck"
    ],
    "name:nld_x_preferred": [
      "Bellanaleck"
    ],
    "name:pli_x_preferred": [
      "बेल्लानालेच्क"
    ],
    "name:spa_x_preferred": [
      "Bellanaleck"
    ],
    "name:swe_x_preferred": [
      "Bellanaleck"
    ],
    "qs_pg:aaroncc": "GB",
    "qs_pg:gn_country": "GB",
    "qs_pg:gn_fcode": "PPL",
    "qs_pg:gn_pop": 0,
    "qs_pg:name": "Bellanaleck",
    "qs_pg:name_adm0": "United Kingdom",
    "qs_pg:name_adm1": "Northern Ireland",
    "qs_pg:photos": 28,
    "qs_pg:photos_1k": 6,
    "qs_pg:photos_9k": 1,
    "qs_pg:photos_9r": 2,
    "qs_pg:photos_all": 28,
    "qs_pg:photos_sr": 2,
    "qs_pg:pop_sr": 0,
    "qs_pg:qs_pg_placetype": "locality",
    "qs_pg:qs_pg_placetype_gp": "Town",
    "qs_pg:woe_adm0": 23424975,
    "woe:adm0_id": 23424975,
    "woe:name_adm0": "United Kingdom",
    "woe:name_adm1": "Northern Ireland",
    "woe:placetype": "Town",
    "wof:name": "Bellanaleck",
    "wof:placetype": "locality"
  },
  "geometry": {"coordinates":[-7.63333,54.28333],"type":"Point"}
}
