{
  "type": "Feature",
  "properties": {
    "gn:country":"GB",
    "gn:fcode":"PPL",
    "gn:population":12712,
    "iso:country":"GB",
    "name:ang_x_preferred":[
        "\u0112at\u016bn Socn"
    ],
    "name:ara_x_preferred":[
        "\u064a\u062a\u0648\u0646 \u0633\u0643\u0646"
    ],
    "name:arz_x_preferred":[
        "\u064a\u062a\u0648\u0646 \u0633\u0643\u0646"
    ],
    "name:ceb_x_preferred":[
        "Eaton Socon"
    ],
    "name:cym_x_preferred":[
        "Eaton Socon"
    ],
    "name:eng_x_preferred":[
        "Eaton Socon"
    ],
    "name:fas_x_preferred":[
        "\u0627\u06cc\u062a\u0648\u0646 \u0633\u0627\u06a9\u0646"
    ],
    "name:fra_x_preferred":[
        "Eaton Socon"
    ],
    "name:gle_x_preferred":[
        "Eaton Socon"
    ],
    "name:lld_x_preferred":[
        "Eaton Socon"
    ],
    "name:nld_x_preferred":[
        "Eaton Socon"
    ],
    "name:pol_x_preferred":[
        "Eaton Socon"
    ],
    "name:swe_x_preferred":[
        "Eaton Socon"
    ],
    "qs_pg:aaroncc":"GB",
    "qs_pg:gn_country":"GB",
    "qs_pg:gn_fcode":"PPL",
    "qs_pg:gn_pop":12712,
    "qs_pg:name":"Eaton Socon",
    "qs_pg:name_adm0":"United Kingdom",
    "qs_pg:name_adm1":"England",
    "qs_pg:photos":326,
    "qs_pg:photos_1k":66,
    "qs_pg:photos_9k":1,
    "qs_pg:photos_9r":5,
    "qs_pg:photos_all":326,
    "qs_pg:photos_sr":5,
    "qs_pg:pop_sr":6,
    "qs_pg:qs_pg_placetype":"locality",
    "qs_pg:qs_pg_placetype_gp":"Town",
    "qs_pg:woe_adm0":23424975,
    "woe:adm0_id":23424975,
    "woe:name_adm0":"United Kingdom",
    "woe:name_adm1":"England",
    "woe:placetype":"Town",
    "wof:name":"Eaton Socon",
    "wof:placetype":"neighbourhood",
    "wof:population":12712
},
  "geometry": {"coordinates":[-0.28925,52.21752],"type":"Point"}
}