{
  "type": "Feature",
  "properties": {
    "iso:country": "GB",
    "name:cym_x_preferred": [
      "Lower Upham"
    ],
    "name:eng_x_preferred": [
      "Lower Upham"
    ],
    "name:fra_x_preferred": [
      "Lower Upham"
    ],
    "name:nld_x_preferred": [
      "Lower Upham"
    ],
    "name:pol_x_preferred": [
      "Lower Upham"
    ],
    "qs_pg:aaroncc": "GB",
    "qs_pg:name": "Lower Upham",
    "qs_pg:name_adm0": "United Kingdom",
    "qs_pg:name_adm1": "England",
    "qs_pg:photos": 265,
    "qs_pg:photos_1k": 54,
    "qs_pg:photos_9k": 1,
    "qs_pg:photos_9r": 4,
    "qs_pg:photos_all": 265,
    "qs_pg:photos_sr": 5,
    "qs_pg:pop_sr": 0,
    "qs_pg:qs_pg_placetype": "locality",
    "qs_pg:qs_pg_placetype_gp": "Town",
    "qs_pg:woe_adm0": 23424975,
    "woe:adm0_id": 23424975,
    "woe:name_adm0": "United Kingdom",
    "woe:name_adm1": "England",
    "woe:placetype": "Town",
    "wof:name": "Lower Upham",
    "wof:placetype": "neighbourhood"
  },
  "geometry": {"coordinates":[-1.275444,50.984586],"type":"Point"}
}
