{
  "type": "Feature",
  "properties": {
    "gn:admin1_code":"ENG",
    "gn:admin2_code":"J6",
    "gn:admin3_code":"00EM131",
    "gn:asciiname":"Wooperton",
    "gn:country_code":"GB",
    "gn:dem":87,
    "gn:feature_class":"P",
    "gn:feature_code":"PPL",
    "gn:name":"Wooperton",
    "gn:population":0,
    "gn:timezone":"Europe/London",
    "iso:country":"GB",
    "wof:name":"Wooperton",
    "wof:placetype":"neighbourhood"
},
  "geometry": {"coordinates":[-1.93685,55.47668],"type":"Point"}
}