{
  "type": "Feature",
  "properties": {
    "iso:country":"GB",
    "name:ben_x_preferred":[
        "\u0993\u09af\u09bc\u09be\u099f\u09be\u09b0\u09b2\u09c1"
    ],
    "name:eng_x_preferred":[
        "Waterloo"
    ],
    "name:eus_x_preferred":[
        "Waterloo"
    ],
    "name:fra_x_preferred":[
        "Waterloo"
    ],
    "name:nld_x_preferred":[
        "Waterloo"
    ],
    "qs_pg:aaroncc":"GB",
    "qs_pg:name":"Waterloo",
    "qs_pg:name_adm0":"United Kingdom",
    "qs_pg:name_adm1":"Scotland",
    "qs_pg:photos":61,
    "qs_pg:photos_1k":12,
    "qs_pg:photos_9k":1,
    "qs_pg:photos_9r":2,
    "qs_pg:photos_all":61,
    "qs_pg:photos_sr":2,
    "qs_pg:pop_sr":0,
    "qs_pg:qs_pg_placetype":"locality",
    "qs_pg:qs_pg_placetype_gp":"Town",
    "qs_pg:woe_adm0":23424975,
    "woe:adm0_id":23424975,
    "woe:name_adm0":"United Kingdom",
    "woe:name_adm1":"Scotland",
    "woe:placetype":"Town",
    "wof:name":"Waterloo",
    "wof:placetype":"locality"
},
  "geometry": {"coordinates":[-3.543477,56.530903],"type":"Point"}
}