{
  "type": "Feature",
  "properties": {
    "gn:country": "GB",
    "gn:fcode": "PPL",
    "gn:population": 0,
    "iso:country": "GB",
    "name:ben_x_preferred": [
      "ওয়েলডন"
    ],
    "name:ceb_x_preferred": [
      "Weldon"
    ],
    "name:cym_x_preferred": [
      "Weldon"
    ],
    "name:deu_x_preferred": [
      "Weldon"
    ],
    "name:eng_x_preferred": [
      "Weldon"
    ],
    "name:fas_x_preferred": [
      "ولدون"
    ],
    "name:fra_x_preferred": [
      "Weldon"
    ],
    "name:guj_x_preferred": [
      "વેલ્ડોન"
    ],
    "name:jpn_x_preferred": [
      "ウェルドン"
    ],
    "name:kan_x_preferred": [
      "ವೆಲ್ಡನ್"
    ],
    "name:kor_x_preferred": [
      "웰든"
    ],
    "name:lit_x_preferred": [
      "Veldonas"
    ],
    "name:nld_x_preferred": [
      "Weldon"
    ],
    "name:pol_x_preferred": [
      "Weldon"
    ],
    "name:por_x_preferred": [
      "Weldon"
    ],
    "name:rus_x_preferred": [
      "Уэлдон"
    ],
    "name:spa_x_preferred": [
      "Weldon"
    ],
    "name:swe_x_preferred": [
      "Weldon"
    ],
    "name:swe_x_variant": [
      "Weldon"
    ],
    "name:tam_x_preferred": [
      "வெல்டன்"
    ],
    "name:tel_x_preferred": [
      "వెల్డన్"
    ],
    "name:urd_x_preferred": [
      "ویلدون"
    ],
    "qs_pg:aaroncc": "GB",
    "qs_pg:gn_country": "GB",
    "qs_pg:gn_fcode": "PPL",
    "qs_pg:gn_pop": 0,
    "qs_pg:name": "Elmdon",
    "qs_pg:name_adm0": "United Kingdom",
    "qs_pg:name_adm1": "England",
    "qs_pg:photos": 152,
    "qs_pg:photos_1k": 31,
    "qs_pg:photos_9k": 1,
    "qs_pg:photos_9r": 4,
    "qs_pg:photos_all": 152,
    "qs_pg:photos_sr": 4,
    "qs_pg:pop_sr": 0,
    "qs_pg:qs_pg_placetype": "locality",
    "qs_pg:qs_pg_placetype_gp": "Town",
    "qs_pg:woe_adm0": 23424975,
    "woe:adm0_id": 23424975,
    "woe:name_adm0": "United Kingdom",
    "woe:name_adm1": "England",
    "woe:placetype": "Town",
    "wof:name": "Elmdon",
    "wof:placetype": "neighbourhood"
  },
  "geometry": {"coordinates":[-0.63333,52.48333],"type":"Point"}
}
