{
  "type": "Feature",
  "properties": {
    "gn:gn_country":"GB",
    "gn:gn_fcode":"PPL",
    "gn:gn_pop":0,
    "iso:country":"GB",
    "name:ben_x_preferred":[
        "\u0993\u09af\u09bc\u09c7\u09b2\u09a1\u09a8"
    ],
    "name:cym_x_preferred":[
        "Weldon"
    ],
    "name:deu_x_preferred":[
        "Weldon"
    ],
    "name:eng_x_preferred":[
        "Weldon"
    ],
    "name:fra_x_preferred":[
        "Weldon"
    ],
    "name:guj_x_preferred":[
        "\u0ab5\u0ac7\u0ab2\u0acd\u0aa1\u0acb\u0aa8"
    ],
    "name:jpn_x_preferred":[
        "\u30a6\u30a7\u30eb\u30c9\u30f3"
    ],
    "name:kan_x_preferred":[
        "\u0cb5\u0cc6\u0cb2\u0ccd\u0ca1\u0ca8\u0ccd"
    ],
    "name:kor_x_preferred":[
        "\uc6f0\ub4e0"
    ],
    "name:lit_x_preferred":[
        "Veldonas"
    ],
    "name:nld_x_preferred":[
        "Weldon"
    ],
    "name:pol_x_preferred":[
        "Weldon"
    ],
    "name:por_x_preferred":[
        "Weldon"
    ],
    "name:rus_x_preferred":[
        "\u0423\u044d\u043b\u0434\u043e\u043d"
    ],
    "name:spa_x_preferred":[
        "Weldon"
    ],
    "name:swe_x_preferred":[
        "Weldon "
    ],
    "name:tam_x_preferred":[
        "\u0bb5\u0bc6\u0bb2\u0bcd\u0b9f\u0ba9\u0bcd"
    ],
    "name:tel_x_preferred":[
        "\u0c35\u0c46\u0c32\u0c4d\u0c21\u0c28\u0c4d"
    ],
    "name:unk_x_variant":[
        "Weldon"
    ],
    "name:urd_x_preferred":[
        "\u0648\u06cc\u0644\u062f\u0648\u0646"
    ],
    "qs_pg:aaroncc":"GB",
    "qs_pg:gn_country":"GB",
    "qs_pg:gn_fcode":"PPL",
    "qs_pg:gn_pop":0,
    "qs_pg:name":"Elmdon",
    "qs_pg:name_adm0":"United Kingdom",
    "qs_pg:name_adm1":"England",
    "qs_pg:photos":152,
    "qs_pg:photos_1k":31,
    "qs_pg:photos_9k":1,
    "qs_pg:photos_9r":4,
    "qs_pg:photos_all":152,
    "qs_pg:photos_sr":4,
    "qs_pg:pop_sr":0,
    "qs_pg:qs_pg_placetype":"locality",
    "qs_pg:qs_pg_placetype_gp":"Town",
    "qs_pg:woe_adm0":23424975,
    "woe:adm0_id":23424975,
    "woe:name_adm0":"United Kingdom",
    "woe:name_adm1":"England",
    "woe:placetype":"Town",
    "wof:name":"Elmdon",
    "wof:placetype":"neighbourhood"
},
  "geometry": {"coordinates":[-0.63333,52.48333],"type":"Point"}
}