{
  "type": "Feature",
  "properties": {
    "iso:country": "GB",
    "name:ben_x_preferred": [
      "স্প্রোসটন"
    ],
    "name:ceb_x_preferred": [
      "Sprowston"
    ],
    "name:cym_x_preferred": [
      "Sprowston"
    ],
    "name:deu_x_preferred": [
      "Sprowston"
    ],
    "name:eng_x_preferred": [
      "New Sprowston"
    ],
    "name:eng_x_variant": [
      "Sprowston"
    ],
    "name:fas_x_preferred": [
      "اسپروزتون"
    ],
    "name:fra_x_preferred": [
      "Sprowston"
    ],
    "name:guj_x_preferred": [
      "સ્પ્રોવસ્ટન"
    ],
    "name:ita_x_preferred": [
      "Sprowston"
    ],
    "name:jpn_x_preferred": [
      "スプロ―ストン"
    ],
    "name:kan_x_preferred": [
      "ಸ್ಪ್ರೋಸ್ಟನ್"
    ],
    "name:kor_x_preferred": [
      "스프로스톤"
    ],
    "name:lit_x_preferred": [
      "Spraustonas"
    ],
    "name:nld_x_preferred": [
      "Sprowston"
    ],
    "name:nob_x_preferred": [
      "Sprowston"
    ],
    "name:nor_x_preferred": [
      "Sprowston"
    ],
    "name:pol_x_preferred": [
      "Sprowston"
    ],
    "name:por_x_preferred": [
      "Sprowston"
    ],
    "name:rus_x_preferred": [
      "Спраустон"
    ],
    "name:spa_x_preferred": [
      "Sprowston"
    ],
    "name:swe_x_preferred": [
      "Sprowston"
    ],
    "name:tam_x_preferred": [
      "ஸ்பிரோவ்ஸ்டன்"
    ],
    "name:tel_x_preferred": [
      "స్ప్రోస్టన్"
    ],
    "name:urd_x_preferred": [
      "سپرووسٹن"
    ],
    "qs:gn_adm0_cc": "GB",
    "qs:gn_local": 2641181,
    "qs:gn_nam_loc": "Norwich, Norwich, Norfolk, England, GB",
    "qs:gn_namadm1": "ENG",
    "qs:local_max": 5858,
    "qs:local_sum": 22582,
    "qs:localhoods": 10,
    "qs:name": "New Sprowston",
    "qs:name_adm0": "United Kingdom",
    "qs:name_adm1": "England",
    "qs:name_adm2": "Norfolk",
    "qs:name_lau": "Norwich City",
    "qs:name_local": "Norwich",
    "qs:photo_max": 386,
    "qs:photo_sum": 2290,
    "qs:placetype": "Suburb",
    "qs:quad_count": 89,
    "qs:woe_adm0": 23424975,
    "qs:woe_adm1": 24554868,
    "qs:woe_adm2": 12602141,
    "qs:woe_lau": 12696028,
    "qs:woe_local": 30704,
    "qs:woe_ver": "7.10.0",
    "wd:wordcount": 959,
    "wof:lang": [
      "eng"
    ],
    "wof:name": "New Sprowston",
    "wof:placetype": "neighbourhood"
  },
  "geometry": {"coordinates":[1.303096,52.644804],"type":"Point"}
}
