{
  "type": "Feature",
  "properties": {
    "iso:country":"GB",
    "name:ben_x_preferred":[
        "\u09b8\u09cd\u09aa\u09cd\u09b0\u09cb\u09b8\u099f\u09a8"
    ],
    "name:ceb_x_preferred":[
        "Sprowston"
    ],
    "name:cym_x_preferred":[
        "Sprowston"
    ],
    "name:deu_x_preferred":[
        "Sprowston"
    ],
    "name:eng_x_preferred":[
        "New Sprowston"
    ],
    "name:eng_x_variant":[
        "Sprowston"
    ],
    "name:fas_x_preferred":[
        "\u0627\u0633\u067e\u0631\u0648\u0632\u062a\u0648\u0646"
    ],
    "name:fra_x_preferred":[
        "Sprowston"
    ],
    "name:guj_x_preferred":[
        "\u0ab8\u0acd\u0aaa\u0acd\u0ab0\u0acb\u0ab5\u0ab8\u0acd\u0a9f\u0aa8"
    ],
    "name:ita_x_preferred":[
        "Sprowston"
    ],
    "name:jpn_x_preferred":[
        "\u30b9\u30d7\u30ed\u2015\u30b9\u30c8\u30f3"
    ],
    "name:kan_x_preferred":[
        "\u0cb8\u0ccd\u0caa\u0ccd\u0cb0\u0ccb\u0cb8\u0ccd\u0c9f\u0ca8\u0ccd"
    ],
    "name:kor_x_preferred":[
        "\uc2a4\ud504\ub85c\uc2a4\ud1a4"
    ],
    "name:lit_x_preferred":[
        "Spraustonas"
    ],
    "name:nld_x_preferred":[
        "Sprowston"
    ],
    "name:nob_x_preferred":[
        "Sprowston"
    ],
    "name:nor_x_preferred":[
        "Sprowston"
    ],
    "name:pol_x_preferred":[
        "Sprowston"
    ],
    "name:por_x_preferred":[
        "Sprowston"
    ],
    "name:rus_x_preferred":[
        "\u0421\u043f\u0440\u0430\u0443\u0441\u0442\u043e\u043d"
    ],
    "name:spa_x_preferred":[
        "Sprowston"
    ],
    "name:swe_x_preferred":[
        "Sprowston"
    ],
    "name:tam_x_preferred":[
        "\u0bb8\u0bcd\u0baa\u0bbf\u0bb0\u0bcb\u0bb5\u0bcd\u0bb8\u0bcd\u0b9f\u0ba9\u0bcd"
    ],
    "name:tel_x_preferred":[
        "\u0c38\u0c4d\u0c2a\u0c4d\u0c30\u0c4b\u0c38\u0c4d\u0c1f\u0c28\u0c4d"
    ],
    "name:urd_x_preferred":[
        "\u0633\u067e\u0631\u0648\u0648\u0633\u0679\u0646"
    ],
    "qs:gn_adm0_cc":"GB",
    "qs:gn_local":2641181,
    "qs:gn_nam_loc":"Norwich, Norwich, Norfolk, England, GB",
    "qs:gn_namadm1":"ENG",
    "qs:local_max":5858,
    "qs:local_sum":22582,
    "qs:localhoods":10,
    "qs:name":"New Sprowston",
    "qs:name_adm0":"United Kingdom",
    "qs:name_adm1":"England",
    "qs:name_adm2":"Norfolk",
    "qs:name_lau":"Norwich City",
    "qs:name_local":"Norwich",
    "qs:photo_max":386,
    "qs:photo_sum":2290,
    "qs:placetype":"Suburb",
    "qs:quad_count":89,
    "qs:woe_adm0":23424975,
    "qs:woe_adm1":24554868,
    "qs:woe_adm2":12602141,
    "qs:woe_lau":12696028,
    "qs:woe_local":30704,
    "qs:woe_ver":"7.10.0",
    "wd:wordcount":959,
    "wof:lang":[
        "eng"
    ],
    "wof:name":"New Sprowston",
    "wof:placetype":"neighbourhood"
},
  "geometry": {"coordinates":[1.303096,52.644804],"type":"Point"}
}