{
  "type": "Feature",
  "properties": {
    "iso:country":"GB",
    "name:ceb_x_preferred":[
        "Sprowston"
    ],
    "name:cym_x_preferred":[
        "Sprowston"
    ],
    "name:eng_x_preferred":[
        "New Sprowston"
    ],
    "name:nld_x_preferred":[
        "Sprowston"
    ],
    "name:nor_x_preferred":[
        "Sprowston"
    ],
    "name:pol_x_preferred":[
        "Sprowston"
    ],
    "name:swe_x_preferred":[
        "Sprowston"
    ],
    "name:unk_x_variant":[
        "New Sprowston"
    ],
    "qs:gn_adm0_cc":"GB",
    "qs:gn_local":2641181,
    "qs:gn_nam_loc":"Norwich, Norwich, Norfolk, England, GB",
    "qs:gn_namadm1":"ENG",
    "qs:local_max":5858,
    "qs:local_sum":22582,
    "qs:localhoods":10,
    "qs:name":"New Sprowston",
    "qs:name_adm0":"United Kingdom",
    "qs:name_adm1":"England",
    "qs:name_adm2":"Norfolk",
    "qs:name_lau":"Norwich City",
    "qs:name_local":"Norwich",
    "qs:photo_max":386,
    "qs:photo_sum":2290,
    "qs:placetype":"Suburb",
    "qs:quad_count":89,
    "qs:woe_adm0":23424975,
    "qs:woe_adm1":24554868,
    "qs:woe_adm2":12602141,
    "qs:woe_lau":12696028,
    "qs:woe_local":30704,
    "qs:woe_ver":"7.10.0",
    "wd:wordcount":959,
    "wof:lang":[
        "eng"
    ],
    "wof:name":"New Sprowston",
    "wof:placetype":"neighbourhood"
},
  "geometry": {"coordinates":[1.303096,52.644804],"type":"Point"}
}