{
  "type": "Feature",
  "properties": {
    "iso:country":"GB",
    "name:eng_x_preferred":[
        "Strathtay"
    ],
    "name:eus_x_preferred":[
        "Strathtay"
    ],
    "name:fra_x_preferred":[
        "Strathtay"
    ],
    "name:gle_x_preferred":[
        "Srath Tatha"
    ],
    "name:nld_x_preferred":[
        "Strathtay"
    ],
    "qs_pg:aaroncc":"GB",
    "qs_pg:name":"Strathtay",
    "qs_pg:name_adm0":"United Kingdom",
    "qs_pg:name_adm1":"Scotland",
    "qs_pg:photos":19,
    "qs_pg:photos_1k":4,
    "qs_pg:photos_9k":1,
    "qs_pg:photos_9r":1,
    "qs_pg:photos_all":19,
    "qs_pg:photos_sr":1,
    "qs_pg:pop_sr":0,
    "qs_pg:qs_pg_placetype":"locality",
    "qs_pg:qs_pg_placetype_gp":"Town",
    "qs_pg:woe_adm0":23424975,
    "woe:adm0_id":23424975,
    "woe:name_adm0":"United Kingdom",
    "woe:name_adm1":"Scotland",
    "woe:placetype":"Town",
    "wof:name":"Strathtay",
    "wof:placetype":"locality"
},
  "geometry": {"coordinates":[-3.77479,56.661156],"type":"Point"}
}