{
  "type": "Feature",
  "properties": {
    "gn:admin1_code": "ENG",
    "gn:admin2_code": "P6",
    "gn:admin3_code": "45UD",
    "gn:admin4_code": "45UD025",
    "gn:asciiname": "Coates",
    "gn:country_code": "GB",
    "gn:dem": 21,
    "gn:feature_class": "P",
    "gn:feature_code": "PPL",
    "gn:name": "Coates",
    "gn:population": 0,
    "gn:timezone": "Europe/London",
    "iso:country": "GB",
    "name:ceb_x_preferred": [
      "Coates"
    ],
    "name:deu_x_preferred": [
      "Coates"
    ],
    "name:fra_x_preferred": [
      "Coates"
    ],
    "name:heb_x_preferred": [
      "קואטס"
    ],
    "name:ita_x_preferred": [
      "Coates"
    ],
    "name:nld_x_preferred": [
      "Coates"
    ],
    "name:pol_x_preferred": [
      "Coates"
    ],
    "name:por_x_preferred": [
      "Coates"
    ],
    "name:spa_x_preferred": [
      "Coates"
    ],
    "name:swe_x_preferred": [
      "Coates"
    ],
    "wof:name": "Coates",
    "wof:placetype": "neighbourhood"
  },
  "geometry": {"coordinates":[-0.58189,50.9507],"type":"Point"}
}
