{
  "type": "Feature",
  "properties": {
    "gn:gn_country":"GB",
    "gn:gn_fcode":"PPL",
    "gn:gn_pop":0,
    "iso:country":"GB",
    "name:deu_x_preferred":[
        "Cromdale"
    ],
    "name:eng_x_preferred":[
        "Cromdale"
    ],
    "name:eus_x_preferred":[
        "Cromdale"
    ],
    "name:fra_x_preferred":[
        "Cromdale"
    ],
    "name:gla_x_preferred":[
        "Cromdhail"
    ],
    "name:nld_x_preferred":[
        "Cromdale"
    ],
    "qs_pg:aaroncc":"GB",
    "qs_pg:gn_country":"GB",
    "qs_pg:gn_fcode":"PPL",
    "qs_pg:gn_pop":0,
    "qs_pg:name":"Cromdale",
    "qs_pg:name_adm0":"United Kingdom",
    "qs_pg:name_adm1":"Scotland",
    "qs_pg:photos":59,
    "qs_pg:photos_1k":12,
    "qs_pg:photos_9k":1,
    "qs_pg:photos_9r":2,
    "qs_pg:photos_all":59,
    "qs_pg:photos_sr":2,
    "qs_pg:pop_sr":0,
    "qs_pg:qs_pg_placetype":"locality",
    "qs_pg:qs_pg_placetype_gp":"Town",
    "qs_pg:woe_adm0":23424975,
    "woe:adm0_id":23424975,
    "woe:name_adm0":"United Kingdom",
    "woe:name_adm1":"Scotland",
    "woe:placetype":"Town",
    "wof:name":"Cromdale",
    "wof:placetype":"locality"
},
  "geometry": {"coordinates":[-3.53831,57.3376],"type":"Point"}
}