{
  "type": "Feature",
  "properties": {
    "gn:country":"GB",
    "gn:fcode":"PPL",
    "gn:population":0,
    "iso:country":"GB",
    "name:ceb_x_preferred":[
        "Scarrington"
    ],
    "name:eng_x_preferred":[
        "Scarrington"
    ],
    "name:fra_x_preferred":[
        "Scarrington"
    ],
    "name:gle_x_preferred":[
        "Scarrington"
    ],
    "name:jpn_x_preferred":[
        "\u30b9\u30ab\u30fc\u30ea\u30f3\u30c8\u30f3"
    ],
    "name:lld_x_preferred":[
        "Scarrington"
    ],
    "name:nan_x_preferred":[
        "Scarrington"
    ],
    "name:nld_x_preferred":[
        "Scarrington"
    ],
    "name:pol_x_preferred":[
        "Scarrington"
    ],
    "name:swe_x_preferred":[
        "Scarrington"
    ],
    "name:tur_x_preferred":[
        "Scarrington"
    ],
    "qs_pg:aaroncc":"GB",
    "qs_pg:gn_country":"GB",
    "qs_pg:gn_fcode":"PPL",
    "qs_pg:gn_pop":0,
    "qs_pg:name":"Darrington",
    "qs_pg:name_adm0":"United Kingdom",
    "qs_pg:name_adm1":"England",
    "qs_pg:photos":67,
    "qs_pg:photos_1k":14,
    "qs_pg:photos_9k":1,
    "qs_pg:photos_9r":2,
    "qs_pg:photos_all":67,
    "qs_pg:photos_sr":2,
    "qs_pg:pop_sr":0,
    "qs_pg:qs_pg_placetype":"locality",
    "qs_pg:qs_pg_placetype_gp":"Town",
    "qs_pg:woe_adm0":23424975,
    "woe:adm0_id":23424975,
    "woe:name_adm0":"United Kingdom",
    "woe:name_adm1":"England",
    "woe:placetype":"Town",
    "wof:name":"Darrington",
    "wof:placetype":"neighbourhood"
},
  "geometry": {"coordinates":[-0.90697,52.96748],"type":"Point"}
}