{
  "type": "Feature",
  "properties": {
    "gn:admin1_code": "SCT",
    "gn:admin2_code": "T7",
    "gn:asciiname": "Dubton",
    "gn:country_code": "GB",
    "gn:dem": 18,
    "gn:feature_class": "P",
    "gn:feature_code": "PPL",
    "gn:name": "Dubton",
    "gn:population": 0,
    "gn:timezone": "Europe/London",
    "iso:country": "GB",
    "wof:name": "Dubton",
    "wof:placetype": "locality"
  },
  "geometry": {"coordinates":[-2.48675,56.73628000000001],"type":"Point"}
}
