{
  "type": "Feature",
  "properties": {
    "gn:admin1_code":"SCT",
    "gn:admin2_code":"V3",
    "gn:asciiname":"Uags",
    "gn:country_code":"GB",
    "gn:dem":59,
    "gn:feature_class":"P",
    "gn:feature_code":"PPL",
    "gn:name":"Uags",
    "gn:population":0,
    "gn:timezone":"Europe/London",
    "iso:country":"GB",
    "wof:name":"Uags",
    "wof:placetype":"locality"
},
  "geometry": {"coordinates":[-5.78333,57.35],"type":"Point"}
}