{
  "type": "Feature",
  "properties": {
    "gn:country":"GB",
    "gn:fcode":"PPL",
    "gn:population":0,
    "iso:country":"GB",
    "name:ara_x_preferred":[
        "\u0637\u0627\u0644\u0645\u064a\u0646"
    ],
    "name:azb_x_preferred":[
        "\u0637\u0627\u0644\u0645\u06cc\u0646"
    ],
    "name:deu_x_preferred":[
        "Talmine"
    ],
    "name:fas_x_preferred":[
        "\u0637\u0627\u0644\u0645\u06cc\u0646"
    ],
    "name:fra_x_preferred":[
        "Talmine"
    ],
    "name:ita_x_preferred":[
        "Talmine"
    ],
    "name:kab_x_preferred":[
        "Talmin"
    ],
    "name:msa_x_preferred":[
        "Talmin"
    ],
    "name:por_x_preferred":[
        "Talmine"
    ],
    "name:ron_x_preferred":[
        "Talmine"
    ],
    "name:rus_x_preferred":[
        "\u0422\u0430\u043b\u044c\u043c\u0438\u043d"
    ],
    "name:spa_x_preferred":[
        "Talmine"
    ],
    "name:urd_x_preferred":[
        "\u0637\u0627\u0644\u0645\u06cc\u0646"
    ],
    "name:vie_x_preferred":[
        "Talmine"
    ],
    "qs_pg:aaroncc":"GB",
    "qs_pg:gn_country":"GB",
    "qs_pg:gn_fcode":"PPL",
    "qs_pg:gn_pop":0,
    "qs_pg:name":"Talmine",
    "qs_pg:name_adm0":"United Kingdom",
    "qs_pg:name_adm1":"Scotland",
    "qs_pg:photos":495,
    "qs_pg:photos_1k":100,
    "qs_pg:photos_9k":2,
    "qs_pg:photos_9r":5,
    "qs_pg:photos_all":495,
    "qs_pg:photos_sr":7,
    "qs_pg:pop_sr":0,
    "qs_pg:qs_pg_placetype":"locality",
    "qs_pg:qs_pg_placetype_gp":"Town",
    "qs_pg:woe_adm0":23424975,
    "woe:adm0_id":23424975,
    "woe:name_adm0":"United Kingdom",
    "woe:name_adm1":"Scotland",
    "woe:placetype":"Town",
    "wof:name":"Talmine",
    "wof:placetype":"locality"
},
  "geometry": {"coordinates":[-4.43168,58.52755],"type":"Point"}
}