{
  "type": "Feature",
  "properties": {
    "gn:admin1_code": "NIR",
    "gn:admin2_code": "N09000010",
    "gn:asciiname": "Ardarragh",
    "gn:cc2": "GB",
    "gn:country_code": "GB",
    "gn:dem": 84,
    "gn:feature_class": "P",
    "gn:feature_code": "PPL",
    "gn:name": "Ardarragh",
    "gn:population": 0,
    "gn:timezone": "Europe/London",
    "iso:country": "GB",
    "name:und_x_variant": [
      "Ardaragh",
      "Ardarragh"
    ],
    "wof:name": "Ardarragh",
    "wof:placetype": "locality"
  },
  "geometry": {"coordinates":[-6.26667,54.23333],"type":"Point"}
}
