{
  "type": "Feature",
  "properties": {
    "gn:country":"GB",
    "gn:fcode":"PPL",
    "gn:population":5375,
    "iso:country":"GB",
    "name:ben_x_preferred":[
        "\u09a1\u09be\u0987\u099a"
    ],
    "name:ceb_x_preferred":[
        "Dyce"
    ],
    "name:deu_x_preferred":[
        "Dyce"
    ],
    "name:eng_x_preferred":[
        "Dyce"
    ],
    "name:eus_x_preferred":[
        "Dyce"
    ],
    "name:fra_x_preferred":[
        "Dyce"
    ],
    "name:gla_x_preferred":[
        "Deis"
    ],
    "name:gle_x_preferred":[
        "Deis"
    ],
    "name:guj_x_preferred":[
        "\u0aa1\u0abe\u0a88\u0ab8"
    ],
    "name:jpn_x_preferred":[
        "\u30c0\u30a4\u30b9"
    ],
    "name:kan_x_preferred":[
        "\u0ca1\u0cc8\u0cb8\u0ccd"
    ],
    "name:kor_x_preferred":[
        "\ub2e4\uc774\uc2a4"
    ],
    "name:lit_x_preferred":[
        "Daisas"
    ],
    "name:nld_x_preferred":[
        "Dyce"
    ],
    "name:por_x_preferred":[
        "Dyce"
    ],
    "name:rus_x_preferred":[
        "\u0414\u0430\u0439\u0441"
    ],
    "name:sco_x_preferred":[
        "Dyce"
    ],
    "name:spa_x_preferred":[
        "Dyce"
    ],
    "name:swe_x_preferred":[
        "Dyce"
    ],
    "name:tam_x_preferred":[
        "\u0b9f\u0bcd\u0baf\u0bb8\u0bcd"
    ],
    "name:tel_x_preferred":[
        "\u0c21\u0c48\u0c38\u0c4d"
    ],
    "name:urd_x_preferred":[
        "\u062f\u06cc\u06a9\u06cc"
    ],
    "qs_pg:aaroncc":"GB",
    "qs_pg:gn_country":"GB",
    "qs_pg:gn_fcode":"PPL",
    "qs_pg:gn_pop":5375,
    "qs_pg:name":"Dyce",
    "qs_pg:name_adm0":"United Kingdom",
    "qs_pg:name_adm1":"Scotland",
    "qs_pg:photos":352,
    "qs_pg:photos_1k":71,
    "qs_pg:photos_9k":2,
    "qs_pg:photos_9r":5,
    "qs_pg:photos_all":352,
    "qs_pg:photos_sr":6,
    "qs_pg:pop_sr":5,
    "qs_pg:qs_pg_placetype":"locality",
    "qs_pg:qs_pg_placetype_gp":"Town",
    "qs_pg:woe_adm0":23424975,
    "woe:adm0_id":23424975,
    "woe:name_adm0":"United Kingdom",
    "woe:name_adm1":"Scotland",
    "woe:placetype":"Town",
    "wof:name":"Dyce",
    "wof:placetype":"locality",
    "wof:population":5730
},
  "geometry": {"coordinates":[-2.17676,57.20522],"type":"Point"}
}