{
  "type": "Feature",
  "properties": {
    "iso:country":"GB",
    "name:bul_x_preferred":[
        "\u0414\u0443\u043d\u0430\u043c\u0430\u043d\u0430\u0433\u0445"
    ],
    "name:ceb_x_preferred":[
        "Dunnamanagh"
    ],
    "name:eng_x_preferred":[
        "Donemana"
    ],
    "name:eus_x_preferred":[
        "Donemana"
    ],
    "name:fra_x_preferred":[
        "Donemana"
    ],
    "name:gle_x_preferred":[
        "D\u00fan na Manach"
    ],
    "name:jpn_x_preferred":[
        "\u30c6\u30a3\u30ed\u30f3\u5dde"
    ],
    "name:msa_x_preferred":[
        "Donemana"
    ],
    "name:nld_x_preferred":[
        "Donemana"
    ],
    "name:pli_x_preferred":[
        "\u0926\u094b\u0928\u0947\u092e\u093e\u0928\u093e"
    ],
    "name:spa_x_preferred":[
        "Donemana"
    ],
    "name:swe_x_preferred":[
        "Dunnamanagh"
    ],
    "qs_pg:aaroncc":"GB",
    "qs_pg:name":"Donemana",
    "qs_pg:name_adm0":"United Kingdom",
    "qs_pg:name_adm1":"Northern Ireland",
    "qs_pg:photos":14,
    "qs_pg:photos_1k":3,
    "qs_pg:photos_9k":1,
    "qs_pg:photos_9r":1,
    "qs_pg:photos_all":14,
    "qs_pg:photos_sr":1,
    "qs_pg:pop_sr":0,
    "qs_pg:qs_pg_placetype":"locality",
    "qs_pg:qs_pg_placetype_gp":"Town",
    "qs_pg:woe_adm0":23424975,
    "woe:adm0_id":23424975,
    "woe:name_adm0":"United Kingdom",
    "woe:name_adm1":"Northern Ireland",
    "woe:placetype":"Town",
    "wof:name":"Donemana",
    "wof:placetype":"locality"
},
  "geometry": {"coordinates":[-7.3054355,54.875359],"type":"Point"}
}