{
  "type": "Feature",
  "properties": {
    "iso:country":"GB",
    "name:bul_x_preferred":[
        "\u0410\u043c\u0435\u0440\u0442\u044a\u043d"
    ],
    "name:eng_x_preferred":[
        "Amerton"
    ],
    "name:fra_x_preferred":[
        "Amerton"
    ],
    "name:nld_x_preferred":[
        "Amerton"
    ],
    "name:pol_x_preferred":[
        "Amerton"
    ],
    "qs_pg:aaroncc":"GB",
    "qs_pg:name":"Amerton",
    "qs_pg:name_adm0":"United Kingdom",
    "qs_pg:name_adm1":"England",
    "qs_pg:photos":217,
    "qs_pg:photos_1k":44,
    "qs_pg:photos_9k":1,
    "qs_pg:photos_9r":4,
    "qs_pg:photos_all":217,
    "qs_pg:photos_sr":4,
    "qs_pg:pop_sr":0,
    "qs_pg:qs_pg_placetype":"locality",
    "qs_pg:qs_pg_placetype_gp":"Town",
    "qs_pg:woe_adm0":23424975,
    "woe:adm0_id":23424975,
    "woe:name_adm0":"United Kingdom",
    "woe:name_adm1":"England",
    "woe:placetype":"Town",
    "wof:name":"Amerton",
    "wof:placetype":"neighbourhood"
},
  "geometry": {"coordinates":[-2.009768,52.847026],"type":"Point"}
}