{
  "type": "Feature",
  "properties": {
    "gn:admin1_code": "SCT",
    "gn:admin2_code": "T8",
    "gn:asciiname": "Edendonich",
    "gn:country_code": "GB",
    "gn:dem": 102,
    "gn:feature_class": "P",
    "gn:feature_code": "PPL",
    "gn:name": "Edendonich",
    "gn:population": 0,
    "gn:timezone": "Europe/London",
    "iso:country": "GB",
    "wof:name": "Edendonich",
    "wof:placetype": "locality"
  },
  "geometry": {"coordinates":[-4.97659,56.41036],"type":"Point"}
}
