{
  "type": "Feature",
  "properties": {
    "gn:country":"GB",
    "gn:fcode":"PPL",
    "gn:population":0,
    "iso:country":"GB",
    "name:aze_x_preferred":[
        "Qiqqlsvik"
    ],
    "name:ceb_x_preferred":[
        "Giggleswick"
    ],
    "name:eng_x_preferred":[
        "Giggleswick"
    ],
    "name:fra_x_preferred":[
        "Giggleswick"
    ],
    "name:gle_x_preferred":[
        "Giggleswick"
    ],
    "name:jpn_x_preferred":[
        "\u30b8\u30b0\u30eb\u30b9\u30a6\u30a3\u30c3\u30af"
    ],
    "name:lld_x_preferred":[
        "Giggleswick"
    ],
    "name:nld_x_preferred":[
        "Giggleswick"
    ],
    "name:pol_x_preferred":[
        "Giggleswick"
    ],
    "name:rus_x_preferred":[
        "\u0413\u0438\u0433\u0433\u043b\u0441\u0432\u0438\u043a"
    ],
    "name:swe_x_preferred":[
        "Giggleswick"
    ],
    "name:tur_x_preferred":[
        "Giggleswick"
    ],
    "name:zho_x_preferred":[
        "\u5409\u683c\u723e\u65af\u5a01\u514b"
    ],
    "qs_pg:aaroncc":"GB",
    "qs_pg:gn_country":"GB",
    "qs_pg:gn_fcode":"PPL",
    "qs_pg:gn_pop":0,
    "qs_pg:name":"Muggleswick",
    "qs_pg:name_adm0":"United Kingdom",
    "qs_pg:name_adm1":"England",
    "qs_pg:photos":44,
    "qs_pg:photos_1k":9,
    "qs_pg:photos_9k":1,
    "qs_pg:photos_9r":2,
    "qs_pg:photos_all":44,
    "qs_pg:photos_sr":2,
    "qs_pg:pop_sr":0,
    "qs_pg:qs_pg_placetype":"locality",
    "qs_pg:qs_pg_placetype_gp":"Town",
    "qs_pg:woe_adm0":23424975,
    "woe:adm0_id":23424975,
    "woe:name_adm0":"United Kingdom",
    "woe:name_adm1":"England",
    "woe:placetype":"Town",
    "wof:name":"Muggleswick",
    "wof:placetype":"neighbourhood"
},
  "geometry": {"coordinates":[-2.28848,54.07195],"type":"Point"}
}