{
  "type": "Feature",
  "properties": {
    "iso:country":"GB",
    "name:cym_x_preferred":[
        "South Oxhey"
    ],
    "name:eng_x_preferred":[
        "South Oxhey"
    ],
    "name:eng_x_variant":[
        "S Oxhey",
        "South Oxney"
    ],
    "name:fas_x_preferred":[
        "\u0633\u0627\u0648\u062a \u0622\u06a9\u0633\u06cc"
    ],
    "name:fra_x_preferred":[
        "South Oxhey"
    ],
    "name:gle_x_preferred":[
        "South Oxhey"
    ],
    "name:ita_x_preferred":[
        "South Oxhey"
    ],
    "name:jpn_x_preferred":[
        "\u30b5\u30a6\u30b9\u30aa\u30ad\u30b7\u30fc"
    ],
    "name:nld_x_preferred":[
        "South Oxhey"
    ],
    "name:pol_x_preferred":[
        "South Oxhey"
    ],
    "name:vol_x_preferred":[
        "South Oxhey"
    ],
    "qs:gn_adm0_cc":"GB",
    "qs:gn_fcode":"PPLX",
    "qs:gn_local":2635925,
    "qs:gn_nam_loc":"Three Rivers, Hertfordshire, England, GB",
    "qs:gn_namadm1":"ENG",
    "qs:gn_name":"South Oxney",
    "qs:local_max":451,
    "qs:local_sum":697,
    "qs:localhoods":3,
    "qs:name":"South Oxhey",
    "qs:name_adm0":"United Kingdom",
    "qs:name_adm1":"England",
    "qs:name_adm2":"Hertfordshire",
    "qs:name_lau":"Three Rivers District",
    "qs:name_local":"Three Rivers District",
    "qs:photo_max":21,
    "qs:photo_sum":126,
    "qs:placetype":"Suburb",
    "qs:quad_count":31,
    "qs:woe_adm0":23424975,
    "qs:woe_adm1":24554868,
    "qs:woe_adm2":12602170,
    "qs:woe_lau":12695982,
    "qs:woe_local":12695982,
    "qs:woe_ver":"7.10.0",
    "wd:wordcount":1485,
    "wof:lang":[
        "eng"
    ],
    "wof:name":"South Oxhey",
    "wof:placetype":"neighbourhood"
},
  "geometry": {"coordinates":[-0.391388,51.627368],"type":"Point"}
}