{
  "type": "Feature",
  "properties": {
    "iso:country":"GB",
    "name:cym_x_preferred":[
        "Canford Cliffs"
    ],
    "name:eng_x_preferred":[
        "Canford Cliffs"
    ],
    "name:pol_x_preferred":[
        "Canford Cliffs"
    ],
    "name:unk_x_variant":[
        "Canford Cliffs"
    ],
    "qs:gn_fcode":"PPL",
    "qs:gn_local":0,
    "qs:gn_namadm1":"ENG",
    "qs:gn_name":"Canford Cliffs",
    "qs:local_max":5072,
    "qs:local_sum":20849,
    "qs:localhoods":9,
    "qs:name":"Canford Cliffs",
    "qs:name_adm0":"United Kingdom",
    "qs:name_adm1":"England",
    "qs:name_adm2":"Dorset",
    "qs:name_lau":"Poole Borough",
    "qs:name_local":"Poole",
    "qs:photo_max":368,
    "qs:photo_sum":5011,
    "qs:placetype":"Suburb",
    "qs:quad_count":201,
    "qs:woe_adm0":23424975,
    "qs:woe_adm1":24554868,
    "qs:woe_adm2":12602183,
    "qs:woe_lau":12696157,
    "qs:woe_local":32326,
    "qs:woe_ver":"7.10.0",
    "wd:wordcount":740,
    "wof:lang":[
        "eng"
    ],
    "wof:name":"Canford Cliffs",
    "wof:placetype":"neighbourhood"
},
  "geometry": {"coordinates":[-1.938745,50.693296],"type":"Point"}
}