{
  "type": "Feature",
  "properties": {
    "iso:country":"GB",
    "wof:name":"Kippax Common",
    "wof:placetype":"neighbourhood"
},
  "geometry": {"coordinates":[-1.38288224942177,53.77540432722297],"type":"Point"}
}