{
  "type": "Feature",
  "properties": {
    "gn:admin1_code":"ENG",
    "gn:admin2_code":"J6",
    "gn:admin3_code":"00EM162",
    "gn:asciiname":"Widdrington",
    "gn:country_code":"GB",
    "gn:dem":17,
    "gn:feature_class":"P",
    "gn:feature_code":"PPL",
    "gn:name":"Widdrington",
    "gn:population":0,
    "gn:timezone":"Europe/London",
    "iso:country":"GB",
    "name:deu_x_preferred":[
        "Widdrington"
    ],
    "name:swe_x_preferred":[
        "Widdrington"
    ],
    "wof:name":"Widdrington",
    "wof:placetype":"neighbourhood"
},
  "geometry": {"coordinates":[-1.58333,55.25],"type":"Point"}
}