{
  "type": "Feature",
  "properties": {
    "gn:admin1_code":"WLS",
    "gn:admin2_code":"Y4",
    "gn:admin3_code":"00PP002",
    "gn:asciiname":"St Bride's Netherwent",
    "gn:country_code":"GB",
    "gn:dem":71,
    "gn:feature_class":"P",
    "gn:feature_code":"PPL",
    "gn:name":"St Bride's Netherwent",
    "gn:population":0,
    "gn:timezone":"Europe/London",
    "iso:country":"GB",
    "wof:name":"St Bride's Netherwent",
    "wof:placetype":"neighbourhood"
},
  "geometry": {"coordinates":[-2.82134,51.60219],"type":"Point"}
}