{
  "type": "Feature",
  "properties": {
    "iso:country":"GB",
    "name:eng_x_preferred":[
        "Oldhall"
    ],
    "name:unk_x_variant":[
        "Oldhall"
    ],
    "qs:gn_local":0,
    "qs:local_max":4949,
    "qs:local_sum":11872,
    "qs:localhoods":6,
    "qs:name":"Oldhall",
    "qs:name_adm0":"United Kingdom",
    "qs:name_adm1":"Scotland",
    "qs:name_adm2":"Strathclyde",
    "qs:name_lau":"Renfrewshire",
    "qs:name_local":"Paisley",
    "qs:photo_max":52,
    "qs:photo_sum":205,
    "qs:placetype":"Suburb",
    "qs:quad_count":15,
    "qs:woe_adm0":23424975,
    "qs:woe_adm1":12578048,
    "qs:woe_adm2":12602207,
    "qs:woe_lau":12696207,
    "qs:woe_local":31342,
    "qs:woe_ver":"7.10.0",
    "wof:lang":[
        "eng"
    ],
    "wof:name":"Oldhall",
    "wof:placetype":"neighbourhood"
},
  "geometry": {"coordinates":[-4.391028,55.847276],"type":"Point"}
}