{
  "type": "Feature",
  "properties": {
    "iso:country":"GB",
    "wof:name":"Rotherham Town Centre",
    "wof:placetype":"neighbourhood"
},
  "geometry": {"coordinates":[-1.35534745704034,53.43235858138247],"type":"Point"}
}