{
  "type": "Feature",
  "properties": {
    "iso:country":"GB",
    "name:ara_x_preferred":[
        "\u0646\u064a\u0648\u0628\u064a"
    ],
    "name:cat_x_preferred":[
        "Noob"
    ],
    "name:ces_x_preferred":[
        "Noob"
    ],
    "name:dan_x_preferred":[
        "Noob"
    ],
    "name:deu_x_preferred":[
        "Neuling"
    ],
    "name:ell_x_preferred":[
        "Noob"
    ],
    "name:fas_x_preferred":[
        "\u0646\u0648\u0628"
    ],
    "name:fin_x_preferred":[
        "Noob"
    ],
    "name:fra_x_preferred":[
        "Newbie"
    ],
    "name:heb_x_preferred":[
        "Noob"
    ],
    "name:hye_x_preferred":[
        "\u0546\u0578\u0582\u0562"
    ],
    "name:ita_x_preferred":[
        "Newbie"
    ],
    "name:jpn_x_preferred":[
        "\u30cb\u30e5\u30fc\u30d3\u30fc"
    ],
    "name:nld_x_preferred":[
        "Newbie"
    ],
    "name:nor_x_preferred":[
        "Newbie"
    ],
    "name:pol_x_preferred":[
        "Newbie"
    ],
    "name:por_x_preferred":[
        "Newbie"
    ],
    "name:spa_x_preferred":[
        "Newbie"
    ],
    "name:tur_x_preferred":[
        "Newbie"
    ],
    "name:ukr_x_preferred":[
        "\u041d\u043e\u0432\u0430\u0447\u043e\u043a"
    ],
    "qs_pg:aaroncc":"GB",
    "qs_pg:name":"Newbie",
    "qs_pg:name_adm0":"United Kingdom",
    "qs_pg:name_adm1":"Scotland",
    "qs_pg:photos":9,
    "qs_pg:photos_1k":2,
    "qs_pg:photos_9k":1,
    "qs_pg:photos_9r":1,
    "qs_pg:photos_all":9,
    "qs_pg:photos_sr":1,
    "qs_pg:pop_sr":0,
    "qs_pg:qs_pg_placetype":"locality",
    "qs_pg:qs_pg_placetype_gp":"Town",
    "qs_pg:woe_adm0":23424975,
    "woe:adm0_id":23424975,
    "woe:name_adm0":"United Kingdom",
    "woe:name_adm1":"Scotland",
    "woe:placetype":"Town",
    "wof:name":"Newbie",
    "wof:placetype":"locality"
},
  "geometry": {"coordinates":[-3.28062,54.974358],"type":"Point"}
}