{
  "type": "Feature",
  "properties": {
    "iso:country":"GB",
    "name:cym_x_preferred":[
        "Babeny"
    ],
    "name:eng_x_preferred":[
        "Babeny"
    ],
    "name:fra_x_preferred":[
        "Babeny"
    ],
    "name:nld_x_preferred":[
        "Babeny"
    ],
    "qs_pg:aaroncc":"GB",
    "qs_pg:name":"Babeny",
    "qs_pg:name_adm0":"United Kingdom",
    "qs_pg:name_adm1":"England",
    "qs_pg:photos":276,
    "qs_pg:photos_1k":56,
    "qs_pg:photos_9k":1,
    "qs_pg:photos_9r":4,
    "qs_pg:photos_all":276,
    "qs_pg:photos_sr":5,
    "qs_pg:pop_sr":0,
    "qs_pg:qs_pg_placetype":"locality",
    "qs_pg:qs_pg_placetype_gp":"Town",
    "qs_pg:woe_adm0":23424975,
    "woe:adm0_id":23424975,
    "woe:name_adm0":"United Kingdom",
    "woe:name_adm1":"England",
    "woe:placetype":"Town",
    "wof:name":"Babeny",
    "wof:placetype":"neighbourhood"
},
  "geometry": {"coordinates":[-3.864097,50.550283],"type":"Point"}
}