{
  "type": "Feature",
  "properties": {
    "gn:admin1_code":"NIR",
    "gn:admin2_code":"N09000008",
    "gn:asciiname":"Ballygalley",
    "gn:country_code":"GB",
    "gn:dem":35,
    "gn:feature_class":"P",
    "gn:feature_code":"PPL",
    "gn:name":"Ballygalley",
    "gn:population":0,
    "gn:timezone":"Europe/London",
    "iso:country":"GB",
    "wof:name":"Ballygalley",
    "wof:placetype":"locality"
},
  "geometry": {"coordinates":[-5.8552,54.89547],"type":"Point"}
}