{
  "type": "Feature",
  "properties": {
    "iso:country":"GB",
    "name:eng_x_preferred":[
        "Cinderhall"
    ],
    "name:unk_x_variant":[
        "Cinderhall"
    ],
    "qs:gn_adm0_cc":"GB",
    "qs:gn_local":2652263,
    "qs:gn_nam_loc":"bilston",
    "qs:gn_namadm1":"ENG",
    "qs:local_max":5369,
    "qs:local_sum":43913,
    "qs:localhoods":32,
    "qs:name":"Cinderhall",
    "qs:name_adm0":"United Kingdom",
    "qs:name_adm1":"England",
    "qs:name_adm2":"Nottinghamshire",
    "qs:name_lau":"Nottingham City",
    "qs:name_local":"Nottingham",
    "qs:photo_max":118,
    "qs:photo_sum":246,
    "qs:placetype":"Suburb",
    "qs:quad_count":8,
    "qs:woe_adm0":23424975,
    "qs:woe_adm1":24554868,
    "qs:woe_adm2":12602147,
    "qs:woe_lau":12696180,
    "qs:woe_local":30720,
    "qs:woe_ver":"7.10.0",
    "wof:lang":[
        "eng"
    ],
    "wof:name":"Cinderhall",
    "wof:placetype":"neighbourhood"
},
  "geometry": {"coordinates":[-1.20397,52.989421],"type":"Point"}
}