{
  "type": "Feature",
  "properties": {
    "gn:gn_country":"GB",
    "gn:gn_fcode":"PPL",
    "gn:gn_pop":0,
    "iso:country":"GB",
    "name:dut_x_preferred":[
        "King's Nympton"
    ],
    "name:eng_x_preferred":[
        "King's Nympton"
    ],
    "name:fre_x_preferred":[
        "King's Nympton"
    ],
    "name:lat_x_preferred":[
        "Nymet Regis"
    ],
    "name:pol_x_preferred":[
        "King's Nympton"
    ],
    "name:swe_x_preferred":[
        "King's Nympton"
    ],
    "name:wel_x_preferred":[
        "King's Nympton"
    ],
    "qs_pg:aaroncc":"GB",
    "qs_pg:gn_country":"GB",
    "qs_pg:gn_fcode":"PPL",
    "qs_pg:gn_pop":0,
    "qs_pg:name":"Kings Brompton",
    "qs_pg:name_adm0":"United Kingdom",
    "qs_pg:name_adm1":"England",
    "qs_pg:photos":10,
    "qs_pg:photos_1k":2,
    "qs_pg:photos_9k":1,
    "qs_pg:photos_9r":1,
    "qs_pg:photos_all":10,
    "qs_pg:photos_sr":1,
    "qs_pg:pop_sr":0,
    "qs_pg:qs_pg_placetype":"locality",
    "qs_pg:qs_pg_placetype_gp":"Town",
    "qs_pg:woe_adm0":23424975,
    "woe:adm0_id":23424975,
    "woe:name_adm0":"United Kingdom",
    "woe:name_adm1":"England",
    "woe:placetype":"Town",
    "wof:name":"Kings Brompton",
    "wof:placetype":"neighbourhood"
},
  "geometry": {"coordinates":[-3.88333,50.95],"type":"Point"}
}