{
  "type": "Feature",
  "properties": {
    "gn:population":2170,
    "iso:country":"GB",
    "name:bre_x_preferred":[
        "Kintore"
    ],
    "name:ceb_x_preferred":[
        "Kintore"
    ],
    "name:cym_x_preferred":[
        "Kintore"
    ],
    "name:deu_x_preferred":[
        "Kintore"
    ],
    "name:eng_x_preferred":[
        "Kintore"
    ],
    "name:eus_x_preferred":[
        "Kintore"
    ],
    "name:gla_x_preferred":[
        "Ceann T\u00f2rr"
    ],
    "name:gla_x_variant":[
        "Ceann-an-Tor"
    ],
    "name:gle_x_preferred":[
        "Ceann T\u00f3rr"
    ],
    "name:ita_x_preferred":[
        "Kintore"
    ],
    "name:nld_x_preferred":[
        "Kintore"
    ],
    "name:sco_x_preferred":[
        "Kintore"
    ],
    "name:spa_x_preferred":[
        "Kintore"
    ],
    "name:swe_x_preferred":[
        "Kintore"
    ],
    "qs:a0":"United Kingdom",
    "qs:a1":"*Aberdeenshire",
    "qs:a1_lc":"GB11QB0000",
    "qs:a1r":"0Scotland",
    "qs:a1r_lc":"GB11000000",
    "qs:adm0":"United Kingdom",
    "qs:la_lc":"*",
    "qs:level":"locality",
    "qs:loc":"Kintore",
    "qs:loc_alt":"Kintore",
    "qs:pop":0,
    "qs:type":"buffered point",
    "wd:wordcount":542,
    "wof:name":"Kintore",
    "wof:placetype":"locality",
    "wof:population":2170
},
  "geometry": {"coordinates":[-2.347119,57.237674],"type":"Point"}
}