{
  "type": "Feature",
  "properties": {
    "gn:country":"GB",
    "gn:fcode":"PPL",
    "gn:population":0,
    "iso:country":"GB",
    "name:cym_x_preferred":[
        "Plumpton"
    ],
    "name:eng_x_preferred":[
        "Plumpton"
    ],
    "name:fas_x_preferred":[
        "\u067e\u0644\u0627\u0645\u067e\u062a\u0648\u0646"
    ],
    "name:gle_x_preferred":[
        "Plumpton"
    ],
    "name:nld_x_preferred":[
        "Plumpton"
    ],
    "name:pol_x_preferred":[
        "Plumpton"
    ],
    "name:swe_x_preferred":[
        "Plumpton"
    ],
    "name:und_x_variant":[
        "Plumpton Wall"
    ],
    "qs_pg:aaroncc":"GB",
    "qs_pg:gn_country":"GB",
    "qs_pg:gn_fcode":"PPL",
    "qs_pg:gn_pop":0,
    "qs_pg:name":"Plumpton Hall",
    "qs_pg:name_adm0":"United Kingdom",
    "qs_pg:name_adm1":"England",
    "qs_pg:photos":24,
    "qs_pg:photos_1k":5,
    "qs_pg:photos_9k":1,
    "qs_pg:photos_9r":1,
    "qs_pg:photos_all":24,
    "qs_pg:photos_sr":1,
    "qs_pg:pop_sr":0,
    "qs_pg:qs_pg_placetype":"locality",
    "qs_pg:qs_pg_placetype_gp":"Town",
    "qs_pg:woe_adm0":23424975,
    "woe:adm0_id":23424975,
    "woe:name_adm0":"United Kingdom",
    "woe:name_adm1":"England",
    "woe:placetype":"Town",
    "wof:name":"Plumpton Hall",
    "wof:placetype":"neighbourhood"
},
  "geometry": {"coordinates":[-2.76667,54.71667],"type":"Point"}
}