{
  "type": "Feature",
  "properties": {
    "gn:admin1_code": "WLS",
    "gn:admin2_code": "Y2",
    "gn:admin3_code": "00NC030",
    "gn:asciiname": "Gallt - y - foel",
    "gn:country_code": "GB",
    "gn:dem": 283,
    "gn:feature_class": "P",
    "gn:feature_code": "PPL",
    "gn:name": "Gallt - y - foel",
    "gn:population": 0,
    "gn:timezone": "Europe/London",
    "iso:country": "GB",
    "wof:name": "Gallt - y - foel",
    "wof:placetype": "neighbourhood"
  },
  "geometry": {"coordinates":[-4.12713,53.14018000000001],"type":"Point"}
}
