{
  "type": "Feature",
  "properties": {
    "gn:country":"GB",
    "gn:fcode":"PPLL",
    "gn:population":10,
    "iso:country":"GB",
    "qs_pg:aaroncc":"GB",
    "qs_pg:gn_country":"GB",
    "qs_pg:gn_fcode":"PPLL",
    "qs_pg:gn_pop":10,
    "qs_pg:name":"Faichem",
    "qs_pg:photos_9r":0,
    "qs_pg:photos_sr":0,
    "qs_pg:pop_sr":1,
    "qs_pg:qs_pg_placetype":"locality",
    "wof:name":"Faichem",
    "wof:placetype":"locality",
    "wof:population":10
},
  "geometry": {"coordinates":[-4.82783,57.0721],"type":"Point"}
}