{
  "type": "Feature",
  "properties": {
    "gn:admin1_code":"ENG",
    "gn:admin2_code":"D3",
    "gn:admin3_code":"17UH",
    "gn:asciiname":"Woolley Bridge",
    "gn:country_code":"GB",
    "gn:dem":125,
    "gn:feature_class":"P",
    "gn:feature_code":"PPL",
    "gn:name":"Woolley Bridge",
    "gn:population":0,
    "gn:timezone":"Europe/London",
    "iso:country":"GB",
    "name:cym_x_preferred":[
        "Woolley Bridge"
    ],
    "name:pol_x_preferred":[
        "Woolley Bridge"
    ],
    "wof:name":"Woolley Bridge",
    "wof:placetype":"neighbourhood"
},
  "geometry": {"coordinates":[-1.98685,53.4588],"type":"Point"}
}