{
  "type": "Feature",
  "properties": {
    "gn:admin1_code":"SCT",
    "gn:admin2_code":"V3",
    "gn:asciiname":"Forse",
    "gn:country_code":"GB",
    "gn:dem":65,
    "gn:feature_class":"P",
    "gn:feature_code":"PPL",
    "gn:name":"Forse",
    "gn:population":0,
    "gn:timezone":"Europe/London",
    "iso:country":"GB",
    "wof:name":"Forse",
    "wof:placetype":"locality"
},
  "geometry": {"coordinates":[-3.33363,58.28999],"type":"Point"}
}