{
  "type": "Feature",
  "properties": {
    "gn:admin1_code":"SCT",
    "gn:admin2_code":"U2",
    "gn:asciiname":"Kirkland",
    "gn:country_code":"GB",
    "gn:dem":120,
    "gn:feature_class":"P",
    "gn:feature_code":"PPLL",
    "gn:name":"Kirkland",
    "gn:population":0,
    "gn:timezone":"Europe/London",
    "iso:country":"GB",
    "name:cat_x_preferred":[
        "Kirkland"
    ],
    "name:ceb_x_preferred":[
        "Kirkland"
    ],
    "name:deu_x_preferred":[
        "Kirkland"
    ],
    "name:fra_x_preferred":[
        "Kirkland"
    ],
    "name:ita_x_preferred":[
        "Kirkland"
    ],
    "name:kor_x_preferred":[
        "\ucee4\ud074\ub79c\ub4dc"
    ],
    "name:nld_x_preferred":[
        "Kirkland"
    ],
    "name:pol_x_preferred":[
        "Kirkland"
    ],
    "name:por_x_preferred":[
        "Kirkland"
    ],
    "name:rus_x_preferred":[
        "\u041a\u0438\u0440\u043a\u043b\u0435\u043d\u0434"
    ],
    "name:spa_x_preferred":[
        "Kirkland"
    ],
    "name:srp_x_preferred":[
        "\u041a\u0435\u0440\u043a\u043b\u0430\u043d\u0434"
    ],
    "name:swe_x_preferred":[
        "Kirkland"
    ],
    "name:ukr_x_preferred":[
        "\u041a\u0435\u0440\u043a\u043b\u0435\u043d\u0434"
    ],
    "name:vol_x_preferred":[
        "Kirkland"
    ],
    "wof:name":"Kirkland",
    "wof:placetype":"locality"
},
  "geometry": {"coordinates":[-3.52052,55.19151],"type":"Point"}
}