{
  "type": "Feature",
  "properties": {
    "gn:admin1_code":"SCT",
    "gn:admin2_code":"U2",
    "gn:asciiname":"Kirkland",
    "gn:country_code":"GB",
    "gn:dem":120,
    "gn:feature_class":"P",
    "gn:feature_code":"PPLL",
    "gn:name":"Kirkland",
    "gn:population":0,
    "gn:timezone":"Europe/London",
    "iso:country":"GB",
    "wof:name":"Kirkland",
    "wof:placetype":"locality"
},
  "geometry": {"coordinates":[-3.52052,55.19151],"type":"Point"}
}