{
  "type": "Feature",
  "properties": {
    "gn:population":2500,
    "iso:country":"GB",
    "name:ceb_x_preferred":[
        "Barnwood"
    ],
    "name:eng_x_preferred":[
        "Barnwood"
    ],
    "name:spa_x_preferred":[
        "Barnwood"
    ],
    "name:swe_x_preferred":[
        "Barnwood"
    ],
    "name:unk_x_variant":[
        "Barnwood"
    ],
    "qs:gn_adm0_cc":"GB",
    "qs:gn_fcode":"PPL",
    "qs:gn_local":2648404,
    "qs:gn_nam_loc":"Gloucester, Gloucester, Gloucestershire, England, GB",
    "qs:gn_namadm1":"ENG",
    "qs:gn_name":"Barnwood",
    "qs:local_max":4990,
    "qs:local_sum":10986,
    "qs:localhoods":13,
    "qs:name":"Barnwood",
    "qs:name_adm0":"United Kingdom",
    "qs:name_adm1":"England",
    "qs:name_adm2":"Gloucestershire",
    "qs:name_lau":"Gloucester City",
    "qs:name_local":"Gloucester",
    "qs:photo_max":258,
    "qs:photo_sum":553,
    "qs:placetype":"Suburb",
    "qs:quad_count":29,
    "qs:woe_adm0":23424975,
    "qs:woe_adm1":24554868,
    "qs:woe_adm2":12602184,
    "qs:woe_lau":12695955,
    "qs:woe_local":21248,
    "qs:woe_ver":"7.10.0",
    "wd:wordcount":486,
    "wof:lang":[
        "eng"
    ],
    "wof:name":"Barnwood",
    "wof:placetype":"neighbourhood",
    "wof:population":2500
},
  "geometry": {"coordinates":[-2.203022,51.861786],"type":"Point"}
}