{
  "type": "Feature",
  "properties": {
    "gn:population":8551,
    "iso:country":"GB",
    "name:ben_x_preferred":[
        "\u09a8\u09be\u09b0\u09bf\u09a8"
    ],
    "name:ceb_x_preferred":[
        "Nairn"
    ],
    "name:ces_x_preferred":[
        "Nairn"
    ],
    "name:cym_x_preferred":[
        "Nairn"
    ],
    "name:deu_x_preferred":[
        "Nairn"
    ],
    "name:eng_x_preferred":[
        "Nairn"
    ],
    "name:eus_x_preferred":[
        "Nairn"
    ],
    "name:fas_x_preferred":[
        "\u0646\u06cc\u0631\u0646"
    ],
    "name:fra_x_preferred":[
        "Nairn"
    ],
    "name:gla_x_preferred":[
        "Inbhir Narann"
    ],
    "name:gle_x_preferred":[
        "Inbhir Narann"
    ],
    "name:guj_x_preferred":[
        "\u0aa8\u0abe\u0aaf\u0ab0\u0acd\u0aa8"
    ],
    "name:hbs_x_preferred":[
        "Nairn"
    ],
    "name:heb_x_preferred":[
        "\u05e0\u05d9\u05d9\u05e8\u05df"
    ],
    "name:ita_x_preferred":[
        "Nairn"
    ],
    "name:jpn_x_preferred":[
        "\u30cd\u30a2\u30f3"
    ],
    "name:kan_x_preferred":[
        "\u0ca8\u0cbe\u0caf\u0cb0\u0ccd"
    ],
    "name:kor_x_preferred":[
        "\ub124\uc5b8"
    ],
    "name:lit_x_preferred":[
        "Nernas"
    ],
    "name:nld_x_preferred":[
        "Nairn"
    ],
    "name:nno_x_preferred":[
        "Nairn"
    ],
    "name:nob_x_preferred":[
        "Nairn"
    ],
    "name:nor_x_preferred":[
        "Nairn"
    ],
    "name:pol_x_preferred":[
        "Nairn"
    ],
    "name:por_x_preferred":[
        "Nairn"
    ],
    "name:rus_x_preferred":[
        "\u041d\u044d\u0440\u043d"
    ],
    "name:sco_x_preferred":[
        "Nairn"
    ],
    "name:slv_x_preferred":[
        "Nairn"
    ],
    "name:spa_x_preferred":[
        "Nairn"
    ],
    "name:swe_x_preferred":[
        "Nairn"
    ],
    "name:tam_x_preferred":[
        "\u0ba8\u0bc8\u0bb0\u0bcd\u0ba9\u0bcd"
    ],
    "name:tel_x_preferred":[
        "\u0c28\u0c48\u0c30\u0c4d\u0c28\u0c4d"
    ],
    "name:ukr_x_preferred":[
        "\u041d\u0435\u0440\u043d"
    ],
    "name:urd_x_preferred":[
        "\u0646\u06cc\u0631\u0646"
    ],
    "name:zho_x_preferred":[
        "\u5948\u6069"
    ],
    "qs:a0":"United Kingdom",
    "qs:a1":"*Highland",
    "qs:a1_lc":"GB11QT0000",
    "qs:a1r":"0Scotland",
    "qs:a1r_lc":"GB11000000",
    "qs:adm0":"United Kingdom",
    "qs:la_lc":"*",
    "qs:level":"locality",
    "qs:loc":"Nairn",
    "qs:loc_alt":"Nairn",
    "qs:pop":0,
    "qs:type":"buffered point",
    "wd:wordcount":1413,
    "wof:lang":[
        "eng"
    ],
    "wof:name":"Nairn",
    "wof:placetype":"locality",
    "wof:population":8551
},
  "geometry": {"coordinates":[-3.869079,57.585033],"type":"Point"}
}