{
  "type": "Feature",
  "properties": {
    "gn:population": 8551,
    "iso:country": "GB",
    "name:ben_x_preferred": [
      "নারিন"
    ],
    "name:ceb_x_preferred": [
      "Nairn"
    ],
    "name:ces_x_preferred": [
      "Nairn"
    ],
    "name:cym_x_preferred": [
      "Nairn"
    ],
    "name:deu_x_preferred": [
      "Nairn"
    ],
    "name:eng_x_preferred": [
      "Nairn"
    ],
    "name:eus_x_preferred": [
      "Nairn"
    ],
    "name:fas_x_preferred": [
      "نیرن"
    ],
    "name:fra_x_preferred": [
      "Nairn"
    ],
    "name:gla_x_preferred": [
      "Inbhir Narann"
    ],
    "name:gle_x_preferred": [
      "Inbhir Narann"
    ],
    "name:guj_x_preferred": [
      "નાયર્ન"
    ],
    "name:hbs_x_preferred": [
      "Nairn"
    ],
    "name:heb_x_preferred": [
      "ניירן"
    ],
    "name:ita_x_preferred": [
      "Nairn"
    ],
    "name:jpn_x_preferred": [
      "ネアン"
    ],
    "name:kan_x_preferred": [
      "ನಾಯರ್"
    ],
    "name:kor_x_preferred": [
      "네언"
    ],
    "name:lit_x_preferred": [
      "Nernas"
    ],
    "name:nld_x_preferred": [
      "Nairn"
    ],
    "name:nno_x_preferred": [
      "Nairn"
    ],
    "name:nob_x_preferred": [
      "Nairn"
    ],
    "name:nor_x_preferred": [
      "Nairn"
    ],
    "name:pol_x_preferred": [
      "Nairn"
    ],
    "name:por_x_preferred": [
      "Nairn"
    ],
    "name:rus_x_preferred": [
      "Нэрн"
    ],
    "name:sco_x_preferred": [
      "Nairn"
    ],
    "name:slv_x_preferred": [
      "Nairn"
    ],
    "name:spa_x_preferred": [
      "Nairn"
    ],
    "name:swe_x_preferred": [
      "Nairn"
    ],
    "name:tam_x_preferred": [
      "நைர்ன்"
    ],
    "name:tel_x_preferred": [
      "నైర్న్"
    ],
    "name:ukr_x_preferred": [
      "Нерн"
    ],
    "name:urd_x_preferred": [
      "نیرن"
    ],
    "name:zho_x_preferred": [
      "奈恩"
    ],
    "qs:a0": "United Kingdom",
    "qs:a1": "*Highland",
    "qs:a1_lc": "GB11QT0000",
    "qs:a1r": "0Scotland",
    "qs:a1r_lc": "GB11000000",
    "qs:adm0": "United Kingdom",
    "qs:la_lc": "*",
    "qs:level": "locality",
    "qs:loc": "Nairn",
    "qs:loc_alt": "Nairn",
    "qs:pop": 0,
    "qs:type": "buffered point",
    "wd:wordcount": 1413,
    "wof:lang": [
      "eng"
    ],
    "wof:name": "Nairn",
    "wof:placetype": "locality",
    "wof:population": 8551
  },
  "geometry": {"coordinates":[-3.869079,57.585033],"type":"Point"}
}
