{
  "type": "Feature",
  "properties": {
    "iso:country": "GB",
    "wof:name": "Brandling Village",
    "wof:placetype": "neighbourhood"
  },
  "geometry": {"coordinates":[-1.60851911787885,54.98582222984119],"type":"Point"}
}
