{
  "type": "Feature",
  "properties": {
    "gn:admin1_code":"WLS",
    "gn:admin2_code":"Y7",
    "gn:admin3_code":"00NS006",
    "gn:asciiname":"Hill Mountain",
    "gn:country_code":"GB",
    "gn:dem":89,
    "gn:feature_class":"P",
    "gn:feature_code":"PPL",
    "gn:name":"Hill Mountain",
    "gn:population":673,
    "gn:timezone":"Europe/London",
    "iso:country":"GB",
    "name:spa_x_preferred":[
        "Hill Mountain"
    ],
    "name:swe_x_preferred":[
        "Hill Mountain"
    ],
    "wof:name":"Hill Mountain",
    "wof:placetype":"neighbourhood",
    "wof:population":673
},
  "geometry": {"coordinates":[-4.93139,51.73667],"type":"Point"}
}