{
  "type": "Feature",
  "properties": {
    "gn:admin1_code":"SCT",
    "gn:admin2_code":"T9",
    "gn:asciiname":"Blainslie",
    "gn:country_code":"GB",
    "gn:dem":224,
    "gn:feature_class":"P",
    "gn:feature_code":"PPL",
    "gn:name":"Blainslie",
    "gn:population":0,
    "gn:timezone":"Europe/London",
    "iso:country":"GB",
    "wof:name":"Blainslie",
    "wof:placetype":"locality"
},
  "geometry": {"coordinates":[-2.73333,55.68333000000001],"type":"Point"}
}