{
  "type": "Feature",
  "properties": {
    "gn:country":"GB",
    "gn:fcode":"PPLL",
    "gn:population":0,
    "iso:country":"GB",
    "name:eng_x_preferred":[
        "Racton"
    ],
    "name:fra_x_preferred":[
        "Racton"
    ],
    "name:nld_x_preferred":[
        "Racton"
    ],
    "qs_pg:aaroncc":"GB",
    "qs_pg:gn_country":"GB",
    "qs_pg:gn_fcode":"PPLL",
    "qs_pg:gn_pop":0,
    "qs_pg:name":"Racton",
    "qs_pg:name_adm0":"United Kingdom",
    "qs_pg:name_adm1":"England",
    "qs_pg:photos":87,
    "qs_pg:photos_1k":18,
    "qs_pg:photos_9k":1,
    "qs_pg:photos_9r":3,
    "qs_pg:photos_all":87,
    "qs_pg:photos_sr":3,
    "qs_pg:pop_sr":0,
    "qs_pg:qs_pg_placetype":"locality",
    "qs_pg:qs_pg_placetype_gp":"Town",
    "qs_pg:woe_adm0":23424975,
    "woe:adm0_id":23424975,
    "woe:name_adm0":"United Kingdom",
    "woe:name_adm1":"England",
    "woe:placetype":"Town",
    "wof:name":"Racton",
    "wof:placetype":"neighbourhood"
},
  "geometry": {"coordinates":[-0.88972,50.87569],"type":"Point"}
}