{
  "type": "Feature",
  "properties": {
    "gn:country":"GB",
    "iso:country":"GB",
    "name:cym_x_preferred":[
        "Ffwrnes"
    ],
    "name:eng_x_preferred":[
        "Furnace"
    ],
    "name:fra_x_preferred":[
        "Furnace"
    ],
    "name:gle_x_preferred":[
        "Ffwrnes"
    ],
    "name:nld_x_preferred":[
        "Furnace"
    ],
    "qs_pg:aaroncc":"GB",
    "qs_pg:gn_country":"GB",
    "qs_pg:name":"Furnace",
    "qs_pg:name_adm0":"United Kingdom",
    "qs_pg:name_adm1":"Wales",
    "qs_pg:photos":233,
    "qs_pg:photos_1k":47,
    "qs_pg:photos_9k":1,
    "qs_pg:photos_9r":4,
    "qs_pg:photos_all":233,
    "qs_pg:photos_sr":4,
    "qs_pg:pop_sr":0,
    "qs_pg:qs_pg_placetype":"locality",
    "qs_pg:qs_pg_placetype_gp":"Town",
    "qs_pg:woe_adm0":23424975,
    "woe:adm0_id":23424975,
    "woe:name_adm0":"United Kingdom",
    "woe:name_adm1":"Wales",
    "woe:placetype":"Town",
    "wof:name":"Furnace",
    "wof:placetype":"neighbourhood"
},
  "geometry": {"coordinates":[-4.253082,51.652537],"type":"Point"}
}