{
  "type": "Feature",
  "properties": {
    "gn:gn_country":"GB",
    "gn:gn_fcode":"PPL",
    "gn:gn_pop":0,
    "iso:country":"GB",
    "name:dut_x_preferred":[
        "Stoborough"
    ],
    "name:eng_x_preferred":[
        "Stoborough"
    ],
    "name:fre_x_preferred":[
        "Stoborough"
    ],
    "name:ger_x_preferred":[
        "Stoborough"
    ],
    "name:pol_x_preferred":[
        "Stoborough"
    ],
    "name:wel_x_preferred":[
        "Stoborough"
    ],
    "qs_pg:aaroncc":"GB",
    "qs_pg:gn_country":"GB",
    "qs_pg:gn_fcode":"PPL",
    "qs_pg:gn_pop":0,
    "qs_pg:name":"Stoborough",
    "qs_pg:name_adm0":"United Kingdom",
    "qs_pg:name_adm1":"England",
    "qs_pg:photos":32,
    "qs_pg:photos_1k":6,
    "qs_pg:photos_9k":1,
    "qs_pg:photos_9r":2,
    "qs_pg:photos_all":32,
    "qs_pg:photos_sr":2,
    "qs_pg:pop_sr":0,
    "qs_pg:qs_pg_placetype":"locality",
    "qs_pg:qs_pg_placetype_gp":"Town",
    "qs_pg:woe_adm0":23424975,
    "woe:adm0_id":23424975,
    "woe:name_adm0":"United Kingdom",
    "woe:name_adm1":"England",
    "woe:placetype":"Town",
    "wof:name":"Stoborough",
    "wof:placetype":"neighbourhood"
},
  "geometry": {"coordinates":[-2.11069,50.67514],"type":"Point"}
}