{
  "type": "Feature",
  "properties": {
    "gn:admin1_code":"ENG",
    "gn:admin2_code":"P6",
    "gn:admin3_code":"45UD",
    "gn:admin4_code":"45UD012",
    "gn:asciiname":"Upper Marden",
    "gn:country_code":"GB",
    "gn:dem":154,
    "gn:feature_class":"P",
    "gn:feature_code":"PPL",
    "gn:name":"Upper Marden",
    "gn:population":0,
    "gn:timezone":"Europe/London",
    "iso:country":"GB",
    "wof:name":"Upper Marden",
    "wof:placetype":"neighbourhood"
},
  "geometry": {"coordinates":[-0.86826,50.92132],"type":"Point"}
}