{
  "type": "Feature",
  "properties": {
    "gn:country":"GB",
    "gn:fcode":"PPL",
    "gn:population":0,
    "iso:country":"GB",
    "name:ara_x_preferred":[
        "\u0643\u0631\u0627\u064a"
    ],
    "name:cat_x_preferred":[
        "Cray Inc."
    ],
    "name:cor_x_preferred":[
        "Crai"
    ],
    "name:cym_x_preferred":[
        "Crai"
    ],
    "name:deu_x_preferred":[
        "Cray"
    ],
    "name:fin_x_preferred":[
        "Cray"
    ],
    "name:fra_x_preferred":[
        "Cray"
    ],
    "name:gle_x_preferred":[
        "Crai"
    ],
    "name:heb_x_preferred":[
        "Cray"
    ],
    "name:hun_x_preferred":[
        "Cray"
    ],
    "name:ita_x_preferred":[
        "Cray Inc."
    ],
    "name:jpn_x_preferred":[
        "\u30af\u30ec\u30a4"
    ],
    "name:kaz_x_preferred":[
        "Cray Inc."
    ],
    "name:kor_x_preferred":[
        "\ud06c\ub808\uc774"
    ],
    "name:mal_x_preferred":[
        "\u0d15\u0d4d\u0d30\u0d47"
    ],
    "name:nor_x_preferred":[
        "Cray Inc."
    ],
    "name:pol_x_preferred":[
        "Cray Inc."
    ],
    "name:por_x_preferred":[
        "Cray Research"
    ],
    "name:ron_x_preferred":[
        "Cray"
    ],
    "name:rus_x_preferred":[
        "Cray"
    ],
    "name:spa_x_preferred":[
        "Cray Inc."
    ],
    "name:swe_x_preferred":[
        "Cray"
    ],
    "name:ukr_x_preferred":[
        "Cray"
    ],
    "name:zho_x_preferred":[
        "\u514b\u96f7\u516c\u53f8"
    ],
    "qs_pg:aaroncc":"GB",
    "qs_pg:gn_country":"GB",
    "qs_pg:gn_fcode":"PPL",
    "qs_pg:gn_pop":0,
    "qs_pg:name":"Cray",
    "qs_pg:name_adm0":"United Kingdom",
    "qs_pg:name_adm1":"Scotland",
    "qs_pg:photos":76,
    "qs_pg:photos_1k":15,
    "qs_pg:photos_9k":1,
    "qs_pg:photos_9r":3,
    "qs_pg:photos_all":76,
    "qs_pg:photos_sr":3,
    "qs_pg:pop_sr":0,
    "qs_pg:qs_pg_placetype":"locality",
    "qs_pg:qs_pg_placetype_gp":"Town",
    "qs_pg:woe_adm0":23424975,
    "woe:adm0_id":23424975,
    "woe:name_adm0":"United Kingdom",
    "woe:name_adm1":"Scotland",
    "woe:placetype":"Town",
    "wof:name":"Cray",
    "wof:placetype":"locality"
},
  "geometry": {"coordinates":[-3.38333,56.73333],"type":"Point"}
}