{
  "type": "Feature",
  "properties": {
    "gn:population":1909,
    "iso:country":"GB",
    "name:ceb_x_preferred":[
        "Newburgh"
    ],
    "name:dut_x_preferred":[
        "Newburgh"
    ],
    "name:eng_x_preferred":[
        "Newburgh"
    ],
    "name:gla_x_preferred":[
        "Am Borgh \u00d9r"
    ],
    "name:ita_x_preferred":[
        "Newburgh"
    ],
    "name:jpn_x_preferred":[
        "\u30cb\u30e5\u30fc\u30d0\u30fc\u30b0"
    ],
    "name:sco_x_preferred":[
        "Neeburgh"
    ],
    "name:swe_x_preferred":[
        "Newburgh"
    ],
    "name:wel_x_preferred":[
        "Newburgh"
    ],
    "qs:a0":"United Kingdom",
    "qs:a1":"*Fife",
    "qs:a1_lc":"GB11QR0000",
    "qs:a1r":"0Scotland",
    "qs:a1r_lc":"GB11000000",
    "qs:adm0":"United Kingdom",
    "qs:la_lc":"*",
    "qs:level":"locality",
    "qs:loc":"Newburgh",
    "qs:loc_alt":"Newburgh",
    "qs:pop":0,
    "qs:type":"buffered point",
    "wd:wordcount":1083,
    "wof:lang":[
        "eng"
    ],
    "wof:name":"Newburgh",
    "wof:placetype":"locality",
    "wof:population":1909
},
  "geometry": {"coordinates":[-3.237058,56.350768],"type":"Point"}
}