{
  "type": "Feature",
  "properties": {
    "iso:country": "GB",
    "wof:name": "Sale Moor",
    "wof:placetype": "neighbourhood"
  },
  "geometry": {"coordinates":[-2.30402212092533,53.42014157723191],"type":"Point"}
}
