{
  "type": "Feature",
  "properties": {
    "gn:country":"GB",
    "gn:fcode":"PPL",
    "gn:population":0,
    "iso:country":"GB",
    "name:deu_x_preferred":[
        "Skipness"
    ],
    "name:eng_x_preferred":[
        "Skipness"
    ],
    "name:fas_x_preferred":[
        "\u0627\u0633\u06a9\u06cc\u067e\u0646\u0633"
    ],
    "name:fra_x_preferred":[
        "Skipness"
    ],
    "name:gla_x_preferred":[
        "Sgibinis"
    ],
    "name:gle_x_preferred":[
        "Sgibinis"
    ],
    "name:heb_x_preferred":[
        "\u05e1\u05e7\u05d9\u05e4\u05e0\u05e1"
    ],
    "name:ita_x_preferred":[
        "Skipness"
    ],
    "name:nds_x_preferred":[
        "Skipness"
    ],
    "name:nld_x_preferred":[
        "Skipness"
    ],
    "name:rus_x_preferred":[
        "\u0417\u0430\u043c\u043e\u043a \u0421\u043a\u0438\u043f\u043d\u0435\u0441\u0441"
    ],
    "name:ukr_x_preferred":[
        "\u0417\u0430\u043c\u043e\u043a \u0421\u043a\u0456\u043f\u043d\u0435\u0441\u0441"
    ],
    "qs_pg:aaroncc":"GB",
    "qs_pg:gn_country":"GB",
    "qs_pg:gn_fcode":"PPL",
    "qs_pg:gn_pop":0,
    "qs_pg:name":"Skipness",
    "qs_pg:name_adm0":"United Kingdom",
    "qs_pg:name_adm1":"Scotland",
    "qs_pg:photos":522,
    "qs_pg:photos_1k":106,
    "qs_pg:photos_9k":2,
    "qs_pg:photos_9r":5,
    "qs_pg:photos_all":522,
    "qs_pg:photos_sr":7,
    "qs_pg:pop_sr":0,
    "qs_pg:qs_pg_placetype":"locality",
    "qs_pg:qs_pg_placetype_gp":"Town",
    "qs_pg:woe_adm0":23424975,
    "woe:adm0_id":23424975,
    "woe:name_adm0":"United Kingdom",
    "woe:name_adm1":"Scotland",
    "woe:placetype":"Town",
    "wof:name":"Skipness",
    "wof:placetype":"locality"
},
  "geometry": {"coordinates":[-5.34723,55.76653],"type":"Point"}
}