{
  "type": "Feature",
  "properties": {
    "iso:country":"GB",
    "name:cym_x_preferred":[
        "Hamstreet"
    ],
    "name:eng_x_preferred":[
        "Hamstreet"
    ],
    "name:fra_x_preferred":[
        "Hamstreet"
    ],
    "name:nld_x_preferred":[
        "Hamstreet"
    ],
    "name:pol_x_preferred":[
        "Hamstreet"
    ],
    "name:spa_x_preferred":[
        "Hamstreet"
    ],
    "name:swe_x_preferred":[
        "Hamstreet"
    ],
    "name:zho_x_preferred":[
        "\u6f22\u59c6\u65af\u7fe0\u7279"
    ],
    "qs:a0":"United Kingdom",
    "qs:a1":"*Kent",
    "qs:a1_lc":"GB12290000",
    "qs:a1r":"0England",
    "qs:a1r_lc":"GB12000000",
    "qs:adm0":"United Kingdom",
    "qs:la_lc":"*",
    "qs:level":"locality",
    "qs:loc":"Hamstreet",
    "qs:loc_alt":"Hamstreet",
    "qs:pop":0,
    "qs:type":"buffered point",
    "wd:wordcount":539,
    "wof:name":"Hamstreet",
    "wof:placetype":"neighbourhood"
},
  "geometry": {"coordinates":[0.858919,51.064106],"type":"Point"}
}