{
  "type": "Feature",
  "properties": {
    "gn:country":"GB",
    "gn:fcode":"PPL",
    "gn:population":0,
    "iso:country":"GB",
    "name:bre_x_preferred":[
        "Glan-y-fferi"
    ],
    "name:cym_x_preferred":[
        "Glan-y-fferi"
    ],
    "name:deu_x_preferred":[
        "Glan-y-fferi"
    ],
    "name:eng_x_preferred":[
        "Ferryside"
    ],
    "name:eus_x_preferred":[
        "Ferryside"
    ],
    "name:fas_x_preferred":[
        "\u0641\u0631\u06cc\u0633\u0627\u06cc\u062f"
    ],
    "name:fra_x_preferred":[
        "Ferryside"
    ],
    "name:ita_x_preferred":[
        "Ferryside"
    ],
    "name:nld_x_preferred":[
        "Ferryside"
    ],
    "name:sco_x_preferred":[
        "Glan-y-fferi"
    ],
    "name:spa_x_preferred":[
        "Ferryside"
    ],
    "name:swe_x_preferred":[
        "Ferryside"
    ],
    "qs_pg:aaroncc":"GB",
    "qs_pg:gn_country":"GB",
    "qs_pg:gn_fcode":"PPL",
    "qs_pg:gn_pop":0,
    "qs_pg:name":"Ferryside",
    "qs_pg:name_adm0":"United Kingdom",
    "qs_pg:name_adm1":"Wales",
    "qs_pg:photos":554,
    "qs_pg:photos_1k":112,
    "qs_pg:photos_9k":2,
    "qs_pg:photos_9r":5,
    "qs_pg:photos_all":554,
    "qs_pg:photos_sr":8,
    "qs_pg:pop_sr":0,
    "qs_pg:qs_pg_placetype":"locality",
    "qs_pg:qs_pg_placetype_gp":"Town",
    "qs_pg:woe_adm0":23424975,
    "woe:adm0_id":23424975,
    "woe:name_adm0":"United Kingdom",
    "woe:name_adm1":"Wales",
    "woe:placetype":"Town",
    "wof:name":"Ferryside",
    "wof:placetype":"neighbourhood",
    "wof:population":846
},
  "geometry": {"coordinates":[-4.369,51.76784],"type":"Point"}
}