{
  "type": "Feature",
  "properties": {
    "iso:country":"GB",
    "name:cym_x_preferred":[
        "South Tehidy"
    ],
    "name:eng_x_preferred":[
        "South Tehidy"
    ],
    "name:eus_x_preferred":[
        "South Tehidy"
    ],
    "name:fra_x_preferred":[
        "South Tehidy"
    ],
    "name:nld_x_preferred":[
        "South Tehidy"
    ],
    "name:pol_x_preferred":[
        "South Tehidy"
    ],
    "name:spa_x_preferred":[
        "South Tehidy"
    ],
    "name:swe_x_preferred":[
        "South Tehidy"
    ],
    "qs_pg:aaroncc":"GB",
    "qs_pg:name":"South Tehidy",
    "qs_pg:name_adm0":"United Kingdom",
    "qs_pg:name_adm1":"England",
    "qs_pg:photos":162,
    "qs_pg:photos_1k":33,
    "qs_pg:photos_9k":1,
    "qs_pg:photos_9r":4,
    "qs_pg:photos_all":162,
    "qs_pg:photos_sr":4,
    "qs_pg:pop_sr":0,
    "qs_pg:qs_pg_placetype":"locality",
    "qs_pg:qs_pg_placetype_gp":"Town",
    "qs_pg:woe_adm0":23424975,
    "woe:adm0_id":23424975,
    "woe:name_adm0":"United Kingdom",
    "woe:name_adm1":"England",
    "woe:placetype":"Town",
    "wof:name":"South Tehidy",
    "wof:placetype":"neighbourhood"
},
  "geometry": {"coordinates":[-5.298156,50.238751],"type":"Point"}
}