{
  "type": "Feature",
  "properties": {
    "gn:country":"GB",
    "gn:fcode":"PPL",
    "gn:population":0,
    "iso:country":"GB",
    "name:ara_x_preferred":[
        "\u062a\u0634\u0644\u064a\u0646\u063a\u062a\u0648\u0646"
    ],
    "name:cym_x_preferred":[
        "Chellington"
    ],
    "name:eng_x_preferred":[
        "Chellington"
    ],
    "name:fas_x_preferred":[
        "\u0686\u0644\u06cc\u0646\u06af\u062a\u0648\u0646"
    ],
    "name:fra_x_preferred":[
        "Chellington"
    ],
    "name:nld_x_preferred":[
        "Chellington"
    ],
    "name:pol_x_preferred":[
        "Chellington"
    ],
    "qs_pg:aaroncc":"GB",
    "qs_pg:gn_country":"GB",
    "qs_pg:gn_fcode":"PPL",
    "qs_pg:gn_pop":0,
    "qs_pg:name":"Chellington",
    "qs_pg:name_adm0":"United Kingdom",
    "qs_pg:name_adm1":"England",
    "qs_pg:photos":109,
    "qs_pg:photos_1k":22,
    "qs_pg:photos_9k":1,
    "qs_pg:photos_9r":3,
    "qs_pg:photos_all":109,
    "qs_pg:photos_sr":3,
    "qs_pg:pop_sr":0,
    "qs_pg:qs_pg_placetype":"locality",
    "qs_pg:qs_pg_placetype_gp":"Town",
    "qs_pg:woe_adm0":23424975,
    "woe:adm0_id":23424975,
    "woe:name_adm0":"United Kingdom",
    "woe:name_adm1":"England",
    "woe:placetype":"Town",
    "wof:name":"Chellington",
    "wof:placetype":"neighbourhood"
},
  "geometry": {"coordinates":[-0.60137,52.19196],"type":"Point"}
}