{
  "type": "Feature",
  "properties": {
    "gn:admin1_code":"SCT",
    "gn:admin2_code":"V9",
    "gn:asciiname":"Whitehall Village",
    "gn:country_code":"GB",
    "gn:dem":8,
    "gn:feature_class":"P",
    "gn:feature_code":"PPL",
    "gn:name":"Whitehall Village",
    "gn:population":0,
    "gn:timezone":"Europe/London",
    "iso:country":"GB",
    "wof:name":"Whitehall Village",
    "wof:placetype":"locality"
},
  "geometry": {"coordinates":[-2.60781,59.14193],"type":"Point"}
}