{
  "type": "Feature",
  "properties": {
    "gn:admin1_code":"WLS",
    "gn:admin2_code":"Y4",
    "gn:admin3_code":"00PP010",
    "gn:asciiname":"Bryngwyn",
    "gn:country_code":"GB",
    "gn:dem":75,
    "gn:feature_class":"P",
    "gn:feature_code":"PPL",
    "gn:name":"Bryngwyn",
    "gn:population":0,
    "gn:timezone":"Europe/London",
    "iso:country":"GB",
    "name:bre_x_preferred":[
        "Bryngwyn"
    ],
    "name:cym_x_preferred":[
        "Bryngwyn"
    ],
    "name:eus_x_preferred":[
        "Bryngwyn"
    ],
    "wof:name":"Bryngwyn",
    "wof:placetype":"neighbourhood"
},
  "geometry": {"coordinates":[-2.88477,51.77926],"type":"Point"}
}