{
  "type": "Feature",
  "properties": {
    "iso:country":"GB",
    "qs_pg:aaroncc":"GB",
    "qs_pg:name":"Wood Lanes",
    "qs_pg:name_adm0":"United Kingdom",
    "qs_pg:name_adm1":"England",
    "qs_pg:photos":2504,
    "qs_pg:photos_1k":507,
    "qs_pg:photos_9k":11,
    "qs_pg:photos_9r":10,
    "qs_pg:photos_all":2504,
    "qs_pg:photos_sr":18,
    "qs_pg:pop_sr":0,
    "qs_pg:qs_pg_placetype":"locality",
    "qs_pg:qs_pg_placetype_gp":"Town",
    "qs_pg:woe_adm0":23424975,
    "woe:adm0_id":23424975,
    "woe:name_adm0":"United Kingdom",
    "woe:name_adm1":"England",
    "woe:placetype":"Town",
    "wof:name":"Wood Lanes",
    "wof:placetype":"neighbourhood"
},
  "geometry": {"coordinates":[-2.054958,53.340354],"type":"Point"}
}