{
  "type": "Feature",
  "properties": {
    "gn:admin1_code":"SCT",
    "gn:admin2_code":"V1",
    "gn:asciiname":"Buckhaven and Methil",
    "gn:country_code":"GB",
    "gn:dem":27,
    "gn:feature_class":"P",
    "gn:feature_code":"PPL",
    "gn:name":"Buckhaven and Methil",
    "gn:population":0,
    "gn:timezone":"Europe/London",
    "iso:country":"GB",
    "wof:name":"Buckhaven and Methil",
    "wof:placetype":"locality"
},
  "geometry": {"coordinates":[-3.03079,56.1745],"type":"Point"}
}