{
  "type": "Feature",
  "properties": {
    "iso:country": "GB",
    "wof:name": "Wilsden Hill",
    "wof:placetype": "neighbourhood"
  },
  "geometry": {"coordinates":[-1.86786879868045,53.82466012213145],"type":"Point"}
}
