{
  "type": "Feature",
  "properties": {
    "iso:country":"GB",
    "name:ceb_x_preferred":[
        "Darmsden"
    ],
    "name:eng_x_preferred":[
        "Darmsden"
    ],
    "name:fra_x_preferred":[
        "Darmsden"
    ],
    "name:nld_x_preferred":[
        "Darmsden"
    ],
    "name:pol_x_preferred":[
        "Darmsden"
    ],
    "name:swe_x_preferred":[
        "Darmsden"
    ],
    "qs_pg:aaroncc":"GB",
    "qs_pg:name":"Darmsden",
    "qs_pg:name_adm0":"United Kingdom",
    "qs_pg:name_adm1":"England",
    "qs_pg:photos":91,
    "qs_pg:photos_1k":18,
    "qs_pg:photos_9k":1,
    "qs_pg:photos_9r":3,
    "qs_pg:photos_all":91,
    "qs_pg:photos_sr":3,
    "qs_pg:pop_sr":0,
    "qs_pg:qs_pg_placetype":"locality",
    "qs_pg:qs_pg_placetype_gp":"Town",
    "qs_pg:woe_adm0":23424975,
    "woe:adm0_id":23424975,
    "woe:name_adm0":"United Kingdom",
    "woe:name_adm1":"England",
    "woe:placetype":"Town",
    "wof:name":"Darmsden",
    "wof:placetype":"neighbourhood"
},
  "geometry": {"coordinates":[1.072325,52.144313],"type":"Point"}
}