{
  "type": "Feature",
  "properties": {
    "gn:admin1_code":"ENG",
    "gn:admin2_code":"P4",
    "gn:admin3_code":"00MB049",
    "gn:asciiname":"Crookham",
    "gn:country_code":"GB",
    "gn:dem":112,
    "gn:feature_class":"P",
    "gn:feature_code":"PPL",
    "gn:name":"Crookham",
    "gn:population":0,
    "gn:timezone":"Europe/London",
    "iso:country":"GB",
    "name:ara_x_preferred":[
        "\u0643\u0631\u0648\u0647\u0645"
    ],
    "name:cym_x_preferred":[
        "Crookham"
    ],
    "name:pol_x_preferred":[
        "Crookham"
    ],
    "wof:name":"Crookham",
    "wof:placetype":"neighbourhood"
},
  "geometry": {"coordinates":[-1.22854,51.37575],"type":"Point"}
}