{
  "type": "Feature",
  "properties": {
    "gn:admin1_code":"NIR",
    "gn:admin2_code":"N09000005",
    "gn:asciiname":"Crew",
    "gn:country_code":"GB",
    "gn:dem":39,
    "gn:feature_class":"P",
    "gn:feature_code":"PPL",
    "gn:name":"Crew",
    "gn:population":0,
    "gn:timezone":"Europe/London",
    "iso:country":"GB",
    "wof:name":"Crew",
    "wof:placetype":"locality"
},
  "geometry": {"coordinates":[-7.51667,54.71666999999999],"type":"Point"}
}