{
  "type": "Feature",
  "properties": {
    "gn:admin1_code":"NIR",
    "gn:admin2_code":"N09000005",
    "gn:asciiname":"Crew",
    "gn:country_code":"GB",
    "gn:dem":39,
    "gn:feature_class":"P",
    "gn:feature_code":"PPL",
    "gn:name":"Crew",
    "gn:population":0,
    "gn:timezone":"Europe/London",
    "iso:country":"GB",
    "name:aze_x_preferred":[
        "Ekipaj"
    ],
    "name:bel_x_preferred":[
        "\u042d\u043a\u0456\u043f\u0430\u0436"
    ],
    "name:bul_x_preferred":[
        "\u0415\u043a\u0438\u043f\u0430\u0436"
    ],
    "name:cat_x_preferred":[
        "Tripulaci\u00f3"
    ],
    "name:ell_x_preferred":[
        "\u03a0\u03bb\u03ae\u03c1\u03c9\u03bc\u03b1"
    ],
    "name:epo_x_preferred":[
        "Skipo"
    ],
    "name:eus_x_preferred":[
        "Eskifaia"
    ],
    "name:fas_x_preferred":[
        "\u062e\u062f\u0645\u0647"
    ],
    "name:fra_x_preferred":[
        "\u00c9quipage"
    ],
    "name:fry_x_preferred":[
        "Bemanning"
    ],
    "name:hin_x_preferred":[
        "\u0915\u0930\u094d\u092e\u0940\u0926\u0932"
    ],
    "name:hrv_x_preferred":[
        "Posada"
    ],
    "name:isl_x_preferred":[
        "\u00c1h\u00f6fn"
    ],
    "name:ita_x_preferred":[
        "Equipaggio"
    ],
    "name:jpn_x_preferred":[
        "\u4e57\u7d44\u54e1"
    ],
    "name:kaz_x_preferred":[
        "\u042d\u043a\u0438\u043f\u0430\u0436"
    ],
    "name:lit_x_preferred":[
        "\u012egula"
    ],
    "name:nld_x_preferred":[
        "Bemanning"
    ],
    "name:nor_x_preferred":[
        "Mannskap"
    ],
    "name:pol_x_preferred":[
        "Za\u0142oga"
    ],
    "name:por_x_preferred":[
        "Tripula\u00e7\u00e3o"
    ],
    "name:rus_x_preferred":[
        "\u042d\u043a\u0438\u043f\u0430\u0436"
    ],
    "name:slv_x_preferred":[
        "Posadka"
    ],
    "name:spa_x_preferred":[
        "Tripulaci\u00f3n"
    ],
    "name:swe_x_preferred":[
        "Bes\u00e4ttning"
    ],
    "name:ukr_x_preferred":[
        "\u0415\u043a\u0456\u043f\u0430\u0436"
    ],
    "name:uzb_x_preferred":[
        "Ekipaj"
    ],
    "wof:name":"Crew",
    "wof:placetype":"locality"
},
  "geometry": {"coordinates":[-7.51667,54.71666999999999],"type":"Point"}
}