{
  "type": "Feature",
  "properties": {
    "gn:admin1_code": "NIR",
    "gn:admin2_code": "N09000005",
    "gn:asciiname": "Crew",
    "gn:country_code": "GB",
    "gn:dem": 39,
    "gn:feature_class": "P",
    "gn:feature_code": "PPL",
    "gn:name": "Crew",
    "gn:population": 0,
    "gn:timezone": "Europe/London",
    "iso:country": "GB",
    "name:aze_x_preferred": [
      "Ekipaj"
    ],
    "name:bel_x_preferred": [
      "Экіпаж"
    ],
    "name:bul_x_preferred": [
      "Екипаж"
    ],
    "name:cat_x_preferred": [
      "Tripulació"
    ],
    "name:ell_x_preferred": [
      "Πλήρωμα"
    ],
    "name:epo_x_preferred": [
      "Skipo"
    ],
    "name:eus_x_preferred": [
      "Eskifaia"
    ],
    "name:fas_x_preferred": [
      "خدمه"
    ],
    "name:fra_x_preferred": [
      "Équipage"
    ],
    "name:fry_x_preferred": [
      "Bemanning"
    ],
    "name:hin_x_preferred": [
      "कर्मीदल"
    ],
    "name:hrv_x_preferred": [
      "Posada"
    ],
    "name:isl_x_preferred": [
      "Áhöfn"
    ],
    "name:ita_x_preferred": [
      "Equipaggio"
    ],
    "name:jpn_x_preferred": [
      "乗組員"
    ],
    "name:kaz_x_preferred": [
      "Экипаж"
    ],
    "name:lit_x_preferred": [
      "Įgula"
    ],
    "name:nld_x_preferred": [
      "Bemanning"
    ],
    "name:nor_x_preferred": [
      "Mannskap"
    ],
    "name:pol_x_preferred": [
      "Załoga"
    ],
    "name:por_x_preferred": [
      "Tripulação"
    ],
    "name:rus_x_preferred": [
      "Экипаж"
    ],
    "name:slv_x_preferred": [
      "Posadka"
    ],
    "name:spa_x_preferred": [
      "Tripulación"
    ],
    "name:swe_x_preferred": [
      "Besättning"
    ],
    "name:ukr_x_preferred": [
      "Екіпаж"
    ],
    "name:uzb_x_preferred": [
      "Ekipaj"
    ],
    "wof:name": "Crew",
    "wof:placetype": "locality"
  },
  "geometry": {"coordinates":[-7.51667,54.71666999999999],"type":"Point"}
}
