{
  "type": "Feature",
  "properties": {
    "gn:population":13804,
    "iso:country":"GB",
    "name:ben_x_preferred":[
        "\u09a8\u099f\u09bf\u0982\u09b2\u09c7"
    ],
    "name:bul_x_preferred":[
        "\u041a\u043d\u043e\u0442\u0438\u043d\u0433\u043b\u0435\u0439"
    ],
    "name:ceb_x_preferred":[
        "Knottingley"
    ],
    "name:cym_x_preferred":[
        "Knottingley"
    ],
    "name:deu_x_preferred":[
        "Knottingley"
    ],
    "name:eng_x_preferred":[
        "Knottingley"
    ],
    "name:fas_x_preferred":[
        "\u0646\u0627\u062a\u06cc\u0646\u06af\u0644\u06cc"
    ],
    "name:fra_x_preferred":[
        "Knottingley"
    ],
    "name:gle_x_preferred":[
        "Knottingley"
    ],
    "name:guj_x_preferred":[
        "\u0aa8\u0acb\u0a9f\u0abf\u0a82\u0a97\u0ab2\u0ac0"
    ],
    "name:ita_x_preferred":[
        "Knottingley"
    ],
    "name:jpn_x_preferred":[
        "\u30ce\u30c3\u30c6\u30a3\u30f3\u30b0\u30ea\u30fc"
    ],
    "name:kan_x_preferred":[
        "\u0c95\u0ccd\u0ca8\u0ccb\u0c9f\u0cbf\u0c82\u0c97\u0ccd\u0cb2\u0cbf"
    ],
    "name:kor_x_preferred":[
        "\ub178\ud305\uae00\ub9ac"
    ],
    "name:lit_x_preferred":[
        "Notinglis"
    ],
    "name:nld_x_preferred":[
        "Knottingley"
    ],
    "name:nno_x_preferred":[
        "Knottingley"
    ],
    "name:pol_x_preferred":[
        "Knottingley"
    ],
    "name:por_x_preferred":[
        "Knottingley"
    ],
    "name:ron_x_preferred":[
        "Knottingley"
    ],
    "name:rus_x_preferred":[
        "\u041d\u043e\u0442\u0442\u0438\u043d\u0433\u043b\u0438"
    ],
    "name:spa_x_preferred":[
        "Knottingley"
    ],
    "name:swe_x_preferred":[
        "Knottingley"
    ],
    "name:tam_x_preferred":[
        "\u0b95\u0bcd\u0ba8\u0bcb\u0b9f\u0bcd\u0b9f\u0bbf\u0b99\u0bcd\u0bb2\u0bc7"
    ],
    "name:tel_x_preferred":[
        "\u0c28\u0c3e\u0c1f\u0c4d\u0c1f\u0c3f\u0c28\u0c4d\u0c17\u0c4d\u0c32\u0c47"
    ],
    "name:unk_x_variant":[
        "Knottingly"
    ],
    "name:urd_x_preferred":[
        "\u0646\u0648\u062a\u062a\u06cc\u0646\u062c\u0644\u06d2"
    ],
    "qs:a0":"United Kingdom",
    "qs:a1":"*Wakefield",
    "qs:a1_lc":"GB12DB0000",
    "qs:a1r":"0England",
    "qs:a1r_lc":"GB12000000",
    "qs:adm0":"United Kingdom",
    "qs:la_lc":"*",
    "qs:level":"locality",
    "qs:loc":"Knottingley",
    "qs:loc_alt":"Knottingley",
    "qs:pop":0,
    "qs:type":"buffered point",
    "wd:wordcount":918,
    "wof:name":"Knottingley",
    "wof:placetype":"neighbourhood",
    "wof:population":13804
},
  "geometry": {"coordinates":[-1.25746,53.70858],"type":"Point"}
}