{
  "type": "Feature",
  "properties": {
    "gn:population": 13804,
    "iso:country": "GB",
    "name:ben_x_preferred": [
      "নটিংলে"
    ],
    "name:bul_x_preferred": [
      "Кнотинглей"
    ],
    "name:ceb_x_preferred": [
      "Knottingley"
    ],
    "name:cym_x_preferred": [
      "Knottingley"
    ],
    "name:deu_x_preferred": [
      "Knottingley"
    ],
    "name:eng_x_preferred": [
      "Knottingley"
    ],
    "name:fas_x_preferred": [
      "ناتینگلی"
    ],
    "name:fra_x_preferred": [
      "Knottingley"
    ],
    "name:gle_x_preferred": [
      "Knottingley"
    ],
    "name:guj_x_preferred": [
      "નોટિંગલી"
    ],
    "name:ita_x_preferred": [
      "Knottingley"
    ],
    "name:jpn_x_preferred": [
      "ノッティングリー"
    ],
    "name:kan_x_preferred": [
      "ಕ್ನೋಟಿಂಗ್ಲಿ"
    ],
    "name:kor_x_preferred": [
      "노팅글리"
    ],
    "name:lit_x_preferred": [
      "Notinglis"
    ],
    "name:nld_x_preferred": [
      "Knottingley"
    ],
    "name:nno_x_preferred": [
      "Knottingley"
    ],
    "name:pol_x_preferred": [
      "Knottingley"
    ],
    "name:por_x_preferred": [
      "Knottingley"
    ],
    "name:ron_x_preferred": [
      "Knottingley"
    ],
    "name:rus_x_preferred": [
      "Ноттингли"
    ],
    "name:spa_x_preferred": [
      "Knottingley"
    ],
    "name:swe_x_preferred": [
      "Knottingley"
    ],
    "name:tam_x_preferred": [
      "க்நோட்டிங்லே"
    ],
    "name:tel_x_preferred": [
      "నాట్టిన్గ్లే"
    ],
    "name:und_x_variant": [
      "Knottingly"
    ],
    "name:urd_x_preferred": [
      "نوتتینجلے"
    ],
    "qs:a0": "United Kingdom",
    "qs:a1": "*Wakefield",
    "qs:a1_lc": "GB12DB0000",
    "qs:a1r": "0England",
    "qs:a1r_lc": "GB12000000",
    "qs:adm0": "United Kingdom",
    "qs:la_lc": "*",
    "qs:level": "locality",
    "qs:loc": "Knottingley",
    "qs:loc_alt": "Knottingley",
    "qs:pop": 0,
    "qs:type": "buffered point",
    "wd:wordcount": 918,
    "wof:name": "Knottingley",
    "wof:placetype": "neighbourhood",
    "wof:population": 13804
  },
  "geometry": {"coordinates":[-1.25746,53.70858],"type":"Point"}
}
