{
  "type": "Feature",
  "properties": {
    "iso:country":"GB",
    "name:ara_x_preferred":[
        "\u0646\u0648\u0631\u062a\u0648\u0646"
    ],
    "name:bar_x_preferred":[
        "Norton"
    ],
    "name:cat_x_preferred":[
        "Norton"
    ],
    "name:ceb_x_preferred":[
        "Norton"
    ],
    "name:ces_x_preferred":[
        "Norton"
    ],
    "name:cym_x_preferred":[
        "Norton"
    ],
    "name:dan_x_preferred":[
        "Norton"
    ],
    "name:deu_x_preferred":[
        "Norton"
    ],
    "name:fas_x_preferred":[
        "\u0646\u0648\u0631\u062a\u0648\u0646"
    ],
    "name:fin_x_preferred":[
        "Norton"
    ],
    "name:fra_x_preferred":[
        "Norton"
    ],
    "name:heb_x_preferred":[
        "\u05e0\u05d5\u05e8\u05d8\u05d5\u05df"
    ],
    "name:hun_x_preferred":[
        "Norton"
    ],
    "name:ita_x_preferred":[
        "Norton"
    ],
    "name:jpn_x_preferred":[
        "\u30ce\u30fc\u30c8\u30f3"
    ],
    "name:nld_x_preferred":[
        "Norton"
    ],
    "name:pol_x_preferred":[
        "Norton"
    ],
    "name:por_x_preferred":[
        "Norton"
    ],
    "name:rus_x_preferred":[
        "\u041d\u043e\u0440\u0442\u043e\u043d"
    ],
    "name:spa_x_preferred":[
        "Norton"
    ],
    "name:srp_x_preferred":[
        "\u041d\u043e\u0440\u0442\u043e\u043d"
    ],
    "name:swa_x_preferred":[
        "Norton"
    ],
    "name:swe_x_preferred":[
        "Norton"
    ],
    "name:ukr_x_preferred":[
        "\u041d\u043e\u0440\u0442\u043e\u043d"
    ],
    "name:vol_x_preferred":[
        "Norton"
    ],
    "qs_pg:aaroncc":"GB",
    "qs_pg:name":"Norton",
    "qs_pg:name_adm0":"United Kingdom",
    "qs_pg:name_adm1":"England",
    "qs_pg:photos":17,
    "qs_pg:photos_1k":3,
    "qs_pg:photos_9k":1,
    "qs_pg:photos_9r":1,
    "qs_pg:photos_all":17,
    "qs_pg:photos_sr":1,
    "qs_pg:pop_sr":0,
    "qs_pg:qs_pg_placetype":"locality",
    "qs_pg:qs_pg_placetype_gp":"Town",
    "qs_pg:woe_adm0":23424975,
    "woe:adm0_id":23424975,
    "woe:name_adm0":"United Kingdom",
    "woe:name_adm1":"England",
    "woe:placetype":"Town",
    "wof:name":"Norton",
    "wof:placetype":"neighbourhood"
},
  "geometry": {"coordinates":[0.82068,51.322601],"type":"Point"}
}