{
  "type": "Feature",
  "properties": {
    "iso:country":"GB",
    "name:ceb_x_preferred":[
        "Tonge"
    ],
    "name:deu_x_preferred":[
        "Tonge"
    ],
    "name:fra_x_preferred":[
        "Tonge"
    ],
    "name:pol_x_preferred":[
        "Tonge"
    ],
    "name:swe_x_preferred":[
        "Tonge"
    ],
    "qs_pg:aaroncc":"GB",
    "qs_pg:name":"Tonge",
    "qs_pg:name_adm0":"United Kingdom",
    "qs_pg:name_adm1":"England",
    "qs_pg:photos":39,
    "qs_pg:photos_1k":8,
    "qs_pg:photos_9k":1,
    "qs_pg:photos_9r":2,
    "qs_pg:photos_all":39,
    "qs_pg:photos_sr":2,
    "qs_pg:pop_sr":0,
    "qs_pg:qs_pg_placetype":"locality",
    "qs_pg:qs_pg_placetype_gp":"Town",
    "qs_pg:woe_adm0":23424975,
    "woe:adm0_id":23424975,
    "woe:name_adm0":"United Kingdom",
    "woe:name_adm1":"England",
    "woe:placetype":"Town",
    "wof:name":"Tonge",
    "wof:placetype":"neighbourhood"
},
  "geometry": {"coordinates":[-1.379106,52.804901],"type":"Point"}
}