{
  "type": "Feature",
  "properties": {
    "gn:gn_country":"GB",
    "gn:gn_fcode":"PPL",
    "gn:gn_pop":0,
    "iso:country":"GB",
    "name:eng_x_preferred":[
        "Hatton of Fintray"
    ],
    "name:eus_x_preferred":[
        "Hatton of Fintray"
    ],
    "name:fra_x_preferred":[
        "Fintray"
    ],
    "name:gle_x_preferred":[
        "Fionntraigh"
    ],
    "name:nld_x_preferred":[
        "Hatton of Fintray"
    ],
    "name:unk_x_variant":[
        "Fintray"
    ],
    "qs_pg:aaroncc":"GB",
    "qs_pg:gn_country":"GB",
    "qs_pg:gn_fcode":"PPL",
    "qs_pg:gn_pop":0,
    "qs_pg:name":"Hatton of Fintray",
    "qs_pg:name_adm0":"United Kingdom",
    "qs_pg:name_adm1":"Scotland",
    "qs_pg:photos":1173,
    "qs_pg:photos_1k":238,
    "qs_pg:photos_9k":5,
    "qs_pg:photos_9r":7,
    "qs_pg:photos_all":1173,
    "qs_pg:photos_sr":11,
    "qs_pg:pop_sr":0,
    "qs_pg:qs_pg_placetype":"locality",
    "qs_pg:qs_pg_placetype_gp":"Town",
    "qs_pg:woe_adm0":23424975,
    "woe:adm0_id":23424975,
    "woe:name_adm0":"United Kingdom",
    "woe:name_adm1":"Scotland",
    "woe:placetype":"Town",
    "wof:name":"Hatton of Fintray",
    "wof:placetype":"locality"
},
  "geometry": {"coordinates":[-2.26318,57.23824],"type":"Point"}
}