{
  "type": "Feature",
  "properties": {
    "gn:admin1_code": "ENG",
    "gn:admin2_code": "M7",
    "gn:asciiname": "Marsden",
    "gn:country_code": "GB",
    "gn:dem": 36,
    "gn:feature_class": "P",
    "gn:feature_code": "PPL",
    "gn:name": "Marsden",
    "gn:population": 0,
    "gn:timezone": "Europe/London",
    "iso:country": "GB",
    "name:pol_x_preferred": [
      "Marsden"
    ],
    "wof:name": "Marsden",
    "wof:placetype": "neighbourhood"
  },
  "geometry": {"coordinates":[-1.36667,54.96666999999999],"type":"Point"}
}
