{
  "type": "Feature",
  "properties": {
    "iso:country":"GB",
    "name:bul_x_preferred":[
        "\u041d\u044e \u0411\u0440\u0430\u0439\u0442\u044a\u043d"
    ],
    "name:cat_x_preferred":[
        "New Brighton"
    ],
    "name:ceb_x_preferred":[
        "New Brighton"
    ],
    "name:deu_x_preferred":[
        "New Brighton"
    ],
    "name:fra_x_preferred":[
        "New Brighton"
    ],
    "name:ita_x_preferred":[
        "New Brighton"
    ],
    "name:kor_x_preferred":[
        "\ub274\ube0c\ub77c\uc774\ud134"
    ],
    "name:nld_x_preferred":[
        "New Brighton"
    ],
    "name:pol_x_preferred":[
        "New Brighton"
    ],
    "name:spa_x_preferred":[
        "New Brighton"
    ],
    "name:srp_x_preferred":[
        "\u040a\u0443 \u0411\u0440\u0430\u0458\u0442\u043e\u043d"
    ],
    "name:swe_x_preferred":[
        "New Brighton"
    ],
    "name:ukr_x_preferred":[
        "\u041d\u044c\u044e-\u0411\u0440\u0430\u0439\u0442\u043e\u043d"
    ],
    "name:vol_x_preferred":[
        "New Brighton"
    ],
    "qs_pg:aaroncc":"GB",
    "qs_pg:name":"New Brighton",
    "qs_pg:name_adm0":"United Kingdom",
    "qs_pg:name_adm1":"Wales",
    "qs_pg:photos":148,
    "qs_pg:photos_1k":30,
    "qs_pg:photos_9k":1,
    "qs_pg:photos_9r":3,
    "qs_pg:photos_all":148,
    "qs_pg:photos_sr":3,
    "qs_pg:pop_sr":0,
    "qs_pg:qs_pg_placetype":"locality",
    "qs_pg:qs_pg_placetype_gp":"Town",
    "qs_pg:woe_adm0":23424975,
    "woe:adm0_id":23424975,
    "woe:name_adm0":"United Kingdom",
    "woe:name_adm1":"Wales",
    "woe:placetype":"Town",
    "wof:name":"New Brighton",
    "wof:placetype":"neighbourhood"
},
  "geometry": {"coordinates":[-3.116866,53.180343],"type":"Point"}
}