{
  "type": "Feature",
  "properties": {
    "gn:admin1_code":"ENG",
    "gn:admin2_code":"F8",
    "gn:admin3_code":"26UD",
    "gn:admin4_code":"26UD007",
    "gn:asciiname":"Chapmore End",
    "gn:country_code":"GB",
    "gn:dem":75,
    "gn:feature_class":"P",
    "gn:feature_code":"PPL",
    "gn:name":"Chapmore End",
    "gn:population":0,
    "gn:timezone":"Europe/London",
    "iso:country":"GB",
    "name:pol_x_preferred":[
        "Chapmore End"
    ],
    "wof:name":"Chapmore End",
    "wof:placetype":"neighbourhood"
},
  "geometry": {"coordinates":[-0.07454,51.83206],"type":"Point"}
}