{
  "type": "Feature",
  "properties": {
    "gn:admin1_code": "ENG",
    "gn:admin2_code": "J1",
    "gn:admin3_code": "34UH",
    "gn:asciiname": "Harrowden",
    "gn:country_code": "GB",
    "gn:dem": 77,
    "gn:feature_class": "P",
    "gn:feature_code": "PPL",
    "gn:name": "Harrowden",
    "gn:population": 0,
    "gn:timezone": "Europe/London",
    "iso:country": "GB",
    "wof:name": "Harrowden",
    "wof:placetype": "neighbourhood"
  },
  "geometry": {"coordinates":[-0.71667,52.31667],"type":"Point"}
}
