{
  "type": "Feature",
  "properties": {
    "iso:country":"GB",
    "name:eng_x_preferred":[
        "New Brighton"
    ],
    "name:eng_x_variant":[
        "Newbrighton"
    ],
    "name:unk_x_variant":[
        "New Brighton"
    ],
    "qs:gn_adm0_cc":"GB",
    "qs:gn_fcode":"PPL",
    "qs:gn_local":2634192,
    "qs:gn_nam_loc":"settle",
    "qs:gn_namadm1":"ENG",
    "qs:gn_name":"New Brighton",
    "qs:local_max":5349,
    "qs:local_sum":11195,
    "qs:localhoods":4,
    "qs:name":"New Brighton",
    "qs:name_adm0":"United Kingdom",
    "qs:name_adm1":"England",
    "qs:name_adm2":"Merseyside",
    "qs:name_lau":"Wirral Metropolitan Borough",
    "qs:name_local":"Wallasey",
    "qs:photo_max":676,
    "qs:photo_sum":5349,
    "qs:placetype":"Suburb",
    "qs:quad_count":126,
    "qs:woe_adm0":23424975,
    "qs:woe_adm1":24554868,
    "qs:woe_adm2":12602161,
    "qs:woe_lau":12695853,
    "qs:woe_local":39017,
    "qs:woe_ver":"7.10.0",
    "wof:lang":[
        "eng"
    ],
    "wof:name":"New Brighton",
    "wof:placetype":"neighbourhood"
},
  "geometry": {"coordinates":[-3.050872,53.438716],"type":"Point"}
}