{
  "type": "Feature",
  "properties": {
    "gn:country":"GB",
    "gn:fcode":"PPL",
    "gn:population":0,
    "iso:country":"GB",
    "name:cor_x_preferred":[
        "Bostalek"
    ],
    "name:cym_x_preferred":[
        "Botallack"
    ],
    "name:cym_x_variant":[
        "Bostalek"
    ],
    "name:eng_x_preferred":[
        "Botallack"
    ],
    "name:eus_x_preferred":[
        "Botallack"
    ],
    "name:fra_x_preferred":[
        "Botallack"
    ],
    "name:gle_x_preferred":[
        "Botallack"
    ],
    "name:nld_x_preferred":[
        "Botallack"
    ],
    "name:pol_x_preferred":[
        "Botallack"
    ],
    "name:pol_x_variant":[
        "Bouldnor"
    ],
    "name:rus_x_preferred":[
        "\u0411\u043e\u0442\u043e\u043b\u044d\u043a"
    ],
    "qs_pg:aaroncc":"GB",
    "qs_pg:gn_country":"GB",
    "qs_pg:gn_fcode":"PPL",
    "qs_pg:gn_pop":0,
    "qs_pg:name":"Botallack",
    "qs_pg:name_adm0":"United Kingdom",
    "qs_pg:name_adm1":"England",
    "qs_pg:photos":944,
    "qs_pg:photos_1k":191,
    "qs_pg:photos_9k":4,
    "qs_pg:photos_9r":6,
    "qs_pg:photos_all":944,
    "qs_pg:photos_sr":10,
    "qs_pg:pop_sr":0,
    "qs_pg:qs_pg_placetype":"locality",
    "qs_pg:qs_pg_placetype_gp":"Town",
    "qs_pg:woe_adm0":23424975,
    "woe:adm0_id":23424975,
    "woe:name_adm0":"United Kingdom",
    "woe:name_adm1":"England",
    "woe:placetype":"Town",
    "wof:name":"Botallack",
    "wof:placetype":"neighbourhood"
},
  "geometry": {"coordinates":[-5.68238,50.13771],"type":"Point"}
}