{
  "type": "Feature",
  "properties": {
    "iso:country":"GB",
    "name:ceb_x_preferred":[
        "Newton Morrell"
    ],
    "name:fas_x_preferred":[
        "\u0646\u06cc\u0648\u062a\u0646 \u0645\u0648\u0631\u0644"
    ],
    "name:nld_x_preferred":[
        "Newton Morrell"
    ],
    "name:pol_x_preferred":[
        "Newton Morrell"
    ],
    "name:swe_x_preferred":[
        "Newton Morrell"
    ],
    "qs_pg:aaroncc":"GB",
    "qs_pg:name":"Newton Morrell",
    "qs_pg:name_adm0":"United Kingdom",
    "qs_pg:name_adm1":"England",
    "qs_pg:photos":38,
    "qs_pg:photos_1k":8,
    "qs_pg:photos_9k":1,
    "qs_pg:photos_9r":2,
    "qs_pg:photos_all":38,
    "qs_pg:photos_sr":2,
    "qs_pg:pop_sr":0,
    "qs_pg:qs_pg_placetype":"locality",
    "qs_pg:qs_pg_placetype_gp":"Town",
    "qs_pg:woe_adm0":23424975,
    "woe:adm0_id":23424975,
    "woe:name_adm0":"United Kingdom",
    "woe:name_adm1":"England",
    "woe:placetype":"Town",
    "wof:name":"Newton Morrell",
    "wof:placetype":"neighbourhood"
},
  "geometry": {"coordinates":[-1.092717,51.962126],"type":"Point"}
}