{
  "type": "Feature",
  "properties": {
    "iso:country": "GB",
    "name:azb_x_preferred": [
      "فریهیل"
    ],
    "name:ceb_x_preferred": [
      "Ferryhill"
    ],
    "name:cym_x_preferred": [
      "Ferryhill"
    ],
    "name:eng_x_preferred": [
      "Ferryhill"
    ],
    "name:fas_x_preferred": [
      "فریهیل"
    ],
    "name:fra_x_preferred": [
      "Ferryhill"
    ],
    "name:ita_x_preferred": [
      "Ferryhill"
    ],
    "name:nld_x_preferred": [
      "Ferryhill"
    ],
    "name:nno_x_preferred": [
      "Ferryhill"
    ],
    "name:pol_x_preferred": [
      "Ferryhill"
    ],
    "name:ron_x_preferred": [
      "Ferryhill"
    ],
    "name:swe_x_preferred": [
      "Ferryhill"
    ],
    "name:vol_x_preferred": [
      "Ferryhill"
    ],
    "qs:gn_adm0_cc": "GB",
    "qs:gn_local": 0,
    "qs:gn_nam_loc": "aultmore",
    "qs:gn_namadm1": "SCT",
    "qs:local_max": 5072,
    "qs:local_sum": 21104,
    "qs:localhoods": 11,
    "qs:name": "Ferryhill",
    "qs:name_adm0": "United Kingdom",
    "qs:name_adm1": "Scotland",
    "qs:name_adm2": "Grampian",
    "qs:name_lau": "Aberdeen City",
    "qs:name_local": "Aberdeen",
    "qs:photo_max": 586,
    "qs:photo_sum": 5072,
    "qs:placetype": "Suburb",
    "qs:quad_count": 93,
    "qs:woe_adm0": 23424975,
    "qs:woe_adm1": 12578048,
    "qs:woe_adm2": 12602202,
    "qs:woe_lau": 12696182,
    "qs:woe_local": 10243,
    "qs:woe_ver": "7.10.0",
    "wd:wordcount": 793,
    "wof:lang": [
      "eng"
    ],
    "wof:name": "Ferryhill",
    "wof:placetype": "neighbourhood"
  },
  "geometry": {"coordinates":[-2.10198,57.142751],"type":"Point"}
}
