{
  "type": "Feature",
  "properties": {
    "gn:admin1_code":"NIR",
    "gn:admin2_code":"N09000006",
    "gn:asciiname":"Garrison",
    "gn:country_code":"GB",
    "gn:dem":47,
    "gn:feature_class":"P",
    "gn:feature_code":"PPL",
    "gn:name":"Garrison",
    "gn:population":0,
    "gn:timezone":"Europe/London",
    "iso:country":"GB",
    "wof:name":"Garrison",
    "wof:placetype":"locality"
},
  "geometry": {"coordinates":[-8.08333,54.41667],"type":"Point"}
}