{
  "type": "Feature",
  "properties": {
    "gn:admin1_code": "NIR",
    "gn:admin2_code": "N09000006",
    "gn:asciiname": "Garrison",
    "gn:country_code": "GB",
    "gn:dem": 47,
    "gn:feature_class": "P",
    "gn:feature_code": "PPL",
    "gn:name": "Garrison",
    "gn:population": 0,
    "gn:timezone": "Europe/London",
    "iso:country": "GB",
    "name:afr_x_preferred": [
      "Garnisoen"
    ],
    "name:ara_x_preferred": [
      "حامية عسكرية"
    ],
    "name:bel_x_preferred": [
      "Гарнізон"
    ],
    "name:bos_x_preferred": [
      "Garnizon"
    ],
    "name:bul_x_preferred": [
      "Гарнизон"
    ],
    "name:cat_x_preferred": [
      "Guarnició"
    ],
    "name:dan_x_preferred": [
      "Garnison"
    ],
    "name:deu_x_preferred": [
      "Garnison"
    ],
    "name:ell_x_preferred": [
      "Φρουρά"
    ],
    "name:epo_x_preferred": [
      "Garnizono"
    ],
    "name:est_x_preferred": [
      "Garnison"
    ],
    "name:eus_x_preferred": [
      "Garnizio"
    ],
    "name:fas_x_preferred": [
      "پادگان"
    ],
    "name:fin_x_preferred": [
      "Varuskunta"
    ],
    "name:fra_x_preferred": [
      "Garnison"
    ],
    "name:fry_x_preferred": [
      "Garnizoen"
    ],
    "name:gla_x_preferred": [
      "Gearastan"
    ],
    "name:heb_x_preferred": [
      "חיל מצב"
    ],
    "name:hrv_x_preferred": [
      "Garnizon"
    ],
    "name:hye_x_preferred": [
      "Կայազոր"
    ],
    "name:ido_x_preferred": [
      "Garnizono"
    ],
    "name:ind_x_preferred": [
      "Garnisun"
    ],
    "name:ita_x_preferred": [
      "Guarnigione"
    ],
    "name:jpn_x_preferred": [
      "駐屯地"
    ],
    "name:kan_x_preferred": [
      "ಕಾವಲುಪಡೆ"
    ],
    "name:kat_x_preferred": [
      "გარნიზონი"
    ],
    "name:kaz_x_preferred": [
      "Гарнизон"
    ],
    "name:kir_x_preferred": [
      "Гарнизон"
    ],
    "name:kor_x_preferred": [
      "주둔지"
    ],
    "name:lit_x_preferred": [
      "Įgula"
    ],
    "name:msa_x_preferred": [
      "Garison"
    ],
    "name:nld_x_preferred": [
      "Garnizoen"
    ],
    "name:nno_x_preferred": [
      "Garnison"
    ],
    "name:nor_x_preferred": [
      "Garnison"
    ],
    "name:oci_x_preferred": [
      "Garnison"
    ],
    "name:pol_x_preferred": [
      "Garnizon"
    ],
    "name:por_x_preferred": [
      "Guarnição"
    ],
    "name:ron_x_preferred": [
      "Garnizoană"
    ],
    "name:rus_x_preferred": [
      "Гарнизон"
    ],
    "name:slk_x_preferred": [
      "Posádka"
    ],
    "name:slv_x_preferred": [
      "Garnizija"
    ],
    "name:spa_x_preferred": [
      "Guarnición"
    ],
    "name:srp_x_preferred": [
      "Гарнизон"
    ],
    "name:swe_x_preferred": [
      "Garnison"
    ],
    "name:tur_x_preferred": [
      "Garnizon"
    ],
    "name:tyv_x_preferred": [
      "Гарнизон"
    ],
    "name:ukr_x_preferred": [
      "Гарнізон"
    ],
    "name:zho_x_preferred": [
      "屯駐地"
    ],
    "wof:name": "Garrison",
    "wof:placetype": "locality"
  },
  "geometry": {"coordinates":[-8.08333,54.41667],"type":"Point"}
}
