{
  "type": "Feature",
  "properties": {
    "iso:country":"GB",
    "name:eng_x_preferred":[
        "Keiss"
    ],
    "name:eus_x_preferred":[
        "Keiss"
    ],
    "name:gla_x_preferred":[
        "C\u00e8is"
    ],
    "name:gle_x_preferred":[
        "C\u00e9is"
    ],
    "name:gle_x_variant":[
        "C\u00e8is"
    ],
    "name:nld_x_preferred":[
        "Keiss"
    ],
    "name:swe_x_preferred":[
        "Keiss"
    ],
    "qs_pg:aaroncc":"GB",
    "qs_pg:name":"Keiss",
    "qs_pg:name_adm0":"United Kingdom",
    "qs_pg:name_adm1":"Scotland",
    "qs_pg:photos":109,
    "qs_pg:photos_1k":22,
    "qs_pg:photos_9k":1,
    "qs_pg:photos_9r":3,
    "qs_pg:photos_all":109,
    "qs_pg:photos_sr":3,
    "qs_pg:pop_sr":0,
    "qs_pg:qs_pg_placetype":"locality",
    "qs_pg:qs_pg_placetype_gp":"Town",
    "qs_pg:woe_adm0":23424975,
    "woe:adm0_id":23424975,
    "woe:name_adm0":"United Kingdom",
    "woe:name_adm1":"Scotland",
    "woe:placetype":"Town",
    "wof:name":"Keiss",
    "wof:placetype":"locality"
},
  "geometry": {"coordinates":[-3.120117,58.531777],"type":"Point"}
}