{
  "type": "Feature",
  "properties": {
    "gn:admin1_code":"SCT",
    "gn:admin2_code":"T7",
    "gn:asciiname":"Braehead Village",
    "gn:country_code":"GB",
    "gn:dem":96,
    "gn:feature_class":"P",
    "gn:feature_code":"PPL",
    "gn:name":"Braehead Village",
    "gn:population":0,
    "gn:timezone":"Europe/London",
    "iso:country":"GB",
    "wof:name":"Braehead Village",
    "wof:placetype":"locality"
},
  "geometry": {"coordinates":[-2.51553,56.66837],"type":"Point"}
}