{
  "type": "Feature",
  "properties": {
    "gn:population":1309,
    "iso:country":"GB",
    "name:afr_x_preferred":[
        "Bushmills"
    ],
    "name:bul_x_preferred":[
        "\u0411\u0443\u0448\u043c\u0438\u043b\u0441"
    ],
    "name:ceb_x_preferred":[
        "Bushmills"
    ],
    "name:ces_x_preferred":[
        "Bushmills"
    ],
    "name:deu_x_preferred":[
        "Bushmills"
    ],
    "name:eng_x_preferred":[
        "Bushmills"
    ],
    "name:eus_x_preferred":[
        "Bushmills"
    ],
    "name:fas_x_preferred":[
        "\u0628\u0648\u0634\u0645\u06cc\u0644\u0632"
    ],
    "name:fra_x_preferred":[
        "Bushmills"
    ],
    "name:gla_x_preferred":[
        "Muileann na Buaise"
    ],
    "name:gle_x_preferred":[
        "Muileann na Buaise"
    ],
    "name:ita_x_preferred":[
        "Bushmills"
    ],
    "name:jpn_x_preferred":[
        "\u30d6\u30c3\u30b7\u30e5\u30df\u30eb\u30ba"
    ],
    "name:msa_x_preferred":[
        "Bushmills"
    ],
    "name:nld_x_preferred":[
        "Bushmills"
    ],
    "name:nob_x_preferred":[
        "Bushmills"
    ],
    "name:nor_x_preferred":[
        "Bushmills"
    ],
    "name:pli_x_preferred":[
        "\u092c\u0941\u0936\u094d\u092e\u093f\u0932\u094d\u0932\u094d\u0938"
    ],
    "name:rus_x_preferred":[
        "\u0411\u0443\u0448\u043c\u0438\u043b\u0441"
    ],
    "name:sco_x_preferred":[
        "Bushmill"
    ],
    "name:spa_x_preferred":[
        "Bushmills"
    ],
    "name:swe_x_preferred":[
        "Bushmills"
    ],
    "qs:a0":"United Kingdom",
    "qs:a1":"*Moyle",
    "qs:a1_lc":"N_A",
    "qs:a1r":"0Northern Ireland",
    "qs:a1r_lc":"N_A",
    "qs:adm0":"United Kingdom",
    "qs:la_lc":"*",
    "qs:level":"locality",
    "qs:loc":"Bushmills",
    "qs:loc_alt":"Bushmills",
    "qs:pop":0,
    "qs:type":"buffered point",
    "wd:wordcount":564,
    "wof:name":"Bushmills",
    "wof:placetype":"locality",
    "wof:population":1309
},
  "geometry": {"coordinates":[-6.522303,55.203109],"type":"Point"}
}