{
  "type": "Feature",
  "properties": {
    "gn:country":"GB",
    "gn:fcode":"PPL",
    "gn:population":0,
    "iso:country":"GB",
    "name:bre_x_preferred":[
        "Garnant"
    ],
    "name:ces_x_preferred":[
        "Garnant"
    ],
    "name:cym_x_preferred":[
        "Garnant"
    ],
    "name:deu_x_preferred":[
        "Garnant"
    ],
    "name:eng_x_preferred":[
        "Garnant"
    ],
    "name:eus_x_preferred":[
        "Pontnewynydd"
    ],
    "name:eus_x_variant":[
        "Garnant"
    ],
    "name:fas_x_preferred":[
        "\u06af\u0627\u0631\u0646\u0627\u0646\u062a"
    ],
    "name:fra_x_preferred":[
        "Garnant"
    ],
    "name:gla_x_preferred":[
        "Garnant"
    ],
    "name:gle_x_preferred":[
        "Garnant"
    ],
    "name:heb_x_preferred":[
        "\u05d2\u05e8\u05e0\u05e8\u05d8"
    ],
    "name:hun_x_preferred":[
        "Garnant"
    ],
    "name:nld_x_preferred":[
        "Garnant"
    ],
    "name:oci_x_preferred":[
        "Garnant"
    ],
    "name:sco_x_preferred":[
        "Garnant"
    ],
    "name:slk_x_preferred":[
        "Garnant"
    ],
    "qs_pg:aaroncc":"GB",
    "qs_pg:gn_country":"GB",
    "qs_pg:gn_fcode":"PPL",
    "qs_pg:gn_pop":0,
    "qs_pg:name":"Garnant",
    "qs_pg:name_adm0":"United Kingdom",
    "qs_pg:name_adm1":"Wales",
    "qs_pg:photos":12,
    "qs_pg:photos_1k":2,
    "qs_pg:photos_9k":1,
    "qs_pg:photos_9r":1,
    "qs_pg:photos_all":12,
    "qs_pg:photos_sr":1,
    "qs_pg:pop_sr":0,
    "qs_pg:qs_pg_placetype":"locality",
    "qs_pg:qs_pg_placetype_gp":"Town",
    "qs_pg:woe_adm0":23424975,
    "woe:adm0_id":23424975,
    "woe:name_adm0":"United Kingdom",
    "woe:name_adm1":"Wales",
    "woe:placetype":"Town",
    "wof:name":"Garnant",
    "wof:placetype":"neighbourhood"
},
  "geometry": {"coordinates":[-3.90561,51.80153],"type":"Point"}
}