{
  "type": "Feature",
  "properties": {
    "gn:country":"GB",
    "gn:fcode":"PPL",
    "gn:population":3560,
    "iso:country":"GB",
    "name:bul_x_preferred":[
        "\u041a\u0438\u043b\u0431\u0430\u0440\u0447\u0430\u043d"
    ],
    "name:ceb_x_preferred":[
        "Kilbarchan"
    ],
    "name:deu_x_preferred":[
        "Kilbarchan"
    ],
    "name:eng_x_preferred":[
        "Kilbarchan"
    ],
    "name:eus_x_preferred":[
        "Kilbarchan"
    ],
    "name:fas_x_preferred":[
        "\u06a9\u06cc\u0644\u0628\u0627\u0631\u0686\u0627\u0646"
    ],
    "name:fra_x_preferred":[
        "Kilbarchan"
    ],
    "name:gla_x_preferred":[
        "Cill Bhearchain"
    ],
    "name:gle_x_preferred":[
        "Cill Bhearchain"
    ],
    "name:heb_x_preferred":[
        "\u05e7\u05d9\u05dc\u05d1\u05d0\u05e8\u05db\u05df"
    ],
    "name:ita_x_preferred":[
        "Kilbarchan"
    ],
    "name:jpn_x_preferred":[
        "\u30ad\u30eb\u30d0\u30fc\u30b7\u30e3\u30f3"
    ],
    "name:nld_x_preferred":[
        "Kilbarchan"
    ],
    "name:spa_x_preferred":[
        "Kilbarchan"
    ],
    "name:swe_x_preferred":[
        "Kilbarchan"
    ],
    "qs_pg:aaroncc":"GB",
    "qs_pg:gn_country":"GB",
    "qs_pg:gn_fcode":"PPL",
    "qs_pg:gn_pop":3560,
    "qs_pg:name":"Kilbarchan",
    "qs_pg:name_adm0":"United Kingdom",
    "qs_pg:name_adm1":"Scotland",
    "qs_pg:photos":139,
    "qs_pg:photos_1k":28,
    "qs_pg:photos_9k":1,
    "qs_pg:photos_9r":3,
    "qs_pg:photos_all":139,
    "qs_pg:photos_sr":3,
    "qs_pg:pop_sr":4,
    "qs_pg:qs_pg_placetype":"locality",
    "qs_pg:qs_pg_placetype_gp":"Town",
    "qs_pg:woe_adm0":23424975,
    "woe:adm0_id":23424975,
    "woe:name_adm0":"United Kingdom",
    "woe:name_adm1":"Scotland",
    "woe:placetype":"Town",
    "wof:name":"Kilbarchan",
    "wof:placetype":"locality",
    "wof:population":3580
},
  "geometry": {"coordinates":[-4.55356,55.8362],"type":"Point"}
}