{
  "type": "Feature",
  "properties": {
    "gn:country":"GB",
    "iso:country":"GB",
    "name:amh_x_preferred":[
        "\u1262\u127a \u12b8\u12f5"
    ],
    "name:cat_x_preferred":[
        "Beachy Head"
    ],
    "name:ces_x_preferred":[
        "Beachy Head"
    ],
    "name:cym_x_preferred":[
        "Pentir Beachy"
    ],
    "name:deu_x_preferred":[
        "Beachy Head"
    ],
    "name:epo_x_preferred":[
        "Beachy Head"
    ],
    "name:fin_x_preferred":[
        "Beachy Head"
    ],
    "name:fra_x_preferred":[
        "Beachy Head"
    ],
    "name:glg_x_preferred":[
        "Beachy Head"
    ],
    "name:hye_x_preferred":[
        "\u0532\u056b\u0579\u056b-\u0540\u0565\u0564"
    ],
    "name:ita_x_preferred":[
        "Beachy Head"
    ],
    "name:jpn_x_preferred":[
        "\u30d3\u30fc\u30c1\u30fc\u5cac"
    ],
    "name:kaz_x_preferred":[
        "\u0411\u0438\u0447\u0438-\u0425\u0435\u0434"
    ],
    "name:lit_x_preferred":[
        "Bi\u010dio ky\u0161ulys"
    ],
    "name:nld_x_preferred":[
        "Beachy Head"
    ],
    "name:nno_x_preferred":[
        "Beachy Head"
    ],
    "name:nor_x_preferred":[
        "Beachy Head"
    ],
    "name:pol_x_preferred":[
        "Beachy Head"
    ],
    "name:por_x_preferred":[
        "Beachy Head"
    ],
    "name:rus_x_preferred":[
        "\u0411\u0438\u0447\u0438-\u0425\u0435\u0434"
    ],
    "name:slv_x_preferred":[
        "Beachy Head"
    ],
    "name:spa_x_preferred":[
        "Cabo Beachy"
    ],
    "name:swe_x_preferred":[
        "Beachy Head"
    ],
    "name:tur_x_preferred":[
        "Beachy Head"
    ],
    "name:vie_x_preferred":[
        "Beachy Head"
    ],
    "name:wuu_x_preferred":[
        "\u6602\u5934\u89d2"
    ],
    "name:zho_x_preferred":[
        "\u6bd4\u5947\u89d2"
    ],
    "qs_pg:aaroncc":"GB",
    "qs_pg:gn_country":"GB",
    "qs_pg:name":"Beachy Head",
    "qs_pg:name_adm0":"United Kingdom",
    "qs_pg:name_adm1":"England",
    "qs_pg:photos":4892,
    "qs_pg:photos_1k":991,
    "qs_pg:photos_9k":22,
    "qs_pg:photos_9r":13,
    "qs_pg:photos_all":4892,
    "qs_pg:photos_sr":24,
    "qs_pg:pop_sr":0,
    "qs_pg:qs_pg_placetype":"locality",
    "qs_pg:qs_pg_placetype_gp":"Town",
    "qs_pg:woe_adm0":23424975,
    "woe:adm0_id":23424975,
    "woe:name_adm0":"United Kingdom",
    "woe:name_adm1":"England",
    "woe:placetype":"Town",
    "wof:name":"Beachy Head",
    "wof:placetype":"neighbourhood"
},
  "geometry": {"coordinates":[0.244445,50.736998],"type":"Point"}
}