{
  "type": "Feature",
  "properties": {
    "gn:country":"GB",
    "gn:fcode":"PPL",
    "gn:population":0,
    "iso:country":"GB",
    "name:bre_x_preferred":[
        "Sgiwen"
    ],
    "name:bul_x_preferred":[
        "\u0421\u043a\u0438\u0443\u0435\u043d"
    ],
    "name:cat_x_preferred":[
        "Skewen"
    ],
    "name:ceb_x_preferred":[
        "Skewen"
    ],
    "name:cym_x_preferred":[
        "Sgiwen"
    ],
    "name:eng_x_preferred":[
        "Skewen"
    ],
    "name:eus_x_preferred":[
        "Skewen"
    ],
    "name:fra_x_preferred":[
        "Skewen"
    ],
    "name:gle_x_preferred":[
        "Sgiwen"
    ],
    "name:heb_x_preferred":[
        "\u05e1\u05e7\u05d9\u05d5\u05d0\u05df"
    ],
    "name:ita_x_preferred":[
        "Skewen"
    ],
    "name:nld_x_preferred":[
        "Skewen"
    ],
    "name:rus_x_preferred":[
        "\u0421\u043a\u0443\u044d\u043d"
    ],
    "name:spa_x_preferred":[
        "Skewen"
    ],
    "name:swe_x_preferred":[
        "Skewen"
    ],
    "name:szl_x_preferred":[
        "Skewen"
    ],
    "qs_pg:aaroncc":"GB",
    "qs_pg:gn_country":"GB",
    "qs_pg:gn_fcode":"PPL",
    "qs_pg:gn_pop":0,
    "qs_pg:name":"Skewen",
    "qs_pg:name_adm0":"United Kingdom",
    "qs_pg:name_adm1":"Wales",
    "qs_pg:photos":42,
    "qs_pg:photos_1k":9,
    "qs_pg:photos_9k":1,
    "qs_pg:photos_9r":2,
    "qs_pg:photos_all":42,
    "qs_pg:photos_sr":2,
    "qs_pg:pop_sr":0,
    "qs_pg:qs_pg_placetype":"locality",
    "qs_pg:qs_pg_placetype_gp":"Town",
    "qs_pg:woe_adm0":23424975,
    "woe:adm0_id":23424975,
    "woe:name_adm0":"United Kingdom",
    "woe:name_adm1":"Wales",
    "woe:placetype":"Town",
    "wof:name":"Skewen",
    "wof:placetype":"neighbourhood"
},
  "geometry": {"coordinates":[-3.84994,51.66035],"type":"Point"}
}