{
  "type": "Feature",
  "properties": {
    "gn:admin1_code":"ENG",
    "gn:admin2_code":"F7",
    "gn:admin3_code":"00GA060",
    "gn:asciiname":"Steens Bridge",
    "gn:country_code":"GB",
    "gn:dem":130,
    "gn:feature_class":"P",
    "gn:feature_code":"PPL",
    "gn:name":"Steens Bridge",
    "gn:population":0,
    "gn:timezone":"Europe/London",
    "iso:country":"GB",
    "wof:name":"Steens Bridge",
    "wof:placetype":"neighbourhood"
},
  "geometry": {"coordinates":[-2.66667,52.21667],"type":"Point"}
}