{
  "type": "Feature",
  "properties": {
    "iso:country": "GB",
    "wof:name": "Carr House Gate",
    "wof:placetype": "neighbourhood"
  },
  "geometry": {"coordinates":[-1.77364096043702,53.7465167552068],"type":"Point"}
}
