{
  "type": "Feature",
  "properties": {
    "iso:country": "GB",
    "name:eng_x_preferred": [
      "Newthorpe"
    ],
    "name:nld_x_preferred": [
      "Newthorpe"
    ],
    "name:pol_x_preferred": [
      "Newthorpe"
    ],
    "name:pol_x_variant": [
      "Newthorpe"
    ],
    "qs_pg:aaroncc": "GB",
    "qs_pg:name": "Newthorpe",
    "qs_pg:name_adm0": "United Kingdom",
    "qs_pg:name_adm1": "England",
    "qs_pg:photos": 454,
    "qs_pg:photos_1k": 92,
    "qs_pg:photos_9k": 2,
    "qs_pg:photos_9r": 5,
    "qs_pg:photos_all": 454,
    "qs_pg:photos_sr": 7,
    "qs_pg:pop_sr": 0,
    "qs_pg:qs_pg_placetype": "locality",
    "qs_pg:qs_pg_placetype_gp": "Town",
    "qs_pg:woe_adm0": 23424975,
    "woe:adm0_id": 23424975,
    "woe:name_adm0": "United Kingdom",
    "woe:name_adm1": "England",
    "woe:placetype": "Town",
    "wof:name": "Newthorpe",
    "wof:placetype": "neighbourhood"
  },
  "geometry": {"coordinates":[-1.287631,53.782955],"type":"Point"}
}
