{
  "type": "Feature",
  "properties": {
    "gn:admin1_code": "NIR",
    "gn:admin2_code": "N09000009",
    "gn:asciiname": "Galbally",
    "gn:country_code": "GB",
    "gn:dem": 126,
    "gn:feature_class": "P",
    "gn:feature_code": "PPL",
    "gn:name": "Galbally",
    "gn:population": 0,
    "gn:timezone": "Europe/London",
    "iso:country": "GB",
    "wof:name": "Galbally",
    "wof:placetype": "locality"
  },
  "geometry": {"coordinates":[-6.88333,54.53333000000001],"type":"Point"}
}
