{
  "type": "Feature",
  "properties": {
    "gn:country":"GB",
    "gn:fcode":"PPL",
    "gn:population":0,
    "iso:country":"GB",
    "name:bel_x_preferred":[
        "\u0406\u043d\u0456\u0448\u043c\u043e\u0440"
    ],
    "name:bre_x_preferred":[
        "Inis M\u00f3r"
    ],
    "name:cat_x_preferred":[
        "Inis M\u00f3r"
    ],
    "name:ceb_x_preferred":[
        "Aranmore"
    ],
    "name:cym_x_preferred":[
        "Inis M\u00f3r"
    ],
    "name:deu_x_preferred":[
        "\u00c1rainn"
    ],
    "name:ell_x_preferred":[
        "\u038a\u03bd\u03b9\u03c3\u03bc\u03bf\u03c1"
    ],
    "name:epo_x_preferred":[
        "Insulo Ini\u015dmoro"
    ],
    "name:eus_x_preferred":[
        "Inis M\u00f3r"
    ],
    "name:fin_x_preferred":[
        "Inis M\u00f3r"
    ],
    "name:fra_x_preferred":[
        "Inis M\u00f3r"
    ],
    "name:gle_x_preferred":[
        "Inis M\u00f3r"
    ],
    "name:glg_x_preferred":[
        "Inis M\u00f3r"
    ],
    "name:ita_x_preferred":[
        "Inis M\u00f3r"
    ],
    "name:nds_x_preferred":[
        "Inishmore"
    ],
    "name:nno_x_preferred":[
        "Inishmore"
    ],
    "name:nor_x_preferred":[
        "Inis M\u00f3r"
    ],
    "name:pol_x_preferred":[
        "Inis M\u00f3r"
    ],
    "name:rus_x_preferred":[
        "\u0418\u043d\u0438\u0448\u043c\u043e\u0440"
    ],
    "name:swe_x_preferred":[
        "Aranmore"
    ],
    "name:tur_x_preferred":[
        "Inis M\u00f3r"
    ],
    "name:zho_x_preferred":[
        "\u4f0a\u5c3c\u4ec0\u83ab\u723e\u5cf6"
    ],
    "qs_pg:aaroncc":"GB",
    "qs_pg:gn_country":"GB",
    "qs_pg:gn_fcode":"PPL",
    "qs_pg:gn_pop":0,
    "qs_pg:name":"Inishmore",
    "qs_pg:name_adm0":"United Kingdom",
    "qs_pg:name_adm1":"Northern Ireland",
    "qs_pg:photos":44,
    "qs_pg:photos_1k":9,
    "qs_pg:photos_9k":1,
    "qs_pg:photos_9r":2,
    "qs_pg:photos_all":44,
    "qs_pg:photos_sr":2,
    "qs_pg:pop_sr":0,
    "qs_pg:qs_pg_placetype":"locality",
    "qs_pg:qs_pg_placetype_gp":"Town",
    "qs_pg:woe_adm0":23424975,
    "woe:adm0_id":23424975,
    "woe:name_adm0":"United Kingdom",
    "woe:name_adm1":"Northern Ireland",
    "woe:placetype":"Town",
    "wof:name":"Inishmore",
    "wof:placetype":"locality"
},
  "geometry": {"coordinates":[-7.58333,54.26667],"type":"Point"}
}