{
  "type": "Feature",
  "properties": {
    "iso:country": "GB",
    "wof:name": "Gipton Wood",
    "wof:placetype": "neighbourhood"
  },
  "geometry": {"coordinates":[-1.50438219102298,53.81993210591789],"type":"Point"}
}
