{
  "type": "Feature",
  "properties": {
    "iso:country": "GB",
    "name:eng_x_preferred": [
      "Killen"
    ],
    "name:eus_x_preferred": [
      "Killen"
    ],
    "name:swe_x_preferred": [
      "Killen"
    ],
    "qs_pg:aaroncc": "GB",
    "qs_pg:name": "Killen",
    "qs_pg:name_adm0": "United Kingdom",
    "qs_pg:name_adm1": "Scotland",
    "qs_pg:photos": 12,
    "qs_pg:photos_1k": 2,
    "qs_pg:photos_9k": 1,
    "qs_pg:photos_9r": 1,
    "qs_pg:photos_all": 12,
    "qs_pg:photos_sr": 1,
    "qs_pg:pop_sr": 0,
    "qs_pg:qs_pg_placetype": "locality",
    "qs_pg:qs_pg_placetype_gp": "Town",
    "qs_pg:woe_adm0": 23424975,
    "woe:adm0_id": 23424975,
    "woe:name_adm0": "United Kingdom",
    "woe:name_adm1": "Scotland",
    "woe:placetype": "Town",
    "wof:name": "Killen",
    "wof:placetype": "locality"
  },
  "geometry": {"coordinates":[-4.215745,57.5942805],"type":"Point"}
}
