{
  "type": "Feature",
  "properties": {
    "iso:country":"GB",
    "name:eng_x_preferred":[
        "Moldgreen"
    ],
    "qs:gn_local":0,
    "qs:local_max":5224,
    "qs:local_sum":14356,
    "qs:localhoods":28,
    "qs:name":"Moldgreen",
    "qs:name_adm0":"United Kingdom",
    "qs:name_adm1":"England",
    "qs:name_adm2":"West Yorkshire",
    "qs:name_lau":"Kirklees Metropolitan Borough",
    "qs:name_local":"Huddersfield",
    "qs:photo_max":55,
    "qs:photo_sum":114,
    "qs:placetype":"Suburb",
    "qs:quad_count":7,
    "qs:woe_adm0":23424975,
    "qs:woe_adm1":24554868,
    "qs:woe_adm2":12602197,
    "qs:woe_lau":12695872,
    "qs:woe_local":24083,
    "qs:woe_ver":"7.10.0",
    "wof:lang":[
        "eng"
    ],
    "wof:name":"Moldgreen",
    "wof:placetype":"neighbourhood"
},
  "geometry": {"coordinates":[-1.764987,53.64423],"type":"Point"}
}