{
  "type": "Feature",
  "properties": {
    "iso:country":"GB",
    "name:eng_x_preferred":[
        "Astley Green"
    ],
    "qs:gn_adm0_cc":"GB",
    "qs:gn_local":2656876,
    "qs:gn_nam_loc":"astley",
    "qs:gn_namadm1":"ENG",
    "qs:local_max":862,
    "qs:local_sum":862,
    "qs:localhoods":1,
    "qs:name":"Astley Green",
    "qs:name_adm0":"United Kingdom",
    "qs:name_adm1":"England",
    "qs:name_adm2":"Greater Manchester",
    "qs:name_lau":"Wigan Metropolitan Borough",
    "qs:name_local":"Astley",
    "qs:photo_max":267,
    "qs:photo_sum":862,
    "qs:placetype":"Suburb",
    "qs:quad_count":63,
    "qs:woe_adm0":23424975,
    "qs:woe_adm1":24554868,
    "qs:woe_adm2":12602158,
    "qs:woe_lau":12695848,
    "qs:woe_local":11282,
    "qs:woe_ver":"7.10.0",
    "wof:lang":[
        "eng"
    ],
    "wof:name":"Astley Green",
    "wof:placetype":"neighbourhood"
},
  "geometry": {"coordinates":[-2.453748,53.499074],"type":"Point"}
}