{
  "type": "Feature",
  "properties": {
    "gn:country": "GB",
    "gn:fcode": "PPL",
    "gn:population": 891,
    "iso:country": "GB",
    "name:ceb_x_preferred": [
      "Lostock"
    ],
    "name:eng_x_preferred": [
      "Lostock"
    ],
    "name:swe_x_preferred": [
      "Lostock"
    ],
    "name:swe_x_variant": [
      "Lostock"
    ],
    "qs_pg:aaroncc": "GB",
    "qs_pg:gn_country": "GB",
    "qs_pg:gn_fcode": "PPL",
    "qs_pg:gn_pop": 891,
    "qs_pg:name": "Lostock",
    "qs_pg:photos_9r": 0,
    "qs_pg:photos_sr": 0,
    "qs_pg:pop_sr": 2,
    "qs_pg:qs_pg_placetype": "locality",
    "wof:name": "Lostock",
    "wof:placetype": "neighbourhood",
    "wof:population": 891
  },
  "geometry": {"coordinates":[-2.50265,53.57885],"type":"Point"}
}
