{
  "type": "Feature",
  "properties": {
    "name:ceb_x_preferred":[
        "Southside"
    ],
    "name:deu_x_preferred":[
        "Southside"
    ],
    "name:ita_x_preferred":[
        "Southside"
    ],
    "name:kor_x_preferred":[
        "\uc0ac\uc6b0\uc2a4\uc0ac\uc774\ub4dc"
    ],
    "name:nld_x_preferred":[
        "Southside"
    ],
    "name:pol_x_preferred":[
        "Southside"
    ],
    "name:por_x_preferred":[
        "Southside"
    ],
    "name:swe_x_preferred":[
        "Southside"
    ],
    "name:ukr_x_preferred":[
        "\u0421\u0430\u0443\u0442\u0441\u0430\u0439\u0434"
    ],
    "wd:wordcount":228,
    "wof:name":"Southside",
    "wof:placetype":"neighbourhood"
},
  "geometry": {"coordinates":[-3.18632669065348,55.93535612765956],"type":"Point"}
}