{
  "type": "Feature",
  "properties": {
    "iso:country":"GB",
    "name:ceb_x_preferred":[
        "Fulford"
    ],
    "name:eng_x_preferred":[
        "Fulford"
    ],
    "name:eng_x_variant":[
        "Gate Fulford"
    ],
    "name:epo_x_preferred":[
        "Fulford"
    ],
    "name:gle_x_preferred":[
        "Fulford"
    ],
    "name:ita_x_preferred":[
        "Fulford"
    ],
    "name:nld_x_preferred":[
        "Fulford"
    ],
    "name:nor_x_preferred":[
        "Fulford"
    ],
    "name:pol_x_preferred":[
        "Fulford"
    ],
    "name:por_x_preferred":[
        "Fulford"
    ],
    "name:spa_x_preferred":[
        "Fulford"
    ],
    "name:swe_x_preferred":[
        "Fulford"
    ],
    "name:szl_x_preferred":[
        "Fulford"
    ],
    "name:unk_x_variant":[
        "Fulford"
    ],
    "qs:gn_local":0,
    "qs:local_max":6977,
    "qs:local_sum":18915,
    "qs:localhoods":4,
    "qs:name":"Fulford",
    "qs:name_adm0":"United Kingdom",
    "qs:name_adm1":"England",
    "qs:name_adm2":"North Yorkshire",
    "qs:name_lau":"York City",
    "qs:name_local":"York",
    "qs:photo_max":514,
    "qs:photo_sum":4769,
    "qs:placetype":"Suburb",
    "qs:quad_count":158,
    "qs:woe_adm0":23424975,
    "qs:woe_adm1":24554868,
    "qs:woe_adm2":12602195,
    "qs:woe_lau":12696148,
    "qs:woe_local":41415,
    "qs:woe_ver":"7.10.0",
    "wd:wordcount":839,
    "wof:lang":[
        "eng"
    ],
    "wof:name":"Fulford",
    "wof:placetype":"neighbourhood"
},
  "geometry": {"coordinates":[-1.071681,53.949202],"type":"Point"}
}