{
  "type": "Feature",
  "properties": {
    "iso:country":"GB",
    "name:bel_x_preferred":[
        "\u0424\u0443\u043b\u0444\u0430\u0440\u0434"
    ],
    "name:ben_x_preferred":[
        "\u09ab\u09c1\u09b2\u09ab\u09cb\u09b0\u09cd\u09a1"
    ],
    "name:ceb_x_preferred":[
        "Fulford"
    ],
    "name:deu_x_preferred":[
        "Fulford"
    ],
    "name:ell_x_preferred":[
        "\u03a6\u03bf\u03cd\u03bb\u03c6\u03bf\u03c1\u03bd\u03c4"
    ],
    "name:eng_x_preferred":[
        "Fulford"
    ],
    "name:eng_x_variant":[
        "Gate Fulford"
    ],
    "name:epo_x_preferred":[
        "Fulford"
    ],
    "name:fas_x_preferred":[
        "\u0641\u0648\u0644\u0641\u0648\u0631\u062f"
    ],
    "name:fra_x_preferred":[
        "Fulford"
    ],
    "name:gle_x_preferred":[
        "Fulford"
    ],
    "name:guj_x_preferred":[
        "\u0aab\u0ab2\u0aab\u0acb\u0ab0\u0acd\u0aa1"
    ],
    "name:ita_x_preferred":[
        "Fulford"
    ],
    "name:jpn_x_preferred":[
        "\u30d5\u30eb\u30d5\u30a9\u30fc\u30c9"
    ],
    "name:kan_x_preferred":[
        "\u0cab\u0cb2\u0ccd\u0cab\u0cb0\u0ccd\u0ca1\u0ccd"
    ],
    "name:kor_x_preferred":[
        "\ud384\ud3ec\ub4dc"
    ],
    "name:lit_x_preferred":[
        "Fulfordas"
    ],
    "name:nld_x_preferred":[
        "Fulford"
    ],
    "name:nob_x_preferred":[
        "Fulford"
    ],
    "name:nor_x_preferred":[
        "Fulford"
    ],
    "name:pol_x_preferred":[
        "Fulford"
    ],
    "name:por_x_preferred":[
        "Fulford"
    ],
    "name:rus_x_preferred":[
        "\u0424\u0443\u043b\u0444\u043e\u0440\u0434"
    ],
    "name:spa_x_preferred":[
        "Fulford"
    ],
    "name:swe_x_preferred":[
        "Fulford"
    ],
    "name:szl_x_preferred":[
        "Fulford"
    ],
    "name:tam_x_preferred":[
        "\u0baa\u0bbf\u0baf\u0bc2\u0bb2\u0bcd\u0baa\u0bcb\u0bb0\u0bcd\u0b9f\u0bcd"
    ],
    "name:tel_x_preferred":[
        "\u0c2b\u0c41\u0c32\u0c4d\u0c2b\u0c4b\u0c30\u0c4d\u0c21\u0c4d"
    ],
    "name:urd_x_preferred":[
        "\u0641\u0648\u0644\u0641\u0648\u0631\u0688"
    ],
    "qs:gn_local":0,
    "qs:local_max":6977,
    "qs:local_sum":18915,
    "qs:localhoods":4,
    "qs:name":"Fulford",
    "qs:name_adm0":"United Kingdom",
    "qs:name_adm1":"England",
    "qs:name_adm2":"North Yorkshire",
    "qs:name_lau":"York City",
    "qs:name_local":"York",
    "qs:photo_max":514,
    "qs:photo_sum":4769,
    "qs:placetype":"Suburb",
    "qs:quad_count":158,
    "qs:woe_adm0":23424975,
    "qs:woe_adm1":24554868,
    "qs:woe_adm2":12602195,
    "qs:woe_lau":12696148,
    "qs:woe_local":41415,
    "qs:woe_ver":"7.10.0",
    "wd:wordcount":839,
    "wof:lang":[
        "eng"
    ],
    "wof:name":"Fulford",
    "wof:placetype":"neighbourhood"
},
  "geometry": {"coordinates":[-1.071681,53.949202],"type":"Point"}
}