{
  "type": "Feature",
  "properties": {
    "iso:country": "GB",
    "name:bel_x_preferred": [
      "Фулфард"
    ],
    "name:ben_x_preferred": [
      "ফুলফোর্ড"
    ],
    "name:ceb_x_preferred": [
      "Fulford"
    ],
    "name:deu_x_preferred": [
      "Fulford"
    ],
    "name:ell_x_preferred": [
      "Φούλφορντ"
    ],
    "name:eng_x_preferred": [
      "Fulford"
    ],
    "name:eng_x_variant": [
      "Gate Fulford"
    ],
    "name:epo_x_preferred": [
      "Fulford"
    ],
    "name:fas_x_preferred": [
      "فولفورد"
    ],
    "name:fra_x_preferred": [
      "Fulford"
    ],
    "name:gle_x_preferred": [
      "Fulford"
    ],
    "name:guj_x_preferred": [
      "ફલફોર્ડ"
    ],
    "name:ita_x_preferred": [
      "Fulford"
    ],
    "name:jpn_x_preferred": [
      "フルフォード"
    ],
    "name:kan_x_preferred": [
      "ಫಲ್ಫರ್ಡ್"
    ],
    "name:kor_x_preferred": [
      "펄포드"
    ],
    "name:lit_x_preferred": [
      "Fulfordas"
    ],
    "name:nld_x_preferred": [
      "Fulford"
    ],
    "name:nob_x_preferred": [
      "Fulford"
    ],
    "name:nor_x_preferred": [
      "Fulford"
    ],
    "name:pol_x_preferred": [
      "Fulford"
    ],
    "name:por_x_preferred": [
      "Fulford"
    ],
    "name:rus_x_preferred": [
      "Фулфорд"
    ],
    "name:spa_x_preferred": [
      "Fulford"
    ],
    "name:swe_x_preferred": [
      "Fulford"
    ],
    "name:szl_x_preferred": [
      "Fulford"
    ],
    "name:tam_x_preferred": [
      "பியூல்போர்ட்"
    ],
    "name:tel_x_preferred": [
      "ఫుల్ఫోర్డ్"
    ],
    "name:urd_x_preferred": [
      "فولفورڈ"
    ],
    "qs:gn_local": 0,
    "qs:local_max": 6977,
    "qs:local_sum": 18915,
    "qs:localhoods": 4,
    "qs:name": "Fulford",
    "qs:name_adm0": "United Kingdom",
    "qs:name_adm1": "England",
    "qs:name_adm2": "North Yorkshire",
    "qs:name_lau": "York City",
    "qs:name_local": "York",
    "qs:photo_max": 514,
    "qs:photo_sum": 4769,
    "qs:placetype": "Suburb",
    "qs:quad_count": 158,
    "qs:woe_adm0": 23424975,
    "qs:woe_adm1": 24554868,
    "qs:woe_adm2": 12602195,
    "qs:woe_lau": 12696148,
    "qs:woe_local": 41415,
    "qs:woe_ver": "7.10.0",
    "wd:wordcount": 839,
    "wof:lang": [
      "eng"
    ],
    "wof:name": "Fulford",
    "wof:placetype": "neighbourhood"
  },
  "geometry": {"coordinates":[-1.071681,53.949202],"type":"Point"}
}
