{
  "type": "Feature",
  "properties": {
    "iso:country":"GB",
    "name:baq_x_preferred":[
        "Bersham"
    ],
    "name:bre_x_preferred":[
        "Bers"
    ],
    "name:cat_x_preferred":[
        "Bersham"
    ],
    "name:dut_x_preferred":[
        "Bersham"
    ],
    "name:eng_x_preferred":[
        "Bersham"
    ],
    "name:ger_x_preferred":[
        "Bersham"
    ],
    "name:gle_x_preferred":[
        "Bersham"
    ],
    "name:glg_x_preferred":[
        "Bersham"
    ],
    "name:sco_x_preferred":[
        "Bers"
    ],
    "name:wel_x_preferred":[
        "Y Bers"
    ],
    "qs_pg:aaroncc":"GB",
    "qs_pg:name":"Bersham",
    "qs_pg:name_adm0":"United Kingdom",
    "qs_pg:name_adm1":"Wales",
    "qs_pg:photos":81,
    "qs_pg:photos_1k":16,
    "qs_pg:photos_9k":1,
    "qs_pg:photos_9r":3,
    "qs_pg:photos_all":81,
    "qs_pg:photos_sr":3,
    "qs_pg:pop_sr":0,
    "qs_pg:qs_pg_placetype":"locality",
    "qs_pg:qs_pg_placetype_gp":"Town",
    "qs_pg:woe_adm0":23424975,
    "woe:adm0_id":23424975,
    "woe:name_adm0":"United Kingdom",
    "woe:name_adm1":"Wales",
    "woe:placetype":"Town",
    "wof:name":"Bersham",
    "wof:placetype":"neighbourhood"
},
  "geometry": {"coordinates":[-3.029119,53.035587],"type":"Point"}
}