{
  "type": "Feature",
  "properties": {
    "gn:gn_country":"GB",
    "gn:gn_fcode":"PPL",
    "gn:gn_pop":0,
    "iso:country":"GB",
    "name:eng_x_preferred":[
        "Plumbridge"
    ],
    "name:fra_x_preferred":[
        "Plumbridge"
    ],
    "name:gle_x_preferred":[
        "Droichead an Phlum"
    ],
    "name:msa_x_preferred":[
        "Plumbridge"
    ],
    "name:nld_x_preferred":[
        "Plumbridge"
    ],
    "name:pli_x_preferred":[
        "\u092a\u094d\u0932\u0941\u092e\u094d\u092c\u094d\u0930\u093f\u0926\u094d\u0917\u0947"
    ],
    "qs_pg:aaroncc":"GB",
    "qs_pg:gn_country":"GB",
    "qs_pg:gn_fcode":"PPL",
    "qs_pg:gn_pop":0,
    "qs_pg:name":"Plumbridge",
    "qs_pg:name_adm0":"United Kingdom",
    "qs_pg:name_adm1":"Northern Ireland",
    "qs_pg:photos":23,
    "qs_pg:photos_1k":5,
    "qs_pg:photos_9k":1,
    "qs_pg:photos_9r":1,
    "qs_pg:photos_all":23,
    "qs_pg:photos_sr":1,
    "qs_pg:pop_sr":0,
    "qs_pg:qs_pg_placetype":"locality",
    "qs_pg:qs_pg_placetype_gp":"Town",
    "qs_pg:woe_adm0":23424975,
    "woe:adm0_id":23424975,
    "woe:name_adm0":"United Kingdom",
    "woe:name_adm1":"Northern Ireland",
    "woe:placetype":"Town",
    "wof:name":"Plumbridge",
    "wof:placetype":"locality"
},
  "geometry": {"coordinates":[-7.25,54.76667],"type":"Point"}
}