{
  "type": "Feature",
  "properties": {
    "gn:country":"GB",
    "gn:fcode":"PPL",
    "gn:population":0,
    "iso:country":"GB",
    "name:cym_x_preferred":[
        "Alberbury"
    ],
    "name:eng_x_preferred":[
        "Alberbury"
    ],
    "name:fra_x_preferred":[
        "Alberbury"
    ],
    "name:jpn_x_preferred":[
        "\u30a2\u30eb\u30d0\u30fc\u30d9\u30ea\u30fc"
    ],
    "name:nld_x_preferred":[
        "Alberbury"
    ],
    "name:pol_x_preferred":[
        "Alberbury"
    ],
    "qs_pg:aaroncc":"GB",
    "qs_pg:gn_country":"GB",
    "qs_pg:gn_fcode":"PPL",
    "qs_pg:gn_pop":0,
    "qs_pg:name":"Alberbury",
    "qs_pg:name_adm0":"United Kingdom",
    "qs_pg:name_adm1":"England",
    "qs_pg:photos":785,
    "qs_pg:photos_1k":159,
    "qs_pg:photos_9k":3,
    "qs_pg:photos_9r":6,
    "qs_pg:photos_all":785,
    "qs_pg:photos_sr":9,
    "qs_pg:pop_sr":0,
    "qs_pg:qs_pg_placetype":"locality",
    "qs_pg:qs_pg_placetype_gp":"Town",
    "qs_pg:woe_adm0":23424975,
    "woe:adm0_id":23424975,
    "woe:name_adm0":"United Kingdom",
    "woe:name_adm1":"England",
    "woe:placetype":"Town",
    "wof:name":"Alberbury",
    "wof:placetype":"neighbourhood"
},
  "geometry": {"coordinates":[-2.95074,52.72234],"type":"Point"}
}