{
  "type": "Feature",
  "properties": {
    "gn:population":1742,
    "iso:country":"GB",
    "name:bul_x_preferred":[
        "\u0410\u0431\u0435\u0440\u0434\u043e\u0443\u0440"
    ],
    "name:cat_x_preferred":[
        "Aberdour"
    ],
    "name:ceb_x_preferred":[
        "Aberdour"
    ],
    "name:cym_x_preferred":[
        "Aberdour"
    ],
    "name:deu_x_preferred":[
        "Aberdour"
    ],
    "name:eng_x_preferred":[
        "Aberdour"
    ],
    "name:eus_x_preferred":[
        "Aberdour"
    ],
    "name:fin_x_preferred":[
        "Aberdour"
    ],
    "name:fra_x_preferred":[
        "Aberdour"
    ],
    "name:gla_x_preferred":[
        "Obar Dhobhair"
    ],
    "name:gle_x_preferred":[
        "Obar Dobhair"
    ],
    "name:heb_x_preferred":[
        "\u05d0\u05d1\u05e8\u05d3\u05d5\u05e8"
    ],
    "name:ita_x_preferred":[
        "Aberdour"
    ],
    "name:nld_x_preferred":[
        "Aberdour"
    ],
    "name:nno_x_preferred":[
        "Aberdour"
    ],
    "name:nob_x_preferred":[
        "Aberdour"
    ],
    "name:nor_x_preferred":[
        "Aberdour"
    ],
    "name:por_x_preferred":[
        "Aberdour"
    ],
    "name:ron_x_preferred":[
        "Aberdour"
    ],
    "name:sco_x_preferred":[
        "Aiberdour"
    ],
    "name:slv_x_preferred":[
        "Aberdour"
    ],
    "name:spa_x_preferred":[
        "Aberdour"
    ],
    "name:swe_x_preferred":[
        "Aberdour"
    ],
    "qs:a0":"United Kingdom",
    "qs:a1":"*Fife",
    "qs:a1_lc":"GB11QR0000",
    "qs:a1r":"0Scotland",
    "qs:a1r_lc":"GB11000000",
    "qs:adm0":"United Kingdom",
    "qs:la_lc":"*",
    "qs:level":"locality",
    "qs:loc":"Aberdour",
    "qs:loc_alt":"Aberdour",
    "qs:pop":0,
    "qs:type":"buffered point",
    "wd:wordcount":1660,
    "wof:lang":[
        "eng"
    ],
    "wof:name":"Aberdour",
    "wof:placetype":"locality",
    "wof:population":1742
},
  "geometry": {"coordinates":[-3.30106,56.053634],"type":"Point"}
}