{
  "type": "Feature",
  "properties": {
    "gn:admin1_code":"WLS",
    "gn:admin2_code":"X7",
    "gn:admin3_code":"00NU028",
    "gn:asciiname":"Pentre-Gwenlais",
    "gn:country_code":"GB",
    "gn:dem":124,
    "gn:feature_class":"P",
    "gn:feature_code":"PPL",
    "gn:name":"Pentre-Gwenlais",
    "gn:population":0,
    "gn:timezone":"Europe/London",
    "iso:country":"GB",
    "wof:name":"Pentre-Gwenlais",
    "wof:placetype":"neighbourhood"
},
  "geometry": {"coordinates":[-4.01957,51.82661],"type":"Point"}
}