{
  "type": "Feature",
  "properties": {
    "gn:admin1_code":"ENG",
    "gn:admin2_code":"Z7",
    "gn:admin3_code":"00EQ092",
    "gn:asciiname":"Alderley Park",
    "gn:country_code":"GB",
    "gn:dem":114,
    "gn:feature_class":"P",
    "gn:feature_code":"PPL",
    "gn:name":"Alderley Park",
    "gn:population":0,
    "gn:timezone":"Europe/London",
    "iso:country":"GB",
    "wof:name":"Alderley Park",
    "wof:placetype":"neighbourhood"
},
  "geometry": {"coordinates":[-2.2311,53.27632],"type":"Point"}
}