{
  "type": "Feature",
  "properties": {
    "gn:admin1_code": "NIR",
    "gn:admin2_code": "N09000006",
    "gn:asciiname": "Leitrim",
    "gn:country_code": "GB",
    "gn:dem": 52,
    "gn:feature_class": "P",
    "gn:feature_code": "PPL",
    "gn:name": "Leitrim",
    "gn:population": 0,
    "gn:timezone": "Europe/London",
    "iso:country": "GB",
    "name:ceb_x_preferred": [
      "Leitrim"
    ],
    "name:deu_x_preferred": [
      "Leitrim"
    ],
    "name:pol_x_preferred": [
      "Leitrim"
    ],
    "name:rus_x_preferred": [
      "Литрим"
    ],
    "name:swe_x_preferred": [
      "Leitrim"
    ],
    "wof:name": "Leitrim",
    "wof:placetype": "locality"
  },
  "geometry": {"coordinates":[-7.31667,54.16667],"type":"Point"}
}
