{
  "type": "Feature",
  "properties": {
    "gn:country":"GB",
    "gn:fcode":"PPL",
    "gn:population":0,
    "iso:country":"GB",
    "name:cym_x_preferred":[
        "Titchfield"
    ],
    "name:eng_x_preferred":[
        "Titchfield"
    ],
    "name:fra_x_preferred":[
        "Titchfield"
    ],
    "name:gle_x_preferred":[
        "Titchfield"
    ],
    "name:jpn_x_preferred":[
        "\u30c6\u30a3\u30c3\u30c1\u30d5\u30a3\u30fc\u30eb\u30c9"
    ],
    "name:lat_x_preferred":[
        "Titchfield"
    ],
    "name:lld_x_preferred":[
        "Titchfield"
    ],
    "name:nld_x_preferred":[
        "Titchfield"
    ],
    "name:pol_x_preferred":[
        "Titchfield"
    ],
    "name:pol_x_variant":[
        "Clappersgate"
    ],
    "name:spa_x_preferred":[
        "Titchfield"
    ],
    "name:swe_x_preferred":[
        "Titchfield"
    ],
    "qs_pg:aaroncc":"GB",
    "qs_pg:gn_country":"GB",
    "qs_pg:gn_fcode":"PPL",
    "qs_pg:gn_pop":0,
    "qs_pg:name":"Titchfield",
    "qs_pg:name_adm0":"United Kingdom",
    "qs_pg:name_adm1":"England",
    "qs_pg:photos":608,
    "qs_pg:photos_1k":123,
    "qs_pg:photos_9k":3,
    "qs_pg:photos_9r":5,
    "qs_pg:photos_all":608,
    "qs_pg:photos_sr":8,
    "qs_pg:pop_sr":0,
    "qs_pg:qs_pg_placetype":"locality",
    "qs_pg:qs_pg_placetype_gp":"Town",
    "qs_pg:woe_adm0":23424975,
    "woe:adm0_id":23424975,
    "woe:name_adm0":"United Kingdom",
    "woe:name_adm1":"England",
    "woe:placetype":"Town",
    "wof:name":"Titchfield",
    "wof:placetype":"neighbourhood"
},
  "geometry": {"coordinates":[-1.23716,50.85115],"type":"Point"}
}