{
  "type": "Feature",
  "properties": {
    "gn:population":3367,
    "iso:country":"GB",
    "name:ceb_x_preferred":[
        "Kirkcudbright"
    ],
    "name:cym_x_preferred":[
        "Kirkcudbright"
    ],
    "name:deu_x_preferred":[
        "Kirkcudbright"
    ],
    "name:eng_x_preferred":[
        "Kirkcudbright"
    ],
    "name:eng_x_variant":[
        "Kircudbright"
    ],
    "name:eus_x_preferred":[
        "Kirkcudbright"
    ],
    "name:fas_x_preferred":[
        "\u06a9\u0631\u06a9\u0627\u062f\u0628\u0631\u0627\u06cc\u062a"
    ],
    "name:fin_x_preferred":[
        "Kirkcudbright"
    ],
    "name:fra_x_preferred":[
        "Kirkcudbright"
    ],
    "name:gla_x_preferred":[
        "Cille Chuithbeirt"
    ],
    "name:gle_x_preferred":[
        "Cille Chuithbeirt"
    ],
    "name:hbs_x_preferred":[
        "Kirkcudbright"
    ],
    "name:ita_x_preferred":[
        "Kirkcudbright"
    ],
    "name:jpn_x_preferred":[
        "\u30ab\u30fc\u30af\u30fc\u30d6\u30ea\u30fc"
    ],
    "name:nld_x_preferred":[
        "Kirkcudbright"
    ],
    "name:pol_x_preferred":[
        "Kirkcudbright"
    ],
    "name:rus_x_preferred":[
        "\u041a\u0435\u0440\u043a\u0443\u0431\u0440\u0438"
    ],
    "name:sco_x_preferred":[
        "Kirkcoubrie"
    ],
    "name:spa_x_preferred":[
        "Kirkcudbright"
    ],
    "name:swe_x_preferred":[
        "Kirkcudbright"
    ],
    "name:ukr_x_preferred":[
        "\u041a\u0435\u0440\u043a\u0443\u0431\u0440\u0456"
    ],
    "qs:a0":"United Kingdom",
    "qs:a1":"*Dumfries and Galloway",
    "qs:a1_lc":"GB11QH0000",
    "qs:a1r":"0Scotland",
    "qs:a1r_lc":"GB11000000",
    "qs:adm0":"United Kingdom",
    "qs:la_lc":"*",
    "qs:level":"locality",
    "qs:loc":"Kirkcudbright",
    "qs:loc_alt":"Kirkcudbright",
    "qs:pop":0,
    "qs:type":"buffered point",
    "wd:wordcount":1898,
    "wof:lang":[
        "eng"
    ],
    "wof:name":"Kirkcudbright",
    "wof:placetype":"locality",
    "wof:population":3367
},
  "geometry": {"coordinates":[-4.049153,54.835888],"type":"Point"}
}