{
  "type": "Feature",
  "properties": {
    "iso:country":"GB",
    "name:cym_x_preferred":[
        "Coal Aston"
    ],
    "name:eng_x_preferred":[
        "Coal Aston"
    ],
    "name:epo_x_preferred":[
        "Coal Aston"
    ],
    "name:fra_x_preferred":[
        "Coal Aston"
    ],
    "name:jpn_x_preferred":[
        "\u30b3\u30fc\u30eb\u30fb\u30a2\u30b9\u30c8\u30f3"
    ],
    "name:nld_x_preferred":[
        "Coal Aston"
    ],
    "name:pol_x_preferred":[
        "Coal Aston"
    ],
    "qs_pg:aaroncc":"GB",
    "qs_pg:name":"Coal Aston",
    "qs_pg:name_adm0":"United Kingdom",
    "qs_pg:name_adm1":"England",
    "qs_pg:photos":62,
    "qs_pg:photos_1k":13,
    "qs_pg:photos_9k":1,
    "qs_pg:photos_9r":2,
    "qs_pg:photos_all":62,
    "qs_pg:photos_sr":2,
    "qs_pg:pop_sr":0,
    "qs_pg:qs_pg_placetype":"locality",
    "qs_pg:qs_pg_placetype_gp":"Town",
    "qs_pg:woe_adm0":23424975,
    "woe:adm0_id":23424975,
    "woe:name_adm0":"United Kingdom",
    "woe:name_adm1":"England",
    "woe:placetype":"Town",
    "wof:name":"Coal Aston",
    "wof:placetype":"neighbourhood"
},
  "geometry": {"coordinates":[-1.45911,53.312728],"type":"Point"}
}