{
  "type": "Feature",
  "properties": {
    "gn:country": "GB",
    "gn:fcode": "PPL",
    "gn:population": 0,
    "iso:country": "GB",
    "name:ben_x_preferred": [
      "হিপারহোম"
    ],
    "name:deu_x_preferred": [
      "Hipperholme"
    ],
    "name:eng_x_preferred": [
      "Hipperholme"
    ],
    "name:fra_x_preferred": [
      "Hipperholme"
    ],
    "name:guj_x_preferred": [
      "હિપરહોમ"
    ],
    "name:jpn_x_preferred": [
      "ヒッパーホルム"
    ],
    "name:kan_x_preferred": [
      "ಹಿಪ್ಪರ್ಹೋಮ್"
    ],
    "name:kor_x_preferred": [
      "히페르홀름"
    ],
    "name:lit_x_preferred": [
      "Hiperholmas"
    ],
    "name:nld_x_preferred": [
      "Hipperholme"
    ],
    "name:pol_x_preferred": [
      "Hipperholme"
    ],
    "name:por_x_preferred": [
      "Hipperholme"
    ],
    "name:rus_x_preferred": [
      "Хипперхолм"
    ],
    "name:spa_x_preferred": [
      "Hipperholme"
    ],
    "name:tam_x_preferred": [
      "ஹிப்பேர்ஹோல்ம்"
    ],
    "name:tel_x_preferred": [
      "హిప్పెర్హొల్మే"
    ],
    "name:urd_x_preferred": [
      "ہیپپیرہولمی"
    ],
    "qs_pg:aaroncc": "GB",
    "qs_pg:gn_country": "GB",
    "qs_pg:gn_fcode": "PPL",
    "qs_pg:gn_pop": 0,
    "qs_pg:name": "Hipperholme",
    "qs_pg:name_adm0": "United Kingdom",
    "qs_pg:name_adm1": "England",
    "qs_pg:photos": 102,
    "qs_pg:photos_1k": 21,
    "qs_pg:photos_9k": 1,
    "qs_pg:photos_9r": 3,
    "qs_pg:photos_all": 102,
    "qs_pg:photos_sr": 3,
    "qs_pg:pop_sr": 0,
    "qs_pg:qs_pg_placetype": "locality",
    "qs_pg:qs_pg_placetype_gp": "Town",
    "qs_pg:woe_adm0": 23424975,
    "woe:adm0_id": 23424975,
    "woe:name_adm0": "United Kingdom",
    "woe:name_adm1": "England",
    "woe:placetype": "Town",
    "wof:name": "Hipperholme",
    "wof:placetype": "neighbourhood"
  },
  "geometry": {"coordinates":[-1.81173,53.72551],"type":"Point"}
}
