{
  "type": "Feature",
  "properties": {
    "gn:country":"GB",
    "gn:fcode":"PPL",
    "gn:population":0,
    "iso:country":"GB",
    "name:ben_x_preferred":[
        "\u09b9\u09bf\u09aa\u09be\u09b0\u09b9\u09cb\u09ae"
    ],
    "name:deu_x_preferred":[
        "Hipperholme"
    ],
    "name:eng_x_preferred":[
        "Hipperholme"
    ],
    "name:fra_x_preferred":[
        "Hipperholme"
    ],
    "name:gle_x_preferred":[
        "Hipperholme"
    ],
    "name:guj_x_preferred":[
        "\u0ab9\u0abf\u0aaa\u0ab0\u0ab9\u0acb\u0aae"
    ],
    "name:ita_x_preferred":[
        "Hipperholme"
    ],
    "name:jpn_x_preferred":[
        "\u30d2\u30c3\u30d1\u30fc\u30db\u30eb\u30e0"
    ],
    "name:kan_x_preferred":[
        "\u0cb9\u0cbf\u0caa\u0ccd\u0caa\u0cb0\u0ccd\u0cb9\u0ccb\u0cae\u0ccd"
    ],
    "name:kor_x_preferred":[
        "\ud788\ud398\ub974\ud640\ub984"
    ],
    "name:lit_x_preferred":[
        "Hiperholmas"
    ],
    "name:nld_x_preferred":[
        "Hipperholme"
    ],
    "name:pol_x_preferred":[
        "Hipperholme"
    ],
    "name:por_x_preferred":[
        "Hipperholme"
    ],
    "name:rus_x_preferred":[
        "\u0425\u0438\u043f\u043f\u0435\u0440\u0445\u043e\u043b\u043c"
    ],
    "name:spa_x_preferred":[
        "Hipperholme"
    ],
    "name:tam_x_preferred":[
        "\u0bb9\u0bbf\u0baa\u0bcd\u0baa\u0bc7\u0bb0\u0bcd\u0bb9\u0bcb\u0bb2\u0bcd\u0bae\u0bcd"
    ],
    "name:tel_x_preferred":[
        "\u0c39\u0c3f\u0c2a\u0c4d\u0c2a\u0c46\u0c30\u0c4d\u0c39\u0c4a\u0c32\u0c4d\u0c2e\u0c47"
    ],
    "name:urd_x_preferred":[
        "\u06c1\u06cc\u067e\u067e\u06cc\u0631\u06c1\u0648\u0644\u0645\u06cc"
    ],
    "qs_pg:aaroncc":"GB",
    "qs_pg:gn_country":"GB",
    "qs_pg:gn_fcode":"PPL",
    "qs_pg:gn_pop":0,
    "qs_pg:name":"Hipperholme",
    "qs_pg:name_adm0":"United Kingdom",
    "qs_pg:name_adm1":"England",
    "qs_pg:photos":102,
    "qs_pg:photos_1k":21,
    "qs_pg:photos_9k":1,
    "qs_pg:photos_9r":3,
    "qs_pg:photos_all":102,
    "qs_pg:photos_sr":3,
    "qs_pg:pop_sr":0,
    "qs_pg:qs_pg_placetype":"locality",
    "qs_pg:qs_pg_placetype_gp":"Town",
    "qs_pg:woe_adm0":23424975,
    "woe:adm0_id":23424975,
    "woe:name_adm0":"United Kingdom",
    "woe:name_adm1":"England",
    "woe:placetype":"Town",
    "wof:name":"Hipperholme",
    "wof:placetype":"neighbourhood"
},
  "geometry": {"coordinates":[-1.81173,53.72551],"type":"Point"}
}