{
  "type": "Feature",
  "properties": {
    "iso:country":"GB",
    "name:eng_x_preferred":[
        "Brookfield"
    ],
    "name:eus_x_preferred":[
        "Brookfield"
    ],
    "name:fra_x_preferred":[
        "Brookfield"
    ],
    "name:gla_x_preferred":[
        "Achadh an t-Sruthain"
    ],
    "name:gle_x_preferred":[
        "Achadh an t-Sruthain"
    ],
    "name:lat_x_preferred":[
        "Brookfield"
    ],
    "name:nld_x_preferred":[
        "Brookfield"
    ],
    "name:spa_x_preferred":[
        "Brookfield"
    ],
    "name:swe_x_preferred":[
        "Brookfield"
    ],
    "name:urd_x_preferred":[
        "\u0628\u0631\u0648\u06a9\u0641\u06cc\u0644\u0688\u060c \u0631\u06cc\u0646\u0641\u0631\u06cc\u0648\u0634\u0627\u0626\u0631"
    ],
    "name:urd_x_variant":[
        "\u0628\u0631\u0648\u06a9\u0641\u06cc\u0644\u0688"
    ],
    "qs_pg:aaroncc":"GB",
    "qs_pg:name":"Brookfield",
    "qs_pg:name_adm0":"United Kingdom",
    "qs_pg:name_adm1":"Scotland",
    "qs_pg:photos":34,
    "qs_pg:photos_1k":7,
    "qs_pg:photos_9k":1,
    "qs_pg:photos_9r":2,
    "qs_pg:photos_all":34,
    "qs_pg:photos_sr":2,
    "qs_pg:pop_sr":0,
    "qs_pg:qs_pg_placetype":"locality",
    "qs_pg:qs_pg_placetype_gp":"Town",
    "qs_pg:woe_adm0":23424975,
    "woe:adm0_id":23424975,
    "woe:name_adm0":"United Kingdom",
    "woe:name_adm1":"Scotland",
    "woe:placetype":"Town",
    "wof:name":"Brookfield",
    "wof:placetype":"locality"
},
  "geometry": {"coordinates":[-4.533206,55.845078],"type":"Point"}
}