{
  "type": "Feature",
  "properties": {
    "iso:country":"GB",
    "name:eng_x_preferred":[
        "Georgetown"
    ],
    "name:unk_x_variant":[
        "Georgetown"
    ],
    "qs:gn_adm0_cc":"GB",
    "qs:gn_local":2642705,
    "qs:gn_nam_loc":"Merthyr Tydfil, Wales, GB",
    "qs:gn_namadm1":"WLS",
    "qs:local_max":1129,
    "qs:local_sum":2009,
    "qs:localhoods":4,
    "qs:name":"Georgetown",
    "qs:name_adm0":"United Kingdom",
    "qs:name_adm1":"Wales",
    "qs:name_adm2":"Merthyr Tydfil County Borough",
    "qs:name_lau":"Merthyr Tydfil County Borough",
    "qs:name_local":"Merthyr Tydfil",
    "qs:photo_max":114,
    "qs:photo_sum":508,
    "qs:placetype":"Suburb",
    "qs:quad_count":16,
    "qs:woe_adm0":23424975,
    "qs:woe_adm1":12578049,
    "qs:woe_adm2":12602222,
    "qs:woe_lau":12696125,
    "qs:woe_local":28757,
    "qs:woe_ver":"7.10.0",
    "wof:lang":[
        "eng"
    ],
    "wof:name":"Georgetown",
    "wof:placetype":"neighbourhood"
},
  "geometry": {"coordinates":[-3.383857,51.747905],"type":"Point"}
}