{
  "type": "Feature",
  "properties": {
    "gn:gn_country":"GB",
    "iso:country":"GB",
    "qs_pg:aaroncc":"GB",
    "qs_pg:gn_country":"GB",
    "qs_pg:name":"The Lhen",
    "qs_pg:name_adm0":"United Kingdom",
    "qs_pg:name_adm1":"Isle of Man",
    "qs_pg:photos":725,
    "qs_pg:photos_1k":147,
    "qs_pg:photos_9k":3,
    "qs_pg:photos_9r":5,
    "qs_pg:photos_all":725,
    "qs_pg:photos_sr":8,
    "qs_pg:pop_sr":0,
    "qs_pg:qs_pg_placetype":"locality",
    "qs_pg:qs_pg_placetype_gp":"Town",
    "qs_pg:woe_adm0":23424975,
    "woe:adm0_id":23424975,
    "woe:name_adm0":"United Kingdom",
    "woe:name_adm1":"Isle of Man",
    "woe:placetype":"Town",
    "wof:name":"The Lhen",
    "wof:placetype":"locality"
},
  "geometry": {"coordinates":[-4.513664,54.377208],"type":"Point"}
}