{
  "type": "Feature",
  "properties": {
    "gn:country": "GB",
    "gn:fcode": "PPL",
    "gn:population": 6266,
    "iso:country": "GB",
    "name:azb_x_preferred": [
      "بوتول"
    ],
    "name:ben_x_preferred": [
      "বোথওয়েল"
    ],
    "name:ceb_x_preferred": [
      "Bothwell"
    ],
    "name:cym_x_preferred": [
      "Bothwell"
    ],
    "name:deu_x_preferred": [
      "Bothwell"
    ],
    "name:eng_x_preferred": [
      "Bothwell"
    ],
    "name:eus_x_preferred": [
      "Bothwell"
    ],
    "name:fas_x_preferred": [
      "بوتول"
    ],
    "name:fra_x_preferred": [
      "Bothwell"
    ],
    "name:guj_x_preferred": [
      "બૉથવેલ"
    ],
    "name:ita_x_preferred": [
      "Bothwell"
    ],
    "name:jpn_x_preferred": [
      "ボスウェル"
    ],
    "name:kan_x_preferred": [
      "ಬೋತ್ವೆಲ್"
    ],
    "name:kor_x_preferred": [
      "보트웰"
    ],
    "name:lit_x_preferred": [
      "Botvelis"
    ],
    "name:nld_x_preferred": [
      "Bothwell"
    ],
    "name:nno_x_preferred": [
      "Bothwell"
    ],
    "name:nob_x_preferred": [
      "Bothwell"
    ],
    "name:pol_x_preferred": [
      "Bothwell"
    ],
    "name:por_x_preferred": [
      "Bothwell"
    ],
    "name:rus_x_preferred": [
      "Босуэлл"
    ],
    "name:sco_x_preferred": [
      "Boddle"
    ],
    "name:spa_x_preferred": [
      "Bothwell"
    ],
    "name:swe_x_preferred": [
      "Bothwell"
    ],
    "name:tam_x_preferred": [
      "பொதுவெள்"
    ],
    "name:tel_x_preferred": [
      "బోత్ వెల్"
    ],
    "name:urd_x_preferred": [
      "بوتھویل"
    ],
    "qs_pg:aaroncc": "GB",
    "qs_pg:gn_country": "GB",
    "qs_pg:gn_fcode": "PPL",
    "qs_pg:gn_pop": 6266,
    "qs_pg:name": "Bothwell",
    "qs_pg:name_adm0": "United Kingdom",
    "qs_pg:name_adm1": "Scotland",
    "qs_pg:photos": 369,
    "qs_pg:photos_1k": 75,
    "qs_pg:photos_9k": 2,
    "qs_pg:photos_9r": 5,
    "qs_pg:photos_all": 369,
    "qs_pg:photos_sr": 6,
    "qs_pg:pop_sr": 5,
    "qs_pg:qs_pg_placetype": "locality",
    "qs_pg:qs_pg_placetype_gp": "Town",
    "qs_pg:woe_adm0": 23424975,
    "woe:adm0_id": 23424975,
    "woe:name_adm0": "United Kingdom",
    "woe:name_adm1": "Scotland",
    "woe:placetype": "Town",
    "wof:name": "Bothwell",
    "wof:placetype": "locality",
    "wof:population": 6410
  },
  "geometry": {"coordinates":[-4.06835,55.80272],"type":"Point"}
}
