{
  "type": "Feature",
  "properties": {
    "gn:country":"GB",
    "gn:fcode":"PPL",
    "gn:population":6266,
    "iso:country":"GB",
    "name:ast_x_preferred":[
        "Bothwell"
    ],
    "name:azb_x_preferred":[
        "\u0628\u0648\u062a\u0648\u0644"
    ],
    "name:ben_x_preferred":[
        "\u09ac\u09cb\u09a5\u0993\u09af\u09bc\u09c7\u09b2"
    ],
    "name:ceb_x_preferred":[
        "Bothwell"
    ],
    "name:cym_x_preferred":[
        "Bothwell"
    ],
    "name:deu_x_preferred":[
        "Bothwell"
    ],
    "name:eng_x_preferred":[
        "Bothwell"
    ],
    "name:eus_x_preferred":[
        "Bothwell"
    ],
    "name:fas_x_preferred":[
        "\u0628\u0648\u062a\u0648\u0644"
    ],
    "name:fra_x_preferred":[
        "Bothwell"
    ],
    "name:guj_x_preferred":[
        "\u0aac\u0ac9\u0aa5\u0ab5\u0ac7\u0ab2"
    ],
    "name:heb_x_preferred":[
        "\u05d1\u05d5\u05ea'\u05d5\u05d5\u05dc"
    ],
    "name:ita_x_preferred":[
        "Bothwell"
    ],
    "name:jpn_x_preferred":[
        "\u30dc\u30b9\u30a6\u30a7\u30eb"
    ],
    "name:kan_x_preferred":[
        "\u0cac\u0ccb\u0ca4\u0ccd\u0cb5\u0cc6\u0cb2\u0ccd"
    ],
    "name:kor_x_preferred":[
        "\ubcf4\ud2b8\uc6f0"
    ],
    "name:lit_x_preferred":[
        "Botvelis"
    ],
    "name:nld_x_preferred":[
        "Bothwell"
    ],
    "name:nno_x_preferred":[
        "Bothwell"
    ],
    "name:nob_x_preferred":[
        "Bothwell"
    ],
    "name:pol_x_preferred":[
        "Bothwell"
    ],
    "name:por_x_preferred":[
        "Bothwell"
    ],
    "name:rus_x_preferred":[
        "\u0411\u043e\u0441\u0443\u044d\u043b\u043b"
    ],
    "name:sco_x_preferred":[
        "Boddle"
    ],
    "name:spa_x_preferred":[
        "Bothwell"
    ],
    "name:swe_x_preferred":[
        "Bothwell"
    ],
    "name:tam_x_preferred":[
        "\u0baa\u0bca\u0ba4\u0bc1\u0bb5\u0bc6\u0bb3\u0bcd"
    ],
    "name:tel_x_preferred":[
        "\u0c2c\u0c4b\u0c24\u0c4d \u0c35\u0c46\u0c32\u0c4d"
    ],
    "name:urd_x_preferred":[
        "\u0628\u0648\u062a\u06be\u0648\u06cc\u0644"
    ],
    "qs_pg:aaroncc":"GB",
    "qs_pg:gn_country":"GB",
    "qs_pg:gn_fcode":"PPL",
    "qs_pg:gn_pop":6266,
    "qs_pg:name":"Bothwell",
    "qs_pg:name_adm0":"United Kingdom",
    "qs_pg:name_adm1":"Scotland",
    "qs_pg:photos":369,
    "qs_pg:photos_1k":75,
    "qs_pg:photos_9k":2,
    "qs_pg:photos_9r":5,
    "qs_pg:photos_all":369,
    "qs_pg:photos_sr":6,
    "qs_pg:pop_sr":5,
    "qs_pg:qs_pg_placetype":"locality",
    "qs_pg:qs_pg_placetype_gp":"Town",
    "qs_pg:woe_adm0":23424975,
    "woe:adm0_id":23424975,
    "woe:name_adm0":"United Kingdom",
    "woe:name_adm1":"Scotland",
    "woe:placetype":"Town",
    "wof:name":"Bothwell",
    "wof:placetype":"locality",
    "wof:population":6410
},
  "geometry": {"coordinates":[-4.06835,55.80272],"type":"Point"}
}