{
  "type": "Feature",
  "properties": {
    "gn:country": "GB",
    "gn:fcode": "PPL",
    "gn:population": 10256,
    "iso:country": "GB",
    "name:ben_x_preferred": [
      "ব্রডস্টোন"
    ],
    "name:bul_x_preferred": [
      "Броадстоне"
    ],
    "name:ceb_x_preferred": [
      "Broadstone"
    ],
    "name:cym_x_preferred": [
      "Broadstone"
    ],
    "name:deu_x_preferred": [
      "Broadstone"
    ],
    "name:ell_x_preferred": [
      "Μπρόουντστοουν"
    ],
    "name:eng_x_preferred": [
      "Broadstone"
    ],
    "name:fas_x_preferred": [
      "برودستون"
    ],
    "name:fra_x_preferred": [
      "Broadstone"
    ],
    "name:fra_x_variant": [
      "Broadstone"
    ],
    "name:guj_x_preferred": [
      "બ્રોડસ્ટોન"
    ],
    "name:heb_x_preferred": [
      "ברודסטון"
    ],
    "name:ind_x_preferred": [
      "Broadstone"
    ],
    "name:ita_x_preferred": [
      "Broadstone"
    ],
    "name:jpn_x_preferred": [
      "ブロードストーン"
    ],
    "name:kan_x_preferred": [
      "ಬ್ರಾಡ್ಸ್ಟೋನ್"
    ],
    "name:kat_x_preferred": [
      "ბროდსტოუნი"
    ],
    "name:kor_x_preferred": [
      "브로드스톤"
    ],
    "name:lit_x_preferred": [
      "Brodstaunas"
    ],
    "name:nld_x_preferred": [
      "Broadstone"
    ],
    "name:pol_x_preferred": [
      "Broadstone"
    ],
    "name:por_x_preferred": [
      "Broadstone"
    ],
    "name:rus_x_preferred": [
      "Бродстоун"
    ],
    "name:spa_x_preferred": [
      "Broadstone"
    ],
    "name:spa_x_variant": [
      "Broadstone"
    ],
    "name:swe_x_preferred": [
      "Broadstone"
    ],
    "name:tam_x_preferred": [
      "ப்ரோடுஸ்டோன்"
    ],
    "name:tel_x_preferred": [
      "బ్రాడ్ స్టోన్"
    ],
    "name:urd_x_preferred": [
      "بروادسٹنی"
    ],
    "qs_pg:aaroncc": "GB",
    "qs_pg:gn_country": "GB",
    "qs_pg:gn_fcode": "PPL",
    "qs_pg:gn_pop": 10256,
    "qs_pg:name": "Broadstone",
    "qs_pg:name_adm0": "United Kingdom",
    "qs_pg:name_adm1": "England",
    "qs_pg:photos": 1648,
    "qs_pg:photos_1k": 334,
    "qs_pg:photos_9k": 7,
    "qs_pg:photos_9r": 8,
    "qs_pg:photos_all": 1648,
    "qs_pg:photos_sr": 13,
    "qs_pg:pop_sr": 6,
    "qs_pg:qs_pg_placetype": "locality",
    "qs_pg:qs_pg_placetype_gp": "Town",
    "qs_pg:woe_adm0": 23424975,
    "woe:adm0_id": 23424975,
    "woe:name_adm0": "United Kingdom",
    "woe:name_adm1": "England",
    "woe:placetype": "Town",
    "wof:name": "Broadstone",
    "wof:placetype": "neighbourhood",
    "wof:population": 10256
  },
  "geometry": {"coordinates":[-1.98333,50.75],"type":"Point"}
}
