{
  "type": "Feature",
  "properties": {
    "gn:country":"GB",
    "gn:fcode":"PPL",
    "gn:population":10256,
    "iso:country":"GB",
    "name:ben_x_preferred":[
        "\u09ac\u09cd\u09b0\u09a1\u09b8\u09cd\u099f\u09cb\u09a8"
    ],
    "name:bul_x_preferred":[
        "\u0411\u0440\u043e\u0430\u0434\u0441\u0442\u043e\u043d\u0435"
    ],
    "name:ceb_x_preferred":[
        "Broadstone"
    ],
    "name:cym_x_preferred":[
        "Broadstone"
    ],
    "name:deu_x_preferred":[
        "Broadstone"
    ],
    "name:ell_x_preferred":[
        "\u039c\u03c0\u03c1\u03cc\u03bf\u03c5\u03bd\u03c4\u03c3\u03c4\u03bf\u03bf\u03c5\u03bd"
    ],
    "name:eng_x_preferred":[
        "Broadstone"
    ],
    "name:fas_x_preferred":[
        "\u0628\u0631\u0648\u062f\u0633\u062a\u0648\u0646"
    ],
    "name:fra_x_preferred":[
        "Broadstone"
    ],
    "name:fra_x_variant":[
        "Broadstone"
    ],
    "name:guj_x_preferred":[
        "\u0aac\u0acd\u0ab0\u0acb\u0aa1\u0ab8\u0acd\u0a9f\u0acb\u0aa8"
    ],
    "name:heb_x_preferred":[
        "\u05d1\u05e8\u05d5\u05d3\u05e1\u05d8\u05d5\u05df"
    ],
    "name:ind_x_preferred":[
        "Broadstone"
    ],
    "name:ita_x_preferred":[
        "Broadstone"
    ],
    "name:jpn_x_preferred":[
        "\u30d6\u30ed\u30fc\u30c9\u30b9\u30c8\u30fc\u30f3"
    ],
    "name:kan_x_preferred":[
        "\u0cac\u0ccd\u0cb0\u0cbe\u0ca1\u0ccd\u0cb8\u0ccd\u0c9f\u0ccb\u0ca8\u0ccd"
    ],
    "name:kat_x_preferred":[
        "\u10d1\u10e0\u10dd\u10d3\u10e1\u10e2\u10dd\u10e3\u10dc\u10d8"
    ],
    "name:kor_x_preferred":[
        "\ube0c\ub85c\ub4dc\uc2a4\ud1a4"
    ],
    "name:lit_x_preferred":[
        "Brodstaunas"
    ],
    "name:nld_x_preferred":[
        "Broadstone"
    ],
    "name:pol_x_preferred":[
        "Broadstone"
    ],
    "name:por_x_preferred":[
        "Broadstone"
    ],
    "name:rus_x_preferred":[
        "\u0411\u0440\u043e\u0434\u0441\u0442\u043e\u0443\u043d"
    ],
    "name:spa_x_preferred":[
        "Broadstone"
    ],
    "name:spa_x_variant":[
        "Broadstone"
    ],
    "name:swe_x_preferred":[
        "Broadstone"
    ],
    "name:tam_x_preferred":[
        "\u0baa\u0bcd\u0bb0\u0bcb\u0b9f\u0bc1\u0bb8\u0bcd\u0b9f\u0bcb\u0ba9\u0bcd"
    ],
    "name:tel_x_preferred":[
        "\u0c2c\u0c4d\u0c30\u0c3e\u0c21\u0c4d \u0c38\u0c4d\u0c1f\u0c4b\u0c28\u0c4d"
    ],
    "name:urd_x_preferred":[
        "\u0628\u0631\u0648\u0627\u062f\u0633\u0679\u0646\u06cc"
    ],
    "qs_pg:aaroncc":"GB",
    "qs_pg:gn_country":"GB",
    "qs_pg:gn_fcode":"PPL",
    "qs_pg:gn_pop":10256,
    "qs_pg:name":"Broadstone",
    "qs_pg:name_adm0":"United Kingdom",
    "qs_pg:name_adm1":"England",
    "qs_pg:photos":1648,
    "qs_pg:photos_1k":334,
    "qs_pg:photos_9k":7,
    "qs_pg:photos_9r":8,
    "qs_pg:photos_all":1648,
    "qs_pg:photos_sr":13,
    "qs_pg:pop_sr":6,
    "qs_pg:qs_pg_placetype":"locality",
    "qs_pg:qs_pg_placetype_gp":"Town",
    "qs_pg:woe_adm0":23424975,
    "woe:adm0_id":23424975,
    "woe:name_adm0":"United Kingdom",
    "woe:name_adm1":"England",
    "woe:placetype":"Town",
    "wof:name":"Broadstone",
    "wof:placetype":"neighbourhood",
    "wof:population":10256
},
  "geometry": {"coordinates":[-1.98333,50.75],"type":"Point"}
}