{
  "type": "Feature",
  "properties": {
    "gn:admin1_code":"ENG",
    "gn:admin2_code":"I9",
    "gn:admin3_code":"33UE",
    "gn:admin4_code":"33UE068",
    "gn:asciiname":"Southgate",
    "gn:country_code":"GB",
    "gn:dem":13,
    "gn:feature_class":"P",
    "gn:feature_code":"PPL",
    "gn:name":"Southgate",
    "gn:population":0,
    "gn:timezone":"Europe/London",
    "iso:country":"GB",
    "wof:name":"Southgate",
    "wof:placetype":"neighbourhood"
},
  "geometry": {"coordinates":[0.49644,52.87314],"type":"Point"}
}