{
  "type": "Feature",
  "properties": {
    "gn:admin1_code": "ENG",
    "gn:admin2_code": "I9",
    "gn:admin3_code": "33UE",
    "gn:admin4_code": "33UE068",
    "gn:asciiname": "Southgate",
    "gn:country_code": "GB",
    "gn:dem": 13,
    "gn:feature_class": "P",
    "gn:feature_code": "PPL",
    "gn:name": "Southgate",
    "gn:population": 0,
    "gn:timezone": "Europe/London",
    "iso:country": "GB",
    "name:cat_x_preferred": [
      "Southgate"
    ],
    "name:ceb_x_preferred": [
      "Southgate"
    ],
    "name:cym_x_preferred": [
      "Southgate"
    ],
    "name:deu_x_preferred": [
      "Southgate"
    ],
    "name:ita_x_preferred": [
      "Southgate"
    ],
    "name:jpn_x_preferred": [
      "サウスゲート"
    ],
    "name:kor_x_preferred": [
      "사우스게이트"
    ],
    "name:nld_x_preferred": [
      "Southgate"
    ],
    "name:pol_x_preferred": [
      "Southgate"
    ],
    "name:por_x_preferred": [
      "Southgate"
    ],
    "name:rus_x_preferred": [
      "Саутгейт"
    ],
    "name:srp_x_preferred": [
      "Саут Гејт"
    ],
    "name:swe_x_preferred": [
      "Southgate"
    ],
    "name:urd_x_preferred": [
      "ساؤتھ گیٹ"
    ],
    "name:vol_x_preferred": [
      "Southgate"
    ],
    "wof:name": "Southgate",
    "wof:placetype": "neighbourhood"
  },
  "geometry": {"coordinates":[0.49644,52.87314],"type":"Point"}
}
