{
  "type": "Feature",
  "properties": {
    "gn:admin1_code":"ENG",
    "gn:admin2_code":"I9",
    "gn:admin3_code":"33UE",
    "gn:admin4_code":"33UE068",
    "gn:asciiname":"Southgate",
    "gn:country_code":"GB",
    "gn:dem":13,
    "gn:feature_class":"P",
    "gn:feature_code":"PPL",
    "gn:name":"Southgate",
    "gn:population":0,
    "gn:timezone":"Europe/London",
    "iso:country":"GB",
    "name:cat_x_preferred":[
        "Southgate"
    ],
    "name:ceb_x_preferred":[
        "Southgate"
    ],
    "name:cym_x_preferred":[
        "Southgate"
    ],
    "name:deu_x_preferred":[
        "Southgate"
    ],
    "name:ita_x_preferred":[
        "Southgate"
    ],
    "name:jpn_x_preferred":[
        "\u30b5\u30a6\u30b9\u30b2\u30fc\u30c8"
    ],
    "name:kor_x_preferred":[
        "\uc0ac\uc6b0\uc2a4\uac8c\uc774\ud2b8"
    ],
    "name:nld_x_preferred":[
        "Southgate"
    ],
    "name:pol_x_preferred":[
        "Southgate"
    ],
    "name:por_x_preferred":[
        "Southgate"
    ],
    "name:rus_x_preferred":[
        "\u0421\u0430\u0443\u0442\u0433\u0435\u0439\u0442"
    ],
    "name:srp_x_preferred":[
        "\u0421\u0430\u0443\u0442 \u0413\u0435\u0458\u0442"
    ],
    "name:swe_x_preferred":[
        "Southgate"
    ],
    "name:urd_x_preferred":[
        "\u0633\u0627\u0624\u062a\u06be \u06af\u06cc\u0679"
    ],
    "name:vol_x_preferred":[
        "Southgate"
    ],
    "wof:name":"Southgate",
    "wof:placetype":"neighbourhood"
},
  "geometry": {"coordinates":[0.49644,52.87314],"type":"Point"}
}