{
  "type": "Feature",
  "properties": {
    "gn:country":"GB",
    "gn:fcode":"PPL",
    "gn:population":0,
    "iso:country":"GB",
    "name:bre_x_preferred":[
        "Talacre"
    ],
    "name:cym_x_preferred":[
        "Talacre"
    ],
    "name:eng_x_preferred":[
        "Talacre"
    ],
    "name:eus_x_preferred":[
        "Talacre"
    ],
    "name:fra_x_preferred":[
        "Talacre"
    ],
    "name:gle_x_preferred":[
        "Talacre"
    ],
    "name:nld_x_preferred":[
        "Talacre"
    ],
    "name:rus_x_preferred":[
        "\u0422\u0430\u043b\u0430\u043a\u0440"
    ],
    "name:spa_x_preferred":[
        "Talacre"
    ],
    "name:swe_x_preferred":[
        "Talacre"
    ],
    "qs_pg:aaroncc":"GB",
    "qs_pg:gn_country":"GB",
    "qs_pg:gn_fcode":"PPL",
    "qs_pg:gn_pop":0,
    "qs_pg:name":"Talacre",
    "qs_pg:name_adm0":"United Kingdom",
    "qs_pg:name_adm1":"Wales",
    "qs_pg:photos":1617,
    "qs_pg:photos_1k":328,
    "qs_pg:photos_9k":7,
    "qs_pg:photos_9r":8,
    "qs_pg:photos_all":1617,
    "qs_pg:photos_sr":13,
    "qs_pg:pop_sr":0,
    "qs_pg:qs_pg_placetype":"locality",
    "qs_pg:qs_pg_placetype_gp":"Town",
    "qs_pg:woe_adm0":23424975,
    "woe:adm0_id":23424975,
    "woe:name_adm0":"United Kingdom",
    "woe:name_adm1":"Wales",
    "woe:placetype":"Town",
    "wof:name":"Talacre",
    "wof:placetype":"neighbourhood",
    "wof:population":347
},
  "geometry": {"coordinates":[-3.32474,53.34942],"type":"Point"}
}