{
  "type": "Feature",
  "properties": {
    "gn:country":"GB",
    "gn:fcode":"PPL",
    "gn:population":0,
    "iso:country":"GB",
    "name:cym_x_preferred":[
        "Springfield"
    ],
    "name:eng_x_preferred":[
        "Springfield"
    ],
    "name:eus_x_preferred":[
        "Springfield"
    ],
    "name:gle_x_preferred":[
        "Achadh an Fhuarain"
    ],
    "name:nld_x_preferred":[
        "Springfield"
    ],
    "name:slv_x_preferred":[
        "Springfield"
    ],
    "name:spa_x_preferred":[
        "Springfield"
    ],
    "name:swe_x_preferred":[
        "Springfield"
    ],
    "qs_pg:aaroncc":"GB",
    "qs_pg:gn_country":"GB",
    "qs_pg:gn_fcode":"PPL",
    "qs_pg:gn_pop":0,
    "qs_pg:name":"Springfield",
    "qs_pg:name_adm0":"United Kingdom",
    "qs_pg:name_adm1":"Scotland",
    "qs_pg:photos":78,
    "qs_pg:photos_1k":16,
    "qs_pg:photos_9k":1,
    "qs_pg:photos_9r":3,
    "qs_pg:photos_all":78,
    "qs_pg:photos_sr":3,
    "qs_pg:pop_sr":0,
    "qs_pg:qs_pg_placetype":"locality",
    "qs_pg:qs_pg_placetype_gp":"Town",
    "qs_pg:woe_adm0":23424975,
    "woe:adm0_id":23424975,
    "woe:name_adm0":"United Kingdom",
    "woe:name_adm1":"Scotland",
    "woe:placetype":"Town",
    "wof:name":"Springfield",
    "wof:placetype":"locality",
    "wof:population":960
},
  "geometry": {"coordinates":[-3.06667,56.28333],"type":"Point"}
}