{
  "type": "Feature",
  "properties": {
    "gn:country":"GB",
    "gn:fcode":"PPL",
    "gn:population":0,
    "iso:country":"GB",
    "name:cym_x_preferred":[
        "Lawrenny"
    ],
    "name:cym_x_variant":[
        "Lawrenni"
    ],
    "name:eng_x_preferred":[
        "Lawrenny"
    ],
    "name:fra_x_preferred":[
        "Lawrenny"
    ],
    "name:gle_x_preferred":[
        "Lawrenni"
    ],
    "name:nld_x_preferred":[
        "Lawrenny"
    ],
    "qs_pg:aaroncc":"GB",
    "qs_pg:gn_country":"GB",
    "qs_pg:gn_fcode":"PPL",
    "qs_pg:gn_pop":0,
    "qs_pg:name":"Lawrenny",
    "qs_pg:name_adm0":"United Kingdom",
    "qs_pg:name_adm1":"Wales",
    "qs_pg:photos":118,
    "qs_pg:photos_1k":24,
    "qs_pg:photos_9k":1,
    "qs_pg:photos_9r":3,
    "qs_pg:photos_all":118,
    "qs_pg:photos_sr":3,
    "qs_pg:pop_sr":0,
    "qs_pg:qs_pg_placetype":"locality",
    "qs_pg:qs_pg_placetype_gp":"Town",
    "qs_pg:woe_adm0":23424975,
    "woe:adm0_id":23424975,
    "woe:name_adm0":"United Kingdom",
    "woe:name_adm1":"Wales",
    "woe:placetype":"Town",
    "wof:name":"Lawrenny",
    "wof:placetype":"neighbourhood"
},
  "geometry": {"coordinates":[-4.87194,51.72583],"type":"Point"}
}