{
  "type": "Feature",
  "properties": {
    "iso:country": "GB",
    "name:cym_x_preferred": [
      "Canal Foot"
    ],
    "name:eng_x_preferred": [
      "Canal Foot"
    ],
    "name:fra_x_preferred": [
      "canal Foot"
    ],
    "name:nld_x_preferred": [
      "Canal Foot"
    ],
    "qs_pg:aaroncc": "GB",
    "qs_pg:name": "Canal Foot",
    "qs_pg:name_adm0": "United Kingdom",
    "qs_pg:name_adm1": "England",
    "qs_pg:photos": 90,
    "qs_pg:photos_1k": 18,
    "qs_pg:photos_9k": 1,
    "qs_pg:photos_9r": 3,
    "qs_pg:photos_all": 90,
    "qs_pg:photos_sr": 3,
    "qs_pg:pop_sr": 0,
    "qs_pg:qs_pg_placetype": "locality",
    "qs_pg:qs_pg_placetype_gp": "Town",
    "qs_pg:woe_adm0": 23424975,
    "woe:adm0_id": 23424975,
    "woe:name_adm0": "United Kingdom",
    "woe:name_adm1": "England",
    "woe:placetype": "Town",
    "wof:name": "Canal Foot",
    "wof:placetype": "neighbourhood"
  },
  "geometry": {"coordinates":[-3.054113,54.1900505],"type":"Point"}
}
