{
  "type": "Feature",
  "properties": {
    "gn:admin1_code":"SCT",
    "gn:admin2_code":"V8",
    "gn:asciiname":"Calderbank",
    "gn:country_code":"GB",
    "gn:dem":118,
    "gn:feature_class":"P",
    "gn:feature_code":"PPL",
    "gn:name":"Calderbank",
    "gn:population":1610,
    "gn:timezone":"Europe/London",
    "iso:country":"GB",
    "name:bre_x_preferred":[
        "Calderbank"
    ],
    "name:eus_x_preferred":[
        "Calderbank"
    ],
    "name:spa_x_preferred":[
        "Calderbank"
    ],
    "name:swe_x_preferred":[
        "Calderbank"
    ],
    "wof:name":"Calderbank",
    "wof:placetype":"locality",
    "wof:population":1610
},
  "geometry": {"coordinates":[-3.9707,55.84318],"type":"Point"}
}