{
  "type": "Feature",
  "properties": {
    "gn:admin1_code": "ENG",
    "gn:admin2_code": "G5",
    "gn:admin3_code": "6945807",
    "gn:asciiname": "Bishopstone",
    "gn:country_code": "GB",
    "gn:dem": 8,
    "gn:feature_class": "P",
    "gn:feature_code": "PPL",
    "gn:name": "Bishopstone",
    "gn:population": 0,
    "gn:timezone": "Europe/London",
    "iso:country": "GB",
    "name:ceb_x_preferred": [
      "Bishopstone"
    ],
    "name:jpn_x_preferred": [
      "ビショップストーン"
    ],
    "name:nld_x_preferred": [
      "Bishopstone"
    ],
    "name:pol_x_preferred": [
      "Bishopstone"
    ],
    "name:swe_x_preferred": [
      "Bishopstone"
    ],
    "wof:name": "Bishopstone",
    "wof:placetype": "neighbourhood"
  },
  "geometry": {"coordinates":[1.19167,51.37083],"type":"Point"}
}
