{
  "type": "Feature",
  "properties": {
    "gn:admin1_code":"NIR",
    "gn:admin2_code":"N09000006",
    "gn:asciiname":"Irish Town",
    "gn:country_code":"GB",
    "gn:dem":273,
    "gn:feature_class":"P",
    "gn:feature_code":"PPL",
    "gn:name":"Irish Town",
    "gn:population":0,
    "gn:timezone":"Europe/London",
    "iso:country":"GB",
    "wof:name":"Irish Town",
    "wof:placetype":"locality"
},
  "geometry": {"coordinates":[-7.13333,54.71666999999999],"type":"Point"}
}