{
  "type": "Feature",
  "properties": {
    "iso:country":"GB",
    "name:eng_x_preferred":[
        "Windmill Hill"
    ],
    "wof:name":"Windmill Hill",
    "wof:placetype":"neighbourhood"
},
  "geometry": {"coordinates":[-2.58675745584831,51.43824729150759],"type":"Point"}
}