{
  "type": "Feature",
  "properties": {
    "iso:country":"GB",
    "name:ceb_x_preferred":[
        "Waddington"
    ],
    "name:cym_x_preferred":[
        "Waddington"
    ],
    "name:eng_x_preferred":[
        "Waddington"
    ],
    "name:fas_x_preferred":[
        "\u0648\u062f\u062f\u06cc\u0646\u06af\u062a\u0648\u0646"
    ],
    "name:fra_x_preferred":[
        "Waddington"
    ],
    "name:gle_x_preferred":[
        "Waddington"
    ],
    "name:ita_x_preferred":[
        "Waddington"
    ],
    "name:jpn_x_preferred":[
        "\u30a6\u30a9\u30c7\u30a3\u30f3\u30c8\u30f3"
    ],
    "name:lld_x_preferred":[
        "Waddington"
    ],
    "name:nld_x_preferred":[
        "Waddington"
    ],
    "name:pol_x_preferred":[
        "Waddington"
    ],
    "name:spa_x_preferred":[
        "Waddington"
    ],
    "name:swe_x_preferred":[
        "Waddington"
    ],
    "name:tur_x_preferred":[
        "Waddington"
    ],
    "qs:a0":"United Kingdom",
    "qs:a1":"*Lancashire",
    "qs:a1_lc":"GB12300000",
    "qs:a1r":"0England",
    "qs:a1r_lc":"GB12000000",
    "qs:adm0":"United Kingdom",
    "qs:la_lc":"*",
    "qs:level":"locality",
    "qs:loc":"Waddington",
    "qs:loc_alt":"Waddington",
    "qs:pop":0,
    "qs:type":"buffered point",
    "wd:wordcount":586,
    "wof:name":"Waddington",
    "wof:placetype":"neighbourhood"
},
  "geometry": {"coordinates":[-2.412441,53.889507],"type":"Point"}
}