{
  "type": "Feature",
  "properties": {
    "iso:country":"GB",
    "name:ceb_x_preferred":[
        "Bigton Wick"
    ],
    "name:eng_x_preferred":[
        "Bigton"
    ],
    "name:eus_x_preferred":[
        "Bigton"
    ],
    "name:fra_x_preferred":[
        "Bigton"
    ],
    "name:jpn_x_preferred":[
        "\u30d3\u30c3\u30b0\u30c8\u30f3"
    ],
    "name:nld_x_preferred":[
        "Bigton"
    ],
    "name:swe_x_preferred":[
        "Bigton Wick"
    ],
    "qs_pg:aaroncc":"GB",
    "qs_pg:name":"Bigton",
    "qs_pg:name_adm0":"United Kingdom",
    "qs_pg:name_adm1":"Scotland",
    "qs_pg:photos":620,
    "qs_pg:photos_1k":126,
    "qs_pg:photos_9k":3,
    "qs_pg:photos_9r":5,
    "qs_pg:photos_all":620,
    "qs_pg:photos_sr":8,
    "qs_pg:pop_sr":0,
    "qs_pg:qs_pg_placetype":"locality",
    "qs_pg:qs_pg_placetype_gp":"Town",
    "qs_pg:woe_adm0":23424975,
    "woe:adm0_id":23424975,
    "woe:name_adm0":"United Kingdom",
    "woe:name_adm1":"Scotland",
    "woe:placetype":"Town",
    "wof:name":"Bigton",
    "wof:placetype":"locality"
},
  "geometry": {"coordinates":[-1.336812,59.970391],"type":"Point"}
}