{
  "type": "Feature",
  "properties": {
    "gn:admin1_code":"SCT",
    "gn:admin2_code":"T6",
    "gn:asciiname":"Kinmuck",
    "gn:country_code":"GB",
    "gn:dem":115,
    "gn:feature_class":"P",
    "gn:feature_code":"PPL",
    "gn:name":"Kinmuck",
    "gn:population":0,
    "gn:timezone":"Europe/London",
    "iso:country":"GB",
    "name:eus_x_preferred":[
        "Kinmuck"
    ],
    "wof:name":"Kinmuck",
    "wof:placetype":"locality"
},
  "geometry": {"coordinates":[-2.30407,57.26876],"type":"Point"}
}