{
  "type": "Feature",
  "properties": {
    "iso:country":"GB",
    "name:bre_x_preferred":[
        "Llangiwa"
    ],
    "name:cym_x_preferred":[
        "Llangiwa"
    ],
    "name:eng_x_preferred":[
        "Llangua"
    ],
    "name:eus_x_preferred":[
        "Llangua"
    ],
    "name:fra_x_preferred":[
        "Llangua"
    ],
    "name:jpn_x_preferred":[
        "\u30b9\u30e9\u30f3\u30ae\u30a2"
    ],
    "name:nld_x_preferred":[
        "Llangua"
    ],
    "qs_pg:aaroncc":"GB",
    "qs_pg:name":"Llangua",
    "qs_pg:name_adm0":"United Kingdom",
    "qs_pg:name_adm1":"Wales",
    "qs_pg:photos":27,
    "qs_pg:photos_1k":5,
    "qs_pg:photos_9k":1,
    "qs_pg:photos_9r":2,
    "qs_pg:photos_all":27,
    "qs_pg:photos_sr":2,
    "qs_pg:pop_sr":0,
    "qs_pg:qs_pg_placetype":"locality",
    "qs_pg:qs_pg_placetype_gp":"Town",
    "qs_pg:woe_adm0":23424975,
    "woe:adm0_id":23424975,
    "woe:name_adm0":"United Kingdom",
    "woe:name_adm1":"Wales",
    "woe:placetype":"Town",
    "wof:name":"Llangua",
    "wof:placetype":"locality"
},
  "geometry": {"coordinates":[-2.888202,51.927754],"type":"Point"}
}