{
  "type": "Feature",
  "properties": {
    "gn:country":"GB",
    "gn:fcode":"PPL",
    "gn:population":3447,
    "iso:country":"GB",
    "name:bul_x_preferred":[
        "\u0428\u0438\u0440\u043b\u0430\u043d\u0434"
    ],
    "name:ceb_x_preferred":[
        "Shirland"
    ],
    "name:cym_x_preferred":[
        "Shirland"
    ],
    "name:eng_x_preferred":[
        "Shirland"
    ],
    "name:fas_x_preferred":[
        "\u0634\u06cc\u0631\u0644\u0646\u062f"
    ],
    "name:fra_x_preferred":[
        "Shirland"
    ],
    "name:ita_x_preferred":[
        "Shirland"
    ],
    "name:nld_x_preferred":[
        "Shirland"
    ],
    "name:pol_x_preferred":[
        "Shirland"
    ],
    "name:swe_x_preferred":[
        "Shirland"
    ],
    "qs_pg:aaroncc":"GB",
    "qs_pg:gn_country":"GB",
    "qs_pg:gn_fcode":"PPL",
    "qs_pg:gn_pop":3447,
    "qs_pg:name":"Shirland",
    "qs_pg:name_adm0":"United Kingdom",
    "qs_pg:name_adm1":"England",
    "qs_pg:photos":13,
    "qs_pg:photos_1k":3,
    "qs_pg:photos_9k":1,
    "qs_pg:photos_9r":1,
    "qs_pg:photos_all":13,
    "qs_pg:photos_sr":1,
    "qs_pg:pop_sr":4,
    "qs_pg:qs_pg_placetype":"locality",
    "qs_pg:qs_pg_placetype_gp":"Town",
    "qs_pg:woe_adm0":23424975,
    "woe:adm0_id":23424975,
    "woe:name_adm0":"United Kingdom",
    "woe:name_adm1":"England",
    "woe:placetype":"Town",
    "wof:name":"Shirland",
    "wof:placetype":"neighbourhood",
    "wof:population":3447
},
  "geometry": {"coordinates":[-1.40464,53.12155],"type":"Point"}
}