{
  "type": "Feature",
  "properties": {
    "iso:country":"GB",
    "wof:name":"Hebburn Row",
    "wof:placetype":"neighbourhood"
},
  "geometry": {"coordinates":[-1.51834663777917,54.97936459366721],"type":"Point"}
}