{
  "type": "Feature",
  "properties": {
    "gn:country":"GB",
    "gn:fcode":"PPL",
    "gn:population":0,
    "iso:country":"GB",
    "name:deu_x_preferred":[
        "Temple Balsall"
    ],
    "name:eng_x_preferred":[
        "Temple Balsall"
    ],
    "name:fra_x_preferred":[
        "Temple Balsall"
    ],
    "name:gle_x_preferred":[
        "Temple Balsall"
    ],
    "name:nld_x_preferred":[
        "Temple Balsall"
    ],
    "name:pol_x_preferred":[
        "Temple Balsall"
    ],
    "name:sco_x_preferred":[
        "Temple Balsall"
    ],
    "qs_pg:aaroncc":"GB",
    "qs_pg:gn_country":"GB",
    "qs_pg:gn_fcode":"PPL",
    "qs_pg:gn_pop":0,
    "qs_pg:name":"Temple Balsall",
    "qs_pg:name_adm0":"United Kingdom",
    "qs_pg:name_adm1":"England",
    "qs_pg:photos":159,
    "qs_pg:photos_1k":32,
    "qs_pg:photos_9k":1,
    "qs_pg:photos_9r":4,
    "qs_pg:photos_all":159,
    "qs_pg:photos_sr":4,
    "qs_pg:pop_sr":0,
    "qs_pg:qs_pg_placetype":"locality",
    "qs_pg:qs_pg_placetype_gp":"Town",
    "qs_pg:woe_adm0":23424975,
    "woe:adm0_id":23424975,
    "woe:name_adm0":"United Kingdom",
    "woe:name_adm1":"England",
    "woe:placetype":"Town",
    "wof:name":"Temple Balsall",
    "wof:placetype":"neighbourhood"
},
  "geometry": {"coordinates":[-1.69647,52.38296],"type":"Point"}
}