{
  "type": "Feature",
  "properties": {
    "iso:country":"GB",
    "name:cym_x_preferred":[
        "Pendrift"
    ],
    "name:eng_x_preferred":[
        "Pendrift"
    ],
    "name:eus_x_preferred":[
        "Pendrift"
    ],
    "name:fra_x_preferred":[
        "Pendrift"
    ],
    "name:nld_x_preferred":[
        "Pendrift"
    ],
    "qs_pg:aaroncc":"GB",
    "qs_pg:name":"Pendrift",
    "qs_pg:name_adm0":"United Kingdom",
    "qs_pg:name_adm1":"England",
    "qs_pg:photos":21,
    "qs_pg:photos_1k":4,
    "qs_pg:photos_9k":1,
    "qs_pg:photos_9r":1,
    "qs_pg:photos_all":21,
    "qs_pg:photos_sr":1,
    "qs_pg:pop_sr":0,
    "qs_pg:qs_pg_placetype":"locality",
    "qs_pg:qs_pg_placetype_gp":"Town",
    "qs_pg:woe_adm0":23424975,
    "woe:adm0_id":23424975,
    "woe:name_adm0":"United Kingdom",
    "woe:name_adm1":"England",
    "woe:placetype":"Town",
    "wof:name":"Pendrift",
    "wof:placetype":"neighbourhood"
},
  "geometry": {"coordinates":[-4.669747,50.54349],"type":"Point"}
}