{
  "type": "Feature",
  "properties": {
    "gn:admin1_code": "NIR",
    "gn:admin2_code": "N09000005",
    "gn:asciiname": "The Rock",
    "gn:country_code": "GB",
    "gn:dem": 168,
    "gn:feature_class": "P",
    "gn:feature_code": "PPL",
    "gn:name": "The Rock",
    "gn:population": 0,
    "gn:timezone": "Europe/London",
    "iso:country": "GB",
    "name:ara_x_preferred": [
      "ذا روك"
    ],
    "name:bar_x_preferred": [
      "The Rock"
    ],
    "name:bos_x_preferred": [
      "The Rock"
    ],
    "name:ceb_x_preferred": [
      "The Rock"
    ],
    "name:dan_x_preferred": [
      "The Rock"
    ],
    "name:deu_x_preferred": [
      "The Rock"
    ],
    "name:ell_x_preferred": [
      "The Rock"
    ],
    "name:fas_x_preferred": [
      "صخره"
    ],
    "name:fra_x_preferred": [
      "The Rock"
    ],
    "name:heb_x_preferred": [
      "דה רוק"
    ],
    "name:ind_x_preferred": [
      "The Rock"
    ],
    "name:ita_x_preferred": [
      "The Rock"
    ],
    "name:jpn_x_preferred": [
      "ザ・ロック"
    ],
    "name:kor_x_preferred": [
      "더 록"
    ],
    "name:nld_x_preferred": [
      "The Rock"
    ],
    "name:nor_x_preferred": [
      "The Rock"
    ],
    "name:pol_x_preferred": [
      "The Rock"
    ],
    "name:swe_x_preferred": [
      "The Rock"
    ],
    "name:tha_x_preferred": [
      "เดอะ ร็อก"
    ],
    "name:tur_x_preferred": [
      "The Rock"
    ],
    "wof:name": "The Rock",
    "wof:placetype": "locality"
  },
  "geometry": {"coordinates":[-7.68333,54.65],"type":"Point"}
}
