{
  "type": "Feature",
  "properties": {
    "gn:admin1_code":"NIR",
    "gn:admin2_code":"N09000005",
    "gn:asciiname":"The Rock",
    "gn:country_code":"GB",
    "gn:dem":168,
    "gn:feature_class":"P",
    "gn:feature_code":"PPL",
    "gn:name":"The Rock",
    "gn:population":0,
    "gn:timezone":"Europe/London",
    "iso:country":"GB",
    "name:ara_x_preferred":[
        "\u0630\u0627 \u0631\u0648\u0643"
    ],
    "name:bar_x_preferred":[
        "The Rock"
    ],
    "name:bos_x_preferred":[
        "The Rock"
    ],
    "name:ceb_x_preferred":[
        "The Rock"
    ],
    "name:dan_x_preferred":[
        "The Rock"
    ],
    "name:deu_x_preferred":[
        "The Rock"
    ],
    "name:ell_x_preferred":[
        "The Rock"
    ],
    "name:fas_x_preferred":[
        "\u0635\u062e\u0631\u0647"
    ],
    "name:fra_x_preferred":[
        "The Rock"
    ],
    "name:heb_x_preferred":[
        "\u05d3\u05d4 \u05e8\u05d5\u05e7"
    ],
    "name:ind_x_preferred":[
        "The Rock"
    ],
    "name:ita_x_preferred":[
        "The Rock"
    ],
    "name:jpn_x_preferred":[
        "\u30b6\u30fb\u30ed\u30c3\u30af"
    ],
    "name:kor_x_preferred":[
        "\ub354 \ub85d"
    ],
    "name:nld_x_preferred":[
        "The Rock"
    ],
    "name:nor_x_preferred":[
        "The Rock"
    ],
    "name:pol_x_preferred":[
        "The Rock"
    ],
    "name:swe_x_preferred":[
        "The Rock"
    ],
    "name:tha_x_preferred":[
        "\u0e40\u0e14\u0e2d\u0e30 \u0e23\u0e47\u0e2d\u0e01"
    ],
    "name:tur_x_preferred":[
        "The Rock"
    ],
    "wof:name":"The Rock",
    "wof:placetype":"locality"
},
  "geometry": {"coordinates":[-7.68333,54.65],"type":"Point"}
}