{
  "type": "Feature",
  "properties": {
    "iso:country": "GB",
    "qs_pg:aaroncc": "GB",
    "qs_pg:name": "Talla Linnfoots",
    "qs_pg:name_adm0": "United Kingdom",
    "qs_pg:name_adm1": "Scotland",
    "qs_pg:photos": 241,
    "qs_pg:photos_1k": 49,
    "qs_pg:photos_9k": 1,
    "qs_pg:photos_9r": 4,
    "qs_pg:photos_all": 241,
    "qs_pg:photos_sr": 4,
    "qs_pg:pop_sr": 0,
    "qs_pg:qs_pg_placetype": "locality",
    "qs_pg:qs_pg_placetype_gp": "Town",
    "qs_pg:woe_adm0": 23424975,
    "woe:adm0_id": 23424975,
    "woe:name_adm0": "United Kingdom",
    "woe:name_adm1": "Scotland",
    "woe:placetype": "Town",
    "wof:name": "Talla Linnfoots",
    "wof:placetype": "locality"
  },
  "geometry": {"coordinates":[-3.36379,55.46736],"type":"Point"}
}
