{
  "type": "Feature",
  "properties": {
    "gn:gn_country":"GB",
    "gn:gn_fcode":"PPL",
    "gn:gn_pop":0,
    "iso:country":"GB",
    "name:dut_x_preferred":[
        "Walton-on-the-Hill"
    ],
    "name:eng_x_preferred":[
        "Walton-on-the-Hill"
    ],
    "name:fre_x_preferred":[
        "Walton-on-the-Hill"
    ],
    "name:unk_x_variant":[
        "Walton"
    ],
    "name:urd_x_preferred":[
        "\u0648\u0627\u0644\u0679\u0646-\u0622\u0646-\u062f\u06c1-\u06c1\u0644"
    ],
    "qs_pg:aaroncc":"GB",
    "qs_pg:gn_country":"GB",
    "qs_pg:gn_fcode":"PPL",
    "qs_pg:gn_pop":0,
    "qs_pg:name":"Walton on the Hill",
    "qs_pg:name_adm0":"United Kingdom",
    "qs_pg:name_adm1":"England",
    "qs_pg:photos":70,
    "qs_pg:photos_1k":14,
    "qs_pg:photos_9k":1,
    "qs_pg:photos_9r":2,
    "qs_pg:photos_all":70,
    "qs_pg:photos_sr":2,
    "qs_pg:pop_sr":0,
    "qs_pg:qs_pg_placetype":"locality",
    "qs_pg:qs_pg_placetype_gp":"Town",
    "qs_pg:woe_adm0":23424975,
    "woe:adm0_id":23424975,
    "woe:name_adm0":"United Kingdom",
    "woe:name_adm1":"England",
    "woe:placetype":"Town",
    "wof:name":"Walton on the Hill",
    "wof:placetype":"neighbourhood"
},
  "geometry": {"coordinates":[-0.24805,51.28296],"type":"Point"}
}