{
  "type": "Feature",
  "properties": {
    "gn:population": 5978,
    "iso:country": "GB",
    "name:ben_x_preferred": [
      "ব্যানকোরি"
    ],
    "name:bul_x_preferred": [
      "Банчорй"
    ],
    "name:ceb_x_preferred": [
      "Banchory"
    ],
    "name:cym_x_preferred": [
      "Banchory"
    ],
    "name:deu_x_preferred": [
      "Banchory"
    ],
    "name:eng_x_preferred": [
      "Banchory"
    ],
    "name:eus_x_preferred": [
      "Banchory"
    ],
    "name:fas_x_preferred": [
      "بانچوری"
    ],
    "name:fra_x_preferred": [
      "Banchory"
    ],
    "name:gla_x_preferred": [
      "Beannchar"
    ],
    "name:gle_x_preferred": [
      "Beannchar"
    ],
    "name:guj_x_preferred": [
      "બાંચોરી"
    ],
    "name:ita_x_preferred": [
      "Banchory"
    ],
    "name:jpn_x_preferred": [
      "バンコリー"
    ],
    "name:kan_x_preferred": [
      "ಬಾಂಚೊರಿ"
    ],
    "name:kor_x_preferred": [
      "밴코리"
    ],
    "name:lit_x_preferred": [
      "Bankoris"
    ],
    "name:nld_x_preferred": [
      "Banchory"
    ],
    "name:nno_x_preferred": [
      "Banchory"
    ],
    "name:nob_x_preferred": [
      "Banchory"
    ],
    "name:nor_x_preferred": [
      "Banchory"
    ],
    "name:pol_x_preferred": [
      "Banchory"
    ],
    "name:por_x_preferred": [
      "Banchory"
    ],
    "name:rus_x_preferred": [
      "Банхори"
    ],
    "name:sco_x_preferred": [
      "Banchry"
    ],
    "name:sco_x_variant": [
      "Banchory"
    ],
    "name:spa_x_preferred": [
      "Banchory"
    ],
    "name:swe_x_preferred": [
      "Banchory"
    ],
    "name:tam_x_preferred": [
      "பான்சோரி"
    ],
    "name:tel_x_preferred": [
      "బాంచోరి"
    ],
    "name:urd_x_preferred": [
      "بانچوری"
    ],
    "name:zho_x_preferred": [
      "班科里"
    ],
    "qs:a0": "United Kingdom",
    "qs:a1": "*Aberdeenshire",
    "qs:a1_lc": "GB11QB0000",
    "qs:a1r": "0Scotland",
    "qs:a1r_lc": "GB11000000",
    "qs:adm0": "United Kingdom",
    "qs:la_lc": "*",
    "qs:level": "locality",
    "qs:loc": "Banchory",
    "qs:loc_alt": "Banchory",
    "qs:pop": 0,
    "qs:type": "buffered point",
    "wd:wordcount": 1171,
    "wof:name": "Banchory",
    "wof:placetype": "locality",
    "wof:population": 5978
  },
  "geometry": {"coordinates":[-2.488395,57.052191],"type":"Point"}
}
