{
  "type": "Feature",
  "properties": {
    "gn:population":5978,
    "iso:country":"GB",
    "name:ben_x_preferred":[
        "\u09ac\u09cd\u09af\u09be\u09a8\u0995\u09cb\u09b0\u09bf"
    ],
    "name:bul_x_preferred":[
        "\u0411\u0430\u043d\u0447\u043e\u0440\u0439"
    ],
    "name:ceb_x_preferred":[
        "Banchory"
    ],
    "name:cym_x_preferred":[
        "Banchory"
    ],
    "name:deu_x_preferred":[
        "Banchory"
    ],
    "name:eng_x_preferred":[
        "Banchory"
    ],
    "name:eus_x_preferred":[
        "Banchory"
    ],
    "name:fas_x_preferred":[
        "\u0628\u0627\u0646\u0686\u0648\u0631\u06cc"
    ],
    "name:fra_x_preferred":[
        "Banchory"
    ],
    "name:gla_x_preferred":[
        "Beannchar"
    ],
    "name:gle_x_preferred":[
        "Beannchar"
    ],
    "name:guj_x_preferred":[
        "\u0aac\u0abe\u0a82\u0a9a\u0acb\u0ab0\u0ac0"
    ],
    "name:ita_x_preferred":[
        "Banchory"
    ],
    "name:jpn_x_preferred":[
        "\u30d0\u30f3\u30b3\u30ea\u30fc"
    ],
    "name:kan_x_preferred":[
        "\u0cac\u0cbe\u0c82\u0c9a\u0cca\u0cb0\u0cbf"
    ],
    "name:kor_x_preferred":[
        "\ubc34\ucf54\ub9ac"
    ],
    "name:lit_x_preferred":[
        "Bankoris"
    ],
    "name:nld_x_preferred":[
        "Banchory"
    ],
    "name:nno_x_preferred":[
        "Banchory"
    ],
    "name:nob_x_preferred":[
        "Banchory"
    ],
    "name:nor_x_preferred":[
        "Banchory"
    ],
    "name:pol_x_preferred":[
        "Banchory"
    ],
    "name:por_x_preferred":[
        "Banchory"
    ],
    "name:rus_x_preferred":[
        "\u0411\u0430\u043d\u0445\u043e\u0440\u0438"
    ],
    "name:sco_x_preferred":[
        "Banchry"
    ],
    "name:sco_x_variant":[
        "Banchory"
    ],
    "name:spa_x_preferred":[
        "Banchory"
    ],
    "name:swe_x_preferred":[
        "Banchory"
    ],
    "name:tam_x_preferred":[
        "\u0baa\u0bbe\u0ba9\u0bcd\u0b9a\u0bcb\u0bb0\u0bbf"
    ],
    "name:tel_x_preferred":[
        "\u0c2c\u0c3e\u0c02\u0c1a\u0c4b\u0c30\u0c3f"
    ],
    "name:urd_x_preferred":[
        "\u0628\u0627\u0646\u0686\u0648\u0631\u06cc"
    ],
    "name:zho_x_preferred":[
        "\u73ed\u79d1\u91cc"
    ],
    "qs:a0":"United Kingdom",
    "qs:a1":"*Aberdeenshire",
    "qs:a1_lc":"GB11QB0000",
    "qs:a1r":"0Scotland",
    "qs:a1r_lc":"GB11000000",
    "qs:adm0":"United Kingdom",
    "qs:la_lc":"*",
    "qs:level":"locality",
    "qs:loc":"Banchory",
    "qs:loc_alt":"Banchory",
    "qs:pop":0,
    "qs:type":"buffered point",
    "wd:wordcount":1171,
    "wof:name":"Banchory",
    "wof:placetype":"locality",
    "wof:population":5978
},
  "geometry": {"coordinates":[-2.488395,57.052191],"type":"Point"}
}