{
  "type": "Feature",
  "properties": {
    "gn:admin1_code":"WLS",
    "gn:admin2_code":"X7",
    "gn:admin3_code":"00NU059",
    "gn:asciiname":"Pen-y-banc",
    "gn:country_code":"GB",
    "gn:dem":50,
    "gn:feature_class":"P",
    "gn:feature_code":"PPL",
    "gn:name":"Pen-y-banc",
    "gn:population":0,
    "gn:timezone":"Europe/London",
    "iso:country":"GB",
    "wof:name":"Pen-y-banc",
    "wof:placetype":"neighbourhood"
},
  "geometry": {"coordinates":[-4.01278,51.89583],"type":"Point"}
}