{
  "type": "Feature",
  "properties": {
    "gn:admin1_code":"WLS",
    "gn:admin2_code":"Y4",
    "gn:admin3_code":"00PP007",
    "gn:asciiname":"Little Mill",
    "gn:country_code":"GB",
    "gn:dem":65,
    "gn:feature_class":"P",
    "gn:feature_code":"PPL",
    "gn:name":"Little Mill",
    "gn:population":0,
    "gn:timezone":"Europe/London",
    "iso:country":"GB",
    "name:cym_x_preferred":[
        "Little Mill"
    ],
    "name:eus_x_preferred":[
        "Little Mill"
    ],
    "wof:name":"Little Mill",
    "wof:placetype":"neighbourhood"
},
  "geometry": {"coordinates":[-2.98528,51.72],"type":"Point"}
}