{
  "type": "Feature",
  "properties": {
    "gn:population":1987,
    "iso:country":"GB",
    "name:ceb_x_preferred":[
        "Sanquhar"
    ],
    "name:cym_x_preferred":[
        "Sanquhar"
    ],
    "name:deu_x_preferred":[
        "Sanquhar"
    ],
    "name:eng_x_preferred":[
        "Sanquhar"
    ],
    "name:eus_x_preferred":[
        "Sanquhar"
    ],
    "name:fas_x_preferred":[
        "\u0633\u0646\u06a9\u0648\u0647\u0631"
    ],
    "name:fra_x_preferred":[
        "Sanquhar"
    ],
    "name:gla_x_preferred":[
        "An t-Seann Chathair"
    ],
    "name:gle_x_preferred":[
        "An t-Seann Chathair"
    ],
    "name:ita_x_preferred":[
        "Sanquhar"
    ],
    "name:lit_x_preferred":[
        "Senkeras"
    ],
    "name:nld_x_preferred":[
        "Sanquhar"
    ],
    "name:sco_x_preferred":[
        "Sanchar"
    ],
    "name:spa_x_preferred":[
        "Sanquhar"
    ],
    "name:swe_x_preferred":[
        "Sanquhar"
    ],
    "qs:a0":"United Kingdom",
    "qs:a1":"*Dumfries and Galloway",
    "qs:a1_lc":"GB11QH0000",
    "qs:a1r":"0Scotland",
    "qs:a1r_lc":"GB11000000",
    "qs:adm0":"United Kingdom",
    "qs:la_lc":"*",
    "qs:level":"locality",
    "qs:loc":"Sanquhar",
    "qs:loc_alt":"Sanquhar",
    "qs:pop":0,
    "qs:type":"buffered point",
    "wd:wordcount":2937,
    "wof:lang":[
        "eng"
    ],
    "wof:name":"Sanquhar",
    "wof:placetype":"locality",
    "wof:population":1987
},
  "geometry": {"coordinates":[-3.921964,55.367895],"type":"Point"}
}