{
  "type": "Feature",
  "properties": {
    "gn:country":"GB",
    "gn:fcode":"PPL",
    "gn:population":0,
    "iso:country":"GB",
    "name:ast_x_preferred":[
        "Norton-on-Derwent"
    ],
    "name:azb_x_preferred":[
        "\u0646\u0648\u0631\u062a\u0648\u0646-\u0622\u0646-\u062f\u0631\u0648\u0646\u062a"
    ],
    "name:ceb_x_preferred":[
        "Norton-on-Derwent"
    ],
    "name:cym_x_preferred":[
        "Norton-on-Derwent"
    ],
    "name:eng_x_preferred":[
        "Norton-on-Derwent"
    ],
    "name:fas_x_preferred":[
        "\u0646\u0648\u0631\u062a\u0648\u0646-\u0622\u0646-\u062f\u0631\u0648\u0646\u062a"
    ],
    "name:fra_x_preferred":[
        "Norton-on-Derwent"
    ],
    "name:gle_x_preferred":[
        "Norton-on-Derwent"
    ],
    "name:ita_x_preferred":[
        "Norton-on-Derwent"
    ],
    "name:lld_x_preferred":[
        "Norton-on-Derwent"
    ],
    "name:nld_x_preferred":[
        "Norton-on-Derwent"
    ],
    "name:nno_x_preferred":[
        "Norton-on-Derwent"
    ],
    "name:pol_x_preferred":[
        "Norton-on-Derwent"
    ],
    "name:spa_x_preferred":[
        "Norton-on-Derwent"
    ],
    "name:swe_x_preferred":[
        "Norton-on-Derwent"
    ],
    "name:tur_x_preferred":[
        "Norton-on-Derwent"
    ],
    "qs_pg:aaroncc":"GB",
    "qs_pg:gn_country":"GB",
    "qs_pg:gn_fcode":"PPL",
    "qs_pg:gn_pop":0,
    "qs_pg:name":"Norton",
    "qs_pg:name_adm0":"United Kingdom",
    "qs_pg:name_adm1":"England",
    "qs_pg:photos":56,
    "qs_pg:photos_1k":11,
    "qs_pg:photos_9k":1,
    "qs_pg:photos_9r":2,
    "qs_pg:photos_all":56,
    "qs_pg:photos_sr":2,
    "qs_pg:pop_sr":0,
    "qs_pg:qs_pg_placetype":"locality",
    "qs_pg:qs_pg_placetype_gp":"Town",
    "qs_pg:woe_adm0":23424975,
    "woe:adm0_id":23424975,
    "woe:name_adm0":"United Kingdom",
    "woe:name_adm1":"England",
    "woe:placetype":"Town",
    "wof:name":"Norton",
    "wof:placetype":"neighbourhood",
    "wof:population":7000
},
  "geometry": {"coordinates":[-0.7802,54.11889],"type":"Point"}
}