{
  "type": "Feature",
  "properties": {
    "iso:country":"GB",
    "name:eng_x_preferred":[
        "Catherine-de-Barnes"
    ],
    "name:fra_x_preferred":[
        "Catherine-de-Barnes"
    ],
    "name:gle_x_preferred":[
        "Catherine-de-Barnes"
    ],
    "name:nld_x_preferred":[
        "Catherine-de-Barnes"
    ],
    "name:pol_x_preferred":[
        "Catherine-de-Barnes"
    ],
    "name:spa_x_preferred":[
        "Catherine-de-Barnes"
    ],
    "name:swe_x_preferred":[
        "Catherine-de-Barnes"
    ],
    "qs_pg:aaroncc":"GB",
    "qs_pg:name":"Catherine-de-Barnes",
    "qs_pg:name_adm0":"United Kingdom",
    "qs_pg:name_adm1":"England",
    "qs_pg:photos":22,
    "qs_pg:photos_1k":4,
    "qs_pg:photos_9k":1,
    "qs_pg:photos_9r":1,
    "qs_pg:photos_all":22,
    "qs_pg:photos_sr":1,
    "qs_pg:pop_sr":0,
    "qs_pg:qs_pg_placetype":"locality",
    "qs_pg:qs_pg_placetype_gp":"Town",
    "qs_pg:woe_adm0":23424975,
    "woe:adm0_id":23424975,
    "woe:name_adm0":"United Kingdom",
    "woe:name_adm1":"England",
    "woe:placetype":"Town",
    "wof:name":"Catherine-de-Barnes",
    "wof:placetype":"neighbourhood"
},
  "geometry": {"coordinates":[-1.736354,52.421554],"type":"Point"}
}