{
  "type": "Feature",
  "properties": {
    "iso:country":"GB",
    "name:eng_x_preferred":[
        "Clyne Valley"
    ],
    "qs:gn_local":0,
    "qs:local_max":696,
    "qs:local_sum":696,
    "qs:localhoods":1,
    "qs:name":"Clyne Valley",
    "qs:name_adm0":"United Kingdom",
    "qs:name_adm1":"Wales",
    "qs:name_adm2":"Swansea City and County",
    "qs:name_lau":"Swansea City and County",
    "qs:name_local":"Sketty",
    "qs:photo_max":83,
    "qs:photo_sum":696,
    "qs:placetype":"Suburb",
    "qs:quad_count":47,
    "qs:woe_adm0":23424975,
    "qs:woe_adm1":12578049,
    "qs:woe_adm2":12602229,
    "qs:woe_lau":12696131,
    "qs:woe_local":34916,
    "qs:woe_ver":"7.10.0",
    "wof:lang":[
        "eng"
    ],
    "wof:name":"Clyne Valley",
    "wof:placetype":"neighbourhood"
},
  "geometry": {"coordinates":[-3.993494,51.606795],"type":"Point"}
}