{
  "type": "Feature",
  "properties": {
    "gn:country":"GB",
    "iso:country":"GB",
    "name:eng_x_preferred":[
        "Bimbister"
    ],
    "name:eus_x_preferred":[
        "Bimbister"
    ],
    "name:fra_x_preferred":[
        "Bimbister"
    ],
    "name:nld_x_preferred":[
        "Bimbister"
    ],
    "qs_pg:aaroncc":"GB",
    "qs_pg:gn_country":"GB",
    "qs_pg:name":"Bimbister",
    "qs_pg:name_adm0":"United Kingdom",
    "qs_pg:name_adm1":"Scotland",
    "qs_pg:photos":698,
    "qs_pg:photos_1k":141,
    "qs_pg:photos_9k":3,
    "qs_pg:photos_9r":5,
    "qs_pg:photos_all":698,
    "qs_pg:photos_sr":8,
    "qs_pg:pop_sr":0,
    "qs_pg:qs_pg_placetype":"locality",
    "qs_pg:qs_pg_placetype_gp":"Town",
    "qs_pg:woe_adm0":23424975,
    "woe:adm0_id":23424975,
    "woe:name_adm0":"United Kingdom",
    "woe:name_adm1":"Scotland",
    "woe:placetype":"Town",
    "wof:name":"Bimbister",
    "wof:placetype":"locality"
},
  "geometry": {"coordinates":[-3.227577,59.001127],"type":"Point"}
}