{
  "type": "Feature",
  "properties": {
    "iso:country":"GB",
    "name:cym_x_preferred":[
        "Flowery Field"
    ],
    "name:deu_x_preferred":[
        "Flowery Field"
    ],
    "name:eng_x_preferred":[
        "Flowery Field"
    ],
    "name:fra_x_preferred":[
        "Flowery Field"
    ],
    "name:gle_x_preferred":[
        "Ancoats"
    ],
    "name:nld_x_preferred":[
        "Flowery Field"
    ],
    "name:pol_x_preferred":[
        "Flowery Field"
    ],
    "name:unk_x_variant":[
        "Flowery Field"
    ],
    "qs:gn_adm0_cc":"GB",
    "qs:gn_local":2646327,
    "qs:gn_nam_loc":"hyde",
    "qs:gn_namadm1":"ENG",
    "qs:local_max":1183,
    "qs:local_sum":1303,
    "qs:localhoods":2,
    "qs:name":"Flowery Field",
    "qs:name_adm0":"United Kingdom",
    "qs:name_adm1":"England",
    "qs:name_adm2":"Greater Manchester",
    "qs:name_lau":"Tameside Metropolitan Borough",
    "qs:name_local":"Hyde",
    "qs:photo_max":73,
    "qs:photo_sum":120,
    "qs:placetype":"Suburb",
    "qs:quad_count":13,
    "qs:woe_adm0":23424975,
    "qs:woe_adm1":24554868,
    "qs:woe_adm2":12602158,
    "qs:woe_lau":12695846,
    "qs:woe_local":24257,
    "qs:woe_ver":"7.10.0",
    "wd:wordcount":585,
    "wof:lang":[
        "eng"
    ],
    "wof:name":"Flowery Field",
    "wof:placetype":"neighbourhood"
},
  "geometry": {"coordinates":[-2.145035,53.38414],"type":"Point"}
}