{
  "type": "Feature",
  "properties": {
    "gn:country": "GB",
    "gn:fcode": "PPL",
    "gn:population": 0,
    "iso:country": "GB",
    "name:bul_x_preferred": [
      "Рослеа"
    ],
    "name:ceb_x_preferred": [
      "Rosslea"
    ],
    "name:deu_x_preferred": [
      "Rosslea"
    ],
    "name:eng_x_preferred": [
      "Rosslea"
    ],
    "name:eus_x_preferred": [
      "Rosslea"
    ],
    "name:fas_x_preferred": [
      "راسلی"
    ],
    "name:fra_x_preferred": [
      "Rosslea"
    ],
    "name:gle_x_preferred": [
      "Ros Liath"
    ],
    "name:ita_x_preferred": [
      "Rosslea"
    ],
    "name:msa_x_preferred": [
      "Rosslea"
    ],
    "name:nld_x_preferred": [
      "Rosslea"
    ],
    "name:pli_x_preferred": [
      "रोस्स्ला"
    ],
    "name:spa_x_preferred": [
      "Rosslea"
    ],
    "name:swe_x_preferred": [
      "Rosslea"
    ],
    "name:und_x_variant": [
      "Roslea"
    ],
    "qs_pg:aaroncc": "GB",
    "qs_pg:gn_country": "GB",
    "qs_pg:gn_fcode": "PPL",
    "qs_pg:gn_pop": 0,
    "qs_pg:name": "Rosslea",
    "qs_pg:name_adm0": "United Kingdom",
    "qs_pg:name_adm1": "Northern Ireland",
    "qs_pg:photos": 60,
    "qs_pg:photos_1k": 12,
    "qs_pg:photos_9k": 1,
    "qs_pg:photos_9r": 2,
    "qs_pg:photos_all": 60,
    "qs_pg:photos_sr": 2,
    "qs_pg:pop_sr": 0,
    "qs_pg:qs_pg_placetype": "locality",
    "qs_pg:qs_pg_placetype_gp": "Town",
    "qs_pg:woe_adm0": 23424975,
    "woe:adm0_id": 23424975,
    "woe:name_adm0": "United Kingdom",
    "woe:name_adm1": "Northern Ireland",
    "woe:placetype": "Town",
    "wof:name": "Rosslea",
    "wof:placetype": "locality"
  },
  "geometry": {"coordinates":[-7.18333,54.23333],"type":"Point"}
}
