{
  "type": "Feature",
  "properties": {
    "iso:country": "GB",
    "name:ara_x_preferred": [
      "بورول"
    ],
    "name:ben_x_preferred": [
      "বুরওয়েল"
    ],
    "name:ceb_x_preferred": [
      "Burwell"
    ],
    "name:cym_x_preferred": [
      "Burwell"
    ],
    "name:deu_x_preferred": [
      "Burwell"
    ],
    "name:eng_x_preferred": [
      "Burwell"
    ],
    "name:fas_x_preferred": [
      "برول"
    ],
    "name:fra_x_preferred": [
      "Burwell"
    ],
    "name:gle_x_preferred": [
      "Burwell"
    ],
    "name:guj_x_preferred": [
      "બરવેલ"
    ],
    "name:ita_x_preferred": [
      "Burwell"
    ],
    "name:jpn_x_preferred": [
      "バーウェル"
    ],
    "name:jpn_x_variant": [
      "バーウェル"
    ],
    "name:kan_x_preferred": [
      "ಬರ್ವೆಲ್"
    ],
    "name:kor_x_preferred": [
      "버웰"
    ],
    "name:lit_x_preferred": [
      "Burvelis"
    ],
    "name:nld_x_preferred": [
      "Burwell"
    ],
    "name:pol_x_preferred": [
      "Burwell"
    ],
    "name:por_x_preferred": [
      "Burwell"
    ],
    "name:rus_x_preferred": [
      "Барвел"
    ],
    "name:spa_x_preferred": [
      "Burwell"
    ],
    "name:swe_x_preferred": [
      "Burwell"
    ],
    "name:tam_x_preferred": [
      "பரவெல்"
    ],
    "name:tel_x_preferred": [
      "బర్వేల్"
    ],
    "name:urd_x_preferred": [
      "برویل"
    ],
    "name:vol_x_preferred": [
      "Burwell"
    ],
    "qs:a0": "United Kingdom",
    "qs:a1": "*Cambridgeshire",
    "qs:a1_lc": "GB12120000",
    "qs:a1r": "0England",
    "qs:a1r_lc": "GB12000000",
    "qs:adm0": "United Kingdom",
    "qs:la_lc": "*",
    "qs:level": "locality",
    "qs:loc": "Burwell",
    "qs:loc_alt": "Burwell",
    "qs:pop": 0,
    "qs:type": "buffered point",
    "wof:name": "Burwell",
    "wof:placetype": "neighbourhood"
  },
  "geometry": {"coordinates":[0.325659,52.273772],"type":"Point"}
}
