{
  "type": "Feature",
  "properties": {
    "iso:country":"GB",
    "name:ara_x_preferred":[
        "\u0628\u0648\u0631\u0648\u0644"
    ],
    "name:ben_x_preferred":[
        "\u09ac\u09c1\u09b0\u0993\u09af\u09bc\u09c7\u09b2"
    ],
    "name:ceb_x_preferred":[
        "Burwell"
    ],
    "name:cym_x_preferred":[
        "Burwell"
    ],
    "name:deu_x_preferred":[
        "Burwell"
    ],
    "name:eng_x_preferred":[
        "Burwell"
    ],
    "name:fas_x_preferred":[
        "\u0628\u0631\u0648\u0644"
    ],
    "name:fra_x_preferred":[
        "Burwell"
    ],
    "name:gle_x_preferred":[
        "Burwell"
    ],
    "name:guj_x_preferred":[
        "\u0aac\u0ab0\u0ab5\u0ac7\u0ab2"
    ],
    "name:ita_x_preferred":[
        "Burwell"
    ],
    "name:jpn_x_preferred":[
        "\u30d0\u30fc\u30a6\u30a7\u30eb"
    ],
    "name:jpn_x_variant":[
        "\u30d0\u30fc\u30a6\u30a7\u30eb"
    ],
    "name:kan_x_preferred":[
        "\u0cac\u0cb0\u0ccd\u0cb5\u0cc6\u0cb2\u0ccd"
    ],
    "name:kor_x_preferred":[
        "\ubc84\uc6f0"
    ],
    "name:lit_x_preferred":[
        "Burvelis"
    ],
    "name:nld_x_preferred":[
        "Burwell"
    ],
    "name:pol_x_preferred":[
        "Burwell"
    ],
    "name:por_x_preferred":[
        "Burwell"
    ],
    "name:rus_x_preferred":[
        "\u0411\u0430\u0440\u0432\u0435\u043b"
    ],
    "name:spa_x_preferred":[
        "Burwell"
    ],
    "name:swe_x_preferred":[
        "Burwell"
    ],
    "name:tam_x_preferred":[
        "\u0baa\u0bb0\u0bb5\u0bc6\u0bb2\u0bcd"
    ],
    "name:tel_x_preferred":[
        "\u0c2c\u0c30\u0c4d\u0c35\u0c47\u0c32\u0c4d"
    ],
    "name:urd_x_preferred":[
        "\u0628\u0631\u0648\u06cc\u0644"
    ],
    "name:vol_x_preferred":[
        "Burwell"
    ],
    "qs:a0":"United Kingdom",
    "qs:a1":"*Cambridgeshire",
    "qs:a1_lc":"GB12120000",
    "qs:a1r":"0England",
    "qs:a1r_lc":"GB12000000",
    "qs:adm0":"United Kingdom",
    "qs:la_lc":"*",
    "qs:level":"locality",
    "qs:loc":"Burwell",
    "qs:loc_alt":"Burwell",
    "qs:pop":0,
    "qs:type":"buffered point",
    "wof:name":"Burwell",
    "wof:placetype":"neighbourhood"
},
  "geometry": {"coordinates":[0.325659,52.273772],"type":"Point"}
}