{
  "type": "Feature",
  "properties": {
    "iso:country":"GB",
    "name:eng_x_preferred":[
        "Coventry Walsgrave Triangle"
    ],
    "name:unk_x_variant":[
        "Coventry Walsgrave Triangle"
    ],
    "qs:gn_adm0_cc":"GB",
    "qs:gn_local":2652221,
    "qs:local_max":5581,
    "qs:local_sum":33638,
    "qs:localhoods":22,
    "qs:name":"Coventry Walsgrave Triangle",
    "qs:name_adm0":"United Kingdom",
    "qs:name_adm1":"England",
    "qs:name_adm2":"West Midlands",
    "qs:name_lau":"Coventry City",
    "qs:name_local":"Coventry",
    "qs:photo_max":403,
    "qs:photo_sum":1123,
    "qs:placetype":"Suburb",
    "qs:quad_count":80,
    "qs:woe_adm0":23424975,
    "qs:woe_adm1":24554868,
    "qs:woe_adm2":12602191,
    "qs:woe_lau":12695864,
    "qs:woe_local":17044,
    "qs:woe_ver":"7.10.0",
    "wof:lang":[
        "eng"
    ],
    "wof:name":"Coventry Walsgrave Triangle",
    "wof:placetype":"neighbourhood"
},
  "geometry": {"coordinates":[-1.43609,52.436328],"type":"Point"}
}