{
  "type": "Feature",
  "properties": {
    "gn:admin1_code":"ENG",
    "gn:admin2_code":"C9",
    "gn:admin3_code":"16UB",
    "gn:admin4_code":"16UB025",
    "gn:asciiname":"Ullock",
    "gn:country_code":"GB",
    "gn:dem":118,
    "gn:feature_class":"P",
    "gn:feature_code":"PPL",
    "gn:name":"Ullock",
    "gn:population":0,
    "gn:timezone":"Europe/London",
    "iso:country":"GB",
    "name:cym_x_preferred":[
        "Ullock"
    ],
    "name:pol_x_preferred":[
        "Ullock"
    ],
    "wof:name":"Ullock",
    "wof:placetype":"neighbourhood"
},
  "geometry": {"coordinates":[-3.43048,54.59882],"type":"Point"}
}