{
  "type": "Feature",
  "properties": {
    "gn:admin1_code":"ENG",
    "gn:admin2_code":"M6",
    "gn:admin3_code":"00HD018",
    "gn:asciiname":"Petty France",
    "gn:country_code":"GB",
    "gn:dem":157,
    "gn:feature_class":"P",
    "gn:feature_code":"PPL",
    "gn:name":"Petty France",
    "gn:population":0,
    "gn:timezone":"Europe/London",
    "iso:country":"GB",
    "name:pol_x_preferred":[
        "Petty France"
    ],
    "wof:name":"Petty France",
    "wof:placetype":"neighbourhood"
},
  "geometry": {"coordinates":[-2.30945,51.5668],"type":"Point"}
}