{
  "type": "Feature",
  "properties": {
    "gn:country":"GB",
    "gn:fcode":"PPL",
    "gn:population":0,
    "iso:country":"GB",
    "name:bre_x_preferred":[
        "Stepaside"
    ],
    "name:cym_x_preferred":[
        "Stepaside"
    ],
    "name:eng_x_preferred":[
        "Stepaside"
    ],
    "name:fra_x_preferred":[
        "Stepaside"
    ],
    "name:nld_x_preferred":[
        "Stepaside"
    ],
    "name:spa_x_preferred":[
        "Stepaside"
    ],
    "name:swe_x_preferred":[
        "Stepaside"
    ],
    "qs_pg:aaroncc":"GB",
    "qs_pg:gn_country":"GB",
    "qs_pg:gn_fcode":"PPL",
    "qs_pg:gn_pop":0,
    "qs_pg:name":"Stepaside",
    "qs_pg:name_adm0":"United Kingdom",
    "qs_pg:name_adm1":"Wales",
    "qs_pg:photos":163,
    "qs_pg:photos_1k":33,
    "qs_pg:photos_9k":1,
    "qs_pg:photos_9r":4,
    "qs_pg:photos_all":163,
    "qs_pg:photos_sr":4,
    "qs_pg:pop_sr":0,
    "qs_pg:qs_pg_placetype":"locality",
    "qs_pg:qs_pg_placetype_gp":"Town",
    "qs_pg:woe_adm0":23424975,
    "woe:adm0_id":23424975,
    "woe:name_adm0":"United Kingdom",
    "woe:name_adm1":"Wales",
    "woe:placetype":"Town",
    "wof:name":"Stepaside",
    "wof:placetype":"neighbourhood",
    "wof:population":619
},
  "geometry": {"coordinates":[-4.70639,51.73028],"type":"Point"}
}