{
  "type": "Feature",
  "properties": {
    "gn:country":"GB",
    "gn:fcode":"PPL",
    "gn:population":0,
    "iso:country":"GB",
    "name:ara_x_preferred":[
        "\u0641\u0631\u0646\u062f\u064a\u0634"
    ],
    "name:arz_x_preferred":[
        "\u0641\u0631\u0646\u062f\u064a\u0634"
    ],
    "name:cym_x_preferred":[
        "Farndish"
    ],
    "name:eng_x_preferred":[
        "Farndish"
    ],
    "name:fas_x_preferred":[
        "\u0641\u0627\u0631\u0646\u062f\u06cc\u0634"
    ],
    "name:fra_x_preferred":[
        "Farndish"
    ],
    "name:gle_x_preferred":[
        "Farndish"
    ],
    "name:lld_x_preferred":[
        "Farndish"
    ],
    "name:nld_x_preferred":[
        "Farndish"
    ],
    "name:pol_x_preferred":[
        "Farndish"
    ],
    "name:swe_x_preferred":[
        "Farndish"
    ],
    "name:tur_x_preferred":[
        "Farndish"
    ],
    "qs_pg:aaroncc":"GB",
    "qs_pg:gn_country":"GB",
    "qs_pg:gn_fcode":"PPL",
    "qs_pg:gn_pop":0,
    "qs_pg:name":"Farndish",
    "qs_pg:name_adm0":"United Kingdom",
    "qs_pg:name_adm1":"England",
    "qs_pg:photos":242,
    "qs_pg:photos_1k":49,
    "qs_pg:photos_9k":1,
    "qs_pg:photos_9r":4,
    "qs_pg:photos_all":242,
    "qs_pg:photos_sr":4,
    "qs_pg:pop_sr":0,
    "qs_pg:qs_pg_placetype":"locality",
    "qs_pg:qs_pg_placetype_gp":"Town",
    "qs_pg:woe_adm0":23424975,
    "woe:adm0_id":23424975,
    "woe:name_adm0":"United Kingdom",
    "woe:name_adm1":"England",
    "woe:placetype":"Town",
    "wof:name":"Farndish",
    "wof:placetype":"neighbourhood"
},
  "geometry": {"coordinates":[-0.64253,52.26359],"type":"Point"}
}