{
  "type": "Feature",
  "properties": {
    "iso:country":"GB",
    "wof:name":"Haigh Fold",
    "wof:placetype":"neighbourhood"
},
  "geometry": {"coordinates":[-1.72195655485428,53.81364806838651],"type":"Point"}
}