{
  "type": "Feature",
  "properties": {
    "iso:country":"GB",
    "wof:name":"Batemoor",
    "wof:placetype":"neighbourhood"
},
  "geometry": {"coordinates":[-1.46834489073064,53.31996382299848],"type":"Point"}
}