{
  "type": "Feature",
  "properties": {
    "iso:country":"GB",
    "name:eng_x_preferred":[
        "Beck Row"
    ],
    "name:fra_x_preferred":[
        "Beck Row"
    ],
    "name:gle_x_preferred":[
        "Beck Row"
    ],
    "name:nld_x_preferred":[
        "Beck Row"
    ],
    "name:pol_x_preferred":[
        "Beck Row"
    ],
    "name:swe_x_preferred":[
        "Beck Row"
    ],
    "qs_pg:aaroncc":"GB",
    "qs_pg:name":"Beck Row",
    "qs_pg:name_adm0":"United Kingdom",
    "qs_pg:name_adm1":"England",
    "qs_pg:photos":687,
    "qs_pg:photos_1k":139,
    "qs_pg:photos_9k":3,
    "qs_pg:photos_9r":5,
    "qs_pg:photos_all":687,
    "qs_pg:photos_sr":8,
    "qs_pg:pop_sr":0,
    "qs_pg:qs_pg_placetype":"locality",
    "qs_pg:qs_pg_placetype_gp":"Town",
    "qs_pg:woe_adm0":23424975,
    "woe:adm0_id":23424975,
    "woe:name_adm0":"United Kingdom",
    "woe:name_adm1":"England",
    "woe:placetype":"Town",
    "wof:name":"Beck Row",
    "wof:placetype":"neighbourhood"
},
  "geometry": {"coordinates":[0.473999,52.370359],"type":"Point"}
}