{
  "type": "Feature",
  "properties": {
    "gn:country":"GB",
    "gn:fcode":"PPL",
    "gn:population":0,
    "iso:country":"GB",
    "name:ara_x_preferred":[
        "\u0645\u0644\u062a\u0634\u0628\u0648\u0631\u0646"
    ],
    "name:arz_x_preferred":[
        "\u0645\u0644\u062a\u0634\u0628\u0648\u0631\u0646"
    ],
    "name:cym_x_preferred":[
        "Melchbourne"
    ],
    "name:eng_x_preferred":[
        "Melchbourne"
    ],
    "name:fas_x_preferred":[
        "\u0645\u0644\u0686\u0628\u0648\u0631\u0646"
    ],
    "name:fra_x_preferred":[
        "Melchbourne"
    ],
    "name:gle_x_preferred":[
        "Melchbourne"
    ],
    "name:jpn_x_preferred":[
        "\u30e1\u30eb\u30c1\u30dc\u30fc\u30f3"
    ],
    "name:nld_x_preferred":[
        "Melchbourne"
    ],
    "name:pol_x_preferred":[
        "Melchbourne"
    ],
    "name:swe_x_preferred":[
        "Melchbourne"
    ],
    "qs_pg:aaroncc":"GB",
    "qs_pg:gn_country":"GB",
    "qs_pg:gn_fcode":"PPL",
    "qs_pg:gn_pop":0,
    "qs_pg:name":"Melchbourne",
    "qs_pg:name_adm0":"United Kingdom",
    "qs_pg:name_adm1":"England",
    "qs_pg:photos_9r":0,
    "qs_pg:photos_sr":0,
    "qs_pg:pop_sr":0,
    "qs_pg:qs_pg_placetype":"locality",
    "qs_pg:qs_pg_placetype_gp":"Town",
    "qs_pg:woe_adm0":23424975,
    "woe:adm0_id":23424975,
    "woe:name_adm0":"United Kingdom",
    "woe:name_adm1":"England",
    "woe:placetype":"Town",
    "wof:name":"Melchbourne",
    "wof:placetype":"neighbourhood"
},
  "geometry": {"coordinates":[-0.49327,52.28018],"type":"Point"}
}