{
  "type": "Feature",
  "properties": {
    "gn:admin1_code":"ENG",
    "gn:admin2_code":"I9",
    "gn:admin3_code":"33UB",
    "gn:admin4_code":"33UB059",
    "gn:asciiname":"West Tofts",
    "gn:country_code":"GB",
    "gn:dem":28,
    "gn:feature_class":"P",
    "gn:feature_code":"PPL",
    "gn:name":"West Tofts",
    "gn:population":0,
    "gn:timezone":"Europe/London",
    "iso:country":"GB",
    "wof:name":"West Tofts",
    "wof:placetype":"neighbourhood"
},
  "geometry": {"coordinates":[0.70531,52.5011],"type":"Point"}
}