{
  "type": "Feature",
  "properties": {
    "gn:country":"GB",
    "gn:fcode":"PPL",
    "gn:population":1274,
    "iso:country":"GB",
    "name:bul_x_preferred":[
        "\u041a\u0438\u043d\u0433\u043b\u0430\u0441\u0438\u0435"
    ],
    "name:ceb_x_preferred":[
        "Kinglassie"
    ],
    "name:cym_x_preferred":[
        "Kinglassie"
    ],
    "name:eng_x_preferred":[
        "Kinglassie"
    ],
    "name:eus_x_preferred":[
        "Kinglassie"
    ],
    "name:fra_x_preferred":[
        "Kinglassie"
    ],
    "name:gle_x_preferred":[
        "Cille MoGhlasaidh"
    ],
    "name:ita_x_preferred":[
        "Kinglassie"
    ],
    "name:nld_x_preferred":[
        "Kinglassie"
    ],
    "name:nno_x_preferred":[
        "Kinglassie"
    ],
    "name:nob_x_preferred":[
        "Kinglassie"
    ],
    "name:pol_x_preferred":[
        "Kinglassie"
    ],
    "name:spa_x_preferred":[
        "Kinglassie"
    ],
    "name:swe_x_preferred":[
        "Kinglassie"
    ],
    "qs_pg:aaroncc":"GB",
    "qs_pg:gn_country":"GB",
    "qs_pg:gn_fcode":"PPL",
    "qs_pg:gn_pop":1274,
    "qs_pg:name":"Kinglassie",
    "qs_pg:name_adm0":"United Kingdom",
    "qs_pg:name_adm1":"Scotland",
    "qs_pg:photos":279,
    "qs_pg:photos_1k":57,
    "qs_pg:photos_9k":1,
    "qs_pg:photos_9r":4,
    "qs_pg:photos_all":279,
    "qs_pg:photos_sr":5,
    "qs_pg:pop_sr":3,
    "qs_pg:qs_pg_placetype":"locality",
    "qs_pg:qs_pg_placetype_gp":"Town",
    "qs_pg:woe_adm0":23424975,
    "woe:adm0_id":23424975,
    "woe:name_adm0":"United Kingdom",
    "woe:name_adm1":"Scotland",
    "woe:placetype":"Town",
    "wof:name":"Kinglassie",
    "wof:placetype":"locality",
    "wof:population":1820
},
  "geometry": {"coordinates":[-3.24241,56.17371],"type":"Point"}
}