{
  "type": "Feature",
  "properties": {
    "gn:admin1_code":"SCT",
    "gn:admin2_code":"T5",
    "gn:asciiname":"Walton",
    "gn:country_code":"GB",
    "gn:dem":93,
    "gn:feature_class":"P",
    "gn:feature_code":"PPL",
    "gn:name":"Walton",
    "gn:population":0,
    "gn:timezone":"Europe/London",
    "iso:country":"GB",
    "wof:name":"Walton",
    "wof:placetype":"locality"
},
  "geometry": {"coordinates":[-2.2131,57.19269],"type":"Point"}
}