{
  "type": "Feature",
  "properties": {
    "gn:admin1_code":"SCT",
    "gn:admin2_code":"T5",
    "gn:asciiname":"Walton",
    "gn:country_code":"GB",
    "gn:dem":93,
    "gn:feature_class":"P",
    "gn:feature_code":"PPL",
    "gn:name":"Walton",
    "gn:population":0,
    "gn:timezone":"Europe/London",
    "iso:country":"GB",
    "name:cat_x_preferred":[
        "Walton"
    ],
    "name:ceb_x_preferred":[
        "Walton"
    ],
    "name:ces_x_preferred":[
        "Walton"
    ],
    "name:cym_x_preferred":[
        "Walton"
    ],
    "name:deu_x_preferred":[
        "Walton"
    ],
    "name:fra_x_preferred":[
        "Walton"
    ],
    "name:heb_x_preferred":[
        "\u05d5\u05d5\u05dc\u05d8\u05d5\u05df"
    ],
    "name:ita_x_preferred":[
        "Walton"
    ],
    "name:jpn_x_preferred":[
        "\u30a6\u30a9\u30eb\u30c8\u30f3"
    ],
    "name:lav_x_preferred":[
        "Voltons"
    ],
    "name:lit_x_preferred":[
        "Walton"
    ],
    "name:nld_x_preferred":[
        "Walton"
    ],
    "name:pol_x_preferred":[
        "Walton"
    ],
    "name:por_x_preferred":[
        "Walton"
    ],
    "name:rus_x_preferred":[
        "\u0423\u043e\u043b\u0442\u043e\u043d"
    ],
    "name:slv_x_preferred":[
        "Walton"
    ],
    "name:srp_x_preferred":[
        "\u0412\u043e\u043b\u0442\u043e\u043d"
    ],
    "name:swe_x_preferred":[
        "Walton"
    ],
    "name:ukr_x_preferred":[
        "\u0412\u043e\u043b\u0442\u043e\u043d"
    ],
    "name:urd_x_preferred":[
        "\u0648\u0627\u0644\u0679\u0646"
    ],
    "name:vol_x_preferred":[
        "Walton"
    ],
    "wof:name":"Walton",
    "wof:placetype":"locality"
},
  "geometry": {"coordinates":[-2.2131,57.19269],"type":"Point"}
}