{
  "type": "Feature",
  "properties": {
    "gn:country": "GB",
    "iso:country": "GB",
    "name:pol_x_preferred": [
      "Freshfield"
    ],
    "qs_pg:aaroncc": "GB",
    "qs_pg:gn_country": "GB",
    "qs_pg:name": "Freshfield",
    "qs_pg:name_adm0": "United Kingdom",
    "qs_pg:name_adm1": "England",
    "qs_pg:photos": 361,
    "qs_pg:photos_1k": 73,
    "qs_pg:photos_9k": 2,
    "qs_pg:photos_9r": 5,
    "qs_pg:photos_all": 361,
    "qs_pg:photos_sr": 6,
    "qs_pg:pop_sr": 0,
    "qs_pg:qs_pg_placetype": "locality",
    "qs_pg:qs_pg_placetype_gp": "Town",
    "qs_pg:woe_adm0": 23424975,
    "woe:adm0_id": 23424975,
    "woe:name_adm0": "United Kingdom",
    "woe:name_adm1": "England",
    "woe:placetype": "Town",
    "wof:name": "Freshfield",
    "wof:placetype": "neighbourhood"
  },
  "geometry": {"coordinates":[-3.10647,53.563291],"type":"Point"}
}
