{
  "type": "Feature",
  "properties": {
    "gn:admin1_code":"ENG",
    "gn:admin2_code":"J6",
    "gn:admin3_code":"00EM017",
    "gn:asciiname":"Newlands",
    "gn:country_code":"GB",
    "gn:dem":63,
    "gn:feature_class":"P",
    "gn:feature_code":"PPL",
    "gn:name":"Newlands",
    "gn:population":0,
    "gn:timezone":"Europe/London",
    "iso:country":"GB",
    "name:bar_x_preferred":[
        "Newlands"
    ],
    "name:ceb_x_preferred":[
        "Newlands"
    ],
    "name:deu_x_preferred":[
        "Newlands"
    ],
    "name:fra_x_preferred":[
        "Newlands"
    ],
    "name:pol_x_preferred":[
        "Newlands"
    ],
    "name:rus_x_preferred":[
        "\u041d\u044c\u044e\u043b\u0435\u043d\u0434\u0441"
    ],
    "name:ukr_x_preferred":[
        "\u041d\u044c\u044e\u043b\u0435\u043d\u0434\u0441"
    ],
    "wof:name":"Newlands",
    "wof:placetype":"neighbourhood"
},
  "geometry": {"coordinates":[-1.81667,55.58333],"type":"Point"}
}