{
  "type": "Feature",
  "properties": {
    "iso:country":"GB",
    "name:eng_x_preferred":[
        "Ardchullarie More"
    ],
    "name:eus_x_preferred":[
        "Ardchullarie More"
    ],
    "name:fra_x_preferred":[
        "Ardchullarie More"
    ],
    "name:mya_x_preferred":[
        "\u1021\u102c\u1001\u103b\u1030\u101c\u102c\u101b\u102e \u1019\u1031\u102c"
    ],
    "name:nld_x_preferred":[
        "Ardchullarie More"
    ],
    "qs_pg:aaroncc":"GB",
    "qs_pg:name":"Ardchullarie More",
    "qs_pg:name_adm0":"United Kingdom",
    "qs_pg:name_adm1":"Scotland",
    "qs_pg:photos":356,
    "qs_pg:photos_1k":72,
    "qs_pg:photos_9k":2,
    "qs_pg:photos_9r":5,
    "qs_pg:photos_all":356,
    "qs_pg:photos_sr":6,
    "qs_pg:pop_sr":0,
    "qs_pg:qs_pg_placetype":"locality",
    "qs_pg:qs_pg_placetype_gp":"Town",
    "qs_pg:woe_adm0":23424975,
    "woe:adm0_id":23424975,
    "woe:name_adm0":"United Kingdom",
    "woe:name_adm1":"Scotland",
    "woe:placetype":"Town",
    "wof:name":"Ardchullarie More",
    "wof:placetype":"locality"
},
  "geometry": {"coordinates":[-4.294281,56.295062],"type":"Point"}
}