{
  "type": "Feature",
  "properties": {
    "iso:country":"GB",
    "wof:name":"Paradise",
    "wof:placetype":"neighbourhood"
},
  "geometry": {"coordinates":[-1.66510242072959,54.96616675354478],"type":"Point"}
}