{
  "type": "Feature",
  "properties": {
    "iso:country": "GB",
    "name:ara_x_preferred": [
      "فردوس"
    ],
    "name:arg_x_preferred": [
      "Paradiso"
    ],
    "name:aze_x_preferred": [
      "Cənnət"
    ],
    "name:bak_x_preferred": [
      "Ожмах"
    ],
    "name:bel_x_preferred": [
      "Рай"
    ],
    "name:bos_x_preferred": [
      "Raj"
    ],
    "name:bre_x_preferred": [
      "Baradoz"
    ],
    "name:bul_x_preferred": [
      "Рай"
    ],
    "name:cat_x_preferred": [
      "Paradís"
    ],
    "name:ces_x_preferred": [
      "Ráj"
    ],
    "name:ckb_x_preferred": [
      "پاردێز"
    ],
    "name:cos_x_preferred": [
      "Paradisu"
    ],
    "name:dan_x_preferred": [
      "Paradis"
    ],
    "name:deu_x_preferred": [
      "Paradies"
    ],
    "name:ell_x_preferred": [
      "Παράδεισος"
    ],
    "name:epo_x_preferred": [
      "Paradizo"
    ],
    "name:eus_x_preferred": [
      "Paradisu"
    ],
    "name:fas_x_preferred": [
      "پردیس"
    ],
    "name:fin_x_preferred": [
      "Paratiisi"
    ],
    "name:fra_x_preferred": [
      "Paradis"
    ],
    "name:fry_x_preferred": [
      "Paradys"
    ],
    "name:fur_x_preferred": [
      "Paradîs"
    ],
    "name:gla_x_preferred": [
      "Pàrras"
    ],
    "name:hin_x_preferred": [
      "पैराडाइज"
    ],
    "name:hrv_x_preferred": [
      "Raj"
    ],
    "name:hye_x_preferred": [
      "Դրախտ"
    ],
    "name:ido_x_preferred": [
      "Paradizo"
    ],
    "name:ind_x_preferred": [
      "Firdaus"
    ],
    "name:ita_x_preferred": [
      "Paradiso"
    ],
    "name:jav_x_preferred": [
      "Swarga"
    ],
    "name:jpn_x_preferred": [
      "楽園"
    ],
    "name:kat_x_preferred": [
      "სამოთხე"
    ],
    "name:kaz_x_preferred": [
      "Жәннәт"
    ],
    "name:lav_x_preferred": [
      "Paradīze"
    ],
    "name:lit_x_preferred": [
      "Rojus"
    ],
    "name:mlg_x_preferred": [
      "Paradisa"
    ],
    "name:msa_x_preferred": [
      "Firdaus"
    ],
    "name:nau_x_preferred": [
      "Paradis"
    ],
    "name:nld_x_preferred": [
      "Paradijs"
    ],
    "name:nno_x_preferred": [
      "Paradis"
    ],
    "name:nor_x_preferred": [
      "Paradis"
    ],
    "name:nrm_x_preferred": [
      "Paradis"
    ],
    "name:oci_x_preferred": [
      "Paradís"
    ],
    "name:por_x_preferred": [
      "Paraíso"
    ],
    "name:ron_x_preferred": [
      "Rai"
    ],
    "name:rus_x_preferred": [
      "Рай"
    ],
    "name:slk_x_preferred": [
      "Raj"
    ],
    "name:slv_x_preferred": [
      "Raj"
    ],
    "name:som_x_preferred": [
      "Jano"
    ],
    "name:spa_x_preferred": [
      "Paraíso"
    ],
    "name:sqi_x_preferred": [
      "Parajsa"
    ],
    "name:srp_x_preferred": [
      "Рај"
    ],
    "name:swa_x_preferred": [
      "Paradiso"
    ],
    "name:swe_x_preferred": [
      "Paradis"
    ],
    "name:tat_x_preferred": [
      "Җәннәт"
    ],
    "name:tgl_x_preferred": [
      "Paraiso"
    ],
    "name:ukr_x_preferred": [
      "Рай"
    ],
    "name:urd_x_preferred": [
      "فردوس"
    ],
    "name:zho_x_preferred": [
      "樂園"
    ],
    "wof:name": "Paradise",
    "wof:placetype": "neighbourhood"
  },
  "geometry": {"coordinates":[-1.66510242072959,54.96616675354478],"type":"Point"}
}
