{
  "type": "Feature",
  "properties": {
    "gn:admin1_code": "WLS",
    "gn:admin2_code": "X7",
    "gn:admin3_code": "00NU010",
    "gn:asciiname": "Glandy Cross",
    "gn:country_code": "GB",
    "gn:dem": 196,
    "gn:feature_class": "P",
    "gn:feature_code": "PPL",
    "gn:name": "Glandy Cross",
    "gn:population": 0,
    "gn:timezone": "Europe/London",
    "iso:country": "GB",
    "wof:name": "Glandy Cross",
    "wof:placetype": "neighbourhood"
  },
  "geometry": {"coordinates":[-4.70028,51.90667],"type":"Point"}
}
