{
  "type": "Feature",
  "properties": {
    "iso:country":"GB",
    "name:eng_x_preferred":[
        "Chinatown"
    ],
    "name:nld_x_preferred":[
        "Chinatown"
    ],
    "qs:gn_adm0_cc":"GB",
    "qs:gn_local":2641673,
    "qs:gn_nam_loc":"Newcastle upon Tyne, England, GB",
    "qs:gn_namadm1":"ENG",
    "qs:local_max":5187,
    "qs:local_sum":44051,
    "qs:localhoods":35,
    "qs:name":"Chinatown",
    "qs:name_adm0":"United Kingdom",
    "qs:name_adm1":"England",
    "qs:name_adm2":"Tyne and Wear",
    "qs:name_lau":"Newcastle upon Tyne City",
    "qs:name_local":"Newcastle upon Tyne",
    "qs:photo_max":845,
    "qs:photo_sum":5187,
    "qs:placetype":"Suburb",
    "qs:quad_count":64,
    "qs:woe_adm0":23424975,
    "qs:woe_adm1":24554868,
    "qs:woe_adm2":12602156,
    "qs:woe_lau":12695859,
    "qs:woe_local":30079,
    "qs:woe_ver":"7.10.0",
    "wd:wordcount":8212,
    "wof:lang":[
        "eng"
    ],
    "wof:name":"Chinatown",
    "wof:placetype":"neighbourhood"
},
  "geometry": {"coordinates":[-1.620324,54.972487],"type":"Point"}
}