{
  "type": "Feature",
  "properties": {
    "gn:country":"GB",
    "gn:fcode":"PPL",
    "gn:population":0,
    "iso:country":"GB",
    "name:ast_x_preferred":[
        "Dawley"
    ],
    "name:azb_x_preferred":[
        "\u062f\u0627\u0648\u0644\u06cc"
    ],
    "name:ben_x_preferred":[
        "\u09a1\u09b2\u09bf\u09c7"
    ],
    "name:cym_x_preferred":[
        "Dawley"
    ],
    "name:deu_x_preferred":[
        "Dawley"
    ],
    "name:eng_x_preferred":[
        "Dawley"
    ],
    "name:fas_x_preferred":[
        "\u062f\u0627\u0648\u0644\u06cc"
    ],
    "name:fin_x_preferred":[
        "Dawley"
    ],
    "name:fra_x_preferred":[
        "Dawley"
    ],
    "name:gle_x_preferred":[
        "Dawley"
    ],
    "name:guj_x_preferred":[
        "\u0aa1\u0acb\u0ab5\u0acd\u0ab2\u0ac0"
    ],
    "name:ita_x_preferred":[
        "Dawley"
    ],
    "name:jpn_x_preferred":[
        "\u30c9\u30fc\u30ea\u30fc"
    ],
    "name:kan_x_preferred":[
        "\u0ca1\u0cbe\u0cb5\u0ccd\u0cb2\u0cbf"
    ],
    "name:kor_x_preferred":[
        "\uadf8\ub808\uc774\ud2b8 \ub2e4\uc6b8\ub9ac"
    ],
    "name:lat_x_preferred":[
        "Dawley Magna"
    ],
    "name:lit_x_preferred":[
        "Didysis Daulis"
    ],
    "name:lld_x_preferred":[
        "Dawley"
    ],
    "name:nan_x_preferred":[
        "Dawley"
    ],
    "name:nld_x_preferred":[
        "Dawley"
    ],
    "name:nno_x_preferred":[
        "Dawley"
    ],
    "name:pol_x_preferred":[
        "Dawley"
    ],
    "name:por_x_preferred":[
        "Dawley"
    ],
    "name:rus_x_preferred":[
        "\u0414\u043e\u0443\u043b\u0438"
    ],
    "name:spa_x_preferred":[
        "Dawley"
    ],
    "name:swe_x_preferred":[
        "Dawley"
    ],
    "name:tam_x_preferred":[
        "\u0b9f\u0bb5\u0bcd\u0bb2\u0bc7"
    ],
    "name:tel_x_preferred":[
        "\u0c26\u0c35\u0c4d\u0c32\u0c40"
    ],
    "name:tur_x_preferred":[
        "Dawley"
    ],
    "name:urd_x_preferred":[
        "\u062f\u0627\u0648\u0644\u06d2"
    ],
    "name:vol_x_preferred":[
        "Dawley"
    ],
    "name:zho_x_preferred":[
        "\u9053\u5229"
    ],
    "qs_pg:aaroncc":"GB",
    "qs_pg:gn_country":"GB",
    "qs_pg:gn_fcode":"PPL",
    "qs_pg:gn_pop":0,
    "qs_pg:name":"Dawley",
    "qs_pg:name_adm0":"United Kingdom",
    "qs_pg:name_adm1":"England",
    "qs_pg:photos":225,
    "qs_pg:photos_1k":46,
    "qs_pg:photos_9k":1,
    "qs_pg:photos_9r":4,
    "qs_pg:photos_all":225,
    "qs_pg:photos_sr":4,
    "qs_pg:pop_sr":0,
    "qs_pg:qs_pg_placetype":"locality",
    "qs_pg:qs_pg_placetype_gp":"Town",
    "qs_pg:woe_adm0":23424975,
    "woe:adm0_id":23424975,
    "woe:name_adm0":"United Kingdom",
    "woe:name_adm1":"England",
    "woe:placetype":"Town",
    "wof:name":"Dawley",
    "wof:placetype":"neighbourhood"
},
  "geometry": {"coordinates":[-2.46738,52.66486],"type":"Point"}
}