{
  "type": "Feature",
  "properties": {
    "iso:country":"GB",
    "name:ara_x_preferred":[
        "\u0641\u0644\u0643\u0648\u0644 \u0647\u064a\u062b"
    ],
    "name:cym_x_preferred":[
        "Flackwell Heath"
    ],
    "name:eng_x_preferred":[
        "Flackwell Heath"
    ],
    "name:fas_x_preferred":[
        "\u0641\u0644\u06a9\u0648\u0644 \u0647\u06cc\u062b"
    ],
    "name:fra_x_preferred":[
        "Flackwell Heath"
    ],
    "name:nld_x_preferred":[
        "Flackwell Heath"
    ],
    "name:pol_x_preferred":[
        "Flackwell Heath"
    ],
    "qs_pg:aaroncc":"GB",
    "qs_pg:name":"Flackwell Heath",
    "qs_pg:name_adm0":"United Kingdom",
    "qs_pg:name_adm1":"England",
    "qs_pg:photos":43,
    "qs_pg:photos_1k":9,
    "qs_pg:photos_9k":10,
    "qs_pg:photos_9r":9,
    "qs_pg:photos_all":2152,
    "qs_pg:photos_sr":2,
    "qs_pg:pop_sr":0,
    "qs_pg:qs_pg_placetype":"locality",
    "qs_pg:qs_pg_placetype_gp":"Town",
    "qs_pg:woe_adm0":23424975,
    "woe:adm0_id":23424975,
    "woe:name_adm0":"United Kingdom",
    "woe:name_adm1":"England",
    "woe:placetype":"Town",
    "wof:name":"Flackwell Heath",
    "wof:placetype":"neighbourhood"
},
  "geometry": {"coordinates":[-0.707244,51.59964],"type":"Point"}
}