{
  "type": "Feature",
  "properties": {
    "gn:country":"GB",
    "iso:country":"GB",
    "name:ceb_x_preferred":[
        "Spey Bay"
    ],
    "name:eng_x_preferred":[
        "Spey Bay"
    ],
    "name:eus_x_preferred":[
        "Spey Bay"
    ],
    "name:fra_x_preferred":[
        "Spey Bay"
    ],
    "name:gla_x_preferred":[
        "Inbhir Sp\u00e8"
    ],
    "name:nld_x_preferred":[
        "Spey Bay"
    ],
    "name:swe_x_preferred":[
        "Spey Bay"
    ],
    "qs_pg:aaroncc":"GB",
    "qs_pg:gn_country":"GB",
    "qs_pg:name":"Spey Bay",
    "qs_pg:name_adm0":"United Kingdom",
    "qs_pg:name_adm1":"Scotland",
    "qs_pg:photos":688,
    "qs_pg:photos_1k":139,
    "qs_pg:photos_9k":3,
    "qs_pg:photos_9r":5,
    "qs_pg:photos_all":688,
    "qs_pg:photos_sr":8,
    "qs_pg:pop_sr":0,
    "qs_pg:qs_pg_placetype":"locality",
    "qs_pg:qs_pg_placetype_gp":"Town",
    "qs_pg:woe_adm0":23424975,
    "woe:adm0_id":23424975,
    "woe:name_adm0":"United Kingdom",
    "woe:name_adm1":"Scotland",
    "woe:placetype":"Town",
    "wof:name":"Spey Bay",
    "wof:placetype":"locality"
},
  "geometry": {"coordinates":[-3.0939,57.6734055],"type":"Point"}
}