{
  "type": "Feature",
  "properties": {
    "gn:admin1_code": "ENG",
    "gn:admin2_code": "F2",
    "gn:admin3_code": "24UC",
    "gn:admin4_code": "24UC005",
    "gn:asciiname": "Conford",
    "gn:country_code": "GB",
    "gn:dem": 99,
    "gn:feature_class": "P",
    "gn:feature_code": "PPL",
    "gn:name": "Conford",
    "gn:population": 0,
    "gn:timezone": "Europe/London",
    "iso:country": "GB",
    "name:cym_x_preferred": [
      "Conford"
    ],
    "name:pol_x_preferred": [
      "Conford"
    ],
    "wof:name": "Conford",
    "wof:placetype": "neighbourhood"
  },
  "geometry": {"coordinates":[-0.82698,51.08762],"type":"Point"}
}
