{
  "type": "Feature",
  "properties": {
    "iso:country":"GB",
    "name:cym_x_preferred":[
        "Stoke Charity"
    ],
    "name:eng_x_preferred":[
        "Stoke Charity"
    ],
    "name:fra_x_preferred":[
        "Stoke Charity"
    ],
    "name:gle_x_preferred":[
        "Stoke Charity"
    ],
    "name:nld_x_preferred":[
        "Stoke Charity"
    ],
    "name:pol_x_preferred":[
        "Stoke Charity"
    ],
    "name:swe_x_preferred":[
        "Stoke Charity"
    ],
    "qs_pg:aaroncc":"GB",
    "qs_pg:name":"Stoke Charity",
    "qs_pg:name_adm0":"United Kingdom",
    "qs_pg:name_adm1":"England",
    "qs_pg:photos":32,
    "qs_pg:photos_1k":6,
    "qs_pg:photos_9k":1,
    "qs_pg:photos_9r":2,
    "qs_pg:photos_all":32,
    "qs_pg:photos_sr":2,
    "qs_pg:pop_sr":0,
    "qs_pg:qs_pg_placetype":"locality",
    "qs_pg:qs_pg_placetype_gp":"Town",
    "qs_pg:woe_adm0":23424975,
    "woe:adm0_id":23424975,
    "woe:name_adm0":"United Kingdom",
    "woe:name_adm1":"England",
    "woe:placetype":"Town",
    "wof:name":"Stoke Charity",
    "wof:placetype":"neighbourhood"
},
  "geometry": {"coordinates":[-1.304518,51.150931],"type":"Point"}
}