{
  "type": "Feature",
  "properties": {
    "iso:country":"GB",
    "name:ceb_x_preferred":[
        "Quinta"
    ],
    "name:ces_x_preferred":[
        "Kvinta"
    ],
    "name:deu_x_preferred":[
        "Quinta"
    ],
    "name:fra_x_preferred":[
        "Quinte"
    ],
    "name:glg_x_preferred":[
        "Quinta"
    ],
    "name:ita_x_preferred":[
        "Quinta"
    ],
    "name:por_x_preferred":[
        "Quinta"
    ],
    "name:rus_x_preferred":[
        "\u041a\u0438\u043d\u0442\u0430"
    ],
    "name:spa_x_preferred":[
        "Quinta"
    ],
    "name:srp_x_preferred":[
        "\u041a\u0432\u0438\u043d\u0442\u0430"
    ],
    "name:swe_x_preferred":[
        "Quinta"
    ],
    "qs_pg:aaroncc":"GB",
    "qs_pg:name":"Quinta",
    "qs_pg:name_adm0":"United Kingdom",
    "qs_pg:name_adm1":"England",
    "qs_pg:photos":206,
    "qs_pg:photos_1k":42,
    "qs_pg:photos_9k":1,
    "qs_pg:photos_9r":4,
    "qs_pg:photos_all":206,
    "qs_pg:photos_sr":4,
    "qs_pg:pop_sr":0,
    "qs_pg:qs_pg_placetype":"locality",
    "qs_pg:qs_pg_placetype_gp":"Town",
    "qs_pg:woe_adm0":23424975,
    "woe:adm0_id":23424975,
    "woe:name_adm0":"United Kingdom",
    "woe:name_adm1":"England",
    "woe:placetype":"Town",
    "wof:name":"Quinta",
    "wof:placetype":"neighbourhood"
},
  "geometry": {"coordinates":[-3.070635,52.913224],"type":"Point"}
}