{
  "type": "Feature",
  "properties": {
    "iso:country":"GB",
    "name:dut_x_preferred":[
        "South Boarhunt"
    ],
    "name:eng_x_preferred":[
        "South Boarhunt"
    ],
    "name:fre_x_preferred":[
        "South Boarhunt"
    ],
    "name:wel_x_preferred":[
        "South Boarhunt"
    ],
    "qs_pg:aaroncc":"GB",
    "qs_pg:name":"South Boarhunt",
    "qs_pg:name_adm0":"United Kingdom",
    "qs_pg:name_adm1":"England",
    "qs_pg:photos":22,
    "qs_pg:photos_1k":4,
    "qs_pg:photos_9k":1,
    "qs_pg:photos_9r":1,
    "qs_pg:photos_all":22,
    "qs_pg:photos_sr":1,
    "qs_pg:pop_sr":0,
    "qs_pg:qs_pg_placetype":"locality",
    "qs_pg:qs_pg_placetype_gp":"Town",
    "qs_pg:woe_adm0":23424975,
    "woe:adm0_id":23424975,
    "woe:name_adm0":"United Kingdom",
    "woe:name_adm1":"England",
    "woe:placetype":"Town",
    "wof:name":"South Boarhunt",
    "wof:placetype":"neighbourhood"
},
  "geometry": {"coordinates":[-1.146526,50.887699],"type":"Point"}
}