{
  "type": "Feature",
  "properties": {
    "gn:gn_country":"GB",
    "gn:gn_fcode":"PPL",
    "gn:gn_pop":0,
    "iso:country":"GB",
    "name:ara_x_preferred":[
        "\u0643\u064a\u0633"
    ],
    "name:cym_x_preferred":[
        "Keysoe"
    ],
    "name:eng_x_preferred":[
        "Keysoe"
    ],
    "name:fas_x_preferred":[
        "\u06a9\u06cc\u200c\u0633\u0648"
    ],
    "name:fra_x_preferred":[
        "Keysoe"
    ],
    "name:nld_x_preferred":[
        "Keysoe"
    ],
    "name:pol_x_preferred":[
        "Keysoe"
    ],
    "qs_pg:aaroncc":"GB",
    "qs_pg:gn_country":"GB",
    "qs_pg:gn_fcode":"PPL",
    "qs_pg:gn_pop":0,
    "qs_pg:name":"Keysoe",
    "qs_pg:name_adm0":"United Kingdom",
    "qs_pg:name_adm1":"England",
    "qs_pg:photos":446,
    "qs_pg:photos_1k":90,
    "qs_pg:photos_9k":2,
    "qs_pg:photos_9r":5,
    "qs_pg:photos_all":446,
    "qs_pg:photos_sr":6,
    "qs_pg:pop_sr":0,
    "qs_pg:qs_pg_placetype":"locality",
    "qs_pg:qs_pg_placetype_gp":"Town",
    "qs_pg:woe_adm0":23424975,
    "woe:adm0_id":23424975,
    "woe:name_adm0":"United Kingdom",
    "woe:name_adm1":"England",
    "woe:placetype":"Town",
    "wof:name":"Keysoe",
    "wof:placetype":"neighbourhood"
},
  "geometry": {"coordinates":[-0.42478,52.25161],"type":"Point"}
}