{
  "type": "Feature",
  "properties": {
    "iso:country":"GB",
    "name:ceb_x_preferred":[
        "Waunarlwydd"
    ],
    "name:cym_x_preferred":[
        "Waunarlwydd"
    ],
    "name:eng_x_preferred":[
        "Waunarlwydd"
    ],
    "name:eus_x_preferred":[
        "Waunarlwydd"
    ],
    "name:fra_x_preferred":[
        "Waunarlwydd"
    ],
    "name:gle_x_preferred":[
        "Waunarlwydd"
    ],
    "name:nld_x_preferred":[
        "Waunarlwydd"
    ],
    "name:swe_x_preferred":[
        "Waunarlwydd"
    ],
    "qs:gn_adm0_cc":"GB",
    "qs:gn_fcode":"PPL",
    "qs:gn_local":2636432,
    "qs:gn_nam_loc":"Swansea, Wales, GB",
    "qs:gn_namadm1":"WLS",
    "qs:gn_name":"Waunarlwydd",
    "qs:local_max":5058,
    "qs:local_sum":16167,
    "qs:localhoods":17,
    "qs:name":"Waunarlwydd",
    "qs:name_adm0":"United Kingdom",
    "qs:name_adm1":"Wales",
    "qs:name_adm2":"Swansea City and County",
    "qs:name_lau":"Swansea City and County",
    "qs:name_local":"Swansea",
    "qs:photo_max":71,
    "qs:photo_sum":256,
    "qs:placetype":"Suburb",
    "qs:quad_count":52,
    "qs:woe_adm0":23424975,
    "qs:woe_adm1":12578049,
    "qs:woe_adm2":12602229,
    "qs:woe_lau":12696131,
    "qs:woe_local":36758,
    "qs:woe_ver":"7.10.0",
    "wd:wordcount":605,
    "wof:lang":[
        "eng"
    ],
    "wof:name":"Waunarlwydd",
    "wof:placetype":"neighbourhood"
},
  "geometry": {"coordinates":[-4.030073,51.635258],"type":"Point"}
}