{
  "type": "Feature",
  "properties": {
    "iso:country": "GB",
    "name:cym_x_preferred": [
      "Llanfleiddan"
    ],
    "name:eus_x_preferred": [
      "Llanblethian"
    ],
    "qs_pg:aaroncc": "GB",
    "qs_pg:name": "Llanblethian",
    "qs_pg:name_adm0": "United Kingdom",
    "qs_pg:name_adm1": "Wales",
    "qs_pg:photos": 23,
    "qs_pg:photos_1k": 5,
    "qs_pg:photos_9k": 1,
    "qs_pg:photos_9r": 1,
    "qs_pg:photos_all": 23,
    "qs_pg:photos_sr": 1,
    "qs_pg:pop_sr": 0,
    "qs_pg:qs_pg_placetype": "locality",
    "qs_pg:qs_pg_placetype_gp": "Town",
    "qs_pg:woe_adm0": 23424975,
    "woe:adm0_id": 23424975,
    "woe:name_adm0": "United Kingdom",
    "woe:name_adm1": "Wales",
    "woe:placetype": "Town",
    "wof:name": "Llanblethian",
    "wof:placetype": "neighbourhood"
  },
  "geometry": {"coordinates":[-3.456852,51.455487],"type":"Point"}
}
