{
  "type": "Feature",
  "properties": {
    "gn:admin1_code":"ENG",
    "gn:admin2_code":"C6",
    "gn:admin3_code":"00HE203",
    "gn:asciiname":"Treesmill",
    "gn:country_code":"GB",
    "gn:dem":14,
    "gn:feature_class":"P",
    "gn:feature_code":"PPL",
    "gn:name":"Treesmill",
    "gn:population":0,
    "gn:timezone":"Europe/London",
    "iso:country":"GB",
    "name:eus_x_preferred":[
        "Treesmill"
    ],
    "wof:name":"Treesmill",
    "wof:placetype":"neighbourhood"
},
  "geometry": {"coordinates":[-4.6861,50.36786],"type":"Point"}
}