{
  "type": "Feature",
  "properties": {
    "gn:admin1_code":"ENG",
    "gn:admin2_code":"E6",
    "gn:admin3_code":"23UF",
    "gn:admin4_code":"23UF006",
    "gn:asciiname":"Brookthorpe",
    "gn:country_code":"GB",
    "gn:dem":53,
    "gn:feature_class":"P",
    "gn:feature_code":"PPL",
    "gn:name":"Brookthorpe",
    "gn:population":0,
    "gn:timezone":"Europe/London",
    "iso:country":"GB",
    "name:cym_x_preferred":[
        "Brookthorpe"
    ],
    "name:pol_x_preferred":[
        "Brookthorpe"
    ],
    "wof:name":"Brookthorpe",
    "wof:placetype":"neighbourhood"
},
  "geometry": {"coordinates":[-2.23829,51.80819],"type":"Point"}
}