{
  "type": "Feature",
  "properties": {
    "iso:country":"GB",
    "name:bre_x_preferred":[
        "Rhydyfelin"
    ],
    "name:cym_x_preferred":[
        "Rhydyfelin"
    ],
    "name:eus_x_preferred":[
        "Rhydyfelin"
    ],
    "qs_pg:aaroncc":"GB",
    "qs_pg:name":"Rhydyfelin",
    "qs_pg:name_adm0":"United Kingdom",
    "qs_pg:name_adm1":"Wales",
    "qs_pg:photos":37,
    "qs_pg:photos_1k":7,
    "qs_pg:photos_9k":1,
    "qs_pg:photos_9r":2,
    "qs_pg:photos_all":37,
    "qs_pg:photos_sr":2,
    "qs_pg:pop_sr":0,
    "qs_pg:qs_pg_placetype":"locality",
    "qs_pg:qs_pg_placetype_gp":"Town",
    "qs_pg:woe_adm0":23424975,
    "woe:adm0_id":23424975,
    "woe:name_adm0":"United Kingdom",
    "woe:name_adm1":"Wales",
    "woe:placetype":"Town",
    "wof:name":"Rhydyfelin",
    "wof:placetype":"neighbourhood"
},
  "geometry": {"coordinates":[-4.071893,52.391315],"type":"Point"}
}