{
  "type": "Feature",
  "properties": {
    "gn:admin1_code": "NIR",
    "gn:admin2_code": "N09000010",
    "gn:asciiname": "Raffrey",
    "gn:country_code": "GB",
    "gn:dem": 47,
    "gn:feature_class": "P",
    "gn:feature_code": "PPL",
    "gn:name": "Raffrey",
    "gn:population": 0,
    "gn:timezone": "Europe/London",
    "iso:country": "GB",
    "wof:name": "Raffrey",
    "wof:placetype": "locality"
  },
  "geometry": {"coordinates":[-5.74211,54.44085],"type":"Point"}
}
