{
  "type": "Feature",
  "properties": {
    "gn:admin1_code":"ENG",
    "gn:admin2_code":"E2",
    "gn:admin3_code":"21UH",
    "gn:admin4_code":"21UH042",
    "gn:asciiname":"Friar's Gate",
    "gn:country_code":"GB",
    "gn:dem":80,
    "gn:feature_class":"P",
    "gn:feature_code":"PPL",
    "gn:name":"Friar's Gate",
    "gn:population":0,
    "gn:timezone":"Europe/London",
    "iso:country":"GB",
    "wof:name":"Friar's Gate",
    "wof:placetype":"neighbourhood"
},
  "geometry": {"coordinates":[0.13527,51.08018],"type":"Point"}
}