{
  "type": "Feature",
  "properties": {
    "iso:country":"GB",
    "name:ceb_x_preferred":[
        "Blackbird Leys"
    ],
    "name:eng_x_preferred":[
        "Blackbird Leys"
    ],
    "name:nld_x_preferred":[
        "Blackbird Leys"
    ],
    "name:swe_x_preferred":[
        "Blackbird Leys"
    ],
    "name:unk_x_variant":[
        "Blackbird Leys"
    ],
    "qs:gn_adm0_cc":"GB",
    "qs:gn_local":2640729,
    "qs:gn_nam_loc":"Oxford, Oxford, Oxfordshire, England, GB",
    "qs:gn_namadm1":"ENG",
    "qs:local_max":5302,
    "qs:local_sum":22337,
    "qs:localhoods":8,
    "qs:name":"Blackbird Leys",
    "qs:name_adm0":"United Kingdom",
    "qs:name_adm1":"England",
    "qs:name_adm2":"Oxfordshire",
    "qs:name_lau":"Oxford City",
    "qs:name_local":"Oxford",
    "qs:photo_max":178,
    "qs:photo_sum":936,
    "qs:placetype":"Suburb",
    "qs:quad_count":73,
    "qs:woe_adm0":23424975,
    "qs:woe_adm1":24554868,
    "qs:woe_adm2":12602175,
    "qs:woe_lau":12696058,
    "qs:woe_local":31278,
    "qs:woe_ver":"7.10.0",
    "wd:wordcount":914,
    "wof:lang":[
        "eng"
    ],
    "wof:name":"Blackbird Leys",
    "wof:placetype":"neighbourhood"
},
  "geometry": {"coordinates":[-1.203939,51.711414],"type":"Point"}
}