{
  "type": "Feature",
  "properties": {
    "iso:country":"GB",
    "name:ben_x_preferred":[
        "\u09ac\u09cd\u09b2\u09cd\u09af\u09be\u0995\u09ac\u09be\u09b0\u09cd\u09a1 \u09b2\u09c7\u099c"
    ],
    "name:ceb_x_preferred":[
        "Blackbird Leys"
    ],
    "name:deu_x_preferred":[
        "Blackbird Leys"
    ],
    "name:ell_x_preferred":[
        "\u039c\u03c0\u03bb\u03b1\u03ba\u03bc\u03c0\u03b9\u03c1\u03bd\u03c4 \u039b\u03ad\u03b9\u03c2"
    ],
    "name:eng_x_preferred":[
        "Blackbird Leys"
    ],
    "name:fra_x_preferred":[
        "Blackbird Leys"
    ],
    "name:guj_x_preferred":[
        "\u0aac\u0acd\u0ab2\u0ac7\u0a95\u0aac\u0ab0\u0acd\u0aa1 \u0ab2\u0ac0\u0ab8"
    ],
    "name:jpn_x_preferred":[
        "\u30d6\u30e9\u30c3\u30af\u30d0\u30fc\u30c9\u30fb\u30ec\u30a4\u30ba"
    ],
    "name:kan_x_preferred":[
        "\u0cac\u0ccd\u0cb2\u0ccd\u0caf\u0cbe\u0c95\u0ccd\u0cac\u0cb0\u0ccd\u0ca1\u0ccd \u0cb2\u0cc7\u0cb8\u0ccd"
    ],
    "name:kor_x_preferred":[
        "\ube0c\ub799\ubc84\ub4dc \ub808\uc774\uc2a4"
    ],
    "name:lit_x_preferred":[
        "Blakbird Leisas"
    ],
    "name:nld_x_preferred":[
        "Blackbird Leys"
    ],
    "name:por_x_preferred":[
        "Blackbird Leys"
    ],
    "name:rus_x_preferred":[
        "\u0411\u043b\u044d\u043a\u0431\u0435\u0440\u0434-\u041b\u0435\u0439\u0441"
    ],
    "name:spa_x_preferred":[
        "Blackbird Leys"
    ],
    "name:swe_x_preferred":[
        "Blackbird Leys"
    ],
    "name:tam_x_preferred":[
        "\u0baa\u0bbf\u0bb3\u0bbe\u0b95\u0bcd\u0baa\u0bc7\u0bb0\u0bcd\u0b9f\u0bcd  \u0bb2\u0bc7\u0baf\u0bcd\u0bb8\u0bcd"
    ],
    "name:tel_x_preferred":[
        "\u0c2c\u0c4d\u0c32\u0c3e\u0c15\u0c4d \u0c2c\u0c30\u0c4d\u0c21\u0c4d \u0c32\u0c47\u0c38\u0c4d"
    ],
    "name:unk_x_variant":[
        "Blackbird Leys"
    ],
    "name:urd_x_preferred":[
        "\u0628\u0644\u06cc\u06a9 \u0628\u0631\u0688\u00a0\u0644\u06cc\u06cc\u0633"
    ],
    "qs:gn_adm0_cc":"GB",
    "qs:gn_local":2640729,
    "qs:gn_nam_loc":"Oxford, Oxford, Oxfordshire, England, GB",
    "qs:gn_namadm1":"ENG",
    "qs:local_max":5302,
    "qs:local_sum":22337,
    "qs:localhoods":8,
    "qs:name":"Blackbird Leys",
    "qs:name_adm0":"United Kingdom",
    "qs:name_adm1":"England",
    "qs:name_adm2":"Oxfordshire",
    "qs:name_lau":"Oxford City",
    "qs:name_local":"Oxford",
    "qs:photo_max":178,
    "qs:photo_sum":936,
    "qs:placetype":"Suburb",
    "qs:quad_count":73,
    "qs:woe_adm0":23424975,
    "qs:woe_adm1":24554868,
    "qs:woe_adm2":12602175,
    "qs:woe_lau":12696058,
    "qs:woe_local":31278,
    "qs:woe_ver":"7.10.0",
    "wd:wordcount":914,
    "wof:lang":[
        "eng"
    ],
    "wof:name":"Blackbird Leys",
    "wof:placetype":"neighbourhood"
},
  "geometry": {"coordinates":[-1.201078,51.721837],"type":"Point"}
}