{
  "type": "Feature",
  "properties": {
    "iso:country": "GB",
    "name:ben_x_preferred": [
      "ব্ল্যাকবার্ড লেজ"
    ],
    "name:ceb_x_preferred": [
      "Blackbird Leys"
    ],
    "name:deu_x_preferred": [
      "Blackbird Leys"
    ],
    "name:ell_x_preferred": [
      "Μπλακμπιρντ Λέις"
    ],
    "name:eng_x_preferred": [
      "Blackbird Leys"
    ],
    "name:fra_x_preferred": [
      "Blackbird Leys"
    ],
    "name:guj_x_preferred": [
      "બ્લેકબર્ડ લીસ"
    ],
    "name:jpn_x_preferred": [
      "ブラックバード・レイズ"
    ],
    "name:kan_x_preferred": [
      "ಬ್ಲ್ಯಾಕ್ಬರ್ಡ್ ಲೇಸ್"
    ],
    "name:kor_x_preferred": [
      "브랙버드 레이스"
    ],
    "name:lit_x_preferred": [
      "Blakbird Leisas"
    ],
    "name:nld_x_preferred": [
      "Blackbird Leys"
    ],
    "name:por_x_preferred": [
      "Blackbird Leys"
    ],
    "name:rus_x_preferred": [
      "Блэкберд-Лейс"
    ],
    "name:spa_x_preferred": [
      "Blackbird Leys"
    ],
    "name:swe_x_preferred": [
      "Blackbird Leys"
    ],
    "name:tam_x_preferred": [
      "பிளாக்பேர்ட் லேய்ஸ்"
    ],
    "name:tel_x_preferred": [
      "బ్లాక్ బర్డ్ లేస్"
    ],
    "name:urd_x_preferred": [
      "بلیک برڈ لییس"
    ],
    "qs:gn_adm0_cc": "GB",
    "qs:gn_local": 2640729,
    "qs:gn_nam_loc": "Oxford, Oxford, Oxfordshire, England, GB",
    "qs:gn_namadm1": "ENG",
    "qs:local_max": 5302,
    "qs:local_sum": 22337,
    "qs:localhoods": 8,
    "qs:name": "Blackbird Leys",
    "qs:name_adm0": "United Kingdom",
    "qs:name_adm1": "England",
    "qs:name_adm2": "Oxfordshire",
    "qs:name_lau": "Oxford City",
    "qs:name_local": "Oxford",
    "qs:photo_max": 178,
    "qs:photo_sum": 936,
    "qs:placetype": "Suburb",
    "qs:quad_count": 73,
    "qs:woe_adm0": 23424975,
    "qs:woe_adm1": 24554868,
    "qs:woe_adm2": 12602175,
    "qs:woe_lau": 12696058,
    "qs:woe_local": 31278,
    "qs:woe_ver": "7.10.0",
    "wd:wordcount": 914,
    "wof:lang": [
      "eng"
    ],
    "wof:name": "Blackbird Leys",
    "wof:placetype": "neighbourhood"
  },
  "geometry": {"coordinates":[-1.201078,51.721837],"type":"Point"}
}
