{
  "type": "Feature",
  "properties": {
    "gn:country":"GB",
    "gn:fcode":"PPL",
    "gn:population":4500,
    "iso:country":"GB",
    "name:ceb_x_preferred":[
        "Winscombe"
    ],
    "name:deu_x_preferred":[
        "Winscombe"
    ],
    "name:eng_x_preferred":[
        "Winscombe"
    ],
    "name:fas_x_preferred":[
        "\u0648\u06cc\u0646\u0632 \u06a9\u0627\u0645\u0628"
    ],
    "name:fra_x_preferred":[
        "Winscombe"
    ],
    "name:jpn_x_preferred":[
        "\u30a6\u30a3\u30f3\u30b9\u30af\u30fc\u30e0"
    ],
    "name:nld_x_preferred":[
        "Winscombe"
    ],
    "name:pol_x_preferred":[
        "Winscombe"
    ],
    "name:spa_x_preferred":[
        "Winscombe"
    ],
    "name:swe_x_preferred":[
        "Winscombe"
    ],
    "qs_pg:aaroncc":"GB",
    "qs_pg:gn_country":"GB",
    "qs_pg:gn_fcode":"PPL",
    "qs_pg:gn_pop":4500,
    "qs_pg:name":"Winscombe",
    "qs_pg:name_adm0":"United Kingdom",
    "qs_pg:name_adm1":"England",
    "qs_pg:photos":398,
    "qs_pg:photos_1k":81,
    "qs_pg:photos_9k":2,
    "qs_pg:photos_9r":5,
    "qs_pg:photos_all":398,
    "qs_pg:photos_sr":6,
    "qs_pg:pop_sr":4,
    "qs_pg:qs_pg_placetype":"locality",
    "qs_pg:qs_pg_placetype_gp":"Town",
    "qs_pg:woe_adm0":23424975,
    "woe:adm0_id":23424975,
    "woe:name_adm0":"United Kingdom",
    "woe:name_adm1":"England",
    "woe:placetype":"Town",
    "wof:name":"Winscombe",
    "wof:placetype":"neighbourhood",
    "wof:population":4546
},
  "geometry": {"coordinates":[-2.83177,51.31321],"type":"Point"}
}