{
  "type": "Feature",
  "properties": {
    "iso:country":"GB",
    "name:eng_x_preferred":[
        "Dunford Bridge"
    ],
    "name:fra_x_preferred":[
        "Dunford Bridge"
    ],
    "name:nld_x_preferred":[
        "Dunford Bridge"
    ],
    "name:pol_x_preferred":[
        "Dunford Bridge"
    ],
    "name:swe_x_preferred":[
        "Dunford Bridge"
    ],
    "qs_pg:aaroncc":"GB",
    "qs_pg:name":"Dunford Bridge",
    "qs_pg:name_adm0":"United Kingdom",
    "qs_pg:name_adm1":"England",
    "qs_pg:photos":822,
    "qs_pg:photos_1k":167,
    "qs_pg:photos_9k":4,
    "qs_pg:photos_9r":6,
    "qs_pg:photos_all":822,
    "qs_pg:photos_sr":9,
    "qs_pg:pop_sr":0,
    "qs_pg:qs_pg_placetype":"locality",
    "qs_pg:qs_pg_placetype_gp":"Town",
    "qs_pg:woe_adm0":23424975,
    "woe:adm0_id":23424975,
    "woe:name_adm0":"United Kingdom",
    "woe:name_adm1":"England",
    "woe:placetype":"Town",
    "wof:name":"Dunford Bridge",
    "wof:placetype":"neighbourhood"
},
  "geometry": {"coordinates":[-1.7692915,53.519351],"type":"Point"}
}