{
  "type": "Feature",
  "properties": {
    "gn:country": "GB",
    "gn:fcode": "PPL",
    "gn:population": 16808,
    "iso:country": "GB",
    "name:ben_x_preferred": [
      "লংফিল্ড"
    ],
    "name:bul_x_preferred": [
      "Лонгфиелд"
    ],
    "name:ceb_x_preferred": [
      "Longfield"
    ],
    "name:cym_x_preferred": [
      "Longfield"
    ],
    "name:deu_x_preferred": [
      "Longfield"
    ],
    "name:eng_x_preferred": [
      "Longfield"
    ],
    "name:fas_x_preferred": [
      "لانگفیلد"
    ],
    "name:fra_x_preferred": [
      "Longfield"
    ],
    "name:guj_x_preferred": [
      "લોંગફીલ્ડ"
    ],
    "name:jpn_x_preferred": [
      "ロングフィールド"
    ],
    "name:kan_x_preferred": [
      "ಲಾಂಗ್ಫೀಲ್ಡ್"
    ],
    "name:kor_x_preferred": [
      "롱필드"
    ],
    "name:lit_x_preferred": [
      "Longfildas"
    ],
    "name:nld_x_preferred": [
      "Longfield"
    ],
    "name:pol_x_preferred": [
      "Longfield"
    ],
    "name:por_x_preferred": [
      "Longfield"
    ],
    "name:rus_x_preferred": [
      "Лонгфилд"
    ],
    "name:spa_x_preferred": [
      "Longfield"
    ],
    "name:swe_x_preferred": [
      "Longfield"
    ],
    "name:tam_x_preferred": [
      "லோங்பியீல்டு"
    ],
    "name:tel_x_preferred": [
      "లాంగ్ ఫీల్డ్"
    ],
    "name:urd_x_preferred": [
      "لونجفیلڈ"
    ],
    "qs_pg:aaroncc": "GB",
    "qs_pg:gn_country": "GB",
    "qs_pg:gn_fcode": "PPL",
    "qs_pg:gn_pop": 16808,
    "qs_pg:name": "Longfield",
    "qs_pg:name_adm0": "United Kingdom",
    "qs_pg:name_adm1": "England",
    "qs_pg:photos": 5000,
    "qs_pg:photos_1k": 1000,
    "qs_pg:photos_9k": 22,
    "qs_pg:photos_9r": 14,
    "qs_pg:photos_all": 5000,
    "qs_pg:photos_sr": 24,
    "qs_pg:pop_sr": 6,
    "qs_pg:qs_pg_placetype": "locality",
    "qs_pg:qs_pg_placetype_gp": "Town",
    "qs_pg:woe_adm0": 23424975,
    "woe:adm0_id": 23424975,
    "woe:name_adm0": "United Kingdom",
    "woe:name_adm1": "England",
    "woe:placetype": "Town",
    "wof:name": "Longfield",
    "wof:placetype": "neighbourhood",
    "wof:population": 16808
  },
  "geometry": {"coordinates":[0.30212,51.3969],"type":"Point"}
}
