{
  "type": "Feature",
  "properties": {
    "gn:gn_country":"GB",
    "gn:gn_fcode":"PPL",
    "gn:gn_pop":16808,
    "gn:population":16808,
    "iso:country":"GB",
    "name:ben_x_preferred":[
        "\u09b2\u0982\u09ab\u09bf\u09b2\u09cd\u09a1"
    ],
    "name:bul_x_preferred":[
        "\u041b\u043e\u043d\u0433\u0444\u0438\u0435\u043b\u0434"
    ],
    "name:dut_x_preferred":[
        "Longfield"
    ],
    "name:eng_x_preferred":[
        "Longfield"
    ],
    "name:fre_x_preferred":[
        "Longfield"
    ],
    "name:ger_x_preferred":[
        "Longfield"
    ],
    "name:guj_x_preferred":[
        "\u0ab2\u0acb\u0a82\u0a97\u0aab\u0ac0\u0ab2\u0acd\u0aa1"
    ],
    "name:jpn_x_preferred":[
        "\u30ed\u30f3\u30b0\u30d5\u30a3\u30fc\u30eb\u30c9"
    ],
    "name:kan_x_preferred":[
        "\u0cb2\u0cbe\u0c82\u0c97\u0ccd\u0cab\u0cc0\u0cb2\u0ccd\u0ca1\u0ccd"
    ],
    "name:kor_x_preferred":[
        "\ub871\ud544\ub4dc"
    ],
    "name:lit_x_preferred":[
        "Longfildas"
    ],
    "name:pol_x_preferred":[
        "Longfield"
    ],
    "name:por_x_preferred":[
        "Longfield"
    ],
    "name:rus_x_preferred":[
        "\u041b\u043e\u043d\u0433\u0444\u0438\u043b\u0434"
    ],
    "name:spa_x_preferred":[
        "Longfield"
    ],
    "name:swe_x_preferred":[
        "Longfield"
    ],
    "name:tam_x_preferred":[
        "\u0bb2\u0bcb\u0b99\u0bcd\u0baa\u0bbf\u0baf\u0bc0\u0bb2\u0bcd\u0b9f\u0bc1"
    ],
    "name:tel_x_preferred":[
        "\u0c32\u0c3e\u0c02\u0c17\u0c4d \u0c2b\u0c40\u0c32\u0c4d\u0c21\u0c4d"
    ],
    "name:urd_x_preferred":[
        "\u0644\u0648\u0646\u062c\u0641\u06cc\u0644\u0688"
    ],
    "name:wel_x_preferred":[
        "Longfield"
    ],
    "qs_pg:aaroncc":"GB",
    "qs_pg:gn_country":"GB",
    "qs_pg:gn_fcode":"PPL",
    "qs_pg:gn_pop":16808,
    "qs_pg:name":"Longfield",
    "qs_pg:name_adm0":"United Kingdom",
    "qs_pg:name_adm1":"England",
    "qs_pg:photos":5000,
    "qs_pg:photos_1k":1000,
    "qs_pg:photos_9k":22,
    "qs_pg:photos_9r":14,
    "qs_pg:photos_all":5000,
    "qs_pg:photos_sr":24,
    "qs_pg:pop_sr":6,
    "qs_pg:qs_pg_placetype":"locality",
    "qs_pg:qs_pg_placetype_gp":"Town",
    "qs_pg:woe_adm0":23424975,
    "woe:adm0_id":23424975,
    "woe:name_adm0":"United Kingdom",
    "woe:name_adm1":"England",
    "woe:placetype":"Town",
    "wof:name":"Longfield",
    "wof:placetype":"neighbourhood",
    "wof:population":16808
},
  "geometry": {"coordinates":[0.30212,51.3969],"type":"Point"}
}