{
  "type": "Feature",
  "properties": {
    "iso:country":"GB",
    "wof:name":"East Gateshead",
    "wof:placetype":"neighbourhood"
},
  "geometry": {"coordinates":[-1.58386414634318,54.96360228641431],"type":"Point"}
}