{
  "type": "Feature",
  "properties": {
    "iso:country":"GB",
    "name:cym_x_preferred":[
        "Over Hulton"
    ],
    "name:eng_x_preferred":[
        "Over Hulton"
    ],
    "name:fra_x_preferred":[
        "Over Hulton"
    ],
    "name:nld_x_preferred":[
        "Over Hulton"
    ],
    "name:pol_x_preferred":[
        "Over Hulton"
    ],
    "qs:gn_adm0_cc":"GB",
    "qs:gn_local":2652522,
    "qs:gn_nam_loc":"kirkby-in-furness",
    "qs:gn_namadm1":"ENG",
    "qs:local_max":2081,
    "qs:local_sum":7311,
    "qs:localhoods":9,
    "qs:name":"Over Hulton",
    "qs:name_adm0":"United Kingdom",
    "qs:name_adm1":"England",
    "qs:name_adm2":"Greater Manchester",
    "qs:name_lau":"Bolton Metropolitan Borough",
    "qs:name_local":"Bolton",
    "qs:photo_max":164,
    "qs:photo_sum":355,
    "qs:placetype":"Suburb",
    "qs:quad_count":38,
    "qs:woe_adm0":23424975,
    "qs:woe_adm1":24554868,
    "qs:woe_adm2":12602158,
    "qs:woe_lau":12695839,
    "qs:woe_local":13189,
    "qs:woe_ver":"7.10.0",
    "wd:wordcount":777,
    "wof:lang":[
        "eng"
    ],
    "wof:name":"Over Hulton",
    "wof:placetype":"neighbourhood"
},
  "geometry": {"coordinates":[-2.492063,53.527161],"type":"Point"}
}