{
  "type": "Feature",
  "properties": {
    "gn:country":"GB",
    "gn:fcode":"PPL",
    "gn:population":240,
    "iso:country":"GB",
    "name:ara_x_preferred":[
        "\u0622\u0628\u0628\u0631 \u0633\u062a\u0648\u0646\u062f\u0646"
    ],
    "name:cym_x_preferred":[
        "Upper Stondon"
    ],
    "name:fas_x_preferred":[
        "\u0622\u067e\u0631 \u0627\u0633\u062a\u0627\u0646\u062f\u0646"
    ],
    "name:fra_x_preferred":[
        "Upper Stondon"
    ],
    "name:pol_x_preferred":[
        "Upper Stondon"
    ],
    "qs_pg:aaroncc":"GB",
    "qs_pg:gn_country":"GB",
    "qs_pg:gn_fcode":"PPL",
    "qs_pg:gn_pop":240,
    "qs_pg:name":"Upper Stondon",
    "qs_pg:name_adm0":"United Kingdom",
    "qs_pg:name_adm1":"England",
    "qs_pg:photos":17,
    "qs_pg:photos_1k":3,
    "qs_pg:photos_9k":1,
    "qs_pg:photos_9r":1,
    "qs_pg:photos_all":17,
    "qs_pg:photos_sr":1,
    "qs_pg:pop_sr":2,
    "qs_pg:qs_pg_placetype":"locality",
    "qs_pg:qs_pg_placetype_gp":"Town",
    "qs_pg:woe_adm0":23424975,
    "woe:adm0_id":23424975,
    "woe:name_adm0":"United Kingdom",
    "woe:name_adm1":"England",
    "woe:placetype":"Town",
    "wof:name":"Upper Stondon",
    "wof:placetype":"neighbourhood",
    "wof:population":240
},
  "geometry": {"coordinates":[-0.48185,51.93839],"type":"Point"}
}