{
  "type": "Feature",
  "properties": {
    "gn:admin1_code":"ENG",
    "gn:admin2_code":"E2",
    "gn:admin3_code":"21UC",
    "gn:asciiname":"Friday Street",
    "gn:country_code":"GB",
    "gn:dem":16,
    "gn:feature_class":"P",
    "gn:feature_code":"PPL",
    "gn:name":"Friday Street",
    "gn:population":0,
    "gn:timezone":"Europe/London",
    "iso:country":"GB",
    "name:pol_x_preferred":[
        "Friday Street"
    ],
    "wof:name":"Friday Street",
    "wof:placetype":"neighbourhood"
},
  "geometry": {"coordinates":[0.29852,50.80984],"type":"Point"}
}