{
  "type": "Feature",
  "properties": {
    "gn:admin1_code":"SCT",
    "gn:admin2_code":"T8",
    "gn:asciiname":"West Kames",
    "gn:country_code":"GB",
    "gn:dem":17,
    "gn:feature_class":"P",
    "gn:feature_code":"PPL",
    "gn:name":"West Kames",
    "gn:population":0,
    "gn:timezone":"Europe/London",
    "iso:country":"GB",
    "wof:name":"West Kames",
    "wof:placetype":"locality"
},
  "geometry": {"coordinates":[-5.34519,56.04961],"type":"Point"}
}