{
  "type": "Feature",
  "properties": {
    "gn:country":"GB",
    "gn:fcode":"PPL",
    "gn:population":0,
    "iso:country":"GB",
    "name:ceb_x_preferred":[
        "Ashmore"
    ],
    "name:cym_x_preferred":[
        "Ashmore"
    ],
    "name:eng_x_preferred":[
        "Ashmore"
    ],
    "name:fas_x_preferred":[
        "\u0627\u0634\u0645\u0648\u0631"
    ],
    "name:fra_x_preferred":[
        "Ashmore"
    ],
    "name:ita_x_preferred":[
        "Ashmore"
    ],
    "name:nld_x_preferred":[
        "Ashmore"
    ],
    "name:nob_x_preferred":[
        "Ashmore"
    ],
    "name:pol_x_preferred":[
        "Ashmore"
    ],
    "name:swe_x_preferred":[
        "Ashmore"
    ],
    "qs_pg:aaroncc":"GB",
    "qs_pg:gn_country":"GB",
    "qs_pg:gn_fcode":"PPL",
    "qs_pg:gn_pop":0,
    "qs_pg:name":"Cashmoor",
    "qs_pg:name_adm0":"United Kingdom",
    "qs_pg:name_adm1":"England",
    "qs_pg:photos":116,
    "qs_pg:photos_1k":24,
    "qs_pg:photos_9k":1,
    "qs_pg:photos_9r":3,
    "qs_pg:photos_all":116,
    "qs_pg:photos_sr":3,
    "qs_pg:pop_sr":0,
    "qs_pg:qs_pg_placetype":"locality",
    "qs_pg:qs_pg_placetype_gp":"Town",
    "qs_pg:woe_adm0":23424975,
    "woe:adm0_id":23424975,
    "woe:name_adm0":"United Kingdom",
    "woe:name_adm1":"England",
    "woe:placetype":"Town",
    "wof:name":"Cashmoor",
    "wof:placetype":"neighbourhood"
},
  "geometry": {"coordinates":[-2.13333,50.95],"type":"Point"}
}