{
  "type": "Feature",
  "properties": {
    "iso:country":"GB",
    "name:bre_x_preferred":[
        "Ffwrnais"
    ],
    "name:cym_x_preferred":[
        "Ffwrnais"
    ],
    "name:eng_x_preferred":[
        "Furnace"
    ],
    "name:fra_x_preferred":[
        "Furnace"
    ],
    "name:nld_x_preferred":[
        "Furnace"
    ],
    "name:ukr_x_preferred":[
        "\u0424\u0435\u0440\u043d\u0456\u0441"
    ],
    "qs_pg:aaroncc":"GB",
    "qs_pg:name":"Furnace",
    "qs_pg:name_adm0":"United Kingdom",
    "qs_pg:name_adm1":"Wales",
    "qs_pg:photos":183,
    "qs_pg:photos_1k":37,
    "qs_pg:photos_9k":1,
    "qs_pg:photos_9r":4,
    "qs_pg:photos_all":183,
    "qs_pg:photos_sr":4,
    "qs_pg:pop_sr":0,
    "qs_pg:qs_pg_placetype":"locality",
    "qs_pg:qs_pg_placetype_gp":"Town",
    "qs_pg:woe_adm0":23424975,
    "woe:adm0_id":23424975,
    "woe:name_adm0":"United Kingdom",
    "woe:name_adm1":"Wales",
    "woe:placetype":"Town",
    "wof:name":"Furnace",
    "wof:placetype":"neighbourhood"
},
  "geometry": {"coordinates":[-3.940422,52.538139],"type":"Point"}
}