{
  "type": "Feature",
  "properties": {
    "iso:country": "GB",
    "name:bre_x_preferred": [
      "Defynnog"
    ],
    "name:cym_x_preferred": [
      "Defynnog"
    ],
    "name:deu_x_preferred": [
      "Defynnog"
    ],
    "name:eng_x_preferred": [
      "Defynnog"
    ],
    "name:epo_x_preferred": [
      "Defynnog"
    ],
    "name:eus_x_preferred": [
      "Defynnog"
    ],
    "name:fra_x_preferred": [
      "Defynnog"
    ],
    "name:gle_x_preferred": [
      "Defynnog"
    ],
    "name:glg_x_preferred": [
      "Defynnog"
    ],
    "name:nld_x_preferred": [
      "Defynnog"
    ],
    "name:sco_x_preferred": [
      "Defynnog"
    ],
    "qs_pg:aaroncc": "GB",
    "qs_pg:name": "Defynnog",
    "qs_pg:name_adm0": "United Kingdom",
    "qs_pg:name_adm1": "Wales",
    "qs_pg:photos": 48,
    "qs_pg:photos_1k": 10,
    "qs_pg:photos_9k": 1,
    "qs_pg:photos_9r": 2,
    "qs_pg:photos_all": 48,
    "qs_pg:photos_sr": 2,
    "qs_pg:pop_sr": 0,
    "qs_pg:qs_pg_placetype": "locality",
    "qs_pg:qs_pg_placetype_gp": "Town",
    "qs_pg:woe_adm0": 23424975,
    "woe:adm0_id": 23424975,
    "woe:name_adm0": "United Kingdom",
    "woe:name_adm1": "Wales",
    "woe:placetype": "Town",
    "wof:name": "Defynnog",
    "wof:placetype": "neighbourhood"
  },
  "geometry": {"coordinates":[-3.564548,51.931406],"type":"Point"}
}
