{
  "type": "Feature",
  "properties": {
    "iso:country": "GB",
    "name:eng_x_preferred": [
      "Cowley St John"
    ],
    "name:eng_x_variant": [
      "Cowley Road Area"
    ],
    "wof:name": "Cowley St John",
    "wof:placetype": "neighbourhood"
  },
  "geometry": {"coordinates":[-1.22378703510661,51.74043537227524],"type":"Point"}
}
