{
  "type": "Feature",
  "properties": {
    "iso:country":"GB",
    "name:eng_x_preferred":[
        "Carnbo"
    ],
    "name:eus_x_preferred":[
        "Carnbo"
    ],
    "name:fra_x_preferred":[
        "Carnbo"
    ],
    "name:gle_x_preferred":[
        "C\u00e1rn B\u00f3"
    ],
    "name:nld_x_preferred":[
        "Carnbo"
    ],
    "qs_pg:aaroncc":"GB",
    "qs_pg:name":"Carnbo",
    "qs_pg:name_adm0":"United Kingdom",
    "qs_pg:name_adm1":"Scotland",
    "qs_pg:photos":16,
    "qs_pg:photos_1k":3,
    "qs_pg:photos_9k":1,
    "qs_pg:photos_9r":1,
    "qs_pg:photos_all":16,
    "qs_pg:photos_sr":1,
    "qs_pg:pop_sr":0,
    "qs_pg:qs_pg_placetype":"locality",
    "qs_pg:qs_pg_placetype_gp":"Town",
    "qs_pg:woe_adm0":23424975,
    "woe:adm0_id":23424975,
    "woe:name_adm0":"United Kingdom",
    "woe:name_adm1":"Scotland",
    "woe:placetype":"Town",
    "wof:name":"Carnbo",
    "wof:placetype":"locality"
},
  "geometry": {"coordinates":[-3.521169,56.224076],"type":"Point"}
}