{
  "type": "Feature",
  "properties": {
    "gn:admin1_code":"ENG",
    "gn:admin2_code":"L6",
    "gn:admin3_code":"00GG190",
    "gn:asciiname":"Loughton",
    "gn:country_code":"GB",
    "gn:dem":231,
    "gn:feature_class":"P",
    "gn:feature_code":"PPL",
    "gn:name":"Loughton",
    "gn:population":0,
    "gn:timezone":"Europe/London",
    "iso:country":"GB",
    "name:cym_x_preferred":[
        "Loughton"
    ],
    "name:pol_x_preferred":[
        "Loughton"
    ],
    "wof:name":"Loughton",
    "wof:placetype":"neighbourhood"
},
  "geometry": {"coordinates":[-2.56667,52.43333000000001],"type":"Point"}
}