{
  "type": "Feature",
  "properties": {
    "gn:admin1_code":"ENG",
    "gn:admin2_code":"D4",
    "gn:admin3_code":"18UE",
    "gn:admin4_code":"18UE021",
    "gn:asciiname":"Oldways End",
    "gn:country_code":"GB",
    "gn:dem":235,
    "gn:feature_class":"P",
    "gn:feature_code":"PPL",
    "gn:name":"Oldways End",
    "gn:population":0,
    "gn:timezone":"Europe/London",
    "iso:country":"GB",
    "wof:name":"Oldways End",
    "wof:placetype":"neighbourhood"
},
  "geometry": {"coordinates":[-3.61417,51.01222],"type":"Point"}
}