{
  "type": "Feature",
  "properties": {
    "gn:country":"GB",
    "gn:fcode":"PPL",
    "gn:population":4477,
    "iso:country":"GB",
    "name:bar_x_preferred":[
        "Donnington"
    ],
    "name:ceb_x_preferred":[
        "Donnington"
    ],
    "name:cym_x_preferred":[
        "Donnington"
    ],
    "name:fra_x_preferred":[
        "Donnington"
    ],
    "name:ita_x_preferred":[
        "Donnington"
    ],
    "name:nld_x_preferred":[
        "Donnington"
    ],
    "name:pol_x_preferred":[
        "Donnington"
    ],
    "name:swe_x_preferred":[
        "Donnington"
    ],
    "qs_pg:aaroncc":"GB",
    "qs_pg:gn_country":"GB",
    "qs_pg:gn_fcode":"PPL",
    "qs_pg:gn_pop":4477,
    "qs_pg:name":"Donnington",
    "qs_pg:name_adm0":"United Kingdom",
    "qs_pg:name_adm1":"England",
    "qs_pg:photos":212,
    "qs_pg:photos_1k":43,
    "qs_pg:photos_9k":1,
    "qs_pg:photos_9r":4,
    "qs_pg:photos_all":212,
    "qs_pg:photos_sr":4,
    "qs_pg:pop_sr":4,
    "qs_pg:qs_pg_placetype":"locality",
    "qs_pg:qs_pg_placetype_gp":"Town",
    "qs_pg:woe_adm0":23424975,
    "woe:adm0_id":23424975,
    "woe:name_adm0":"United Kingdom",
    "woe:name_adm1":"England",
    "woe:placetype":"Town",
    "wof:name":"Donnington",
    "wof:placetype":"neighbourhood",
    "wof:population":4477
},
  "geometry": {"coordinates":[-1.72142,51.95135],"type":"Point"}
}