{
  "type": "Feature",
  "properties": {
    "gn:admin1_code":"WLS",
    "gn:admin2_code":"Y2",
    "gn:admin3_code":"00NC043",
    "gn:asciiname":"Tanyraltt",
    "gn:country_code":"GB",
    "gn:dem":120,
    "gn:feature_class":"P",
    "gn:feature_code":"PPLL",
    "gn:name":"Tanyraltt",
    "gn:population":0,
    "gn:timezone":"Europe/London",
    "iso:country":"GB",
    "name:und_x_variant":[
        "Tanrallt"
    ],
    "wof:name":"Tanyraltt",
    "wof:placetype":"neighbourhood"
},
  "geometry": {"coordinates":[-4.25634,53.04626],"type":"Point"}
}