{
  "type": "Feature",
  "properties": {
    "gn:country": "GB",
    "gn:fcode": "PPL",
    "gn:population": 18808,
    "iso:country": "GB",
    "name:bul_x_preferred": [
      "Хебурн"
    ],
    "name:ceb_x_preferred": [
      "Hebburn"
    ],
    "name:cym_x_preferred": [
      "Hebburn"
    ],
    "name:deu_x_preferred": [
      "Hebburn"
    ],
    "name:eng_x_preferred": [
      "Hebburn"
    ],
    "name:fas_x_preferred": [
      "هبورن"
    ],
    "name:fra_x_preferred": [
      "Hebburn"
    ],
    "name:gle_x_preferred": [
      "Hebburn"
    ],
    "name:ita_x_preferred": [
      "Hebburn"
    ],
    "name:jpn_x_preferred": [
      "ヘバーン"
    ],
    "name:nld_x_preferred": [
      "Hebburn"
    ],
    "name:nld_x_variant": [
      "Darrington"
    ],
    "name:pol_x_preferred": [
      "Hebburn"
    ],
    "name:swe_x_preferred": [
      "Hebburn"
    ],
    "name:ukr_x_preferred": [
      "Геббурн"
    ],
    "name:und_x_variant": [
      "Hebburn-on-Tyne"
    ],
    "name:zho_x_preferred": [
      "赫伯恩"
    ],
    "qs_pg:aaroncc": "GB",
    "qs_pg:gn_country": "GB",
    "qs_pg:gn_fcode": "PPL",
    "qs_pg:gn_pop": 18808,
    "qs_pg:name": "Hebburn",
    "qs_pg:name_adm0": "United Kingdom",
    "qs_pg:name_adm1": "England",
    "qs_pg:photos": 280,
    "qs_pg:photos_1k": 57,
    "qs_pg:photos_9k": 1,
    "qs_pg:photos_9r": 4,
    "qs_pg:photos_all": 280,
    "qs_pg:photos_sr": 5,
    "qs_pg:pop_sr": 6,
    "qs_pg:qs_pg_placetype": "locality",
    "qs_pg:qs_pg_placetype_gp": "Town",
    "qs_pg:woe_adm0": 23424975,
    "woe:adm0_id": 23424975,
    "woe:name_adm0": "United Kingdom",
    "woe:name_adm1": "England",
    "woe:placetype": "Town",
    "wof:name": "Hebburn",
    "wof:placetype": "neighbourhood",
    "wof:population": 18808
  },
  "geometry": {"coordinates":[-1.51546,54.97302],"type":"Point"}
}
