{
  "type": "Feature",
  "properties": {
    "gn:country":"GB",
    "gn:fcode":"PPL",
    "gn:population":18808,
    "iso:country":"GB",
    "name:bul_x_preferred":[
        "\u0425\u0435\u0431\u0443\u0440\u043d"
    ],
    "name:ceb_x_preferred":[
        "Hebburn"
    ],
    "name:cym_x_preferred":[
        "Hebburn"
    ],
    "name:deu_x_preferred":[
        "Hebburn"
    ],
    "name:eng_x_preferred":[
        "Hebburn"
    ],
    "name:fas_x_preferred":[
        "\u0647\u0628\u0648\u0631\u0646"
    ],
    "name:fra_x_preferred":[
        "Hebburn"
    ],
    "name:gle_x_preferred":[
        "Hebburn"
    ],
    "name:ita_x_preferred":[
        "Hebburn"
    ],
    "name:jpn_x_preferred":[
        "\u30d8\u30d0\u30fc\u30f3"
    ],
    "name:nld_x_preferred":[
        "Hebburn"
    ],
    "name:nld_x_variant":[
        "Darrington"
    ],
    "name:pol_x_preferred":[
        "Hebburn"
    ],
    "name:swe_x_preferred":[
        "Hebburn"
    ],
    "name:ukr_x_preferred":[
        "\u0413\u0435\u0431\u0431\u0443\u0440\u043d"
    ],
    "name:und_x_variant":[
        "Hebburn-on-Tyne"
    ],
    "name:zho_x_preferred":[
        "\u8d6b\u4f2f\u6069"
    ],
    "qs_pg:aaroncc":"GB",
    "qs_pg:gn_country":"GB",
    "qs_pg:gn_fcode":"PPL",
    "qs_pg:gn_pop":18808,
    "qs_pg:name":"Hebburn",
    "qs_pg:name_adm0":"United Kingdom",
    "qs_pg:name_adm1":"England",
    "qs_pg:photos":280,
    "qs_pg:photos_1k":57,
    "qs_pg:photos_9k":1,
    "qs_pg:photos_9r":4,
    "qs_pg:photos_all":280,
    "qs_pg:photos_sr":5,
    "qs_pg:pop_sr":6,
    "qs_pg:qs_pg_placetype":"locality",
    "qs_pg:qs_pg_placetype_gp":"Town",
    "qs_pg:woe_adm0":23424975,
    "woe:adm0_id":23424975,
    "woe:name_adm0":"United Kingdom",
    "woe:name_adm1":"England",
    "woe:placetype":"Town",
    "wof:name":"Hebburn",
    "wof:placetype":"neighbourhood",
    "wof:population":18808
},
  "geometry": {"coordinates":[-1.51546,54.97302],"type":"Point"}
}