{
  "type": "Feature",
  "properties": {
    "gn:admin1_code": "NIR",
    "gn:admin2_code": "N09000002",
    "gn:asciiname": "Millford",
    "gn:country_code": "GB",
    "gn:dem": 46,
    "gn:feature_class": "P",
    "gn:feature_code": "PPL",
    "gn:name": "Millford",
    "gn:population": 0,
    "gn:timezone": "Europe/London",
    "iso:country": "GB",
    "wof:name": "Millford",
    "wof:placetype": "locality"
  },
  "geometry": {"coordinates":[-6.68333,54.33333],"type":"Point"}
}
