{
  "type": "Feature",
  "properties": {
    "iso:country":"GB",
    "name:ceb_x_preferred":[
        "Walterston Castle"
    ],
    "name:eus_x_preferred":[
        "Walterston"
    ],
    "name:swe_x_preferred":[
        "Walterston Castle"
    ],
    "qs_pg:aaroncc":"GB",
    "qs_pg:name":"Walterston",
    "qs_pg:name_adm0":"United Kingdom",
    "qs_pg:name_adm1":"Wales",
    "qs_pg:photos":337,
    "qs_pg:photos_1k":68,
    "qs_pg:photos_9k":1,
    "qs_pg:photos_9r":5,
    "qs_pg:photos_all":337,
    "qs_pg:photos_sr":5,
    "qs_pg:pop_sr":0,
    "qs_pg:qs_pg_placetype":"locality",
    "qs_pg:qs_pg_placetype_gp":"Town",
    "qs_pg:woe_adm0":23424975,
    "woe:adm0_id":23424975,
    "woe:name_adm0":"United Kingdom",
    "woe:name_adm1":"Wales",
    "woe:placetype":"Town",
    "wof:name":"Walterston",
    "wof:placetype":"neighbourhood"
},
  "geometry": {"coordinates":[-3.307914,51.447641],"type":"Point"}
}