{
  "type": "Feature",
  "properties": {
    "gn:admin1_code":"ENG",
    "gn:admin2_code":"J1",
    "gn:admin3_code":"34UE",
    "gn:admin4_code":"34UE014",
    "gn:asciiname":"Little Oakley",
    "gn:country_code":"GB",
    "gn:dem":79,
    "gn:feature_class":"P",
    "gn:feature_code":"PPL",
    "gn:name":"Little Oakley",
    "gn:population":0,
    "gn:timezone":"Europe/London",
    "iso:country":"GB",
    "name:cym_x_preferred":[
        "Little Oakley"
    ],
    "name:pol_x_preferred":[
        "Little Oakley"
    ],
    "wof:name":"Little Oakley",
    "wof:placetype":"neighbourhood"
},
  "geometry": {"coordinates":[-0.68974,52.46069],"type":"Point"}
}