{
  "type": "Feature",
  "properties": {
    "gn:fcode":"PPLA2",
    "gn:population":56679,
    "iso:country":"GB",
    "name:ceb_x_preferred":[
        "Castlereagh"
    ],
    "name:dan_x_preferred":[
        "Castlereagh"
    ],
    "name:deu_x_preferred":[
        "Castlereagh"
    ],
    "name:eng_x_preferred":[
        "Castlereagh"
    ],
    "name:jpn_x_preferred":[
        "\u30ab\u30fc\u30b9\u30eb\u30ec\u30a4"
    ],
    "name:nld_x_preferred":[
        "Castlereagh"
    ],
    "name:pol_x_preferred":[
        "Castlereagh"
    ],
    "name:swe_x_preferred":[
        "Castlereagh"
    ],
    "qs_pg:aaroncc":"GB",
    "qs_pg:gn_fcode":"PPLA2",
    "qs_pg:gn_pop":56679,
    "qs_pg:name":"Castlereagh",
    "qs_pg:name_adm0":"United Kingdom",
    "qs_pg:name_adm1":"Northern Ireland",
    "qs_pg:photos":68,
    "qs_pg:photos_1k":14,
    "qs_pg:photos_9k":1,
    "qs_pg:photos_9r":2,
    "qs_pg:photos_all":68,
    "qs_pg:photos_sr":2,
    "qs_pg:pop_sr":0,
    "qs_pg:qs_pg_placetype":"locality",
    "qs_pg:qs_pg_placetype_gp":"Town",
    "qs_pg:woe_adm0":23424975,
    "woe:adm0_id":23424975,
    "woe:name_adm0":"United Kingdom",
    "woe:name_adm1":"Northern Ireland",
    "woe:placetype":"Town",
    "wof:name":"Castlereagh",
    "wof:placetype":"neighbourhood",
    "wof:population":56679
},
  "geometry": {"coordinates":[-5.882004,54.579073],"type":"Point"}
}