{
  "type": "Feature",
  "properties": {
    "iso:country":"GB",
    "name:ceb_x_preferred":[
        "Castlereagh"
    ],
    "name:dan_x_preferred":[
        "Castlereagh"
    ],
    "name:deu_x_preferred":[
        "Castlereagh"
    ],
    "name:jpn_x_preferred":[
        "\u30ab\u30fc\u30b9\u30eb\u30ec\u30a4"
    ],
    "name:nld_x_preferred":[
        "Castlereagh"
    ],
    "name:pol_x_preferred":[
        "Castlereagh"
    ],
    "name:swe_x_preferred":[
        "Castlereagh"
    ],
    "wof:name":"Castlereagh",
    "wof:placetype":"neighbourhood"
},
  "geometry": {"coordinates":[-5.88200376814483,54.57907340606121],"type":"Point"}
}