{
  "type": "Feature",
  "properties": {
    "iso:country":"GB",
    "name:eng_x_preferred":[
        "Rhydypenau"
    ],
    "name:unk_x_variant":[
        "Rhydypenau"
    ],
    "qs:gn_adm0_cc":"GB",
    "qs:gn_local":2643985,
    "qs:gn_nam_loc":"llanishen",
    "qs:gn_namadm1":"WLS",
    "qs:local_max":1169,
    "qs:local_sum":1169,
    "qs:localhoods":1,
    "qs:name":"Rhydypenau",
    "qs:name_adm0":"United Kingdom",
    "qs:name_adm1":"Wales",
    "qs:name_adm2":"Cardiff County",
    "qs:name_lau":"Cardiff County",
    "qs:name_local":"Llanishen",
    "qs:photo_max":197,
    "qs:photo_sum":1169,
    "qs:placetype":"Suburb",
    "qs:quad_count":50,
    "qs:woe_adm0":23424975,
    "qs:woe_adm1":12578049,
    "qs:woe_adm2":12602215,
    "qs:woe_lau":12696132,
    "qs:woe_local":27027,
    "qs:woe_ver":"7.10.0",
    "wof:lang":[
        "eng"
    ],
    "wof:name":"Rhydypenau",
    "wof:placetype":"neighbourhood"
},
  "geometry": {"coordinates":[-3.180988,51.520743],"type":"Point"}
}