{
  "type": "Feature",
  "properties": {
    "iso:country":"GB",
    "name:gle_x_preferred":[
        "Lemington"
    ],
    "name:pol_x_preferred":[
        "Lemington"
    ],
    "wof:name":"Lemington",
    "wof:placetype":"neighbourhood"
},
  "geometry": {"coordinates":[-1.71298060006483,54.97665306275145],"type":"Point"}
}