{
  "type": "Feature",
  "properties": {
    "iso:country":"GB",
    "name:cym_x_preferred":[
        "Waterfoot"
    ],
    "name:eng_x_preferred":[
        "Waterfoot"
    ],
    "name:eus_x_preferred":[
        "Waterfoot"
    ],
    "name:fas_x_preferred":[
        "\u0648\u0627\u062a\u0631\u0641\u0648\u062a"
    ],
    "name:fra_x_preferred":[
        "Waterfoot"
    ],
    "name:nld_x_preferred":[
        "Waterfoot"
    ],
    "name:sco_x_preferred":[
        "Watterfit"
    ],
    "name:spa_x_preferred":[
        "Waterfoot"
    ],
    "qs_pg:aaroncc":"GB",
    "qs_pg:name":"Waterfoot",
    "qs_pg:name_adm0":"United Kingdom",
    "qs_pg:name_adm1":"Scotland",
    "qs_pg:photos":18,
    "qs_pg:photos_1k":4,
    "qs_pg:photos_9k":1,
    "qs_pg:photos_9r":1,
    "qs_pg:photos_all":18,
    "qs_pg:photos_sr":1,
    "qs_pg:pop_sr":0,
    "qs_pg:qs_pg_placetype":"locality",
    "qs_pg:qs_pg_placetype_gp":"Town",
    "qs_pg:woe_adm0":23424975,
    "woe:adm0_id":23424975,
    "woe:name_adm0":"United Kingdom",
    "woe:name_adm1":"Scotland",
    "woe:placetype":"Town",
    "wof:name":"Waterfoot",
    "wof:placetype":"locality"
},
  "geometry": {"coordinates":[-4.282146,55.765957],"type":"Point"}
}