{
  "type": "Feature",
  "properties": {
    "gn:admin1_code":"WLS",
    "gn:admin2_code":"Y7",
    "gn:admin3_code":"00NS005",
    "gn:asciiname":"Treffynnon",
    "gn:cc2":"GB",
    "gn:country_code":"GB",
    "gn:dem":111,
    "gn:feature_class":"P",
    "gn:feature_code":"PPL",
    "gn:name":"Treffynnon",
    "gn:population":0,
    "gn:timezone":"Europe/London",
    "iso:country":"GB",
    "name:und_x_variant":[
        "Treffynon",
        "Treffynnon"
    ],
    "wof:name":"Treffynnon",
    "wof:placetype":"neighbourhood"
},
  "geometry": {"coordinates":[-5.12694,51.91472],"type":"Point"}
}