{
  "type": "Feature",
  "properties": {
    "gn:gn_country":"GB",
    "gn:gn_fcode":"PPL",
    "gn:gn_pop":1449,
    "gn:population":1449,
    "iso:country":"GB",
    "name:ara_x_preferred":[
        "\u0628\u0644\u0632\u064a\u062b"
    ],
    "name:bul_x_preferred":[
        "\u041f\u043e\u043b\u0437\u0435\u0430\u0442\u0445"
    ],
    "name:chi_x_preferred":[
        "\u6ce2\u723e\u9f4a\u601d"
    ],
    "name:dut_x_preferred":[
        "Polzeath"
    ],
    "name:eng_x_preferred":[
        "Polzeath"
    ],
    "name:fre_x_preferred":[
        "Polzeath"
    ],
    "name:ita_x_preferred":[
        "Polzeath"
    ],
    "name:pol_x_preferred":[
        "Polzeath"
    ],
    "name:swe_x_preferred":[
        "Polzeath"
    ],
    "name:wel_x_preferred":[
        "Polzeath"
    ],
    "qs_pg:aaroncc":"GB",
    "qs_pg:gn_country":"GB",
    "qs_pg:gn_fcode":"PPL",
    "qs_pg:gn_pop":1449,
    "qs_pg:name":"Polzeath",
    "qs_pg:name_adm0":"United Kingdom",
    "qs_pg:name_adm1":"England",
    "qs_pg:photos":701,
    "qs_pg:photos_1k":142,
    "qs_pg:photos_9k":3,
    "qs_pg:photos_9r":5,
    "qs_pg:photos_all":701,
    "qs_pg:photos_sr":8,
    "qs_pg:pop_sr":3,
    "qs_pg:qs_pg_placetype":"locality",
    "qs_pg:qs_pg_placetype_gp":"Town",
    "qs_pg:woe_adm0":23424975,
    "woe:adm0_id":23424975,
    "woe:name_adm0":"United Kingdom",
    "woe:name_adm1":"England",
    "woe:placetype":"Town",
    "wof:name":"Polzeath",
    "wof:placetype":"neighbourhood",
    "wof:population":1449
},
  "geometry": {"coordinates":[-4.91759,50.56956],"type":"Point"}
}