{
  "type": "Feature",
  "properties": {
    "gn:country":"GB",
    "gn:fcode":"PPL",
    "gn:population":1449,
    "iso:country":"GB",
    "name:ara_x_preferred":[
        "\u0628\u0644\u0632\u064a\u062b"
    ],
    "name:arz_x_preferred":[
        "\u0628\u0644\u0632\u064a\u062b"
    ],
    "name:bul_x_preferred":[
        "\u041f\u043e\u043b\u0437\u0435\u0430\u0442\u0445"
    ],
    "name:ceb_x_preferred":[
        "Polzeath"
    ],
    "name:cor_x_preferred":[
        "Pollsygh"
    ],
    "name:cym_x_preferred":[
        "Polzeath"
    ],
    "name:cym_x_variant":[
        "Pollsygh"
    ],
    "name:eng_x_preferred":[
        "Polzeath"
    ],
    "name:eus_x_preferred":[
        "Polzeath"
    ],
    "name:fas_x_preferred":[
        "\u067e\u0644\u0632\u06cc\u062b"
    ],
    "name:fra_x_preferred":[
        "Polzeath"
    ],
    "name:gle_x_preferred":[
        "Polzeath"
    ],
    "name:ita_x_preferred":[
        "Polzeath"
    ],
    "name:jpn_x_preferred":[
        "\u30dd\u30eb\u30c4\u30a7\u30b9"
    ],
    "name:nld_x_preferred":[
        "Polzeath"
    ],
    "name:pol_x_preferred":[
        "Polzeath"
    ],
    "name:swe_x_preferred":[
        "Polzeath"
    ],
    "name:tha_x_preferred":[
        "\u0e1e\u0e2d\u0e25\u0e41\u0e0b\u0e47\u0e18"
    ],
    "name:zho_x_preferred":[
        "\u6ce2\u723e\u9f4a\u601d"
    ],
    "qs_pg:aaroncc":"GB",
    "qs_pg:gn_country":"GB",
    "qs_pg:gn_fcode":"PPL",
    "qs_pg:gn_pop":1449,
    "qs_pg:name":"Polzeath",
    "qs_pg:name_adm0":"United Kingdom",
    "qs_pg:name_adm1":"England",
    "qs_pg:photos":701,
    "qs_pg:photos_1k":142,
    "qs_pg:photos_9k":3,
    "qs_pg:photos_9r":5,
    "qs_pg:photos_all":701,
    "qs_pg:photos_sr":8,
    "qs_pg:pop_sr":3,
    "qs_pg:qs_pg_placetype":"locality",
    "qs_pg:qs_pg_placetype_gp":"Town",
    "qs_pg:woe_adm0":23424975,
    "woe:adm0_id":23424975,
    "woe:name_adm0":"United Kingdom",
    "woe:name_adm1":"England",
    "woe:placetype":"Town",
    "wof:name":"Polzeath",
    "wof:placetype":"neighbourhood",
    "wof:population":1449
},
  "geometry": {"coordinates":[-4.91759,50.56956],"type":"Point"}
}