{
  "type": "Feature",
  "properties": {
    "iso:country": "GB",
    "wof:name": "Ferncliffe",
    "wof:placetype": "neighbourhood"
  },
  "geometry": {"coordinates":[-1.82646977577526,53.84837180979124],"type":"Point"}
}
