{
  "type": "Feature",
  "properties": {
    "gn:country": "GB",
    "gn:fcode": "PPL",
    "gn:population": 0,
    "iso:country": "GB",
    "name:ceb_x_preferred": [
      "Auchencairn"
    ],
    "name:eng_x_preferred": [
      "Auchencairn"
    ],
    "name:eus_x_preferred": [
      "Auchencairn"
    ],
    "name:fra_x_preferred": [
      "Auchencairn"
    ],
    "name:gla_x_preferred": [
      "Achadh nan Càrn"
    ],
    "name:gle_x_preferred": [
      "Achadh an Cáirn"
    ],
    "name:nld_x_preferred": [
      "Auchencairn"
    ],
    "name:rus_x_preferred": [
      "Ошенкерн"
    ],
    "name:swe_x_preferred": [
      "Auchencairn"
    ],
    "qs_pg:aaroncc": "GB",
    "qs_pg:gn_country": "GB",
    "qs_pg:gn_fcode": "PPL",
    "qs_pg:gn_pop": 0,
    "qs_pg:name": "Auchencairn",
    "qs_pg:name_adm0": "United Kingdom",
    "qs_pg:name_adm1": "Scotland",
    "qs_pg:photos": 65,
    "qs_pg:photos_1k": 13,
    "qs_pg:photos_9k": 1,
    "qs_pg:photos_9r": 2,
    "qs_pg:photos_all": 65,
    "qs_pg:photos_sr": 2,
    "qs_pg:pop_sr": 0,
    "qs_pg:qs_pg_placetype": "locality",
    "qs_pg:qs_pg_placetype_gp": "Town",
    "qs_pg:woe_adm0": 23424975,
    "woe:adm0_id": 23424975,
    "woe:name_adm0": "United Kingdom",
    "woe:name_adm1": "Scotland",
    "woe:placetype": "Town",
    "wof:name": "Auchencairn",
    "wof:placetype": "locality"
  },
  "geometry": {"coordinates":[-3.87296,54.84177],"type":"Point"}
}
