{
  "type": "Feature",
  "properties": {
    "gn:gn_country":"GB",
    "gn:gn_fcode":"PPL",
    "gn:gn_pop":0,
    "iso:country":"GB",
    "name:eng_x_preferred":[
        "Auchencairn"
    ],
    "name:fra_x_preferred":[
        "Auchencairn"
    ],
    "name:gla_x_preferred":[
        "Achadh nan C\u00e0rn"
    ],
    "name:gle_x_preferred":[
        "Achadh an C\u00e1irn"
    ],
    "name:nld_x_preferred":[
        "Auchencairn"
    ],
    "name:rus_x_preferred":[
        "\u041e\u0448\u0435\u043d\u043a\u0435\u0440\u043d"
    ],
    "name:swe_x_preferred":[
        "Auchencairn"
    ],
    "qs_pg:aaroncc":"GB",
    "qs_pg:gn_country":"GB",
    "qs_pg:gn_fcode":"PPL",
    "qs_pg:gn_pop":0,
    "qs_pg:name":"Auchencairn",
    "qs_pg:name_adm0":"United Kingdom",
    "qs_pg:name_adm1":"Scotland",
    "qs_pg:photos":65,
    "qs_pg:photos_1k":13,
    "qs_pg:photos_9k":1,
    "qs_pg:photos_9r":2,
    "qs_pg:photos_all":65,
    "qs_pg:photos_sr":2,
    "qs_pg:pop_sr":0,
    "qs_pg:qs_pg_placetype":"locality",
    "qs_pg:qs_pg_placetype_gp":"Town",
    "qs_pg:woe_adm0":23424975,
    "woe:adm0_id":23424975,
    "woe:name_adm0":"United Kingdom",
    "woe:name_adm1":"Scotland",
    "woe:placetype":"Town",
    "wof:name":"Auchencairn",
    "wof:placetype":"locality"
},
  "geometry": {"coordinates":[-3.87296,54.84177],"type":"Point"}
}