{
  "type": "Feature",
  "properties": {
    "iso:country":"GB",
    "name:ara_x_preferred":[
        "\u0627\u0633\u062a\u0645\u0648\u0631"
    ],
    "name:arz_x_preferred":[
        "\u0627\u0633\u062a\u0645\u0648\u0631"
    ],
    "name:cym_x_preferred":[
        "Astmoor"
    ],
    "name:eng_x_preferred":[
        "Astmoor"
    ],
    "name:fra_x_preferred":[
        "Astmoor"
    ],
    "name:gle_x_preferred":[
        "Astmoor"
    ],
    "name:nld_x_preferred":[
        "Astmoor"
    ],
    "qs_pg:aaroncc":"GB",
    "qs_pg:name":"Astmoor",
    "qs_pg:name_adm0":"United Kingdom",
    "qs_pg:name_adm1":"England",
    "qs_pg:photos":15,
    "qs_pg:photos_1k":3,
    "qs_pg:photos_9k":1,
    "qs_pg:photos_9r":1,
    "qs_pg:photos_all":15,
    "qs_pg:photos_sr":1,
    "qs_pg:pop_sr":0,
    "qs_pg:qs_pg_placetype":"locality",
    "qs_pg:qs_pg_placetype_gp":"Town",
    "qs_pg:woe_adm0":23424975,
    "woe:adm0_id":23424975,
    "woe:name_adm0":"United Kingdom",
    "woe:name_adm1":"England",
    "woe:placetype":"Town",
    "wof:name":"Astmoor",
    "wof:placetype":"neighbourhood"
},
  "geometry": {"coordinates":[-2.696542,53.351371],"type":"Point"}
}