{
  "type": "Feature",
  "properties": {
    "iso:country": "GB",
    "name:eng_x_preferred": [
      "Grotton"
    ],
    "name:fra_x_preferred": [
      "Grotton"
    ],
    "name:nld_x_preferred": [
      "Grotton"
    ],
    "qs:gn_local": 0,
    "qs:local_max": 2114,
    "qs:local_sum": 4721,
    "qs:localhoods": 7,
    "qs:name": "Grotton",
    "qs:name_adm0": "United Kingdom",
    "qs:name_adm1": "England",
    "qs:name_adm2": "Greater Manchester",
    "qs:name_lau": "Oldham Metropolitan Borough",
    "qs:name_local": "Oldham",
    "qs:photo_max": 150,
    "qs:photo_sum": 998,
    "qs:placetype": "Suburb",
    "qs:quad_count": 105,
    "qs:woe_adm0": 23424975,
    "qs:woe_adm1": 24554868,
    "qs:woe_adm2": 12602158,
    "qs:woe_lau": 12695842,
    "qs:woe_local": 31017,
    "qs:woe_ver": "7.10.0",
    "wd:wordcount": 392,
    "wof:lang": [
      "eng"
    ],
    "wof:name": "Grotton",
    "wof:placetype": "neighbourhood"
  },
  "geometry": {"coordinates":[-2.034201,53.545771],"type":"Point"}
}
