{
  "type": "Feature",
  "properties": {
    "iso:country":"GB",
    "name:cym_x_preferred":[
        "Haughton-le-Skerne"
    ],
    "name:eng_x_preferred":[
        "Haughton le Skerne"
    ],
    "name:eng_x_variant":[
        "Houghton-le-Skerne"
    ],
    "name:pol_x_preferred":[
        "Haughton-le-Skerne"
    ],
    "name:unk_x_variant":[
        "Houghton-le-Skerne",
        "Haughton le Skerne"
    ],
    "qs:gn_adm0_cc":"GB",
    "qs:gn_fcode":"PPL",
    "qs:gn_local":2649676,
    "qs:gn_nam_loc":"skellow",
    "qs:gn_namadm1":"ENG",
    "qs:gn_name":"Haughton le Skerne",
    "qs:local_max":2319,
    "qs:local_sum":4115,
    "qs:localhoods":3,
    "qs:name":"Haughton le Skerne",
    "qs:name_adm0":"United Kingdom",
    "qs:name_adm1":"England",
    "qs:name_adm2":"County Durham",
    "qs:name_lau":"Darlington Borough",
    "qs:name_local":"Darlington",
    "qs:photo_max":47,
    "qs:photo_sum":429,
    "qs:placetype":"Suburb",
    "qs:quad_count":49,
    "qs:woe_adm0":23424975,
    "qs:woe_adm1":24554868,
    "qs:woe_adm2":12602150,
    "qs:woe_lau":12696152,
    "qs:woe_local":17940,
    "qs:woe_ver":"7.10.0",
    "wd:wordcount":235,
    "wof:lang":[
        "eng"
    ],
    "wof:name":"Haughton le Skerne",
    "wof:placetype":"neighbourhood"
},
  "geometry": {"coordinates":[-1.521891,54.531891],"type":"Point"}
}