{
  "type": "Feature",
  "properties": {
    "gn:country":"GB",
    "gn:fcode":"PPL",
    "gn:population":0,
    "iso:country":"GB",
    "name:cym_x_preferred":[
        "Canford Magna"
    ],
    "name:eng_x_preferred":[
        "Canford Magna"
    ],
    "name:fra_x_preferred":[
        "Canford Magna"
    ],
    "name:nld_x_preferred":[
        "Canford Magna"
    ],
    "name:pol_x_preferred":[
        "Canford Magna"
    ],
    "qs_pg:aaroncc":"GB",
    "qs_pg:gn_country":"GB",
    "qs_pg:gn_fcode":"PPL",
    "qs_pg:gn_pop":0,
    "qs_pg:name":"Canford Magna",
    "qs_pg:name_adm0":"United Kingdom",
    "qs_pg:name_adm1":"England",
    "qs_pg:photos":713,
    "qs_pg:photos_1k":144,
    "qs_pg:photos_9k":3,
    "qs_pg:photos_9r":5,
    "qs_pg:photos_all":713,
    "qs_pg:photos_sr":8,
    "qs_pg:pop_sr":0,
    "qs_pg:qs_pg_placetype":"locality",
    "qs_pg:qs_pg_placetype_gp":"Town",
    "qs_pg:woe_adm0":23424975,
    "woe:adm0_id":23424975,
    "woe:name_adm0":"United Kingdom",
    "woe:name_adm1":"England",
    "woe:placetype":"Town",
    "wof:name":"Canford Magna",
    "wof:placetype":"neighbourhood"
},
  "geometry": {"coordinates":[-1.95555,50.78409],"type":"Point"}
}