{
  "type": "Feature",
  "properties": {
    "gn:country":"GB",
    "iso:country":"GB",
    "name:cor_x_preferred":[
        "Ros"
    ],
    "name:cym_x_preferred":[
        "Rose"
    ],
    "name:eng_x_preferred":[
        "Rose"
    ],
    "name:eus_x_preferred":[
        "Rose"
    ],
    "name:fra_x_preferred":[
        "Rose"
    ],
    "name:nld_x_preferred":[
        "Rose"
    ],
    "qs_pg:aaroncc":"GB",
    "qs_pg:gn_country":"GB",
    "qs_pg:name":"Rose",
    "qs_pg:name_adm0":"United Kingdom",
    "qs_pg:name_adm1":"England",
    "qs_pg:photos":472,
    "qs_pg:photos_1k":96,
    "qs_pg:photos_9k":2,
    "qs_pg:photos_9r":5,
    "qs_pg:photos_all":472,
    "qs_pg:photos_sr":7,
    "qs_pg:pop_sr":0,
    "qs_pg:qs_pg_placetype":"locality",
    "qs_pg:qs_pg_placetype_gp":"Town",
    "qs_pg:woe_adm0":23424975,
    "woe:adm0_id":23424975,
    "woe:name_adm0":"United Kingdom",
    "woe:name_adm1":"England",
    "woe:placetype":"Town",
    "wof:name":"Rose",
    "wof:placetype":"neighbourhood"
},
  "geometry": {"coordinates":[-5.148982,50.365065],"type":"Point"}
}