{
  "type": "Feature",
  "properties": {
    "iso:country":"GB",
    "name:ara_x_preferred":[
        "\u0628\u062f\u064a\u0648"
    ],
    "name:cym_x_preferred":[
        "Bodieve"
    ],
    "name:eng_x_preferred":[
        "Bodieve"
    ],
    "name:eus_x_preferred":[
        "Bodieve"
    ],
    "name:fra_x_preferred":[
        "Bodieve"
    ],
    "name:nld_x_preferred":[
        "Bodieve"
    ],
    "name:pol_x_preferred":[
        "Bodieve"
    ],
    "qs_pg:aaroncc":"GB",
    "qs_pg:name":"Bodieve",
    "qs_pg:name_adm0":"United Kingdom",
    "qs_pg:name_adm1":"England",
    "qs_pg:photos":35,
    "qs_pg:photos_1k":7,
    "qs_pg:photos_9k":1,
    "qs_pg:photos_9r":2,
    "qs_pg:photos_all":35,
    "qs_pg:photos_sr":2,
    "qs_pg:pop_sr":0,
    "qs_pg:qs_pg_placetype":"locality",
    "qs_pg:qs_pg_placetype_gp":"Town",
    "qs_pg:woe_adm0":23424975,
    "woe:adm0_id":23424975,
    "woe:name_adm0":"United Kingdom",
    "woe:name_adm1":"England",
    "woe:placetype":"Town",
    "wof:name":"Bodieve",
    "wof:placetype":"neighbourhood"
},
  "geometry": {"coordinates":[-4.834156,50.523358],"type":"Point"}
}