{
  "type": "Feature",
  "properties": {
    "iso:country":"GB",
    "name:cym_x_preferred":[
        "Elton"
    ],
    "name:eng_x_preferred":[
        "Elton"
    ],
    "name:nld_x_preferred":[
        "Elton"
    ],
    "name:pol_x_preferred":[
        "Elton"
    ],
    "qs:gn_fcode":"PPLX",
    "qs:gn_local":0,
    "qs:gn_namadm1":"ENG",
    "qs:gn_name":"Elton",
    "qs:local_max":5064,
    "qs:local_sum":5747,
    "qs:localhoods":2,
    "qs:name":"Elton",
    "qs:name_adm0":"United Kingdom",
    "qs:name_adm1":"England",
    "qs:name_adm2":"Greater Manchester",
    "qs:name_lau":"Bury Metropolitan Borough",
    "qs:name_local":"Bury",
    "qs:photo_max":1709,
    "qs:photo_sum":5064,
    "qs:placetype":"Suburb",
    "qs:quad_count":123,
    "qs:woe_adm0":23424975,
    "qs:woe_adm1":24554868,
    "qs:woe_adm2":12602158,
    "qs:woe_lau":12695840,
    "qs:woe_local":14711,
    "qs:woe_ver":"7.10.0",
    "wof:lang":[
        "eng"
    ],
    "wof:name":"Elton",
    "wof:placetype":"neighbourhood"
},
  "geometry": {"coordinates":[-2.30401,53.593241],"type":"Point"}
}