{
  "type": "Feature",
  "properties": {
    "gn:admin1_code": "ENG",
    "gn:admin2_code": "P3",
    "gn:admin3_code": "44UE",
    "gn:admin4_code": "44UE079",
    "gn:asciiname": "Abbot's Salford",
    "gn:country_code": "GB",
    "gn:dem": 35,
    "gn:feature_class": "P",
    "gn:feature_code": "PPL",
    "gn:name": "Abbot's Salford",
    "gn:population": 0,
    "gn:timezone": "Europe/London",
    "iso:country": "GB",
    "name:pol_x_preferred": [
      "Abbot's Salford"
    ],
    "wof:name": "Abbot's Salford",
    "wof:placetype": "neighbourhood"
  },
  "geometry": {"coordinates":[-1.90149,52.15058],"type":"Point"}
}
