{
  "type": "Feature",
  "properties": {
    "gn:country":"GB",
    "iso:country":"GB",
    "qs_pg:aaroncc":"GB",
    "qs_pg:gn_country":"GB",
    "qs_pg:name":"Walney",
    "qs_pg:name_adm0":"United Kingdom",
    "qs_pg:name_adm1":"England",
    "qs_pg:photos":832,
    "qs_pg:photos_1k":169,
    "qs_pg:photos_9k":4,
    "qs_pg:photos_9r":6,
    "qs_pg:photos_all":832,
    "qs_pg:photos_sr":9,
    "qs_pg:pop_sr":0,
    "qs_pg:qs_pg_placetype":"locality",
    "qs_pg:qs_pg_placetype_gp":"Town",
    "qs_pg:woe_adm0":23424975,
    "woe:adm0_id":23424975,
    "woe:name_adm0":"United Kingdom",
    "woe:name_adm1":"England",
    "woe:placetype":"Town",
    "wof:name":"Walney",
    "wof:placetype":"neighbourhood"
},
  "geometry": {"coordinates":[-3.267574,54.1166575],"type":"Point"}
}