{
  "type": "Feature",
  "properties": {
    "gn:gn_country":"GB",
    "gn:gn_fcode":"PPL",
    "gn:gn_pop":0,
    "iso:country":"GB",
    "name:deu_x_preferred":[
        "Portencross"
    ],
    "name:eng_x_preferred":[
        "Portencross"
    ],
    "name:fra_x_preferred":[
        "Portencross"
    ],
    "name:gla_x_preferred":[
        "Port na Coise"
    ],
    "name:gle_x_preferred":[
        "Port na Crois"
    ],
    "name:nld_x_preferred":[
        "Portencross"
    ],
    "name:sco_x_preferred":[
        "Portencross"
    ],
    "name:unk_x_variant":[
        "Portna Cross"
    ],
    "qs_pg:aaroncc":"GB",
    "qs_pg:gn_country":"GB",
    "qs_pg:gn_fcode":"PPL",
    "qs_pg:gn_pop":0,
    "qs_pg:name":"Portencross",
    "qs_pg:name_adm0":"United Kingdom",
    "qs_pg:name_adm1":"Scotland",
    "qs_pg:photos":1609,
    "qs_pg:photos_1k":326,
    "qs_pg:photos_9k":7,
    "qs_pg:photos_9r":8,
    "qs_pg:photos_all":1609,
    "qs_pg:photos_sr":13,
    "qs_pg:pop_sr":0,
    "qs_pg:qs_pg_placetype":"locality",
    "qs_pg:qs_pg_placetype_gp":"Town",
    "qs_pg:woe_adm0":23424975,
    "woe:adm0_id":23424975,
    "woe:name_adm0":"United Kingdom",
    "woe:name_adm1":"Scotland",
    "woe:placetype":"Town",
    "wof:name":"Portencross",
    "wof:placetype":"locality"
},
  "geometry": {"coordinates":[-4.90313,55.69974],"type":"Point"}
}