{
  "type": "Feature",
  "properties": {
    "iso:country":"GB",
    "name:ceb_x_preferred":[
        "Long Compton"
    ],
    "name:pol_x_preferred":[
        "Long Compton"
    ],
    "name:spa_x_preferred":[
        "Long Compton"
    ],
    "name:swe_x_preferred":[
        "Long Compton"
    ],
    "qs_pg:aaroncc":"GB",
    "qs_pg:name":"Long Compton",
    "qs_pg:name_adm0":"United Kingdom",
    "qs_pg:name_adm1":"England",
    "qs_pg:photos":7,
    "qs_pg:photos_1k":1,
    "qs_pg:photos_9k":1,
    "qs_pg:photos_9r":1,
    "qs_pg:photos_all":7,
    "qs_pg:photos_sr":1,
    "qs_pg:pop_sr":0,
    "qs_pg:qs_pg_placetype":"locality",
    "qs_pg:qs_pg_placetype_gp":"Town",
    "qs_pg:woe_adm0":23424975,
    "woe:adm0_id":23424975,
    "woe:name_adm0":"United Kingdom",
    "woe:name_adm1":"England",
    "woe:placetype":"Town",
    "wof:name":"Long Compton",
    "wof:placetype":"neighbourhood"
},
  "geometry": {"coordinates":[-2.204834,52.796333],"type":"Point"}
}