{
  "type": "Feature",
  "properties": {
    "iso:country":"GB",
    "name:eng_x_preferred":[
        "Neville's Cross"
    ],
    "name:fra_x_preferred":[
        "Neville's Cross"
    ],
    "name:hye_x_preferred":[
        "\u0546\u0587\u056b\u056c\u056b \u056d\u0561\u0579"
    ],
    "name:jpn_x_preferred":[
        "\u30cd\u30f4\u30a3\u30eb\u30ba\u30fb\u30af\u30ed\u30b9"
    ],
    "qs_pg:aaroncc":"GB",
    "qs_pg:name":"Nevilles Cross",
    "qs_pg:name_adm0":"United Kingdom",
    "qs_pg:name_adm1":"England",
    "qs_pg:photos":429,
    "qs_pg:photos_1k":87,
    "qs_pg:photos_9k":2,
    "qs_pg:photos_9r":5,
    "qs_pg:photos_all":429,
    "qs_pg:photos_sr":6,
    "qs_pg:pop_sr":0,
    "qs_pg:qs_pg_placetype":"locality",
    "qs_pg:qs_pg_placetype_gp":"Town",
    "qs_pg:woe_adm0":23424975,
    "woe:adm0_id":23424975,
    "woe:name_adm0":"United Kingdom",
    "woe:name_adm1":"England",
    "woe:placetype":"Town",
    "wof:name":"Nevilles Cross",
    "wof:placetype":"neighbourhood"
},
  "geometry": {"coordinates":[-1.577653,54.767226],"type":"Point"}
}