{
  "type": "Feature",
  "properties": {
    "gn:admin1_code":"WLS",
    "gn:admin2_code":"X7",
    "gn:admin3_code":"00NU032",
    "gn:asciiname":"Trostre",
    "gn:country_code":"GB",
    "gn:dem":6,
    "gn:feature_class":"P",
    "gn:feature_code":"PPL",
    "gn:name":"Trostre",
    "gn:population":0,
    "gn:timezone":"Europe/London",
    "iso:country":"GB",
    "wof:name":"Trostre",
    "wof:placetype":"neighbourhood"
},
  "geometry": {"coordinates":[-4.13667,51.67598],"type":"Point"}
}