{
  "type": "Feature",
  "properties": {
    "gn:country": "GB",
    "gn:fcode": "PPL",
    "gn:population": 3835,
    "iso:country": "GB",
    "name:ceb_x_preferred": [
      "Linthwaite"
    ],
    "name:eng_x_preferred": [
      "Linthwaite"
    ],
    "name:fra_x_preferred": [
      "Linthwaite"
    ],
    "name:nld_x_preferred": [
      "Linthwaite"
    ],
    "name:pol_x_preferred": [
      "Linthwaite"
    ],
    "name:swe_x_preferred": [
      "Linthwaite"
    ],
    "qs_pg:aaroncc": "GB",
    "qs_pg:gn_country": "GB",
    "qs_pg:gn_fcode": "PPL",
    "qs_pg:gn_pop": 3835,
    "qs_pg:name": "Swinithwaite",
    "qs_pg:name_adm0": "United Kingdom",
    "qs_pg:name_adm1": "England",
    "qs_pg:photos": 102,
    "qs_pg:photos_1k": 21,
    "qs_pg:photos_9k": 1,
    "qs_pg:photos_9r": 3,
    "qs_pg:photos_all": 102,
    "qs_pg:photos_sr": 3,
    "qs_pg:pop_sr": 4,
    "qs_pg:qs_pg_placetype": "locality",
    "qs_pg:qs_pg_placetype_gp": "Town",
    "qs_pg:woe_adm0": 23424975,
    "woe:adm0_id": 23424975,
    "woe:name_adm0": "United Kingdom",
    "woe:name_adm1": "England",
    "woe:placetype": "Town",
    "wof:name": "Swinithwaite",
    "wof:placetype": "neighbourhood",
    "wof:population": 3835
  },
  "geometry": {"coordinates":[-1.85017,53.62418],"type":"Point"}
}
