{
  "type": "Feature",
  "properties": {
    "gn:admin1_code": "ENG",
    "gn:admin2_code": "Z6",
    "gn:admin3_code": "00KC035",
    "gn:asciiname": "How End",
    "gn:country_code": "GB",
    "gn:dem": 54,
    "gn:elevation": "53.0",
    "gn:feature_class": "P",
    "gn:feature_code": "PPL",
    "gn:name": "How End",
    "gn:population": 0,
    "gn:timezone": "Europe/London",
    "iso:country": "GB",
    "name:ara_x_preferred": [
      "آاو اند"
    ],
    "name:cym_x_preferred": [
      "How End"
    ],
    "name:fas_x_preferred": [
      "هاو اند"
    ],
    "name:fra_x_preferred": [
      "How End"
    ],
    "name:pol_x_preferred": [
      "How End"
    ],
    "wof:name": "How End",
    "wof:placetype": "neighbourhood"
  },
  "geometry": {"coordinates":[-0.49511,52.05589000000001],"type":"Point"}
}
