{
  "type": "Feature",
  "properties": {
    "gn:country":"GB",
    "gn:fcode":"PPL",
    "gn:population":0,
    "iso:country":"GB",
    "name:ara_x_preferred":[
        "\u0647\u0627\u0631\u063a\u0631\u064a\u0641"
    ],
    "name:arz_x_preferred":[
        "\u0647\u0627\u0631\u062c\u0631\u064a\u0641"
    ],
    "name:cym_x_preferred":[
        "Hargrave"
    ],
    "name:eng_x_preferred":[
        "Hargrave"
    ],
    "name:fra_x_preferred":[
        "Hargrave"
    ],
    "name:gle_x_preferred":[
        "Hargrave"
    ],
    "name:nld_x_preferred":[
        "Hargrave"
    ],
    "name:pol_x_preferred":[
        "Hargrave"
    ],
    "qs_pg:aaroncc":"GB",
    "qs_pg:gn_country":"GB",
    "qs_pg:gn_fcode":"PPL",
    "qs_pg:gn_pop":0,
    "qs_pg:name":"Hargrave",
    "qs_pg:name_adm0":"United Kingdom",
    "qs_pg:name_adm1":"England",
    "qs_pg:photos":48,
    "qs_pg:photos_1k":10,
    "qs_pg:photos_9k":1,
    "qs_pg:photos_9r":2,
    "qs_pg:photos_all":48,
    "qs_pg:photos_sr":2,
    "qs_pg:pop_sr":0,
    "qs_pg:qs_pg_placetype":"locality",
    "qs_pg:qs_pg_placetype_gp":"Town",
    "qs_pg:woe_adm0":23424975,
    "woe:adm0_id":23424975,
    "woe:name_adm0":"United Kingdom",
    "woe:name_adm1":"England",
    "woe:placetype":"Town",
    "wof:name":"Hargrave",
    "wof:placetype":"neighbourhood"
},
  "geometry": {"coordinates":[-2.76667,53.15],"type":"Point"}
}