{
  "type": "Feature",
  "properties": {
    "gn:country": "GB",
    "gn:fcode": "PPL",
    "gn:population": 1873,
    "iso:country": "GB",
    "name:bul_x_preferred": [
      "Гриметхорпе"
    ],
    "name:ceb_x_preferred": [
      "Grimethorpe"
    ],
    "name:eng_x_preferred": [
      "Grimethorpe"
    ],
    "name:fas_x_preferred": [
      "گرایمثورپ"
    ],
    "name:fra_x_preferred": [
      "Grimethorpe"
    ],
    "name:ita_x_preferred": [
      "Grimethorpe"
    ],
    "name:jpn_x_preferred": [
      "グライムソープ"
    ],
    "name:nld_x_preferred": [
      "Grimethorpe"
    ],
    "name:nob_x_preferred": [
      "Grimethorpe"
    ],
    "name:pol_x_preferred": [
      "Grimethorpe"
    ],
    "name:spa_x_preferred": [
      "Grimethorpe"
    ],
    "name:swe_x_preferred": [
      "Grimethorpe"
    ],
    "qs_pg:aaroncc": "GB",
    "qs_pg:gn_country": "GB",
    "qs_pg:gn_fcode": "PPL",
    "qs_pg:gn_pop": 1873,
    "qs_pg:name": "Grimethorpe",
    "qs_pg:name_adm0": "United Kingdom",
    "qs_pg:name_adm1": "England",
    "qs_pg:photos": 159,
    "qs_pg:photos_1k": 32,
    "qs_pg:photos_9k": 1,
    "qs_pg:photos_9r": 4,
    "qs_pg:photos_all": 159,
    "qs_pg:photos_sr": 4,
    "qs_pg:pop_sr": 3,
    "qs_pg:qs_pg_placetype": "locality",
    "qs_pg:qs_pg_placetype_gp": "Town",
    "qs_pg:woe_adm0": 23424975,
    "woe:adm0_id": 23424975,
    "woe:name_adm0": "United Kingdom",
    "woe:name_adm1": "England",
    "woe:placetype": "Town",
    "wof:name": "Grimethorpe",
    "wof:placetype": "neighbourhood",
    "wof:population": 4672
  },
  "geometry": {"coordinates":[-1.37688,53.5765],"type":"Point"}
}
