{
  "type": "Feature",
  "properties": {
    "gn:country":"GB",
    "gn:fcode":"PPL",
    "gn:population":1873,
    "iso:country":"GB",
    "name:bul_x_preferred":[
        "\u0413\u0440\u0438\u043c\u0435\u0442\u0445\u043e\u0440\u043f\u0435"
    ],
    "name:ceb_x_preferred":[
        "Grimethorpe"
    ],
    "name:eng_x_preferred":[
        "Grimethorpe"
    ],
    "name:fas_x_preferred":[
        "\u06af\u0631\u0627\u06cc\u0645\u062b\u0648\u0631\u067e"
    ],
    "name:fra_x_preferred":[
        "Grimethorpe"
    ],
    "name:ita_x_preferred":[
        "Grimethorpe"
    ],
    "name:jpn_x_preferred":[
        "\u30b0\u30e9\u30a4\u30e0\u30bd\u30fc\u30d7"
    ],
    "name:nld_x_preferred":[
        "Grimethorpe"
    ],
    "name:nob_x_preferred":[
        "Grimethorpe"
    ],
    "name:pol_x_preferred":[
        "Grimethorpe"
    ],
    "name:spa_x_preferred":[
        "Grimethorpe"
    ],
    "name:swe_x_preferred":[
        "Grimethorpe"
    ],
    "qs_pg:aaroncc":"GB",
    "qs_pg:gn_country":"GB",
    "qs_pg:gn_fcode":"PPL",
    "qs_pg:gn_pop":1873,
    "qs_pg:name":"Grimethorpe",
    "qs_pg:name_adm0":"United Kingdom",
    "qs_pg:name_adm1":"England",
    "qs_pg:photos":159,
    "qs_pg:photos_1k":32,
    "qs_pg:photos_9k":1,
    "qs_pg:photos_9r":4,
    "qs_pg:photos_all":159,
    "qs_pg:photos_sr":4,
    "qs_pg:pop_sr":3,
    "qs_pg:qs_pg_placetype":"locality",
    "qs_pg:qs_pg_placetype_gp":"Town",
    "qs_pg:woe_adm0":23424975,
    "woe:adm0_id":23424975,
    "woe:name_adm0":"United Kingdom",
    "woe:name_adm1":"England",
    "woe:placetype":"Town",
    "wof:name":"Grimethorpe",
    "wof:placetype":"neighbourhood",
    "wof:population":4672
},
  "geometry": {"coordinates":[-1.37688,53.5765],"type":"Point"}
}