{
  "type": "Feature",
  "properties": {
    "iso:country":"GB",
    "name:eng_x_preferred":[
        "Bishops Wood"
    ],
    "name:fra_x_preferred":[
        "Bishops Wood"
    ],
    "name:nld_x_preferred":[
        "Bishops Wood"
    ],
    "name:pol_x_preferred":[
        "Bishops Wood"
    ],
    "qs_pg:aaroncc":"GB",
    "qs_pg:name":"Bishop's Wood",
    "qs_pg:name_adm0":"United Kingdom",
    "qs_pg:name_adm1":"England",
    "qs_pg:photos":2238,
    "qs_pg:photos_1k":453,
    "qs_pg:photos_9k":10,
    "qs_pg:photos_9r":9,
    "qs_pg:photos_all":2238,
    "qs_pg:photos_sr":16,
    "qs_pg:pop_sr":0,
    "qs_pg:qs_pg_placetype":"locality",
    "qs_pg:qs_pg_placetype_gp":"Town",
    "qs_pg:woe_adm0":23424975,
    "woe:adm0_id":23424975,
    "woe:name_adm0":"United Kingdom",
    "woe:name_adm1":"England",
    "woe:placetype":"Town",
    "wof:name":"Bishop's Wood",
    "wof:placetype":"neighbourhood"
},
  "geometry": {"coordinates":[-2.284126,52.687309],"type":"Point"}
}