{
  "type": "Feature",
  "properties": {
    "iso:country":"GB",
    "name:ceb_x_preferred":[
        "Beacon Hill"
    ],
    "name:deu_x_preferred":[
        "Beacon Hill"
    ],
    "name:fra_x_preferred":[
        "Beacon Hill"
    ],
    "name:ita_x_preferred":[
        "Beacon Hill"
    ],
    "name:kor_x_preferred":[
        "\ube44\ucee8\ud790"
    ],
    "name:rus_x_preferred":[
        "\u0411\u0438\u043a\u043e\u043d-\u0425\u0438\u043b\u043b"
    ],
    "name:swe_x_preferred":[
        "Beacon Hill"
    ],
    "qs_pg:aaroncc":"GB",
    "qs_pg:name":"Beacon Hill",
    "qs_pg:name_adm0":"United Kingdom",
    "qs_pg:name_adm1":"England",
    "qs_pg:photos":41,
    "qs_pg:photos_1k":8,
    "qs_pg:photos_9k":1,
    "qs_pg:photos_9r":2,
    "qs_pg:photos_all":41,
    "qs_pg:photos_sr":2,
    "qs_pg:pop_sr":0,
    "qs_pg:qs_pg_placetype":"locality",
    "qs_pg:qs_pg_placetype_gp":"Town",
    "qs_pg:woe_adm0":23424975,
    "woe:adm0_id":23424975,
    "woe:name_adm0":"United Kingdom",
    "woe:name_adm1":"England",
    "woe:placetype":"Town",
    "wof:name":"Beacon Hill",
    "wof:placetype":"neighbourhood"
},
  "geometry": {"coordinates":[-2.044916,50.752035],"type":"Point"}
}