{
  "type": "Feature",
  "properties": {
    "gn:admin1_code":"WLS",
    "gn:admin2_code":"Y2",
    "gn:admin3_code":"00NC017",
    "gn:asciiname":"Tai'n Lon",
    "gn:country_code":"GB",
    "gn:dem":73,
    "gn:feature_class":"P",
    "gn:feature_code":"PPL",
    "gn:name":"Tai'n Lon",
    "gn:population":0,
    "gn:timezone":"Europe/London",
    "iso:country":"GB",
    "wof:name":"Tai'n Lon",
    "wof:placetype":"neighbourhood"
},
  "geometry": {"coordinates":[-4.32338,53.02529000000001],"type":"Point"}
}