{
  "type": "Feature",
  "properties": {
    "gn:country": "GB",
    "gn:fcode": "PPL",
    "gn:population": 10823,
    "iso:country": "GB",
    "name:deu_x_preferred": [
      "Knowle"
    ],
    "name:nld_x_preferred": [
      "Knowle"
    ],
    "name:pol_x_preferred": [
      "Knowle"
    ],
    "name:swe_x_preferred": [
      "Knowle"
    ],
    "qs_pg:aaroncc": "GB",
    "qs_pg:gn_country": "GB",
    "qs_pg:gn_fcode": "PPL",
    "qs_pg:gn_pop": 10823,
    "qs_pg:name": "Knowle",
    "qs_pg:name_adm0": "United Kingdom",
    "qs_pg:name_adm1": "England",
    "qs_pg:photos": 1146,
    "qs_pg:photos_1k": 232,
    "qs_pg:photos_9k": 5,
    "qs_pg:photos_9r": 7,
    "qs_pg:photos_all": 1146,
    "qs_pg:photos_sr": 11,
    "qs_pg:pop_sr": 6,
    "qs_pg:qs_pg_placetype": "locality",
    "qs_pg:qs_pg_placetype_gp": "Town",
    "qs_pg:woe_adm0": 23424975,
    "woe:adm0_id": 23424975,
    "woe:name_adm0": "United Kingdom",
    "woe:name_adm1": "England",
    "woe:placetype": "Town",
    "wof:name": "Knowle",
    "wof:placetype": "neighbourhood",
    "wof:population": 10823
  },
  "geometry": {"coordinates":[-1.73333,52.38333],"type":"Point"}
}
