{
  "type": "Feature",
  "properties": {
    "iso:country":"GB",
    "name:eng_x_preferred":[
        "Burnt Hill"
    ],
    "name:fra_x_preferred":[
        "Burnt Hill"
    ],
    "name:gle_x_preferred":[
        "Burnt Hill"
    ],
    "name:nld_x_preferred":[
        "Burnt Hill"
    ],
    "qs_pg:aaroncc":"GB",
    "qs_pg:name":"Burnt Hill",
    "qs_pg:name_adm0":"United Kingdom",
    "qs_pg:name_adm1":"England",
    "qs_pg:photos":193,
    "qs_pg:photos_1k":39,
    "qs_pg:photos_9k":1,
    "qs_pg:photos_9r":4,
    "qs_pg:photos_all":193,
    "qs_pg:photos_sr":4,
    "qs_pg:pop_sr":0,
    "qs_pg:qs_pg_placetype":"locality",
    "qs_pg:qs_pg_placetype_gp":"Town",
    "qs_pg:woe_adm0":23424975,
    "woe:adm0_id":23424975,
    "woe:name_adm0":"United Kingdom",
    "woe:name_adm1":"England",
    "woe:placetype":"Town",
    "wof:name":"Burnt Hill",
    "wof:placetype":"neighbourhood"
},
  "geometry": {"coordinates":[-1.203689,51.487957],"type":"Point"}
}