{
  "type": "Feature",
  "properties": {
    "gn:gn_country":"GB",
    "gn:gn_fcode":"PPL",
    "gn:gn_pop":0,
    "gn:population":1846,
    "iso:country":"GB",
    "name:cym_x_preferred":[
        "Ingrave"
    ],
    "name:eng_x_preferred":[
        "Ingrave"
    ],
    "name:fas_x_preferred":[
        "\u0627\u06cc\u0646\u06af\u0631\u06cc\u0648"
    ],
    "name:fra_x_preferred":[
        "Ingrave"
    ],
    "name:ita_x_preferred":[
        "Ingrave"
    ],
    "name:nld_x_preferred":[
        "Ingrave"
    ],
    "name:pol_x_preferred":[
        "Ingrave"
    ],
    "name:spa_x_preferred":[
        "Ingrave"
    ],
    "qs_pg:aaroncc":"GB",
    "qs_pg:gn_country":"GB",
    "qs_pg:gn_fcode":"PPL",
    "qs_pg:gn_pop":0,
    "qs_pg:name":"Ingrave",
    "qs_pg:name_adm0":"United Kingdom",
    "qs_pg:name_adm1":"England",
    "qs_pg:photos_9r":0,
    "qs_pg:photos_sr":0,
    "qs_pg:pop_sr":0,
    "qs_pg:qs_pg_placetype":"locality",
    "qs_pg:qs_pg_placetype_gp":"Town",
    "qs_pg:woe_adm0":23424975,
    "woe:adm0_id":23424975,
    "woe:name_adm0":"United Kingdom",
    "woe:name_adm1":"England",
    "woe:placetype":"Town",
    "wof:name":"Ingrave",
    "wof:placetype":"neighbourhood",
    "wof:population":1846
},
  "geometry": {"coordinates":[0.34058,51.60416],"type":"Point"}
}