{
  "type": "Feature",
  "properties": {
    "gn:admin1_code":"SCT",
    "gn:admin2_code":"V3",
    "gn:asciiname":"Ardshave",
    "gn:country_code":"GB",
    "gn:dem":81,
    "gn:feature_class":"P",
    "gn:feature_code":"PPL",
    "gn:name":"Ardshave",
    "gn:population":0,
    "gn:timezone":"Europe/London",
    "iso:country":"GB",
    "wof:name":"Ardshave",
    "wof:placetype":"locality"
},
  "geometry": {"coordinates":[-4.09026,57.92987],"type":"Point"}
}