{
  "type": "Feature",
  "properties": {
    "iso:country":"GB",
    "name:eng_x_preferred":[
        "Blakenhall Heath"
    ],
    "name:unk_x_variant":[
        "Blakenhall Heath"
    ],
    "qs:gn_local":0,
    "qs:local_max":2515,
    "qs:local_sum":9671,
    "qs:localhoods":12,
    "qs:name":"Blakenhall Heath",
    "qs:name_adm0":"United Kingdom",
    "qs:name_adm1":"England",
    "qs:name_adm2":"West Midlands",
    "qs:name_lau":"Walsall Metropolitan Borough",
    "qs:name_local":"Walsall",
    "qs:photo_max":105,
    "qs:photo_sum":215,
    "qs:placetype":"Suburb",
    "qs:quad_count":23,
    "qs:woe_adm0":23424975,
    "qs:woe_adm1":24554868,
    "qs:woe_adm2":12602191,
    "qs:woe_lau":12695868,
    "qs:woe_local":39052,
    "qs:woe_ver":"7.10.0",
    "wd:wordcount":372,
    "wof:lang":[
        "eng"
    ],
    "wof:name":"Blakenhall Heath",
    "wof:placetype":"neighbourhood"
},
  "geometry": {"coordinates":[-1.995192,52.612845],"type":"Point"}
}