{
  "type": "Feature",
  "properties": {
    "iso:country":"GB",
    "name:cym_x_preferred":[
        "Pwllglas"
    ],
    "name:eng_x_preferred":[
        "Pwllglas"
    ],
    "name:fra_x_preferred":[
        "Pwllglas"
    ],
    "name:nld_x_preferred":[
        "Pwllglas"
    ],
    "qs_pg:aaroncc":"GB",
    "qs_pg:name":"Pwllglas",
    "qs_pg:name_adm0":"United Kingdom",
    "qs_pg:name_adm1":"Wales",
    "qs_pg:photos":17,
    "qs_pg:photos_1k":3,
    "qs_pg:photos_9k":1,
    "qs_pg:photos_9r":1,
    "qs_pg:photos_all":17,
    "qs_pg:photos_sr":1,
    "qs_pg:pop_sr":0,
    "qs_pg:qs_pg_placetype":"locality",
    "qs_pg:qs_pg_placetype_gp":"Town",
    "qs_pg:woe_adm0":23424975,
    "woe:adm0_id":23424975,
    "woe:name_adm0":"United Kingdom",
    "woe:name_adm1":"Wales",
    "woe:placetype":"Town",
    "wof:name":"Pwllglas",
    "wof:placetype":"neighbourhood"
},
  "geometry": {"coordinates":[-3.316154,53.080621],"type":"Point"}
}