{
  "type": "Feature",
  "properties": {
    "iso:country":"GB",
    "name:dut_x_preferred":[
        "Thrupp"
    ],
    "name:eng_x_preferred":[
        "Thrupp"
    ],
    "name:fre_x_preferred":[
        "Thrupp"
    ],
    "name:pol_x_preferred":[
        "Thrupp"
    ],
    "name:swe_x_preferred":[
        "Thrupp"
    ],
    "qs_pg:aaroncc":"GB",
    "qs_pg:name":"Thrupp",
    "qs_pg:name_adm0":"United Kingdom",
    "qs_pg:name_adm1":"England",
    "qs_pg:photos":313,
    "qs_pg:photos_1k":63,
    "qs_pg:photos_9k":1,
    "qs_pg:photos_9r":5,
    "qs_pg:photos_all":313,
    "qs_pg:photos_sr":5,
    "qs_pg:pop_sr":0,
    "qs_pg:qs_pg_placetype":"locality",
    "qs_pg:qs_pg_placetype_gp":"Town",
    "qs_pg:woe_adm0":23424975,
    "woe:adm0_id":23424975,
    "woe:name_adm0":"United Kingdom",
    "woe:name_adm1":"England",
    "woe:placetype":"Town",
    "wof:name":"Thrupp",
    "wof:placetype":"neighbourhood"
},
  "geometry": {"coordinates":[-1.303939,51.839252],"type":"Point"}
}