{
  "type": "Feature",
  "properties": {
    "gn:gn_country":"GB",
    "gn:gn_fcode":"PPL",
    "gn:gn_pop":0,
    "gn:population":1362,
    "iso:country":"GB",
    "name:cym_x_preferred":[
        "Blaengwynfi"
    ],
    "name:eng_x_preferred":[
        "Blaengwynfi"
    ],
    "name:eus_x_preferred":[
        "Blaengwynfi"
    ],
    "name:fra_x_preferred":[
        "Blaengwynfi"
    ],
    "name:nld_x_preferred":[
        "Blaengwynfi"
    ],
    "name:spa_x_preferred":[
        "Blaengwynfi"
    ],
    "qs_pg:aaroncc":"GB",
    "qs_pg:gn_country":"GB",
    "qs_pg:gn_fcode":"PPL",
    "qs_pg:gn_pop":0,
    "qs_pg:name":"Blaengwynfi",
    "qs_pg:name_adm0":"United Kingdom",
    "qs_pg:name_adm1":"Wales",
    "qs_pg:photos":49,
    "qs_pg:photos_1k":10,
    "qs_pg:photos_9k":1,
    "qs_pg:photos_9r":2,
    "qs_pg:photos_all":49,
    "qs_pg:photos_sr":2,
    "qs_pg:pop_sr":0,
    "qs_pg:qs_pg_placetype":"locality",
    "qs_pg:qs_pg_placetype_gp":"Town",
    "qs_pg:woe_adm0":23424975,
    "woe:adm0_id":23424975,
    "woe:name_adm0":"United Kingdom",
    "woe:name_adm1":"Wales",
    "woe:placetype":"Town",
    "wof:name":"Blaengwynfi",
    "wof:placetype":"neighbourhood",
    "wof:population":1362
},
  "geometry": {"coordinates":[-3.60371,51.65623],"type":"Point"}
}