{
  "type": "Feature",
  "properties": {
    "iso:country":"GB",
    "name:ceb_x_preferred":[
        "Stonehouse"
    ],
    "name:deu_x_preferred":[
        "Stonehouse"
    ],
    "name:eng_x_preferred":[
        "Stonehouse"
    ],
    "name:ita_x_preferred":[
        "Stonehouse"
    ],
    "name:pol_x_preferred":[
        "Stonehouse"
    ],
    "name:swe_x_preferred":[
        "Stonehouse"
    ],
    "qs:gn_adm0_cc":"GB",
    "qs:gn_local":2640194,
    "qs:gn_nam_loc":"Plymouth",
    "qs:gn_namadm1":"ENG",
    "qs:local_max":8196,
    "qs:local_sum":38773,
    "qs:localhoods":38,
    "qs:name":"Stonehouse",
    "qs:name_adm0":"United Kingdom",
    "qs:name_adm1":"England",
    "qs:name_adm2":"Devon",
    "qs:name_lau":"Plymouth City",
    "qs:name_local":"Plymouth",
    "qs:photo_max":242,
    "qs:photo_sum":1886,
    "qs:placetype":"Suburb",
    "qs:quad_count":52,
    "qs:woe_adm0":23424975,
    "qs:woe_adm1":24554868,
    "qs:woe_adm2":12602182,
    "qs:woe_lau":12696173,
    "qs:woe_local":32185,
    "qs:woe_ver":"7.10.0",
    "wd:wordcount":77,
    "wof:lang":[
        "eng"
    ],
    "wof:name":"Stonehouse",
    "wof:placetype":"neighbourhood"
},
  "geometry": {"coordinates":[-4.163194,50.364368],"type":"Point"}
}