{
  "type": "Feature",
  "properties": {
    "gn:country":"GB",
    "gn:fcode":"PPL",
    "gn:population":0,
    "iso:country":"GB",
    "name:ceb_x_preferred":[
        "Westmeston"
    ],
    "name:cym_x_preferred":[
        "Westmeston"
    ],
    "name:eng_x_preferred":[
        "Westmeston"
    ],
    "name:fas_x_preferred":[
        "\u0648\u0633\u062a\u0645\u0633\u062a\u0648\u0646"
    ],
    "name:fra_x_preferred":[
        "Westmeston"
    ],
    "name:ita_x_preferred":[
        "Westmeston"
    ],
    "name:nld_x_preferred":[
        "Westmeston"
    ],
    "name:pol_x_preferred":[
        "Westmeston"
    ],
    "name:swe_x_preferred":[
        "Westmeston"
    ],
    "name:swe_x_variant":[
        "Westmeston"
    ],
    "qs_pg:aaroncc":"GB",
    "qs_pg:gn_country":"GB",
    "qs_pg:gn_fcode":"PPL",
    "qs_pg:gn_pop":0,
    "qs_pg:name":"Westerton",
    "qs_pg:name_adm0":"United Kingdom",
    "qs_pg:name_adm1":"England",
    "qs_pg:photos":758,
    "qs_pg:photos_1k":154,
    "qs_pg:photos_9k":3,
    "qs_pg:photos_9r":6,
    "qs_pg:photos_all":758,
    "qs_pg:photos_sr":9,
    "qs_pg:pop_sr":0,
    "qs_pg:qs_pg_placetype":"locality",
    "qs_pg:qs_pg_placetype_gp":"Town",
    "qs_pg:woe_adm0":23424975,
    "woe:adm0_id":23424975,
    "woe:name_adm0":"United Kingdom",
    "woe:name_adm1":"England",
    "woe:placetype":"Town",
    "wof:name":"Westerton",
    "wof:placetype":"neighbourhood"
},
  "geometry": {"coordinates":[-0.09888,50.90693],"type":"Point"}
}