{
  "type": "Feature",
  "properties": {
    "gn:country":"GB",
    "gn:fcode":"PPL",
    "gn:population":0,
    "iso:country":"GB",
    "name:deu_x_preferred":[
        "Gateside"
    ],
    "qs_pg:aaroncc":"GB",
    "qs_pg:gn_country":"GB",
    "qs_pg:gn_fcode":"PPL",
    "qs_pg:gn_pop":0,
    "qs_pg:name":"Gateside",
    "qs_pg:name_adm0":"United Kingdom",
    "qs_pg:name_adm1":"Scotland",
    "qs_pg:photos":663,
    "qs_pg:photos_1k":134,
    "qs_pg:photos_9k":3,
    "qs_pg:photos_9r":5,
    "qs_pg:photos_all":663,
    "qs_pg:photos_sr":8,
    "qs_pg:pop_sr":0,
    "qs_pg:qs_pg_placetype":"locality",
    "qs_pg:qs_pg_placetype_gp":"Town",
    "qs_pg:woe_adm0":23424975,
    "woe:adm0_id":23424975,
    "woe:name_adm0":"United Kingdom",
    "woe:name_adm1":"Scotland",
    "woe:placetype":"Town",
    "wof:name":"Gateside",
    "wof:placetype":"locality"
},
  "geometry": {"coordinates":[-3.31667,56.26667],"type":"Point"}
}