{
  "type": "Feature",
  "properties": {
    "gn:admin1_code":"ENG",
    "gn:admin2_code":"C9",
    "gn:admin3_code":"16UF",
    "gn:admin4_code":"16UF001",
    "gn:asciiname":"Newbiggin",
    "gn:country_code":"GB",
    "gn:dem":183,
    "gn:feature_class":"P",
    "gn:feature_code":"PPL",
    "gn:name":"Newbiggin",
    "gn:population":0,
    "gn:timezone":"Europe/London",
    "iso:country":"GB",
    "name:ceb_x_preferred":[
        "Newbiggin"
    ],
    "name:deu_x_preferred":[
        "Newbiggin"
    ],
    "name:nld_x_preferred":[
        "Newbiggin"
    ],
    "name:pol_x_preferred":[
        "Newbiggin"
    ],
    "name:swe_x_preferred":[
        "Newbiggin"
    ],
    "wof:name":"Newbiggin",
    "wof:placetype":"neighbourhood"
},
  "geometry": {"coordinates":[-2.68333,54.81667],"type":"Point"}
}