{
  "type": "Feature",
  "properties": {
    "iso:country":"GB",
    "name:cym_x_preferred":[
        "Lower Town"
    ],
    "name:fas_x_preferred":[
        "\u0644\u0648\u0648\u0631 \u062a\u0627\u0648\u0646"
    ],
    "name:rus_x_preferred":[
        "\u041b\u043e\u0443\u044d\u0440\u0442\u0430\u0443\u043d"
    ],
    "qs_pg:aaroncc":"GB",
    "qs_pg:name":"Lower Town",
    "qs_pg:name_adm0":"United Kingdom",
    "qs_pg:name_adm1":"Wales",
    "qs_pg:photos":173,
    "qs_pg:photos_1k":35,
    "qs_pg:photos_9k":1,
    "qs_pg:photos_9r":4,
    "qs_pg:photos_all":173,
    "qs_pg:photos_sr":4,
    "qs_pg:pop_sr":0,
    "qs_pg:qs_pg_placetype":"locality",
    "qs_pg:qs_pg_placetype_gp":"Town",
    "qs_pg:woe_adm0":23424975,
    "woe:adm0_id":23424975,
    "woe:name_adm0":"United Kingdom",
    "woe:name_adm1":"Wales",
    "woe:placetype":"Town",
    "wof:name":"Lower Town",
    "wof:placetype":"neighbourhood"
},
  "geometry": {"coordinates":[-4.968981,51.997525],"type":"Point"}
}