{
  "type": "Feature",
  "properties": {
    "iso:country":"GB",
    "name:fra_x_preferred":[
        "Thorncliffe"
    ],
    "qs_pg:aaroncc":"GB",
    "qs_pg:name":"Thorncliffe",
    "qs_pg:name_adm0":"United Kingdom",
    "qs_pg:name_adm1":"England",
    "qs_pg:photos":172,
    "qs_pg:photos_1k":35,
    "qs_pg:photos_9k":1,
    "qs_pg:photos_9r":4,
    "qs_pg:photos_all":172,
    "qs_pg:photos_sr":4,
    "qs_pg:pop_sr":0,
    "qs_pg:qs_pg_placetype":"locality",
    "qs_pg:qs_pg_placetype_gp":"Town",
    "qs_pg:woe_adm0":23424975,
    "woe:adm0_id":23424975,
    "woe:name_adm0":"United Kingdom",
    "woe:name_adm1":"England",
    "woe:placetype":"Town",
    "wof:name":"Thorncliffe",
    "wof:placetype":"neighbourhood"
},
  "geometry": {"coordinates":[-1.95865,53.133583],"type":"Point"}
}