{
  "type": "Feature",
  "properties": {
    "name:eng_x_preferred":[
        "Amblecote"
    ],
    "name:fra_x_preferred":[
        "Amblecote"
    ],
    "name:ita_x_preferred":[
        "Amblecote"
    ],
    "name:nld_x_preferred":[
        "Amblecote"
    ],
    "wd:wordcount":1634,
    "wof:name":"Amblecote",
    "wof:placetype":"neighbourhood"
},
  "geometry": {"coordinates":[-2.15286335951663,52.46405768636929],"type":"Point"}
}