{
  "type": "Feature",
  "properties": {
    "iso:country":"GB",
    "name:cat_x_preferred":[
        "Amblecote"
    ],
    "name:eng_x_preferred":[
        "Amblecote"
    ],
    "name:fra_x_preferred":[
        "Amblecote"
    ],
    "name:gle_x_preferred":[
        "Amblecote"
    ],
    "name:ita_x_preferred":[
        "Amblecote"
    ],
    "name:nld_x_preferred":[
        "Amblecote"
    ],
    "name:pol_x_preferred":[
        "Amblecote"
    ],
    "wd:wordcount":1634,
    "wof:name":"Amblecote",
    "wof:placetype":"neighbourhood"
},
  "geometry": {"coordinates":[-2.152863,52.464058],"type":"Point"}
}