{
  "type": "Feature",
  "properties": {
    "iso:country":"GB",
    "wof:name":"Higher Broughton",
    "wof:placetype":"neighbourhood"
},
  "geometry": {"coordinates":[-2.26132133192324,53.50741637680897],"type":"Point"}
}