{
  "type": "Feature",
  "properties": {
    "gn:country": "GB",
    "gn:fcode": "PPL",
    "gn:population": 0,
    "iso:country": "GB",
    "name:bel_x_preferred": [
      "Прэскат"
    ],
    "name:cat_x_preferred": [
      "Prescott"
    ],
    "name:ceb_x_preferred": [
      "Prescott"
    ],
    "name:ces_x_preferred": [
      "Prescott"
    ],
    "name:deu_x_preferred": [
      "Prescott"
    ],
    "name:fin_x_preferred": [
      "Prescott"
    ],
    "name:fra_x_preferred": [
      "Prescott"
    ],
    "name:hun_x_preferred": [
      "Prescott"
    ],
    "name:ita_x_preferred": [
      "Prescott"
    ],
    "name:jpn_x_preferred": [
      "プレスコット"
    ],
    "name:kor_x_preferred": [
      "프레스콧"
    ],
    "name:nld_x_preferred": [
      "Prescott"
    ],
    "name:pol_x_preferred": [
      "Prescott"
    ],
    "name:por_x_preferred": [
      "Prescott"
    ],
    "name:rus_x_preferred": [
      "Прескотт"
    ],
    "name:spa_x_preferred": [
      "Prescott"
    ],
    "name:srp_x_preferred": [
      "Прескот"
    ],
    "name:swe_x_preferred": [
      "Prescott"
    ],
    "name:vol_x_preferred": [
      "Prescott"
    ],
    "qs_pg:aaroncc": "GB",
    "qs_pg:gn_country": "GB",
    "qs_pg:gn_fcode": "PPL",
    "qs_pg:gn_pop": 0,
    "qs_pg:name": "Prescott",
    "qs_pg:name_adm0": "United Kingdom",
    "qs_pg:name_adm1": "England",
    "qs_pg:photos": 3723,
    "qs_pg:photos_1k": 754,
    "qs_pg:photos_9k": 17,
    "qs_pg:photos_9r": 12,
    "qs_pg:photos_all": 3723,
    "qs_pg:photos_sr": 21,
    "qs_pg:pop_sr": 0,
    "qs_pg:qs_pg_placetype": "locality",
    "qs_pg:qs_pg_placetype_gp": "Town",
    "qs_pg:woe_adm0": 23424975,
    "woe:adm0_id": 23424975,
    "woe:name_adm0": "United Kingdom",
    "woe:name_adm1": "England",
    "woe:placetype": "Town",
    "wof:name": "Prescott",
    "wof:placetype": "neighbourhood"
  },
  "geometry": {"coordinates":[-2.22648,52.57109],"type":"Point"}
}
