{
  "type": "Feature",
  "properties": {
    "gn:gn_country":"GB",
    "iso:country":"GB",
    "name:ceb_x_preferred":[
        "Bruray"
    ],
    "name:fra_x_preferred":[
        "Bruray"
    ],
    "name:gla_x_preferred":[
        "Bruray"
    ],
    "name:heb_x_preferred":[
        "\u05d1\u05e8\u05d5\u05e8\u05d9\u05d9"
    ],
    "name:nld_x_preferred":[
        "Bruray"
    ],
    "name:nno_x_preferred":[
        "Bruray"
    ],
    "name:nor_x_preferred":[
        "Bruray"
    ],
    "name:sco_x_preferred":[
        "Bruray"
    ],
    "name:spa_x_preferred":[
        "Bruray"
    ],
    "name:swe_x_preferred":[
        "Bruray"
    ],
    "name:zho_x_preferred":[
        "\u5e03\u9b6f\u62c9\u5cf6"
    ],
    "qs_pg:aaroncc":"GB",
    "qs_pg:gn_country":"GB",
    "qs_pg:name":"Bruray",
    "qs_pg:name_adm0":"United Kingdom",
    "qs_pg:name_adm1":"Scotland",
    "qs_pg:photos":35,
    "qs_pg:photos_1k":7,
    "qs_pg:photos_9k":1,
    "qs_pg:photos_9r":2,
    "qs_pg:photos_all":35,
    "qs_pg:photos_sr":2,
    "qs_pg:pop_sr":0,
    "qs_pg:qs_pg_placetype":"locality",
    "qs_pg:qs_pg_placetype_gp":"Town",
    "qs_pg:woe_adm0":23424975,
    "woe:adm0_id":23424975,
    "woe:name_adm0":"United Kingdom",
    "woe:name_adm1":"Scotland",
    "woe:placetype":"Town",
    "wof:name":"Bruray",
    "wof:placetype":"locality"
},
  "geometry": {"coordinates":[-0.735139,60.424487],"type":"Point"}
}