{
  "type": "Feature",
  "properties": {
    "gn:admin1_code":"SCT",
    "gn:admin2_code":"V1",
    "gn:asciiname":"Luthrie",
    "gn:country_code":"GB",
    "gn:dem":65,
    "gn:feature_class":"P",
    "gn:feature_code":"PPL",
    "gn:name":"Luthrie",
    "gn:population":0,
    "gn:timezone":"Europe/London",
    "iso:country":"GB",
    "name:eus_x_preferred":[
        "Luthrie"
    ],
    "name:ita_x_preferred":[
        "Luthrie"
    ],
    "wof:name":"Luthrie",
    "wof:placetype":"locality"
},
  "geometry": {"coordinates":[-3.0851,56.36378000000001],"type":"Point"}
}