{
  "type": "Feature",
  "properties": {
    "iso:country": "GB",
    "name:eng_x_preferred": [
      "Ardfernal"
    ],
    "name:eus_x_preferred": [
      "Ardfernal"
    ],
    "name:fra_x_preferred": [
      "Ardfernal"
    ],
    "name:gle_x_preferred": [
      "Áird Fheárnail"
    ],
    "name:nld_x_preferred": [
      "Ardfernal"
    ],
    "qs_pg:aaroncc": "GB",
    "qs_pg:name": "Ardfernal",
    "qs_pg:name_adm0": "United Kingdom",
    "qs_pg:name_adm1": "Scotland",
    "qs_pg:photos": 99,
    "qs_pg:photos_1k": 20,
    "qs_pg:photos_9k": 1,
    "qs_pg:photos_9r": 3,
    "qs_pg:photos_all": 99,
    "qs_pg:photos_sr": 3,
    "qs_pg:pop_sr": 0,
    "qs_pg:qs_pg_placetype": "locality",
    "qs_pg:qs_pg_placetype_gp": "Town",
    "qs_pg:woe_adm0": 23424975,
    "woe:adm0_id": 23424975,
    "woe:name_adm0": "United Kingdom",
    "woe:name_adm1": "Scotland",
    "woe:placetype": "Town",
    "wof:name": "Ardfernal",
    "wof:placetype": "locality"
  },
  "geometry": {"coordinates":[-5.916051,55.875792],"type":"Point"}
}
