{
  "type": "Feature",
  "properties": {
    "gn:admin1_code":"WLS",
    "gn:admin2_code":"Y7",
    "gn:admin3_code":"00NS005",
    "gn:asciiname":"Llanreithan",
    "gn:cc2":"GB",
    "gn:country_code":"GB",
    "gn:dem":115,
    "gn:feature_class":"P",
    "gn:feature_code":"PPL",
    "gn:name":"Llanreithan",
    "gn:population":0,
    "gn:timezone":"Europe/London",
    "iso:country":"GB",
    "name:und_x_variant":[
        "Llanrithan",
        "Llanreithan"
    ],
    "wof:name":"Llanreithan",
    "wof:placetype":"neighbourhood"
},
  "geometry": {"coordinates":[-5.10806,51.91556],"type":"Point"}
}