{
  "type": "Feature",
  "properties": {
    "iso:country":"GB",
    "wof:name":"Tyersal Gate",
    "wof:placetype":"neighbourhood"
},
  "geometry": {"coordinates":[-1.70563441071647,53.78274144598067],"type":"Point"}
}