{
  "type": "Feature",
  "properties": {
    "gn:admin1_code":"WLS",
    "gn:admin2_code":"Y7",
    "gn:admin3_code":"00NS014",
    "gn:asciiname":"Pentre Galar",
    "gn:country_code":"GB",
    "gn:dem":282,
    "gn:feature_class":"P",
    "gn:feature_code":"PPL",
    "gn:name":"Pentre Galar",
    "gn:population":0,
    "gn:timezone":"Europe/London",
    "iso:country":"GB",
    "wof:name":"Pentre Galar",
    "wof:placetype":"neighbourhood"
},
  "geometry": {"coordinates":[-4.65139,51.94917],"type":"Point"}
}