{
  "type": "Feature",
  "properties": {
    "gn:admin1_code":"ENG",
    "gn:admin2_code":"M3",
    "gn:admin3_code":"40UD",
    "gn:admin4_code":"40UD013",
    "gn:asciiname":"South Brewham",
    "gn:cc2":"GB",
    "gn:country_code":"GB",
    "gn:dem":105,
    "gn:feature_class":"P",
    "gn:feature_code":"PPL",
    "gn:name":"South Brewham",
    "gn:population":0,
    "gn:timezone":"Europe/London",
    "iso:country":"GB",
    "name:ceb_x_preferred":[
        "Brewham"
    ],
    "name:ita_x_preferred":[
        "Brewham"
    ],
    "name:nld_x_preferred":[
        "Brewham"
    ],
    "name:pol_x_preferred":[
        "Brewham"
    ],
    "name:swe_x_preferred":[
        "Brewham"
    ],
    "name:und_x_variant":[
        "South Brewham"
    ],
    "wof:name":"South Brewham",
    "wof:placetype":"neighbourhood"
},
  "geometry": {"coordinates":[-2.40167,51.12306],"type":"Point"}
}