{
  "type": "Feature",
  "properties": {
    "gn:population": 5257,
    "iso:country": "GB",
    "name:azb_x_preferred": [
      "وم"
    ],
    "name:ben_x_preferred": [
      "ওয়াম নগর"
    ],
    "name:ceb_x_preferred": [
      "Wem"
    ],
    "name:cym_x_preferred": [
      "Wem"
    ],
    "name:deu_x_preferred": [
      "Wem"
    ],
    "name:eng_x_preferred": [
      "Wem"
    ],
    "name:fas_x_preferred": [
      "وم، شروپ‌شر"
    ],
    "name:fas_x_variant": [
      "وم"
    ],
    "name:fra_x_preferred": [
      "Wem"
    ],
    "name:gle_x_preferred": [
      "Wem"
    ],
    "name:guj_x_preferred": [
      "વેમ"
    ],
    "name:heb_x_preferred": [
      "ום"
    ],
    "name:hun_x_preferred": [
      "Wem"
    ],
    "name:ita_x_preferred": [
      "Wem"
    ],
    "name:jpn_x_preferred": [
      "ウェム・アーバン"
    ],
    "name:kan_x_preferred": [
      "ವೆಮ್"
    ],
    "name:kor_x_preferred": [
      "웸"
    ],
    "name:lit_x_preferred": [
      "Vem Urbanas"
    ],
    "name:nld_x_preferred": [
      "Wem"
    ],
    "name:nno_x_preferred": [
      "Wem"
    ],
    "name:pol_x_preferred": [
      "Wem"
    ],
    "name:por_x_preferred": [
      "Wem"
    ],
    "name:ron_x_preferred": [
      "Wem"
    ],
    "name:rus_x_preferred": [
      "Уэм"
    ],
    "name:spa_x_preferred": [
      "Wem"
    ],
    "name:swe_x_preferred": [
      "Wem"
    ],
    "name:szl_x_preferred": [
      "Wem"
    ],
    "name:tam_x_preferred": [
      "வெம்"
    ],
    "name:tel_x_preferred": [
      "వెమ్"
    ],
    "name:ukr_x_preferred": [
      "Вем"
    ],
    "name:urd_x_preferred": [
      "ویم"
    ],
    "name:vol_x_preferred": [
      "Wem"
    ],
    "name:zho_x_preferred": [
      "韋姆"
    ],
    "qs:a0": "United Kingdom",
    "qs:a1": "*Shropshire",
    "qs:a1_lc": "GB12GG0000",
    "qs:a1r": "0England",
    "qs:a1r_lc": "GB12000000",
    "qs:adm0": "United Kingdom",
    "qs:la_lc": "*",
    "qs:level": "locality",
    "qs:loc": "Wem",
    "qs:loc_alt": "Wem",
    "qs:pop": 0,
    "qs:type": "buffered point",
    "wd:wordcount": 1177,
    "wof:name": "Wem",
    "wof:placetype": "neighbourhood",
    "wof:population": 5257
  },
  "geometry": {"coordinates":[-2.722197,52.856535],"type":"Point"}
}
