{
  "type": "Feature",
  "properties": {
    "gn:admin1_code":"SCT",
    "gn:admin2_code":"V3",
    "gn:asciiname":"Urchany",
    "gn:country_code":"GB",
    "gn:dem":142,
    "gn:feature_class":"P",
    "gn:feature_code":"PPL",
    "gn:name":"Urchany",
    "gn:population":0,
    "gn:timezone":"Europe/London",
    "iso:country":"GB",
    "wof:name":"Urchany",
    "wof:placetype":"locality"
},
  "geometry": {"coordinates":[-3.86667,57.51667],"type":"Point"}
}