{
  "type": "Feature",
  "properties": {
    "iso:country": "GB",
    "name:bul_x_preferred": [
      "Дънгивън"
    ],
    "name:ceb_x_preferred": [
      "Dungiven"
    ],
    "name:deu_x_preferred": [
      "Dungiven"
    ],
    "name:eng_x_preferred": [
      "Dungiven"
    ],
    "name:eus_x_preferred": [
      "Dungiven"
    ],
    "name:fas_x_preferred": [
      "دانجیون"
    ],
    "name:fra_x_preferred": [
      "Dungiven"
    ],
    "name:gla_x_preferred": [
      "Dún Geimhin"
    ],
    "name:gle_x_preferred": [
      "Dún Geimhin"
    ],
    "name:ita_x_preferred": [
      "Dungiven"
    ],
    "name:msa_x_preferred": [
      "Dungiven"
    ],
    "name:nld_x_preferred": [
      "Dungiven"
    ],
    "name:nob_x_preferred": [
      "Dungiven"
    ],
    "name:nor_x_preferred": [
      "Dungiven"
    ],
    "name:pli_x_preferred": [
      "दुन्गिवें"
    ],
    "name:spa_x_preferred": [
      "Dungiven"
    ],
    "name:swe_x_preferred": [
      "Dungiven"
    ],
    "qs:a0": "United Kingdom",
    "qs:a1": "*Limavady",
    "qs:a1_lc": "N_A",
    "qs:a1r": "0Northern Ireland",
    "qs:a1r_lc": "N_A",
    "qs:adm0": "United Kingdom",
    "qs:la_lc": "*",
    "qs:level": "locality",
    "qs:loc": "Dungiven",
    "qs:loc_alt": "Dungiven",
    "qs:pop": 0,
    "qs:type": "buffered point",
    "wd:wordcount": 1130,
    "wof:name": "Dungiven",
    "wof:placetype": "locality"
  },
  "geometry": {"coordinates":[-6.919497,54.925663],"type":"Point"}
}
