{
  "type": "Feature",
  "properties": {
    "iso:country":"GB",
    "name:bul_x_preferred":[
        "\u0414\u044a\u043d\u0433\u0438\u0432\u044a\u043d"
    ],
    "name:ceb_x_preferred":[
        "Dungiven"
    ],
    "name:deu_x_preferred":[
        "Dungiven"
    ],
    "name:eng_x_preferred":[
        "Dungiven"
    ],
    "name:eus_x_preferred":[
        "Dungiven"
    ],
    "name:fas_x_preferred":[
        "\u062f\u0627\u0646\u062c\u06cc\u0648\u0646"
    ],
    "name:fra_x_preferred":[
        "Dungiven"
    ],
    "name:gla_x_preferred":[
        "D\u00fan Geimhin"
    ],
    "name:gle_x_preferred":[
        "D\u00fan Geimhin"
    ],
    "name:ita_x_preferred":[
        "Dungiven"
    ],
    "name:msa_x_preferred":[
        "Dungiven"
    ],
    "name:nld_x_preferred":[
        "Dungiven"
    ],
    "name:nob_x_preferred":[
        "Dungiven"
    ],
    "name:nor_x_preferred":[
        "Dungiven"
    ],
    "name:pli_x_preferred":[
        "\u0926\u0941\u0928\u094d\u0917\u093f\u0935\u0947\u0902"
    ],
    "name:spa_x_preferred":[
        "Dungiven"
    ],
    "name:swe_x_preferred":[
        "Dungiven"
    ],
    "qs:a0":"United Kingdom",
    "qs:a1":"*Limavady",
    "qs:a1_lc":"N_A",
    "qs:a1r":"0Northern Ireland",
    "qs:a1r_lc":"N_A",
    "qs:adm0":"United Kingdom",
    "qs:la_lc":"*",
    "qs:level":"locality",
    "qs:loc":"Dungiven",
    "qs:loc_alt":"Dungiven",
    "qs:pop":0,
    "qs:type":"buffered point",
    "wd:wordcount":1130,
    "wof:name":"Dungiven",
    "wof:placetype":"locality"
},
  "geometry": {"coordinates":[-6.919497,54.925663],"type":"Point"}
}