{
  "type": "Feature",
  "properties": {
    "gn:country":"GB",
    "gn:fcode":"PPL",
    "gn:population":0,
    "iso:country":"GB",
    "name:azb_x_preferred":[
        "\u0647\u0648\u0631\u0646\u06a9\u0644\u0627\u06cc\u0641"
    ],
    "name:ceb_x_preferred":[
        "Horncliffe"
    ],
    "name:cym_x_preferred":[
        "Horncliffe"
    ],
    "name:eng_x_preferred":[
        "Horncliffe"
    ],
    "name:fas_x_preferred":[
        "\u0647\u0648\u0631\u0646\u06a9\u0644\u0627\u06cc\u0641"
    ],
    "name:fra_x_preferred":[
        "Horncliffe"
    ],
    "name:ita_x_preferred":[
        "Horncliffe"
    ],
    "name:nld_x_preferred":[
        "Horncliffe"
    ],
    "name:pol_x_preferred":[
        "Horncliffe"
    ],
    "name:sco_x_preferred":[
        "Hurklay"
    ],
    "name:swe_x_preferred":[
        "Horncliffe"
    ],
    "qs_pg:aaroncc":"GB",
    "qs_pg:gn_country":"GB",
    "qs_pg:gn_fcode":"PPL",
    "qs_pg:gn_pop":0,
    "qs_pg:name":"Horncliffe",
    "qs_pg:name_adm0":"United Kingdom",
    "qs_pg:name_adm1":"England",
    "qs_pg:photos":347,
    "qs_pg:photos_1k":70,
    "qs_pg:photos_9k":2,
    "qs_pg:photos_9r":5,
    "qs_pg:photos_all":347,
    "qs_pg:photos_sr":5,
    "qs_pg:pop_sr":0,
    "qs_pg:qs_pg_placetype":"locality",
    "qs_pg:qs_pg_placetype_gp":"Town",
    "qs_pg:woe_adm0":23424975,
    "woe:adm0_id":23424975,
    "woe:name_adm0":"United Kingdom",
    "woe:name_adm1":"England",
    "woe:placetype":"Town",
    "wof:name":"Horncliffe",
    "wof:placetype":"locality"
},
  "geometry": {"coordinates":[-2.11667,55.75],"type":"Point"}
}