{
  "type": "Feature",
  "properties": {
    "gn:admin1_code": "ENG",
    "gn:admin2_code": "Q4",
    "gn:admin3_code": "47UD",
    "gn:asciiname": "Crabbs Cross",
    "gn:country_code": "GB",
    "gn:dem": 147,
    "gn:feature_class": "P",
    "gn:feature_code": "PPL",
    "gn:name": "Crabbs Cross",
    "gn:population": 0,
    "gn:timezone": "Europe/London",
    "iso:country": "GB",
    "name:pol_x_preferred": [
      "Crabbs Cross"
    ],
    "wof:name": "Crabbs Cross",
    "wof:placetype": "neighbourhood"
  },
  "geometry": {"coordinates":[-1.94074,52.27989],"type":"Point"}
}
