{
  "type": "Feature",
  "properties": {
    "gn:country":"GB",
    "iso:country":"GB",
    "name:dut_x_variant":[
        "Brea of Achnahaird"
    ],
    "name:eng_x_preferred":[
        "Brae of Achnahaird"
    ],
    "name:eng_x_variant":[
        "Brea of Achnahaird"
    ],
    "name:eus_x_preferred":[
        "Brae of Achnahaird"
    ],
    "name:nld_x_preferred":[
        "Brae of Achnahaird"
    ],
    "name:nld_x_variant":[
        "Brea of Achnahaird"
    ],
    "qs_pg:aaroncc":"GB",
    "qs_pg:gn_country":"GB",
    "qs_pg:name":"Brae of Achnahaird",
    "qs_pg:name_adm0":"United Kingdom",
    "qs_pg:name_adm1":"Scotland",
    "qs_pg:photos":643,
    "qs_pg:photos_1k":130,
    "qs_pg:photos_9k":3,
    "qs_pg:photos_9r":5,
    "qs_pg:photos_all":643,
    "qs_pg:photos_sr":8,
    "qs_pg:pop_sr":0,
    "qs_pg:qs_pg_placetype":"locality",
    "qs_pg:qs_pg_placetype_gp":"Town",
    "qs_pg:woe_adm0":23424975,
    "woe:adm0_id":23424975,
    "woe:name_adm0":"United Kingdom",
    "woe:name_adm1":"Scotland",
    "woe:placetype":"Town",
    "wof:name":"Brae of Achnahaird",
    "wof:placetype":"locality"
},
  "geometry": {"coordinates":[-5.362701,58.068771],"type":"Point"}
}