{
  "type": "Feature",
  "properties": {
    "gn:admin1_code": "ENG",
    "gn:admin2_code": "F2",
    "gn:admin3_code": "24UB",
    "gn:admin4_code": "24UB003",
    "gn:asciiname": "Wolverton",
    "gn:country_code": "GB",
    "gn:dem": 122,
    "gn:feature_class": "P",
    "gn:feature_code": "PPL",
    "gn:name": "Wolverton",
    "gn:population": 0,
    "gn:timezone": "Europe/London",
    "iso:country": "GB",
    "name:cym_x_preferred": [
      "Wolverton"
    ],
    "name:pol_x_preferred": [
      "Wolverton"
    ],
    "wof:name": "Wolverton",
    "wof:placetype": "neighbourhood"
  },
  "geometry": {"coordinates":[-1.20867,51.32375],"type":"Point"}
}
