{
  "type": "Feature",
  "properties": {
    "iso:country":"GB",
    "name:cym_x_preferred":[
        "Chidden"
    ],
    "name:eng_x_preferred":[
        "Chidden"
    ],
    "name:fra_x_preferred":[
        "Chidden"
    ],
    "name:nld_x_preferred":[
        "Chidden"
    ],
    "name:pol_x_preferred":[
        "Chidden"
    ],
    "qs_pg:aaroncc":"GB",
    "qs_pg:name":"Chidden",
    "qs_pg:name_adm0":"United Kingdom",
    "qs_pg:name_adm1":"England",
    "qs_pg:photos":907,
    "qs_pg:photos_1k":184,
    "qs_pg:photos_9k":4,
    "qs_pg:photos_9r":6,
    "qs_pg:photos_all":907,
    "qs_pg:photos_sr":10,
    "qs_pg:pop_sr":0,
    "qs_pg:qs_pg_placetype":"locality",
    "qs_pg:qs_pg_placetype_gp":"Town",
    "qs_pg:woe_adm0":23424975,
    "woe:adm0_id":23424975,
    "woe:name_adm0":"United Kingdom",
    "woe:name_adm1":"England",
    "woe:placetype":"Town",
    "wof:name":"Chidden",
    "wof:placetype":"neighbourhood"
},
  "geometry": {"coordinates":[-1.039066,50.970373],"type":"Point"}
}