{
  "type": "Feature",
  "properties": {
    "iso:country":"GB",
    "wof:name":"Old Benwell",
    "wof:placetype":"neighbourhood"
},
  "geometry": {"coordinates":[-1.67621290732174,54.97418787574183],"type":"Point"}
}