{
  "type": "Feature",
  "properties": {
    "gn:country":"GB",
    "gn:fcode":"PPL",
    "gn:population":0,
    "iso:country":"GB",
    "name:eng_x_preferred":[
        "Knocknacarry"
    ],
    "name:eus_x_preferred":[
        "Knocknacarry"
    ],
    "name:fra_x_preferred":[
        "Knocknacarry"
    ],
    "name:gla_x_preferred":[
        "Cnoc na Caraidh"
    ],
    "name:gle_x_preferred":[
        "Cnoc na Caraidh"
    ],
    "name:msa_x_preferred":[
        "Knocknacarry"
    ],
    "name:nld_x_preferred":[
        "Knocknacarry"
    ],
    "name:pli_x_preferred":[
        "\u0915\u094d\u0928\u094b\u091a\u094d\u0915\u094d\u0928\u093e\u0915\u093e\u0930\u094d\u0930\u0940"
    ],
    "name:spa_x_preferred":[
        "Knocknacarry"
    ],
    "qs_pg:aaroncc":"GB",
    "qs_pg:gn_country":"GB",
    "qs_pg:gn_fcode":"PPL",
    "qs_pg:gn_pop":0,
    "qs_pg:name":"Knocknacarry",
    "qs_pg:name_adm0":"United Kingdom",
    "qs_pg:name_adm1":"Northern Ireland",
    "qs_pg:photos":46,
    "qs_pg:photos_1k":9,
    "qs_pg:photos_9k":1,
    "qs_pg:photos_9r":2,
    "qs_pg:photos_all":46,
    "qs_pg:photos_sr":2,
    "qs_pg:pop_sr":0,
    "qs_pg:qs_pg_placetype":"locality",
    "qs_pg:qs_pg_placetype_gp":"Town",
    "qs_pg:woe_adm0":23424975,
    "woe:adm0_id":23424975,
    "woe:name_adm0":"United Kingdom",
    "woe:name_adm1":"Northern Ireland",
    "woe:placetype":"Town",
    "wof:name":"Knocknacarry",
    "wof:placetype":"locality"
},
  "geometry": {"coordinates":[-6.05,55.11667],"type":"Point"}
}