{
  "type": "Feature",
  "properties": {
    "gn:country":"GB",
    "gn:fcode":"PPL",
    "gn:population":0,
    "iso:country":"GB",
    "name:bre_x_preferred":[
        "Lagavulin"
    ],
    "name:deu_x_preferred":[
        "Lagavulin"
    ],
    "name:eng_x_preferred":[
        "Lagavulin"
    ],
    "name:eus_x_preferred":[
        "Lagavulin"
    ],
    "name:fas_x_preferred":[
        "\u0644\u0627\u06af\u0627\u0648\u0648\u0644\u06cc\u0646"
    ],
    "name:fra_x_preferred":[
        "Lagavulin"
    ],
    "name:gle_x_preferred":[
        "Lag a' Mhuilinn"
    ],
    "name:nld_x_preferred":[
        "Lagavulin"
    ],
    "name:oci_x_preferred":[
        "Lagavulin"
    ],
    "name:sco_x_preferred":[
        "Lagavulin"
    ],
    "name:swe_x_preferred":[
        "Lagavulin"
    ],
    "name:und_x_variant":[
        "Laggavoulin"
    ],
    "qs_pg:aaroncc":"GB",
    "qs_pg:gn_country":"GB",
    "qs_pg:gn_fcode":"PPL",
    "qs_pg:gn_pop":0,
    "qs_pg:name":"Lagavulin",
    "qs_pg:name_adm0":"United Kingdom",
    "qs_pg:name_adm1":"Scotland",
    "qs_pg:photos":641,
    "qs_pg:photos_1k":130,
    "qs_pg:photos_9k":3,
    "qs_pg:photos_9r":5,
    "qs_pg:photos_all":641,
    "qs_pg:photos_sr":8,
    "qs_pg:pop_sr":0,
    "qs_pg:qs_pg_placetype":"locality",
    "qs_pg:qs_pg_placetype_gp":"Town",
    "qs_pg:woe_adm0":23424975,
    "woe:adm0_id":23424975,
    "woe:name_adm0":"United Kingdom",
    "woe:name_adm1":"Scotland",
    "woe:placetype":"Town",
    "wof:name":"Lagavulin",
    "wof:placetype":"locality"
},
  "geometry": {"coordinates":[-6.12692,55.63576],"type":"Point"}
}