{
  "type": "Feature",
  "properties": {
    "iso:country":"GB",
    "name:cym_x_preferred":[
        "Deadwater"
    ],
    "name:eng_x_preferred":[
        "Deadwater"
    ],
    "name:fra_x_preferred":[
        "Deadwater"
    ],
    "name:gle_x_preferred":[
        "Deadwater"
    ],
    "name:jpn_x_preferred":[
        "\u30c7\u30c3\u30c9\u30a6\u30a9\u30fc\u30bf\u30fc"
    ],
    "name:nld_x_preferred":[
        "Deadwater"
    ],
    "name:pol_x_preferred":[
        "Deadwater"
    ],
    "qs_pg:aaroncc":"GB",
    "qs_pg:name":"Deadwater",
    "qs_pg:name_adm0":"United Kingdom",
    "qs_pg:name_adm1":"England",
    "qs_pg:photos":76,
    "qs_pg:photos_1k":15,
    "qs_pg:photos_9k":1,
    "qs_pg:photos_9r":3,
    "qs_pg:photos_all":76,
    "qs_pg:photos_sr":3,
    "qs_pg:pop_sr":0,
    "qs_pg:qs_pg_placetype":"locality",
    "qs_pg:qs_pg_placetype_gp":"Town",
    "qs_pg:woe_adm0":23424975,
    "woe:adm0_id":23424975,
    "woe:name_adm0":"United Kingdom",
    "woe:name_adm1":"England",
    "woe:placetype":"Town",
    "wof:name":"Deadwater",
    "wof:placetype":"locality"
},
  "geometry": {"coordinates":[-2.625754,55.269165],"type":"Point"}
}