{
  "type": "Feature",
  "properties": {
    "iso:country": "GB",
    "name:cym_x_preferred": [
      "Benthall"
    ],
    "name:eng_x_preferred": [
      "Benthall"
    ],
    "name:fra_x_preferred": [
      "Benthall"
    ],
    "name:nld_x_preferred": [
      "Benthall"
    ],
    "name:pol_x_preferred": [
      "Benthall"
    ],
    "qs:a0": "United Kingdom",
    "qs:a1": "*Shropshire",
    "qs:a1_lc": "GB12GG0000",
    "qs:a1r": "0England",
    "qs:a1r_lc": "GB12000000",
    "qs:adm0": "United Kingdom",
    "qs:la_lc": "*",
    "qs:level": "locality",
    "qs:loc": "Benthall",
    "qs:loc_alt": "Benthall",
    "qs:pop": 0,
    "qs:type": "buffered point",
    "wd:wordcount": 81,
    "wof:name": "Benthall",
    "wof:placetype": "neighbourhood"
  },
  "geometry": {"coordinates":[-2.481581,52.612961],"type":"Point"}
}
