{
  "type": "Feature",
  "properties": {
    "gn:admin1_code":"ENG",
    "gn:admin2_code":"A7",
    "gn:asciiname":"Tile Cross",
    "gn:country_code":"GB",
    "gn:dem":103,
    "gn:feature_class":"P",
    "gn:feature_code":"PPL",
    "gn:name":"Tile Cross",
    "gn:population":0,
    "gn:timezone":"Europe/London",
    "iso:country":"GB",
    "wof:name":"Tile Cross",
    "wof:placetype":"neighbourhood"
},
  "geometry": {"coordinates":[-1.76798,52.47645],"type":"Point"}
}