{
  "type": "Feature",
  "properties": {
    "iso:country":"GB",
    "name:cym_x_preferred":[
        "Laity Moor"
    ],
    "name:eng_x_preferred":[
        "Laity Moor"
    ],
    "name:eus_x_preferred":[
        "Laity Moor"
    ],
    "name:fra_x_preferred":[
        "Laity Moor"
    ],
    "name:nld_x_preferred":[
        "Laity Moor"
    ],
    "qs_pg:aaroncc":"GB",
    "qs_pg:name":"Laity Moor",
    "qs_pg:name_adm0":"United Kingdom",
    "qs_pg:name_adm1":"England",
    "qs_pg:photos":60,
    "qs_pg:photos_1k":12,
    "qs_pg:photos_9k":1,
    "qs_pg:photos_9r":2,
    "qs_pg:photos_all":60,
    "qs_pg:photos_sr":2,
    "qs_pg:pop_sr":0,
    "qs_pg:qs_pg_placetype":"locality",
    "qs_pg:qs_pg_placetype_gp":"Town",
    "qs_pg:woe_adm0":23424975,
    "woe:adm0_id":23424975,
    "woe:name_adm0":"United Kingdom",
    "woe:name_adm1":"England",
    "woe:placetype":"Town",
    "wof:name":"Laity Moor",
    "wof:placetype":"neighbourhood"
},
  "geometry": {"coordinates":[-5.133361,50.178973],"type":"Point"}
}