{
  "type": "Feature",
  "properties": {
    "iso:country": "GB",
    "name:eng_x_preferred": [
      "Newtown"
    ],
    "wof:name": "Newtown",
    "wof:placetype": "neighbourhood"
  },
  "geometry": {"coordinates":[0.13271865144281,52.19099426329119],"type":"Point"}
}
