{
  "type": "Feature",
  "properties": {
    "iso:country": "GB",
    "wof:name": "Hollins End",
    "wof:placetype": "neighbourhood"
  },
  "geometry": {"coordinates":[-1.41540503563465,53.35259924952866],"type":"Point"}
}
