{
  "type": "Feature",
  "properties": {
    "gn:admin1_code":"ENG",
    "gn:admin2_code":"Z6",
    "gn:admin3_code":"00KC044",
    "gn:asciiname":"Upper Shelton",
    "gn:country_code":"GB",
    "gn:dem":56,
    "gn:elevation":"53.0",
    "gn:feature_class":"P",
    "gn:feature_code":"PPL",
    "gn:name":"Upper Shelton",
    "gn:population":0,
    "gn:timezone":"Europe/London",
    "iso:country":"GB",
    "name:ara_x_preferred":[
        "\u0622\u0628\u0628\u0631 \u0634\u0644\u062a\u0648\u0646"
    ],
    "name:cym_x_preferred":[
        "Upper Shelton"
    ],
    "name:fas_x_preferred":[
        "\u0622\u067e\u0631 \u0634\u0644\u062a\u0648\u0646"
    ],
    "name:fra_x_preferred":[
        "Upper Shelton"
    ],
    "name:pol_x_preferred":[
        "Upper Shelton"
    ],
    "wof:name":"Upper Shelton",
    "wof:placetype":"neighbourhood"
},
  "geometry": {"coordinates":[-0.55382,52.08059],"type":"Point"}
}