{
  "type": "Feature",
  "properties": {
    "gn:admin1_code": "SCT",
    "gn:admin2_code": "W3",
    "gn:asciiname": "Wester Quarff",
    "gn:country_code": "GB",
    "gn:dem": 105,
    "gn:feature_class": "P",
    "gn:feature_code": "PPL",
    "gn:name": "Wester Quarff",
    "gn:population": 0,
    "gn:timezone": "Europe/London",
    "iso:country": "GB",
    "wof:name": "Wester Quarff",
    "wof:placetype": "locality"
  },
  "geometry": {"coordinates":[-1.26478,60.09512],"type":"Point"}
}
