{
  "type": "Feature",
  "properties": {
    "iso:country": "GB",
    "qs_pg:aaroncc": "GB",
    "qs_pg:name": "Macclesfield Forest",
    "qs_pg:name_adm0": "United Kingdom",
    "qs_pg:name_adm1": "England",
    "qs_pg:photos": 1301,
    "qs_pg:photos_1k": 264,
    "qs_pg:photos_9k": 6,
    "qs_pg:photos_9r": 7,
    "qs_pg:photos_all": 1301,
    "qs_pg:photos_sr": 12,
    "qs_pg:pop_sr": 0,
    "qs_pg:qs_pg_placetype": "locality",
    "qs_pg:qs_pg_placetype_gp": "Town",
    "qs_pg:woe_adm0": 23424975,
    "woe:adm0_id": 23424975,
    "woe:name_adm0": "United Kingdom",
    "woe:name_adm1": "England",
    "woe:placetype": "Town",
    "wof:name": "Macclesfield Forest",
    "wof:placetype": "neighbourhood"
  },
  "geometry": {"coordinates":[-2.028136,53.245392],"type":"Point"}
}
