{
  "type": "Feature",
  "properties": {
    "iso:country":"GB",
    "name:eng_x_preferred":[
        "Gilnahirk"
    ],
    "qs:gn_adm0_cc":"GB",
    "qs:gn_fcode":"PPL",
    "qs:gn_local":2655984,
    "qs:gn_nam_loc":"Belfast, Belfast, Belfast, Northern Ireland, GB",
    "qs:gn_namadm1":"NIR",
    "qs:gn_name":"Gilnahirk",
    "qs:local_max":5029,
    "qs:local_sum":45783,
    "qs:localhoods":44,
    "qs:name":"Gilnahirk",
    "qs:name_adm0":"United Kingdom",
    "qs:name_adm1":"Northern Ireland",
    "qs:name_adm2":"Down",
    "qs:name_lau":"Belfast",
    "qs:name_local":"Belfast",
    "qs:photo_max":33,
    "qs:photo_sum":150,
    "qs:placetype":"Suburb",
    "qs:quad_count":24,
    "qs:woe_adm0":23424975,
    "qs:woe_adm1":20070563,
    "qs:woe_adm2":20071113,
    "qs:woe_lau":20078326,
    "qs:woe_local":44544,
    "qs:woe_ver":"7.10.0",
    "wof:lang":[
        "eng"
    ],
    "wof:name":"Gilnahirk",
    "wof:placetype":"neighbourhood"
},
  "geometry": {"coordinates":[-5.842125,54.586874],"type":"Point"}
}