{
  "type": "Feature",
  "properties": {
    "iso:country":"GB",
    "name:cym_x_preferred":[
        "Carisbrooke"
    ],
    "name:eng_x_preferred":[
        "Carisbrooke"
    ],
    "name:fra_x_preferred":[
        "Carisbrooke"
    ],
    "name:lat_x_preferred":[
        "Carisbrooke"
    ],
    "name:nld_x_preferred":[
        "Carisbrooke"
    ],
    "name:pol_x_preferred":[
        "Carisbrooke"
    ],
    "qs_pg:aaroncc":"GB",
    "qs_pg:name":"Carisbrook",
    "qs_pg:name_adm0":"United Kingdom",
    "qs_pg:name_adm1":"England",
    "qs_pg:photos":1879,
    "qs_pg:photos_1k":381,
    "qs_pg:photos_9k":8,
    "qs_pg:photos_9r":9,
    "qs_pg:photos_all":1879,
    "qs_pg:photos_sr":15,
    "qs_pg:pop_sr":0,
    "qs_pg:qs_pg_placetype":"locality",
    "qs_pg:qs_pg_placetype_gp":"Town",
    "qs_pg:woe_adm0":23424975,
    "woe:adm0_id":23424975,
    "woe:name_adm0":"United Kingdom",
    "woe:name_adm1":"England",
    "woe:placetype":"Town",
    "wof:name":"Carisbrook",
    "wof:placetype":"neighbourhood"
},
  "geometry": {"coordinates":[-1.313552,50.687405],"type":"Point"}
}