{
  "type": "Feature",
  "properties": {
    "gn:population":5073,
    "iso:country":"GB",
    "name:ceb_x_preferred":[
        "Bridge of Allan"
    ],
    "name:deu_x_preferred":[
        "Bridge of Allan"
    ],
    "name:eng_x_preferred":[
        "Bridge of Allan"
    ],
    "name:eus_x_preferred":[
        "Bridge of Allan"
    ],
    "name:fas_x_preferred":[
        "\u0628\u0631\u06cc\u062c \u0622\u0648 \u0627\u0644\u0646"
    ],
    "name:fra_x_preferred":[
        "Bridge of Allan"
    ],
    "name:gla_x_preferred":[
        "Drochaid Alain"
    ],
    "name:gle_x_preferred":[
        "Drochaid Alain"
    ],
    "name:glg_x_preferred":[
        "Bridge of Allan"
    ],
    "name:heb_x_preferred":[
        "\u05d1\u05e8\u05d9\u05d2 \u05d0\u05dc\u05df"
    ],
    "name:ita_x_preferred":[
        "Bridge of Allan"
    ],
    "name:nld_x_preferred":[
        "Bridge of Allan"
    ],
    "name:pol_x_preferred":[
        "Bridge of Allan"
    ],
    "name:sco_x_preferred":[
        "Brig Allan"
    ],
    "name:spa_x_preferred":[
        "Bridge of Allan"
    ],
    "name:swe_x_preferred":[
        "Bridge of Allan"
    ],
    "name:zho_x_preferred":[
        "\u5e03\u91cc\u54f2\u592b\u4e9a\u4f26"
    ],
    "qs:a0":"United Kingdom",
    "qs:a1":"*Stirling",
    "qs:a1_lc":"GB11RG0000",
    "qs:a1r":"0Scotland",
    "qs:a1r_lc":"GB11000000",
    "qs:adm0":"United Kingdom",
    "qs:la_lc":"*",
    "qs:level":"locality",
    "qs:loc":"Bridge of Allan",
    "qs:loc_alt":"Bridge of Allan",
    "qs:pop":0,
    "qs:type":"buffered point",
    "wd:wordcount":1006,
    "wof:name":"Bridge of Allan",
    "wof:placetype":"locality",
    "wof:population":5073
},
  "geometry": {"coordinates":[-3.945717,56.154717],"type":"Point"}
}