{
  "type": "Feature",
  "properties": {
    "gn:admin1_code":"NIR",
    "gn:admin2_code":"N09000010",
    "gn:asciiname":"Dromara",
    "gn:country_code":"GB",
    "gn:dem":141,
    "gn:feature_class":"P",
    "gn:feature_code":"PPL",
    "gn:name":"Dromara",
    "gn:population":0,
    "gn:timezone":"Europe/London",
    "iso:country":"GB",
    "name:ceb_x_preferred":[
        "Dromara"
    ],
    "name:eus_x_preferred":[
        "Dromara"
    ],
    "name:fas_x_preferred":[
        "\u062f\u0631\u0648\u0645\u0627\u0631\u0627"
    ],
    "name:gle_x_preferred":[
        "Droim mBearach"
    ],
    "name:ita_x_preferred":[
        "Dromara"
    ],
    "name:msa_x_preferred":[
        "Dromara"
    ],
    "name:nld_x_preferred":[
        "Dromara"
    ],
    "name:pli_x_preferred":[
        "\u0926\u094d\u0930\u094b\u092e\u093e\u0930\u093e"
    ],
    "name:spa_x_preferred":[
        "Dromara"
    ],
    "name:swe_x_preferred":[
        "Dromara"
    ],
    "wof:name":"Dromara",
    "wof:placetype":"locality"
},
  "geometry": {"coordinates":[-6.01667,54.36666999999999],"type":"Point"}
}