{
  "type": "Feature",
  "properties": {
    "gn:admin1_code":"NIR",
    "gn:admin2_code":"N09000010",
    "gn:asciiname":"Dromara",
    "gn:country_code":"GB",
    "gn:dem":141,
    "gn:feature_class":"P",
    "gn:feature_code":"PPL",
    "gn:name":"Dromara",
    "gn:population":0,
    "gn:timezone":"Europe/London",
    "iso:country":"GB",
    "wof:name":"Dromara",
    "wof:placetype":"locality"
},
  "geometry": {"coordinates":[-6.01667,54.36666999999999],"type":"Point"}
}