{
  "type": "Feature",
  "properties": {
    "gn:admin1_code":"ENG",
    "gn:admin2_code":"C6",
    "gn:admin3_code":"00HE071",
    "gn:asciiname":"Trevadlock",
    "gn:country_code":"GB",
    "gn:dem":171,
    "gn:feature_class":"P",
    "gn:feature_code":"PPL",
    "gn:name":"Trevadlock",
    "gn:population":0,
    "gn:timezone":"Europe/London",
    "iso:country":"GB",
    "wof:name":"Trevadlock",
    "wof:placetype":"neighbourhood"
},
  "geometry": {"coordinates":[-4.45184,50.5858],"type":"Point"}
}