{
  "type": "Feature",
  "properties": {
    "iso:country":"GB",
    "name:ell_x_preferred":[
        "\u03a4\u03bf\u03c5\u03ad\u03c1\u03c4\u03bf\u03bd"
    ],
    "name:eng_x_preferred":[
        "Twerton"
    ],
    "name:gle_x_preferred":[
        "Twerton"
    ],
    "name:lld_x_preferred":[
        "Twerton"
    ],
    "name:nld_x_preferred":[
        "Twerton"
    ],
    "name:vec_x_preferred":[
        "Twerton"
    ],
    "qs:gn_fcode":"PPLX",
    "qs:gn_local":0,
    "qs:gn_namadm1":"ENG",
    "qs:gn_name":"Twerton",
    "qs:local_max":5278,
    "qs:local_sum":20573,
    "qs:localhoods":11,
    "qs:name":"Twerton",
    "qs:name_adm0":"United Kingdom",
    "qs:name_adm1":"England",
    "qs:name_adm2":"Somerset",
    "qs:name_lau":"Bath and North East Somerset",
    "qs:name_local":"Bath",
    "qs:photo_max":165,
    "qs:photo_sum":693,
    "qs:placetype":"Suburb",
    "qs:quad_count":48,
    "qs:woe_adm0":23424975,
    "qs:woe_adm1":24554868,
    "qs:woe_adm2":12602185,
    "qs:woe_lau":12696136,
    "qs:woe_local":12056,
    "qs:woe_ver":"7.10.0",
    "wd:wordcount":550,
    "wof:lang":[
        "eng"
    ],
    "wof:name":"Twerton",
    "wof:placetype":"neighbourhood"
},
  "geometry": {"coordinates":[-2.409092,51.38782],"type":"Point"}
}