{
  "type": "Feature",
  "properties": {
    "gn:country":"GB",
    "gn:fcode":"PPL",
    "gn:population":0,
    "iso:country":"GB",
    "name:ceb_x_preferred":[
        "Wark"
    ],
    "name:deu_x_preferred":[
        "Wark"
    ],
    "name:nds_x_preferred":[
        "Wark"
    ],
    "name:nld_x_preferred":[
        "Wark"
    ],
    "name:pol_x_preferred":[
        "Wark"
    ],
    "name:rus_x_preferred":[
        "\u0423\u043e\u0440\u043a"
    ],
    "name:swe_x_preferred":[
        "Wark"
    ],
    "qs_pg:aaroncc":"GB",
    "qs_pg:gn_country":"GB",
    "qs_pg:gn_fcode":"PPL",
    "qs_pg:gn_pop":0,
    "qs_pg:name":"Wark",
    "qs_pg:name_adm0":"United Kingdom",
    "qs_pg:name_adm1":"England",
    "qs_pg:photos":25,
    "qs_pg:photos_1k":5,
    "qs_pg:photos_9k":1,
    "qs_pg:photos_9r":1,
    "qs_pg:photos_all":25,
    "qs_pg:photos_sr":1,
    "qs_pg:pop_sr":0,
    "qs_pg:qs_pg_placetype":"locality",
    "qs_pg:qs_pg_placetype_gp":"Town",
    "qs_pg:woe_adm0":23424975,
    "woe:adm0_id":23424975,
    "woe:name_adm0":"United Kingdom",
    "woe:name_adm1":"England",
    "woe:placetype":"Town",
    "wof:name":"Wark",
    "wof:placetype":"neighbourhood"
},
  "geometry": {"coordinates":[-2.26667,55.63333],"type":"Point"}
}