{
  "type": "Feature",
  "properties": {
    "iso:country":"GB",
    "name:eng_x_preferred":[
        "Laisterdyke"
    ],
    "name:gle_x_preferred":[
        "Laisterdyke"
    ],
    "qs:gn_adm0_cc":"GB",
    "qs:gn_local":2654993,
    "qs:gn_nam_loc":"Bradford",
    "qs:gn_namadm1":"ENG",
    "qs:local_max":4399,
    "qs:local_sum":22210,
    "qs:localhoods":31,
    "qs:name":"Laisterdyke",
    "qs:name_adm0":"United Kingdom",
    "qs:name_adm1":"England",
    "qs:name_adm2":"West Yorkshire",
    "qs:name_lau":"Bradford City of",
    "qs:name_local":"Bradford",
    "qs:photo_max":578,
    "qs:photo_sum":986,
    "qs:placetype":"Suburb",
    "qs:quad_count":31,
    "qs:woe_adm0":23424975,
    "qs:woe_adm1":24554868,
    "qs:woe_adm2":12602197,
    "qs:woe_lau":12695870,
    "qs:woe_local":13527,
    "qs:woe_ver":"7.10.0",
    "wd:wordcount":760,
    "wof:lang":[
        "eng"
    ],
    "wof:name":"Laisterdyke",
    "wof:placetype":"neighbourhood"
},
  "geometry": {"coordinates":[-1.713634,53.792582],"type":"Point"}
}