{
  "type": "Feature",
  "properties": {
    "gn:country": "GB",
    "gn:fcode": "PPL",
    "gn:population": 0,
    "iso:country": "GB",
    "name:ara_x_preferred": [
      "سولهم"
    ],
    "name:ceb_x_preferred": [
      "Sulham"
    ],
    "name:cym_x_preferred": [
      "Sulham"
    ],
    "name:fas_x_preferred": [
      "سالام"
    ],
    "name:ita_x_preferred": [
      "Sulham"
    ],
    "name:nld_x_preferred": [
      "Sulham"
    ],
    "name:pol_x_preferred": [
      "Sulham"
    ],
    "name:swe_x_preferred": [
      "Sulham"
    ],
    "qs_pg:aaroncc": "GB",
    "qs_pg:gn_country": "GB",
    "qs_pg:gn_fcode": "PPL",
    "qs_pg:gn_pop": 0,
    "qs_pg:name": "Sulham",
    "qs_pg:name_adm0": "United Kingdom",
    "qs_pg:name_adm1": "England",
    "qs_pg:photos": 97,
    "qs_pg:photos_1k": 20,
    "qs_pg:photos_9k": 1,
    "qs_pg:photos_9r": 3,
    "qs_pg:photos_all": 97,
    "qs_pg:photos_sr": 3,
    "qs_pg:pop_sr": 0,
    "qs_pg:qs_pg_placetype": "locality",
    "qs_pg:qs_pg_placetype_gp": "Town",
    "qs_pg:woe_adm0": 23424975,
    "woe:adm0_id": 23424975,
    "woe:name_adm0": "United Kingdom",
    "woe:name_adm1": "England",
    "woe:placetype": "Town",
    "wof:name": "Sulham",
    "wof:placetype": "neighbourhood"
  },
  "geometry": {"coordinates":[-0.67008,50.97853],"type":"Point"}
}
