{
  "type": "Feature",
  "properties": {
    "gn:gn_country":"GB",
    "gn:gn_fcode":"PPL",
    "gn:gn_pop":5000,
    "gn:population":5000,
    "iso:country":"GB",
    "name:ceb_x_preferred":[
        "Copthorne"
    ],
    "name:eng_x_preferred":[
        "Copthorne"
    ],
    "name:fra_x_preferred":[
        "Copthorne"
    ],
    "name:jpn_x_preferred":[
        "\u30b3\u30d7\u30bd\u30fc\u30f3 "
    ],
    "name:jpn_x_variant":[
        "\u30b3\u30d7\u30bd\u30fc\u30f3"
    ],
    "name:nld_x_preferred":[
        "Copthorne"
    ],
    "name:pol_x_preferred":[
        "Copthorne "
    ],
    "name:pol_x_variant":[
        "Copthorne"
    ],
    "name:spa_x_preferred":[
        "Copthorne"
    ],
    "name:swe_x_preferred":[
        "Copthorne"
    ],
    "qs_pg:aaroncc":"GB",
    "qs_pg:gn_country":"GB",
    "qs_pg:gn_fcode":"PPL",
    "qs_pg:gn_pop":5000,
    "qs_pg:name":"Copthorne",
    "qs_pg:name_adm0":"United Kingdom",
    "qs_pg:name_adm1":"England",
    "qs_pg:photos":114,
    "qs_pg:photos_1k":23,
    "qs_pg:photos_9k":1,
    "qs_pg:photos_9r":3,
    "qs_pg:photos_all":114,
    "qs_pg:photos_sr":3,
    "qs_pg:pop_sr":4,
    "qs_pg:qs_pg_placetype":"locality",
    "qs_pg:qs_pg_placetype_gp":"Town",
    "qs_pg:woe_adm0":23424975,
    "woe:adm0_id":23424975,
    "woe:name_adm0":"United Kingdom",
    "woe:name_adm1":"England",
    "woe:placetype":"Town",
    "wof:name":"Copthorne",
    "wof:placetype":"neighbourhood",
    "wof:population":5000
},
  "geometry": {"coordinates":[-0.11742,51.13929],"type":"Point"}
}