{
  "type": "Feature",
  "properties": {
    "iso:country":"GB",
    "name:ben_x_preferred":[
        "\u0987\u09a8\u0997\u09b2"
    ],
    "name:deu_x_preferred":[
        "Ingol"
    ],
    "name:eng_x_preferred":[
        "Ingol"
    ],
    "name:fra_x_preferred":[
        "Ingol"
    ],
    "name:guj_x_preferred":[
        "\u0a88\u0a82\u0a97\u0acb\u0ab2"
    ],
    "name:jpn_x_preferred":[
        "\u30a4\u30f3\u30b4\u30eb"
    ],
    "name:kan_x_preferred":[
        "\u0c87\u0c82\u0c97\u0ccb\u0cb2\u0ccd"
    ],
    "name:kor_x_preferred":[
        "\uc778\uace8"
    ],
    "name:lit_x_preferred":[
        "Ingolas"
    ],
    "name:nld_x_preferred":[
        "Ingol"
    ],
    "name:pol_x_preferred":[
        "Ingol"
    ],
    "name:por_x_preferred":[
        "Ingol"
    ],
    "name:rus_x_preferred":[
        "\u0418\u043d\u0433\u043e\u043b"
    ],
    "name:spa_x_preferred":[
        "Ingol"
    ],
    "name:tam_x_preferred":[
        "\u0b87\u0b99\u0bcd\u0b95\u0bcb\u0bb2\u0bcd"
    ],
    "name:tel_x_preferred":[
        "\u0c07\u0c02\u0c17\u0c4b\u0c32\u0c4d"
    ],
    "name:unk_x_variant":[
        "Ingol"
    ],
    "name:urd_x_preferred":[
        "\u0627\u0646\u062c\u0648\u0644"
    ],
    "qs:gn_adm0_cc":"GB",
    "qs:gn_local":2639912,
    "qs:gn_nam_loc":"Preston, Lancashire, England, GB",
    "qs:gn_namadm1":"ENG",
    "qs:local_max":4953,
    "qs:local_sum":17452,
    "qs:localhoods":9,
    "qs:name":"Ingol",
    "qs:name_adm0":"United Kingdom",
    "qs:name_adm1":"England",
    "qs:name_adm2":"Lancashire",
    "qs:name_lau":"Preston Borough",
    "qs:name_local":"Preston",
    "qs:photo_max":155,
    "qs:photo_sum":685,
    "qs:placetype":"Suburb",
    "qs:quad_count":54,
    "qs:woe_adm0":23424975,
    "qs:woe_adm1":24554868,
    "qs:woe_adm2":12602160,
    "qs:woe_lau":12696003,
    "qs:woe_local":32566,
    "qs:woe_ver":"7.10.0",
    "wd:wordcount":365,
    "wof:lang":[
        "eng"
    ],
    "wof:name":"Ingol",
    "wof:placetype":"neighbourhood"
},
  "geometry": {"coordinates":[-2.739294,53.782447],"type":"Point"}
}