{
  "type": "Feature",
  "properties": {
    "iso:country": "GB",
    "name:ben_x_preferred": [
      "ইনগল"
    ],
    "name:deu_x_preferred": [
      "Ingol"
    ],
    "name:eng_x_preferred": [
      "Ingol"
    ],
    "name:fra_x_preferred": [
      "Ingol"
    ],
    "name:guj_x_preferred": [
      "ઈંગોલ"
    ],
    "name:jpn_x_preferred": [
      "インゴル"
    ],
    "name:kan_x_preferred": [
      "ಇಂಗೋಲ್"
    ],
    "name:kor_x_preferred": [
      "인골"
    ],
    "name:lit_x_preferred": [
      "Ingolas"
    ],
    "name:nld_x_preferred": [
      "Ingol"
    ],
    "name:pol_x_preferred": [
      "Ingol"
    ],
    "name:por_x_preferred": [
      "Ingol"
    ],
    "name:rus_x_preferred": [
      "Ингол"
    ],
    "name:spa_x_preferred": [
      "Ingol"
    ],
    "name:tam_x_preferred": [
      "இங்கோல்"
    ],
    "name:tel_x_preferred": [
      "ఇంగోల్"
    ],
    "name:urd_x_preferred": [
      "انجول"
    ],
    "qs:gn_adm0_cc": "GB",
    "qs:gn_local": 2639912,
    "qs:gn_nam_loc": "Preston, Lancashire, England, GB",
    "qs:gn_namadm1": "ENG",
    "qs:local_max": 4953,
    "qs:local_sum": 17452,
    "qs:localhoods": 9,
    "qs:name": "Ingol",
    "qs:name_adm0": "United Kingdom",
    "qs:name_adm1": "England",
    "qs:name_adm2": "Lancashire",
    "qs:name_lau": "Preston Borough",
    "qs:name_local": "Preston",
    "qs:photo_max": 155,
    "qs:photo_sum": 685,
    "qs:placetype": "Suburb",
    "qs:quad_count": 54,
    "qs:woe_adm0": 23424975,
    "qs:woe_adm1": 24554868,
    "qs:woe_adm2": 12602160,
    "qs:woe_lau": 12696003,
    "qs:woe_local": 32566,
    "qs:woe_ver": "7.10.0",
    "wd:wordcount": 365,
    "wof:lang": [
      "eng"
    ],
    "wof:name": "Ingol",
    "wof:placetype": "neighbourhood"
  },
  "geometry": {"coordinates":[-2.739294,53.782447],"type":"Point"}
}
