{
  "type": "Feature",
  "properties": {
    "gn:country":"GB",
    "gn:fcode":"PPL",
    "gn:population":0,
    "iso:country":"GB",
    "name:aze_x_preferred":[
        "Elton"
    ],
    "name:ceb_x_preferred":[
        "Elton"
    ],
    "name:ces_x_preferred":[
        "Elton"
    ],
    "name:deu_x_preferred":[
        "Elton"
    ],
    "name:ita_x_preferred":[
        "Elton"
    ],
    "name:jpn_x_preferred":[
        "\u30a8\u30eb\u30c8\u30f3"
    ],
    "name:lav_x_preferred":[
        "Eltons"
    ],
    "name:nld_x_preferred":[
        "Elton"
    ],
    "name:nno_x_preferred":[
        "Elton"
    ],
    "name:pol_x_preferred":[
        "Elton"
    ],
    "name:por_x_preferred":[
        "Elton"
    ],
    "name:ron_x_preferred":[
        "Elton"
    ],
    "name:rus_x_preferred":[
        "\u042d\u043b\u0442\u043e\u043d"
    ],
    "name:spa_x_preferred":[
        "Elton"
    ],
    "name:swe_x_preferred":[
        "Elton"
    ],
    "name:ukr_x_preferred":[
        "\u0415\u043b\u044c\u0442\u043e\u043d"
    ],
    "name:und_x_variant":[
        "Eaton"
    ],
    "qs_pg:aaroncc":"GB",
    "qs_pg:gn_country":"GB",
    "qs_pg:gn_fcode":"PPL",
    "qs_pg:gn_pop":0,
    "qs_pg:name":"Elton",
    "qs_pg:name_adm0":"United Kingdom",
    "qs_pg:name_adm1":"England",
    "qs_pg:photos":21,
    "qs_pg:photos_1k":4,
    "qs_pg:photos_9k":1,
    "qs_pg:photos_9r":1,
    "qs_pg:photos_all":21,
    "qs_pg:photos_sr":1,
    "qs_pg:pop_sr":0,
    "qs_pg:qs_pg_placetype":"locality",
    "qs_pg:qs_pg_placetype_gp":"Town",
    "qs_pg:woe_adm0":23424975,
    "woe:adm0_id":23424975,
    "woe:name_adm0":"United Kingdom",
    "woe:name_adm1":"England",
    "woe:placetype":"Town",
    "wof:name":"Elton",
    "wof:placetype":"neighbourhood"
},
  "geometry": {"coordinates":[-2.63333,53.16667],"type":"Point"}
}