{
  "type": "Feature",
  "properties": {
    "gn:gn_country":"GB",
    "gn:gn_fcode":"PPL",
    "gn:gn_pop":0,
    "iso:country":"GB",
    "name:dut_x_preferred":[
        "Winterbourne Gunner"
    ],
    "name:eng_x_preferred":[
        "Winterbourne Gunner"
    ],
    "name:fre_x_preferred":[
        "Winterbourne Gunner"
    ],
    "name:pol_x_preferred":[
        "Winterbourne Gunner"
    ],
    "name:unk_x_variant":[
        "Winterbourne Cherborough"
    ],
    "qs_pg:aaroncc":"GB",
    "qs_pg:gn_country":"GB",
    "qs_pg:gn_fcode":"PPL",
    "qs_pg:gn_pop":0,
    "qs_pg:name":"Winterbourne Gunner",
    "qs_pg:name_adm0":"United Kingdom",
    "qs_pg:name_adm1":"England",
    "qs_pg:photos":59,
    "qs_pg:photos_1k":12,
    "qs_pg:photos_9k":1,
    "qs_pg:photos_9r":2,
    "qs_pg:photos_all":59,
    "qs_pg:photos_sr":2,
    "qs_pg:pop_sr":0,
    "qs_pg:qs_pg_placetype":"locality",
    "qs_pg:qs_pg_placetype_gp":"Town",
    "qs_pg:woe_adm0":23424975,
    "woe:adm0_id":23424975,
    "woe:name_adm0":"United Kingdom",
    "woe:name_adm1":"England",
    "woe:placetype":"Town",
    "wof:name":"Winterbourne Gunner",
    "wof:placetype":"neighbourhood"
},
  "geometry": {"coordinates":[-1.74436,51.11608],"type":"Point"}
}