{
  "type": "Feature",
  "properties": {
    "iso:country":"GB",
    "name:dut_x_preferred":[
        "Fresgoe"
    ],
    "name:eng_x_preferred":[
        "Fresgoe"
    ],
    "name:gla_x_preferred":[
        "Gleann Fhionnainn"
    ],
    "qs_pg:aaroncc":"GB",
    "qs_pg:name":"Fresgoe",
    "qs_pg:name_adm0":"United Kingdom",
    "qs_pg:name_adm1":"Scotland",
    "qs_pg:photos":154,
    "qs_pg:photos_1k":31,
    "qs_pg:photos_9k":1,
    "qs_pg:photos_9r":4,
    "qs_pg:photos_all":154,
    "qs_pg:photos_sr":4,
    "qs_pg:pop_sr":0,
    "qs_pg:qs_pg_placetype":"locality",
    "qs_pg:qs_pg_placetype_gp":"Town",
    "qs_pg:woe_adm0":23424975,
    "woe:adm0_id":23424975,
    "woe:name_adm0":"United Kingdom",
    "woe:name_adm1":"Scotland",
    "woe:placetype":"Town",
    "wof:name":"Fresgoe",
    "wof:placetype":"locality"
},
  "geometry": {"coordinates":[-3.7933395,58.5698995],"type":"Point"}
}