{
  "type": "Feature",
  "properties": {
    "gn:country":"GB",
    "gn:fcode":"PPLL",
    "gn:population":7228,
    "iso:country":"GB",
    "name:bel_x_preferred":[
        "\u0411\u2019\u044e\u0442"
    ],
    "name:bre_x_preferred":[
        "Eilean Bh\u00f2id"
    ],
    "name:ceb_x_preferred":[
        "Island of Bute"
    ],
    "name:cym_x_preferred":[
        "Ynys Bute"
    ],
    "name:deu_x_preferred":[
        "Isle of Bute"
    ],
    "name:ell_x_preferred":[
        "\u039c\u03c0\u03b9\u03bf\u03c5\u03c4"
    ],
    "name:eng_x_preferred":[
        "Isle of Bute"
    ],
    "name:eng_x_variant":[
        "Bute"
    ],
    "name:est_x_preferred":[
        "Bute"
    ],
    "name:eus_x_preferred":[
        "Bute uhartea"
    ],
    "name:gla_x_preferred":[
        "Eilean Bh\u00f2id"
    ],
    "name:gle_x_preferred":[
        "Eilean Bh\u00f3id"
    ],
    "name:jpn_x_preferred":[
        "\u30d3\u30e5\u30fc\u30c8\u5cf6"
    ],
    "name:nld_x_preferred":[
        "Bute"
    ],
    "name:nno_x_preferred":[
        "Isle of Bute"
    ],
    "name:nor_x_preferred":[
        "Bute"
    ],
    "name:pol_x_preferred":[
        "Bute"
    ],
    "name:rus_x_preferred":[
        "\u0411\u044c\u044e\u0442"
    ],
    "name:srp_x_preferred":[
        "\u041e\u0441\u0442\u0440\u0432\u043e \u0411\u0458\u0443\u0442"
    ],
    "name:swe_x_preferred":[
        "Isle of Bute"
    ],
    "name:und_x_variant":[
        "Bure"
    ],
    "name:zho_x_preferred":[
        "\u6bd4\u7279\u5cf6"
    ],
    "qs_pg:aaroncc":"GB",
    "qs_pg:gn_country":"GB",
    "qs_pg:gn_fcode":"PPLL",
    "qs_pg:gn_pop":7228,
    "qs_pg:name":"Isle of Bute",
    "qs_pg:photos_9r":0,
    "qs_pg:photos_sr":0,
    "qs_pg:pop_sr":5,
    "qs_pg:qs_pg_placetype":"locality",
    "wof:name":"Isle of Bute",
    "wof:placetype":"locality",
    "wof:population":7228
},
  "geometry": {"coordinates":[-5.05586,55.83663],"type":"Point"}
}