{
  "type": "Feature",
  "properties": {
    "gn:gn_country":"GB",
    "gn:gn_fcode":"PPLL",
    "gn:gn_pop":7228,
    "gn:population":7228,
    "iso:country":"GB",
    "name:eng_x_preferred":[
        "Isle of Bute"
    ],
    "name:eng_x_variant":[
        "Bute"
    ],
    "name:unk_x_variant":[
        "Bure"
    ],
    "qs_pg:aaroncc":"GB",
    "qs_pg:gn_country":"GB",
    "qs_pg:gn_fcode":"PPLL",
    "qs_pg:gn_pop":7228,
    "qs_pg:name":"Isle of Bute",
    "qs_pg:photos_9r":0,
    "qs_pg:photos_sr":0,
    "qs_pg:pop_sr":5,
    "qs_pg:qs_pg_placetype":"locality",
    "wof:name":"Isle of Bute",
    "wof:placetype":"locality",
    "wof:population":7228
},
  "geometry": {"coordinates":[-5.05586,55.83663],"type":"Point"}
}