{
  "type": "Feature",
  "properties": {
    "gn:admin1_code":"WLS",
    "gn:admin2_code":"X6",
    "gn:admin3_code":"00NQ020",
    "gn:asciiname":"Pren-gwyn",
    "gn:country_code":"GB",
    "gn:dem":201,
    "gn:feature_class":"P",
    "gn:feature_code":"PPL",
    "gn:name":"Pren-gwyn",
    "gn:population":0,
    "gn:timezone":"Europe/London",
    "iso:country":"GB",
    "name:bre_x_preferred":[
        "Pren-gwyn"
    ],
    "name:cym_x_preferred":[
        "Pren-gwyn"
    ],
    "name:eus_x_preferred":[
        "Pren-gwyn"
    ],
    "wof:name":"Pren-gwyn",
    "wof:placetype":"neighbourhood"
},
  "geometry": {"coordinates":[-4.29953,52.07353],"type":"Point"}
}