{
  "type": "Feature",
  "properties": {
    "gn:admin1_code":"ENG",
    "gn:admin2_code":"B1",
    "gn:admin3_code":"00BL003",
    "gn:asciiname":"Chequerbent",
    "gn:country_code":"GB",
    "gn:dem":128,
    "gn:feature_class":"P",
    "gn:feature_code":"PPL",
    "gn:name":"Chequerbent",
    "gn:population":0,
    "gn:timezone":"Europe/London",
    "iso:country":"GB",
    "wof:name":"Chequerbent",
    "wof:placetype":"neighbourhood"
},
  "geometry": {"coordinates":[-2.50138,53.55149],"type":"Point"}
}