{
  "type": "Feature",
  "properties": {
    "iso:country":"GB",
    "name:cat_x_preferred":[
        "Woodside"
    ],
    "name:ceb_x_preferred":[
        "Woodside"
    ],
    "name:deu_x_preferred":[
        "Woodside"
    ],
    "name:fin_x_preferred":[
        "Woodside"
    ],
    "name:fra_x_preferred":[
        "Woodside"
    ],
    "name:fry_x_preferred":[
        "Woodside"
    ],
    "name:hin_x_preferred":[
        "\u0935\u0941\u0921\u0938\u093e\u0907\u0921 \u092a\u093e\u0930\u094d\u0915"
    ],
    "name:ita_x_preferred":[
        "Woodside"
    ],
    "name:kor_x_preferred":[
        "\uc6b0\ub4dc\uc0ac\uc774\ub4dc"
    ],
    "name:nld_x_preferred":[
        "Woodside"
    ],
    "name:pol_x_preferred":[
        "Woodside"
    ],
    "name:por_x_preferred":[
        "Woodside"
    ],
    "name:rus_x_preferred":[
        "\u0412\u0443\u0434\u0441\u0430\u0439\u0434"
    ],
    "name:srp_x_preferred":[
        "\u0412\u0443\u0434\u0441\u0430\u0458\u0434"
    ],
    "name:swe_x_preferred":[
        "Woodside"
    ],
    "name:vol_x_preferred":[
        "Woodside"
    ],
    "qs_pg:aaroncc":"GB",
    "qs_pg:name":"Woodside",
    "qs_pg:name_adm0":"United Kingdom",
    "qs_pg:name_adm1":"Scotland",
    "qs_pg:photos":251,
    "qs_pg:photos_1k":51,
    "qs_pg:photos_9k":1,
    "qs_pg:photos_9r":4,
    "qs_pg:photos_all":251,
    "qs_pg:photos_sr":5,
    "qs_pg:pop_sr":0,
    "qs_pg:qs_pg_placetype":"locality",
    "qs_pg:qs_pg_placetype_gp":"Town",
    "qs_pg:woe_adm0":23424975,
    "woe:adm0_id":23424975,
    "woe:name_adm0":"United Kingdom",
    "woe:name_adm1":"Scotland",
    "woe:placetype":"Town",
    "wof:name":"Woodside",
    "wof:placetype":"neighbourhood"
},
  "geometry": {"coordinates":[-4.280376,55.876177],"type":"Point"}
}