{
  "type": "Feature",
  "properties": {
    "gn:country":"GB",
    "iso:country":"GB",
    "qs_pg:aaroncc":"GB",
    "qs_pg:gn_country":"GB",
    "qs_pg:name":"Balevullin",
    "qs_pg:name_adm0":"United Kingdom",
    "qs_pg:name_adm1":"Scotland",
    "qs_pg:photos":374,
    "qs_pg:photos_1k":76,
    "qs_pg:photos_9k":2,
    "qs_pg:photos_9r":5,
    "qs_pg:photos_all":374,
    "qs_pg:photos_sr":6,
    "qs_pg:pop_sr":0,
    "qs_pg:qs_pg_placetype":"locality",
    "qs_pg:qs_pg_placetype_gp":"Town",
    "qs_pg:woe_adm0":23424975,
    "woe:adm0_id":23424975,
    "woe:name_adm0":"United Kingdom",
    "woe:name_adm1":"Scotland",
    "woe:placetype":"Town",
    "wof:name":"Balevullin",
    "wof:placetype":"locality"
},
  "geometry": {"coordinates":[-6.960697,56.5212495],"type":"Point"}
}