{
  "type": "Feature",
  "properties": {
    "gn:admin1_code":"ENG",
    "gn:admin2_code":"C6",
    "gn:admin3_code":"00HE120",
    "gn:asciiname":"Ruan Laniforne",
    "gn:country_code":"GB",
    "gn:dem":18,
    "gn:feature_class":"P",
    "gn:feature_code":"PPL",
    "gn:name":"Ruan Laniforne",
    "gn:population":0,
    "gn:timezone":"Europe/London",
    "iso:country":"GB",
    "wof:name":"Ruan Laniforne",
    "wof:placetype":"neighbourhood"
},
  "geometry": {"coordinates":[-4.95423,50.24043],"type":"Point"}
}