{
  "type": "Feature",
  "properties": {
    "gn:country": "GB",
    "gn:fcode": "PPL",
    "gn:population": 0,
    "iso:country": "GB",
    "name:eng_x_preferred": [
      "North Chailey"
    ],
    "name:pol_x_preferred": [
      "North Chailey"
    ],
    "name:spa_x_preferred": [
      "North Chailey"
    ],
    "name:swe_x_preferred": [
      "North Chailey"
    ],
    "qs_pg:aaroncc": "GB",
    "qs_pg:gn_country": "GB",
    "qs_pg:gn_fcode": "PPL",
    "qs_pg:gn_pop": 0,
    "qs_pg:name": "North Chailey",
    "qs_pg:name_adm0": "United Kingdom",
    "qs_pg:name_adm1": "England",
    "qs_pg:photos": 762,
    "qs_pg:photos_1k": 154,
    "qs_pg:photos_9k": 3,
    "qs_pg:photos_9r": 6,
    "qs_pg:photos_all": 762,
    "qs_pg:photos_sr": 9,
    "qs_pg:pop_sr": 0,
    "qs_pg:qs_pg_placetype": "locality",
    "qs_pg:qs_pg_placetype_gp": "Town",
    "qs_pg:woe_adm0": 23424975,
    "woe:adm0_id": 23424975,
    "woe:name_adm0": "United Kingdom",
    "woe:name_adm1": "England",
    "woe:placetype": "Town",
    "wof:name": "North Chailey",
    "wof:placetype": "neighbourhood",
    "wof:population": 1021
  },
  "geometry": {"coordinates":[-0.02105,50.93831],"type":"Point"}
}
