{
  "type": "Feature",
  "properties": {
    "gn:population": 866,
    "iso:country": "GB",
    "name:bul_x_preferred": [
      "Даилй"
    ],
    "name:ceb_x_preferred": [
      "Dailly"
    ],
    "name:cym_x_preferred": [
      "Dailly"
    ],
    "name:deu_x_preferred": [
      "Dailly"
    ],
    "name:eng_x_preferred": [
      "Dailly"
    ],
    "name:eus_x_preferred": [
      "Dailly"
    ],
    "name:fas_x_preferred": [
      "دیلی"
    ],
    "name:fra_x_preferred": [
      "Dailly"
    ],
    "name:gla_x_preferred": [
      "Dail Mhaol Chiarain"
    ],
    "name:ita_x_preferred": [
      "Dailly"
    ],
    "name:nld_x_preferred": [
      "Dailly"
    ],
    "name:spa_x_preferred": [
      "Dailly"
    ],
    "name:swe_x_preferred": [
      "Dailly"
    ],
    "qs:a0": "United Kingdom",
    "qs:a1": "*South Ayrshire",
    "qs:a1_lc": "GB11RE0000",
    "qs:a1r": "0Scotland",
    "qs:a1r_lc": "GB11000000",
    "qs:adm0": "United Kingdom",
    "qs:la_lc": "*",
    "qs:level": "locality",
    "qs:loc": "Dailly",
    "qs:loc_alt": "Dailly",
    "qs:pop": 0,
    "qs:type": "buffered point",
    "wd:wordcount": 130,
    "wof:name": "Dailly",
    "wof:placetype": "locality",
    "wof:population": 866
  },
  "geometry": {"coordinates":[-4.727677,55.27757],"type":"Point"}
}
