{
  "type": "Feature",
  "properties": {
    "gn:population":866,
    "iso:country":"GB",
    "name:bul_x_preferred":[
        "\u0414\u0430\u0438\u043b\u0439"
    ],
    "name:ceb_x_preferred":[
        "Dailly"
    ],
    "name:cym_x_preferred":[
        "Dailly"
    ],
    "name:deu_x_preferred":[
        "Dailly"
    ],
    "name:dut_x_preferred":[
        "Dailly"
    ],
    "name:eng_x_preferred":[
        "Dailly"
    ],
    "name:fre_x_preferred":[
        "Dailly"
    ],
    "name:ger_x_preferred":[
        "Dailly"
    ],
    "name:gla_x_preferred":[
        "Dail Mhaol Chiarain"
    ],
    "name:spa_x_preferred":[
        "Dailly"
    ],
    "name:swe_x_preferred":[
        "Dailly"
    ],
    "name:wel_x_preferred":[
        "Dailly"
    ],
    "qs:a0":"United Kingdom",
    "qs:a1":"*South Ayrshire",
    "qs:a1_lc":"GB11RE0000",
    "qs:a1r":"0Scotland",
    "qs:a1r_lc":"GB11000000",
    "qs:adm0":"United Kingdom",
    "qs:la_lc":"*",
    "qs:level":"locality",
    "qs:loc":"Dailly",
    "qs:loc_alt":"Dailly",
    "qs:pop":0,
    "qs:type":"buffered point",
    "wd:wordcount":130,
    "wof:name":"Dailly",
    "wof:placetype":"locality",
    "wof:population":866
},
  "geometry": {"coordinates":[-4.727677,55.27757],"type":"Point"}
}