{
  "type": "Feature",
  "properties": {
    "gn:country":"GB",
    "gn:fcode":"PPL",
    "gn:population":0,
    "iso:country":"GB",
    "name:bul_x_preferred":[
        "\u0413\u043b\u0435\u043d\u0434\u0430\u0440\u0443\u0435\u043b"
    ],
    "name:ceb_x_preferred":[
        "Glendaruel"
    ],
    "name:deu_x_preferred":[
        "Glendaruel"
    ],
    "name:eng_x_preferred":[
        "Glendaruel"
    ],
    "name:eus_x_preferred":[
        "Glendaruel"
    ],
    "name:fra_x_preferred":[
        "Glendaruel"
    ],
    "name:gla_x_preferred":[
        "Gleann Da-Ruail"
    ],
    "name:gle_x_preferred":[
        "Gleann D\u00e1 Ruadhail"
    ],
    "name:gle_x_variant":[
        "Gleann Da-Ruail"
    ],
    "name:nld_x_preferred":[
        "Glendaruel"
    ],
    "name:swe_x_preferred":[
        "Glendaruel"
    ],
    "name:zho_x_preferred":[
        "\u683c\u862d\u9054\u9b6f\u723e"
    ],
    "qs_pg:aaroncc":"GB",
    "qs_pg:gn_country":"GB",
    "qs_pg:gn_fcode":"PPL",
    "qs_pg:gn_pop":0,
    "qs_pg:name":"Clachan of Glendaruel",
    "qs_pg:name_adm0":"United Kingdom",
    "qs_pg:name_adm1":"Scotland",
    "qs_pg:photos":125,
    "qs_pg:photos_1k":25,
    "qs_pg:photos_9k":1,
    "qs_pg:photos_9r":3,
    "qs_pg:photos_all":125,
    "qs_pg:photos_sr":3,
    "qs_pg:pop_sr":0,
    "qs_pg:qs_pg_placetype":"locality",
    "qs_pg:qs_pg_placetype_gp":"Town",
    "qs_pg:woe_adm0":23424975,
    "woe:adm0_id":23424975,
    "woe:name_adm0":"United Kingdom",
    "woe:name_adm1":"Scotland",
    "woe:placetype":"Town",
    "wof:name":"Clachan of Glendaruel",
    "wof:placetype":"locality"
},
  "geometry": {"coordinates":[-5.2143,56.00904],"type":"Point"}
}