{
  "type": "Feature",
  "properties": {
    "iso:country":"GB",
    "name:cat_x_preferred":[
        "Broughton"
    ],
    "name:ceb_x_preferred":[
        "Broughton"
    ],
    "name:deu_x_preferred":[
        "Broughton"
    ],
    "name:eng_x_preferred":[
        "Broughton"
    ],
    "name:fra_x_preferred":[
        "Broughton"
    ],
    "name:hbs_x_preferred":[
        "Broton"
    ],
    "name:ita_x_preferred":[
        "Broughton"
    ],
    "name:nld_x_preferred":[
        "Broughton"
    ],
    "name:nor_x_preferred":[
        "Broughton"
    ],
    "name:pol_x_preferred":[
        "Broughton"
    ],
    "name:por_x_preferred":[
        "Broughton"
    ],
    "name:rus_x_preferred":[
        "\u0411\u0440\u043e\u0442\u043e\u043d"
    ],
    "name:srp_x_preferred":[
        "\u0411\u0440\u043e\u0442\u043e\u043d"
    ],
    "name:swe_x_preferred":[
        "Broughton"
    ],
    "name:ukr_x_preferred":[
        "\u0411\u0440\u043e\u0442\u043e\u043d"
    ],
    "name:vol_x_preferred":[
        "Broughton"
    ],
    "name:zho_x_preferred":[
        "\u5e03\u6d1b\u9813"
    ],
    "qs:gn_adm0_cc":"GB",
    "qs:gn_fcode":"PPL",
    "qs:gn_local":2634889,
    "qs:gn_nam_loc":"woodside",
    "qs:gn_namadm1":"ENG",
    "qs:gn_name":"Broughton",
    "qs:local_max":5266,
    "qs:local_sum":14155,
    "qs:localhoods":6,
    "qs:name":"Broughton",
    "qs:name_adm0":"United Kingdom",
    "qs:name_adm1":"England",
    "qs:name_adm2":"Greater Manchester",
    "qs:name_lau":"Salford Metropolitan Borough",
    "qs:name_local":"Salford",
    "qs:photo_max":48,
    "qs:photo_sum":589,
    "qs:placetype":"Suburb",
    "qs:quad_count":40,
    "qs:woe_adm0":23424975,
    "qs:woe_adm1":24554868,
    "qs:woe_adm2":12602158,
    "qs:woe_funk":"Grouping neighborhood",
    "qs:woe_lau":12695844,
    "qs:woe_local":33887,
    "qs:woe_ver":"7.10.0",
    "wof:lang":[
        "eng"
    ],
    "wof:name":"Broughton",
    "wof:placetype":"neighbourhood"
},
  "geometry": {"coordinates":[-2.265227,53.501533],"type":"Point"}
}