{
  "type": "Feature",
  "properties": {
    "iso:country":"GB",
    "name:eng_x_preferred":[
        "West Knighton"
    ],
    "wof:name":"West Knighton",
    "wof:placetype":"neighbourhood"
},
  "geometry": {"coordinates":[-1.12321383473107,52.60117807381295],"type":"Point"}
}