{
  "type": "Feature",
  "properties": {
    "gn:admin1_code":"ENG",
    "gn:admin2_code":"A4",
    "gn:admin3_code":"00HA032",
    "gn:asciiname":"Norton Hawkfield",
    "gn:country_code":"GB",
    "gn:dem":67,
    "gn:feature_class":"P",
    "gn:feature_code":"PPL",
    "gn:name":"Norton Hawkfield",
    "gn:population":0,
    "gn:timezone":"Europe/London",
    "iso:country":"GB",
    "wof:name":"Norton Hawkfield",
    "wof:placetype":"neighbourhood"
},
  "geometry": {"coordinates":[-2.59179,51.38236],"type":"Point"}
}