{
  "type": "Feature",
  "properties": {
    "iso:country":"GB",
    "name:eng_x_preferred":[
        "Westvale"
    ],
    "qs:gn_adm0_cc":"GB",
    "qs:gn_local":2645313,
    "qs:gn_nam_loc":"kirkby",
    "qs:gn_namadm1":"ENG",
    "qs:local_max":157,
    "qs:local_sum":220,
    "qs:localhoods":2,
    "qs:name":"Westvale",
    "qs:name_adm0":"United Kingdom",
    "qs:name_adm1":"England",
    "qs:name_adm2":"Merseyside",
    "qs:name_lau":"Knowsley Metropolitan Borough",
    "qs:name_local":"Kirkby",
    "qs:photo_max":25,
    "qs:photo_sum":63,
    "qs:placetype":"Suburb",
    "qs:quad_count":6,
    "qs:woe_adm0":23424975,
    "qs:woe_adm1":24554868,
    "qs:woe_adm2":12602161,
    "qs:woe_lau":12695849,
    "qs:woe_local":25361,
    "qs:woe_ver":"7.10.0",
    "wof:lang":[
        "eng"
    ],
    "wof:name":"Westvale",
    "wof:placetype":"neighbourhood"
},
  "geometry": {"coordinates":[-2.89032,53.481949],"type":"Point"}
}