{
  "type": "Feature",
  "properties": {
    "iso:country":"GB",
    "name:eng_x_preferred":[
        "Dane Hills"
    ],
    "name:gle_x_preferred":[
        "Dane Hills"
    ],
    "name:unk_x_variant":[
        "Dane Hills"
    ],
    "qs:gn_local":0,
    "qs:local_max":5184,
    "qs:local_sum":19731,
    "qs:localhoods":13,
    "qs:name":"Dane Hills",
    "qs:name_adm0":"United Kingdom",
    "qs:name_adm1":"England",
    "qs:name_adm2":"Leicestershire",
    "qs:name_lau":"Leicester City",
    "qs:name_local":"Leicester",
    "qs:photo_max":159,
    "qs:photo_sum":947,
    "qs:placetype":"Suburb",
    "qs:quad_count":61,
    "qs:woe_adm0":23424975,
    "qs:woe_adm1":24554868,
    "qs:woe_adm2":12602144,
    "qs:woe_lau":12696154,
    "qs:woe_local":26062,
    "qs:woe_ver":"7.10.0",
    "wd:wordcount":95,
    "wof:lang":[
        "eng"
    ],
    "wof:name":"Dane Hills",
    "wof:placetype":"neighbourhood"
},
  "geometry": {"coordinates":[-1.161084,52.637669],"type":"Point"}
}