{
  "type": "Feature",
  "properties": {
    "gn:admin1_code":"WLS",
    "gn:admin2_code":"Z3",
    "gn:admin3_code":"00PD026",
    "gn:asciiname":"Saint Lythans",
    "gn:country_code":"GB",
    "gn:dem":115,
    "gn:feature_class":"P",
    "gn:feature_code":"PPL",
    "gn:name":"Saint Lythans",
    "gn:population":0,
    "gn:timezone":"Europe/London",
    "iso:country":"GB",
    "name:cym_x_preferred":[
        "Llwyneliddon"
    ],
    "name:eus_x_preferred":[
        "St Lythans"
    ],
    "wof:name":"Saint Lythans",
    "wof:placetype":"neighbourhood"
},
  "geometry": {"coordinates":[-3.28028,51.45083],"type":"Point"}
}