{
  "type": "Feature",
  "properties": {
    "iso:country":"GB",
    "wof:name":"Gaeltacht Quarter",
    "wof:placetype":"neighbourhood"
},
  "geometry": {"coordinates":[-5.95871498456815,54.59607873239328],"type":"Point"}
}