{
  "type": "Feature",
  "properties": {
    "iso:country": "GB",
    "name:bul_x_preferred": [
      "Доуне"
    ],
    "name:ceb_x_preferred": [
      "Doune"
    ],
    "name:cym_x_preferred": [
      "Doune"
    ],
    "name:deu_x_preferred": [
      "Doune"
    ],
    "name:eng_x_preferred": [
      "Doune"
    ],
    "name:eus_x_preferred": [
      "Doune"
    ],
    "name:fas_x_preferred": [
      "دون"
    ],
    "name:fra_x_preferred": [
      "Doune"
    ],
    "name:gla_x_preferred": [
      "An Dùn"
    ],
    "name:gle_x_preferred": [
      "An Dún"
    ],
    "name:glg_x_preferred": [
      "Doune"
    ],
    "name:ita_x_preferred": [
      "Doune"
    ],
    "name:jpn_x_preferred": [
      "ドゥーン"
    ],
    "name:nds_x_preferred": [
      "Doune"
    ],
    "name:nld_x_preferred": [
      "Doune"
    ],
    "name:pol_x_preferred": [
      "Doune"
    ],
    "name:sco_x_preferred": [
      "Doune"
    ],
    "name:spa_x_preferred": [
      "Doune"
    ],
    "name:swe_x_preferred": [
      "Doune"
    ],
    "name:zho_x_preferred": [
      "杜恩"
    ],
    "qs:a0": "United Kingdom",
    "qs:a1": "*Stirling",
    "qs:a1_lc": "GB11RG0000",
    "qs:a1r": "0Scotland",
    "qs:a1r_lc": "GB11000000",
    "qs:adm0": "United Kingdom",
    "qs:la_lc": "*",
    "qs:level": "locality",
    "qs:loc": "Doune",
    "qs:loc_alt": "Doune",
    "qs:pop": 0,
    "qs:type": "buffered point",
    "wd:wordcount": 849,
    "wof:name": "Doune",
    "wof:placetype": "locality"
  },
  "geometry": {"coordinates":[-4.051337,56.189661],"type":"Point"}
}
