{
  "type": "Feature",
  "properties": {
    "gn:population": 7349,
    "iso:country": "GB",
    "name:ben_x_preferred": [
      "র‍্যাডক্লিফ অন ট্রেন্ট"
    ],
    "name:ceb_x_preferred": [
      "Radcliffe on Trent"
    ],
    "name:deu_x_preferred": [
      "Radcliffe on Trent"
    ],
    "name:eng_x_preferred": [
      "Radcliffe on Trent"
    ],
    "name:eng_x_variant": [
      "Radcliffe-on-Trent"
    ],
    "name:fas_x_preferred": [
      "ردکلیف آن ترنت"
    ],
    "name:fra_x_preferred": [
      "Radcliffe on Trent"
    ],
    "name:guj_x_preferred": [
      "રેડક્લિફ-ઓન-ટ્રેન્ટ"
    ],
    "name:ita_x_preferred": [
      "Radcliffe-on-Trent"
    ],
    "name:jpn_x_preferred": [
      "ラドクリフ・オン・トレント"
    ],
    "name:kan_x_preferred": [
      "ರಾಡ್ಕ್ಲಿಫ್-ಆನ್-ಟ್ರೆಂಟ್"
    ],
    "name:kor_x_preferred": [
      "래드클리프 온 트렌트"
    ],
    "name:lit_x_preferred": [
      "Radklif prie Trento"
    ],
    "name:nld_x_preferred": [
      "Radcliffe on Trent"
    ],
    "name:pol_x_preferred": [
      "Radcliffe on Trent"
    ],
    "name:por_x_preferred": [
      "Radcliffe-on-Trent"
    ],
    "name:rus_x_preferred": [
      "Радклиф-он-Трент"
    ],
    "name:spa_x_preferred": [
      "Radcliffe-on-Trent"
    ],
    "name:swe_x_preferred": [
      "Radcliffe on Trent"
    ],
    "name:tam_x_preferred": [
      "ஷார்ல்ஸ்டன்"
    ],
    "name:tel_x_preferred": [
      "రెడ్క్లిఫ్-ఆన్-ట్రెంట్"
    ],
    "name:und_x_variant": [
      "Radcliffe"
    ],
    "name:urd_x_preferred": [
      "رادکلیفی-ون-ترینت"
    ],
    "qs:a0": "United Kingdom",
    "qs:a1": "*Nottinghamshire",
    "qs:a1_lc": "GB12370000",
    "qs:a1r": "0England",
    "qs:a1r_lc": "GB12000000",
    "qs:adm0": "United Kingdom",
    "qs:la_lc": "*",
    "qs:level": "locality",
    "qs:loc": "Radcliffe on Trent",
    "qs:loc_alt": "Radcliffe on Trent",
    "qs:pop": 0,
    "qs:type": "buffered point",
    "wd:wordcount": 681,
    "wof:name": "Radcliffe on Trent",
    "wof:placetype": "neighbourhood",
    "wof:population": 7349
  },
  "geometry": {"coordinates":[-1.029633,52.946593],"type":"Point"}
}
