{
  "type": "Feature",
  "properties": {
    "iso:country": "GB",
    "name:ara_x_preferred": [
      "إلغين"
    ],
    "name:azb_x_preferred": [
      "القین"
    ],
    "name:aze_x_preferred": [
      "Elqin"
    ],
    "name:ben_x_preferred": [
      "এল্গিন শহর"
    ],
    "name:bre_x_preferred": [
      "Eilginn"
    ],
    "name:bul_x_preferred": [
      "Елгин"
    ],
    "name:cat_x_preferred": [
      "Elgin"
    ],
    "name:ceb_x_preferred": [
      "Elgin"
    ],
    "name:ces_x_preferred": [
      "Elgin"
    ],
    "name:cym_x_preferred": [
      "Elgin"
    ],
    "name:dan_x_preferred": [
      "Elgin"
    ],
    "name:deu_x_preferred": [
      "Elgin"
    ],
    "name:eng_x_preferred": [
      "Elgin"
    ],
    "name:epo_x_preferred": [
      "Elgin"
    ],
    "name:eus_x_preferred": [
      "Elgin"
    ],
    "name:fas_x_preferred": [
      "الگین"
    ],
    "name:fin_x_preferred": [
      "Elgin"
    ],
    "name:fra_x_preferred": [
      "Elgin"
    ],
    "name:gla_x_preferred": [
      "Eilginn"
    ],
    "name:gle_x_preferred": [
      "Eilginn"
    ],
    "name:guj_x_preferred": [
      "એલ્ગિન"
    ],
    "name:hbs_x_preferred": [
      "Elgin"
    ],
    "name:heb_x_preferred": [
      "אלגין"
    ],
    "name:ita_x_preferred": [
      "Elgin"
    ],
    "name:jpn_x_preferred": [
      "エルギン"
    ],
    "name:kan_x_preferred": [
      "ಎಲ್ಗಿನ್"
    ],
    "name:kaz_x_preferred": [
      "Элгин"
    ],
    "name:kor_x_preferred": [
      "엘긴"
    ],
    "name:lit_x_preferred": [
      "Elgin Sitis"
    ],
    "name:nld_x_preferred": [
      "Elgin"
    ],
    "name:nno_x_preferred": [
      "Elgin"
    ],
    "name:nob_x_preferred": [
      "Elgin"
    ],
    "name:nor_x_preferred": [
      "Elgin"
    ],
    "name:pol_x_preferred": [
      "Elgin"
    ],
    "name:por_x_preferred": [
      "Elgin"
    ],
    "name:rus_x_preferred": [
      "Элгин"
    ],
    "name:sco_x_preferred": [
      "Elgin"
    ],
    "name:spa_x_preferred": [
      "Elgin"
    ],
    "name:swe_x_preferred": [
      "Elgin"
    ],
    "name:tam_x_preferred": [
      "எல்ஜின்"
    ],
    "name:tel_x_preferred": [
      "ఎలిగిన్"
    ],
    "name:ukr_x_preferred": [
      "Елгін"
    ],
    "name:urd_x_preferred": [
      "یلجین"
    ],
    "name:zho_x_preferred": [
      "埃爾金"
    ],
    "qs:a0": "United Kingdom",
    "qs:a1": "*Moray",
    "qs:a1_lc": "GB11QX0000",
    "qs:a1r": "0Scotland",
    "qs:a1r_lc": "GB11000000",
    "qs:adm0": "United Kingdom",
    "qs:la_lc": "*",
    "qs:level": "locality",
    "qs:loc": "Elgin",
    "qs:loc_alt": "Elgin",
    "qs:pop": 0,
    "qs:type": "buffered point",
    "wd:wordcount": 4953,
    "wof:name": "Elgin",
    "wof:placetype": "locality"
  },
  "geometry": {"coordinates":[-3.320025,57.64802],"type":"Point"}
}
