{
  "type": "Feature",
  "properties": {
    "gn:country":"GB",
    "gn:fcode":"PPL",
    "gn:population":0,
    "iso:country":"GB",
    "name:deu_x_preferred":[
        "Smithton"
    ],
    "name:eng_x_preferred":[
        "Smithton"
    ],
    "name:eus_x_preferred":[
        "Smithton"
    ],
    "name:fra_x_preferred":[
        "Smithton"
    ],
    "name:gle_x_preferred":[
        "Baile a' Ghobhainn"
    ],
    "name:spa_x_preferred":[
        "Smithton"
    ],
    "qs_pg:aaroncc":"GB",
    "qs_pg:gn_country":"GB",
    "qs_pg:gn_fcode":"PPL",
    "qs_pg:gn_pop":0,
    "qs_pg:name":"Smithton",
    "qs_pg:name_adm0":"United Kingdom",
    "qs_pg:name_adm1":"Scotland",
    "qs_pg:photos":42,
    "qs_pg:photos_1k":9,
    "qs_pg:photos_9k":1,
    "qs_pg:photos_9r":2,
    "qs_pg:photos_all":42,
    "qs_pg:photos_sr":2,
    "qs_pg:pop_sr":0,
    "qs_pg:qs_pg_placetype":"locality",
    "qs_pg:qs_pg_placetype_gp":"Town",
    "qs_pg:woe_adm0":23424975,
    "woe:adm0_id":23424975,
    "woe:name_adm0":"United Kingdom",
    "woe:name_adm1":"Scotland",
    "woe:placetype":"Town",
    "wof:name":"Smithton",
    "wof:placetype":"locality",
    "wof:population":2090
},
  "geometry": {"coordinates":[-4.15141,57.47956],"type":"Point"}
}