{
  "type": "Feature",
  "properties": {
    "iso:country": "GB",
    "name:ara_x_preferred": [
      "صندوق"
    ],
    "name:bak_x_preferred": [
      "Ҡумта"
    ],
    "name:bjn_x_preferred": [
      "Kutak"
    ],
    "name:bre_x_preferred": [
      "Kased"
    ],
    "name:cat_x_preferred": [
      "Caixa"
    ],
    "name:cdo_x_preferred": [
      "Ăk-ăk"
    ],
    "name:ces_x_preferred": [
      "Bedna"
    ],
    "name:deu_x_preferred": [
      "Kasten"
    ],
    "name:ell_x_preferred": [
      "Κουτί"
    ],
    "name:epo_x_preferred": [
      "Skatolo"
    ],
    "name:eus_x_preferred": [
      "Kaxa"
    ],
    "name:fas_x_preferred": [
      "جعبه"
    ],
    "name:fin_x_preferred": [
      "Laatikko"
    ],
    "name:fra_x_preferred": [
      "Boîte"
    ],
    "name:gla_x_preferred": [
      "Bogsa"
    ],
    "name:gle_x_preferred": [
      "Bosca"
    ],
    "name:hat_x_preferred": [
      "Bwat"
    ],
    "name:heb_x_preferred": [
      "קופסה"
    ],
    "name:ido_x_preferred": [
      "Buxo"
    ],
    "name:ind_x_preferred": [
      "Kotak"
    ],
    "name:ita_x_preferred": [
      "Scatola"
    ],
    "name:kan_x_preferred": [
      "ಪೆಟ್ಟಿಗೆ"
    ],
    "name:kaz_x_preferred": [
      "Жәшік"
    ],
    "name:khm_x_preferred": [
      "ប្រអប់"
    ],
    "name:lav_x_preferred": [
      "Kaste"
    ],
    "name:msa_x_preferred": [
      "Kotak"
    ],
    "name:nah_x_preferred": [
      "Caxitl"
    ],
    "name:nld_x_preferred": [
      "Doos"
    ],
    "name:pol_x_preferred": [
      "Skrzynia"
    ],
    "name:ron_x_preferred": [
      "Cutie"
    ],
    "name:rus_x_preferred": [
      "Коробка"
    ],
    "name:scn_x_preferred": [
      "Cascia"
    ],
    "name:sco_x_preferred": [
      "Box"
    ],
    "name:spa_x_preferred": [
      "Caja"
    ],
    "name:swa_x_preferred": [
      "Boksi"
    ],
    "name:swe_x_preferred": [
      "Låda"
    ],
    "name:tam_x_preferred": [
      "பெட்டி"
    ],
    "name:tgk_x_preferred": [
      "Қуттӣ"
    ],
    "name:tha_x_preferred": [
      "กล่อง"
    ],
    "name:tur_x_preferred": [
      "Kutu"
    ],
    "name:ukr_x_preferred": [
      "Коробка"
    ],
    "name:xho_x_preferred": [
      "Ibhokisi"
    ],
    "qs_pg:aaroncc": "GB",
    "qs_pg:name": "Box",
    "qs_pg:name_adm0": "United Kingdom",
    "qs_pg:name_adm1": "Wales",
    "qs_pg:photos": 648,
    "qs_pg:photos_1k": 131,
    "qs_pg:photos_9k": 3,
    "qs_pg:photos_9r": 5,
    "qs_pg:photos_all": 648,
    "qs_pg:photos_sr": 8,
    "qs_pg:pop_sr": 0,
    "qs_pg:qs_pg_placetype": "locality",
    "qs_pg:qs_pg_placetype_gp": "Town",
    "qs_pg:woe_adm0": 23424975,
    "woe:adm0_id": 23424975,
    "woe:name_adm0": "United Kingdom",
    "woe:name_adm1": "Wales",
    "woe:placetype": "Town",
    "wof:name": "Box",
    "wof:placetype": "neighbourhood"
  },
  "geometry": {"coordinates":[-4.161211,51.683825],"type":"Point"}
}
