{
  "type": "Feature",
  "properties": {
    "gn:country": "GB",
    "gn:fcode": "PPL",
    "gn:population": 0,
    "iso:country": "GB",
    "name:ces_x_preferred": [
      "Pitt"
    ],
    "name:deu_x_preferred": [
      "Pitt"
    ],
    "name:epo_x_preferred": [
      "Pitt"
    ],
    "name:fas_x_preferred": [
      "پیت"
    ],
    "name:fra_x_preferred": [
      "Pitt"
    ],
    "name:heb_x_preferred": [
      "פיט"
    ],
    "name:ita_x_preferred": [
      "Pitt"
    ],
    "name:jpn_x_preferred": [
      "ピット"
    ],
    "name:kor_x_preferred": [
      "피트"
    ],
    "name:nld_x_preferred": [
      "Pitt"
    ],
    "name:pol_x_preferred": [
      "Pitt"
    ],
    "name:por_x_preferred": [
      "Pitt"
    ],
    "name:rus_x_preferred": [
      "Питт"
    ],
    "name:spa_x_preferred": [
      "Pitt"
    ],
    "name:swe_x_preferred": [
      "Pitt"
    ],
    "name:tur_x_preferred": [
      "Pitt"
    ],
    "name:ukr_x_preferred": [
      "Пітт"
    ],
    "qs_pg:aaroncc": "GB",
    "qs_pg:gn_country": "GB",
    "qs_pg:gn_fcode": "PPL",
    "qs_pg:gn_pop": 0,
    "qs_pg:name": "Pitt",
    "qs_pg:name_adm0": "United Kingdom",
    "qs_pg:name_adm1": "England",
    "qs_pg:photos": 109,
    "qs_pg:photos_1k": 22,
    "qs_pg:photos_9k": 1,
    "qs_pg:photos_9r": 3,
    "qs_pg:photos_all": 109,
    "qs_pg:photos_sr": 3,
    "qs_pg:pop_sr": 0,
    "qs_pg:qs_pg_placetype": "locality",
    "qs_pg:qs_pg_placetype_gp": "Town",
    "qs_pg:woe_adm0": 23424975,
    "woe:adm0_id": 23424975,
    "woe:name_adm0": "United Kingdom",
    "woe:name_adm1": "England",
    "woe:placetype": "Town",
    "wof:name": "Pitt",
    "wof:placetype": "neighbourhood"
  },
  "geometry": {"coordinates":[-1.35887,51.05007],"type":"Point"}
}
