{
  "type": "Feature",
  "properties": {
    "gn:gn_country":"GB",
    "gn:gn_fcode":"PPL",
    "gn:gn_pop":0,
    "iso:country":"GB",
    "name:ces_x_preferred":[
        "Pitt"
    ],
    "name:deu_x_preferred":[
        "Pitt"
    ],
    "name:epo_x_preferred":[
        "Pitt"
    ],
    "name:fas_x_preferred":[
        "\u067e\u06cc\u062a"
    ],
    "name:fra_x_preferred":[
        "Pitt"
    ],
    "name:heb_x_preferred":[
        "\u05e4\u05d9\u05d8"
    ],
    "name:ita_x_preferred":[
        "Pitt"
    ],
    "name:jpn_x_preferred":[
        "\u30d4\u30c3\u30c8"
    ],
    "name:kor_x_preferred":[
        "\ud53c\ud2b8"
    ],
    "name:nld_x_preferred":[
        "Pitt"
    ],
    "name:pol_x_preferred":[
        "Pitt"
    ],
    "name:por_x_preferred":[
        "Pitt"
    ],
    "name:rus_x_preferred":[
        "\u041f\u0438\u0442\u0442"
    ],
    "name:spa_x_preferred":[
        "Pitt"
    ],
    "name:swe_x_preferred":[
        "Pitt"
    ],
    "name:tur_x_preferred":[
        "Pitt"
    ],
    "name:ukr_x_preferred":[
        "\u041f\u0456\u0442\u0442"
    ],
    "qs_pg:aaroncc":"GB",
    "qs_pg:gn_country":"GB",
    "qs_pg:gn_fcode":"PPL",
    "qs_pg:gn_pop":0,
    "qs_pg:name":"Pitt",
    "qs_pg:name_adm0":"United Kingdom",
    "qs_pg:name_adm1":"England",
    "qs_pg:photos":109,
    "qs_pg:photos_1k":22,
    "qs_pg:photos_9k":1,
    "qs_pg:photos_9r":3,
    "qs_pg:photos_all":109,
    "qs_pg:photos_sr":3,
    "qs_pg:pop_sr":0,
    "qs_pg:qs_pg_placetype":"locality",
    "qs_pg:qs_pg_placetype_gp":"Town",
    "qs_pg:woe_adm0":23424975,
    "woe:adm0_id":23424975,
    "woe:name_adm0":"United Kingdom",
    "woe:name_adm1":"England",
    "woe:placetype":"Town",
    "wof:name":"Pitt",
    "wof:placetype":"neighbourhood"
},
  "geometry": {"coordinates":[-1.35887,51.05007],"type":"Point"}
}