{
  "type": "Feature",
  "properties": {
    "iso:country":"GB",
    "name:eng_x_preferred":[
        "Roedean"
    ],
    "qs:gn_adm0_cc":"GB",
    "qs:gn_local":2654710,
    "qs:gn_nam_loc":"brighton",
    "qs:gn_namadm1":"ENG",
    "qs:local_max":5326,
    "qs:local_sum":36385,
    "qs:localhoods":16,
    "qs:name":"Roedean",
    "qs:name_adm0":"United Kingdom",
    "qs:name_adm1":"England",
    "qs:name_adm2":"East Sussex",
    "qs:name_lau":"Brighton and Hove City",
    "qs:name_local":"Brighton",
    "qs:photo_max":236,
    "qs:photo_sum":1461,
    "qs:placetype":"Suburb",
    "qs:quad_count":61,
    "qs:woe_adm0":23424975,
    "qs:woe_adm1":24554868,
    "qs:woe_adm2":12602167,
    "qs:woe_lau":12696151,
    "qs:woe_local":13911,
    "qs:woe_ver":"7.10.0",
    "wof:lang":[
        "eng"
    ],
    "wof:name":"Roedean",
    "wof:placetype":"neighbourhood"
},
  "geometry": {"coordinates":[-0.078433,50.810188],"type":"Point"}
}