{
  "type": "Feature",
  "properties": {
    "gn:admin1_code":"ENG",
    "gn:admin2_code":"D8",
    "gn:admin3_code":"00EJ030",
    "gn:asciiname":"Easington",
    "gn:country_code":"GB",
    "gn:dem":134,
    "gn:feature_class":"P",
    "gn:feature_code":"PPL",
    "gn:name":"Easington",
    "gn:population":7193,
    "gn:timezone":"Europe/London",
    "iso:country":"GB",
    "name:fas_x_preferred":[
        "\u0627\u06cc\u0632\u06cc\u0646\u06af\u062a\u0648\u0646"
    ],
    "name:fra_x_preferred":[
        "Easington"
    ],
    "name:ita_x_preferred":[
        "Easington"
    ],
    "name:nld_x_preferred":[
        "Easington"
    ],
    "name:nor_x_preferred":[
        "Easington"
    ],
    "name:pol_x_preferred":[
        "Easington"
    ],
    "name:ron_x_preferred":[
        "Easington"
    ],
    "name:swe_x_preferred":[
        "Easington"
    ],
    "name:vol_x_preferred":[
        "Easington"
    ],
    "wof:name":"Easington",
    "wof:placetype":"neighbourhood",
    "wof:population":7193
},
  "geometry": {"coordinates":[-1.35917,54.78528000000001],"type":"Point"}
}