{
  "type": "Feature",
  "properties": {
    "gn:admin1_code":"ENG",
    "gn:admin2_code":"D8",
    "gn:admin3_code":"00EJ030",
    "gn:asciiname":"Easington",
    "gn:country_code":"GB",
    "gn:dem":134,
    "gn:feature_class":"P",
    "gn:feature_code":"PPL",
    "gn:name":"Easington",
    "gn:population":7193,
    "gn:timezone":"Europe/London",
    "iso:country":"GB",
    "wof:name":"Easington",
    "wof:placetype":"neighbourhood",
    "wof:population":7193
},
  "geometry": {"coordinates":[-1.35917,54.78528000000001],"type":"Point"}
}