{
  "type": "Feature",
  "properties": {
    "gn:admin1_code":"WLS",
    "gn:admin2_code":"Z4",
    "gn:admin3_code":"00NL008",
    "gn:asciiname":"Cefn Mawr",
    "gn:country_code":"GB",
    "gn:dem":138,
    "gn:feature_class":"P",
    "gn:feature_code":"PPL",
    "gn:name":"Cefn Mawr",
    "gn:population":0,
    "gn:timezone":"Europe/London",
    "iso:country":"GB",
    "name:bre_x_preferred":[
        "Cefn Mawr"
    ],
    "name:bul_x_preferred":[
        "\u041a\u0435\u0432\u043d \u041c\u0430\u0443\u0440"
    ],
    "name:cym_x_preferred":[
        "Cefn Mawr"
    ],
    "name:eus_x_preferred":[
        "Cefn Mawr"
    ],
    "name:fra_x_preferred":[
        "Cefn Mawr"
    ],
    "name:lit_x_preferred":[
        "Kevn Mauras"
    ],
    "name:spa_x_preferred":[
        "Cefn-Mawr"
    ],
    "wof:name":"Cefn Mawr",
    "wof:placetype":"neighbourhood"
},
  "geometry": {"coordinates":[-3.07343,52.97449],"type":"Point"}
}