{
  "type": "Feature",
  "properties": {
    "iso:country":"GB",
    "name:ceb_x_preferred":[
        "Amberley"
    ],
    "name:deu_x_preferred":[
        "Amberley"
    ],
    "name:nld_x_preferred":[
        "Amberley"
    ],
    "name:pol_x_preferred":[
        "Amberley"
    ],
    "name:swe_x_preferred":[
        "Amberley"
    ],
    "qs_pg:aaroncc":"GB",
    "qs_pg:name":"Amberley",
    "qs_pg:name_adm0":"United Kingdom",
    "qs_pg:name_adm1":"England",
    "qs_pg:photos":179,
    "qs_pg:photos_1k":36,
    "qs_pg:photos_9k":1,
    "qs_pg:photos_9r":4,
    "qs_pg:photos_all":179,
    "qs_pg:photos_sr":4,
    "qs_pg:pop_sr":0,
    "qs_pg:qs_pg_placetype":"locality",
    "qs_pg:qs_pg_placetype_gp":"Town",
    "qs_pg:woe_adm0":23424975,
    "woe:adm0_id":23424975,
    "woe:name_adm0":"United Kingdom",
    "woe:name_adm1":"England",
    "woe:placetype":"Town",
    "wof:name":"Amberley",
    "wof:placetype":"neighbourhood"
},
  "geometry": {"coordinates":[-2.221357,51.715217],"type":"Point"}
}