{
  "type": "Feature",
  "properties": {
    "iso:country":"GB",
    "wof:name":"Pollard Park",
    "wof:placetype":"neighbourhood"
},
  "geometry": {"coordinates":[-1.73470241850616,53.79970995691458],"type":"Point"}
}