{
  "type": "Feature",
  "properties": {
    "iso:country":"GB",
    "wof:name":"Cleadon Park",
    "wof:placetype":"neighbourhood"
},
  "geometry": {"coordinates":[-1.40827264174767,54.96772836806844],"type":"Point"}
}