{
  "type": "Feature",
  "properties": {
    "gn:admin1_code":"SCT",
    "gn:admin2_code":"V3",
    "gn:asciiname":"Auckingill",
    "gn:cc2":"GB",
    "gn:country_code":"GB",
    "gn:dem":28,
    "gn:feature_class":"P",
    "gn:feature_code":"PPL",
    "gn:name":"Auckingill",
    "gn:population":0,
    "gn:timezone":"Europe/London",
    "iso:country":"GB",
    "name:und_x_variant":[
        "Auchingill",
        "Auckingill"
    ],
    "wof:name":"Auckingill",
    "wof:placetype":"locality"
},
  "geometry": {"coordinates":[-3.08333,58.56667],"type":"Point"}
}