{
  "type": "Feature",
  "properties": {
    "iso:country":"GB",
    "wof:name":"MIddleton",
    "wof:placetype":"neighbourhood"
},
  "geometry": {"coordinates":[-1.81571232407356,53.93729110985804],"type":"Point"}
}