{
  "type": "Feature",
  "properties": {
    "gn:admin1_code":"WLS",
    "gn:admin2_code":"Y2",
    "gn:admin3_code":"00NC004",
    "gn:asciiname":"Islawr-Dref",
    "gn:country_code":"GB",
    "gn:dem":201,
    "gn:feature_class":"P",
    "gn:feature_code":"PPL",
    "gn:name":"Islawr-Dref",
    "gn:population":0,
    "gn:timezone":"Europe/London",
    "iso:country":"GB",
    "wof:name":"Islawr-Dref",
    "wof:placetype":"neighbourhood"
},
  "geometry": {"coordinates":[-3.95319,52.71823000000001],"type":"Point"}
}