{
  "type": "Feature",
  "properties": {
    "iso:country":"GB",
    "name:eng_x_preferred":[
        "Weeping Cross"
    ],
    "name:unk_x_variant":[
        "Weeping Cross"
    ],
    "qs:gn_local":0,
    "qs:local_max":3240,
    "qs:local_sum":6017,
    "qs:localhoods":5,
    "qs:name":"Weeping Cross",
    "qs:name_adm0":"United Kingdom",
    "qs:name_adm1":"England",
    "qs:name_adm2":"Staffordshire",
    "qs:name_lau":"Stafford Borough",
    "qs:name_local":"Stafford",
    "qs:photo_max":112,
    "qs:photo_sum":690,
    "qs:placetype":"Suburb",
    "qs:quad_count":103,
    "qs:woe_adm0":23424975,
    "qs:woe_adm1":24554868,
    "qs:woe_adm2":12602189,
    "qs:woe_lau":12696077,
    "qs:woe_local":35801,
    "qs:woe_ver":"7.10.0",
    "wof:lang":[
        "eng"
    ],
    "wof:name":"Weeping Cross",
    "wof:placetype":"neighbourhood"
},
  "geometry": {"coordinates":[-2.074611,52.797238],"type":"Point"}
}