{
  "type": "Feature",
  "properties": {
    "iso:country": "GB",
    "name:ceb_x_preferred": [
      "Alstonefield"
    ],
    "name:cym_x_preferred": [
      "Alstonefield"
    ],
    "name:eng_x_preferred": [
      "Stoneyfield"
    ],
    "name:eng_x_variant": [
      "Alstonefield"
    ],
    "name:fra_x_preferred": [
      "Alstonefield"
    ],
    "name:nld_x_preferred": [
      "Alstonefield"
    ],
    "name:pol_x_preferred": [
      "Alstonefield"
    ],
    "name:spa_x_preferred": [
      "Alstonefield"
    ],
    "name:swe_x_preferred": [
      "Alstonefield"
    ],
    "name:und_x_variant": [
      "Alstonfield"
    ],
    "qs:gn_fcode": "PPL",
    "qs:gn_local": 0,
    "qs:gn_namadm1": "ENG",
    "qs:gn_name": "Alstonefield",
    "qs:local_max": 1726,
    "qs:local_sum": 5953,
    "qs:localhoods": 6,
    "qs:name": "Stoneyfield",
    "qs:name_adm0": "United Kingdom",
    "qs:name_adm1": "England",
    "qs:name_adm2": "Greater Manchester",
    "qs:name_lau": "Rochdale Metropolitan Borough",
    "qs:name_local": "Rochdale",
    "qs:photo_max": 148,
    "qs:photo_sum": 623,
    "qs:placetype": "Suburb",
    "qs:quad_count": 40,
    "qs:woe_adm0": 23424975,
    "qs:woe_adm1": 24554868,
    "qs:woe_adm2": 12602158,
    "qs:woe_lau": 12695843,
    "qs:woe_local": 33424,
    "qs:woe_ver": "7.10.0",
    "wd:wordcount": 217,
    "wof:lang": [
      "eng"
    ],
    "wof:name": "Stoneyfield",
    "wof:placetype": "neighbourhood"
  },
  "geometry": {"coordinates":[-2.157889,53.609481],"type":"Point"}
}
