{
  "type": "Feature",
  "properties": {
    "gn:admin1_code":"ENG",
    "gn:admin2_code":"O7",
    "gn:asciiname":"Stanley",
    "gn:country_code":"GB",
    "gn:dem":41,
    "gn:feature_class":"P",
    "gn:feature_code":"PPL",
    "gn:name":"Stanley",
    "gn:population":0,
    "gn:timezone":"Europe/London",
    "iso:country":"GB",
    "name:pol_x_preferred":[
        "Stanley"
    ],
    "wof:name":"Stanley",
    "wof:placetype":"neighbourhood"
},
  "geometry": {"coordinates":[-1.47582,53.7139],"type":"Point"}
}