{
  "type": "Feature",
  "properties": {
    "iso:country": "GB",
    "wof:name": "Market Quarter",
    "wof:placetype": "neighbourhood"
  },
  "geometry": {"coordinates":[-5.92074919092946,54.59536600248347],"type":"Point"}
}
