{
  "type": "Feature",
  "properties": {
    "iso:country": "GB",
    "name:ceb_x_preferred": [
      "Woodcote"
    ],
    "name:deu_x_preferred": [
      "Woodcote"
    ],
    "name:eng_x_preferred": [
      "Woodcote"
    ],
    "name:fra_x_preferred": [
      "Woodcote"
    ],
    "name:nld_x_preferred": [
      "Woodcote"
    ],
    "name:pol_x_preferred": [
      "Woodcote"
    ],
    "name:spa_x_preferred": [
      "Woodcote"
    ],
    "name:swe_x_preferred": [
      "Woodcote"
    ],
    "qs:a0": "United Kingdom",
    "qs:a1": "*Oxfordshire",
    "qs:a1_lc": "GB12380000",
    "qs:a1r": "0England",
    "qs:a1r_lc": "GB12000000",
    "qs:adm0": "United Kingdom",
    "qs:la_lc": "*",
    "qs:level": "locality",
    "qs:loc": "Woodcote",
    "qs:loc_alt": "Woodcote",
    "qs:pop": 0,
    "qs:type": "buffered point",
    "wd:wordcount": 1343,
    "wof:name": "Woodcote",
    "wof:placetype": "neighbourhood"
  },
  "geometry": {"coordinates":[-1.076658,51.533044],"type":"Point"}
}
