{
  "type": "Feature",
  "properties": {
    "gn:country":"GB",
    "gn:fcode":"PPL",
    "gn:population":0,
    "iso:country":"GB",
    "name:ast_x_preferred":[
        "Wolverton"
    ],
    "name:ben_x_preferred":[
        "\u0989\u09b2\u09ad\u09be\u09b0\u09cd\u099f\u09a8"
    ],
    "name:deu_x_preferred":[
        "Wolverton"
    ],
    "name:eng_x_preferred":[
        "Wolverton"
    ],
    "name:fas_x_preferred":[
        "\u0648\u0644\u0648\u0631\u062a\u0648\u0646"
    ],
    "name:fra_x_preferred":[
        "Wolverton"
    ],
    "name:gle_x_preferred":[
        "Wolverton"
    ],
    "name:guj_x_preferred":[
        "\u0ab5\u0acb\u0ab2\u0acd\u0ab5\u0ab0\u0ab0\u0acd\u0a9f\u0aa8"
    ],
    "name:ita_x_preferred":[
        "Wolverton"
    ],
    "name:jpn_x_preferred":[
        "\u30a6\u30a9\u30eb\u30f4\u30a1\u30fc\u30c8\u30f3"
    ],
    "name:kan_x_preferred":[
        "\u0cb5\u0cca\u0cb2\u0ccd\u0cb5\u0cb0\u0ccd\u0c9f\u0ca8\u0ccd"
    ],
    "name:kor_x_preferred":[
        "\uc6b8\ubc84\ud134"
    ],
    "name:lit_x_preferred":[
        "Volvertonas"
    ],
    "name:nld_x_preferred":[
        "Wolverton"
    ],
    "name:nno_x_preferred":[
        "Wolverton"
    ],
    "name:nob_x_preferred":[
        "Wolverton"
    ],
    "name:pol_x_preferred":[
        "Wolverton"
    ],
    "name:por_x_preferred":[
        "Wolverton"
    ],
    "name:rus_x_preferred":[
        "\u0423\u043e\u043b\u0432\u0435\u0440\u0442\u043e\u043d"
    ],
    "name:spa_x_preferred":[
        "Wolverton"
    ],
    "name:tam_x_preferred":[
        "\u0b92\u0bb2\u0bb5\u0bc7\u0bb0\u0bcd\u0b9f\u0bcd\u0b9f\u0bcb\u0ba9\u0bcd"
    ],
    "name:tel_x_preferred":[
        "\u0c35\u0c4b\u0c32\u0c4d\u0c35\u0c46\u0c30\u0c4d\u0c1f\u0c28\u0c4d"
    ],
    "name:urd_x_preferred":[
        "\u0648\u0648\u0644\u0648\u06cc\u0631\u0679\u0646"
    ],
    "name:zho_x_preferred":[
        "\u6c83\u4f5b\u9813"
    ],
    "qs_pg:aaroncc":"GB",
    "qs_pg:gn_country":"GB",
    "qs_pg:gn_fcode":"PPL",
    "qs_pg:gn_pop":0,
    "qs_pg:name":"Wolverton",
    "qs_pg:name_adm0":"United Kingdom",
    "qs_pg:name_adm1":"England",
    "qs_pg:photos":425,
    "qs_pg:photos_1k":86,
    "qs_pg:photos_9k":2,
    "qs_pg:photos_9r":5,
    "qs_pg:photos_all":425,
    "qs_pg:photos_sr":6,
    "qs_pg:pop_sr":0,
    "qs_pg:qs_pg_placetype":"locality",
    "qs_pg:qs_pg_placetype_gp":"Town",
    "qs_pg:woe_adm0":23424975,
    "woe:adm0_id":23424975,
    "woe:name_adm0":"United Kingdom",
    "woe:name_adm1":"England",
    "woe:placetype":"Town",
    "wof:name":"Wolverton",
    "wof:placetype":"neighbourhood"
},
  "geometry": {"coordinates":[-0.81659,52.06246],"type":"Point"}
}