{
  "type": "Feature",
  "properties": {
    "iso:country":"GB",
    "name:cor_x_preferred":[
        "Enysskawen"
    ],
    "name:cym_x_preferred":[
        "Enysskawen"
    ],
    "name:eng_x_preferred":[
        "Enniscaven"
    ],
    "name:eus_x_preferred":[
        "Enysskawen"
    ],
    "qs_pg:aaroncc":"GB",
    "qs_pg:name":"Enniscaven",
    "qs_pg:name_adm0":"United Kingdom",
    "qs_pg:name_adm1":"England",
    "qs_pg:photos":18,
    "qs_pg:photos_1k":4,
    "qs_pg:photos_9k":1,
    "qs_pg:photos_9r":1,
    "qs_pg:photos_all":18,
    "qs_pg:photos_sr":1,
    "qs_pg:pop_sr":0,
    "qs_pg:qs_pg_placetype":"locality",
    "qs_pg:qs_pg_placetype_gp":"Town",
    "qs_pg:woe_adm0":23424975,
    "woe:adm0_id":23424975,
    "woe:name_adm0":"United Kingdom",
    "woe:name_adm1":"England",
    "woe:placetype":"Town",
    "wof:name":"Enniscaven",
    "wof:placetype":"neighbourhood"
},
  "geometry": {"coordinates":[-4.876213,50.404578],"type":"Point"}
}