{
  "type": "Feature",
  "properties": {
    "iso:country":"GB",
    "name:ceb_x_preferred":[
        "Leith Hill"
    ],
    "name:deu_x_preferred":[
        "Leith Hill"
    ],
    "name:lat_x_preferred":[
        "Leith Hill"
    ],
    "name:nno_x_preferred":[
        "Leith Hill"
    ],
    "name:nor_x_preferred":[
        "Leith Hill"
    ],
    "name:swe_x_preferred":[
        "Leith Hill"
    ],
    "qs_pg:aaroncc":"GB",
    "qs_pg:name":"Leith Hill",
    "qs_pg:name_adm0":"United Kingdom",
    "qs_pg:name_adm1":"England",
    "qs_pg:photos":752,
    "qs_pg:photos_1k":152,
    "qs_pg:photos_9k":3,
    "qs_pg:photos_9r":6,
    "qs_pg:photos_all":752,
    "qs_pg:photos_sr":9,
    "qs_pg:pop_sr":0,
    "qs_pg:qs_pg_placetype":"locality",
    "qs_pg:qs_pg_placetype_gp":"Town",
    "qs_pg:woe_adm0":23424975,
    "woe:adm0_id":23424975,
    "woe:name_adm0":"United Kingdom",
    "woe:name_adm1":"England",
    "woe:placetype":"Town",
    "wof:name":"Leith Hill",
    "wof:placetype":"neighbourhood"
},
  "geometry": {"coordinates":[-0.37376,51.172792],"type":"Point"}
}