{
  "type": "Feature",
  "properties": {
    "gn:population": 22291,
    "iso:country": "GB",
    "name:azb_x_preferred": [
      "آربروث"
    ],
    "name:ben_x_preferred": [
      "আরব্রোথ"
    ],
    "name:bul_x_preferred": [
      "Арброут"
    ],
    "name:ceb_x_preferred": [
      "Arbroath"
    ],
    "name:ces_x_preferred": [
      "Arbroath"
    ],
    "name:cym_x_preferred": [
      "Arbroath"
    ],
    "name:deu_x_preferred": [
      "Arbroath"
    ],
    "name:eng_x_preferred": [
      "Arbroath"
    ],
    "name:eus_x_preferred": [
      "Arbroath"
    ],
    "name:fas_x_preferred": [
      "آربروث"
    ],
    "name:fra_x_preferred": [
      "Arbroath"
    ],
    "name:fry_x_preferred": [
      "Arbroath"
    ],
    "name:gla_x_preferred": [
      "Obar Bhrothaig"
    ],
    "name:gle_x_preferred": [
      "Obar Bhrothaig"
    ],
    "name:glg_x_preferred": [
      "Arbroath"
    ],
    "name:guj_x_preferred": [
      "આર્બ્રોથ"
    ],
    "name:heb_x_preferred": [
      "ארברואת'"
    ],
    "name:ita_x_preferred": [
      "Arbroath"
    ],
    "name:jpn_x_preferred": [
      "アーブロース"
    ],
    "name:kan_x_preferred": [
      "ಅರ್ಬ್ರೊತ್"
    ],
    "name:kor_x_preferred": [
      "아르브로스"
    ],
    "name:lit_x_preferred": [
      "Arbrotas"
    ],
    "name:nld_x_preferred": [
      "Arbroath"
    ],
    "name:nno_x_preferred": [
      "Arbroath"
    ],
    "name:nob_x_preferred": [
      "Arbroath"
    ],
    "name:nor_x_preferred": [
      "Arbroath"
    ],
    "name:pol_x_preferred": [
      "Arbroath"
    ],
    "name:por_x_preferred": [
      "Arbroath"
    ],
    "name:rus_x_preferred": [
      "Арброт"
    ],
    "name:sco_x_preferred": [
      "Aiberbrothock"
    ],
    "name:spa_x_preferred": [
      "Arbroath"
    ],
    "name:swe_x_preferred": [
      "Arbroath"
    ],
    "name:tam_x_preferred": [
      "அரப்ரோத்"
    ],
    "name:tel_x_preferred": [
      "అర్బ్రోత్"
    ],
    "name:ukr_x_preferred": [
      "Арброт"
    ],
    "name:urd_x_preferred": [
      "اربرواتھ"
    ],
    "name:zho_x_preferred": [
      "阿布羅斯"
    ],
    "name:zho_x_variant": [
      "阿布洛斯"
    ],
    "qs:a0": "United Kingdom",
    "qs:a1": "*Angus",
    "qs:a1_lc": "GB11QC0000",
    "qs:a1r": "0Scotland",
    "qs:a1r_lc": "GB11000000",
    "qs:adm0": "United Kingdom",
    "qs:la_lc": "*",
    "qs:level": "locality",
    "qs:loc": "Arbroath",
    "qs:loc_alt": "Arbroath",
    "qs:pop": 0,
    "qs:type": "buffered point",
    "wd:wordcount": 7665,
    "wof:name": "Arbroath",
    "wof:placetype": "locality",
    "wof:population": 22291
  },
  "geometry": {"coordinates":[-2.5854,56.563142],"type":"Point"}
}
