{
  "type": "Feature",
  "properties": {
    "iso:country":"GB",
    "wof:name":"West Morton",
    "wof:placetype":"neighbourhood"
},
  "geometry": {"coordinates":[-1.86114539136689,53.8832944327558],"type":"Point"}
}