{
  "type": "Feature",
  "properties": {
    "gn:admin1_code":"SCT",
    "gn:admin2_code":"U2",
    "gn:asciiname":"Carslae",
    "gn:cc2":"GB",
    "gn:country_code":"GB",
    "gn:dem":9,
    "gn:feature_class":"P",
    "gn:feature_code":"PPL",
    "gn:name":"Carslae",
    "gn:population":0,
    "gn:timezone":"Europe/London",
    "iso:country":"GB",
    "name:und_x_variant":[
        "Carslaer",
        "Carslae"
    ],
    "wof:name":"Carslae",
    "wof:placetype":"locality"
},
  "geometry": {"coordinates":[-4.45,54.88333000000001],"type":"Point"}
}