{
  "type": "Feature",
  "properties": {
    "gn:admin1_code":"ENG",
    "gn:admin2_code":"M9",
    "gn:admin3_code":"41UF",
    "gn:admin4_code":"41UF003",
    "gn:asciiname":"Blymhill",
    "gn:country_code":"GB",
    "gn:dem":113,
    "gn:feature_class":"P",
    "gn:feature_code":"PPL",
    "gn:name":"Blymhill",
    "gn:population":0,
    "gn:timezone":"Europe/London",
    "iso:country":"GB",
    "name:pol_x_preferred":[
        "Blymhill"
    ],
    "wof:name":"Blymhill",
    "wof:placetype":"neighbourhood"
},
  "geometry": {"coordinates":[-2.28141,52.70851],"type":"Point"}
}