{
  "type": "Feature",
  "properties": {
    "iso:country":"GB",
    "name:cym_x_preferred":[
        "Croespenmaen"
    ],
    "name:eng_x_preferred":[
        "Croespenmaen"
    ],
    "name:eus_x_preferred":[
        "Croespenmaen"
    ],
    "name:gle_x_preferred":[
        "Croespenmaen"
    ],
    "name:jpn_x_preferred":[
        "\u30af\u30ed\u30a4\u30b9\u30da\u30f3\u30de\u30a4\u30f3"
    ],
    "name:nld_x_preferred":[
        "Croespenmaen"
    ],
    "qs_pg:aaroncc":"GB",
    "qs_pg:name":"Croespenmaen",
    "qs_pg:name_adm0":"United Kingdom",
    "qs_pg:name_adm1":"Wales",
    "qs_pg:photos":89,
    "qs_pg:photos_1k":18,
    "qs_pg:photos_9k":1,
    "qs_pg:photos_9r":3,
    "qs_pg:photos_all":89,
    "qs_pg:photos_sr":3,
    "qs_pg:pop_sr":0,
    "qs_pg:qs_pg_placetype":"locality",
    "qs_pg:qs_pg_placetype_gp":"Town",
    "qs_pg:woe_adm0":23424975,
    "woe:adm0_id":23424975,
    "woe:name_adm0":"United Kingdom",
    "woe:name_adm1":"Wales",
    "woe:placetype":"Town",
    "wof:name":"Croespenmaen",
    "wof:placetype":"neighbourhood"
},
  "geometry": {"coordinates":[-3.165543,51.681549],"type":"Point"}
}