{
  "type": "Feature",
  "properties": {
    "iso:country":"GB",
    "name:eng_x_preferred":[
        "Ainthorpe"
    ],
    "name:fra_x_preferred":[
        "Ainthorpe"
    ],
    "name:gle_x_preferred":[
        "Ainthorpe"
    ],
    "name:nld_x_preferred":[
        "Ainthorpe"
    ],
    "name:pol_x_preferred":[
        "Ainthorpe"
    ],
    "qs_pg:aaroncc":"GB",
    "qs_pg:name":"Ainthorpe",
    "qs_pg:name_adm0":"United Kingdom",
    "qs_pg:name_adm1":"England",
    "qs_pg:photos":147,
    "qs_pg:photos_1k":30,
    "qs_pg:photos_9k":1,
    "qs_pg:photos_9r":3,
    "qs_pg:photos_all":147,
    "qs_pg:photos_sr":3,
    "qs_pg:pop_sr":0,
    "qs_pg:qs_pg_placetype":"locality",
    "qs_pg:qs_pg_placetype_gp":"Town",
    "qs_pg:woe_adm0":23424975,
    "woe:adm0_id":23424975,
    "woe:name_adm0":"United Kingdom",
    "woe:name_adm1":"England",
    "woe:placetype":"Town",
    "wof:name":"Ainthorpe",
    "wof:placetype":"neighbourhood"
},
  "geometry": {"coordinates":[-0.914783,54.453175],"type":"Point"}
}