{
  "type": "Feature",
  "properties": {
    "iso:country": "GB",
    "name:cym_x_preferred": [
      "Frampton Mansell"
    ],
    "name:eng_x_preferred": [
      "Frampton Mansell"
    ],
    "name:fra_x_preferred": [
      "Frampton Mansell"
    ],
    "name:nld_x_preferred": [
      "Frampton Mansell"
    ],
    "name:pol_x_preferred": [
      "Frampton Mansell"
    ],
    "qs_pg:aaroncc": "GB",
    "qs_pg:name": "Frampton Mansell",
    "qs_pg:name_adm0": "United Kingdom",
    "qs_pg:name_adm1": "England",
    "qs_pg:photos": 113,
    "qs_pg:photos_1k": 23,
    "qs_pg:photos_9k": 1,
    "qs_pg:photos_9r": 3,
    "qs_pg:photos_all": 113,
    "qs_pg:photos_sr": 3,
    "qs_pg:pop_sr": 0,
    "qs_pg:qs_pg_placetype": "locality",
    "qs_pg:qs_pg_placetype_gp": "Town",
    "qs_pg:woe_adm0": 23424975,
    "woe:adm0_id": 23424975,
    "woe:name_adm0": "United Kingdom",
    "woe:name_adm1": "England",
    "woe:placetype": "Town",
    "wof:name": "Frampton Mansell",
    "wof:placetype": "neighbourhood"
  },
  "geometry": {"coordinates":[-2.118129,51.714213],"type":"Point"}
}
