{
  "type": "Feature",
  "properties": {
    "iso:country": "GB",
    "name:eng_x_preferred": [
      "Savile Town"
    ],
    "qs:gn_adm0_cc": "GB",
    "qs:gn_local": 2651286,
    "qs:gn_nam_loc": "dewsbury",
    "qs:gn_namadm1": "ENG",
    "qs:local_max": 1410,
    "qs:local_sum": 5702,
    "qs:localhoods": 14,
    "qs:name": "Savile Town",
    "qs:name_adm0": "United Kingdom",
    "qs:name_adm1": "England",
    "qs:name_adm2": "West Yorkshire",
    "qs:name_lau": "Kirklees Metropolitan Borough",
    "qs:name_local": "Dewsbury",
    "qs:photo_max": 93,
    "qs:photo_sum": 217,
    "qs:placetype": "Suburb",
    "qs:quad_count": 20,
    "qs:woe_adm0": 23424975,
    "qs:woe_adm1": 24554868,
    "qs:woe_adm2": 12602197,
    "qs:woe_lau": 12695872,
    "qs:woe_local": 18152,
    "qs:woe_ver": "7.10.0",
    "wd:wordcount": 560,
    "wof:lang": [
      "eng"
    ],
    "wof:name": "Savile Town",
    "wof:placetype": "neighbourhood"
  },
  "geometry": {"coordinates":[-1.628597,53.68505],"type":"Point"}
}
