{
  "type": "Feature",
  "properties": {
    "gn:country": "GB",
    "gn:fcode": "PPL",
    "gn:population": 0,
    "iso:country": "GB",
    "name:bul_x_preferred": [
      "Портбалинтрае"
    ],
    "name:ceb_x_preferred": [
      "Portballintrae"
    ],
    "name:eng_x_preferred": [
      "Portballintrae"
    ],
    "name:eus_x_preferred": [
      "Portballintrae"
    ],
    "name:fas_x_preferred": [
      "پوربلینترا"
    ],
    "name:fra_x_preferred": [
      "Portballintrae"
    ],
    "name:gla_x_preferred": [
      "Port Bhaile an Trá"
    ],
    "name:gle_x_preferred": [
      "Port Bhaile an Trá"
    ],
    "name:ita_x_preferred": [
      "Portballintrae"
    ],
    "name:msa_x_preferred": [
      "Portballintrae"
    ],
    "name:nld_x_preferred": [
      "Portballintrae"
    ],
    "name:pli_x_preferred": [
      "पोर्त्बल्लिन्त्राए"
    ],
    "name:spa_x_preferred": [
      "Portballintrae"
    ],
    "name:swe_x_preferred": [
      "Portballintrae"
    ],
    "qs_pg:aaroncc": "GB",
    "qs_pg:gn_country": "GB",
    "qs_pg:gn_fcode": "PPL",
    "qs_pg:gn_pop": 0,
    "qs_pg:name": "Portballintrae",
    "qs_pg:name_adm0": "United Kingdom",
    "qs_pg:name_adm1": "Northern Ireland",
    "qs_pg:photos": 731,
    "qs_pg:photos_1k": 148,
    "qs_pg:photos_9k": 3,
    "qs_pg:photos_9r": 5,
    "qs_pg:photos_all": 731,
    "qs_pg:photos_sr": 8,
    "qs_pg:pop_sr": 0,
    "qs_pg:qs_pg_placetype": "locality",
    "qs_pg:qs_pg_placetype_gp": "Town",
    "qs_pg:woe_adm0": 23424975,
    "woe:adm0_id": 23424975,
    "woe:name_adm0": "United Kingdom",
    "woe:name_adm1": "Northern Ireland",
    "woe:placetype": "Town",
    "wof:name": "Portballintrae",
    "wof:placetype": "locality"
  },
  "geometry": {"coordinates":[-6.54388,55.21577],"type":"Point"}
}
