{
  "type": "Feature",
  "properties": {
    "gn:gn_country":"GB",
    "gn:gn_fcode":"PPL",
    "gn:gn_pop":0,
    "iso:country":"GB",
    "name:bul_x_preferred":[
        "\u041f\u043e\u0440\u0442\u0431\u0430\u043b\u0438\u043d\u0442\u0440\u0430\u0435"
    ],
    "name:ceb_x_preferred":[
        "Portballintrae"
    ],
    "name:eng_x_preferred":[
        "Portballintrae"
    ],
    "name:eus_x_preferred":[
        "Portballintrae"
    ],
    "name:fas_x_preferred":[
        "\u067e\u0648\u0631\u0628\u0644\u06cc\u0646\u062a\u0631\u0627"
    ],
    "name:fra_x_preferred":[
        "Portballintrae"
    ],
    "name:gla_x_preferred":[
        "Port Bhaile an Tr\u00e1"
    ],
    "name:gle_x_preferred":[
        "Port Bhaile an Tr\u00e1"
    ],
    "name:ita_x_preferred":[
        "Portballintrae"
    ],
    "name:msa_x_preferred":[
        "Portballintrae"
    ],
    "name:nld_x_preferred":[
        "Portballintrae"
    ],
    "name:pli_x_preferred":[
        "\u092a\u094b\u0930\u094d\u0924\u094d\u092c\u0932\u094d\u0932\u093f\u0928\u094d\u0924\u094d\u0930\u093e\u090f"
    ],
    "name:spa_x_preferred":[
        "Portballintrae"
    ],
    "name:swe_x_preferred":[
        "Portballintrae"
    ],
    "qs_pg:aaroncc":"GB",
    "qs_pg:gn_country":"GB",
    "qs_pg:gn_fcode":"PPL",
    "qs_pg:gn_pop":0,
    "qs_pg:name":"Portballintrae",
    "qs_pg:name_adm0":"United Kingdom",
    "qs_pg:name_adm1":"Northern Ireland",
    "qs_pg:photos":731,
    "qs_pg:photos_1k":148,
    "qs_pg:photos_9k":3,
    "qs_pg:photos_9r":5,
    "qs_pg:photos_all":731,
    "qs_pg:photos_sr":8,
    "qs_pg:pop_sr":0,
    "qs_pg:qs_pg_placetype":"locality",
    "qs_pg:qs_pg_placetype_gp":"Town",
    "qs_pg:woe_adm0":23424975,
    "woe:adm0_id":23424975,
    "woe:name_adm0":"United Kingdom",
    "woe:name_adm1":"Northern Ireland",
    "woe:placetype":"Town",
    "wof:name":"Portballintrae",
    "wof:placetype":"locality"
},
  "geometry": {"coordinates":[-6.54388,55.21577],"type":"Point"}
}