{
  "type": "Feature",
  "properties": {
    "gn:admin1_code":"SCT",
    "gn:admin2_code":"V3",
    "gn:asciiname":"Mains of Dalvey",
    "gn:cc2":"GB",
    "gn:country_code":"GB",
    "gn:dem":258,
    "gn:feature_class":"P",
    "gn:feature_code":"PPL",
    "gn:name":"Mains of Dalvey",
    "gn:population":0,
    "gn:timezone":"Europe/London",
    "iso:country":"GB",
    "name:und_x_variant":[
        "Dalvey",
        "Mains of Dalvey"
    ],
    "wof:name":"Mains of Dalvey",
    "wof:placetype":"locality"
},
  "geometry": {"coordinates":[-3.48333,57.35],"type":"Point"}
}