{
  "type": "Feature",
  "properties": {
    "gn:admin1_code":"WLS",
    "gn:admin2_code":"Y7",
    "gn:admin3_code":"00NS008",
    "gn:asciiname":"Leweston",
    "gn:country_code":"GB",
    "gn:dem":62,
    "gn:feature_class":"P",
    "gn:feature_code":"PPL",
    "gn:name":"Leweston",
    "gn:population":0,
    "gn:timezone":"Europe/London",
    "iso:country":"GB",
    "wof:name":"Leweston",
    "wof:placetype":"neighbourhood"
},
  "geometry": {"coordinates":[-4.99389,51.86194],"type":"Point"}
}