{
  "type": "Feature",
  "properties": {
    "iso:country":"GB",
    "name:ita_x_preferred":[
        "Saltergate"
    ],
    "name:jpn_x_preferred":[
        "\u30ec\u30af\u30ea\u30a8\u30fc\u30b7\u30e7\u30f3\u30fb\u30b0\u30e9\u30a6\u30f3\u30c9"
    ],
    "name:pol_x_preferred":[
        "Saltergate"
    ],
    "qs_pg:aaroncc":"GB",
    "qs_pg:name":"Saltergate",
    "qs_pg:name_adm0":"United Kingdom",
    "qs_pg:name_adm1":"England",
    "qs_pg:photos":357,
    "qs_pg:photos_1k":72,
    "qs_pg:photos_9k":2,
    "qs_pg:photos_9r":5,
    "qs_pg:photos_all":357,
    "qs_pg:photos_sr":6,
    "qs_pg:pop_sr":0,
    "qs_pg:qs_pg_placetype":"locality",
    "qs_pg:qs_pg_placetype_gp":"Town",
    "qs_pg:woe_adm0":23424975,
    "woe:adm0_id":23424975,
    "woe:name_adm0":"United Kingdom",
    "woe:name_adm1":"England",
    "woe:placetype":"Town",
    "wof:name":"Saltergate",
    "wof:placetype":"neighbourhood"
},
  "geometry": {"coordinates":[-0.694069,54.334092],"type":"Point"}
}