{
  "type": "Feature",
  "properties": {
    "iso:country":"GB",
    "name:ceb_x_preferred":[
        "Sydenham"
    ],
    "name:deu_x_preferred":[
        "Sydenham"
    ],
    "name:eng_x_preferred":[
        "Sydenham"
    ],
    "name:fra_x_preferred":[
        "Sydenham"
    ],
    "name:nld_x_preferred":[
        "Sydenham"
    ],
    "name:pol_x_preferred":[
        "Sydenham"
    ],
    "name:ron_x_preferred":[
        "Sydenham"
    ],
    "name:swe_x_preferred":[
        "Sydenham"
    ],
    "qs:gn_adm0_cc":"GB",
    "qs:gn_fcode":"PPL",
    "qs:gn_local":2655984,
    "qs:gn_nam_loc":"Belfast, Belfast, Belfast, Northern Ireland, GB",
    "qs:gn_namadm1":"NIR",
    "qs:gn_name":"Sydenham",
    "qs:local_max":5029,
    "qs:local_sum":45783,
    "qs:localhoods":44,
    "qs:name":"Sydenham",
    "qs:name_adm0":"United Kingdom",
    "qs:name_adm1":"Northern Ireland",
    "qs:name_adm2":"Belfast",
    "qs:name_lau":"Belfast",
    "qs:name_local":"Belfast",
    "qs:photo_max":253,
    "qs:photo_sum":1062,
    "qs:placetype":"Suburb",
    "qs:quad_count":42,
    "qs:woe_adm0":23424975,
    "qs:woe_adm1":20070563,
    "qs:woe_adm2":20071112,
    "qs:woe_lau":20078326,
    "qs:woe_local":44544,
    "qs:woe_ver":"7.10.0",
    "wof:lang":[
        "eng"
    ],
    "wof:name":"Sydenham",
    "wof:placetype":"neighbourhood"
},
  "geometry": {"coordinates":[-5.873255,54.607762],"type":"Point"}
}