{
  "type": "Feature",
  "properties": {
    "iso:country":"GB",
    "name:eng_x_preferred":[
        "Hest Bank"
    ],
    "qs:a0":"United Kingdom",
    "qs:a1":"*Lancashire",
    "qs:a1_lc":"GB12300000",
    "qs:a1r":"0England",
    "qs:a1r_lc":"GB12000000",
    "qs:adm0":"United Kingdom",
    "qs:la_lc":"*",
    "qs:level":"locality",
    "qs:loc":"Hest Bank",
    "qs:loc_alt":"Hest Bank",
    "qs:pop":0,
    "qs:type":"buffered point",
    "wof:lang":[
        "eng"
    ],
    "wof:name":"Hest Bank",
    "wof:placetype":"neighbourhood"
},
  "geometry": {"coordinates":[-2.809207,54.091568],"type":"Point"}
}