{
  "type": "Feature",
  "properties": {
    "iso:country":"GB",
    "name:eng_x_preferred":[
        "Morice Town"
    ],
    "name:gle_x_preferred":[
        "Morice Town"
    ],
    "name:urd_x_preferred":[
        "\u0645\u0648\u0631\u0633 \u0679\u0627\u0624\u0646\u060c \u0627\u0646\u06af\u0644\u0633\u062a\u0627\u0646"
    ],
    "name:urd_x_variant":[
        "\u0645\u0648\u0631\u0633 \u0679\u0627\u0624\u0646"
    ],
    "qs:gn_adm0_cc":"GB",
    "qs:gn_local":2640194,
    "qs:gn_nam_loc":"Plymouth",
    "qs:gn_namadm1":"ENG",
    "qs:local_max":8196,
    "qs:local_sum":38773,
    "qs:localhoods":38,
    "qs:name":"Morice Town",
    "qs:name_adm0":"United Kingdom",
    "qs:name_adm1":"England",
    "qs:name_adm2":"Devon",
    "qs:name_lau":"Plymouth City",
    "qs:name_local":"Plymouth",
    "qs:photo_max":70,
    "qs:photo_sum":580,
    "qs:placetype":"Suburb",
    "qs:quad_count":41,
    "qs:woe_adm0":23424975,
    "qs:woe_adm1":24554868,
    "qs:woe_adm2":12602182,
    "qs:woe_lau":12696173,
    "qs:woe_local":32185,
    "qs:woe_ver":"7.10.0",
    "wd:wordcount":86,
    "wof:lang":[
        "eng"
    ],
    "wof:name":"Morice Town",
    "wof:placetype":"neighbourhood"
},
  "geometry": {"coordinates":[-4.181721,50.376689],"type":"Point"}
}