{
  "type": "Feature",
  "properties": {
    "gn:admin1_code":"SCT",
    "gn:admin2_code":"U2",
    "gn:asciiname":"Dunscore",
    "gn:country_code":"GB",
    "gn:dem":110,
    "gn:feature_class":"P",
    "gn:feature_code":"PPL",
    "gn:name":"Dunscore",
    "gn:population":0,
    "gn:timezone":"Europe/London",
    "iso:country":"GB",
    "name:deu_x_preferred":[
        "Dunscore"
    ],
    "name:eus_x_preferred":[
        "Dunscore"
    ],
    "name:gla_x_preferred":[
        "D\u00f9n Sgoir"
    ],
    "name:gle_x_preferred":[
        "D\u00f9n Sgoir"
    ],
    "wof:name":"Dunscore",
    "wof:placetype":"locality"
},
  "geometry": {"coordinates":[-3.77896,55.14005],"type":"Point"}
}