{
  "type": "Feature",
  "properties": {
    "iso:country":"GB",
    "name:bre_x_preferred":[
        "Talywain"
    ],
    "name:cym_x_preferred":[
        "Tal-y-waun"
    ],
    "name:deu_x_preferred":[
        "Talywain"
    ],
    "name:eng_x_preferred":[
        "Talywain"
    ],
    "name:eus_x_preferred":[
        "Talywain"
    ],
    "name:fra_x_preferred":[
        "Talywain"
    ],
    "name:glg_x_preferred":[
        "Talywain"
    ],
    "name:nld_x_preferred":[
        "Talywain"
    ],
    "name:sco_x_preferred":[
        "Talywain"
    ],
    "qs_pg:aaroncc":"GB",
    "qs_pg:name":"Talywain",
    "qs_pg:name_adm0":"United Kingdom",
    "qs_pg:name_adm1":"Wales",
    "qs_pg:photos":42,
    "qs_pg:photos_1k":9,
    "qs_pg:photos_9k":1,
    "qs_pg:photos_9r":2,
    "qs_pg:photos_all":42,
    "qs_pg:photos_sr":2,
    "qs_pg:pop_sr":0,
    "qs_pg:qs_pg_placetype":"locality",
    "qs_pg:qs_pg_placetype_gp":"Town",
    "qs_pg:woe_adm0":23424975,
    "woe:adm0_id":23424975,
    "woe:name_adm0":"United Kingdom",
    "woe:name_adm1":"Wales",
    "woe:placetype":"Town",
    "wof:name":"Talywain",
    "wof:placetype":"neighbourhood"
},
  "geometry": {"coordinates":[-3.082823,51.729167],"type":"Point"}
}