{
  "type": "Feature",
  "properties": {
    "gn:admin1_code": "ENG",
    "gn:admin2_code": "J3",
    "gn:admin3_code": "00FD042",
    "gn:asciiname": "High Risby",
    "gn:country_code": "GB",
    "gn:dem": 68,
    "gn:feature_class": "P",
    "gn:feature_code": "PPL",
    "gn:name": "High Risby",
    "gn:population": 0,
    "gn:timezone": "Europe/London",
    "iso:country": "GB",
    "wof:name": "High Risby",
    "wof:placetype": "neighbourhood"
  },
  "geometry": {"coordinates":[-0.61163,53.62008],"type":"Point"}
}
