{
  "type": "Feature",
  "properties": {
    "gn:admin1_code":"SCT",
    "gn:admin2_code":"T7",
    "gn:asciiname":"Balnaboth",
    "gn:country_code":"GB",
    "gn:dem":266,
    "gn:feature_class":"P",
    "gn:feature_code":"PPL",
    "gn:name":"Balnaboth",
    "gn:population":0,
    "gn:timezone":"Europe/London",
    "iso:country":"GB",
    "wof:name":"Balnaboth",
    "wof:placetype":"locality"
},
  "geometry": {"coordinates":[-3.12271,56.7885],"type":"Point"}
}