{
  "type": "Feature",
  "properties": {
    "iso:country": "GB",
    "name:arg_x_preferred": [
      "Vimbre"
    ],
    "name:cat_x_preferred": [
      "Vímet"
    ],
    "name:eus_x_preferred": [
      "Zume"
    ],
    "name:fra_x_preferred": [
      "Osier"
    ],
    "name:glg_x_preferred": [
      "Vime"
    ],
    "name:heb_x_preferred": [
      "קליעת נצרים"
    ],
    "name:ind_x_preferred": [
      "Anyaman"
    ],
    "name:ita_x_preferred": [
      "Vimine"
    ],
    "name:kor_x_preferred": [
      "고리버들 의자"
    ],
    "name:nah_x_preferred": [
      "Tlacōtl"
    ],
    "name:nld_x_preferred": [
      "Wicker"
    ],
    "name:oci_x_preferred": [
      "Vim"
    ],
    "name:pol_x_preferred": [
      "Wiklina"
    ],
    "name:por_x_preferred": [
      "Vime"
    ],
    "name:spa_x_preferred": [
      "Mimbre"
    ],
    "wof:name": "Wicker",
    "wof:placetype": "neighbourhood"
  },
  "geometry": {"coordinates":[-1.4626850142139,53.38711917043282],"type":"Point"}
}
