{
  "type": "Feature",
  "properties": {
    "iso:country":"GB",
    "name:arg_x_preferred":[
        "Vimbre"
    ],
    "name:cat_x_preferred":[
        "V\u00edmet"
    ],
    "name:eus_x_preferred":[
        "Zume"
    ],
    "name:fra_x_preferred":[
        "Osier"
    ],
    "name:glg_x_preferred":[
        "Vime"
    ],
    "name:heb_x_preferred":[
        "\u05e7\u05dc\u05d9\u05e2\u05ea \u05e0\u05e6\u05e8\u05d9\u05dd"
    ],
    "name:ind_x_preferred":[
        "Anyaman"
    ],
    "name:ita_x_preferred":[
        "Vimine"
    ],
    "name:kor_x_preferred":[
        "\uace0\ub9ac\ubc84\ub4e4 \uc758\uc790"
    ],
    "name:nah_x_preferred":[
        "Tlac\u014dtl"
    ],
    "name:nld_x_preferred":[
        "Wicker"
    ],
    "name:oci_x_preferred":[
        "Vim"
    ],
    "name:pol_x_preferred":[
        "Wiklina"
    ],
    "name:por_x_preferred":[
        "Vime"
    ],
    "name:spa_x_preferred":[
        "Mimbre"
    ],
    "wof:name":"Wicker",
    "wof:placetype":"neighbourhood"
},
  "geometry": {"coordinates":[-1.4626850142139,53.38711917043282],"type":"Point"}
}