{
  "type": "Feature",
  "properties": {
    "iso:country":"GB",
    "wof:name":"Wicker",
    "wof:placetype":"neighbourhood"
},
  "geometry": {"coordinates":[-1.4626850142139,53.38711917043282],"type":"Point"}
}