{
  "type": "Feature",
  "properties": {
    "gn:admin1_code":"SCT",
    "gn:admin2_code":"T6",
    "gn:asciiname":"Ratchhill",
    "gn:country_code":"GB",
    "gn:dem":71,
    "gn:feature_class":"P",
    "gn:feature_code":"PPL",
    "gn:name":"Ratchhill",
    "gn:population":0,
    "gn:timezone":"Europe/London",
    "iso:country":"GB",
    "wof:name":"Ratchhill",
    "wof:placetype":"locality"
},
  "geometry": {"coordinates":[-2.37751,57.24548],"type":"Point"}
}