{
  "type": "Feature",
  "properties": {
    "gn:country":"GB",
    "gn:fcode":"PPL",
    "gn:population":0,
    "iso:country":"GB",
    "name:cym_x_preferred":[
        "Woolacombe"
    ],
    "name:deu_x_preferred":[
        "Woolacombe"
    ],
    "name:eng_x_preferred":[
        "Woolacombe"
    ],
    "name:fas_x_preferred":[
        "\u0648\u0648\u0644\u0627\u06a9\u0627\u0645\u0628"
    ],
    "name:fra_x_preferred":[
        "Woolacombe"
    ],
    "name:ita_x_preferred":[
        "Woolacombe"
    ],
    "name:lat_x_preferred":[
        "Woolacombe"
    ],
    "name:nld_x_preferred":[
        "Woolacombe"
    ],
    "name:pol_x_preferred":[
        "Woolacombe"
    ],
    "name:spa_x_preferred":[
        "Woolacombe"
    ],
    "name:swe_x_preferred":[
        "Woolacombe"
    ],
    "name:ukr_x_preferred":[
        "\u0412\u0443\u043b\u0430\u043a\u043e\u043c\u0431"
    ],
    "qs_pg:aaroncc":"GB",
    "qs_pg:gn_country":"GB",
    "qs_pg:gn_fcode":"PPL",
    "qs_pg:gn_pop":0,
    "qs_pg:name":"Woolacombe",
    "qs_pg:name_adm0":"United Kingdom",
    "qs_pg:name_adm1":"England",
    "qs_pg:photos":5000,
    "qs_pg:photos_1k":1000,
    "qs_pg:photos_9k":22,
    "qs_pg:photos_9r":14,
    "qs_pg:photos_all":5000,
    "qs_pg:photos_sr":24,
    "qs_pg:pop_sr":0,
    "qs_pg:qs_pg_placetype":"locality",
    "qs_pg:qs_pg_placetype_gp":"Town",
    "qs_pg:woe_adm0":23424975,
    "woe:adm0_id":23424975,
    "woe:name_adm0":"United Kingdom",
    "woe:name_adm1":"England",
    "woe:placetype":"Town",
    "wof:name":"Woolacombe",
    "wof:placetype":"neighbourhood",
    "wof:population":840
},
  "geometry": {"coordinates":[-4.20689,51.17296],"type":"Point"}
}