{
  "type": "Feature",
  "properties": {
    "gn:admin1_code":"ENG",
    "gn:admin2_code":"H7",
    "gn:admin3_code":"32UC",
    "gn:admin4_code":"32UC027",
    "gn:asciiname":"New Bolingbroke",
    "gn:country_code":"GB",
    "gn:dem":4,
    "gn:feature_class":"P",
    "gn:feature_code":"PPL",
    "gn:name":"New Bolingbroke",
    "gn:population":289,
    "gn:timezone":"Europe/London",
    "iso:country":"GB",
    "name:cym_x_preferred":[
        "New Bolingbroke"
    ],
    "name:pol_x_preferred":[
        "New Bolingbroke"
    ],
    "wof:name":"New Bolingbroke",
    "wof:placetype":"neighbourhood",
    "wof:population":289
},
  "geometry": {"coordinates":[-0.04807,53.10299000000001],"type":"Point"}
}