{
  "type": "Feature",
  "properties": {
    "iso:country": "GB",
    "wof:name": "Shiregreen",
    "wof:placetype": "neighbourhood"
  },
  "geometry": {"coordinates":[-1.44596265177807,53.43113238184488],"type":"Point"}
}
