{
  "type": "Feature",
  "properties": {
    "iso:country":"GB",
    "name:cym_x_preferred":[
        "Creigiau"
    ],
    "name:eng_x_preferred":[
        "Creigiau"
    ],
    "wof:name":"Creigiau",
    "wof:placetype":"neighbourhood"
},
  "geometry": {"coordinates":[-3.32551407449956,51.52307346204922],"type":"Point"}
}