{
  "type": "Feature",
  "properties": {
    "iso:country":"GB",
    "name:eng_x_preferred":[
        "Upper Battenhall"
    ],
    "qs:gn_adm0_cc":"GB",
    "qs:gn_local":2633563,
    "qs:gn_nam_loc":"Worcester, Worcester, Worcestershire, England, GB",
    "qs:gn_namadm1":"ENG",
    "qs:local_max":5291,
    "qs:local_sum":11154,
    "qs:localhoods":9,
    "qs:name":"Upper Battenhall",
    "qs:name_adm0":"United Kingdom",
    "qs:name_adm1":"England",
    "qs:name_adm2":"Worcestershire",
    "qs:name_lau":"Worcester City",
    "qs:name_local":"Worcester",
    "qs:photo_max":716,
    "qs:photo_sum":1018,
    "qs:placetype":"Suburb",
    "qs:quad_count":55,
    "qs:woe_adm0":23424975,
    "qs:woe_adm1":24554868,
    "qs:woe_adm2":12602192,
    "qs:woe_lau":12695972,
    "qs:woe_local":41117,
    "qs:woe_ver":"7.10.0",
    "wof:lang":[
        "eng"
    ],
    "wof:name":"Upper Battenhall",
    "wof:placetype":"neighbourhood"
},
  "geometry": {"coordinates":[-2.191735,52.181735],"type":"Point"}
}