{
  "type": "Feature",
  "properties": {
    "gn:admin1_code": "ENG",
    "gn:admin2_code": "J6",
    "gn:admin3_code": "00EM003",
    "gn:asciiname": "Warenford",
    "gn:country_code": "GB",
    "gn:dem": 77,
    "gn:feature_class": "P",
    "gn:feature_code": "PPL",
    "gn:name": "Warenford",
    "gn:population": 0,
    "gn:timezone": "Europe/London",
    "iso:country": "GB",
    "wof:name": "Warenford",
    "wof:placetype": "neighbourhood"
  },
  "geometry": {"coordinates":[-1.78442,55.54983000000001],"type":"Point"}
}
