{
  "type": "Feature",
  "properties": {
    "gn:admin1_code":"WLS",
    "gn:admin2_code":"Y2",
    "gn:admin3_code":"00NC012",
    "gn:asciiname":"Sarn",
    "gn:country_code":"GB",
    "gn:dem":79,
    "gn:feature_class":"P",
    "gn:feature_code":"PPL",
    "gn:name":"Sarn",
    "gn:population":0,
    "gn:timezone":"Europe/London",
    "iso:country":"GB",
    "name:bre_x_preferred":[
        "Sarn"
    ],
    "name:ceb_x_preferred":[
        "Sarn"
    ],
    "name:cym_x_preferred":[
        "Sarn"
    ],
    "name:fra_x_preferred":[
        "Sarn"
    ],
    "name:spa_x_preferred":[
        "Sarn"
    ],
    "name:swe_x_preferred":[
        "Sarn"
    ],
    "wof:name":"Sarn",
    "wof:placetype":"neighbourhood"
},
  "geometry": {"coordinates":[-4.61667,52.85],"type":"Point"}
}