{
  "type": "Feature",
  "properties": {
    "gn:admin1_code":"SCT",
    "gn:admin2_code":"V3",
    "gn:asciiname":"Ardnagrask",
    "gn:country_code":"GB",
    "gn:dem":69,
    "gn:feature_class":"P",
    "gn:feature_code":"PPL",
    "gn:name":"Ardnagrask",
    "gn:population":0,
    "gn:timezone":"Europe/London",
    "iso:country":"GB",
    "name:eus_x_preferred":[
        "Ardnagrask"
    ],
    "name:nld_x_preferred":[
        "Ardnagrask"
    ],
    "wof:name":"Ardnagrask",
    "wof:placetype":"locality"
},
  "geometry": {"coordinates":[-4.47779,57.50872],"type":"Point"}
}