{
  "type": "Feature",
  "properties": {
    "gn:admin1_code":"ENG",
    "gn:admin2_code":"G5",
    "gn:admin3_code":"29UP",
    "gn:asciiname":"Higham Wood",
    "gn:country_code":"GB",
    "gn:dem":43,
    "gn:feature_class":"P",
    "gn:feature_code":"PPL",
    "gn:name":"Higham Wood",
    "gn:population":0,
    "gn:timezone":"Europe/London",
    "iso:country":"GB",
    "name:und_x_variant":[
        "Highnam Woods"
    ],
    "wof:name":"Higham Wood",
    "wof:placetype":"neighbourhood"
},
  "geometry": {"coordinates":[0.295,51.21296],"type":"Point"}
}