{
  "type": "Feature",
  "properties": {
    "gn:gn_country":"GB",
    "gn:gn_fcode":"PPL",
    "gn:gn_pop":3939,
    "gn:population":3939,
    "iso:country":"GB",
    "name:unk_x_variant":[
        "Hample"
    ],
    "qs_pg:aaroncc":"GB",
    "qs_pg:gn_country":"GB",
    "qs_pg:gn_fcode":"PPL",
    "qs_pg:gn_pop":3939,
    "qs_pg:name":"Hamble",
    "qs_pg:name_adm0":"United Kingdom",
    "qs_pg:name_adm1":"England",
    "qs_pg:photos":3219,
    "qs_pg:photos_1k":652,
    "qs_pg:photos_9k":14,
    "qs_pg:photos_9r":11,
    "qs_pg:photos_all":3219,
    "qs_pg:photos_sr":20,
    "qs_pg:pop_sr":4,
    "qs_pg:qs_pg_placetype":"locality",
    "qs_pg:qs_pg_placetype_gp":"Town",
    "qs_pg:woe_adm0":23424975,
    "woe:adm0_id":23424975,
    "woe:name_adm0":"United Kingdom",
    "woe:name_adm1":"England",
    "woe:placetype":"Town",
    "wof:name":"Hamble",
    "wof:placetype":"neighbourhood",
    "wof:population":3939
},
  "geometry": {"coordinates":[-1.32432,50.85966],"type":"Point"}
}