{
  "type": "Feature",
  "properties": {
    "gn:gn_country":"GB",
    "gn:gn_fcode":"PPL",
    "gn:gn_pop":0,
    "iso:country":"GB",
    "name:ara_x_preferred":[
        "\u062f\u0627\u0646\u063a\u0644\u0627\u0633"
    ],
    "name:dut_x_preferred":[
        "Dunglass"
    ],
    "name:eng_x_preferred":[
        "Dunglass"
    ],
    "name:fre_x_preferred":[
        "Dunglass"
    ],
    "name:spa_x_preferred":[
        "Dunglass"
    ],
    "qs_pg:aaroncc":"GB",
    "qs_pg:gn_country":"GB",
    "qs_pg:gn_fcode":"PPL",
    "qs_pg:gn_pop":0,
    "qs_pg:name":"Dunglass",
    "qs_pg:name_adm0":"United Kingdom",
    "qs_pg:name_adm1":"Scotland",
    "qs_pg:photos":138,
    "qs_pg:photos_1k":28,
    "qs_pg:photos_9k":1,
    "qs_pg:photos_9r":3,
    "qs_pg:photos_all":138,
    "qs_pg:photos_sr":3,
    "qs_pg:pop_sr":0,
    "qs_pg:qs_pg_placetype":"locality",
    "qs_pg:qs_pg_placetype_gp":"Town",
    "qs_pg:woe_adm0":23424975,
    "woe:adm0_id":23424975,
    "woe:name_adm0":"United Kingdom",
    "woe:name_adm1":"Scotland",
    "woe:placetype":"Town",
    "wof:name":"Dunglass",
    "wof:placetype":"locality"
},
  "geometry": {"coordinates":[-2.36667,55.93333],"type":"Point"}
}