{
  "type": "Feature",
  "properties": {
    "gn:country":"GB",
    "gn:fcode":"PPL",
    "gn:population":496,
    "iso:country":"GB",
    "name:ceb_x_preferred":[
        "Kirkton of Largo"
    ],
    "name:eng_x_preferred":[
        "Upper Largo"
    ],
    "name:eus_x_preferred":[
        "Upper Largo"
    ],
    "name:fra_x_preferred":[
        "Upper Largo"
    ],
    "name:ita_x_preferred":[
        "Upper Largo"
    ],
    "name:jpn_x_preferred":[
        "\u30a2\u30c3\u30d1\u30fc\u30fb\u30e9\u30fc\u30b4"
    ],
    "name:nld_x_preferred":[
        "Upper Largo"
    ],
    "name:swe_x_preferred":[
        "Kirkton of Largo"
    ],
    "qs_pg:aaroncc":"GB",
    "qs_pg:gn_country":"GB",
    "qs_pg:gn_fcode":"PPL",
    "qs_pg:gn_pop":496,
    "qs_pg:name":"Kirkton of Largo",
    "qs_pg:name_adm0":"United Kingdom",
    "qs_pg:name_adm1":"Scotland",
    "qs_pg:photos":156,
    "qs_pg:photos_1k":32,
    "qs_pg:photos_9k":1,
    "qs_pg:photos_9r":4,
    "qs_pg:photos_all":156,
    "qs_pg:photos_sr":4,
    "qs_pg:pop_sr":2,
    "qs_pg:qs_pg_placetype":"locality",
    "qs_pg:qs_pg_placetype_gp":"Town",
    "qs_pg:woe_adm0":23424975,
    "woe:adm0_id":23424975,
    "woe:name_adm0":"United Kingdom",
    "woe:name_adm1":"Scotland",
    "woe:placetype":"Town",
    "wof:name":"Kirkton of Largo",
    "wof:placetype":"locality",
    "wof:population":496
},
  "geometry": {"coordinates":[-2.91667,56.21667],"type":"Point"}
}