{
  "type": "Feature",
  "properties": {
    "iso:country":"GB",
    "name:eng_x_preferred":[
        "Hillmorton"
    ],
    "name:fra_x_preferred":[
        "Hillmorton"
    ],
    "name:nld_x_preferred":[
        "Hillmorton"
    ],
    "name:pol_x_preferred":[
        "Hillmorton"
    ],
    "qs:gn_adm0_cc":"GB",
    "qs:gn_fcode":"PPLX",
    "qs:gn_local":2638978,
    "qs:gn_nam_loc":"rugby",
    "qs:gn_namadm1":"ENG",
    "qs:gn_name":"Hillmorton",
    "qs:local_max":1665,
    "qs:local_sum":6610,
    "qs:localhoods":5,
    "qs:name":"Hillmorton",
    "qs:name_adm0":"United Kingdom",
    "qs:name_adm1":"England",
    "qs:name_adm2":"Warwickshire",
    "qs:name_lau":"Rugby Borough",
    "qs:name_local":"Rugby",
    "qs:photo_max":137,
    "qs:photo_sum":1369,
    "qs:placetype":"Suburb",
    "qs:quad_count":105,
    "qs:woe_adm0":23424975,
    "qs:woe_adm1":24554868,
    "qs:woe_adm2":12602190,
    "qs:woe_lau":12696100,
    "qs:woe_local":33744,
    "qs:woe_ver":"7.10.0",
    "wd:wordcount":198,
    "wof:lang":[
        "eng"
    ],
    "wof:name":"Hillmorton",
    "wof:placetype":"neighbourhood"
},
  "geometry": {"coordinates":[-1.215924,52.362137],"type":"Point"}
}