{
  "type": "Feature",
  "properties": {
    "iso:country":"GB",
    "name:ceb_x_preferred":[
        "Winton"
    ],
    "name:deu_x_preferred":[
        "Winton"
    ],
    "name:eng_x_preferred":[
        "Winton"
    ],
    "name:fin_x_preferred":[
        "Winton"
    ],
    "name:fra_x_preferred":[
        "Winton"
    ],
    "name:ita_x_preferred":[
        "Winton"
    ],
    "name:nds_x_preferred":[
        "Winton"
    ],
    "name:nld_x_preferred":[
        "Winton"
    ],
    "name:pol_x_preferred":[
        "Winton"
    ],
    "name:por_x_preferred":[
        "Winton"
    ],
    "name:rus_x_preferred":[
        "\u0423\u0438\u043d\u0442\u043e\u043d"
    ],
    "name:spa_x_preferred":[
        "Winton"
    ],
    "name:swe_x_preferred":[
        "Winton"
    ],
    "name:vol_x_preferred":[
        "Winton"
    ],
    "qs:gn_fcode":"PPLX",
    "qs:gn_local":0,
    "qs:gn_namadm1":"ENG",
    "qs:gn_name":"Winton",
    "qs:local_max":21166,
    "qs:local_sum":41041,
    "qs:localhoods":7,
    "qs:name":"Winton",
    "qs:name_adm0":"United Kingdom",
    "qs:name_adm1":"England",
    "qs:name_adm2":"Dorset",
    "qs:name_lau":"Bournemouth Borough",
    "qs:name_local":"Bournemouth",
    "qs:photo_max":1027,
    "qs:photo_sum":4863,
    "qs:placetype":"Suburb",
    "qs:quad_count":109,
    "qs:woe_adm0":23424975,
    "qs:woe_adm1":24554868,
    "qs:woe_adm2":12602183,
    "qs:woe_lau":12696150,
    "qs:woe_local":13383,
    "qs:woe_ver":"7.10.0",
    "wd:wordcount":318,
    "wof:lang":[
        "eng"
    ],
    "wof:name":"Winton",
    "wof:placetype":"neighbourhood"
},
  "geometry": {"coordinates":[-1.878759,50.740144],"type":"Point"}
}