{
  "type": "Feature",
  "properties": {
    "gn:country":"GB",
    "gn:fcode":"PPL",
    "gn:population":0,
    "iso:country":"GB",
    "name:azb_x_preferred":[
        "\u0633\u0646\u062a \u0645\u0627\u0648\u0633"
    ],
    "name:cym_x_preferred":[
        "St Mawes"
    ],
    "name:deu_x_preferred":[
        "St Mawes"
    ],
    "name:eng_x_preferred":[
        "St Mawes"
    ],
    "name:eng_x_variant":[
        "Saint Mawes"
    ],
    "name:eus_x_preferred":[
        "St Mawes"
    ],
    "name:fas_x_preferred":[
        "\u0633\u0646\u062a \u0645\u0627\u0648\u0633"
    ],
    "name:gle_x_preferred":[
        "St Mawes"
    ],
    "name:ita_x_preferred":[
        "Saint Mawes"
    ],
    "name:lat_x_preferred":[
        "St Mawes"
    ],
    "name:nld_x_preferred":[
        "St Mawes"
    ],
    "name:pol_x_preferred":[
        "St Mawes"
    ],
    "name:spa_x_preferred":[
        "St Mawes"
    ],
    "name:swe_x_preferred":[
        "St Mawes"
    ],
    "qs_pg:aaroncc":"GB",
    "qs_pg:gn_country":"GB",
    "qs_pg:gn_fcode":"PPL",
    "qs_pg:gn_pop":0,
    "qs_pg:name":"St. Mawes",
    "qs_pg:name_adm0":"United Kingdom",
    "qs_pg:name_adm1":"England",
    "qs_pg:photos":2509,
    "qs_pg:photos_1k":508,
    "qs_pg:photos_9k":11,
    "qs_pg:photos_9r":10,
    "qs_pg:photos_all":2509,
    "qs_pg:photos_sr":18,
    "qs_pg:pop_sr":0,
    "qs_pg:qs_pg_placetype":"locality",
    "qs_pg:qs_pg_placetype_gp":"Town",
    "qs_pg:woe_adm0":23424975,
    "woe:adm0_id":23424975,
    "woe:name_adm0":"United Kingdom",
    "woe:name_adm1":"England",
    "woe:placetype":"Town",
    "wof:name":"St. Mawes",
    "wof:placetype":"neighbourhood"
},
  "geometry": {"coordinates":[-5.01222,50.15944],"type":"Point"}
}