{
  "type": "Feature",
  "properties": {
    "gn:gn_country":"GB",
    "gn:gn_fcode":"PPL",
    "gn:gn_pop":0,
    "iso:country":"GB",
    "name:bre_x_preferred":[
        "Llandegfedd"
    ],
    "name:cym_x_preferred":[
        "Llandegfedd"
    ],
    "name:eng_x_preferred":[
        "Llandegveth"
    ],
    "name:eus_x_preferred":[
        "Llandegveth"
    ],
    "name:fra_x_preferred":[
        "Llandegveth"
    ],
    "name:nld_x_preferred":[
        "Llandegveth"
    ],
    "qs_pg:aaroncc":"GB",
    "qs_pg:gn_country":"GB",
    "qs_pg:gn_fcode":"PPL",
    "qs_pg:gn_pop":0,
    "qs_pg:name":"Llandegveth",
    "qs_pg:name_adm0":"United Kingdom",
    "qs_pg:name_adm1":"Wales",
    "qs_pg:photos":97,
    "qs_pg:photos_1k":20,
    "qs_pg:photos_9k":1,
    "qs_pg:photos_9r":3,
    "qs_pg:photos_all":97,
    "qs_pg:photos_sr":3,
    "qs_pg:pop_sr":0,
    "qs_pg:qs_pg_placetype":"locality",
    "qs_pg:qs_pg_placetype_gp":"Town",
    "qs_pg:woe_adm0":23424975,
    "woe:adm0_id":23424975,
    "woe:name_adm0":"United Kingdom",
    "woe:name_adm1":"Wales",
    "woe:placetype":"Town",
    "wof:name":"Llandegveth",
    "wof:placetype":"neighbourhood"
},
  "geometry": {"coordinates":[-2.95559,51.65476],"type":"Point"}
}