{
  "type": "Feature",
  "properties": {
    "iso:country": "GB",
    "name:azb_x_preferred": [
      "فیترستون"
    ],
    "name:ben_x_preferred": [
      "ফেদারস্টোন"
    ],
    "name:ceb_x_preferred": [
      "Featherstone"
    ],
    "name:cym_x_preferred": [
      "Featherstone"
    ],
    "name:deu_x_preferred": [
      "Featherstone"
    ],
    "name:eng_x_preferred": [
      "Featherstone"
    ],
    "name:fas_x_preferred": [
      "فیترستون"
    ],
    "name:fra_x_preferred": [
      "Featherstone"
    ],
    "name:gle_x_preferred": [
      "Featherstone"
    ],
    "name:guj_x_preferred": [
      "ફીધરસ્ટોન"
    ],
    "name:ita_x_preferred": [
      "Featherstone"
    ],
    "name:jpn_x_preferred": [
      "フェザーストーン"
    ],
    "name:kan_x_preferred": [
      "ಫೆದರ್ ಸ್ಟೋನ್"
    ],
    "name:kor_x_preferred": [
      "페더스톤"
    ],
    "name:lit_x_preferred": [
      "Feterstonas"
    ],
    "name:nld_x_preferred": [
      "Featherstone"
    ],
    "name:nno_x_preferred": [
      "Featherstone"
    ],
    "name:nob_x_preferred": [
      "Featherstone"
    ],
    "name:pol_x_preferred": [
      "Featherstone"
    ],
    "name:por_x_preferred": [
      "Featherstone"
    ],
    "name:ron_x_preferred": [
      "Featherstone"
    ],
    "name:rus_x_preferred": [
      "Феверстоун"
    ],
    "name:spa_x_preferred": [
      "Featherstone"
    ],
    "name:swe_x_preferred": [
      "Featherstone"
    ],
    "name:tam_x_preferred": [
      "பித்தர்ஸ்டோன்"
    ],
    "name:tel_x_preferred": [
      "ఫెదర్స్టోన్"
    ],
    "name:urd_x_preferred": [
      "فیتھیرسٹنی"
    ],
    "qs:a0": "United Kingdom",
    "qs:a1": "*Wakefield",
    "qs:a1_lc": "GB12DB0000",
    "qs:a1r": "0England",
    "qs:a1r_lc": "GB12000000",
    "qs:adm0": "United Kingdom",
    "qs:la_lc": "*",
    "qs:level": "locality",
    "qs:loc": "Featherstone",
    "qs:loc_alt": "Featherstone",
    "qs:pop": 0,
    "qs:type": "buffered point",
    "wd:wordcount": 1308,
    "wof:name": "Featherstone",
    "wof:placetype": "neighbourhood"
  },
  "geometry": {"coordinates":[-1.358393,53.674226],"type":"Point"}
}
