{
  "type": "Feature",
  "properties": {
    "iso:country":"GB",
    "name:ben_x_preferred":[
        "\u0993\u09b2\u09cd\u09a1\u09cd\u09a1 \u0995\u09c7\u099f\u09a8"
    ],
    "name:bul_x_preferred":[
        "\u041e\u0443\u043b\u0434 \u041a\u0430\u0442\u044a\u043d"
    ],
    "name:ceb_x_preferred":[
        "Old Catton"
    ],
    "name:cym_x_preferred":[
        "Old Catton"
    ],
    "name:deu_x_preferred":[
        "Old Catton"
    ],
    "name:eng_x_preferred":[
        "Old Catton"
    ],
    "name:fas_x_preferred":[
        "\u0627\u0648\u0644\u062f \u06a9\u0627\u062a\u0648\u0646"
    ],
    "name:fra_x_preferred":[
        "Old Catton"
    ],
    "name:guj_x_preferred":[
        "\u0a93\u0ab2\u0acd\u0aa1 \u0a95\u0ac7\u0a9f\u0aa8"
    ],
    "name:ita_x_preferred":[
        "Old Catton"
    ],
    "name:jpn_x_preferred":[
        "\u30aa\u30fc\u30eb\u30c9\u30fb\u30ab\u30c3\u30c8\u30f3"
    ],
    "name:kan_x_preferred":[
        "\u0c93\u0cb2\u0ccd\u0ca1\u0ccd \u0c95\u0ccd\u0caf\u0cbe\u0c9f\u0ca8\u0ccd"
    ],
    "name:kor_x_preferred":[
        "\uc62c\ub4dc \uce90\ud2bc"
    ],
    "name:lit_x_preferred":[
        "Old Katonas"
    ],
    "name:nld_x_preferred":[
        "Old Catton"
    ],
    "name:pol_x_preferred":[
        "Old Catton"
    ],
    "name:por_x_preferred":[
        "Old Catton"
    ],
    "name:rus_x_preferred":[
        "\u041e\u043b\u0434-\u041a\u044d\u0442\u0442\u043e\u043d"
    ],
    "name:spa_x_preferred":[
        "Old Catton"
    ],
    "name:swe_x_preferred":[
        "Old Catton"
    ],
    "name:tam_x_preferred":[
        "\u0b93\u0bb2\u0bcd\u0b9f\u0bcd \u0b95\u0bc7\u0b9f\u0bcd\u0b9f\u0ba9\u0bcd"
    ],
    "name:tel_x_preferred":[
        "\u0c13\u0c32\u0c4d\u0c21\u0c4d \u0c15\u0c3e\u0c1f\u0c28\u0c4d"
    ],
    "name:urd_x_preferred":[
        "\u0627\u0648\u0644\u0688\u00a0\u06a9\u0627\u062a\u0679\u0646"
    ],
    "qs:gn_adm0_cc":"GB",
    "qs:gn_local":2641181,
    "qs:gn_nam_loc":"Norwich, Norwich, Norfolk, England, GB",
    "qs:gn_namadm1":"ENG",
    "qs:local_max":5858,
    "qs:local_sum":22582,
    "qs:localhoods":10,
    "qs:name":"Old Catton",
    "qs:name_adm0":"United Kingdom",
    "qs:name_adm1":"England",
    "qs:name_adm2":"Norfolk",
    "qs:name_lau":"Broadland District",
    "qs:name_local":"Norwich",
    "qs:photo_max":179,
    "qs:photo_sum":518,
    "qs:placetype":"Suburb",
    "qs:quad_count":48,
    "qs:woe_adm0":23424975,
    "qs:woe_adm1":24554868,
    "qs:woe_adm2":12602141,
    "qs:woe_lau":12696024,
    "qs:woe_local":30704,
    "qs:woe_ver":"7.10.0",
    "wd:wordcount":1023,
    "wof:lang":[
        "eng"
    ],
    "wof:name":"Old Catton",
    "wof:placetype":"neighbourhood"
},
  "geometry": {"coordinates":[1.315452,52.659603],"type":"Point"}
}