{
  "type": "Feature",
  "properties": {
    "iso:country":"GB",
    "name:bul_x_preferred":[
        "\u041e\u0443\u043b\u0434 \u041a\u0430\u0442\u044a\u043d"
    ],
    "name:ceb_x_preferred":[
        "Old Catton"
    ],
    "name:cym_x_preferred":[
        "Old Catton"
    ],
    "name:eng_x_preferred":[
        "Old Catton"
    ],
    "name:fra_x_preferred":[
        "Old Catton"
    ],
    "name:nld_x_preferred":[
        "Old Catton"
    ],
    "name:pol_x_preferred":[
        "Old Catton"
    ],
    "name:swe_x_preferred":[
        "Old Catton"
    ],
    "name:unk_x_variant":[
        "Old Catton"
    ],
    "qs:gn_adm0_cc":"GB",
    "qs:gn_local":2641181,
    "qs:gn_nam_loc":"Norwich, Norwich, Norfolk, England, GB",
    "qs:gn_namadm1":"ENG",
    "qs:local_max":5858,
    "qs:local_sum":22582,
    "qs:localhoods":10,
    "qs:name":"Old Catton",
    "qs:name_adm0":"United Kingdom",
    "qs:name_adm1":"England",
    "qs:name_adm2":"Norfolk",
    "qs:name_lau":"Broadland District",
    "qs:name_local":"Norwich",
    "qs:photo_max":179,
    "qs:photo_sum":518,
    "qs:placetype":"Suburb",
    "qs:quad_count":48,
    "qs:woe_adm0":23424975,
    "qs:woe_adm1":24554868,
    "qs:woe_adm2":12602141,
    "qs:woe_lau":12696024,
    "qs:woe_local":30704,
    "qs:woe_ver":"7.10.0",
    "wd:wordcount":1023,
    "wof:lang":[
        "eng"
    ],
    "wof:name":"Old Catton",
    "wof:placetype":"neighbourhood"
},
  "geometry": {"coordinates":[1.315452,52.659603],"type":"Point"}
}