{
  "type": "Feature",
  "properties": {
    "iso:country": "GB",
    "name:ben_x_preferred": [
      "ওল্ড্ড কেটন"
    ],
    "name:bul_x_preferred": [
      "Оулд Катън"
    ],
    "name:ceb_x_preferred": [
      "Old Catton"
    ],
    "name:cym_x_preferred": [
      "Old Catton"
    ],
    "name:deu_x_preferred": [
      "Old Catton"
    ],
    "name:eng_x_preferred": [
      "Old Catton"
    ],
    "name:fas_x_preferred": [
      "اولد کاتون"
    ],
    "name:fra_x_preferred": [
      "Old Catton"
    ],
    "name:guj_x_preferred": [
      "ઓલ્ડ કેટન"
    ],
    "name:ita_x_preferred": [
      "Old Catton"
    ],
    "name:jpn_x_preferred": [
      "オールド・カットン"
    ],
    "name:kan_x_preferred": [
      "ಓಲ್ಡ್ ಕ್ಯಾಟನ್"
    ],
    "name:kor_x_preferred": [
      "올드 캐튼"
    ],
    "name:lit_x_preferred": [
      "Old Katonas"
    ],
    "name:nld_x_preferred": [
      "Old Catton"
    ],
    "name:pol_x_preferred": [
      "Old Catton"
    ],
    "name:por_x_preferred": [
      "Old Catton"
    ],
    "name:rus_x_preferred": [
      "Олд-Кэттон"
    ],
    "name:spa_x_preferred": [
      "Old Catton"
    ],
    "name:swe_x_preferred": [
      "Old Catton"
    ],
    "name:tam_x_preferred": [
      "ஓல்ட் கேட்டன்"
    ],
    "name:tel_x_preferred": [
      "ఓల్డ్ కాటన్"
    ],
    "name:urd_x_preferred": [
      "اولڈ کاتٹن"
    ],
    "qs:gn_adm0_cc": "GB",
    "qs:gn_local": 2641181,
    "qs:gn_nam_loc": "Norwich, Norwich, Norfolk, England, GB",
    "qs:gn_namadm1": "ENG",
    "qs:local_max": 5858,
    "qs:local_sum": 22582,
    "qs:localhoods": 10,
    "qs:name": "Old Catton",
    "qs:name_adm0": "United Kingdom",
    "qs:name_adm1": "England",
    "qs:name_adm2": "Norfolk",
    "qs:name_lau": "Broadland District",
    "qs:name_local": "Norwich",
    "qs:photo_max": 179,
    "qs:photo_sum": 518,
    "qs:placetype": "Suburb",
    "qs:quad_count": 48,
    "qs:woe_adm0": 23424975,
    "qs:woe_adm1": 24554868,
    "qs:woe_adm2": 12602141,
    "qs:woe_lau": 12696024,
    "qs:woe_local": 30704,
    "qs:woe_ver": "7.10.0",
    "wd:wordcount": 1023,
    "wof:lang": [
      "eng"
    ],
    "wof:name": "Old Catton",
    "wof:placetype": "neighbourhood"
  },
  "geometry": {"coordinates":[1.315452,52.659603],"type":"Point"}
}
