{
  "type": "Feature",
  "properties": {
    "iso:country":"GB",
    "name:eng_x_preferred":[
        "Hayley Green"
    ],
    "qs:gn_adm0_cc":"GB",
    "qs:gn_fcode":"PPL",
    "qs:gn_local":2647639,
    "qs:gn_nam_loc":"halesowen",
    "qs:gn_namadm1":"ENG",
    "qs:gn_name":"Halfpenny Green",
    "qs:local_max":616,
    "qs:local_sum":1577,
    "qs:localhoods":3,
    "qs:name":"Hayley Green",
    "qs:name_adm0":"United Kingdom",
    "qs:name_adm1":"England",
    "qs:name_adm2":"West Midlands",
    "qs:name_lau":"Dudley Metropolitan Borough",
    "qs:name_local":"Halesowen",
    "qs:photo_max":69,
    "qs:photo_sum":616,
    "qs:placetype":"Suburb",
    "qs:quad_count":70,
    "qs:woe_adm0":23424975,
    "qs:woe_adm1":24554868,
    "qs:woe_adm2":12602191,
    "qs:woe_lau":12695865,
    "qs:woe_local":22165,
    "qs:woe_ver":"7.10.0",
    "wd:wordcount":24,
    "wof:lang":[
        "eng"
    ],
    "wof:name":"Hayley Green",
    "wof:placetype":"neighbourhood"
},
  "geometry": {"coordinates":[-2.093365,52.423142],"type":"Point"}
}