{
  "type": "Feature",
  "properties": {
    "gn:admin1_code":"ENG",
    "gn:admin2_code":"P6",
    "gn:admin3_code":"45UF",
    "gn:admin4_code":"45UF021",
    "gn:asciiname":"Buckman Corner",
    "gn:country_code":"GB",
    "gn:dem":67,
    "gn:feature_class":"P",
    "gn:feature_code":"PPL",
    "gn:name":"Buckman Corner",
    "gn:population":0,
    "gn:timezone":"Europe/London",
    "iso:country":"GB",
    "wof:name":"Buckman Corner",
    "wof:placetype":"neighbourhood"
},
  "geometry": {"coordinates":[-0.43375,51.04997],"type":"Point"}
}