{
  "type": "Feature",
  "properties": {
    "gn:population":2499,
    "iso:country":"GB",
    "name:ceb_x_preferred":[
        "Castlewellan"
    ],
    "name:ces_x_preferred":[
        "Castlewellan"
    ],
    "name:deu_x_preferred":[
        "Castlewellan"
    ],
    "name:eng_x_preferred":[
        "Castlewellan"
    ],
    "name:eus_x_preferred":[
        "Castlewellan"
    ],
    "name:fas_x_preferred":[
        "\u06a9\u0627\u0633\u062a\u0644 \u0648\u0644\u0646"
    ],
    "name:fra_x_preferred":[
        "Castlewellan"
    ],
    "name:gle_x_preferred":[
        "Caisle\u00e1n Uidhil\u00edn"
    ],
    "name:heb_x_preferred":[
        "\u05e7\u05d0\u05e1\u05dc\u05d5\u05d5\u05dc\u05d0\u05df"
    ],
    "name:ita_x_preferred":[
        "Castlewellan"
    ],
    "name:jpn_x_preferred":[
        "\u30ad\u30e3\u30c3\u30b9\u30eb\u30a6\u30a7\u30e9\u30f3"
    ],
    "name:msa_x_preferred":[
        "Castlewellan"
    ],
    "name:nld_x_preferred":[
        "Castlewellan"
    ],
    "name:nob_x_preferred":[
        "Castlewellan"
    ],
    "name:nor_x_preferred":[
        "Castlewellan"
    ],
    "name:pli_x_preferred":[
        "\u0915\u093e\u0938\u094d\u0924\u094d\u0932\u0947\u0935\u0947\u0932\u094d\u0932\u0928"
    ],
    "name:spa_x_preferred":[
        "Castlewellan"
    ],
    "name:swe_x_preferred":[
        "Castlewellan"
    ],
    "qs:a0":"United Kingdom",
    "qs:a1":"*Down",
    "qs:a1_lc":"N_A",
    "qs:a1r":"0Northern Ireland",
    "qs:a1r_lc":"N_A",
    "qs:adm0":"United Kingdom",
    "qs:la_lc":"*",
    "qs:level":"locality",
    "qs:loc":"Castlewellan",
    "qs:loc_alt":"Castlewellan",
    "qs:pop":0,
    "qs:type":"buffered point",
    "wd:wordcount":1043,
    "wof:lang":[
        "eng"
    ],
    "wof:name":"Castlewellan",
    "wof:placetype":"locality",
    "wof:population":2499
},
  "geometry": {"coordinates":[-5.941139,54.25528],"type":"Point"}
}