{
  "type": "Feature",
  "properties": {
    "gn:population":2499,
    "iso:country":"GB",
    "name:ceb_x_preferred":[
        "Castlewellan"
    ],
    "name:cze_x_preferred":[
        "Castlewellan"
    ],
    "name:dut_x_preferred":[
        "Castlewellan"
    ],
    "name:eng_x_preferred":[
        "Castlewellan"
    ],
    "name:fre_x_preferred":[
        "Castlewellan"
    ],
    "name:ger_x_preferred":[
        "Castlewellan"
    ],
    "name:gle_x_preferred":[
        "Caisle\u00e1n Uidhil\u00edn"
    ],
    "name:heb_x_preferred":[
        "\u05e7\u05d0\u05e1\u05dc\u05d5\u05d5\u05dc\u05d0\u05df"
    ],
    "name:may_x_preferred":[
        "Castlewellan"
    ],
    "name:msa_x_preferred":[
        "Castlewellan"
    ],
    "name:nld_x_preferred":[
        "Castlewellan"
    ],
    "name:nob_x_preferred":[
        "Castlewellan"
    ],
    "name:nor_x_preferred":[
        "Castlewellan"
    ],
    "name:pli_x_preferred":[
        "\u0915\u093e\u0938\u094d\u0924\u094d\u0932\u0947\u0935\u0947\u0932\u094d\u0932\u0928"
    ],
    "name:spa_x_preferred":[
        "Castlewellan"
    ],
    "name:swe_x_preferred":[
        "Castlewellan"
    ],
    "qs:a0":"United Kingdom",
    "qs:a1":"*Down",
    "qs:a1_lc":"N_A",
    "qs:a1r":"0Northern Ireland",
    "qs:a1r_lc":"N_A",
    "qs:adm0":"United Kingdom",
    "qs:la_lc":"*",
    "qs:level":"locality",
    "qs:loc":"Castlewellan",
    "qs:loc_alt":"Castlewellan",
    "qs:pop":0,
    "qs:type":"buffered point",
    "wd:wordcount":1043,
    "wof:lang":[
        "eng"
    ],
    "wof:name":"Castlewellan",
    "wof:placetype":"locality",
    "wof:population":2499
},
  "geometry": {"coordinates":[-5.941139,54.25528],"type":"Point"}
}