{
  "type": "Feature",
  "properties": {
    "gn:population": 2499,
    "iso:country": "GB",
    "name:ceb_x_preferred": [
      "Castlewellan"
    ],
    "name:ces_x_preferred": [
      "Castlewellan"
    ],
    "name:deu_x_preferred": [
      "Castlewellan"
    ],
    "name:eng_x_preferred": [
      "Castlewellan"
    ],
    "name:eus_x_preferred": [
      "Castlewellan"
    ],
    "name:fas_x_preferred": [
      "کاستل ولن"
    ],
    "name:fra_x_preferred": [
      "Castlewellan"
    ],
    "name:gle_x_preferred": [
      "Caisleán Uidhilín"
    ],
    "name:heb_x_preferred": [
      "קאסלוולאן"
    ],
    "name:ita_x_preferred": [
      "Castlewellan"
    ],
    "name:msa_x_preferred": [
      "Castlewellan"
    ],
    "name:nld_x_preferred": [
      "Castlewellan"
    ],
    "name:nob_x_preferred": [
      "Castlewellan"
    ],
    "name:nor_x_preferred": [
      "Castlewellan"
    ],
    "name:pli_x_preferred": [
      "कास्त्लेवेल्लन"
    ],
    "name:spa_x_preferred": [
      "Castlewellan"
    ],
    "name:swe_x_preferred": [
      "Castlewellan"
    ],
    "qs:a0": "United Kingdom",
    "qs:a1": "*Down",
    "qs:a1_lc": "N_A",
    "qs:a1r": "0Northern Ireland",
    "qs:a1r_lc": "N_A",
    "qs:adm0": "United Kingdom",
    "qs:la_lc": "*",
    "qs:level": "locality",
    "qs:loc": "Castlewellan",
    "qs:loc_alt": "Castlewellan",
    "qs:pop": 0,
    "qs:type": "buffered point",
    "wd:wordcount": 1043,
    "wof:lang": [
      "eng"
    ],
    "wof:name": "Castlewellan",
    "wof:placetype": "locality",
    "wof:population": 2499
  },
  "geometry": {"coordinates":[-5.941139,54.25528],"type":"Point"}
}
