{
  "type": "Feature",
  "properties": {
    "gn:country":"GB",
    "iso:country":"GB",
    "name:eng_x_preferred":[
        "Borghastan"
    ],
    "name:eus_x_preferred":[
        "Borrowston"
    ],
    "name:fra_x_preferred":[
        "Borghastan"
    ],
    "name:gle_x_preferred":[
        "Borghastan"
    ],
    "name:nld_x_preferred":[
        "Borghastan"
    ],
    "qs_pg:aaroncc":"GB",
    "qs_pg:gn_country":"GB",
    "qs_pg:name":"Borghastan",
    "qs_pg:name_adm0":"United Kingdom",
    "qs_pg:name_adm1":"Scotland",
    "qs_pg:photos":279,
    "qs_pg:photos_1k":57,
    "qs_pg:photos_9k":1,
    "qs_pg:photos_9r":4,
    "qs_pg:photos_all":279,
    "qs_pg:photos_sr":5,
    "qs_pg:pop_sr":0,
    "qs_pg:qs_pg_placetype":"locality",
    "qs_pg:qs_pg_placetype_gp":"Town",
    "qs_pg:woe_adm0":23424975,
    "woe:adm0_id":23424975,
    "woe:name_adm0":"United Kingdom",
    "woe:name_adm1":"Scotland",
    "woe:placetype":"Town",
    "wof:name":"Borghastan",
    "wof:placetype":"locality"
},
  "geometry": {"coordinates":[-6.809062,58.281311],"type":"Point"}
}