{
  "type": "Feature",
  "properties": {
    "gn:admin1_code":"ENG",
    "gn:admin2_code":"M9",
    "gn:admin3_code":"41UD",
    "gn:admin4_code":"41UD015",
    "gn:asciiname":"Haselour",
    "gn:country_code":"GB",
    "gn:dem":63,
    "gn:feature_class":"P",
    "gn:feature_code":"PPL",
    "gn:name":"Haselour",
    "gn:population":0,
    "gn:timezone":"Europe/London",
    "iso:country":"GB",
    "wof:name":"Haselour",
    "wof:placetype":"neighbourhood"
},
  "geometry": {"coordinates":[-1.69704,52.69334],"type":"Point"}
}