{
  "type": "Feature",
  "properties": {
    "gn:admin1_code":"ENG",
    "gn:admin2_code":"J9",
    "gn:admin3_code":"37UG",
    "gn:admin4_code":"37UG071",
    "gn:asciiname":"Staunton in the Vale",
    "gn:country_code":"GB",
    "gn:dem":29,
    "gn:feature_class":"P",
    "gn:feature_code":"PPL",
    "gn:name":"Staunton in the Vale",
    "gn:population":0,
    "gn:timezone":"Europe/London",
    "iso:country":"GB",
    "name:und_x_variant":[
        "Staunton",
        "Staunton in the Vale"
    ],
    "wof:name":"Staunton in the Vale",
    "wof:placetype":"neighbourhood"
},
  "geometry": {"coordinates":[-0.80109,52.98439000000001],"type":"Point"}
}