{
  "type": "Feature",
  "properties": {
    "gn:gn_country":"GB",
    "gn:gn_fcode":"PPL",
    "gn:gn_pop":0,
    "iso:country":"GB",
    "name:bul_x_preferred":[
        "\u0421\u0430\u0443\u0447\u0438\u0435"
    ],
    "name:dut_x_preferred":[
        "Sauchie"
    ],
    "name:eng_x_preferred":[
        "Sauchie"
    ],
    "name:fre_x_preferred":[
        "Sauchie"
    ],
    "name:swe_x_preferred":[
        "Sauchie"
    ],
    "qs_pg:aaroncc":"GB",
    "qs_pg:gn_country":"GB",
    "qs_pg:gn_fcode":"PPL",
    "qs_pg:gn_pop":0,
    "qs_pg:name":"Sauchie",
    "qs_pg:name_adm0":"United Kingdom",
    "qs_pg:name_adm1":"Scotland",
    "qs_pg:photos":72,
    "qs_pg:photos_1k":15,
    "qs_pg:photos_9k":1,
    "qs_pg:photos_9r":2,
    "qs_pg:photos_all":72,
    "qs_pg:photos_sr":2,
    "qs_pg:pop_sr":0,
    "qs_pg:qs_pg_placetype":"locality",
    "qs_pg:qs_pg_placetype_gp":"Town",
    "qs_pg:woe_adm0":23424975,
    "woe:adm0_id":23424975,
    "woe:name_adm0":"United Kingdom",
    "woe:name_adm1":"Scotland",
    "woe:placetype":"Town",
    "wof:name":"Sauchie",
    "wof:placetype":"locality"
},
  "geometry": {"coordinates":[-3.76611,56.12869],"type":"Point"}
}