{
  "type": "Feature",
  "properties": {
    "gn:country": "GB",
    "gn:fcode": "PPL",
    "gn:population": 0,
    "iso:country": "GB",
    "name:bul_x_preferred": [
      "Саучие"
    ],
    "name:ceb_x_preferred": [
      "Sauchie"
    ],
    "name:eng_x_preferred": [
      "Sauchie"
    ],
    "name:fra_x_preferred": [
      "Sauchie"
    ],
    "name:nld_x_preferred": [
      "Sauchie"
    ],
    "name:spa_x_preferred": [
      "Sauchie"
    ],
    "name:swe_x_preferred": [
      "Sauchie"
    ],
    "qs_pg:aaroncc": "GB",
    "qs_pg:gn_country": "GB",
    "qs_pg:gn_fcode": "PPL",
    "qs_pg:gn_pop": 0,
    "qs_pg:name": "Sauchie",
    "qs_pg:name_adm0": "United Kingdom",
    "qs_pg:name_adm1": "Scotland",
    "qs_pg:photos": 72,
    "qs_pg:photos_1k": 15,
    "qs_pg:photos_9k": 1,
    "qs_pg:photos_9r": 2,
    "qs_pg:photos_all": 72,
    "qs_pg:photos_sr": 2,
    "qs_pg:pop_sr": 0,
    "qs_pg:qs_pg_placetype": "locality",
    "qs_pg:qs_pg_placetype_gp": "Town",
    "qs_pg:woe_adm0": 23424975,
    "woe:adm0_id": 23424975,
    "woe:name_adm0": "United Kingdom",
    "woe:name_adm1": "Scotland",
    "woe:placetype": "Town",
    "wof:name": "Sauchie",
    "wof:placetype": "locality"
  },
  "geometry": {"coordinates":[-3.76611,56.12869],"type":"Point"}
}
