{
  "type": "Feature",
  "properties": {
    "iso:country":"GB",
    "name:eng_x_preferred":[
        "East Mains"
    ],
    "name:eng_x_variant":[
        "E Mains"
    ],
    "name:unk_x_variant":[
        "East Mains"
    ],
    "qs:gn_adm0_cc":"GB",
    "qs:gn_local":2650405,
    "qs:gn_nam_loc":"east kilbride",
    "qs:gn_namadm1":"SCT",
    "qs:local_max":926,
    "qs:local_sum":1438,
    "qs:localhoods":2,
    "qs:name":"East Mains",
    "qs:name_adm0":"United Kingdom",
    "qs:name_adm1":"Scotland",
    "qs:name_adm2":"Strathclyde",
    "qs:name_lau":"South Lanarkshire",
    "qs:name_local":"East Kilbride",
    "qs:photo_max":96,
    "qs:photo_sum":926,
    "qs:placetype":"Suburb",
    "qs:quad_count":99,
    "qs:woe_adm0":23424975,
    "qs:woe_adm1":12578048,
    "qs:woe_adm2":12602207,
    "qs:woe_lau":12696210,
    "qs:woe_local":19019,
    "qs:woe_ver":"7.10.0",
    "wof:lang":[
        "eng"
    ],
    "wof:name":"East Mains",
    "wof:placetype":"neighbourhood"
},
  "geometry": {"coordinates":[-4.180843,55.762597],"type":"Point"}
}