{
  "type": "Feature",
  "properties": {
    "iso:country":"GB",
    "name:eng_x_preferred":[
        "Horsell"
    ],
    "name:fra_x_preferred":[
        "Horsell"
    ],
    "name:nld_x_preferred":[
        "Horsell"
    ],
    "name:pol_x_preferred":[
        "Horsell"
    ],
    "name:urd_x_preferred":[
        "\u06c1\u0648\u0631\u0633\u0644"
    ],
    "qs_pg:aaroncc":"GB",
    "qs_pg:name":"Horsell",
    "qs_pg:name_adm0":"United Kingdom",
    "qs_pg:name_adm1":"England",
    "qs_pg:photos":324,
    "qs_pg:photos_1k":66,
    "qs_pg:photos_9k":1,
    "qs_pg:photos_9r":5,
    "qs_pg:photos_all":324,
    "qs_pg:photos_sr":5,
    "qs_pg:pop_sr":0,
    "qs_pg:qs_pg_placetype":"locality",
    "qs_pg:qs_pg_placetype_gp":"Town",
    "qs_pg:woe_adm0":23424975,
    "woe:adm0_id":23424975,
    "woe:name_adm0":"United Kingdom",
    "woe:name_adm1":"England",
    "woe:placetype":"Town",
    "wof:name":"Horsell",
    "wof:placetype":"neighbourhood"
},
  "geometry": {"coordinates":[-0.5746065,51.324691],"type":"Point"}
}