{
  "type": "Feature",
  "properties": {
    "iso:country": "GB",
    "wof:name": "Pittsmoor",
    "wof:placetype": "neighbourhood"
  },
  "geometry": {"coordinates":[-1.46379983837629,53.398148047811],"type":"Point"}
}
