{
  "type": "Feature",
  "properties": {
    "gn:admin1_code":"ENG",
    "gn:admin2_code":"K2",
    "gn:admin3_code":"38UD",
    "gn:admin4_code":"38UD043",
    "gn:asciiname":"Postcombe",
    "gn:country_code":"GB",
    "gn:dem":108,
    "gn:feature_class":"P",
    "gn:feature_code":"PPL",
    "gn:name":"Postcombe",
    "gn:population":0,
    "gn:timezone":"Europe/London",
    "iso:country":"GB",
    "name:pol_x_preferred":[
        "Postcombe"
    ],
    "wof:name":"Postcombe",
    "wof:placetype":"neighbourhood"
},
  "geometry": {"coordinates":[-0.9722,51.6911],"type":"Point"}
}