{
  "type": "Feature",
  "properties": {
    "iso:country":"GB",
    "name:bar_x_preferred":[
        "Sinope"
    ],
    "name:bul_x_preferred":[
        "\u0421\u0438\u043d\u043e\u043f\u0430"
    ],
    "name:cat_x_preferred":[
        "Sinope"
    ],
    "name:ceb_x_preferred":[
        "Sinope"
    ],
    "name:deu_x_preferred":[
        "Sinope"
    ],
    "name:ell_x_preferred":[
        "\u03a3\u03b9\u03bd\u03ce\u03c0\u03b7"
    ],
    "name:epo_x_preferred":[
        "Sinopo"
    ],
    "name:eus_x_preferred":[
        "Sinope"
    ],
    "name:fin_x_preferred":[
        "Sinope"
    ],
    "name:fra_x_preferred":[
        "Sinope"
    ],
    "name:jpn_x_preferred":[
        "\u30b7\u30ce\u30fc\u30da"
    ],
    "name:kor_x_preferred":[
        "\uc2dc\ub178\ud398"
    ],
    "name:lat_x_preferred":[
        "Sinope"
    ],
    "name:nds_x_preferred":[
        "Sinope"
    ],
    "name:nld_x_preferred":[
        "Sinope"
    ],
    "name:nor_x_preferred":[
        "Sinope"
    ],
    "name:pol_x_preferred":[
        "Sinope"
    ],
    "name:por_x_preferred":[
        "Sinope"
    ],
    "name:rus_x_preferred":[
        "\u0421\u0438\u043d\u043e\u043f\u0430"
    ],
    "name:slk_x_preferred":[
        "Sin\u00f3p\u00e9"
    ],
    "name:spa_x_preferred":[
        "Sinope"
    ],
    "name:srp_x_preferred":[
        "\u0421\u0438\u043d\u043e\u043f\u0430"
    ],
    "name:swe_x_preferred":[
        "Sinope"
    ],
    "qs_pg:aaroncc":"GB",
    "qs_pg:name":"Sinope",
    "qs_pg:name_adm0":"United Kingdom",
    "qs_pg:name_adm1":"England",
    "qs_pg:photos":55,
    "qs_pg:photos_1k":11,
    "qs_pg:photos_9k":1,
    "qs_pg:photos_9r":2,
    "qs_pg:photos_all":55,
    "qs_pg:photos_sr":2,
    "qs_pg:pop_sr":0,
    "qs_pg:qs_pg_placetype":"locality",
    "qs_pg:qs_pg_placetype_gp":"Town",
    "qs_pg:woe_adm0":23424975,
    "woe:adm0_id":23424975,
    "woe:name_adm0":"United Kingdom",
    "woe:name_adm1":"England",
    "woe:placetype":"Town",
    "wof:name":"Sinope",
    "wof:placetype":"neighbourhood"
},
  "geometry": {"coordinates":[-1.385564,52.744281],"type":"Point"}
}