{
  "type": "Feature",
  "properties": {
    "iso:country":"GB",
    "wof:name":"Priestthorpe",
    "wof:placetype":"neighbourhood"
},
  "geometry": {"coordinates":[-1.82830083138406,53.85404239158027],"type":"Point"}
}