{
  "type": "Feature",
  "properties": {
    "iso:country":"GB",
    "name:deu_x_preferred":[
        "Delgatie Castle"
    ],
    "name:kaz_x_preferred":[
        "\u0414\u0435\u043b\u0433\u0430\u0442\u0438 \u0441\u0430\u0440\u0430\u0439\u044b"
    ],
    "name:por_x_preferred":[
        "Castelo Delgatie"
    ],
    "name:rus_x_preferred":[
        "\u0417\u0430\u043c\u043e\u043a \u0414\u0435\u043b\u0433\u0430\u0442\u0438"
    ],
    "name:sco_x_preferred":[
        "Delgatie Castle"
    ],
    "name:ukr_x_preferred":[
        "\u0417\u0430\u043c\u043e\u043a \u0414\u0435\u043b\u0433\u0430\u0442\u0456"
    ],
    "qs_pg:aaroncc":"GB",
    "qs_pg:name":"Delgatie Castle",
    "qs_pg:name_adm0":"United Kingdom",
    "qs_pg:name_adm1":"Scotland",
    "qs_pg:photos":277,
    "qs_pg:photos_1k":56,
    "qs_pg:photos_9k":1,
    "qs_pg:photos_9r":4,
    "qs_pg:photos_all":277,
    "qs_pg:photos_sr":5,
    "qs_pg:pop_sr":0,
    "qs_pg:qs_pg_placetype":"locality",
    "qs_pg:qs_pg_placetype_gp":"Town",
    "qs_pg:woe_adm0":23424975,
    "woe:adm0_id":23424975,
    "woe:name_adm0":"United Kingdom",
    "woe:name_adm1":"Scotland",
    "woe:placetype":"Town",
    "wof:name":"Delgatie Castle",
    "wof:placetype":"locality"
},
  "geometry": {"coordinates":[-2.411241,57.545911],"type":"Point"}
}