{
  "type": "Feature",
  "properties": {
    "gn:admin1_code":"WLS",
    "gn:admin2_code":"Y7",
    "gn:admin3_code":"00NS008",
    "gn:asciiname":"Portfield Gate",
    "gn:country_code":"GB",
    "gn:dem":92,
    "gn:feature_class":"P",
    "gn:feature_code":"PPL",
    "gn:name":"Portfield Gate",
    "gn:population":0,
    "gn:timezone":"Europe/London",
    "iso:country":"GB",
    "wof:name":"Portfield Gate",
    "wof:placetype":"neighbourhood"
},
  "geometry": {"coordinates":[-5.01667,51.79917],"type":"Point"}
}