{
  "type": "Feature",
  "properties": {
    "iso:country":"GB",
    "name:eng_x_preferred":[
        "Tinsley Green"
    ],
    "name:fra_x_preferred":[
        "Tinsley Green"
    ],
    "name:pol_x_preferred":[
        "Tinsley Green"
    ],
    "name:unk_x_variant":[
        "Tinsley Green"
    ],
    "qs:gn_adm0_cc":"GB",
    "qs:gn_local":2652053,
    "qs:gn_nam_loc":"crawley",
    "qs:gn_namadm1":"ENG",
    "qs:local_max":3302,
    "qs:local_sum":11152,
    "qs:localhoods":7,
    "qs:name":"Tinsley Green",
    "qs:name_adm0":"United Kingdom",
    "qs:name_adm1":"England",
    "qs:name_adm2":"West Sussex",
    "qs:name_lau":"Crawley Borough",
    "qs:name_local":"Crawley",
    "qs:photo_max":105,
    "qs:photo_sum":422,
    "qs:placetype":"Suburb",
    "qs:quad_count":30,
    "qs:woe_adm0":23424975,
    "qs:woe_adm1":24554868,
    "qs:woe_adm2":12602177,
    "qs:woe_lau":12696106,
    "qs:woe_local":17233,
    "qs:woe_ver":"7.10.0",
    "wd:wordcount":1996,
    "wof:lang":[
        "eng"
    ],
    "wof:name":"Tinsley Green",
    "wof:placetype":"neighbourhood"
},
  "geometry": {"coordinates":[-0.163482,51.137934],"type":"Point"}
}