{
  "type": "Feature",
  "properties": {
    "gn:country": "GB",
    "gn:fcode": "PPL",
    "gn:population": 0,
    "iso:country": "GB",
    "name:eng_x_preferred": [
      "Stourton"
    ],
    "name:fra_x_preferred": [
      "Stourton"
    ],
    "name:nld_x_preferred": [
      "Stourton"
    ],
    "name:pol_x_preferred": [
      "Stourton"
    ],
    "name:pol_x_variant": [
      "Stourton"
    ],
    "name:por_x_preferred": [
      "Stourton"
    ],
    "qs_pg:aaroncc": "GB",
    "qs_pg:gn_country": "GB",
    "qs_pg:gn_fcode": "PPL",
    "qs_pg:gn_pop": 0,
    "qs_pg:name": "Stourton",
    "qs_pg:name_adm0": "United Kingdom",
    "qs_pg:name_adm1": "England",
    "qs_pg:photos": 4997,
    "qs_pg:photos_1k": 1000,
    "qs_pg:photos_9k": 22,
    "qs_pg:photos_9r": 14,
    "qs_pg:photos_all": 4997,
    "qs_pg:photos_sr": 24,
    "qs_pg:pop_sr": 0,
    "qs_pg:qs_pg_placetype": "locality",
    "qs_pg:qs_pg_placetype_gp": "Town",
    "qs_pg:woe_adm0": 23424975,
    "woe:adm0_id": 23424975,
    "woe:name_adm0": "United Kingdom",
    "woe:name_adm1": "England",
    "woe:placetype": "Town",
    "wof:name": "Stourton",
    "wof:placetype": "neighbourhood"
  },
  "geometry": {"coordinates":[-2.31556,51.105],"type":"Point"}
}
