{
  "type": "Feature",
  "properties": {
    "iso:country":"GB",
    "name:deu_x_preferred":[
        "Waterfront"
    ],
    "name:eng_x_preferred":[
        "Waterfront"
    ],
    "name:eng_x_variant":[
        "Docklands",
        "Tiger Bay"
    ],
    "name:fra_x_preferred":[
        "Waterfront"
    ],
    "name:ita_x_preferred":[
        "Waterfront"
    ],
    "name:nld_x_preferred":[
        "Waterfront"
    ],
    "name:swe_x_preferred":[
        "Waterfront"
    ],
    "qs:gn_adm0_cc":"GB",
    "qs:gn_local":2653822,
    "qs:gn_nam_loc":"Cardiff, Cardiff, Cardiff, Wales, GB",
    "qs:gn_namadm1":"WLS",
    "qs:local_max":5000,
    "qs:local_sum":46092,
    "qs:localhoods":22,
    "qs:name":"Waterfront",
    "qs:name_adm0":"United Kingdom",
    "qs:name_adm1":"Wales",
    "qs:name_adm2":"Cardiff County",
    "qs:name_lau":"Cardiff County",
    "qs:name_local":"Cardiff",
    "qs:photo_max":41,
    "qs:photo_sum":176,
    "qs:placetype":"Suburb",
    "qs:quad_count":16,
    "qs:woe_adm0":23424975,
    "qs:woe_adm1":12578049,
    "qs:woe_adm2":12602215,
    "qs:woe_lau":12696132,
    "qs:woe_local":15127,
    "qs:woe_ver":"7.10.0",
    "wd:wordcount":319,
    "wof:lang":[
        "eng"
    ],
    "wof:name":"Waterfront",
    "wof:placetype":"neighbourhood"
},
  "geometry": {"coordinates":[-3.139284,51.471247],"type":"Point"}
}