{
  "type": "Feature",
  "properties": {
    "iso:country":"GB",
    "wof:name":"Low End Town",
    "wof:placetype":"neighbourhood"
},
  "geometry": {"coordinates":[-1.59528470004245,53.74221913079751],"type":"Point"}
}