{
  "type": "Feature",
  "properties": {
    "gn:admin1_code":"SCT",
    "gn:admin2_code":"W5",
    "gn:asciiname":"Hyndfordbridge-end",
    "gn:country_code":"GB",
    "gn:dem":200,
    "gn:feature_class":"P",
    "gn:feature_code":"PPL",
    "gn:name":"Hyndfordbridge-end",
    "gn:population":0,
    "gn:timezone":"Europe/London",
    "iso:country":"GB",
    "wof:name":"Hyndfordbridge-end",
    "wof:placetype":"locality"
},
  "geometry": {"coordinates":[-3.73333,55.66667],"type":"Point"}
}