{
  "type": "Feature",
  "properties": {
    "iso:country":"GB",
    "name:eng_x_preferred":[
        "Lower Stanton St. Quintin"
    ],
    "name:eng_x_variant":[
        "Lower Stanton Saint Quintin"
    ],
    "qs_pg:aaroncc":"GB",
    "qs_pg:name":"Lower Stanton St. Quintin",
    "qs_pg:name_adm0":"United Kingdom",
    "qs_pg:name_adm1":"England",
    "qs_pg:photos":95,
    "qs_pg:photos_1k":19,
    "qs_pg:photos_9k":1,
    "qs_pg:photos_9r":3,
    "qs_pg:photos_all":95,
    "qs_pg:photos_sr":3,
    "qs_pg:pop_sr":0,
    "qs_pg:qs_pg_placetype":"locality",
    "qs_pg:qs_pg_placetype_gp":"Town",
    "qs_pg:woe_adm0":23424975,
    "woe:adm0_id":23424975,
    "woe:name_adm0":"United Kingdom",
    "woe:name_adm1":"England",
    "woe:placetype":"Town",
    "wof:name":"Lower Stanton St. Quintin",
    "wof:placetype":"neighbourhood"
},
  "geometry": {"coordinates":[-2.13478,51.532134],"type":"Point"}
}