{
  "type": "Feature",
  "properties": {
    "gn:admin1_code": "NIR",
    "gn:admin2_code": "N09000004",
    "gn:asciiname": "Corkey",
    "gn:country_code": "GB",
    "gn:dem": 243,
    "gn:feature_class": "P",
    "gn:feature_code": "PPL",
    "gn:name": "Corkey",
    "gn:population": 0,
    "gn:timezone": "Europe/London",
    "iso:country": "GB",
    "name:spa_x_preferred": [
      "Corkey"
    ],
    "wof:name": "Corkey",
    "wof:placetype": "locality"
  },
  "geometry": {"coordinates":[-6.28333,55.03333000000001],"type":"Point"}
}
