{
  "type": "Feature",
  "properties": {
    "gn:admin1_code": "ENG",
    "gn:admin2_code": "Q4",
    "gn:admin3_code": "47UF",
    "gn:admin4_code": "47UF046",
    "gn:asciiname": "Crossway Green",
    "gn:country_code": "GB",
    "gn:dem": 91,
    "gn:feature_class": "P",
    "gn:feature_code": "PPL",
    "gn:name": "Crossway Green",
    "gn:population": 0,
    "gn:timezone": "Europe/London",
    "iso:country": "GB",
    "name:fra_x_preferred": [
      "Crossway Green"
    ],
    "name:pol_x_preferred": [
      "Crossway Green"
    ],
    "wof:name": "Crossway Green",
    "wof:placetype": "neighbourhood"
  },
  "geometry": {"coordinates":[-2.23709,52.31509000000001],"type":"Point"}
}
