{
  "type": "Feature",
  "properties": {
    "gn:country":"GB",
    "gn:fcode":"PPL",
    "gn:population":0,
    "iso:country":"GB",
    "name:cym_x_preferred":[
        "Oswaldtwistle"
    ],
    "name:dan_x_preferred":[
        "Oswaldtwistle"
    ],
    "name:deu_x_preferred":[
        "Oswaldtwistle"
    ],
    "name:eng_x_preferred":[
        "Oswaldtwistle"
    ],
    "name:fas_x_preferred":[
        "\u0622\u0632\u0648\u0627\u0644\u062f\u062a\u0648\u06cc\u0633\u062a\u0644"
    ],
    "name:fra_x_preferred":[
        "Oswaldtwistle"
    ],
    "name:gle_x_preferred":[
        "Oswaldtwistle"
    ],
    "name:ido_x_preferred":[
        "Clearbrook"
    ],
    "name:ind_x_preferred":[
        "Oswaldtwistle"
    ],
    "name:ita_x_preferred":[
        "Oswaldtwistle"
    ],
    "name:nld_x_preferred":[
        "Oswaldtwistle"
    ],
    "name:nno_x_preferred":[
        "Oswaldtwistle"
    ],
    "name:pol_x_preferred":[
        "Oswaldtwistle"
    ],
    "name:spa_x_preferred":[
        "Oswaldtwistle"
    ],
    "name:swe_x_preferred":[
        "Oswaldtwistle"
    ],
    "name:vol_x_preferred":[
        "Oswaldtwistle"
    ],
    "qs_pg:aaroncc":"GB",
    "qs_pg:gn_country":"GB",
    "qs_pg:gn_fcode":"PPL",
    "qs_pg:gn_pop":0,
    "qs_pg:name":"Oswaldtwistle",
    "qs_pg:name_adm0":"United Kingdom",
    "qs_pg:name_adm1":"England",
    "qs_pg:photos":208,
    "qs_pg:photos_1k":42,
    "qs_pg:photos_9k":1,
    "qs_pg:photos_9r":4,
    "qs_pg:photos_all":208,
    "qs_pg:photos_sr":4,
    "qs_pg:pop_sr":0,
    "qs_pg:qs_pg_placetype":"locality",
    "qs_pg:qs_pg_placetype_gp":"Town",
    "qs_pg:woe_adm0":23424975,
    "woe:adm0_id":23424975,
    "woe:name_adm0":"United Kingdom",
    "woe:name_adm1":"England",
    "woe:placetype":"Town",
    "wof:name":"Oswaldtwistle",
    "wof:placetype":"neighbourhood"
},
  "geometry": {"coordinates":[-2.39993,53.74195],"type":"Point"}
}