{
  "type": "Feature",
  "properties": {
    "gn:gn_country":"GB",
    "gn:gn_fcode":"PPL",
    "gn:gn_pop":0,
    "iso:country":"GB",
    "name:dan_x_preferred":[
        "Oswaldtwistle"
    ],
    "name:dut_x_preferred":[
        "Oswaldtwistle"
    ],
    "name:eng_x_preferred":[
        "Oswaldtwistle"
    ],
    "name:fre_x_preferred":[
        "Oswaldtwistle"
    ],
    "name:ger_x_preferred":[
        "Oswaldtwistle"
    ],
    "name:ind_x_preferred":[
        "Oswaldtwistle"
    ],
    "name:ita_x_preferred":[
        "Oswaldtwistle"
    ],
    "name:nno_x_preferred":[
        "Oswaldtwistle"
    ],
    "name:pol_x_preferred":[
        "Oswaldtwistle"
    ],
    "name:spa_x_preferred":[
        "Oswaldtwistle"
    ],
    "name:swe_x_preferred":[
        "Oswaldtwistle"
    ],
    "name:vol_x_preferred":[
        "Oswaldtwistle"
    ],
    "name:wel_x_preferred":[
        "Oswaldtwistle"
    ],
    "qs_pg:aaroncc":"GB",
    "qs_pg:gn_country":"GB",
    "qs_pg:gn_fcode":"PPL",
    "qs_pg:gn_pop":0,
    "qs_pg:name":"Oswaldtwistle",
    "qs_pg:name_adm0":"United Kingdom",
    "qs_pg:name_adm1":"England",
    "qs_pg:photos":208,
    "qs_pg:photos_1k":42,
    "qs_pg:photos_9k":1,
    "qs_pg:photos_9r":4,
    "qs_pg:photos_all":208,
    "qs_pg:photos_sr":4,
    "qs_pg:pop_sr":0,
    "qs_pg:qs_pg_placetype":"locality",
    "qs_pg:qs_pg_placetype_gp":"Town",
    "qs_pg:woe_adm0":23424975,
    "woe:adm0_id":23424975,
    "woe:name_adm0":"United Kingdom",
    "woe:name_adm1":"England",
    "woe:placetype":"Town",
    "wof:name":"Oswaldtwistle",
    "wof:placetype":"neighbourhood"
},
  "geometry": {"coordinates":[-2.39993,53.74195],"type":"Point"}
}