{
  "type": "Feature",
  "properties": {
    "iso:country": "GB",
    "name:eng_x_preferred": [
      "St John Street"
    ],
    "wof:name": "St John Street",
    "wof:placetype": "neighbourhood"
  },
  "geometry": {"coordinates":[-1.26188157484283,51.75621773089041],"type":"Point"}
}
