{
  "type": "Feature",
  "properties": {
    "gn:country":"GB",
    "gn:fcode":"PPL",
    "gn:population":0,
    "iso:country":"GB",
    "name:eng_x_preferred":[
        "Leverburgh"
    ],
    "name:eus_x_preferred":[
        "Leverburgh"
    ],
    "name:fas_x_preferred":[
        "\u0644\u0648\u0631\u0628\u0631\u06af"
    ],
    "name:fin_x_preferred":[
        "An T\u00f2b"
    ],
    "name:fra_x_preferred":[
        "Leverburgh"
    ],
    "name:gla_x_preferred":[
        "An T\u00f2b"
    ],
    "name:gle_x_preferred":[
        "An T\u00f3b"
    ],
    "name:gle_x_variant":[
        "An T\u00f2b"
    ],
    "name:jpn_x_preferred":[
        "\u30ec\u30f4\u30a1\u30fc\u30d0\u30e9"
    ],
    "name:lit_x_preferred":[
        "Leverburgas"
    ],
    "name:nld_x_preferred":[
        "Leverburgh"
    ],
    "name:swe_x_preferred":[
        "Leverburgh"
    ],
    "qs_pg:aaroncc":"GB",
    "qs_pg:gn_country":"GB",
    "qs_pg:gn_fcode":"PPL",
    "qs_pg:gn_pop":0,
    "qs_pg:name":"Leverburgh",
    "qs_pg:name_adm0":"United Kingdom",
    "qs_pg:name_adm1":"Scotland",
    "qs_pg:photos":684,
    "qs_pg:photos_1k":139,
    "qs_pg:photos_9k":3,
    "qs_pg:photos_9r":5,
    "qs_pg:photos_all":684,
    "qs_pg:photos_sr":8,
    "qs_pg:pop_sr":0,
    "qs_pg:qs_pg_placetype":"locality",
    "qs_pg:qs_pg_placetype_gp":"Town",
    "qs_pg:woe_adm0":23424975,
    "woe:adm0_id":23424975,
    "woe:name_adm0":"United Kingdom",
    "woe:name_adm1":"Scotland",
    "woe:placetype":"Town",
    "wof:name":"Leverburgh",
    "wof:placetype":"locality"
},
  "geometry": {"coordinates":[-7.00885,57.77115],"type":"Point"}
}