{
  "type": "Feature",
  "properties": {
    "iso:country":"GB",
    "name:ben_x_preferred":[
        "\u098f\u0995\u09cd\u09b2\u09c7\u09b8\u09be"
    ],
    "name:deu_x_preferred":[
        "Ecclesall"
    ],
    "name:eng_x_preferred":[
        "Eccleshill"
    ],
    "name:eng_x_variant":[
        "Ecclesall"
    ],
    "name:fra_x_preferred":[
        "Ecclesall"
    ],
    "name:gle_x_preferred":[
        "Ecclesall"
    ],
    "name:guj_x_preferred":[
        "\u0a8f\u0a95\u0acd\u0ab2\u0ac7\u0ab8\u0acb\u0ab2"
    ],
    "name:ita_x_preferred":[
        "Ecclesall"
    ],
    "name:jpn_x_preferred":[
        "\u30a8\u30c3\u30af\u30eb\u30b5\u30eb"
    ],
    "name:kan_x_preferred":[
        "\u0c8e\u0c95\u0ccd\u0cb8\u0cc6\u0cb2\u0ccd\u0cb8\u0ccd"
    ],
    "name:kor_x_preferred":[
        "\uc5d0\ud074\ub808\uc0b4"
    ],
    "name:lit_x_preferred":[
        "Eklesalas"
    ],
    "name:pol_x_preferred":[
        "Ecclesall"
    ],
    "name:por_x_preferred":[
        "Ecclesall"
    ],
    "name:rus_x_preferred":[
        "\u042d\u043a\u043b\u0441\u043e\u043b"
    ],
    "name:spa_x_preferred":[
        "Ecclesall"
    ],
    "name:tam_x_preferred":[
        "\u0b8f\u0b95\u0bcd\u0b95\u0bb2\u0bc6\u0bb8\u0bcd\u0b86\u0bb2\u0bcd"
    ],
    "name:tel_x_preferred":[
        "\u0c0e\u0c15\u0c4d\u0c32\u0c46\u0c38\u0c3e\u0c32\u0c4d"
    ],
    "name:urd_x_preferred":[
        "\u06cc\u06a9\u06a9\u0644\u06cc\u0633\u0627\u0644"
    ],
    "qs:gn_adm0_cc":"GB",
    "qs:gn_fcode":"PPL",
    "qs:gn_local":2654993,
    "qs:gn_nam_loc":"Bradford",
    "qs:gn_namadm1":"ENG",
    "qs:gn_name":"Ecclesall",
    "qs:local_max":4399,
    "qs:local_sum":22210,
    "qs:localhoods":31,
    "qs:name":"Eccleshill",
    "qs:name_adm0":"United Kingdom",
    "qs:name_adm1":"England",
    "qs:name_adm2":"West Yorkshire",
    "qs:name_lau":"Bradford City of",
    "qs:name_local":"Bradford",
    "qs:photo_max":8,
    "qs:photo_sum":19,
    "qs:placetype":"Suburb",
    "qs:quad_count":4,
    "qs:woe_adm0":23424975,
    "qs:woe_adm1":24554868,
    "qs:woe_adm2":12602197,
    "qs:woe_lau":12695870,
    "qs:woe_local":13527,
    "qs:woe_ver":"7.10.0",
    "wd:wordcount":1364,
    "wof:lang":[
        "eng"
    ],
    "wof:name":"Eccleshill",
    "wof:placetype":"neighbourhood"
},
  "geometry": {"coordinates":[-1.72984,53.820729],"type":"Point"}
}