{
  "type": "Feature",
  "properties": {
    "gn:admin1_code":"SCT",
    "gn:admin2_code":"T8",
    "gn:asciiname":"Bellochantuy",
    "gn:country_code":"GB",
    "gn:dem":7,
    "gn:feature_class":"P",
    "gn:feature_code":"PPL",
    "gn:name":"Bellochantuy",
    "gn:population":0,
    "gn:timezone":"Europe/London",
    "iso:country":"GB",
    "name:eus_x_preferred":[
        "Bellochantuy"
    ],
    "wof:name":"Bellochantuy",
    "wof:placetype":"locality"
},
  "geometry": {"coordinates":[-5.70212,55.53127],"type":"Point"}
}