{
  "type": "Feature",
  "properties": {
    "gn:admin1_code":"SCT",
    "gn:admin2_code":"V3",
    "gn:asciiname":"Fourpenny",
    "gn:country_code":"GB",
    "gn:dem":33,
    "gn:feature_class":"P",
    "gn:feature_code":"PPL",
    "gn:name":"Fourpenny",
    "gn:population":0,
    "gn:timezone":"Europe/London",
    "iso:country":"GB",
    "wof:name":"Fourpenny",
    "wof:placetype":"locality"
},
  "geometry": {"coordinates":[-4.02585,57.91984],"type":"Point"}
}