{
  "type": "Feature",
  "properties": {
    "gn:country": "GB",
    "gn:fcode": "PPL",
    "gn:population": 1234,
    "iso:country": "GB",
    "name:ceb_x_preferred": [
      "Moy"
    ],
    "name:eng_x_preferred": [
      "Moy"
    ],
    "name:eus_x_preferred": [
      "Moy"
    ],
    "name:fas_x_preferred": [
      "موی"
    ],
    "name:fra_x_preferred": [
      "Moy"
    ],
    "name:gle_x_preferred": [
      "An Maigh"
    ],
    "name:msa_x_preferred": [
      "Moy"
    ],
    "name:nld_x_preferred": [
      "Moy"
    ],
    "name:pli_x_preferred": [
      "मोय"
    ],
    "name:spa_x_preferred": [
      "Moy"
    ],
    "name:swe_x_preferred": [
      "Moy"
    ],
    "qs_pg:aaroncc": "GB",
    "qs_pg:gn_country": "GB",
    "qs_pg:gn_fcode": "PPL",
    "qs_pg:gn_pop": 1234,
    "qs_pg:name": "Moy",
    "qs_pg:name_adm0": "United Kingdom",
    "qs_pg:name_adm1": "Northern Ireland",
    "qs_pg:photos": 52,
    "qs_pg:photos_1k": 11,
    "qs_pg:photos_9k": 1,
    "qs_pg:photos_9r": 2,
    "qs_pg:photos_all": 52,
    "qs_pg:photos_sr": 2,
    "qs_pg:pop_sr": 3,
    "qs_pg:qs_pg_placetype": "locality",
    "qs_pg:qs_pg_placetype_gp": "Town",
    "qs_pg:woe_adm0": 23424975,
    "woe:adm0_id": 23424975,
    "woe:name_adm0": "United Kingdom",
    "woe:name_adm1": "Northern Ireland",
    "woe:placetype": "Town",
    "wof:name": "Moy",
    "wof:placetype": "locality",
    "wof:population": 1234
  },
  "geometry": {"coordinates":[-6.66667,54.45],"type":"Point"}
}
