{
  "type": "Feature",
  "properties": {
    "iso:country":"GB",
    "name:eng_x_preferred":[
        "Balado"
    ],
    "name:fra_x_preferred":[
        "Balado"
    ],
    "name:nld_x_preferred":[
        "Balado"
    ],
    "name:por_x_preferred":[
        "Balado"
    ],
    "qs_pg:aaroncc":"GB",
    "qs_pg:name":"Balado",
    "qs_pg:name_adm0":"United Kingdom",
    "qs_pg:name_adm1":"Scotland",
    "qs_pg:photos":1204,
    "qs_pg:photos_1k":244,
    "qs_pg:photos_9k":5,
    "qs_pg:photos_9r":7,
    "qs_pg:photos_all":1204,
    "qs_pg:photos_sr":11,
    "qs_pg:pop_sr":0,
    "qs_pg:qs_pg_placetype":"locality",
    "qs_pg:qs_pg_placetype_gp":"Town",
    "qs_pg:woe_adm0":23424975,
    "woe:adm0_id":23424975,
    "woe:name_adm0":"United Kingdom",
    "woe:name_adm1":"Scotland",
    "woe:placetype":"Town",
    "wof:name":"Balado",
    "wof:placetype":"locality"
},
  "geometry": {"coordinates":[-3.460006,56.209138],"type":"Point"}
}