{
  "type": "Feature",
  "properties": {
    "gn:admin1_code":"SCT",
    "gn:admin2_code":"U2",
    "gn:asciiname":"Terreglestown",
    "gn:country_code":"GB",
    "gn:dem":7,
    "gn:feature_class":"P",
    "gn:feature_code":"PPL",
    "gn:name":"Terreglestown",
    "gn:population":0,
    "gn:timezone":"Europe/London",
    "iso:country":"GB",
    "wof:name":"Terreglestown",
    "wof:placetype":"locality"
},
  "geometry": {"coordinates":[-3.65,55.06667],"type":"Point"}
}