{
  "type": "Feature",
  "properties": {
    "iso:country":"GB",
    "name:deu_x_preferred":[
        "Haddon"
    ],
    "name:fra_x_preferred":[
        "Haddon"
    ],
    "name:ita_x_preferred":[
        "Haddon"
    ],
    "name:pol_x_preferred":[
        "Haddon"
    ],
    "name:rus_x_preferred":[
        "\u0425\u044d\u0434\u0434\u043e\u043d"
    ],
    "qs_pg:aaroncc":"GB",
    "qs_pg:name":"Haddon",
    "qs_pg:name_adm0":"United Kingdom",
    "qs_pg:name_adm1":"England",
    "qs_pg:photos":35,
    "qs_pg:photos_1k":7,
    "qs_pg:photos_9k":1,
    "qs_pg:photos_9r":2,
    "qs_pg:photos_all":35,
    "qs_pg:photos_sr":2,
    "qs_pg:pop_sr":0,
    "qs_pg:qs_pg_placetype":"locality",
    "qs_pg:qs_pg_placetype_gp":"Town",
    "qs_pg:woe_adm0":23424975,
    "woe:adm0_id":23424975,
    "woe:name_adm0":"United Kingdom",
    "woe:name_adm1":"England",
    "woe:placetype":"Town",
    "wof:name":"Haddon",
    "wof:placetype":"neighbourhood"
},
  "geometry": {"coordinates":[-2.462278,50.965525],"type":"Point"}
}