{
  "type": "Feature",
  "properties": {
    "iso:country":"GB",
    "name:cor_x_preferred":[
        "Boskednin"
    ],
    "name:cym_x_preferred":[
        "Boskednin"
    ],
    "name:deu_x_preferred":[
        "Boskednan"
    ],
    "name:eng_x_preferred":[
        "Boskednan"
    ],
    "name:eus_x_preferred":[
        "Boskednan"
    ],
    "name:eus_x_variant":[
        "Boskednin"
    ],
    "name:fra_x_preferred":[
        "Boskednan"
    ],
    "name:pol_x_preferred":[
        "Boskednan"
    ],
    "qs_pg:aaroncc":"GB",
    "qs_pg:name":"Boskednan",
    "qs_pg:name_adm0":"United Kingdom",
    "qs_pg:name_adm1":"England",
    "qs_pg:photos":22,
    "qs_pg:photos_1k":4,
    "qs_pg:photos_9k":1,
    "qs_pg:photos_9r":1,
    "qs_pg:photos_all":22,
    "qs_pg:photos_sr":1,
    "qs_pg:pop_sr":0,
    "qs_pg:qs_pg_placetype":"locality",
    "qs_pg:qs_pg_placetype_gp":"Town",
    "qs_pg:woe_adm0":23424975,
    "woe:adm0_id":23424975,
    "woe:name_adm0":"United Kingdom",
    "woe:name_adm1":"England",
    "woe:placetype":"Town",
    "wof:name":"Boskednan",
    "wof:placetype":"neighbourhood"
},
  "geometry": {"coordinates":[-5.581741,50.156143],"type":"Point"}
}