{
  "type": "Feature",
  "properties": {
    "iso:country":"GB",
    "name:ces_x_preferred":[
        "Gott"
    ],
    "name:deu_x_preferred":[
        "Gott"
    ],
    "name:fra_x_preferred":[
        "Gott"
    ],
    "name:rus_x_preferred":[
        "\u0413\u043e\u0442\u0442"
    ],
    "qs_pg:aaroncc":"GB",
    "qs_pg:name":"Gott",
    "qs_pg:name_adm0":"United Kingdom",
    "qs_pg:name_adm1":"Scotland",
    "qs_pg:photos":43,
    "qs_pg:photos_1k":9,
    "qs_pg:photos_9k":1,
    "qs_pg:photos_9r":2,
    "qs_pg:photos_all":43,
    "qs_pg:photos_sr":2,
    "qs_pg:pop_sr":0,
    "qs_pg:qs_pg_placetype":"locality",
    "qs_pg:qs_pg_placetype_gp":"Town",
    "qs_pg:woe_adm0":23424975,
    "woe:adm0_id":23424975,
    "woe:name_adm0":"United Kingdom",
    "woe:name_adm1":"Scotland",
    "woe:placetype":"Town",
    "wof:name":"Gott",
    "wof:placetype":"locality"
},
  "geometry": {"coordinates":[-1.209545,60.200019],"type":"Point"}
}