{
  "type": "Feature",
  "properties": {
    "gn:country":"GB",
    "gn:fcode":"PPL",
    "gn:population":0,
    "iso:country":"GB",
    "name:eng_x_preferred":[
        "Swinbrook"
    ],
    "name:fra_x_preferred":[
        "Swinbrook"
    ],
    "name:gle_x_preferred":[
        "Swinbrook"
    ],
    "name:jpn_x_preferred":[
        "\u30b9\u30a6\u30a3\u30f3\u30d6\u30ed\u30c3\u30af"
    ],
    "name:nld_x_preferred":[
        "Swinbrook"
    ],
    "name:pol_x_preferred":[
        "Swinbrook"
    ],
    "qs_pg:aaroncc":"GB",
    "qs_pg:gn_country":"GB",
    "qs_pg:gn_fcode":"PPL",
    "qs_pg:gn_pop":0,
    "qs_pg:name":"Swinbrook",
    "qs_pg:name_adm0":"United Kingdom",
    "qs_pg:name_adm1":"England",
    "qs_pg:photos":204,
    "qs_pg:photos_1k":41,
    "qs_pg:photos_9k":1,
    "qs_pg:photos_9r":4,
    "qs_pg:photos_all":204,
    "qs_pg:photos_sr":4,
    "qs_pg:pop_sr":0,
    "qs_pg:qs_pg_placetype":"locality",
    "qs_pg:qs_pg_placetype_gp":"Town",
    "qs_pg:woe_adm0":23424975,
    "woe:adm0_id":23424975,
    "woe:name_adm0":"United Kingdom",
    "woe:name_adm1":"England",
    "woe:placetype":"Town",
    "wof:name":"Swinbrook",
    "wof:placetype":"neighbourhood"
},
  "geometry": {"coordinates":[-1.59399,51.80729],"type":"Point"}
}