{
  "type": "Feature",
  "properties": {
    "gn:country":"GB",
    "gn:fcode":"PPL",
    "gn:population":2039,
    "iso:country":"GB",
    "name:bul_x_preferred":[
        "\u0421\u043b\u0435\u0438\u0433\u0445\u0446"
    ],
    "name:ceb_x_preferred":[
        "Sleights"
    ],
    "name:deu_x_preferred":[
        "Sleights"
    ],
    "name:eng_x_preferred":[
        "Sleights"
    ],
    "name:fra_x_preferred":[
        "Sleights"
    ],
    "name:nld_x_preferred":[
        "Sleights"
    ],
    "name:pol_x_preferred":[
        "Sleights"
    ],
    "name:spa_x_preferred":[
        "Sleights"
    ],
    "name:swe_x_preferred":[
        "Sleights"
    ],
    "qs_pg:aaroncc":"GB",
    "qs_pg:gn_country":"GB",
    "qs_pg:gn_fcode":"PPL",
    "qs_pg:gn_pop":2039,
    "qs_pg:name":"Sleights",
    "qs_pg:name_adm0":"United Kingdom",
    "qs_pg:name_adm1":"England",
    "qs_pg:photos":188,
    "qs_pg:photos_1k":38,
    "qs_pg:photos_9k":1,
    "qs_pg:photos_9r":4,
    "qs_pg:photos_all":188,
    "qs_pg:photos_sr":4,
    "qs_pg:pop_sr":4,
    "qs_pg:qs_pg_placetype":"locality",
    "qs_pg:qs_pg_placetype_gp":"Town",
    "qs_pg:woe_adm0":23424975,
    "woe:adm0_id":23424975,
    "woe:name_adm0":"United Kingdom",
    "woe:name_adm1":"England",
    "woe:placetype":"Town",
    "wof:name":"Sleights",
    "wof:placetype":"neighbourhood",
    "wof:population":1972
},
  "geometry": {"coordinates":[-0.66484,54.45506],"type":"Point"}
}