{
  "type": "Feature",
  "properties": {
    "gn:country":"GB",
    "iso:country":"GB",
    "name:deu_x_preferred":[
        "Glasson Dock"
    ],
    "name:eng_x_preferred":[
        "Glasson Dock"
    ],
    "name:fra_x_preferred":[
        "Glasson Dock"
    ],
    "name:nld_x_preferred":[
        "Glasson Dock"
    ],
    "name:pol_x_preferred":[
        "Glasson Dock"
    ],
    "qs_pg:aaroncc":"GB",
    "qs_pg:gn_country":"GB",
    "qs_pg:name":"Glasson Dock",
    "qs_pg:name_adm0":"United Kingdom",
    "qs_pg:name_adm1":"England",
    "qs_pg:photos":653,
    "qs_pg:photos_1k":132,
    "qs_pg:photos_9k":3,
    "qs_pg:photos_9r":5,
    "qs_pg:photos_all":653,
    "qs_pg:photos_sr":8,
    "qs_pg:pop_sr":0,
    "qs_pg:qs_pg_placetype":"locality",
    "qs_pg:qs_pg_placetype_gp":"Town",
    "qs_pg:woe_adm0":23424975,
    "woe:adm0_id":23424975,
    "woe:name_adm0":"United Kingdom",
    "woe:name_adm1":"England",
    "woe:placetype":"Town",
    "wof:name":"Glasson Dock",
    "wof:placetype":"neighbourhood"
},
  "geometry": {"coordinates":[-2.848452,53.997881],"type":"Point"}
}