{
  "type": "Feature",
  "properties": {
    "gn:country":"GB",
    "gn:fcode":"PPL",
    "gn:population":0,
    "iso:country":"GB",
    "name:bul_x_preferred":[
        "\u041c\u043e\u043d\u043f\u0435\u043b\u0438\u0435"
    ],
    "name:cat_x_preferred":[
        "Montpelier"
    ],
    "name:ceb_x_preferred":[
        "Montpelier"
    ],
    "name:deu_x_preferred":[
        "Montpelier"
    ],
    "name:epo_x_preferred":[
        "Montpeliero"
    ],
    "name:fas_x_preferred":[
        "\u0645\u0648\u0646\u200c\u067e\u0644\u06cc\u0647"
    ],
    "name:heb_x_preferred":[
        "\u05de\u05d5\u05e0\u05e4\u05dc\u05d9\u05d9\u05d4"
    ],
    "name:hun_x_preferred":[
        "Montpelier"
    ],
    "name:ita_x_preferred":[
        "Montpelier"
    ],
    "name:jpn_x_preferred":[
        "\u30e2\u30f3\u30c8\u30d4\u30ea\u30a2"
    ],
    "name:kor_x_preferred":[
        "\ubaac\ud2b8\ud544\ub9ac\uc5b4"
    ],
    "name:kur_x_preferred":[
        "Montpelier"
    ],
    "name:nld_x_preferred":[
        "Montpelier"
    ],
    "name:pol_x_preferred":[
        "Montpelier"
    ],
    "name:por_x_preferred":[
        "Montpelier"
    ],
    "name:rus_x_preferred":[
        "\u041c\u043e\u043d\u043f\u0435\u043b\u044c\u0435"
    ],
    "name:slk_x_preferred":[
        "Montpelier"
    ],
    "name:spa_x_preferred":[
        "Montpelier"
    ],
    "name:srp_x_preferred":[
        "\u041c\u043e\u043d\u0442\u043f\u0438\u043b\u0438\u0458\u0435\u0440"
    ],
    "name:swa_x_preferred":[
        "Montpelier"
    ],
    "name:swe_x_preferred":[
        "Montpelier"
    ],
    "name:ukr_x_preferred":[
        "\u041c\u043e\u043d\u043f\u0435\u043b\u044c\u0454"
    ],
    "name:urd_x_preferred":[
        "\u0645\u0648\u0646\u0679\u067e\u06cc\u0644\u06cc\u0626\u0631"
    ],
    "name:zho_x_preferred":[
        "\u8499\u5f7c\u5229\u57c3"
    ],
    "qs_pg:aaroncc":"GB",
    "qs_pg:gn_country":"GB",
    "qs_pg:gn_fcode":"PPL",
    "qs_pg:gn_pop":0,
    "qs_pg:name":"Montpelier",
    "qs_pg:name_adm0":"United Kingdom",
    "qs_pg:name_adm1":"England",
    "qs_pg:photos":1235,
    "qs_pg:photos_1k":250,
    "qs_pg:photos_9k":5,
    "qs_pg:photos_9r":7,
    "qs_pg:photos_all":1235,
    "qs_pg:photos_sr":11,
    "qs_pg:pop_sr":0,
    "qs_pg:qs_pg_placetype":"neighbourhood",
    "qs_pg:qs_pg_placetype_gp":"Suburb",
    "qs_pg:woe_adm0":23424975,
    "woe:adm0_id":23424975,
    "woe:name_adm0":"United Kingdom",
    "woe:name_adm1":"England",
    "woe:placetype":"Suburb",
    "wof:name":"Montpelier",
    "wof:placetype":"neighbourhood"
},
  "geometry": {"coordinates":[-2.08328,51.8932],"type":"Point"}
}