{
  "type": "Feature",
  "properties": {
    "gn:country": "GB",
    "gn:fcode": "PPL",
    "gn:population": 0,
    "iso:country": "GB",
    "name:bul_x_preferred": [
      "Монпелие"
    ],
    "name:cat_x_preferred": [
      "Montpelier"
    ],
    "name:ceb_x_preferred": [
      "Montpelier"
    ],
    "name:deu_x_preferred": [
      "Montpelier"
    ],
    "name:epo_x_preferred": [
      "Montpeliero"
    ],
    "name:fas_x_preferred": [
      "مون‌پلیه"
    ],
    "name:heb_x_preferred": [
      "מונפלייה"
    ],
    "name:hun_x_preferred": [
      "Montpelier"
    ],
    "name:ita_x_preferred": [
      "Montpelier"
    ],
    "name:jpn_x_preferred": [
      "モントピリア"
    ],
    "name:kor_x_preferred": [
      "몬트필리어"
    ],
    "name:kur_x_preferred": [
      "Montpelier"
    ],
    "name:nld_x_preferred": [
      "Montpelier"
    ],
    "name:pol_x_preferred": [
      "Montpelier"
    ],
    "name:por_x_preferred": [
      "Montpelier"
    ],
    "name:rus_x_preferred": [
      "Монпелье"
    ],
    "name:slk_x_preferred": [
      "Montpelier"
    ],
    "name:spa_x_preferred": [
      "Montpelier"
    ],
    "name:srp_x_preferred": [
      "Монтпилијер"
    ],
    "name:swa_x_preferred": [
      "Montpelier"
    ],
    "name:swe_x_preferred": [
      "Montpelier"
    ],
    "name:ukr_x_preferred": [
      "Монпельє"
    ],
    "name:urd_x_preferred": [
      "مونٹپیلیئر"
    ],
    "name:zho_x_preferred": [
      "蒙彼利埃"
    ],
    "qs_pg:aaroncc": "GB",
    "qs_pg:gn_country": "GB",
    "qs_pg:gn_fcode": "PPL",
    "qs_pg:gn_pop": 0,
    "qs_pg:name": "Montpelier",
    "qs_pg:name_adm0": "United Kingdom",
    "qs_pg:name_adm1": "England",
    "qs_pg:photos": 1235,
    "qs_pg:photos_1k": 250,
    "qs_pg:photos_9k": 5,
    "qs_pg:photos_9r": 7,
    "qs_pg:photos_all": 1235,
    "qs_pg:photos_sr": 11,
    "qs_pg:pop_sr": 0,
    "qs_pg:qs_pg_placetype": "neighbourhood",
    "qs_pg:qs_pg_placetype_gp": "Suburb",
    "qs_pg:woe_adm0": 23424975,
    "woe:adm0_id": 23424975,
    "woe:name_adm0": "United Kingdom",
    "woe:name_adm1": "England",
    "woe:placetype": "Suburb",
    "wof:name": "Montpelier",
    "wof:placetype": "neighbourhood"
  },
  "geometry": {"coordinates":[-2.08328,51.8932],"type":"Point"}
}
