{
  "type": "Feature",
  "properties": {
    "gn:gn_country":"GB",
    "gn:gn_fcode":"PPL",
    "gn:gn_pop":0,
    "iso:country":"GB",
    "name:eng_x_preferred":[
        "Overbury"
    ],
    "name:fra_x_preferred":[
        "Overbury"
    ],
    "name:jpn_x_preferred":[
        "\u30aa\u30fc\u30f4\u30a1\u30fc\u30d9\u30ea"
    ],
    "name:nld_x_preferred":[
        "Overbury"
    ],
    "name:pol_x_preferred":[
        "Overbury"
    ],
    "name:unk_x_variant":[
        "Overbury"
    ],
    "qs_pg:aaroncc":"GB",
    "qs_pg:gn_country":"GB",
    "qs_pg:gn_fcode":"PPL",
    "qs_pg:gn_pop":0,
    "qs_pg:name":"Avebury",
    "qs_pg:name_adm0":"United Kingdom",
    "qs_pg:name_adm1":"England",
    "qs_pg:photos":4997,
    "qs_pg:photos_1k":1000,
    "qs_pg:photos_9k":22,
    "qs_pg:photos_9r":14,
    "qs_pg:photos_all":4997,
    "qs_pg:photos_sr":24,
    "qs_pg:pop_sr":0,
    "qs_pg:qs_pg_placetype":"locality",
    "qs_pg:qs_pg_placetype_gp":"Town",
    "qs_pg:woe_adm0":23424975,
    "woe:adm0_id":23424975,
    "woe:name_adm0":"United Kingdom",
    "woe:name_adm1":"England",
    "woe:placetype":"Town",
    "wof:name":"Avebury",
    "wof:placetype":"neighbourhood"
},
  "geometry": {"coordinates":[-2.06264,52.03499],"type":"Point"}
}