{
  "type": "Feature",
  "properties": {
    "gn:country":"GB",
    "gn:fcode":"PPL",
    "gn:population":599,
    "iso:country":"GB",
    "name:ceb_x_preferred":[
        "Portpatrick"
    ],
    "name:cym_x_preferred":[
        "Portpatrick"
    ],
    "name:deu_x_preferred":[
        "Portpatrick"
    ],
    "name:eng_x_preferred":[
        "Portpatrick"
    ],
    "name:eus_x_preferred":[
        "Portpatrick"
    ],
    "name:fas_x_preferred":[
        "\u067e\u0648\u0631\u062a\u200c\u067e\u062a\u0631\u06cc\u06a9"
    ],
    "name:fra_x_preferred":[
        "Portpatrick"
    ],
    "name:gla_x_preferred":[
        "Port Ph\u00e0draig"
    ],
    "name:gle_x_preferred":[
        "Port Ph\u00e1draig"
    ],
    "name:ita_x_preferred":[
        "Portpatrick"
    ],
    "name:nld_x_preferred":[
        "Portpatrick"
    ],
    "name:sco_x_preferred":[
        "Portpaitrick"
    ],
    "name:spa_x_preferred":[
        "Portpatrick"
    ],
    "name:swe_x_preferred":[
        "Portpatrick"
    ],
    "name:zho_x_preferred":[
        "\u6d3e\u5c48\u514b\u6e2f"
    ],
    "qs_pg:aaroncc":"GB",
    "qs_pg:gn_country":"GB",
    "qs_pg:gn_fcode":"PPL",
    "qs_pg:gn_pop":599,
    "qs_pg:name":"Portpatrick",
    "qs_pg:name_adm0":"United Kingdom",
    "qs_pg:name_adm1":"Scotland",
    "qs_pg:photos":3006,
    "qs_pg:photos_1k":609,
    "qs_pg:photos_9k":13,
    "qs_pg:photos_9r":11,
    "qs_pg:photos_all":3006,
    "qs_pg:photos_sr":19,
    "qs_pg:pop_sr":2,
    "qs_pg:qs_pg_placetype":"locality",
    "qs_pg:qs_pg_placetype_gp":"Town",
    "qs_pg:woe_adm0":23424975,
    "woe:adm0_id":23424975,
    "woe:name_adm0":"United Kingdom",
    "woe:name_adm1":"Scotland",
    "woe:placetype":"Town",
    "wof:name":"Portpatrick",
    "wof:placetype":"locality",
    "wof:population":620
},
  "geometry": {"coordinates":[-5.11705,54.84143],"type":"Point"}
}