{
  "type": "Feature",
  "properties": {
    "iso:country":"GB",
    "name:bel_x_preferred":[
        "\u0406\u0442\u0430\u043d"
    ],
    "name:cat_x_preferred":[
        "Eaton"
    ],
    "name:ceb_x_preferred":[
        "Eaton"
    ],
    "name:deu_x_preferred":[
        "Eaton"
    ],
    "name:eng_x_preferred":[
        "Eaton"
    ],
    "name:fra_x_preferred":[
        "Eaton"
    ],
    "name:heb_x_preferred":[
        "\u05d0\u05d9\u05d8\u05d5\u05df"
    ],
    "name:ita_x_preferred":[
        "Eaton"
    ],
    "name:lav_x_preferred":[
        "\u012atons"
    ],
    "name:mlg_x_preferred":[
        "Eaton"
    ],
    "name:nds_x_preferred":[
        "Eaton"
    ],
    "name:nld_x_preferred":[
        "Eaton"
    ],
    "name:pol_x_preferred":[
        "Eaton"
    ],
    "name:por_x_preferred":[
        "Eaton"
    ],
    "name:ron_x_preferred":[
        "Eaton"
    ],
    "name:rus_x_preferred":[
        "Eaton"
    ],
    "name:spa_x_preferred":[
        "Eaton"
    ],
    "name:srp_x_preferred":[
        "\u0418\u0442\u043e\u043d"
    ],
    "name:swe_x_preferred":[
        "Eaton"
    ],
    "name:ukr_x_preferred":[
        "\u0406\u0442\u043e\u043d"
    ],
    "name:vol_x_preferred":[
        "Eaton"
    ],
    "qs:gn_adm0_cc":"GB",
    "qs:gn_fcode":"PPL",
    "qs:gn_local":2641181,
    "qs:gn_nam_loc":"Norwich, Norwich, Norfolk, England, GB",
    "qs:gn_namadm1":"ENG",
    "qs:gn_name":"Neaton",
    "qs:local_max":5858,
    "qs:local_sum":22582,
    "qs:localhoods":10,
    "qs:name":"Eaton",
    "qs:name_adm0":"United Kingdom",
    "qs:name_adm1":"England",
    "qs:name_adm2":"Norfolk",
    "qs:name_lau":"Norwich City",
    "qs:name_local":"Norwich",
    "qs:photo_max":326,
    "qs:photo_sum":2457,
    "qs:placetype":"Suburb",
    "qs:quad_count":116,
    "qs:woe_adm0":23424975,
    "qs:woe_adm1":24554868,
    "qs:woe_adm2":12602141,
    "qs:woe_lau":12696028,
    "qs:woe_local":30704,
    "qs:woe_ver":"7.10.0",
    "wof:lang":[
        "eng"
    ],
    "wof:name":"Eaton",
    "wof:placetype":"neighbourhood"
},
  "geometry": {"coordinates":[1.262068,52.61513],"type":"Point"}
}