{
  "type": "Feature",
  "properties": {
    "gn:admin1_code":"ENG",
    "gn:admin2_code":"F2",
    "gn:admin3_code":"24UP",
    "gn:asciiname":"Weeke",
    "gn:country_code":"GB",
    "gn:dem":86,
    "gn:feature_class":"P",
    "gn:feature_code":"PPL",
    "gn:name":"Weeke",
    "gn:population":0,
    "gn:timezone":"Europe/London",
    "iso:country":"GB",
    "name:pol_x_preferred":[
        "Weeke"
    ],
    "wof:name":"Weeke",
    "wof:placetype":"neighbourhood"
},
  "geometry": {"coordinates":[-1.33333,51.06667],"type":"Point"}
}