{
  "type": "Feature",
  "properties": {
    "gn:admin1_code":"ENG",
    "gn:admin2_code":"I9",
    "gn:admin3_code":"33UB",
    "gn:admin4_code":"33UB030",
    "gn:asciiname":"Great Fransham",
    "gn:country_code":"GB",
    "gn:dem":68,
    "gn:feature_class":"P",
    "gn:feature_code":"PPL",
    "gn:name":"Great Fransham",
    "gn:population":0,
    "gn:timezone":"Europe/London",
    "iso:country":"GB",
    "name:cym_x_preferred":[
        "Great Fransham"
    ],
    "name:pol_x_preferred":[
        "Great Fransham"
    ],
    "name:und_x_variant":[
        "Fransham"
    ],
    "wof:name":"Great Fransham",
    "wof:placetype":"neighbourhood"
},
  "geometry": {"coordinates":[0.80508,52.6852],"type":"Point"}
}