{
  "type": "Feature",
  "properties": {
    "iso:country":"GB",
    "name:eng_x_preferred":[
        "Intack"
    ],
    "name:unk_x_variant":[
        "Intack"
    ],
    "qs:gn_local":0,
    "qs:local_max":2015,
    "qs:local_sum":4792,
    "qs:localhoods":5,
    "qs:name":"Intack",
    "qs:name_adm0":"United Kingdom",
    "qs:name_adm1":"England",
    "qs:name_adm2":"Lancashire",
    "qs:name_lau":"Blackburn with Darwen",
    "qs:name_local":"Blackburn",
    "qs:photo_max":301,
    "qs:photo_sum":918,
    "qs:placetype":"Suburb",
    "qs:quad_count":65,
    "qs:woe_adm0":23424975,
    "qs:woe_adm1":24554868,
    "qs:woe_adm2":12602160,
    "qs:woe_lau":12696178,
    "qs:woe_local":12850,
    "qs:woe_ver":"7.10.0",
    "wof:lang":[
        "eng"
    ],
    "wof:name":"Intack",
    "wof:placetype":"neighbourhood"
},
  "geometry": {"coordinates":[-2.446321,53.749351],"type":"Point"}
}