{
  "type": "Feature",
  "properties": {
    "gn:admin1_code":"NIR",
    "gn:admin2_code":"N09000006",
    "gn:asciiname":"Altamuskin",
    "gn:country_code":"GB",
    "gn:dem":206,
    "gn:feature_class":"P",
    "gn:feature_code":"PPL",
    "gn:name":"Altamuskin",
    "gn:population":0,
    "gn:timezone":"Europe/London",
    "iso:country":"GB",
    "name:eus_x_preferred":[
        "Altamuskin"
    ],
    "name:msa_x_preferred":[
        "Altamuskin"
    ],
    "name:pli_x_preferred":[
        "\u0905\u0932\u094d\u0924\u093e\u092e\u0941\u0938\u094d\u0915\u093f\u0928"
    ],
    "name:spa_x_preferred":[
        "Altamuskin"
    ],
    "wof:name":"Altamuskin",
    "wof:placetype":"locality"
},
  "geometry": {"coordinates":[-7.08333,54.51667],"type":"Point"}
}