{
  "type": "Feature",
  "properties": {
    "iso:country":"GB",
    "name:eng_x_preferred":[
        "Baldersby St James"
    ],
    "name:fra_x_preferred":[
        "Baldersby St James"
    ],
    "name:jpn_x_preferred":[
        "\u30d0\u30eb\u30c0\u30fc\u30b9\u30d3\u30fc\u30fb\u30bb\u30f3\u30c8\u30fb\u30b8\u30a7\u30fc\u30e0\u30ba"
    ],
    "name:nld_x_preferred":[
        "Baldersby St James"
    ],
    "name:pol_x_preferred":[
        "Baldersby St James"
    ],
    "qs_pg:aaroncc":"GB",
    "qs_pg:name":"Baldersby-st-James",
    "qs_pg:name_adm0":"United Kingdom",
    "qs_pg:name_adm1":"England",
    "qs_pg:photos":71,
    "qs_pg:photos_1k":14,
    "qs_pg:photos_9k":1,
    "qs_pg:photos_9r":2,
    "qs_pg:photos_all":71,
    "qs_pg:photos_sr":2,
    "qs_pg:pop_sr":0,
    "qs_pg:qs_pg_placetype":"locality",
    "qs_pg:qs_pg_placetype_gp":"Town",
    "qs_pg:woe_adm0":23424975,
    "woe:adm0_id":23424975,
    "woe:name_adm0":"United Kingdom",
    "woe:name_adm1":"England",
    "woe:placetype":"Town",
    "wof:name":"Baldersby-st-James",
    "wof:placetype":"neighbourhood"
},
  "geometry": {"coordinates":[-1.443457,54.187829],"type":"Point"}
}