{
  "type": "Feature",
  "properties": {
    "gn:admin1_code":"ENG",
    "gn:admin2_code":"F2",
    "gn:admin3_code":"24UB",
    "gn:admin4_code":"24UB001",
    "gn:asciiname":"Plastow Green",
    "gn:country_code":"GB",
    "gn:dem":94,
    "gn:feature_class":"P",
    "gn:feature_code":"PPL",
    "gn:name":"Plastow Green",
    "gn:population":0,
    "gn:timezone":"Europe/London",
    "iso:country":"GB",
    "name:cym_x_preferred":[
        "Plastow Green"
    ],
    "name:pol_x_preferred":[
        "Plastow Green"
    ],
    "wof:name":"Plastow Green",
    "wof:placetype":"neighbourhood"
},
  "geometry": {"coordinates":[-1.23455,51.35477],"type":"Point"}
}