{
  "type": "Feature",
  "properties": {
    "gn:population":1639,
    "iso:country":"GB",
    "name:azb_x_preferred":[
        "\u067e\u0648\u0631\u062a\u0648\u06cc\u0642"
    ],
    "name:bul_x_preferred":[
        "\u041f\u043e\u0440\u0442\u0430\u0432\u043e\u0433\u0438\u0435"
    ],
    "name:ceb_x_preferred":[
        "Portavogie"
    ],
    "name:eng_x_preferred":[
        "Portavogie"
    ],
    "name:eus_x_preferred":[
        "Portavogie"
    ],
    "name:fas_x_preferred":[
        "\u067e\u0648\u0631\u062a\u0648\u06cc\u06af"
    ],
    "name:fra_x_preferred":[
        "Portavogie"
    ],
    "name:gle_x_preferred":[
        "Port a' Bhogaigh"
    ],
    "name:ita_x_preferred":[
        "Portavogie"
    ],
    "name:msa_x_preferred":[
        "Portavogie"
    ],
    "name:nld_x_preferred":[
        "Portavogie"
    ],
    "name:pli_x_preferred":[
        "\u092a\u094b\u0930\u094d\u0924\u093e\u0935\u094b\u0917\u093f\u090f"
    ],
    "name:spa_x_preferred":[
        "Portavogie"
    ],
    "name:swe_x_preferred":[
        "Portavogie"
    ],
    "qs:a0":"United Kingdom",
    "qs:a1":"*Ards",
    "qs:a1_lc":"N_A",
    "qs:a1r":"0Northern Ireland",
    "qs:a1r_lc":"N_A",
    "qs:adm0":"United Kingdom",
    "qs:la_lc":"*",
    "qs:level":"locality",
    "qs:loc":"Portavogie",
    "qs:loc_alt":"Portavogie",
    "qs:pop":0,
    "qs:type":"buffered point",
    "wd:wordcount":1491,
    "wof:name":"Portavogie",
    "wof:placetype":"locality",
    "wof:population":1639
},
  "geometry": {"coordinates":[-5.442796,54.455086],"type":"Point"}
}