{
  "type": "Feature",
  "properties": {
    "iso:country":"GB",
    "name:dut_x_preferred":[
        "Tattenhoe"
    ],
    "name:eng_x_preferred":[
        "Tattenhoe"
    ],
    "name:fre_x_preferred":[
        "Tattenhoe"
    ],
    "name:nob_x_preferred":[
        "Tattenhoe"
    ],
    "name:wel_x_preferred":[
        "Tattenhoe"
    ],
    "qs_pg:aaroncc":"GB",
    "qs_pg:name":"Tattenhoe",
    "qs_pg:name_adm0":"United Kingdom",
    "qs_pg:name_adm1":"England",
    "qs_pg:photos":2285,
    "qs_pg:photos_1k":463,
    "qs_pg:photos_9k":10,
    "qs_pg:photos_9r":9,
    "qs_pg:photos_all":2285,
    "qs_pg:photos_sr":17,
    "qs_pg:pop_sr":0,
    "qs_pg:qs_pg_placetype":"locality",
    "qs_pg:qs_pg_placetype_gp":"Town",
    "qs_pg:woe_adm0":23424975,
    "woe:adm0_id":23424975,
    "woe:name_adm0":"United Kingdom",
    "woe:name_adm1":"England",
    "woe:placetype":"Town",
    "wof:name":"Tattenhoe",
    "wof:placetype":"neighbourhood"
},
  "geometry": {"coordinates":[-0.845775,51.994618],"type":"Point"}
}