{
  "type": "Feature",
  "properties": {
    "gn:country":"GB",
    "gn:fcode":"PPLX",
    "gn:population":0,
    "iso:country":"GB",
    "name:ceb_x_preferred":[
        "Swindon"
    ],
    "name:pol_x_preferred":[
        "Swindon"
    ],
    "name:swe_x_preferred":[
        "Swindon"
    ],
    "name:und_x_variant":[
        "Swan Village"
    ],
    "qs_pg:aaroncc":"GB",
    "qs_pg:gn_country":"GB",
    "qs_pg:gn_fcode":"PPLX",
    "qs_pg:gn_pop":0,
    "qs_pg:name":"Swindon Village",
    "qs_pg:name_adm0":"United Kingdom",
    "qs_pg:name_adm1":"England",
    "qs_pg:photos":2,
    "qs_pg:photos_1k":1,
    "qs_pg:photos_9k":1,
    "qs_pg:photos_9r":1,
    "qs_pg:photos_all":2,
    "qs_pg:photos_sr":1,
    "qs_pg:pop_sr":0,
    "qs_pg:qs_pg_placetype":"neighbourhood",
    "qs_pg:qs_pg_placetype_gp":"Suburb",
    "qs_pg:woe_adm0":23424975,
    "woe:adm0_id":23424975,
    "woe:name_adm0":"United Kingdom",
    "woe:name_adm1":"England",
    "woe:placetype":"Suburb",
    "wof:name":"Swindon Village",
    "wof:placetype":"neighbourhood"
},
  "geometry": {"coordinates":[-2.01667,52.53333],"type":"Point"}
}