{
  "type": "Feature",
  "properties": {
    "gn:admin1_code":"SCT",
    "gn:admin2_code":"W4",
    "gn:asciiname":"Whitletts",
    "gn:country_code":"GB",
    "gn:dem":27,
    "gn:feature_class":"P",
    "gn:feature_code":"PPL",
    "gn:name":"Whitletts",
    "gn:population":0,
    "gn:timezone":"Europe/London",
    "iso:country":"GB",
    "wof:name":"Whitletts",
    "wof:placetype":"locality"
},
  "geometry": {"coordinates":[-4.59173,55.47435],"type":"Point"}
}