{
  "type": "Feature",
  "properties": {
    "iso:country":"GB",
    "name:ara_x_preferred":[
        "\u0648\u0631\u0633\u0644\u064a"
    ],
    "name:cym_x_preferred":[
        "Waresley"
    ],
    "name:eng_x_preferred":[
        "Waresley"
    ],
    "name:fas_x_preferred":[
        "\u0648\u0627\u0631\u0633\u0644\u06cc"
    ],
    "name:fra_x_preferred":[
        "Waresley"
    ],
    "name:ita_x_preferred":[
        "Waresley"
    ],
    "name:nld_x_preferred":[
        "Waresley"
    ],
    "name:pol_x_preferred":[
        "Waresley"
    ],
    "name:swe_x_preferred":[
        "Waresley"
    ],
    "qs_pg:aaroncc":"GB",
    "qs_pg:name":"Waresley",
    "qs_pg:name_adm0":"United Kingdom",
    "qs_pg:name_adm1":"England",
    "qs_pg:photos":925,
    "qs_pg:photos_1k":187,
    "qs_pg:photos_9k":4,
    "qs_pg:photos_9r":6,
    "qs_pg:photos_all":925,
    "qs_pg:photos_sr":10,
    "qs_pg:pop_sr":0,
    "qs_pg:qs_pg_placetype":"locality",
    "qs_pg:qs_pg_placetype_gp":"Town",
    "qs_pg:woe_adm0":23424975,
    "woe:adm0_id":23424975,
    "woe:name_adm0":"United Kingdom",
    "woe:name_adm1":"England",
    "woe:placetype":"Town",
    "wof:name":"Waresley",
    "wof:placetype":"neighbourhood"
},
  "geometry": {"coordinates":[-0.175781,52.180773],"type":"Point"}
}