{
  "type": "Feature",
  "properties": {
    "gn:admin1_code":"ENG",
    "gn:admin2_code":"A4",
    "gn:admin3_code":"00HA044",
    "gn:asciiname":"Upper Swainswick",
    "gn:country_code":"GB",
    "gn:dem":84,
    "gn:feature_class":"P",
    "gn:feature_code":"PPL",
    "gn:name":"Upper Swainswick",
    "gn:population":0,
    "gn:timezone":"Europe/London",
    "iso:country":"GB",
    "name:und_x_variant":[
        "Swainswick",
        "Upper Swainswick"
    ],
    "wof:name":"Upper Swainswick",
    "wof:placetype":"neighbourhood"
},
  "geometry": {"coordinates":[-2.35096,51.41393],"type":"Point"}
}