{
  "type": "Feature",
  "properties": {
    "gn:admin1_code":"ENG",
    "gn:admin2_code":"H7",
    "gn:admin3_code":"32UE",
    "gn:admin4_code":"32UE041",
    "gn:asciiname":"Haceby",
    "gn:country_code":"GB",
    "gn:dem":68,
    "gn:feature_class":"P",
    "gn:feature_code":"PPL",
    "gn:name":"Haceby",
    "gn:population":0,
    "gn:timezone":"Europe/London",
    "iso:country":"GB",
    "name:pol_x_preferred":[
        "Haceby"
    ],
    "wof:name":"Haceby",
    "wof:placetype":"neighbourhood"
},
  "geometry": {"coordinates":[-0.47009,52.91196],"type":"Point"}
}