{
  "type": "Feature",
  "properties": {
    "gn:admin1_code": "ENG",
    "gn:admin2_code": "D4",
    "gn:admin3_code": "18UH",
    "gn:admin4_code": "18UH022",
    "gn:asciiname": "Holcombe Burnell Barton",
    "gn:country_code": "GB",
    "gn:dem": 165,
    "gn:feature_class": "P",
    "gn:feature_code": "PPL",
    "gn:name": "Holcombe Burnell Barton",
    "gn:population": 0,
    "gn:timezone": "Europe/London",
    "iso:country": "GB",
    "wof:name": "Holcombe Burnell Barton",
    "wof:placetype": "neighbourhood"
  },
  "geometry": {"coordinates":[-3.61759,50.71304],"type":"Point"}
}
