{
  "type": "Feature",
  "properties": {
    "gn:admin1_code":"NIR",
    "gn:admin2_code":"N09000009",
    "gn:asciiname":"Oritor",
    "gn:country_code":"GB",
    "gn:dem":89,
    "gn:feature_class":"P",
    "gn:feature_code":"PPL",
    "gn:name":"Oritor",
    "gn:population":0,
    "gn:timezone":"Europe/London",
    "iso:country":"GB",
    "wof:name":"Oritor",
    "wof:placetype":"locality"
},
  "geometry": {"coordinates":[-6.80225,54.65695],"type":"Point"}
}