{
  "type": "Feature",
  "properties": {
    "iso:country":"GB",
    "name:cym_x_preferred":[
        "Bilston"
    ],
    "name:eng_x_preferred":[
        "Bilston"
    ],
    "name:eus_x_preferred":[
        "Bilston"
    ],
    "name:fra_x_preferred":[
        "Bilston"
    ],
    "name:ita_x_preferred":[
        "Bilston"
    ],
    "name:jpn_x_preferred":[
        "\u30d3\u30eb\u30b9\u30c8\u30f3"
    ],
    "name:nld_x_preferred":[
        "Bilston"
    ],
    "name:nno_x_preferred":[
        "Bilston i Midtlothian"
    ],
    "name:nob_x_preferred":[
        "Bilston"
    ],
    "name:spa_x_preferred":[
        "Bilston"
    ],
    "name:swe_x_preferred":[
        "Bilston"
    ],
    "qs_pg:aaroncc":"GB",
    "qs_pg:name":"Bilston",
    "qs_pg:name_adm0":"United Kingdom",
    "qs_pg:name_adm1":"Scotland",
    "qs_pg:photos":332,
    "qs_pg:photos_1k":67,
    "qs_pg:photos_9k":1,
    "qs_pg:photos_9r":5,
    "qs_pg:photos_all":332,
    "qs_pg:photos_sr":5,
    "qs_pg:pop_sr":0,
    "qs_pg:qs_pg_placetype":"locality",
    "qs_pg:qs_pg_placetype_gp":"Town",
    "qs_pg:woe_adm0":23424975,
    "woe:adm0_id":23424975,
    "woe:name_adm0":"United Kingdom",
    "woe:name_adm1":"Scotland",
    "woe:placetype":"Town",
    "wof:name":"Bilston",
    "wof:placetype":"locality"
},
  "geometry": {"coordinates":[-3.177945,55.872629],"type":"Point"}
}