{
  "type": "Feature",
  "properties": {
    "gn:admin1_code":"SCT",
    "gn:admin2_code":"V3",
    "gn:asciiname":"Oykell Bridge",
    "gn:country_code":"GB",
    "gn:dem":51,
    "gn:feature_class":"P",
    "gn:feature_code":"PPL",
    "gn:name":"Oykell Bridge",
    "gn:population":0,
    "gn:timezone":"Europe/London",
    "iso:country":"GB",
    "wof:name":"Oykell Bridge",
    "wof:placetype":"locality"
},
  "geometry": {"coordinates":[-4.71667,57.96667],"type":"Point"}
}