{
  "type": "Feature",
  "properties": {
    "gn:country":"GB",
    "gn:fcode":"PPL",
    "gn:population":5609,
    "iso:country":"GB",
    "name:ara_x_preferred":[
        "\u0623\u0648\u062f\u064a\u0646\u063a\u0633\u062a\u0646"
    ],
    "name:arz_x_preferred":[
        "\u0627\u0648\u062f\u064a\u0646\u062c\u0633\u062a\u0646"
    ],
    "name:ast_x_preferred":[
        "Uddingston"
    ],
    "name:azb_x_preferred":[
        "\u0627\u0648\u062f\u06cc\u0646\u0642\u0633\u062a\u0648\u0646"
    ],
    "name:bel_x_preferred":[
        "\u0410\u0434\u044b\u043d\u0433\u0441\u0442\u0430\u043d"
    ],
    "name:bul_x_preferred":[
        "\u0423\u0434\u0438\u043d\u0433\u0441\u0442\u043e\u043d"
    ],
    "name:ceb_x_preferred":[
        "Uddingston"
    ],
    "name:cym_x_preferred":[
        "Uddingston"
    ],
    "name:deu_x_preferred":[
        "Uddingston"
    ],
    "name:eng_x_preferred":[
        "Uddingston"
    ],
    "name:eus_x_preferred":[
        "Uddingston"
    ],
    "name:fas_x_preferred":[
        "\u0627\u0648\u062f\u06cc\u0646\u06af\u0633\u062a\u0648\u0646"
    ],
    "name:fra_x_preferred":[
        "Uddingston"
    ],
    "name:gla_x_preferred":[
        "Baile Udain"
    ],
    "name:gle_x_preferred":[
        "Baile Udain"
    ],
    "name:heb_x_preferred":[
        "\u05d0\u05d5\u05d3\u05d9\u05e0\u05d2\u05e1\u05d8\u05d5\u05df"
    ],
    "name:ita_x_preferred":[
        "Uddingston"
    ],
    "name:jpn_x_preferred":[
        "\u30a2\u30c7\u30a3\u30f3\u30b9\u30c8\u30f3"
    ],
    "name:nld_x_preferred":[
        "Uddingston"
    ],
    "name:spa_x_preferred":[
        "Uddingston"
    ],
    "name:swe_x_preferred":[
        "Uddingston"
    ],
    "qs_pg:aaroncc":"GB",
    "qs_pg:gn_country":"GB",
    "qs_pg:gn_fcode":"PPL",
    "qs_pg:gn_pop":5609,
    "qs_pg:name":"Uddingston",
    "qs_pg:name_adm0":"United Kingdom",
    "qs_pg:name_adm1":"Scotland",
    "qs_pg:photos":302,
    "qs_pg:photos_1k":61,
    "qs_pg:photos_9k":1,
    "qs_pg:photos_9r":5,
    "qs_pg:photos_all":302,
    "qs_pg:photos_sr":5,
    "qs_pg:pop_sr":5,
    "qs_pg:qs_pg_placetype":"locality",
    "qs_pg:qs_pg_placetype_gp":"Town",
    "qs_pg:woe_adm0":23424975,
    "woe:adm0_id":23424975,
    "woe:name_adm0":"United Kingdom",
    "woe:name_adm1":"Scotland",
    "woe:placetype":"Town",
    "wof:name":"Uddingston",
    "wof:placetype":"locality",
    "wof:population":5610
},
  "geometry": {"coordinates":[-4.08362,55.81971],"type":"Point"}
}