{
  "type": "Feature",
  "properties": {
    "gn:admin1_code":"WLS",
    "gn:admin2_code":"Y8",
    "gn:admin3_code":"00NN107",
    "gn:asciiname":"Cascob",
    "gn:country_code":"GB",
    "gn:dem":238,
    "gn:feature_class":"P",
    "gn:feature_code":"PPL",
    "gn:name":"Cascob",
    "gn:population":0,
    "gn:timezone":"Europe/London",
    "iso:country":"GB",
    "name:cym_x_preferred":[
        "Casgob"
    ],
    "wof:name":"Cascob",
    "wof:placetype":"neighbourhood"
},
  "geometry": {"coordinates":[-3.1157,52.291],"type":"Point"}
}