{
  "type": "Feature",
  "properties": {
    "gn:population": 9477,
    "iso:country": "GB",
    "name:ceb_x_preferred": [
      "Queensferry"
    ],
    "name:deu_x_preferred": [
      "South Queensferry"
    ],
    "name:eng_x_preferred": [
      "Queensferry"
    ],
    "name:eng_x_variant": [
      "South Queensferry"
    ],
    "name:eus_x_preferred": [
      "South Queensferry"
    ],
    "name:fas_x_preferred": [
      "ساوث"
    ],
    "name:fra_x_preferred": [
      "Queensferry"
    ],
    "name:gla_x_preferred": [
      "Cas Chaolais"
    ],
    "name:gle_x_preferred": [
      "Cas Chaolas"
    ],
    "name:hbs_x_preferred": [
      "Queensferry"
    ],
    "name:heb_x_preferred": [
      "סאות קווינספרי"
    ],
    "name:ita_x_preferred": [
      "South Queensferry"
    ],
    "name:jpn_x_preferred": [
      "サウス・クィーンズフェリー"
    ],
    "name:nld_x_preferred": [
      "Queensferry"
    ],
    "name:pol_x_preferred": [
      "South Queensferry"
    ],
    "name:spa_x_preferred": [
      "South Queensferry"
    ],
    "name:swe_x_preferred": [
      "Queensferry"
    ],
    "name:urd_x_preferred": [
      "جنوبی کوئنزفیری"
    ],
    "qs:a0": "United Kingdom",
    "qs:a1": "*City of Edinburgh",
    "qs:a1_lc": "GB11QP0000",
    "qs:a1r": "0Scotland",
    "qs:a1r_lc": "GB11000000",
    "qs:adm0": "United Kingdom",
    "qs:la_lc": "*",
    "qs:level": "locality",
    "qs:loc": "Queensferry",
    "qs:loc_alt": "Queensferry",
    "qs:pop": 0,
    "qs:type": "buffered point",
    "wd:wordcount": 2026,
    "wof:name": "Queensferry",
    "wof:placetype": "neighbourhood",
    "wof:population": 9477
  },
  "geometry": {"coordinates":[-3.403729,55.989507],"type":"Point"}
}
