{
  "type": "Feature",
  "properties": {
    "gn:population":9477,
    "iso:country":"GB",
    "name:ceb_x_preferred":[
        "Queensferry"
    ],
    "name:deu_x_preferred":[
        "South Queensferry"
    ],
    "name:eng_x_preferred":[
        "Queensferry"
    ],
    "name:eng_x_variant":[
        "South Queensferry"
    ],
    "name:eus_x_preferred":[
        "South Queensferry"
    ],
    "name:fas_x_preferred":[
        "\u0633\u0627\u0648\u062b"
    ],
    "name:fra_x_preferred":[
        "Queensferry"
    ],
    "name:gla_x_preferred":[
        "Cas Chaolais"
    ],
    "name:gle_x_preferred":[
        "Cas Chaolas"
    ],
    "name:hbs_x_preferred":[
        "Queensferry"
    ],
    "name:heb_x_preferred":[
        "\u05e1\u05d0\u05d5\u05ea \u05e7\u05d5\u05d5\u05d9\u05e0\u05e1\u05e4\u05e8\u05d9"
    ],
    "name:ita_x_preferred":[
        "South Queensferry"
    ],
    "name:jpn_x_preferred":[
        "\u30b5\u30a6\u30b9\u30fb\u30af\u30a3\u30fc\u30f3\u30ba\u30d5\u30a7\u30ea\u30fc"
    ],
    "name:nld_x_preferred":[
        "Queensferry"
    ],
    "name:pol_x_preferred":[
        "South Queensferry"
    ],
    "name:spa_x_preferred":[
        "South Queensferry"
    ],
    "name:swe_x_preferred":[
        "Queensferry"
    ],
    "name:urd_x_preferred":[
        "\u062c\u0646\u0648\u0628\u06cc \u06a9\u0648\u0626\u0646\u0632\u0641\u06cc\u0631\u06cc"
    ],
    "qs:a0":"United Kingdom",
    "qs:a1":"*City of Edinburgh",
    "qs:a1_lc":"GB11QP0000",
    "qs:a1r":"0Scotland",
    "qs:a1r_lc":"GB11000000",
    "qs:adm0":"United Kingdom",
    "qs:la_lc":"*",
    "qs:level":"locality",
    "qs:loc":"Queensferry",
    "qs:loc_alt":"Queensferry",
    "qs:pop":0,
    "qs:type":"buffered point",
    "wd:wordcount":2026,
    "wof:name":"Queensferry",
    "wof:placetype":"neighbourhood",
    "wof:population":9477
},
  "geometry": {"coordinates":[-3.403729,55.989507],"type":"Point"}
}