{
  "type": "Feature",
  "properties": {
    "gn:admin1_code":"WLS",
    "gn:admin2_code":"Y7",
    "gn:admin3_code":"00NS006",
    "gn:asciiname":"Houghton",
    "gn:country_code":"GB",
    "gn:dem":63,
    "gn:feature_class":"P",
    "gn:feature_code":"PPL",
    "gn:name":"Houghton",
    "gn:population":0,
    "gn:timezone":"Europe/London",
    "iso:country":"GB",
    "wof:name":"Houghton",
    "wof:placetype":"neighbourhood"
},
  "geometry": {"coordinates":[-4.92083,51.72889],"type":"Point"}
}