{
  "type": "Feature",
  "properties": {
    "gn:admin1_code": "WLS",
    "gn:admin2_code": "Y7",
    "gn:admin3_code": "00NS006",
    "gn:asciiname": "Houghton",
    "gn:country_code": "GB",
    "gn:dem": 63,
    "gn:feature_class": "P",
    "gn:feature_code": "PPL",
    "gn:name": "Houghton",
    "gn:population": 0,
    "gn:timezone": "Europe/London",
    "iso:country": "GB",
    "name:ara_x_preferred": [
      "هوتون"
    ],
    "name:cat_x_preferred": [
      "Houghton"
    ],
    "name:ceb_x_preferred": [
      "Houghton"
    ],
    "name:deu_x_preferred": [
      "Houghton"
    ],
    "name:epo_x_preferred": [
      "Houghton"
    ],
    "name:fin_x_preferred": [
      "Houghton"
    ],
    "name:fra_x_preferred": [
      "Houghton"
    ],
    "name:ita_x_preferred": [
      "Houghton"
    ],
    "name:nld_x_preferred": [
      "Houghton"
    ],
    "name:pol_x_preferred": [
      "Houghton"
    ],
    "name:por_x_preferred": [
      "Houghton"
    ],
    "name:rus_x_preferred": [
      "Хафтон"
    ],
    "name:spa_x_preferred": [
      "Houghton"
    ],
    "name:swe_x_preferred": [
      "Houghton"
    ],
    "name:ukr_x_preferred": [
      "Гоутен"
    ],
    "name:vol_x_preferred": [
      "Houghton"
    ],
    "wof:name": "Houghton",
    "wof:placetype": "neighbourhood"
  },
  "geometry": {"coordinates":[-4.92083,51.72889],"type":"Point"}
}
