{
  "type": "Feature",
  "properties": {
    "gn:population": 2263,
    "iso:country": "GB",
    "name:cat_x_preferred": [
      "Castledawson"
    ],
    "name:ceb_x_preferred": [
      "Castledawson"
    ],
    "name:ces_x_preferred": [
      "Castledawson"
    ],
    "name:ell_x_preferred": [
      "Κάστλντοσον"
    ],
    "name:eng_x_preferred": [
      "Castledawson"
    ],
    "name:eus_x_preferred": [
      "Castledawson"
    ],
    "name:fas_x_preferred": [
      "کسلداوسون"
    ],
    "name:fra_x_preferred": [
      "Castledawson"
    ],
    "name:fry_x_preferred": [
      "Castledawson"
    ],
    "name:gla_x_preferred": [
      "An Seanmhullach"
    ],
    "name:gle_x_preferred": [
      "An Seanmhullach"
    ],
    "name:glg_x_preferred": [
      "Castledawson"
    ],
    "name:heb_x_preferred": [
      "קסלדאווסון"
    ],
    "name:hye_x_preferred": [
      "Քասլդոուսն"
    ],
    "name:ita_x_preferred": [
      "Castledawson"
    ],
    "name:jpn_x_preferred": [
      "キャッスルドーソン"
    ],
    "name:lit_x_preferred": [
      "Kasldosonas"
    ],
    "name:ltz_x_preferred": [
      "Castledawson"
    ],
    "name:msa_x_preferred": [
      "Castledawson"
    ],
    "name:nld_x_preferred": [
      "Castledawson"
    ],
    "name:oci_x_preferred": [
      "Castledawson"
    ],
    "name:pli_x_preferred": [
      "कास्त्लेदाव्सों"
    ],
    "name:por_x_preferred": [
      "Castledawson"
    ],
    "name:spa_x_preferred": [
      "Castledawson"
    ],
    "name:swe_x_preferred": [
      "Castledawson"
    ],
    "name:tat_x_preferred": [
      "Кәстлдоусон"
    ],
    "qs:a0": "United Kingdom",
    "qs:a1": "*Magherafelt",
    "qs:a1_lc": "N_A",
    "qs:a1r": "0Northern Ireland",
    "qs:a1r_lc": "N_A",
    "qs:adm0": "United Kingdom",
    "qs:la_lc": "*",
    "qs:level": "locality",
    "qs:loc": "Castledawson",
    "qs:loc_alt": "Castledawson",
    "qs:pop": 0,
    "qs:type": "buffered point",
    "wd:wordcount": 560,
    "wof:name": "Castledawson",
    "wof:placetype": "locality",
    "wof:population": 2263
  },
  "geometry": {"coordinates":[-6.555042,54.778568],"type":"Point"}
}
