{
  "type": "Feature",
  "properties": {
    "gn:population":2263,
    "iso:country":"GB",
    "name:ast_x_preferred":[
        "Castledawson"
    ],
    "name:aze_x_preferred":[
        "Kastledavson"
    ],
    "name:cat_x_preferred":[
        "Castledawson"
    ],
    "name:ceb_x_preferred":[
        "Castledawson"
    ],
    "name:ces_x_preferred":[
        "Castledawson"
    ],
    "name:ell_x_preferred":[
        "\u039a\u03ac\u03c3\u03c4\u03bb\u03bd\u03c4\u03bf\u03c3\u03bf\u03bd"
    ],
    "name:eng_x_preferred":[
        "Castledawson"
    ],
    "name:eus_x_preferred":[
        "Castledawson"
    ],
    "name:fas_x_preferred":[
        "\u06a9\u0633\u0644\u062f\u0627\u0648\u0633\u0648\u0646"
    ],
    "name:fra_x_preferred":[
        "Castledawson"
    ],
    "name:fry_x_preferred":[
        "Castledawson"
    ],
    "name:gla_x_preferred":[
        "An Seanmhullach"
    ],
    "name:gle_x_preferred":[
        "An Seanmhullach"
    ],
    "name:glg_x_preferred":[
        "Castledawson"
    ],
    "name:heb_x_preferred":[
        "\u05e7\u05e1\u05dc\u05d3\u05d0\u05d5\u05d5\u05e1\u05d5\u05df"
    ],
    "name:hye_x_preferred":[
        "\u0554\u0561\u057d\u056c\u0564\u0578\u0578\u0582\u057d\u0576"
    ],
    "name:ita_x_preferred":[
        "Castledawson"
    ],
    "name:jpn_x_preferred":[
        "\u30ad\u30e3\u30c3\u30b9\u30eb\u30c9\u30fc\u30bd\u30f3"
    ],
    "name:lit_x_preferred":[
        "Kasldosonas"
    ],
    "name:ltz_x_preferred":[
        "Castledawson"
    ],
    "name:msa_x_preferred":[
        "Castledawson"
    ],
    "name:nld_x_preferred":[
        "Castledawson"
    ],
    "name:oci_x_preferred":[
        "Castledawson"
    ],
    "name:pli_x_preferred":[
        "\u0915\u093e\u0938\u094d\u0924\u094d\u0932\u0947\u0926\u093e\u0935\u094d\u0938\u094b\u0902"
    ],
    "name:por_x_preferred":[
        "Castledawson"
    ],
    "name:spa_x_preferred":[
        "Castledawson"
    ],
    "name:swe_x_preferred":[
        "Castledawson"
    ],
    "name:tat_x_preferred":[
        "\u041a\u04d9\u0441\u0442\u043b\u0434\u043e\u0443\u0441\u043e\u043d"
    ],
    "qs:a0":"United Kingdom",
    "qs:a1":"*Magherafelt",
    "qs:a1_lc":"N_A",
    "qs:a1r":"0Northern Ireland",
    "qs:a1r_lc":"N_A",
    "qs:adm0":"United Kingdom",
    "qs:la_lc":"*",
    "qs:level":"locality",
    "qs:loc":"Castledawson",
    "qs:loc_alt":"Castledawson",
    "qs:pop":0,
    "qs:type":"buffered point",
    "wd:wordcount":560,
    "wof:name":"Castledawson",
    "wof:placetype":"locality",
    "wof:population":2263
},
  "geometry": {"coordinates":[-6.555042,54.778568],"type":"Point"}
}