{
  "type": "Feature",
  "properties": {
    "gn:admin1_code":"ENG",
    "gn:admin2_code":"I9",
    "gn:admin3_code":"33UF",
    "gn:admin4_code":"33UF091",
    "gn:asciiname":"Stalham Green",
    "gn:country_code":"GB",
    "gn:dem":3,
    "gn:feature_class":"P",
    "gn:feature_code":"PPL",
    "gn:name":"Stalham Green",
    "gn:population":0,
    "gn:timezone":"Europe/London",
    "iso:country":"GB",
    "wof:name":"Stalham Green",
    "wof:placetype":"neighbourhood"
},
  "geometry": {"coordinates":[1.52942,52.76756999999999],"type":"Point"}
}