{
  "type": "Feature",
  "properties": {
    "gn:admin1_code":"SCT",
    "gn:admin2_code":"T6",
    "gn:asciiname":"Pinkie",
    "gn:country_code":"GB",
    "gn:dem":82,
    "gn:feature_class":"P",
    "gn:feature_code":"PPLL",
    "gn:name":"Pinkie",
    "gn:population":0,
    "gn:timezone":"Europe/London",
    "iso:country":"GB",
    "name:deu_x_preferred":[
        "Pinkie"
    ],
    "wof:name":"Pinkie",
    "wof:placetype":"locality"
},
  "geometry": {"coordinates":[-2.17813,57.2608],"type":"Point"}
}