{
  "type": "Feature",
  "properties": {
    "gn:country": "GB",
    "gn:fcode": "PPL",
    "gn:population": 4,
    "iso:country": "GB",
    "name:eng_x_preferred": [
      "Bracorina"
    ],
    "name:eus_x_preferred": [
      "Bracorina"
    ],
    "name:nld_x_preferred": [
      "Bracorina"
    ],
    "qs_pg:aaroncc": "GB",
    "qs_pg:gn_country": "GB",
    "qs_pg:gn_fcode": "PPL",
    "qs_pg:gn_pop": 4,
    "qs_pg:name": "Bracorina",
    "qs_pg:name_adm0": "United Kingdom",
    "qs_pg:name_adm1": "Scotland",
    "qs_pg:photos": 44,
    "qs_pg:photos_1k": 9,
    "qs_pg:photos_9k": 1,
    "qs_pg:photos_9r": 2,
    "qs_pg:photos_all": 44,
    "qs_pg:photos_sr": 2,
    "qs_pg:pop_sr": 1,
    "qs_pg:qs_pg_placetype": "locality",
    "qs_pg:qs_pg_placetype_gp": "Town",
    "qs_pg:woe_adm0": 23424975,
    "woe:adm0_id": 23424975,
    "woe:name_adm0": "United Kingdom",
    "woe:name_adm1": "Scotland",
    "woe:placetype": "Town",
    "wof:name": "Bracorina",
    "wof:placetype": "locality",
    "wof:population": 4
  },
  "geometry": {"coordinates":[-5.74336,56.96964],"type":"Point"}
}
