{
  "type": "Feature",
  "properties": {
    "gn:population":17576,
    "iso:country":"GB",
    "name:ben_x_preferred":[
        "\u0993\u09af\u09bc\u09c7\u09b0"
    ],
    "name:cat_x_preferred":[
        "Ware"
    ],
    "name:ceb_x_preferred":[
        "Ware"
    ],
    "name:cym_x_preferred":[
        "Ware"
    ],
    "name:deu_x_preferred":[
        "Ware"
    ],
    "name:eng_x_preferred":[
        "Ware"
    ],
    "name:epo_x_preferred":[
        "Ware"
    ],
    "name:fas_x_preferred":[
        "\u0648\u0631\u060c \u0647\u0631\u062a\u0641\u0648\u0631\u062f\u0634\u0631"
    ],
    "name:fra_x_preferred":[
        "Ware"
    ],
    "name:gle_x_preferred":[
        "Ware"
    ],
    "name:guj_x_preferred":[
        "\u0ab5\u0ac7\u0ab0"
    ],
    "name:ita_x_preferred":[
        "Ware"
    ],
    "name:jpn_x_preferred":[
        "\u30a6\u30a7\u30a2"
    ],
    "name:kan_x_preferred":[
        "\u0cb5\u0cc7\u0cb0\u0ccd"
    ],
    "name:kor_x_preferred":[
        "\uc6cc"
    ],
    "name:lit_x_preferred":[
        "Veris"
    ],
    "name:mkd_x_preferred":[
        "\u0412\u0435\u0440"
    ],
    "name:nld_x_preferred":[
        "Ware"
    ],
    "name:nno_x_preferred":[
        "Ware"
    ],
    "name:oci_x_preferred":[
        "Ware"
    ],
    "name:pol_x_preferred":[
        "Ware"
    ],
    "name:por_x_preferred":[
        "Ware"
    ],
    "name:ron_x_preferred":[
        "Ware"
    ],
    "name:rus_x_preferred":[
        "\u0412\u044d\u0440"
    ],
    "name:spa_x_preferred":[
        "Ware"
    ],
    "name:swe_x_preferred":[
        "Ware"
    ],
    "name:tam_x_preferred":[
        "\u0bb5\u0bbe\u0bb0\u0bcd"
    ],
    "name:tel_x_preferred":[
        "\u0c35\u0c47\u0c30\u0c4d"
    ],
    "name:urd_x_preferred":[
        "\u0648\u0627\u0631\u06cc"
    ],
    "name:vol_x_preferred":[
        "Ware"
    ],
    "qs:a0":"United Kingdom",
    "qs:a1":"*Hertfordshire",
    "qs:a1_lc":"GB12260000",
    "qs:a1r":"0England",
    "qs:a1r_lc":"GB12000000",
    "qs:adm0":"United Kingdom",
    "qs:la_lc":"*",
    "qs:level":"locality",
    "qs:loc":"Ware",
    "qs:loc_alt":"Ware",
    "qs:pop":0,
    "qs:type":"buffered point",
    "wd:wordcount":3070,
    "wof:lang":[
        "eng"
    ],
    "wof:name":"Ware",
    "wof:placetype":"neighbourhood",
    "wof:population":17576
},
  "geometry": {"coordinates":[-0.029965,51.809417],"type":"Point"}
}