{
  "type": "Feature",
  "properties": {
    "gn:population": 17576,
    "iso:country": "GB",
    "name:ara_x_preferred": [
      "ور"
    ],
    "name:azb_x_preferred": [
      "ور"
    ],
    "name:ben_x_preferred": [
      "ওয়ের"
    ],
    "name:cat_x_preferred": [
      "Ware"
    ],
    "name:ceb_x_preferred": [
      "Ware"
    ],
    "name:cym_x_preferred": [
      "Ware"
    ],
    "name:deu_x_preferred": [
      "Ware"
    ],
    "name:eng_x_preferred": [
      "Ware"
    ],
    "name:epo_x_preferred": [
      "Ware"
    ],
    "name:fas_x_preferred": [
      "ور، هرتفوردشر"
    ],
    "name:fas_x_variant": [
      "ور"
    ],
    "name:fra_x_preferred": [
      "Ware"
    ],
    "name:gle_x_preferred": [
      "Ware"
    ],
    "name:guj_x_preferred": [
      "વેર"
    ],
    "name:ita_x_preferred": [
      "Ware"
    ],
    "name:jpn_x_preferred": [
      "ウェア"
    ],
    "name:kan_x_preferred": [
      "ವೇರ್"
    ],
    "name:kor_x_preferred": [
      "워"
    ],
    "name:lit_x_preferred": [
      "Veris"
    ],
    "name:mkd_x_preferred": [
      "Вер"
    ],
    "name:nld_x_preferred": [
      "Ware"
    ],
    "name:nno_x_preferred": [
      "Ware"
    ],
    "name:nob_x_preferred": [
      "Ware"
    ],
    "name:oci_x_preferred": [
      "Ware"
    ],
    "name:pol_x_preferred": [
      "Ware"
    ],
    "name:por_x_preferred": [
      "Ware"
    ],
    "name:ron_x_preferred": [
      "Ware"
    ],
    "name:rus_x_preferred": [
      "Вэр"
    ],
    "name:spa_x_preferred": [
      "Ware"
    ],
    "name:swe_x_preferred": [
      "Ware"
    ],
    "name:tam_x_preferred": [
      "வார்"
    ],
    "name:tel_x_preferred": [
      "వేర్"
    ],
    "name:urd_x_preferred": [
      "واری"
    ],
    "name:vol_x_preferred": [
      "Ware"
    ],
    "qs:a0": "United Kingdom",
    "qs:a1": "*Hertfordshire",
    "qs:a1_lc": "GB12260000",
    "qs:a1r": "0England",
    "qs:a1r_lc": "GB12000000",
    "qs:adm0": "United Kingdom",
    "qs:la_lc": "*",
    "qs:level": "locality",
    "qs:loc": "Ware",
    "qs:loc_alt": "Ware",
    "qs:pop": 0,
    "qs:type": "buffered point",
    "wd:wordcount": 3070,
    "wof:lang": [
      "eng"
    ],
    "wof:name": "Ware",
    "wof:placetype": "neighbourhood",
    "wof:population": 17576
  },
  "geometry": {"coordinates":[-0.029965,51.809417],"type":"Point"}
}
