{
  "type": "Feature",
  "properties": {
    "gn:country":"GB",
    "gn:fcode":"PPLA3",
    "gn:population":0,
    "iso:country":"GB",
    "name:cat_x_preferred":[
        "Charlton"
    ],
    "name:ceb_x_preferred":[
        "Charlton"
    ],
    "name:deu_x_preferred":[
        "Charlton"
    ],
    "name:est_x_preferred":[
        "Charlton"
    ],
    "name:fra_x_preferred":[
        "Charlton"
    ],
    "name:heb_x_preferred":[
        "\u05e6'\u05e8\u05dc\u05d8\u05d5\u05df"
    ],
    "name:ita_x_preferred":[
        "Charlton"
    ],
    "name:nld_x_preferred":[
        "Charlton"
    ],
    "name:nor_x_preferred":[
        "Charlton"
    ],
    "name:pol_x_preferred":[
        "Charlton"
    ],
    "name:rus_x_preferred":[
        "\u0427\u0430\u0440\u043b\u0442\u043e\u043d"
    ],
    "name:spa_x_preferred":[
        "Charlton"
    ],
    "name:srp_x_preferred":[
        "\u0427\u0430\u0440\u043b\u0442\u043e\u043d"
    ],
    "name:swe_x_preferred":[
        "Charlton"
    ],
    "name:ukr_x_preferred":[
        "\u0427\u0430\u0440\u043b\u0442\u043e\u043d"
    ],
    "qs_pg:aaroncc":"GB",
    "qs_pg:gn_country":"GB",
    "qs_pg:gn_fcode":"PPLA3",
    "qs_pg:gn_pop":0,
    "qs_pg:name":"Charlton",
    "qs_pg:name_adm0":"United Kingdom",
    "qs_pg:name_adm1":"England",
    "qs_pg:photos":517,
    "qs_pg:photos_1k":105,
    "qs_pg:photos_9k":2,
    "qs_pg:photos_9r":0,
    "qs_pg:photos_all":517,
    "qs_pg:photos_sr":0,
    "qs_pg:pop_sr":0,
    "qs_pg:qs_pg_placetype":"locality",
    "qs_pg:qs_pg_placetype_gp":"Town",
    "qs_pg:woe_adm0":23424975,
    "wof:name":"Charlton",
    "wof:placetype":"neighbourhood"
},
  "geometry": {"coordinates":[-2.05639,51.59917],"type":"Point"}
}