{
  "type": "Feature",
  "properties": {
    "iso:country":"GB",
    "wof:name":"Pickles Hill",
    "wof:placetype":"neighbourhood"
},
  "geometry": {"coordinates":[-1.79275260335386,53.77354448505767],"type":"Point"}
}