{
  "type": "Feature",
  "properties": {
    "iso:country":"GB",
    "name:bre_x_preferred":[
        "Ynyslas"
    ],
    "name:cym_x_preferred":[
        "Aberleri"
    ],
    "name:cym_x_variant":[
        "Ynyslas"
    ],
    "name:eng_x_preferred":[
        "Ynyslas"
    ],
    "name:eus_x_preferred":[
        "Ynyslas"
    ],
    "name:fra_x_preferred":[
        "Ynyslas"
    ],
    "name:gle_x_preferred":[
        "Ynyslas"
    ],
    "name:nld_x_preferred":[
        "Ynyslas"
    ],
    "name:tur_x_preferred":[
        "Ynyslas"
    ],
    "qs_pg:aaroncc":"GB",
    "qs_pg:name":"Ynyslas",
    "qs_pg:name_adm0":"United Kingdom",
    "qs_pg:name_adm1":"Wales",
    "qs_pg:photos":1093,
    "qs_pg:photos_1k":221,
    "qs_pg:photos_9k":5,
    "qs_pg:photos_9r":7,
    "qs_pg:photos_all":1093,
    "qs_pg:photos_sr":11,
    "qs_pg:pop_sr":0,
    "qs_pg:qs_pg_placetype":"locality",
    "qs_pg:qs_pg_placetype_gp":"Town",
    "qs_pg:woe_adm0":23424975,
    "woe:adm0_id":23424975,
    "woe:name_adm0":"United Kingdom",
    "woe:name_adm1":"Wales",
    "woe:placetype":"Town",
    "wof:name":"Ynyslas",
    "wof:placetype":"neighbourhood"
},
  "geometry": {"coordinates":[-4.053354,52.512695],"type":"Point"}
}