{
  "type": "Feature",
  "properties": {
    "name:azb_x_preferred":[
        "\u0645\u0646\u0648\u0631 \u067e\u0627\u0631\u06a9"
    ],
    "name:ces_x_preferred":[
        "Manor Park"
    ],
    "name:deu_x_preferred":[
        "Manor Park"
    ],
    "name:eng_x_preferred":[
        "Manor Park"
    ],
    "name:fas_x_preferred":[
        "\u0645\u0646\u0648\u0631 \u067e\u0627\u0631\u06a9\u060c \u0644\u0646\u062f\u0646"
    ],
    "name:fas_x_variant":[
        "\u0645\u0646\u0648\u0631 \u067e\u0627\u0631\u06a9"
    ],
    "name:fra_x_preferred":[
        "Manor Park"
    ],
    "name:heb_x_preferred":[
        "\u05de\u05e0\u05d5\u05e8 \u05e4\u05d0\u05e8\u05e7"
    ],
    "name:ita_x_preferred":[
        "Manor Park"
    ],
    "name:jpn_x_preferred":[
        "\u30de\u30ca\u30fc\u30fb\u30d1\u30fc\u30af"
    ],
    "name:nld_x_preferred":[
        "Manor Park"
    ],
    "name:nob_x_preferred":[
        "Manor Park"
    ],
    "name:rus_x_preferred":[
        "\u043f\u0430\u0440\u043a \u043c\u0430\u043d\u043e\u0440"
    ],
    "name:slk_x_preferred":[
        "Manor Park"
    ],
    "wd:wordcount":100,
    "wof:name":"Manor Park",
    "wof:placetype":"neighbourhood"
},
  "geometry": {"coordinates":[0.04878421250394,51.55182591831467],"type":"Point"}
}