{
  "type": "Feature",
  "properties": {
    "iso:country": "GB",
    "name:azb_x_preferred": [
      "منور پارک"
    ],
    "name:ces_x_preferred": [
      "Manor Park"
    ],
    "name:deu_x_preferred": [
      "Manor Park"
    ],
    "name:eng_x_preferred": [
      "Manor Park"
    ],
    "name:fas_x_preferred": [
      "منور پارک، لندن"
    ],
    "name:fas_x_variant": [
      "منور پارک"
    ],
    "name:fra_x_preferred": [
      "Manor Park"
    ],
    "name:heb_x_preferred": [
      "מנור פארק"
    ],
    "name:ita_x_preferred": [
      "Manor Park"
    ],
    "name:jpn_x_preferred": [
      "マナー・パーク"
    ],
    "name:nld_x_preferred": [
      "Manor Park"
    ],
    "name:nob_x_preferred": [
      "Manor Park"
    ],
    "name:rus_x_preferred": [
      "парк манор"
    ],
    "name:slk_x_preferred": [
      "Manor Park"
    ],
    "wd:wordcount": 100,
    "wof:name": "Manor Park",
    "wof:placetype": "neighbourhood"
  },
  "geometry": {"coordinates":[0.04878421250394,51.55182591831467],"type":"Point"}
}
