{
  "type": "Feature",
  "properties": {
    "gn:admin1_code":"ENG",
    "gn:admin2_code":"D4",
    "gn:admin3_code":"18UB",
    "gn:admin4_code":"18UB003",
    "gn:asciiname":"Raymond's Hill",
    "gn:country_code":"GB",
    "gn:dem":186,
    "gn:feature_class":"P",
    "gn:feature_code":"PPL",
    "gn:name":"Raymond's Hill",
    "gn:population":768,
    "gn:timezone":"Europe/London",
    "iso:country":"GB",
    "name:cym_x_preferred":[
        "Raymond's Hill"
    ],
    "name:pol_x_preferred":[
        "Raymond\u2019s Hill"
    ],
    "name:spa_x_preferred":[
        "Raymond's Hill"
    ],
    "name:swe_x_preferred":[
        "Raymond's Hill"
    ],
    "wof:name":"Raymond's Hill",
    "wof:placetype":"neighbourhood",
    "wof:population":768
},
  "geometry": {"coordinates":[-2.9682,50.7624],"type":"Point"}
}