{
  "type": "Feature",
  "properties": {
    "gn:admin1_code":"ENG",
    "gn:admin2_code":"C9",
    "gn:admin3_code":"16UE",
    "gn:admin4_code":"16UE016",
    "gn:asciiname":"Duddon",
    "gn:cc2":"GB",
    "gn:country_code":"GB",
    "gn:dem":8,
    "gn:feature_class":"P",
    "gn:feature_code":"PPL",
    "gn:name":"Duddon",
    "gn:population":0,
    "gn:timezone":"Europe/London",
    "iso:country":"GB",
    "name:und_x_variant":[
        "Duddon Furnace",
        "Duddon"
    ],
    "wof:name":"Duddon",
    "wof:placetype":"neighbourhood"
},
  "geometry": {"coordinates":[-3.23333,54.26667],"type":"Point"}
}