{
  "type": "Feature",
  "properties": {
    "gn:admin1_code": "WLS",
    "gn:admin2_code": "Y7",
    "gn:admin3_code": "00NS005",
    "gn:asciiname": "Llandeloy",
    "gn:country_code": "GB",
    "gn:dem": 97,
    "gn:feature_class": "P",
    "gn:feature_code": "PPL",
    "gn:name": "Llandeloy",
    "gn:population": 0,
    "gn:timezone": "Europe/London",
    "iso:country": "GB",
    "name:cym_x_preferred": [
      "Llandeloy"
    ],
    "wof:name": "Llandeloy",
    "wof:placetype": "neighbourhood"
  },
  "geometry": {"coordinates":[-5.11362,51.89736],"type":"Point"}
}
