{
  "type": "Feature",
  "properties": {
    "iso:country":"GB",
    "name:ceb_x_preferred":[
        "Woodend"
    ],
    "name:deu_x_preferred":[
        "Woodend"
    ],
    "name:fra_x_preferred":[
        "Woodend"
    ],
    "name:pol_x_preferred":[
        "Woodend"
    ],
    "name:swe_x_preferred":[
        "Woodend"
    ],
    "qs_pg:aaroncc":"GB",
    "qs_pg:name":"Woodend",
    "qs_pg:name_adm0":"United Kingdom",
    "qs_pg:name_adm1":"England",
    "qs_pg:photos":125,
    "qs_pg:photos_1k":25,
    "qs_pg:photos_9k":1,
    "qs_pg:photos_9r":3,
    "qs_pg:photos_all":125,
    "qs_pg:photos_sr":3,
    "qs_pg:pop_sr":0,
    "qs_pg:qs_pg_placetype":"locality",
    "qs_pg:qs_pg_placetype_gp":"Town",
    "qs_pg:woe_adm0":23424975,
    "woe:adm0_id":23424975,
    "woe:name_adm0":"United Kingdom",
    "woe:name_adm1":"England",
    "woe:placetype":"Town",
    "wof:name":"Woodend",
    "wof:placetype":"neighbourhood"
},
  "geometry": {"coordinates":[-3.526954,54.502047],"type":"Point"}
}