{
  "type": "Feature",
  "properties": {
    "gn:country":"GB",
    "gn:fcode":"PPL",
    "gn:population":0,
    "iso:country":"GB",
    "name:cym_x_preferred":[
        "Trimdon Grange"
    ],
    "name:eng_x_preferred":[
        "Trimdon Grange"
    ],
    "name:fra_x_preferred":[
        "Trimdon Grange"
    ],
    "name:nld_x_preferred":[
        "Trimdon Grange"
    ],
    "name:pol_x_preferred":[
        "Trimdon Grange"
    ],
    "name:swe_x_preferred":[
        "Trimdon Grange"
    ],
    "qs_pg:aaroncc":"GB",
    "qs_pg:gn_country":"GB",
    "qs_pg:gn_fcode":"PPL",
    "qs_pg:gn_pop":0,
    "qs_pg:name":"Trimdon Grange",
    "qs_pg:name_adm0":"United Kingdom",
    "qs_pg:name_adm1":"England",
    "qs_pg:photos":20,
    "qs_pg:photos_1k":4,
    "qs_pg:photos_9k":1,
    "qs_pg:photos_9r":1,
    "qs_pg:photos_all":20,
    "qs_pg:photos_sr":1,
    "qs_pg:pop_sr":0,
    "qs_pg:qs_pg_placetype":"locality",
    "qs_pg:qs_pg_placetype_gp":"Town",
    "qs_pg:woe_adm0":23424975,
    "woe:adm0_id":23424975,
    "woe:name_adm0":"United Kingdom",
    "woe:name_adm1":"England",
    "woe:placetype":"Town",
    "wof:name":"Trimdon Grange",
    "wof:placetype":"neighbourhood",
    "wof:population":1304
},
  "geometry": {"coordinates":[-1.42611,54.71414],"type":"Point"}
}