{
  "type": "Feature",
  "properties": {
    "gn:gn_country":"GB",
    "gn:gn_fcode":"PPL",
    "gn:gn_pop":0,
    "iso:country":"GB",
    "name:ara_x_preferred":[
        "\u0623\u0628\u0647\u0648\u0644"
    ],
    "name:chi_x_preferred":[
        "\u963f\u666e\u970d\u723e"
    ],
    "name:dut_x_preferred":[
        "Uphall"
    ],
    "name:eng_x_preferred":[
        "Uphall"
    ],
    "name:fre_x_preferred":[
        "Uphall"
    ],
    "name:ger_x_preferred":[
        "Uphall"
    ],
    "name:gle_x_preferred":[
        "Ubhalaidh"
    ],
    "name:slv_x_preferred":[
        "Uphall"
    ],
    "qs_pg:aaroncc":"GB",
    "qs_pg:gn_country":"GB",
    "qs_pg:gn_fcode":"PPL",
    "qs_pg:gn_pop":0,
    "qs_pg:name":"Uphall",
    "qs_pg:name_adm0":"United Kingdom",
    "qs_pg:name_adm1":"Scotland",
    "qs_pg:photos":62,
    "qs_pg:photos_1k":13,
    "qs_pg:photos_9k":1,
    "qs_pg:photos_9r":2,
    "qs_pg:photos_all":62,
    "qs_pg:photos_sr":2,
    "qs_pg:pop_sr":0,
    "qs_pg:qs_pg_placetype":"locality",
    "qs_pg:qs_pg_placetype_gp":"Town",
    "qs_pg:woe_adm0":23424975,
    "woe:adm0_id":23424975,
    "woe:name_adm0":"United Kingdom",
    "woe:name_adm1":"Scotland",
    "woe:placetype":"Town",
    "wof:name":"Uphall",
    "wof:placetype":"locality"
},
  "geometry": {"coordinates":[-3.51104,55.93025],"type":"Point"}
}