{
  "type": "Feature",
  "properties": {
    "gn:country": "GB",
    "gn:fcode": "PPL",
    "gn:population": 4549,
    "iso:country": "GB",
    "name:bre_x_preferred": [
      "Cross Hands"
    ],
    "name:ceb_x_preferred": [
      "Cross Hands"
    ],
    "name:cym_x_preferred": [
      "Cross Hands"
    ],
    "name:eng_x_preferred": [
      "Cross Hands"
    ],
    "name:eus_x_preferred": [
      "Cross Hands"
    ],
    "name:fas_x_preferred": [
      "کراس هندز"
    ],
    "name:fra_x_preferred": [
      "Cross Hands"
    ],
    "name:nld_x_preferred": [
      "Cross Hands"
    ],
    "name:swe_x_preferred": [
      "Cross Hands"
    ],
    "qs_pg:aaroncc": "GB",
    "qs_pg:gn_country": "GB",
    "qs_pg:gn_fcode": "PPL",
    "qs_pg:gn_pop": 4549,
    "qs_pg:name": "Cross Hands",
    "qs_pg:name_adm0": "United Kingdom",
    "qs_pg:name_adm1": "Wales",
    "qs_pg:photos": 337,
    "qs_pg:photos_1k": 68,
    "qs_pg:photos_9k": 1,
    "qs_pg:photos_9r": 5,
    "qs_pg:photos_all": 337,
    "qs_pg:photos_sr": 5,
    "qs_pg:pop_sr": 4,
    "qs_pg:qs_pg_placetype": "locality",
    "qs_pg:qs_pg_placetype_gp": "Town",
    "qs_pg:woe_adm0": 23424975,
    "woe:adm0_id": 23424975,
    "woe:name_adm0": "United Kingdom",
    "woe:name_adm1": "Wales",
    "woe:placetype": "Town",
    "wof:name": "Cross Hands",
    "wof:placetype": "neighbourhood",
    "wof:population": 4549
  },
  "geometry": {"coordinates":[-4.0875,51.79306],"type":"Point"}
}
