{
  "type": "Feature",
  "properties": {
    "iso:country":"GB",
    "name:cat_x_preferred":[
        "Westfield"
    ],
    "name:ceb_x_preferred":[
        "Westfield"
    ],
    "name:deu_x_preferred":[
        "Westfield"
    ],
    "name:fra_x_preferred":[
        "Westfield"
    ],
    "name:ita_x_preferred":[
        "Westfield"
    ],
    "name:jpn_x_preferred":[
        "\u30a6\u30a7\u30b9\u30c8\u30d5\u30a3\u30fc\u30eb\u30c9"
    ],
    "name:kor_x_preferred":[
        "\uc6e8\uc2a4\ud2b8\ud544\ub4dc"
    ],
    "name:nld_x_preferred":[
        "Westfield"
    ],
    "name:pol_x_preferred":[
        "Westfield"
    ],
    "name:por_x_preferred":[
        "Westfield"
    ],
    "name:ron_x_preferred":[
        "Westfield"
    ],
    "name:rus_x_preferred":[
        "\u0423\u044d\u0441\u0442\u0444\u0438\u043b\u0434"
    ],
    "name:sco_x_preferred":[
        "Westfield"
    ],
    "name:spa_x_preferred":[
        "Westfield"
    ],
    "name:srp_x_preferred":[
        "\u0412\u0435\u0441\u0442\u0444\u0438\u043b\u0434"
    ],
    "name:swe_x_preferred":[
        "Westfield"
    ],
    "name:urd_x_preferred":[
        "\u0648\u06cc\u0633\u0679 \u0641\u06cc\u0644\u0688"
    ],
    "name:vol_x_preferred":[
        "Westfield"
    ],
    "qs_pg:aaroncc":"GB",
    "qs_pg:name":"Westfield",
    "qs_pg:name_adm0":"United Kingdom",
    "qs_pg:name_adm1":"England",
    "qs_pg:photos":98,
    "qs_pg:photos_1k":20,
    "qs_pg:photos_9k":1,
    "qs_pg:photos_9r":3,
    "qs_pg:photos_all":98,
    "qs_pg:photos_sr":3,
    "qs_pg:pop_sr":0,
    "qs_pg:qs_pg_placetype":"locality",
    "qs_pg:qs_pg_placetype_gp":"Town",
    "qs_pg:woe_adm0":23424975,
    "woe:adm0_id":23424975,
    "woe:name_adm0":"United Kingdom",
    "woe:name_adm1":"England",
    "woe:placetype":"Town",
    "wof:name":"Westfield",
    "wof:placetype":"neighbourhood"
},
  "geometry": {"coordinates":[-1.352466,53.322833],"type":"Point"}
}