{
  "type": "Feature",
  "properties": {
    "iso:country": "GB",
    "name:cat_x_preferred": [
      "Westfield"
    ],
    "name:ceb_x_preferred": [
      "Westfield"
    ],
    "name:deu_x_preferred": [
      "Westfield"
    ],
    "name:fra_x_preferred": [
      "Westfield"
    ],
    "name:ita_x_preferred": [
      "Westfield"
    ],
    "name:jpn_x_preferred": [
      "ウェストフィールド"
    ],
    "name:kor_x_preferred": [
      "웨스트필드"
    ],
    "name:nld_x_preferred": [
      "Westfield"
    ],
    "name:pol_x_preferred": [
      "Westfield"
    ],
    "name:por_x_preferred": [
      "Westfield"
    ],
    "name:ron_x_preferred": [
      "Westfield"
    ],
    "name:rus_x_preferred": [
      "Уэстфилд"
    ],
    "name:sco_x_preferred": [
      "Westfield"
    ],
    "name:spa_x_preferred": [
      "Westfield"
    ],
    "name:srp_x_preferred": [
      "Вестфилд"
    ],
    "name:swe_x_preferred": [
      "Westfield"
    ],
    "name:urd_x_preferred": [
      "ویسٹ فیلڈ"
    ],
    "name:vol_x_preferred": [
      "Westfield"
    ],
    "qs_pg:aaroncc": "GB",
    "qs_pg:name": "Westfield",
    "qs_pg:name_adm0": "United Kingdom",
    "qs_pg:name_adm1": "England",
    "qs_pg:photos": 98,
    "qs_pg:photos_1k": 20,
    "qs_pg:photos_9k": 1,
    "qs_pg:photos_9r": 3,
    "qs_pg:photos_all": 98,
    "qs_pg:photos_sr": 3,
    "qs_pg:pop_sr": 0,
    "qs_pg:qs_pg_placetype": "locality",
    "qs_pg:qs_pg_placetype_gp": "Town",
    "qs_pg:woe_adm0": 23424975,
    "woe:adm0_id": 23424975,
    "woe:name_adm0": "United Kingdom",
    "woe:name_adm1": "England",
    "woe:placetype": "Town",
    "wof:name": "Westfield",
    "wof:placetype": "neighbourhood"
  },
  "geometry": {"coordinates":[-1.352466,53.322833],"type":"Point"}
}
