{
  "type": "Feature",
  "properties": {
    "gn:admin1_code":"SCT",
    "gn:admin2_code":"T8",
    "gn:asciiname":"Gometra House",
    "gn:country_code":"GB",
    "gn:dem":43,
    "gn:feature_class":"P",
    "gn:feature_code":"PPL",
    "gn:name":"Gometra House",
    "gn:population":0,
    "gn:timezone":"Europe/London",
    "iso:country":"GB",
    "wof:name":"Gometra House",
    "wof:placetype":"locality"
},
  "geometry": {"coordinates":[-6.2983,56.48503],"type":"Point"}
}