{
  "type": "Feature",
  "properties": {
    "gn:admin1_code":"SCT",
    "gn:admin2_code":"T9",
    "gn:asciiname":"Longnewton",
    "gn:country_code":"GB",
    "gn:dem":137,
    "gn:feature_class":"P",
    "gn:feature_code":"PPL",
    "gn:name":"Longnewton",
    "gn:population":0,
    "gn:timezone":"Europe/London",
    "iso:country":"GB",
    "name:ceb_x_preferred":[
        "Longnewton"
    ],
    "name:fra_x_preferred":[
        "Longnewton"
    ],
    "name:pol_x_preferred":[
        "Longnewton"
    ],
    "name:swe_x_preferred":[
        "Longnewton"
    ],
    "wof:name":"Longnewton",
    "wof:placetype":"locality"
},
  "geometry": {"coordinates":[-2.66667,55.53333000000001],"type":"Point"}
}