{
  "type": "Feature",
  "properties": {
    "iso:country":"GB",
    "name:bre_x_preferred":[
        "Hampton"
    ],
    "name:cat_x_preferred":[
        "Hampton"
    ],
    "name:ceb_x_preferred":[
        "Hampton"
    ],
    "name:ces_x_preferred":[
        "Hampton"
    ],
    "name:deu_x_preferred":[
        "Hampton"
    ],
    "name:fin_x_preferred":[
        "Hampton"
    ],
    "name:fra_x_preferred":[
        "Hampton"
    ],
    "name:hin_x_preferred":[
        "\u0939\u0948\u092e\u094d\u092a\u091f\u0928"
    ],
    "name:hun_x_preferred":[
        "Hampton"
    ],
    "name:ita_x_preferred":[
        "Hampton"
    ],
    "name:jpn_x_preferred":[
        "\u30cf\u30f3\u30d7\u30c8\u30f3"
    ],
    "name:kor_x_preferred":[
        "\ud584\ud504\ud134"
    ],
    "name:mlg_x_preferred":[
        "Hampton"
    ],
    "name:nld_x_preferred":[
        "Hampton"
    ],
    "name:pol_x_preferred":[
        "Hampton"
    ],
    "name:por_x_preferred":[
        "Hampton"
    ],
    "name:rus_x_preferred":[
        "\u0425\u0430\u043c\u043f\u0442\u043e\u043d"
    ],
    "name:spa_x_preferred":[
        "Hampton"
    ],
    "name:srp_x_preferred":[
        "\u0425\u0435\u043c\u043f\u0442\u043e\u043d"
    ],
    "name:swe_x_preferred":[
        "Hampton"
    ],
    "name:ukr_x_preferred":[
        "\u0413\u0435\u043c\u043f\u0442\u043e\u043d"
    ],
    "name:vol_x_preferred":[
        "Hampton"
    ],
    "name:zho_x_preferred":[
        "\u6c49\u666e\u987f"
    ],
    "qs_pg:aaroncc":"GB",
    "qs_pg:name":"Hampton",
    "qs_pg:name_adm0":"United Kingdom",
    "qs_pg:name_adm1":"England",
    "qs_pg:photos":319,
    "qs_pg:photos_1k":65,
    "qs_pg:photos_9k":1,
    "qs_pg:photos_9r":5,
    "qs_pg:photos_all":319,
    "qs_pg:photos_sr":5,
    "qs_pg:pop_sr":0,
    "qs_pg:qs_pg_placetype":"locality",
    "qs_pg:qs_pg_placetype_gp":"Town",
    "qs_pg:woe_adm0":23424975,
    "woe:adm0_id":23424975,
    "woe:name_adm0":"United Kingdom",
    "woe:name_adm1":"England",
    "woe:placetype":"Town",
    "wof:name":"Hampton",
    "wof:placetype":"neighbourhood"
},
  "geometry": {"coordinates":[-2.376995,52.474572],"type":"Point"}
}