{
  "type": "Feature",
  "properties": {
    "iso:country":"GB",
    "name:deu_x_preferred":[
        "Auchindrain"
    ],
    "name:eng_x_preferred":[
        "Auchindrain"
    ],
    "name:eus_x_preferred":[
        "Auchindrain"
    ],
    "name:fra_x_preferred":[
        "Auchindrain"
    ],
    "name:gle_x_preferred":[
        "Achadh an Droighinn"
    ],
    "name:nld_x_preferred":[
        "Auchindrain"
    ],
    "qs_pg:aaroncc":"GB",
    "qs_pg:name":"Auchindrain",
    "qs_pg:name_adm0":"United Kingdom",
    "qs_pg:name_adm1":"Scotland",
    "qs_pg:photos":144,
    "qs_pg:photos_1k":29,
    "qs_pg:photos_9k":1,
    "qs_pg:photos_9r":3,
    "qs_pg:photos_all":144,
    "qs_pg:photos_sr":3,
    "qs_pg:pop_sr":0,
    "qs_pg:qs_pg_placetype":"locality",
    "qs_pg:qs_pg_placetype_gp":"Town",
    "qs_pg:woe_adm0":23424975,
    "woe:adm0_id":23424975,
    "woe:name_adm0":"United Kingdom",
    "woe:name_adm1":"Scotland",
    "woe:placetype":"Town",
    "wof:name":"Auchindrain",
    "wof:placetype":"locality"
},
  "geometry": {"coordinates":[-5.178165,56.175135],"type":"Point"}
}