{
  "type": "Feature",
  "properties": {
    "gn:admin1_code": "ENG",
    "gn:admin2_code": "I9",
    "gn:admin3_code": "33UB",
    "gn:admin4_code": "33UB022",
    "gn:asciiname": "Southburgh",
    "gn:country_code": "GB",
    "gn:dem": 51,
    "gn:feature_class": "P",
    "gn:feature_code": "PPL",
    "gn:name": "Southburgh",
    "gn:population": 0,
    "gn:timezone": "Europe/London",
    "iso:country": "GB",
    "wof:name": "Southburgh",
    "wof:placetype": "neighbourhood"
  },
  "geometry": {"coordinates":[0.94516,52.60406],"type":"Point"}
}
