{
  "type": "Feature",
  "properties": {
    "iso:country": "GB",
    "name:fra_x_preferred": [
      "Westerton"
    ],
    "name:pol_x_preferred": [
      "Westerton"
    ],
    "wof:name": "Westerton",
    "wof:placetype": "neighbourhood"
  },
  "geometry": {"coordinates":[-1.56850551176376,53.72316216333159],"type":"Point"}
}
