{
  "type": "Feature",
  "properties": {
    "gn:admin1_code":"NIR",
    "gn:admin2_code":"N09000006",
    "gn:asciiname":"Portinode",
    "gn:country_code":"GB",
    "gn:dem":55,
    "gn:feature_class":"P",
    "gn:feature_code":"PPL",
    "gn:name":"Portinode",
    "gn:population":0,
    "gn:timezone":"Europe/London",
    "iso:country":"GB",
    "wof:name":"Portinode",
    "wof:placetype":"locality"
},
  "geometry": {"coordinates":[-7.77433,54.52869000000001],"type":"Point"}
}