{
  "type": "Feature",
  "properties": {
    "gn:admin1_code":"NIR",
    "gn:admin2_code":"N09000007",
    "gn:asciiname":"Aghalee",
    "gn:cc2":"GB",
    "gn:country_code":"GB",
    "gn:dem":30,
    "gn:feature_class":"P",
    "gn:feature_code":"PPL",
    "gn:name":"Aghalee",
    "gn:population":0,
    "gn:timezone":"Europe/London",
    "iso:country":"GB",
    "name:ceb_x_preferred":[
        "Aghalee"
    ],
    "name:eus_x_preferred":[
        "Aghalee"
    ],
    "name:fas_x_preferred":[
        "\u0622\u06af\u0627\u0644\u06cc"
    ],
    "name:gla_x_preferred":[
        "Achadh L\u00ed"
    ],
    "name:gle_x_preferred":[
        "Achadh L\u00ed"
    ],
    "name:ita_x_preferred":[
        "Aghalee"
    ],
    "name:msa_x_preferred":[
        "Aghalee"
    ],
    "name:nld_x_preferred":[
        "Aghalee"
    ],
    "name:pli_x_preferred":[
        "\u0905\u0918\u0932\u0940"
    ],
    "name:spa_x_preferred":[
        "Aghalee"
    ],
    "name:swe_x_preferred":[
        "Aghalee"
    ],
    "name:und_x_variant":[
        "Aughalee"
    ],
    "wof:name":"Aghalee",
    "wof:placetype":"locality"
},
  "geometry": {"coordinates":[-6.26607,54.52208],"type":"Point"}
}