{
  "type": "Feature",
  "properties": {
    "iso:country":"GB",
    "name:eng_x_preferred":[
        "Portsea"
    ],
    "name:pol_x_preferred":[
        "Portsea"
    ],
    "name:unk_x_variant":[
        "Portsea"
    ],
    "qs:gn_fcode":"PPLX",
    "qs:gn_local":0,
    "qs:gn_namadm1":"ENG",
    "qs:gn_name":"Portsea",
    "qs:local_max":5349,
    "qs:local_sum":51768,
    "qs:localhoods":25,
    "qs:name":"Portsea",
    "qs:name_adm0":"United Kingdom",
    "qs:name_adm1":"England",
    "qs:name_adm2":"Hampshire",
    "qs:name_lau":"Portsmouth City",
    "qs:name_local":"Portsmouth",
    "qs:photo_max":559,
    "qs:photo_sum":4650,
    "qs:placetype":"Suburb",
    "qs:quad_count":54,
    "qs:woe_adm0":23424975,
    "qs:woe_adm1":24554868,
    "qs:woe_adm2":12602169,
    "qs:woe_lau":12696158,
    "qs:woe_local":32452,
    "qs:woe_ver":"7.10.0",
    "wd:wordcount":31,
    "wof:lang":[
        "eng"
    ],
    "wof:name":"Portsea",
    "wof:placetype":"neighbourhood"
},
  "geometry": {"coordinates":[-1.109595,50.797033],"type":"Point"}
}