{
  "type": "Feature",
  "properties": {
    "iso:country":"GB",
    "name:deu_x_preferred":[
        "Cippenham"
    ],
    "name:eng_x_preferred":[
        "Cippenham"
    ],
    "name:fra_x_preferred":[
        "Cippenham"
    ],
    "name:nld_x_preferred":[
        "Cippenham"
    ],
    "name:unk_x_variant":[
        "Cippenham"
    ],
    "qs:gn_adm0_cc":"GB",
    "qs:gn_local":2637626,
    "qs:gn_nam_loc":"slough",
    "qs:gn_namadm1":"ENG",
    "qs:local_max":4645,
    "qs:local_sum":12202,
    "qs:localhoods":4,
    "qs:name":"Cippenham",
    "qs:name_adm0":"United Kingdom",
    "qs:name_adm1":"England",
    "qs:name_adm2":"Berkshire",
    "qs:name_lau":"Slough Borough",
    "qs:name_local":"Slough",
    "qs:photo_max":533,
    "qs:photo_sum":4458,
    "qs:placetype":"Suburb",
    "qs:quad_count":178,
    "qs:woe_adm0":23424975,
    "qs:woe_adm1":24554868,
    "qs:woe_adm2":26821262,
    "qs:woe_lau":12696167,
    "qs:woe_local":35009,
    "qs:woe_ver":"7.10.0",
    "wd:wordcount":569,
    "wof:lang":[
        "eng"
    ],
    "wof:name":"Cippenham",
    "wof:placetype":"neighbourhood"
},
  "geometry": {"coordinates":[-0.660366,51.505699],"type":"Point"}
}