{
  "type": "Feature",
  "properties": {
    "iso:country":"GB",
    "name:ces_x_preferred":[
        "Chartwell"
    ],
    "name:deu_x_preferred":[
        "Chartwell"
    ],
    "name:epo_x_preferred":[
        "Chartwell"
    ],
    "name:fra_x_preferred":[
        "Chartwell"
    ],
    "name:heb_x_preferred":[
        "\u05e6'\u05e8\u05d8\u05d5\u05d5\u05dc"
    ],
    "name:hye_x_preferred":[
        "\u0549\u0561\u0580\u0569\u057e\u0565\u056c"
    ],
    "name:jpn_x_preferred":[
        "\u30c1\u30e3\u30fc\u30c8\u30a6\u30a7\u30eb"
    ],
    "name:nld_x_preferred":[
        "Chartwell"
    ],
    "name:por_x_preferred":[
        "Chartwell"
    ],
    "name:srp_x_preferred":[
        "\u0427\u0430\u0440\u0442\u0432\u0435\u043b"
    ],
    "name:zho_x_preferred":[
        "\u67e5\u7279\u97e6\u5c14\u5e84\u56ed"
    ],
    "qs_pg:aaroncc":"GB",
    "qs_pg:name":"Chartwell",
    "qs_pg:name_adm0":"United Kingdom",
    "qs_pg:name_adm1":"England",
    "qs_pg:photos":1750,
    "qs_pg:photos_1k":355,
    "qs_pg:photos_9k":8,
    "qs_pg:photos_9r":8,
    "qs_pg:photos_all":1750,
    "qs_pg:photos_sr":14,
    "qs_pg:pop_sr":0,
    "qs_pg:qs_pg_placetype":"locality",
    "qs_pg:qs_pg_placetype_gp":"Town",
    "qs_pg:woe_adm0":23424975,
    "woe:adm0_id":23424975,
    "woe:name_adm0":"United Kingdom",
    "woe:name_adm1":"England",
    "woe:placetype":"Town",
    "wof:name":"Chartwell",
    "wof:placetype":"neighbourhood"
},
  "geometry": {"coordinates":[0.083384,51.2442625],"type":"Point"}
}