{
  "type": "Feature",
  "properties": {
    "iso:country":"GB",
    "wof:name":"Holme VIllage",
    "wof:placetype":"neighbourhood"
},
  "geometry": {"coordinates":[-1.70368891413212,53.77848133965194],"type":"Point"}
}