{
  "type": "Feature",
  "properties": {
    "iso:country": "GB",
    "name:cym_x_preferred": [
      "Haworth"
    ],
    "name:deu_x_preferred": [
      "Haworth"
    ],
    "name:epo_x_preferred": [
      "Haworth"
    ],
    "name:eus_x_preferred": [
      "Haworth"
    ],
    "name:fas_x_preferred": [
      "هاورث"
    ],
    "name:fin_x_preferred": [
      "Haworth"
    ],
    "name:fra_x_preferred": [
      "Haworth"
    ],
    "name:fry_x_preferred": [
      "Haworth"
    ],
    "name:ita_x_preferred": [
      "Haworth"
    ],
    "name:jpn_x_preferred": [
      "ハワース"
    ],
    "name:lim_x_preferred": [
      "Haworth"
    ],
    "name:nld_x_preferred": [
      "Haworth"
    ],
    "name:pol_x_preferred": [
      "Haworth"
    ],
    "name:rus_x_preferred": [
      "Хоэрт"
    ],
    "name:spa_x_preferred": [
      "Haworth"
    ],
    "wof:name": "Haworth",
    "wof:placetype": "neighbourhood"
  },
  "geometry": {"coordinates":[-1.94590323888356,53.8313470122242],"type":"Point"}
}
