{
  "type": "Feature",
  "properties": {
    "iso:country":"GB",
    "name:cym_x_preferred":[
        "Haworth"
    ],
    "name:deu_x_preferred":[
        "Haworth"
    ],
    "name:epo_x_preferred":[
        "Haworth"
    ],
    "name:eus_x_preferred":[
        "Haworth"
    ],
    "name:fas_x_preferred":[
        "\u0647\u0627\u0648\u0631\u062b"
    ],
    "name:fin_x_preferred":[
        "Haworth"
    ],
    "name:fra_x_preferred":[
        "Haworth"
    ],
    "name:fry_x_preferred":[
        "Haworth"
    ],
    "name:ita_x_preferred":[
        "Haworth"
    ],
    "name:jpn_x_preferred":[
        "\u30cf\u30ef\u30fc\u30b9"
    ],
    "name:lim_x_preferred":[
        "Haworth"
    ],
    "name:nld_x_preferred":[
        "Haworth"
    ],
    "name:pol_x_preferred":[
        "Haworth"
    ],
    "name:rus_x_preferred":[
        "\u0425\u043e\u044d\u0440\u0442"
    ],
    "name:spa_x_preferred":[
        "Haworth"
    ],
    "wof:name":"Haworth",
    "wof:placetype":"neighbourhood"
},
  "geometry": {"coordinates":[-1.94590323888356,53.8313470122242],"type":"Point"}
}