{
  "type": "Feature",
  "properties": {
    "iso:country":"GB",
    "wof:name":"Haworth",
    "wof:placetype":"neighbourhood"
},
  "geometry": {"coordinates":[-1.94590323888356,53.8313470122242],"type":"Point"}
}