{
  "type": "Feature",
  "properties": {
    "gn:country": "GB",
    "gn:fcode": "PPL",
    "gn:population": 0,
    "iso:country": "GB",
    "name:azb_x_preferred": [
      "وینچلسی"
    ],
    "name:ceb_x_preferred": [
      "Winchelsea"
    ],
    "name:cym_x_preferred": [
      "Winchelsea"
    ],
    "name:deu_x_preferred": [
      "Winchelsea"
    ],
    "name:eng_x_preferred": [
      "Winchelsea"
    ],
    "name:eus_x_preferred": [
      "Winchelsea"
    ],
    "name:fas_x_preferred": [
      "وینچلسی"
    ],
    "name:fra_x_preferred": [
      "Winchelsea"
    ],
    "name:isl_x_preferred": [
      "Winchelsea"
    ],
    "name:ita_x_preferred": [
      "Winchelsea"
    ],
    "name:jpn_x_preferred": [
      "ウィンチェルシー"
    ],
    "name:nld_x_preferred": [
      "Winchelsea"
    ],
    "name:nno_x_preferred": [
      "Winchelsea"
    ],
    "name:pol_x_preferred": [
      "Winchelsea"
    ],
    "name:ron_x_preferred": [
      "Winchelsea"
    ],
    "name:spa_x_preferred": [
      "Winchelsea"
    ],
    "name:swe_x_preferred": [
      "Winchelsea"
    ],
    "name:tur_x_preferred": [
      "Winchelsea"
    ],
    "name:zho_x_preferred": [
      "溫奇爾西"
    ],
    "qs_pg:aaroncc": "GB",
    "qs_pg:gn_country": "GB",
    "qs_pg:gn_fcode": "PPL",
    "qs_pg:gn_pop": 0,
    "qs_pg:name": "Winchelsea",
    "qs_pg:name_adm0": "United Kingdom",
    "qs_pg:name_adm1": "England",
    "qs_pg:photos": 1980,
    "qs_pg:photos_1k": 401,
    "qs_pg:photos_9k": 9,
    "qs_pg:photos_9r": 9,
    "qs_pg:photos_all": 1980,
    "qs_pg:photos_sr": 15,
    "qs_pg:pop_sr": 0,
    "qs_pg:qs_pg_placetype": "locality",
    "qs_pg:qs_pg_placetype_gp": "Town",
    "qs_pg:woe_adm0": 23424975,
    "woe:adm0_id": 23424975,
    "woe:name_adm0": "United Kingdom",
    "woe:name_adm1": "England",
    "woe:placetype": "Town",
    "wof:name": "Winchelsea",
    "wof:placetype": "neighbourhood"
  },
  "geometry": {"coordinates":[0.7081,50.92376],"type":"Point"}
}
