{
  "type": "Feature",
  "properties": {
    "iso:country": "GB",
    "name:ara_x_preferred": [
      "قلعة ستوكيساي"
    ],
    "name:ceb_x_preferred": [
      "Stokesay Castle"
    ],
    "name:cym_x_preferred": [
      "Castell Stokesay"
    ],
    "name:deu_x_preferred": [
      "Stokesay Castle"
    ],
    "name:swe_x_preferred": [
      "Stokesay Castle"
    ],
    "qs_pg:aaroncc": "GB",
    "qs_pg:name": "Stokesay Castle",
    "qs_pg:name_adm0": "United Kingdom",
    "qs_pg:name_adm1": "England",
    "qs_pg:photos": 711,
    "qs_pg:photos_1k": 144,
    "qs_pg:photos_9k": 3,
    "qs_pg:photos_9r": 5,
    "qs_pg:photos_all": 711,
    "qs_pg:photos_sr": 8,
    "qs_pg:pop_sr": 0,
    "qs_pg:qs_pg_placetype": "locality",
    "qs_pg:qs_pg_placetype_gp": "Town",
    "qs_pg:woe_adm0": 23424975,
    "woe:adm0_id": 23424975,
    "woe:name_adm0": "United Kingdom",
    "woe:name_adm1": "England",
    "woe:placetype": "Town",
    "wof:name": "Stokesay Castle",
    "wof:placetype": "neighbourhood"
  },
  "geometry": {"coordinates":[-2.831135,52.430072],"type":"Point"}
}
