{
  "type": "Feature",
  "properties": {
    "gn:country":"GB",
    "gn:fcode":"PPL",
    "gn:population":230,
    "iso:country":"GB",
    "name:ceb_x_preferred":[
        "Bretton"
    ],
    "name:cym_x_preferred":[
        "Bretton"
    ],
    "name:deu_x_preferred":[
        "Bretton"
    ],
    "name:swe_x_preferred":[
        "Bretton"
    ],
    "qs_pg:aaroncc":"GB",
    "qs_pg:gn_country":"GB",
    "qs_pg:gn_fcode":"PPL",
    "qs_pg:gn_pop":230,
    "qs_pg:name":"Bretton",
    "qs_pg:name_adm0":"United Kingdom",
    "qs_pg:name_adm1":"Wales",
    "qs_pg:photos":55,
    "qs_pg:photos_1k":11,
    "qs_pg:photos_9k":1,
    "qs_pg:photos_9r":2,
    "qs_pg:photos_all":55,
    "qs_pg:photos_sr":2,
    "qs_pg:pop_sr":2,
    "qs_pg:qs_pg_placetype":"locality",
    "qs_pg:qs_pg_placetype_gp":"Town",
    "qs_pg:woe_adm0":23424975,
    "woe:adm0_id":23424975,
    "woe:name_adm0":"United Kingdom",
    "woe:name_adm1":"Wales",
    "woe:placetype":"Town",
    "wof:name":"Bretton",
    "wof:placetype":"neighbourhood",
    "wof:population":230
},
  "geometry": {"coordinates":[-2.5393,52.72278],"type":"Point"}
}