{
  "type": "Feature",
  "properties": {
    "iso:country":"GB",
    "name:eng_x_preferred":[
        "Chaddesden"
    ],
    "name:gle_x_preferred":[
        "Chaddesden"
    ],
    "name:jpn_x_preferred":[
        "\u30c1\u30e3\u30c3\u30c7\u30b9\u30c7\u30f3"
    ],
    "name:nld_x_preferred":[
        "Chaddesden"
    ],
    "name:pol_x_preferred":[
        "Chaddesden"
    ],
    "name:unk_x_variant":[
        "Chaddesden"
    ],
    "qs:gn_adm0_cc":"GB",
    "qs:gn_fcode":"PPL",
    "qs:gn_local":2650000,
    "qs:gn_nam_loc":"rauceby",
    "qs:gn_namadm1":"ENG",
    "qs:gn_name":"Chaddesden",
    "qs:local_max":4610,
    "qs:local_sum":19661,
    "qs:localhoods":15,
    "qs:name":"Chaddesden",
    "qs:name_adm0":"United Kingdom",
    "qs:name_adm1":"England",
    "qs:name_adm2":"Derbyshire",
    "qs:name_lau":"Derby City",
    "qs:name_local":"Derby",
    "qs:photo_max":148,
    "qs:photo_sum":1741,
    "qs:placetype":"Suburb",
    "qs:quad_count":88,
    "qs:woe_adm0":23424975,
    "qs:woe_adm1":24554868,
    "qs:woe_adm2":12602143,
    "qs:woe_lau":12696153,
    "qs:woe_local":18114,
    "qs:woe_ver":"7.10.0",
    "wd:wordcount":911,
    "wof:lang":[
        "eng"
    ],
    "wof:name":"Chaddesden",
    "wof:placetype":"neighbourhood"
},
  "geometry": {"coordinates":[-1.442878,52.923259],"type":"Point"}
}