{
  "type": "Feature",
  "properties": {
    "gn:country":"GB",
    "gn:fcode":"PPL",
    "gn:population":0,
    "iso:country":"GB",
    "name:eng_x_preferred":[
        "Dundrod"
    ],
    "name:eus_x_preferred":[
        "Dundrod"
    ],
    "name:fra_x_preferred":[
        "Dundrod"
    ],
    "name:gla_x_preferred":[
        "D\u00fan dTrod"
    ],
    "name:gle_x_preferred":[
        "D\u00fan dTrod"
    ],
    "name:jpn_x_preferred":[
        "\u30c0\u30f3\u30c9\u30ed\u30c3\u30c9"
    ],
    "name:msa_x_preferred":[
        "Dundrod"
    ],
    "name:nld_x_preferred":[
        "Dundrod"
    ],
    "name:pli_x_preferred":[
        "\u0926\u0941\u0928\u094d\u0926\u094d\u0930\u094b\u0921\u093c"
    ],
    "name:spa_x_preferred":[
        "Dundrod"
    ],
    "qs_pg:aaroncc":"GB",
    "qs_pg:gn_country":"GB",
    "qs_pg:gn_fcode":"PPL",
    "qs_pg:gn_pop":0,
    "qs_pg:name":"Dundrod",
    "qs_pg:name_adm0":"United Kingdom",
    "qs_pg:name_adm1":"Northern Ireland",
    "qs_pg:photos":106,
    "qs_pg:photos_1k":21,
    "qs_pg:photos_9k":1,
    "qs_pg:photos_9r":3,
    "qs_pg:photos_all":106,
    "qs_pg:photos_sr":3,
    "qs_pg:pop_sr":0,
    "qs_pg:qs_pg_placetype":"locality",
    "qs_pg:qs_pg_placetype_gp":"Town",
    "qs_pg:woe_adm0":23424975,
    "woe:adm0_id":23424975,
    "woe:name_adm0":"United Kingdom",
    "woe:name_adm1":"Northern Ireland",
    "woe:placetype":"Town",
    "wof:name":"Dundrod",
    "wof:placetype":"locality"
},
  "geometry": {"coordinates":[-6.11667,54.61667],"type":"Point"}
}