{
  "type": "Feature",
  "properties": {
    "iso:country":"GB",
    "name:ceb_x_preferred":[
        "Fairlie"
    ],
    "name:cym_x_preferred":[
        "Fairlie"
    ],
    "name:deu_x_preferred":[
        "Fairlie"
    ],
    "name:eng_x_preferred":[
        "Fairlie"
    ],
    "name:fra_x_preferred":[
        "Fairlie"
    ],
    "name:gla_x_preferred":[
        "F\u00e0irlidh"
    ],
    "name:gle_x_preferred":[
        "F\u00e1irlidh"
    ],
    "name:nld_x_preferred":[
        "Fairlie"
    ],
    "name:sco_x_preferred":[
        "Fairlie"
    ],
    "name:swe_x_preferred":[
        "Fairlie"
    ],
    "qs:a0":"United Kingdom",
    "qs:a1":"*North Ayrshire",
    "qs:a1_lc":"GB11QY0000",
    "qs:a1r":"0Scotland",
    "qs:a1r_lc":"GB11000000",
    "qs:adm0":"United Kingdom",
    "qs:la_lc":"*",
    "qs:level":"locality",
    "qs:loc":"Fairlie",
    "qs:loc_alt":"Fairlie",
    "qs:pop":0,
    "qs:type":"buffered point",
    "wd:wordcount":980,
    "wof:name":"Fairlie",
    "wof:placetype":"locality"
},
  "geometry": {"coordinates":[-4.853192,55.755426],"type":"Point"}
}