{
  "type": "Feature",
  "properties": {
    "iso:country":"GB",
    "name:eng_x_preferred":[
        "Arewater Green"
    ],
    "qs:gn_adm0_cc":"GB",
    "qs:gn_local":2643558,
    "qs:gn_nam_loc":"Loughton, Epping Forest District, Essex, England, GB",
    "qs:gn_namadm1":"ENG",
    "qs:local_max":3228,
    "qs:local_sum":5352,
    "qs:localhoods":2,
    "qs:name":"Arewater Green",
    "qs:name_adm0":"United Kingdom",
    "qs:name_adm1":"England",
    "qs:name_adm2":"Essex",
    "qs:name_lau":"Epping Forest District",
    "qs:name_local":"Loughton",
    "qs:photo_max":108,
    "qs:photo_sum":3228,
    "qs:placetype":"Suburb",
    "qs:quad_count":272,
    "qs:woe_adm0":23424975,
    "qs:woe_adm1":24554868,
    "qs:woe_adm2":12602168,
    "qs:woe_lau":12695946,
    "qs:woe_local":27508,
    "qs:woe_ver":"7.10.0",
    "wof:lang":[
        "eng"
    ],
    "wof:name":"Arewater Green",
    "wof:placetype":"neighbourhood"
},
  "geometry": {"coordinates":[0.056487,51.6611],"type":"Point"}
}