{
  "type": "Feature",
  "properties": {
    "iso:country":"GB",
    "name:ceb_x_preferred":[
        "Aydon Castle"
    ],
    "name:deu_x_preferred":[
        "Aydon Castle"
    ],
    "name:fra_x_preferred":[
        "Ch\u00e2teau d'Aydon"
    ],
    "name:pnb_x_preferred":[
        "\u0627\u06cc\u0648\u0688\u0646 \u0642\u0644\u0639\u06c1"
    ],
    "name:rus_x_preferred":[
        "\u0417\u0430\u043c\u043e\u043a \u042d\u0439\u0434\u043e\u043d"
    ],
    "name:swe_x_preferred":[
        "Aydon Castle"
    ],
    "qs_pg:aaroncc":"GB",
    "qs_pg:name":"Aydon Castle",
    "qs_pg:name_adm0":"United Kingdom",
    "qs_pg:name_adm1":"England",
    "qs_pg:photos":105,
    "qs_pg:photos_1k":21,
    "qs_pg:photos_9k":1,
    "qs_pg:photos_9r":3,
    "qs_pg:photos_all":105,
    "qs_pg:photos_sr":3,
    "qs_pg:pop_sr":0,
    "qs_pg:qs_pg_placetype":"locality",
    "qs_pg:qs_pg_placetype_gp":"Town",
    "qs_pg:woe_adm0":23424975,
    "woe:adm0_id":23424975,
    "woe:name_adm0":"United Kingdom",
    "woe:name_adm1":"England",
    "woe:placetype":"Town",
    "wof:name":"Aydon Castle",
    "wof:placetype":"neighbourhood"
},
  "geometry": {"coordinates":[-1.99994,54.992269],"type":"Point"}
}