{
  "type": "Feature",
  "properties": {
    "gn:country":"GB",
    "gn:fcode":"PPL",
    "gn:population":0,
    "iso:country":"GB",
    "name:azb_x_preferred":[
        "\u0627\u0634 \u0648\u06cc\u0644"
    ],
    "name:cym_x_preferred":[
        "Ash Vale"
    ],
    "name:deu_x_preferred":[
        "Ash Vale"
    ],
    "name:eng_x_preferred":[
        "Ash Vale"
    ],
    "name:fas_x_preferred":[
        "\u0627\u0634 \u0648\u06cc\u0644"
    ],
    "name:fra_x_preferred":[
        "Ash Vale"
    ],
    "name:gle_x_preferred":[
        "Ash Vale"
    ],
    "name:nld_x_preferred":[
        "Ash Vale"
    ],
    "name:pol_x_preferred":[
        "Ash Vale"
    ],
    "name:spa_x_preferred":[
        "Ash Vale"
    ],
    "name:swe_x_preferred":[
        "Ashtead"
    ],
    "qs_pg:aaroncc":"GB",
    "qs_pg:gn_country":"GB",
    "qs_pg:gn_fcode":"PPL",
    "qs_pg:gn_pop":0,
    "qs_pg:name":"Ash Vale",
    "qs_pg:name_adm0":"United Kingdom",
    "qs_pg:name_adm1":"England",
    "qs_pg:photos":358,
    "qs_pg:photos_1k":73,
    "qs_pg:photos_9k":2,
    "qs_pg:photos_9r":5,
    "qs_pg:photos_all":358,
    "qs_pg:photos_sr":6,
    "qs_pg:pop_sr":0,
    "qs_pg:qs_pg_placetype":"locality",
    "qs_pg:qs_pg_placetype_gp":"Town",
    "qs_pg:woe_adm0":23424975,
    "woe:adm0_id":23424975,
    "woe:name_adm0":"United Kingdom",
    "woe:name_adm1":"England",
    "woe:placetype":"Town",
    "wof:name":"Ash Vale",
    "wof:placetype":"neighbourhood"
},
  "geometry": {"coordinates":[-0.72115,51.26997],"type":"Point"}
}