{
  "type": "Feature",
  "properties": {
    "iso:country":"GB",
    "wof:name":"Ilkley",
    "wof:placetype":"neighbourhood"
},
  "geometry": {"coordinates":[-1.82566868894641,53.92529788095479],"type":"Point"}
}