{
  "type": "Feature",
  "properties": {
    "iso:country": "GB",
    "name:azb_x_preferred": [
      "ایلکی"
    ],
    "name:ceb_x_preferred": [
      "Ilkley"
    ],
    "name:cym_x_preferred": [
      "Ilkley"
    ],
    "name:deu_x_preferred": [
      "Ilkley"
    ],
    "name:epo_x_preferred": [
      "Ilkley"
    ],
    "name:fas_x_preferred": [
      "ایلکی"
    ],
    "name:fra_x_preferred": [
      "Ilkley"
    ],
    "name:gle_x_preferred": [
      "Ilkley"
    ],
    "name:ita_x_preferred": [
      "Ilkley"
    ],
    "name:nld_x_preferred": [
      "Ilkley"
    ],
    "name:nno_x_preferred": [
      "Ilkley"
    ],
    "name:pol_x_preferred": [
      "Ilkley"
    ],
    "name:ron_x_preferred": [
      "Ilkley"
    ],
    "name:rus_x_preferred": [
      "Илкли"
    ],
    "name:spa_x_preferred": [
      "Ilkley"
    ],
    "name:swe_x_preferred": [
      "Ilkley"
    ],
    "name:vol_x_preferred": [
      "Ilkley"
    ],
    "name:zho_x_preferred": [
      "伊爾克利"
    ],
    "wof:name": "Ilkley",
    "wof:placetype": "neighbourhood"
  },
  "geometry": {"coordinates":[-1.82566868894641,53.92529788095479],"type":"Point"}
}
