{
  "type": "Feature",
  "properties": {
    "iso:country":"GB",
    "wof:name":"Upper Marsh",
    "wof:placetype":"neighbourhood"
},
  "geometry": {"coordinates":[-1.96856255204245,53.82195804558867],"type":"Point"}
}