{
  "type": "Feature",
  "properties": {
    "gn:country": "GB",
    "gn:fcode": "PPL",
    "gn:population": 0,
    "iso:country": "GB",
    "name:ara_x_preferred": [
      "غوكت"
    ],
    "name:ceb_x_preferred": [
      "Gawcott"
    ],
    "name:cym_x_preferred": [
      "Gawcott"
    ],
    "name:eng_x_preferred": [
      "Gawcott"
    ],
    "name:fas_x_preferred": [
      "گاکات"
    ],
    "name:fra_x_preferred": [
      "Gawcott"
    ],
    "name:ita_x_preferred": [
      "Gawcott"
    ],
    "name:jpn_x_preferred": [
      "ゴウコット"
    ],
    "name:nld_x_preferred": [
      "Gawcott"
    ],
    "name:pol_x_preferred": [
      "Gawcott"
    ],
    "name:por_x_preferred": [
      "Gawcott"
    ],
    "name:spa_x_preferred": [
      "Gawcott"
    ],
    "name:swe_x_preferred": [
      "Gawcott"
    ],
    "qs_pg:aaroncc": "GB",
    "qs_pg:gn_country": "GB",
    "qs_pg:gn_fcode": "PPL",
    "qs_pg:gn_pop": 0,
    "qs_pg:name": "Gawcott",
    "qs_pg:name_adm0": "United Kingdom",
    "qs_pg:name_adm1": "England",
    "qs_pg:photos_9r": 0,
    "qs_pg:photos_sr": 0,
    "qs_pg:pop_sr": 0,
    "qs_pg:qs_pg_placetype": "locality",
    "qs_pg:qs_pg_placetype_gp": "Town",
    "qs_pg:woe_adm0": 23424975,
    "woe:adm0_id": 23424975,
    "woe:name_adm0": "United Kingdom",
    "woe:name_adm1": "England",
    "woe:placetype": "Town",
    "wof:name": "Gawcott",
    "wof:placetype": "neighbourhood",
    "wof:population": 778
  },
  "geometry": {"coordinates":[-1.0101,51.98136],"type":"Point"}
}
