{
  "type": "Feature",
  "properties": {
    "gn:gn_country":"GB",
    "gn:gn_fcode":"PPL",
    "gn:gn_pop":0,
    "iso:country":"GB",
    "name:ben_x_preferred":[
        "\u0993\u09b2\u09cd\u09af\u09be\u09b0\u099f\u09cb\u09a8"
    ],
    "name:deu_x_preferred":[
        "Ollerton"
    ],
    "name:eng_x_preferred":[
        "Ollerton"
    ],
    "name:fra_x_preferred":[
        "Ollerton"
    ],
    "name:guj_x_preferred":[
        "\u0a93\u0ab2\u0ab0\u0acd\u0a9f\u0aa8"
    ],
    "name:jpn_x_preferred":[
        "\u30aa\u30e9\u30fc\u30c8\u30f3"
    ],
    "name:kan_x_preferred":[
        "\u0c92\u0cb2\u0cc6\u0cb0\u0ccd\u0c9f\u0ca8\u0ccd"
    ],
    "name:kor_x_preferred":[
        "\uc62c\ub808\ud134"
    ],
    "name:lit_x_preferred":[
        "Oljertonas"
    ],
    "name:nld_x_preferred":[
        "Ollerton"
    ],
    "name:nno_x_preferred":[
        "Ollerton"
    ],
    "name:pol_x_preferred":[
        "Ollerton"
    ],
    "name:por_x_preferred":[
        "Ollerton"
    ],
    "name:ron_x_preferred":[
        "Ollerton"
    ],
    "name:rus_x_preferred":[
        "\u041e\u043b\u043b\u0435\u0440\u0442\u043e\u043d"
    ],
    "name:spa_x_preferred":[
        "Ollerton"
    ],
    "name:tam_x_preferred":[
        "\u0b92\u0bb2\u0bcd\u0bb2\u0bc6\u0bb0\u0bcd\u0b9f\u0ba9\u0bcd"
    ],
    "name:tel_x_preferred":[
        "\u0c12\u0c32\u0c47\u0c1f\u0c4d\u0c30\u0c3e\u0c28\u0c4d"
    ],
    "name:unk_x_variant":[
        "Ollerton"
    ],
    "name:urd_x_preferred":[
        "\u0648\u0644\u06cc\u0631\u0679\u0646"
    ],
    "qs_pg:aaroncc":"GB",
    "qs_pg:gn_country":"GB",
    "qs_pg:gn_fcode":"PPL",
    "qs_pg:gn_pop":0,
    "qs_pg:name":"New Ollerton",
    "qs_pg:name_adm0":"United Kingdom",
    "qs_pg:name_adm1":"England",
    "qs_pg:photos":216,
    "qs_pg:photos_1k":44,
    "qs_pg:photos_9k":1,
    "qs_pg:photos_9r":4,
    "qs_pg:photos_all":216,
    "qs_pg:photos_sr":4,
    "qs_pg:pop_sr":0,
    "qs_pg:qs_pg_placetype":"locality",
    "qs_pg:qs_pg_placetype_gp":"Town",
    "qs_pg:woe_adm0":23424975,
    "woe:adm0_id":23424975,
    "woe:name_adm0":"United Kingdom",
    "woe:name_adm1":"England",
    "woe:placetype":"Town",
    "wof:name":"New Ollerton",
    "wof:placetype":"neighbourhood"
},
  "geometry": {"coordinates":[-1.01667,53.21667],"type":"Point"}
}