{
  "type": "Feature",
  "properties": {
    "gn:admin1_code":"WLS",
    "gn:admin2_code":"Y4",
    "gn:admin3_code":"00PP002",
    "gn:asciiname":"Llanvair Discoed",
    "gn:country_code":"GB",
    "gn:dem":44,
    "gn:feature_class":"P",
    "gn:feature_code":"PPL",
    "gn:name":"Llanvair Discoed",
    "gn:population":0,
    "gn:timezone":"Europe/London",
    "iso:country":"GB",
    "wof:name":"Llanvair Discoed",
    "wof:placetype":"neighbourhood"
},
  "geometry": {"coordinates":[-2.79861,51.62667],"type":"Point"}
}