{
  "type": "Feature",
  "properties": {
    "iso:country": "GB",
    "name:ceb_x_preferred": [
      "Ainsworth"
    ],
    "name:deu_x_preferred": [
      "Ainsworth"
    ],
    "name:fra_x_preferred": [
      "Ainsworth"
    ],
    "name:ido_x_preferred": [
      "Ainsworth"
    ],
    "name:ita_x_preferred": [
      "Ainsworth"
    ],
    "name:jpn_x_preferred": [
      "エインズワース"
    ],
    "name:nds_x_preferred": [
      "Ainsworth"
    ],
    "name:nld_x_preferred": [
      "Ainsworth"
    ],
    "name:pol_x_preferred": [
      "Ainsworth"
    ],
    "name:por_x_preferred": [
      "Ainsworth"
    ],
    "name:rus_x_preferred": [
      "Эйнсуорт"
    ],
    "name:spa_x_preferred": [
      "Ainsworth"
    ],
    "name:srp_x_preferred": [
      "Ејнсворт"
    ],
    "name:swe_x_preferred": [
      "Ainsworth"
    ],
    "name:ukr_x_preferred": [
      "Ейнсворт"
    ],
    "name:vol_x_preferred": [
      "Ainsworth"
    ],
    "qs_pg:aaroncc": "GB",
    "qs_pg:name": "Ainsworth",
    "qs_pg:name_adm0": "United Kingdom",
    "qs_pg:name_adm1": "England",
    "qs_pg:photos": 23,
    "qs_pg:photos_1k": 5,
    "qs_pg:photos_9k": 1,
    "qs_pg:photos_9r": 1,
    "qs_pg:photos_all": 23,
    "qs_pg:photos_sr": 1,
    "qs_pg:pop_sr": 0,
    "qs_pg:qs_pg_placetype": "neighbourhood",
    "qs_pg:qs_pg_placetype_gp": "Suburb",
    "qs_pg:woe_adm0": 23424975,
    "woe:adm0_id": 23424975,
    "woe:name_adm0": "United Kingdom",
    "woe:name_adm1": "England",
    "woe:placetype": "Suburb",
    "wof:name": "Ainsworth",
    "wof:placetype": "neighbourhood"
  },
  "geometry": {"coordinates":[-2.326827,53.5622595],"type":"Point"}
}
