{
  "type": "Feature",
  "properties": {
    "iso:country":"GB",
    "name:bre_x_preferred":[
        "Newtown"
    ],
    "name:cat_x_preferred":[
        "Newtown"
    ],
    "name:ceb_x_preferred":[
        "Newtown"
    ],
    "name:ces_x_preferred":[
        "Newtown"
    ],
    "name:cym_x_preferred":[
        "Newtown"
    ],
    "name:dan_x_preferred":[
        "Newtown"
    ],
    "name:deu_x_preferred":[
        "Newtown"
    ],
    "name:eng_x_preferred":[
        "Newtown"
    ],
    "name:est_x_preferred":[
        "Newtown"
    ],
    "name:fas_x_preferred":[
        "\u0646\u06cc\u0648\u062a\u0627\u0648\u0646"
    ],
    "name:fin_x_preferred":[
        "Newtown"
    ],
    "name:fra_x_preferred":[
        "Newtown"
    ],
    "name:heb_x_preferred":[
        "\u05e0\u05d9\u05d5\u05d8\u05d0\u05d5\u05df"
    ],
    "name:hun_x_preferred":[
        "Newtown"
    ],
    "name:ita_x_preferred":[
        "Newtown"
    ],
    "name:jpn_x_preferred":[
        "\u30cb\u30e5\u30fc\u30bf\u30a6\u30f3"
    ],
    "name:kor_x_preferred":[
        "\ub274\ud0c0\uc6b4"
    ],
    "name:mlg_x_preferred":[
        "Newtown"
    ],
    "name:nld_x_preferred":[
        "Newtown"
    ],
    "name:pol_x_preferred":[
        "Newtown"
    ],
    "name:rus_x_preferred":[
        "\u041d\u044c\u044e\u0442\u0430\u0443\u043d"
    ],
    "name:spa_x_preferred":[
        "Newtown"
    ],
    "name:srp_x_preferred":[
        "\u040a\u0443\u0442\u0430\u0443\u043d"
    ],
    "name:swe_x_preferred":[
        "Newtown"
    ],
    "name:urd_x_preferred":[
        "\u0646\u06cc\u0648 \u0679\u0627\u0624\u0646"
    ],
    "name:vol_x_preferred":[
        "Newtown"
    ],
    "qs:gn_fcode":"PPL",
    "qs:gn_local":0,
    "qs:gn_namadm1":"ENG",
    "qs:gn_name":"Newtown",
    "qs:local_max":1435,
    "qs:local_sum":3473,
    "qs:localhoods":6,
    "qs:name":"Newtown",
    "qs:name_adm0":"United Kingdom",
    "qs:name_adm1":"England",
    "qs:name_adm2":"Greater Manchester",
    "qs:name_lau":"Wigan Metropolitan Borough",
    "qs:name_local":"Wigan",
    "qs:photo_max":312,
    "qs:photo_sum":883,
    "qs:placetype":"Suburb",
    "qs:quad_count":28,
    "qs:woe_adm0":23424975,
    "qs:woe_adm1":24554868,
    "qs:woe_adm2":12602158,
    "qs:woe_lau":12695848,
    "qs:woe_local":40445,
    "qs:woe_ver":"7.10.0",
    "wd:wordcount":516,
    "wof:lang":[
        "eng"
    ],
    "wof:name":"Newtown",
    "wof:placetype":"neighbourhood"
},
  "geometry": {"coordinates":[-2.652391,53.546385],"type":"Point"}
}