{
  "type": "Feature",
  "properties": {
    "gn:admin1_code":"ENG",
    "gn:admin2_code":"E6",
    "gn:admin3_code":"23UD",
    "gn:admin4_code":"23UD022",
    "gn:asciiname":"Glasshouse",
    "gn:country_code":"GB",
    "gn:dem":112,
    "gn:feature_class":"P",
    "gn:feature_code":"PPL",
    "gn:name":"Glasshouse",
    "gn:population":0,
    "gn:timezone":"Europe/London",
    "iso:country":"GB",
    "wof:name":"Glasshouse",
    "wof:placetype":"neighbourhood"
},
  "geometry": {"coordinates":[-2.42394,51.8909],"type":"Point"}
}