{
  "type": "Feature",
  "properties": {
    "iso:country":"GB",
    "wof:name":"The Moor",
    "wof:placetype":"neighbourhood"
},
  "geometry": {"coordinates":[-1.47351881825352,53.37584869852967],"type":"Point"}
}