{
  "type": "Feature",
  "properties": {
    "gn:admin1_code":"WLS",
    "gn:admin2_code":"Y2",
    "gn:admin3_code":"00NC061",
    "gn:asciiname":"Llangwnadl",
    "gn:country_code":"GB",
    "gn:dem":53,
    "gn:feature_class":"P",
    "gn:feature_code":"PPL",
    "gn:name":"Llangwnadl",
    "gn:population":0,
    "gn:timezone":"Europe/London",
    "iso:country":"GB",
    "wof:name":"Llangwnadl",
    "wof:placetype":"neighbourhood"
},
  "geometry": {"coordinates":[-4.66667,52.86666999999999],"type":"Point"}
}