{
  "type": "Feature",
  "properties": {
    "gn:admin1_code": "NIR",
    "gn:admin2_code": "N09000004",
    "gn:asciiname": "Billy",
    "gn:country_code": "GB",
    "gn:dem": 73,
    "gn:feature_class": "P",
    "gn:feature_code": "PPL",
    "gn:name": "Billy",
    "gn:population": 0,
    "gn:timezone": "Europe/London",
    "iso:country": "GB",
    "name:bre_x_preferred": [
      "Billy"
    ],
    "name:ceb_x_preferred": [
      "Billy"
    ],
    "name:ces_x_preferred": [
      "Billy"
    ],
    "name:deu_x_preferred": [
      "Billy"
    ],
    "name:est_x_preferred": [
      "Billy"
    ],
    "name:fas_x_preferred": [
      "بیلی"
    ],
    "name:fin_x_preferred": [
      "Billy"
    ],
    "name:fra_x_preferred": [
      "Billy"
    ],
    "name:heb_x_preferred": [
      "בילי"
    ],
    "name:ind_x_preferred": [
      "Billy"
    ],
    "name:ita_x_preferred": [
      "Billy"
    ],
    "name:jpn_x_preferred": [
      "ビリー"
    ],
    "name:nds_x_preferred": [
      "Billy"
    ],
    "name:nld_x_preferred": [
      "Billy"
    ],
    "name:nor_x_preferred": [
      "Billy"
    ],
    "name:oci_x_preferred": [
      "Billy"
    ],
    "name:pms_x_preferred": [
      "Billy"
    ],
    "name:pol_x_preferred": [
      "Billy"
    ],
    "name:por_x_preferred": [
      "Billy"
    ],
    "name:rus_x_preferred": [
      "Бийи"
    ],
    "name:slk_x_preferred": [
      "Billy"
    ],
    "name:spa_x_preferred": [
      "Billy"
    ],
    "name:srp_x_preferred": [
      "Бији"
    ],
    "name:swe_x_preferred": [
      "Billy"
    ],
    "name:ukr_x_preferred": [
      "Бії"
    ],
    "wof:name": "Billy",
    "wof:placetype": "locality"
  },
  "geometry": {"coordinates":[-6.48333,55.16667],"type":"Point"}
}
