{
  "type": "Feature",
  "properties": {
    "gn:admin1_code":"NIR",
    "gn:admin2_code":"N09000004",
    "gn:asciiname":"Billy",
    "gn:country_code":"GB",
    "gn:dem":73,
    "gn:feature_class":"P",
    "gn:feature_code":"PPL",
    "gn:name":"Billy",
    "gn:population":0,
    "gn:timezone":"Europe/London",
    "iso:country":"GB",
    "wof:name":"Billy",
    "wof:placetype":"locality"
},
  "geometry": {"coordinates":[-6.48333,55.16667],"type":"Point"}
}