{
  "type": "Feature",
  "properties": {
    "gn:admin1_code":"NIR",
    "gn:admin2_code":"N09000004",
    "gn:asciiname":"Billy",
    "gn:country_code":"GB",
    "gn:dem":73,
    "gn:feature_class":"P",
    "gn:feature_code":"PPL",
    "gn:name":"Billy",
    "gn:population":0,
    "gn:timezone":"Europe/London",
    "iso:country":"GB",
    "name:bre_x_preferred":[
        "Billy"
    ],
    "name:ceb_x_preferred":[
        "Billy"
    ],
    "name:ces_x_preferred":[
        "Billy"
    ],
    "name:deu_x_preferred":[
        "Billy"
    ],
    "name:est_x_preferred":[
        "Billy"
    ],
    "name:fas_x_preferred":[
        "\u0628\u06cc\u0644\u06cc"
    ],
    "name:fin_x_preferred":[
        "Billy"
    ],
    "name:fra_x_preferred":[
        "Billy"
    ],
    "name:heb_x_preferred":[
        "\u05d1\u05d9\u05dc\u05d9"
    ],
    "name:ind_x_preferred":[
        "Billy"
    ],
    "name:ita_x_preferred":[
        "Billy"
    ],
    "name:jpn_x_preferred":[
        "\u30d3\u30ea\u30fc"
    ],
    "name:nds_x_preferred":[
        "Billy"
    ],
    "name:nld_x_preferred":[
        "Billy"
    ],
    "name:nor_x_preferred":[
        "Billy"
    ],
    "name:oci_x_preferred":[
        "Billy"
    ],
    "name:pms_x_preferred":[
        "Billy"
    ],
    "name:pol_x_preferred":[
        "Billy"
    ],
    "name:por_x_preferred":[
        "Billy"
    ],
    "name:rus_x_preferred":[
        "\u0411\u0438\u0439\u0438"
    ],
    "name:slk_x_preferred":[
        "Billy"
    ],
    "name:spa_x_preferred":[
        "Billy"
    ],
    "name:srp_x_preferred":[
        "\u0411\u0438\u0458\u0438"
    ],
    "name:swe_x_preferred":[
        "Billy"
    ],
    "name:ukr_x_preferred":[
        "\u0411\u0456\u0457"
    ],
    "wof:name":"Billy",
    "wof:placetype":"locality"
},
  "geometry": {"coordinates":[-6.48333,55.16667],"type":"Point"}
}