{
  "type": "Feature",
  "properties": {
    "gn:country":"GB",
    "gn:fcode":"PPL",
    "gn:population":0,
    "iso:country":"GB",
    "name:cym_x_preferred":[
        "Lecwydd"
    ],
    "name:eng_x_preferred":[
        "Leckwith"
    ],
    "name:eus_x_preferred":[
        "Leckwith"
    ],
    "name:jpn_x_preferred":[
        "\u30ec\u30c3\u30af\u30a6\u30a3\u30ba"
    ],
    "name:nld_x_preferred":[
        "Leckwith"
    ],
    "qs_pg:aaroncc":"GB",
    "qs_pg:gn_country":"GB",
    "qs_pg:gn_fcode":"PPL",
    "qs_pg:gn_pop":0,
    "qs_pg:name":"Leckwith",
    "qs_pg:name_adm0":"United Kingdom",
    "qs_pg:name_adm1":"Wales",
    "qs_pg:photos":974,
    "qs_pg:photos_1k":197,
    "qs_pg:photos_9k":4,
    "qs_pg:photos_9r":6,
    "qs_pg:photos_all":974,
    "qs_pg:photos_sr":10,
    "qs_pg:pop_sr":0,
    "qs_pg:qs_pg_placetype":"locality",
    "qs_pg:qs_pg_placetype_gp":"Town",
    "qs_pg:woe_adm0":23424975,
    "woe:adm0_id":23424975,
    "woe:name_adm0":"United Kingdom",
    "woe:name_adm1":"Wales",
    "woe:placetype":"Town",
    "wof:name":"Leckwith",
    "wof:placetype":"neighbourhood"
},
  "geometry": {"coordinates":[-3.21278,51.46167],"type":"Point"}
}