{
  "type": "Feature",
  "properties": {
    "gn:country":"GB",
    "iso:country":"GB",
    "name:ceb_x_preferred":[
        "Lismore"
    ],
    "name:cym_x_preferred":[
        "Lismore"
    ],
    "name:deu_x_preferred":[
        "Lismore"
    ],
    "name:fra_x_preferred":[
        "Lismore"
    ],
    "name:ita_x_preferred":[
        "Lismore"
    ],
    "name:kat_x_preferred":[
        "\u10da\u10d8\u10e1\u10db\u10dd\u10e0\u10d8"
    ],
    "name:kor_x_preferred":[
        "\ub9ac\uc988\ubaa8\uc5b4"
    ],
    "name:mlg_x_preferred":[
        "Lismore"
    ],
    "name:nld_x_preferred":[
        "Lismore"
    ],
    "name:pol_x_preferred":[
        "Lismore"
    ],
    "name:por_x_preferred":[
        "Lismore"
    ],
    "name:spa_x_preferred":[
        "Lismore"
    ],
    "name:swe_x_preferred":[
        "Lismore"
    ],
    "qs_pg:aaroncc":"GB",
    "qs_pg:gn_country":"GB",
    "qs_pg:name":"Lismore",
    "qs_pg:name_adm0":"United Kingdom",
    "qs_pg:name_adm1":"Scotland",
    "qs_pg:photos":72,
    "qs_pg:photos_1k":15,
    "qs_pg:photos_9k":1,
    "qs_pg:photos_9r":2,
    "qs_pg:photos_all":72,
    "qs_pg:photos_sr":2,
    "qs_pg:pop_sr":0,
    "qs_pg:qs_pg_placetype":"locality",
    "qs_pg:qs_pg_placetype_gp":"Town",
    "qs_pg:woe_adm0":23424975,
    "woe:adm0_id":23424975,
    "woe:name_adm0":"United Kingdom",
    "woe:name_adm1":"Scotland",
    "woe:placetype":"Town",
    "wof:name":"Lismore",
    "wof:placetype":"locality"
},
  "geometry": {"coordinates":[-5.504099,56.516697],"type":"Point"}
}