{
  "type": "Feature",
  "properties": {
    "iso:country":"GB",
    "name:eng_x_preferred":[
        "Kendray"
    ],
    "name:fra_x_preferred":[
        "Kendray"
    ],
    "name:gle_x_preferred":[
        "Kendray"
    ],
    "name:jpn_x_preferred":[
        "\u30b1\u30f3\u30c9\u30ec\u30a4"
    ],
    "name:nld_x_preferred":[
        "Kendray"
    ],
    "name:pol_x_preferred":[
        "Kendray"
    ],
    "qs:gn_adm0_cc":"GB",
    "qs:gn_local":2654680,
    "qs:gn_nam_loc":"little weighton",
    "qs:gn_namadm1":"ENG",
    "qs:local_max":2141,
    "qs:local_sum":8332,
    "qs:localhoods":12,
    "qs:name":"Kendray",
    "qs:name_adm0":"United Kingdom",
    "qs:name_adm1":"England",
    "qs:name_adm2":"South Yorkshire",
    "qs:name_lau":"Barnsley Metropolitan Borough",
    "qs:name_local":"Barnsley",
    "qs:photo_max":30,
    "qs:photo_sum":149,
    "qs:placetype":"Suburb",
    "qs:quad_count":18,
    "qs:woe_adm0":23424975,
    "qs:woe_adm1":24554868,
    "qs:woe_adm2":12602196,
    "qs:woe_lau":12695854,
    "qs:woe_local":11916,
    "qs:woe_ver":"7.10.0",
    "wd:wordcount":270,
    "wof:lang":[
        "eng"
    ],
    "wof:name":"Kendray",
    "wof:placetype":"neighbourhood"
},
  "geometry": {"coordinates":[-1.454684,53.54614],"type":"Point"}
}