{
  "type": "Feature",
  "properties": {
    "gn:admin1_code":"SCT",
    "gn:admin2_code":"V3",
    "gn:asciiname":"East Canisbay",
    "gn:country_code":"GB",
    "gn:dem":36,
    "gn:feature_class":"P",
    "gn:feature_code":"PPL",
    "gn:name":"East Canisbay",
    "gn:population":0,
    "gn:timezone":"Europe/London",
    "iso:country":"GB",
    "wof:name":"East Canisbay",
    "wof:placetype":"locality"
},
  "geometry": {"coordinates":[-3.11667,58.63333000000001],"type":"Point"}
}