{
  "type": "Feature",
  "properties": {
    "gn:country":"GB",
    "iso:country":"GB",
    "name:eng_x_preferred":[
        "Ardaneaskan"
    ],
    "name:eus_x_preferred":[
        "Ardaneaskan"
    ],
    "name:gle_x_preferred":[
        "\u00c1ird nan Easgann"
    ],
    "name:nld_x_preferred":[
        "Ardaneaskan"
    ],
    "qs_pg:aaroncc":"GB",
    "qs_pg:gn_country":"GB",
    "qs_pg:name":"Ardaneaskan",
    "qs_pg:name_adm0":"United Kingdom",
    "qs_pg:name_adm1":"Scotland",
    "qs_pg:photos":77,
    "qs_pg:photos_1k":16,
    "qs_pg:photos_9k":1,
    "qs_pg:photos_9r":3,
    "qs_pg:photos_all":77,
    "qs_pg:photos_sr":3,
    "qs_pg:pop_sr":0,
    "qs_pg:qs_pg_placetype":"locality",
    "qs_pg:qs_pg_placetype_gp":"Town",
    "qs_pg:woe_adm0":23424975,
    "woe:adm0_id":23424975,
    "woe:name_adm0":"United Kingdom",
    "woe:name_adm1":"Scotland",
    "woe:placetype":"Town",
    "wof:name":"Ardaneaskan",
    "wof:placetype":"locality"
},
  "geometry": {"coordinates":[-5.604916,57.350422],"type":"Point"}
}