{
  "type": "Feature",
  "properties": {
    "gn:country":"GB",
    "gn:fcode":"PPL",
    "gn:population":0,
    "iso:country":"GB",
    "name:bre_x_preferred":[
        "Port na h-Abhainne"
    ],
    "name:bul_x_preferred":[
        "\u041f\u043e\u0440\u0442\u043d\u0430\u0445\u0430\u0432\u0435\u043d"
    ],
    "name:ceb_x_preferred":[
        "Portnahaven"
    ],
    "name:deu_x_preferred":[
        "Portnahaven"
    ],
    "name:eng_x_preferred":[
        "Portnahaven"
    ],
    "name:eus_x_preferred":[
        "Portnahaven"
    ],
    "name:fas_x_preferred":[
        "\u067e\u0648\u0631\u062a\u0646\u0627\u0647\u0627\u0648\u0646"
    ],
    "name:fra_x_preferred":[
        "Portnahaven"
    ],
    "name:gla_x_preferred":[
        "Port na h-Abhainne"
    ],
    "name:gle_x_preferred":[
        "Port na h-Abhainn"
    ],
    "name:heb_x_preferred":[
        "\u05e4\u05d5\u05e8\u05d8\u05e0\u05d4\u05d0\u05d1\u05df"
    ],
    "name:ita_x_preferred":[
        "Portnahaven"
    ],
    "name:jpn_x_preferred":[
        "\u30dd\u30fc\u30c8\u30ca\u30d8\u30a4\u30f4\u30f3"
    ],
    "name:nld_x_preferred":[
        "Portnahaven"
    ],
    "name:pol_x_preferred":[
        "Portnahaven"
    ],
    "name:spa_x_preferred":[
        "Portnahaven"
    ],
    "name:swe_x_preferred":[
        "Portnahaven"
    ],
    "qs_pg:aaroncc":"GB",
    "qs_pg:gn_country":"GB",
    "qs_pg:gn_fcode":"PPL",
    "qs_pg:gn_pop":0,
    "qs_pg:name":"Portnahaven",
    "qs_pg:name_adm0":"United Kingdom",
    "qs_pg:name_adm1":"Scotland",
    "qs_pg:photos":399,
    "qs_pg:photos_1k":81,
    "qs_pg:photos_9k":2,
    "qs_pg:photos_9r":5,
    "qs_pg:photos_all":399,
    "qs_pg:photos_sr":6,
    "qs_pg:pop_sr":0,
    "qs_pg:qs_pg_placetype":"locality",
    "qs_pg:qs_pg_placetype_gp":"Town",
    "qs_pg:woe_adm0":23424975,
    "woe:adm0_id":23424975,
    "woe:name_adm0":"United Kingdom",
    "woe:name_adm1":"Scotland",
    "woe:placetype":"Town",
    "wof:name":"Portnahaven",
    "wof:placetype":"locality"
},
  "geometry": {"coordinates":[-6.50799,55.68079],"type":"Point"}
}