{
  "type": "Feature",
  "properties": {
    "gn:admin1_code": "WLS",
    "gn:admin2_code": "Y7",
    "gn:admin3_code": "00NS010",
    "gn:asciiname": "Warren",
    "gn:country_code": "GB",
    "gn:dem": 51,
    "gn:feature_class": "P",
    "gn:feature_code": "PPL",
    "gn:name": "Warren",
    "gn:population": 0,
    "gn:timezone": "Europe/London",
    "iso:country": "GB",
    "name:fra_x_preferred": [
      "Garenne"
    ],
    "name:gle_x_preferred": [
      "Coinicéar"
    ],
    "wof:name": "Warren",
    "wof:placetype": "neighbourhood"
  },
  "geometry": {"coordinates":[-4.98944,51.63778],"type":"Point"}
}
