{
  "type": "Feature",
  "properties": {
    "gn:admin1_code":"ENG",
    "gn:admin2_code":"C6",
    "gn:admin3_code":"00HE037",
    "gn:asciiname":"Forrabury",
    "gn:country_code":"GB",
    "gn:dem":62,
    "gn:feature_class":"P",
    "gn:feature_code":"PPL",
    "gn:name":"Forrabury",
    "gn:population":0,
    "gn:timezone":"Europe/London",
    "iso:country":"GB",
    "wof:name":"Forrabury",
    "wof:placetype":"neighbourhood"
},
  "geometry": {"coordinates":[-4.69291,50.68562],"type":"Point"}
}