{
  "type": "Feature",
  "properties": {
    "iso:country": "GB",
    "name:ceb_x_preferred": [
      "Brownsover"
    ],
    "name:eng_x_preferred": [
      "Brownsover"
    ],
    "name:fra_x_preferred": [
      "Brownsover"
    ],
    "name:nld_x_preferred": [
      "Brownsover"
    ],
    "name:pol_x_preferred": [
      "Brownsover"
    ],
    "name:swe_x_preferred": [
      "Brownsover"
    ],
    "qs:gn_adm0_cc": "GB",
    "qs:gn_local": 2638978,
    "qs:gn_nam_loc": "rugby",
    "qs:gn_namadm1": "ENG",
    "qs:local_max": 1665,
    "qs:local_sum": 6610,
    "qs:localhoods": 5,
    "qs:name": "Brownsover",
    "qs:name_adm0": "United Kingdom",
    "qs:name_adm1": "England",
    "qs:name_adm2": "Warwickshire",
    "qs:name_lau": "Rugby Borough",
    "qs:name_local": "Rugby",
    "qs:photo_max": 438,
    "qs:photo_sum": 1657,
    "qs:placetype": "Suburb",
    "qs:quad_count": 82,
    "qs:woe_adm0": 23424975,
    "qs:woe_adm1": 24554868,
    "qs:woe_adm2": 12602190,
    "qs:woe_lau": 12696100,
    "qs:woe_local": 33744,
    "qs:woe_ver": "7.10.0",
    "wd:wordcount": 427,
    "wof:lang": [
      "eng"
    ],
    "wof:name": "Brownsover",
    "wof:placetype": "neighbourhood"
  },
  "geometry": {"coordinates":[-1.250794,52.387164],"type":"Point"}
}
