{
  "type": "Feature",
  "properties": {
    "gn:admin1_code": "ENG",
    "gn:admin2_code": "J7",
    "gn:admin3_code": "36UF",
    "gn:admin4_code": "36UF049",
    "gn:asciiname": "Carlton",
    "gn:country_code": "GB",
    "gn:dem": 161,
    "gn:feature_class": "P",
    "gn:feature_code": "PPL",
    "gn:name": "Carlton",
    "gn:population": 0,
    "gn:timezone": "Europe/London",
    "iso:country": "GB",
    "name:ceb_x_preferred": [
      "Carlton"
    ],
    "name:ces_x_preferred": [
      "Carlton"
    ],
    "name:deu_x_preferred": [
      "Carlton"
    ],
    "name:fas_x_preferred": [
      "کارلتون"
    ],
    "name:fra_x_preferred": [
      "Carlton"
    ],
    "name:heb_x_preferred": [
      "קרלטון"
    ],
    "name:ind_x_preferred": [
      "Carlton"
    ],
    "name:ita_x_preferred": [
      "Carlton"
    ],
    "name:jpn_x_preferred": [
      "カールトン"
    ],
    "name:mlg_x_preferred": [
      "Carlton"
    ],
    "name:nld_x_preferred": [
      "Carlton"
    ],
    "name:pol_x_preferred": [
      "Carlton"
    ],
    "name:por_x_preferred": [
      "Carlton"
    ],
    "name:slk_x_preferred": [
      "Carlton"
    ],
    "name:spa_x_preferred": [
      "Carlton"
    ],
    "name:srp_x_preferred": [
      "Карлтон"
    ],
    "name:swe_x_preferred": [
      "Carlton"
    ],
    "name:urd_x_preferred": [
      "کارلٹن"
    ],
    "name:vol_x_preferred": [
      "Carlton"
    ],
    "wof:name": "Carlton",
    "wof:placetype": "neighbourhood"
  },
  "geometry": {"coordinates":[-1.06667,54.26667],"type":"Point"}
}
