{
  "type": "Feature",
  "properties": {
    "gn:admin1_code":"ENG",
    "gn:admin2_code":"J7",
    "gn:admin3_code":"36UF",
    "gn:admin4_code":"36UF049",
    "gn:asciiname":"Carlton",
    "gn:country_code":"GB",
    "gn:dem":161,
    "gn:feature_class":"P",
    "gn:feature_code":"PPL",
    "gn:name":"Carlton",
    "gn:population":0,
    "gn:timezone":"Europe/London",
    "iso:country":"GB",
    "wof:name":"Carlton",
    "wof:placetype":"neighbourhood"
},
  "geometry": {"coordinates":[-1.06667,54.26667],"type":"Point"}
}