{
  "type": "Feature",
  "properties": {
    "gn:admin1_code":"ENG",
    "gn:admin2_code":"D6",
    "gn:admin3_code":"19UH",
    "gn:admin4_code":"19UH106",
    "gn:asciiname":"Yellowham Wood",
    "gn:country_code":"GB",
    "gn:dem":95,
    "gn:feature_class":"P",
    "gn:feature_code":"PPL",
    "gn:name":"Yellowham Wood",
    "gn:population":0,
    "gn:timezone":"Europe/London",
    "iso:country":"GB",
    "wof:name":"Yellowham Wood",
    "wof:placetype":"neighbourhood"
},
  "geometry": {"coordinates":[-2.38944,50.73944],"type":"Point"}
}