{
  "type": "Feature",
  "properties": {
    "iso:country": "GB",
    "name:ceb_x_preferred": [
      "Parkside"
    ],
    "name:deu_x_preferred": [
      "Parkside"
    ],
    "name:eng_x_preferred": [
      "Parkside"
    ],
    "name:swe_x_preferred": [
      "Parkside"
    ],
    "qs:gn_adm0_cc": "GB",
    "qs:gn_fcode": "PPLX",
    "qs:gn_local": 2652221,
    "qs:gn_namadm1": "ENG",
    "qs:gn_name": "Parkside",
    "qs:local_max": 5581,
    "qs:local_sum": 33638,
    "qs:localhoods": 22,
    "qs:name": "Parkside",
    "qs:name_adm0": "United Kingdom",
    "qs:name_adm1": "England",
    "qs:name_adm2": "West Midlands",
    "qs:name_lau": "Coventry City",
    "qs:name_local": "Coventry",
    "qs:photo_max": 1911,
    "qs:photo_sum": 4693,
    "qs:placetype": "Suburb",
    "qs:quad_count": 68,
    "qs:woe_adm0": 23424975,
    "qs:woe_adm1": 24554868,
    "qs:woe_adm2": 12602191,
    "qs:woe_lau": 12695864,
    "qs:woe_local": 17044,
    "qs:woe_ver": "7.10.0",
    "wof:lang": [
      "eng"
    ],
    "wof:name": "Parkside",
    "wof:placetype": "neighbourhood"
  },
  "geometry": {"coordinates":[-1.506287,52.407417],"type":"Point"}
}
