{
  "type": "Feature",
  "properties": {
    "iso:country": "GB",
    "name:eng_x_preferred": [
      "Bushfield"
    ],
    "qs:gn_adm0_cc": "GB",
    "qs:gn_local": 2640354,
    "qs:local_max": 4681,
    "qs:local_sum": 19610,
    "qs:localhoods": 18,
    "qs:name": "Bushfield",
    "qs:name_adm0": "United Kingdom",
    "qs:name_adm1": "England",
    "qs:name_adm2": "Cambridgeshire",
    "qs:name_lau": "Peterborough City",
    "qs:name_local": "Peterborough",
    "qs:photo_max": 77,
    "qs:photo_sum": 227,
    "qs:placetype": "Suburb",
    "qs:quad_count": 26,
    "qs:woe_adm0": 23424975,
    "qs:woe_adm1": 24554868,
    "qs:woe_adm2": 12602140,
    "qs:woe_lau": 12696170,
    "qs:woe_local": 31931,
    "qs:woe_ver": "7.10.0",
    "wof:lang": [
      "eng"
    ],
    "wof:name": "Bushfield",
    "wof:placetype": "neighbourhood"
  },
  "geometry": {"coordinates":[-0.27145,52.537158],"type":"Point"}
}
