{
  "type": "Feature",
  "properties": {
    "iso:country": "GB",
    "name:eng_x_preferred": [
      "Willowholme"
    ],
    "qs:gn_adm0_cc": "GB",
    "qs:gn_local": 2653775,
    "qs:gn_nam_loc": "Carlisle, Carlisle, Cumbria, England, GB",
    "qs:gn_namadm1": "ENG",
    "qs:local_max": 4448,
    "qs:local_sum": 11892,
    "qs:localhoods": 11,
    "qs:name": "Willowholme",
    "qs:name_adm0": "United Kingdom",
    "qs:name_adm1": "England",
    "qs:name_adm2": "Cumbria",
    "qs:name_lau": "Carlisle City",
    "qs:name_local": "Carlisle",
    "qs:photo_max": 933,
    "qs:photo_sum": 2541,
    "qs:placetype": "Suburb",
    "qs:quad_count": 32,
    "qs:woe_adm0": 23424975,
    "qs:woe_adm1": 24554868,
    "qs:woe_adm2": 12602148,
    "qs:woe_lau": 12695902,
    "qs:woe_local": 15178,
    "qs:woe_ver": "7.10.0",
    "wof:lang": [
      "eng"
    ],
    "wof:name": "Willowholme",
    "wof:placetype": "neighbourhood"
  },
  "geometry": {"coordinates":[-2.940421,54.89931],"type":"Point"}
}
