{
  "type": "Feature",
  "properties": {
    "gn:admin1_code": "ENG",
    "gn:admin2_code": "C6",
    "gn:admin3_code": "00HE026",
    "gn:asciiname": "Holywell Bay",
    "gn:country_code": "GB",
    "gn:dem": 10,
    "gn:feature_class": "P",
    "gn:feature_code": "PPL",
    "gn:name": "Holywell Bay",
    "gn:population": 0,
    "gn:timezone": "Europe/London",
    "iso:country": "GB",
    "wof:name": "Holywell Bay",
    "wof:placetype": "neighbourhood"
  },
  "geometry": {"coordinates":[-5.14207,50.38704],"type":"Point"}
}
