{
  "type": "Feature",
  "properties": {
    "iso:country": "GB",
    "name:ceb_x_preferred": [
      "Enniskillen Airport"
    ],
    "name:eng_x_preferred": [
      "Enniskillen/St Angelo Airport"
    ],
    "name:eng_x_variant": [
      "ENK",
      "EGAB"
    ],
    "name:fas_x_preferred": [
      "فرودگاه انیسکیلن\\سنت آنجلو"
    ],
    "name:msa_x_preferred": [
      "Lapangan Terbang St Angelo"
    ],
    "name:pms_x_preferred": [
      "Enniskillen - St Angelo Airport"
    ],
    "name:pol_x_preferred": [
      "Port lotniczy Enniskillen-St Angelo"
    ],
    "name:ron_x_preferred": [
      "Aeroportul Enniskillen/St Angelo"
    ],
    "name:swe_x_preferred": [
      "Enniskillen Airport"
    ],
    "name:tgk_x_preferred": [
      "Фурудгоҳи онискилнснт онҷлу"
    ],
    "name:zho_x_preferred": [
      "恩尼斯基林/聖天使機場"
    ],
    "oa:elevation_ft": "155",
    "oa:type": "medium_airport",
    "wd:wordcount": 512,
    "woe:hierarchy": {
      "country_id": 23424975,
      "county_id": 20071114,
      "localadmin_id": 20078335,
      "planet_id": 1,
      "state_id": 20070563
    },
    "wof:name": "Enniskillen Airport",
    "wof:placetype": "campus"
  },
  "geometry": {"coordinates":[-7.651944,54.398611],"type":"Point"}
}
