{
  "type": "Feature",
  "properties": {
    "iso:country":"GB",
    "name:ceb_x_preferred":[
        "Enniskillen Airport"
    ],
    "name:eng_x_preferred":[
        "Enniskillen/St Angelo Airport"
    ],
    "name:eng_x_variant":[
        "ENK",
        "EGAB"
    ],
    "name:fas_x_preferred":[
        "\u0641\u0631\u0648\u062f\u06af\u0627\u0647 \u0627\u0646\u06cc\u0633\u06a9\u06cc\u0644\u0646\\\u0633\u0646\u062a \u0622\u0646\u062c\u0644\u0648"
    ],
    "name:gle_x_preferred":[
        "Aerfort Inis Ceithleann"
    ],
    "name:hun_x_preferred":[
        "Enniskillen/St Angelo rep\u00fcl\u0151t\u00e9r"
    ],
    "name:msa_x_preferred":[
        "Lapangan Terbang St Angelo"
    ],
    "name:pms_x_preferred":[
        "Enniskillen - St Angelo Airport"
    ],
    "name:pol_x_preferred":[
        "Port lotniczy Enniskillen-St Angelo"
    ],
    "name:ron_x_preferred":[
        "Aeroportul Enniskillen/St Angelo"
    ],
    "name:swe_x_preferred":[
        "Enniskillen Airport"
    ],
    "name:tgk_x_preferred":[
        "\u0424\u0443\u0440\u0443\u0434\u0433\u043e\u04b3\u0438 \u043e\u043d\u0438\u0441\u043a\u0438\u043b\u043d\u0441\u043d\u0442 \u043e\u043d\u04b7\u043b\u0443"
    ],
    "name:zho_x_preferred":[
        "\u6069\u5c3c\u65af\u57fa\u6797/\u8056\u5929\u4f7f\u6a5f\u5834"
    ],
    "oa:elevation_ft":"155",
    "oa:type":"medium_airport",
    "wd:wordcount":512,
    "woe:hierarchy":{
        "country_id":23424975,
        "county_id":20071114,
        "localadmin_id":20078335,
        "planet_id":1,
        "state_id":20070563
    },
    "wof:name":"Enniskillen Airport",
    "wof:placetype":"campus"
},
  "geometry": {"coordinates":[-7.651944,54.398611],"type":"Point"}
}