{
  "type": "Feature",
  "properties": {
    "gn:country":"GB",
    "gn:fcode":"PPL",
    "gn:population":0,
    "iso:country":"GB",
    "name:bar_x_preferred":[
        "Wallis"
    ],
    "name:cat_x_preferred":[
        "Wallis"
    ],
    "name:ceb_x_preferred":[
        "Wallis"
    ],
    "name:ces_x_preferred":[
        "Wallis"
    ],
    "name:deu_x_preferred":[
        "Wallis"
    ],
    "name:epo_x_preferred":[
        "Wallis"
    ],
    "name:fin_x_preferred":[
        "Wallis"
    ],
    "name:fra_x_preferred":[
        "Wallis"
    ],
    "name:heb_x_preferred":[
        "\u05d5\u05d0\u05dc\u05d9\u05e1"
    ],
    "name:hun_x_preferred":[
        "Wallis"
    ],
    "name:ita_x_preferred":[
        "Wallis"
    ],
    "name:lav_x_preferred":[
        "Wallis"
    ],
    "name:nld_x_preferred":[
        "Wallis"
    ],
    "name:pol_x_preferred":[
        "Wallis"
    ],
    "name:por_x_preferred":[
        "Wallis"
    ],
    "name:rus_x_preferred":[
        "\u0423\u043e\u043b\u043b\u0438\u0441"
    ],
    "name:slk_x_preferred":[
        "Wallis"
    ],
    "name:spa_x_preferred":[
        "Wallis"
    ],
    "name:stq_x_preferred":[
        "Wallis"
    ],
    "name:swe_x_preferred":[
        "Wallis"
    ],
    "name:ukr_x_preferred":[
        "\u0412\u043e\u043b\u043b\u0456\u0441"
    ],
    "qs_pg:aaroncc":"GB",
    "qs_pg:gn_country":"GB",
    "qs_pg:gn_fcode":"PPL",
    "qs_pg:gn_pop":0,
    "qs_pg:name":"Wallis",
    "qs_pg:name_adm0":"United Kingdom",
    "qs_pg:name_adm1":"Wales",
    "qs_pg:photos":26,
    "qs_pg:photos_1k":5,
    "qs_pg:photos_9k":1,
    "qs_pg:photos_9r":2,
    "qs_pg:photos_all":26,
    "qs_pg:photos_sr":2,
    "qs_pg:pop_sr":0,
    "qs_pg:qs_pg_placetype":"locality",
    "qs_pg:qs_pg_placetype_gp":"Town",
    "qs_pg:woe_adm0":23424975,
    "woe:adm0_id":23424975,
    "woe:name_adm0":"United Kingdom",
    "woe:name_adm1":"Wales",
    "woe:placetype":"Town",
    "wof:name":"Wallis",
    "wof:placetype":"neighbourhood"
},
  "geometry": {"coordinates":[-4.89154,51.89473],"type":"Point"}
}