{
  "type": "Feature",
  "properties": {
    "gn:admin1_code":"NIR",
    "gn:admin2_code":"N09000005",
    "gn:asciiname":"Altamullan",
    "gn:cc2":"GB",
    "gn:country_code":"GB",
    "gn:dem":96,
    "gn:feature_class":"P",
    "gn:feature_code":"PPL",
    "gn:name":"Altamullan",
    "gn:population":0,
    "gn:timezone":"Europe/London",
    "iso:country":"GB",
    "name:und_x_variant":[
        "Altmullan",
        "Altamullan"
    ],
    "wof:name":"Altamullan",
    "wof:placetype":"locality"
},
  "geometry": {"coordinates":[-7.73333,54.68333000000001],"type":"Point"}
}