{
  "type": "Feature",
  "properties": {
    "gn:country":"GB",
    "gn:fcode":"PPL",
    "gn:population":876,
    "iso:country":"GB",
    "name:bul_x_preferred":[
        "\u0410\u0431\u0435\u0440\u043b\u0430\u0434\u0439"
    ],
    "name:ceb_x_preferred":[
        "Aberlady"
    ],
    "name:cym_x_preferred":[
        "Aberlady"
    ],
    "name:dan_x_preferred":[
        "Aberlady"
    ],
    "name:deu_x_preferred":[
        "Aberlady"
    ],
    "name:eng_x_preferred":[
        "Aberlady"
    ],
    "name:eus_x_preferred":[
        "Aberlady"
    ],
    "name:fas_x_preferred":[
        "\u0627\u0628\u0631\u0644\u06cc\u062f\u06cc"
    ],
    "name:fin_x_preferred":[
        "Aberlady"
    ],
    "name:fra_x_preferred":[
        "Aberlady"
    ],
    "name:gla_x_preferred":[
        "Obar L\u00ecobhaite"
    ],
    "name:gle_x_preferred":[
        "Obar L\u00edobhaite"
    ],
    "name:gle_x_variant":[
        "Obar L\u00ecobhaite"
    ],
    "name:ita_x_preferred":[
        "Aberlady"
    ],
    "name:jpn_x_preferred":[
        "\u30a2\u30d0\u30ec\u30c7\u30a3"
    ],
    "name:nld_x_preferred":[
        "Aberlady"
    ],
    "name:nno_x_preferred":[
        "Aberlady"
    ],
    "name:nob_x_preferred":[
        "Aberlady"
    ],
    "name:sco_x_preferred":[
        "Aiberleddy"
    ],
    "name:sco_x_variant":[
        "Aiberlady"
    ],
    "name:spa_x_preferred":[
        "Aberlady"
    ],
    "name:swe_x_preferred":[
        "Aberlady"
    ],
    "qs_pg:aaroncc":"GB",
    "qs_pg:gn_country":"GB",
    "qs_pg:gn_fcode":"PPL",
    "qs_pg:gn_pop":876,
    "qs_pg:name":"Aberlady",
    "qs_pg:name_adm0":"United Kingdom",
    "qs_pg:name_adm1":"Scotland",
    "qs_pg:photos":820,
    "qs_pg:photos_1k":166,
    "qs_pg:photos_9k":4,
    "qs_pg:photos_9r":6,
    "qs_pg:photos_all":820,
    "qs_pg:photos_sr":9,
    "qs_pg:pop_sr":2,
    "qs_pg:qs_pg_placetype":"locality",
    "qs_pg:qs_pg_placetype_gp":"Town",
    "qs_pg:woe_adm0":23424975,
    "woe:adm0_id":23424975,
    "woe:name_adm0":"United Kingdom",
    "woe:name_adm1":"Scotland",
    "woe:placetype":"Town",
    "wof:name":"Aberlady",
    "wof:placetype":"locality",
    "wof:population":1180
},
  "geometry": {"coordinates":[-2.85851,56.00884],"type":"Point"}
}