{
  "type": "Feature",
  "properties": {
    "gn:admin1_code":"WLS",
    "gn:admin2_code":"Y1",
    "gn:admin3_code":"00NJ010",
    "gn:asciiname":"Gwernymynydd",
    "gn:country_code":"GB",
    "gn:dem":189,
    "gn:feature_class":"P",
    "gn:feature_code":"PPL",
    "gn:name":"Gwernymynydd",
    "gn:population":0,
    "gn:timezone":"Europe/London",
    "iso:country":"GB",
    "name:bre_x_preferred":[
        "Gwernymynydd"
    ],
    "name:ceb_x_preferred":[
        "Gwernymynydd"
    ],
    "name:cor_x_preferred":[
        "Gwernymynydd"
    ],
    "name:cym_x_preferred":[
        "Gwernymynydd"
    ],
    "name:eus_x_preferred":[
        "Gwernymynydd"
    ],
    "name:fas_x_preferred":[
        "\u06af\u0648\u0626\u0631\u0646\u06cc\u200c\u0645\u0627\u06cc\u0646\u062f"
    ],
    "name:fra_x_preferred":[
        "Gwernymynydd"
    ],
    "name:gla_x_preferred":[
        "Gwernymynydd"
    ],
    "name:gle_x_preferred":[
        "Gwernymynydd"
    ],
    "name:ita_x_preferred":[
        "Gwernymynydd"
    ],
    "name:spa_x_preferred":[
        "Gwernymynydd"
    ],
    "name:swe_x_preferred":[
        "Gwernymynydd"
    ],
    "wof:name":"Gwernymynydd",
    "wof:placetype":"neighbourhood"
},
  "geometry": {"coordinates":[-3.1681,53.15645],"type":"Point"}
}