{
  "type": "Feature",
  "properties": {
    "gn:admin1_code":"ENG",
    "gn:admin2_code":"E5",
    "gn:asciiname":"Portobello",
    "gn:country_code":"GB",
    "gn:dem":95,
    "gn:feature_class":"P",
    "gn:feature_code":"PPL",
    "gn:name":"Portobello",
    "gn:population":0,
    "gn:timezone":"Europe/London",
    "iso:country":"GB",
    "wof:name":"Portobello",
    "wof:placetype":"neighbourhood"
},
  "geometry": {"coordinates":[-1.5607,54.89495],"type":"Point"}
}