{
  "type": "Feature",
  "properties": {
    "gn:admin1_code": "ENG",
    "gn:admin2_code": "E5",
    "gn:asciiname": "Portobello",
    "gn:country_code": "GB",
    "gn:dem": 95,
    "gn:feature_class": "P",
    "gn:feature_code": "PPL",
    "gn:name": "Portobello",
    "gn:population": 0,
    "gn:timezone": "Europe/London",
    "iso:country": "GB",
    "name:ceb_x_preferred": [
      "Portobello"
    ],
    "name:deu_x_preferred": [
      "Portobello"
    ],
    "name:eus_x_preferred": [
      "Portobello"
    ],
    "name:fra_x_preferred": [
      "Portobello"
    ],
    "name:heb_x_preferred": [
      "פורטובלו"
    ],
    "name:ita_x_preferred": [
      "Portobello"
    ],
    "name:nld_x_preferred": [
      "Portobello"
    ],
    "name:por_x_preferred": [
      "Portobello"
    ],
    "name:spa_x_preferred": [
      "Portobello"
    ],
    "name:swe_x_preferred": [
      "Portobello"
    ],
    "wof:name": "Portobello",
    "wof:placetype": "neighbourhood"
  },
  "geometry": {"coordinates":[-1.5607,54.89495],"type":"Point"}
}
