{
  "type": "Feature",
  "properties": {
    "gn:admin1_code":"WLS",
    "gn:admin2_code":"X6",
    "gn:admin3_code":"00NQ031",
    "gn:asciiname":"Cross Inn",
    "gn:country_code":"GB",
    "gn:dem":148,
    "gn:feature_class":"P",
    "gn:feature_code":"PPL",
    "gn:name":"Cross Inn",
    "gn:population":0,
    "gn:timezone":"Europe/London",
    "iso:country":"GB",
    "wof:name":"Cross Inn",
    "wof:placetype":"neighbourhood"
},
  "geometry": {"coordinates":[-4.35655,52.18943],"type":"Point"}
}