{
  "type": "Feature",
  "properties": {
    "iso:country":"GB",
    "name:eng_x_preferred":[
        "Blakeshall"
    ],
    "name:fra_x_preferred":[
        "Blakeshall"
    ],
    "name:gle_x_preferred":[
        "Blakeshall"
    ],
    "name:nld_x_preferred":[
        "Blakeshall"
    ],
    "name:pol_x_preferred":[
        "Blakeshall"
    ],
    "qs_pg:aaroncc":"GB",
    "qs_pg:name":"Blakeshall",
    "qs_pg:name_adm0":"United Kingdom",
    "qs_pg:name_adm1":"England",
    "qs_pg:photos":35,
    "qs_pg:photos_1k":7,
    "qs_pg:photos_9k":1,
    "qs_pg:photos_9r":2,
    "qs_pg:photos_all":35,
    "qs_pg:photos_sr":2,
    "qs_pg:pop_sr":0,
    "qs_pg:qs_pg_placetype":"locality",
    "qs_pg:qs_pg_placetype_gp":"Town",
    "qs_pg:woe_adm0":23424975,
    "woe:adm0_id":23424975,
    "woe:name_adm0":"United Kingdom",
    "woe:name_adm1":"England",
    "woe:placetype":"Town",
    "wof:name":"Blakeshall",
    "wof:placetype":"neighbourhood"
},
  "geometry": {"coordinates":[-2.247948,52.429444],"type":"Point"}
}