{
  "type": "Feature",
  "properties": {
    "iso:country":"GB",
    "name:eng_x_preferred":[
        "Cusworth"
    ],
    "name:unk_x_variant":[
        "Cusworth"
    ],
    "qs:gn_adm0_cc":"GB",
    "qs:gn_fcode":"PPL",
    "qs:gn_local":2657332,
    "qs:gn_nam_loc":"bewholme",
    "qs:gn_namadm1":"ENG",
    "qs:gn_name":"Cudworth",
    "qs:local_max":2329,
    "qs:local_sum":7008,
    "qs:localhoods":6,
    "qs:name":"Cusworth",
    "qs:name_adm0":"United Kingdom",
    "qs:name_adm1":"England",
    "qs:name_adm2":"South Yorkshire",
    "qs:name_lau":"Doncaster Metropolitan Borough",
    "qs:name_local":"Doncaster",
    "qs:photo_max":125,
    "qs:photo_sum":597,
    "qs:placetype":"Suburb",
    "qs:quad_count":38,
    "qs:woe_adm0":23424975,
    "qs:woe_adm1":24554868,
    "qs:woe_adm2":12602196,
    "qs:woe_lau":12695855,
    "qs:woe_local":18307,
    "qs:woe_ver":"7.10.0",
    "wof:lang":[
        "eng"
    ],
    "wof:name":"Cusworth",
    "wof:placetype":"neighbourhood"
},
  "geometry": {"coordinates":[-1.176863,53.52952],"type":"Point"}
}