{
  "type": "Feature",
  "properties": {
    "iso:country":"GB",
    "name:ben_x_preferred":[
        "\u0995\u09be\u09a1\u0993\u09b0\u09cd\u09a5"
    ],
    "name:ceb_x_preferred":[
        "Cudworth"
    ],
    "name:deu_x_preferred":[
        "Cudworth"
    ],
    "name:eng_x_preferred":[
        "Cusworth"
    ],
    "name:eng_x_variant":[
        "Cudworth"
    ],
    "name:fas_x_preferred":[
        "\u06a9\u0627\u062f\u0648\u0631\u062b"
    ],
    "name:fra_x_preferred":[
        "Cudworth"
    ],
    "name:gle_x_preferred":[
        "Cudworth"
    ],
    "name:guj_x_preferred":[
        "\u0a95\u0aa1\u0ab5\u0ab0\u0acd\u0aa5"
    ],
    "name:ita_x_preferred":[
        "Cudworth"
    ],
    "name:jpn_x_preferred":[
        "\u30ab\u30c3\u30c9\u30ef\u30fc\u30b9"
    ],
    "name:kan_x_preferred":[
        "\u0c95\u0cc1\u0ca1\u0ccd\u0cb5\u0cb0\u0ccd\u0ca4\u0ccd"
    ],
    "name:kor_x_preferred":[
        "\ucee4\ub4dc\uc6cc\uc2a4"
    ],
    "name:lit_x_preferred":[
        "Kladvortas"
    ],
    "name:nld_x_preferred":[
        "Cudworth"
    ],
    "name:pol_x_preferred":[
        "Cudworth"
    ],
    "name:por_x_preferred":[
        "Cudworth"
    ],
    "name:rus_x_preferred":[
        "\u041a\u0430\u0434\u0432\u043e\u0440\u0444"
    ],
    "name:spa_x_preferred":[
        "Cudworth"
    ],
    "name:swe_x_preferred":[
        "Cudworth"
    ],
    "name:tam_x_preferred":[
        "\u0b95\u0bc2\u0b92\u0bb0\u0bcd\u0ba4\u0bcd"
    ],
    "name:tel_x_preferred":[
        "\u0c15\u0c41\u0c21\u0c4d\u0c35\u0c30\u0c4d\u0c24\u0c4d"
    ],
    "name:urd_x_preferred":[
        "\u06a9\u0648\u062f\u0648\u0648\u0631\u062a\u06be"
    ],
    "name:zho_x_preferred":[
        "\u5361\u5fb7\u6c83\u601d"
    ],
    "qs:gn_adm0_cc":"GB",
    "qs:gn_fcode":"PPL",
    "qs:gn_local":2657332,
    "qs:gn_nam_loc":"bewholme",
    "qs:gn_namadm1":"ENG",
    "qs:gn_name":"Cudworth",
    "qs:local_max":2329,
    "qs:local_sum":7008,
    "qs:localhoods":6,
    "qs:name":"Cusworth",
    "qs:name_adm0":"United Kingdom",
    "qs:name_adm1":"England",
    "qs:name_adm2":"South Yorkshire",
    "qs:name_lau":"Doncaster Metropolitan Borough",
    "qs:name_local":"Doncaster",
    "qs:photo_max":125,
    "qs:photo_sum":597,
    "qs:placetype":"Suburb",
    "qs:quad_count":38,
    "qs:woe_adm0":23424975,
    "qs:woe_adm1":24554868,
    "qs:woe_adm2":12602196,
    "qs:woe_lau":12695855,
    "qs:woe_local":18307,
    "qs:woe_ver":"7.10.0",
    "wof:lang":[
        "eng"
    ],
    "wof:name":"Cusworth",
    "wof:placetype":"neighbourhood"
},
  "geometry": {"coordinates":[-1.176863,53.52952],"type":"Point"}
}