{
  "type": "Feature",
  "properties": {
    "iso:country":"GB",
    "name:cym_x_preferred":[
        "Black Dog"
    ],
    "name:eng_x_preferred":[
        "Black Dog"
    ],
    "name:fra_x_preferred":[
        "Black Dog"
    ],
    "name:nld_x_preferred":[
        "Black Dog"
    ],
    "name:pol_x_preferred":[
        "Black Dog"
    ],
    "name:pol_x_variant":[
        "Black Dog"
    ],
    "qs_pg:aaroncc":"GB",
    "qs_pg:name":"Black Dog",
    "qs_pg:name_adm0":"United Kingdom",
    "qs_pg:name_adm1":"England",
    "qs_pg:photos":79,
    "qs_pg:photos_1k":16,
    "qs_pg:photos_9k":1,
    "qs_pg:photos_9r":3,
    "qs_pg:photos_all":79,
    "qs_pg:photos_sr":3,
    "qs_pg:pop_sr":0,
    "qs_pg:qs_pg_placetype":"locality",
    "qs_pg:qs_pg_placetype_gp":"Town",
    "qs_pg:woe_adm0":23424975,
    "woe:adm0_id":23424975,
    "woe:name_adm0":"United Kingdom",
    "woe:name_adm1":"England",
    "woe:placetype":"Town",
    "wof:name":"Black Dog",
    "wof:placetype":"neighbourhood"
},
  "geometry": {"coordinates":[-3.699302,50.874839],"type":"Point"}
}