{
  "type": "Feature",
  "properties": {
    "gn:admin1_code":"ENG",
    "gn:admin2_code":"P3",
    "gn:admin3_code":"44UE",
    "gn:admin4_code":"44UE093",
    "gn:asciiname":"Tanworth",
    "gn:country_code":"GB",
    "gn:dem":158,
    "gn:feature_class":"P",
    "gn:feature_code":"PPL",
    "gn:name":"Tanworth",
    "gn:population":0,
    "gn:timezone":"Europe/London",
    "iso:country":"GB",
    "wof:name":"Tanworth",
    "wof:placetype":"neighbourhood"
},
  "geometry": {"coordinates":[-1.83618,52.33329000000001],"type":"Point"}
}