{
  "type": "Feature",
  "properties": {
    "gn:gn_country":"GB",
    "gn:gn_fcode":"PPL",
    "gn:gn_pop":0,
    "gn:population":630,
    "iso:country":"GB",
    "name:bul_x_preferred":[
        "\u041b\u0430\u043d\u0443\u0440\u0442\u0438\u0434 \u0423\u0435\u043b\u0441"
    ],
    "name:cym_x_preferred":[
        "Llanwrtyd"
    ],
    "name:unk_x_variant":[
        "Llanwrtyd Wells"
    ],
    "qs_pg:aaroncc":"GB",
    "qs_pg:gn_country":"GB",
    "qs_pg:gn_fcode":"PPL",
    "qs_pg:gn_pop":0,
    "qs_pg:name":"Llanwrtyd",
    "qs_pg:name_adm0":"United Kingdom",
    "qs_pg:name_adm1":"Wales",
    "qs_pg:photos":85,
    "qs_pg:photos_1k":17,
    "qs_pg:photos_9k":1,
    "qs_pg:photos_9r":3,
    "qs_pg:photos_all":85,
    "qs_pg:photos_sr":3,
    "qs_pg:pop_sr":0,
    "qs_pg:qs_pg_placetype":"locality",
    "qs_pg:qs_pg_placetype_gp":"Town",
    "qs_pg:woe_adm0":23424975,
    "woe:adm0_id":23424975,
    "woe:name_adm0":"United Kingdom",
    "woe:name_adm1":"Wales",
    "woe:placetype":"Town",
    "wof:name":"Llanwrtyd",
    "wof:placetype":"neighbourhood",
    "wof:population":630
},
  "geometry": {"coordinates":[-3.63924,52.10659],"type":"Point"}
}