{
  "type": "Feature",
  "properties": {
    "gn:gn_country":"GB",
    "gn:gn_fcode":"PPL",
    "gn:gn_pop":0,
    "iso:country":"GB",
    "name:dut_x_preferred":[
        "St Margaret's Hope"
    ],
    "name:eng_x_preferred":[
        "Saint Margaret's Hope"
    ],
    "name:fre_x_preferred":[
        "St Margaret's Hope"
    ],
    "name:ger_x_preferred":[
        "St. Margaret\u2019s Hope"
    ],
    "name:ita_x_preferred":[
        "St Margaret's Hope"
    ],
    "name:jpn_x_preferred":[
        "\u30bb\u30f3\u30c8\u30de\u30fc\u30ac\u30ec\u30c3\u30c8\u6e7e"
    ],
    "name:nno_x_preferred":[
        "St. Margaret's Hope"
    ],
    "name:nob_x_preferred":[
        "St. Margaret's Hope"
    ],
    "name:sco_x_preferred":[
        "St Margaret's Hup"
    ],
    "name:swe_x_preferred":[
        "St. Margaret's Hope"
    ],
    "name:unk_x_variant":[
        "Saint Margarets Hope"
    ],
    "qs_pg:aaroncc":"GB",
    "qs_pg:gn_country":"GB",
    "qs_pg:gn_fcode":"PPL",
    "qs_pg:gn_pop":0,
    "qs_pg:name":"St. Margaret's Hope",
    "qs_pg:name_adm0":"United Kingdom",
    "qs_pg:name_adm1":"Scotland",
    "qs_pg:photos":422,
    "qs_pg:photos_1k":86,
    "qs_pg:photos_9k":2,
    "qs_pg:photos_9r":5,
    "qs_pg:photos_all":422,
    "qs_pg:photos_sr":6,
    "qs_pg:pop_sr":0,
    "qs_pg:qs_pg_placetype":"locality",
    "qs_pg:qs_pg_placetype_gp":"Town",
    "qs_pg:woe_adm0":23424975,
    "woe:adm0_id":23424975,
    "woe:name_adm0":"United Kingdom",
    "woe:name_adm1":"Scotland",
    "woe:placetype":"Town",
    "wof:name":"St. Margaret's Hope",
    "wof:placetype":"locality"
},
  "geometry": {"coordinates":[-2.95,58.81667],"type":"Point"}
}