{
  "type": "Feature",
  "properties": {
    "gn:population":3392,
    "iso:country":"GB",
    "name:ben_x_preferred":[
        "\u0993\u09ad\u09be\u09b0\u09cd\u099f\u09a8"
    ],
    "name:ceb_x_preferred":[
        "Overton"
    ],
    "name:cym_x_preferred":[
        "Overton"
    ],
    "name:dut_x_preferred":[
        "Overton"
    ],
    "name:eng_x_preferred":[
        "Overton"
    ],
    "name:ger_x_preferred":[
        "Overton"
    ],
    "name:guj_x_preferred":[
        "\u0a93\u0ab5\u0ab0\u0a9f\u0aa8"
    ],
    "name:jpn_x_preferred":[
        "\u30aa\u30d0\u30fc\u30c8\u30f3"
    ],
    "name:kan_x_preferred":[
        "\u0c93\u0cb5\u0cb0\u0ccd\u0c9f\u0ca8\u0ccd"
    ],
    "name:kor_x_preferred":[
        "\uc624\ubc84\ud134"
    ],
    "name:lit_x_preferred":[
        "Overtonas"
    ],
    "name:nld_x_preferred":[
        "Overton"
    ],
    "name:pol_x_preferred":[
        "Overton"
    ],
    "name:por_x_preferred":[
        "Overton"
    ],
    "name:rus_x_preferred":[
        "\u041e\u0432\u0435\u0440\u0442\u043e\u043d"
    ],
    "name:spa_x_preferred":[
        "Overton"
    ],
    "name:swe_x_preferred":[
        "Overton"
    ],
    "name:tam_x_preferred":[
        "\u0b93\u0bb5\u0bc6\u0bb0\u0bcd\u0b9f\u0bcd\u0b9f\u0ba9\u0bcd"
    ],
    "name:tel_x_preferred":[
        "\u0c13\u0c35\u0c30\u0c4d\u0c1f\u0c28\u0c4d"
    ],
    "name:urd_x_preferred":[
        "\u0627\u0648\u0648\u0631\u0679\u0646\u060c \u06c1\u06cc\u0645\u067e\u0634\u0627\u0626\u0631"
    ],
    "name:wel_x_preferred":[
        "Overton"
    ],
    "qs:a0":"United Kingdom",
    "qs:a1":"*Hampshire",
    "qs:a1_lc":"GB12240000",
    "qs:a1r":"0England",
    "qs:a1r_lc":"GB12000000",
    "qs:adm0":"United Kingdom",
    "qs:la_lc":"*",
    "qs:level":"locality",
    "qs:loc":"Overton",
    "qs:loc_alt":"Overton",
    "qs:pop":0,
    "qs:type":"buffered point",
    "wd:wordcount":2297,
    "wof:name":"Overton",
    "wof:placetype":"neighbourhood",
    "wof:population":3392
},
  "geometry": {"coordinates":[-1.262301,51.243727],"type":"Point"}
}