{
  "type": "Feature",
  "properties": {
    "gn:population": 3392,
    "iso:country": "GB",
    "name:ara_x_preferred": [
      "أوفرتون"
    ],
    "name:ben_x_preferred": [
      "ওভার্টন"
    ],
    "name:ceb_x_preferred": [
      "Overton"
    ],
    "name:cym_x_preferred": [
      "Overton"
    ],
    "name:deu_x_preferred": [
      "Overton"
    ],
    "name:eng_x_preferred": [
      "Overton"
    ],
    "name:fas_x_preferred": [
      "اورتون"
    ],
    "name:guj_x_preferred": [
      "ઓવરટન"
    ],
    "name:ita_x_preferred": [
      "Overton"
    ],
    "name:jpn_x_preferred": [
      "オバートン"
    ],
    "name:kan_x_preferred": [
      "ಓವರ್ಟನ್"
    ],
    "name:kor_x_preferred": [
      "오버턴"
    ],
    "name:lit_x_preferred": [
      "Overtonas"
    ],
    "name:nld_x_preferred": [
      "Overton"
    ],
    "name:pol_x_preferred": [
      "Overton"
    ],
    "name:por_x_preferred": [
      "Overton"
    ],
    "name:rus_x_preferred": [
      "Овертон"
    ],
    "name:spa_x_preferred": [
      "Overton"
    ],
    "name:swe_x_preferred": [
      "Overton"
    ],
    "name:tam_x_preferred": [
      "ஓவெர்ட்டன்"
    ],
    "name:tel_x_preferred": [
      "ఓవర్టన్"
    ],
    "name:urd_x_preferred": [
      "اوورٹن، ہیمپشائر"
    ],
    "name:urd_x_variant": [
      "اوورٹن"
    ],
    "qs:a0": "United Kingdom",
    "qs:a1": "*Hampshire",
    "qs:a1_lc": "GB12240000",
    "qs:a1r": "0England",
    "qs:a1r_lc": "GB12000000",
    "qs:adm0": "United Kingdom",
    "qs:la_lc": "*",
    "qs:level": "locality",
    "qs:loc": "Overton",
    "qs:loc_alt": "Overton",
    "qs:pop": 0,
    "qs:type": "buffered point",
    "wd:wordcount": 2297,
    "wof:name": "Overton",
    "wof:placetype": "neighbourhood",
    "wof:population": 3392
  },
  "geometry": {"coordinates":[-1.262301,51.243727],"type":"Point"}
}
