{
  "type": "Feature",
  "properties": {
    "gn:admin1_code":"ENG",
    "gn:admin2_code":"J6",
    "gn:admin3_code":"00EM070",
    "gn:asciiname":"Haydon Bridge",
    "gn:country_code":"GB",
    "gn:dem":65,
    "gn:feature_class":"P",
    "gn:feature_code":"PPL",
    "gn:name":"Haydon Bridge",
    "gn:population":1557,
    "gn:timezone":"Europe/London",
    "iso:country":"GB",
    "name:ceb_x_preferred":[
        "Haydon Bridge"
    ],
    "name:cym_x_preferred":[
        "Haydon Bridge"
    ],
    "name:ell_x_preferred":[
        "\u03a7\u03ad\u03b9\u03bd\u03c4\u03bf\u03bd \u039c\u03c0\u03c1\u03b9\u03c4\u03b6"
    ],
    "name:eng_x_preferred":[
        "Haydon Bridge"
    ],
    "name:fas_x_preferred":[
        "\u0647\u06cc\u062f\u0648\u0646 \u0628\u0631\u06cc\u062c"
    ],
    "name:fra_x_preferred":[
        "Haydon Bridge"
    ],
    "name:gle_x_preferred":[
        "Haydon Bridge"
    ],
    "name:ita_x_preferred":[
        "Haydon Bridge"
    ],
    "name:jpn_x_preferred":[
        "\u30d8\u30a4\u30c9\u30f3\u30fb\u30d6\u30ea\u30c3\u30b8"
    ],
    "name:nld_x_preferred":[
        "Haydon Bridge"
    ],
    "name:pol_x_preferred":[
        "Haydon Bridge"
    ],
    "name:rus_x_preferred":[
        "\u0425\u0435\u0439\u0434\u043e\u043d \u0411\u0440\u0438\u0434\u0436"
    ],
    "name:swe_x_preferred":[
        "Haydon Bridge"
    ],
    "name:zho_x_preferred":[
        "\u6d77\u767b\u6a4b"
    ],
    "qs:a0":"United Kingdom",
    "qs:a1":"*Northumberland",
    "qs:a1_lc":"GB12EM0000",
    "qs:a1r":"0England",
    "qs:a1r_lc":"GB12000000",
    "qs:adm0":"United Kingdom",
    "qs:la_lc":"*",
    "qs:level":"locality",
    "qs:loc":"Haydon Bridge",
    "qs:loc_alt":"Haydon Bridge",
    "qs:pop":0,
    "qs:type":"buffered point",
    "wd:wordcount":1285,
    "wof:name":"Haydon Bridge",
    "wof:placetype":"neighbourhood",
    "wof:population":1557
},
  "geometry": {"coordinates":[-2.245854,54.973261],"type":"Point"}
}