{
  "type": "Feature",
  "properties": {
    "iso:country": "GB",
    "name:ceb_x_preferred": [
      "Haydon Bridge"
    ],
    "name:cym_x_preferred": [
      "Haydon Bridge"
    ],
    "name:ell_x_preferred": [
      "Χέιντον Μπριτζ"
    ],
    "name:eng_x_preferred": [
      "Haydon Bridge"
    ],
    "name:fas_x_preferred": [
      "هیدون بریج"
    ],
    "name:fra_x_preferred": [
      "Haydon Bridge"
    ],
    "name:ita_x_preferred": [
      "Haydon Bridge"
    ],
    "name:jpn_x_preferred": [
      "ヘイドン・ブリッジ"
    ],
    "name:nld_x_preferred": [
      "Haydon Bridge"
    ],
    "name:pol_x_preferred": [
      "Haydon Bridge"
    ],
    "name:rus_x_preferred": [
      "Хейдон Бридж"
    ],
    "name:swe_x_preferred": [
      "Haydon Bridge"
    ],
    "qs:a0": "United Kingdom",
    "qs:a1": "*Northumberland",
    "qs:a1_lc": "GB12EM0000",
    "qs:a1r": "0England",
    "qs:a1r_lc": "GB12000000",
    "qs:adm0": "United Kingdom",
    "qs:la_lc": "*",
    "qs:level": "locality",
    "qs:loc": "Haydon Bridge",
    "qs:loc_alt": "Haydon Bridge",
    "qs:pop": 0,
    "qs:type": "buffered point",
    "wd:wordcount": 1285,
    "wof:name": "Haydon Bridge",
    "wof:placetype": "neighbourhood"
  },
  "geometry": {"coordinates":[-2.245854,54.973261],"type":"Point"}
}
