{
  "type": "Feature",
  "properties": {
    "iso:country":"GB",
    "name:ceb_x_preferred":[
        "Haydon Bridge"
    ],
    "name:cym_x_preferred":[
        "Haydon Bridge"
    ],
    "name:dut_x_preferred":[
        "Haydon Bridge"
    ],
    "name:eng_x_preferred":[
        "Haydon Bridge"
    ],
    "name:fre_x_preferred":[
        "Haydon Bridge"
    ],
    "name:gre_x_preferred":[
        "\u03a7\u03ad\u03b9\u03bd\u03c4\u03bf\u03bd \u039c\u03c0\u03c1\u03b9\u03c4\u03b6"
    ],
    "name:ita_x_preferred":[
        "Haydon Bridge"
    ],
    "name:jpn_x_preferred":[
        "\u30d8\u30a4\u30c9\u30f3\u30fb\u30d6\u30ea\u30c3\u30b8"
    ],
    "name:pol_x_preferred":[
        "Haydon Bridge"
    ],
    "name:rus_x_preferred":[
        "\u0425\u0435\u0439\u0434\u043e\u043d \u0411\u0440\u0438\u0434\u0436"
    ],
    "name:swe_x_preferred":[
        "Haydon Bridge"
    ],
    "name:wel_x_preferred":[
        "Haydon Bridge"
    ],
    "qs:a0":"United Kingdom",
    "qs:a1":"*Northumberland",
    "qs:a1_lc":"GB12EM0000",
    "qs:a1r":"0England",
    "qs:a1r_lc":"GB12000000",
    "qs:adm0":"United Kingdom",
    "qs:la_lc":"*",
    "qs:level":"locality",
    "qs:loc":"Haydon Bridge",
    "qs:loc_alt":"Haydon Bridge",
    "qs:pop":0,
    "qs:type":"buffered point",
    "wd:wordcount":1285,
    "wof:name":"Haydon Bridge",
    "wof:placetype":"neighbourhood"
},
  "geometry": {"coordinates":[-2.245854,54.973261],"type":"Point"}
}