{
  "type": "Feature",
  "properties": {
    "gn:country": "GB",
    "gn:fcode": "PPL",
    "gn:population": 0,
    "iso:country": "GB",
    "name:bul_x_preferred": [
      "Гретна Грийн"
    ],
    "name:deu_x_preferred": [
      "Gretna Green"
    ],
    "name:eng_x_preferred": [
      "Gretna Green"
    ],
    "name:epo_x_preferred": [
      "Gretna Green"
    ],
    "name:eus_x_preferred": [
      "Gretna Green"
    ],
    "name:fas_x_preferred": [
      "گرتنا گرین"
    ],
    "name:fra_x_preferred": [
      "Gretna Green"
    ],
    "name:heb_x_preferred": [
      "גרטנה גרין"
    ],
    "name:hun_x_preferred": [
      "Gretna Green"
    ],
    "name:ita_x_preferred": [
      "Gretna Green"
    ],
    "name:jpn_x_preferred": [
      "グレトナ・グリーン"
    ],
    "name:kor_x_preferred": [
      "그레트나그린"
    ],
    "name:nld_x_preferred": [
      "Gretna Green"
    ],
    "name:pol_x_preferred": [
      "Gretna Green"
    ],
    "name:rus_x_preferred": [
      "Гретна-Грин"
    ],
    "name:sco_x_preferred": [
      "Gretna Green"
    ],
    "name:spa_x_preferred": [
      "Gretna Green"
    ],
    "name:swe_x_preferred": [
      "Gretna Green"
    ],
    "qs_pg:aaroncc": "GB",
    "qs_pg:gn_country": "GB",
    "qs_pg:gn_fcode": "PPL",
    "qs_pg:gn_pop": 0,
    "qs_pg:name": "Gretna Green",
    "qs_pg:name_adm0": "United Kingdom",
    "qs_pg:name_adm1": "Scotland",
    "qs_pg:photos": 319,
    "qs_pg:photos_1k": 65,
    "qs_pg:photos_9k": 1,
    "qs_pg:photos_9r": 5,
    "qs_pg:photos_all": 319,
    "qs_pg:photos_sr": 5,
    "qs_pg:pop_sr": 0,
    "qs_pg:qs_pg_placetype": "locality",
    "qs_pg:qs_pg_placetype_gp": "Town",
    "qs_pg:woe_adm0": 23424975,
    "woe:adm0_id": 23424975,
    "woe:name_adm0": "United Kingdom",
    "woe:name_adm1": "Scotland",
    "woe:placetype": "Town",
    "wof:name": "Gretna Green",
    "wof:placetype": "locality"
  },
  "geometry": {"coordinates":[-3.06618,55.00279],"type":"Point"}
}
