{
  "type": "Feature",
  "properties": {
    "gn:gn_country":"GB",
    "gn:gn_fcode":"PPL",
    "gn:gn_pop":0,
    "iso:country":"GB",
    "name:bul_x_preferred":[
        "\u0413\u0440\u0435\u0442\u043d\u0430 \u0413\u0440\u0438\u0439\u043d"
    ],
    "name:dut_x_preferred":[
        "Gretna Green"
    ],
    "name:eng_x_preferred":[
        "Gretna Green"
    ],
    "name:epo_x_preferred":[
        "Gretna Green"
    ],
    "name:fas_x_preferred":[
        "\u06af\u0631\u062a\u0646\u0627 \u06af\u0631\u06cc\u0646"
    ],
    "name:fre_x_preferred":[
        "Gretna Green"
    ],
    "name:ger_x_preferred":[
        "Gretna Green"
    ],
    "name:heb_x_preferred":[
        "\u05d2\u05e8\u05d8\u05e0\u05d4 \u05d2\u05e8\u05d9\u05df"
    ],
    "name:hun_x_preferred":[
        "Gretna Green"
    ],
    "name:ita_x_preferred":[
        "Gretna Green"
    ],
    "name:jpn_x_preferred":[
        "\u30b0\u30ec\u30c8\u30ca\u30fb\u30b0\u30ea\u30fc\u30f3"
    ],
    "name:kor_x_preferred":[
        "\uadf8\ub808\ud2b8\ub098\uadf8\ub9b0"
    ],
    "name:per_x_preferred":[
        "\u06af\u0631\u062a\u0646\u0627 \u06af\u0631\u06cc\u0646"
    ],
    "name:rus_x_preferred":[
        "\u0413\u0440\u0435\u0442\u043d\u0430-\u0413\u0440\u0438\u043d"
    ],
    "name:sco_x_preferred":[
        "Gretna Green"
    ],
    "name:spa_x_preferred":[
        "Gretna Green"
    ],
    "name:swe_x_preferred":[
        "Gretna Green"
    ],
    "qs_pg:aaroncc":"GB",
    "qs_pg:gn_country":"GB",
    "qs_pg:gn_fcode":"PPL",
    "qs_pg:gn_pop":0,
    "qs_pg:name":"Gretna Green",
    "qs_pg:name_adm0":"United Kingdom",
    "qs_pg:name_adm1":"Scotland",
    "qs_pg:photos":319,
    "qs_pg:photos_1k":65,
    "qs_pg:photos_9k":1,
    "qs_pg:photos_9r":5,
    "qs_pg:photos_all":319,
    "qs_pg:photos_sr":5,
    "qs_pg:pop_sr":0,
    "qs_pg:qs_pg_placetype":"locality",
    "qs_pg:qs_pg_placetype_gp":"Town",
    "qs_pg:woe_adm0":23424975,
    "woe:adm0_id":23424975,
    "woe:name_adm0":"United Kingdom",
    "woe:name_adm1":"Scotland",
    "woe:placetype":"Town",
    "wof:name":"Gretna Green",
    "wof:placetype":"locality"
},
  "geometry": {"coordinates":[-3.06618,55.00279],"type":"Point"}
}