{
  "type": "Feature",
  "properties": {
    "gn:country":"GB",
    "gn:fcode":"PPL",
    "gn:population":0,
    "iso:country":"GB",
    "name:deu_x_preferred":[
        "Old Deer"
    ],
    "name:eng_x_preferred":[
        "Old Deer"
    ],
    "name:eus_x_preferred":[
        "Old Deer"
    ],
    "name:fra_x_preferred":[
        "Old Deer"
    ],
    "name:gle_x_preferred":[
        "D\u00e9ir"
    ],
    "name:nld_x_preferred":[
        "Old Deer"
    ],
    "name:sco_x_preferred":[
        "Auld Deer"
    ],
    "qs_pg:aaroncc":"GB",
    "qs_pg:gn_country":"GB",
    "qs_pg:gn_fcode":"PPL",
    "qs_pg:gn_pop":0,
    "qs_pg:name":"Old Deer",
    "qs_pg:name_adm0":"United Kingdom",
    "qs_pg:name_adm1":"Scotland",
    "qs_pg:photos":719,
    "qs_pg:photos_1k":146,
    "qs_pg:photos_9k":3,
    "qs_pg:photos_9r":5,
    "qs_pg:photos_all":719,
    "qs_pg:photos_sr":8,
    "qs_pg:pop_sr":0,
    "qs_pg:qs_pg_placetype":"locality",
    "qs_pg:qs_pg_placetype_gp":"Town",
    "qs_pg:woe_adm0":23424975,
    "woe:adm0_id":23424975,
    "woe:name_adm0":"United Kingdom",
    "woe:name_adm1":"Scotland",
    "woe:placetype":"Town",
    "wof:name":"Old Deer",
    "wof:placetype":"locality"
},
  "geometry": {"coordinates":[-2.03771,57.51929],"type":"Point"}
}