{
  "type": "Feature",
  "properties": {
    "gn:admin1_code": "NIR",
    "gn:admin2_code": "N09000006",
    "gn:asciiname": "Scotch Town",
    "gn:country_code": "GB",
    "gn:dem": 159,
    "gn:feature_class": "P",
    "gn:feature_code": "PPL",
    "gn:name": "Scotch Town",
    "gn:population": 0,
    "gn:timezone": "Europe/London",
    "iso:country": "GB",
    "wof:name": "Scotch Town",
    "wof:placetype": "locality"
  },
  "geometry": {"coordinates":[-7.15,54.73333],"type":"Point"}
}
