{
  "type": "Feature",
  "properties": {
    "gn:country":"GB",
    "gn:fcode":"PPL",
    "gn:population":1796,
    "iso:country":"GB",
    "name:ceb_x_preferred":[
        "Brandiston"
    ],
    "name:cym_x_preferred":[
        "Brandiston"
    ],
    "name:nld_x_preferred":[
        "Brandiston"
    ],
    "name:pol_x_preferred":[
        "Brandiston"
    ],
    "name:swe_x_preferred":[
        "Brandiston"
    ],
    "name:und_x_variant":[
        "Briston"
    ],
    "qs_pg:aaroncc":"GB",
    "qs_pg:gn_country":"GB",
    "qs_pg:gn_fcode":"PPL",
    "qs_pg:gn_pop":1796,
    "qs_pg:name":"Brandiston",
    "qs_pg:name_adm0":"United Kingdom",
    "qs_pg:name_adm1":"England",
    "qs_pg:photos_9r":0,
    "qs_pg:photos_sr":0,
    "qs_pg:pop_sr":3,
    "qs_pg:qs_pg_placetype":"locality",
    "qs_pg:qs_pg_placetype_gp":"Town",
    "qs_pg:woe_adm0":23424975,
    "woe:adm0_id":23424975,
    "woe:name_adm0":"United Kingdom",
    "woe:name_adm1":"England",
    "woe:placetype":"Town",
    "wof:name":"Brandiston",
    "wof:placetype":"neighbourhood",
    "wof:population":3057
},
  "geometry": {"coordinates":[1.05899,52.85369],"type":"Point"}
}