{
  "type": "Feature",
  "properties": {
    "gn:country": "GB",
    "gn:fcode": "PPL",
    "gn:population": 0,
    "iso:country": "GB",
    "name:cym_x_preferred": [
      "Gartcosh"
    ],
    "name:eng_x_preferred": [
      "Gartcosh"
    ],
    "name:eus_x_preferred": [
      "Gartcosh"
    ],
    "name:fas_x_preferred": [
      "گارتکوش"
    ],
    "name:fra_x_preferred": [
      "Gartcosh"
    ],
    "name:gla_x_preferred": [
      "Gart Cois"
    ],
    "name:gle_x_preferred": [
      "Gart Cois"
    ],
    "name:ita_x_preferred": [
      "Gartcosh"
    ],
    "name:nld_x_preferred": [
      "Gartcosh"
    ],
    "name:spa_x_preferred": [
      "Gartcosh"
    ],
    "name:swe_x_preferred": [
      "Gartcosh"
    ],
    "qs_pg:aaroncc": "GB",
    "qs_pg:gn_country": "GB",
    "qs_pg:gn_fcode": "PPL",
    "qs_pg:gn_pop": 0,
    "qs_pg:name": "Gartcosh",
    "qs_pg:name_adm0": "United Kingdom",
    "qs_pg:name_adm1": "Scotland",
    "qs_pg:photos": 18,
    "qs_pg:photos_1k": 4,
    "qs_pg:photos_9k": 1,
    "qs_pg:photos_9r": 1,
    "qs_pg:photos_all": 18,
    "qs_pg:photos_sr": 1,
    "qs_pg:pop_sr": 0,
    "qs_pg:qs_pg_placetype": "locality",
    "qs_pg:qs_pg_placetype_gp": "Town",
    "qs_pg:woe_adm0": 23424975,
    "woe:adm0_id": 23424975,
    "woe:name_adm0": "United Kingdom",
    "woe:name_adm1": "Scotland",
    "woe:placetype": "Town",
    "wof:name": "Gartcosh",
    "wof:placetype": "locality",
    "wof:population": 2130
  },
  "geometry": {"coordinates":[-4.0817,55.88841],"type":"Point"}
}
