{
  "type": "Feature",
  "properties": {
    "iso:country":"GB",
    "name:cym_x_preferred":[
        "South Ascot"
    ],
    "name:eng_x_preferred":[
        "South Ascot"
    ],
    "name:fra_x_preferred":[
        "South Ascot"
    ],
    "name:gle_x_preferred":[
        "South Ascot"
    ],
    "name:jpn_x_preferred":[
        "\u30b5\u30a6\u30b9\u30fb\u30a2\u30b9\u30b3\u30c3\u30c8"
    ],
    "name:nld_x_preferred":[
        "South Ascot"
    ],
    "qs_pg:aaroncc":"GB",
    "qs_pg:name":"South Ascot",
    "qs_pg:name_adm0":"United Kingdom",
    "qs_pg:name_adm1":"England",
    "qs_pg:photos":46,
    "qs_pg:photos_1k":9,
    "qs_pg:photos_9k":1,
    "qs_pg:photos_9r":2,
    "qs_pg:photos_all":46,
    "qs_pg:photos_sr":2,
    "qs_pg:pop_sr":0,
    "qs_pg:qs_pg_placetype":"locality",
    "qs_pg:qs_pg_placetype_gp":"Town",
    "qs_pg:woe_adm0":23424975,
    "woe:adm0_id":23424975,
    "woe:name_adm0":"United Kingdom",
    "woe:name_adm1":"England",
    "woe:placetype":"Town",
    "wof:name":"South Ascot",
    "wof:placetype":"neighbourhood"
},
  "geometry": {"coordinates":[-0.667591,51.404399],"type":"Point"}
}