{
  "type": "Feature",
  "properties": {
    "iso:country": "GB",
    "name:eng_x_preferred": [
      "Wylde Green"
    ],
    "name:gle_x_preferred": [
      "Wylde Green"
    ],
    "qs:gn_adm0_cc": "GB",
    "qs:gn_fcode": "PPL",
    "qs:gn_local": 2636486,
    "qs:gn_nam_loc": "sutton coldfield",
    "qs:gn_namadm1": "ENG",
    "qs:gn_name": "Wylde Green",
    "qs:local_max": 2553,
    "qs:local_sum": 7617,
    "qs:localhoods": 7,
    "qs:name": "Wylde Green",
    "qs:name_adm0": "United Kingdom",
    "qs:name_adm1": "England",
    "qs:name_adm2": "West Midlands",
    "qs:name_lau": "Birmingham City",
    "qs:name_local": "Sutton Coldfield",
    "qs:photo_max": 230,
    "qs:photo_sum": 894,
    "qs:placetype": "Suburb",
    "qs:quad_count": 43,
    "qs:woe_adm0": 23424975,
    "qs:woe_adm1": 24554868,
    "qs:woe_adm2": 12602191,
    "qs:woe_lau": 12695863,
    "qs:woe_local": 36679,
    "qs:woe_ver": "7.10.0",
    "wd:wordcount": 611,
    "wof:lang": [
      "eng"
    ],
    "wof:name": "Wylde Green",
    "wof:placetype": "neighbourhood"
  },
  "geometry": {"coordinates":[-1.821878,52.540865],"type":"Point"}
}
