{
  "type": "Feature",
  "properties": {
    "gn:country":"GB",
    "gn:fcode":"PPL",
    "gn:population":0,
    "iso:country":"GB",
    "name:eng_x_preferred":[
        "Hartwood"
    ],
    "name:eus_x_preferred":[
        "Hartwood"
    ],
    "name:fra_x_preferred":[
        "Hartwood"
    ],
    "name:gla_x_preferred":[
        "Coille an Daimh"
    ],
    "name:gle_x_preferred":[
        "Coille an Daimh"
    ],
    "name:ita_x_preferred":[
        "Hartwood"
    ],
    "name:nld_x_preferred":[
        "Hartwood"
    ],
    "name:sco_x_preferred":[
        "Hertwid"
    ],
    "name:spa_x_preferred":[
        "Hartwood"
    ],
    "qs_pg:aaroncc":"GB",
    "qs_pg:gn_country":"GB",
    "qs_pg:gn_fcode":"PPL",
    "qs_pg:gn_pop":0,
    "qs_pg:name":"Hartwood",
    "qs_pg:name_adm0":"United Kingdom",
    "qs_pg:name_adm1":"Scotland",
    "qs_pg:photos":207,
    "qs_pg:photos_1k":42,
    "qs_pg:photos_9k":1,
    "qs_pg:photos_9r":4,
    "qs_pg:photos_all":207,
    "qs_pg:photos_sr":4,
    "qs_pg:pop_sr":0,
    "qs_pg:qs_pg_placetype":"locality",
    "qs_pg:qs_pg_placetype_gp":"Town",
    "qs_pg:woe_adm0":23424975,
    "woe:adm0_id":23424975,
    "woe:name_adm0":"United Kingdom",
    "woe:name_adm1":"Scotland",
    "woe:placetype":"Town",
    "wof:name":"Hartwood",
    "wof:placetype":"locality"
},
  "geometry": {"coordinates":[-3.83783,55.81127],"type":"Point"}
}