{
  "type": "Feature",
  "properties": {
    "iso:country":"GB",
    "name:deu_x_preferred":[
        "Heaton"
    ],
    "name:eng_x_preferred":[
        "Heaton"
    ],
    "name:fra_x_preferred":[
        "Heaton"
    ],
    "name:heb_x_preferred":[
        "\u05d4\u05d9\u05d8\u05d5\u05df"
    ],
    "name:pol_x_preferred":[
        "Heaton"
    ],
    "name:rus_x_preferred":[
        "\u0425\u0438\u0442\u043e\u043d"
    ],
    "name:swe_x_preferred":[
        "Heaton"
    ],
    "name:ukr_x_preferred":[
        "\u0413\u0456\u0442\u043e\u043d"
    ],
    "qs:gn_adm0_cc":"GB",
    "qs:gn_fcode":"PPLX",
    "qs:gn_local":2641673,
    "qs:gn_nam_loc":"Newcastle upon Tyne, England, GB",
    "qs:gn_namadm1":"ENG",
    "qs:gn_name":"Heaton",
    "qs:local_max":5187,
    "qs:local_sum":44051,
    "qs:localhoods":35,
    "qs:name":"Heaton",
    "qs:name_adm0":"United Kingdom",
    "qs:name_adm1":"England",
    "qs:name_adm2":"Tyne and Wear",
    "qs:name_lau":"Newcastle upon Tyne City",
    "qs:name_local":"Newcastle upon Tyne",
    "qs:photo_max":202,
    "qs:photo_sum":2491,
    "qs:placetype":"Suburb",
    "qs:quad_count":78,
    "qs:woe_adm0":23424975,
    "qs:woe_adm1":24554868,
    "qs:woe_adm2":12602156,
    "qs:woe_lau":12695859,
    "qs:woe_local":30079,
    "qs:woe_ver":"7.10.0",
    "wof:lang":[
        "eng"
    ],
    "wof:name":"Heaton",
    "wof:placetype":"neighbourhood"
},
  "geometry": {"coordinates":[-1.581619,54.98486],"type":"Point"}
}