{
  "type": "Feature",
  "properties": {
    "gn:admin1_code":"NIR",
    "gn:admin2_code":"N09000007",
    "gn:asciiname":"Ballinderry Upper",
    "gn:cc2":"GB",
    "gn:country_code":"GB",
    "gn:dem":59,
    "gn:feature_class":"P",
    "gn:feature_code":"PPL",
    "gn:name":"Ballinderry Upper",
    "gn:population":0,
    "gn:timezone":"Europe/London",
    "iso:country":"GB",
    "name:und_x_variant":[
        "Upper Ballinderry",
        "Ballinderry Upper"
    ],
    "wof:name":"Ballinderry Upper",
    "wof:placetype":"locality"
},
  "geometry": {"coordinates":[-6.21667,54.53333000000001],"type":"Point"}
}