{
  "type": "Feature",
  "properties": {
    "gn:admin1_code":"NIR",
    "gn:admin2_code":"N09000007",
    "gn:asciiname":"Ballinderry Upper",
    "gn:cc2":"GB",
    "gn:country_code":"GB",
    "gn:dem":59,
    "gn:feature_class":"P",
    "gn:feature_code":"PPL",
    "gn:name":"Ballinderry Upper",
    "gn:population":0,
    "gn:timezone":"Europe/London",
    "iso:country":"GB",
    "name:eus_x_preferred":[
        "Upper Ballinderry"
    ],
    "name:msa_x_preferred":[
        "Upper Ballinderry"
    ],
    "name:pli_x_preferred":[
        "\u0909\u092a\u094d\u092a\u0947\u0930 \u092c\u0932\u094d\u0932\u093f\u0928\u094d\u0926\u0947\u0930\u094d\u0930\u0940"
    ],
    "name:spa_x_preferred":[
        "Upper Ballinderry"
    ],
    "name:und_x_variant":[
        "Ballinderry Upper"
    ],
    "wof:name":"Ballinderry Upper",
    "wof:placetype":"locality"
},
  "geometry": {"coordinates":[-6.21667,54.53333000000001],"type":"Point"}
}