{
  "type": "Feature",
  "properties": {
    "gn:admin1_code":"ENG",
    "gn:admin2_code":"J6",
    "gn:admin3_code":"00EM095",
    "gn:asciiname":"Smeafield",
    "gn:country_code":"GB",
    "gn:dem":22,
    "gn:feature_class":"P",
    "gn:feature_code":"PPL",
    "gn:name":"Smeafield",
    "gn:population":0,
    "gn:timezone":"Europe/London",
    "iso:country":"GB",
    "wof:name":"Smeafield",
    "wof:placetype":"neighbourhood"
},
  "geometry": {"coordinates":[-1.85401,55.63224],"type":"Point"}
}