{
  "type": "Feature",
  "properties": {
    "iso:country":"GB",
    "name:arg_x_preferred":[
        "Hyde Park"
    ],
    "name:bar_x_preferred":[
        "Hyde Park"
    ],
    "name:bul_x_preferred":[
        "\u0425\u0430\u0439\u0434 \u041f\u0430\u0440\u043a"
    ],
    "name:ceb_x_preferred":[
        "Hyde Park"
    ],
    "name:ces_x_preferred":[
        "Hyde Park"
    ],
    "name:dan_x_preferred":[
        "Hyde Park"
    ],
    "name:deu_x_preferred":[
        "Hyde Park"
    ],
    "name:epo_x_preferred":[
        "Hyde Park"
    ],
    "name:fra_x_preferred":[
        "Hyde Park"
    ],
    "name:heb_x_preferred":[
        "\u05d4\u05d9\u05d9\u05d3 \u05e4\u05d0\u05e8\u05e7"
    ],
    "name:ita_x_preferred":[
        "Hyde Park"
    ],
    "name:kor_x_preferred":[
        "\ud558\uc774\ub4dc \ud30c\ud06c"
    ],
    "name:msa_x_preferred":[
        "Taman Hyde"
    ],
    "name:nld_x_preferred":[
        "Hyde Park"
    ],
    "name:nor_x_preferred":[
        "Hyde Park"
    ],
    "name:pol_x_preferred":[
        "Hyde Park"
    ],
    "name:por_x_preferred":[
        "Hyde Park"
    ],
    "name:rus_x_preferred":[
        "\u0413\u0430\u0439\u0434-\u043f\u0430\u0440\u043a"
    ],
    "name:slk_x_preferred":[
        "Hyde Park"
    ],
    "name:spa_x_preferred":[
        "Hyde Park"
    ],
    "name:srp_x_preferred":[
        "\u0425\u0430\u0458\u0434 \u041f\u0430\u0440\u043a"
    ],
    "name:swe_x_preferred":[
        "Hyde Park"
    ],
    "name:ukr_x_preferred":[
        "\u0413\u0430\u0439\u0434-\u043f\u0430\u0440\u043a"
    ],
    "name:vol_x_preferred":[
        "Hyde Park"
    ],
    "name:zho_x_preferred":[
        "\u6d77\u5fb7\u516c\u56ed"
    ],
    "wof:name":"Hyde Park",
    "wof:placetype":"neighbourhood"
},
  "geometry": {"coordinates":[-1.56732472757545,53.81290555163742],"type":"Point"}
}