{
  "type": "Feature",
  "properties": {
    "iso:country": "GB",
    "name:arg_x_preferred": [
      "Hyde Park"
    ],
    "name:bar_x_preferred": [
      "Hyde Park"
    ],
    "name:bul_x_preferred": [
      "Хайд Парк"
    ],
    "name:ceb_x_preferred": [
      "Hyde Park"
    ],
    "name:ces_x_preferred": [
      "Hyde Park"
    ],
    "name:dan_x_preferred": [
      "Hyde Park"
    ],
    "name:deu_x_preferred": [
      "Hyde Park"
    ],
    "name:epo_x_preferred": [
      "Hyde Park"
    ],
    "name:fra_x_preferred": [
      "Hyde Park"
    ],
    "name:heb_x_preferred": [
      "הייד פארק"
    ],
    "name:ita_x_preferred": [
      "Hyde Park"
    ],
    "name:kor_x_preferred": [
      "하이드 파크"
    ],
    "name:msa_x_preferred": [
      "Taman Hyde"
    ],
    "name:nld_x_preferred": [
      "Hyde Park"
    ],
    "name:nor_x_preferred": [
      "Hyde Park"
    ],
    "name:pol_x_preferred": [
      "Hyde Park"
    ],
    "name:por_x_preferred": [
      "Hyde Park"
    ],
    "name:rus_x_preferred": [
      "Гайд-парк"
    ],
    "name:slk_x_preferred": [
      "Hyde Park"
    ],
    "name:spa_x_preferred": [
      "Hyde Park"
    ],
    "name:srp_x_preferred": [
      "Хајд Парк"
    ],
    "name:swe_x_preferred": [
      "Hyde Park"
    ],
    "name:ukr_x_preferred": [
      "Гайд-парк"
    ],
    "name:vol_x_preferred": [
      "Hyde Park"
    ],
    "name:zho_x_preferred": [
      "海德公园"
    ],
    "wof:name": "Hyde Park",
    "wof:placetype": "neighbourhood"
  },
  "geometry": {"coordinates":[-1.56732472757545,53.81290555163742],"type":"Point"}
}
