{
  "type": "Feature",
  "properties": {
    "iso:country":"GB",
    "wof:name":"Hyde Park",
    "wof:placetype":"neighbourhood"
},
  "geometry": {"coordinates":[-1.56732472757545,53.81290555163742],"type":"Point"}
}