{
  "type": "Feature",
  "properties": {
    "gn:country":"GB",
    "gn:fcode":"PPL",
    "gn:population":0,
    "iso:country":"GB",
    "name:ara_x_preferred":[
        "\u0645\u0648 \u0643\u0622\u0628"
    ],
    "name:cym_x_preferred":[
        "Mow Cop"
    ],
    "name:eng_x_preferred":[
        "Mow Cop"
    ],
    "name:fra_x_preferred":[
        "Mow Cop"
    ],
    "name:nld_x_preferred":[
        "Mow Cop"
    ],
    "name:pol_x_preferred":[
        "Mow Cop"
    ],
    "qs_pg:aaroncc":"GB",
    "qs_pg:gn_country":"GB",
    "qs_pg:gn_fcode":"PPL",
    "qs_pg:gn_pop":0,
    "qs_pg:name":"Mow Cop",
    "qs_pg:name_adm0":"United Kingdom",
    "qs_pg:name_adm1":"England",
    "qs_pg:photos":763,
    "qs_pg:photos_1k":155,
    "qs_pg:photos_9k":3,
    "qs_pg:photos_9r":6,
    "qs_pg:photos_all":763,
    "qs_pg:photos_sr":9,
    "qs_pg:pop_sr":0,
    "qs_pg:qs_pg_placetype":"locality",
    "qs_pg:qs_pg_placetype_gp":"Town",
    "qs_pg:woe_adm0":23424975,
    "woe:adm0_id":23424975,
    "woe:name_adm0":"United Kingdom",
    "woe:name_adm1":"England",
    "woe:placetype":"Town",
    "wof:name":"Mow Cop",
    "wof:placetype":"neighbourhood"
},
  "geometry": {"coordinates":[-2.21657,53.11125],"type":"Point"}
}