{
  "type": "Feature",
  "properties": {
    "iso:country": "GB",
    "name:eng_x_preferred": [
      "Thurnby Lodge"
    ],
    "wof:name": "Thurnby Lodge",
    "wof:placetype": "neighbourhood"
  },
  "geometry": {"coordinates":[-1.06052879037354,52.63874776043222],"type":"Point"}
}
