{
  "type": "Feature",
  "properties": {
    "gn:admin1_code":"ENG",
    "gn:admin2_code":"M3",
    "gn:admin3_code":"40UD",
    "gn:admin4_code":"40UD107",
    "gn:asciiname":"Higher Wambrook",
    "gn:country_code":"GB",
    "gn:dem":183,
    "gn:feature_class":"P",
    "gn:feature_code":"PPL",
    "gn:name":"Higher Wambrook",
    "gn:population":0,
    "gn:timezone":"Europe/London",
    "iso:country":"GB",
    "wof:name":"Higher Wambrook",
    "wof:placetype":"neighbourhood"
},
  "geometry": {"coordinates":[-3.00684,50.8712],"type":"Point"}
}