{
  "type": "Feature",
  "properties": {
    "gn:admin1_code": "WLS",
    "gn:admin2_code": "Z3",
    "gn:admin3_code": "00PD019",
    "gn:asciiname": "Eglwys-Brewis",
    "gn:country_code": "GB",
    "gn:dem": 49,
    "gn:feature_class": "P",
    "gn:feature_code": "PPL",
    "gn:name": "Eglwys-Brewis",
    "gn:population": 0,
    "gn:timezone": "Europe/London",
    "iso:country": "GB",
    "wof:name": "Eglwys-Brewis",
    "wof:placetype": "neighbourhood"
  },
  "geometry": {"coordinates":[-3.41694,51.41389],"type":"Point"}
}
