{
  "type": "Feature",
  "properties": {
    "gn:admin1_code":"ENG",
    "gn:admin2_code":"H7",
    "gn:admin3_code":"32UF",
    "gn:admin4_code":"32UF019",
    "gn:asciiname":"Sutton Saint James",
    "gn:country_code":"GB",
    "gn:dem":3,
    "gn:feature_class":"P",
    "gn:feature_code":"PPL",
    "gn:name":"Sutton Saint James",
    "gn:population":0,
    "gn:timezone":"Europe/London",
    "iso:country":"GB",
    "wof:name":"Sutton Saint James",
    "wof:placetype":"neighbourhood"
},
  "geometry": {"coordinates":[0.06472,52.74419],"type":"Point"}
}