{
  "type": "Feature",
  "properties": {
    "gn:population":4321,
    "iso:country":"GB",
    "name:ceb_x_preferred":[
        "West Kilbride"
    ],
    "name:cym_x_preferred":[
        "West Kilbride"
    ],
    "name:deu_x_preferred":[
        "West Kilbride"
    ],
    "name:dut_x_preferred":[
        "West Kilbride"
    ],
    "name:eng_x_preferred":[
        "West Kilbride"
    ],
    "name:fre_x_preferred":[
        "West Kilbride"
    ],
    "name:ger_x_preferred":[
        "West Kilbride"
    ],
    "name:gla_x_preferred":[
        "Cille Bhr\u00ecghde an Iar"
    ],
    "name:gle_x_preferred":[
        "Cille Bhr\u00edghde an Iar"
    ],
    "name:jpn_x_preferred":[
        "\u30a6\u30a8\u30b9\u30c8\u30fb\u30ad\u30eb\u30d6\u30e9\u30a4\u30c9"
    ],
    "name:pol_x_preferred":[
        "West Kilbride"
    ],
    "name:sco_x_preferred":[
        "Wast Kilbride"
    ],
    "name:swe_x_preferred":[
        "West Kilbride"
    ],
    "name:wel_x_preferred":[
        "West Kilbride"
    ],
    "qs:a0":"United Kingdom",
    "qs:a1":"*North Ayrshire",
    "qs:a1_lc":"GB11QY0000",
    "qs:a1r":"0Scotland",
    "qs:a1r_lc":"GB11000000",
    "qs:adm0":"United Kingdom",
    "qs:la_lc":"*",
    "qs:level":"locality",
    "qs:loc":"West Kilbride",
    "qs:loc_alt":"West Kilbride",
    "qs:pop":0,
    "qs:type":"buffered point",
    "wd:wordcount":3686,
    "wof:name":"West Kilbride",
    "wof:placetype":"locality",
    "wof:population":4321
},
  "geometry": {"coordinates":[-4.862414,55.687974],"type":"Point"}
}