{
  "type": "Feature",
  "properties": {
    "iso:country":"GB",
    "name:cym_x_preferred":[
        "Friog"
    ],
    "name:eng_x_preferred":[
        "Friog"
    ],
    "name:eus_x_preferred":[
        "Friog"
    ],
    "name:fra_x_preferred":[
        "Friog"
    ],
    "name:gle_x_preferred":[
        "Friog"
    ],
    "name:nld_x_preferred":[
        "Friog"
    ],
    "qs_pg:aaroncc":"GB",
    "qs_pg:name":"Friog",
    "qs_pg:name_adm0":"United Kingdom",
    "qs_pg:name_adm1":"Wales",
    "qs_pg:photos":58,
    "qs_pg:photos_1k":12,
    "qs_pg:photos_9k":1,
    "qs_pg:photos_9r":2,
    "qs_pg:photos_all":58,
    "qs_pg:photos_sr":2,
    "qs_pg:pop_sr":0,
    "qs_pg:qs_pg_placetype":"locality",
    "qs_pg:qs_pg_placetype_gp":"Town",
    "qs_pg:woe_adm0":23424975,
    "woe:adm0_id":23424975,
    "woe:name_adm0":"United Kingdom",
    "woe:name_adm1":"Wales",
    "woe:placetype":"Town",
    "wof:name":"Friog",
    "wof:placetype":"neighbourhood"
},
  "geometry": {"coordinates":[-4.044824,52.691575],"type":"Point"}
}