{
  "type": "Feature",
  "properties": {
    "gn:admin1_code": "ENG",
    "gn:admin2_code": "I9",
    "gn:admin3_code": "33UF",
    "gn:admin4_code": "33UF033",
    "gn:asciiname": "Croxton",
    "gn:country_code": "GB",
    "gn:dem": 66,
    "gn:feature_class": "P",
    "gn:feature_code": "PPL",
    "gn:name": "Croxton",
    "gn:population": 0,
    "gn:timezone": "Europe/London",
    "iso:country": "GB",
    "name:ceb_x_preferred": [
      "Croxton"
    ],
    "name:deu_x_preferred": [
      "Croxton"
    ],
    "name:fra_x_preferred": [
      "Croxton"
    ],
    "name:nld_x_preferred": [
      "Croxton"
    ],
    "name:pol_x_preferred": [
      "Croxton"
    ],
    "name:swe_x_preferred": [
      "Croxton"
    ],
    "wof:name": "Croxton",
    "wof:placetype": "neighbourhood"
  },
  "geometry": {"coordinates":[0.95,52.85],"type":"Point"}
}
