{
  "type": "Feature",
  "properties": {
    "gn:admin1_code":"ENG",
    "gn:admin2_code":"H7",
    "gn:admin3_code":"32UC",
    "gn:admin4_code":"32UC044",
    "gn:asciiname":"Edlington",
    "gn:country_code":"GB",
    "gn:dem":65,
    "gn:feature_class":"P",
    "gn:feature_code":"PPL",
    "gn:name":"Edlington",
    "gn:population":0,
    "gn:timezone":"Europe/London",
    "iso:country":"GB",
    "name:ceb_x_preferred":[
        "Edlington"
    ],
    "name:cym_x_preferred":[
        "Edlington"
    ],
    "name:pol_x_preferred":[
        "Edlington"
    ],
    "name:swe_x_preferred":[
        "Edlington"
    ],
    "wof:name":"Edlington",
    "wof:placetype":"neighbourhood"
},
  "geometry": {"coordinates":[-0.15286,53.22785],"type":"Point"}
}