{
  "type": "Feature",
  "properties": {
    "gn:country": "GB",
    "gn:fcode": "PPL",
    "gn:population": 499,
    "iso:country": "GB",
    "name:bre_x_preferred": [
      "Cille Chuimein"
    ],
    "name:cat_x_preferred": [
      "Fort August"
    ],
    "name:ceb_x_preferred": [
      "Fort Augustus"
    ],
    "name:ces_x_preferred": [
      "Fort Augustus"
    ],
    "name:cym_x_preferred": [
      "Fort Augustus"
    ],
    "name:deu_x_preferred": [
      "Fort Augustus"
    ],
    "name:eng_x_preferred": [
      "Fort Augustus"
    ],
    "name:eus_x_preferred": [
      "Fort Augustus"
    ],
    "name:fra_x_preferred": [
      "Fort Augustus"
    ],
    "name:gla_x_preferred": [
      "Cille Chuimein"
    ],
    "name:gle_x_preferred": [
      "Cille Chuimein"
    ],
    "name:ita_x_preferred": [
      "Forte Augusto"
    ],
    "name:jpn_x_preferred": [
      "フォート・オーガスタス"
    ],
    "name:nld_x_preferred": [
      "Fort Augustus"
    ],
    "name:nno_x_preferred": [
      "Fort Augustus"
    ],
    "name:nob_x_preferred": [
      "Fort Augustus"
    ],
    "name:pol_x_preferred": [
      "fort augustus"
    ],
    "name:rus_x_preferred": [
      "Форт-Огастус"
    ],
    "name:spa_x_preferred": [
      "Fuerte Augusto"
    ],
    "name:swe_x_preferred": [
      "Fort Augustus"
    ],
    "name:zho_x_preferred": [
      "奧古斯都堡"
    ],
    "qs_pg:aaroncc": "GB",
    "qs_pg:gn_country": "GB",
    "qs_pg:gn_fcode": "PPL",
    "qs_pg:gn_pop": 499,
    "qs_pg:name": "Fort Augustus",
    "qs_pg:name_adm0": "United Kingdom",
    "qs_pg:name_adm1": "Scotland",
    "qs_pg:photos": 3952,
    "qs_pg:photos_1k": 801,
    "qs_pg:photos_9k": 18,
    "qs_pg:photos_9r": 12,
    "qs_pg:photos_all": 3952,
    "qs_pg:photos_sr": 22,
    "qs_pg:pop_sr": 2,
    "qs_pg:qs_pg_placetype": "locality",
    "qs_pg:qs_pg_placetype_gp": "Town",
    "qs_pg:woe_adm0": 23424975,
    "woe:adm0_id": 23424975,
    "woe:name_adm0": "United Kingdom",
    "woe:name_adm1": "Scotland",
    "woe:placetype": "Town",
    "wof:name": "Fort Augustus",
    "wof:placetype": "locality",
    "wof:population": 670
  },
  "geometry": {"coordinates":[-4.68224,57.14313],"type":"Point"}
}
