{
  "type": "Feature",
  "properties": {
    "iso:country":"GB",
    "name:cym_x_preferred":[
        "Releath"
    ],
    "name:eng_x_preferred":[
        "Releath"
    ],
    "name:eus_x_preferred":[
        "Releath"
    ],
    "name:fra_x_preferred":[
        "Releath"
    ],
    "name:nld_x_preferred":[
        "Releath"
    ],
    "qs_pg:aaroncc":"GB",
    "qs_pg:name":"Releath",
    "qs_pg:name_adm0":"United Kingdom",
    "qs_pg:name_adm1":"England",
    "qs_pg:photos":108,
    "qs_pg:photos_1k":22,
    "qs_pg:photos_9k":1,
    "qs_pg:photos_9r":3,
    "qs_pg:photos_all":108,
    "qs_pg:photos_sr":3,
    "qs_pg:pop_sr":0,
    "qs_pg:qs_pg_placetype":"locality",
    "qs_pg:qs_pg_placetype_gp":"Town",
    "qs_pg:woe_adm0":23424975,
    "woe:adm0_id":23424975,
    "woe:name_adm0":"United Kingdom",
    "woe:name_adm1":"England",
    "woe:placetype":"Town",
    "wof:name":"Releath",
    "wof:placetype":"neighbourhood"
},
  "geometry": {"coordinates":[-5.302104,50.127951],"type":"Point"}
}