{
  "type": "Feature",
  "properties": {
    "gn:country": "GB",
    "gn:fcode": "PPL",
    "gn:population": 2187,
    "iso:country": "GB",
    "name:azb_x_preferred": [
      "آرتینقتون"
    ],
    "name:ceb_x_preferred": [
      "Artington"
    ],
    "name:fas_x_preferred": [
      "واتلینگتون، آکسفوردشر"
    ],
    "name:fas_x_variant": [
      "آرتینگتون"
    ],
    "name:pol_x_preferred": [
      "Artington"
    ],
    "name:swe_x_preferred": [
      "Artington"
    ],
    "qs_pg:aaroncc": "GB",
    "qs_pg:gn_country": "GB",
    "qs_pg:gn_fcode": "PPL",
    "qs_pg:gn_pop": 2187,
    "qs_pg:name": "Artington",
    "qs_pg:name_adm0": "United Kingdom",
    "qs_pg:name_adm1": "England",
    "qs_pg:photos": 38,
    "qs_pg:photos_1k": 8,
    "qs_pg:photos_9k": 1,
    "qs_pg:photos_9r": 2,
    "qs_pg:photos_all": 38,
    "qs_pg:photos_sr": 2,
    "qs_pg:pop_sr": 4,
    "qs_pg:qs_pg_placetype": "locality",
    "qs_pg:qs_pg_placetype_gp": "Town",
    "qs_pg:woe_adm0": 23424975,
    "woe:adm0_id": 23424975,
    "woe:name_adm0": "United Kingdom",
    "woe:name_adm1": "England",
    "woe:placetype": "Town",
    "wof:name": "Artington",
    "wof:placetype": "neighbourhood",
    "wof:population": 2187
  },
  "geometry": {"coordinates":[-1.00448,51.64327],"type":"Point"}
}
