{
  "type": "Feature",
  "properties": {
    "gn:gn_country":"GB",
    "gn:gn_fcode":"PPL",
    "gn:gn_pop":2187,
    "gn:population":2187,
    "iso:country":"GB",
    "name:fas_x_preferred":[
        "\u0648\u0627\u062a\u0644\u06cc\u0646\u06af\u062a\u0648\u0646\u060c \u0622\u06a9\u0633\u0641\u0648\u0631\u062f\u0634\u0631"
    ],
    "qs_pg:aaroncc":"GB",
    "qs_pg:gn_country":"GB",
    "qs_pg:gn_fcode":"PPL",
    "qs_pg:gn_pop":2187,
    "qs_pg:name":"Artington",
    "qs_pg:name_adm0":"United Kingdom",
    "qs_pg:name_adm1":"England",
    "qs_pg:photos":38,
    "qs_pg:photos_1k":8,
    "qs_pg:photos_9k":1,
    "qs_pg:photos_9r":2,
    "qs_pg:photos_all":38,
    "qs_pg:photos_sr":2,
    "qs_pg:pop_sr":4,
    "qs_pg:qs_pg_placetype":"locality",
    "qs_pg:qs_pg_placetype_gp":"Town",
    "qs_pg:woe_adm0":23424975,
    "woe:adm0_id":23424975,
    "woe:name_adm0":"United Kingdom",
    "woe:name_adm1":"England",
    "woe:placetype":"Town",
    "wof:name":"Artington",
    "wof:placetype":"neighbourhood",
    "wof:population":2187
},
  "geometry": {"coordinates":[-1.00448,51.64327],"type":"Point"}
}