{
  "type": "Feature",
  "properties": {
    "gn:country":"GB",
    "gn:fcode":"PPL",
    "gn:population":5507,
    "iso:country":"GB",
    "name:bul_x_preferred":[
        "\u0427\u0430\u043f\u0435\u043b\u0445\u0430\u043b"
    ],
    "name:ceb_x_preferred":[
        "Chapelhall"
    ],
    "name:eng_x_preferred":[
        "Chapelhall"
    ],
    "name:eus_x_preferred":[
        "Chapelhall"
    ],
    "name:fra_x_preferred":[
        "Chapelhall"
    ],
    "name:nld_x_preferred":[
        "Chapelhall"
    ],
    "name:spa_x_preferred":[
        "Chapelhall"
    ],
    "name:swe_x_preferred":[
        "Chapelhall"
    ],
    "qs_pg:aaroncc":"GB",
    "qs_pg:gn_country":"GB",
    "qs_pg:gn_fcode":"PPL",
    "qs_pg:gn_pop":5507,
    "qs_pg:name":"Chapelhill",
    "qs_pg:name_adm0":"United Kingdom",
    "qs_pg:name_adm1":"Scotland",
    "qs_pg:photos":125,
    "qs_pg:photos_1k":25,
    "qs_pg:photos_9k":1,
    "qs_pg:photos_9r":3,
    "qs_pg:photos_all":125,
    "qs_pg:photos_sr":3,
    "qs_pg:pop_sr":5,
    "qs_pg:qs_pg_placetype":"locality",
    "qs_pg:qs_pg_placetype_gp":"Town",
    "qs_pg:woe_adm0":23424975,
    "woe:adm0_id":23424975,
    "woe:name_adm0":"United Kingdom",
    "woe:name_adm1":"Scotland",
    "woe:placetype":"Town",
    "wof:name":"Chapelhill",
    "wof:placetype":"locality",
    "wof:population":6560
},
  "geometry": {"coordinates":[-3.94881,55.84349],"type":"Point"}
}