{
  "type": "Feature",
  "properties": {
    "gn:admin1_code":"SCT",
    "gn:admin2_code":"T6",
    "gn:asciiname":"Tavelty",
    "gn:country_code":"GB",
    "gn:dem":52,
    "gn:feature_class":"P",
    "gn:feature_code":"PPLL",
    "gn:name":"Tavelty",
    "gn:population":0,
    "gn:timezone":"Europe/London",
    "iso:country":"GB",
    "wof:name":"Tavelty",
    "wof:placetype":"locality"
},
  "geometry": {"coordinates":[-2.34953,57.24455],"type":"Point"}
}