{
  "type": "Feature",
  "properties": {
    "iso:country":"GB",
    "name:cym_x_preferred":[
        "South Darenth"
    ],
    "name:eng_x_preferred":[
        "South Darenth"
    ],
    "name:fra_x_preferred":[
        "South Darenth"
    ],
    "name:nld_x_preferred":[
        "South Darenth"
    ],
    "name:pol_x_preferred":[
        "South Darenth"
    ],
    "name:spa_x_preferred":[
        "South Darenth"
    ],
    "qs_pg:aaroncc":"GB",
    "qs_pg:name":"South Darenth",
    "qs_pg:name_adm0":"United Kingdom",
    "qs_pg:name_adm1":"England",
    "qs_pg:photos":1621,
    "qs_pg:photos_1k":328,
    "qs_pg:photos_9k":7,
    "qs_pg:photos_9r":8,
    "qs_pg:photos_all":1621,
    "qs_pg:photos_sr":13,
    "qs_pg:pop_sr":0,
    "qs_pg:qs_pg_placetype":"locality",
    "qs_pg:qs_pg_placetype_gp":"Town",
    "qs_pg:woe_adm0":23424975,
    "woe:adm0_id":23424975,
    "woe:name_adm0":"United Kingdom",
    "woe:name_adm1":"England",
    "woe:placetype":"Town",
    "wof:name":"South Darenth",
    "wof:placetype":"neighbourhood"
},
  "geometry": {"coordinates":[0.26144,51.359723],"type":"Point"}
}