{
  "type": "Feature",
  "properties": {
    "iso:country":"GB",
    "name:aze_x_preferred":[
        "Lendport"
    ],
    "name:bel_x_preferred":[
        "\u041b\u0435\u043d\u0434\u043f\u0430\u0440\u0442"
    ],
    "name:bul_x_preferred":[
        "\u041b\u0435\u043d\u0434\u043f\u043e\u0440\u0442"
    ],
    "name:cat_x_preferred":[
        "Landport"
    ],
    "name:deu_x_preferred":[
        "Landport"
    ],
    "name:eng_x_preferred":[
        "Landport"
    ],
    "name:epo_x_preferred":[
        "Landport"
    ],
    "name:fas_x_preferred":[
        "\u0644\u0646\u062f\u067e\u0648\u0631\u062a"
    ],
    "name:fra_x_preferred":[
        "Landport"
    ],
    "name:gle_x_preferred":[
        "Landport"
    ],
    "name:heb_x_preferred":[
        "\u05dc\u05e0\u05d3\u05e4\u05d5\u05e8\u05d8"
    ],
    "name:ita_x_preferred":[
        "Landport"
    ],
    "name:kat_x_preferred":[
        "\u10da\u10d4\u10dc\u10d3\u10de\u10dd\u10e0\u10e2\u10d8"
    ],
    "name:ltz_x_preferred":[
        "Landport"
    ],
    "name:nld_x_preferred":[
        "Landport"
    ],
    "name:por_x_preferred":[
        "Landport"
    ],
    "name:rus_x_preferred":[
        "\u041b\u0435\u043d\u0434\u043f\u043e\u0440\u0442"
    ],
    "name:sin_x_preferred":[
        "\u0dbd\u0dd1\u0db1\u0dca\u0da9\u0dca\u0db4\u0ddd\u0dbb\u0dca\u0da7\u0dca"
    ],
    "qs:gn_fcode":"PPLX",
    "qs:gn_local":0,
    "qs:gn_namadm1":"ENG",
    "qs:gn_name":"Landport",
    "qs:local_max":5349,
    "qs:local_sum":51768,
    "qs:localhoods":25,
    "qs:name":"Landport",
    "qs:name_adm0":"United Kingdom",
    "qs:name_adm1":"England",
    "qs:name_adm2":"Hampshire",
    "qs:name_lau":"Portsmouth City",
    "qs:name_local":"Portsmouth",
    "qs:photo_max":118,
    "qs:photo_sum":569,
    "qs:placetype":"Suburb",
    "qs:quad_count":22,
    "qs:woe_adm0":23424975,
    "qs:woe_adm1":24554868,
    "qs:woe_adm2":12602169,
    "qs:woe_lau":12696158,
    "qs:woe_local":32452,
    "qs:woe_ver":"7.10.0",
    "wd:wordcount":208,
    "wof:lang":[
        "eng"
    ],
    "wof:name":"Landport",
    "wof:placetype":"neighbourhood"
},
  "geometry": {"coordinates":[-1.102337,50.809989],"type":"Point"}
}