{
  "type": "Feature",
  "properties": {
    "gn:admin1_code":"SCT",
    "gn:admin2_code":"T6",
    "gn:asciiname":"Schivas",
    "gn:country_code":"GB",
    "gn:dem":59,
    "gn:feature_class":"P",
    "gn:feature_code":"PPL",
    "gn:name":"Schivas",
    "gn:population":0,
    "gn:timezone":"Europe/London",
    "iso:country":"GB",
    "wof:name":"Schivas",
    "wof:placetype":"locality"
},
  "geometry": {"coordinates":[-2.16667,57.41667],"type":"Point"}
}