{
  "type": "Feature",
  "properties": {
    "iso:country":"GB",
    "qs_pg:aaroncc":"GB",
    "qs_pg:name":"Agivey",
    "qs_pg:name_adm0":"United Kingdom",
    "qs_pg:name_adm1":"Northern Ireland",
    "qs_pg:photos":150,
    "qs_pg:photos_1k":30,
    "qs_pg:photos_9k":1,
    "qs_pg:photos_9r":3,
    "qs_pg:photos_all":150,
    "qs_pg:photos_sr":3,
    "qs_pg:pop_sr":0,
    "qs_pg:qs_pg_placetype":"locality",
    "qs_pg:qs_pg_placetype_gp":"Town",
    "qs_pg:woe_adm0":23424975,
    "woe:adm0_id":23424975,
    "woe:name_adm0":"United Kingdom",
    "woe:name_adm1":"Northern Ireland",
    "woe:placetype":"Town",
    "wof:name":"Agivey",
    "wof:placetype":"locality"
},
  "geometry": {"coordinates":[-6.566219,55.041604],"type":"Point"}
}