{
  "type": "Feature",
  "properties": {
    "gn:admin1_code":"NIR",
    "gn:admin2_code":"N09000006",
    "gn:asciiname":"Ballagh Cross Roads",
    "gn:cc2":"GB",
    "gn:country_code":"GB",
    "gn:dem":88,
    "gn:feature_class":"P",
    "gn:feature_code":"PPL",
    "gn:name":"Ballagh Cross Roads",
    "gn:population":0,
    "gn:timezone":"Europe/London",
    "iso:country":"GB",
    "name:und_x_variant":[
        "Ballagh",
        "Ballagh Cross Roads"
    ],
    "wof:name":"Ballagh Cross Roads",
    "wof:placetype":"locality"
},
  "geometry": {"coordinates":[-7.33333,54.21666999999999],"type":"Point"}
}