{
  "type": "Feature",
  "properties": {
    "iso:country":"GB",
    "name:ces_x_preferred":[
        "Ettrick"
    ],
    "name:eng_x_preferred":[
        "Ettrick"
    ],
    "name:eus_x_preferred":[
        "Ettrick"
    ],
    "name:fas_x_preferred":[
        "\u0627\u062a\u0631\u06cc\u06a9"
    ],
    "name:fra_x_preferred":[
        "Ettrick"
    ],
    "name:gla_x_preferred":[
        "Eadaraig"
    ],
    "name:gle_x_preferred":[
        "Eadaraig"
    ],
    "name:hun_x_preferred":[
        "Ettrick"
    ],
    "name:ita_x_preferred":[
        "Ettrick"
    ],
    "name:jpn_x_preferred":[
        "\u30a8\u30c8\u30ea\u30c3\u30af"
    ],
    "name:nld_x_preferred":[
        "Ettrick"
    ],
    "name:rus_x_preferred":[
        "\u042d\u0442\u0440\u0438\u043a"
    ],
    "name:sco_x_preferred":[
        "Ettrick"
    ],
    "qs_pg:aaroncc":"GB",
    "qs_pg:name":"Ettrick",
    "qs_pg:name_adm0":"United Kingdom",
    "qs_pg:name_adm1":"Scotland",
    "qs_pg:photos":103,
    "qs_pg:photos_1k":21,
    "qs_pg:photos_9k":1,
    "qs_pg:photos_9r":3,
    "qs_pg:photos_all":103,
    "qs_pg:photos_sr":3,
    "qs_pg:pop_sr":0,
    "qs_pg:qs_pg_placetype":"locality",
    "qs_pg:qs_pg_placetype_gp":"Town",
    "qs_pg:woe_adm0":23424975,
    "woe:adm0_id":23424975,
    "woe:name_adm0":"United Kingdom",
    "woe:name_adm1":"Scotland",
    "woe:placetype":"Town",
    "wof:name":"Ettrick",
    "wof:placetype":"locality"
},
  "geometry": {"coordinates":[-3.159032,55.417323],"type":"Point"}
}