{
  "type": "Feature",
  "properties": {
    "gn:country": "GB",
    "gn:fcode": "PPL",
    "gn:population": 0,
    "iso:country": "GB",
    "name:cym_x_preferred": [
      "Thorpe Waterville"
    ],
    "name:eng_x_preferred": [
      "Thorpe Waterville"
    ],
    "name:fra_x_preferred": [
      "Thorpe Waterville"
    ],
    "name:nld_x_preferred": [
      "Thorpe Waterville"
    ],
    "name:pol_x_preferred": [
      "Thorpe Waterville"
    ],
    "name:swe_x_preferred": [
      "Thorpe Waterville"
    ],
    "name:und_x_variant": [
      "Thorpe"
    ],
    "qs_pg:aaroncc": "GB",
    "qs_pg:gn_country": "GB",
    "qs_pg:gn_fcode": "PPL",
    "qs_pg:gn_pop": 0,
    "qs_pg:name": "Thorpe Waterville",
    "qs_pg:name_adm0": "United Kingdom",
    "qs_pg:name_adm1": "England",
    "qs_pg:photos": 65,
    "qs_pg:photos_1k": 13,
    "qs_pg:photos_9k": 1,
    "qs_pg:photos_9r": 2,
    "qs_pg:photos_all": 65,
    "qs_pg:photos_sr": 2,
    "qs_pg:pop_sr": 0,
    "qs_pg:qs_pg_placetype": "locality",
    "qs_pg:qs_pg_placetype_gp": "Town",
    "qs_pg:woe_adm0": 23424975,
    "woe:adm0_id": 23424975,
    "woe:name_adm0": "United Kingdom",
    "woe:name_adm1": "England",
    "woe:placetype": "Town",
    "wof:name": "Thorpe Waterville",
    "wof:placetype": "neighbourhood"
  },
  "geometry": {"coordinates":[-0.49498,52.42203],"type":"Point"}
}
