{
  "type": "Feature",
  "properties": {
    "gn:country":"GB",
    "gn:fcode":"PPL",
    "gn:population":0,
    "iso:country":"GB",
    "name:cym_x_preferred":[
        "Matfield"
    ],
    "name:eng_x_preferred":[
        "Matfield"
    ],
    "name:fra_x_preferred":[
        "Matfield"
    ],
    "name:gle_x_preferred":[
        "Matfield"
    ],
    "name:ita_x_preferred":[
        "Matfield"
    ],
    "name:nld_x_preferred":[
        "Matfield"
    ],
    "name:pol_x_preferred":[
        "Matfield"
    ],
    "name:rus_x_preferred":[
        "\u041c\u0430\u0442\u0444\u0438\u043b\u0434"
    ],
    "qs_pg:aaroncc":"GB",
    "qs_pg:gn_country":"GB",
    "qs_pg:gn_fcode":"PPL",
    "qs_pg:gn_pop":0,
    "qs_pg:name":"Matfield",
    "qs_pg:name_adm0":"United Kingdom",
    "qs_pg:name_adm1":"England",
    "qs_pg:photos":92,
    "qs_pg:photos_1k":19,
    "qs_pg:photos_9k":1,
    "qs_pg:photos_9r":3,
    "qs_pg:photos_all":92,
    "qs_pg:photos_sr":3,
    "qs_pg:pop_sr":0,
    "qs_pg:qs_pg_placetype":"locality",
    "qs_pg:qs_pg_placetype_gp":"Town",
    "qs_pg:woe_adm0":23424975,
    "woe:adm0_id":23424975,
    "woe:name_adm0":"United Kingdom",
    "woe:name_adm1":"England",
    "woe:placetype":"Town",
    "wof:name":"Matfield",
    "wof:placetype":"neighbourhood"
},
  "geometry": {"coordinates":[0.37089,51.15227],"type":"Point"}
}