{
  "type": "Feature",
  "properties": {
    "iso:country":"GB",
    "name:ceb_x_preferred":[
        "Earlston"
    ],
    "name:chi_x_preferred":[
        "\u5384\u5c14\u65af\u987f"
    ],
    "name:cym_x_preferred":[
        "Earlston"
    ],
    "name:dut_x_preferred":[
        "Earlston"
    ],
    "name:eng_x_preferred":[
        "Earlston"
    ],
    "name:ger_x_preferred":[
        "Earlston"
    ],
    "name:gla_x_preferred":[
        "D\u00f9n Airchill"
    ],
    "name:gle_x_preferred":[
        "D\u00fan Airchill"
    ],
    "name:jpn_x_preferred":[
        "\u30a2\u30fc\u30eb\u30b9\u30c8\u30f3"
    ],
    "name:nno_x_preferred":[
        "Earlston"
    ],
    "name:nob_x_preferred":[
        "Earlston"
    ],
    "name:nor_x_preferred":[
        "Earlston"
    ],
    "name:swe_x_preferred":[
        "Earlston"
    ],
    "name:wel_x_preferred":[
        "Earlston"
    ],
    "name:zho_x_preferred":[
        "\u5384\u5c14\u65af\u987f"
    ],
    "qs:a0":"United Kingdom",
    "qs:a1":"*Scottish Borders",
    "qs:a1_lc":"GB11QE0000",
    "qs:a1r":"0Scotland",
    "qs:a1r_lc":"GB11000000",
    "qs:adm0":"United Kingdom",
    "qs:la_lc":"*",
    "qs:level":"locality",
    "qs:loc":"Earlston",
    "qs:loc_alt":"Earlston",
    "qs:pop":0,
    "qs:type":"buffered point",
    "wd:wordcount":1014,
    "wof:lang":[
        "eng"
    ],
    "wof:name":"Earlston",
    "wof:placetype":"locality"
},
  "geometry": {"coordinates":[-2.675133,55.639663],"type":"Point"}
}