{
  "type": "Feature",
  "properties": {
    "iso:country":"GB",
    "wof:name":"Queen's Quarter",
    "wof:placetype":"neighbourhood"
},
  "geometry": {"coordinates":[-5.93622733287259,54.58639779860527],"type":"Point"}
}