{
  "type": "Feature",
  "properties": {
    "gn:country":"GB",
    "gn:fcode":"PPL",
    "gn:population":0,
    "iso:country":"GB",
    "name:ceb_x_preferred":[
        "Broadwas"
    ],
    "name:eng_x_preferred":[
        "Broadwas"
    ],
    "name:fra_x_preferred":[
        "Broadwas"
    ],
    "name:gle_x_preferred":[
        "Broadwas"
    ],
    "name:lld_x_preferred":[
        "Broadwas"
    ],
    "name:nan_x_preferred":[
        "Broadwas"
    ],
    "name:nld_x_preferred":[
        "Broadwas"
    ],
    "name:pol_x_preferred":[
        "Broadwas"
    ],
    "name:swe_x_preferred":[
        "Broadwas"
    ],
    "name:tur_x_preferred":[
        "Broadwas"
    ],
    "qs_pg:aaroncc":"GB",
    "qs_pg:gn_country":"GB",
    "qs_pg:gn_fcode":"PPL",
    "qs_pg:gn_pop":0,
    "qs_pg:name":"Broadwaters",
    "qs_pg:name_adm0":"United Kingdom",
    "qs_pg:name_adm1":"England",
    "qs_pg:photos":129,
    "qs_pg:photos_1k":26,
    "qs_pg:photos_9k":1,
    "qs_pg:photos_9r":3,
    "qs_pg:photos_all":129,
    "qs_pg:photos_sr":3,
    "qs_pg:pop_sr":0,
    "qs_pg:qs_pg_placetype":"locality",
    "qs_pg:qs_pg_placetype_gp":"Town",
    "qs_pg:woe_adm0":23424975,
    "woe:adm0_id":23424975,
    "woe:name_adm0":"United Kingdom",
    "woe:name_adm1":"England",
    "woe:placetype":"Town",
    "wof:name":"Broadwaters",
    "wof:placetype":"neighbourhood",
    "wof:population":318
},
  "geometry": {"coordinates":[-2.35487,52.19486],"type":"Point"}
}