{
  "type": "Feature",
  "properties": {
    "iso:country":"GB",
    "name:ceb_x_preferred":[
        "Dundonald"
    ],
    "name:deu_x_preferred":[
        "Dundonald"
    ],
    "name:eng_x_preferred":[
        "Dundonald"
    ],
    "name:eus_x_preferred":[
        "Dundonald"
    ],
    "name:fra_x_preferred":[
        "Dundonald"
    ],
    "name:nld_x_preferred":[
        "Dundonald"
    ],
    "name:sco_x_preferred":[
        "Dundonal"
    ],
    "name:spa_x_preferred":[
        "Dundonald"
    ],
    "name:swe_x_preferred":[
        "Dundonald"
    ],
    "qs:a0":"United Kingdom",
    "qs:a1":"*South Ayrshire",
    "qs:a1_lc":"GB11RE0000",
    "qs:a1r":"0Scotland",
    "qs:a1r_lc":"GB11000000",
    "qs:adm0":"United Kingdom",
    "qs:la_lc":"*",
    "qs:level":"locality",
    "qs:loc":"Dundonald",
    "qs:loc_alt":"Dundonald",
    "qs:pop":0,
    "qs:type":"buffered point",
    "wd:wordcount":1289,
    "wof:name":"Dundonald",
    "wof:placetype":"locality"
},
  "geometry": {"coordinates":[-4.595557,55.579578],"type":"Point"}
}