{
  "type": "Feature",
  "properties": {
    "iso:country":"GB",
    "oa:elevation_ft":"286",
    "oa:type":"small_airport",
    "woe:hierarchy":{
        "country_id":23424975,
        "county_id":12602168,
        "localadmin_id":12695941,
        "planet_id":1,
        "state_id":24554868
    },
    "wof:name":"Andrewsfield Airfield",
    "wof:placetype":"campus"
},
  "geometry": {"coordinates":[0.44916666666667,51.895],"type":"Point"}
}