{
  "type": "Feature",
  "properties": {
    "iso:country":"GB",
    "name:afr_x_preferred":[
        "Britannia"
    ],
    "name:ara_x_preferred":[
        "\u0628\u0631\u064a\u062a\u0627\u0646\u064a\u0627"
    ],
    "name:ces_x_preferred":[
        "Britannia"
    ],
    "name:cym_x_preferred":[
        "Britannia"
    ],
    "name:dan_x_preferred":[
        "Britannia"
    ],
    "name:deu_x_preferred":[
        "Britannia"
    ],
    "name:fas_x_preferred":[
        "\u0628\u0631\u06cc\u062a\u0627\u0646\u06cc\u0627"
    ],
    "name:fra_x_preferred":[
        "Britannia"
    ],
    "name:glg_x_preferred":[
        "Britannia"
    ],
    "name:heb_x_preferred":[
        "\u05d1\u05e8\u05d9\u05d8\u05e0\u05d9\u05d4"
    ],
    "name:ind_x_preferred":[
        "Britannia"
    ],
    "name:ita_x_preferred":[
        "Britannia"
    ],
    "name:jpn_x_preferred":[
        "\u30d6\u30ea\u30bf\u30cb\u30a2"
    ],
    "name:kat_x_preferred":[
        "\u10d1\u10e0\u10d8\u10e2\u10d0\u10dc\u10d8\u10d0"
    ],
    "name:kor_x_preferred":[
        "\ube0c\ub9ac\ud0c0\ub2c8\uc544"
    ],
    "name:lat_x_preferred":[
        "Britannia"
    ],
    "name:nld_x_preferred":[
        "Britannia"
    ],
    "name:nno_x_preferred":[
        "Britannia"
    ],
    "name:nor_x_preferred":[
        "Britannia"
    ],
    "name:por_x_preferred":[
        "Brit\u00e2nia"
    ],
    "name:rus_x_preferred":[
        "\u0411\u0440\u0438\u0442\u0430\u043d\u0438\u044f"
    ],
    "name:srp_x_preferred":[
        "\u0411\u0440\u0438\u0442\u0430\u043d\u0438\u0458\u0430"
    ],
    "name:swe_x_preferred":[
        "Britannia"
    ],
    "name:tha_x_preferred":[
        "\u0e1a\u0e23\u0e34\u0e41\u0e17\u0e19\u0e40\u0e19\u0e35\u0e22"
    ],
    "name:tur_x_preferred":[
        "Britannia"
    ],
    "name:ukr_x_preferred":[
        "\u0411\u0440\u0438\u0442\u0430\u043d\u0456\u044f"
    ],
    "name:zho_x_preferred":[
        "\u4e0d\u5217\u98a0\u5c3c\u4e9a"
    ],
    "qs_pg:aaroncc":"GB",
    "qs_pg:name":"Britannia",
    "qs_pg:name_adm0":"United Kingdom",
    "qs_pg:name_adm1":"England",
    "qs_pg:photos":61,
    "qs_pg:photos_1k":12,
    "qs_pg:photos_9k":1,
    "qs_pg:photos_9r":2,
    "qs_pg:photos_all":61,
    "qs_pg:photos_sr":2,
    "qs_pg:pop_sr":0,
    "qs_pg:qs_pg_placetype":"locality",
    "qs_pg:qs_pg_placetype_gp":"Town",
    "qs_pg:woe_adm0":23424975,
    "woe:adm0_id":23424975,
    "woe:name_adm0":"United Kingdom",
    "woe:name_adm1":"England",
    "woe:placetype":"Town",
    "wof:name":"Britannia",
    "wof:placetype":"locality"
},
  "geometry": {"coordinates":[-3.072223,52.925993],"type":"Point"}
}