{
  "type": "Feature",
  "properties": {
    "iso:country": "GB",
    "name:afr_x_preferred": [
      "Britannia"
    ],
    "name:ara_x_preferred": [
      "بريتانيا"
    ],
    "name:ces_x_preferred": [
      "Britannia"
    ],
    "name:cym_x_preferred": [
      "Britannia"
    ],
    "name:dan_x_preferred": [
      "Britannia"
    ],
    "name:deu_x_preferred": [
      "Britannia"
    ],
    "name:fas_x_preferred": [
      "بریتانیا"
    ],
    "name:fra_x_preferred": [
      "Britannia"
    ],
    "name:glg_x_preferred": [
      "Britannia"
    ],
    "name:heb_x_preferred": [
      "בריטניה"
    ],
    "name:ind_x_preferred": [
      "Britannia"
    ],
    "name:ita_x_preferred": [
      "Britannia"
    ],
    "name:jpn_x_preferred": [
      "ブリタニア"
    ],
    "name:kat_x_preferred": [
      "ბრიტანია"
    ],
    "name:kor_x_preferred": [
      "브리타니아"
    ],
    "name:lat_x_preferred": [
      "Britannia"
    ],
    "name:nld_x_preferred": [
      "Britannia"
    ],
    "name:nno_x_preferred": [
      "Britannia"
    ],
    "name:nor_x_preferred": [
      "Britannia"
    ],
    "name:por_x_preferred": [
      "Britânia"
    ],
    "name:rus_x_preferred": [
      "Британия"
    ],
    "name:srp_x_preferred": [
      "Британија"
    ],
    "name:swe_x_preferred": [
      "Britannia"
    ],
    "name:tha_x_preferred": [
      "บริแทนเนีย"
    ],
    "name:tur_x_preferred": [
      "Britannia"
    ],
    "name:ukr_x_preferred": [
      "Британія"
    ],
    "name:zho_x_preferred": [
      "不列颠尼亚"
    ],
    "qs_pg:aaroncc": "GB",
    "qs_pg:name": "Britannia",
    "qs_pg:name_adm0": "United Kingdom",
    "qs_pg:name_adm1": "England",
    "qs_pg:photos": 61,
    "qs_pg:photos_1k": 12,
    "qs_pg:photos_9k": 1,
    "qs_pg:photos_9r": 2,
    "qs_pg:photos_all": 61,
    "qs_pg:photos_sr": 2,
    "qs_pg:pop_sr": 0,
    "qs_pg:qs_pg_placetype": "locality",
    "qs_pg:qs_pg_placetype_gp": "Town",
    "qs_pg:woe_adm0": 23424975,
    "woe:adm0_id": 23424975,
    "woe:name_adm0": "United Kingdom",
    "woe:name_adm1": "England",
    "woe:placetype": "Town",
    "wof:name": "Britannia",
    "wof:placetype": "locality"
  },
  "geometry": {"coordinates":[-3.072223,52.925993],"type":"Point"}
}
