{
  "type": "Feature",
  "properties": {
    "iso:country":"GB",
    "name:eng_x_preferred":[
        "Markethill"
    ],
    "name:eus_x_preferred":[
        "Markethill"
    ],
    "name:fas_x_preferred":[
        "\u0645\u0627\u0631\u06a9\u062a\u0647\u06cc\u0644"
    ],
    "name:fra_x_preferred":[
        "Markethill"
    ],
    "name:gla_x_preferred":[
        "Cnoc an Mhargaidh"
    ],
    "name:gle_x_preferred":[
        "Cnoc an Mhargaidh"
    ],
    "name:ita_x_preferred":[
        "Markethill"
    ],
    "name:msa_x_preferred":[
        "Markethill"
    ],
    "name:nld_x_preferred":[
        "Markethill"
    ],
    "name:pli_x_preferred":[
        "\u092e\u0930\u094d\u0915\u0947\u0925\u093f\u0932\u094d\u0932"
    ],
    "name:spa_x_preferred":[
        "Markethill"
    ],
    "qs:a0":"United Kingdom",
    "qs:a1":"*Armagh City and District",
    "qs:a1_lc":"N_A",
    "qs:a1r":"0Northern Ireland",
    "qs:a1r_lc":"N_A",
    "qs:adm0":"United Kingdom",
    "qs:la_lc":"*",
    "qs:level":"locality",
    "qs:loc":"Markethill",
    "qs:loc_alt":"Markethill",
    "qs:pop":0,
    "qs:type":"buffered point",
    "wd:wordcount":1045,
    "wof:name":"Markethill",
    "wof:placetype":"locality"
},
  "geometry": {"coordinates":[-6.51931,54.296974],"type":"Point"}
}