{
  "type": "Feature",
  "properties": {
    "iso:country": "GB",
    "name:deu_x_preferred": [
      "Achavanich"
    ],
    "qs_pg:aaroncc": "GB",
    "qs_pg:name": "Achavanich",
    "qs_pg:name_adm0": "United Kingdom",
    "qs_pg:name_adm1": "Scotland",
    "qs_pg:photos": 48,
    "qs_pg:photos_1k": 10,
    "qs_pg:photos_9k": 1,
    "qs_pg:photos_9r": 2,
    "qs_pg:photos_all": 48,
    "qs_pg:photos_sr": 2,
    "qs_pg:pop_sr": 0,
    "qs_pg:qs_pg_placetype": "locality",
    "qs_pg:qs_pg_placetype_gp": "Town",
    "qs_pg:woe_adm0": 23424975,
    "woe:adm0_id": 23424975,
    "woe:name_adm0": "United Kingdom",
    "woe:name_adm1": "Scotland",
    "woe:placetype": "Town",
    "wof:name": "Achavanich",
    "wof:placetype": "locality"
  },
  "geometry": {"coordinates":[-3.3887025,58.357431],"type":"Point"}
}
