{
  "type": "Feature",
  "properties": {
    "gn:gn_country":"GB",
    "iso:country":"GB",
    "name:cym_x_preferred":[
        "Maker"
    ],
    "name:eng_x_preferred":[
        "Maker"
    ],
    "name:fra_x_preferred":[
        "Maker"
    ],
    "name:nld_x_preferred":[
        "Maker"
    ],
    "name:pol_x_preferred":[
        "Maker"
    ],
    "qs_pg:aaroncc":"GB",
    "qs_pg:gn_country":"GB",
    "qs_pg:name":"Maker",
    "qs_pg:name_adm0":"United Kingdom",
    "qs_pg:name_adm1":"England",
    "qs_pg:photos":317,
    "qs_pg:photos_1k":64,
    "qs_pg:photos_9k":1,
    "qs_pg:photos_9r":5,
    "qs_pg:photos_all":317,
    "qs_pg:photos_sr":5,
    "qs_pg:pop_sr":0,
    "qs_pg:qs_pg_placetype":"locality",
    "qs_pg:qs_pg_placetype_gp":"Town",
    "qs_pg:woe_adm0":23424975,
    "woe:adm0_id":23424975,
    "woe:name_adm0":"United Kingdom",
    "woe:name_adm1":"England",
    "woe:placetype":"Town",
    "wof:name":"Maker",
    "wof:placetype":"neighbourhood"
},
  "geometry": {"coordinates":[-4.163017,50.338483],"type":"Point"}
}