{
  "type": "Feature",
  "properties": {
    "gn:admin1_code":"ENG",
    "gn:admin2_code":"J7",
    "gn:admin3_code":"36UF",
    "gn:admin4_code":"36UF068",
    "gn:asciiname":"Helperthorpe",
    "gn:country_code":"GB",
    "gn:dem":78,
    "gn:feature_class":"P",
    "gn:feature_code":"PPL",
    "gn:name":"Helperthorpe",
    "gn:population":0,
    "gn:timezone":"Europe/London",
    "iso:country":"GB",
    "name:pol_x_preferred":[
        "Helperthorpe"
    ],
    "wof:name":"Helperthorpe",
    "wof:placetype":"neighbourhood"
},
  "geometry": {"coordinates":[-0.54361,54.11958000000001],"type":"Point"}
}