{
  "type": "Feature",
  "properties": {
    "iso:country":"GB",
    "name:eng_x_preferred":[
        "Romsey Town"
    ],
    "wof:name":"Romsey Town",
    "wof:placetype":"neighbourhood"
},
  "geometry": {"coordinates":[0.14925537240979,52.20034155694918],"type":"Point"}
}