{
  "type": "Feature",
  "properties": {
    "gn:gn_country":"GB",
    "gn:gn_fcode":"PPL",
    "gn:gn_pop":497,
    "gn:population":497,
    "iso:country":"GB",
    "name:bre_x_preferred":[
        "C\u00e0rradal"
    ],
    "name:eng_x_preferred":[
        "Carradale"
    ],
    "name:fra_x_preferred":[
        "Carradale"
    ],
    "name:gla_x_preferred":[
        "C\u00e0radal"
    ],
    "name:gle_x_preferred":[
        "C\u00e1rradal"
    ],
    "name:nld_x_preferred":[
        "Carradale"
    ],
    "name:swe_x_preferred":[
        "Carradale"
    ],
    "name:ukr_x_preferred":[
        "\u041a\u0430\u0440\u0440\u0430\u0434\u0435\u0439\u043b"
    ],
    "qs_pg:aaroncc":"GB",
    "qs_pg:gn_country":"GB",
    "qs_pg:gn_fcode":"PPL",
    "qs_pg:gn_pop":497,
    "qs_pg:name":"Carradale",
    "qs_pg:name_adm0":"United Kingdom",
    "qs_pg:name_adm1":"Scotland",
    "qs_pg:photos":454,
    "qs_pg:photos_1k":92,
    "qs_pg:photos_9k":2,
    "qs_pg:photos_9r":5,
    "qs_pg:photos_all":454,
    "qs_pg:photos_sr":7,
    "qs_pg:pop_sr":2,
    "qs_pg:qs_pg_placetype":"locality",
    "qs_pg:qs_pg_placetype_gp":"Town",
    "qs_pg:woe_adm0":23424975,
    "woe:adm0_id":23424975,
    "woe:name_adm0":"United Kingdom",
    "woe:name_adm1":"Scotland",
    "woe:placetype":"Town",
    "wof:name":"Carradale",
    "wof:placetype":"locality",
    "wof:population":497
},
  "geometry": {"coordinates":[-5.47197,55.58926],"type":"Point"}
}