{
  "type": "Feature",
  "properties": {
    "gn:gn_country":"GB",
    "iso:country":"GB",
    "name:eus_x_preferred":[
        "New Tolsta"
    ],
    "name:gle_x_preferred":[
        "Bail' \u00dar Tholastaidh"
    ],
    "qs_pg:aaroncc":"GB",
    "qs_pg:gn_country":"GB",
    "qs_pg:name":"New Tolsta",
    "qs_pg:name_adm0":"United Kingdom",
    "qs_pg:name_adm1":"Scotland",
    "qs_pg:photos":353,
    "qs_pg:photos_1k":72,
    "qs_pg:photos_9k":2,
    "qs_pg:photos_9r":5,
    "qs_pg:photos_all":353,
    "qs_pg:photos_sr":6,
    "qs_pg:pop_sr":0,
    "qs_pg:qs_pg_placetype":"locality",
    "qs_pg:qs_pg_placetype_gp":"Town",
    "qs_pg:woe_adm0":23424975,
    "woe:adm0_id":23424975,
    "woe:name_adm0":"United Kingdom",
    "woe:name_adm1":"Scotland",
    "woe:placetype":"Town",
    "wof:name":"New Tolsta",
    "wof:placetype":"locality"
},
  "geometry": {"coordinates":[-6.212768,58.368124],"type":"Point"}
}