{
  "type": "Feature",
  "properties": {
    "gn:admin1_code": "SCT",
    "gn:admin2_code": "V6",
    "gn:asciiname": "Bridge of Lossie",
    "gn:country_code": "GB",
    "gn:dem": 158,
    "gn:feature_class": "P",
    "gn:feature_code": "PPL",
    "gn:name": "Bridge of Lossie",
    "gn:population": 0,
    "gn:timezone": "Europe/London",
    "iso:country": "GB",
    "wof:name": "Bridge of Lossie",
    "wof:placetype": "locality"
  },
  "geometry": {"coordinates":[-3.46667,57.55],"type":"Point"}
}
