{
  "type": "Feature",
  "properties": {
    "gn:population":9472,
    "iso:country":"GB",
    "name:bul_x_preferred":[
        "\u0411\u0430\u043b\u0438\u043a\u043b\u0435\u044a\u0440"
    ],
    "name:cat_x_preferred":[
        "Ballyclare"
    ],
    "name:ceb_x_preferred":[
        "Ballyclare"
    ],
    "name:deu_x_preferred":[
        "Ballyclare"
    ],
    "name:eng_x_preferred":[
        "Ballyclare"
    ],
    "name:eus_x_preferred":[
        "Ballyclare"
    ],
    "name:fra_x_preferred":[
        "Ballyclare"
    ],
    "name:gla_x_preferred":[
        "Bealach Cl\u00e1ir"
    ],
    "name:gle_x_preferred":[
        "Bealach Cl\u00e1ir"
    ],
    "name:heb_x_preferred":[
        "\u05d1\u05dc\u05d9\u05e7\u05dc\u05d9\u05d9\u05e8"
    ],
    "name:jpn_x_preferred":[
        "\u30d0\u30ea\u30fc\u30af\u30ec\u30a2"
    ],
    "name:lit_x_preferred":[
        "Balikleras"
    ],
    "name:msa_x_preferred":[
        "Ballyclare"
    ],
    "name:nld_x_preferred":[
        "Ballyclare"
    ],
    "name:nob_x_preferred":[
        "Ballyclare"
    ],
    "name:nor_x_preferred":[
        "Ballyclare"
    ],
    "name:pol_x_preferred":[
        "Ballyclare"
    ],
    "name:por_x_preferred":[
        "Ballyclare"
    ],
    "name:rus_x_preferred":[
        "\u0411\u0430\u043b\u043b\u0438\u043a\u043b\u044d\u0440"
    ],
    "name:swe_x_preferred":[
        "Ballyclare"
    ],
    "name:zho_x_preferred":[
        "\u5df4\u5229\u514b\u840a\u723e"
    ],
    "qs:a0":"United Kingdom",
    "qs:a1":"*Newtownabbey",
    "qs:a1_lc":"N_A",
    "qs:a1r":"0Northern Ireland",
    "qs:a1r_lc":"N_A",
    "qs:adm0":"United Kingdom",
    "qs:la_lc":"*",
    "qs:level":"locality",
    "qs:loc":"Ballyclare",
    "qs:loc_alt":"Ballyclare",
    "qs:pop":0,
    "qs:type":"buffered point",
    "wd:wordcount":2085,
    "wof:name":"Ballyclare",
    "wof:placetype":"locality",
    "wof:population":9472
},
  "geometry": {"coordinates":[-5.9984,54.750606],"type":"Point"}
}