{
  "type": "Feature",
  "properties": {
    "gn:population": 9472,
    "iso:country": "GB",
    "name:bul_x_preferred": [
      "Баликлеър"
    ],
    "name:cat_x_preferred": [
      "Ballyclare"
    ],
    "name:ceb_x_preferred": [
      "Ballyclare"
    ],
    "name:deu_x_preferred": [
      "Ballyclare"
    ],
    "name:eng_x_preferred": [
      "Ballyclare"
    ],
    "name:eus_x_preferred": [
      "Ballyclare"
    ],
    "name:fra_x_preferred": [
      "Ballyclare"
    ],
    "name:gla_x_preferred": [
      "Bealach Cláir"
    ],
    "name:gle_x_preferred": [
      "Bealach Cláir"
    ],
    "name:heb_x_preferred": [
      "בליקלייר"
    ],
    "name:ita_x_preferred": [
      "Ballyclare"
    ],
    "name:jpn_x_preferred": [
      "バリークレア"
    ],
    "name:lit_x_preferred": [
      "Balikleras"
    ],
    "name:msa_x_preferred": [
      "Ballyclare"
    ],
    "name:nld_x_preferred": [
      "Ballyclare"
    ],
    "name:nob_x_preferred": [
      "Ballyclare"
    ],
    "name:nor_x_preferred": [
      "Ballyclare"
    ],
    "name:pol_x_preferred": [
      "Ballyclare"
    ],
    "name:por_x_preferred": [
      "Ballyclare"
    ],
    "name:rus_x_preferred": [
      "Балликлэр"
    ],
    "name:rus_x_variant": [
      "Балликлер"
    ],
    "name:sco_x_preferred": [
      "Bellyclare"
    ],
    "name:spa_x_preferred": [
      "Ballyclare"
    ],
    "name:swe_x_preferred": [
      "Ballyclare"
    ],
    "name:zho_x_preferred": [
      "巴利克萊爾"
    ],
    "qs:a0": "United Kingdom",
    "qs:a1": "*Newtownabbey",
    "qs:a1_lc": "N_A",
    "qs:a1r": "0Northern Ireland",
    "qs:a1r_lc": "N_A",
    "qs:adm0": "United Kingdom",
    "qs:la_lc": "*",
    "qs:level": "locality",
    "qs:loc": "Ballyclare",
    "qs:loc_alt": "Ballyclare",
    "qs:pop": 0,
    "qs:type": "buffered point",
    "wd:wordcount": 2085,
    "wof:name": "Ballyclare",
    "wof:placetype": "locality",
    "wof:population": 9472
  },
  "geometry": {"coordinates":[-5.9984,54.750606],"type":"Point"}
}
