{
  "type": "Feature",
  "properties": {
    "gn:admin1_code":"WLS",
    "gn:admin2_code":"X7",
    "gn:admin3_code":"00NU033",
    "gn:asciiname":"Sylen",
    "gn:country_code":"GB",
    "gn:dem":225,
    "gn:feature_class":"P",
    "gn:feature_code":"PPL",
    "gn:name":"Sylen",
    "gn:population":0,
    "gn:timezone":"Europe/London",
    "iso:country":"GB",
    "wof:name":"Sylen",
    "wof:placetype":"neighbourhood"
},
  "geometry": {"coordinates":[-4.1567,51.74126],"type":"Point"}
}