{
  "type": "Feature",
  "properties": {
    "gn:gn_country":"GB",
    "gn:gn_fcode":"PPL",
    "gn:gn_pop":0,
    "iso:country":"GB",
    "name:ara_x_preferred":[
        "\u0628\u064a\u0644"
    ],
    "name:dut_x_preferred":[
        "Poyle"
    ],
    "name:eng_x_preferred":[
        "Poyle"
    ],
    "name:fre_x_preferred":[
        "Poyle"
    ],
    "name:pol_x_preferred":[
        "Poyle"
    ],
    "name:wel_x_preferred":[
        "Poyle"
    ],
    "qs_pg:aaroncc":"GB",
    "qs_pg:gn_country":"GB",
    "qs_pg:gn_fcode":"PPL",
    "qs_pg:gn_pop":0,
    "qs_pg:name":"Poyle",
    "qs_pg:name_adm0":"United Kingdom",
    "qs_pg:name_adm1":"England",
    "qs_pg:photos":773,
    "qs_pg:photos_1k":157,
    "qs_pg:photos_9k":3,
    "qs_pg:photos_9r":6,
    "qs_pg:photos_all":773,
    "qs_pg:photos_sr":9,
    "qs_pg:pop_sr":0,
    "qs_pg:qs_pg_placetype":"locality",
    "qs_pg:qs_pg_placetype_gp":"Town",
    "qs_pg:woe_adm0":23424975,
    "woe:adm0_id":23424975,
    "woe:name_adm0":"United Kingdom",
    "woe:name_adm1":"England",
    "woe:placetype":"Town",
    "wof:name":"Poyle",
    "wof:placetype":"neighbourhood"
},
  "geometry": {"coordinates":[-0.51664,51.47648],"type":"Point"}
}