{
  "type": "Feature",
  "properties": {
    "iso:country":"GB",
    "name:eng_x_preferred":[
        "New Chesterton"
    ],
    "name:unk_x_variant":[
        "Chesterton",
        "New Chesterton"
    ],
    "qs:gn_adm0_cc":"GB",
    "qs:gn_fcode":"PPL",
    "qs:gn_local":2653941,
    "qs:gn_nam_loc":"Cambridge, Cambridgeshire, Cambridge, England, GB",
    "qs:gn_namadm1":"ENG",
    "qs:gn_name":"Chesterton",
    "qs:local_max":12386,
    "qs:local_sum":48350,
    "qs:localhoods":5,
    "qs:name":"New Chesterton",
    "qs:name_adm0":"United Kingdom",
    "qs:name_adm1":"England",
    "qs:name_adm2":"Cambridgeshire",
    "qs:name_lau":"Cambridge City",
    "qs:name_local":"Cambridge",
    "qs:photo_max":248,
    "qs:photo_sum":6254,
    "qs:placetype":"Suburb",
    "qs:quad_count":154,
    "qs:woe_adm0":23424975,
    "qs:woe_adm1":24554868,
    "qs:woe_adm2":12602140,
    "qs:woe_lau":12695882,
    "qs:woe_local":14979,
    "qs:woe_ver":"7.10.0",
    "wof:lang":[
        "eng"
    ],
    "wof:name":"New Chesterton",
    "wof:placetype":"neighbourhood"
},
  "geometry": {"coordinates":[0.116996,52.209584],"type":"Point"}
}