{
  "type": "Feature",
  "properties": {
    "iso:country":"GB",
    "name:ceb_x_preferred":[
        "Unst"
    ],
    "name:cym_x_preferred":[
        "Unst"
    ],
    "name:dan_x_preferred":[
        "Unst"
    ],
    "name:deu_x_preferred":[
        "Unst"
    ],
    "name:ell_x_preferred":[
        "\u039f\u03c5\u03bd\u03c3\u03c4"
    ],
    "name:eus_x_preferred":[
        "Unst"
    ],
    "name:fao_x_preferred":[
        "Unst"
    ],
    "name:fin_x_preferred":[
        "Unst"
    ],
    "name:fra_x_preferred":[
        "Unst"
    ],
    "name:gla_x_preferred":[
        "Unst"
    ],
    "name:heb_x_preferred":[
        "\u05d0\u05d5\u05e0\u05e1\u05d8"
    ],
    "name:hun_x_preferred":[
        "Unst"
    ],
    "name:isl_x_preferred":[
        "\u00danst"
    ],
    "name:ita_x_preferred":[
        "Unst"
    ],
    "name:jpn_x_preferred":[
        "\u30a2\u30f3\u30b9\u30c8\u5cf6"
    ],
    "name:lit_x_preferred":[
        "Anstas"
    ],
    "name:nld_x_preferred":[
        "Unst"
    ],
    "name:nno_x_preferred":[
        "Unst"
    ],
    "name:nor_x_preferred":[
        "Unst"
    ],
    "name:pnb_x_preferred":[
        "\u0627\u0646\u0633\u0679"
    ],
    "name:pol_x_preferred":[
        "Unst"
    ],
    "name:por_x_preferred":[
        "Unst"
    ],
    "name:rus_x_preferred":[
        "\u0410\u043d\u0441\u0442"
    ],
    "name:sco_x_preferred":[
        "Unst"
    ],
    "name:spa_x_preferred":[
        "Unst"
    ],
    "name:srp_x_preferred":[
        "\u0410\u043d\u0441\u0442"
    ],
    "name:swa_x_preferred":[
        "Unst"
    ],
    "name:swe_x_preferred":[
        "Unst"
    ],
    "name:ukr_x_preferred":[
        "\u0410\u043d\u0441\u0442"
    ],
    "name:zho_x_preferred":[
        "\u5b89\u65af\u7279\u5cf6"
    ],
    "qs_pg:aaroncc":"GB",
    "qs_pg:name":"Unst",
    "qs_pg:name_adm0":"United Kingdom",
    "qs_pg:name_adm1":"Scotland",
    "qs_pg:photos":83,
    "qs_pg:photos_1k":17,
    "qs_pg:photos_9k":1,
    "qs_pg:photos_9r":3,
    "qs_pg:photos_all":83,
    "qs_pg:photos_sr":3,
    "qs_pg:pop_sr":0,
    "qs_pg:qs_pg_placetype":"locality",
    "qs_pg:qs_pg_placetype_gp":"Town",
    "qs_pg:woe_adm0":23424975,
    "woe:adm0_id":23424975,
    "woe:name_adm0":"United Kingdom",
    "woe:name_adm1":"Scotland",
    "woe:placetype":"Town",
    "wof:name":"Unst",
    "wof:placetype":"locality"
},
  "geometry": {"coordinates":[-0.883026,60.75764],"type":"Point"}
}