{
  "type": "Feature",
  "properties": {
    "iso:country":"GB",
    "name:eng_x_preferred":[
        "Salterhebble"
    ],
    "name:unk_x_variant":[
        "Salterhebble"
    ],
    "qs:gn_local":0,
    "qs:local_max":4211,
    "qs:local_sum":11660,
    "qs:localhoods":16,
    "qs:name":"Salterhebble",
    "qs:name_adm0":"United Kingdom",
    "qs:name_adm1":"England",
    "qs:name_adm2":"West Yorkshire",
    "qs:name_lau":"Calderdale Metropolitan Borough",
    "qs:name_local":"Halifax",
    "qs:photo_max":38,
    "qs:photo_sum":126,
    "qs:placetype":"Suburb",
    "qs:quad_count":10,
    "qs:woe_adm0":23424975,
    "qs:woe_adm1":24554868,
    "qs:woe_adm2":12602197,
    "qs:woe_lau":12695871,
    "qs:woe_local":22179,
    "qs:woe_ver":"7.10.0",
    "wd:wordcount":340,
    "wof:lang":[
        "eng"
    ],
    "wof:name":"Salterhebble",
    "wof:placetype":"neighbourhood"
},
  "geometry": {"coordinates":[-1.85798,53.6999],"type":"Point"}
}