{
  "type": "Feature",
  "properties": {
    "iso:country":"GB",
    "name:ara_x_preferred":[
        "\u0628\u0644\u0643\u0631\u064a\u0633"
    ],
    "name:arz_x_preferred":[
        "\u0628\u0644\u0643\u0631\u064a\u0633"
    ],
    "name:cor_x_preferred":[
        "Pollkerys"
    ],
    "name:cym_x_preferred":[
        "Polkerris"
    ],
    "name:cym_x_variant":[
        "Pollkerys"
    ],
    "name:eng_x_preferred":[
        "Polkerris"
    ],
    "name:eus_x_preferred":[
        "Polkerris"
    ],
    "name:fra_x_preferred":[
        "Polkerris"
    ],
    "name:gle_x_preferred":[
        "Polkerris"
    ],
    "name:nld_x_preferred":[
        "Polkerris"
    ],
    "name:pol_x_preferred":[
        "Polkerris"
    ],
    "qs_pg:aaroncc":"GB",
    "qs_pg:name":"Polkerris",
    "qs_pg:name_adm0":"United Kingdom",
    "qs_pg:name_adm1":"England",
    "qs_pg:photos":409,
    "qs_pg:photos_1k":83,
    "qs_pg:photos_9k":2,
    "qs_pg:photos_9r":5,
    "qs_pg:photos_all":409,
    "qs_pg:photos_sr":6,
    "qs_pg:pop_sr":0,
    "qs_pg:qs_pg_placetype":"locality",
    "qs_pg:qs_pg_placetype_gp":"Town",
    "qs_pg:woe_adm0":23424975,
    "woe:adm0_id":23424975,
    "woe:name_adm0":"United Kingdom",
    "woe:name_adm1":"England",
    "woe:placetype":"Town",
    "wof:name":"Polkerris",
    "wof:placetype":"neighbourhood"
},
  "geometry": {"coordinates":[-4.68481,50.338969],"type":"Point"}
}