{
  "type": "Feature",
  "properties": {
    "iso:country":"GB",
    "wof:name":"West Denton",
    "wof:placetype":"neighbourhood"
},
  "geometry": {"coordinates":[-1.70931528490041,54.99472647692034],"type":"Point"}
}