{
  "type": "Feature",
  "properties": {
    "gn:admin1_code":"ENG",
    "gn:admin2_code":"D4",
    "gn:admin3_code":"18UL",
    "gn:admin4_code":"18UL001",
    "gn:asciiname":"Ashbury",
    "gn:country_code":"GB",
    "gn:dem":176,
    "gn:feature_class":"P",
    "gn:feature_code":"PPL",
    "gn:name":"Ashbury",
    "gn:population":0,
    "gn:timezone":"Europe/London",
    "iso:country":"GB",
    "wof:name":"Ashbury",
    "wof:placetype":"neighbourhood"
},
  "geometry": {"coordinates":[-4.11667,50.75],"type":"Point"}
}