{
  "type": "Feature",
  "properties": {
    "gn:country":"GB",
    "gn:fcode":"PPL",
    "gn:population":0,
    "iso:country":"GB",
    "name:eng_x_preferred":[
        "Veensgarth"
    ],
    "name:eus_x_preferred":[
        "Veensgarth"
    ],
    "name:fra_x_preferred":[
        "Veensgarth"
    ],
    "name:nld_x_preferred":[
        "Veensgarth"
    ],
    "name:pol_x_preferred":[
        "Veensgarth"
    ],
    "name:rus_x_preferred":[
        "\u0412\u0438\u043d\u0441\u0433\u0430\u0440\u0442"
    ],
    "qs_pg:aaroncc":"GB",
    "qs_pg:gn_country":"GB",
    "qs_pg:gn_fcode":"PPL",
    "qs_pg:gn_pop":0,
    "qs_pg:name":"Veensgarth",
    "qs_pg:name_adm0":"United Kingdom",
    "qs_pg:name_adm1":"Scotland",
    "qs_pg:photos":21,
    "qs_pg:photos_1k":4,
    "qs_pg:photos_9k":1,
    "qs_pg:photos_9r":1,
    "qs_pg:photos_all":21,
    "qs_pg:photos_sr":1,
    "qs_pg:pop_sr":0,
    "qs_pg:qs_pg_placetype":"locality",
    "qs_pg:qs_pg_placetype_gp":"Town",
    "qs_pg:woe_adm0":23424975,
    "woe:adm0_id":23424975,
    "woe:name_adm0":"United Kingdom",
    "woe:name_adm1":"Scotland",
    "woe:placetype":"Town",
    "wof:name":"Veensgarth",
    "wof:placetype":"locality"
},
  "geometry": {"coordinates":[-1.23021,60.18318],"type":"Point"}
}