{
  "type": "Feature",
  "properties": {
    "gn:admin1_code": "SCT",
    "gn:admin2_code": "W1",
    "gn:asciiname": "Tullybannocher",
    "gn:country_code": "GB",
    "gn:dem": 71,
    "gn:feature_class": "P",
    "gn:feature_code": "PPL",
    "gn:name": "Tullybannocher",
    "gn:population": 0,
    "gn:timezone": "Europe/London",
    "iso:country": "GB",
    "wof:name": "Tullybannocher",
    "wof:placetype": "locality"
  },
  "geometry": {"coordinates":[-4.01434,56.37281],"type":"Point"}
}
