{
  "type": "Feature",
  "properties": {
    "iso:country":"GB",
    "name:ceb_x_preferred":[
        "Eaglescliffe"
    ],
    "name:cym_x_preferred":[
        "Eaglescliffe"
    ],
    "name:eng_x_preferred":[
        "Eaglescliffe"
    ],
    "name:fas_x_preferred":[
        "\u0627\u06cc\u06af\u0644\u0632\u06a9\u0644\u06cc\u0641"
    ],
    "name:fra_x_preferred":[
        "Eaglescliffe"
    ],
    "name:gle_x_preferred":[
        "Eaglescliffe"
    ],
    "name:heb_x_preferred":[
        "\u05d0\u05d9\u05d2\u05dc\u05e1\u05e7\u05dc\u05d9\u05e3"
    ],
    "name:ita_x_preferred":[
        "Eaglescliffe"
    ],
    "name:nan_x_preferred":[
        "Eaglescliffe"
    ],
    "name:nld_x_preferred":[
        "Eaglescliffe"
    ],
    "name:pol_x_preferred":[
        "Eaglescliffe"
    ],
    "name:swe_x_preferred":[
        "Eaglescliffe"
    ],
    "name:urd_x_preferred":[
        "\u0627\u06cc\u06af\u0644\u0632\u06a9\u0644\u0641"
    ],
    "qs_pg:aaroncc":"GB",
    "qs_pg:name":"Eaglescliffe",
    "qs_pg:name_adm0":"United Kingdom",
    "qs_pg:name_adm1":"England",
    "qs_pg:photos":768,
    "qs_pg:photos_1k":156,
    "qs_pg:photos_9k":3,
    "qs_pg:photos_9r":6,
    "qs_pg:photos_all":768,
    "qs_pg:photos_sr":9,
    "qs_pg:pop_sr":0,
    "qs_pg:qs_pg_placetype":"locality",
    "qs_pg:qs_pg_placetype_gp":"Town",
    "qs_pg:woe_adm0":23424975,
    "woe:adm0_id":23424975,
    "woe:name_adm0":"United Kingdom",
    "woe:name_adm1":"England",
    "woe:placetype":"Town",
    "wof:name":"Eaglescliffe",
    "wof:placetype":"neighbourhood"
},
  "geometry": {"coordinates":[-1.34325,54.532886],"type":"Point"}
}