{
  "type": "Feature",
  "properties": {
    "gn:admin1_code":"SCT",
    "gn:admin2_code":"T8",
    "gn:asciiname":"Castleton",
    "gn:country_code":"GB",
    "gn:dem":34,
    "gn:feature_class":"P",
    "gn:feature_code":"PPL",
    "gn:name":"Castleton",
    "gn:population":0,
    "gn:timezone":"Europe/London",
    "iso:country":"GB",
    "wof:name":"Castleton",
    "wof:placetype":"locality"
},
  "geometry": {"coordinates":[-5.39978,56.01028],"type":"Point"}
}