{
  "type": "Feature",
  "properties": {
    "gn:admin1_code":"SCT",
    "gn:admin2_code":"T8",
    "gn:asciiname":"Castleton",
    "gn:country_code":"GB",
    "gn:dem":34,
    "gn:feature_class":"P",
    "gn:feature_code":"PPL",
    "gn:name":"Castleton",
    "gn:population":0,
    "gn:timezone":"Europe/London",
    "iso:country":"GB",
    "name:ceb_x_preferred":[
        "Castleton"
    ],
    "name:deu_x_preferred":[
        "Castleton"
    ],
    "name:fin_x_preferred":[
        "Castleton"
    ],
    "name:fra_x_preferred":[
        "Castleton"
    ],
    "name:ita_x_preferred":[
        "Castleton"
    ],
    "name:nld_x_preferred":[
        "Castleton"
    ],
    "name:pol_x_preferred":[
        "Castleton"
    ],
    "name:swe_x_preferred":[
        "Castleton"
    ],
    "name:ukr_x_preferred":[
        "\u041a\u0430\u0441\u043b\u0442\u043e\u043d"
    ],
    "name:vie_x_preferred":[
        "Castleton"
    ],
    "wof:name":"Castleton",
    "wof:placetype":"locality"
},
  "geometry": {"coordinates":[-5.39978,56.01028],"type":"Point"}
}