{
  "type": "Feature",
  "properties": {
    "gn:admin1_code":"ENG",
    "gn:admin2_code":"L6",
    "gn:admin3_code":"00GG071",
    "gn:asciiname":"Harton",
    "gn:country_code":"GB",
    "gn:dem":174,
    "gn:feature_class":"P",
    "gn:feature_code":"PPL",
    "gn:name":"Harton",
    "gn:population":0,
    "gn:timezone":"Europe/London",
    "iso:country":"GB",
    "wof:name":"Harton",
    "wof:placetype":"neighbourhood"
},
  "geometry": {"coordinates":[-2.76375,52.49144],"type":"Point"}
}