{
  "type": "Feature",
  "properties": {
    "iso:country":"GB",
    "name:ceb_x_preferred":[
        "Clifton Campville"
    ],
    "name:eng_x_preferred":[
        "Cliftonville"
    ],
    "name:eng_x_variant":[
        "Clifton Campville"
    ],
    "name:fra_x_preferred":[
        "Clifton Campville"
    ],
    "name:gle_x_preferred":[
        "Clifton Campville"
    ],
    "name:lld_x_preferred":[
        "Clifton Campville"
    ],
    "name:nan_x_preferred":[
        "Clifton Campville"
    ],
    "name:nld_x_preferred":[
        "Clifton Campville"
    ],
    "name:pol_x_preferred":[
        "Clifton Campville"
    ],
    "name:spa_x_preferred":[
        "Clifton Campville"
    ],
    "name:swe_x_preferred":[
        "Clifton Campville"
    ],
    "name:tur_x_preferred":[
        "Clifton Campville"
    ],
    "qs:gn_fcode":"PPL",
    "qs:gn_local":0,
    "qs:gn_nam_loc":"salford priors",
    "qs:gn_namadm1":"ENG",
    "qs:gn_name":"Clifton Campville",
    "qs:local_max":4658,
    "qs:local_sum":19788,
    "qs:localhoods":12,
    "qs:name":"Cliftonville",
    "qs:name_adm0":"United Kingdom",
    "qs:name_adm1":"England",
    "qs:name_adm2":"Northamptonshire",
    "qs:name_lau":"Northampton Borough",
    "qs:name_local":"Northampton",
    "qs:photo_max":291,
    "qs:photo_sum":2192,
    "qs:placetype":"Suburb",
    "qs:quad_count":83,
    "qs:woe_adm0":23424975,
    "qs:woe_adm1":24554868,
    "qs:woe_adm2":12602146,
    "qs:woe_lau":12696034,
    "qs:woe_local":30599,
    "qs:woe_ver":"7.10.0",
    "wof:lang":[
        "eng"
    ],
    "wof:name":"Cliftonville",
    "wof:placetype":"neighbourhood"
},
  "geometry": {"coordinates":[-0.88201,52.234528],"type":"Point"}
}