{
  "type": "Feature",
  "properties": {
    "gn:admin1_code":"WLS",
    "gn:admin2_code":"X6",
    "gn:admin3_code":"00NQ008",
    "gn:asciiname":"Elerch",
    "gn:country_code":"GB",
    "gn:dem":187,
    "gn:feature_class":"P",
    "gn:feature_code":"PPL",
    "gn:name":"Elerch",
    "gn:population":0,
    "gn:timezone":"Europe/London",
    "iso:country":"GB",
    "wof:name":"Elerch",
    "wof:placetype":"neighbourhood"
},
  "geometry": {"coordinates":[-3.93922,52.46008000000001],"type":"Point"}
}