{
  "type": "Feature",
  "properties": {
    "gn:admin1_code": "ENG",
    "gn:admin2_code": "D6",
    "gn:admin3_code": "19UC",
    "gn:admin4_code": "19UC001",
    "gn:asciiname": "Winkton",
    "gn:country_code": "GB",
    "gn:dem": 10,
    "gn:feature_class": "P",
    "gn:feature_code": "PPL",
    "gn:name": "Winkton",
    "gn:population": 0,
    "gn:timezone": "Europe/London",
    "iso:country": "GB",
    "wof:name": "Winkton",
    "wof:placetype": "neighbourhood"
  },
  "geometry": {"coordinates":[-1.77195,50.76418],"type":"Point"}
}
