{
  "type": "Feature",
  "properties": {
    "iso:country":"GB",
    "name:ben_x_preferred":[
        "\u09b8\u09c7\u09a8\u09cd\u09a1\u09cd\u09b0\u09bf\u099c"
    ],
    "name:ceb_x_preferred":[
        "Sandridge"
    ],
    "name:cym_x_preferred":[
        "Sandridge"
    ],
    "name:deu_x_preferred":[
        "Sandridge"
    ],
    "name:eng_x_preferred":[
        "Sandridge"
    ],
    "name:fas_x_preferred":[
        "\u0633\u0646\u0628\u0631\u06cc\u062c"
    ],
    "name:fra_x_preferred":[
        "Sandridge"
    ],
    "name:gle_x_preferred":[
        "Sandridge"
    ],
    "name:guj_x_preferred":[
        "\u0ab8\u0ac7\u0aa8\u0acd\u0aa1\u0acd\u0ab0\u0ac0\u0a9c"
    ],
    "name:ita_x_preferred":[
        "Sandridge"
    ],
    "name:jpn_x_preferred":[
        "\u30b5\u30f3\u30c9\u30ea\u30c3\u30b8"
    ],
    "name:kan_x_preferred":[
        "\u0cb8\u0ccd\u0caf\u0cbe\u0c82\u0ca1\u0ccd\u0cb0\u0cbf\u0c9c\u0ccd"
    ],
    "name:kor_x_preferred":[
        "\uc0cc\ub4dc\ub9ac\uc9c0"
    ],
    "name:lit_x_preferred":[
        "Sandrid\u017eas"
    ],
    "name:lld_x_preferred":[
        "Sandridge"
    ],
    "name:nld_x_preferred":[
        "Sandridge"
    ],
    "name:pol_x_preferred":[
        "Sandridge"
    ],
    "name:por_x_preferred":[
        "Sandridge"
    ],
    "name:rus_x_preferred":[
        "\u0421\u044d\u043d\u0434\u0440\u0438\u0434\u0436"
    ],
    "name:spa_x_preferred":[
        "Sandridge"
    ],
    "name:tam_x_preferred":[
        "\u0b9a\u0ba3\u0bcd\u0b9f\u0bb0\u0bbf\u0b9f\u0bcd\u0b9c\u0bcd"
    ],
    "name:tel_x_preferred":[
        "\u0c36\u0c3e\u0c02\u0c21\u0c4d\u0c30\u0c3f\u0c21\u0c4d\u0c1c\u0c4d"
    ],
    "name:tur_x_preferred":[
        "Sandridge"
    ],
    "name:urd_x_preferred":[
        "\u0633\u0627\u0646\u062f\u0631\u062c"
    ],
    "name:zho_x_preferred":[
        "\u6851\u5fb7\u91cc\u5947"
    ],
    "qs:gn_adm0_cc":"GB",
    "qs:gn_fcode":"PPL",
    "qs:gn_local":2638867,
    "qs:gn_nam_loc":"langford",
    "qs:gn_namadm1":"ENG",
    "qs:gn_name":"Sandridge",
    "qs:local_max":5477,
    "qs:local_sum":11965,
    "qs:localhoods":6,
    "qs:name":"Sandridge",
    "qs:name_adm0":"United Kingdom",
    "qs:name_adm1":"England",
    "qs:name_adm2":"Hertfordshire",
    "qs:name_lau":"St. Albans City and District",
    "qs:name_local":"St. Albans",
    "qs:photo_max":117,
    "qs:photo_sum":1174,
    "qs:placetype":"Suburb",
    "qs:quad_count":134,
    "qs:woe_adm0":23424975,
    "qs:woe_adm1":24554868,
    "qs:woe_adm2":12602170,
    "qs:woe_lau":12695980,
    "qs:woe_local":35564,
    "qs:woe_ver":"7.10.0",
    "wof:name":"Sandridge",
    "wof:placetype":"neighbourhood"
},
  "geometry": {"coordinates":[-0.276739,51.799877],"type":"Point"}
}