{
  "type": "Feature",
  "properties": {
    "iso:country": "GB",
    "name:ben_x_preferred": [
      "সেন্ড্রিজ"
    ],
    "name:ceb_x_preferred": [
      "Sandridge"
    ],
    "name:cym_x_preferred": [
      "Sandridge"
    ],
    "name:deu_x_preferred": [
      "Sandridge"
    ],
    "name:eng_x_preferred": [
      "Sandridge"
    ],
    "name:fas_x_preferred": [
      "سنبریج"
    ],
    "name:fra_x_preferred": [
      "Sandridge"
    ],
    "name:guj_x_preferred": [
      "સેન્ડ્રીજ"
    ],
    "name:ita_x_preferred": [
      "Sandridge"
    ],
    "name:jpn_x_preferred": [
      "サンドリッジ"
    ],
    "name:kan_x_preferred": [
      "ಸ್ಯಾಂಡ್ರಿಜ್"
    ],
    "name:kor_x_preferred": [
      "샌드리지"
    ],
    "name:lit_x_preferred": [
      "Sandridžas"
    ],
    "name:nld_x_preferred": [
      "Sandridge"
    ],
    "name:pol_x_preferred": [
      "Sandridge"
    ],
    "name:por_x_preferred": [
      "Sandridge"
    ],
    "name:rus_x_preferred": [
      "Сэндридж"
    ],
    "name:spa_x_preferred": [
      "Sandridge"
    ],
    "name:tam_x_preferred": [
      "சண்டரிட்ஜ்"
    ],
    "name:tel_x_preferred": [
      "శాండ్రిడ్జ్"
    ],
    "name:urd_x_preferred": [
      "ساندرج"
    ],
    "qs:gn_adm0_cc": "GB",
    "qs:gn_fcode": "PPL",
    "qs:gn_local": 2638867,
    "qs:gn_nam_loc": "langford",
    "qs:gn_namadm1": "ENG",
    "qs:gn_name": "Sandridge",
    "qs:local_max": 5477,
    "qs:local_sum": 11965,
    "qs:localhoods": 6,
    "qs:name": "Sandridge",
    "qs:name_adm0": "United Kingdom",
    "qs:name_adm1": "England",
    "qs:name_adm2": "Hertfordshire",
    "qs:name_lau": "St. Albans City and District",
    "qs:name_local": "St. Albans",
    "qs:photo_max": 117,
    "qs:photo_sum": 1174,
    "qs:placetype": "Suburb",
    "qs:quad_count": 134,
    "qs:woe_adm0": 23424975,
    "qs:woe_adm1": 24554868,
    "qs:woe_adm2": 12602170,
    "qs:woe_lau": 12695980,
    "qs:woe_local": 35564,
    "qs:woe_ver": "7.10.0",
    "wof:name": "Sandridge",
    "wof:placetype": "neighbourhood"
  },
  "geometry": {"coordinates":[-0.276739,51.799877],"type":"Point"}
}
