{
  "type": "Feature",
  "properties": {
    "iso:country": "GB",
    "name:bre_x_preferred": [
      "Cearrara"
    ],
    "name:cat_x_preferred": [
      "Kerrera"
    ],
    "name:ceb_x_preferred": [
      "Kerrera"
    ],
    "name:deu_x_preferred": [
      "Kerrera"
    ],
    "name:ell_x_preferred": [
      "Κέρρερα"
    ],
    "name:fra_x_preferred": [
      "Kerrera"
    ],
    "name:gla_x_preferred": [
      "Cearrara"
    ],
    "name:gle_x_preferred": [
      "Cearrara"
    ],
    "name:hun_x_preferred": [
      "Kerrera"
    ],
    "name:ita_x_preferred": [
      "Kerrera"
    ],
    "name:nds_x_preferred": [
      "Kerrera"
    ],
    "name:nno_x_preferred": [
      "Kerrera"
    ],
    "name:nor_x_preferred": [
      "Kerrera"
    ],
    "name:rus_x_preferred": [
      "Керрера"
    ],
    "name:spa_x_preferred": [
      "Kerrera"
    ],
    "name:swe_x_preferred": [
      "Kerrera"
    ],
    "name:zho_x_preferred": [
      "凱勒拉島"
    ],
    "qs_pg:aaroncc": "GB",
    "qs_pg:name": "Kerrera",
    "qs_pg:name_adm0": "United Kingdom",
    "qs_pg:name_adm1": "Scotland",
    "qs_pg:photos": 164,
    "qs_pg:photos_1k": 33,
    "qs_pg:photos_9k": 1,
    "qs_pg:photos_9r": 4,
    "qs_pg:photos_all": 164,
    "qs_pg:photos_sr": 4,
    "qs_pg:pop_sr": 0,
    "qs_pg:qs_pg_placetype": "locality",
    "qs_pg:qs_pg_placetype_gp": "Town",
    "qs_pg:woe_adm0": 23424975,
    "woe:adm0_id": 23424975,
    "woe:name_adm0": "United Kingdom",
    "woe:name_adm1": "Scotland",
    "woe:placetype": "Town",
    "wof:name": "Kerrera",
    "wof:placetype": "locality"
  },
  "geometry": {"coordinates":[-5.532817,56.399939],"type":"Point"}
}
