{
  "type": "Feature",
  "properties": {
    "iso:country": "GB",
    "name:cym_x_preferred": [
      "Stanton"
    ],
    "name:eng_x_preferred": [
      "Stanton"
    ],
    "name:nld_x_preferred": [
      "Stanton"
    ],
    "name:pol_x_preferred": [
      "Stanton"
    ],
    "name:pol_x_variant": [
      "Stanton"
    ],
    "qs_pg:aaroncc": "GB",
    "qs_pg:name": "Stanton",
    "qs_pg:name_adm0": "United Kingdom",
    "qs_pg:name_adm1": "England",
    "qs_pg:photos": 6,
    "qs_pg:photos_1k": 1,
    "qs_pg:photos_9k": 1,
    "qs_pg:photos_9r": 1,
    "qs_pg:photos_all": 6,
    "qs_pg:photos_sr": 1,
    "qs_pg:pop_sr": 0,
    "qs_pg:qs_pg_placetype": "locality",
    "qs_pg:qs_pg_placetype_gp": "Town",
    "qs_pg:woe_adm0": 23424975,
    "woe:adm0_id": 23424975,
    "woe:name_adm0": "United Kingdom",
    "woe:name_adm1": "England",
    "woe:placetype": "Town",
    "wof:name": "Stanton",
    "wof:placetype": "neighbourhood"
  },
  "geometry": {"coordinates":[-1.773412,55.218815],"type":"Point"}
}
