{
  "type": "Feature",
  "properties": {
    "gn:country":"GB",
    "gn:fcode":"PPL",
    "gn:population":0,
    "iso:country":"GB",
    "name:ell_x_preferred":[
        "\u03a7\u03ac\u03c1\u03bb\u03bf\u03bf\u03c5 \u03a7\u03b9\u03bb"
    ],
    "name:eng_x_preferred":[
        "Harlow Hill"
    ],
    "name:gle_x_preferred":[
        "Harlow Hill"
    ],
    "name:lld_x_preferred":[
        "Harlow Hill"
    ],
    "name:nld_x_preferred":[
        "Harlow Hill"
    ],
    "name:pol_x_preferred":[
        "Harlow Hill"
    ],
    "name:swe_x_preferred":[
        "Harlow Hill"
    ],
    "qs_pg:aaroncc":"GB",
    "qs_pg:gn_country":"GB",
    "qs_pg:gn_fcode":"PPL",
    "qs_pg:gn_pop":0,
    "qs_pg:name":"Harlow Hill",
    "qs_pg:name_adm0":"United Kingdom",
    "qs_pg:name_adm1":"England",
    "qs_pg:photos":82,
    "qs_pg:photos_1k":17,
    "qs_pg:photos_9k":1,
    "qs_pg:photos_9r":3,
    "qs_pg:photos_all":82,
    "qs_pg:photos_sr":3,
    "qs_pg:pop_sr":0,
    "qs_pg:qs_pg_placetype":"locality",
    "qs_pg:qs_pg_placetype_gp":"Town",
    "qs_pg:woe_adm0":23424975,
    "woe:adm0_id":23424975,
    "woe:name_adm0":"United Kingdom",
    "woe:name_adm1":"England",
    "woe:placetype":"Town",
    "wof:name":"Harlow Hill",
    "wof:placetype":"neighbourhood"
},
  "geometry": {"coordinates":[-1.87848,55.00956],"type":"Point"}
}