{
  "type": "Feature",
  "properties": {
    "gn:country":"GB",
    "gn:fcode":"PPL",
    "gn:population":0,
    "iso:country":"GB",
    "name:ara_x_preferred":[
        "\u062a\u0634\u064a\u0643\u0643\u0633\u0646\u062f\u0633"
    ],
    "name:cym_x_preferred":[
        "Chicksands"
    ],
    "name:eng_x_preferred":[
        "Chicksands"
    ],
    "name:fas_x_preferred":[
        "\u0686\u06cc\u06a9\u0633\u0646\u062f\u0632"
    ],
    "name:fra_x_preferred":[
        "Chicksands"
    ],
    "name:ita_x_preferred":[
        "Chicksands"
    ],
    "name:kor_x_preferred":[
        "\uce59\uc0cc\uc988"
    ],
    "name:nld_x_preferred":[
        "Chicksands"
    ],
    "name:pol_x_preferred":[
        "Chicksands"
    ],
    "name:spa_x_preferred":[
        "Chicksands"
    ],
    "name:vol_x_preferred":[
        "Chicksands"
    ],
    "qs_pg:aaroncc":"GB",
    "qs_pg:gn_country":"GB",
    "qs_pg:gn_fcode":"PPL",
    "qs_pg:gn_pop":0,
    "qs_pg:name":"Chicksands",
    "qs_pg:name_adm0":"United Kingdom",
    "qs_pg:name_adm1":"England",
    "qs_pg:photos":144,
    "qs_pg:photos_1k":29,
    "qs_pg:photos_9k":1,
    "qs_pg:photos_9r":3,
    "qs_pg:photos_all":144,
    "qs_pg:photos_sr":3,
    "qs_pg:pop_sr":0,
    "qs_pg:qs_pg_placetype":"locality",
    "qs_pg:qs_pg_placetype_gp":"Town",
    "qs_pg:woe_adm0":23424975,
    "woe:adm0_id":23424975,
    "woe:name_adm0":"United Kingdom",
    "woe:name_adm1":"England",
    "woe:placetype":"Town",
    "wof:name":"Chicksands",
    "wof:placetype":"neighbourhood",
    "wof:population":1396
},
  "geometry": {"coordinates":[-0.3639,52.04585],"type":"Point"}
}