{
  "type": "Feature",
  "properties": {
    "gn:admin1_code": "SCT",
    "gn:admin2_code": "V3",
    "gn:asciiname": "Gobernuisgeach",
    "gn:cc2": "GB",
    "gn:country_code": "GB",
    "gn:dem": 291,
    "gn:feature_class": "P",
    "gn:feature_code": "PPL",
    "gn:name": "Gobernuisgeach",
    "gn:population": 0,
    "gn:timezone": "Europe/London",
    "iso:country": "GB",
    "name:und_x_variant": [
      "Gobernuisgach",
      "Gobernuisgeach"
    ],
    "wof:name": "Gobernuisgeach",
    "wof:placetype": "locality"
  },
  "geometry": {"coordinates":[-3.73333,58.25],"type":"Point"}
}
