{
  "type": "Feature",
  "properties": {
    "iso:country":"GB",
    "name:eng_x_preferred":[
        "City Centre"
    ],
    "wof:name":"City Centre",
    "wof:placetype":"neighbourhood"
},
  "geometry": {"coordinates":[-1.13142497472678,52.63440492558785],"type":"Point"}
}