{
  "type": "Feature",
  "properties": {
    "iso:country":"GB",
    "name:dut_x_preferred":[
        "Burnt Yates"
    ],
    "name:eng_x_preferred":[
        "Burnt Yates"
    ],
    "name:fre_x_preferred":[
        "Burnt Yates"
    ],
    "name:pol_x_preferred":[
        "Burnt Yates"
    ],
    "qs_pg:aaroncc":"GB",
    "qs_pg:name":"Burnt Yates",
    "qs_pg:name_adm0":"United Kingdom",
    "qs_pg:name_adm1":"England",
    "qs_pg:photos":109,
    "qs_pg:photos_1k":22,
    "qs_pg:photos_9k":1,
    "qs_pg:photos_9r":3,
    "qs_pg:photos_all":109,
    "qs_pg:photos_sr":3,
    "qs_pg:pop_sr":0,
    "qs_pg:qs_pg_placetype":"locality",
    "qs_pg:qs_pg_placetype_gp":"Town",
    "qs_pg:woe_adm0":23424975,
    "woe:adm0_id":23424975,
    "woe:name_adm0":"United Kingdom",
    "woe:name_adm1":"England",
    "woe:placetype":"Town",
    "wof:name":"Burnt Yates",
    "wof:placetype":"neighbourhood"
},
  "geometry": {"coordinates":[-1.609016,54.045486],"type":"Point"}
}