{
  "type": "Feature",
  "properties": {
    "gn:admin1_code":"ENG",
    "gn:admin2_code":"H7",
    "gn:admin3_code":"32UG",
    "gn:admin4_code":"32UG050",
    "gn:asciiname":"Keisby",
    "gn:country_code":"GB",
    "gn:dem":62,
    "gn:feature_class":"P",
    "gn:feature_code":"PPL",
    "gn:name":"Keisby",
    "gn:population":0,
    "gn:timezone":"Europe/London",
    "iso:country":"GB",
    "name:pol_x_preferred":[
        "Keisby"
    ],
    "wof:name":"Keisby",
    "wof:placetype":"neighbourhood"
},
  "geometry": {"coordinates":[-0.45922,52.84463],"type":"Point"}
}