{
  "type": "Feature",
  "properties": {
    "gn:admin1_code":"ENG",
    "gn:admin2_code":"H5",
    "gn:admin3_code":"31UC",
    "gn:admin4_code":"31UC017",
    "gn:asciiname":"Quorn",
    "gn:country_code":"GB",
    "gn:dem":46,
    "gn:feature_class":"P",
    "gn:feature_code":"PPL",
    "gn:name":"Quorn",
    "gn:population":0,
    "gn:timezone":"Europe/London",
    "iso:country":"GB",
    "name:ceb_x_preferred":[
        "Quorn"
    ],
    "name:cym_x_preferred":[
        "Quorn"
    ],
    "name:deu_x_preferred":[
        "Quorn"
    ],
    "name:fas_x_preferred":[
        "\u06a9\u0648\u0631\u0646"
    ],
    "name:ita_x_preferred":[
        "Quorn"
    ],
    "name:pol_x_preferred":[
        "Quorn"
    ],
    "name:spa_x_preferred":[
        "Quorn"
    ],
    "wof:name":"Quorn",
    "wof:placetype":"neighbourhood"
},
  "geometry": {"coordinates":[-1.17173,52.74272],"type":"Point"}
}