{
  "type": "Feature",
  "properties": {
    "gn:country":"GB",
    "iso:country":"GB",
    "qs_pg:aaroncc":"GB",
    "qs_pg:gn_country":"GB",
    "qs_pg:name":"Weighbridge",
    "qs_pg:name_adm0":"United Kingdom",
    "qs_pg:name_adm1":"Channel Islands",
    "qs_pg:photos":298,
    "qs_pg:photos_1k":60,
    "qs_pg:photos_9k":1,
    "qs_pg:photos_9r":4,
    "qs_pg:photos_all":298,
    "qs_pg:photos_sr":5,
    "qs_pg:pop_sr":0,
    "qs_pg:qs_pg_placetype":"locality",
    "qs_pg:qs_pg_placetype_gp":"Town",
    "qs_pg:woe_adm0":23424975,
    "woe:adm0_id":23424975,
    "woe:name_adm0":"United Kingdom",
    "woe:name_adm1":"Channel Islands",
    "woe:placetype":"Town",
    "wof:name":"Weighbridge",
    "wof:placetype":"locality"
},
  "geometry": {"coordinates":[-2.115876,49.181212],"type":"Point"}
}