{
  "type": "Feature",
  "properties": {
    "gn:admin1_code":"SCT",
    "gn:admin2_code":"T5",
    "gn:asciiname":"Shielhill",
    "gn:country_code":"GB",
    "gn:dem":52,
    "gn:feature_class":"P",
    "gn:feature_code":"PPLL",
    "gn:name":"Shielhill",
    "gn:population":0,
    "gn:timezone":"Europe/London",
    "iso:country":"GB",
    "wof:name":"Shielhill",
    "wof:placetype":"locality"
},
  "geometry": {"coordinates":[-2.10925,57.20708000000001],"type":"Point"}
}