{
  "type": "Feature",
  "properties": {
    "iso:country": "GB",
    "name:cym_x_preferred": [
      "Castell Penrhyn"
    ],
    "name:deu_x_preferred": [
      "Penrhyn Castle"
    ],
    "name:eus_x_preferred": [
      "Penrhyn gaztelua"
    ],
    "name:pol_x_preferred": [
      "Zamek Penrhyn"
    ],
    "name:rus_x_preferred": [
      "Пенрин"
    ],
    "name:zho_x_preferred": [
      "彭林城堡"
    ],
    "qs_pg:aaroncc": "GB",
    "qs_pg:name": "Penrhyn Castle",
    "qs_pg:name_adm0": "United Kingdom",
    "qs_pg:name_adm1": "Wales",
    "qs_pg:photos": 420,
    "qs_pg:photos_1k": 85,
    "qs_pg:photos_9k": 2,
    "qs_pg:photos_9r": 5,
    "qs_pg:photos_all": 420,
    "qs_pg:photos_sr": 6,
    "qs_pg:pop_sr": 0,
    "qs_pg:qs_pg_placetype": "locality",
    "qs_pg:qs_pg_placetype_gp": "Town",
    "qs_pg:woe_adm0": 23424975,
    "woe:adm0_id": 23424975,
    "woe:name_adm0": "United Kingdom",
    "woe:name_adm1": "Wales",
    "woe:placetype": "Town",
    "wof:name": "Penrhyn Castle",
    "wof:placetype": "neighbourhood"
  },
  "geometry": {"coordinates":[-4.095368,53.226316],"type":"Point"}
}
