{
  "type": "Feature",
  "properties": {
    "gn:country":"GB",
    "gn:fcode":"PPL",
    "gn:population":0,
    "iso:country":"GB",
    "name:eng_x_preferred":[
        "Sollas"
    ],
    "name:eus_x_preferred":[
        "Sollas"
    ],
    "name:fra_x_preferred":[
        "Sollas"
    ],
    "name:gla_x_preferred":[
        "Solas"
    ],
    "name:gle_x_preferred":[
        "Solas"
    ],
    "name:jpn_x_preferred":[
        "\u30bd\u30e9\u30b9"
    ],
    "name:nld_x_preferred":[
        "Sollas"
    ],
    "qs_pg:aaroncc":"GB",
    "qs_pg:gn_country":"GB",
    "qs_pg:gn_fcode":"PPL",
    "qs_pg:gn_pop":0,
    "qs_pg:name":"Sollas",
    "qs_pg:name_adm0":"United Kingdom",
    "qs_pg:name_adm1":"Scotland",
    "qs_pg:photos":47,
    "qs_pg:photos_1k":10,
    "qs_pg:photos_9k":1,
    "qs_pg:photos_9r":2,
    "qs_pg:photos_all":47,
    "qs_pg:photos_sr":2,
    "qs_pg:pop_sr":0,
    "qs_pg:qs_pg_placetype":"locality",
    "qs_pg:qs_pg_placetype_gp":"Town",
    "qs_pg:woe_adm0":23424975,
    "woe:adm0_id":23424975,
    "woe:name_adm0":"United Kingdom",
    "woe:name_adm1":"Scotland",
    "woe:placetype":"Town",
    "wof:name":"Sollas",
    "wof:placetype":"locality"
},
  "geometry": {"coordinates":[-7.35,57.65],"type":"Point"}
}