{
  "type": "Feature",
  "properties": {
    "gn:gn_country":"GB",
    "gn:gn_fcode":"PPL",
    "gn:gn_pop":6392,
    "gn:population":5984,
    "iso:country":"GB",
    "name:ceb_x_preferred":[
        "St Leonards"
    ],
    "name:cym_x_preferred":[
        "St Leonards"
    ],
    "name:eng_x_preferred":[
        "St Leonards"
    ],
    "name:eng_x_variant":[
        "Saint Leonards"
    ],
    "name:fra_x_preferred":[
        "St Leonards"
    ],
    "name:nld_x_preferred":[
        "St Leonards"
    ],
    "name:pol_x_preferred":[
        "St Leonards "
    ],
    "name:pol_x_variant":[
        "St Leonards"
    ],
    "name:spa_x_preferred":[
        "St Leonards"
    ],
    "name:swe_x_preferred":[
        "St Leonards "
    ],
    "name:swe_x_variant":[
        "St Leonards"
    ],
    "qs_pg:aaroncc":"GB",
    "qs_pg:gn_country":"GB",
    "qs_pg:gn_fcode":"PPL",
    "qs_pg:gn_pop":6392,
    "qs_pg:name":"St. Leonards",
    "qs_pg:name_adm0":"United Kingdom",
    "qs_pg:name_adm1":"England",
    "qs_pg:photos":48,
    "qs_pg:photos_1k":10,
    "qs_pg:photos_9k":1,
    "qs_pg:photos_9r":2,
    "qs_pg:photos_all":48,
    "qs_pg:photos_sr":2,
    "qs_pg:pop_sr":5,
    "qs_pg:qs_pg_placetype":"locality",
    "qs_pg:qs_pg_placetype_gp":"Town",
    "qs_pg:woe_adm0":23424975,
    "woe:adm0_id":23424975,
    "woe:name_adm0":"United Kingdom",
    "woe:name_adm1":"England",
    "woe:placetype":"Town",
    "wof:name":"St. Leonards",
    "wof:placetype":"neighbourhood",
    "wof:population":5984
},
  "geometry": {"coordinates":[-1.85,50.83333],"type":"Point"}
}