{
  "type": "Feature",
  "properties": {
    "iso:country": "GB",
    "name:ben_x_preferred": [
      "কাডওর্থ"
    ],
    "name:ceb_x_preferred": [
      "Cudworth"
    ],
    "name:deu_x_preferred": [
      "Cudworth"
    ],
    "name:eng_x_preferred": [
      "Cudworth"
    ],
    "name:fas_x_preferred": [
      "کادورث"
    ],
    "name:fra_x_preferred": [
      "Cudworth"
    ],
    "name:guj_x_preferred": [
      "કડવર્થ"
    ],
    "name:ita_x_preferred": [
      "Cudworth"
    ],
    "name:jpn_x_preferred": [
      "カッドワース"
    ],
    "name:kan_x_preferred": [
      "ಕುಡ್ವರ್ತ್"
    ],
    "name:kor_x_preferred": [
      "커드워스"
    ],
    "name:lit_x_preferred": [
      "Kladvortas"
    ],
    "name:nld_x_preferred": [
      "Cudworth"
    ],
    "name:pol_x_preferred": [
      "Cudworth"
    ],
    "name:por_x_preferred": [
      "Cudworth"
    ],
    "name:rus_x_preferred": [
      "Кадворф"
    ],
    "name:spa_x_preferred": [
      "Cudworth"
    ],
    "name:swe_x_preferred": [
      "Cudworth"
    ],
    "name:swe_x_variant": [
      "Cudworth"
    ],
    "name:tam_x_preferred": [
      "கூஒர்த்"
    ],
    "name:tel_x_preferred": [
      "కుడ్వర్త్"
    ],
    "name:urd_x_preferred": [
      "کودوورتھ"
    ],
    "name:zho_x_preferred": [
      "卡德沃思"
    ],
    "qs:a0": "United Kingdom",
    "qs:a1": "*Barnsley",
    "qs:a1_lc": "GB12CC0000",
    "qs:a1r": "0England",
    "qs:a1r_lc": "GB12000000",
    "qs:adm0": "United Kingdom",
    "qs:la_lc": "*",
    "qs:level": "locality",
    "qs:loc": "Cudworth",
    "qs:loc_alt": "Cudworth",
    "qs:pop": 0,
    "qs:type": "buffered point",
    "wof:name": "Cudworth",
    "wof:placetype": "neighbourhood"
  },
  "geometry": {"coordinates":[-1.413038,53.57893],"type":"Point"}
}
