{
  "type": "Feature",
  "properties": {
    "iso:country":"GB",
    "name:ben_x_preferred":[
        "\u0995\u09be\u09a1\u0993\u09b0\u09cd\u09a5"
    ],
    "name:ceb_x_preferred":[
        "Cudworth"
    ],
    "name:deu_x_preferred":[
        "Cudworth"
    ],
    "name:eng_x_preferred":[
        "Cudworth"
    ],
    "name:fas_x_preferred":[
        "\u06a9\u0627\u062f\u0648\u0631\u062b"
    ],
    "name:fra_x_preferred":[
        "Cudworth"
    ],
    "name:guj_x_preferred":[
        "\u0a95\u0aa1\u0ab5\u0ab0\u0acd\u0aa5"
    ],
    "name:ita_x_preferred":[
        "Cudworth"
    ],
    "name:jpn_x_preferred":[
        "\u30ab\u30c3\u30c9\u30ef\u30fc\u30b9"
    ],
    "name:kan_x_preferred":[
        "\u0c95\u0cc1\u0ca1\u0ccd\u0cb5\u0cb0\u0ccd\u0ca4\u0ccd"
    ],
    "name:kor_x_preferred":[
        "\ucee4\ub4dc\uc6cc\uc2a4"
    ],
    "name:lit_x_preferred":[
        "Kladvortas"
    ],
    "name:nld_x_preferred":[
        "Cudworth"
    ],
    "name:pol_x_preferred":[
        "Cudworth"
    ],
    "name:por_x_preferred":[
        "Cudworth"
    ],
    "name:rus_x_preferred":[
        "\u041a\u0430\u0434\u0432\u043e\u0440\u0444"
    ],
    "name:spa_x_preferred":[
        "Cudworth"
    ],
    "name:swe_x_preferred":[
        "Cudworth "
    ],
    "name:swe_x_variant":[
        "Cudworth"
    ],
    "name:tam_x_preferred":[
        "\u0b95\u0bc2\u0b92\u0bb0\u0bcd\u0ba4\u0bcd"
    ],
    "name:tel_x_preferred":[
        "\u0c15\u0c41\u0c21\u0c4d\u0c35\u0c30\u0c4d\u0c24\u0c4d"
    ],
    "name:urd_x_preferred":[
        "\u06a9\u0648\u062f\u0648\u0648\u0631\u062a\u06be"
    ],
    "name:zho_x_preferred":[
        "\u5361\u5fb7\u6c83\u601d"
    ],
    "qs:a0":"United Kingdom",
    "qs:a1":"*Barnsley",
    "qs:a1_lc":"GB12CC0000",
    "qs:a1r":"0England",
    "qs:a1r_lc":"GB12000000",
    "qs:adm0":"United Kingdom",
    "qs:la_lc":"*",
    "qs:level":"locality",
    "qs:loc":"Cudworth",
    "qs:loc_alt":"Cudworth",
    "qs:pop":0,
    "qs:type":"buffered point",
    "wof:name":"Cudworth",
    "wof:placetype":"neighbourhood"
},
  "geometry": {"coordinates":[-1.413038,53.57893],"type":"Point"}
}