{
  "type": "Feature",
  "properties": {
    "iso:country":"GB",
    "name:eng_x_preferred":[
        "Bonehill"
    ],
    "qs:a0":"United Kingdom",
    "qs:a1":"*Staffordshire",
    "qs:a1_lc":"GB12410000",
    "qs:a1r":"0England",
    "qs:a1r_lc":"GB12000000",
    "qs:adm0":"United Kingdom",
    "qs:la_lc":"*",
    "qs:level":"locality",
    "qs:loc":"Bonehill",
    "qs:loc_alt":"Bonehill",
    "qs:pop":0,
    "qs:type":"buffered point",
    "wof:name":"Bonehill",
    "wof:placetype":"neighbourhood"
},
  "geometry": {"coordinates":[-1.715113,52.617887],"type":"Point"}
}