{
  "type": "Feature",
  "properties": {
    "gn:admin1_code":"SCT",
    "gn:admin2_code":"U2",
    "gn:asciiname":"Castlewigg",
    "gn:country_code":"GB",
    "gn:dem":84,
    "gn:feature_class":"P",
    "gn:feature_code":"PPL",
    "gn:name":"Castlewigg",
    "gn:population":0,
    "gn:timezone":"Europe/London",
    "iso:country":"GB",
    "wof:name":"Castlewigg",
    "wof:placetype":"locality"
},
  "geometry": {"coordinates":[-4.43333,54.75],"type":"Point"}
}