{
  "type": "Feature",
  "properties": {
    "iso:country":"GB",
    "name:cat_x_preferred":[
        "Sedbury"
    ],
    "name:cym_x_preferred":[
        "Sedbury"
    ],
    "name:eng_x_preferred":[
        "Sedbury"
    ],
    "name:fas_x_preferred":[
        "\u0633\u062f\u0628\u0631\u06cc"
    ],
    "name:fra_x_preferred":[
        "Sedbury"
    ],
    "name:gle_x_preferred":[
        "Sedbury"
    ],
    "name:nld_x_preferred":[
        "Sedbury"
    ],
    "name:pol_x_preferred":[
        "Sedbury"
    ],
    "name:por_x_preferred":[
        "Sedbury"
    ],
    "name:spa_x_preferred":[
        "Sedbury"
    ],
    "name:swe_x_preferred":[
        "Sedbury"
    ],
    "qs_pg:aaroncc":"GB",
    "qs_pg:name":"Sedbury",
    "qs_pg:name_adm0":"United Kingdom",
    "qs_pg:name_adm1":"England",
    "qs_pg:photos":184,
    "qs_pg:photos_1k":37,
    "qs_pg:photos_9k":1,
    "qs_pg:photos_9r":4,
    "qs_pg:photos_all":184,
    "qs_pg:photos_sr":4,
    "qs_pg:pop_sr":0,
    "qs_pg:qs_pg_placetype":"locality",
    "qs_pg:qs_pg_placetype_gp":"Town",
    "qs_pg:woe_adm0":23424975,
    "woe:adm0_id":23424975,
    "woe:name_adm0":"United Kingdom",
    "woe:name_adm1":"England",
    "woe:placetype":"Town",
    "wof:name":"Sedbury",
    "wof:placetype":"neighbourhood"
},
  "geometry": {"coordinates":[-2.662467,51.643169],"type":"Point"}
}