{
  "type": "Feature",
  "properties": {
    "iso:country":"GB",
    "name:ceb_x_preferred":[
        "Gosforth"
    ],
    "name:gle_x_preferred":[
        "Gosforth"
    ],
    "name:ita_x_preferred":[
        "Gosforth"
    ],
    "name:jpn_x_preferred":[
        "\u30b4\u30b9\u30d5\u30a9\u30fc\u30b9"
    ],
    "name:nor_x_preferred":[
        "Gosforth"
    ],
    "name:pol_x_preferred":[
        "Gosforth"
    ],
    "name:swe_x_preferred":[
        "Gosforth"
    ],
    "wof:name":"Gosforth",
    "wof:placetype":"neighbourhood"
},
  "geometry": {"coordinates":[-1.62100409765766,55.00993469759008],"type":"Point"}
}