{
  "type": "Feature",
  "properties": {
    "gn:country":"GB",
    "gn:fcode":"PPL",
    "gn:population":0,
    "iso:country":"GB",
    "name:deu_x_preferred":[
        "Forgandenny"
    ],
    "name:eng_x_preferred":[
        "Forgandenny"
    ],
    "name:eus_x_preferred":[
        "Forgandenny"
    ],
    "name:fas_x_preferred":[
        "\u0641\u0648\u0631\u06af\u0646\u062f\u0646\u06cc"
    ],
    "name:fra_x_preferred":[
        "Forgandenny"
    ],
    "name:gla_x_preferred":[
        "Forgrann Eithne"
    ],
    "name:gle_x_preferred":[
        "Forgrann Eithne"
    ],
    "name:ita_x_preferred":[
        "Forgandenny"
    ],
    "name:nld_x_preferred":[
        "Forgandenny"
    ],
    "name:spa_x_preferred":[
        "Forgandenny"
    ],
    "name:swe_x_preferred":[
        "Forgandenny"
    ],
    "qs_pg:aaroncc":"GB",
    "qs_pg:gn_country":"GB",
    "qs_pg:gn_fcode":"PPL",
    "qs_pg:gn_pop":0,
    "qs_pg:name":"Forgandenny",
    "qs_pg:name_adm0":"United Kingdom",
    "qs_pg:name_adm1":"Scotland",
    "qs_pg:photos":52,
    "qs_pg:photos_1k":11,
    "qs_pg:photos_9k":1,
    "qs_pg:photos_9r":2,
    "qs_pg:photos_all":52,
    "qs_pg:photos_sr":2,
    "qs_pg:pop_sr":0,
    "qs_pg:qs_pg_placetype":"locality",
    "qs_pg:qs_pg_placetype_gp":"Town",
    "qs_pg:woe_adm0":23424975,
    "woe:adm0_id":23424975,
    "woe:name_adm0":"United Kingdom",
    "woe:name_adm1":"Scotland",
    "woe:placetype":"Town",
    "wof:name":"Forgandenny",
    "wof:placetype":"locality",
    "wof:population":590
},
  "geometry": {"coordinates":[-3.47841,56.34596],"type":"Point"}
}