{
  "type": "Feature",
  "properties": {
    "iso:country":"GB",
    "name:ceb_x_preferred":[
        "Welford-on-Avon"
    ],
    "name:eng_x_preferred":[
        "Welford-on-Avon"
    ],
    "name:fra_x_preferred":[
        "Welford-on-Avon"
    ],
    "name:jpn_x_preferred":[
        "\u30a6\u30a7\u30eb\u30d5\u30a9\u30fc\u30c9\u30fb\u30aa\u30f3\u30fb\u30a2\u30dd\u30f3"
    ],
    "name:nld_x_preferred":[
        "Welford-on-Avon"
    ],
    "name:pol_x_preferred":[
        "Welford-on-Avon"
    ],
    "name:spa_x_preferred":[
        "Welford-on-Avon"
    ],
    "name:swe_x_preferred":[
        "Welford-on-Avon"
    ],
    "qs_pg:aaroncc":"GB",
    "qs_pg:name":"Welford on Avon",
    "qs_pg:name_adm0":"United Kingdom",
    "qs_pg:name_adm1":"England",
    "qs_pg:photos":94,
    "qs_pg:photos_1k":19,
    "qs_pg:photos_9k":1,
    "qs_pg:photos_9r":3,
    "qs_pg:photos_all":94,
    "qs_pg:photos_sr":3,
    "qs_pg:pop_sr":0,
    "qs_pg:qs_pg_placetype":"locality",
    "qs_pg:qs_pg_placetype_gp":"Town",
    "qs_pg:woe_adm0":23424975,
    "woe:adm0_id":23424975,
    "woe:name_adm0":"United Kingdom",
    "woe:name_adm1":"England",
    "woe:placetype":"Town",
    "wof:name":"Welford on Avon",
    "wof:placetype":"neighbourhood"
},
  "geometry": {"coordinates":[-1.788368,52.16793],"type":"Point"}
}