{
  "type": "Feature",
  "properties": {
    "gn:country":"GB",
    "gn:fcode":"PPL",
    "gn:population":2003,
    "iso:country":"GB",
    "name:ceb_x_preferred":[
        "Southowram"
    ],
    "name:eng_x_preferred":[
        "Southowram"
    ],
    "name:fra_x_preferred":[
        "Southowram"
    ],
    "name:gle_x_preferred":[
        "Southowram"
    ],
    "name:lld_x_preferred":[
        "Southowram"
    ],
    "name:nld_x_preferred":[
        "Southowram"
    ],
    "name:pol_x_preferred":[
        "Southowram"
    ],
    "name:swe_x_preferred":[
        "Southowram"
    ],
    "qs_pg:aaroncc":"GB",
    "qs_pg:gn_country":"GB",
    "qs_pg:gn_fcode":"PPL",
    "qs_pg:gn_pop":2003,
    "qs_pg:name":"Southowram",
    "qs_pg:name_adm0":"United Kingdom",
    "qs_pg:name_adm1":"England",
    "qs_pg:photos":37,
    "qs_pg:photos_1k":7,
    "qs_pg:photos_9k":1,
    "qs_pg:photos_9r":2,
    "qs_pg:photos_all":37,
    "qs_pg:photos_sr":2,
    "qs_pg:pop_sr":4,
    "qs_pg:qs_pg_placetype":"locality",
    "qs_pg:qs_pg_placetype_gp":"Town",
    "qs_pg:woe_adm0":23424975,
    "woe:adm0_id":23424975,
    "woe:name_adm0":"United Kingdom",
    "woe:name_adm1":"England",
    "woe:placetype":"Town",
    "wof:name":"Southowram",
    "wof:placetype":"neighbourhood",
    "wof:population":2003
},
  "geometry": {"coordinates":[-1.83181,53.70988],"type":"Point"}
}