{
  "type": "Feature",
  "properties": {
    "iso:country":"GB",
    "name:eng_x_preferred":[
        "Saint Matthew's"
    ],
    "name:eng_x_variant":[
        "St. Matthew's"
    ],
    "wof:name":"Saint Matthew's",
    "wof:placetype":"neighbourhood"
},
  "geometry": {"coordinates":[-1.12311369887747,52.6416015126032],"type":"Point"}
}