{
  "type": "Feature",
  "properties": {
    "gn:country":"GB",
    "gn:fcode":"PPL",
    "gn:population":0,
    "iso:country":"GB",
    "name:cym_x_preferred":[
        "Llansanffraid Gwynll\u0175g"
    ],
    "name:eng_x_preferred":[
        "St. Brides Wentloog"
    ],
    "name:eng_x_variant":[
        "Saint Brides Wentlooge"
    ],
    "name:eus_x_preferred":[
        "St. Brides Wentloog"
    ],
    "name:nld_x_preferred":[
        "St. Brides Wentloog"
    ],
    "qs_pg:aaroncc":"GB",
    "qs_pg:gn_country":"GB",
    "qs_pg:gn_fcode":"PPL",
    "qs_pg:gn_pop":0,
    "qs_pg:name":"St. Brides Wentlooge",
    "qs_pg:name_adm0":"United Kingdom",
    "qs_pg:name_adm1":"Wales",
    "qs_pg:photos":119,
    "qs_pg:photos_1k":24,
    "qs_pg:photos_9k":1,
    "qs_pg:photos_9r":3,
    "qs_pg:photos_all":119,
    "qs_pg:photos_sr":3,
    "qs_pg:pop_sr":0,
    "qs_pg:qs_pg_placetype":"locality",
    "qs_pg:qs_pg_placetype_gp":"Town",
    "qs_pg:woe_adm0":23424975,
    "woe:adm0_id":23424975,
    "woe:name_adm0":"United Kingdom",
    "woe:name_adm1":"Wales",
    "woe:placetype":"Town",
    "wof:name":"St. Brides Wentlooge",
    "wof:placetype":"neighbourhood"
},
  "geometry": {"coordinates":[-3.0175,51.53389],"type":"Point"}
}