{
  "type": "Feature",
  "properties": {
    "gn:admin1_code":"ENG",
    "gn:admin2_code":"N5",
    "gn:admin3_code":"42UF",
    "gn:admin4_code":"42UF049",
    "gn:asciiname":"Lackford Green",
    "gn:country_code":"GB",
    "gn:dem":17,
    "gn:feature_class":"P",
    "gn:feature_code":"PPL",
    "gn:name":"Lackford Green",
    "gn:population":0,
    "gn:timezone":"Europe/London",
    "iso:country":"GB",
    "wof:name":"Lackford Green",
    "wof:placetype":"neighbourhood"
},
  "geometry": {"coordinates":[0.62099,52.3062],"type":"Point"}
}