{
  "type": "Feature",
  "properties": {
    "iso:country": "GB",
    "name:ceb_x_preferred": [
      "Drayton"
    ],
    "name:deu_x_preferred": [
      "Drayton"
    ],
    "name:eng_x_preferred": [
      "Drayton"
    ],
    "name:fra_x_preferred": [
      "Drayton"
    ],
    "name:ita_x_preferred": [
      "Drayton"
    ],
    "name:jpn_x_preferred": [
      "ドレイトン"
    ],
    "name:nds_x_preferred": [
      "Drayton"
    ],
    "name:nld_x_preferred": [
      "Drayton"
    ],
    "name:pol_x_preferred": [
      "Drayton"
    ],
    "name:rus_x_preferred": [
      "Дрейтон"
    ],
    "name:swe_x_preferred": [
      "Drayton"
    ],
    "qs:gn_fcode": "PPLX",
    "qs:gn_local": 0,
    "qs:gn_namadm1": "ENG",
    "qs:gn_name": "Drayton",
    "qs:local_max": 5349,
    "qs:local_sum": 51768,
    "qs:localhoods": 25,
    "qs:name": "Drayton",
    "qs:name_adm0": "United Kingdom",
    "qs:name_adm1": "England",
    "qs:name_adm2": "Hampshire",
    "qs:name_lau": "Portsmouth City",
    "qs:name_local": "Portsmouth",
    "qs:photo_max": 63,
    "qs:photo_sum": 432,
    "qs:placetype": "Suburb",
    "qs:quad_count": 36,
    "qs:woe_adm0": 23424975,
    "qs:woe_adm1": 24554868,
    "qs:woe_adm2": 12602169,
    "qs:woe_lau": 12696158,
    "qs:woe_local": 32452,
    "qs:woe_ver": "7.10.0",
    "wd:wordcount": 140,
    "wof:lang": [
      "eng"
    ],
    "wof:name": "Drayton",
    "wof:placetype": "neighbourhood"
  },
  "geometry": {"coordinates":[-1.046406,50.846304],"type":"Point"}
}
