{
  "type": "Feature",
  "properties": {
    "gn:population": 7899,
    "iso:country": "GB",
    "name:ben_x_preferred": [
      "স্টোরিংটন"
    ],
    "name:bul_x_preferred": [
      "Сторингтон"
    ],
    "name:ceb_x_preferred": [
      "Storrington"
    ],
    "name:deu_x_preferred": [
      "Storrington"
    ],
    "name:eng_x_preferred": [
      "Storrington"
    ],
    "name:fra_x_preferred": [
      "Storrington"
    ],
    "name:guj_x_preferred": [
      "સ્ટોરિંગટન"
    ],
    "name:jpn_x_preferred": [
      "ストーリントン"
    ],
    "name:kan_x_preferred": [
      "ಸ್ಟಾರಿಂಗ್ಟನ್"
    ],
    "name:kor_x_preferred": [
      "스토링턴"
    ],
    "name:lit_x_preferred": [
      "Storingtonas"
    ],
    "name:nld_x_preferred": [
      "Storrington"
    ],
    "name:pol_x_preferred": [
      "Storrington"
    ],
    "name:por_x_preferred": [
      "Storrington"
    ],
    "name:rus_x_preferred": [
      "Сторингтон"
    ],
    "name:spa_x_preferred": [
      "Storrington"
    ],
    "name:swe_x_preferred": [
      "Storrington"
    ],
    "name:tam_x_preferred": [
      "ஸ்டோரிங்டன்"
    ],
    "name:tel_x_preferred": [
      "స్టోర్రింగ్టన్"
    ],
    "name:urd_x_preferred": [
      "ستورینجٹن"
    ],
    "qs:a0": "United Kingdom",
    "qs:a1": "*West Sussex",
    "qs:a1_lc": "GB12450000",
    "qs:a1r": "0England",
    "qs:a1r_lc": "GB12000000",
    "qs:adm0": "United Kingdom",
    "qs:la_lc": "*",
    "qs:level": "locality",
    "qs:loc": "Storrington",
    "qs:loc_alt": "Storrington",
    "qs:pop": 0,
    "qs:type": "buffered point",
    "wd:wordcount": 781,
    "wof:lang": [
      "eng"
    ],
    "wof:name": "Storrington",
    "wof:placetype": "neighbourhood",
    "wof:population": 7899
  },
  "geometry": {"coordinates":[-0.451871,50.91702],"type":"Point"}
}
