{
  "type": "Feature",
  "properties": {
    "gn:population":7899,
    "iso:country":"GB",
    "name:ben_x_preferred":[
        "\u09b8\u09cd\u099f\u09cb\u09b0\u09bf\u0982\u099f\u09a8"
    ],
    "name:bul_x_preferred":[
        "\u0421\u0442\u043e\u0440\u0438\u043d\u0433\u0442\u043e\u043d"
    ],
    "name:ceb_x_preferred":[
        "Storrington"
    ],
    "name:deu_x_preferred":[
        "Storrington"
    ],
    "name:eng_x_preferred":[
        "Storrington"
    ],
    "name:fra_x_preferred":[
        "Storrington"
    ],
    "name:guj_x_preferred":[
        "\u0ab8\u0acd\u0a9f\u0acb\u0ab0\u0abf\u0a82\u0a97\u0a9f\u0aa8"
    ],
    "name:jpn_x_preferred":[
        "\u30b9\u30c8\u30fc\u30ea\u30f3\u30c8\u30f3"
    ],
    "name:kan_x_preferred":[
        "\u0cb8\u0ccd\u0c9f\u0cbe\u0cb0\u0cbf\u0c82\u0c97\u0ccd\u0c9f\u0ca8\u0ccd"
    ],
    "name:kor_x_preferred":[
        "\uc2a4\ud1a0\ub9c1\ud134"
    ],
    "name:lit_x_preferred":[
        "Storingtonas"
    ],
    "name:nld_x_preferred":[
        "Storrington"
    ],
    "name:pol_x_preferred":[
        "Storrington"
    ],
    "name:por_x_preferred":[
        "Storrington"
    ],
    "name:rus_x_preferred":[
        "\u0421\u0442\u043e\u0440\u0438\u043d\u0433\u0442\u043e\u043d"
    ],
    "name:spa_x_preferred":[
        "Storrington"
    ],
    "name:swe_x_preferred":[
        "Storrington"
    ],
    "name:tam_x_preferred":[
        "\u0bb8\u0bcd\u0b9f\u0bcb\u0bb0\u0bbf\u0b99\u0bcd\u0b9f\u0ba9\u0bcd"
    ],
    "name:tel_x_preferred":[
        "\u0c38\u0c4d\u0c1f\u0c4b\u0c30\u0c4d\u0c30\u0c3f\u0c02\u0c17\u0c4d\u0c1f\u0c28\u0c4d"
    ],
    "name:urd_x_preferred":[
        "\u0633\u062a\u0648\u0631\u06cc\u0646\u062c\u0679\u0646"
    ],
    "qs:a0":"United Kingdom",
    "qs:a1":"*West Sussex",
    "qs:a1_lc":"GB12450000",
    "qs:a1r":"0England",
    "qs:a1r_lc":"GB12000000",
    "qs:adm0":"United Kingdom",
    "qs:la_lc":"*",
    "qs:level":"locality",
    "qs:loc":"Storrington",
    "qs:loc_alt":"Storrington",
    "qs:pop":0,
    "qs:type":"buffered point",
    "wd:wordcount":781,
    "wof:lang":[
        "eng"
    ],
    "wof:name":"Storrington",
    "wof:placetype":"neighbourhood",
    "wof:population":7899
},
  "geometry": {"coordinates":[-0.451871,50.91702],"type":"Point"}
}