{
  "type": "Feature",
  "properties": {
    "iso:country":"GB",
    "name:eng_x_preferred":[
        "Boughspring"
    ],
    "name:fre_x_preferred":[
        "Boughspring"
    ],
    "name:pol_x_preferred":[
        "Boughspring"
    ],
    "qs_pg:aaroncc":"GB",
    "qs_pg:name":"Boughspring",
    "qs_pg:name_adm0":"United Kingdom",
    "qs_pg:name_adm1":"England",
    "qs_pg:photos":211,
    "qs_pg:photos_1k":43,
    "qs_pg:photos_9k":1,
    "qs_pg:photos_9r":4,
    "qs_pg:photos_all":211,
    "qs_pg:photos_sr":4,
    "qs_pg:pop_sr":0,
    "qs_pg:qs_pg_placetype":"locality",
    "qs_pg:qs_pg_placetype_gp":"Town",
    "qs_pg:woe_adm0":23424975,
    "woe:adm0_id":23424975,
    "woe:name_adm0":"United Kingdom",
    "woe:name_adm1":"England",
    "woe:placetype":"Town",
    "wof:name":"Boughspring",
    "wof:placetype":"neighbourhood"
},
  "geometry": {"coordinates":[-2.660236,51.675376],"type":"Point"}
}