{
  "type": "Feature",
  "properties": {
    "gn:admin1_code":"SCT",
    "gn:admin2_code":"T6",
    "gn:asciiname":"Cushnie",
    "gn:country_code":"GB",
    "gn:dem":262,
    "gn:feature_class":"P",
    "gn:feature_code":"PPL",
    "gn:name":"Cushnie",
    "gn:population":0,
    "gn:timezone":"Europe/London",
    "iso:country":"GB",
    "wof:name":"Cushnie",
    "wof:placetype":"locality"
},
  "geometry": {"coordinates":[-2.81667,57.31667],"type":"Point"}
}