{
  "type": "Feature",
  "properties": {
    "gn:admin1_code":"SCT",
    "gn:admin2_code":"T6",
    "gn:asciiname":"Whitestone",
    "gn:country_code":"GB",
    "gn:dem":93,
    "gn:feature_class":"P",
    "gn:feature_code":"PPL",
    "gn:name":"Whitestone",
    "gn:population":0,
    "gn:timezone":"Europe/London",
    "iso:country":"GB",
    "name:ceb_x_preferred":[
        "Whitestone"
    ],
    "name:fra_x_preferred":[
        "Whitestone"
    ],
    "name:pol_x_preferred":[
        "Whitestone"
    ],
    "name:swe_x_preferred":[
        "Whitestone"
    ],
    "wof:name":"Whitestone",
    "wof:placetype":"locality"
},
  "geometry": {"coordinates":[-2.59531,57.022],"type":"Point"}
}