{
  "type": "Feature",
  "properties": {
    "iso:country":"GB",
    "name:eng_x_preferred":[
        "Clay Bottom"
    ],
    "wof:name":"Clay Bottom",
    "wof:placetype":"neighbourhood"
},
  "geometry": {"coordinates":[-2.54571668185184,51.47171619908446],"type":"Point"}
}