{
  "type": "Feature",
  "properties": {
    "iso:country":"GB",
    "name:cor_x_preferred":[
        "Trethmahonyer"
    ],
    "name:cym_x_preferred":[
        "Helford Passage"
    ],
    "name:cym_x_variant":[
        "Trethmahonyer"
    ],
    "name:eng_x_preferred":[
        "Helford Passage"
    ],
    "name:eus_x_preferred":[
        "Helford Passage"
    ],
    "name:eus_x_variant":[
        "Trethmahonyer"
    ],
    "name:fra_x_preferred":[
        "Helford Passage"
    ],
    "name:gle_x_preferred":[
        "Trethmahonyer"
    ],
    "name:nld_x_preferred":[
        "Helford Passage"
    ],
    "name:pol_x_preferred":[
        "Helford Passage"
    ],
    "qs_pg:aaroncc":"GB",
    "qs_pg:name":"Helford Passage",
    "qs_pg:name_adm0":"United Kingdom",
    "qs_pg:name_adm1":"England",
    "qs_pg:photos":287,
    "qs_pg:photos_1k":58,
    "qs_pg:photos_9k":1,
    "qs_pg:photos_9r":4,
    "qs_pg:photos_all":287,
    "qs_pg:photos_sr":5,
    "qs_pg:pop_sr":0,
    "qs_pg:qs_pg_placetype":"locality",
    "qs_pg:qs_pg_placetype_gp":"Town",
    "qs_pg:woe_adm0":23424975,
    "woe:adm0_id":23424975,
    "woe:name_adm0":"United Kingdom",
    "woe:name_adm1":"England",
    "woe:placetype":"Town",
    "wof:name":"Helford Passage",
    "wof:placetype":"neighbourhood"
},
  "geometry": {"coordinates":[-5.128941,50.100156],"type":"Point"}
}