{
  "type": "Feature",
  "properties": {
    "gn:admin1_code":"NIR",
    "gn:admin2_code":"N09000010",
    "gn:asciiname":"Cullaville",
    "gn:cc2":"GB",
    "gn:country_code":"GB",
    "gn:dem":117,
    "gn:feature_class":"P",
    "gn:feature_code":"PPL",
    "gn:name":"Cullaville",
    "gn:population":0,
    "gn:timezone":"Europe/London",
    "iso:country":"GB",
    "name:eus_x_preferred":[
        "Cullaville"
    ],
    "name:msa_x_preferred":[
        "Cullaville"
    ],
    "name:pli_x_preferred":[
        "\u0915\u0932\u094d\u0932\u093e\u0935\u093f\u0932\u094d\u0932\u0947"
    ],
    "name:spa_x_preferred":[
        "Cullaville"
    ],
    "name:und_x_variant":[
        "Culloville"
    ],
    "wof:name":"Cullaville",
    "wof:placetype":"locality"
},
  "geometry": {"coordinates":[-6.63333,54.06667],"type":"Point"}
}