{
  "type": "Feature",
  "properties": {
    "gn:population":2354,
    "iso:country":"GB",
    "name:bul_x_preferred":[
        "\u0410\u043b\u0439\u0442\u0445"
    ],
    "name:ceb_x_preferred":[
        "Alyth"
    ],
    "name:ces_x_preferred":[
        "Alyth"
    ],
    "name:cym_x_preferred":[
        "Alyth"
    ],
    "name:deu_x_preferred":[
        "Alyth"
    ],
    "name:eng_x_preferred":[
        "Alyth"
    ],
    "name:eus_x_preferred":[
        "Alyth"
    ],
    "name:fas_x_preferred":[
        "\u0627\u0644\u06cc\u062b"
    ],
    "name:fra_x_preferred":[
        "Alyth"
    ],
    "name:gla_x_preferred":[
        "\u00c0ilt"
    ],
    "name:gle_x_preferred":[
        "Ailt"
    ],
    "name:heb_x_preferred":[
        "\u05d0\u05dc\u05d9\u05d9\u05ea'"
    ],
    "name:hun_x_preferred":[
        "Alyth"
    ],
    "name:ita_x_preferred":[
        "Alyth"
    ],
    "name:nld_x_preferred":[
        "Alyth"
    ],
    "name:nno_x_preferred":[
        "Alyth"
    ],
    "name:nob_x_preferred":[
        "Alyth"
    ],
    "name:nor_x_preferred":[
        "Alyth"
    ],
    "name:sco_x_preferred":[
        "Ailyth"
    ],
    "name:spa_x_preferred":[
        "Alyth"
    ],
    "name:swe_x_preferred":[
        "Alyth"
    ],
    "qs:a0":"United Kingdom",
    "qs:a1":"*Perth and Kinross",
    "qs:a1_lc":"GB11RB0000",
    "qs:a1r":"0Scotland",
    "qs:a1r_lc":"GB11000000",
    "qs:adm0":"United Kingdom",
    "qs:la_lc":"*",
    "qs:level":"locality",
    "qs:loc":"Alyth",
    "qs:loc_alt":"Alyth",
    "qs:pop":0,
    "qs:type":"buffered point",
    "wd:wordcount":870,
    "wof:name":"Alyth",
    "wof:placetype":"locality",
    "wof:population":2354
},
  "geometry": {"coordinates":[-3.232547,56.624562],"type":"Point"}
}