{
  "type": "Feature",
  "properties": {
    "gn:country":"GB",
    "gn:fcode":"PPL",
    "gn:population":18330,
    "iso:country":"GB",
    "name:ceb_x_preferred":[
        "Mansfield Woodhouse"
    ],
    "name:eng_x_preferred":[
        "Mansfield Woodhouse"
    ],
    "name:fas_x_preferred":[
        "\u0645\u0646\u0632\u0641\u06cc\u0644\u062f \u0648\u0648\u062f\u0647\u0627\u0648\u0633"
    ],
    "name:fra_x_preferred":[
        "Mansfield Woodhouse"
    ],
    "name:gle_x_preferred":[
        "Mansfield Woodhouse"
    ],
    "name:ita_x_preferred":[
        "Mansfield Woodhouse"
    ],
    "name:nan_x_preferred":[
        "Mansfield Woodhouse"
    ],
    "name:nld_x_preferred":[
        "Mansfield Woodhouse"
    ],
    "name:nob_x_preferred":[
        "Mansfield Woodhouse"
    ],
    "name:pol_x_preferred":[
        "Mansfield Woodhouse"
    ],
    "name:rus_x_preferred":[
        "\u041c\u0430\u043d\u0441\u0444\u0438\u043b\u0434-\u0412\u0443\u0434\u0445\u0430\u0443\u0441"
    ],
    "name:swe_x_preferred":[
        "Mansfield Woodhouse"
    ],
    "name:urd_x_preferred":[
        "\u0645\u06cc\u0646\u0633\u0641\u06cc\u0644\u0688 \u0648\u0648\u0688 \u06c1\u0627\u0624\u0633"
    ],
    "name:vol_x_preferred":[
        "Mansfield Woodhouse"
    ],
    "name:zho_x_preferred":[
        "\u66fc\u65af\u83f2\u5c14\u5fb7\u4f0d\u5fb7\u8c6a\u65af"
    ],
    "qs_pg:aaroncc":"GB",
    "qs_pg:gn_country":"GB",
    "qs_pg:gn_fcode":"PPL",
    "qs_pg:gn_pop":18330,
    "qs_pg:name":"Mansfield Woodhouse",
    "qs_pg:name_adm0":"United Kingdom",
    "qs_pg:name_adm1":"England",
    "qs_pg:photos":441,
    "qs_pg:photos_1k":89,
    "qs_pg:photos_9k":2,
    "qs_pg:photos_9r":5,
    "qs_pg:photos_all":441,
    "qs_pg:photos_sr":6,
    "qs_pg:pop_sr":6,
    "qs_pg:qs_pg_placetype":"locality",
    "qs_pg:qs_pg_placetype_gp":"Town",
    "qs_pg:woe_adm0":23424975,
    "woe:adm0_id":23424975,
    "woe:name_adm0":"United Kingdom",
    "woe:name_adm1":"England",
    "woe:placetype":"Town",
    "wof:name":"Mansfield Woodhouse",
    "wof:placetype":"neighbourhood",
    "wof:population":18330
},
  "geometry": {"coordinates":[-1.19384,53.16495],"type":"Point"}
}