{
  "type": "Feature",
  "properties": {
    "iso:country":"GB",
    "name:eng_x_preferred":[
        "Achateny"
    ],
    "name:gle_x_preferred":[
        "Achadh an Teine"
    ],
    "name:nld_x_preferred":[
        "Achateny"
    ],
    "name:swe_x_preferred":[
        "Achateny Water"
    ],
    "qs_pg:aaroncc":"GB",
    "qs_pg:name":"Achateny",
    "qs_pg:name_adm0":"United Kingdom",
    "qs_pg:name_adm1":"Scotland",
    "qs_pg:photos":28,
    "qs_pg:photos_1k":6,
    "qs_pg:photos_9k":1,
    "qs_pg:photos_9r":2,
    "qs_pg:photos_all":28,
    "qs_pg:photos_sr":2,
    "qs_pg:pop_sr":0,
    "qs_pg:qs_pg_placetype":"locality",
    "qs_pg:qs_pg_placetype_gp":"Town",
    "qs_pg:woe_adm0":23424975,
    "woe:adm0_id":23424975,
    "woe:name_adm0":"United Kingdom",
    "woe:name_adm1":"Scotland",
    "woe:placetype":"Town",
    "wof:name":"Achateny",
    "wof:placetype":"locality"
},
  "geometry": {"coordinates":[-6.039733,56.757051],"type":"Point"}
}