{
  "type": "Feature",
  "properties": {
    "gn:admin1_code":"SCT",
    "gn:admin2_code":"T8",
    "gn:asciiname":"Torloisk House",
    "gn:country_code":"GB",
    "gn:dem":77,
    "gn:feature_class":"P",
    "gn:feature_code":"PPL",
    "gn:name":"Torloisk House",
    "gn:population":0,
    "gn:timezone":"Europe/London",
    "iso:country":"GB",
    "wof:name":"Torloisk House",
    "wof:placetype":"locality"
},
  "geometry": {"coordinates":[-6.2138,56.5323],"type":"Point"}
}