{
  "type": "Feature",
  "properties": {
    "iso:country":"GB",
    "name:bre_x_preferred":[
        "Charlestown"
    ],
    "name:cat_x_preferred":[
        "Charlestown"
    ],
    "name:ceb_x_preferred":[
        "Charlestown"
    ],
    "name:deu_x_preferred":[
        "Charlestown"
    ],
    "name:eng_x_preferred":[
        "Charlestown"
    ],
    "name:est_x_preferred":[
        "Charlestown"
    ],
    "name:eus_x_preferred":[
        "Charlestown"
    ],
    "name:fin_x_preferred":[
        "Charlestown"
    ],
    "name:fra_x_preferred":[
        "Charlestown"
    ],
    "name:hun_x_preferred":[
        "Charlestown"
    ],
    "name:ita_x_preferred":[
        "Charlestown"
    ],
    "name:jpn_x_preferred":[
        "\u30c1\u30e3\u30fc\u30eb\u30ba\u30bf\u30a6\u30f3"
    ],
    "name:kor_x_preferred":[
        "\ucc30\uc2a4\ud0c0\uc6b4"
    ],
    "name:mlg_x_preferred":[
        "Charlestown"
    ],
    "name:nld_x_preferred":[
        "Charlestown"
    ],
    "name:pol_x_preferred":[
        "Charlestown"
    ],
    "name:por_x_preferred":[
        "Charlestown"
    ],
    "name:rus_x_preferred":[
        "\u0427\u0430\u0440\u043b\u0441\u0442\u0430\u0443\u043d"
    ],
    "name:slv_x_preferred":[
        "Charlestown"
    ],
    "name:spa_x_preferred":[
        "Charlestown"
    ],
    "name:srp_x_preferred":[
        "\u0427\u0430\u0440\u043b\u0441\u0442\u0430\u0443\u043d"
    ],
    "name:swe_x_preferred":[
        "Charlestown"
    ],
    "name:ukr_x_preferred":[
        "\u0427\u0430\u0440\u043b\u0441\u0442\u0430\u0443\u043d"
    ],
    "name:urd_x_preferred":[
        "\u0686\u0627\u0631\u0644\u0633 \u0679\u0627\u0624\u0646"
    ],
    "name:vep_x_preferred":[
        "\u010carlstaun"
    ],
    "name:vol_x_preferred":[
        "Charlestown"
    ],
    "name:zho_x_preferred":[
        "\u67e5\u5c14\u65af\u6566"
    ],
    "qs:gn_adm0_cc":"GB",
    "qs:gn_local":2634889,
    "qs:gn_nam_loc":"woodside",
    "qs:gn_namadm1":"ENG",
    "qs:local_max":5266,
    "qs:local_sum":14155,
    "qs:localhoods":6,
    "qs:name":"Charlestown",
    "qs:name_adm0":"United Kingdom",
    "qs:name_adm1":"England",
    "qs:name_adm2":"Greater Manchester",
    "qs:name_lau":"Salford Metropolitan Borough",
    "qs:name_local":"Salford",
    "qs:photo_max":393,
    "qs:photo_sum":1894,
    "qs:placetype":"Suburb",
    "qs:quad_count":85,
    "qs:woe_adm0":23424975,
    "qs:woe_adm1":24554868,
    "qs:woe_adm2":12602158,
    "qs:woe_lau":12695844,
    "qs:woe_local":33887,
    "qs:woe_ver":"7.10.0",
    "wd:wordcount":145,
    "wof:lang":[
        "eng"
    ],
    "wof:name":"Charlestown",
    "wof:placetype":"neighbourhood"
},
  "geometry": {"coordinates":[-2.281811,53.497396],"type":"Point"}
}