{
  "type": "Feature",
  "properties": {
    "gn:admin1_code":"ENG",
    "gn:admin2_code":"Z6",
    "gn:admin3_code":"00KC039",
    "gn:asciiname":"Newmill End",
    "gn:country_code":"GB",
    "gn:dem":98,
    "gn:feature_class":"P",
    "gn:feature_code":"PPL",
    "gn:name":"Newmill End",
    "gn:population":0,
    "gn:timezone":"Europe/London",
    "iso:country":"GB",
    "wof:name":"Newmill End",
    "wof:placetype":"neighbourhood"
},
  "geometry": {"coordinates":[-0.37405,51.85041],"type":"Point"}
}