{
  "type": "Feature",
  "properties": {
    "iso:country":"GB",
    "name:eng_x_preferred":[
        "Littleover"
    ],
    "name:eng_x_variant":[
        "Littlecover"
    ],
    "name:gle_x_preferred":[
        "Littleover"
    ],
    "name:jpn_x_preferred":[
        "\u30ea\u30c8\u30eb\u30aa\u30fc\u30d0\u30fc"
    ],
    "name:pol_x_preferred":[
        "Littleover"
    ],
    "qs:gn_adm0_cc":"GB",
    "qs:gn_fcode":"PPL",
    "qs:gn_local":2650000,
    "qs:gn_nam_loc":"rauceby",
    "qs:gn_namadm1":"ENG",
    "qs:gn_name":"Littleover",
    "qs:local_max":4610,
    "qs:local_sum":19661,
    "qs:localhoods":15,
    "qs:name":"Littleover",
    "qs:name_adm0":"United Kingdom",
    "qs:name_adm1":"England",
    "qs:name_adm2":"Derbyshire",
    "qs:name_lau":"Derby City",
    "qs:name_local":"Derby",
    "qs:photo_max":28,
    "qs:photo_sum":254,
    "qs:placetype":"Suburb",
    "qs:quad_count":48,
    "qs:woe_adm0":23424975,
    "qs:woe_adm1":24554868,
    "qs:woe_adm2":12602143,
    "qs:woe_lau":12696153,
    "qs:woe_local":18114,
    "qs:woe_ver":"7.10.0",
    "wd:wordcount":768,
    "wof:lang":[
        "eng"
    ],
    "wof:name":"Littleover",
    "wof:placetype":"neighbourhood"
},
  "geometry": {"coordinates":[-1.526868,52.89636],"type":"Point"}
}