{
  "type": "Feature",
  "properties": {
    "gn:country": "GB",
    "gn:fcode": "PPL",
    "gn:population": 978,
    "iso:country": "GB",
    "name:bul_x_preferred": [
      "Тарвес"
    ],
    "name:ceb_x_preferred": [
      "Tarves"
    ],
    "name:cym_x_preferred": [
      "Tarves"
    ],
    "name:eng_x_preferred": [
      "Tarves"
    ],
    "name:eus_x_preferred": [
      "Tarves"
    ],
    "name:fra_x_preferred": [
      "Tarves"
    ],
    "name:gle_x_preferred": [
      "Tarbhais"
    ],
    "name:ita_x_preferred": [
      "Tarves"
    ],
    "name:nld_x_preferred": [
      "Tarves"
    ],
    "name:spa_x_preferred": [
      "Tarves"
    ],
    "name:swe_x_preferred": [
      "Tarves"
    ],
    "qs_pg:aaroncc": "GB",
    "qs_pg:gn_country": "GB",
    "qs_pg:gn_fcode": "PPL",
    "qs_pg:gn_pop": 978,
    "qs_pg:name": "Tarves",
    "qs_pg:name_adm0": "United Kingdom",
    "qs_pg:name_adm1": "Scotland",
    "qs_pg:photos": 636,
    "qs_pg:photos_1k": 129,
    "qs_pg:photos_9k": 3,
    "qs_pg:photos_9r": 5,
    "qs_pg:photos_all": 636,
    "qs_pg:photos_sr": 8,
    "qs_pg:pop_sr": 2,
    "qs_pg:qs_pg_placetype": "locality",
    "qs_pg:qs_pg_placetype_gp": "Town",
    "qs_pg:woe_adm0": 23424975,
    "woe:adm0_id": 23424975,
    "woe:name_adm0": "United Kingdom",
    "woe:name_adm1": "Scotland",
    "woe:placetype": "Town",
    "wof:name": "Tarves",
    "wof:placetype": "locality",
    "wof:population": 1000
  },
  "geometry": {"coordinates":[-2.22195,57.37079],"type":"Point"}
}
