{
  "type": "Feature",
  "properties": {
    "gn:gn_country":"GB",
    "gn:gn_fcode":"PPL",
    "gn:gn_pop":978,
    "gn:population":1000,
    "iso:country":"GB",
    "name:baq_x_preferred":[
        "Tarves"
    ],
    "name:bul_x_preferred":[
        "\u0422\u0430\u0440\u0432\u0435\u0441"
    ],
    "name:dut_x_preferred":[
        "Tarves"
    ],
    "name:eng_x_preferred":[
        "Tarves"
    ],
    "name:fre_x_preferred":[
        "Tarves"
    ],
    "name:gle_x_preferred":[
        "Tarbhais"
    ],
    "name:swe_x_preferred":[
        "Tarves"
    ],
    "name:wel_x_preferred":[
        "Tarves"
    ],
    "qs_pg:aaroncc":"GB",
    "qs_pg:gn_country":"GB",
    "qs_pg:gn_fcode":"PPL",
    "qs_pg:gn_pop":978,
    "qs_pg:name":"Tarves",
    "qs_pg:name_adm0":"United Kingdom",
    "qs_pg:name_adm1":"Scotland",
    "qs_pg:photos":636,
    "qs_pg:photos_1k":129,
    "qs_pg:photos_9k":3,
    "qs_pg:photos_9r":5,
    "qs_pg:photos_all":636,
    "qs_pg:photos_sr":8,
    "qs_pg:pop_sr":2,
    "qs_pg:qs_pg_placetype":"locality",
    "qs_pg:qs_pg_placetype_gp":"Town",
    "qs_pg:woe_adm0":23424975,
    "woe:adm0_id":23424975,
    "woe:name_adm0":"United Kingdom",
    "woe:name_adm1":"Scotland",
    "woe:placetype":"Town",
    "wof:name":"Tarves",
    "wof:placetype":"locality",
    "wof:population":1000
},
  "geometry": {"coordinates":[-2.22195,57.37079],"type":"Point"}
}