{
  "type": "Feature",
  "properties": {
    "iso:country":"GB",
    "name:cat_x_preferred":[
        "Buckland"
    ],
    "name:dan_x_preferred":[
        "Buckland"
    ],
    "name:deu_x_preferred":[
        "Buckland"
    ],
    "name:eng_x_preferred":[
        "Buckland"
    ],
    "name:fas_x_preferred":[
        "\u0628\u0627\u06a9\u0644\u0646\u062f"
    ],
    "name:fra_x_preferred":[
        "Buckland"
    ],
    "name:hbs_x_preferred":[
        "Bakland"
    ],
    "name:ita_x_preferred":[
        "Buckland"
    ],
    "name:nld_x_preferred":[
        "Buckland"
    ],
    "name:pol_x_preferred":[
        "Buckland"
    ],
    "name:por_x_preferred":[
        "Buckland"
    ],
    "name:rus_x_preferred":[
        "\u0411\u0430\u043a\u043b\u0435\u043d\u0434"
    ],
    "name:spa_x_preferred":[
        "Buckland"
    ],
    "name:srp_x_preferred":[
        "\u0411\u0430\u043a\u043b\u0430\u043d\u0434"
    ],
    "name:unk_x_variant":[
        "Buckland"
    ],
    "name:vol_x_preferred":[
        "Buckland"
    ],
    "qs:gn_fcode":"PPLX",
    "qs:gn_local":0,
    "qs:gn_namadm1":"ENG",
    "qs:gn_name":"Buckland",
    "qs:local_max":5349,
    "qs:local_sum":51768,
    "qs:localhoods":25,
    "qs:name":"Buckland",
    "qs:name_adm0":"United Kingdom",
    "qs:name_adm1":"England",
    "qs:name_adm2":"Hampshire",
    "qs:name_lau":"Portsmouth City",
    "qs:name_local":"Portsmouth",
    "qs:photo_max":391,
    "qs:photo_sum":1469,
    "qs:placetype":"Suburb",
    "qs:quad_count":30,
    "qs:woe_adm0":23424975,
    "qs:woe_adm1":24554868,
    "qs:woe_adm2":12602169,
    "qs:woe_lau":12696158,
    "qs:woe_local":32452,
    "qs:woe_ver":"7.10.0",
    "wof:lang":[
        "eng"
    ],
    "wof:name":"Buckland",
    "wof:placetype":"neighbourhood"
},
  "geometry": {"coordinates":[-1.089434,50.803761],"type":"Point"}
}