{
  "type": "Feature",
  "properties": {
    "iso:country":"GB",
    "name:dut_x_preferred":[
        "Harrington"
    ],
    "name:eng_x_preferred":[
        "High Harrington"
    ],
    "name:gle_x_preferred":[
        "Harrington"
    ],
    "name:ita_x_preferred":[
        "Harrington"
    ],
    "name:nld_x_preferred":[
        "Harrington"
    ],
    "name:pol_x_preferred":[
        "Harrington"
    ],
    "qs:a0":"United Kingdom",
    "qs:a1":"*Cumbria",
    "qs:a1_lc":"GB12160000",
    "qs:a1r":"0England",
    "qs:a1r_lc":"GB12000000",
    "qs:adm0":"United Kingdom",
    "qs:la_lc":"*",
    "qs:level":"locality",
    "qs:loc":"High Harrington",
    "qs:loc_alt":"High Harrington",
    "qs:pop":0,
    "qs:type":"buffered point",
    "wd:wordcount":485,
    "wof:name":"High Harrington",
    "wof:placetype":"neighbourhood"
},
  "geometry": {"coordinates":[-3.545684,54.614603],"type":"Point"}
}