{
  "type": "Feature",
  "properties": {
    "iso:country": "GB",
    "name:ceb_x_preferred": [
      "Berwyn"
    ],
    "name:deu_x_preferred": [
      "Berwyn"
    ],
    "name:fra_x_preferred": [
      "Berwyn"
    ],
    "name:ita_x_preferred": [
      "Berwyn"
    ],
    "name:nld_x_preferred": [
      "Berwyn"
    ],
    "name:pol_x_preferred": [
      "Berwyn"
    ],
    "name:por_x_preferred": [
      "Berwyn"
    ],
    "name:srp_x_preferred": [
      "Бервин"
    ],
    "name:swe_x_preferred": [
      "Berwyn"
    ],
    "name:ukr_x_preferred": [
      "Бервін"
    ],
    "name:vol_x_preferred": [
      "Berwyn"
    ],
    "qs_pg:aaroncc": "GB",
    "qs_pg:name": "Berwyn",
    "qs_pg:name_adm0": "United Kingdom",
    "qs_pg:name_adm1": "Wales",
    "qs_pg:photos": 697,
    "qs_pg:photos_1k": 141,
    "qs_pg:photos_9k": 3,
    "qs_pg:photos_9r": 5,
    "qs_pg:photos_all": 697,
    "qs_pg:photos_sr": 8,
    "qs_pg:pop_sr": 0,
    "qs_pg:qs_pg_placetype": "locality",
    "qs_pg:qs_pg_placetype_gp": "Town",
    "qs_pg:woe_adm0": 23424975,
    "woe:adm0_id": 23424975,
    "woe:name_adm0": "United Kingdom",
    "woe:name_adm1": "Wales",
    "woe:placetype": "Town",
    "wof:name": "Berwyn",
    "wof:placetype": "neighbourhood"
  },
  "geometry": {"coordinates":[-3.196946,52.980379],"type":"Point"}
}
