{
  "type": "Feature",
  "properties": {
    "iso:country":"GB",
    "name:bul_x_preferred":[
        "\u0422\u043e\u043b\u0431\u044a\u0442 \u0413\u0440\u0438\u0439\u043d"
    ],
    "name:dut_x_preferred":[
        "Talbot Green"
    ],
    "name:eng_x_preferred":[
        "Talbot Green"
    ],
    "name:fre_x_preferred":[
        "Talbot Green"
    ],
    "name:wel_x_preferred":[
        "Tonysguboriau"
    ],
    "qs_pg:aaroncc":"GB",
    "qs_pg:name":"Talbot Green",
    "qs_pg:name_adm0":"United Kingdom",
    "qs_pg:name_adm1":"Wales",
    "qs_pg:photos":38,
    "qs_pg:photos_1k":8,
    "qs_pg:photos_9k":1,
    "qs_pg:photos_9r":2,
    "qs_pg:photos_all":38,
    "qs_pg:photos_sr":2,
    "qs_pg:pop_sr":0,
    "qs_pg:qs_pg_placetype":"locality",
    "qs_pg:qs_pg_placetype_gp":"Town",
    "qs_pg:woe_adm0":23424975,
    "woe:adm0_id":23424975,
    "woe:name_adm0":"United Kingdom",
    "woe:name_adm1":"Wales",
    "woe:placetype":"Town",
    "wof:name":"Talbot Green",
    "wof:placetype":"neighbourhood"
},
  "geometry": {"coordinates":[-3.391427,51.5329815],"type":"Point"}
}