{
  "type": "Feature",
  "properties": {
    "iso:country":"GB",
    "name:eng_x_preferred":[
        "Upper Dicker"
    ],
    "name:gle_x_preferred":[
        "Upper Dicker"
    ],
    "name:pol_x_preferred":[
        "Upper Dicker"
    ],
    "name:spa_x_preferred":[
        "Upper Dicker"
    ],
    "name:swe_x_preferred":[
        "Upper Dicker"
    ],
    "qs_pg:aaroncc":"GB",
    "qs_pg:name":"Upper Dicker",
    "qs_pg:name_adm0":"United Kingdom",
    "qs_pg:name_adm1":"England",
    "qs_pg:photos":142,
    "qs_pg:photos_1k":29,
    "qs_pg:photos_9k":1,
    "qs_pg:photos_9r":3,
    "qs_pg:photos_all":142,
    "qs_pg:photos_sr":3,
    "qs_pg:pop_sr":0,
    "qs_pg:qs_pg_placetype":"locality",
    "qs_pg:qs_pg_placetype_gp":"Town",
    "qs_pg:woe_adm0":23424975,
    "woe:adm0_id":23424975,
    "woe:name_adm0":"United Kingdom",
    "woe:name_adm1":"England",
    "woe:placetype":"Town",
    "wof:name":"Upper Dicker",
    "wof:placetype":"neighbourhood"
},
  "geometry": {"coordinates":[0.214061,50.871844],"type":"Point"}
}