{
  "type": "Feature",
  "properties": {
    "iso:country": "GB",
    "name:eng_x_preferred": [
      "Hardraw"
    ],
    "name:fra_x_preferred": [
      "Hardraw"
    ],
    "name:nld_x_preferred": [
      "Hardraw"
    ],
    "name:pol_x_preferred": [
      "Hardraw"
    ],
    "qs_pg:aaroncc": "GB",
    "qs_pg:name": "Hardraw",
    "qs_pg:name_adm0": "United Kingdom",
    "qs_pg:name_adm1": "England",
    "qs_pg:photos": 649,
    "qs_pg:photos_1k": 132,
    "qs_pg:photos_9k": 3,
    "qs_pg:photos_9r": 5,
    "qs_pg:photos_all": 649,
    "qs_pg:photos_sr": 8,
    "qs_pg:pop_sr": 0,
    "qs_pg:qs_pg_placetype": "locality",
    "qs_pg:qs_pg_placetype_gp": "Town",
    "qs_pg:woe_adm0": 23424975,
    "woe:adm0_id": 23424975,
    "woe:name_adm0": "United Kingdom",
    "woe:name_adm1": "England",
    "woe:placetype": "Town",
    "wof:name": "Hardraw",
    "wof:placetype": "neighbourhood"
  },
  "geometry": {"coordinates":[-2.205376,54.316923],"type":"Point"}
}
