{
  "type": "Feature",
  "properties": {
    "gn:admin1_code":"ENG",
    "gn:admin2_code":"H7",
    "gn:admin3_code":"32UC",
    "gn:admin4_code":"32UC011",
    "gn:asciiname":"Saleby",
    "gn:country_code":"GB",
    "gn:dem":13,
    "gn:feature_class":"P",
    "gn:feature_code":"PPL",
    "gn:name":"Saleby",
    "gn:population":0,
    "gn:timezone":"Europe/London",
    "iso:country":"GB",
    "name:cym_x_preferred":[
        "Saleby"
    ],
    "name:pol_x_preferred":[
        "Saleby"
    ],
    "wof:name":"Saleby",
    "wof:placetype":"neighbourhood"
},
  "geometry": {"coordinates":[0.18428,53.28561],"type":"Point"}
}