{
  "type": "Feature",
  "properties": {
    "gn:gn_country":"GB",
    "gn:gn_fcode":"PPL",
    "gn:gn_pop":0,
    "iso:country":"GB",
    "name:ceb_x_preferred":[
        "Southrepps"
    ],
    "name:cym_x_preferred":[
        "Southrepps"
    ],
    "name:fas_x_preferred":[
        "\u0633\u0627\u0648\u062a\u0631\u067e\u0633"
    ],
    "name:ita_x_preferred":[
        "Southrepps"
    ],
    "name:nld_x_preferred":[
        "Southrepps"
    ],
    "name:pol_x_preferred":[
        "Southrepps"
    ],
    "name:por_x_preferred":[
        "Southrepps"
    ],
    "name:spa_x_preferred":[
        "Southrepps"
    ],
    "name:swe_x_preferred":[
        "Southrepps"
    ],
    "qs_pg:aaroncc":"GB",
    "qs_pg:gn_country":"GB",
    "qs_pg:gn_fcode":"PPL",
    "qs_pg:gn_pop":0,
    "qs_pg:name":"Southrepps",
    "qs_pg:name_adm0":"United Kingdom",
    "qs_pg:name_adm1":"England",
    "qs_pg:photos":111,
    "qs_pg:photos_1k":22,
    "qs_pg:photos_9k":1,
    "qs_pg:photos_9r":3,
    "qs_pg:photos_all":111,
    "qs_pg:photos_sr":3,
    "qs_pg:pop_sr":0,
    "qs_pg:qs_pg_placetype":"locality",
    "qs_pg:qs_pg_placetype_gp":"Town",
    "qs_pg:woe_adm0":23424975,
    "woe:adm0_id":23424975,
    "woe:name_adm0":"United Kingdom",
    "woe:name_adm1":"England",
    "woe:placetype":"Town",
    "wof:name":"Southrepps",
    "wof:placetype":"neighbourhood"
},
  "geometry": {"coordinates":[1.33724,52.90423],"type":"Point"}
}