{
  "type": "Feature",
  "properties": {
    "gn:country": "GB",
    "gn:fcode": "PPL",
    "gn:population": 50,
    "iso:country": "GB",
    "name:ceb_x_preferred": [
      "Sandyford"
    ],
    "name:eus_x_preferred": [
      "Sandyford"
    ],
    "name:pol_x_preferred": [
      "Sandyford"
    ],
    "name:rus_x_preferred": [
      "Сандифорд"
    ],
    "name:swe_x_preferred": [
      "Sandyford"
    ],
    "name:urd_x_preferred": [
      "سینڈی فورڈ"
    ],
    "qs_pg:aaroncc": "GB",
    "qs_pg:gn_country": "GB",
    "qs_pg:gn_fcode": "PPL",
    "qs_pg:gn_pop": 50,
    "qs_pg:name": "Sandyford",
    "qs_pg:name_adm0": "United Kingdom",
    "qs_pg:name_adm1": "England",
    "qs_pg:photos": 417,
    "qs_pg:photos_1k": 84,
    "qs_pg:photos_9k": 2,
    "qs_pg:photos_9r": 5,
    "qs_pg:photos_all": 417,
    "qs_pg:photos_sr": 6,
    "qs_pg:pop_sr": 1,
    "qs_pg:qs_pg_placetype": "locality",
    "qs_pg:qs_pg_placetype_gp": "Town",
    "qs_pg:woe_adm0": 23424975,
    "woe:adm0_id": 23424975,
    "woe:name_adm0": "United Kingdom",
    "woe:name_adm1": "England",
    "woe:placetype": "Town",
    "wof:name": "Sandyford",
    "wof:placetype": "neighbourhood",
    "wof:population": 50
  },
  "geometry": {"coordinates":[-2.62367,52.90259],"type":"Point"}
}
