{
  "type": "Feature",
  "properties": {
    "iso:country": "GB",
    "name:bre_x_preferred": [
      "Mynydd-y-garreg"
    ],
    "name:cym_x_preferred": [
      "Mynydd-y-garreg"
    ],
    "name:eng_x_preferred": [
      "Mynydd-y-Garreg"
    ],
    "name:fra_x_preferred": [
      "Mynydd-y-Garreg"
    ],
    "name:nld_x_preferred": [
      "Mynydd-y-Garreg"
    ],
    "qs_pg:aaroncc": "GB",
    "qs_pg:name": "Mynyddygarreg",
    "qs_pg:name_adm0": "United Kingdom",
    "qs_pg:name_adm1": "Wales",
    "qs_pg:photos": 31,
    "qs_pg:photos_1k": 6,
    "qs_pg:photos_9k": 1,
    "qs_pg:photos_9r": 2,
    "qs_pg:photos_all": 31,
    "qs_pg:photos_sr": 2,
    "qs_pg:pop_sr": 0,
    "qs_pg:qs_pg_placetype": "locality",
    "qs_pg:qs_pg_placetype_gp": "Town",
    "qs_pg:woe_adm0": 23424975,
    "woe:adm0_id": 23424975,
    "woe:name_adm0": "United Kingdom",
    "woe:name_adm1": "Wales",
    "woe:placetype": "Town",
    "wof:name": "Mynyddygarreg",
    "wof:placetype": "neighbourhood"
  },
  "geometry": {"coordinates":[-4.305438,51.740011],"type":"Point"}
}
