{
  "type": "Feature",
  "properties": {
    "gn:admin1_code":"ENG",
    "gn:admin2_code":"D4",
    "gn:admin3_code":"18UG",
    "gn:admin4_code":"18UG045",
    "gn:asciiname":"Inner Hope",
    "gn:country_code":"GB",
    "gn:dem":35,
    "gn:feature_class":"P",
    "gn:feature_code":"PPLL",
    "gn:name":"Inner Hope",
    "gn:population":249,
    "gn:timezone":"Europe/London",
    "iso:country":"GB",
    "name:und_x_variant":[
        "Hope Cove"
    ],
    "wof:name":"Inner Hope",
    "wof:placetype":"neighbourhood",
    "wof:population":249
},
  "geometry": {"coordinates":[-3.85692,50.24352],"type":"Point"}
}