{
  "type": "Feature",
  "properties": {
    "iso:country":"GB",
    "wof:name":"Littlemoor Bottom",
    "wof:placetype":"neighbourhood"
},
  "geometry": {"coordinates":[-1.65868500049711,53.78955333626499],"type":"Point"}
}