{
  "type": "Feature",
  "properties": {
    "gn:admin1_code":"SCT",
    "gn:admin2_code":"W1",
    "gn:asciiname":"Finnart",
    "gn:country_code":"GB",
    "gn:dem":283,
    "gn:feature_class":"P",
    "gn:feature_code":"PPL",
    "gn:name":"Finnart",
    "gn:population":0,
    "gn:timezone":"Europe/London",
    "iso:country":"GB",
    "wof:name":"Finnart",
    "wof:placetype":"locality"
},
  "geometry": {"coordinates":[-4.41667,56.66667],"type":"Point"}
}