{
  "type": "Feature",
  "properties": {
    "iso:country":"GB",
    "name:eng_x_preferred":[
        "Alvaston"
    ],
    "name:fra_x_preferred":[
        "Alvaston"
    ],
    "name:gle_x_preferred":[
        "Alvaston"
    ],
    "name:jpn_x_preferred":[
        "\u30a2\u30eb\u30d0\u30b9\u30c8\u30f3"
    ],
    "name:pol_x_preferred":[
        "Alvaston"
    ],
    "name:unk_x_variant":[
        "Alvaston"
    ],
    "name:vol_x_preferred":[
        "Allerton"
    ],
    "qs:gn_adm0_cc":"GB",
    "qs:gn_fcode":"PPL",
    "qs:gn_local":2650000,
    "qs:gn_nam_loc":"rauceby",
    "qs:gn_namadm1":"ENG",
    "qs:gn_name":"Alveston",
    "qs:local_max":4610,
    "qs:local_sum":19661,
    "qs:localhoods":15,
    "qs:name":"Alvaston",
    "qs:name_adm0":"United Kingdom",
    "qs:name_adm1":"England",
    "qs:name_adm2":"Derbyshire",
    "qs:name_lau":"Derby City",
    "qs:name_local":"Derby",
    "qs:photo_max":182,
    "qs:photo_sum":1412,
    "qs:placetype":"Suburb",
    "qs:quad_count":83,
    "qs:woe_adm0":23424975,
    "qs:woe_adm1":24554868,
    "qs:woe_adm2":12602143,
    "qs:woe_lau":12696153,
    "qs:woe_local":18114,
    "qs:woe_ver":"7.10.0",
    "wd:wordcount":1385,
    "wof:lang":[
        "eng"
    ],
    "wof:name":"Alvaston",
    "wof:placetype":"neighbourhood"
},
  "geometry": {"coordinates":[-1.40919,52.896885],"type":"Point"}
}