{
  "type": "Feature",
  "properties": {
    "iso:country":"GB",
    "wof:name":"Low FArm",
    "wof:placetype":"neighbourhood"
},
  "geometry": {"coordinates":[-1.60598493125637,53.8522619791454],"type":"Point"}
}