{
  "type": "Feature",
  "properties": {
    "gn:admin1_code": "ENG",
    "gn:admin2_code": "L6",
    "gn:admin3_code": "00GG145",
    "gn:asciiname": "Asterley",
    "gn:country_code": "GB",
    "gn:dem": 102,
    "gn:feature_class": "P",
    "gn:feature_code": "PPL",
    "gn:name": "Asterley",
    "gn:population": 0,
    "gn:timezone": "Europe/London",
    "iso:country": "GB",
    "name:cym_x_preferred": [
      "Asterley"
    ],
    "name:pol_x_preferred": [
      "Asterley"
    ],
    "wof:name": "Asterley",
    "wof:placetype": "neighbourhood"
  },
  "geometry": {"coordinates":[-2.92562,52.65756999999999],"type":"Point"}
}
