{
  "type": "Feature",
  "properties": {
    "iso:country":"GB",
    "name:ceb_x_preferred":[
        "West End"
    ],
    "name:fra_x_preferred":[
        "West End"
    ],
    "name:isl_x_preferred":[
        "West End"
    ],
    "name:ita_x_preferred":[
        "West End"
    ],
    "name:kor_x_preferred":[
        "\uc6e8\uc2a4\ud2b8\uc5d4\ub4dc"
    ],
    "name:nld_x_preferred":[
        "West End"
    ],
    "name:nor_x_preferred":[
        "West End"
    ],
    "name:pol_x_preferred":[
        "West End"
    ],
    "name:rus_x_preferred":[
        "\u0412\u0435\u0441\u0442-\u042d\u043d\u0434"
    ],
    "name:slk_x_preferred":[
        "West End"
    ],
    "name:spa_x_preferred":[
        "West End"
    ],
    "name:swe_x_preferred":[
        "West End"
    ],
    "qs_pg:aaroncc":"GB",
    "qs_pg:name":"West End",
    "qs_pg:name_adm0":"United Kingdom",
    "qs_pg:name_adm1":"Scotland",
    "qs_pg:photos":33,
    "qs_pg:photos_1k":7,
    "qs_pg:photos_9k":1,
    "qs_pg:photos_9r":2,
    "qs_pg:photos_all":33,
    "qs_pg:photos_sr":2,
    "qs_pg:pop_sr":0,
    "qs_pg:qs_pg_placetype":"locality",
    "qs_pg:qs_pg_placetype_gp":"Town",
    "qs_pg:woe_adm0":23424975,
    "woe:adm0_id":23424975,
    "woe:name_adm0":"United Kingdom",
    "woe:name_adm1":"Scotland",
    "woe:placetype":"Town",
    "wof:name":"West End",
    "wof:placetype":"locality"
},
  "geometry": {"coordinates":[-6.383695,55.731314],"type":"Point"}
}