{
  "type": "Feature",
  "properties": {
    "iso:country": "GB",
    "name:deu_x_preferred": [
      "Juniper Green"
    ],
    "name:eng_x_preferred": [
      "Juniper Green"
    ],
    "name:eus_x_preferred": [
      "Juniper Green"
    ],
    "name:nld_x_preferred": [
      "Juniper Green"
    ],
    "qs:gn_adm0_cc": "GB",
    "qs:gn_fcode": "PPL",
    "qs:gn_local": 2651685,
    "qs:gn_nam_loc": "currie",
    "qs:gn_namadm1": "SCT",
    "qs:gn_name": "Juniper Green",
    "qs:local_max": 710,
    "qs:local_sum": 710,
    "qs:localhoods": 1,
    "qs:name": "Juniper Green",
    "qs:name_adm0": "United Kingdom",
    "qs:name_adm1": "Scotland",
    "qs:name_adm2": "Lothian",
    "qs:name_lau": "City of Edinburgh",
    "qs:name_local": "Currie",
    "qs:photo_max": 44,
    "qs:photo_sum": 710,
    "qs:placetype": "Suburb",
    "qs:quad_count": 98,
    "qs:woe_adm0": 23424975,
    "qs:woe_adm1": 12578048,
    "qs:woe_adm2": 12602204,
    "qs:woe_lau": 12696195,
    "qs:woe_local": 17675,
    "qs:woe_ver": "7.10.0",
    "wd:wordcount": 649,
    "wof:lang": [
      "eng"
    ],
    "wof:name": "Juniper Green",
    "wof:placetype": "neighbourhood"
  },
  "geometry": {"coordinates":[-3.285216,55.905203],"type":"Point"}
}
