{
  "type": "Feature",
  "properties": {
    "iso:country":"GB",
    "name:gle_x_preferred":[
        "Cockersdale"
    ],
    "wof:name":"Cockersdale",
    "wof:placetype":"neighbourhood"
},
  "geometry": {"coordinates":[-1.64849975367317,53.76446389056203],"type":"Point"}
}