{
  "type": "Feature",
  "properties": {
    "iso:country":"GB",
    "name:eng_x_preferred":[
        "Woodhouses"
    ],
    "qs:gn_adm0_cc":"GB",
    "qs:gn_fcode":"PPL",
    "qs:gn_local":2638678,
    "qs:gn_nam_loc":"sale",
    "qs:gn_namadm1":"ENG",
    "qs:gn_name":"Woodhouse",
    "qs:local_max":1744,
    "qs:local_sum":3320,
    "qs:localhoods":3,
    "qs:name":"Woodhouses",
    "qs:name_adm0":"United Kingdom",
    "qs:name_adm1":"England",
    "qs:name_adm2":"Greater Manchester",
    "qs:name_lau":"Trafford Metropolitan Borough",
    "qs:name_local":"Sale",
    "qs:photo_max":15,
    "qs:photo_sum":57,
    "qs:placetype":"Suburb",
    "qs:quad_count":22,
    "qs:woe_adm0":23424975,
    "qs:woe_adm1":24554868,
    "qs:woe_adm2":12602158,
    "qs:woe_lau":12695847,
    "qs:woe_local":33875,
    "qs:woe_ver":"7.10.0",
    "wof:lang":[
        "eng"
    ],
    "wof:name":"Woodhouses",
    "wof:placetype":"neighbourhood"
},
  "geometry": {"coordinates":[-2.38034,53.409249],"type":"Point"}
}