{
  "type": "Feature",
  "properties": {
    "iso:country":"GB",
    "name:ben_x_preferred":[
        "\u09a1\u09a8\u09cd\u099f\u09b8\u09c7"
    ],
    "name:bul_x_preferred":[
        "\u0414\u0430\u0443\u043d\u0446\u0435\u0439"
    ],
    "name:deu_x_preferred":[
        "Dauntsey"
    ],
    "name:eng_x_preferred":[
        "Dauntsey"
    ],
    "name:fra_x_preferred":[
        "Dauntsey"
    ],
    "name:guj_x_preferred":[
        "\u0aa1\u0acc\u0a82\u0a9f\u0ab8\u0ac0"
    ],
    "name:jpn_x_preferred":[
        "\u30c9\u30a6\u30f3\u30c4\u30a3\u30fc"
    ],
    "name:kan_x_preferred":[
        "\u0ca1\u0cbe\u0c82\u0c9f\u0ccd\u0cb8\u0cc6"
    ],
    "name:kor_x_preferred":[
        "\ub3c8\uce58"
    ],
    "name:lit_x_preferred":[
        "Dauntsis"
    ],
    "name:nld_x_preferred":[
        "Dauntsey"
    ],
    "name:pol_x_preferred":[
        "Dauntsey"
    ],
    "name:por_x_preferred":[
        "Dauntsey"
    ],
    "name:rus_x_preferred":[
        "\u0414\u043e\u043d\u0442\u0441\u0438"
    ],
    "name:spa_x_preferred":[
        "Dauntsey"
    ],
    "name:swe_x_preferred":[
        "Dauntsey"
    ],
    "name:tam_x_preferred":[
        "\u0b9f\u0bb5\u0bc1\u0ba3\u0bcd\u0b9f\u0bcd\u0b9a\u0bc6\u0baf\u0bcd"
    ],
    "name:tel_x_preferred":[
        "\u0c21\u0c02\u0c1f\u0c4d\u0c38\u0c3f"
    ],
    "name:urd_x_preferred":[
        "\u062f\u0627\u0648\u0646\u062a\u0633\u06cc\u06cc"
    ],
    "qs_pg:aaroncc":"GB",
    "qs_pg:name":"Dauntsey",
    "qs_pg:name_adm0":"United Kingdom",
    "qs_pg:name_adm1":"England",
    "qs_pg:photos":121,
    "qs_pg:photos_1k":25,
    "qs_pg:photos_9k":1,
    "qs_pg:photos_9r":3,
    "qs_pg:photos_all":121,
    "qs_pg:photos_sr":3,
    "qs_pg:pop_sr":0,
    "qs_pg:qs_pg_placetype":"locality",
    "qs_pg:qs_pg_placetype_gp":"Town",
    "qs_pg:woe_adm0":23424975,
    "woe:adm0_id":23424975,
    "woe:name_adm0":"United Kingdom",
    "woe:name_adm1":"England",
    "woe:placetype":"Town",
    "wof:name":"Dauntsey",
    "wof:placetype":"neighbourhood"
},
  "geometry": {"coordinates":[-1.989812,51.539001],"type":"Point"}
}