{
  "type": "Feature",
  "properties": {
    "iso:country": "GB",
    "name:ben_x_preferred": [
      "ডন্টসে"
    ],
    "name:bul_x_preferred": [
      "Даунцей"
    ],
    "name:ceb_x_preferred": [
      "Dauntsey"
    ],
    "name:deu_x_preferred": [
      "Dauntsey"
    ],
    "name:eng_x_preferred": [
      "Dauntsey"
    ],
    "name:fra_x_preferred": [
      "Dauntsey"
    ],
    "name:guj_x_preferred": [
      "ડૌંટસી"
    ],
    "name:jpn_x_preferred": [
      "ドウンツィー"
    ],
    "name:kan_x_preferred": [
      "ಡಾಂಟ್ಸೆ"
    ],
    "name:kor_x_preferred": [
      "돈치"
    ],
    "name:lit_x_preferred": [
      "Dauntsis"
    ],
    "name:nld_x_preferred": [
      "Dauntsey"
    ],
    "name:pol_x_preferred": [
      "Dauntsey"
    ],
    "name:por_x_preferred": [
      "Dauntsey"
    ],
    "name:rus_x_preferred": [
      "Донтси"
    ],
    "name:spa_x_preferred": [
      "Dauntsey"
    ],
    "name:swe_x_preferred": [
      "Dauntsey"
    ],
    "name:tam_x_preferred": [
      "டவுண்ட்செய்"
    ],
    "name:tel_x_preferred": [
      "డంట్సి"
    ],
    "name:urd_x_preferred": [
      "داونتسیی"
    ],
    "qs_pg:aaroncc": "GB",
    "qs_pg:name": "Dauntsey",
    "qs_pg:name_adm0": "United Kingdom",
    "qs_pg:name_adm1": "England",
    "qs_pg:photos": 121,
    "qs_pg:photos_1k": 25,
    "qs_pg:photos_9k": 1,
    "qs_pg:photos_9r": 3,
    "qs_pg:photos_all": 121,
    "qs_pg:photos_sr": 3,
    "qs_pg:pop_sr": 0,
    "qs_pg:qs_pg_placetype": "locality",
    "qs_pg:qs_pg_placetype_gp": "Town",
    "qs_pg:woe_adm0": 23424975,
    "woe:adm0_id": 23424975,
    "woe:name_adm0": "United Kingdom",
    "woe:name_adm1": "England",
    "woe:placetype": "Town",
    "wof:name": "Dauntsey",
    "wof:placetype": "neighbourhood"
  },
  "geometry": {"coordinates":[-1.989812,51.539001],"type":"Point"}
}
