{
  "type": "Feature",
  "properties": {
    "iso:country":"GB",
    "name:cym_x_preferred":[
        "Tylwch"
    ],
    "name:eng_x_preferred":[
        "Tylwch"
    ],
    "name:eus_x_preferred":[
        "Tylwch"
    ],
    "name:fra_x_preferred":[
        "Tylwch"
    ],
    "name:nld_x_preferred":[
        "Tylwch"
    ],
    "qs_pg:aaroncc":"GB",
    "qs_pg:name":"Tylwch",
    "qs_pg:name_adm0":"United Kingdom",
    "qs_pg:name_adm1":"Wales",
    "qs_pg:photos":59,
    "qs_pg:photos_1k":12,
    "qs_pg:photos_9k":1,
    "qs_pg:photos_9r":2,
    "qs_pg:photos_all":59,
    "qs_pg:photos_sr":2,
    "qs_pg:pop_sr":0,
    "qs_pg:qs_pg_placetype":"locality",
    "qs_pg:qs_pg_placetype_gp":"Town",
    "qs_pg:woe_adm0":23424975,
    "woe:adm0_id":23424975,
    "woe:name_adm0":"United Kingdom",
    "woe:name_adm1":"Wales",
    "woe:placetype":"Town",
    "wof:name":"Tylwch",
    "wof:placetype":"neighbourhood"
},
  "geometry": {"coordinates":[-3.514595,52.409121],"type":"Point"}
}