{
  "type": "Feature",
  "properties": {
    "gn:gn_country":"GB",
    "gn:gn_fcode":"PPL",
    "gn:gn_pop":0,
    "iso:country":"GB",
    "name:dut_x_preferred":[
        "Scarva"
    ],
    "name:eng_x_preferred":[
        "Scarva"
    ],
    "name:fre_x_preferred":[
        "Scarva"
    ],
    "name:gle_x_preferred":[
        "Scarbhach"
    ],
    "name:may_x_preferred":[
        "Scarva"
    ],
    "name:pli_x_preferred":[
        "\u0938\u094d\u0915\u093e\u0930\u0935\u093e"
    ],
    "name:swe_x_preferred":[
        "Scarva"
    ],
    "qs_pg:aaroncc":"GB",
    "qs_pg:gn_country":"GB",
    "qs_pg:gn_fcode":"PPL",
    "qs_pg:gn_pop":0,
    "qs_pg:name":"Scarva",
    "qs_pg:name_adm0":"United Kingdom",
    "qs_pg:name_adm1":"Northern Ireland",
    "qs_pg:photos":1860,
    "qs_pg:photos_1k":377,
    "qs_pg:photos_9k":8,
    "qs_pg:photos_9r":9,
    "qs_pg:photos_all":1860,
    "qs_pg:photos_sr":15,
    "qs_pg:pop_sr":0,
    "qs_pg:qs_pg_placetype":"locality",
    "qs_pg:qs_pg_placetype_gp":"Town",
    "qs_pg:woe_adm0":23424975,
    "woe:adm0_id":23424975,
    "woe:name_adm0":"United Kingdom",
    "woe:name_adm1":"Northern Ireland",
    "woe:placetype":"Town",
    "wof:name":"Scarva",
    "wof:placetype":"locality"
},
  "geometry": {"coordinates":[-6.36667,54.33333],"type":"Point"}
}