{
  "type": "Feature",
  "properties": {
    "gn:country":"GB",
    "gn:fcode":"PPL",
    "gn:population":0,
    "iso:country":"GB",
    "name:eus_x_preferred":[
        "Ballycarry"
    ],
    "name:msa_x_preferred":[
        "Ballycarry"
    ],
    "name:nld_x_preferred":[
        "Ballycarry"
    ],
    "name:pli_x_preferred":[
        "\u092c\u0932\u094d\u0932\u094d\u092f\u094d\u0915\u093e\u0930\u094d\u0930\u0940"
    ],
    "name:spa_x_preferred":[
        "Ballycarry"
    ],
    "qs_pg:aaroncc":"GB",
    "qs_pg:gn_country":"GB",
    "qs_pg:gn_fcode":"PPL",
    "qs_pg:gn_pop":0,
    "qs_pg:name":"Ballycarry",
    "qs_pg:name_adm0":"United Kingdom",
    "qs_pg:name_adm1":"Northern Ireland",
    "qs_pg:photos":195,
    "qs_pg:photos_1k":40,
    "qs_pg:photos_9k":1,
    "qs_pg:photos_9r":4,
    "qs_pg:photos_all":195,
    "qs_pg:photos_sr":4,
    "qs_pg:pop_sr":0,
    "qs_pg:qs_pg_placetype":"locality",
    "qs_pg:qs_pg_placetype_gp":"Town",
    "qs_pg:woe_adm0":23424975,
    "woe:adm0_id":23424975,
    "woe:name_adm0":"United Kingdom",
    "woe:name_adm1":"Northern Ireland",
    "woe:placetype":"Town",
    "wof:name":"Ballycarry",
    "wof:placetype":"locality"
},
  "geometry": {"coordinates":[-5.76667,54.76667],"type":"Point"}
}