{
  "type": "Feature",
  "properties": {
    "iso:country":"GB",
    "name:cym_x_preferred":[
        "Mere Brow"
    ],
    "name:eng_x_preferred":[
        "Mere Brow"
    ],
    "name:fra_x_preferred":[
        "Mere Brow"
    ],
    "name:gle_x_preferred":[
        "Mere Brow"
    ],
    "name:nld_x_preferred":[
        "Mere Brow"
    ],
    "name:pol_x_preferred":[
        "Mere Brow"
    ],
    "name:spa_x_preferred":[
        "Mere Brow"
    ],
    "name:swe_x_preferred":[
        "Mere Brow"
    ],
    "qs_pg:aaroncc":"GB",
    "qs_pg:name":"Mere Brow",
    "qs_pg:name_adm0":"United Kingdom",
    "qs_pg:name_adm1":"England",
    "qs_pg:photos":493,
    "qs_pg:photos_1k":100,
    "qs_pg:photos_9k":2,
    "qs_pg:photos_9r":5,
    "qs_pg:photos_all":493,
    "qs_pg:photos_sr":7,
    "qs_pg:pop_sr":0,
    "qs_pg:qs_pg_placetype":"locality",
    "qs_pg:qs_pg_placetype_gp":"Town",
    "qs_pg:woe_adm0":23424975,
    "woe:adm0_id":23424975,
    "woe:name_adm0":"United Kingdom",
    "woe:name_adm1":"England",
    "woe:placetype":"Town",
    "wof:name":"Mere Brow",
    "wof:placetype":"neighbourhood"
},
  "geometry": {"coordinates":[-2.884769,53.661017],"type":"Point"}
}