{
  "type": "Feature",
  "properties": {
    "gn:admin1_code": "SCT",
    "gn:admin2_code": "V6",
    "gn:asciiname": "Auchindoun",
    "gn:country_code": "GB",
    "gn:dem": 244,
    "gn:feature_class": "P",
    "gn:feature_code": "PPL",
    "gn:name": "Auchindoun",
    "gn:population": 0,
    "gn:timezone": "Europe/London",
    "iso:country": "GB",
    "name:eng_x_preferred": [
      "Auchindoun"
    ],
    "name:eng_x_variant": [
      "Milltown of Auchindoun"
    ],
    "wof:name": "Auchindoun",
    "wof:placetype": "locality"
  },
  "geometry": {"coordinates":[-3.06667,57.43333000000001],"type":"Point"}
}
