{
  "type": "Feature",
  "properties": {
    "gn:country": "GB",
    "gn:fcode": "PPL",
    "gn:population": 0,
    "iso:country": "GB",
    "name:cym_x_preferred": [
      "Park Street"
    ],
    "name:eng_x_preferred": [
      "Park Street"
    ],
    "name:fra_x_preferred": [
      "Park Street"
    ],
    "name:nld_x_preferred": [
      "Park Street"
    ],
    "name:pol_x_preferred": [
      "Park Street"
    ],
    "name:pol_x_variant": [
      "Park Street"
    ],
    "name:spa_x_preferred": [
      "Park Street"
    ],
    "qs_pg:aaroncc": "GB",
    "qs_pg:gn_country": "GB",
    "qs_pg:gn_fcode": "PPL",
    "qs_pg:gn_pop": 0,
    "qs_pg:name": "Park Street",
    "qs_pg:name_adm0": "United Kingdom",
    "qs_pg:name_adm1": "England",
    "qs_pg:photos_9r": 0,
    "qs_pg:photos_sr": 0,
    "qs_pg:pop_sr": 0,
    "qs_pg:qs_pg_placetype": "locality",
    "qs_pg:qs_pg_placetype_gp": "Town",
    "qs_pg:woe_adm0": 23424975,
    "woe:adm0_id": 23424975,
    "woe:name_adm0": "United Kingdom",
    "woe:name_adm1": "England",
    "woe:placetype": "Town",
    "wof:name": "Park Street",
    "wof:placetype": "neighbourhood"
  },
  "geometry": {"coordinates":[-0.33333,51.71667],"type":"Point"}
}
