{
  "type": "Feature",
  "properties": {
    "gn:admin1_code":"ENG",
    "gn:admin2_code":"N7",
    "gn:admin3_code":"43UM",
    "gn:asciiname":"Mayford",
    "gn:country_code":"GB",
    "gn:dem":30,
    "gn:feature_class":"P",
    "gn:feature_code":"PPL",
    "gn:name":"Mayford",
    "gn:population":0,
    "gn:timezone":"Europe/London",
    "iso:country":"GB",
    "name:pol_x_preferred":[
        "Mayford"
    ],
    "name:urd_x_preferred":[
        "\u0645\u0626\u06d2\u0641\u0648\u0631\u0688"
    ],
    "wof:name":"Mayford",
    "wof:placetype":"neighbourhood"
},
  "geometry": {"coordinates":[-0.57451,51.29558],"type":"Point"}
}