{
  "type": "Feature",
  "properties": {
    "iso:country": "GB",
    "name:ara_x_preferred": [
      "كوليرين"
    ],
    "name:bre_x_preferred": [
      "Cúil Raithin"
    ],
    "name:bre_x_variant": [
      "Cúil Rathain"
    ],
    "name:bul_x_preferred": [
      "Коулрейн"
    ],
    "name:cat_x_preferred": [
      "Coleraine"
    ],
    "name:ceb_x_preferred": [
      "Coleraine"
    ],
    "name:cym_x_preferred": [
      "Coleraine"
    ],
    "name:deu_x_preferred": [
      "Coleraine"
    ],
    "name:ell_x_preferred": [
      "Κόλερεϊν"
    ],
    "name:eng_x_preferred": [
      "Coleraine"
    ],
    "name:eus_x_preferred": [
      "Coleraine"
    ],
    "name:fra_x_preferred": [
      "Coleraine"
    ],
    "name:gla_x_preferred": [
      "Cúil Raithin"
    ],
    "name:gle_x_preferred": [
      "Cúil Raithin"
    ],
    "name:gle_x_variant": [
      "Cúil Rathin"
    ],
    "name:heb_x_preferred": [
      "קולריין"
    ],
    "name:ita_x_preferred": [
      "Coleraine"
    ],
    "name:jpn_x_preferred": [
      "コルレイン"
    ],
    "name:kor_x_preferred": [
      "콜레인"
    ],
    "name:lit_x_preferred": [
      "Kolreinas"
    ],
    "name:ltz_x_preferred": [
      "Coleraine"
    ],
    "name:msa_x_preferred": [
      "Coleraine"
    ],
    "name:nld_x_preferred": [
      "Coleraine"
    ],
    "name:nob_x_preferred": [
      "Coleraine"
    ],
    "name:nor_x_preferred": [
      "Coleraine"
    ],
    "name:pol_x_preferred": [
      "Coleraine"
    ],
    "name:ron_x_preferred": [
      "Districtul Coleraine"
    ],
    "name:rus_x_preferred": [
      "Колрейн"
    ],
    "name:rus_x_variant": [
      "Колрэйн"
    ],
    "name:sco_x_preferred": [
      "Cowlraine"
    ],
    "name:slk_x_preferred": [
      "Coleraine"
    ],
    "name:spa_x_preferred": [
      "Coleraine"
    ],
    "name:swe_x_preferred": [
      "Coleraine"
    ],
    "name:ukr_x_preferred": [
      "Колрейн"
    ],
    "name:urd_x_preferred": [
      "کولرین"
    ],
    "name:zho_x_preferred": [
      "科爾雷因"
    ],
    "qs:a0": "United Kingdom",
    "qs:a1": "*Coleraine",
    "qs:a1_lc": "N_A",
    "qs:a1r": "0Northern Ireland",
    "qs:a1r_lc": "N_A",
    "qs:adm0": "United Kingdom",
    "qs:la_lc": "*",
    "qs:level": "locality",
    "qs:loc": "Coleraine",
    "qs:loc_alt": "Coleraine",
    "qs:pop": 0,
    "qs:type": "buffered point",
    "wof:name": "Coleraine",
    "wof:placetype": "locality"
  },
  "geometry": {"coordinates":[-6.661809,55.13243],"type":"Point"}
}
