{
  "type": "Feature",
  "properties": {
    "iso:country":"GB",
    "name:ara_x_preferred":[
        "\u0643\u0648\u0644\u064a\u0631\u064a\u0646"
    ],
    "name:bre_x_preferred":[
        "C\u00fail Raithin"
    ],
    "name:bre_x_variant":[
        "C\u00fail Rathain"
    ],
    "name:bul_x_preferred":[
        "\u041a\u043e\u0443\u043b\u0440\u0435\u0439\u043d"
    ],
    "name:cat_x_preferred":[
        "Coleraine"
    ],
    "name:ceb_x_preferred":[
        "Coleraine"
    ],
    "name:cym_x_preferred":[
        "Coleraine"
    ],
    "name:deu_x_preferred":[
        "Coleraine"
    ],
    "name:ell_x_preferred":[
        "\u039a\u03cc\u03bb\u03b5\u03c1\u03b5\u03ca\u03bd"
    ],
    "name:eng_x_preferred":[
        "Coleraine"
    ],
    "name:eus_x_preferred":[
        "Coleraine"
    ],
    "name:fra_x_preferred":[
        "Coleraine"
    ],
    "name:gla_x_preferred":[
        "C\u00fail Raithin"
    ],
    "name:gle_x_preferred":[
        "C\u00fail Raithin"
    ],
    "name:gle_x_variant":[
        "C\u00fail Rathin"
    ],
    "name:heb_x_preferred":[
        "\u05e7\u05d5\u05dc\u05e8\u05d9\u05d9\u05df"
    ],
    "name:ita_x_preferred":[
        "Coleraine"
    ],
    "name:jpn_x_preferred":[
        "\u30b3\u30eb\u30ec\u30a4\u30f3"
    ],
    "name:kor_x_preferred":[
        "\ucf5c\ub808\uc778"
    ],
    "name:lit_x_preferred":[
        "Kolreinas"
    ],
    "name:ltz_x_preferred":[
        "Coleraine"
    ],
    "name:msa_x_preferred":[
        "Coleraine"
    ],
    "name:nld_x_preferred":[
        "Coleraine"
    ],
    "name:nob_x_preferred":[
        "Coleraine"
    ],
    "name:nor_x_preferred":[
        "Coleraine"
    ],
    "name:pol_x_preferred":[
        "Coleraine"
    ],
    "name:ron_x_preferred":[
        "Districtul Coleraine"
    ],
    "name:rus_x_preferred":[
        "\u041a\u043e\u043b\u0440\u0435\u0439\u043d"
    ],
    "name:rus_x_variant":[
        "\u041a\u043e\u043b\u0440\u044d\u0439\u043d"
    ],
    "name:sco_x_preferred":[
        "Cowlraine"
    ],
    "name:slk_x_preferred":[
        "Coleraine"
    ],
    "name:spa_x_preferred":[
        "Coleraine"
    ],
    "name:swe_x_preferred":[
        "Coleraine"
    ],
    "name:ukr_x_preferred":[
        "\u041a\u043e\u043b\u0440\u0435\u0439\u043d"
    ],
    "name:urd_x_preferred":[
        "\u06a9\u0648\u0644\u0631\u06cc\u0646"
    ],
    "name:zho_x_preferred":[
        "\u79d1\u723e\u96f7\u56e0"
    ],
    "qs:a0":"United Kingdom",
    "qs:a1":"*Coleraine",
    "qs:a1_lc":"N_A",
    "qs:a1r":"0Northern Ireland",
    "qs:a1r_lc":"N_A",
    "qs:adm0":"United Kingdom",
    "qs:la_lc":"*",
    "qs:level":"locality",
    "qs:loc":"Coleraine",
    "qs:loc_alt":"Coleraine",
    "qs:pop":0,
    "qs:type":"buffered point",
    "wof:name":"Coleraine",
    "wof:placetype":"locality"
},
  "geometry": {"coordinates":[-6.661809,55.13243],"type":"Point"}
}