{
  "type": "Feature",
  "properties": {
    "iso:country":"GB",
    "name:dut_x_preferred":[
        "Crichton"
    ],
    "name:eng_x_preferred":[
        "Crichton"
    ],
    "name:fre_x_preferred":[
        "Crichton"
    ],
    "name:ger_x_preferred":[
        "Crichton"
    ],
    "name:gle_x_preferred":[
        "Cr\u00ecocht\u00e1n"
    ],
    "name:sco_x_preferred":[
        "Crichton"
    ],
    "qs_pg:aaroncc":"GB",
    "qs_pg:name":"Crichton",
    "qs_pg:name_adm0":"United Kingdom",
    "qs_pg:name_adm1":"Scotland",
    "qs_pg:photos":998,
    "qs_pg:photos_1k":202,
    "qs_pg:photos_9k":4,
    "qs_pg:photos_9r":6,
    "qs_pg:photos_all":998,
    "qs_pg:photos_sr":10,
    "qs_pg:pop_sr":0,
    "qs_pg:qs_pg_placetype":"locality",
    "qs_pg:qs_pg_placetype_gp":"Town",
    "qs_pg:woe_adm0":23424975,
    "woe:adm0_id":23424975,
    "woe:name_adm0":"United Kingdom",
    "woe:name_adm1":"Scotland",
    "woe:placetype":"Town",
    "wof:name":"Crichton",
    "wof:placetype":"locality"
},
  "geometry": {"coordinates":[-2.992057,55.842361],"type":"Point"}
}