{
  "type": "Feature",
  "properties": {
    "gn:population":6165,
    "iso:country":"GB",
    "name:bul_x_preferred":[
        "\u041b\u0438\u043f\u0445\u043e\u043a"
    ],
    "name:ceb_x_preferred":[
        "Liphook"
    ],
    "name:cym_x_preferred":[
        "Liphook"
    ],
    "name:deu_x_preferred":[
        "Liphook"
    ],
    "name:eng_x_preferred":[
        "Liphook"
    ],
    "name:fas_x_preferred":[
        "\u0644\u06cc\u067e\u0647\u0648\u06a9"
    ],
    "name:fra_x_preferred":[
        "Liphook"
    ],
    "name:gle_x_preferred":[
        "Liphook"
    ],
    "name:ita_x_preferred":[
        "Liphook"
    ],
    "name:jpn_x_preferred":[
        "\u30ea\u30c3\u30d7\u30db\u30c3\u30af"
    ],
    "name:nld_x_preferred":[
        "Liphook"
    ],
    "name:pol_x_preferred":[
        "Liphook"
    ],
    "name:rus_x_preferred":[
        "\u041b\u0438\u043f\u0445\u0443\u043a"
    ],
    "name:spa_x_preferred":[
        "Liphook"
    ],
    "name:swe_x_preferred":[
        "Liphook"
    ],
    "name:zho_x_preferred":[
        "\u5229\u666e\u80e1\u514b"
    ],
    "qs:a0":"United Kingdom",
    "qs:a1":"*Hampshire",
    "qs:a1_lc":"GB12240000",
    "qs:a1r":"0England",
    "qs:a1r_lc":"GB12000000",
    "qs:adm0":"United Kingdom",
    "qs:la_lc":"*",
    "qs:level":"locality",
    "qs:loc":"Liphook",
    "qs:loc_alt":"Liphook",
    "qs:pop":0,
    "qs:type":"buffered point",
    "wd:wordcount":1995,
    "wof:lang":[
        "eng"
    ],
    "wof:name":"Liphook",
    "wof:placetype":"neighbourhood",
    "wof:population":6165
},
  "geometry": {"coordinates":[-0.802152,51.077156],"type":"Point"}
}