{
  "type": "Feature",
  "properties": {
    "gn:gn_country":"GB",
    "gn:gn_fcode":"PPL",
    "gn:gn_pop":0,
    "iso:country":"GB",
    "name:bre_x_preferred":[
        "Llanddewi Nant Hodni"
    ],
    "name:cym_x_preferred":[
        "Llanddewi Nant Hodni"
    ],
    "name:eng_x_preferred":[
        "Llanthony"
    ],
    "name:eus_x_preferred":[
        "Llanthony"
    ],
    "name:fra_x_preferred":[
        "Llanthony"
    ],
    "name:nld_x_preferred":[
        "Llanthony"
    ],
    "name:por_x_preferred":[
        "Llanthony"
    ],
    "qs_pg:aaroncc":"GB",
    "qs_pg:gn_country":"GB",
    "qs_pg:gn_fcode":"PPL",
    "qs_pg:gn_pop":0,
    "qs_pg:name":"Llanthony",
    "qs_pg:name_adm0":"United Kingdom",
    "qs_pg:name_adm1":"Wales",
    "qs_pg:photos":717,
    "qs_pg:photos_1k":145,
    "qs_pg:photos_9k":3,
    "qs_pg:photos_9r":5,
    "qs_pg:photos_all":717,
    "qs_pg:photos_sr":8,
    "qs_pg:pop_sr":0,
    "qs_pg:qs_pg_placetype":"locality",
    "qs_pg:qs_pg_placetype_gp":"Town",
    "qs_pg:woe_adm0":23424975,
    "woe:adm0_id":23424975,
    "woe:name_adm0":"United Kingdom",
    "woe:name_adm1":"Wales",
    "woe:placetype":"Town",
    "wof:name":"Llanthony",
    "wof:placetype":"neighbourhood"
},
  "geometry": {"coordinates":[-3.03815,51.94316],"type":"Point"}
}