{
  "type": "Feature",
  "properties": {
    "gn:gn_country":"GB",
    "gn:gn_fcode":"PPL",
    "gn:gn_pop":3302,
    "gn:population":3270,
    "iso:country":"GB",
    "name:ceb_x_preferred":[
        "Gobowen"
    ],
    "name:cym_x_preferred":[
        "Gobowen"
    ],
    "name:eng_x_preferred":[
        "Gobowen"
    ],
    "name:fra_x_preferred":[
        "Gobowen"
    ],
    "name:jpn_x_preferred":[
        "\u30b4\u30dc\u30fc\u30a6\u30a7\u30f3"
    ],
    "name:nld_x_preferred":[
        "Gobowen"
    ],
    "name:pol_x_preferred":[
        "Gobowen"
    ],
    "name:spa_x_preferred":[
        "Gobowen"
    ],
    "name:swe_x_preferred":[
        "Gobowen"
    ],
    "qs_pg:aaroncc":"GB",
    "qs_pg:gn_country":"GB",
    "qs_pg:gn_fcode":"PPL",
    "qs_pg:gn_pop":3302,
    "qs_pg:name":"Gobowen",
    "qs_pg:name_adm0":"United Kingdom",
    "qs_pg:name_adm1":"England",
    "qs_pg:photos":223,
    "qs_pg:photos_1k":45,
    "qs_pg:photos_9k":1,
    "qs_pg:photos_9r":4,
    "qs_pg:photos_all":223,
    "qs_pg:photos_sr":4,
    "qs_pg:pop_sr":4,
    "qs_pg:qs_pg_placetype":"locality",
    "qs_pg:qs_pg_placetype_gp":"Town",
    "qs_pg:woe_adm0":23424975,
    "woe:adm0_id":23424975,
    "woe:name_adm0":"United Kingdom",
    "woe:name_adm1":"England",
    "woe:placetype":"Town",
    "wof:name":"Gobowen",
    "wof:placetype":"neighbourhood",
    "wof:population":3270
},
  "geometry": {"coordinates":[-3.03686,52.89615],"type":"Point"}
}