{
  "type": "Feature",
  "properties": {
    "iso:country":"GB",
    "name:deu_x_preferred":[
        "Sauchen"
    ],
    "name:eng_x_preferred":[
        "Sauchen"
    ],
    "name:eus_x_preferred":[
        "Sauchen"
    ],
    "name:fra_x_preferred":[
        "Sauchen"
    ],
    "name:nld_x_preferred":[
        "Sauchen"
    ],
    "name:por_x_preferred":[
        "Sauchen"
    ],
    "name:sco_x_preferred":[
        "Sauchen"
    ],
    "name:spa_x_preferred":[
        "Sauchen"
    ],
    "name:swe_x_preferred":[
        "Sauchen"
    ],
    "name:swe_x_variant":[
        "Ulverscroft"
    ],
    "qs_pg:aaroncc":"GB",
    "qs_pg:name":"Sauchen",
    "qs_pg:name_adm0":"United Kingdom",
    "qs_pg:name_adm1":"Scotland",
    "qs_pg:photos":18,
    "qs_pg:photos_1k":4,
    "qs_pg:photos_9k":1,
    "qs_pg:photos_9r":1,
    "qs_pg:photos_all":18,
    "qs_pg:photos_sr":1,
    "qs_pg:pop_sr":0,
    "qs_pg:qs_pg_placetype":"locality",
    "qs_pg:qs_pg_placetype_gp":"Town",
    "qs_pg:woe_adm0":23424975,
    "woe:adm0_id":23424975,
    "woe:name_adm0":"United Kingdom",
    "woe:name_adm1":"Scotland",
    "woe:placetype":"Town",
    "wof:name":"Sauchen",
    "wof:placetype":"locality"
},
  "geometry": {"coordinates":[-2.492033,57.183701],"type":"Point"}
}