{
  "type": "Feature",
  "properties": {
    "gn:population":4085,
    "iso:country":"GB",
    "name:ast_x_preferred":[
        "Maghera"
    ],
    "name:bul_x_preferred":[
        "\u041c\u0430\u0445\u044a\u0440\u0430"
    ],
    "name:ceb_x_preferred":[
        "Maghera"
    ],
    "name:cym_x_preferred":[
        "Maghera"
    ],
    "name:deu_x_preferred":[
        "Maghera"
    ],
    "name:eng_x_preferred":[
        "Maghera"
    ],
    "name:eus_x_preferred":[
        "Maghera"
    ],
    "name:fas_x_preferred":[
        "\u0645\u0627\u06af\u0631\u0627"
    ],
    "name:fra_x_preferred":[
        "Maghera"
    ],
    "name:gla_x_preferred":[
        "Machaire R\u00e1tha"
    ],
    "name:gle_x_preferred":[
        "Machaire R\u00e1tha"
    ],
    "name:hun_x_preferred":[
        "ny\u00e1r\u00e1dmagyar\u00f3s"
    ],
    "name:ita_x_preferred":[
        "Maghera"
    ],
    "name:jpn_x_preferred":[
        "\u30de\u30b0\u30d8\u30e9"
    ],
    "name:mkd_x_preferred":[
        "\u041c\u0430\u0445\u0435\u0440\u0430"
    ],
    "name:msa_x_preferred":[
        "Maghera"
    ],
    "name:nld_x_preferred":[
        "Maghera"
    ],
    "name:pli_x_preferred":[
        "\u092e\u0918\u0947\u0930\u093e"
    ],
    "name:pol_x_preferred":[
        "Maghera"
    ],
    "name:sco_x_preferred":[
        "Maghera"
    ],
    "name:sco_x_variant":[
        "Machera"
    ],
    "name:spa_x_preferred":[
        "Maghera"
    ],
    "name:swe_x_preferred":[
        "Maghera"
    ],
    "name:szl_x_preferred":[
        "Maghera"
    ],
    "name:zho_x_preferred":[
        "\u99ac\u8d6b\u62c9"
    ],
    "qs:a0":"United Kingdom",
    "qs:a1":"*Magherafelt",
    "qs:a1_lc":"N_A",
    "qs:a1r":"0Northern Ireland",
    "qs:a1r_lc":"N_A",
    "qs:adm0":"United Kingdom",
    "qs:la_lc":"*",
    "qs:level":"locality",
    "qs:loc":"Maghera",
    "qs:loc_alt":"Maghera",
    "qs:pop":0,
    "qs:type":"buffered point",
    "wd:wordcount":764,
    "wof:name":"Maghera",
    "wof:placetype":"locality",
    "wof:population":4085
},
  "geometry": {"coordinates":[-6.670564,54.843612],"type":"Point"}
}