{
  "type": "Feature",
  "properties": {
    "gn:population": 4085,
    "iso:country": "GB",
    "name:bul_x_preferred": [
      "Махъра"
    ],
    "name:ceb_x_preferred": [
      "Maghera"
    ],
    "name:cym_x_preferred": [
      "Maghera"
    ],
    "name:deu_x_preferred": [
      "Maghera"
    ],
    "name:eng_x_preferred": [
      "Maghera"
    ],
    "name:eus_x_preferred": [
      "Maghera"
    ],
    "name:fas_x_preferred": [
      "ماگرا"
    ],
    "name:fra_x_preferred": [
      "Maghera"
    ],
    "name:gla_x_preferred": [
      "Machaire Rátha"
    ],
    "name:gle_x_preferred": [
      "Machaire Rátha"
    ],
    "name:hun_x_preferred": [
      "nyárádmagyarós"
    ],
    "name:ita_x_preferred": [
      "Maghera"
    ],
    "name:msa_x_preferred": [
      "Maghera"
    ],
    "name:nld_x_preferred": [
      "Maghera"
    ],
    "name:pli_x_preferred": [
      "मघेरा"
    ],
    "name:pol_x_preferred": [
      "Maghera"
    ],
    "name:sco_x_preferred": [
      "Maghera"
    ],
    "name:sco_x_variant": [
      "Machera"
    ],
    "name:spa_x_preferred": [
      "Maghera"
    ],
    "name:swe_x_preferred": [
      "Maghera"
    ],
    "name:zho_x_preferred": [
      "馬赫拉"
    ],
    "qs:a0": "United Kingdom",
    "qs:a1": "*Magherafelt",
    "qs:a1_lc": "N_A",
    "qs:a1r": "0Northern Ireland",
    "qs:a1r_lc": "N_A",
    "qs:adm0": "United Kingdom",
    "qs:la_lc": "*",
    "qs:level": "locality",
    "qs:loc": "Maghera",
    "qs:loc_alt": "Maghera",
    "qs:pop": 0,
    "qs:type": "buffered point",
    "wd:wordcount": 764,
    "wof:name": "Maghera",
    "wof:placetype": "locality",
    "wof:population": 4085
  },
  "geometry": {"coordinates":[-6.670564,54.843612],"type":"Point"}
}
