{
  "type": "Feature",
  "properties": {
    "gn:admin1_code":"ENG",
    "gn:admin2_code":"F8",
    "gn:admin3_code":"26UD",
    "gn:admin4_code":"26UD025",
    "gn:asciiname":"Letty Green",
    "gn:country_code":"GB",
    "gn:dem":74,
    "gn:feature_class":"P",
    "gn:feature_code":"PPL",
    "gn:name":"Letty Green",
    "gn:population":316,
    "gn:timezone":"Europe/London",
    "iso:country":"GB",
    "name:eng_x_preferred":[
        "Letty Green"
    ],
    "wof:name":"Letty Green",
    "wof:placetype":"neighbourhood",
    "wof:population":316
},
  "geometry": {"coordinates":[-0.13699,51.78181],"type":"Point"}
}