{
  "type": "Feature",
  "properties": {
    "iso:country":"GB",
    "name:cym_x_preferred":[
        "Allanton"
    ],
    "name:deu_x_preferred":[
        "Allanton"
    ],
    "name:nor_x_preferred":[
        "Allanton"
    ],
    "qs_pg:aaroncc":"GB",
    "qs_pg:name":"Allanton",
    "qs_pg:name_adm0":"United Kingdom",
    "qs_pg:name_adm1":"Scotland",
    "qs_pg:photos":17,
    "qs_pg:photos_1k":3,
    "qs_pg:photos_9k":1,
    "qs_pg:photos_9r":1,
    "qs_pg:photos_all":17,
    "qs_pg:photos_sr":1,
    "qs_pg:pop_sr":0,
    "qs_pg:qs_pg_placetype":"locality",
    "qs_pg:qs_pg_placetype_gp":"Town",
    "qs_pg:woe_adm0":23424975,
    "woe:adm0_id":23424975,
    "woe:name_adm0":"United Kingdom",
    "woe:name_adm1":"Scotland",
    "woe:placetype":"Town",
    "wof:name":"Allanton",
    "wof:placetype":"locality"
},
  "geometry": {"coordinates":[-3.826332,55.799737],"type":"Point"}
}