{
  "type": "Feature",
  "properties": {
    "iso:country":"GB",
    "name:eng_x_preferred":[
        "Woodside"
    ],
    "name:unk_x_variant":[
        "Woodside"
    ],
    "qs:gn_adm0_cc":"GB",
    "qs:gn_local":2634677,
    "qs:gn_nam_loc":"watford",
    "qs:gn_namadm1":"ENG",
    "qs:local_max":5373,
    "qs:local_sum":17367,
    "qs:localhoods":8,
    "qs:name":"Woodside",
    "qs:name_adm0":"United Kingdom",
    "qs:name_adm1":"England",
    "qs:name_adm2":"Hertfordshire",
    "qs:name_lau":"Watford Borough",
    "qs:name_local":"Watford",
    "qs:photo_max":44,
    "qs:photo_sum":137,
    "qs:placetype":"Suburb",
    "qs:quad_count":24,
    "qs:woe_adm0":23424975,
    "qs:woe_adm1":24554868,
    "qs:woe_adm2":12602170,
    "qs:woe_lau":12695983,
    "qs:woe_local":39321,
    "qs:woe_ver":"7.10.0",
    "wd:wordcount":455,
    "wof:lang":[
        "eng"
    ],
    "wof:name":"Woodside",
    "wof:placetype":"neighbourhood"
},
  "geometry": {"coordinates":[-0.399197,51.696531],"type":"Point"}
}