{
  "type": "Feature",
  "properties": {
    "iso:country": "GB",
    "name:ben_x_preferred": [
      "কেডিশহেড"
    ],
    "name:deu_x_preferred": [
      "Cadishead"
    ],
    "name:eng_x_preferred": [
      "Cadishead"
    ],
    "name:fra_x_preferred": [
      "Cadishead"
    ],
    "name:gle_x_preferred": [
      "Cadishead"
    ],
    "name:guj_x_preferred": [
      "કેડિશેડ"
    ],
    "name:ita_x_preferred": [
      "Cadishead"
    ],
    "name:jpn_x_preferred": [
      "キャディシェッド"
    ],
    "name:kan_x_preferred": [
      "ಕ್ಯಾಡಿಸ್ ಹೆಡ್"
    ],
    "name:kor_x_preferred": [
      "캐디스헤드"
    ],
    "name:lit_x_preferred": [
      "Kadishedas"
    ],
    "name:nld_x_preferred": [
      "Cadishead"
    ],
    "name:pol_x_preferred": [
      "Cadishead"
    ],
    "name:por_x_preferred": [
      "Cadishead"
    ],
    "name:rus_x_preferred": [
      "Кэдисхэд"
    ],
    "name:spa_x_preferred": [
      "Cadishead"
    ],
    "name:tam_x_preferred": [
      "காடிஸ்ஹெட்"
    ],
    "name:tel_x_preferred": [
      "క్యాడిషెడ్"
    ],
    "name:urd_x_preferred": [
      "کادیشیاد"
    ],
    "qs_pg:aaroncc": "GB",
    "qs_pg:name": "Cadishead",
    "qs_pg:name_adm0": "United Kingdom",
    "qs_pg:name_adm1": "England",
    "qs_pg:photos": 49,
    "qs_pg:photos_1k": 10,
    "qs_pg:photos_9k": 1,
    "qs_pg:photos_9r": 2,
    "qs_pg:photos_all": 49,
    "qs_pg:photos_sr": 2,
    "qs_pg:pop_sr": 0,
    "qs_pg:qs_pg_placetype": "locality",
    "qs_pg:qs_pg_placetype_gp": "Town",
    "qs_pg:woe_adm0": 23424975,
    "woe:adm0_id": 23424975,
    "woe:name_adm0": "United Kingdom",
    "woe:name_adm1": "England",
    "woe:placetype": "Town",
    "wof:name": "Cadishead",
    "wof:placetype": "neighbourhood"
  },
  "geometry": {"coordinates":[-2.439007,53.423215],"type":"Point"}
}
