{
  "type": "Feature",
  "properties": {
    "iso:country":"GB",
    "name:ben_x_preferred":[
        "\u0995\u09c7\u09a1\u09bf\u09b6\u09b9\u09c7\u09a1"
    ],
    "name:deu_x_preferred":[
        "Cadishead"
    ],
    "name:eng_x_preferred":[
        "Cadishead"
    ],
    "name:fra_x_preferred":[
        "Cadishead"
    ],
    "name:gle_x_preferred":[
        "Cadishead"
    ],
    "name:guj_x_preferred":[
        "\u0a95\u0ac7\u0aa1\u0abf\u0ab6\u0ac7\u0aa1"
    ],
    "name:ita_x_preferred":[
        "Cadishead"
    ],
    "name:jpn_x_preferred":[
        "\u30ad\u30e3\u30c7\u30a3\u30b7\u30a7\u30c3\u30c9"
    ],
    "name:kan_x_preferred":[
        "\u0c95\u0ccd\u0caf\u0cbe\u0ca1\u0cbf\u0cb8\u0ccd \u0cb9\u0cc6\u0ca1\u0ccd"
    ],
    "name:kor_x_preferred":[
        "\uce90\ub514\uc2a4\ud5e4\ub4dc"
    ],
    "name:lit_x_preferred":[
        "Kadishedas"
    ],
    "name:nld_x_preferred":[
        "Cadishead"
    ],
    "name:pol_x_preferred":[
        "Cadishead"
    ],
    "name:por_x_preferred":[
        "Cadishead"
    ],
    "name:rus_x_preferred":[
        "\u041a\u044d\u0434\u0438\u0441\u0445\u044d\u0434"
    ],
    "name:spa_x_preferred":[
        "Cadishead"
    ],
    "name:tam_x_preferred":[
        "\u0b95\u0bbe\u0b9f\u0bbf\u0bb8\u0bcd\u0bb9\u0bc6\u0b9f\u0bcd"
    ],
    "name:tel_x_preferred":[
        "\u0c15\u0c4d\u0c2f\u0c3e\u0c21\u0c3f\u0c37\u0c46\u0c21\u0c4d"
    ],
    "name:urd_x_preferred":[
        "\u06a9\u0627\u062f\u06cc\u0634\u06cc\u0627\u062f"
    ],
    "qs_pg:aaroncc":"GB",
    "qs_pg:name":"Cadishead",
    "qs_pg:name_adm0":"United Kingdom",
    "qs_pg:name_adm1":"England",
    "qs_pg:photos":49,
    "qs_pg:photos_1k":10,
    "qs_pg:photos_9k":1,
    "qs_pg:photos_9r":2,
    "qs_pg:photos_all":49,
    "qs_pg:photos_sr":2,
    "qs_pg:pop_sr":0,
    "qs_pg:qs_pg_placetype":"locality",
    "qs_pg:qs_pg_placetype_gp":"Town",
    "qs_pg:woe_adm0":23424975,
    "woe:adm0_id":23424975,
    "woe:name_adm0":"United Kingdom",
    "woe:name_adm1":"England",
    "woe:placetype":"Town",
    "wof:name":"Cadishead",
    "wof:placetype":"neighbourhood"
},
  "geometry": {"coordinates":[-2.439007,53.423215],"type":"Point"}
}