{
  "type": "Feature",
  "properties": {
    "gn:country": "GB",
    "gn:fcode": "PPL",
    "gn:population": 5962,
    "iso:country": "GB",
    "name:azb_x_preferred": [
      "کوکنزی و پورت استون"
    ],
    "name:cym_x_preferred": [
      "Cockenzie"
    ],
    "name:deu_x_preferred": [
      "Cockenzie and Port Seton"
    ],
    "name:eng_x_preferred": [
      "Cockenzie and Port Seton"
    ],
    "name:eus_x_preferred": [
      "Cockenzie eta Port Seton"
    ],
    "name:fas_x_preferred": [
      "کوکنزی و پورت استون"
    ],
    "name:gla_x_preferred": [
      "Cùl Choinnich"
    ],
    "name:ita_x_preferred": [
      "Cockenzie and Port Seton"
    ],
    "name:nld_x_preferred": [
      "Cockenzie and Port Seton"
    ],
    "name:nno_x_preferred": [
      "Cockenzie and Port Seton"
    ],
    "name:nob_x_preferred": [
      "Cockenzie"
    ],
    "name:swe_x_preferred": [
      "Cockenzie"
    ],
    "qs_pg:aaroncc": "GB",
    "qs_pg:gn_country": "GB",
    "qs_pg:gn_fcode": "PPL",
    "qs_pg:gn_pop": 5962,
    "qs_pg:name": "Cockenzie and Port Seton",
    "qs_pg:name_adm0": "United Kingdom",
    "qs_pg:name_adm1": "Scotland",
    "qs_pg:photos": 419,
    "qs_pg:photos_1k": 85,
    "qs_pg:photos_9k": 2,
    "qs_pg:photos_9r": 5,
    "qs_pg:photos_all": 419,
    "qs_pg:photos_sr": 6,
    "qs_pg:pop_sr": 5,
    "qs_pg:qs_pg_placetype": "locality",
    "qs_pg:qs_pg_placetype_gp": "Town",
    "qs_pg:woe_adm0": 23424975,
    "woe:adm0_id": 23424975,
    "woe:name_adm0": "United Kingdom",
    "woe:name_adm1": "Scotland",
    "woe:placetype": "Town",
    "wof:name": "Cockenzie and Port Seton",
    "wof:placetype": "locality",
    "wof:population": 5660
  },
  "geometry": {"coordinates":[-2.96562,55.96823],"type":"Point"}
}
