{
  "type": "Feature",
  "properties": {
    "gn:gn_country":"GB",
    "gn:gn_fcode":"PPL",
    "gn:gn_pop":1606,
    "gn:population":1650,
    "iso:country":"GB",
    "name:ben_x_preferred":[
        "\u09ac\u09cd\u09b0\u09be\u09ae\u09b9\u09cd\u09af\u09be\u09ae"
    ],
    "name:bul_x_preferred":[
        "\u0411\u0440\u0430\u043c\u0445\u0430\u043c"
    ],
    "name:deu_x_preferred":[
        "Bramham"
    ],
    "name:eng_x_preferred":[
        "Bramham"
    ],
    "name:fra_x_preferred":[
        "Bramham"
    ],
    "name:gle_x_preferred":[
        "Bramham"
    ],
    "name:guj_x_preferred":[
        "\u0aac\u0acd\u0ab0\u0abe\u0aae\u0ab9\u0abe\u0aae"
    ],
    "name:jpn_x_preferred":[
        "\u30d6\u30e9\u30f3\u30cf\u30e0"
    ],
    "name:kan_x_preferred":[
        "\u0cac\u0ccd\u0cb0\u0cbe\u0cae\u0cae\u0ccd"
    ],
    "name:kor_x_preferred":[
        "\ube0c\ub799\ud5d8 \ucef4 \uc624\uadf8\ub108\ub3cc\ud504"
    ],
    "name:lit_x_preferred":[
        "Bramhemas"
    ],
    "name:nld_x_preferred":[
        "Bramham"
    ],
    "name:pol_x_preferred":[
        "Bramham"
    ],
    "name:por_x_preferred":[
        "Bramham"
    ],
    "name:rus_x_preferred":[
        "\u0411\u0440\u044d\u043c\u0445\u044d\u043c"
    ],
    "name:spa_x_preferred":[
        "Bramham"
    ],
    "name:swe_x_preferred":[
        "Bramham"
    ],
    "name:tam_x_preferred":[
        "\u0baa\u0bbf\u0bb0\u0bae\u0bcd\u0bb9\u0bae\u0bcd"
    ],
    "name:tel_x_preferred":[
        "\u0c2c\u0c4d\u0c30\u0c3e\u0c2e\u0c4d\u0c39\u0c2e\u0c4d"
    ],
    "name:urd_x_preferred":[
        "\u0628\u0631\u0627\u0645\u06c1\u0627\u0645"
    ],
    "qs_pg:aaroncc":"GB",
    "qs_pg:gn_country":"GB",
    "qs_pg:gn_fcode":"PPL",
    "qs_pg:gn_pop":1606,
    "qs_pg:name":"Bramham",
    "qs_pg:name_adm0":"United Kingdom",
    "qs_pg:name_adm1":"England",
    "qs_pg:photos":2350,
    "qs_pg:photos_1k":476,
    "qs_pg:photos_9k":10,
    "qs_pg:photos_9r":10,
    "qs_pg:photos_all":2350,
    "qs_pg:photos_sr":17,
    "qs_pg:pop_sr":3,
    "qs_pg:qs_pg_placetype":"locality",
    "qs_pg:qs_pg_placetype_gp":"Town",
    "qs_pg:woe_adm0":23424975,
    "woe:adm0_id":23424975,
    "woe:name_adm0":"United Kingdom",
    "woe:name_adm1":"England",
    "woe:placetype":"Town",
    "wof:name":"Bramham",
    "wof:placetype":"neighbourhood",
    "wof:population":1650
},
  "geometry": {"coordinates":[-1.35452,53.88118],"type":"Point"}
}