{
  "type": "Feature",
  "properties": {
    "gn:admin1_code":"ENG",
    "gn:admin2_code":"H7",
    "gn:admin3_code":"32UG",
    "gn:admin4_code":"32UG012",
    "gn:asciiname":"Twenty",
    "gn:country_code":"GB",
    "gn:dem":6,
    "gn:feature_class":"P",
    "gn:feature_code":"PPL",
    "gn:name":"Twenty",
    "gn:population":0,
    "gn:timezone":"Europe/London",
    "iso:country":"GB",
    "name:pol_x_preferred":[
        "Twenty"
    ],
    "wof:name":"Twenty",
    "wof:placetype":"neighbourhood"
},
  "geometry": {"coordinates":[-0.29114,52.77099000000001],"type":"Point"}
}