{
  "type": "Feature",
  "properties": {
    "gn:admin1_code":"ENG",
    "gn:admin2_code":"C6",
    "gn:admin3_code":"00HE114",
    "gn:asciiname":"Bridge",
    "gn:country_code":"GB",
    "gn:dem":28,
    "gn:feature_class":"P",
    "gn:feature_code":"PPL",
    "gn:name":"Bridge",
    "gn:population":0,
    "gn:timezone":"Europe/London",
    "iso:country":"GB",
    "wof:name":"Bridge",
    "wof:placetype":"neighbourhood"
},
  "geometry": {"coordinates":[-5.2661,50.25725],"type":"Point"}
}