{
  "type": "Feature",
  "properties": {
    "iso:country":"GB",
    "name:eng_x_preferred":[
        "Knapp"
    ],
    "name:eus_x_preferred":[
        "Knapp"
    ],
    "name:fra_x_preferred":[
        "Knapp"
    ],
    "name:nld_x_preferred":[
        "Knapp"
    ],
    "qs_pg:aaroncc":"GB",
    "qs_pg:name":"Knapp",
    "qs_pg:name_adm0":"United Kingdom",
    "qs_pg:name_adm1":"Scotland",
    "qs_pg:photos":107,
    "qs_pg:photos_1k":22,
    "qs_pg:photos_9k":1,
    "qs_pg:photos_9r":3,
    "qs_pg:photos_all":107,
    "qs_pg:photos_sr":3,
    "qs_pg:pop_sr":0,
    "qs_pg:qs_pg_placetype":"locality",
    "qs_pg:qs_pg_placetype_gp":"Town",
    "qs_pg:woe_adm0":23424975,
    "woe:adm0_id":23424975,
    "woe:name_adm0":"United Kingdom",
    "woe:name_adm1":"Scotland",
    "woe:placetype":"Town",
    "wof:name":"Knapp",
    "wof:placetype":"locality"
},
  "geometry": {"coordinates":[-3.126983,56.501828],"type":"Point"}
}