{
  "type": "Feature",
  "properties": {
    "iso:country":"GB",
    "name:dut_x_preferred":[
        "Aldourie"
    ],
    "name:eng_x_preferred":[
        "Aldourie"
    ],
    "name:por_x_preferred":[
        "Aldourie"
    ],
    "qs_pg:aaroncc":"GB",
    "qs_pg:name":"Aldourie",
    "qs_pg:name_adm0":"United Kingdom",
    "qs_pg:name_adm1":"Scotland",
    "qs_pg:photos":382,
    "qs_pg:photos_1k":77,
    "qs_pg:photos_9k":2,
    "qs_pg:photos_9r":5,
    "qs_pg:photos_all":382,
    "qs_pg:photos_sr":6,
    "qs_pg:pop_sr":0,
    "qs_pg:qs_pg_placetype":"locality",
    "qs_pg:qs_pg_placetype_gp":"Town",
    "qs_pg:woe_adm0":23424975,
    "woe:adm0_id":23424975,
    "woe:name_adm0":"United Kingdom",
    "woe:name_adm1":"Scotland",
    "woe:placetype":"Town",
    "wof:name":"Aldourie",
    "wof:placetype":"locality"
},
  "geometry": {"coordinates":[-4.33093,57.40686],"type":"Point"}
}