{
  "type": "Feature",
  "properties": {
    "name:ceb_x_preferred":[
        "Didsbury"
    ],
    "name:cym_x_preferred":[
        "Didsbury"
    ],
    "name:deu_x_preferred":[
        "Didsbury"
    ],
    "name:ell_x_preferred":[
        "\u039d\u03c4\u03af\u03bd\u03c4\u03c3\u03bc\u03c0\u03bf\u03c5\u03c1\u03b9"
    ],
    "name:eng_x_preferred":[
        "Didsbury"
    ],
    "name:fas_x_preferred":[
        "\u062f\u06cc\u062f\u0632\u0628\u0631\u06cc"
    ],
    "name:fra_x_preferred":[
        "Didsbury"
    ],
    "name:gle_x_preferred":[
        "Didsbury"
    ],
    "name:heb_x_preferred":[
        "\u05d3\u05d9\u05d3\u05e1\u05d1\u05d5\u05e8\u05d9"
    ],
    "name:ita_x_preferred":[
        "Didsbury"
    ],
    "name:jpn_x_preferred":[
        "\u30c7\u30a3\u30ba\u30d9\u30ea"
    ],
    "name:nld_x_preferred":[
        "Didsbury"
    ],
    "name:pol_x_preferred":[
        "Didsbury"
    ],
    "name:sco_x_preferred":[
        "Didsbury"
    ],
    "name:spa_x_preferred":[
        "Didsbury"
    ],
    "name:swe_x_preferred":[
        "Didsbury"
    ],
    "wd:wordcount":5429,
    "wof:name":"Didsbury",
    "wof:placetype":"neighbourhood"
},
  "geometry": {"coordinates":[-2.23312593657212,53.41710655518518],"type":"Point"}
}