{
  "type": "Feature",
  "properties": {
    "iso:country":"GB",
    "name:ast_x_preferred":[
        "Didsbury"
    ],
    "name:cat_x_preferred":[
        "Didsbury"
    ],
    "name:ceb_x_preferred":[
        "Didsbury"
    ],
    "name:cym_x_preferred":[
        "Didsbury"
    ],
    "name:deu_x_preferred":[
        "Didsbury"
    ],
    "name:ell_x_preferred":[
        "\u039d\u03c4\u03af\u03bd\u03c4\u03c3\u03bc\u03c0\u03bf\u03c5\u03c1\u03b9"
    ],
    "name:eng_x_preferred":[
        "Didsbury"
    ],
    "name:fas_x_preferred":[
        "\u062f\u06cc\u062f\u0632\u0628\u0631\u06cc"
    ],
    "name:fra_x_preferred":[
        "Didsbury"
    ],
    "name:gle_x_preferred":[
        "Didsbury"
    ],
    "name:heb_x_preferred":[
        "\u05d3\u05d9\u05d3\u05e1\u05d1\u05d5\u05e8\u05d9"
    ],
    "name:ita_x_preferred":[
        "Didsbury"
    ],
    "name:jpn_x_preferred":[
        "\u30c7\u30a3\u30ba\u30d9\u30ea"
    ],
    "name:lld_x_preferred":[
        "Didsbury"
    ],
    "name:nld_x_preferred":[
        "Didsbury"
    ],
    "name:nob_x_preferred":[
        "Didsbury"
    ],
    "name:pol_x_preferred":[
        "Didsbury"
    ],
    "name:por_x_preferred":[
        "Didsbury"
    ],
    "name:rus_x_preferred":[
        "\u0414\u0438\u0434\u0441\u0431\u0435\u0440\u0438"
    ],
    "name:sco_x_preferred":[
        "Didsbury"
    ],
    "name:spa_x_preferred":[
        "Didsbury"
    ],
    "name:swe_x_preferred":[
        "Didsbury"
    ],
    "name:zho_x_preferred":[
        "\u8fea\u5179\u4f2f\u5229"
    ],
    "wd:wordcount":5429,
    "wof:name":"Didsbury",
    "wof:placetype":"neighbourhood"
},
  "geometry": {"coordinates":[-2.233126,53.417107],"type":"Point"}
}