{
  "type": "Feature",
  "properties": {
    "iso:country": "GB",
    "name:ceb_x_preferred": [
      "Didsbury"
    ],
    "name:cym_x_preferred": [
      "Didsbury"
    ],
    "name:deu_x_preferred": [
      "Didsbury"
    ],
    "name:ell_x_preferred": [
      "Ντίντσμπουρι"
    ],
    "name:eng_x_preferred": [
      "Didsbury"
    ],
    "name:fas_x_preferred": [
      "دیدزبری"
    ],
    "name:fra_x_preferred": [
      "Didsbury"
    ],
    "name:gle_x_preferred": [
      "Didsbury"
    ],
    "name:heb_x_preferred": [
      "דידסבורי"
    ],
    "name:ita_x_preferred": [
      "Didsbury"
    ],
    "name:jpn_x_preferred": [
      "ディズベリ"
    ],
    "name:nld_x_preferred": [
      "Didsbury"
    ],
    "name:pol_x_preferred": [
      "Didsbury"
    ],
    "name:sco_x_preferred": [
      "Didsbury"
    ],
    "name:spa_x_preferred": [
      "Didsbury"
    ],
    "name:swe_x_preferred": [
      "Didsbury"
    ],
    "wd:wordcount": 5429,
    "wof:name": "Didsbury",
    "wof:placetype": "neighbourhood"
  },
  "geometry": {"coordinates":[-2.23312593657212,53.41710655518518],"type":"Point"}
}
