{
  "type": "Feature",
  "properties": {
    "gn:admin1_code":"NIR",
    "gn:admin2_code":"N09000010",
    "gn:asciiname":"Ballyward",
    "gn:country_code":"GB",
    "gn:dem":84,
    "gn:feature_class":"P",
    "gn:feature_code":"PPL",
    "gn:name":"Ballyward",
    "gn:population":0,
    "gn:timezone":"Europe/London",
    "iso:country":"GB",
    "wof:name":"Ballyward",
    "wof:placetype":"locality"
},
  "geometry": {"coordinates":[-6.04102,54.2768],"type":"Point"}
}