{
  "type": "Feature",
  "properties": {
    "gn:admin1_code": "ENG",
    "gn:admin2_code": "N4",
    "gn:admin3_code": "41UE",
    "gn:asciiname": "Sideway",
    "gn:country_code": "GB",
    "gn:dem": 108,
    "gn:feature_class": "P",
    "gn:feature_code": "PPLL",
    "gn:name": "Sideway",
    "gn:population": 0,
    "gn:timezone": "Europe/London",
    "iso:country": "GB",
    "name:gle_x_preferred": [
      "Sideway"
    ],
    "name:sco_x_preferred": [
      "Sideway"
    ],
    "wof:name": "Sideway",
    "wof:placetype": "neighbourhood"
  },
  "geometry": {"coordinates":[-2.18388,52.98729],"type":"Point"}
}
