{
  "type": "Feature",
  "properties": {
    "gn:country":"GB",
    "gn:fcode":"PPLX",
    "gn:population":110000,
    "iso:country":"GB",
    "name:ceb_x_preferred":[
        "Mendip"
    ],
    "name:swe_x_preferred":[
        "Mendip"
    ],
    "qs_pg:aaroncc":"GB",
    "qs_pg:gn_country":"GB",
    "qs_pg:gn_fcode":"PPLX",
    "qs_pg:gn_pop":110000,
    "qs_pg:name":"Mendip",
    "qs_pg:photos_9r":0,
    "qs_pg:photos_sr":0,
    "qs_pg:pop_sr":9,
    "qs_pg:qs_pg_placetype":"neighbourhood",
    "wof:name":"Mendip",
    "wof:placetype":"neighbourhood",
    "wof:population":110000
},
  "geometry": {"coordinates":[-2.6266,51.2372],"type":"Point"}
}