{
  "type": "Feature",
  "properties": {
    "gn:admin1_code":"WLS",
    "gn:admin2_code":"Y7",
    "gn:admin3_code":"00NS029",
    "gn:asciiname":"Tavernspite",
    "gn:country_code":"GB",
    "gn:dem":182,
    "gn:feature_class":"P",
    "gn:feature_code":"PPL",
    "gn:name":"Tavernspite",
    "gn:population":349,
    "gn:timezone":"Europe/London",
    "iso:country":"GB",
    "name:cym_x_preferred":[
        "Tavernspite"
    ],
    "wof:name":"Tavernspite",
    "wof:placetype":"neighbourhood",
    "wof:population":349
},
  "geometry": {"coordinates":[-4.64111,51.78194000000001],"type":"Point"}
}