{
  "type": "Feature",
  "properties": {
    "gn:admin1_code":"NIR",
    "gn:admin2_code":"N09000010",
    "gn:asciiname":"Annacloy",
    "gn:country_code":"GB",
    "gn:dem":20,
    "gn:feature_class":"P",
    "gn:feature_code":"PPL",
    "gn:name":"Annacloy",
    "gn:population":0,
    "gn:timezone":"Europe/London",
    "iso:country":"GB",
    "wof:name":"Annacloy",
    "wof:placetype":"locality"
},
  "geometry": {"coordinates":[-5.75,54.35],"type":"Point"}
}