{
  "type": "Feature",
  "properties": {
    "gn:admin1_code":"NIR",
    "gn:admin2_code":"N09000005",
    "gn:asciiname":"Moyle",
    "gn:country_code":"GB",
    "gn:dem":66,
    "gn:feature_class":"P",
    "gn:feature_code":"PPL",
    "gn:name":"Moyle",
    "gn:population":0,
    "gn:timezone":"Europe/London",
    "iso:country":"GB",
    "name:ron_x_preferred":[
        "Moyle"
    ],
    "wof:name":"Moyle",
    "wof:placetype":"locality"
},
  "geometry": {"coordinates":[-7.36667,54.71666999999999],"type":"Point"}
}