{
  "type": "Feature",
  "properties": {
    "iso:country":"GB",
    "name:ara_x_preferred":[
        "\u0639\u200c\u0647 \u063a\u0631\u064a\u0646"
    ],
    "name:cym_x_preferred":[
        "Eye Green"
    ],
    "name:eng_x_preferred":[
        "Eye Green"
    ],
    "name:fra_x_preferred":[
        "Eye Green"
    ],
    "name:nld_x_preferred":[
        "Eye Green"
    ],
    "name:pol_x_preferred":[
        "Eye Green"
    ],
    "name:pol_x_variant":[
        "Parkgate",
        "Eye Green"
    ],
    "name:spa_x_preferred":[
        "Eye Green"
    ],
    "qs_pg:aaroncc":"GB",
    "qs_pg:name":"Eye Green",
    "qs_pg:name_adm0":"United Kingdom",
    "qs_pg:name_adm1":"England",
    "qs_pg:photos":113,
    "qs_pg:photos_1k":23,
    "qs_pg:photos_9k":1,
    "qs_pg:photos_9r":3,
    "qs_pg:photos_all":113,
    "qs_pg:photos_sr":3,
    "qs_pg:pop_sr":0,
    "qs_pg:qs_pg_placetype":"locality",
    "qs_pg:qs_pg_placetype_gp":"Town",
    "qs_pg:woe_adm0":23424975,
    "woe:adm0_id":23424975,
    "woe:name_adm0":"United Kingdom",
    "woe:name_adm1":"England",
    "woe:placetype":"Town",
    "wof:name":"Eye Green",
    "wof:placetype":"neighbourhood"
},
  "geometry": {"coordinates":[-0.183162,52.614688],"type":"Point"}
}