{
  "type": "Feature",
  "properties": {
    "gn:country": "GB",
    "gn:fcode": "PPL",
    "gn:population": 16063,
    "iso:country": "GB",
    "name:ben_x_preferred": [
      "বাকহ্যাভেন"
    ],
    "name:ceb_x_preferred": [
      "Buckhaven"
    ],
    "name:cym_x_preferred": [
      "Buckhaven"
    ],
    "name:deu_x_preferred": [
      "Buckhaven"
    ],
    "name:eng_x_preferred": [
      "Buckhaven"
    ],
    "name:eus_x_preferred": [
      "Buckhaven"
    ],
    "name:fas_x_preferred": [
      "باکهون"
    ],
    "name:fra_x_preferred": [
      "Buckhaven"
    ],
    "name:gla_x_preferred": [
      "Baile 'Ic Eòghainn"
    ],
    "name:gle_x_preferred": [
      "Baile 'Ic Eóghainn"
    ],
    "name:guj_x_preferred": [
      "બકહેવન"
    ],
    "name:ita_x_preferred": [
      "Buckhaven"
    ],
    "name:jpn_x_preferred": [
      "バックヘイブン"
    ],
    "name:kan_x_preferred": [
      "ಬಕ್ಹೇವನ್"
    ],
    "name:kor_x_preferred": [
      "버캐븐"
    ],
    "name:lit_x_preferred": [
      "Bakheivenas"
    ],
    "name:nld_x_preferred": [
      "Buckhaven"
    ],
    "name:por_x_preferred": [
      "Buckhaven"
    ],
    "name:rus_x_preferred": [
      "Бакхейвен"
    ],
    "name:sco_x_preferred": [
      "Buckhynde"
    ],
    "name:spa_x_preferred": [
      "Buckhaven"
    ],
    "name:swe_x_preferred": [
      "Buckhaven"
    ],
    "name:tam_x_preferred": [
      "பக்ஹேவன்"
    ],
    "name:tel_x_preferred": [
      "బుక్హవెన్"
    ],
    "name:ukr_x_preferred": [
      "Бакгейвен"
    ],
    "name:urd_x_preferred": [
      "بوکہاوین"
    ],
    "name:zho_x_preferred": [
      "巴克黑文"
    ],
    "qs_pg:aaroncc": "GB",
    "qs_pg:gn_country": "GB",
    "qs_pg:gn_fcode": "PPL",
    "qs_pg:gn_pop": 16063,
    "qs_pg:name": "Buckhaven",
    "qs_pg:name_adm0": "United Kingdom",
    "qs_pg:name_adm1": "Scotland",
    "qs_pg:photos_9r": 0,
    "qs_pg:photos_sr": 0,
    "qs_pg:pop_sr": 6,
    "qs_pg:qs_pg_placetype": "locality",
    "qs_pg:qs_pg_placetype_gp": "Town",
    "qs_pg:woe_adm0": 23424975,
    "woe:adm0_id": 23424975,
    "woe:name_adm0": "United Kingdom",
    "woe:name_adm1": "Scotland",
    "woe:placetype": "Town",
    "wof:name": "Buckhaven",
    "wof:placetype": "locality",
    "wof:population": 4340
  },
  "geometry": {"coordinates":[-3.03377,56.17149],"type":"Point"}
}
