{
  "type": "Feature",
  "properties": {
    "gn:gn_country":"GB",
    "gn:gn_fcode":"PPL",
    "gn:gn_pop":16063,
    "gn:population":4340,
    "iso:country":"GB",
    "name:baq_x_preferred":[
        "Buckhaven"
    ],
    "name:ben_x_preferred":[
        "\u09ac\u09be\u0995\u09b9\u09cd\u09af\u09be\u09ad\u09c7\u09a8"
    ],
    "name:chi_x_preferred":[
        "\u5df4\u514b\u9ed1\u6587"
    ],
    "name:dut_x_preferred":[
        "Buckhaven"
    ],
    "name:eng_x_preferred":[
        "Buckhaven"
    ],
    "name:fre_x_preferred":[
        "Buckhaven"
    ],
    "name:ger_x_preferred":[
        "Buckhaven"
    ],
    "name:gla_x_preferred":[
        "Baile 'Ic E\u00f2ghainn"
    ],
    "name:gle_x_preferred":[
        "Baile 'Ic E\u00f3ghainn"
    ],
    "name:guj_x_preferred":[
        "\u0aac\u0a95\u0ab9\u0ac7\u0ab5\u0aa8"
    ],
    "name:ita_x_preferred":[
        "Buckhaven"
    ],
    "name:jpn_x_preferred":[
        "\u30d0\u30c3\u30af\u30d8\u30a4\u30d6\u30f3"
    ],
    "name:kan_x_preferred":[
        "\u0cac\u0c95\u0ccd\u0cb9\u0cc7\u0cb5\u0ca8\u0ccd"
    ],
    "name:kor_x_preferred":[
        "\ubc84\uce90\ube10"
    ],
    "name:lit_x_preferred":[
        "Bakheivenas"
    ],
    "name:por_x_preferred":[
        "Buckhaven"
    ],
    "name:rus_x_preferred":[
        "\u0411\u0430\u043a\u0445\u0435\u0439\u0432\u0435\u043d"
    ],
    "name:spa_x_preferred":[
        "Buckhaven"
    ],
    "name:swe_x_preferred":[
        "Buckhaven"
    ],
    "name:tam_x_preferred":[
        "\u0baa\u0b95\u0bcd\u0bb9\u0bc7\u0bb5\u0ba9\u0bcd"
    ],
    "name:tel_x_preferred":[
        "\u0c2c\u0c41\u0c15\u0c4d\u0c39\u0c35\u0c46\u0c28\u0c4d"
    ],
    "name:ukr_x_preferred":[
        "\u0411\u0430\u043a\u0433\u0435\u0439\u0432\u0435\u043d"
    ],
    "name:urd_x_preferred":[
        "\u0628\u0648\u06a9\u06c1\u0627\u0648\u06cc\u0646"
    ],
    "name:wel_x_preferred":[
        "Buckhaven"
    ],
    "qs_pg:aaroncc":"GB",
    "qs_pg:gn_country":"GB",
    "qs_pg:gn_fcode":"PPL",
    "qs_pg:gn_pop":16063,
    "qs_pg:name":"Buckhaven",
    "qs_pg:name_adm0":"United Kingdom",
    "qs_pg:name_adm1":"Scotland",
    "qs_pg:photos_9r":0,
    "qs_pg:photos_sr":0,
    "qs_pg:pop_sr":6,
    "qs_pg:qs_pg_placetype":"locality",
    "qs_pg:qs_pg_placetype_gp":"Town",
    "qs_pg:woe_adm0":23424975,
    "woe:adm0_id":23424975,
    "woe:name_adm0":"United Kingdom",
    "woe:name_adm1":"Scotland",
    "woe:placetype":"Town",
    "wof:name":"Buckhaven",
    "wof:placetype":"locality",
    "wof:population":4340
},
  "geometry": {"coordinates":[-3.03377,56.17149],"type":"Point"}
}