{
  "type": "Feature",
  "properties": {
    "gn:admin1_code":"SCT",
    "gn:admin2_code":"T8",
    "gn:asciiname":"Kilbrennan",
    "gn:country_code":"GB",
    "gn:dem":24,
    "gn:feature_class":"P",
    "gn:feature_code":"PPL",
    "gn:name":"Kilbrennan",
    "gn:population":0,
    "gn:timezone":"Europe/London",
    "iso:country":"GB",
    "wof:name":"Kilbrennan",
    "wof:placetype":"locality"
},
  "geometry": {"coordinates":[-6.16616,56.50763],"type":"Point"}
}