{
  "type": "Feature",
  "properties": {
    "gn:admin1_code": "ENG",
    "gn:admin2_code": "E2",
    "gn:admin3_code": "21UH",
    "gn:admin4_code": "21UH041",
    "gn:asciiname": "Willingdon",
    "gn:cc2": "GB",
    "gn:country_code": "GB",
    "gn:dem": 46,
    "gn:feature_class": "P",
    "gn:feature_code": "PPL",
    "gn:name": "Willingdon",
    "gn:population": 0,
    "gn:timezone": "Europe/London",
    "iso:country": "GB",
    "name:deu_x_preferred": [
      "Willingdon"
    ],
    "name:kor_x_preferred": [
      "윌링던"
    ],
    "name:nds_x_preferred": [
      "Willingdon"
    ],
    "name:und_x_variant": [
      "Wiltingdon"
    ],
    "wof:name": "Willingdon",
    "wof:placetype": "neighbourhood"
  },
  "geometry": {"coordinates":[0.255,50.80008],"type":"Point"}
}
