{
  "type": "Feature",
  "properties": {
    "gn:admin1_code":"SCT",
    "gn:admin2_code":"T9",
    "gn:asciiname":"Linton",
    "gn:country_code":"GB",
    "gn:dem":100,
    "gn:feature_class":"P",
    "gn:feature_code":"PPL",
    "gn:name":"Linton",
    "gn:population":0,
    "gn:timezone":"Europe/London",
    "iso:country":"GB",
    "name:ceb_x_preferred":[
        "Linton"
    ],
    "name:deu_x_preferred":[
        "Linton"
    ],
    "name:fra_x_preferred":[
        "Linton"
    ],
    "name:ita_x_preferred":[
        "Linton"
    ],
    "name:jpn_x_preferred":[
        "\u30ea\u30f3\u30c8\u30f3"
    ],
    "name:nld_x_preferred":[
        "Linton"
    ],
    "name:pol_x_preferred":[
        "Linton"
    ],
    "name:por_x_preferred":[
        "Linton"
    ],
    "name:spa_x_preferred":[
        "Linton"
    ],
    "name:srp_x_preferred":[
        "\u041b\u0438\u0441\u0442\u043e\u043d"
    ],
    "name:swe_x_preferred":[
        "Linton"
    ],
    "name:ukr_x_preferred":[
        "\u041b\u0456\u043d\u0442\u043e\u043d"
    ],
    "wof:name":"Linton",
    "wof:placetype":"locality"
},
  "geometry": {"coordinates":[-2.36667,55.51667],"type":"Point"}
}