{
  "type": "Feature",
  "properties": {
    "gn:admin1_code":"SCT",
    "gn:admin2_code":"T9",
    "gn:asciiname":"Linton",
    "gn:country_code":"GB",
    "gn:dem":100,
    "gn:feature_class":"P",
    "gn:feature_code":"PPL",
    "gn:name":"Linton",
    "gn:population":0,
    "gn:timezone":"Europe/London",
    "iso:country":"GB",
    "wof:name":"Linton",
    "wof:placetype":"locality"
},
  "geometry": {"coordinates":[-2.36667,55.51667],"type":"Point"}
}