{
  "type": "Feature",
  "properties": {
    "gn:gn_country":"GB",
    "gn:gn_fcode":"PPL",
    "gn:gn_pop":0,
    "iso:country":"GB",
    "name:ceb_x_preferred":[
        "Caynham"
    ],
    "name:cym_x_preferred":[
        "Caynham"
    ],
    "name:eng_x_preferred":[
        "Caynham"
    ],
    "name:fra_x_preferred":[
        "Caynham"
    ],
    "name:nld_x_preferred":[
        "Caynham"
    ],
    "name:pol_x_preferred":[
        "Caynham"
    ],
    "name:swe_x_preferred":[
        "Caynham"
    ],
    "qs_pg:aaroncc":"GB",
    "qs_pg:gn_country":"GB",
    "qs_pg:gn_fcode":"PPL",
    "qs_pg:gn_pop":0,
    "qs_pg:name":"Cranham",
    "qs_pg:name_adm0":"United Kingdom",
    "qs_pg:name_adm1":"England",
    "qs_pg:photos":239,
    "qs_pg:photos_1k":48,
    "qs_pg:photos_9k":1,
    "qs_pg:photos_9r":4,
    "qs_pg:photos_all":239,
    "qs_pg:photos_sr":4,
    "qs_pg:pop_sr":0,
    "qs_pg:qs_pg_placetype":"locality",
    "qs_pg:qs_pg_placetype_gp":"Town",
    "qs_pg:woe_adm0":23424975,
    "woe:adm0_id":23424975,
    "woe:name_adm0":"United Kingdom",
    "woe:name_adm1":"England",
    "woe:placetype":"Town",
    "wof:name":"Cranham",
    "wof:placetype":"neighbourhood"
},
  "geometry": {"coordinates":[-2.66174,52.35368],"type":"Point"}
}