{
  "type": "Feature",
  "properties": {
    "gn:gn_country":"GB",
    "gn:gn_fcode":"PPL",
    "gn:gn_pop":0,
    "iso:country":"GB",
    "name:ceb_x_preferred":[
        "Danby Wiske"
    ],
    "name:eng_x_preferred":[
        "Danby Wiske"
    ],
    "name:fra_x_preferred":[
        "Danby Wiske"
    ],
    "name:nld_x_preferred":[
        "Danby Wiske"
    ],
    "name:pol_x_preferred":[
        "Danby Wiske"
    ],
    "name:swe_x_preferred":[
        "Danby Wiske"
    ],
    "qs_pg:aaroncc":"GB",
    "qs_pg:gn_country":"GB",
    "qs_pg:gn_fcode":"PPL",
    "qs_pg:gn_pop":0,
    "qs_pg:name":"Danby Wiske",
    "qs_pg:name_adm0":"United Kingdom",
    "qs_pg:name_adm1":"England",
    "qs_pg:photos":56,
    "qs_pg:photos_1k":11,
    "qs_pg:photos_9k":1,
    "qs_pg:photos_9r":2,
    "qs_pg:photos_all":56,
    "qs_pg:photos_sr":2,
    "qs_pg:pop_sr":0,
    "qs_pg:qs_pg_placetype":"locality",
    "qs_pg:qs_pg_placetype_gp":"Town",
    "qs_pg:woe_adm0":23424975,
    "woe:adm0_id":23424975,
    "woe:name_adm0":"United Kingdom",
    "woe:name_adm1":"England",
    "woe:placetype":"Town",
    "wof:name":"Danby Wiske",
    "wof:placetype":"neighbourhood"
},
  "geometry": {"coordinates":[-1.48264,54.38179],"type":"Point"}
}