{
  "type": "Feature",
  "properties": {
    "gn:country":"GB",
    "gn:fcode":"PPL",
    "gn:population":0,
    "iso:country":"GB",
    "name:ceb_x_preferred":[
        "Besthorpe"
    ],
    "name:cym_x_preferred":[
        "Besthorpe"
    ],
    "name:eng_x_preferred":[
        "Besthorpe"
    ],
    "name:fra_x_preferred":[
        "Besthorpe"
    ],
    "name:gle_x_preferred":[
        "Besthorpe"
    ],
    "name:lld_x_preferred":[
        "Besthorpe"
    ],
    "name:nld_x_preferred":[
        "Besthorpe"
    ],
    "name:pol_x_preferred":[
        "Besthorpe"
    ],
    "name:swe_x_preferred":[
        "Besthorpe"
    ],
    "name:tur_x_preferred":[
        "Besthorpe"
    ],
    "qs_pg:aaroncc":"GB",
    "qs_pg:gn_country":"GB",
    "qs_pg:gn_fcode":"PPL",
    "qs_pg:gn_pop":0,
    "qs_pg:name":"Pensthorpe",
    "qs_pg:name_adm0":"United Kingdom",
    "qs_pg:name_adm1":"England",
    "qs_pg:photos":1540,
    "qs_pg:photos_1k":312,
    "qs_pg:photos_9k":7,
    "qs_pg:photos_9r":8,
    "qs_pg:photos_all":1540,
    "qs_pg:photos_sr":13,
    "qs_pg:pop_sr":0,
    "qs_pg:qs_pg_placetype":"locality",
    "qs_pg:qs_pg_placetype_gp":"Town",
    "qs_pg:woe_adm0":23424975,
    "woe:adm0_id":23424975,
    "woe:name_adm0":"United Kingdom",
    "woe:name_adm1":"England",
    "woe:placetype":"Town",
    "wof:name":"Pensthorpe",
    "wof:placetype":"neighbourhood"
},
  "geometry": {"coordinates":[1.03333,52.51667],"type":"Point"}
}