{
  "type": "Feature",
  "properties": {
    "iso:country": "GB",
    "name:eng_x_preferred": [
      "Shelfield"
    ],
    "name:fra_x_preferred": [
      "Shelfield"
    ],
    "name:nld_x_preferred": [
      "Shelfield"
    ],
    "qs:gn_local": 0,
    "qs:local_max": 2515,
    "qs:local_sum": 9671,
    "qs:localhoods": 12,
    "qs:name": "Shelfield",
    "qs:name_adm0": "United Kingdom",
    "qs:name_adm1": "England",
    "qs:name_adm2": "West Midlands",
    "qs:name_lau": "Walsall Metropolitan Borough",
    "qs:name_local": "Walsall",
    "qs:photo_max": 102,
    "qs:photo_sum": 551,
    "qs:placetype": "Suburb",
    "qs:quad_count": 53,
    "qs:woe_adm0": 23424975,
    "qs:woe_adm1": 24554868,
    "qs:woe_adm2": 12602191,
    "qs:woe_lau": 12695868,
    "qs:woe_local": 39052,
    "qs:woe_ver": "7.10.0",
    "wd:wordcount": 161,
    "wof:lang": [
      "eng"
    ],
    "wof:name": "Shelfield",
    "wof:placetype": "neighbourhood"
  },
  "geometry": {"coordinates":[-1.949005,52.616483],"type":"Point"}
}
