{
  "type": "Feature",
  "properties": {
    "name:eng_x_preferred":[
        "Shettleston"
    ],
    "name:eus_x_preferred":[
        "Shettleston"
    ],
    "name:gle_x_preferred":[
        "Baile Nighean Sheadna"
    ],
    "name:jpn_x_preferred":[
        "\u30b7\u30e3\u30c3\u30c6\u30eb\u30b9\u30c8\u30f3"
    ],
    "name:ukr_x_preferred":[
        "\u0428\u0435\u0442\u0442\u043b\u0441\u0442\u043e\u043d"
    ],
    "wd:wordcount":467,
    "wof:name":"Shettleston",
    "wof:placetype":"neighbourhood"
},
  "geometry": {"coordinates":[-4.16638490014048,55.85125197536716],"type":"Point"}
}