{
  "type": "Feature",
  "properties": {
    "gn:admin1_code":"ENG",
    "gn:admin2_code":"N7",
    "gn:admin3_code":"43UF",
    "gn:asciiname":"Mugswell",
    "gn:country_code":"GB",
    "gn:dem":157,
    "gn:feature_class":"P",
    "gn:feature_code":"PPL",
    "gn:name":"Mugswell",
    "gn:population":0,
    "gn:timezone":"Europe/London",
    "iso:country":"GB",
    "name:pol_x_preferred":[
        "Mugswell"
    ],
    "wof:name":"Mugswell",
    "wof:placetype":"neighbourhood"
},
  "geometry": {"coordinates":[-0.19848,51.27794],"type":"Point"}
}