{
  "type": "Feature",
  "properties": {
    "gn:admin1_code":"ENG",
    "gn:admin2_code":"H2",
    "gn:admin3_code":"30UQ",
    "gn:admin4_code":"30UQ019",
    "gn:asciiname":"Stalmine",
    "gn:country_code":"GB",
    "gn:dem":13,
    "gn:feature_class":"P",
    "gn:feature_code":"PPL",
    "gn:name":"Stalmine",
    "gn:population":0,
    "gn:timezone":"Europe/London",
    "iso:country":"GB",
    "name:pol_x_preferred":[
        "Stalmine"
    ],
    "name:spa_x_preferred":[
        "Stalmine"
    ],
    "name:swe_x_preferred":[
        "Stalmine"
    ],
    "wof:name":"Stalmine",
    "wof:placetype":"neighbourhood"
},
  "geometry": {"coordinates":[-2.95481,53.90004],"type":"Point"}
}