{
  "type": "Feature",
  "properties": {
    "iso:country": "GB",
    "name:eng_x_preferred": [
      "Blakenhall"
    ],
    "name:fra_x_preferred": [
      "Blakenhall"
    ],
    "name:gle_x_preferred": [
      "Blakenhall"
    ],
    "name:ita_x_preferred": [
      "Blakenhall"
    ],
    "name:nld_x_preferred": [
      "Blakenhall"
    ],
    "name:pol_x_preferred": [
      "Blakenhall"
    ],
    "name:pol_x_variant": [
      "Blundellsands"
    ],
    "qs:gn_adm0_cc": "GB",
    "qs:gn_local": 2633687,
    "qs:gn_nam_loc": "easton grey",
    "qs:gn_namadm1": "ENG",
    "qs:local_max": 1959,
    "qs:local_sum": 12898,
    "qs:localhoods": 20,
    "qs:name": "Blakenhall",
    "qs:name_adm0": "United Kingdom",
    "qs:name_adm1": "England",
    "qs:name_adm2": "West Midlands",
    "qs:name_lau": "Wolverhampton Metropolitan Borough",
    "qs:name_local": "Wolverhampton",
    "qs:photo_max": 92,
    "qs:photo_sum": 575,
    "qs:placetype": "Suburb",
    "qs:quad_count": 35,
    "qs:woe_adm0": 23424975,
    "qs:woe_adm1": 24554868,
    "qs:woe_adm2": 12602191,
    "qs:woe_lau": 12695869,
    "qs:woe_local": 40859,
    "qs:woe_ver": "7.10.0",
    "wd:wordcount": 1157,
    "wof:lang": [
      "eng"
    ],
    "wof:name": "Blakenhall",
    "wof:placetype": "neighbourhood"
  },
  "geometry": {"coordinates":[-2.130166,52.574068],"type":"Point"}
}
