{
  "type": "Feature",
  "properties": {
    "gn:admin1_code":"SCT",
    "gn:admin2_code":"T8",
    "gn:asciiname":"Laglingarten",
    "gn:country_code":"GB",
    "gn:dem":59,
    "gn:feature_class":"P",
    "gn:feature_code":"PPL",
    "gn:name":"Laglingarten",
    "gn:population":0,
    "gn:timezone":"Europe/London",
    "iso:country":"GB",
    "wof:name":"Laglingarten",
    "wof:placetype":"locality"
},
  "geometry": {"coordinates":[-4.99552,56.22775],"type":"Point"}
}