{
  "type": "Feature",
  "properties": {
    "iso:country": "GB",
    "name:deu_x_preferred": [
      "Ethie Castle"
    ],
    "name:ita_x_preferred": [
      "Ethie Castle"
    ],
    "name:por_x_preferred": [
      "Castelo Ethie"
    ],
    "name:sco_x_preferred": [
      "Ethie Castle"
    ],
    "qs_pg:aaroncc": "GB",
    "qs_pg:name": "Ethie Castle",
    "qs_pg:name_adm0": "United Kingdom",
    "qs_pg:name_adm1": "Scotland",
    "qs_pg:photos": 49,
    "qs_pg:photos_1k": 10,
    "qs_pg:photos_9k": 1,
    "qs_pg:photos_9r": 2,
    "qs_pg:photos_all": 49,
    "qs_pg:photos_sr": 2,
    "qs_pg:pop_sr": 0,
    "qs_pg:qs_pg_placetype": "locality",
    "qs_pg:qs_pg_placetype_gp": "Town",
    "qs_pg:woe_adm0": 23424975,
    "woe:adm0_id": 23424975,
    "woe:name_adm0": "United Kingdom",
    "woe:name_adm1": "Scotland",
    "woe:placetype": "Town",
    "wof:name": "Ethie Castle",
    "wof:placetype": "locality"
  },
  "geometry": {"coordinates":[-2.499217,56.614025],"type":"Point"}
}
