{
  "type": "Feature",
  "properties": {
    "iso:country": "GB",
    "qs_pg:aaroncc": "GB",
    "qs_pg:name": "Castle Grounds",
    "qs_pg:name_adm0": "United Kingdom",
    "qs_pg:name_adm1": "Wales",
    "qs_pg:photos": 396,
    "qs_pg:photos_1k": 80,
    "qs_pg:photos_9k": 2,
    "qs_pg:photos_9r": 5,
    "qs_pg:photos_all": 396,
    "qs_pg:photos_sr": 6,
    "qs_pg:pop_sr": 0,
    "qs_pg:qs_pg_placetype": "locality",
    "qs_pg:qs_pg_placetype_gp": "Town",
    "qs_pg:woe_adm0": 23424975,
    "woe:adm0_id": 23424975,
    "woe:name_adm0": "United Kingdom",
    "woe:name_adm1": "Wales",
    "woe:placetype": "Town",
    "wof:name": "Castle Grounds",
    "wof:placetype": "neighbourhood"
  },
  "geometry": {"coordinates":[-3.182189,51.48174],"type":"Point"}
}
