{
  "type": "Feature",
  "properties": {
    "gn:admin1_code":"SCT",
    "gn:admin2_code":"T7",
    "gn:asciiname":"Ruthven",
    "gn:country_code":"GB",
    "gn:dem":41,
    "gn:feature_class":"P",
    "gn:feature_code":"PPL",
    "gn:name":"Ruthven",
    "gn:population":0,
    "gn:timezone":"Europe/London",
    "iso:country":"GB",
    "name:eus_x_preferred":[
        "Ruthven"
    ],
    "wof:name":"Ruthven",
    "wof:placetype":"locality"
},
  "geometry": {"coordinates":[-3.15,56.61667],"type":"Point"}
}