{
  "type": "Feature",
  "properties": {
    "gn:admin1_code":"WLS",
    "gn:admin2_code":"X1",
    "gn:admin3_code":"00NA028",
    "gn:asciiname":"Gwredog",
    "gn:country_code":"GB",
    "gn:dem":65,
    "gn:feature_class":"P",
    "gn:feature_code":"PPL",
    "gn:name":"Gwredog",
    "gn:population":0,
    "gn:timezone":"Europe/London",
    "iso:country":"GB",
    "name:ara_x_preferred":[
        "\u0631\u064a\u062f\u0648\u063a"
    ],
    "name:bre_x_preferred":[
        "Gwredog"
    ],
    "wof:name":"Gwredog",
    "wof:placetype":"neighbourhood"
},
  "geometry": {"coordinates":[-4.39656,53.3485],"type":"Point"}
}