{
  "type": "Feature",
  "properties": {
    "iso:country":"GB",
    "name:ceb_x_preferred":[
        "Muncaster Castle"
    ],
    "name:deu_x_preferred":[
        "Muncaster Castle"
    ],
    "name:jpn_x_preferred":[
        "\u30de\u30f3\u30ab\u30b9\u30bf\u30fc\u57ce"
    ],
    "name:rus_x_preferred":[
        "\u0417\u0430\u043c\u043e\u043a \u041c\u0430\u043d\u043a\u0430\u0441\u0442\u0435\u0440"
    ],
    "name:swe_x_preferred":[
        "Muncaster Castle"
    ],
    "qs_pg:aaroncc":"GB",
    "qs_pg:name":"Muncaster Castle",
    "qs_pg:name_adm0":"United Kingdom",
    "qs_pg:name_adm1":"England",
    "qs_pg:photos":745,
    "qs_pg:photos_1k":151,
    "qs_pg:photos_9k":3,
    "qs_pg:photos_9r":5,
    "qs_pg:photos_all":745,
    "qs_pg:photos_sr":8,
    "qs_pg:pop_sr":0,
    "qs_pg:qs_pg_placetype":"locality",
    "qs_pg:qs_pg_placetype_gp":"Town",
    "qs_pg:woe_adm0":23424975,
    "woe:adm0_id":23424975,
    "woe:name_adm0":"United Kingdom",
    "woe:name_adm1":"England",
    "woe:placetype":"Town",
    "wof:name":"Muncaster Castle",
    "wof:placetype":"neighbourhood"
},
  "geometry": {"coordinates":[-3.38188,54.356093],"type":"Point"}
}