{
  "type": "Feature",
  "properties": {
    "iso:country": "GB",
    "wof:name": "Sourmilk Hill",
    "wof:placetype": "neighbourhood"
  },
  "geometry": {"coordinates":[-1.40893125306628,54.86459744865071],"type":"Point"}
}
