{
  "type": "Feature",
  "properties": {
    "iso:country":"GB",
    "wof:name":"Dukes Moor",
    "wof:placetype":"neighbourhood"
},
  "geometry": {"coordinates":[-1.61894235787767,54.99935853265912],"type":"Point"}
}