{
  "type": "Feature",
  "properties": {
    "iso:country":"GB",
    "name:ceb_x_preferred":[
        "Greenham"
    ],
    "name:cym_x_preferred":[
        "Greenham"
    ],
    "name:deu_x_preferred":[
        "Greenham"
    ],
    "name:nld_x_preferred":[
        "Greenham"
    ],
    "name:pol_x_preferred":[
        "Greenham"
    ],
    "name:swe_x_preferred":[
        "Greenham"
    ],
    "qs_pg:aaroncc":"GB",
    "qs_pg:name":"Greenham",
    "qs_pg:name_adm0":"United Kingdom",
    "qs_pg:name_adm1":"England",
    "qs_pg:photos":12,
    "qs_pg:photos_1k":2,
    "qs_pg:photos_9k":1,
    "qs_pg:photos_9r":1,
    "qs_pg:photos_all":12,
    "qs_pg:photos_sr":1,
    "qs_pg:pop_sr":0,
    "qs_pg:qs_pg_placetype":"locality",
    "qs_pg:qs_pg_placetype_gp":"Town",
    "qs_pg:woe_adm0":23424975,
    "woe:adm0_id":23424975,
    "woe:name_adm0":"United Kingdom",
    "woe:name_adm1":"England",
    "woe:placetype":"Town",
    "wof:name":"Greenham",
    "wof:placetype":"neighbourhood"
},
  "geometry": {"coordinates":[-3.318289,50.9727005],"type":"Point"}
}