{
  "type": "Feature",
  "properties": {
    "iso:country": "GB",
    "name:ara_x_preferred": [
      "جامعة ساسكس"
    ],
    "name:azb_x_preferred": [
      "ساسکس بیلیم‌یوردو"
    ],
    "name:cym_x_preferred": [
      "Prifysgol Sussex"
    ],
    "name:dan_x_preferred": [
      "University of Sussex"
    ],
    "name:deu_x_preferred": [
      "University of Sussex"
    ],
    "name:ell_x_preferred": [
      "Πανεπιστήμιο του Σάσσεξ"
    ],
    "name:est_x_preferred": [
      "Sussexi Ülikool"
    ],
    "name:fas_x_preferred": [
      "دانشگاه ساسکس"
    ],
    "name:fra_x_preferred": [
      "Université du Sussex"
    ],
    "name:fry_x_preferred": [
      "Universiteit fan Susseks"
    ],
    "name:ita_x_preferred": [
      "Università del Sussex"
    ],
    "name:jpn_x_preferred": [
      "サセックス大学"
    ],
    "name:kor_x_preferred": [
      "서식스 대학교"
    ],
    "name:nld_x_preferred": [
      "Universiteit van Sussex"
    ],
    "name:pnb_x_preferred": [
      "سوسکس یونیورسٹی"
    ],
    "name:pol_x_preferred": [
      "Uniwersytet Sussex"
    ],
    "name:ron_x_preferred": [
      "Universitatea din Sussex"
    ],
    "name:slv_x_preferred": [
      "Univerza Sussexa"
    ],
    "name:swe_x_preferred": [
      "University of Sussex"
    ],
    "name:tgl_x_preferred": [
      "Unibersidad ng Sussex"
    ],
    "name:tha_x_preferred": [
      "มหาวิทยาลัยซัสเซ็กส์"
    ],
    "name:tur_x_preferred": [
      "Sussex Üniversitesi"
    ],
    "name:ukr_x_preferred": [
      "Університет Сассекса"
    ],
    "name:urd_x_preferred": [
      "یونیورسٹی آف سسیکس"
    ],
    "name:wuu_x_preferred": [
      "萨塞克斯大学"
    ],
    "name:zho_x_preferred": [
      "萨塞克斯大学"
    ],
    "name:zul_x_preferred": [
      "University of Sussex"
    ],
    "qs_pg:aaroncc": "GB",
    "qs_pg:name": "University of Sussex",
    "qs_pg:name_adm0": "United Kingdom",
    "qs_pg:name_adm1": "England",
    "qs_pg:photos": 342,
    "qs_pg:photos_1k": 69,
    "qs_pg:photos_9k": 2,
    "qs_pg:photos_9r": 5,
    "qs_pg:photos_all": 342,
    "qs_pg:photos_sr": 5,
    "qs_pg:pop_sr": 0,
    "qs_pg:qs_pg_placetype": "locality",
    "qs_pg:qs_pg_placetype_gp": "Town",
    "qs_pg:woe_adm0": 23424975,
    "woe:adm0_id": 23424975,
    "woe:name_adm0": "United Kingdom",
    "woe:name_adm1": "England",
    "woe:placetype": "Town",
    "wof:name": "University of Sussex",
    "wof:placetype": "neighbourhood"
  },
  "geometry": {"coordinates":[-0.0868065,50.865299],"type":"Point"}
}
