{
  "type": "Feature",
  "properties": {
    "gn:country": "GB",
    "gn:fcode": "PPL",
    "gn:population": 0,
    "iso:country": "GB",
    "name:ben_x_preferred": [
      "হার্বলডাউন"
    ],
    "name:cym_x_preferred": [
      "Harbledown"
    ],
    "name:deu_x_preferred": [
      "Harbledown"
    ],
    "name:eng_x_preferred": [
      "Harbledown"
    ],
    "name:fra_x_preferred": [
      "Harbledown"
    ],
    "name:guj_x_preferred": [
      "હાર્બ્લેડાઉન"
    ],
    "name:jpn_x_preferred": [
      "ハーブルダウン"
    ],
    "name:kan_x_preferred": [
      "ಹಾರ್ಬೆಲ್ಡೌನ್"
    ],
    "name:kor_x_preferred": [
      "하블다운"
    ],
    "name:lit_x_preferred": [
      "Harbldaunas"
    ],
    "name:nld_x_preferred": [
      "Harbledown"
    ],
    "name:pol_x_preferred": [
      "Harbledown"
    ],
    "name:por_x_preferred": [
      "Harbledown"
    ],
    "name:rus_x_preferred": [
      "Харблдаун"
    ],
    "name:spa_x_preferred": [
      "Harbledown"
    ],
    "name:tam_x_preferred": [
      "ஹர்ப்ளேட்ஓன்"
    ],
    "name:tel_x_preferred": [
      "హర్బ్లేడౌన్"
    ],
    "name:urd_x_preferred": [
      "ہاربلیدوون"
    ],
    "qs_pg:aaroncc": "GB",
    "qs_pg:gn_country": "GB",
    "qs_pg:gn_fcode": "PPL",
    "qs_pg:gn_pop": 0,
    "qs_pg:name": "Harbledown",
    "qs_pg:name_adm0": "United Kingdom",
    "qs_pg:name_adm1": "England",
    "qs_pg:photos": 199,
    "qs_pg:photos_1k": 40,
    "qs_pg:photos_9k": 1,
    "qs_pg:photos_9r": 4,
    "qs_pg:photos_all": 199,
    "qs_pg:photos_sr": 4,
    "qs_pg:pop_sr": 0,
    "qs_pg:qs_pg_placetype": "locality",
    "qs_pg:qs_pg_placetype_gp": "Town",
    "qs_pg:woe_adm0": 23424975,
    "woe:adm0_id": 23424975,
    "woe:name_adm0": "United Kingdom",
    "woe:name_adm1": "England",
    "woe:placetype": "Town",
    "wof:name": "Harbledown",
    "wof:placetype": "neighbourhood"
  },
  "geometry": {"coordinates":[1.05283,51.28328],"type":"Point"}
}
