{
  "type": "Feature",
  "properties": {
    "gn:admin1_code": "ENG",
    "gn:admin2_code": "P3",
    "gn:admin3_code": "44UE",
    "gn:admin4_code": "44UE016",
    "gn:asciiname": "Winderton",
    "gn:country_code": "GB",
    "gn:dem": 143,
    "gn:feature_class": "P",
    "gn:feature_code": "PPL",
    "gn:name": "Winderton",
    "gn:population": 0,
    "gn:timezone": "Europe/London",
    "iso:country": "GB",
    "wof:name": "Winderton",
    "wof:placetype": "neighbourhood"
  },
  "geometry": {"coordinates":[-1.5241,52.06199],"type":"Point"}
}
