{
  "type": "Feature",
  "properties": {
    "iso:country": "GB",
    "name:eng_x_preferred": [
      "Waddicar"
    ],
    "name:pol_x_preferred": [
      "Waddicar"
    ],
    "qs:gn_local": 0,
    "qs:local_max": 145,
    "qs:local_sum": 145,
    "qs:localhoods": 1,
    "qs:name": "Waddicar",
    "qs:name_adm0": "United Kingdom",
    "qs:name_adm1": "England",
    "qs:name_adm2": "Merseyside",
    "qs:name_lau": "Sefton Metropolitan Borough",
    "qs:name_local": "Sefton Metropolitan Borough",
    "qs:photo_max": 25,
    "qs:photo_sum": 145,
    "qs:placetype": "Suburb",
    "qs:quad_count": 27,
    "qs:woe_adm0": 23424975,
    "qs:woe_adm1": 24554868,
    "qs:woe_adm2": 12602161,
    "qs:woe_lau": 12695852,
    "qs:woe_local": 12695852,
    "qs:woe_ver": "7.10.0",
    "wd:wordcount": 44,
    "wof:lang": [
      "eng"
    ],
    "wof:name": "Waddicar",
    "wof:placetype": "neighbourhood"
  },
  "geometry": {"coordinates":[-2.916397,53.491166],"type":"Point"}
}
