{
  "type": "Feature",
  "properties": {
    "gn:country": "GB",
    "gn:fcode": "PPL",
    "gn:population": 0,
    "iso:country": "GB",
    "name:eng_x_preferred": [
      "Ballynure"
    ],
    "name:eus_x_preferred": [
      "Ballynure"
    ],
    "name:fra_x_preferred": [
      "Ballynure"
    ],
    "name:gla_x_preferred": [
      "Baile an Iúir"
    ],
    "name:gle_x_preferred": [
      "Baile an Iúir"
    ],
    "name:msa_x_preferred": [
      "Ballynure"
    ],
    "name:nld_x_preferred": [
      "Ballynure"
    ],
    "name:pli_x_preferred": [
      "बल्ल्य्नुरे"
    ],
    "name:spa_x_preferred": [
      "Ballynure"
    ],
    "qs_pg:aaroncc": "GB",
    "qs_pg:gn_country": "GB",
    "qs_pg:gn_fcode": "PPL",
    "qs_pg:gn_pop": 0,
    "qs_pg:name": "Ballynure",
    "qs_pg:name_adm0": "United Kingdom",
    "qs_pg:name_adm1": "Northern Ireland",
    "qs_pg:photos_9k": 1,
    "qs_pg:photos_9r": 1,
    "qs_pg:photos_all": 1,
    "qs_pg:photos_sr": 0,
    "qs_pg:pop_sr": 0,
    "qs_pg:qs_pg_placetype": "locality",
    "qs_pg:qs_pg_placetype_gp": "Town",
    "qs_pg:woe_adm0": 23424975,
    "woe:adm0_id": 23424975,
    "woe:name_adm0": "United Kingdom",
    "woe:name_adm1": "Northern Ireland",
    "woe:placetype": "Town",
    "wof:name": "Ballynure",
    "wof:placetype": "locality"
  },
  "geometry": {"coordinates":[-5.95,54.76667],"type":"Point"}
}
