{
  "type": "Feature",
  "properties": {
    "gn:admin1_code":"ENG",
    "gn:admin2_code":"Z7",
    "gn:admin3_code":"00EQ077",
    "gn:asciiname":"Jodrell Bank",
    "gn:country_code":"GB",
    "gn:dem":81,
    "gn:feature_class":"P",
    "gn:feature_code":"PPL",
    "gn:name":"Jodrell Bank",
    "gn:population":0,
    "gn:timezone":"Europe/London",
    "iso:country":"GB",
    "name:deu_x_preferred":[
        "Jodrell-Bank-Radioobservatorium"
    ],
    "name:est_x_preferred":[
        "Jodrell Banki observatoorium"
    ],
    "name:gle_x_preferred":[
        "Jodrell Bank"
    ],
    "name:hye_x_preferred":[
        "\u054b\u0578\u0564\u0580\u0565\u056c \u0532\u0565\u0576\u056f\u056b \u057c\u0561\u0564\u056b\u0578\u0561\u057d\u057f\u0572\u0561\u0564\u056b\u057f\u0561\u0580\u0561\u0576"
    ],
    "name:ind_x_preferred":[
        "Jodrell Bank Observatory"
    ],
    "name:ita_x_preferred":[
        "Osservatorio Jodrell Bank"
    ],
    "name:jpn_x_preferred":[
        "\u30b8\u30e7\u30c9\u30ec\u30eb\u30d0\u30f3\u30af\u5929\u6587\u53f0"
    ],
    "name:kor_x_preferred":[
        "\uc870\ub4dc\ub7f4 \ubc45\ud06c \ucc9c\ubb38\ub300"
    ],
    "name:lav_x_preferred":[
        "D\u017eodrela Benka observatorija"
    ],
    "name:ltz_x_preferred":[
        "Jodrell Bank Observatoire"
    ],
    "name:nld_x_preferred":[
        "Jodrell Bank Observatory"
    ],
    "name:nno_x_preferred":[
        "Jodrell Bank Observatory"
    ],
    "name:nor_x_preferred":[
        "Jodrell Bank Observatory"
    ],
    "name:pol_x_preferred":[
        "Obserwatorium Jodrell Bank"
    ],
    "name:por_x_preferred":[
        "Observat\u00f3rio Jodrell Bank"
    ],
    "name:rus_x_preferred":[
        "\u0414\u0436\u043e\u0434\u0440\u0435\u043b\u043b-\u0411\u044d\u043d\u043a"
    ],
    "name:spa_x_preferred":[
        "Observatorio Jodrell Bank"
    ],
    "name:swe_x_preferred":[
        "Jodrell Bank"
    ],
    "name:ukr_x_preferred":[
        "\u041e\u0431\u0441\u0435\u0440\u0432\u0430\u0442\u043e\u0440\u0456\u044f \u0414\u0436\u043e\u0434\u0440\u0435\u043b\u043b \u0411\u0435\u043d\u043a"
    ],
    "name:uzb_x_preferred":[
        "Jodrell-benk radioastronomik rasadxonasi"
    ],
    "name:zho_x_preferred":[
        "\u5353\u745e\u723e\u6cb3\u5cb8\u5929\u6587\u53f0"
    ],
    "wof:name":"Jodrell Bank",
    "wof:placetype":"neighbourhood"
},
  "geometry": {"coordinates":[-2.30231,53.2312],"type":"Point"}
}