{
  "type": "Feature",
  "properties": {
    "gn:gn_country":"GB",
    "gn:gn_fcode":"PPL",
    "gn:gn_pop":0,
    "iso:country":"GB",
    "name:baq_x_preferred":[
        "John o' Groats"
    ],
    "name:cat_x_preferred":[
        "John o' Groats"
    ],
    "name:chi_x_preferred":[
        "\u7d04\u7ff0\u5967\u683c\u7f85\u8328"
    ],
    "name:dan_x_preferred":[
        "John O'Groats"
    ],
    "name:dut_x_preferred":[
        "John o' Groats"
    ],
    "name:eng_x_preferred":[
        "John o' Groats"
    ],
    "name:epo_x_preferred":[
        "John o' Groats"
    ],
    "name:fre_x_preferred":[
        "John o' Groats"
    ],
    "name:ger_x_preferred":[
        "John o\u2019 Groats"
    ],
    "name:gla_x_preferred":[
        "Taigh Iain Ghr\u00f2t"
    ],
    "name:gle_x_preferred":[
        "Taigh Iain Ghr\u00f3t"
    ],
    "name:ice_x_preferred":[
        "John o\u2019 Groats"
    ],
    "name:ita_x_preferred":[
        "John o' Groats"
    ],
    "name:jpn_x_preferred":[
        "\u30b8\u30e7\u30f3\u30fb\u30aa\u30fb\u30b0\u30ed\u30fc\u30c4"
    ],
    "name:kor_x_preferred":[
        "\uc874\uc624\uadf8\ub85c\uce20"
    ],
    "name:nno_x_preferred":[
        "John o' Groats"
    ],
    "name:nob_x_preferred":[
        "John o' Groats"
    ],
    "name:pol_x_preferred":[
        "John o'Groats"
    ],
    "name:por_x_preferred":[
        "John o' Groats"
    ],
    "name:sco_x_preferred":[
        "John o Groats"
    ],
    "name:spa_x_preferred":[
        "John o' Groats"
    ],
    "name:swe_x_preferred":[
        "John o' Groats"
    ],
    "qs_pg:aaroncc":"GB",
    "qs_pg:gn_country":"GB",
    "qs_pg:gn_fcode":"PPL",
    "qs_pg:gn_pop":0,
    "qs_pg:name":"John o'Groats",
    "qs_pg:name_adm0":"United Kingdom",
    "qs_pg:name_adm1":"Scotland",
    "qs_pg:photos":2445,
    "qs_pg:photos_1k":495,
    "qs_pg:photos_9k":11,
    "qs_pg:photos_9r":10,
    "qs_pg:photos_all":2445,
    "qs_pg:photos_sr":17,
    "qs_pg:pop_sr":0,
    "qs_pg:qs_pg_placetype":"locality",
    "qs_pg:qs_pg_placetype_gp":"Town",
    "qs_pg:woe_adm0":23424975,
    "woe:adm0_id":23424975,
    "woe:name_adm0":"United Kingdom",
    "woe:name_adm1":"Scotland",
    "woe:placetype":"Town",
    "wof:name":"John o'Groats",
    "wof:placetype":"locality"
},
  "geometry": {"coordinates":[-3.0627,58.63685],"type":"Point"}
}