{
  "type": "Feature",
  "properties": {
    "gn:country": "GB",
    "gn:fcode": "PPL",
    "gn:population": 0,
    "iso:country": "GB",
    "name:cat_x_preferred": [
      "John o' Groats"
    ],
    "name:ceb_x_preferred": [
      "John o' Groats"
    ],
    "name:dan_x_preferred": [
      "John O'Groats"
    ],
    "name:deu_x_preferred": [
      "John o’ Groats"
    ],
    "name:eng_x_preferred": [
      "John o' Groats"
    ],
    "name:epo_x_preferred": [
      "John o' Groats"
    ],
    "name:eus_x_preferred": [
      "John o' Groats"
    ],
    "name:fra_x_preferred": [
      "John o' Groats"
    ],
    "name:gla_x_preferred": [
      "Taigh Iain Ghròt"
    ],
    "name:gle_x_preferred": [
      "Taigh Iain Ghrót"
    ],
    "name:isl_x_preferred": [
      "John o’ Groats"
    ],
    "name:ita_x_preferred": [
      "John o' Groats"
    ],
    "name:jpn_x_preferred": [
      "ジョン・オ・グローツ"
    ],
    "name:kor_x_preferred": [
      "존오그로츠"
    ],
    "name:nld_x_preferred": [
      "John o' Groats"
    ],
    "name:nno_x_preferred": [
      "John o' Groats"
    ],
    "name:nob_x_preferred": [
      "John o' Groats"
    ],
    "name:pol_x_preferred": [
      "John o'Groats"
    ],
    "name:por_x_preferred": [
      "John o' Groats"
    ],
    "name:sco_x_preferred": [
      "John o Groats"
    ],
    "name:spa_x_preferred": [
      "John o' Groats"
    ],
    "name:swe_x_preferred": [
      "John o' Groats"
    ],
    "name:zho_x_preferred": [
      "約翰奧格羅茨"
    ],
    "qs_pg:aaroncc": "GB",
    "qs_pg:gn_country": "GB",
    "qs_pg:gn_fcode": "PPL",
    "qs_pg:gn_pop": 0,
    "qs_pg:name": "John o'Groats",
    "qs_pg:name_adm0": "United Kingdom",
    "qs_pg:name_adm1": "Scotland",
    "qs_pg:photos": 2445,
    "qs_pg:photos_1k": 495,
    "qs_pg:photos_9k": 11,
    "qs_pg:photos_9r": 10,
    "qs_pg:photos_all": 2445,
    "qs_pg:photos_sr": 17,
    "qs_pg:pop_sr": 0,
    "qs_pg:qs_pg_placetype": "locality",
    "qs_pg:qs_pg_placetype_gp": "Town",
    "qs_pg:woe_adm0": 23424975,
    "woe:adm0_id": 23424975,
    "woe:name_adm0": "United Kingdom",
    "woe:name_adm1": "Scotland",
    "woe:placetype": "Town",
    "wof:name": "John o'Groats",
    "wof:placetype": "locality"
  },
  "geometry": {"coordinates":[-3.0627,58.63685],"type":"Point"}
}
