{
  "type": "Feature",
  "properties": {
    "iso:country":"GB",
    "name:deu_x_preferred":[
        "Highfield"
    ],
    "name:pol_x_preferred":[
        "Highfield"
    ],
    "wof:name":"Highfield",
    "wof:placetype":"neighbourhood"
},
  "geometry": {"coordinates":[-5.97668221772949,54.60236844761606],"type":"Point"}
}