{
  "type": "Feature",
  "properties": {
    "iso:country":"GB",
    "name:dut_x_preferred":[
        "Simonstone"
    ],
    "name:eng_x_preferred":[
        "Simonstone"
    ],
    "name:pol_x_preferred":[
        "Simonstone "
    ],
    "qs_pg:aaroncc":"GB",
    "qs_pg:name":"Simonstone",
    "qs_pg:name_adm0":"United Kingdom",
    "qs_pg:name_adm1":"England",
    "qs_pg:photos":120,
    "qs_pg:photos_1k":24,
    "qs_pg:photos_9k":1,
    "qs_pg:photos_9r":3,
    "qs_pg:photos_all":120,
    "qs_pg:photos_sr":3,
    "qs_pg:pop_sr":0,
    "qs_pg:qs_pg_placetype":"locality",
    "qs_pg:qs_pg_placetype_gp":"Town",
    "qs_pg:woe_adm0":23424975,
    "woe:adm0_id":23424975,
    "woe:name_adm0":"United Kingdom",
    "woe:name_adm1":"England",
    "woe:placetype":"Town",
    "wof:name":"Simonstone",
    "wof:placetype":"neighbourhood"
},
  "geometry": {"coordinates":[-2.19881,54.354655],"type":"Point"}
}