{
  "type": "Feature",
  "properties": {
    "gn:country": "GB",
    "gn:fcode": "PPL",
    "gn:population": 0,
    "iso:country": "GB",
    "name:ceb_x_preferred": [
      "Hatch"
    ],
    "name:deu_x_preferred": [
      "Hatch"
    ],
    "name:fra_x_preferred": [
      "Hatch"
    ],
    "name:ita_x_preferred": [
      "Hatch"
    ],
    "name:jpn_x_preferred": [
      "ハッチ"
    ],
    "name:nld_x_preferred": [
      "Hatch"
    ],
    "name:pol_x_preferred": [
      "Hatch"
    ],
    "name:por_x_preferred": [
      "Hatch"
    ],
    "name:rus_x_preferred": [
      "Хэтч"
    ],
    "name:srp_x_preferred": [
      "Хач"
    ],
    "name:swe_x_preferred": [
      "Hatch"
    ],
    "name:ukr_x_preferred": [
      "Гатч"
    ],
    "name:vol_x_preferred": [
      "Hatch"
    ],
    "qs_pg:aaroncc": "GB",
    "qs_pg:gn_country": "GB",
    "qs_pg:gn_fcode": "PPL",
    "qs_pg:gn_pop": 0,
    "qs_pg:name": "Hatch",
    "qs_pg:name_adm0": "United Kingdom",
    "qs_pg:name_adm1": "England",
    "qs_pg:photos": 101,
    "qs_pg:photos_1k": 20,
    "qs_pg:photos_9k": 1,
    "qs_pg:photos_9r": 3,
    "qs_pg:photos_all": 101,
    "qs_pg:photos_sr": 3,
    "qs_pg:pop_sr": 0,
    "qs_pg:qs_pg_placetype": "locality",
    "qs_pg:qs_pg_placetype_gp": "Town",
    "qs_pg:woe_adm0": 23424975,
    "woe:adm0_id": 23424975,
    "woe:name_adm0": "United Kingdom",
    "woe:name_adm1": "England",
    "woe:placetype": "Town",
    "wof:name": "Hatch",
    "wof:placetype": "neighbourhood"
  },
  "geometry": {"coordinates":[-2.1075,51.05389],"type":"Point"}
}
