{
  "type": "Feature",
  "properties": {
    "gn:admin1_code": "ENG",
    "gn:admin2_code": "A7",
    "gn:asciiname": "Handsworth",
    "gn:country_code": "GB",
    "gn:dem": 123,
    "gn:feature_class": "P",
    "gn:feature_code": "PPL",
    "gn:name": "Handsworth",
    "gn:population": 0,
    "gn:timezone": "Europe/London",
    "iso:country": "GB",
    "name:gle_x_preferred": [
      "Handsworth"
    ],
    "name:pol_x_preferred": [
      "Handsworth"
    ],
    "wof:name": "Handsworth",
    "wof:placetype": "neighbourhood"
  },
  "geometry": {"coordinates":[-1.92673,52.51006],"type":"Point"}
}
