{
  "type": "Feature",
  "properties": {
    "iso:country":"GB",
    "name:ceb_x_preferred":[
        "Clipstone"
    ],
    "name:eng_x_preferred":[
        "Clipstone"
    ],
    "name:nld_x_preferred":[
        "Clipstone"
    ],
    "name:pol_x_preferred":[
        "Clipstone"
    ],
    "name:swe_x_preferred":[
        "Clipstone"
    ],
    "qs:gn_adm0_cc":"GB",
    "qs:gn_local":7290618,
    "qs:gn_nam_loc":"Newark and Sherwood District, Nottinghamshire, England, GB",
    "qs:gn_namadm1":"ENG",
    "qs:local_max":459,
    "qs:local_sum":459,
    "qs:localhoods":1,
    "qs:name":"Clipstone",
    "qs:name_adm0":"United Kingdom",
    "qs:name_adm1":"England",
    "qs:name_adm2":"Nottinghamshire",
    "qs:name_lau":"Newark and Sherwood District",
    "qs:name_local":"Newark and Sherwood District",
    "qs:photo_max":89,
    "qs:photo_sum":459,
    "qs:placetype":"Suburb",
    "qs:quad_count":62,
    "qs:woe_adm0":23424975,
    "qs:woe_adm1":24554868,
    "qs:woe_adm2":12602147,
    "qs:woe_lau":12696055,
    "qs:woe_local":12696055,
    "qs:woe_ver":"7.10.0",
    "wd:wordcount":1406,
    "wof:lang":[
        "eng"
    ],
    "wof:name":"Clipstone",
    "wof:placetype":"neighbourhood"
},
  "geometry": {"coordinates":[-1.108225,53.163078],"type":"Point"}
}