{
  "type": "Feature",
  "properties": {
    "iso:country": "GB",
    "name:azb_x_preferred": [
      "سنت جاست-این-پنویث"
    ],
    "name:ben_x_preferred": [
      "সেন্ট জাস্ট"
    ],
    "name:bre_x_preferred": [
      "Lannyust"
    ],
    "name:ceb_x_preferred": [
      "St. Just"
    ],
    "name:cor_x_preferred": [
      "Lannyust"
    ],
    "name:cym_x_preferred": [
      "St Just in Penwith"
    ],
    "name:deu_x_preferred": [
      "St Just in Penwith"
    ],
    "name:eng_x_preferred": [
      "St Just"
    ],
    "name:eus_x_preferred": [
      "St Just in Penwith"
    ],
    "name:fas_x_preferred": [
      "سنت جاست-این-پنویث"
    ],
    "name:fra_x_preferred": [
      "St Just in Penwith"
    ],
    "name:gle_x_preferred": [
      "St Just in Penwith"
    ],
    "name:guj_x_preferred": [
      "સેંટ જસ્ટ ઇન પેનવિથ"
    ],
    "name:ita_x_preferred": [
      "St Just-in-Penwith"
    ],
    "name:jpn_x_preferred": [
      "セント・ジャスト・イン・ペンウィス"
    ],
    "name:kan_x_preferred": [
      "ಸೇಂಟ್ ಜಸ್ಟ್ ಇನ್ ಪೆನ್ವಿತ್"
    ],
    "name:kor_x_preferred": [
      "세인트 저스트"
    ],
    "name:lat_x_preferred": [
      "St Just"
    ],
    "name:lit_x_preferred": [
      "Sent Džastas"
    ],
    "name:nld_x_preferred": [
      "St Just"
    ],
    "name:nob_x_preferred": [
      "St. Just"
    ],
    "name:pol_x_preferred": [
      "St Just in Penwith"
    ],
    "name:por_x_preferred": [
      "St Just in Penwith"
    ],
    "name:ron_x_preferred": [
      "St Just"
    ],
    "name:rus_x_preferred": [
      "Сент-Джаст-ин-Первиф"
    ],
    "name:spa_x_preferred": [
      "St Just in Penwith"
    ],
    "name:swe_x_preferred": [
      "St Just"
    ],
    "name:tam_x_preferred": [
      "ஸ்ட ஜஸ்ட் இன் பேணவித்"
    ],
    "name:tel_x_preferred": [
      "సెయింట్ జస్ట్ ఇన్ పెన్విత్"
    ],
    "name:urd_x_preferred": [
      "سینٹ جسینٹ ان پینویتھ"
    ],
    "name:zho_x_preferred": [
      "聖賈斯特"
    ],
    "qs:a0": "United Kingdom",
    "qs:a1": "*Cornwall",
    "qs:a1_lc": "GB12HE0000",
    "qs:a1r": "0England",
    "qs:a1r_lc": "GB12000000",
    "qs:adm0": "United Kingdom",
    "qs:la_lc": "*",
    "qs:level": "locality",
    "qs:loc": "St Just",
    "qs:loc_alt": "St Just",
    "qs:pop": 0,
    "qs:type": "buffered point",
    "wof:name": "St Just",
    "wof:placetype": "neighbourhood"
  },
  "geometry": {"coordinates":[-5.678243,50.124544],"type":"Point"}
}
