{
  "type": "Feature",
  "properties": {
    "iso:country":"GB",
    "name:dut_x_preferred":[
        "Aithsetter"
    ],
    "name:eng_x_preferred":[
        "Aithsetter"
    ],
    "name:fao_x_preferred":[
        "Aithsetter"
    ],
    "name:fre_x_preferred":[
        "Aithsetter"
    ],
    "qs_pg:aaroncc":"GB",
    "qs_pg:name":"Aithsetter",
    "qs_pg:name_adm0":"United Kingdom",
    "qs_pg:name_adm1":"Scotland",
    "qs_pg:photos":8,
    "qs_pg:photos_1k":2,
    "qs_pg:photos_9k":1,
    "qs_pg:photos_9r":1,
    "qs_pg:photos_all":8,
    "qs_pg:photos_sr":1,
    "qs_pg:pop_sr":0,
    "qs_pg:qs_pg_placetype":"locality",
    "qs_pg:qs_pg_placetype_gp":"Town",
    "qs_pg:woe_adm0":23424975,
    "woe:adm0_id":23424975,
    "woe:name_adm0":"United Kingdom",
    "woe:name_adm1":"Scotland",
    "woe:placetype":"Town",
    "wof:name":"Aithsetter",
    "wof:placetype":"locality"
},
  "geometry": {"coordinates":[-1.2062025,60.05028750000001],"type":"Point"}
}