{
  "type": "Feature",
  "properties": {
    "gn:country":"GB",
    "gn:fcode":"PPL",
    "gn:population":0,
    "iso:country":"GB",
    "name:cat_x_preferred":[
        "Southerndown"
    ],
    "name:cym_x_preferred":[
        "Southerndown"
    ],
    "name:eng_x_preferred":[
        "Southerndown"
    ],
    "name:eus_x_preferred":[
        "Southerndown"
    ],
    "name:fra_x_preferred":[
        "Southerndown"
    ],
    "name:jpn_x_preferred":[
        "\u30b5\u30a6\u30b6\u30fc\u30f3\u30c0\u30a6\u30f3"
    ],
    "name:nld_x_preferred":[
        "Southerndown"
    ],
    "name:zho_x_preferred":[
        "\u7d39\u68ee\u7576"
    ],
    "qs_pg:aaroncc":"GB",
    "qs_pg:gn_country":"GB",
    "qs_pg:gn_fcode":"PPL",
    "qs_pg:gn_pop":0,
    "qs_pg:name":"Southerndown",
    "qs_pg:name_adm0":"United Kingdom",
    "qs_pg:name_adm1":"Wales",
    "qs_pg:photos":3018,
    "qs_pg:photos_1k":612,
    "qs_pg:photos_9k":13,
    "qs_pg:photos_9r":11,
    "qs_pg:photos_all":3018,
    "qs_pg:photos_sr":19,
    "qs_pg:pop_sr":0,
    "qs_pg:qs_pg_placetype":"locality",
    "qs_pg:qs_pg_placetype_gp":"Town",
    "qs_pg:woe_adm0":23424975,
    "woe:adm0_id":23424975,
    "woe:name_adm0":"United Kingdom",
    "woe:name_adm1":"Wales",
    "woe:placetype":"Town",
    "wof:name":"Southerndown",
    "wof:placetype":"neighbourhood"
},
  "geometry": {"coordinates":[-3.61167,51.45278],"type":"Point"}
}