{
  "type": "Feature",
  "properties": {
    "iso:country": "GB",
    "name:deu_x_preferred": [
      "Lady Wood"
    ],
    "name:heb_x_preferred": [
      "Lady Wood"
    ],
    "name:ita_x_preferred": [
      "Lady Wood"
    ],
    "name:kor_x_preferred": [
      "Lady Wood"
    ],
    "name:por_x_preferred": [
      "Lady Wood"
    ],
    "name:ron_x_preferred": [
      "Lady Wood"
    ],
    "name:spa_x_preferred": [
      "Lady Wood"
    ],
    "name:swe_x_preferred": [
      "Lady Wood"
    ],
    "wof:name": "Lady Wood",
    "wof:placetype": "neighbourhood"
  },
  "geometry": {"coordinates":[-1.49900346517213,53.82878118530213],"type":"Point"}
}
