{
  "type": "Feature",
  "properties": {
    "iso:country":"GB",
    "wof:name":"Low Springs",
    "wof:placetype":"neighbourhood"
},
  "geometry": {"coordinates":[-1.77336916312009,53.86757442509892],"type":"Point"}
}