{
  "type": "Feature",
  "properties": {
    "iso:country":"GB",
    "name:azb_x_preferred":[
        "\u062a\u06cc\u067e\u062a\u0648\u0646"
    ],
    "name:ceb_x_preferred":[
        "Tipton"
    ],
    "name:cym_x_preferred":[
        "Tipton"
    ],
    "name:deu_x_preferred":[
        "Tipton"
    ],
    "name:fas_x_preferred":[
        "\u062a\u06cc\u067e\u062a\u0648\u0646"
    ],
    "name:fra_x_preferred":[
        "Tipton"
    ],
    "name:gle_x_preferred":[
        "Tipton"
    ],
    "name:ita_x_preferred":[
        "Tipton"
    ],
    "name:nld_x_preferred":[
        "Tipton"
    ],
    "name:nno_x_preferred":[
        "Tipton"
    ],
    "name:pol_x_preferred":[
        "Tipton"
    ],
    "name:ron_x_preferred":[
        "Tipton"
    ],
    "name:spa_x_preferred":[
        "Tipton"
    ],
    "name:swe_x_preferred":[
        "Tipton"
    ],
    "name:zho_x_preferred":[
        "\u63d0\u666e\u9813"
    ],
    "wof:name":"Tipton",
    "wof:placetype":"neighbourhood"
},
  "geometry": {"coordinates":[-2.06960754980404,52.5287490062775],"type":"Point"}
}