{
  "type": "Feature",
  "properties": {
    "gn:admin1_code":"SCT",
    "gn:admin2_code":"V2",
    "gn:asciiname":"Summerston",
    "gn:country_code":"GB",
    "gn:dem":41,
    "gn:feature_class":"P",
    "gn:feature_code":"PPL",
    "gn:name":"Summerston",
    "gn:population":0,
    "gn:timezone":"Europe/London",
    "iso:country":"GB",
    "wof:name":"Summerston",
    "wof:placetype":"neighbourhood"
},
  "geometry": {"coordinates":[-4.29172,55.89995],"type":"Point"}
}