{
  "type": "Feature",
  "properties": {
    "gn:gn_country":"GB",
    "gn:gn_fcode":"PPL",
    "gn:gn_pop":8635,
    "gn:population":8635,
    "iso:country":"GB",
    "name:azb_x_preferred":[
        "\u0646\u0627\u0641\u06cc\u0644"
    ],
    "name:bul_x_preferred":[
        "\u041a\u043d\u0430\u043f\u0445\u0438\u043b"
    ],
    "name:ceb_x_preferred":[
        "Knaphill"
    ],
    "name:eng_x_preferred":[
        "Knaphill"
    ],
    "name:fas_x_preferred":[
        "\u0646\u0627\u0641\u06cc\u0644"
    ],
    "name:fra_x_preferred":[
        "Knaphill"
    ],
    "name:nld_x_preferred":[
        "Knaphill"
    ],
    "name:pol_x_preferred":[
        "Knaphill"
    ],
    "name:swe_x_preferred":[
        "Knaphill"
    ],
    "name:urd_x_preferred":[
        "\u0646\u06cc\u067e\u06c1\u0644"
    ],
    "qs_pg:aaroncc":"GB",
    "qs_pg:gn_country":"GB",
    "qs_pg:gn_fcode":"PPL",
    "qs_pg:gn_pop":8635,
    "qs_pg:name":"Knaphill",
    "qs_pg:name_adm0":"United Kingdom",
    "qs_pg:name_adm1":"England",
    "qs_pg:photos":611,
    "qs_pg:photos_1k":124,
    "qs_pg:photos_9k":3,
    "qs_pg:photos_9r":5,
    "qs_pg:photos_all":611,
    "qs_pg:photos_sr":8,
    "qs_pg:pop_sr":5,
    "qs_pg:qs_pg_placetype":"locality",
    "qs_pg:qs_pg_placetype_gp":"Town",
    "qs_pg:woe_adm0":23424975,
    "woe:adm0_id":23424975,
    "woe:name_adm0":"United Kingdom",
    "woe:name_adm1":"England",
    "woe:placetype":"Town",
    "wof:name":"Knaphill",
    "wof:placetype":"neighbourhood",
    "wof:population":8635
},
  "geometry": {"coordinates":[-0.61541,51.31892],"type":"Point"}
}