{
  "type": "Feature",
  "properties": {
    "iso:country":"GB",
    "name:bul_x_preferred":[
        "\u0422\u0430\u043d\u0434\u0440\u0430\u0434\u0436\u0438"
    ],
    "name:ceb_x_preferred":[
        "Tandragee"
    ],
    "name:eng_x_preferred":[
        "Tandragee"
    ],
    "name:eus_x_preferred":[
        "Tandragee"
    ],
    "name:fas_x_preferred":[
        "\u062a\u0646\u062f\u0631\u0627\u06af\u06cc"
    ],
    "name:fra_x_preferred":[
        "Tandragee"
    ],
    "name:gla_x_preferred":[
        "T\u00f3in re Gaoith"
    ],
    "name:gle_x_preferred":[
        "T\u00f3in re Gaoith"
    ],
    "name:ita_x_preferred":[
        "Tandragee"
    ],
    "name:jpn_x_preferred":[
        "\u30bf\u30f3\u30c9\u30e9\u30ae\u30fc"
    ],
    "name:msa_x_preferred":[
        "Tandragee"
    ],
    "name:nld_x_preferred":[
        "Tandragee"
    ],
    "name:pli_x_preferred":[
        "\u0924\u0928\u094d\u0926\u094d\u0930\u0917\u0940"
    ],
    "name:spa_x_preferred":[
        "Tandragee"
    ],
    "name:swe_x_preferred":[
        "Tandragee"
    ],
    "name:und_x_variant":[
        "Tanderagee"
    ],
    "qs:a0":"United Kingdom",
    "qs:a1":"*Armagh City and District",
    "qs:a1_lc":"N_A",
    "qs:a1r":"0Northern Ireland",
    "qs:a1r_lc":"N_A",
    "qs:adm0":"United Kingdom",
    "qs:la_lc":"*",
    "qs:level":"locality",
    "qs:loc":"Tandragee",
    "qs:loc_alt":"Tandragee",
    "qs:pop":0,
    "qs:type":"buffered point",
    "wd:wordcount":528,
    "wof:name":"Tandragee",
    "wof:placetype":"locality"
},
  "geometry": {"coordinates":[-6.41064,54.351013],"type":"Point"}
}