{
  "type": "Feature",
  "properties": {
    "iso:country":"GB",
    "name:bre_x_preferred":[
        "Y Bont-faen"
    ],
    "name:bul_x_preferred":[
        "\u041a\u043e\u0443\u0431\u0440\u0438\u0434\u0436"
    ],
    "name:cat_x_preferred":[
        "Cowbridge"
    ],
    "name:ceb_x_preferred":[
        "Cowbridge"
    ],
    "name:cym_x_preferred":[
        "Y Bont-faen"
    ],
    "name:deu_x_preferred":[
        "Cowbridge"
    ],
    "name:eng_x_preferred":[
        "Cowbridge"
    ],
    "name:eng_x_variant":[
        "Pontfaen",
        "Y Bont-faen"
    ],
    "name:eus_x_preferred":[
        "Lower Machen"
    ],
    "name:eus_x_variant":[
        "Cowbridge"
    ],
    "name:fas_x_preferred":[
        "\u06a9\u0627\u0648\u0628\u0631\u06cc\u062c"
    ],
    "name:fra_x_preferred":[
        "Cowbridge"
    ],
    "name:gle_x_preferred":[
        "Y Bont-faen"
    ],
    "name:glg_x_preferred":[
        "Y Bont-faen"
    ],
    "name:ita_x_preferred":[
        "Cowbridge"
    ],
    "name:jpn_x_preferred":[
        "\u30b3\u30a6\u30d6\u30ea\u30c3\u30b8"
    ],
    "name:lat_x_preferred":[
        "Pons Vianus"
    ],
    "name:nld_x_preferred":[
        "Cowbridge"
    ],
    "name:sco_x_preferred":[
        "Y Bont-faen"
    ],
    "name:spa_x_preferred":[
        "Cowbridge"
    ],
    "name:swe_x_preferred":[
        "Cowbridge"
    ],
    "name:ukr_x_preferred":[
        "\u041a\u0430\u0432\u0431\u0440\u0456\u0434\u0436"
    ],
    "name:zho_x_preferred":[
        "\u6bcd\u725b\u6a4b"
    ],
    "qs:a0":"United Kingdom",
    "qs:a1":"*Bro Morgannwg#the Vale of Glamorgan",
    "qs:a1_lc":"GB13PD0000",
    "qs:a1r":"0Wales",
    "qs:a1r_lc":"GB13000000",
    "qs:adm0":"United Kingdom",
    "qs:la_lc":"*",
    "qs:level":"locality",
    "qs:loc":"Cowbridge",
    "qs:loc_alt":"Cowbridge",
    "qs:pop":0,
    "qs:type":"buffered point",
    "wd:wordcount":1853,
    "wof:lang":[
        "eng"
    ],
    "wof:name":"Cowbridge",
    "wof:placetype":"neighbourhood"
},
  "geometry": {"coordinates":[-3.441427,51.458937],"type":"Point"}
}