{
  "type": "Feature",
  "properties": {
    "iso:country": "GB",
    "name:bre_x_preferred": [
      "Y Bont-faen"
    ],
    "name:bul_x_preferred": [
      "Коубридж"
    ],
    "name:cat_x_preferred": [
      "Cowbridge"
    ],
    "name:ceb_x_preferred": [
      "Cowbridge"
    ],
    "name:cym_x_preferred": [
      "Y Bont-faen"
    ],
    "name:deu_x_preferred": [
      "Cowbridge"
    ],
    "name:eng_x_preferred": [
      "Cowbridge"
    ],
    "name:eng_x_variant": [
      "Pontfaen",
      "Y Bont-faen"
    ],
    "name:eus_x_preferred": [
      "Lower Machen"
    ],
    "name:eus_x_variant": [
      "Cowbridge"
    ],
    "name:fas_x_preferred": [
      "کاوبریج"
    ],
    "name:fra_x_preferred": [
      "Cowbridge"
    ],
    "name:gle_x_preferred": [
      "Y Bont-faen"
    ],
    "name:glg_x_preferred": [
      "Y Bont-faen"
    ],
    "name:ita_x_preferred": [
      "Cowbridge"
    ],
    "name:jpn_x_preferred": [
      "コウブリッジ"
    ],
    "name:nld_x_preferred": [
      "Cowbridge"
    ],
    "name:sco_x_preferred": [
      "Y Bont-faen"
    ],
    "name:spa_x_preferred": [
      "Cowbridge"
    ],
    "name:swe_x_preferred": [
      "Cowbridge"
    ],
    "name:zho_x_preferred": [
      "母牛橋"
    ],
    "qs:a0": "United Kingdom",
    "qs:a1": "*Bro Morgannwg#the Vale of Glamorgan",
    "qs:a1_lc": "GB13PD0000",
    "qs:a1r": "0Wales",
    "qs:a1r_lc": "GB13000000",
    "qs:adm0": "United Kingdom",
    "qs:la_lc": "*",
    "qs:level": "locality",
    "qs:loc": "Cowbridge",
    "qs:loc_alt": "Cowbridge",
    "qs:pop": 0,
    "qs:type": "buffered point",
    "wd:wordcount": 1853,
    "wof:lang": [
      "eng"
    ],
    "wof:name": "Cowbridge",
    "wof:placetype": "neighbourhood"
  },
  "geometry": {"coordinates":[-3.441427,51.458937],"type":"Point"}
}
