{
  "type": "Feature",
  "properties": {
    "gn:admin1_code":"ENG",
    "gn:admin2_code":"C3",
    "gn:admin3_code":"12UG",
    "gn:admin4_code":"12UG083",
    "gn:asciiname":"Wendy",
    "gn:country_code":"GB",
    "gn:dem":24,
    "gn:feature_class":"P",
    "gn:feature_code":"PPL",
    "gn:name":"Wendy",
    "gn:population":0,
    "gn:timezone":"Europe/London",
    "iso:country":"GB",
    "name:cym_x_preferred":[
        "Wendy"
    ],
    "name:pol_x_preferred":[
        "Wendy"
    ],
    "wof:name":"Wendy",
    "wof:placetype":"neighbourhood"
},
  "geometry": {"coordinates":[-0.06918,52.11154000000001],"type":"Point"}
}