{
  "type": "Feature",
  "properties": {
    "gn:admin1_code":"ENG",
    "gn:admin2_code":"E4",
    "gn:admin3_code":"22UH",
    "gn:admin4_code":"22UH025",
    "gn:asciiname":"The Village Willingale",
    "gn:country_code":"GB",
    "gn:dem":72,
    "gn:feature_class":"P",
    "gn:feature_code":"PPL",
    "gn:name":"The Village Willingale",
    "gn:population":0,
    "gn:timezone":"Europe/London",
    "iso:country":"GB",
    "wof:name":"The Village Willingale",
    "wof:placetype":"neighbourhood"
},
  "geometry": {"coordinates":[0.30942,51.74324],"type":"Point"}
}