{
  "type": "Feature",
  "properties": {
    "gn:population": 9120,
    "iso:country": "GB",
    "name:ceb_x_preferred": [
      "Marske-by-the-Sea"
    ],
    "name:deu_x_preferred": [
      "Marske-by-the-Sea"
    ],
    "name:eng_x_preferred": [
      "Marske-by-the-Sea"
    ],
    "name:eng_x_variant": [
      "Marske",
      "Marske by the Sea"
    ],
    "name:epo_x_preferred": [
      "Marske-by-the-Sea"
    ],
    "name:fra_x_preferred": [
      "Marske-by-the-Sea"
    ],
    "name:ita_x_preferred": [
      "Marske-by-the-Sea"
    ],
    "name:nld_x_preferred": [
      "Marske-by-the-Sea"
    ],
    "name:pol_x_preferred": [
      "Marske-by-the-Sea"
    ],
    "name:swe_x_preferred": [
      "Marske-by-the-Sea"
    ],
    "qs:a0": "United Kingdom",
    "qs:a1": "*Redcar and Cleveland",
    "qs:a1_lc": "GB12EE0000",
    "qs:a1r": "0England",
    "qs:a1r_lc": "GB12000000",
    "qs:adm0": "United Kingdom",
    "qs:la_lc": "*",
    "qs:level": "locality",
    "qs:loc": "Marske-by-the-Sea",
    "qs:loc_alt": "Marske-by-the-Sea",
    "qs:pop": 0,
    "qs:type": "buffered point",
    "wd:wordcount": 1621,
    "wof:lang": [
      "eng"
    ],
    "wof:name": "Marske-by-the-Sea",
    "wof:placetype": "neighbourhood",
    "wof:population": 9120
  },
  "geometry": {"coordinates":[-1.017376,54.593442],"type":"Point"}
}
