{
  "type": "Feature",
  "properties": {
    "gn:admin1_code":"ENG",
    "gn:admin2_code":"J6",
    "gn:admin3_code":"00EM041",
    "gn:asciiname":"East Woodburn",
    "gn:country_code":"GB",
    "gn:dem":137,
    "gn:feature_class":"P",
    "gn:feature_code":"PPL",
    "gn:name":"East Woodburn",
    "gn:population":0,
    "gn:timezone":"Europe/London",
    "iso:country":"GB",
    "name:cym_x_preferred":[
        "East Woodburn"
    ],
    "wof:name":"East Woodburn",
    "wof:placetype":"neighbourhood"
},
  "geometry": {"coordinates":[-2.14677,55.1755],"type":"Point"}
}