{
  "type": "Feature",
  "properties": {
    "iso:country": "GB",
    "name:ben_x_preferred": [
      "হ্যাউইক"
    ],
    "name:ceb_x_preferred": [
      "Hawick"
    ],
    "name:cym_x_preferred": [
      "Hawick"
    ],
    "name:deu_x_preferred": [
      "Hawick"
    ],
    "name:ell_x_preferred": [
      "Χόικ"
    ],
    "name:eng_x_preferred": [
      "Hawick"
    ],
    "name:eus_x_preferred": [
      "Hawick"
    ],
    "name:fas_x_preferred": [
      "هاویک"
    ],
    "name:fra_x_preferred": [
      "Hawick"
    ],
    "name:gla_x_preferred": [
      "Hamhaig"
    ],
    "name:gle_x_preferred": [
      "Hamhaig"
    ],
    "name:guj_x_preferred": [
      "હોવિક"
    ],
    "name:ita_x_preferred": [
      "Hawick"
    ],
    "name:jpn_x_preferred": [
      "ホイック"
    ],
    "name:kan_x_preferred": [
      "ಹಾವಿಕ್"
    ],
    "name:kor_x_preferred": [
      "하익"
    ],
    "name:lat_x_preferred": [
      "Hawick"
    ],
    "name:lit_x_preferred": [
      "Hovikas"
    ],
    "name:nld_x_preferred": [
      "Hawick"
    ],
    "name:nno_x_preferred": [
      "Hawick"
    ],
    "name:nob_x_preferred": [
      "Hawick"
    ],
    "name:nor_x_preferred": [
      "Hawick"
    ],
    "name:pol_x_preferred": [
      "Hawick"
    ],
    "name:por_x_preferred": [
      "Hawick"
    ],
    "name:rus_x_preferred": [
      "Хоик"
    ],
    "name:sco_x_preferred": [
      "Haaick"
    ],
    "name:spa_x_preferred": [
      "Hawick"
    ],
    "name:swe_x_preferred": [
      "Hawick"
    ],
    "name:tam_x_preferred": [
      "ஹாவிக்"
    ],
    "name:tel_x_preferred": [
      "హవిక్"
    ],
    "name:ukr_x_preferred": [
      "Хоїк"
    ],
    "name:urd_x_preferred": [
      "ہاویک"
    ],
    "name:zho_x_preferred": [
      "霍伊克"
    ],
    "qs:a0": "United Kingdom",
    "qs:a1": "*Scottish Borders",
    "qs:a1_lc": "GB11QE0000",
    "qs:a1r": "0Scotland",
    "qs:a1r_lc": "GB11000000",
    "qs:adm0": "United Kingdom",
    "qs:la_lc": "*",
    "qs:level": "locality",
    "qs:loc": "Hawick",
    "qs:loc_alt": "Hawick",
    "qs:pop": 0,
    "qs:type": "buffered point",
    "wd:wordcount": 1102,
    "wof:lang": [
      "eng"
    ],
    "wof:name": "Hawick",
    "wof:placetype": "locality"
  },
  "geometry": {"coordinates":[-2.782441,55.42941],"type":"Point"}
}
