{
  "type": "Feature",
  "properties": {
    "iso:country":"GB",
    "name:ben_x_preferred":[
        "\u09b9\u09cd\u09af\u09be\u0989\u0987\u0995"
    ],
    "name:ceb_x_preferred":[
        "Hawick"
    ],
    "name:cym_x_preferred":[
        "Hawick"
    ],
    "name:deu_x_preferred":[
        "Hawick"
    ],
    "name:ell_x_preferred":[
        "\u03a7\u03cc\u03b9\u03ba"
    ],
    "name:eng_x_preferred":[
        "Hawick"
    ],
    "name:eus_x_preferred":[
        "Hawick"
    ],
    "name:fra_x_preferred":[
        "Hawick"
    ],
    "name:gla_x_preferred":[
        "Hamhaig"
    ],
    "name:gle_x_preferred":[
        "Hamhaig"
    ],
    "name:guj_x_preferred":[
        "\u0ab9\u0acb\u0ab5\u0abf\u0a95"
    ],
    "name:ita_x_preferred":[
        "Hawick"
    ],
    "name:jpn_x_preferred":[
        "\u30db\u30a4\u30c3\u30af"
    ],
    "name:kan_x_preferred":[
        "\u0cb9\u0cbe\u0cb5\u0cbf\u0c95\u0ccd"
    ],
    "name:kor_x_preferred":[
        "\ud558\uc775"
    ],
    "name:lat_x_preferred":[
        "Hawick"
    ],
    "name:lit_x_preferred":[
        "Hovikas"
    ],
    "name:nld_x_preferred":[
        "Hawick"
    ],
    "name:nno_x_preferred":[
        "Hawick"
    ],
    "name:nob_x_preferred":[
        "Hawick"
    ],
    "name:nor_x_preferred":[
        "Hawick"
    ],
    "name:pol_x_preferred":[
        "Hawick"
    ],
    "name:por_x_preferred":[
        "Hawick"
    ],
    "name:rus_x_preferred":[
        "\u0425\u043e\u0438\u043a"
    ],
    "name:sco_x_preferred":[
        "Haaick"
    ],
    "name:spa_x_preferred":[
        "Hawick"
    ],
    "name:swe_x_preferred":[
        "Hawick"
    ],
    "name:tam_x_preferred":[
        "\u0bb9\u0bbe\u0bb5\u0bbf\u0b95\u0bcd"
    ],
    "name:tel_x_preferred":[
        "\u0c39\u0c35\u0c3f\u0c15\u0c4d"
    ],
    "name:ukr_x_preferred":[
        "\u0425\u043e\u0457\u043a"
    ],
    "name:urd_x_preferred":[
        "\u06c1\u0627\u0648\u06cc\u06a9"
    ],
    "name:zho_x_preferred":[
        "\u970d\u4f0a\u514b"
    ],
    "qs:a0":"United Kingdom",
    "qs:a1":"*Scottish Borders",
    "qs:a1_lc":"GB11QE0000",
    "qs:a1r":"0Scotland",
    "qs:a1r_lc":"GB11000000",
    "qs:adm0":"United Kingdom",
    "qs:la_lc":"*",
    "qs:level":"locality",
    "qs:loc":"Hawick",
    "qs:loc_alt":"Hawick",
    "qs:pop":0,
    "qs:type":"buffered point",
    "wd:wordcount":1102,
    "wof:lang":[
        "eng"
    ],
    "wof:name":"Hawick",
    "wof:placetype":"locality"
},
  "geometry": {"coordinates":[-2.782441,55.42941],"type":"Point"}
}