{
  "type": "Feature",
  "properties": {
    "gn:country":"GB",
    "gn:fcode":"PPL",
    "gn:population":0,
    "iso:country":"GB",
    "name:cat_x_preferred":[
        "Osborne"
    ],
    "name:ceb_x_preferred":[
        "Osborne"
    ],
    "name:ces_x_preferred":[
        "Osborne"
    ],
    "name:deu_x_preferred":[
        "Osborne"
    ],
    "name:fra_x_preferred":[
        "Osborne"
    ],
    "name:ita_x_preferred":[
        "Osborne"
    ],
    "name:jpn_x_preferred":[
        "\u30aa\u30ba\u30dc\u30fc\u30f3"
    ],
    "name:nld_x_preferred":[
        "Osborne"
    ],
    "name:nor_x_preferred":[
        "Osborne"
    ],
    "name:pol_x_preferred":[
        "Osborne"
    ],
    "name:spa_x_preferred":[
        "Osborne"
    ],
    "name:srp_x_preferred":[
        "\u041e\u0437\u0431\u043e\u0440\u043d"
    ],
    "name:swe_x_preferred":[
        "Osborne"
    ],
    "name:vol_x_preferred":[
        "Osborne"
    ],
    "qs_pg:aaroncc":"GB",
    "qs_pg:gn_country":"GB",
    "qs_pg:gn_fcode":"PPL",
    "qs_pg:gn_pop":0,
    "qs_pg:name":"Osborne",
    "qs_pg:name_adm0":"United Kingdom",
    "qs_pg:name_adm1":"England",
    "qs_pg:photos":953,
    "qs_pg:photos_1k":193,
    "qs_pg:photos_9k":4,
    "qs_pg:photos_9r":6,
    "qs_pg:photos_all":953,
    "qs_pg:photos_sr":10,
    "qs_pg:pop_sr":0,
    "qs_pg:qs_pg_placetype":"locality",
    "qs_pg:qs_pg_placetype_gp":"Town",
    "qs_pg:woe_adm0":23424975,
    "woe:adm0_id":23424975,
    "woe:name_adm0":"United Kingdom",
    "woe:name_adm1":"England",
    "woe:placetype":"Town",
    "wof:name":"Osborne",
    "wof:placetype":"neighbourhood"
},
  "geometry": {"coordinates":[-1.27501,50.75069],"type":"Point"}
}