{
  "type": "Feature",
  "properties": {
    "gn:country": "GB",
    "gn:fcode": "PPL",
    "gn:population": 0,
    "iso:country": "GB",
    "name:ceb_x_preferred": [
      "Osgathorpe"
    ],
    "name:cym_x_preferred": [
      "Osgathorpe"
    ],
    "name:pol_x_preferred": [
      "Osgathorpe"
    ],
    "name:swe_x_preferred": [
      "Osgathorpe"
    ],
    "qs_pg:aaroncc": "GB",
    "qs_pg:gn_country": "GB",
    "qs_pg:gn_fcode": "PPL",
    "qs_pg:gn_pop": 0,
    "qs_pg:name": "Osgathorpe",
    "qs_pg:name_adm0": "United Kingdom",
    "qs_pg:name_adm1": "England",
    "qs_pg:photos": 269,
    "qs_pg:photos_1k": 55,
    "qs_pg:photos_9k": 1,
    "qs_pg:photos_9r": 4,
    "qs_pg:photos_all": 269,
    "qs_pg:photos_sr": 5,
    "qs_pg:pop_sr": 0,
    "qs_pg:qs_pg_placetype": "locality",
    "qs_pg:qs_pg_placetype_gp": "Town",
    "qs_pg:woe_adm0": 23424975,
    "woe:adm0_id": 23424975,
    "woe:name_adm0": "United Kingdom",
    "woe:name_adm1": "England",
    "woe:placetype": "Town",
    "wof:name": "Osgathorpe",
    "wof:placetype": "neighbourhood"
  },
  "geometry": {"coordinates":[-0.87575,53.07687],"type":"Point"}
}
