{
  "type": "Feature",
  "properties": {
    "gn:country":"GB",
    "gn:fcode":"PPL",
    "gn:population":0,
    "iso:country":"GB",
    "name:cat_x_preferred":[
        "Lochcarron"
    ],
    "name:eng_x_preferred":[
        "Lochcarron"
    ],
    "name:eus_x_preferred":[
        "Lochcarron"
    ],
    "name:fra_x_preferred":[
        "Lochcarron"
    ],
    "name:gla_x_preferred":[
        "T\u00f2rr nan Cl\u00e0r"
    ],
    "name:gle_x_preferred":[
        "Loch Carrann"
    ],
    "name:ita_x_preferred":[
        "Lochcarron"
    ],
    "name:nld_x_preferred":[
        "Lochcarron"
    ],
    "name:swe_x_preferred":[
        "Lochcarron"
    ],
    "name:und_x_variant":[
        "Jean Town"
    ],
    "qs_pg:aaroncc":"GB",
    "qs_pg:gn_country":"GB",
    "qs_pg:gn_fcode":"PPL",
    "qs_pg:gn_pop":0,
    "qs_pg:name":"Lochcarron",
    "qs_pg:name_adm0":"United Kingdom",
    "qs_pg:name_adm1":"Scotland",
    "qs_pg:photos":263,
    "qs_pg:photos_1k":53,
    "qs_pg:photos_9k":1,
    "qs_pg:photos_9r":4,
    "qs_pg:photos_all":263,
    "qs_pg:photos_sr":5,
    "qs_pg:pop_sr":0,
    "qs_pg:qs_pg_placetype":"locality",
    "qs_pg:qs_pg_placetype_gp":"Town",
    "qs_pg:woe_adm0":23424975,
    "woe:adm0_id":23424975,
    "woe:name_adm0":"United Kingdom",
    "woe:name_adm1":"Scotland",
    "woe:placetype":"Town",
    "wof:name":"Lochcarron",
    "wof:placetype":"locality"
},
  "geometry": {"coordinates":[-5.49895,57.39833],"type":"Point"}
}