{
  "type": "Feature",
  "properties": {
    "iso:country":"GB",
    "name:deu_x_preferred":[
        "Matford"
    ],
    "name:fra_x_preferred":[
        "Matford"
    ],
    "name:ita_x_preferred":[
        "Matford"
    ],
    "name:pol_x_preferred":[
        "Matford"
    ],
    "qs_pg:aaroncc":"GB",
    "qs_pg:name":"Matford",
    "qs_pg:name_adm0":"United Kingdom",
    "qs_pg:name_adm1":"England",
    "qs_pg:photos":35,
    "qs_pg:photos_1k":7,
    "qs_pg:photos_9k":1,
    "qs_pg:photos_9r":2,
    "qs_pg:photos_all":35,
    "qs_pg:photos_sr":2,
    "qs_pg:pop_sr":0,
    "qs_pg:qs_pg_placetype":"locality",
    "qs_pg:qs_pg_placetype_gp":"Town",
    "qs_pg:woe_adm0":23424975,
    "woe:adm0_id":23424975,
    "woe:name_adm0":"United Kingdom",
    "woe:name_adm1":"England",
    "woe:placetype":"Town",
    "wof:name":"Matford",
    "wof:placetype":"neighbourhood"
},
  "geometry": {"coordinates":[-3.524351,50.681939],"type":"Point"}
}