{
  "type": "Feature",
  "properties": {
    "iso:country":"GB",
    "name:fra_x_preferred":[
        "Wood End"
    ],
    "name:pol_x_preferred":[
        "Wood End"
    ],
    "qs_pg:aaroncc":"GB",
    "qs_pg:name":"Wood End",
    "qs_pg:name_adm0":"United Kingdom",
    "qs_pg:name_adm1":"England",
    "qs_pg:photos":135,
    "qs_pg:photos_1k":27,
    "qs_pg:photos_9k":1,
    "qs_pg:photos_9r":3,
    "qs_pg:photos_all":135,
    "qs_pg:photos_sr":3,
    "qs_pg:pop_sr":0,
    "qs_pg:qs_pg_placetype":"locality",
    "qs_pg:qs_pg_placetype_gp":"Town",
    "qs_pg:woe_adm0":23424975,
    "woe:adm0_id":23424975,
    "woe:name_adm0":"United Kingdom",
    "woe:name_adm1":"England",
    "woe:placetype":"Town",
    "wof:name":"Wood End",
    "wof:placetype":"neighbourhood"
},
  "geometry": {"coordinates":[-1.641865,52.604142],"type":"Point"}
}