{
  "type": "Feature",
  "properties": {
    "iso:country": "GB",
    "name:afr_x_preferred": [
      "Paddington"
    ],
    "name:ara_x_preferred": [
      "بادنغتون"
    ],
    "name:ast_x_preferred": [
      "Paddington"
    ],
    "name:azb_x_preferred": [
      "پدینقتون"
    ],
    "name:aze_x_preferred": [
      "Paddinqton"
    ],
    "name:bel_x_preferred": [
      "Падзінгтан"
    ],
    "name:bul_x_preferred": [
      "Падингтън"
    ],
    "name:cym_x_preferred": [
      "Paddington"
    ],
    "name:deu_x_preferred": [
      "Paddington"
    ],
    "name:eng_x_preferred": [
      "Paddington"
    ],
    "name:fas_x_preferred": [
      "پدینگتون"
    ],
    "name:fra_x_preferred": [
      "Paddington"
    ],
    "name:gle_x_preferred": [
      "Paddington"
    ],
    "name:heb_x_preferred": [
      "פדינגטון"
    ],
    "name:hin_x_preferred": [
      "पैडिंगटन"
    ],
    "name:ind_x_preferred": [
      "Paddington"
    ],
    "name:ita_x_preferred": [
      "Paddington"
    ],
    "name:jpn_x_preferred": [
      "パディントン"
    ],
    "name:kor_x_preferred": [
      "패딩턴"
    ],
    "name:mlg_x_preferred": [
      "Paddington"
    ],
    "name:new_x_preferred": [
      "पैडिंगटन"
    ],
    "name:nld_x_preferred": [
      "Paddington"
    ],
    "name:nor_x_preferred": [
      "Paddington"
    ],
    "name:pol_x_preferred": [
      "Paddington"
    ],
    "name:por_x_preferred": [
      "Paddington"
    ],
    "name:rus_x_preferred": [
      "Паддингтон"
    ],
    "name:spa_x_preferred": [
      "Paddington"
    ],
    "name:swe_x_preferred": [
      "Paddington"
    ],
    "name:tur_x_preferred": [
      "Paddington"
    ],
    "name:ukr_x_preferred": [
      "Паддінгтон"
    ],
    "name:urd_x_preferred": [
      "پیڈنگٹن"
    ],
    "name:zho_x_preferred": [
      "帕丁頓"
    ],
    "qs:gn_adm0_cc": "GB",
    "qs:gn_fcode": "PPL",
    "qs:gn_local": 2649685,
    "qs:gn_nam_loc": "hammerwich",
    "qs:gn_namadm1": "ENG",
    "qs:gn_name": "Waddington",
    "qs:local_max": 3828,
    "qs:local_sum": 7266,
    "qs:localhoods": 4,
    "qs:name": "Paddington",
    "qs:name_adm0": "United Kingdom",
    "qs:name_adm1": "England",
    "qs:name_adm2": "Cheshire",
    "qs:name_lau": "Warrington Borough",
    "qs:name_local": "Warrington",
    "qs:photo_max": 78,
    "qs:photo_sum": 204,
    "qs:placetype": "Suburb",
    "qs:quad_count": 21,
    "qs:woe_adm0": 23424975,
    "qs:woe_adm1": 24554868,
    "qs:woe_adm2": 12602157,
    "qs:woe_lau": 12696172,
    "qs:woe_local": 39210,
    "qs:woe_ver": "7.10.0",
    "wd:wordcount": 2067,
    "wof:lang": [
      "eng"
    ],
    "wof:name": "Paddington",
    "wof:placetype": "neighbourhood"
  },
  "geometry": {"coordinates":[-2.530289,53.398464],"type":"Point"}
}
