{
  "type": "Feature",
  "properties": {
    "gn:admin1_code":"SCT",
    "gn:admin2_code":"V6",
    "gn:asciiname":"Aultmore",
    "gn:country_code":"GB",
    "gn:dem":166,
    "gn:feature_class":"P",
    "gn:feature_code":"PPL",
    "gn:name":"Aultmore",
    "gn:population":0,
    "gn:timezone":"Europe/London",
    "iso:country":"GB",
    "name:eus_x_preferred":[
        "Aultmore"
    ],
    "name:fra_x_preferred":[
        "Aultmore"
    ],
    "wof:name":"Aultmore",
    "wof:placetype":"locality"
},
  "geometry": {"coordinates":[-3.00114,57.56751],"type":"Point"}
}