{
  "type": "Feature",
  "properties": {
    "iso:country":"GB",
    "wof:name":"Shearbridge",
    "wof:placetype":"neighbourhood"
},
  "geometry": {"coordinates":[-1.77132353068213,53.78914769635031],"type":"Point"}
}