{
  "type": "Feature",
  "properties": {
    "iso:country":"GB",
    "name:ceb_x_preferred":[
        "Repps with Bastwick"
    ],
    "name:cym_x_preferred":[
        "Repps with Bastwick"
    ],
    "name:eng_x_preferred":[
        "Repps with Bastwick"
    ],
    "name:eng_x_variant":[
        "Repps With Bastwick"
    ],
    "name:fas_x_preferred":[
        "\u0631\u067e\u0633 \u0648\u06cc\u062a \u0628\u0633\u062a\u0648\u06cc\u06a9"
    ],
    "name:fra_x_preferred":[
        "Repps with Bastwick"
    ],
    "name:ita_x_preferred":[
        "Repps with Bastwick"
    ],
    "name:nld_x_preferred":[
        "Repps with Bastwick"
    ],
    "name:pol_x_preferred":[
        "Repps with Bastwick"
    ],
    "name:spa_x_preferred":[
        "Repps with Bastwick"
    ],
    "name:swe_x_preferred":[
        "Repps with Bastwick"
    ],
    "qs_pg:aaroncc":"GB",
    "qs_pg:name":"Repps With Bastwick",
    "qs_pg:name_adm0":"United Kingdom",
    "qs_pg:name_adm1":"England",
    "qs_pg:photos":64,
    "qs_pg:photos_1k":13,
    "qs_pg:photos_9k":1,
    "qs_pg:photos_9r":2,
    "qs_pg:photos_all":64,
    "qs_pg:photos_sr":2,
    "qs_pg:pop_sr":0,
    "qs_pg:qs_pg_placetype":"locality",
    "qs_pg:qs_pg_placetype_gp":"Town",
    "qs_pg:woe_adm0":23424975,
    "woe:adm0_id":23424975,
    "woe:name_adm0":"United Kingdom",
    "woe:name_adm1":"England",
    "woe:placetype":"Town",
    "wof:name":"Repps with Bastwick",
    "wof:placetype":"neighbourhood"
},
  "geometry": {"coordinates":[1.573019,52.698467],"type":"Point"}
}