{
  "type": "Feature",
  "properties": {
    "gn:country":"GB",
    "gn:fcode":"PPL",
    "gn:population":1575,
    "iso:country":"GB",
    "name:ceb_x_preferred":[
        "Scotby"
    ],
    "name:cym_x_preferred":[
        "Scotby"
    ],
    "name:eng_x_preferred":[
        "Scotby"
    ],
    "name:fra_x_preferred":[
        "Scotby"
    ],
    "name:gle_x_preferred":[
        "Scotby"
    ],
    "name:nld_x_preferred":[
        "Scotby"
    ],
    "name:pol_x_preferred":[
        "Scotby"
    ],
    "name:spa_x_preferred":[
        "Scotby"
    ],
    "name:swe_x_preferred":[
        "Scotby"
    ],
    "qs_pg:aaroncc":"GB",
    "qs_pg:gn_country":"GB",
    "qs_pg:gn_fcode":"PPL",
    "qs_pg:gn_pop":1575,
    "qs_pg:name":"Scotby",
    "qs_pg:name_adm0":"United Kingdom",
    "qs_pg:name_adm1":"England",
    "qs_pg:photos_9r":0,
    "qs_pg:photos_sr":0,
    "qs_pg:pop_sr":3,
    "qs_pg:qs_pg_placetype":"locality",
    "qs_pg:qs_pg_placetype_gp":"Town",
    "qs_pg:woe_adm0":23424975,
    "woe:adm0_id":23424975,
    "woe:name_adm0":"United Kingdom",
    "woe:name_adm1":"England",
    "woe:placetype":"Town",
    "wof:name":"Scotby",
    "wof:placetype":"neighbourhood",
    "wof:population":1575
},
  "geometry": {"coordinates":[-2.87464,54.89004],"type":"Point"}
}