{
  "type": "Feature",
  "properties": {
    "gn:country": "GB",
    "gn:fcode": "PPL",
    "gn:population": 893,
    "iso:country": "GB",
    "name:bul_x_preferred": [
      "Стратхпефер"
    ],
    "name:ceb_x_preferred": [
      "Strathpeffer"
    ],
    "name:cym_x_preferred": [
      "Strathpeffer"
    ],
    "name:deu_x_preferred": [
      "Strathpeffer"
    ],
    "name:eng_x_preferred": [
      "Strathpeffer"
    ],
    "name:eus_x_preferred": [
      "Strathpeffer"
    ],
    "name:fra_x_preferred": [
      "Strathpeffer"
    ],
    "name:gla_x_preferred": [
      "Srath Pheofhair"
    ],
    "name:gle_x_preferred": [
      "Srath Pheofhair"
    ],
    "name:ita_x_preferred": [
      "Strathpeffer"
    ],
    "name:jpn_x_preferred": [
      "ストラスペファー"
    ],
    "name:nld_x_preferred": [
      "Strathpeffer"
    ],
    "name:nno_x_preferred": [
      "Strathpeffer"
    ],
    "name:nob_x_preferred": [
      "Strathpeffer"
    ],
    "name:sco_x_preferred": [
      "Strathpeffer"
    ],
    "name:spa_x_preferred": [
      "Strathpeffer"
    ],
    "name:swe_x_preferred": [
      "Strathpeffer"
    ],
    "name:zho_x_preferred": [
      "斯特拉斯佩弗"
    ],
    "qs_pg:aaroncc": "GB",
    "qs_pg:gn_country": "GB",
    "qs_pg:gn_fcode": "PPL",
    "qs_pg:gn_pop": 893,
    "qs_pg:name": "Strathpeffer",
    "qs_pg:name_adm0": "United Kingdom",
    "qs_pg:name_adm1": "Scotland",
    "qs_pg:photos": 1600,
    "qs_pg:photos_1k": 324,
    "qs_pg:photos_9k": 7,
    "qs_pg:photos_9r": 8,
    "qs_pg:photos_all": 1600,
    "qs_pg:photos_sr": 13,
    "qs_pg:pop_sr": 2,
    "qs_pg:qs_pg_placetype": "locality",
    "qs_pg:qs_pg_placetype_gp": "Town",
    "qs_pg:woe_adm0": 23424975,
    "woe:adm0_id": 23424975,
    "woe:name_adm0": "United Kingdom",
    "woe:name_adm1": "Scotland",
    "woe:placetype": "Town",
    "wof:name": "Strathpeffer",
    "wof:placetype": "locality",
    "wof:population": 1070
  },
  "geometry": {"coordinates":[-4.53832,57.58847],"type":"Point"}
}
