{
  "type": "Feature",
  "properties": {
    "gn:gn_country":"GB",
    "gn:gn_fcode":"PPL",
    "gn:gn_pop":893,
    "gn:population":1070,
    "iso:country":"GB",
    "name:bul_x_preferred":[
        "\u0421\u0442\u0440\u0430\u0442\u0445\u043f\u0435\u0444\u0435\u0440"
    ],
    "name:ceb_x_preferred":[
        "Strathpeffer"
    ],
    "name:cym_x_preferred":[
        "Strathpeffer"
    ],
    "name:deu_x_preferred":[
        "Strathpeffer"
    ],
    "name:eng_x_preferred":[
        "Strathpeffer"
    ],
    "name:eus_x_preferred":[
        "Strathpeffer"
    ],
    "name:fra_x_preferred":[
        "Strathpeffer"
    ],
    "name:gla_x_preferred":[
        "Srath Pheofhair"
    ],
    "name:gle_x_preferred":[
        "Srath Pheofhair"
    ],
    "name:ita_x_preferred":[
        "Strathpeffer"
    ],
    "name:jpn_x_preferred":[
        "\u30b9\u30c8\u30e9\u30b9\u30da\u30d5\u30a1\u30fc"
    ],
    "name:nld_x_preferred":[
        "Strathpeffer"
    ],
    "name:nno_x_preferred":[
        "Strathpeffer"
    ],
    "name:nob_x_preferred":[
        "Strathpeffer"
    ],
    "name:sco_x_preferred":[
        "Strathpeffer"
    ],
    "name:spa_x_preferred":[
        "Strathpeffer"
    ],
    "name:swe_x_preferred":[
        "Strathpeffer"
    ],
    "name:zho_x_preferred":[
        "\u65af\u7279\u62c9\u65af\u4f69\u5f17"
    ],
    "qs_pg:aaroncc":"GB",
    "qs_pg:gn_country":"GB",
    "qs_pg:gn_fcode":"PPL",
    "qs_pg:gn_pop":893,
    "qs_pg:name":"Strathpeffer",
    "qs_pg:name_adm0":"United Kingdom",
    "qs_pg:name_adm1":"Scotland",
    "qs_pg:photos":1600,
    "qs_pg:photos_1k":324,
    "qs_pg:photos_9k":7,
    "qs_pg:photos_9r":8,
    "qs_pg:photos_all":1600,
    "qs_pg:photos_sr":13,
    "qs_pg:pop_sr":2,
    "qs_pg:qs_pg_placetype":"locality",
    "qs_pg:qs_pg_placetype_gp":"Town",
    "qs_pg:woe_adm0":23424975,
    "woe:adm0_id":23424975,
    "woe:name_adm0":"United Kingdom",
    "woe:name_adm1":"Scotland",
    "woe:placetype":"Town",
    "wof:name":"Strathpeffer",
    "wof:placetype":"locality",
    "wof:population":1070
},
  "geometry": {"coordinates":[-4.53832,57.58847],"type":"Point"}
}