{
  "type": "Feature",
  "properties": {
    "gn:country": "GB",
    "gn:fcode": "PPL",
    "gn:population": 0,
    "iso:country": "GB",
    "name:ceb_x_preferred": [
      "Blackwater"
    ],
    "name:chv_x_preferred": [
      "Блэкуотер"
    ],
    "name:cym_x_preferred": [
      "Blackwater"
    ],
    "name:deu_x_preferred": [
      "Blackwater"
    ],
    "name:fas_x_preferred": [
      "بلک‌واتر"
    ],
    "name:fra_x_preferred": [
      "Blackwater"
    ],
    "name:ita_x_preferred": [
      "Blackwater"
    ],
    "name:jpn_x_preferred": [
      "ブラックウォーター"
    ],
    "name:kor_x_preferred": [
      "블랙워터"
    ],
    "name:nds_x_preferred": [
      "Blackwater"
    ],
    "name:nld_x_preferred": [
      "Blackwater"
    ],
    "name:nno_x_preferred": [
      "Blackwater"
    ],
    "name:nor_x_preferred": [
      "Blackwater"
    ],
    "name:pol_x_preferred": [
      "Blackwater"
    ],
    "name:por_x_preferred": [
      "Blackwater"
    ],
    "name:rus_x_preferred": [
      "Блэкуотер"
    ],
    "name:slk_x_preferred": [
      "Blackwater"
    ],
    "name:spa_x_preferred": [
      "Blackwater"
    ],
    "name:srp_x_preferred": [
      "Блеквотер"
    ],
    "name:swe_x_preferred": [
      "Blackwater"
    ],
    "name:ukr_x_preferred": [
      "Блеквотер"
    ],
    "name:urd_x_preferred": [
      "بلیک واٹر"
    ],
    "name:vol_x_preferred": [
      "Blackwater"
    ],
    "qs_pg:aaroncc": "GB",
    "qs_pg:gn_country": "GB",
    "qs_pg:gn_fcode": "PPL",
    "qs_pg:gn_pop": 0,
    "qs_pg:name": "Blackwater",
    "qs_pg:name_adm0": "United Kingdom",
    "qs_pg:name_adm1": "England",
    "qs_pg:photos": 304,
    "qs_pg:photos_1k": 62,
    "qs_pg:photos_9k": 1,
    "qs_pg:photos_9r": 5,
    "qs_pg:photos_all": 304,
    "qs_pg:photos_sr": 5,
    "qs_pg:pop_sr": 0,
    "qs_pg:qs_pg_placetype": "locality",
    "qs_pg:qs_pg_placetype_gp": "Town",
    "qs_pg:woe_adm0": 23424975,
    "woe:adm0_id": 23424975,
    "woe:name_adm0": "United Kingdom",
    "woe:name_adm1": "England",
    "woe:placetype": "Town",
    "wof:name": "Blackwater",
    "wof:placetype": "neighbourhood"
  },
  "geometry": {"coordinates":[-1.28333,50.66667],"type":"Point"}
}
