{
  "type": "Feature",
  "properties": {
    "gn:admin1_code": "SCT",
    "gn:admin2_code": "T7",
    "gn:asciiname": "Little Forter",
    "gn:country_code": "GB",
    "gn:dem": 330,
    "gn:feature_class": "P",
    "gn:feature_code": "PPL",
    "gn:name": "Little Forter",
    "gn:population": 0,
    "gn:timezone": "Europe/London",
    "iso:country": "GB",
    "name:eus_x_preferred": [
      "Little Forter"
    ],
    "wof:name": "Little Forter",
    "wof:placetype": "locality"
  },
  "geometry": {"coordinates":[-3.33469,56.77225],"type":"Point"}
}
