{
  "type": "Feature",
  "properties": {
    "iso:country":"GB",
    "name:dut_x_preferred":[
        "Kirkpatrick-Fleming"
    ],
    "name:eng_x_preferred":[
        "Kirkpatrick-Fleming"
    ],
    "name:fre_x_preferred":[
        "Kirkpatrick-Fleming"
    ],
    "name:ger_x_preferred":[
        "Kirkpatrick-Fleming"
    ],
    "name:gla_x_preferred":[
        "Cille Ph\u00e0draig nam Fleamach"
    ],
    "name:gle_x_preferred":[
        "Cille Ph\u00e0draig nam Fleamach"
    ],
    "qs_pg:aaroncc":"GB",
    "qs_pg:name":"Kirkpatrick-Fleming",
    "qs_pg:name_adm0":"United Kingdom",
    "qs_pg:name_adm1":"Scotland",
    "qs_pg:photos":192,
    "qs_pg:photos_1k":39,
    "qs_pg:photos_9k":1,
    "qs_pg:photos_9r":4,
    "qs_pg:photos_all":192,
    "qs_pg:photos_sr":4,
    "qs_pg:pop_sr":0,
    "qs_pg:qs_pg_placetype":"locality",
    "qs_pg:qs_pg_placetype_gp":"Town",
    "qs_pg:woe_adm0":23424975,
    "woe:adm0_id":23424975,
    "woe:name_adm0":"United Kingdom",
    "woe:name_adm1":"Scotland",
    "woe:placetype":"Town",
    "wof:name":"Kirkpatrick-Fleming",
    "wof:placetype":"locality"
},
  "geometry": {"coordinates":[-3.159127,55.029528],"type":"Point"}
}