{
  "type": "Feature",
  "properties": {
    "gn:population":799,
    "iso:country":"GB",
    "name:bul_x_preferred":[
        "\u0421\u0430\u043d\u0434\u0431\u0430\u043d\u043a"
    ],
    "name:ceb_x_preferred":[
        "Sandbank"
    ],
    "name:eng_x_preferred":[
        "Sandbank"
    ],
    "name:eus_x_preferred":[
        "Sandbank"
    ],
    "name:fas_x_preferred":[
        "\u0633\u0646\u062f\u0628\u0646\u06a9"
    ],
    "name:fra_x_preferred":[
        "Sandbank"
    ],
    "name:gla_x_preferred":[
        "An Oitir"
    ],
    "name:gle_x_preferred":[
        "Taigh a' Chladaich"
    ],
    "name:nld_x_preferred":[
        "Sandbank"
    ],
    "name:rus_x_preferred":[
        "\u0421\u044d\u043d\u0434\u0431\u0430\u043d\u043a"
    ],
    "name:spa_x_preferred":[
        "Sandbank"
    ],
    "name:swe_x_preferred":[
        "Sandbank"
    ],
    "qs:a0":"United Kingdom",
    "qs:a1":"*Argyll and Bute",
    "qs:a1_lc":"GB11QD0000",
    "qs:a1r":"0Scotland",
    "qs:a1r_lc":"GB11000000",
    "qs:adm0":"United Kingdom",
    "qs:la_lc":"*",
    "qs:level":"locality",
    "qs:loc":"Sandbank",
    "qs:loc_alt":"Sandbank",
    "qs:pop":0,
    "qs:type":"buffered point",
    "wof:name":"Sandbank",
    "wof:placetype":"locality",
    "wof:population":799
},
  "geometry": {"coordinates":[-4.948714,55.980753],"type":"Point"}
}