{
  "type": "Feature",
  "properties": {
    "gn:country":"GB",
    "gn:fcode":"PPL",
    "gn:population":0,
    "iso:country":"GB",
    "name:bul_x_preferred":[
        "\u0411\u043b\u0435\u043a\u0441\u0442\u043e\u0443\u043d"
    ],
    "name:cat_x_preferred":[
        "Blackstone"
    ],
    "name:ceb_x_preferred":[
        "Blackstone"
    ],
    "name:deu_x_preferred":[
        "Blackstone"
    ],
    "name:fra_x_preferred":[
        "Blackstone"
    ],
    "name:heb_x_preferred":[
        "\u05d1\u05dc\u05e7\u05e1\u05d8\u05d5\u05df"
    ],
    "name:ita_x_preferred":[
        "Blackstone"
    ],
    "name:jpn_x_preferred":[
        "\u30d6\u30e9\u30c3\u30af\u30b9\u30c8\u30f3"
    ],
    "name:kor_x_preferred":[
        "\ube14\ub799\uc2a4\ud1a4"
    ],
    "name:nld_x_preferred":[
        "Blackstone"
    ],
    "name:nor_x_preferred":[
        "Blackstone"
    ],
    "name:pol_x_preferred":[
        "Blackstone"
    ],
    "name:rus_x_preferred":[
        "\u0411\u043b\u044d\u043a\u0441\u0442\u043e\u043d"
    ],
    "name:spa_x_preferred":[
        "Blackstone"
    ],
    "name:swe_x_preferred":[
        "Blackstone"
    ],
    "name:ukr_x_preferred":[
        "\u0411\u043b\u0435\u043a\u0441\u0442\u043e\u0443\u043d"
    ],
    "name:und_x_variant":[
        "Blackston"
    ],
    "name:vol_x_preferred":[
        "Blackstone"
    ],
    "qs_pg:aaroncc":"GB",
    "qs_pg:gn_country":"GB",
    "qs_pg:gn_fcode":"PPL",
    "qs_pg:gn_pop":0,
    "qs_pg:name":"Blackstone",
    "qs_pg:name_adm0":"United Kingdom",
    "qs_pg:name_adm1":"Scotland",
    "qs_pg:photos":6,
    "qs_pg:photos_1k":1,
    "qs_pg:photos_9k":1,
    "qs_pg:photos_9r":1,
    "qs_pg:photos_all":6,
    "qs_pg:photos_sr":1,
    "qs_pg:pop_sr":0,
    "qs_pg:qs_pg_placetype":"locality",
    "qs_pg:qs_pg_placetype_gp":"Town",
    "qs_pg:woe_adm0":23424975,
    "woe:adm0_id":23424975,
    "woe:name_adm0":"United Kingdom",
    "woe:name_adm1":"Scotland",
    "woe:placetype":"Town",
    "wof:name":"Blackstone",
    "wof:placetype":"locality"
},
  "geometry": {"coordinates":[-3.73333,55.93333],"type":"Point"}
}