{
  "type": "Feature",
  "properties": {
    "iso:country": "GB",
    "name:gle_x_preferred": [
      "Crownhill"
    ],
    "qs_pg:aaroncc": "GB",
    "qs_pg:name": "Crownhill",
    "qs_pg:name_adm0": "United Kingdom",
    "qs_pg:name_adm1": "England",
    "qs_pg:photos": 306,
    "qs_pg:photos_1k": 62,
    "qs_pg:photos_9k": 1,
    "qs_pg:photos_9r": 5,
    "qs_pg:photos_all": 306,
    "qs_pg:photos_sr": 5,
    "qs_pg:pop_sr": 0,
    "qs_pg:qs_pg_placetype": "locality",
    "qs_pg:qs_pg_placetype_gp": "Town",
    "qs_pg:woe_adm0": 23424975,
    "woe:adm0_id": 23424975,
    "woe:name_adm0": "United Kingdom",
    "woe:name_adm1": "England",
    "woe:placetype": "Town",
    "wof:name": "Crownhill",
    "wof:placetype": "neighbourhood"
  },
  "geometry": {"coordinates":[-0.800488,52.024699],"type":"Point"}
}
