{
  "type": "Feature",
  "properties": {
    "iso:country":"GB",
    "wof:name":"Wyle Common",
    "wof:placetype":"neighbourhood"
},
  "geometry": {"coordinates":[-1.75870641312775,53.73731185684569],"type":"Point"}
}