{
  "type": "Feature",
  "properties": {
    "gn:country": "GB",
    "gn:fcode": "PPL",
    "gn:population": 0,
    "iso:country": "GB",
    "name:cat_x_preferred": [
      "Shieldaig"
    ],
    "name:deu_x_preferred": [
      "Shieldaig"
    ],
    "name:eng_x_preferred": [
      "Shieldaig"
    ],
    "name:eus_x_preferred": [
      "Shieldaig"
    ],
    "name:fra_x_preferred": [
      "Shieldaig"
    ],
    "name:gla_x_preferred": [
      "Sìldeag"
    ],
    "name:gle_x_preferred": [
      "Síldeag"
    ],
    "name:nld_x_preferred": [
      "Shieldaig"
    ],
    "name:swe_x_preferred": [
      "Shieldaig"
    ],
    "name:zho_x_preferred": [
      "希爾代格"
    ],
    "qs_pg:aaroncc": "GB",
    "qs_pg:gn_country": "GB",
    "qs_pg:gn_fcode": "PPL",
    "qs_pg:gn_pop": 0,
    "qs_pg:name": "Shieldaig",
    "qs_pg:name_adm0": "United Kingdom",
    "qs_pg:name_adm1": "Scotland",
    "qs_pg:photos": 144,
    "qs_pg:photos_1k": 29,
    "qs_pg:photos_9k": 1,
    "qs_pg:photos_9r": 3,
    "qs_pg:photos_all": 144,
    "qs_pg:photos_sr": 3,
    "qs_pg:pop_sr": 0,
    "qs_pg:qs_pg_placetype": "locality",
    "qs_pg:qs_pg_placetype_gp": "Town",
    "qs_pg:woe_adm0": 23424975,
    "woe:adm0_id": 23424975,
    "woe:name_adm0": "United Kingdom",
    "woe:name_adm1": "Scotland",
    "woe:placetype": "Town",
    "wof:name": "Shieldaig",
    "wof:placetype": "locality"
  },
  "geometry": {"coordinates":[-5.65115,57.52198],"type":"Point"}
}
