{
  "type": "Feature",
  "properties": {
    "gn:admin1_code":"ENG",
    "gn:admin2_code":"G2",
    "gn:admin3_code":"00MW005",
    "gn:asciiname":"Five Houses",
    "gn:country_code":"GB",
    "gn:dem":48,
    "gn:feature_class":"P",
    "gn:feature_code":"PPL",
    "gn:name":"Five Houses",
    "gn:population":0,
    "gn:timezone":"Europe/London",
    "iso:country":"GB",
    "wof:name":"Five Houses",
    "wof:placetype":"neighbourhood"
},
  "geometry": {"coordinates":[-1.39724,50.68629],"type":"Point"}
}