{
  "type": "Feature",
  "properties": {
    "gn:country":"GB",
    "gn:fcode":"PPL",
    "gn:population":0,
    "iso:country":"GB",
    "name:cat_x_preferred":[
        "Castell Combe"
    ],
    "name:ceb_x_preferred":[
        "Castle Combe"
    ],
    "name:deu_x_preferred":[
        "Castle Combe"
    ],
    "name:eng_x_preferred":[
        "Castle Combe"
    ],
    "name:fas_x_preferred":[
        "\u06a9\u0633\u0644 \u06a9\u0648\u0645\u0628"
    ],
    "name:fra_x_preferred":[
        "Castle Combe"
    ],
    "name:glg_x_preferred":[
        "Castle Combe"
    ],
    "name:ita_x_preferred":[
        "Castle Combe"
    ],
    "name:jpn_x_preferred":[
        "\u30ab\u30fc\u30b9\u30eb\u30fb\u30af\u30fc\u30e0"
    ],
    "name:lat_x_preferred":[
        "Castle Combe"
    ],
    "name:msa_x_preferred":[
        "Castle Combe"
    ],
    "name:nld_x_preferred":[
        "Castle Combe"
    ],
    "name:pol_x_preferred":[
        "Castle Combe"
    ],
    "name:slv_x_preferred":[
        "Castle Combe"
    ],
    "name:spa_x_preferred":[
        "Castle Combe"
    ],
    "name:swe_x_preferred":[
        "Castle Combe"
    ],
    "name:vie_x_preferred":[
        "Castle Combe"
    ],
    "qs_pg:aaroncc":"GB",
    "qs_pg:gn_country":"GB",
    "qs_pg:gn_fcode":"PPL",
    "qs_pg:gn_pop":0,
    "qs_pg:name":"Upper Castle Combe",
    "qs_pg:name_adm0":"United Kingdom",
    "qs_pg:name_adm1":"England",
    "qs_pg:photos":4999,
    "qs_pg:photos_1k":1000,
    "qs_pg:photos_9k":22,
    "qs_pg:photos_9r":14,
    "qs_pg:photos_all":4999,
    "qs_pg:photos_sr":24,
    "qs_pg:pop_sr":0,
    "qs_pg:qs_pg_placetype":"locality",
    "qs_pg:qs_pg_placetype_gp":"Town",
    "qs_pg:woe_adm0":23424975,
    "woe:adm0_id":23424975,
    "woe:name_adm0":"United Kingdom",
    "woe:name_adm1":"England",
    "woe:placetype":"Town",
    "wof:name":"Upper Castle Combe",
    "wof:placetype":"neighbourhood"
},
  "geometry": {"coordinates":[-2.22897,51.49289],"type":"Point"}
}