{
  "type": "Feature",
  "properties": {
    "gn:country":"GB",
    "gn:fcode":"PPL",
    "gn:population":0,
    "iso:country":"GB",
    "name:cym_x_preferred":[
        "Upper Boddington"
    ],
    "name:pol_x_preferred":[
        "Upper Boddington"
    ],
    "name:spa_x_preferred":[
        "Upper Boddington"
    ],
    "name:swe_x_preferred":[
        "Upper Boddington"
    ],
    "name:und_x_variant":[
        "Boddington"
    ],
    "qs_pg:aaroncc":"GB",
    "qs_pg:gn_country":"GB",
    "qs_pg:gn_fcode":"PPL",
    "qs_pg:gn_pop":0,
    "qs_pg:name":"Upper Boddington",
    "qs_pg:name_adm0":"United Kingdom",
    "qs_pg:name_adm1":"England",
    "qs_pg:photos":272,
    "qs_pg:photos_1k":55,
    "qs_pg:photos_9k":1,
    "qs_pg:photos_9r":4,
    "qs_pg:photos_all":272,
    "qs_pg:photos_sr":5,
    "qs_pg:pop_sr":0,
    "qs_pg:qs_pg_placetype":"locality",
    "qs_pg:qs_pg_placetype_gp":"Town",
    "qs_pg:woe_adm0":23424975,
    "woe:adm0_id":23424975,
    "woe:name_adm0":"United Kingdom",
    "woe:name_adm1":"England",
    "woe:placetype":"Town",
    "wof:name":"Upper Boddington",
    "wof:placetype":"neighbourhood",
    "wof:population":451
},
  "geometry": {"coordinates":[-1.29595,52.17651],"type":"Point"}
}