{
  "type": "Feature",
  "properties": {
    "gn:gn_country":"GB",
    "gn:gn_fcode":"PPL",
    "gn:gn_pop":18069,
    "gn:population":18069,
    "iso:country":"GB",
    "name:ben_x_preferred":[
        "\u0993\u09af\u09bc\u09be\u09b2\u09a5\u09be\u09ae \u0985\u09cd\u09af\u09be\u09ac\u09c7"
    ],
    "name:cym_x_preferred":[
        "Waltham Abbey "
    ],
    "name:deu_x_preferred":[
        "Waltham Abbey"
    ],
    "name:eng_x_preferred":[
        "Waltham Abbey"
    ],
    "name:fas_x_preferred":[
        "\u0648\u0627\u0644\u062a\u0647\u0627\u0645 \u0627\u0628\u06cc"
    ],
    "name:fra_x_preferred":[
        "Waltham Abbey"
    ],
    "name:gle_x_preferred":[
        "Waltham Abbey"
    ],
    "name:guj_x_preferred":[
        "\u0ab5\u0acb\u0ab2\u0acd\u0aa5\u0aae \u0a8f\u0aac\u0ac0"
    ],
    "name:heb_x_preferred":[
        "\u05de\u05e0\u05d6\u05e8 \u05d5\u05d5\u05dc\u05d8\u05d4\u05d0\u05dd"
    ],
    "name:ita_x_preferred":[
        "Waltham Abbey"
    ],
    "name:jpn_x_preferred":[
        "\u30a6\u30a9\u30eb\u30b5\u30e0\u30fb\u30a2\u30d3\u30fc"
    ],
    "name:kan_x_preferred":[
        "\u0cb5\u0cbe\u0cb2\u0ccd\u0ca5\u0cae\u0ccd \u0c85\u0cac\u0ccd\u0cac\u0cc6"
    ],
    "name:kor_x_preferred":[
        "\uc6d4\uc12c \uc560\ube44"
    ],
    "name:lit_x_preferred":[
        "Valtamas Abis"
    ],
    "name:nld_x_preferred":[
        "Waltham Abbey"
    ],
    "name:nno_x_preferred":[
        "Waltham Abbey i Essex"
    ],
    "name:pol_x_preferred":[
        "Waltham Abbey"
    ],
    "name:por_x_preferred":[
        "Waltham Abbey"
    ],
    "name:ron_x_preferred":[
        "Waltham Abbey"
    ],
    "name:rus_x_preferred":[
        "\u0423\u043e\u043b\u0442\u0445\u044d\u043c-\u042d\u0431\u0431\u0438"
    ],
    "name:spa_x_preferred":[
        "Waltham Abbey"
    ],
    "name:swe_x_preferred":[
        "Waltham Abbey"
    ],
    "name:tam_x_preferred":[
        "\u0bb5\u0bbe\u0bb2\u0bcd\u0ba4\u0bae\u0bcd  \u0b85\u0baa\u0bc7"
    ],
    "name:tel_x_preferred":[
        "\u0c35\u0c3e\u0c32\u0c4d\u0c24\u0c02  \u0c05\u0c2c\u0c4d\u0c2c\u0c47"
    ],
    "name:urd_x_preferred":[
        "\u0648\u0627\u0644\u062a\u06be\u0645\u00a0\u0627\u0628\u06d2"
    ],
    "name:vol_x_preferred":[
        "Waltham Abbey"
    ],
    "qs_pg:aaroncc":"GB",
    "qs_pg:gn_country":"GB",
    "qs_pg:gn_fcode":"PPL",
    "qs_pg:gn_pop":18069,
    "qs_pg:name":"Waltham Abbey",
    "qs_pg:name_adm0":"United Kingdom",
    "qs_pg:name_adm1":"England",
    "qs_pg:photos":1397,
    "qs_pg:photos_1k":283,
    "qs_pg:photos_9k":6,
    "qs_pg:photos_9r":7,
    "qs_pg:photos_all":1397,
    "qs_pg:photos_sr":12,
    "qs_pg:pop_sr":6,
    "qs_pg:qs_pg_placetype":"locality",
    "qs_pg:qs_pg_placetype_gp":"Town",
    "qs_pg:woe_adm0":23424975,
    "woe:adm0_id":23424975,
    "woe:name_adm0":"United Kingdom",
    "woe:name_adm1":"England",
    "woe:placetype":"Town",
    "wof:name":"Waltham Abbey",
    "wof:placetype":"neighbourhood",
    "wof:population":18069
},
  "geometry": {"coordinates":[-0.00421,51.687],"type":"Point"}
}