{
  "type": "Feature",
  "properties": {
    "gn:country":"GB",
    "gn:fcode":"PPL",
    "gn:population":0,
    "iso:country":"GB",
    "name:eng_x_preferred":[
        "Great Rollright"
    ],
    "name:fra_x_preferred":[
        "Great Rollright"
    ],
    "name:gle_x_preferred":[
        "Great Rollright"
    ],
    "name:nld_x_preferred":[
        "Great Rollright"
    ],
    "name:pol_x_preferred":[
        "Great Rollright"
    ],
    "name:spa_x_preferred":[
        "Great Rollright"
    ],
    "name:und_x_variant":[
        "Rollwright"
    ],
    "qs_pg:aaroncc":"GB",
    "qs_pg:gn_country":"GB",
    "qs_pg:gn_fcode":"PPL",
    "qs_pg:gn_pop":0,
    "qs_pg:name":"Great Rollright",
    "qs_pg:name_adm0":"United Kingdom",
    "qs_pg:name_adm1":"England",
    "qs_pg:photos":49,
    "qs_pg:photos_1k":10,
    "qs_pg:photos_9k":1,
    "qs_pg:photos_9r":2,
    "qs_pg:photos_all":49,
    "qs_pg:photos_sr":2,
    "qs_pg:pop_sr":0,
    "qs_pg:qs_pg_placetype":"locality",
    "qs_pg:qs_pg_placetype_gp":"Town",
    "qs_pg:woe_adm0":23424975,
    "woe:adm0_id":23424975,
    "woe:name_adm0":"United Kingdom",
    "woe:name_adm1":"England",
    "woe:placetype":"Town",
    "wof:name":"Great Rollright",
    "wof:placetype":"neighbourhood",
    "wof:population":502
},
  "geometry": {"coordinates":[-1.52864,51.97595],"type":"Point"}
}