{
  "type": "Feature",
  "properties": {
    "iso:country":"GB",
    "wof:name":"North Belfast",
    "wof:placetype":"neighbourhood"
},
  "geometry": {"coordinates":[-5.94355155530779,54.6214305029346],"type":"Point"}
}