{
  "type": "Feature",
  "properties": {
    "iso:country": "GB",
    "name:azb_x_preferred": [
      "ساوت وودهام فررز"
    ],
    "name:ben_x_preferred": [
      "সাউথ উডহ্যাম ফের‍্যারস"
    ],
    "name:ceb_x_preferred": [
      "South Woodham Ferrers"
    ],
    "name:cym_x_preferred": [
      "South Woodham Ferrers"
    ],
    "name:deu_x_preferred": [
      "South Woodham Ferrers"
    ],
    "name:eng_x_preferred": [
      "South Woodham Ferrers"
    ],
    "name:fas_x_preferred": [
      "ساوت وودهام فررز"
    ],
    "name:fra_x_preferred": [
      "South Woodham Ferrers"
    ],
    "name:gle_x_preferred": [
      "Woodham Ferrers Theas"
    ],
    "name:guj_x_preferred": [
      "દક્ષિણ વુડહામ ફેરર્સ"
    ],
    "name:ita_x_preferred": [
      "South Woodham Ferrers"
    ],
    "name:jpn_x_preferred": [
      "南ウッドハム・フェラーズ"
    ],
    "name:kan_x_preferred": [
      "ಸೌತ್ ವುಡಮ್ ಫೆರೆರ್ಸ್"
    ],
    "name:kor_x_preferred": [
      "사우스 우드햄 페어러스"
    ],
    "name:lit_x_preferred": [
      "Saut Vudham Ferersas"
    ],
    "name:nld_x_preferred": [
      "South Woodham Ferrers"
    ],
    "name:nno_x_preferred": [
      "South Woodham Ferrers"
    ],
    "name:pol_x_preferred": [
      "South Woodham Ferrers"
    ],
    "name:por_x_preferred": [
      "South Woodham Ferrers"
    ],
    "name:ron_x_preferred": [
      "South Woodham Ferrers"
    ],
    "name:rus_x_preferred": [
      "Саус-Вудхэм-Феррес"
    ],
    "name:spa_x_preferred": [
      "South Woodham Ferrers"
    ],
    "name:swe_x_preferred": [
      "South Woodham Ferrers"
    ],
    "name:tam_x_preferred": [
      "கிழக்கு வுட்ஹாம் பெற்ரேர்ஸ்"
    ],
    "name:tel_x_preferred": [
      "సౌత్ వుడ్హమ్ ఫెర్రర్స్"
    ],
    "name:urd_x_preferred": [
      "ساؤتھ وودہام فیریرس"
    ],
    "name:vol_x_preferred": [
      "South Woodham Ferrers"
    ],
    "qs:a0": "United Kingdom",
    "qs:a1": "*Essex",
    "qs:a1_lc": "GB12220000",
    "qs:a1r": "0England",
    "qs:a1r_lc": "GB12000000",
    "qs:adm0": "United Kingdom",
    "qs:la_lc": "*",
    "qs:level": "locality",
    "qs:loc": "South Woodham Ferrers",
    "qs:loc_alt": "South Woodham Ferrers",
    "qs:pop": 0,
    "qs:type": "buffered point",
    "wd:wordcount": 1087,
    "wof:name": "South Woodham Ferrers",
    "wof:placetype": "neighbourhood"
  },
  "geometry": {"coordinates":[0.601538,51.65288],"type":"Point"}
}
