{
  "type": "Feature",
  "properties": {
    "iso:country":"GB",
    "qs_pg:aaroncc":"GB",
    "qs_pg:name":"Darnaway",
    "qs_pg:name_adm0":"United Kingdom",
    "qs_pg:name_adm1":"Scotland",
    "qs_pg:photos":344,
    "qs_pg:photos_1k":70,
    "qs_pg:photos_9k":2,
    "qs_pg:photos_9r":5,
    "qs_pg:photos_all":344,
    "qs_pg:photos_sr":5,
    "qs_pg:pop_sr":0,
    "qs_pg:qs_pg_placetype":"locality",
    "qs_pg:qs_pg_placetype_gp":"Town",
    "qs_pg:woe_adm0":23424975,
    "woe:adm0_id":23424975,
    "woe:name_adm0":"United Kingdom",
    "woe:name_adm1":"Scotland",
    "woe:placetype":"Town",
    "wof:name":"Darnaway",
    "wof:placetype":"locality"
},
  "geometry": {"coordinates":[-3.6910195,57.563639],"type":"Point"}
}