{
  "type": "Feature",
  "properties": {
    "iso:country": "GB",
    "name:ceb_x_preferred": [
      "Bower Chalke"
    ],
    "name:eng_x_preferred": [
      "Bowerchalke"
    ],
    "name:fra_x_preferred": [
      "Bowerchalke"
    ],
    "name:nld_x_preferred": [
      "Bower Chalke"
    ],
    "name:pol_x_preferred": [
      "Bowerchalke"
    ],
    "name:swe_x_preferred": [
      "Bower Chalke"
    ],
    "name:swe_x_variant": [
      "Bower Chalke"
    ],
    "qs_pg:aaroncc": "GB",
    "qs_pg:name": "Bowerchalke",
    "qs_pg:name_adm0": "United Kingdom",
    "qs_pg:name_adm1": "England",
    "qs_pg:photos": 187,
    "qs_pg:photos_1k": 38,
    "qs_pg:photos_9k": 1,
    "qs_pg:photos_9r": 4,
    "qs_pg:photos_all": 187,
    "qs_pg:photos_sr": 4,
    "qs_pg:pop_sr": 0,
    "qs_pg:qs_pg_placetype": "locality",
    "qs_pg:qs_pg_placetype_gp": "Town",
    "qs_pg:woe_adm0": 23424975,
    "woe:adm0_id": 23424975,
    "woe:name_adm0": "United Kingdom",
    "woe:name_adm1": "England",
    "woe:placetype": "Town",
    "wof:name": "Bowerchalke",
    "wof:placetype": "neighbourhood"
  },
  "geometry": {"coordinates":[-1.970672,51.00533],"type":"Point"}
}
