{
  "type": "Feature",
  "properties": {
    "iso:country":"GB",
    "wof:name":"Broughton Park",
    "wof:placetype":"neighbourhood"
},
  "geometry": {"coordinates":[-2.25983359924109,53.51408575080545],"type":"Point"}
}