{
  "type": "Feature",
  "properties": {
    "gn:admin1_code": "NIR",
    "gn:admin2_code": "N09000005",
    "gn:asciiname": "Ballymagorry",
    "gn:country_code": "GB",
    "gn:dem": 22,
    "gn:feature_class": "P",
    "gn:feature_code": "PPL",
    "gn:name": "Ballymagorry",
    "gn:population": 0,
    "gn:timezone": "Europe/London",
    "iso:country": "GB",
    "name:eus_x_preferred": [
      "Ballymagorry"
    ],
    "name:ita_x_preferred": [
      "Ballymagorry"
    ],
    "name:msa_x_preferred": [
      "Ballymagorry"
    ],
    "name:pli_x_preferred": [
      "बल्ल्य्मागोर्री"
    ],
    "name:spa_x_preferred": [
      "Ballymagorry"
    ],
    "wof:name": "Ballymagorry",
    "wof:placetype": "locality"
  },
  "geometry": {"coordinates":[-7.43333,54.85],"type":"Point"}
}
