{
  "type": "Feature",
  "properties": {
    "gn:admin1_code":"NIR",
    "gn:admin2_code":"N09000005",
    "gn:asciiname":"Ballymagorry",
    "gn:country_code":"GB",
    "gn:dem":22,
    "gn:feature_class":"P",
    "gn:feature_code":"PPL",
    "gn:name":"Ballymagorry",
    "gn:population":0,
    "gn:timezone":"Europe/London",
    "iso:country":"GB",
    "name:eus_x_preferred":[
        "Ballymagorry"
    ],
    "name:ita_x_preferred":[
        "Ballymagorry"
    ],
    "name:msa_x_preferred":[
        "Ballymagorry"
    ],
    "name:pli_x_preferred":[
        "\u092c\u0932\u094d\u0932\u094d\u092f\u094d\u092e\u093e\u0917\u094b\u0930\u094d\u0930\u0940"
    ],
    "name:spa_x_preferred":[
        "Ballymagorry"
    ],
    "wof:name":"Ballymagorry",
    "wof:placetype":"locality"
},
  "geometry": {"coordinates":[-7.43333,54.85],"type":"Point"}
}