{
  "type": "Feature",
  "properties": {
    "gn:admin1_code":"ENG",
    "gn:admin2_code":"F2",
    "gn:admin3_code":"24UC",
    "gn:admin4_code":"24UC025",
    "gn:asciiname":"West Liss",
    "gn:country_code":"GB",
    "gn:dem":72,
    "gn:feature_class":"P",
    "gn:feature_code":"PPL",
    "gn:name":"West Liss",
    "gn:population":0,
    "gn:timezone":"Europe/London",
    "iso:country":"GB",
    "name:cym_x_preferred":[
        "West Liss"
    ],
    "name:pol_x_preferred":[
        "West Liss"
    ],
    "wof:name":"West Liss",
    "wof:placetype":"neighbourhood"
},
  "geometry": {"coordinates":[-0.90028,51.04865],"type":"Point"}
}