{
  "type": "Feature",
  "properties": {
    "iso:country":"GB",
    "name:cym_x_preferred":[
        "Y Mynydd Bychan"
    ],
    "name:eng_x_preferred":[
        "Heath"
    ],
    "wof:name":"Heath",
    "wof:placetype":"neighbourhood"
},
  "geometry": {"coordinates":[-3.19190423554489,51.51369122258103],"type":"Point"}
}