{
  "type": "Feature",
  "properties": {
    "gn:admin1_code": "ENG",
    "gn:admin2_code": "N7",
    "gn:admin3_code": "43UK",
    "gn:admin4_code": "43UK010",
    "gn:asciiname": "South Nutfield",
    "gn:country_code": "GB",
    "gn:dem": 72,
    "gn:feature_class": "P",
    "gn:feature_code": "PPL",
    "gn:name": "South Nutfield",
    "gn:population": 0,
    "gn:timezone": "Europe/London",
    "iso:country": "GB",
    "wof:name": "South Nutfield",
    "wof:placetype": "neighbourhood"
  },
  "geometry": {"coordinates":[-0.13218,51.22506],"type":"Point"}
}
