{
  "type": "Feature",
  "properties": {
    "iso:country":"GB",
    "name:eng_x_preferred":[
        "Joyce Green"
    ],
    "qs:gn_adm0_cc":"GB",
    "qs:gn_local":2651500,
    "qs:gn_nam_loc":"dartford",
    "qs:gn_namadm1":"ENG",
    "qs:local_max":9078,
    "qs:local_sum":15534,
    "qs:localhoods":4,
    "qs:name":"Joyce Green",
    "qs:name_adm0":"United Kingdom",
    "qs:name_adm1":"England",
    "qs:name_adm2":"Kent",
    "qs:name_lau":"Dartford Borough",
    "qs:name_local":"Dartford",
    "qs:photo_max":87,
    "qs:photo_sum":1412,
    "qs:placetype":"Suburb",
    "qs:quad_count":138,
    "qs:woe_adm0":23424975,
    "qs:woe_adm1":24554868,
    "qs:woe_adm2":12602173,
    "qs:woe_lau":12695987,
    "qs:woe_local":17953,
    "qs:woe_ver":"7.10.0",
    "wd:wordcount":36,
    "wof:lang":[
        "eng"
    ],
    "wof:name":"Joyce Green",
    "wof:placetype":"neighbourhood"
},
  "geometry": {"coordinates":[0.230907,51.454761],"type":"Point"}
}