{
  "type": "Feature",
  "properties": {
    "gn:admin1_code":"ENG",
    "gn:admin2_code":"P6",
    "gn:admin3_code":"45UD",
    "gn:admin4_code":"45UD008",
    "gn:asciiname":"West Burton",
    "gn:country_code":"GB",
    "gn:dem":31,
    "gn:feature_class":"P",
    "gn:feature_code":"PPL",
    "gn:name":"West Burton",
    "gn:population":0,
    "gn:timezone":"Europe/London",
    "iso:country":"GB",
    "name:ceb_x_preferred":[
        "West Burton"
    ],
    "name:pol_x_preferred":[
        "West Burton"
    ],
    "name:swe_x_preferred":[
        "West Burton"
    ],
    "wof:name":"West Burton",
    "wof:placetype":"neighbourhood"
},
  "geometry": {"coordinates":[-0.58399,50.91499],"type":"Point"}
}