{
  "type": "Feature",
  "properties": {
    "iso:country":"GB",
    "name:eng_x_preferred":[
        "Brenish"
    ],
    "name:eus_x_preferred":[
        "Brenish"
    ],
    "name:fra_x_preferred":[
        "Brenish"
    ],
    "name:gle_x_preferred":[
        "Br\u00e9inis"
    ],
    "name:nld_x_preferred":[
        "Brenish"
    ],
    "qs_pg:aaroncc":"GB",
    "qs_pg:name":"Brenish",
    "qs_pg:name_adm0":"United Kingdom",
    "qs_pg:name_adm1":"Scotland",
    "qs_pg:photos":46,
    "qs_pg:photos_1k":9,
    "qs_pg:photos_9k":1,
    "qs_pg:photos_9r":2,
    "qs_pg:photos_all":46,
    "qs_pg:photos_sr":2,
    "qs_pg:pop_sr":0,
    "qs_pg:qs_pg_placetype":"locality",
    "qs_pg:qs_pg_placetype_gp":"Town",
    "qs_pg:woe_adm0":23424975,
    "woe:adm0_id":23424975,
    "woe:name_adm0":"United Kingdom",
    "woe:name_adm1":"Scotland",
    "woe:placetype":"Town",
    "wof:name":"Brenish",
    "wof:placetype":"locality"
},
  "geometry": {"coordinates":[-7.111222,58.119016],"type":"Point"}
}