{
  "type": "Feature",
  "properties": {
    "iso:country":"GB",
    "name:ceb_x_preferred":[
        "Cardiff Bay"
    ],
    "name:cor_x_preferred":[
        "Baya Kardydh"
    ],
    "name:cym_x_preferred":[
        "Bae Caerdydd"
    ],
    "name:deu_x_preferred":[
        "Cardiff Bay"
    ],
    "name:eng_x_preferred":[
        "Cardiff Bay"
    ],
    "name:eng_x_variant":[
        "The Bay",
        "Waterfront City"
    ],
    "name:epo_x_preferred":[
        "Kardifa Golfo"
    ],
    "name:eus_x_preferred":[
        "Cardiffko badia"
    ],
    "name:eus_x_variant":[
        "Atlantic Wharf"
    ],
    "name:nld_x_preferred":[
        "Cardiff Bay"
    ],
    "name:spa_x_preferred":[
        "Bah\u00eda de Cardiff"
    ],
    "name:swe_x_preferred":[
        "Cardiff Bay"
    ],
    "name:unk_x_variant":[
        "Cardiff Bay"
    ],
    "name:zho_x_preferred":[
        "\u52a0\u7684\u592b\u7063"
    ],
    "name:zho_x_variant":[
        "\u52a0\u8fea\u592b\u7063"
    ],
    "qs:gn_adm0_cc":"GB",
    "qs:gn_local":2653822,
    "qs:gn_nam_loc":"Cardiff, Cardiff, Cardiff, Wales, GB",
    "qs:gn_namadm1":"WLS",
    "qs:local_max":5000,
    "qs:local_sum":46092,
    "qs:localhoods":22,
    "qs:name":"Cardiff Bay",
    "qs:name_adm0":"United Kingdom",
    "qs:name_adm1":"Wales",
    "qs:name_adm2":"Cardiff County",
    "qs:name_lau":"Cardiff County",
    "qs:name_local":"Cardiff",
    "qs:photo_max":1117,
    "qs:photo_sum":4139,
    "qs:placetype":"Suburb",
    "qs:quad_count":43,
    "qs:woe_adm0":23424975,
    "qs:woe_adm1":12578049,
    "qs:woe_adm2":12602215,
    "qs:woe_lau":12696132,
    "qs:woe_local":15127,
    "qs:woe_ver":"7.10.0",
    "wd:wordcount":1853,
    "wof:lang":[
        "eng"
    ],
    "wof:name":"Cardiff Bay",
    "wof:placetype":"neighbourhood"
},
  "geometry": {"coordinates":[-3.157137,51.464677],"type":"Point"}
}