{
  "type": "Feature",
  "properties": {
    "gn:admin1_code":"ENG",
    "gn:admin2_code":"E4",
    "gn:admin3_code":"22UQ",
    "gn:admin4_code":"22UQ047",
    "gn:asciiname":"The Downs",
    "gn:country_code":"GB",
    "gn:dem":77,
    "gn:feature_class":"P",
    "gn:feature_code":"PPL",
    "gn:name":"The Downs",
    "gn:population":0,
    "gn:timezone":"Europe/London",
    "iso:country":"GB",
    "wof:name":"The Downs",
    "wof:placetype":"neighbourhood"
},
  "geometry": {"coordinates":[0.40915,51.89686],"type":"Point"}
}