{
  "type": "Feature",
  "properties": {
    "gn:country":"GB",
    "gn:fcode":"PPL",
    "gn:population":0,
    "iso:country":"GB",
    "name:cym_x_preferred":[
        "Pengelli"
    ],
    "name:eng_x_preferred":[
        "Grovesend"
    ],
    "name:eus_x_preferred":[
        "Grovesend"
    ],
    "name:fra_x_preferred":[
        "Grovesend"
    ],
    "name:gle_x_preferred":[
        "Pengelli"
    ],
    "name:nan_x_preferred":[
        "Grovesend"
    ],
    "name:nld_x_preferred":[
        "Grovesend"
    ],
    "name:spa_x_preferred":[
        "Grovesend"
    ],
    "qs_pg:aaroncc":"GB",
    "qs_pg:gn_country":"GB",
    "qs_pg:gn_fcode":"PPL",
    "qs_pg:gn_pop":0,
    "qs_pg:name":"Groeswen",
    "qs_pg:name_adm0":"United Kingdom",
    "qs_pg:name_adm1":"Wales",
    "qs_pg:photos":7,
    "qs_pg:photos_1k":1,
    "qs_pg:photos_9k":1,
    "qs_pg:photos_9r":1,
    "qs_pg:photos_all":7,
    "qs_pg:photos_sr":1,
    "qs_pg:pop_sr":0,
    "qs_pg:qs_pg_placetype":"locality",
    "qs_pg:qs_pg_placetype_gp":"Town",
    "qs_pg:woe_adm0":23424975,
    "woe:adm0_id":23424975,
    "woe:name_adm0":"United Kingdom",
    "woe:name_adm1":"Wales",
    "woe:placetype":"Town",
    "wof:name":"Groeswen",
    "wof:placetype":"neighbourhood",
    "wof:population":1131
},
  "geometry": {"coordinates":[-4.03833,51.68472],"type":"Point"}
}