{
  "type": "Feature",
  "properties": {
    "gn:admin1_code": "SCT",
    "gn:admin2_code": "V3",
    "gn:asciiname": "Highland",
    "gn:country_code": "GB",
    "gn:dem": 3,
    "gn:feature_class": "P",
    "gn:feature_code": "PPLA2",
    "gn:name": "Highland",
    "gn:population": 0,
    "gn:timezone": "Europe/London",
    "iso:country": "GB",
    "name:ara_x_preferred": [
      "مرتفعات"
    ],
    "name:bar_x_preferred": [
      "Highlands"
    ],
    "name:bel_x_preferred": [
      "Узвышша"
    ],
    "name:bul_x_preferred": [
      "Планинска земя"
    ],
    "name:ces_x_preferred": [
      "Vysočina"
    ],
    "name:dan_x_preferred": [
      "Højland"
    ],
    "name:deu_x_preferred": [
      "Hochland"
    ],
    "name:ell_x_preferred": [
      "Υψίπεδο"
    ],
    "name:est_x_preferred": [
      "Mägismaa"
    ],
    "name:fas_x_preferred": [
      "کوهسار"
    ],
    "name:fry_x_preferred": [
      "Heechflakte"
    ],
    "name:hye_x_preferred": [
      "Բարձրավանդակ"
    ],
    "name:ilo_x_preferred": [
      "Tangkig"
    ],
    "name:isl_x_preferred": [
      "Hálendi"
    ],
    "name:kat_x_preferred": [
      "მაღლობი"
    ],
    "name:mal_x_preferred": [
      "ഉന്നതമേഖല"
    ],
    "name:nld_x_preferred": [
      "Hoogvlakte"
    ],
    "name:nno_x_preferred": [
      "Høgland"
    ],
    "name:nor_x_preferred": [
      "Høyland"
    ],
    "name:pol_x_preferred": [
      "Wyżyna"
    ],
    "name:por_x_preferred": [
      "Terras altas"
    ],
    "name:rus_x_preferred": [
      "Нагорье"
    ],
    "name:sco_x_preferred": [
      "Hieland"
    ],
    "name:slk_x_preferred": [
      "Vysočina"
    ],
    "name:srp_x_preferred": [
      "Висија"
    ],
    "name:swe_x_preferred": [
      "Högland"
    ],
    "name:tgl_x_preferred": [
      "Paltok"
    ],
    "name:tur_x_preferred": [
      "Dağlık"
    ],
    "name:ukr_x_preferred": [
      "Нагір'я"
    ],
    "name:vie_x_preferred": [
      "Sơn nguyên"
    ],
    "name:xmf_x_preferred": [
      "ზუკი"
    ],
    "wof:name": "Highland",
    "wof:placetype": "locality"
  },
  "geometry": {"coordinates":[-4.22823,57.48566],"type":"Point"}
}
