{
  "type": "Feature",
  "properties": {
    "gn:admin1_code":"SCT",
    "gn:admin2_code":"V3",
    "gn:asciiname":"Highland",
    "gn:country_code":"GB",
    "gn:dem":3,
    "gn:feature_class":"P",
    "gn:feature_code":"PPLA2",
    "gn:name":"Highland",
    "gn:population":0,
    "gn:timezone":"Europe/London",
    "iso:country":"GB",
    "wof:name":"Highland",
    "wof:placetype":"locality"
},
  "geometry": {"coordinates":[-4.22823,57.48566],"type":"Point"}
}