{
  "type": "Feature",
  "properties": {
    "iso:country":"GB",
    "name:eng_x_preferred":[
        "Jewellery Quarter"
    ],
    "name:ita_x_preferred":[
        "Quartiere dei Gioiellieri"
    ],
    "name:jpn_x_preferred":[
        "\u30b8\u30e5\u30a8\u30e9\u30ea\u30fc\u30fb\u30af\u30a9\u30fc\u30bf\u30fc"
    ],
    "name:nld_x_preferred":[
        "Jewellery Quarter"
    ],
    "name:zho_x_preferred":[
        "\u73e0\u5bf6\u5340"
    ],
    "wd:wordcount":10153,
    "wof:name":"Jewellery Quarter",
    "wof:placetype":"neighbourhood"
},
  "geometry": {"coordinates":[-1.910392,52.486817],"type":"Point"}
}