{
  "type": "Feature",
  "properties": {
    "gn:admin1_code": "ENG",
    "gn:admin2_code": "F7",
    "gn:admin3_code": "00GA099",
    "gn:asciiname": "Hergest",
    "gn:country_code": "GB",
    "gn:dem": 210,
    "gn:feature_class": "P",
    "gn:feature_code": "PPL",
    "gn:name": "Hergest",
    "gn:population": 0,
    "gn:timezone": "Europe/London",
    "iso:country": "GB",
    "name:cym_x_preferred": [
      "Hergest"
    ],
    "name:deu_x_preferred": [
      "Hergest"
    ],
    "name:fra_x_preferred": [
      "Hergest"
    ],
    "wof:name": "Hergest",
    "wof:placetype": "neighbourhood"
  },
  "geometry": {"coordinates":[-3.08333,52.18333],"type":"Point"}
}
