{
  "type": "Feature",
  "properties": {
    "iso:country":"GB",
    "name:eng_x_preferred":[
        "Charlestown"
    ],
    "name:eus_x_preferred":[
        "Charlestown"
    ],
    "name:nld_x_preferred":[
        "Charlestown"
    ],
    "name:urd_x_preferred":[
        "\u0686\u0627\u0631\u0644\u0633 \u0679\u0627\u0624\u0646\u060c \u0628\u0644\u06cc\u06a9 \u0622\u0626\u0644"
    ],
    "name:urd_x_variant":[
        "\u0686\u0627\u0631\u0644\u0633 \u0679\u0627\u0624\u0646"
    ],
    "qs_pg:aaroncc":"GB",
    "qs_pg:name":"Charleston",
    "qs_pg:name_adm0":"United Kingdom",
    "qs_pg:name_adm1":"Scotland",
    "qs_pg:photos":38,
    "qs_pg:photos_1k":8,
    "qs_pg:photos_9k":1,
    "qs_pg:photos_9r":2,
    "qs_pg:photos_all":38,
    "qs_pg:photos_sr":2,
    "qs_pg:pop_sr":0,
    "qs_pg:qs_pg_placetype":"locality",
    "qs_pg:qs_pg_placetype_gp":"Town",
    "qs_pg:woe_adm0":23424975,
    "woe:adm0_id":23424975,
    "woe:name_adm0":"United Kingdom",
    "woe:name_adm1":"Scotland",
    "woe:placetype":"Town",
    "wof:name":"Charleston",
    "wof:placetype":"locality"
},
  "geometry": {"coordinates":[-4.2709775,57.5041085],"type":"Point"}
}