{
  "type": "Feature",
  "properties": {
    "gn:country":"GB",
    "iso:country":"GB",
    "name:cym_x_preferred":[
        "Lydstep"
    ],
    "name:eng_x_preferred":[
        "Lydstep Haven"
    ],
    "name:fra_x_preferred":[
        "Lydstep Haven"
    ],
    "name:gle_x_preferred":[
        "Lydstep"
    ],
    "name:jpn_x_preferred":[
        "\u30ea\u30c3\u30c9\u30b9\u30c6\u30c3\u30d7\u30fb\u30d8\u30a4\u30d6\u30f3"
    ],
    "name:nld_x_preferred":[
        "Lydstep Haven"
    ],
    "qs_pg:aaroncc":"GB",
    "qs_pg:gn_country":"GB",
    "qs_pg:name":"Lydstep Haven",
    "qs_pg:name_adm0":"United Kingdom",
    "qs_pg:name_adm1":"Wales",
    "qs_pg:photos":195,
    "qs_pg:photos_1k":40,
    "qs_pg:photos_9k":1,
    "qs_pg:photos_9r":4,
    "qs_pg:photos_all":195,
    "qs_pg:photos_sr":4,
    "qs_pg:pop_sr":0,
    "qs_pg:qs_pg_placetype":"locality",
    "qs_pg:qs_pg_placetype_gp":"Town",
    "qs_pg:woe_adm0":23424975,
    "woe:adm0_id":23424975,
    "woe:name_adm0":"United Kingdom",
    "woe:name_adm1":"Wales",
    "woe:placetype":"Town",
    "wof:name":"Lydstep Haven",
    "wof:placetype":"neighbourhood"
},
  "geometry": {"coordinates":[-4.766006,51.644228],"type":"Point"}
}