{
  "type": "Feature",
  "properties": {
    "iso:country": "GB",
    "name:bul_x_preferred": [
      "Бардсей"
    ],
    "name:ceb_x_preferred": [
      "Bardsey"
    ],
    "name:deu_x_preferred": [
      "Bardsey"
    ],
    "name:eng_x_preferred": [
      "Bardsey"
    ],
    "name:fas_x_preferred": [
      "بارادسی"
    ],
    "name:fra_x_preferred": [
      "Bardsey"
    ],
    "name:gle_x_preferred": [
      "Bardsey"
    ],
    "name:nld_x_preferred": [
      "Bardsey"
    ],
    "name:pol_x_preferred": [
      "Bardsey"
    ],
    "name:spa_x_preferred": [
      "Bardsey"
    ],
    "name:swe_x_preferred": [
      "Bardsey"
    ],
    "qs_pg:aaroncc": "GB",
    "qs_pg:name": "Bardsey",
    "qs_pg:name_adm0": "United Kingdom",
    "qs_pg:name_adm1": "England",
    "qs_pg:photos": 110,
    "qs_pg:photos_1k": 22,
    "qs_pg:photos_9k": 1,
    "qs_pg:photos_9r": 3,
    "qs_pg:photos_all": 110,
    "qs_pg:photos_sr": 3,
    "qs_pg:pop_sr": 0,
    "qs_pg:qs_pg_placetype": "locality",
    "qs_pg:qs_pg_placetype_gp": "Town",
    "qs_pg:woe_adm0": 23424975,
    "woe:adm0_id": 23424975,
    "woe:name_adm0": "United Kingdom",
    "woe:name_adm1": "England",
    "woe:placetype": "Town",
    "wof:name": "Bardsey",
    "wof:placetype": "neighbourhood"
  },
  "geometry": {"coordinates":[-1.445946,53.88355],"type":"Point"}
}
