{
  "type": "Feature",
  "properties": {
    "gn:admin1_code": "SCT",
    "gn:admin2_code": "T5",
    "gn:asciiname": "Mains of Dyce",
    "gn:country_code": "GB",
    "gn:dem": 38,
    "gn:feature_class": "P",
    "gn:feature_code": "PPLL",
    "gn:name": "Mains of Dyce",
    "gn:population": 0,
    "gn:timezone": "Europe/London",
    "iso:country": "GB",
    "wof:name": "Mains of Dyce",
    "wof:placetype": "locality"
  },
  "geometry": {"coordinates":[-2.18534,57.21554],"type":"Point"}
}
