{
  "type": "Feature",
  "properties": {
    "iso:country":"GB",
    "name:eng_x_preferred":[
        "Lower Pilsley"
    ],
    "name:pol_x_preferred":[
        "Lower Pilsley"
    ],
    "name:spa_x_preferred":[
        "Lower Pilsley"
    ],
    "qs_pg:aaroncc":"GB",
    "qs_pg:name":"Lower Pilsley",
    "qs_pg:name_adm0":"United Kingdom",
    "qs_pg:name_adm1":"England",
    "qs_pg:photos":122,
    "qs_pg:photos_1k":25,
    "qs_pg:photos_9k":1,
    "qs_pg:photos_9r":3,
    "qs_pg:photos_all":122,
    "qs_pg:photos_sr":3,
    "qs_pg:pop_sr":0,
    "qs_pg:qs_pg_placetype":"locality",
    "qs_pg:qs_pg_placetype_gp":"Town",
    "qs_pg:woe_adm0":23424975,
    "woe:adm0_id":23424975,
    "woe:name_adm0":"United Kingdom",
    "woe:name_adm1":"England",
    "woe:placetype":"Town",
    "wof:name":"Lower Pilsley",
    "wof:placetype":"neighbourhood"
},
  "geometry": {"coordinates":[-1.389491,53.161985],"type":"Point"}
}