{
  "type": "Feature",
  "properties": {
    "gn:population":1169,
    "iso:country":"GB",
    "name:ast_x_preferred":[
        "Beauly"
    ],
    "name:bre_x_preferred":[
        "A' Mhanachainn"
    ],
    "name:bre_x_variant":[
        "A Mhanachainn"
    ],
    "name:bul_x_preferred":[
        "\u0411\u0435\u0430\u0443\u043b\u0439"
    ],
    "name:cat_x_preferred":[
        "Beauly"
    ],
    "name:ceb_x_preferred":[
        "Beauly"
    ],
    "name:cym_x_preferred":[
        "Beauly"
    ],
    "name:deu_x_preferred":[
        "Beauly"
    ],
    "name:eng_x_preferred":[
        "Beauly"
    ],
    "name:eus_x_preferred":[
        "Beauly"
    ],
    "name:fas_x_preferred":[
        "\u0628\u0648\u0644\u06cc"
    ],
    "name:gla_x_preferred":[
        "A' Mhanachainn"
    ],
    "name:gla_x_variant":[
        "A Mhanachainn"
    ],
    "name:gle_x_preferred":[
        "A' Mhanachainn"
    ],
    "name:gle_x_variant":[
        "A Mhanachainn"
    ],
    "name:hbs_x_preferred":[
        "Beauly"
    ],
    "name:heb_x_preferred":[
        "\u05d1\u05d9\u05d9\u05d5\u05dc\u05d9"
    ],
    "name:ita_x_preferred":[
        "Beauly"
    ],
    "name:jpn_x_preferred":[
        "\u30d3\u30e5\u30fc\u30ea\u30fc"
    ],
    "name:nld_x_preferred":[
        "Beauly"
    ],
    "name:nno_x_preferred":[
        "Beauly"
    ],
    "name:nob_x_preferred":[
        "Beauly"
    ],
    "name:nor_x_preferred":[
        "Beauly"
    ],
    "name:pol_x_preferred":[
        "Beauly"
    ],
    "name:sco_x_preferred":[
        "Beauly"
    ],
    "name:spa_x_preferred":[
        "Beauly"
    ],
    "name:swe_x_preferred":[
        "Beauly"
    ],
    "name:zho_x_preferred":[
        "\u6bd4\u5c24\u5229"
    ],
    "qs:a0":"United Kingdom",
    "qs:a1":"*Highland",
    "qs:a1_lc":"GB11QT0000",
    "qs:a1r":"0Scotland",
    "qs:a1r_lc":"GB11000000",
    "qs:adm0":"United Kingdom",
    "qs:la_lc":"*",
    "qs:level":"locality",
    "qs:loc":"Beauly",
    "qs:loc_alt":"Beauly",
    "qs:pop":0,
    "qs:type":"buffered point",
    "wd:wordcount":792,
    "wof:lang":[
        "eng"
    ],
    "wof:name":"Beauly",
    "wof:placetype":"locality",
    "wof:population":1169
},
  "geometry": {"coordinates":[-4.460822,57.48359],"type":"Point"}
}