{
  "type": "Feature",
  "properties": {
    "gn:admin1_code":"WLS",
    "gn:admin2_code":"X3",
    "gn:admin3_code":"00PB005",
    "gn:asciiname":"Heol-y-Cyw",
    "gn:country_code":"GB",
    "gn:dem":96,
    "gn:feature_class":"P",
    "gn:feature_code":"PPL",
    "gn:name":"Heol-y-Cyw",
    "gn:population":538,
    "gn:timezone":"Europe/London",
    "iso:country":"GB",
    "name:cym_x_preferred":[
        "Heol-y-cyw"
    ],
    "name:eus_x_preferred":[
        "Heol-y-Cyw"
    ],
    "name:spa_x_preferred":[
        "Heol-y-Cyw"
    ],
    "name:swe_x_preferred":[
        "Heol-y-Cyw"
    ],
    "wof:name":"Heol-y-Cyw",
    "wof:placetype":"neighbourhood",
    "wof:population":538
},
  "geometry": {"coordinates":[-3.52243,51.54743],"type":"Point"}
}