{
  "type": "Feature",
  "properties": {
    "gn:country":"GB",
    "gn:fcode":"PPL",
    "gn:population":0,
    "iso:country":"GB",
    "name:cym_x_preferred":[
        "Penpont"
    ],
    "name:deu_x_preferred":[
        "Penpont"
    ],
    "name:eng_x_preferred":[
        "Penpont"
    ],
    "name:eus_x_preferred":[
        "Penpont"
    ],
    "name:fra_x_preferred":[
        "Penpont"
    ],
    "name:gla_x_preferred":[
        "Penpont"
    ],
    "name:gle_x_preferred":[
        "Penpont"
    ],
    "name:jpn_x_preferred":[
        "\u30da\u30f3\u30dd\u30f3\u30c8"
    ],
    "name:nld_x_preferred":[
        "Penpont"
    ],
    "name:rus_x_preferred":[
        "\u041f\u0435\u043d\u043f\u043e\u043d\u0442"
    ],
    "qs_pg:aaroncc":"GB",
    "qs_pg:gn_country":"GB",
    "qs_pg:gn_fcode":"PPL",
    "qs_pg:gn_pop":0,
    "qs_pg:name":"Penpont",
    "qs_pg:name_adm0":"United Kingdom",
    "qs_pg:name_adm1":"Scotland",
    "qs_pg:photos":38,
    "qs_pg:photos_1k":8,
    "qs_pg:photos_9k":1,
    "qs_pg:photos_9r":2,
    "qs_pg:photos_all":38,
    "qs_pg:photos_sr":2,
    "qs_pg:pop_sr":0,
    "qs_pg:qs_pg_placetype":"locality",
    "qs_pg:qs_pg_placetype_gp":"Town",
    "qs_pg:woe_adm0":23424975,
    "woe:adm0_id":23424975,
    "woe:name_adm0":"United Kingdom",
    "woe:name_adm1":"Scotland",
    "woe:placetype":"Town",
    "wof:name":"Penpont",
    "wof:placetype":"locality"
},
  "geometry": {"coordinates":[-3.81667,55.23333],"type":"Point"}
}