{
  "type": "Feature",
  "properties": {
    "gn:population":1554,
    "iso:country":"GB",
    "name:ceb_x_preferred":[
        "Mickleton"
    ],
    "name:cym_x_preferred":[
        "Mickleton"
    ],
    "name:eng_x_preferred":[
        "Mickleton"
    ],
    "name:fra_x_preferred":[
        "Mickleton"
    ],
    "name:gle_x_preferred":[
        "Mickleton"
    ],
    "name:nld_x_preferred":[
        "Mickleton"
    ],
    "name:pol_x_preferred":[
        "Mickleton"
    ],
    "name:por_x_preferred":[
        "Mickleton"
    ],
    "name:spa_x_preferred":[
        "Mickleton"
    ],
    "name:swe_x_preferred":[
        "Mickleton"
    ],
    "qs:a0":"United Kingdom",
    "qs:a1":"*Gloucestershire",
    "qs:a1_lc":"GB12230000",
    "qs:a1r":"0England",
    "qs:a1r_lc":"GB12000000",
    "qs:adm0":"United Kingdom",
    "qs:la_lc":"*",
    "qs:level":"locality",
    "qs:loc":"Mickleton",
    "qs:loc_alt":"Mickleton",
    "qs:pop":0,
    "qs:type":"buffered point",
    "wd:wordcount":28,
    "wof:lang":[
        "eng"
    ],
    "wof:name":"Mickleton",
    "wof:placetype":"neighbourhood",
    "wof:population":1554
},
  "geometry": {"coordinates":[-1.766681,52.090096],"type":"Point"}
}