{
  "type": "Feature",
  "properties": {
    "gn:country":"GB",
    "gn:fcode":"PPL",
    "gn:population":0,
    "iso:country":"GB",
    "name:bul_x_preferred":[
        "\u041f\u0435\u043d\u0441\u0444\u043e\u0440\u0434"
    ],
    "name:cat_x_preferred":[
        "Pensford"
    ],
    "name:ceb_x_preferred":[
        "Pensford"
    ],
    "name:cym_x_preferred":[
        "Pensford"
    ],
    "name:eng_x_preferred":[
        "Pensford"
    ],
    "name:epo_x_preferred":[
        "Pensford"
    ],
    "name:fas_x_preferred":[
        "\u067e\u0646\u0633\u0641\u0648\u0631\u062f"
    ],
    "name:fra_x_preferred":[
        "Pensford"
    ],
    "name:gle_x_preferred":[
        "Pensford"
    ],
    "name:ind_x_preferred":[
        "Pensford"
    ],
    "name:nld_x_preferred":[
        "Pensford"
    ],
    "name:nno_x_preferred":[
        "Pensford"
    ],
    "name:nob_x_preferred":[
        "Pensford"
    ],
    "name:pol_x_preferred":[
        "Pensford"
    ],
    "name:rus_x_preferred":[
        "\u041f\u0435\u043d\u0441\u0444\u043e\u0440\u0434"
    ],
    "name:spa_x_preferred":[
        "Pensford"
    ],
    "name:swe_x_preferred":[
        "Pensford"
    ],
    "name:ukr_x_preferred":[
        "\u041f\u0435\u043d\u0441\u0444\u043e\u0440\u0434"
    ],
    "name:zho_x_preferred":[
        "\u5f6d\u65af\u798f\u5fb7"
    ],
    "qs_pg:aaroncc":"GB",
    "qs_pg:gn_country":"GB",
    "qs_pg:gn_fcode":"PPL",
    "qs_pg:gn_pop":0,
    "qs_pg:name":"Pensford",
    "qs_pg:name_adm0":"United Kingdom",
    "qs_pg:name_adm1":"England",
    "qs_pg:photos":80,
    "qs_pg:photos_1k":16,
    "qs_pg:photos_9k":1,
    "qs_pg:photos_9r":3,
    "qs_pg:photos_all":80,
    "qs_pg:photos_sr":3,
    "qs_pg:pop_sr":0,
    "qs_pg:qs_pg_placetype":"locality",
    "qs_pg:qs_pg_placetype_gp":"Town",
    "qs_pg:woe_adm0":23424975,
    "woe:adm0_id":23424975,
    "woe:name_adm0":"United Kingdom",
    "woe:name_adm1":"England",
    "woe:placetype":"Town",
    "wof:name":"Pensford",
    "wof:placetype":"neighbourhood",
    "wof:population":870
},
  "geometry": {"coordinates":[-2.54722,51.37111],"type":"Point"}
}