{
  "type": "Feature",
  "properties": {
    "iso:country": "GB",
    "name:cym_x_preferred": [
      "Pontprennau"
    ],
    "name:eng_x_preferred": [
      "Pontprennau"
    ],
    "wof:name": "Pontprennau",
    "wof:placetype": "neighbourhood"
  },
  "geometry": {"coordinates":[-3.14063467849847,51.53579959659726],"type":"Point"}
}
