{
  "type": "Feature",
  "properties": {
    "gn:population": 3846,
    "iso:country": "GB",
    "name:ceb_x_preferred": [
      "Whitwell"
    ],
    "name:cym_x_preferred": [
      "Whitwell"
    ],
    "name:eng_x_preferred": [
      "Whitwell"
    ],
    "name:fas_x_preferred": [
      "وایتول"
    ],
    "name:ita_x_preferred": [
      "Whitwell"
    ],
    "name:nld_x_preferred": [
      "Whitwell"
    ],
    "name:pol_x_preferred": [
      "Whitwell"
    ],
    "name:spa_x_preferred": [
      "Whitwell"
    ],
    "name:swe_x_preferred": [
      "Whitwell"
    ],
    "qs:a0": "United Kingdom",
    "qs:a1": "*Derbyshire",
    "qs:a1_lc": "GB12170000",
    "qs:a1r": "0England",
    "qs:a1r_lc": "GB12000000",
    "qs:adm0": "United Kingdom",
    "qs:la_lc": "*",
    "qs:level": "locality",
    "qs:loc": "Whitwell",
    "qs:loc_alt": "Whitwell",
    "qs:pop": 0,
    "qs:type": "buffered point",
    "wd:wordcount": 674,
    "wof:lang": [
      "eng"
    ],
    "wof:name": "Whitwell",
    "wof:placetype": "neighbourhood",
    "wof:population": 3846
  },
  "geometry": {"coordinates":[-1.209256,53.288672],"type":"Point"}
}
