{
  "type": "Feature",
  "properties": {
    "iso:country":"GB",
    "name:cym_x_preferred":[
        "Lexden"
    ],
    "name:eng_x_preferred":[
        "Lexden"
    ],
    "name:fra_x_preferred":[
        "Lexden"
    ],
    "name:nld_x_preferred":[
        "Lexden"
    ],
    "name:pol_x_preferred":[
        "Lexden"
    ],
    "qs:gn_adm0_cc":"GB",
    "qs:gn_fcode":"PPL",
    "qs:gn_local":2652618,
    "qs:gn_nam_loc":"colchester",
    "qs:gn_namadm1":"ENG",
    "qs:gn_name":"Lexden",
    "qs:local_max":3394,
    "qs:local_sum":11691,
    "qs:localhoods":7,
    "qs:name":"Lexden",
    "qs:name_adm0":"United Kingdom",
    "qs:name_adm1":"England",
    "qs:name_adm2":"Essex",
    "qs:name_lau":"Colchester Borough",
    "qs:name_local":"Colchester",
    "qs:photo_max":159,
    "qs:photo_sum":853,
    "qs:placetype":"Suburb",
    "qs:quad_count":46,
    "qs:woe_adm0":23424975,
    "qs:woe_adm1":24554868,
    "qs:woe_adm2":12602168,
    "qs:woe_lau":12695945,
    "qs:woe_local":16545,
    "qs:woe_ver":"7.10.0",
    "wd:wordcount":971,
    "wof:lang":[
        "eng"
    ],
    "wof:name":"Lexden",
    "wof:placetype":"neighbourhood"
},
  "geometry": {"coordinates":[0.860001,51.888786],"type":"Point"}
}