{
  "type": "Feature",
  "properties": {
    "gn:gn_country":"GB",
    "gn:gn_fcode":"PPL",
    "gn:gn_pop":0,
    "iso:country":"GB",
    "name:cym_x_preferred":[
        "Dalmeny"
    ],
    "name:eng_x_preferred":[
        "Dalmeny"
    ],
    "name:eus_x_preferred":[
        "Dalmeny"
    ],
    "name:fra_x_preferred":[
        "Dalmeny"
    ],
    "name:gla_x_preferred":[
        "Dail Mheinidh"
    ],
    "name:gle_x_preferred":[
        "Dail Mheinidh"
    ],
    "name:jpn_x_preferred":[
        "\u30c0\u30eb\u30e1\u30cb\u30fc"
    ],
    "name:nld_x_preferred":[
        "Dalmeny"
    ],
    "name:sco_x_preferred":[
        "Dalmeny"
    ],
    "name:urd_x_preferred":[
        "\u062c\u0646\u0648\u0628\u06cc \u06a9\u0648\u0626\u0646\u0632\u0641\u06cc\u0631\u06cc"
    ],
    "qs_pg:aaroncc":"GB",
    "qs_pg:gn_country":"GB",
    "qs_pg:gn_fcode":"PPL",
    "qs_pg:gn_pop":0,
    "qs_pg:name":"Dalmeny",
    "qs_pg:name_adm0":"United Kingdom",
    "qs_pg:name_adm1":"Scotland",
    "qs_pg:photos":506,
    "qs_pg:photos_1k":103,
    "qs_pg:photos_9k":2,
    "qs_pg:photos_9r":5,
    "qs_pg:photos_all":506,
    "qs_pg:photos_sr":7,
    "qs_pg:pop_sr":0,
    "qs_pg:qs_pg_placetype":"locality",
    "qs_pg:qs_pg_placetype_gp":"Town",
    "qs_pg:woe_adm0":23424975,
    "woe:adm0_id":23424975,
    "woe:name_adm0":"United Kingdom",
    "woe:name_adm1":"Scotland",
    "woe:placetype":"Town",
    "wof:name":"Dalmeny",
    "wof:placetype":"neighbourhood"
},
  "geometry": {"coordinates":[-3.37426,55.98139],"type":"Point"}
}