{
  "type": "Feature",
  "properties": {
    "gn:admin1_code": "ENG",
    "gn:admin2_code": "G5",
    "gn:admin3_code": "29UE",
    "gn:admin4_code": "29UE011",
    "gn:asciiname": "Martin",
    "gn:country_code": "GB",
    "gn:dem": 87,
    "gn:feature_class": "P",
    "gn:feature_code": "PPL",
    "gn:name": "Martin",
    "gn:population": 0,
    "gn:timezone": "Europe/London",
    "iso:country": "GB",
    "name:cym_x_preferred": [
      "Martin"
    ],
    "name:pol_x_preferred": [
      "Martin"
    ],
    "wof:name": "Martin",
    "wof:placetype": "neighbourhood"
  },
  "geometry": {"coordinates":[1.34437,51.17453],"type":"Point"}
}
