{
  "type": "Feature",
  "properties": {
    "gn:admin1_code":"ENG",
    "gn:admin2_code":"C6",
    "gn:admin3_code":"00HE073",
    "gn:asciiname":"Upton",
    "gn:country_code":"GB",
    "gn:dem":143,
    "gn:feature_class":"P",
    "gn:feature_code":"PPL",
    "gn:name":"Upton",
    "gn:population":0,
    "gn:timezone":"Europe/London",
    "iso:country":"GB",
    "name:cat_x_preferred":[
        "Upton"
    ],
    "name:ceb_x_preferred":[
        "Upton"
    ],
    "name:ces_x_preferred":[
        "Upton"
    ],
    "name:deu_x_preferred":[
        "Upton"
    ],
    "name:fin_x_preferred":[
        "Upton"
    ],
    "name:fra_x_preferred":[
        "Upton"
    ],
    "name:ita_x_preferred":[
        "Upton"
    ],
    "name:nld_x_preferred":[
        "Upton"
    ],
    "name:pol_x_preferred":[
        "Upton"
    ],
    "name:por_x_preferred":[
        "Upton"
    ],
    "name:rus_x_preferred":[
        "\u0410\u043f\u0442\u043e\u043d"
    ],
    "name:spa_x_preferred":[
        "Upton"
    ],
    "name:srp_x_preferred":[
        "\u0410\u043f\u0442\u043e\u043d"
    ],
    "name:swe_x_preferred":[
        "Upton"
    ],
    "name:vol_x_preferred":[
        "Upton"
    ],
    "wof:name":"Upton",
    "wof:placetype":"neighbourhood"
},
  "geometry": {"coordinates":[-4.43333,50.53333],"type":"Point"}
}