{
  "type": "Feature",
  "properties": {
    "iso:country":"GB",
    "wof:name":"Little London",
    "wof:placetype":"neighbourhood"
},
  "geometry": {"coordinates":[-1.6940329568201,53.8520763393654],"type":"Point"}
}