{
  "type": "Feature",
  "properties": {
    "iso:country":"GB",
    "name:hun_x_preferred":[
        "Little London"
    ],
    "name:pol_x_preferred":[
        "Little London"
    ],
    "name:swe_x_preferred":[
        "Lilla London"
    ],
    "wof:name":"Little London",
    "wof:placetype":"neighbourhood"
},
  "geometry": {"coordinates":[-1.6940329568201,53.8520763393654],"type":"Point"}
}