{
  "type": "Feature",
  "properties": {
    "iso:country":"GB",
    "name:ceb_x_preferred":[
        "Silverdale"
    ],
    "name:deu_x_preferred":[
        "Silverdale"
    ],
    "name:eng_x_preferred":[
        "Silverdale"
    ],
    "name:fra_x_preferred":[
        "Silverdale"
    ],
    "name:ita_x_preferred":[
        "Silverdale"
    ],
    "name:nld_x_preferred":[
        "Silverdale"
    ],
    "name:pol_x_preferred":[
        "Silverdale"
    ],
    "name:spa_x_preferred":[
        "Silverdale"
    ],
    "name:srp_x_preferred":[
        "\u0421\u0438\u043b\u0432\u0435\u0440\u0434\u0435\u0458\u043b"
    ],
    "name:swe_x_preferred":[
        "Silverdale"
    ],
    "name:vol_x_preferred":[
        "Silverdale"
    ],
    "qs:gn_adm0_cc":"GB",
    "qs:gn_fcode":"PPL",
    "qs:gn_local":2641674,
    "qs:gn_nam_loc":"newcastle under lyme",
    "qs:gn_namadm1":"ENG",
    "qs:gn_name":"Silverdale",
    "qs:local_max":3651,
    "qs:local_sum":6037,
    "qs:localhoods":7,
    "qs:name":"Silverdale",
    "qs:name_adm0":"United Kingdom",
    "qs:name_adm1":"England",
    "qs:name_adm2":"Staffordshire",
    "qs:name_lau":"Newcastle-under-Lyme Borough",
    "qs:name_local":"Newcastle under Lyme",
    "qs:photo_max":1556,
    "qs:photo_sum":3651,
    "qs:placetype":"Suburb",
    "qs:quad_count":77,
    "qs:woe_adm0":23424975,
    "qs:woe_adm1":24554868,
    "qs:woe_adm2":12602189,
    "qs:woe_lau":12696075,
    "qs:woe_local":30078,
    "qs:woe_ver":"7.10.0",
    "wd:wordcount":62,
    "wof:lang":[
        "eng"
    ],
    "wof:name":"Silverdale",
    "wof:placetype":"neighbourhood"
},
  "geometry": {"coordinates":[-2.276609,53.00392],"type":"Point"}
}