{
  "type": "Feature",
  "properties": {
    "gn:admin1_code":"WLS",
    "gn:admin2_code":"Y7",
    "gn:admin3_code":"00NS068",
    "gn:asciiname":"Middle Mill",
    "gn:country_code":"GB",
    "gn:dem":28,
    "gn:feature_class":"P",
    "gn:feature_code":"PPL",
    "gn:name":"Middle Mill",
    "gn:population":0,
    "gn:timezone":"Europe/London",
    "iso:country":"GB",
    "wof:name":"Middle Mill",
    "wof:placetype":"neighbourhood"
},
  "geometry": {"coordinates":[-5.18972,51.88778],"type":"Point"}
}