{
  "type": "Feature",
  "properties": {
    "iso:country":"GB",
    "name:eng_x_preferred":[
        "Flexford"
    ],
    "name:fra_x_preferred":[
        "Flexford"
    ],
    "name:gle_x_preferred":[
        "Flexford"
    ],
    "name:nld_x_preferred":[
        "Flexford"
    ],
    "name:pol_x_preferred":[
        "Flexford"
    ],
    "name:spa_x_preferred":[
        "Flexford"
    ],
    "qs_pg:aaroncc":"GB",
    "qs_pg:name":"Flexford",
    "qs_pg:name_adm0":"United Kingdom",
    "qs_pg:name_adm1":"England",
    "qs_pg:photos":40,
    "qs_pg:photos_1k":8,
    "qs_pg:photos_9k":1,
    "qs_pg:photos_9r":2,
    "qs_pg:photos_all":40,
    "qs_pg:photos_sr":2,
    "qs_pg:pop_sr":0,
    "qs_pg:qs_pg_placetype":"locality",
    "qs_pg:qs_pg_placetype_gp":"Town",
    "qs_pg:woe_adm0":23424975,
    "woe:adm0_id":23424975,
    "woe:name_adm0":"United Kingdom",
    "woe:name_adm1":"England",
    "woe:placetype":"Town",
    "wof:name":"Flexford",
    "wof:placetype":"neighbourhood"
},
  "geometry": {"coordinates":[-0.678234,51.240594],"type":"Point"}
}