{
  "type": "Feature",
  "properties": {
    "iso:country":"GB",
    "name:pol_x_preferred":[
        "Woodthorpe"
    ],
    "qs_pg:aaroncc":"GB",
    "qs_pg:name":"Woodthorpe",
    "qs_pg:name_adm0":"United Kingdom",
    "qs_pg:name_adm1":"England",
    "qs_pg:photos":567,
    "qs_pg:photos_1k":115,
    "qs_pg:photos_9k":3,
    "qs_pg:photos_9r":5,
    "qs_pg:photos_all":567,
    "qs_pg:photos_sr":8,
    "qs_pg:pop_sr":0,
    "qs_pg:qs_pg_placetype":"locality",
    "qs_pg:qs_pg_placetype_gp":"Town",
    "qs_pg:woe_adm0":23424975,
    "woe:adm0_id":23424975,
    "woe:name_adm0":"United Kingdom",
    "woe:name_adm1":"England",
    "woe:placetype":"Town",
    "wof:name":"Woodthorpe",
    "wof:placetype":"neighbourhood"
},
  "geometry": {"coordinates":[-1.192295,52.753505],"type":"Point"}
}