{
  "type": "Feature",
  "properties": {
    "gn:admin1_code": "NIR",
    "gn:admin2_code": "N09000004",
    "gn:asciiname": "Ballynacanon",
    "gn:country_code": "GB",
    "gn:dem": 97,
    "gn:feature_class": "P",
    "gn:feature_code": "PPL",
    "gn:name": "Ballynacanon",
    "gn:population": 0,
    "gn:timezone": "Europe/London",
    "iso:country": "GB",
    "wof:name": "Ballynacanon",
    "wof:placetype": "locality"
  },
  "geometry": {"coordinates":[-6.71667,55.06667],"type":"Point"}
}
