{
  "type": "Feature",
  "properties": {
    "gn:admin1_code": "SCT",
    "gn:admin2_code": "V3",
    "gn:asciiname": "Fodderty",
    "gn:country_code": "GB",
    "gn:dem": 17,
    "gn:feature_class": "P",
    "gn:feature_code": "PPL",
    "gn:name": "Fodderty",
    "gn:population": 0,
    "gn:timezone": "Europe/London",
    "iso:country": "GB",
    "name:eus_x_preferred": [
      "Fodderty"
    ],
    "name:gle_x_preferred": [
      "Fodhraitidh"
    ],
    "name:nld_x_preferred": [
      "Fodderty"
    ],
    "wof:name": "Fodderty",
    "wof:placetype": "locality"
  },
  "geometry": {"coordinates":[-4.48942,57.60004],"type":"Point"}
}
