{
  "type": "Feature",
  "properties": {
    "gn:admin1_code": "SCT",
    "gn:admin2_code": "V3",
    "gn:asciiname": "Lonemore",
    "gn:country_code": "GB",
    "gn:dem": 11,
    "gn:feature_class": "P",
    "gn:feature_code": "PPL",
    "gn:name": "Lonemore",
    "gn:population": 0,
    "gn:timezone": "Europe/London",
    "iso:country": "GB",
    "name:nld_x_preferred": [
      "Lonemore"
    ],
    "wof:name": "Lonemore",
    "wof:placetype": "locality"
  },
  "geometry": {"coordinates":[-4.08073,57.86936],"type":"Point"}
}
