{
  "type": "Feature",
  "properties": {
    "gn:admin1_code": "01",
    "gn:asciiname": "Agios Nikolaos",
    "gn:country_code": "GB",
    "gn:dem": 33,
    "gn:feature_class": "P",
    "gn:feature_code": "PPL",
    "gn:name": "Ágios Nikólaos",
    "gn:population": 0,
    "gn:timezone": "Asia/Nicosia",
    "iso:country": "GB",
    "name:bul_x_preferred": [
      "Агиос Николаос"
    ],
    "name:ceb_x_preferred": [
      "Agios Nikolaos"
    ],
    "name:deu_x_preferred": [
      "Agios Nikolaos"
    ],
    "name:ell_x_preferred": [
      "Ágios Nikólaos"
    ],
    "name:ell_x_variant": [
      "Άγιος Νικόλαος"
    ],
    "name:fra_x_preferred": [
      "Agios Nikolaos"
    ],
    "name:hrv_x_preferred": [
      "Agios Nikolaos"
    ],
    "name:hye_x_preferred": [
      "Այոս Նիկոլաոս"
    ],
    "name:pol_x_preferred": [
      "Ajos Nikolaos"
    ],
    "name:rus_x_preferred": [
      "Айос-Николаос"
    ],
    "name:spa_x_preferred": [
      "Ágios Nikolaos"
    ],
    "name:swe_x_preferred": [
      "Agios Nikolaos"
    ],
    "name:ukr_x_preferred": [
      "Айос-Ніколаос"
    ],
    "name:und_x_variant": [
      "Yamaçköy",
      "Akbulut",
      "Aynikola",
      "Ayios Nikolaos"
    ],
    "wof:name": "Agios Nikolaos",
    "wof:placetype": "locality"
  },
  "geometry": {"coordinates":[33.8896,35.08904],"type":"Point"}
}
