{
  "type": "Feature",
  "properties": {
    "gn:admin1_code":"01",
    "gn:asciiname":"Agios Nikolaos",
    "gn:country_code":"GB",
    "gn:dem":33,
    "gn:feature_class":"P",
    "gn:feature_code":"PPL",
    "gn:name":"\u00c1gios Nik\u00f3laos",
    "gn:population":0,
    "gn:timezone":"Asia/Nicosia",
    "iso:country":"GB",
    "name:bul_x_preferred":[
        "\u0410\u0433\u0438\u043e\u0441 \u041d\u0438\u043a\u043e\u043b\u0430\u043e\u0441"
    ],
    "name:ceb_x_preferred":[
        "Agios Nikolaos"
    ],
    "name:deu_x_preferred":[
        "Agios Nikolaos"
    ],
    "name:ell_x_preferred":[
        "\u00c1gios Nik\u00f3laos"
    ],
    "name:ell_x_variant":[
        "\u0386\u03b3\u03b9\u03bf\u03c2 \u039d\u03b9\u03ba\u03cc\u03bb\u03b1\u03bf\u03c2"
    ],
    "name:fra_x_preferred":[
        "Agios Nikolaos"
    ],
    "name:hrv_x_preferred":[
        "Agios Nikolaos"
    ],
    "name:hye_x_preferred":[
        "\u0531\u0575\u0578\u057d \u0546\u056b\u056f\u0578\u056c\u0561\u0578\u057d"
    ],
    "name:pol_x_preferred":[
        "Ajos Nikolaos"
    ],
    "name:rus_x_preferred":[
        "\u0410\u0439\u043e\u0441-\u041d\u0438\u043a\u043e\u043b\u0430\u043e\u0441"
    ],
    "name:spa_x_preferred":[
        "\u00c1gios Nikolaos"
    ],
    "name:swe_x_preferred":[
        "Agios Nikolaos"
    ],
    "name:ukr_x_preferred":[
        "\u0410\u0439\u043e\u0441-\u041d\u0456\u043a\u043e\u043b\u0430\u043e\u0441"
    ],
    "name:und_x_variant":[
        "Yama\u00e7k\u00f6y",
        "Akbulut",
        "Aynikola",
        "Ayios Nikolaos"
    ],
    "wof:name":"Agios Nikolaos",
    "wof:placetype":"locality"
},
  "geometry": {"coordinates":[33.8896,35.08904],"type":"Point"}
}