{
  "type": "Feature",
  "properties": {
    "gn:country": "GB",
    "gn:fcode": "PPL",
    "gn:population": 0,
    "iso:country": "GB",
    "name:deu_x_preferred": [
      "Lofthouse"
    ],
    "name:pol_x_preferred": [
      "Lofthouse"
    ],
    "name:rus_x_preferred": [
      "Лофтхаус"
    ],
    "name:und_x_variant": [
      "Lofthouse-in-Nidderdale"
    ],
    "qs_pg:aaroncc": "GB",
    "qs_pg:gn_country": "GB",
    "qs_pg:gn_fcode": "PPL",
    "qs_pg:gn_pop": 0,
    "qs_pg:name": "Lofthouse",
    "qs_pg:name_adm0": "United Kingdom",
    "qs_pg:name_adm1": "England",
    "qs_pg:photos": 338,
    "qs_pg:photos_1k": 68,
    "qs_pg:photos_9k": 1,
    "qs_pg:photos_9r": 5,
    "qs_pg:photos_all": 338,
    "qs_pg:photos_sr": 5,
    "qs_pg:pop_sr": 0,
    "qs_pg:qs_pg_placetype": "locality",
    "qs_pg:qs_pg_placetype_gp": "Town",
    "qs_pg:woe_adm0": 23424975,
    "woe:adm0_id": 23424975,
    "woe:name_adm0": "United Kingdom",
    "woe:name_adm1": "England",
    "woe:placetype": "Town",
    "wof:name": "Lofthouse",
    "wof:placetype": "neighbourhood"
  },
  "geometry": {"coordinates":[-1.83333,54.15],"type":"Point"}
}
