{
  "type": "Feature",
  "properties": {
    "gn:country": "GB",
    "gn:fcode": "PPL",
    "gn:population": 0,
    "iso:country": "GB",
    "name:ben_x_preferred": [
      "এইনট্রি গ্রাম"
    ],
    "name:cat_x_preferred": [
      "Aintree"
    ],
    "name:dan_x_preferred": [
      "Aintree"
    ],
    "name:deu_x_preferred": [
      "Aintree"
    ],
    "name:eng_x_preferred": [
      "Aintree"
    ],
    "name:fas_x_preferred": [
      "اینتری"
    ],
    "name:fra_x_preferred": [
      "Aintree"
    ],
    "name:guj_x_preferred": [
      "આઈનટ્રી"
    ],
    "name:ita_x_preferred": [
      "Aintree"
    ],
    "name:jpn_x_preferred": [
      "アインツリー・ビレッジ"
    ],
    "name:kan_x_preferred": [
      "ಆಂಟ್ರೀ"
    ],
    "name:kor_x_preferred": [
      "에인트리 빌리지"
    ],
    "name:lit_x_preferred": [
      "Aintris Vilažas"
    ],
    "name:nld_x_preferred": [
      "Aintree"
    ],
    "name:nno_x_preferred": [
      "Aintree"
    ],
    "name:nob_x_preferred": [
      "Aintree"
    ],
    "name:pol_x_preferred": [
      "Aintree"
    ],
    "name:por_x_preferred": [
      "Aintree"
    ],
    "name:rus_x_preferred": [
      "Эйнтри"
    ],
    "name:spa_x_preferred": [
      "Aintree"
    ],
    "name:swe_x_preferred": [
      "Aintree"
    ],
    "name:tam_x_preferred": [
      "ஐண்ட்ரீ"
    ],
    "name:tel_x_preferred": [
      "అంట్రీ"
    ],
    "name:urd_x_preferred": [
      "اینتری"
    ],
    "name:zho_x_preferred": [
      "愛因特"
    ],
    "qs_pg:aaroncc": "GB",
    "qs_pg:gn_country": "GB",
    "qs_pg:gn_fcode": "PPL",
    "qs_pg:gn_pop": 0,
    "qs_pg:name": "Aintree",
    "qs_pg:name_adm0": "United Kingdom",
    "qs_pg:name_adm1": "England",
    "qs_pg:photos": 152,
    "qs_pg:photos_1k": 31,
    "qs_pg:photos_9k": 1,
    "qs_pg:photos_9r": 4,
    "qs_pg:photos_all": 152,
    "qs_pg:photos_sr": 4,
    "qs_pg:pop_sr": 0,
    "qs_pg:qs_pg_placetype": "locality",
    "qs_pg:qs_pg_placetype_gp": "Town",
    "qs_pg:woe_adm0": 23424975,
    "woe:adm0_id": 23424975,
    "woe:name_adm0": "United Kingdom",
    "woe:name_adm1": "England",
    "woe:placetype": "Town",
    "wof:name": "Aintree",
    "wof:placetype": "neighbourhood"
  },
  "geometry": {"coordinates":[-2.95202,53.47538],"type":"Point"}
}
