{
  "type": "Feature",
  "properties": {
    "gn:gn_country":"GB",
    "gn:gn_fcode":"PPL",
    "gn:gn_pop":0,
    "iso:country":"GB",
    "name:ben_x_preferred":[
        "\u098f\u0987\u09a8\u099f\u09cd\u09b0\u09bf \u0997\u09cd\u09b0\u09be\u09ae"
    ],
    "name:cat_x_preferred":[
        "Aintree"
    ],
    "name:chi_x_preferred":[
        "\u611b\u56e0\u7279"
    ],
    "name:dan_x_preferred":[
        "Aintree"
    ],
    "name:dut_x_preferred":[
        "Aintree"
    ],
    "name:eng_x_preferred":[
        "Aintree"
    ],
    "name:fre_x_preferred":[
        "Aintree"
    ],
    "name:ger_x_preferred":[
        "Aintree"
    ],
    "name:guj_x_preferred":[
        "\u0a86\u0a88\u0aa8\u0a9f\u0acd\u0ab0\u0ac0"
    ],
    "name:ita_x_preferred":[
        "Aintree"
    ],
    "name:jpn_x_preferred":[
        "\u30a2\u30a4\u30f3\u30c4\u30ea\u30fc\u30fb\u30d3\u30ec\u30c3\u30b8"
    ],
    "name:kan_x_preferred":[
        "\u0c86\u0c82\u0c9f\u0ccd\u0cb0\u0cc0"
    ],
    "name:kor_x_preferred":[
        "\uc5d0\uc778\ud2b8\ub9ac \ube4c\ub9ac\uc9c0"
    ],
    "name:lit_x_preferred":[
        "Aintris Vila\u017eas"
    ],
    "name:nno_x_preferred":[
        "Aintree"
    ],
    "name:nob_x_preferred":[
        "Aintree"
    ],
    "name:pol_x_preferred":[
        "Aintree"
    ],
    "name:por_x_preferred":[
        "Aintree"
    ],
    "name:rus_x_preferred":[
        "\u042d\u0439\u043d\u0442\u0440\u0438"
    ],
    "name:spa_x_preferred":[
        "Aintree"
    ],
    "name:swe_x_preferred":[
        "Aintree"
    ],
    "name:tam_x_preferred":[
        "\u0b90\u0ba3\u0bcd\u0b9f\u0bcd\u0bb0\u0bc0"
    ],
    "name:tel_x_preferred":[
        "\u0c05\u0c02\u0c1f\u0c4d\u0c30\u0c40"
    ],
    "name:urd_x_preferred":[
        "\u0627\u06cc\u0646\u062a\u0631\u06cc"
    ],
    "qs_pg:aaroncc":"GB",
    "qs_pg:gn_country":"GB",
    "qs_pg:gn_fcode":"PPL",
    "qs_pg:gn_pop":0,
    "qs_pg:name":"Aintree",
    "qs_pg:name_adm0":"United Kingdom",
    "qs_pg:name_adm1":"England",
    "qs_pg:photos":152,
    "qs_pg:photos_1k":31,
    "qs_pg:photos_9k":1,
    "qs_pg:photos_9r":4,
    "qs_pg:photos_all":152,
    "qs_pg:photos_sr":4,
    "qs_pg:pop_sr":0,
    "qs_pg:qs_pg_placetype":"locality",
    "qs_pg:qs_pg_placetype_gp":"Town",
    "qs_pg:woe_adm0":23424975,
    "woe:adm0_id":23424975,
    "woe:name_adm0":"United Kingdom",
    "woe:name_adm1":"England",
    "woe:placetype":"Town",
    "wof:name":"Aintree",
    "wof:placetype":"neighbourhood"
},
  "geometry": {"coordinates":[-2.95202,53.47538],"type":"Point"}
}