{
  "type": "Feature",
  "properties": {
    "iso:country":"GB",
    "name:eng_x_preferred":[
        "Auchinloch"
    ],
    "name:eus_x_preferred":[
        "Auchinloch"
    ],
    "name:fra_x_preferred":[
        "Auchinloch"
    ],
    "name:gla_x_preferred":[
        "Achadh an Locha"
    ],
    "name:gle_x_preferred":[
        "Achadh an Locha"
    ],
    "name:ita_x_preferred":[
        "Auchinloch"
    ],
    "name:nld_x_preferred":[
        "Auchinloch"
    ],
    "name:nno_x_preferred":[
        "Auchinloch"
    ],
    "name:spa_x_preferred":[
        "Auchinloch"
    ],
    "name:swe_x_preferred":[
        "Auchinloch"
    ],
    "qs_pg:aaroncc":"GB",
    "qs_pg:name":"Auchinloch",
    "qs_pg:name_adm0":"United Kingdom",
    "qs_pg:name_adm1":"Scotland",
    "qs_pg:photos":39,
    "qs_pg:photos_1k":8,
    "qs_pg:photos_9k":1,
    "qs_pg:photos_9r":2,
    "qs_pg:photos_all":39,
    "qs_pg:photos_sr":2,
    "qs_pg:pop_sr":0,
    "qs_pg:qs_pg_placetype":"locality",
    "qs_pg:qs_pg_placetype_gp":"Town",
    "qs_pg:woe_adm0":23424975,
    "woe:adm0_id":23424975,
    "woe:name_adm0":"United Kingdom",
    "woe:name_adm1":"Scotland",
    "woe:placetype":"Town",
    "wof:name":"Auchinloch",
    "wof:placetype":"locality"
},
  "geometry": {"coordinates":[-4.149506,55.912315],"type":"Point"}
}