{
  "type": "Feature",
  "properties": {
    "gn:admin1_code":"ENG",
    "gn:admin2_code":"M3",
    "gn:admin3_code":"40UF",
    "gn:admin4_code":"40UF031",
    "gn:asciiname":"Capton",
    "gn:country_code":"GB",
    "gn:dem":74,
    "gn:feature_class":"P",
    "gn:feature_code":"PPL",
    "gn:name":"Capton",
    "gn:population":0,
    "gn:timezone":"Europe/London",
    "iso:country":"GB",
    "wof:name":"Capton",
    "wof:placetype":"neighbourhood"
},
  "geometry": {"coordinates":[-3.31744,51.14788],"type":"Point"}
}