{
  "type": "Feature",
  "properties": {
    "gn:admin1_code": "ENG",
    "gn:admin2_code": "K2",
    "gn:admin3_code": "38UF",
    "gn:admin4_code": "38UF028",
    "gn:asciiname": "Lidstone",
    "gn:country_code": "GB",
    "gn:dem": 158,
    "gn:feature_class": "P",
    "gn:feature_code": "PPL",
    "gn:name": "Lidstone",
    "gn:population": 0,
    "gn:timezone": "Europe/London",
    "iso:country": "GB",
    "wof:name": "Lidstone",
    "wof:placetype": "neighbourhood"
  },
  "geometry": {"coordinates":[-1.4844,51.92017],"type":"Point"}
}
