{
  "type": "Feature",
  "properties": {
    "iso:country": "GB",
    "name:eng_x_preferred": [
      "Twinbrook"
    ],
    "qs:gn_adm0_cc": "GB",
    "qs:gn_local": 2655984,
    "qs:gn_nam_loc": "Belfast, Belfast, Belfast, Northern Ireland, GB",
    "qs:gn_namadm1": "NIR",
    "qs:local_max": 5029,
    "qs:local_sum": 45783,
    "qs:localhoods": 44,
    "qs:name": "Twinbrook",
    "qs:name_adm0": "United Kingdom",
    "qs:name_adm1": "Northern Ireland",
    "qs:name_adm2": "Antrim",
    "qs:name_lau": "Lisburn",
    "qs:name_local": "Belfast",
    "qs:photo_max": 13,
    "qs:photo_sum": 34,
    "qs:placetype": "Suburb",
    "qs:quad_count": 11,
    "qs:woe_adm0": 23424975,
    "qs:woe_adm1": 20070563,
    "qs:woe_adm2": 20071110,
    "qs:woe_lau": 20078319,
    "qs:woe_local": 44544,
    "qs:woe_ver": "7.10.0",
    "wd:wordcount": 61,
    "wof:lang": [
      "eng"
    ],
    "wof:name": "Twinbrook",
    "wof:placetype": "neighbourhood"
  },
  "geometry": {"coordinates":[-6.02277,54.551091],"type":"Point"}
}
