{
  "type": "Feature",
  "properties": {
    "gn:country":"GB",
    "gn:fcode":"PPL",
    "gn:population":1896,
    "iso:country":"GB",
    "name:bul_x_preferred":[
        "\u0420\u0445\u0443"
    ],
    "name:ceb_x_preferred":[
        "Rhu"
    ],
    "name:deu_x_preferred":[
        "Rhu"
    ],
    "name:eng_x_preferred":[
        "Rhu"
    ],
    "name:eus_x_preferred":[
        "Rhu"
    ],
    "name:fas_x_preferred":[
        "\u0631\u0648"
    ],
    "name:fra_x_preferred":[
        "Rhu"
    ],
    "name:gle_x_preferred":[
        "An Rubha"
    ],
    "name:ita_x_preferred":[
        "Rhu"
    ],
    "name:nld_x_preferred":[
        "Rhu"
    ],
    "name:sco_x_preferred":[
        "Rhu"
    ],
    "name:spa_x_preferred":[
        "Rhu"
    ],
    "name:swe_x_preferred":[
        "Rhu"
    ],
    "name:und_x_variant":[
        "Row"
    ],
    "qs_pg:aaroncc":"GB",
    "qs_pg:gn_country":"GB",
    "qs_pg:gn_fcode":"PPL",
    "qs_pg:gn_pop":1896,
    "qs_pg:name":"Rhu",
    "qs_pg:name_adm0":"United Kingdom",
    "qs_pg:name_adm1":"Scotland",
    "qs_pg:photos":565,
    "qs_pg:photos_1k":114,
    "qs_pg:photos_9k":3,
    "qs_pg:photos_9r":5,
    "qs_pg:photos_all":565,
    "qs_pg:photos_sr":8,
    "qs_pg:pop_sr":3,
    "qs_pg:qs_pg_placetype":"locality",
    "qs_pg:qs_pg_placetype_gp":"Town",
    "qs_pg:woe_adm0":23424975,
    "woe:adm0_id":23424975,
    "woe:name_adm0":"United Kingdom",
    "woe:name_adm1":"Scotland",
    "woe:placetype":"Town",
    "wof:name":"Rhu",
    "wof:placetype":"locality",
    "wof:population":1870
},
  "geometry": {"coordinates":[-4.76667,56.01667],"type":"Point"}
}