{
  "type": "Feature",
  "properties": {
    "gn:country":"GB",
    "gn:fcode":"PPL",
    "gn:population":0,
    "iso:country":"GB",
    "name:ceb_x_preferred":[
        "Camlough"
    ],
    "name:deu_x_preferred":[
        "Camlough"
    ],
    "name:eng_x_preferred":[
        "Camlough"
    ],
    "name:eus_x_preferred":[
        "Camlough"
    ],
    "name:fas_x_preferred":[
        "\u06a9\u0645\u0644\u0648\u06af"
    ],
    "name:fra_x_preferred":[
        "Camlough"
    ],
    "name:gla_x_preferred":[
        "Camloch"
    ],
    "name:gle_x_preferred":[
        "Camloch"
    ],
    "name:ita_x_preferred":[
        "Camlough"
    ],
    "name:msa_x_preferred":[
        "Camlough"
    ],
    "name:nld_x_preferred":[
        "Camlough"
    ],
    "name:pli_x_preferred":[
        "\u0915\u093e\u092e\u094d\u0932\u094c\u0918"
    ],
    "name:spa_x_preferred":[
        "Camlough"
    ],
    "name:swe_x_preferred":[
        "Camlough"
    ],
    "qs_pg:aaroncc":"GB",
    "qs_pg:gn_country":"GB",
    "qs_pg:gn_fcode":"PPL",
    "qs_pg:gn_pop":0,
    "qs_pg:name":"Camlough",
    "qs_pg:name_adm0":"United Kingdom",
    "qs_pg:name_adm1":"Northern Ireland",
    "qs_pg:photos":73,
    "qs_pg:photos_1k":15,
    "qs_pg:photos_9k":1,
    "qs_pg:photos_9r":2,
    "qs_pg:photos_all":73,
    "qs_pg:photos_sr":2,
    "qs_pg:pop_sr":0,
    "qs_pg:qs_pg_placetype":"locality",
    "qs_pg:qs_pg_placetype_gp":"Town",
    "qs_pg:woe_adm0":23424975,
    "woe:adm0_id":23424975,
    "woe:name_adm0":"United Kingdom",
    "woe:name_adm1":"Northern Ireland",
    "woe:placetype":"Town",
    "wof:name":"Camlough",
    "wof:placetype":"locality"
},
  "geometry": {"coordinates":[-6.41667,54.16667],"type":"Point"}
}