{
  "type": "Feature",
  "properties": {
    "gn:gn_country":"GB",
    "gn:gn_fcode":"PPL",
    "gn:gn_pop":0,
    "iso:country":"GB",
    "name:dut_x_preferred":[
        "Inverie"
    ],
    "name:eng_x_preferred":[
        "Inverie"
    ],
    "name:fre_x_preferred":[
        "Inverie"
    ],
    "name:gla_x_preferred":[
        "Inbhir Aoidhe"
    ],
    "name:gle_x_preferred":[
        "Inbhir Aoidhe"
    ],
    "name:lat_x_preferred":[
        "Inverie"
    ],
    "name:unk_x_variant":[
        "Inverie"
    ],
    "qs_pg:aaroncc":"GB",
    "qs_pg:gn_country":"GB",
    "qs_pg:gn_fcode":"PPL",
    "qs_pg:gn_pop":0,
    "qs_pg:name":"Inverawe",
    "qs_pg:name_adm0":"United Kingdom",
    "qs_pg:name_adm1":"Scotland",
    "qs_pg:photos":111,
    "qs_pg:photos_1k":22,
    "qs_pg:photos_9k":1,
    "qs_pg:photos_9r":3,
    "qs_pg:photos_all":111,
    "qs_pg:photos_sr":3,
    "qs_pg:pop_sr":0,
    "qs_pg:qs_pg_placetype":"locality",
    "qs_pg:qs_pg_placetype_gp":"Town",
    "qs_pg:woe_adm0":23424975,
    "woe:adm0_id":23424975,
    "woe:name_adm0":"United Kingdom",
    "woe:name_adm1":"Scotland",
    "woe:placetype":"Town",
    "wof:name":"Inverawe",
    "wof:placetype":"locality"
},
  "geometry": {"coordinates":[-5.68117,57.03634],"type":"Point"}
}