{
  "type": "Feature",
  "properties": {
    "gn:country":"GB",
    "gn:fcode":"PPL",
    "gn:population":0,
    "iso:country":"GB",
    "name:deu_x_preferred":[
        "Kirtlebridge"
    ],
    "name:eng_x_preferred":[
        "Kirtlebridge"
    ],
    "name:eus_x_preferred":[
        "Kirtlebridge"
    ],
    "name:fra_x_preferred":[
        "Kirtlebridge"
    ],
    "name:gla_x_preferred":[
        "Kirtlebridge"
    ],
    "name:gle_x_preferred":[
        "Kirtlebridge"
    ],
    "name:jpn_x_preferred":[
        "\u30ab\u30fc\u30c8\u30eb\u30d6\u30ea\u30c3\u30b8"
    ],
    "name:nld_x_preferred":[
        "Kirtlebridge"
    ],
    "name:sco_x_preferred":[
        "Kirtlebrig"
    ],
    "qs_pg:aaroncc":"GB",
    "qs_pg:gn_country":"GB",
    "qs_pg:gn_fcode":"PPL",
    "qs_pg:gn_pop":0,
    "qs_pg:name":"Kirtlebridge",
    "qs_pg:name_adm0":"United Kingdom",
    "qs_pg:name_adm1":"Scotland",
    "qs_pg:photos":840,
    "qs_pg:photos_1k":170,
    "qs_pg:photos_9k":4,
    "qs_pg:photos_9r":6,
    "qs_pg:photos_all":840,
    "qs_pg:photos_sr":9,
    "qs_pg:pop_sr":0,
    "qs_pg:qs_pg_placetype":"locality",
    "qs_pg:qs_pg_placetype_gp":"Town",
    "qs_pg:woe_adm0":23424975,
    "woe:adm0_id":23424975,
    "woe:name_adm0":"United Kingdom",
    "woe:name_adm1":"Scotland",
    "woe:placetype":"Town",
    "wof:name":"Kirtlebridge",
    "wof:placetype":"locality"
},
  "geometry": {"coordinates":[-3.19248,55.04385],"type":"Point"}
}