{
  "type": "Feature",
  "properties": {
    "gn:admin1_code":"SCT",
    "gn:admin2_code":"T9",
    "gn:asciiname":"Harrietsfield",
    "gn:cc2":"GB",
    "gn:country_code":"GB",
    "gn:dem":142,
    "gn:feature_class":"P",
    "gn:feature_code":"PPL",
    "gn:name":"Harrietsfield",
    "gn:population":0,
    "gn:timezone":"Europe/London",
    "iso:country":"GB",
    "name:und_x_variant":[
        "Harrietfield",
        "Harrietsfield"
    ],
    "wof:name":"Harrietsfield",
    "wof:placetype":"locality"
},
  "geometry": {"coordinates":[-2.58333,55.53333],"type":"Point"}
}