{
  "type": "Feature",
  "properties": {
    "iso:country":"GB",
    "name:bul_x_preferred":[
        "\u0411\u0440\u043e\u0430\u0434\u0445\u043e\u043b\u043c\u0435"
    ],
    "name:ceb_x_preferred":[
        "Broadholme"
    ],
    "name:cym_x_preferred":[
        "Broadholme"
    ],
    "name:eng_x_preferred":[
        "Bransholme"
    ],
    "name:eng_x_variant":[
        "Broadholme"
    ],
    "name:fra_x_preferred":[
        "Broadholme"
    ],
    "name:nld_x_preferred":[
        "Broadholme"
    ],
    "name:pol_x_preferred":[
        "Broadholme"
    ],
    "name:swe_x_preferred":[
        "Broadholme"
    ],
    "qs:gn_fcode":"PPL",
    "qs:gn_local":0,
    "qs:gn_namadm1":"ENG",
    "qs:gn_name":"Broadholme",
    "qs:local_max":4047,
    "qs:local_sum":20920,
    "qs:localhoods":16,
    "qs:name":"Bransholme",
    "qs:name_adm0":"United Kingdom",
    "qs:name_adm1":"England",
    "qs:name_adm2":"East Riding of Yorkshire",
    "qs:name_lau":"Kingston upon Hull City",
    "qs:name_local":"Hull",
    "qs:photo_max":702,
    "qs:photo_sum":1587,
    "qs:placetype":"Suburb",
    "qs:quad_count":61,
    "qs:woe_adm0":23424975,
    "qs:woe_adm1":24554868,
    "qs:woe_adm2":12602193,
    "qs:woe_lau":12696140,
    "qs:woe_local":25211,
    "qs:woe_ver":"7.10.0",
    "wd:wordcount":599,
    "wof:lang":[
        "eng"
    ],
    "wof:name":"Bransholme",
    "wof:placetype":"neighbourhood"
},
  "geometry": {"coordinates":[-0.31929,53.784719],"type":"Point"}
}