{
  "type": "Feature",
  "properties": {
    "gn:admin1_code":"SCT",
    "gn:admin2_code":"T8",
    "gn:asciiname":"Clachaig",
    "gn:country_code":"GB",
    "gn:dem":83,
    "gn:feature_class":"P",
    "gn:feature_code":"PPL",
    "gn:name":"Clachaig",
    "gn:population":0,
    "gn:timezone":"Europe/London",
    "iso:country":"GB",
    "name:eus_x_preferred":[
        "Clachaig"
    ],
    "wof:name":"Clachaig",
    "wof:placetype":"locality"
},
  "geometry": {"coordinates":[-5.0183,55.98954],"type":"Point"}
}