{
  "type": "Feature",
  "properties": {
    "gn:admin1_code": "SCT",
    "gn:admin2_code": "T6",
    "gn:asciiname": "Kinnernie",
    "gn:country_code": "GB",
    "gn:dem": 185,
    "gn:feature_class": "P",
    "gn:feature_code": "PPL",
    "gn:name": "Kinnernie",
    "gn:population": 0,
    "gn:timezone": "Europe/London",
    "iso:country": "GB",
    "wof:name": "Kinnernie",
    "wof:placetype": "locality"
  },
  "geometry": {"coordinates":[-2.45,57.16667],"type":"Point"}
}
