{
  "type": "Feature",
  "properties": {
    "gn:population": 6166,
    "iso:country": "GB",
    "name:ara_x_preferred": [
      "أولني"
    ],
    "name:azb_x_preferred": [
      "اولنی"
    ],
    "name:ben_x_preferred": [
      "ওলনি"
    ],
    "name:ceb_x_preferred": [
      "Olney"
    ],
    "name:cym_x_preferred": [
      "Olney"
    ],
    "name:deu_x_preferred": [
      "Olney"
    ],
    "name:eng_x_preferred": [
      "Olney"
    ],
    "name:fas_x_preferred": [
      "اولنی، باکینگهام‌شر"
    ],
    "name:fas_x_variant": [
      "اولنی"
    ],
    "name:fra_x_preferred": [
      "Olney"
    ],
    "name:gle_x_preferred": [
      "Olney"
    ],
    "name:guj_x_preferred": [
      "ઓલની"
    ],
    "name:ita_x_preferred": [
      "Olney"
    ],
    "name:jpn_x_preferred": [
      "オルニー"
    ],
    "name:kan_x_preferred": [
      "ಓಲ್ನಿ"
    ],
    "name:kor_x_preferred": [
      "올니"
    ],
    "name:lit_x_preferred": [
      "Olnis"
    ],
    "name:nld_x_preferred": [
      "Olney"
    ],
    "name:nno_x_preferred": [
      "Olney i Buckinghamshire"
    ],
    "name:nob_x_preferred": [
      "Olney"
    ],
    "name:pol_x_preferred": [
      "Olney"
    ],
    "name:por_x_preferred": [
      "Olney"
    ],
    "name:ron_x_preferred": [
      "Olney"
    ],
    "name:rus_x_preferred": [
      "Олни"
    ],
    "name:spa_x_preferred": [
      "Olney"
    ],
    "name:swe_x_preferred": [
      "Olney"
    ],
    "name:tam_x_preferred": [
      "ஒலனே"
    ],
    "name:tel_x_preferred": [
      "ఓల్ని"
    ],
    "name:und_x_variant": [
      "Colne"
    ],
    "name:urd_x_preferred": [
      "ولنے"
    ],
    "name:vol_x_preferred": [
      "Olney"
    ],
    "name:zho_x_preferred": [
      "奧爾尼"
    ],
    "qs:a0": "United Kingdom",
    "qs:a1": "*Milton Keynes",
    "qs:a1_lc": "GB12MG0000",
    "qs:a1r": "0England",
    "qs:a1r_lc": "GB12000000",
    "qs:adm0": "United Kingdom",
    "qs:la_lc": "*",
    "qs:level": "locality",
    "qs:loc": "Olney",
    "qs:loc_alt": "Olney",
    "qs:pop": 0,
    "qs:type": "buffered point",
    "wof:name": "Olney",
    "wof:placetype": "neighbourhood",
    "wof:population": 6166
  },
  "geometry": {"coordinates":[-0.702739,52.158102],"type":"Point"}
}
