{
  "type": "Feature",
  "properties": {
    "gn:admin1_code":"SCT",
    "gn:admin2_code":"U6",
    "gn:asciiname":"Spott",
    "gn:country_code":"GB",
    "gn:dem":81,
    "gn:feature_class":"P",
    "gn:feature_code":"PPL",
    "gn:name":"Spott",
    "gn:population":0,
    "gn:timezone":"Europe/London",
    "iso:country":"GB",
    "name:deu_x_preferred":[
        "Spott"
    ],
    "name:eus_x_preferred":[
        "Spott"
    ],
    "wof:name":"Spott",
    "wof:placetype":"locality"
},
  "geometry": {"coordinates":[-2.52644,55.97083],"type":"Point"}
}