{
  "type": "Feature",
  "properties": {
    "gn:country":"GB",
    "gn:fcode":"PPL",
    "gn:population":0,
    "iso:country":"GB",
    "name:eng_x_preferred":[
        "Spinningdale"
    ],
    "name:eus_x_preferred":[
        "Spinningdale"
    ],
    "name:gla_x_preferred":[
        "Spainiadail"
    ],
    "name:gle_x_preferred":[
        "Spainnigeadal"
    ],
    "name:gle_x_variant":[
        "Spainiadail"
    ],
    "name:nld_x_preferred":[
        "Spinningdale"
    ],
    "qs_pg:aaroncc":"GB",
    "qs_pg:gn_country":"GB",
    "qs_pg:gn_fcode":"PPL",
    "qs_pg:gn_pop":0,
    "qs_pg:name":"Spinningdale",
    "qs_pg:name_adm0":"United Kingdom",
    "qs_pg:name_adm1":"Scotland",
    "qs_pg:photos":15,
    "qs_pg:photos_1k":3,
    "qs_pg:photos_9k":1,
    "qs_pg:photos_9r":1,
    "qs_pg:photos_all":15,
    "qs_pg:photos_sr":1,
    "qs_pg:pop_sr":0,
    "qs_pg:qs_pg_placetype":"locality",
    "qs_pg:qs_pg_placetype_gp":"Town",
    "qs_pg:woe_adm0":23424975,
    "woe:adm0_id":23424975,
    "woe:name_adm0":"United Kingdom",
    "woe:name_adm1":"Scotland",
    "woe:placetype":"Town",
    "wof:name":"Spinningdale",
    "wof:placetype":"locality"
},
  "geometry": {"coordinates":[-4.23485,57.87786],"type":"Point"}
}