{
  "type": "Feature",
  "properties": {
    "gn:country": "GB",
    "gn:fcode": "PPL",
    "gn:population": 0,
    "iso:country": "GB",
    "name:bul_x_preferred": [
      "Аучмитхие"
    ],
    "name:ceb_x_preferred": [
      "Auchmithie"
    ],
    "name:eng_x_preferred": [
      "Auchmithie"
    ],
    "name:eus_x_preferred": [
      "Auchmithie"
    ],
    "name:fra_x_preferred": [
      "Auchmithie"
    ],
    "name:nld_x_preferred": [
      "Auchmithie"
    ],
    "name:swe_x_preferred": [
      "Auchmithie"
    ],
    "qs_pg:aaroncc": "GB",
    "qs_pg:gn_country": "GB",
    "qs_pg:gn_fcode": "PPL",
    "qs_pg:gn_pop": 0,
    "qs_pg:name": "Auchmithie",
    "qs_pg:name_adm0": "United Kingdom",
    "qs_pg:name_adm1": "Scotland",
    "qs_pg:photos": 291,
    "qs_pg:photos_1k": 59,
    "qs_pg:photos_9k": 1,
    "qs_pg:photos_9r": 4,
    "qs_pg:photos_all": 291,
    "qs_pg:photos_sr": 5,
    "qs_pg:pop_sr": 0,
    "qs_pg:qs_pg_placetype": "locality",
    "qs_pg:qs_pg_placetype_gp": "Town",
    "qs_pg:woe_adm0": 23424975,
    "woe:adm0_id": 23424975,
    "woe:name_adm0": "United Kingdom",
    "woe:name_adm1": "Scotland",
    "woe:placetype": "Town",
    "wof:name": "Auchmithie",
    "wof:placetype": "locality"
  },
  "geometry": {"coordinates":[-2.52151,56.58997],"type":"Point"}
}
