{
  "type": "Feature",
  "properties": {
    "iso:country":"GB",
    "name:eng_x_preferred":[
        "Riverside"
    ],
    "wof:name":"Riverside",
    "wof:placetype":"neighbourhood"
},
  "geometry": {"coordinates":[-3.18932931359501,51.47860197608966],"type":"Point"}
}